# Disassembly for central
# From module file: central

## co_consts:
(0, None, ('*',), ('Photo',), "████████████████████████████████████████████████████████████████████████████████\n██                                                                            ██\n██                                           ,▄▓▓▓▓▓▓▓▓▄▄,                    ██\n██                                         ╓▓▓▓▓▓▓▓▓▓▓▓▓▓▓▓▓▄                 ██\n██                                       .▓▓▓▓▓▓▓▓▓▓▓▓▓▓▓▓▓▓▓▓▄               ██\n██                                       ║▓▓▌└''└╙╙╙▀▀▀▀▀▀'╙▓▓▓               ██\n██                                       ║▓▓▌╓▄▄▓▓''''▓▓▄▄▄ƒ▓▓▓               ██\n██                                        ▓▓└└,;,''''''┌,;.'╫▓▌               ██\n██            ╓▄▓▓▓▓▓▓▓▓▓▓▌,              ╟▌'▐.▓▒`'''''▓▒µ╙'▐▓┌               ██\n██          ▄▓▓▓▓▓▓▓▓▓▓▓▓▓▓▓▓▓,          .]╠.'.╙┤-''¡'░│╙┌ '╚▒.               ██\n██         ▓▓▓▓▓▓▓▓▓▓▓▓▓▌└▓▓▓▓▓            '''''',:::::''''.''                ██\n██        ]▓▓▓▓▓▓▓▓▓▀╬╣╙┌,╚▓▓▓▓▌             ''''▓▓▓▄▓▓▒'''                   ██\n██        ╫▓▓▌╝▀▀▀Γ'└ '╙╙╙╙╙▓▓▓▓              '┌' ╙╙╙╙┘'┌'                    ██\n██        ▓▓▓▒╓Mj░∩''''=Q▄7▒▐▓▓▓                ²ε;,,;;φ                      ██\n██       ]▌╙▓▌╙ ▓▀ ┌,'' ▀▓ └▐▓▒▐L            ╓▄⌐ ':'└└:  ╠▓▄µ                 ██\n██       ▓▓µ▓▓':░░┌.':'.░░''▐▓▒▓▌       ,▄▓▓███▌. 4██▓⌐ -▓█████▓▌▄╖           ██\n██      ▐▓▓▓▓▓▄''^▓▓▓▓▓▓▀'']▓▓▓▓▓⌐  ▄▄▓████████▓▌` ╟█▌  ╣▓███████████▌        ██\n██      ╟▓▓▓▓▓█▓▄.'╙╙╙╙└',▄██▓▓▓▓⌐]█████████████▓▒ ╫█▌ å▓▓████████████▌       ██\n██     «╣▓▓▓██████▌≥ε;≤∩╟█████▓▓▓▌▓█████████████▓▓▄▓██╔▓▓██████████████       ██\n██     ]▓▓▓▓█████▓▀'''''┘╙▀▀██▓▓▓▓████████████▓█▓▓▓▓██▓▓▓██████████████µ      ██\n██      ╚▀▓▀▀╠╬╬▒⌐'''''''':╠╬╬╠⌐└╫███████████████▓▓▓▓▓▓▓▓██████████████▓      ██\n██        .''╠╬╬╬╠∩.'''''┌╠╬╬╬╬░:▓███████████████▓▓▓▓▓▓▓▓███████████████      ██\n██        '''╠╬╬╬╬╬▒;''';╠╬╬╬╬╬▒]█████████████████▓▓▓▓▓▓▓███████████████▌     ██\n██        '''╠╬╬╬╬╬╬╟╦;φ╠╬╬╬╬╬╬╠╟█████████████████▓▓▓▓▓▓████████████████▌     ██\n██       :''┌╠╬╬╬╬╬╬╬╬╬╬╬╬╬╬╬╬╬╠▓██████▌╫█████████▓▓▓╣▓▓█████████████████     ██\n██       '''':╬╬╬╬╬╬╬╬╬╬╬╬╬╬╬╬╬░██▓╩┘''''╙█████████▓▓▓▓▓██████████╙██████     ██\n██      .''':  ╬╬╬╬╬╬╬╬╬╬╬╬╬╬╬▒]█╩,ô;µ┌',▓█████████▓▓╬▓▓▓█████████ ██████L    ██\n██      ''''   ╚╬╬╬╬╬╬╬╬╬╬╬╠╠╬Γ ║▒▄Θ▒φ╓▄████████▓▀╙└'^:::╙████████ ▓█████▌    ██\n██     :''''    ╬╬╬╬╬╬╬╬╬╠╠╠╬╬▒  └╨▀▀▓██████████⌐'''''┌;;¡▓███████ ║█████▌    ██\n██    ┌''':    ,╬╬╬╬╬╬╬╠╠╠╬╬╬╬╟         ╙███████,▄;'''ⁿ⌐;▓████████ └█████▌    ██\n██   ┌''.'     ╟╬╬╬╬╬╠╬╬╬╬╬╬╬╬╬╬         █████████▓▓▓▓▓▓██████████⌐ █████▌    ██\n████████████████████████████████████████████████████████████████████████████████", '\n', 1, 5, 4, '┌──────────────┐\n│              │\n│              │\n│              │\n│              │\n│              │\n│              │\n└──────────────┘', '╔══════════════╗\n║ █▓▒░░░░░░▒▓█ ║\n║ ▓▀        ▀▓ ║\n║ ░          ░ ║\n║ ░          ░ ║\n║ ▓▄        ▄▓ ║\n║ █▓▒░░░░░░▒▓█ ║\n╚══════════════╝', <code object Machine at 0x000002406934F630, file "central.py", line 104>, 'Machine', <code object Central at 0x00000240691F13E0, file "central.py", line 268>, 'Central')

## co_names:
('random', 'entities', 'breakroom', 'Photo', 'photo_str', 'len', 'split', 'photo_width', 'photo_height', 'list', 'photo_chars', 'int', 'card_width', 'card_height', 'card_front_str', 'card_back_str', 'Item', 'Machine', 'Room', 'Central')

## bytecode:

   0: RESUME               
   2: LOAD_CONST           0
   4: LOAD_CONST           None
   6: IMPORT_NAME          random
   8: STORE_NAME           random
  10: LOAD_CONST           0
  12: LOAD_CONST           ('*',)
  14: IMPORT_NAME          entities
  16: IMPORT_STAR          
  18: LOAD_CONST           0
  20: LOAD_CONST           ('Photo',)
  22: IMPORT_NAME          breakroom
  24: IMPORT_FROM          Photo
  26: STORE_NAME           Photo
  28: POP_TOP              
  30: LOAD_CONST           "████████████████████████████████████████████████████████████████████████████████\n██                                                                            ██\n██                                           ,▄▓▓▓▓▓▓▓▓▄▄,                    ██\n██                                         ╓▓▓▓▓▓▓▓▓▓▓▓▓▓▓▓▓▄                 ██\n██                                       .▓▓▓▓▓▓▓▓▓▓▓▓▓▓▓▓▓▓▓▓▄               ██\n██                                       ║▓▓▌└''└╙╙╙▀▀▀▀▀▀'╙▓▓▓               ██\n██                                       ║▓▓▌╓▄▄▓▓''''▓▓▄▄▄ƒ▓▓▓               ██\n██                                        ▓▓└└,;,''''''┌,;.'╫▓▌               ██\n██            ╓▄▓▓▓▓▓▓▓▓▓▓▌,              ╟▌'▐.▓▒`'''''▓▒µ╙'▐▓┌               ██\n██          ▄▓▓▓▓▓▓▓▓▓▓▓▓▓▓▓▓▓,          .]╠.'.╙┤-''¡'░│╙┌ '╚▒.               ██\n██         ▓▓▓▓▓▓▓▓▓▓▓▓▓▌└▓▓▓▓▓            '''''',:::::''''.''                ██\n██        ]▓▓▓▓▓▓▓▓▓▀╬╣╙┌,╚▓▓▓▓▌             ''''▓▓▓▄▓▓▒'''                   ██\n██        ╫▓▓▌╝▀▀▀Γ'└ '╙╙╙╙╙▓▓▓▓              '┌' ╙╙╙╙┘'┌'                    ██\n██        ▓▓▓▒╓Mj░∩''''=Q▄7▒▐▓▓▓                ²ε;,,;;φ                      ██\n██       ]▌╙▓▌╙ ▓▀ ┌,'' ▀▓ └▐▓▒▐L            ╓▄⌐ ':'└└:  ╠▓▄µ                 ██\n██       ▓▓µ▓▓':░░┌.':'.░░''▐▓▒▓▌       ,▄▓▓███▌. 4██▓⌐ -▓█████▓▌▄╖           ██\n██      ▐▓▓▓▓▓▄''^▓▓▓▓▓▓▀'']▓▓▓▓▓⌐  ▄▄▓████████▓▌` ╟█▌  ╣▓███████████▌        ██\n██      ╟▓▓▓▓▓█▓▄.'╙╙╙╙└',▄██▓▓▓▓⌐]█████████████▓▒ ╫█▌ å▓▓████████████▌       ██\n██     «╣▓▓▓██████▌≥ε;≤∩╟█████▓▓▓▌▓█████████████▓▓▄▓██╔▓▓██████████████       ██\n██     ]▓▓▓▓█████▓▀'''''┘╙▀▀██▓▓▓▓████████████▓█▓▓▓▓██▓▓▓██████████████µ      ██\n██      ╚▀▓▀▀╠╬╬▒⌐'''''''':╠╬╬╠⌐└╫███████████████▓▓▓▓▓▓▓▓██████████████▓      ██\n██        .''╠╬╬╬╠∩.'''''┌╠╬╬╬╬░:▓███████████████▓▓▓▓▓▓▓▓███████████████      ██\n██        '''╠╬╬╬╬╬▒;''';╠╬╬╬╬╬▒]█████████████████▓▓▓▓▓▓▓███████████████▌     ██\n██        '''╠╬╬╬╬╬╬╟╦;φ╠╬╬╬╬╬╬╠╟█████████████████▓▓▓▓▓▓████████████████▌     ██\n██       :''┌╠╬╬╬╬╬╬╬╬╬╬╬╬╬╬╬╬╬╠▓██████▌╫█████████▓▓▓╣▓▓█████████████████     ██\n██       '''':╬╬╬╬╬╬╬╬╬╬╬╬╬╬╬╬╬░██▓╩┘''''╙█████████▓▓▓▓▓██████████╙██████     ██\n██      .''':  ╬╬╬╬╬╬╬╬╬╬╬╬╬╬╬▒]█╩,ô;µ┌',▓█████████▓▓╬▓▓▓█████████ ██████L    ██\n██      ''''   ╚╬╬╬╬╬╬╬╬╬╬╬╠╠╬Γ ║▒▄Θ▒φ╓▄████████▓▀╙└'^:::╙████████ ▓█████▌    ██\n██     :''''    ╬╬╬╬╬╬╬╬╬╠╠╠╬╬▒  └╨▀▀▓██████████⌐'''''┌;;¡▓███████ ║█████▌    ██\n██    ┌''':    ,╬╬╬╬╬╬╬╠╠╠╬╬╬╬╟         ╙███████,▄;'''ⁿ⌐;▓████████ └█████▌    ██\n██   ┌''.'     ╟╬╬╬╬╬╠╬╬╬╬╬╬╬╬╬╬         █████████▓▓▓▓▓▓██████████⌐ █████▌    ██\n████████████████████████████████████████████████████████████████████████████████"
  32: STORE_NAME           photo_str
  34: PUSH_NULL            
  36: LOAD_NAME            len
  38: LOAD_NAME            photo_str
  40: LOAD_METHOD          split
  62: LOAD_CONST           '\n'
  64: PRECALL              
  68: CALL                 
  78: LOAD_CONST           0
  80: BINARY_SUBSCR        
  90: PRECALL              
  94: CALL                 
 104: LOAD_CONST           1
 106: BINARY_OP            +
 110: STORE_GLOBAL         photo_width
 112: PUSH_NULL            
 114: LOAD_NAME            len
 116: LOAD_NAME            photo_str
 118: LOAD_METHOD          split
 140: LOAD_CONST           '\n'
 142: PRECALL              
 146: CALL                 
 156: PRECALL              
 160: CALL                 
 170: STORE_GLOBAL         photo_height
 172: PUSH_NULL            
 174: LOAD_NAME            list
 176: LOAD_NAME            photo_str
 178: PRECALL              
 182: CALL                 
 192: STORE_GLOBAL         photo_chars
 194: PUSH_NULL            
 196: LOAD_NAME            int
 198: LOAD_GLOBAL          photo_width
 210: LOAD_CONST           1
 212: BINARY_OP            -
 216: LOAD_CONST           5
 218: BINARY_OP            /
 222: PRECALL              
 226: CALL                 
 236: STORE_GLOBAL         card_width
 238: PUSH_NULL            
 240: LOAD_NAME            int
 242: LOAD_GLOBAL          photo_height
 254: LOAD_CONST           4
 256: BINARY_OP            /
 260: PRECALL              
 264: CALL                 
 274: STORE_GLOBAL         card_height
 276: LOAD_CONST           '┌──────────────┐\n│              │\n│              │\n│              │\n│              │\n│              │\n│              │\n└──────────────┘'
 278: STORE_GLOBAL         card_front_str
 280: LOAD_CONST           '╔══════════════╗\n║ █▓▒░░░░░░▒▓█ ║\n║ ▓▀        ▀▓ ║\n║ ░          ░ ║\n║ ░          ░ ║\n║ ▓▄        ▄▓ ║\n║ █▓▒░░░░░░▒▓█ ║\n╚══════════════╝'
 282: STORE_GLOBAL         card_back_str
 284: PUSH_NULL            
 286: LOAD_BUILD_CLASS     
 288: LOAD_CONST           <code object Machine at 0x000002406934F630, file "central.py", line 104>
 290: MAKE_FUNCTION        
 292: LOAD_CONST           'Machine'
 294: LOAD_NAME            Item
 296: PRECALL              
 300: CALL                 
 310: STORE_NAME           Machine
 312: PUSH_NULL            
 314: LOAD_BUILD_CLASS     
 316: LOAD_CONST           <code object Central at 0x00000240691F13E0, file "central.py", line 268>
 318: MAKE_FUNCTION        
 320: LOAD_CONST           'Central'
 322: LOAD_NAME            Room
 324: PRECALL              
 328: CALL                 
 338: STORE_NAME           Central
 340: LOAD_CONST           None
 342: RETURN_VALUE         
