# Disassembly for central.Machine.get_options
# From module file: central

## co_consts:
(None, 'Lobby', <code object <lambda> at 0x000002406945D980, file "central.py", line 116>, 'Check out the machine.', <code object <lambda> at 0x000002406945E3D0, file "central.py", line 120>, 'Insert photo into machine.', <code object <lambda> at 0x000002406945F0F0, file "central.py", line 122>, 'Try to find a match.')

## co_names:
('world', 'rooms', 'is_opened', 'append', 'checked', 'get_child_by_type', 'Photo', 'player')

## bytecode:

   0: MAKE_CELL            self
   2: RESUME               
   4: BUILD_LIST           
   6: STORE_FAST           options
   8: LOAD_DEREF           self
  10: LOAD_ATTR            world
  20: LOAD_ATTR            rooms
  30: LOAD_CONST           'Lobby'
  32: BINARY_SUBSCR        
  42: LOAD_ATTR            is_opened
  52: POP_JUMP_FORWARD_IF_TRUE to 350
  54: LOAD_FAST            options
  56: LOAD_METHOD          append
  78: LOAD_CLOSURE         self
  80: BUILD_TUPLE          
  82: LOAD_CONST           <code object <lambda> at 0x000002406945D980, file "central.py", line 116>
  84: MAKE_FUNCTION        closure
  86: LOAD_CONST           'Check out the machine.'
  88: BUILD_TUPLE          
  90: PRECALL              
  94: CALL                 
 104: POP_TOP              
 106: LOAD_DEREF           self
 108: LOAD_ATTR            checked
 118: POP_JUMP_FORWARD_IF_FALSE to 350
 120: LOAD_DEREF           self
 122: LOAD_METHOD          get_child_by_type
 144: LOAD_GLOBAL          Photo
 156: PRECALL              
 160: CALL                 
 170: POP_JUMP_FORWARD_IF_NOT_NONE to 298
 172: LOAD_DEREF           self
 174: LOAD_ATTR            world
 184: LOAD_ATTR            player
 194: LOAD_METHOD          get_child_by_type
 216: LOAD_GLOBAL          Photo
 228: PRECALL              
 232: CALL                 
 242: POP_JUMP_FORWARD_IF_NONE to 296
 244: LOAD_FAST            options
 246: LOAD_METHOD          append
 268: LOAD_CLOSURE         self
 270: BUILD_TUPLE          
 272: LOAD_CONST           <code object <lambda> at 0x000002406945E3D0, file "central.py", line 120>
 274: MAKE_FUNCTION        closure
 276: LOAD_CONST           'Insert photo into machine.'
 278: BUILD_TUPLE          
 280: PRECALL              
 284: CALL                 
 294: POP_TOP              
 296: JUMP_FORWARD         to 350
 298: LOAD_FAST            options
 300: LOAD_METHOD          append
 322: LOAD_CLOSURE         self
 324: BUILD_TUPLE          
 326: LOAD_CONST           <code object <lambda> at 0x000002406945F0F0, file "central.py", line 122>
 328: MAKE_FUNCTION        closure
 330: LOAD_CONST           'Try to find a match.'
 332: BUILD_TUPLE          
 334: PRECALL              
 338: CALL                 
 348: POP_TOP              
 350: LOAD_FAST            options
 352: RETURN_VALUE         
