# Disassembly for central.Machine.setup
# From module file: central

## co_consts:
(None, 'Mom', 'Dad', 'Hank', 'Barbara', 'Chuck', 'Emily', 'Creativity', 'Intelligence', 2, False, ('face', 'found'))

## co_names:
('world', 'name', 'player', 'range', 'cards', 'append', 'random', 'shuffle')

## bytecode:

   0: RESUME               
   2: LOAD_FAST            self
   4: LOAD_ATTR            world
  14: LOAD_ATTR            name
  24: LOAD_FAST            self
  26: LOAD_ATTR            world
  36: LOAD_ATTR            player
  46: LOAD_ATTR            name
  56: LOAD_CONST           'Mom'
  58: LOAD_CONST           'Dad'
  60: LOAD_CONST           'Hank'
  62: LOAD_CONST           'Barbara'
  64: LOAD_CONST           'Chuck'
  66: LOAD_CONST           'Emily'
  68: LOAD_CONST           'Creativity'
  70: LOAD_CONST           'Intelligence'
  72: BUILD_TUPLE          
  74: GET_ITER             
  76: FOR_ITER             to 176
  78: STORE_FAST           face
  80: LOAD_GLOBAL          NULL + range
  92: LOAD_CONST           2
  94: PRECALL              
  98: CALL                 
 108: GET_ITER             
 110: FOR_ITER             to 174
 112: STORE_FAST           num
 114: LOAD_FAST            self
 116: LOAD_ATTR            cards
 126: LOAD_METHOD          append
 148: LOAD_FAST            face
 150: LOAD_CONST           False
 152: LOAD_CONST           ('face', 'found')
 154: BUILD_CONST_KEY_MAP  
 156: PRECALL              
 160: CALL                 
 170: POP_TOP              
 172: JUMP_BACKWARD        to 110
 174: JUMP_BACKWARD        to 76
 176: LOAD_GLOBAL          NULL + random
 188: LOAD_ATTR            shuffle
 198: LOAD_FAST            self
 200: LOAD_ATTR            cards
 210: PRECALL              
 214: CALL                 
 224: POP_TOP              
 226: LOAD_CONST           None
 228: RETURN_VALUE         
