# Disassembly for central.Machine.start
# From module file: central

## co_consts:
(None, 'You insert the photo into the machine.  The buttons on the panel light up.\nThe screen turns on and displays a set of cards. and the message:\n --- Find all of the matches')

## co_names:
('world', 'player', 'get_child_by_type', 'Photo', 'set_parent', 'setup', 'send_message')

## bytecode:

   0: RESUME               
   2: LOAD_FAST            self
   4: LOAD_ATTR            world
  14: LOAD_ATTR            player
  24: LOAD_METHOD          get_child_by_type
  46: LOAD_GLOBAL          Photo
  58: PRECALL              
  62: CALL                 
  72: STORE_FAST           photo
  74: LOAD_FAST            photo
  76: LOAD_METHOD          set_parent
  98: LOAD_FAST            self
 100: PRECALL              
 104: CALL                 
 114: POP_TOP              
 116: LOAD_FAST            self
 118: LOAD_METHOD          setup
 140: PRECALL              
 144: CALL                 
 154: POP_TOP              
 156: LOAD_FAST            self
 158: LOAD_METHOD          send_message
 180: LOAD_CONST           'You insert the photo into the machine.  The buttons on the panel light up.\nThe screen turns on and displays a set of cards. and the message:\n --- Find all of the matches'
 182: PRECALL              
 186: CALL                 
 196: POP_TOP              
 198: LOAD_CONST           None
 200: RETURN_VALUE         
