# Disassembly for _py_abc.ABCMeta._abc_caches_clear
# From module file: _py_abc

## co_consts:
('Clear the caches (for debugging or testing).', None)

## co_names:
('_abc_cache', 'clear', '_abc_negative_cache')

## bytecode:

   0: RESUME               
   2: LOAD_FAST            cls
   4: LOAD_ATTR            _abc_cache
  14: LOAD_METHOD          clear
  36: PRECALL              
  40: CALL                 
  50: POP_TOP              
  52: LOAD_FAST            cls
  54: LOAD_ATTR            _abc_negative_cache
  64: LOAD_METHOD          clear
  86: PRECALL              
  90: CALL                 
 100: POP_TOP              
 102: LOAD_CONST           None
 104: RETURN_VALUE         
