# Disassembly for _py_abc.ABCMeta.__instancecheck__
# From module file: _py_abc

## co_consts:
('Override for isinstance(instance, cls).', True, False, <code object <genexpr> at 0x00000240693EB230, file "_py_abc.py", line 106>)

## co_names:
('__class__', '_abc_cache', 'type', '_abc_negative_cache_version', 'ABCMeta', '_abc_invalidation_counter', '_abc_negative_cache', '__subclasscheck__', 'any')

## bytecode:

   0: MAKE_CELL            cls
   2: RESUME               
   4: LOAD_FAST            instance
   6: LOAD_ATTR            __class__
  16: STORE_FAST           subclass
  18: LOAD_FAST            subclass
  20: LOAD_DEREF           cls
  22: LOAD_ATTR            _abc_cache
  32: CONTAINS_OP          
  34: POP_JUMP_FORWARD_IF_FALSE to 40
  36: LOAD_CONST           True
  38: RETURN_VALUE         
  40: LOAD_GLOBAL          NULL + type
  52: LOAD_FAST            instance
  54: PRECALL              
  58: CALL                 
  68: STORE_FAST           subtype
  70: LOAD_FAST            subtype
  72: LOAD_FAST            subclass
  74: IS_OP                
  76: POP_JUMP_FORWARD_IF_FALSE to 184
  78: LOAD_DEREF           cls
  80: LOAD_ATTR            _abc_negative_cache_version
  90: LOAD_GLOBAL          ABCMeta
 102: LOAD_ATTR            _abc_invalidation_counter
 112: COMPARE_OP           ==
 118: POP_JUMP_FORWARD_IF_FALSE to 142
 120: LOAD_FAST            subclass
 122: LOAD_DEREF           cls
 124: LOAD_ATTR            _abc_negative_cache
 134: CONTAINS_OP          
 136: POP_JUMP_FORWARD_IF_FALSE to 142
 138: LOAD_CONST           False
 140: RETURN_VALUE         
 142: LOAD_DEREF           cls
 144: LOAD_METHOD          __subclasscheck__
 166: LOAD_FAST            subclass
 168: PRECALL              
 172: CALL                 
 182: RETURN_VALUE         
 184: LOAD_GLOBAL          NULL + any
 196: LOAD_CLOSURE         cls
 198: BUILD_TUPLE          
 200: LOAD_CONST           <code object <genexpr> at 0x00000240693EB230, file "_py_abc.py", line 106>
 202: MAKE_FUNCTION        closure
 204: LOAD_FAST            subclass
 206: LOAD_FAST            subtype
 208: BUILD_TUPLE          
 210: GET_ITER             
 212: PRECALL              
 216: CALL                 
 226: PRECALL              
 230: CALL                 
 240: RETURN_VALUE         
