# Disassembly for _threading_local._localimpl.create_dict.thread_deleted
# From module file: _threading_local

## co_consts:
(None,)

## co_names:
('dicts', 'pop')

## bytecode:

   0: COPY_FREE_VARS       
   2: RESUME               
   4: PUSH_NULL            
   6: LOAD_DEREF           wrlocal
   8: PRECALL              
  12: CALL                 
  22: STORE_FAST           local
  24: LOAD_FAST            local
  26: POP_JUMP_FORWARD_IF_NONE to 84
  28: LOAD_FAST            local
  30: LOAD_ATTR            dicts
  40: LOAD_METHOD          pop
  62: LOAD_FAST            idt
  64: PRECALL              
  68: CALL                 
  78: STORE_FAST           dct
  80: LOAD_CONST           None
  82: RETURN_VALUE         
  84: LOAD_CONST           None
  86: RETURN_VALUE         
