# Disassembly for _threading_local.local.__new__
# From module file: _threading_local

## co_consts:
(None, 'Initialization arguments are not supported', '_local__impl')

## co_names:
('__init__', 'object', 'TypeError', '__new__', '_localimpl', 'localargs', 'RLock', 'locallock', '__setattr__', 'create_dict')

## bytecode:

   0: RESUME               
   2: LOAD_FAST            args
   4: POP_JUMP_FORWARD_IF_TRUE to 10
   6: LOAD_FAST            kw
   8: POP_JUMP_FORWARD_IF_FALSE to 78
  10: LOAD_FAST            cls
  12: LOAD_ATTR            __init__
  22: LOAD_GLOBAL          object
  34: LOAD_ATTR            __init__
  44: IS_OP                
  46: POP_JUMP_FORWARD_IF_FALSE to 78
  48: LOAD_GLOBAL          NULL + TypeError
  60: LOAD_CONST           'Initialization arguments are not supported'
  62: PRECALL              
  66: CALL                 
  76: RAISE_VARARGS        
  78: LOAD_GLOBAL          object
  90: LOAD_METHOD          __new__
 112: LOAD_FAST            cls
 114: PRECALL              
 118: CALL                 
 128: STORE_FAST           self
 130: LOAD_GLOBAL          NULL + _localimpl
 142: PRECALL              
 146: CALL                 
 156: STORE_FAST           impl
 158: LOAD_FAST            args
 160: LOAD_FAST            kw
 162: BUILD_TUPLE          
 164: LOAD_FAST            impl
 166: STORE_ATTR           localargs
 176: LOAD_GLOBAL          NULL + RLock
 188: PRECALL              
 192: CALL                 
 202: LOAD_FAST            impl
 204: STORE_ATTR           locallock
 214: LOAD_GLOBAL          object
 226: LOAD_METHOD          __setattr__
 248: LOAD_FAST            self
 250: LOAD_CONST           '_local__impl'
 252: LOAD_FAST            impl
 254: PRECALL              
 258: CALL                 
 268: POP_TOP              
 270: LOAD_FAST            impl
 272: LOAD_METHOD          create_dict
 294: PRECALL              
 298: CALL                 
 308: POP_TOP              
 310: LOAD_FAST            self
 312: RETURN_VALUE         
