# Disassembly for _threading_local.local.__getattribute__
# From module file: _threading_local

## co_consts:
(None,)

## co_names:
('_patch', 'object', '__getattribute__')

## bytecode:

   0: RESUME               
   2: LOAD_GLOBAL          NULL + _patch
  14: LOAD_FAST            self
  16: PRECALL              
  20: CALL                 
  30: BEFORE_WITH          
  32: POP_TOP              
  34: LOAD_GLOBAL          object
  46: LOAD_METHOD          __getattribute__
  68: LOAD_FAST            self
  70: LOAD_FAST            name
  72: PRECALL              
  76: CALL                 
  86: SWAP                 
  88: LOAD_CONST           None
  90: LOAD_CONST           None
  92: LOAD_CONST           None
  94: PRECALL              
  98: CALL                 
 108: POP_TOP              
 110: RETURN_VALUE         
 112: PUSH_EXC_INFO        
 114: WITH_EXCEPT_START    
 116: POP_JUMP_FORWARD_IF_TRUE to 126
 118: RERAISE              
 120: COPY                 
 122: POP_EXCEPT           
 124: RERAISE              
 126: POP_TOP              
 128: POP_EXCEPT           
 130: POP_TOP              
 132: POP_TOP              
 134: LOAD_CONST           None
 136: RETURN_VALUE         
