# Disassembly for _threading_local._localimpl.create_dict.local_deleted
# From module file: _threading_local

## co_consts:
(None,)

## co_names:
('__dict__',)

## bytecode:

   0: COPY_FREE_VARS       
   2: RESUME               
   4: PUSH_NULL            
   6: LOAD_DEREF           wrthread
   8: PRECALL              
  12: CALL                 
  22: STORE_FAST           thread
  24: LOAD_FAST            thread
  26: POP_JUMP_FORWARD_IF_NONE to 48
  28: LOAD_FAST            thread
  30: LOAD_ATTR            __dict__
  40: LOAD_FAST            key
  42: DELETE_SUBSCR        
  44: LOAD_CONST           None
  46: RETURN_VALUE         
  48: LOAD_CONST           None
  50: RETURN_VALUE         
