# Disassembly for _threading_local._patch
# From module file: _threading_local

## co_consts:
(None, '_local__impl', '__dict__')

## co_names:
('object', '__getattribute__', 'get_dict', 'KeyError', 'create_dict', 'localargs', '__init__', 'locallock', '__setattr__')

## bytecode:

   0: RETURN_GENERATOR     
   2: POP_TOP              
   4: RESUME               
   6: LOAD_GLOBAL          object
  18: LOAD_METHOD          __getattribute__
  40: LOAD_FAST            self
  42: LOAD_CONST           '_local__impl'
  44: PRECALL              
  48: CALL                 
  58: STORE_FAST           impl
  60: NOP                  
  62: LOAD_FAST            impl
  64: LOAD_METHOD          get_dict
  86: PRECALL              
  90: CALL                 
 100: STORE_FAST           dct
 102: JUMP_FORWARD         to 222
 104: PUSH_EXC_INFO        
 106: LOAD_GLOBAL          KeyError
 118: CHECK_EXC_MATCH      
 120: POP_JUMP_FORWARD_IF_FALSE to 214
 122: POP_TOP              
 124: LOAD_FAST            impl
 126: LOAD_METHOD          create_dict
 148: PRECALL              
 152: CALL                 
 162: STORE_FAST           dct
 164: LOAD_FAST            impl
 166: LOAD_ATTR            localargs
 176: UNPACK_SEQUENCE      
 180: STORE_FAST           args
 182: STORE_FAST           kw
 184: PUSH_NULL            
 186: LOAD_FAST            self
 188: LOAD_ATTR            __init__
 198: LOAD_FAST            args
 200: BUILD_MAP            
 202: LOAD_FAST            kw
 204: DICT_MERGE           
 206: CALL_FUNCTION_EX     
 208: POP_TOP              
 210: POP_EXCEPT           
 212: JUMP_FORWARD         to 222
 214: RERAISE              
 216: COPY                 
 218: POP_EXCEPT           
 220: RERAISE              
 222: LOAD_FAST            impl
 224: LOAD_ATTR            locallock
 234: BEFORE_WITH          
 236: POP_TOP              
 238: LOAD_GLOBAL          object
 250: LOAD_METHOD          __setattr__
 272: LOAD_FAST            self
 274: LOAD_CONST           '__dict__'
 276: LOAD_FAST            dct
 278: PRECALL              
 282: CALL                 
 292: POP_TOP              
 294: LOAD_CONST           None
 296: YIELD_VALUE          
 298: RESUME               
 300: POP_TOP              
 302: LOAD_CONST           None
 304: LOAD_CONST           None
 306: LOAD_CONST           None
 308: PRECALL              
 312: CALL                 
 322: POP_TOP              
 324: LOAD_CONST           None
 326: RETURN_VALUE         
 328: PUSH_EXC_INFO        
 330: WITH_EXCEPT_START    
 332: POP_JUMP_FORWARD_IF_TRUE to 342
 334: RERAISE              
 336: COPY                 
 338: POP_EXCEPT           
 340: RERAISE              
 342: POP_TOP              
 344: POP_EXCEPT           
 346: POP_TOP              
 348: POP_TOP              
 350: LOAD_CONST           None
 352: RETURN_VALUE         
