# Disassembly for pickle._Unpickler.load_frame
# From module file: pickle

## co_consts:
(None, '<Q', 8, 'frame size > sys.maxsize: %d')

## co_names:
('unpack', 'read', 'sys', 'maxsize', 'ValueError', '_unframer', 'load_frame')

## bytecode:

   0: RESUME               
   2: LOAD_GLOBAL          NULL + unpack
  14: LOAD_CONST           '<Q'
  16: LOAD_FAST            self
  18: LOAD_METHOD          read
  40: LOAD_CONST           8
  42: PRECALL              
  46: CALL                 
  56: PRECALL              
  60: CALL                 
  70: UNPACK_SEQUENCE      
  74: STORE_FAST           frame_size
  76: LOAD_FAST            frame_size
  78: LOAD_GLOBAL          sys
  90: LOAD_ATTR            maxsize
 100: COMPARE_OP           >
 106: POP_JUMP_FORWARD_IF_FALSE to 144
 108: LOAD_GLOBAL          NULL + ValueError
 120: LOAD_CONST           'frame size > sys.maxsize: %d'
 122: LOAD_FAST            frame_size
 124: BINARY_OP            %
 128: PRECALL              
 132: CALL                 
 142: RAISE_VARARGS        
 144: LOAD_FAST            self
 146: LOAD_ATTR            _unframer
 156: LOAD_METHOD          load_frame
 178: LOAD_FAST            frame_size
 180: PRECALL              
 184: CALL                 
 194: POP_TOP              
 196: LOAD_CONST           None
 198: RETURN_VALUE         
