# Disassembly for pickle._Unpickler.load_tuple
# From module file: pickle

## co_consts:
(None,)

## co_names:
('pop_mark', 'append', 'tuple')

## bytecode:

   0: RESUME               
   2: LOAD_FAST            self
   4: LOAD_METHOD          pop_mark
  26: PRECALL              
  30: CALL                 
  40: STORE_FAST           items
  42: LOAD_FAST            self
  44: LOAD_METHOD          append
  66: LOAD_GLOBAL          NULL + tuple
  78: LOAD_FAST            items
  80: PRECALL              
  84: CALL                 
  94: PRECALL              
  98: CALL                 
 108: POP_TOP              
 110: LOAD_CONST           None
 112: RETURN_VALUE         
