# Disassembly for pickle._Unpickler.load_long1
# From module file: pickle

## co_consts:
(None, 1, 0)

## co_names:
('read', 'append', 'decode_long')

## bytecode:

   0: RESUME               
   2: LOAD_FAST            self
   4: LOAD_METHOD          read
  26: LOAD_CONST           1
  28: PRECALL              
  32: CALL                 
  42: LOAD_CONST           0
  44: BINARY_SUBSCR        
  54: STORE_FAST           n
  56: LOAD_FAST            self
  58: LOAD_METHOD          read
  80: LOAD_FAST            n
  82: PRECALL              
  86: CALL                 
  96: STORE_FAST           data
  98: LOAD_FAST            self
 100: LOAD_METHOD          append
 122: LOAD_GLOBAL          NULL + decode_long
 134: LOAD_FAST            data
 136: PRECALL              
 140: CALL                 
 150: PRECALL              
 154: CALL                 
 164: POP_TOP              
 166: LOAD_CONST           None
 168: RETURN_VALUE         
