# Disassembly for pickle._Pickler.save_list
# From module file: pickle

## co_consts:
(None,)

## co_names:
('bin', 'write', 'EMPTY_LIST', 'MARK', 'LIST', 'memoize', '_batch_appends')

## bytecode:

   0: RESUME               
   2: LOAD_FAST            self
   4: LOAD_ATTR            bin
  14: POP_JUMP_FORWARD_IF_FALSE to 70
  16: LOAD_FAST            self
  18: LOAD_METHOD          write
  40: LOAD_GLOBAL          EMPTY_LIST
  52: PRECALL              
  56: CALL                 
  66: POP_TOP              
  68: JUMP_FORWARD         to 138
  70: LOAD_FAST            self
  72: LOAD_METHOD          write
  94: LOAD_GLOBAL          MARK
 106: LOAD_GLOBAL          LIST
 118: BINARY_OP            +
 122: PRECALL              
 126: CALL                 
 136: POP_TOP              
 138: LOAD_FAST            self
 140: LOAD_METHOD          memoize
 162: LOAD_FAST            obj
 164: PRECALL              
 168: CALL                 
 178: POP_TOP              
 180: LOAD_FAST            self
 182: LOAD_METHOD          _batch_appends
 204: LOAD_FAST            obj
 206: PRECALL              
 210: CALL                 
 220: POP_TOP              
 222: LOAD_CONST           None
 224: RETURN_VALUE         
