# Disassembly for pickle._Pickler.save_float
# From module file: pickle

## co_consts:
(None, '>d', 'ascii', b'\n')

## co_names:
('bin', 'write', 'BINFLOAT', 'pack', 'FLOAT', 'repr', 'encode')

## bytecode:

   0: RESUME               
   2: LOAD_FAST            self
   4: LOAD_ATTR            bin
  14: POP_JUMP_FORWARD_IF_FALSE to 106
  16: LOAD_FAST            self
  18: LOAD_METHOD          write
  40: LOAD_GLOBAL          BINFLOAT
  52: LOAD_GLOBAL          NULL + pack
  64: LOAD_CONST           '>d'
  66: LOAD_FAST            obj
  68: PRECALL              
  72: CALL                 
  82: BINARY_OP            +
  86: PRECALL              
  90: CALL                 
 100: POP_TOP              
 102: LOAD_CONST           None
 104: RETURN_VALUE         
 106: LOAD_FAST            self
 108: LOAD_METHOD          write
 130: LOAD_GLOBAL          FLOAT
 142: LOAD_GLOBAL          NULL + repr
 154: LOAD_FAST            obj
 156: PRECALL              
 160: CALL                 
 170: LOAD_METHOD          encode
 192: LOAD_CONST           'ascii'
 194: PRECALL              
 198: CALL                 
 208: BINARY_OP            +
 212: LOAD_CONST           b'\n'
 214: BINARY_OP            +
 218: PRECALL              
 222: CALL                 
 232: POP_TOP              
 234: LOAD_CONST           None
 236: RETURN_VALUE         
