# Disassembly for pickle._Unpickler.load_tuple3
# From module file: pickle

## co_consts:
(None, -3, -2, -1)

## co_names:
('stack',)

## bytecode:

   0: RESUME               
   2: LOAD_FAST            self
   4: LOAD_ATTR            stack
  14: LOAD_CONST           -3
  16: BINARY_SUBSCR        
  26: LOAD_FAST            self
  28: LOAD_ATTR            stack
  38: LOAD_CONST           -2
  40: BINARY_SUBSCR        
  50: LOAD_FAST            self
  52: LOAD_ATTR            stack
  62: LOAD_CONST           -1
  64: BINARY_SUBSCR        
  74: BUILD_TUPLE          
  76: BUILD_LIST           
  78: LOAD_FAST            self
  80: LOAD_ATTR            stack
  90: LOAD_CONST           -3
  92: LOAD_CONST           None
  94: BUILD_SLICE          
  96: STORE_SUBSCR         
 100: LOAD_CONST           None
 102: RETURN_VALUE         
