# Disassembly for pickle._Unpickler.load_binpersid
# From module file: pickle

## co_consts:
(None,)

## co_names:
('stack', 'pop', 'append', 'persistent_load')

## bytecode:

   0: RESUME               
   2: LOAD_FAST            self
   4: LOAD_ATTR            stack
  14: LOAD_METHOD          pop
  36: PRECALL              
  40: CALL                 
  50: STORE_FAST           pid
  52: LOAD_FAST            self
  54: LOAD_METHOD          append
  76: LOAD_FAST            self
  78: LOAD_METHOD          persistent_load
 100: LOAD_FAST            pid
 102: PRECALL              
 106: CALL                 
 116: PRECALL              
 120: CALL                 
 130: POP_TOP              
 132: LOAD_CONST           None
 134: RETURN_VALUE         
