# Disassembly for pickle._Unpickler._decode_string
# From module file: pickle

## co_consts:
(None, 'bytes')

## co_names:
('encoding', 'decode', 'errors')

## bytecode:

   0: RESUME               
   2: LOAD_FAST            self
   4: LOAD_ATTR            encoding
  14: LOAD_CONST           'bytes'
  16: COMPARE_OP           ==
  22: POP_JUMP_FORWARD_IF_FALSE to 28
  24: LOAD_FAST            value
  26: RETURN_VALUE         
  28: LOAD_FAST            value
  30: LOAD_METHOD          decode
  52: LOAD_FAST            self
  54: LOAD_ATTR            encoding
  64: LOAD_FAST            self
  66: LOAD_ATTR            errors
  76: PRECALL              
  80: CALL                 
  90: RETURN_VALUE         
