# Disassembly for pickle.PicklingError
# From module file: pickle

## co_consts:
('PicklingError', 'This exception is raised when an unpicklable object is passed to the\n    dump() method.\n\n    ', None)

## co_names:
('__name__', '__module__', '__qualname__', '__doc__')

## bytecode:

   0: RESUME               
   2: LOAD_NAME            __name__
   4: STORE_NAME           __module__
   6: LOAD_CONST           'PicklingError'
   8: STORE_NAME           __qualname__
  10: LOAD_CONST           'This exception is raised when an unpicklable object is passed to the\n    dump() method.\n\n    '
  12: STORE_NAME           __doc__
  14: LOAD_CONST           None
  16: RETURN_VALUE         
