# Disassembly for pickle.UnpicklingError
# From module file: pickle

## co_consts:
('UnpicklingError', 'This exception is raised when there is a problem unpickling an object,\n    such as a security violation.\n\n    Note that other exceptions may also be raised during unpickling, including\n    (but not necessarily limited to) AttributeError, EOFError, ImportError,\n    and IndexError.\n\n    ', None)

## co_names:
('__name__', '__module__', '__qualname__', '__doc__')

## bytecode:

   0: RESUME               
   2: LOAD_NAME            __name__
   4: STORE_NAME           __module__
   6: LOAD_CONST           'UnpicklingError'
   8: STORE_NAME           __qualname__
  10: LOAD_CONST           'This exception is raised when there is a problem unpickling an object,\n    such as a security violation.\n\n    Note that other exceptions may also be raised during unpickling, including\n    (but not necessarily limited to) AttributeError, EOFError, ImportError,\n    and IndexError.\n\n    '
  12: STORE_NAME           __doc__
  14: LOAD_CONST           None
  16: RETURN_VALUE         
