# Disassembly for pickle._Unframer.__init__
# From module file: pickle

## co_consts:
(None,)

## co_names:
('file_read', 'file_readline', 'current_frame')

## bytecode:

   0: RESUME               
   2: LOAD_FAST            file_read
   4: LOAD_FAST            self
   6: STORE_ATTR           file_read
  16: LOAD_FAST            file_readline
  18: LOAD_FAST            self
  20: STORE_ATTR           file_readline
  30: LOAD_CONST           None
  32: LOAD_FAST            self
  34: STORE_ATTR           current_frame
  44: LOAD_CONST           None
  46: RETURN_VALUE         
