# Disassembly for pickle._Pickler.save_global
# From module file: pickle

## co_consts:
(None, '__qualname__', 0, ('level',), "Can't pickle ", ": it's not the same object as ", '.', ": it's not found as ", 2, 255, '<B', 65535, '<H', '<i', 4, 3, 'utf-8', b'\n', 'ascii', "can't pickle global identifier '%s.%s' using pickle protocol %i")

## co_names:
('write', 'memo', 'getattr', '__name__', 'whichmodule', '__import__', 'sys', 'modules', '_getattribute', 'PicklingError', 'ImportError', 'KeyError', 'AttributeError', 'proto', '_extension_registry', 'get', 'EXT1', 'pack', 'EXT2', 'EXT4', 'rpartition', 'save', 'STACK_GLOBAL', 'save_reduce', 'GLOBAL', 'bytes', 'fix_imports', '_compat_pickle', 'REVERSE_NAME_MAPPING', 'REVERSE_IMPORT_MAPPING', 'UnicodeEncodeError', 'memoize')

## bytecode:

   0: RESUME               
   2: LOAD_FAST            self
   4: LOAD_ATTR            write
  14: STORE_FAST           write
  16: LOAD_FAST            self
  18: LOAD_ATTR            memo
  28: STORE_FAST           memo
  30: LOAD_FAST            name
  32: POP_JUMP_FORWARD_IF_NOT_NONE to 68
  34: LOAD_GLOBAL          NULL + getattr
  46: LOAD_FAST            obj
  48: LOAD_CONST           '__qualname__'
  50: LOAD_CONST           None
  52: PRECALL              
  56: CALL                 
  66: STORE_FAST           name
  68: LOAD_FAST            name
  70: POP_JUMP_FORWARD_IF_NOT_NONE to 86
  72: LOAD_FAST            obj
  74: LOAD_ATTR            __name__
  84: STORE_FAST           name
  86: LOAD_GLOBAL          NULL + whichmodule
  98: LOAD_FAST            obj
 100: LOAD_FAST            name
 102: PRECALL              
 106: CALL                 
 116: STORE_FAST           module_name
 118: NOP                  
 120: LOAD_GLOBAL          NULL + __import__
 132: LOAD_FAST            module_name
 134: LOAD_CONST           0
 136: KW_NAMES             
 138: PRECALL              
 142: CALL                 
 152: POP_TOP              
 154: LOAD_GLOBAL          sys
 166: LOAD_ATTR            modules
 176: LOAD_FAST            module_name
 178: BINARY_SUBSCR        
 188: STORE_FAST           module
 190: LOAD_GLOBAL          NULL + _getattribute
 202: LOAD_FAST            module
 204: LOAD_FAST            name
 206: PRECALL              
 210: CALL                 
 220: UNPACK_SEQUENCE      
 224: STORE_FAST           obj2
 226: STORE_FAST           parent
 228: LOAD_FAST            obj2
 230: LOAD_FAST            obj
 232: IS_OP                
 234: POP_JUMP_FORWARD_IF_FALSE to 284
 236: LOAD_GLOBAL          NULL + PicklingError
 248: LOAD_CONST           "Can't pickle "
 250: LOAD_FAST            obj
 252: FORMAT_VALUE         repr
 254: LOAD_CONST           ": it's not the same object as "
 256: LOAD_FAST            module_name
 258: FORMAT_VALUE         str
 260: LOAD_CONST           '.'
 262: LOAD_FAST            name
 264: FORMAT_VALUE         str
 266: BUILD_STRING         
 268: PRECALL              
 272: CALL                 
 282: RAISE_VARARGS        
 284: JUMP_FORWARD         to 390
 286: PUSH_EXC_INFO        
 288: LOAD_GLOBAL          ImportError
 300: LOAD_GLOBAL          KeyError
 312: LOAD_GLOBAL          AttributeError
 324: BUILD_TUPLE          
 326: CHECK_EXC_MATCH      
 328: POP_JUMP_FORWARD_IF_FALSE to 382
 330: POP_TOP              
 332: LOAD_GLOBAL          NULL + PicklingError
 344: LOAD_CONST           "Can't pickle "
 346: LOAD_FAST            obj
 348: FORMAT_VALUE         repr
 350: LOAD_CONST           ": it's not found as "
 352: LOAD_FAST            module_name
 354: FORMAT_VALUE         str
 356: LOAD_CONST           '.'
 358: LOAD_FAST            name
 360: FORMAT_VALUE         str
 362: BUILD_STRING         
 364: PRECALL              
 368: CALL                 
 378: LOAD_CONST           None
 380: RAISE_VARARGS        
 382: RERAISE              
 384: COPY                 
 386: POP_EXCEPT           
 388: RERAISE              
 390: LOAD_FAST            self
 392: LOAD_ATTR            proto
 402: LOAD_CONST           2
 404: COMPARE_OP           >=
 410: POP_JUMP_FORWARD_IF_FALSE to 706
 412: LOAD_GLOBAL          NULL + _extension_registry
 424: LOAD_ATTR            get
 434: LOAD_FAST            module_name
 436: LOAD_FAST            name
 438: BUILD_TUPLE          
 440: PRECALL              
 444: CALL                 
 454: STORE_FAST           code
 456: LOAD_FAST            code
 458: POP_JUMP_FORWARD_IF_FALSE to 706
 460: LOAD_FAST            code
 462: LOAD_CONST           0
 464: COMPARE_OP           >
 470: POP_JUMP_FORWARD_IF_TRUE to 476
 472: LOAD_ASSERTION_ERROR 
 474: RAISE_VARARGS        
 476: LOAD_FAST            code
 478: LOAD_CONST           255
 480: COMPARE_OP           <=
 486: POP_JUMP_FORWARD_IF_FALSE to 556
 488: PUSH_NULL            
 490: LOAD_FAST            write
 492: LOAD_GLOBAL          EXT1
 504: LOAD_GLOBAL          NULL + pack
 516: LOAD_CONST           '<B'
 518: LOAD_FAST            code
 520: PRECALL              
 524: CALL                 
 534: BINARY_OP            +
 538: PRECALL              
 542: CALL                 
 552: POP_TOP              
 554: JUMP_FORWARD         to 702
 556: LOAD_FAST            code
 558: LOAD_CONST           65535
 560: COMPARE_OP           <=
 566: POP_JUMP_FORWARD_IF_FALSE to 636
 568: PUSH_NULL            
 570: LOAD_FAST            write
 572: LOAD_GLOBAL          EXT2
 584: LOAD_GLOBAL          NULL + pack
 596: LOAD_CONST           '<H'
 598: LOAD_FAST            code
 600: PRECALL              
 604: CALL                 
 614: BINARY_OP            +
 618: PRECALL              
 622: CALL                 
 632: POP_TOP              
 634: JUMP_FORWARD         to 702
 636: PUSH_NULL            
 638: LOAD_FAST            write
 640: LOAD_GLOBAL          EXT4
 652: LOAD_GLOBAL          NULL + pack
 664: LOAD_CONST           '<i'
 666: LOAD_FAST            code
 668: PRECALL              
 672: CALL                 
 682: BINARY_OP            +
 686: PRECALL              
 690: CALL                 
 700: POP_TOP              
 702: LOAD_CONST           None
 704: RETURN_VALUE         
 706: LOAD_FAST            name
 708: LOAD_METHOD          rpartition
 730: LOAD_CONST           '.'
 732: PRECALL              
 736: CALL                 
 746: LOAD_CONST           2
 748: BINARY_SUBSCR        
 758: STORE_FAST           lastname
 760: LOAD_FAST            parent
 762: LOAD_FAST            module
 764: IS_OP                
 766: POP_JUMP_FORWARD_IF_FALSE to 772
 768: LOAD_FAST            lastname
 770: STORE_FAST           name
 772: LOAD_FAST            self
 774: LOAD_ATTR            proto
 784: LOAD_CONST           4
 786: COMPARE_OP           >=
 792: POP_JUMP_FORWARD_IF_FALSE to 914
 794: LOAD_FAST            self
 796: LOAD_METHOD          save
 818: LOAD_FAST            module_name
 820: PRECALL              
 824: CALL                 
 834: POP_TOP              
 836: LOAD_FAST            self
 838: LOAD_METHOD          save
 860: LOAD_FAST            name
 862: PRECALL              
 866: CALL                 
 876: POP_TOP              
 878: PUSH_NULL            
 880: LOAD_FAST            write
 882: LOAD_GLOBAL          STACK_GLOBAL
 894: PRECALL              
 898: CALL                 
 908: POP_TOP              
 910: EXTENDED_ARG         
 912: JUMP_FORWARD         to 1442
 914: LOAD_FAST            parent
 916: LOAD_FAST            module
 918: IS_OP                
 920: POP_JUMP_FORWARD_IF_FALSE to 982
 922: LOAD_FAST            self
 924: LOAD_METHOD          save_reduce
 946: LOAD_GLOBAL          getattr
 958: LOAD_FAST            parent
 960: LOAD_FAST            lastname
 962: BUILD_TUPLE          
 964: PRECALL              
 968: CALL                 
 978: POP_TOP              
 980: JUMP_FORWARD         to 1442
 982: LOAD_FAST            self
 984: LOAD_ATTR            proto
 994: LOAD_CONST           3
 996: COMPARE_OP           >=
1002: POP_JUMP_FORWARD_IF_FALSE to 1118
1004: PUSH_NULL            
1006: LOAD_FAST            write
1008: LOAD_GLOBAL          GLOBAL
1020: LOAD_GLOBAL          NULL + bytes
1032: LOAD_FAST            module_name
1034: LOAD_CONST           'utf-8'
1036: PRECALL              
1040: CALL                 
1050: BINARY_OP            +
1054: LOAD_CONST           b'\n'
1056: BINARY_OP            +
1060: LOAD_GLOBAL          NULL + bytes
1072: LOAD_FAST            name
1074: LOAD_CONST           'utf-8'
1076: PRECALL              
1080: CALL                 
1090: BINARY_OP            +
1094: LOAD_CONST           b'\n'
1096: BINARY_OP            +
1100: PRECALL              
1104: CALL                 
1114: POP_TOP              
1116: JUMP_FORWARD         to 1442
1118: LOAD_FAST            self
1120: LOAD_ATTR            fix_imports
1130: POP_JUMP_FORWARD_IF_FALSE to 1244
1132: LOAD_GLOBAL          _compat_pickle
1144: LOAD_ATTR            REVERSE_NAME_MAPPING
1154: STORE_FAST           r_name_mapping
1156: LOAD_GLOBAL          _compat_pickle
1168: LOAD_ATTR            REVERSE_IMPORT_MAPPING
1178: STORE_FAST           r_import_mapping
1180: LOAD_FAST            module_name
1182: LOAD_FAST            name
1184: BUILD_TUPLE          
1186: LOAD_FAST            r_name_mapping
1188: CONTAINS_OP          
1190: POP_JUMP_FORWARD_IF_FALSE to 1220
1192: LOAD_FAST            r_name_mapping
1194: LOAD_FAST            module_name
1196: LOAD_FAST            name
1198: BUILD_TUPLE          
1200: BINARY_SUBSCR        
1210: UNPACK_SEQUENCE      
1214: STORE_FAST           module_name
1216: STORE_FAST           name
1218: JUMP_FORWARD         to 1244
1220: LOAD_FAST            module_name
1222: LOAD_FAST            r_import_mapping
1224: CONTAINS_OP          
1226: POP_JUMP_FORWARD_IF_FALSE to 1244
1228: LOAD_FAST            r_import_mapping
1230: LOAD_FAST            module_name
1232: BINARY_SUBSCR        
1242: STORE_FAST           module_name
1244: NOP                  
1246: PUSH_NULL            
1248: LOAD_FAST            write
1250: LOAD_GLOBAL          GLOBAL
1262: LOAD_GLOBAL          NULL + bytes
1274: LOAD_FAST            module_name
1276: LOAD_CONST           'ascii'
1278: PRECALL              
1282: CALL                 
1292: BINARY_OP            +
1296: LOAD_CONST           b'\n'
1298: BINARY_OP            +
1302: LOAD_GLOBAL          NULL + bytes
1314: LOAD_FAST            name
1316: LOAD_CONST           'ascii'
1318: PRECALL              
1322: CALL                 
1332: BINARY_OP            +
1336: LOAD_CONST           b'\n'
1338: BINARY_OP            +
1342: PRECALL              
1346: CALL                 
1356: POP_TOP              
1358: JUMP_FORWARD         to 1442
1360: PUSH_EXC_INFO        
1362: LOAD_GLOBAL          UnicodeEncodeError
1374: CHECK_EXC_MATCH      
1376: POP_JUMP_FORWARD_IF_FALSE to 1434
1378: POP_TOP              
1380: LOAD_GLOBAL          NULL + PicklingError
1392: LOAD_CONST           "can't pickle global identifier '%s.%s' using pickle protocol %i"
1394: LOAD_FAST            module
1396: LOAD_FAST            name
1398: LOAD_FAST            self
1400: LOAD_ATTR            proto
1410: BUILD_TUPLE          
1412: BINARY_OP            %
1416: PRECALL              
1420: CALL                 
1430: LOAD_CONST           None
1432: RAISE_VARARGS        
1434: RERAISE              
1436: COPY                 
1438: POP_EXCEPT           
1440: RERAISE              
1442: LOAD_FAST            self
1444: LOAD_METHOD          memoize
1466: LOAD_FAST            obj
1468: PRECALL              
1472: CALL                 
1482: POP_TOP              
1484: LOAD_CONST           None
1486: RETURN_VALUE         
