# Disassembly for pickle._Unpickler.load_string
# From module file: pickle

## co_consts:
(None, -1, 2, 0, b'"\'', 1, 'the STRING opcode argument must be quoted')

## co_names:
('readline', 'len', 'UnpicklingError', 'append', '_decode_string', 'codecs', 'escape_decode')

## bytecode:

   0: RESUME               
   2: LOAD_FAST            self
   4: LOAD_METHOD          readline
  26: PRECALL              
  30: CALL                 
  40: LOAD_CONST           None
  42: LOAD_CONST           -1
  44: BUILD_SLICE          
  46: BINARY_SUBSCR        
  56: STORE_FAST           data
  58: LOAD_GLOBAL          NULL + len
  70: LOAD_FAST            data
  72: PRECALL              
  76: CALL                 
  86: LOAD_CONST           2
  88: COMPARE_OP           >=
  94: POP_JUMP_FORWARD_IF_FALSE to 174
  96: LOAD_FAST            data
  98: LOAD_CONST           0
 100: BINARY_SUBSCR        
 110: LOAD_FAST            data
 112: LOAD_CONST           -1
 114: BINARY_SUBSCR        
 124: COMPARE_OP           ==
 130: POP_JUMP_FORWARD_IF_FALSE to 174
 132: LOAD_FAST            data
 134: LOAD_CONST           0
 136: BINARY_SUBSCR        
 146: LOAD_CONST           b'"\''
 148: CONTAINS_OP          
 150: POP_JUMP_FORWARD_IF_FALSE to 174
 152: LOAD_FAST            data
 154: LOAD_CONST           1
 156: LOAD_CONST           -1
 158: BUILD_SLICE          
 160: BINARY_SUBSCR        
 170: STORE_FAST           data
 172: JUMP_FORWARD         to 204
 174: LOAD_GLOBAL          NULL + UnpicklingError
 186: LOAD_CONST           'the STRING opcode argument must be quoted'
 188: PRECALL              
 192: CALL                 
 202: RAISE_VARARGS        
 204: LOAD_FAST            self
 206: LOAD_METHOD          append
 228: LOAD_FAST            self
 230: LOAD_METHOD          _decode_string
 252: LOAD_GLOBAL          NULL + codecs
 264: LOAD_ATTR            escape_decode
 274: LOAD_FAST            data
 276: PRECALL              
 280: CALL                 
 290: LOAD_CONST           0
 292: BINARY_SUBSCR        
 302: PRECALL              
 306: CALL                 
 316: PRECALL              
 320: CALL                 
 330: POP_TOP              
 332: LOAD_CONST           None
 334: RETURN_VALUE         
