# Disassembly for pickle._Pickler.__init__
# From module file: pickle

## co_consts:
('This takes a binary file for writing a pickle data stream.\n\n        The optional *protocol* argument tells the pickler to use the\n        given protocol; supported protocols are 0, 1, 2, 3, 4 and 5.\n        The default protocol is 4. It was introduced in Python 3.4, and\n        is incompatible with previous versions.\n\n        Specifying a negative protocol version selects the highest\n        protocol version supported.  The higher the protocol used, the\n        more recent the version of Python needed to read the pickle\n        produced.\n\n        The *file* argument must have a write() method that accepts a\n        single bytes argument. It can thus be a file object opened for\n        binary writing, an io.BytesIO instance, or any other custom\n        object that meets this interface.\n\n        If *fix_imports* is True and *protocol* is less than 3, pickle\n        will try to map the new Python 3 names to the old module names\n        used in Python 2, so that the pickle data stream is readable\n        with Python 2.\n\n        If *buffer_callback* is None (the default), buffer views are\n        serialized into *file* as part of the pickle stream.\n\n        If *buffer_callback* is not None, then it can be called any number\n        of times with a buffer view.  If the callback returns a false value\n        (such as None), the given buffer is out-of-band; otherwise the\n        buffer is serialized in-band, i.e. inside the pickle stream.\n\n        It is an error if *buffer_callback* is not None and *protocol*\n        is None or smaller than 5.\n        ', None, 0, 'pickle protocol must be <= %d', 5, 'buffer_callback needs protocol >= 5', "file must have a 'write' attribute", 1, 3)

## co_names:
('DEFAULT_PROTOCOL', 'HIGHEST_PROTOCOL', 'ValueError', '_buffer_callback', 'write', '_file_write', 'AttributeError', 'TypeError', '_Framer', 'framer', 'write_large_bytes', '_write_large_bytes', 'memo', 'int', 'proto', 'bin', 'fast', 'fix_imports')

## bytecode:

   0: RESUME               
   2: LOAD_FAST            protocol
   4: POP_JUMP_FORWARD_IF_NOT_NONE to 20
   6: LOAD_GLOBAL          DEFAULT_PROTOCOL
  18: STORE_FAST           protocol
  20: LOAD_FAST            protocol
  22: LOAD_CONST           0
  24: COMPARE_OP           <
  30: POP_JUMP_FORWARD_IF_FALSE to 48
  32: LOAD_GLOBAL          HIGHEST_PROTOCOL
  44: STORE_FAST           protocol
  46: JUMP_FORWARD         to 134
  48: LOAD_CONST           0
  50: LOAD_FAST            protocol
  52: SWAP                 
  54: COPY                 
  56: COMPARE_OP           <=
  62: POP_JUMP_FORWARD_IF_FALSE to 86
  64: LOAD_GLOBAL          HIGHEST_PROTOCOL
  76: COMPARE_OP           <=
  82: POP_JUMP_FORWARD_IF_TRUE to 134
  84: JUMP_FORWARD         to 88
  86: POP_TOP              
  88: LOAD_GLOBAL          NULL + ValueError
 100: LOAD_CONST           'pickle protocol must be <= %d'
 102: LOAD_GLOBAL          HIGHEST_PROTOCOL
 114: BINARY_OP            %
 118: PRECALL              
 122: CALL                 
 132: RAISE_VARARGS        
 134: LOAD_FAST            buffer_callback
 136: POP_JUMP_FORWARD_IF_NONE to 180
 138: LOAD_FAST            protocol
 140: LOAD_CONST           5
 142: COMPARE_OP           <
 148: POP_JUMP_FORWARD_IF_FALSE to 180
 150: LOAD_GLOBAL          NULL + ValueError
 162: LOAD_CONST           'buffer_callback needs protocol >= 5'
 164: PRECALL              
 168: CALL                 
 178: RAISE_VARARGS        
 180: LOAD_FAST            buffer_callback
 182: LOAD_FAST            self
 184: STORE_ATTR           _buffer_callback
 194: NOP                  
 196: LOAD_FAST            file
 198: LOAD_ATTR            write
 208: LOAD_FAST            self
 210: STORE_ATTR           _file_write
 220: JUMP_FORWARD         to 280
 222: PUSH_EXC_INFO        
 224: LOAD_GLOBAL          AttributeError
 236: CHECK_EXC_MATCH      
 238: POP_JUMP_FORWARD_IF_FALSE to 272
 240: POP_TOP              
 242: LOAD_GLOBAL          NULL + TypeError
 254: LOAD_CONST           "file must have a 'write' attribute"
 256: PRECALL              
 260: CALL                 
 270: RAISE_VARARGS        
 272: RERAISE              
 274: COPY                 
 276: POP_EXCEPT           
 278: RERAISE              
 280: LOAD_GLOBAL          NULL + _Framer
 292: LOAD_FAST            self
 294: LOAD_ATTR            _file_write
 304: PRECALL              
 308: CALL                 
 318: LOAD_FAST            self
 320: STORE_ATTR           framer
 330: LOAD_FAST            self
 332: LOAD_ATTR            framer
 342: LOAD_ATTR            write
 352: LOAD_FAST            self
 354: STORE_ATTR           write
 364: LOAD_FAST            self
 366: LOAD_ATTR            framer
 376: LOAD_ATTR            write_large_bytes
 386: LOAD_FAST            self
 388: STORE_ATTR           _write_large_bytes
 398: BUILD_MAP            
 400: LOAD_FAST            self
 402: STORE_ATTR           memo
 412: LOAD_GLOBAL          NULL + int
 424: LOAD_FAST            protocol
 426: PRECALL              
 430: CALL                 
 440: LOAD_FAST            self
 442: STORE_ATTR           proto
 452: LOAD_FAST            protocol
 454: LOAD_CONST           1
 456: COMPARE_OP           >=
 462: LOAD_FAST            self
 464: STORE_ATTR           bin
 474: LOAD_CONST           0
 476: LOAD_FAST            self
 478: STORE_ATTR           fast
 488: LOAD_FAST            fix_imports
 490: JUMP_IF_FALSE_OR_POP to 502
 492: LOAD_FAST            protocol
 494: LOAD_CONST           3
 496: COMPARE_OP           <
 502: LOAD_FAST            self
 504: STORE_ATTR           fix_imports
 514: LOAD_CONST           None
 516: RETURN_VALUE         
