# Disassembly for pickle._dump
# From module file: pickle

## co_consts:
(None, ('fix_imports', 'buffer_callback'))

## co_names:
('_Pickler', 'dump')

## bytecode:

   0: RESUME               
   2: LOAD_GLOBAL          NULL + _Pickler
  14: LOAD_FAST            file
  16: LOAD_FAST            protocol
  18: LOAD_FAST            fix_imports
  20: LOAD_FAST            buffer_callback
  22: KW_NAMES             
  24: PRECALL              
  28: CALL                 
  38: LOAD_METHOD          dump
  60: LOAD_FAST            obj
  62: PRECALL              
  66: CALL                 
  76: POP_TOP              
  78: LOAD_CONST           None
  80: RETURN_VALUE         
