# Disassembly for pickle._Unpickler.load_dict.<dictcomp>
# From module file: pickle

## co_consts:
(1,)

## co_names:
()

## bytecode:

   0: COPY_FREE_VARS       
   2: RESUME               
   4: BUILD_MAP            
   6: LOAD_FAST            .0
   8: FOR_ITER             to 50
  10: STORE_FAST           i
  12: LOAD_DEREF           items
  14: LOAD_FAST            i
  16: BINARY_SUBSCR        
  26: LOAD_DEREF           items
  28: LOAD_FAST            i
  30: LOAD_CONST           1
  32: BINARY_OP            +
  36: BINARY_SUBSCR        
  46: MAP_ADD              
  48: JUMP_BACKWARD        to 8
  50: RETURN_VALUE         
