# Disassembly for pickle._Pickler.save_bytes
# From module file: pickle

## co_consts:
(None, 3, (), ('obj',), 'latin1', 255, '<B', 4294967295, 4, '<Q', '<I')

## co_names:
('proto', 'save_reduce', 'bytes', 'codecs', 'encode', 'str', 'len', 'write', 'SHORT_BINBYTES', 'pack', '_write_large_bytes', 'BINBYTES8', 'framer', '_FRAME_SIZE_TARGET', 'BINBYTES', 'memoize')

## bytecode:

   0: RESUME               
   2: LOAD_FAST            self
   4: LOAD_ATTR            proto
  14: LOAD_CONST           3
  16: COMPARE_OP           <
  22: POP_JUMP_FORWARD_IF_FALSE to 192
  24: LOAD_FAST            obj
  26: POP_JUMP_FORWARD_IF_TRUE to 88
  28: LOAD_FAST            self
  30: LOAD_METHOD          save_reduce
  52: LOAD_GLOBAL          bytes
  64: LOAD_CONST           ()
  66: LOAD_FAST            obj
  68: KW_NAMES             
  70: PRECALL              
  74: CALL                 
  84: POP_TOP              
  86: JUMP_FORWARD         to 188
  88: LOAD_FAST            self
  90: LOAD_METHOD          save_reduce
 112: LOAD_GLOBAL          codecs
 124: LOAD_ATTR            encode
 134: LOAD_GLOBAL          NULL + str
 146: LOAD_FAST            obj
 148: LOAD_CONST           'latin1'
 150: PRECALL              
 154: CALL                 
 164: LOAD_CONST           'latin1'
 166: BUILD_TUPLE          
 168: LOAD_FAST            obj
 170: KW_NAMES             
 172: PRECALL              
 176: CALL                 
 186: POP_TOP              
 188: LOAD_CONST           None
 190: RETURN_VALUE         
 192: LOAD_GLOBAL          NULL + len
 204: LOAD_FAST            obj
 206: PRECALL              
 210: CALL                 
 220: STORE_FAST           n
 222: LOAD_FAST            n
 224: LOAD_CONST           255
 226: COMPARE_OP           <=
 232: POP_JUMP_FORWARD_IF_FALSE to 328
 234: LOAD_FAST            self
 236: LOAD_METHOD          write
 258: LOAD_GLOBAL          SHORT_BINBYTES
 270: LOAD_GLOBAL          NULL + pack
 282: LOAD_CONST           '<B'
 284: LOAD_FAST            n
 286: PRECALL              
 290: CALL                 
 300: BINARY_OP            +
 304: LOAD_FAST            obj
 306: BINARY_OP            +
 310: PRECALL              
 314: CALL                 
 324: POP_TOP              
 326: JUMP_FORWARD         to 666
 328: LOAD_FAST            n
 330: LOAD_CONST           4294967295
 332: COMPARE_OP           >
 338: POP_JUMP_FORWARD_IF_FALSE to 452
 340: LOAD_FAST            self
 342: LOAD_ATTR            proto
 352: LOAD_CONST           4
 354: COMPARE_OP           >=
 360: POP_JUMP_FORWARD_IF_FALSE to 452
 362: LOAD_FAST            self
 364: LOAD_METHOD          _write_large_bytes
 386: LOAD_GLOBAL          BINBYTES8
 398: LOAD_GLOBAL          NULL + pack
 410: LOAD_CONST           '<Q'
 412: LOAD_FAST            n
 414: PRECALL              
 418: CALL                 
 428: BINARY_OP            +
 432: LOAD_FAST            obj
 434: PRECALL              
 438: CALL                 
 448: POP_TOP              
 450: JUMP_FORWARD         to 666
 452: LOAD_FAST            n
 454: LOAD_FAST            self
 456: LOAD_ATTR            framer
 466: LOAD_ATTR            _FRAME_SIZE_TARGET
 476: COMPARE_OP           >=
 482: POP_JUMP_FORWARD_IF_FALSE to 574
 484: LOAD_FAST            self
 486: LOAD_METHOD          _write_large_bytes
 508: LOAD_GLOBAL          BINBYTES
 520: LOAD_GLOBAL          NULL + pack
 532: LOAD_CONST           '<I'
 534: LOAD_FAST            n
 536: PRECALL              
 540: CALL                 
 550: BINARY_OP            +
 554: LOAD_FAST            obj
 556: PRECALL              
 560: CALL                 
 570: POP_TOP              
 572: JUMP_FORWARD         to 666
 574: LOAD_FAST            self
 576: LOAD_METHOD          write
 598: LOAD_GLOBAL          BINBYTES
 610: LOAD_GLOBAL          NULL + pack
 622: LOAD_CONST           '<I'
 624: LOAD_FAST            n
 626: PRECALL              
 630: CALL                 
 640: BINARY_OP            +
 644: LOAD_FAST            obj
 646: BINARY_OP            +
 650: PRECALL              
 654: CALL                 
 664: POP_TOP              
 666: LOAD_FAST            self
 668: LOAD_METHOD          memoize
 690: LOAD_FAST            obj
 692: PRECALL              
 696: CALL                 
 706: POP_TOP              
 708: LOAD_CONST           None
 710: RETURN_VALUE         
