# Disassembly for pickle._Unpickler
# From module file: pickle

## co_consts:
('_Unpickler', True, 'ASCII', 'strict', None, ('fix_imports', 'encoding', 'errors', 'buffers'), <code object __init__ at 0x000002406921FE00, file "pickle.py", line 1139>, <code object load at 0x0000024068DC0380, file "pickle.py", line 1187>, <code object pop_mark at 0x00000240693D2760, file "pickle.py", line 1218>, <code object persistent_load at 0x0000024069465990, file "pickle.py", line 1224>, <code object load_proto at 0x000002406922D920, file "pickle.py", line 1229>, 0, <code object load_frame at 0x00000240691EA730, file "pickle.py", line 1236>, <code object load_persid at 0x000002406934F7E0, file "pickle.py", line 1243>, <code object load_binpersid at 0x00000240693AB230, file "pickle.py", line 1252>, <code object load_none at 0x000002406945EA60, file "pickle.py", line 1257>, <code object load_false at 0x000002406945F000, file "pickle.py", line 1261>, <code object load_true at 0x000002406945E100, file "pickle.py", line 1265>, <code object load_int at 0x000002406942D160, file "pickle.py", line 1269>, <code object load_binint at 0x00000240693AA0B0, file "pickle.py", line 1280>, <code object load_binint1 at 0x000002406941AAF0, file "pickle.py", line 1284>, <code object load_binint2 at 0x00000240693ABAF0, file "pickle.py", line 1288>, <code object load_long at 0x000002406921FC90, file "pickle.py", line 1292>, <code object load_long1 at 0x000002406921FB20, file "pickle.py", line 1299>, <code object load_long4 at 0x00000240691F6250, file "pickle.py", line 1305>, <code object load_float at 0x00000240693AB5F0, file "pickle.py", line 1314>, <code object load_binfloat at 0x00000240693AAAB0, file "pickle.py", line 1318>, <code object _decode_string at 0x000002406941B090, file "pickle.py", line 1322>, <code object load_string at 0x00000240695EED60, file "pickle.py", line 1331>, <code object load_binstring at 0x000002406934FB40, file "pickle.py", line 1341>, <code object load_binbytes at 0x00000240691F5A30, file "pickle.py", line 1350>, <code object load_unicode at 0x00000240693A9570, file "pickle.py", line 1358>, <code object load_binunicode at 0x00000240694981F0, file "pickle.py", line 1362>, <code object load_binunicode8 at 0x00000240694983B0, file "pickle.py", line 1370>, <code object load_binbytes8 at 0x00000240691F5F10, file "pickle.py", line 1378>, <code object load_bytearray8 at 0x0000024069498570, file "pickle.py", line 1386>, <code object load_next_buffer at 0x00000240691E9E30, file "pickle.py", line 1396>, <code object load_readonly_buffer at 0x000002406921F9B0, file "pickle.py", line 1407>, <code object load_short_binstring at 0x000002406949CD20, file "pickle.py", line 1414>, <code object load_short_binbytes at 0x000002406922C570, file "pickle.py", line 1420>, <code object load_short_binunicode at 0x000002406949C8D0, file "pickle.py", line 1425>, <code object load_tuple at 0x00000240693D2E80, file "pickle.py", line 1430>, <code object load_empty_tuple at 0x000002406945DF20, file "pickle.py", line 1435>, <code object load_tuple1 at 0x000002406945F780, file "pickle.py", line 1439>, <code object load_tuple2 at 0x000002406944A010, file "pickle.py", line 1443>, <code object load_tuple3 at 0x000002406941B510, file "pickle.py", line 1447>, <code object load_empty_list at 0x000002406945D2F0, file "pickle.py", line 1451>, <code object load_empty_dictionary at 0x000002406945F1E0, file "pickle.py", line 1455>, <code object load_empty_set at 0x00000240693EB430, file "pickle.py", line 1459>, <code object load_frozenset at 0x00000240693D3210, file "pickle.py", line 1463>, <code object load_list at 0x000002406944B550, file "pickle.py", line 1468>, <code object load_dict at 0x000002406949CBB0, file "pickle.py", line 1473>, <code object _instantiate at 0x0000024068E24A20, file "pickle.py", line 1485>, <code object load_inst at 0x0000024069CDC030, file "pickle.py", line 1497>, <code object load_obj at 0x00000240693AB730, file "pickle.py", line 1504>, <code object load_newobj at 0x000002406949D2E0, file "pickle.py", line 1511>, <code object load_newobj_ex at 0x00000240691F5550, file "pickle.py", line 1518>, <code object load_global at 0x00000240691DAD80, file "pickle.py", line 1526>, <code object load_stack_global at 0x0000024069365F30, file "pickle.py", line 1533>, <code object load_ext1 at 0x000002406941B630, file "pickle.py", line 1541>, <code object load_ext2 at 0x00000240693AA830, file "pickle.py", line 1546>, <code object load_ext4 at 0x00000240693AA330, file "pickle.py", line 1551>, <code object get_extension at 0x0000024069365B50, file "pickle.py", line 1556>, <code object find_class at 0x0000024068E1C0F0, file "pickle.py", line 1572>, <code object load_reduce at 0x000002406941B750, file "pickle.py", line 1586>, <code object load_pop at 0x000002406944B330, file "pickle.py", line 1593>, <code object load_pop_mark at 0x000002406945FE10, file "pickle.py", line 1600>, <code object load_dup at 0x00000240693EB230, file "pickle.py", line 1604>, <code object load_get at 0x00000240691F63F0, file "pickle.py", line 1608>, <code object load_binget at 0x000002406942CB20, file "pickle.py", line 1617>, <code object load_long_binget at 0x00000240691F6590, file "pickle.py", line 1626>, <code object load_put at 0x000002406949D730, file "pickle.py", line 1635>, <code object load_binput at 0x000002406922D530, file "pickle.py", line 1642>, <code object load_long_binput at 0x000002406949D8A0, file "pickle.py", line 1649>, <code object load_memoize at 0x000002406944B770, file "pickle.py", line 1656>, <code object load_append at 0x00000240693D30E0, file "pickle.py", line 1661>, <code object load_appends at 0x00000240691E9530, file "pickle.py", line 1668>, <code object load_setitem at 0x00000240693AA970, file "pickle.py", line 1686>, <code object load_setitems at 0x000002406949CE90, file "pickle.py", line 1694>, <code object load_additems at 0x000002406942E290, file "pickle.py", line 1701>, <code object load_build at 0x0000024068C05730, file "pickle.py", line 1712>, <code object load_mark at 0x00000240693D3CC0, file "pickle.py", line 1736>, <code object load_stop at 0x000002406944A450, file "pickle.py", line 1742>)

## co_names:
('__name__', '__module__', '__qualname__', '__init__', 'load', 'pop_mark', 'persistent_load', 'dispatch', 'load_proto', 'PROTO', 'load_frame', 'FRAME', 'load_persid', 'PERSID', 'load_binpersid', 'BINPERSID', 'load_none', 'NONE', 'load_false', 'NEWFALSE', 'load_true', 'NEWTRUE', 'load_int', 'INT', 'load_binint', 'BININT', 'load_binint1', 'BININT1', 'load_binint2', 'BININT2', 'load_long', 'LONG', 'load_long1', 'LONG1', 'load_long4', 'LONG4', 'load_float', 'FLOAT', 'load_binfloat', 'BINFLOAT', '_decode_string', 'load_string', 'STRING', 'load_binstring', 'BINSTRING', 'load_binbytes', 'BINBYTES', 'load_unicode', 'UNICODE', 'load_binunicode', 'BINUNICODE', 'load_binunicode8', 'BINUNICODE8', 'load_binbytes8', 'BINBYTES8', 'load_bytearray8', 'BYTEARRAY8', 'load_next_buffer', 'NEXT_BUFFER', 'load_readonly_buffer', 'READONLY_BUFFER', 'load_short_binstring', 'SHORT_BINSTRING', 'load_short_binbytes', 'SHORT_BINBYTES', 'load_short_binunicode', 'SHORT_BINUNICODE', 'load_tuple', 'TUPLE', 'load_empty_tuple', 'EMPTY_TUPLE', 'load_tuple1', 'TUPLE1', 'load_tuple2', 'TUPLE2', 'load_tuple3', 'TUPLE3', 'load_empty_list', 'EMPTY_LIST', 'load_empty_dictionary', 'EMPTY_DICT', 'load_empty_set', 'EMPTY_SET', 'load_frozenset', 'FROZENSET', 'load_list', 'LIST', 'load_dict', 'DICT', '_instantiate', 'load_inst', 'INST', 'load_obj', 'OBJ', 'load_newobj', 'NEWOBJ', 'load_newobj_ex', 'NEWOBJ_EX', 'load_global', 'GLOBAL', 'load_stack_global', 'STACK_GLOBAL', 'load_ext1', 'EXT1', 'load_ext2', 'EXT2', 'load_ext4', 'EXT4', 'get_extension', 'find_class', 'load_reduce', 'REDUCE', 'load_pop', 'POP', 'load_pop_mark', 'POP_MARK', 'load_dup', 'DUP', 'load_get', 'GET', 'load_binget', 'BINGET', 'load_long_binget', 'LONG_BINGET', 'load_put', 'PUT', 'load_binput', 'BINPUT', 'load_long_binput', 'LONG_BINPUT', 'load_memoize', 'MEMOIZE', 'load_append', 'APPEND', 'load_appends', 'APPENDS', 'load_setitem', 'SETITEM', 'load_setitems', 'SETITEMS', 'load_additems', 'ADDITEMS', 'load_build', 'BUILD', 'load_mark', 'MARK', 'load_stop', 'STOP')

## bytecode:

   0: RESUME               
   2: LOAD_NAME            __name__
   4: STORE_NAME           __module__
   6: LOAD_CONST           '_Unpickler'
   8: STORE_NAME           __qualname__
  10: LOAD_CONST           True
  12: LOAD_CONST           'ASCII'
  14: LOAD_CONST           'strict'
  16: LOAD_CONST           None
  18: LOAD_CONST           ('fix_imports', 'encoding', 'errors', 'buffers')
  20: BUILD_CONST_KEY_MAP  
  22: LOAD_CONST           <code object __init__ at 0x000002406921FE00, file "pickle.py", line 1139>
  24: MAKE_FUNCTION        kwdefaults
  26: STORE_NAME           __init__
  28: LOAD_CONST           <code object load at 0x0000024068DC0380, file "pickle.py", line 1187>
  30: MAKE_FUNCTION        
  32: STORE_NAME           load
  34: LOAD_CONST           <code object pop_mark at 0x00000240693D2760, file "pickle.py", line 1218>
  36: MAKE_FUNCTION        
  38: STORE_NAME           pop_mark
  40: LOAD_CONST           <code object persistent_load at 0x0000024069465990, file "pickle.py", line 1224>
  42: MAKE_FUNCTION        
  44: STORE_NAME           persistent_load
  46: BUILD_MAP            
  48: STORE_NAME           dispatch
  50: LOAD_CONST           <code object load_proto at 0x000002406922D920, file "pickle.py", line 1229>
  52: MAKE_FUNCTION        
  54: STORE_NAME           load_proto
  56: LOAD_NAME            load_proto
  58: LOAD_NAME            dispatch
  60: LOAD_NAME            PROTO
  62: LOAD_CONST           0
  64: BINARY_SUBSCR        
  74: STORE_SUBSCR         
  78: LOAD_CONST           <code object load_frame at 0x00000240691EA730, file "pickle.py", line 1236>
  80: MAKE_FUNCTION        
  82: STORE_NAME           load_frame
  84: LOAD_NAME            load_frame
  86: LOAD_NAME            dispatch
  88: LOAD_NAME            FRAME
  90: LOAD_CONST           0
  92: BINARY_SUBSCR        
 102: STORE_SUBSCR         
 106: LOAD_CONST           <code object load_persid at 0x000002406934F7E0, file "pickle.py", line 1243>
 108: MAKE_FUNCTION        
 110: STORE_NAME           load_persid
 112: LOAD_NAME            load_persid
 114: LOAD_NAME            dispatch
 116: LOAD_NAME            PERSID
 118: LOAD_CONST           0
 120: BINARY_SUBSCR        
 130: STORE_SUBSCR         
 134: LOAD_CONST           <code object load_binpersid at 0x00000240693AB230, file "pickle.py", line 1252>
 136: MAKE_FUNCTION        
 138: STORE_NAME           load_binpersid
 140: LOAD_NAME            load_binpersid
 142: LOAD_NAME            dispatch
 144: LOAD_NAME            BINPERSID
 146: LOAD_CONST           0
 148: BINARY_SUBSCR        
 158: STORE_SUBSCR         
 162: LOAD_CONST           <code object load_none at 0x000002406945EA60, file "pickle.py", line 1257>
 164: MAKE_FUNCTION        
 166: STORE_NAME           load_none
 168: LOAD_NAME            load_none
 170: LOAD_NAME            dispatch
 172: LOAD_NAME            NONE
 174: LOAD_CONST           0
 176: BINARY_SUBSCR        
 186: STORE_SUBSCR         
 190: LOAD_CONST           <code object load_false at 0x000002406945F000, file "pickle.py", line 1261>
 192: MAKE_FUNCTION        
 194: STORE_NAME           load_false
 196: LOAD_NAME            load_false
 198: LOAD_NAME            dispatch
 200: LOAD_NAME            NEWFALSE
 202: LOAD_CONST           0
 204: BINARY_SUBSCR        
 214: STORE_SUBSCR         
 218: LOAD_CONST           <code object load_true at 0x000002406945E100, file "pickle.py", line 1265>
 220: MAKE_FUNCTION        
 222: STORE_NAME           load_true
 224: LOAD_NAME            load_true
 226: LOAD_NAME            dispatch
 228: LOAD_NAME            NEWTRUE
 230: LOAD_CONST           0
 232: BINARY_SUBSCR        
 242: STORE_SUBSCR         
 246: LOAD_CONST           <code object load_int at 0x000002406942D160, file "pickle.py", line 1269>
 248: MAKE_FUNCTION        
 250: STORE_NAME           load_int
 252: LOAD_NAME            load_int
 254: LOAD_NAME            dispatch
 256: LOAD_NAME            INT
 258: LOAD_CONST           0
 260: BINARY_SUBSCR        
 270: STORE_SUBSCR         
 274: LOAD_CONST           <code object load_binint at 0x00000240693AA0B0, file "pickle.py", line 1280>
 276: MAKE_FUNCTION        
 278: STORE_NAME           load_binint
 280: LOAD_NAME            load_binint
 282: LOAD_NAME            dispatch
 284: LOAD_NAME            BININT
 286: LOAD_CONST           0
 288: BINARY_SUBSCR        
 298: STORE_SUBSCR         
 302: LOAD_CONST           <code object load_binint1 at 0x000002406941AAF0, file "pickle.py", line 1284>
 304: MAKE_FUNCTION        
 306: STORE_NAME           load_binint1
 308: LOAD_NAME            load_binint1
 310: LOAD_NAME            dispatch
 312: LOAD_NAME            BININT1
 314: LOAD_CONST           0
 316: BINARY_SUBSCR        
 326: STORE_SUBSCR         
 330: LOAD_CONST           <code object load_binint2 at 0x00000240693ABAF0, file "pickle.py", line 1288>
 332: MAKE_FUNCTION        
 334: STORE_NAME           load_binint2
 336: LOAD_NAME            load_binint2
 338: LOAD_NAME            dispatch
 340: LOAD_NAME            BININT2
 342: LOAD_CONST           0
 344: BINARY_SUBSCR        
 354: STORE_SUBSCR         
 358: LOAD_CONST           <code object load_long at 0x000002406921FC90, file "pickle.py", line 1292>
 360: MAKE_FUNCTION        
 362: STORE_NAME           load_long
 364: LOAD_NAME            load_long
 366: LOAD_NAME            dispatch
 368: LOAD_NAME            LONG
 370: LOAD_CONST           0
 372: BINARY_SUBSCR        
 382: STORE_SUBSCR         
 386: LOAD_CONST           <code object load_long1 at 0x000002406921FB20, file "pickle.py", line 1299>
 388: MAKE_FUNCTION        
 390: STORE_NAME           load_long1
 392: LOAD_NAME            load_long1
 394: LOAD_NAME            dispatch
 396: LOAD_NAME            LONG1
 398: LOAD_CONST           0
 400: BINARY_SUBSCR        
 410: STORE_SUBSCR         
 414: LOAD_CONST           <code object load_long4 at 0x00000240691F6250, file "pickle.py", line 1305>
 416: MAKE_FUNCTION        
 418: STORE_NAME           load_long4
 420: LOAD_NAME            load_long4
 422: LOAD_NAME            dispatch
 424: LOAD_NAME            LONG4
 426: LOAD_CONST           0
 428: BINARY_SUBSCR        
 438: STORE_SUBSCR         
 442: LOAD_CONST           <code object load_float at 0x00000240693AB5F0, file "pickle.py", line 1314>
 444: MAKE_FUNCTION        
 446: STORE_NAME           load_float
 448: LOAD_NAME            load_float
 450: LOAD_NAME            dispatch
 452: LOAD_NAME            FLOAT
 454: LOAD_CONST           0
 456: BINARY_SUBSCR        
 466: STORE_SUBSCR         
 470: LOAD_CONST           <code object load_binfloat at 0x00000240693AAAB0, file "pickle.py", line 1318>
 472: MAKE_FUNCTION        
 474: STORE_NAME           load_binfloat
 476: LOAD_NAME            load_binfloat
 478: LOAD_NAME            dispatch
 480: LOAD_NAME            BINFLOAT
 482: LOAD_CONST           0
 484: BINARY_SUBSCR        
 494: STORE_SUBSCR         
 498: LOAD_CONST           <code object _decode_string at 0x000002406941B090, file "pickle.py", line 1322>
 500: MAKE_FUNCTION        
 502: STORE_NAME           _decode_string
 504: LOAD_CONST           <code object load_string at 0x00000240695EED60, file "pickle.py", line 1331>
 506: MAKE_FUNCTION        
 508: STORE_NAME           load_string
 510: LOAD_NAME            load_string
 512: LOAD_NAME            dispatch
 514: LOAD_NAME            STRING
 516: LOAD_CONST           0
 518: BINARY_SUBSCR        
 528: STORE_SUBSCR         
 532: LOAD_CONST           <code object load_binstring at 0x000002406934FB40, file "pickle.py", line 1341>
 534: MAKE_FUNCTION        
 536: STORE_NAME           load_binstring
 538: LOAD_NAME            load_binstring
 540: LOAD_NAME            dispatch
 542: LOAD_NAME            BINSTRING
 544: LOAD_CONST           0
 546: BINARY_SUBSCR        
 556: STORE_SUBSCR         
 560: LOAD_CONST           <code object load_binbytes at 0x00000240691F5A30, file "pickle.py", line 1350>
 562: MAKE_FUNCTION        
 564: STORE_NAME           load_binbytes
 566: LOAD_NAME            load_binbytes
 568: LOAD_NAME            dispatch
 570: LOAD_NAME            BINBYTES
 572: LOAD_CONST           0
 574: BINARY_SUBSCR        
 584: STORE_SUBSCR         
 588: LOAD_CONST           <code object load_unicode at 0x00000240693A9570, file "pickle.py", line 1358>
 590: MAKE_FUNCTION        
 592: STORE_NAME           load_unicode
 594: LOAD_NAME            load_unicode
 596: LOAD_NAME            dispatch
 598: LOAD_NAME            UNICODE
 600: LOAD_CONST           0
 602: BINARY_SUBSCR        
 612: STORE_SUBSCR         
 616: LOAD_CONST           <code object load_binunicode at 0x00000240694981F0, file "pickle.py", line 1362>
 618: MAKE_FUNCTION        
 620: STORE_NAME           load_binunicode
 622: LOAD_NAME            load_binunicode
 624: LOAD_NAME            dispatch
 626: LOAD_NAME            BINUNICODE
 628: LOAD_CONST           0
 630: BINARY_SUBSCR        
 640: STORE_SUBSCR         
 644: LOAD_CONST           <code object load_binunicode8 at 0x00000240694983B0, file "pickle.py", line 1370>
 646: MAKE_FUNCTION        
 648: STORE_NAME           load_binunicode8
 650: LOAD_NAME            load_binunicode8
 652: LOAD_NAME            dispatch
 654: LOAD_NAME            BINUNICODE8
 656: LOAD_CONST           0
 658: BINARY_SUBSCR        
 668: STORE_SUBSCR         
 672: LOAD_CONST           <code object load_binbytes8 at 0x00000240691F5F10, file "pickle.py", line 1378>
 674: MAKE_FUNCTION        
 676: STORE_NAME           load_binbytes8
 678: LOAD_NAME            load_binbytes8
 680: LOAD_NAME            dispatch
 682: LOAD_NAME            BINBYTES8
 684: LOAD_CONST           0
 686: BINARY_SUBSCR        
 696: STORE_SUBSCR         
 700: LOAD_CONST           <code object load_bytearray8 at 0x0000024069498570, file "pickle.py", line 1386>
 702: MAKE_FUNCTION        
 704: STORE_NAME           load_bytearray8
 706: LOAD_NAME            load_bytearray8
 708: LOAD_NAME            dispatch
 710: LOAD_NAME            BYTEARRAY8
 712: LOAD_CONST           0
 714: BINARY_SUBSCR        
 724: STORE_SUBSCR         
 728: LOAD_CONST           <code object load_next_buffer at 0x00000240691E9E30, file "pickle.py", line 1396>
 730: MAKE_FUNCTION        
 732: STORE_NAME           load_next_buffer
 734: LOAD_NAME            load_next_buffer
 736: LOAD_NAME            dispatch
 738: LOAD_NAME            NEXT_BUFFER
 740: LOAD_CONST           0
 742: BINARY_SUBSCR        
 752: STORE_SUBSCR         
 756: LOAD_CONST           <code object load_readonly_buffer at 0x000002406921F9B0, file "pickle.py", line 1407>
 758: MAKE_FUNCTION        
 760: STORE_NAME           load_readonly_buffer
 762: LOAD_NAME            load_readonly_buffer
 764: LOAD_NAME            dispatch
 766: LOAD_NAME            READONLY_BUFFER
 768: LOAD_CONST           0
 770: BINARY_SUBSCR        
 780: STORE_SUBSCR         
 784: LOAD_CONST           <code object load_short_binstring at 0x000002406949CD20, file "pickle.py", line 1414>
 786: MAKE_FUNCTION        
 788: STORE_NAME           load_short_binstring
 790: LOAD_NAME            load_short_binstring
 792: LOAD_NAME            dispatch
 794: LOAD_NAME            SHORT_BINSTRING
 796: LOAD_CONST           0
 798: BINARY_SUBSCR        
 808: STORE_SUBSCR         
 812: LOAD_CONST           <code object load_short_binbytes at 0x000002406922C570, file "pickle.py", line 1420>
 814: MAKE_FUNCTION        
 816: STORE_NAME           load_short_binbytes
 818: LOAD_NAME            load_short_binbytes
 820: LOAD_NAME            dispatch
 822: LOAD_NAME            SHORT_BINBYTES
 824: LOAD_CONST           0
 826: BINARY_SUBSCR        
 836: STORE_SUBSCR         
 840: LOAD_CONST           <code object load_short_binunicode at 0x000002406949C8D0, file "pickle.py", line 1425>
 842: MAKE_FUNCTION        
 844: STORE_NAME           load_short_binunicode
 846: LOAD_NAME            load_short_binunicode
 848: LOAD_NAME            dispatch
 850: LOAD_NAME            SHORT_BINUNICODE
 852: LOAD_CONST           0
 854: BINARY_SUBSCR        
 864: STORE_SUBSCR         
 868: LOAD_CONST           <code object load_tuple at 0x00000240693D2E80, file "pickle.py", line 1430>
 870: MAKE_FUNCTION        
 872: STORE_NAME           load_tuple
 874: LOAD_NAME            load_tuple
 876: LOAD_NAME            dispatch
 878: LOAD_NAME            TUPLE
 880: LOAD_CONST           0
 882: BINARY_SUBSCR        
 892: STORE_SUBSCR         
 896: LOAD_CONST           <code object load_empty_tuple at 0x000002406945DF20, file "pickle.py", line 1435>
 898: MAKE_FUNCTION        
 900: STORE_NAME           load_empty_tuple
 902: LOAD_NAME            load_empty_tuple
 904: LOAD_NAME            dispatch
 906: LOAD_NAME            EMPTY_TUPLE
 908: LOAD_CONST           0
 910: BINARY_SUBSCR        
 920: STORE_SUBSCR         
 924: LOAD_CONST           <code object load_tuple1 at 0x000002406945F780, file "pickle.py", line 1439>
 926: MAKE_FUNCTION        
 928: STORE_NAME           load_tuple1
 930: LOAD_NAME            load_tuple1
 932: LOAD_NAME            dispatch
 934: LOAD_NAME            TUPLE1
 936: LOAD_CONST           0
 938: BINARY_SUBSCR        
 948: STORE_SUBSCR         
 952: LOAD_CONST           <code object load_tuple2 at 0x000002406944A010, file "pickle.py", line 1443>
 954: MAKE_FUNCTION        
 956: STORE_NAME           load_tuple2
 958: LOAD_NAME            load_tuple2
 960: LOAD_NAME            dispatch
 962: LOAD_NAME            TUPLE2
 964: LOAD_CONST           0
 966: BINARY_SUBSCR        
 976: STORE_SUBSCR         
 980: LOAD_CONST           <code object load_tuple3 at 0x000002406941B510, file "pickle.py", line 1447>
 982: MAKE_FUNCTION        
 984: STORE_NAME           load_tuple3
 986: LOAD_NAME            load_tuple3
 988: LOAD_NAME            dispatch
 990: LOAD_NAME            TUPLE3
 992: LOAD_CONST           0
 994: BINARY_SUBSCR        
1004: STORE_SUBSCR         
1008: LOAD_CONST           <code object load_empty_list at 0x000002406945D2F0, file "pickle.py", line 1451>
1010: MAKE_FUNCTION        
1012: STORE_NAME           load_empty_list
1014: LOAD_NAME            load_empty_list
1016: LOAD_NAME            dispatch
1018: LOAD_NAME            EMPTY_LIST
1020: LOAD_CONST           0
1022: BINARY_SUBSCR        
1032: STORE_SUBSCR         
1036: LOAD_CONST           <code object load_empty_dictionary at 0x000002406945F1E0, file "pickle.py", line 1455>
1038: MAKE_FUNCTION        
1040: STORE_NAME           load_empty_dictionary
1042: LOAD_NAME            load_empty_dictionary
1044: LOAD_NAME            dispatch
1046: LOAD_NAME            EMPTY_DICT
1048: LOAD_CONST           0
1050: BINARY_SUBSCR        
1060: STORE_SUBSCR         
1064: LOAD_CONST           <code object load_empty_set at 0x00000240693EB430, file "pickle.py", line 1459>
1066: MAKE_FUNCTION        
1068: STORE_NAME           load_empty_set
1070: LOAD_NAME            load_empty_set
1072: LOAD_NAME            dispatch
1074: LOAD_NAME            EMPTY_SET
1076: LOAD_CONST           0
1078: BINARY_SUBSCR        
1088: STORE_SUBSCR         
1092: LOAD_CONST           <code object load_frozenset at 0x00000240693D3210, file "pickle.py", line 1463>
1094: MAKE_FUNCTION        
1096: STORE_NAME           load_frozenset
1098: LOAD_NAME            load_frozenset
1100: LOAD_NAME            dispatch
1102: LOAD_NAME            FROZENSET
1104: LOAD_CONST           0
1106: BINARY_SUBSCR        
1116: STORE_SUBSCR         
1120: LOAD_CONST           <code object load_list at 0x000002406944B550, file "pickle.py", line 1468>
1122: MAKE_FUNCTION        
1124: STORE_NAME           load_list
1126: LOAD_NAME            load_list
1128: LOAD_NAME            dispatch
1130: LOAD_NAME            LIST
1132: LOAD_CONST           0
1134: BINARY_SUBSCR        
1144: STORE_SUBSCR         
1148: LOAD_CONST           <code object load_dict at 0x000002406949CBB0, file "pickle.py", line 1473>
1150: MAKE_FUNCTION        
1152: STORE_NAME           load_dict
1154: LOAD_NAME            load_dict
1156: LOAD_NAME            dispatch
1158: LOAD_NAME            DICT
1160: LOAD_CONST           0
1162: BINARY_SUBSCR        
1172: STORE_SUBSCR         
1176: LOAD_CONST           <code object _instantiate at 0x0000024068E24A20, file "pickle.py", line 1485>
1178: MAKE_FUNCTION        
1180: STORE_NAME           _instantiate
1182: LOAD_CONST           <code object load_inst at 0x0000024069CDC030, file "pickle.py", line 1497>
1184: MAKE_FUNCTION        
1186: STORE_NAME           load_inst
1188: LOAD_NAME            load_inst
1190: LOAD_NAME            dispatch
1192: LOAD_NAME            INST
1194: LOAD_CONST           0
1196: BINARY_SUBSCR        
1206: STORE_SUBSCR         
1210: LOAD_CONST           <code object load_obj at 0x00000240693AB730, file "pickle.py", line 1504>
1212: MAKE_FUNCTION        
1214: STORE_NAME           load_obj
1216: LOAD_NAME            load_obj
1218: LOAD_NAME            dispatch
1220: LOAD_NAME            OBJ
1222: LOAD_CONST           0
1224: BINARY_SUBSCR        
1234: STORE_SUBSCR         
1238: LOAD_CONST           <code object load_newobj at 0x000002406949D2E0, file "pickle.py", line 1511>
1240: MAKE_FUNCTION        
1242: STORE_NAME           load_newobj
1244: LOAD_NAME            load_newobj
1246: LOAD_NAME            dispatch
1248: LOAD_NAME            NEWOBJ
1250: LOAD_CONST           0
1252: BINARY_SUBSCR        
1262: STORE_SUBSCR         
1266: LOAD_CONST           <code object load_newobj_ex at 0x00000240691F5550, file "pickle.py", line 1518>
1268: MAKE_FUNCTION        
1270: STORE_NAME           load_newobj_ex
1272: LOAD_NAME            load_newobj_ex
1274: LOAD_NAME            dispatch
1276: LOAD_NAME            NEWOBJ_EX
1278: LOAD_CONST           0
1280: BINARY_SUBSCR        
1290: STORE_SUBSCR         
1294: LOAD_CONST           <code object load_global at 0x00000240691DAD80, file "pickle.py", line 1526>
1296: MAKE_FUNCTION        
1298: STORE_NAME           load_global
1300: LOAD_NAME            load_global
1302: LOAD_NAME            dispatch
1304: LOAD_NAME            GLOBAL
1306: LOAD_CONST           0
1308: BINARY_SUBSCR        
1318: STORE_SUBSCR         
1322: LOAD_CONST           <code object load_stack_global at 0x0000024069365F30, file "pickle.py", line 1533>
1324: MAKE_FUNCTION        
1326: STORE_NAME           load_stack_global
1328: LOAD_NAME            load_stack_global
1330: LOAD_NAME            dispatch
1332: LOAD_NAME            STACK_GLOBAL
1334: LOAD_CONST           0
1336: BINARY_SUBSCR        
1346: STORE_SUBSCR         
1350: LOAD_CONST           <code object load_ext1 at 0x000002406941B630, file "pickle.py", line 1541>
1352: MAKE_FUNCTION        
1354: STORE_NAME           load_ext1
1356: LOAD_NAME            load_ext1
1358: LOAD_NAME            dispatch
1360: LOAD_NAME            EXT1
1362: LOAD_CONST           0
1364: BINARY_SUBSCR        
1374: STORE_SUBSCR         
1378: LOAD_CONST           <code object load_ext2 at 0x00000240693AA830, file "pickle.py", line 1546>
1380: MAKE_FUNCTION        
1382: STORE_NAME           load_ext2
1384: LOAD_NAME            load_ext2
1386: LOAD_NAME            dispatch
1388: LOAD_NAME            EXT2
1390: LOAD_CONST           0
1392: BINARY_SUBSCR        
1402: STORE_SUBSCR         
1406: LOAD_CONST           <code object load_ext4 at 0x00000240693AA330, file "pickle.py", line 1551>
1408: MAKE_FUNCTION        
1410: STORE_NAME           load_ext4
1412: LOAD_NAME            load_ext4
1414: LOAD_NAME            dispatch
1416: LOAD_NAME            EXT4
1418: LOAD_CONST           0
1420: BINARY_SUBSCR        
1430: STORE_SUBSCR         
1434: LOAD_CONST           <code object get_extension at 0x0000024069365B50, file "pickle.py", line 1556>
1436: MAKE_FUNCTION        
1438: STORE_NAME           get_extension
1440: LOAD_CONST           <code object find_class at 0x0000024068E1C0F0, file "pickle.py", line 1572>
1442: MAKE_FUNCTION        
1444: STORE_NAME           find_class
1446: LOAD_CONST           <code object load_reduce at 0x000002406941B750, file "pickle.py", line 1586>
1448: MAKE_FUNCTION        
1450: STORE_NAME           load_reduce
1452: LOAD_NAME            load_reduce
1454: LOAD_NAME            dispatch
1456: LOAD_NAME            REDUCE
1458: LOAD_CONST           0
1460: BINARY_SUBSCR        
1470: STORE_SUBSCR         
1474: LOAD_CONST           <code object load_pop at 0x000002406944B330, file "pickle.py", line 1593>
1476: MAKE_FUNCTION        
1478: STORE_NAME           load_pop
1480: LOAD_NAME            load_pop
1482: LOAD_NAME            dispatch
1484: LOAD_NAME            POP
1486: LOAD_CONST           0
1488: BINARY_SUBSCR        
1498: STORE_SUBSCR         
1502: LOAD_CONST           <code object load_pop_mark at 0x000002406945FE10, file "pickle.py", line 1600>
1504: MAKE_FUNCTION        
1506: STORE_NAME           load_pop_mark
1508: LOAD_NAME            load_pop_mark
1510: LOAD_NAME            dispatch
1512: LOAD_NAME            POP_MARK
1514: LOAD_CONST           0
1516: BINARY_SUBSCR        
1526: STORE_SUBSCR         
1530: LOAD_CONST           <code object load_dup at 0x00000240693EB230, file "pickle.py", line 1604>
1532: MAKE_FUNCTION        
1534: STORE_NAME           load_dup
1536: LOAD_NAME            load_dup
1538: LOAD_NAME            dispatch
1540: LOAD_NAME            DUP
1542: LOAD_CONST           0
1544: BINARY_SUBSCR        
1554: STORE_SUBSCR         
1558: LOAD_CONST           <code object load_get at 0x00000240691F63F0, file "pickle.py", line 1608>
1560: MAKE_FUNCTION        
1562: STORE_NAME           load_get
1564: LOAD_NAME            load_get
1566: LOAD_NAME            dispatch
1568: LOAD_NAME            GET
1570: LOAD_CONST           0
1572: BINARY_SUBSCR        
1582: STORE_SUBSCR         
1586: LOAD_CONST           <code object load_binget at 0x000002406942CB20, file "pickle.py", line 1617>
1588: MAKE_FUNCTION        
1590: STORE_NAME           load_binget
1592: LOAD_NAME            load_binget
1594: LOAD_NAME            dispatch
1596: LOAD_NAME            BINGET
1598: LOAD_CONST           0
1600: BINARY_SUBSCR        
1610: STORE_SUBSCR         
1614: LOAD_CONST           <code object load_long_binget at 0x00000240691F6590, file "pickle.py", line 1626>
1616: MAKE_FUNCTION        
1618: STORE_NAME           load_long_binget
1620: LOAD_NAME            load_long_binget
1622: LOAD_NAME            dispatch
1624: LOAD_NAME            LONG_BINGET
1626: LOAD_CONST           0
1628: BINARY_SUBSCR        
1638: STORE_SUBSCR         
1642: LOAD_CONST           <code object load_put at 0x000002406949D730, file "pickle.py", line 1635>
1644: MAKE_FUNCTION        
1646: STORE_NAME           load_put
1648: LOAD_NAME            load_put
1650: LOAD_NAME            dispatch
1652: LOAD_NAME            PUT
1654: LOAD_CONST           0
1656: BINARY_SUBSCR        
1666: STORE_SUBSCR         
1670: LOAD_CONST           <code object load_binput at 0x000002406922D530, file "pickle.py", line 1642>
1672: MAKE_FUNCTION        
1674: STORE_NAME           load_binput
1676: LOAD_NAME            load_binput
1678: LOAD_NAME            dispatch
1680: LOAD_NAME            BINPUT
1682: LOAD_CONST           0
1684: BINARY_SUBSCR        
1694: STORE_SUBSCR         
1698: LOAD_CONST           <code object load_long_binput at 0x000002406949D8A0, file "pickle.py", line 1649>
1700: MAKE_FUNCTION        
1702: STORE_NAME           load_long_binput
1704: LOAD_NAME            load_long_binput
1706: LOAD_NAME            dispatch
1708: LOAD_NAME            LONG_BINPUT
1710: LOAD_CONST           0
1712: BINARY_SUBSCR        
1722: STORE_SUBSCR         
1726: LOAD_CONST           <code object load_memoize at 0x000002406944B770, file "pickle.py", line 1656>
1728: MAKE_FUNCTION        
1730: STORE_NAME           load_memoize
1732: LOAD_NAME            load_memoize
1734: LOAD_NAME            dispatch
1736: LOAD_NAME            MEMOIZE
1738: LOAD_CONST           0
1740: BINARY_SUBSCR        
1750: STORE_SUBSCR         
1754: LOAD_CONST           <code object load_append at 0x00000240693D30E0, file "pickle.py", line 1661>
1756: MAKE_FUNCTION        
1758: STORE_NAME           load_append
1760: LOAD_NAME            load_append
1762: LOAD_NAME            dispatch
1764: LOAD_NAME            APPEND
1766: LOAD_CONST           0
1768: BINARY_SUBSCR        
1778: STORE_SUBSCR         
1782: LOAD_CONST           <code object load_appends at 0x00000240691E9530, file "pickle.py", line 1668>
1784: MAKE_FUNCTION        
1786: STORE_NAME           load_appends
1788: LOAD_NAME            load_appends
1790: LOAD_NAME            dispatch
1792: LOAD_NAME            APPENDS
1794: LOAD_CONST           0
1796: BINARY_SUBSCR        
1806: STORE_SUBSCR         
1810: LOAD_CONST           <code object load_setitem at 0x00000240693AA970, file "pickle.py", line 1686>
1812: MAKE_FUNCTION        
1814: STORE_NAME           load_setitem
1816: LOAD_NAME            load_setitem
1818: LOAD_NAME            dispatch
1820: LOAD_NAME            SETITEM
1822: LOAD_CONST           0
1824: BINARY_SUBSCR        
1834: STORE_SUBSCR         
1838: LOAD_CONST           <code object load_setitems at 0x000002406949CE90, file "pickle.py", line 1694>
1840: MAKE_FUNCTION        
1842: STORE_NAME           load_setitems
1844: LOAD_NAME            load_setitems
1846: LOAD_NAME            dispatch
1848: LOAD_NAME            SETITEMS
1850: LOAD_CONST           0
1852: BINARY_SUBSCR        
1862: STORE_SUBSCR         
1866: LOAD_CONST           <code object load_additems at 0x000002406942E290, file "pickle.py", line 1701>
1868: MAKE_FUNCTION        
1870: STORE_NAME           load_additems
1872: LOAD_NAME            load_additems
1874: LOAD_NAME            dispatch
1876: LOAD_NAME            ADDITEMS
1878: LOAD_CONST           0
1880: BINARY_SUBSCR        
1890: STORE_SUBSCR         
1894: LOAD_CONST           <code object load_build at 0x0000024068C05730, file "pickle.py", line 1712>
1896: MAKE_FUNCTION        
1898: STORE_NAME           load_build
1900: LOAD_NAME            load_build
1902: LOAD_NAME            dispatch
1904: LOAD_NAME            BUILD
1906: LOAD_CONST           0
1908: BINARY_SUBSCR        
1918: STORE_SUBSCR         
1922: LOAD_CONST           <code object load_mark at 0x00000240693D3CC0, file "pickle.py", line 1736>
1924: MAKE_FUNCTION        
1926: STORE_NAME           load_mark
1928: LOAD_NAME            load_mark
1930: LOAD_NAME            dispatch
1932: LOAD_NAME            MARK
1934: LOAD_CONST           0
1936: BINARY_SUBSCR        
1946: STORE_SUBSCR         
1950: LOAD_CONST           <code object load_stop at 0x000002406944A450, file "pickle.py", line 1742>
1952: MAKE_FUNCTION        
1954: STORE_NAME           load_stop
1956: LOAD_NAME            load_stop
1958: LOAD_NAME            dispatch
1960: LOAD_NAME            STOP
1962: LOAD_CONST           0
1964: BINARY_SUBSCR        
1974: STORE_SUBSCR         
1978: LOAD_CONST           None
1980: RETURN_VALUE         
