# Disassembly for pickle._Unpickler.load_obj
# From module file: pickle

## co_consts:
(None, 0)

## co_names:
('pop_mark', 'pop', '_instantiate')

## bytecode:

   0: RESUME               
   2: LOAD_FAST            self
   4: LOAD_METHOD          pop_mark
  26: PRECALL              
  30: CALL                 
  40: STORE_FAST           args
  42: LOAD_FAST            args
  44: LOAD_METHOD          pop
  66: LOAD_CONST           0
  68: PRECALL              
  72: CALL                 
  82: STORE_FAST           cls
  84: LOAD_FAST            self
  86: LOAD_METHOD          _instantiate
 108: LOAD_FAST            cls
 110: LOAD_FAST            args
 112: PRECALL              
 116: CALL                 
 126: POP_TOP              
 128: LOAD_CONST           None
 130: RETURN_VALUE         
