# Disassembly for pickle._Unpickler.load_long_binput
# From module file: pickle

## co_consts:
(None, '<I', 4, 'negative LONG_BINPUT argument', -1)

## co_names:
('unpack', 'read', 'maxsize', 'ValueError', 'stack', 'memo')

## bytecode:

   0: RESUME               
   2: LOAD_GLOBAL          NULL + unpack
  14: LOAD_CONST           '<I'
  16: LOAD_FAST            self
  18: LOAD_METHOD          read
  40: LOAD_CONST           4
  42: PRECALL              
  46: CALL                 
  56: PRECALL              
  60: CALL                 
  70: UNPACK_SEQUENCE      
  74: STORE_FAST           i
  76: LOAD_FAST            i
  78: LOAD_GLOBAL          maxsize
  90: COMPARE_OP           >
  96: POP_JUMP_FORWARD_IF_FALSE to 128
  98: LOAD_GLOBAL          NULL + ValueError
 110: LOAD_CONST           'negative LONG_BINPUT argument'
 112: PRECALL              
 116: CALL                 
 126: RAISE_VARARGS        
 128: LOAD_FAST            self
 130: LOAD_ATTR            stack
 140: LOAD_CONST           -1
 142: BINARY_SUBSCR        
 152: LOAD_FAST            self
 154: LOAD_ATTR            memo
 164: LOAD_FAST            i
 166: STORE_SUBSCR         
 170: LOAD_CONST           None
 172: RETURN_VALUE         
