# Disassembly for pickle._Unframer.readinto
# From module file: pickle

## co_consts:
(None, 0, 'pickle exhausted before end of frame')

## co_names:
('current_frame', 'readinto', 'len', 'file_read', 'UnpicklingError')

## bytecode:

   0: RESUME               
   2: LOAD_FAST            self
   4: LOAD_ATTR            current_frame
  14: POP_JUMP_FORWARD_IF_FALSE to 290
  16: LOAD_FAST            self
  18: LOAD_ATTR            current_frame
  28: LOAD_METHOD          readinto
  50: LOAD_FAST            buf
  52: PRECALL              
  56: CALL                 
  66: STORE_FAST           n
  68: LOAD_FAST            n
  70: LOAD_CONST           0
  72: COMPARE_OP           ==
  78: POP_JUMP_FORWARD_IF_FALSE to 218
  80: LOAD_GLOBAL          NULL + len
  92: LOAD_FAST            buf
  94: PRECALL              
  98: CALL                 
 108: LOAD_CONST           0
 110: COMPARE_OP           !=
 116: POP_JUMP_FORWARD_IF_FALSE to 218
 118: LOAD_CONST           None
 120: LOAD_FAST            self
 122: STORE_ATTR           current_frame
 132: LOAD_GLOBAL          NULL + len
 144: LOAD_FAST            buf
 146: PRECALL              
 150: CALL                 
 160: STORE_FAST           n
 162: LOAD_FAST            self
 164: LOAD_METHOD          file_read
 186: LOAD_FAST            n
 188: PRECALL              
 192: CALL                 
 202: LOAD_FAST            buf
 204: LOAD_CONST           None
 206: LOAD_CONST           None
 208: BUILD_SLICE          
 210: STORE_SUBSCR         
 214: LOAD_FAST            n
 216: RETURN_VALUE         
 218: LOAD_FAST            n
 220: LOAD_GLOBAL          NULL + len
 232: LOAD_FAST            buf
 234: PRECALL              
 238: CALL                 
 248: COMPARE_OP           <
 254: POP_JUMP_FORWARD_IF_FALSE to 286
 256: LOAD_GLOBAL          NULL + UnpicklingError
 268: LOAD_CONST           'pickle exhausted before end of frame'
 270: PRECALL              
 274: CALL                 
 284: RAISE_VARARGS        
 286: LOAD_FAST            n
 288: RETURN_VALUE         
 290: LOAD_GLOBAL          NULL + len
 302: LOAD_FAST            buf
 304: PRECALL              
 308: CALL                 
 318: STORE_FAST           n
 320: LOAD_FAST            self
 322: LOAD_METHOD          file_read
 344: LOAD_FAST            n
 346: PRECALL              
 350: CALL                 
 360: LOAD_FAST            buf
 362: LOAD_CONST           None
 364: LOAD_CONST           None
 366: BUILD_SLICE          
 368: STORE_SUBSCR         
 372: LOAD_FAST            n
 374: RETURN_VALUE         
