# Disassembly for pickle._Unpickler.pop_mark
# From module file: pickle

## co_consts:
(None,)

## co_names:
('stack', 'metastack', 'pop', 'append')

## bytecode:

   0: RESUME               
   2: LOAD_FAST            self
   4: LOAD_ATTR            stack
  14: STORE_FAST           items
  16: LOAD_FAST            self
  18: LOAD_ATTR            metastack
  28: LOAD_METHOD          pop
  50: PRECALL              
  54: CALL                 
  64: LOAD_FAST            self
  66: STORE_ATTR           stack
  76: LOAD_FAST            self
  78: LOAD_ATTR            stack
  88: LOAD_ATTR            append
  98: LOAD_FAST            self
 100: STORE_ATTR           append
 110: LOAD_FAST            items
 112: RETURN_VALUE         
