# Disassembly for pickle._Unpickler.load_bytearray8
# From module file: pickle

## co_consts:
(None, '<Q', 8, "BYTEARRAY8 exceeds system's maximum size of %d bytes")

## co_names:
('unpack', 'read', 'maxsize', 'UnpicklingError', 'bytearray', 'readinto', 'append')

## bytecode:

   0: RESUME               
   2: LOAD_GLOBAL          NULL + unpack
  14: LOAD_CONST           '<Q'
  16: LOAD_FAST            self
  18: LOAD_METHOD          read
  40: LOAD_CONST           8
  42: PRECALL              
  46: CALL                 
  56: PRECALL              
  60: CALL                 
  70: UNPACK_SEQUENCE      
  74: STORE_FAST           len
  76: LOAD_FAST            len
  78: LOAD_GLOBAL          maxsize
  90: COMPARE_OP           >
  96: POP_JUMP_FORWARD_IF_FALSE to 144
  98: LOAD_GLOBAL          NULL + UnpicklingError
 110: LOAD_CONST           "BYTEARRAY8 exceeds system's maximum size of %d bytes"
 112: LOAD_GLOBAL          maxsize
 124: BINARY_OP            %
 128: PRECALL              
 132: CALL                 
 142: RAISE_VARARGS        
 144: LOAD_GLOBAL          NULL + bytearray
 156: LOAD_FAST            len
 158: PRECALL              
 162: CALL                 
 172: STORE_FAST           b
 174: LOAD_FAST            self
 176: LOAD_METHOD          readinto
 198: LOAD_FAST            b
 200: PRECALL              
 204: CALL                 
 214: POP_TOP              
 216: LOAD_FAST            self
 218: LOAD_METHOD          append
 240: LOAD_FAST            b
 242: PRECALL              
 246: CALL                 
 256: POP_TOP              
 258: LOAD_CONST           None
 260: RETURN_VALUE         
