# Disassembly for pickle.PickleError
# From module file: pickle

## co_consts:
('PickleError', 'A common base class for the other pickling exceptions.', None)

## co_names:
('__name__', '__module__', '__qualname__', '__doc__')

## bytecode:

   0: RESUME               
   2: LOAD_NAME            __name__
   4: STORE_NAME           __module__
   6: LOAD_CONST           'PickleError'
   8: STORE_NAME           __qualname__
  10: LOAD_CONST           'A common base class for the other pickling exceptions.'
  12: STORE_NAME           __doc__
  14: LOAD_CONST           None
  16: RETURN_VALUE         
