# Disassembly for pickle._Unframer.read
# From module file: pickle

## co_consts:
(None, 0, 'pickle exhausted before end of frame')

## co_names:
('current_frame', 'read', 'file_read', 'len', 'UnpicklingError')

## bytecode:

   0: RESUME               
   2: LOAD_FAST            self
   4: LOAD_ATTR            current_frame
  14: POP_JUMP_FORWARD_IF_FALSE to 212
  16: LOAD_FAST            self
  18: LOAD_ATTR            current_frame
  28: LOAD_METHOD          read
  50: LOAD_FAST            n
  52: PRECALL              
  56: CALL                 
  66: STORE_FAST           data
  68: LOAD_FAST            data
  70: POP_JUMP_FORWARD_IF_TRUE to 140
  72: LOAD_FAST            n
  74: LOAD_CONST           0
  76: COMPARE_OP           !=
  82: POP_JUMP_FORWARD_IF_FALSE to 140
  84: LOAD_CONST           None
  86: LOAD_FAST            self
  88: STORE_ATTR           current_frame
  98: LOAD_FAST            self
 100: LOAD_METHOD          file_read
 122: LOAD_FAST            n
 124: PRECALL              
 128: CALL                 
 138: RETURN_VALUE         
 140: LOAD_GLOBAL          NULL + len
 152: LOAD_FAST            data
 154: PRECALL              
 158: CALL                 
 168: LOAD_FAST            n
 170: COMPARE_OP           <
 176: POP_JUMP_FORWARD_IF_FALSE to 208
 178: LOAD_GLOBAL          NULL + UnpicklingError
 190: LOAD_CONST           'pickle exhausted before end of frame'
 192: PRECALL              
 196: CALL                 
 206: RAISE_VARARGS        
 208: LOAD_FAST            data
 210: RETURN_VALUE         
 212: LOAD_FAST            self
 214: LOAD_METHOD          file_read
 236: LOAD_FAST            n
 238: PRECALL              
 242: CALL                 
 252: RETURN_VALUE         
