# Disassembly for pickle._load
# From module file: pickle

## co_consts:
(None, ('fix_imports', 'buffers', 'encoding', 'errors'))

## co_names:
('_Unpickler', 'load')

## bytecode:

   0: RESUME               
   2: LOAD_GLOBAL          NULL + _Unpickler
  14: LOAD_FAST            file
  16: LOAD_FAST            fix_imports
  18: LOAD_FAST            buffers
  20: LOAD_FAST            encoding
  22: LOAD_FAST            errors
  24: KW_NAMES             
  26: PRECALL              
  30: CALL                 
  40: LOAD_METHOD          load
  62: PRECALL              
  66: CALL                 
  76: RETURN_VALUE         
