# Disassembly for argparse._ActionsContainer._check_conflict
# From module file: argparse

## co_consts:
(None,)

## co_names:
('option_strings', '_option_string_actions', 'append', '_get_handler')

## bytecode:

   0: RESUME               
   2: BUILD_LIST           
   4: STORE_FAST           confl_optionals
   6: LOAD_FAST            action
   8: LOAD_ATTR            option_strings
  18: GET_ITER             
  20: FOR_ITER             to 116
  22: STORE_FAST           option_string
  24: LOAD_FAST            option_string
  26: LOAD_FAST            self
  28: LOAD_ATTR            _option_string_actions
  38: CONTAINS_OP          
  40: POP_JUMP_FORWARD_IF_FALSE to 114
  42: LOAD_FAST            self
  44: LOAD_ATTR            _option_string_actions
  54: LOAD_FAST            option_string
  56: BINARY_SUBSCR        
  66: STORE_FAST           confl_optional
  68: LOAD_FAST            confl_optionals
  70: LOAD_METHOD          append
  92: LOAD_FAST            option_string
  94: LOAD_FAST            confl_optional
  96: BUILD_TUPLE          
  98: PRECALL              
 102: CALL                 
 112: POP_TOP              
 114: JUMP_BACKWARD        to 20
 116: LOAD_FAST            confl_optionals
 118: POP_JUMP_FORWARD_IF_FALSE to 188
 120: LOAD_FAST            self
 122: LOAD_METHOD          _get_handler
 144: PRECALL              
 148: CALL                 
 158: STORE_FAST           conflict_handler
 160: PUSH_NULL            
 162: LOAD_FAST            conflict_handler
 164: LOAD_FAST            action
 166: LOAD_FAST            confl_optionals
 168: PRECALL              
 172: CALL                 
 182: POP_TOP              
 184: LOAD_CONST           None
 186: RETURN_VALUE         
 188: LOAD_CONST           None
 190: RETURN_VALUE         
