# Disassembly for argparse.BooleanOptionalAction.__init__
# From module file: argparse

## co_consts:
(None, '--', '--no-', 2, 0, ('option_strings', 'dest', 'nargs', 'default', 'type', 'choices', 'required', 'help', 'metavar'))

## co_names:
('append', 'startswith', 'super', '__init__')

## bytecode:

   0: COPY_FREE_VARS       
   2: RESUME               
   4: BUILD_LIST           
   6: STORE_FAST           _option_strings
   8: LOAD_FAST            option_strings
  10: GET_ITER             
  12: FOR_ITER             to 170
  14: STORE_FAST           option_string
  16: LOAD_FAST            _option_strings
  18: LOAD_METHOD          append
  40: LOAD_FAST            option_string
  42: PRECALL              
  46: CALL                 
  56: POP_TOP              
  58: LOAD_FAST            option_string
  60: LOAD_METHOD          startswith
  82: LOAD_CONST           '--'
  84: PRECALL              
  88: CALL                 
  98: POP_JUMP_FORWARD_IF_FALSE to 168
 100: LOAD_CONST           '--no-'
 102: LOAD_FAST            option_string
 104: LOAD_CONST           2
 106: LOAD_CONST           None
 108: BUILD_SLICE          
 110: BINARY_SUBSCR        
 120: BINARY_OP            +
 124: STORE_FAST           option_string
 126: LOAD_FAST            _option_strings
 128: LOAD_METHOD          append
 150: LOAD_FAST            option_string
 152: PRECALL              
 156: CALL                 
 166: POP_TOP              
 168: JUMP_BACKWARD        to 12
 170: LOAD_GLOBAL          NULL + super
 182: PRECALL              
 186: CALL                 
 196: LOAD_METHOD          __init__
 218: LOAD_FAST            _option_strings
 220: LOAD_FAST            dest
 222: LOAD_CONST           0
 224: LOAD_FAST            default
 226: LOAD_FAST            type
 228: LOAD_FAST            choices
 230: LOAD_FAST            required
 232: LOAD_FAST            help
 234: LOAD_FAST            metavar
 236: KW_NAMES             
 238: PRECALL              
 242: CALL                 
 252: POP_TOP              
 254: LOAD_CONST           None
 256: RETURN_VALUE         
