# Disassembly for argparse.ArgumentParser._parse_known_args.<listcomp>
# From module file: argparse

## co_consts:
()

## co_names:
('help', 'SUPPRESS', '_get_action_name')

## bytecode:

   0: RESUME               
   2: BUILD_LIST           
   4: LOAD_FAST            .0
   6: FOR_ITER             to 70
   8: STORE_FAST           action
  10: LOAD_FAST            action
  12: LOAD_ATTR            help
  22: LOAD_GLOBAL          SUPPRESS
  34: IS_OP                
  36: POP_JUMP_BACKWARD_IF_FALSE to 6
  38: LOAD_GLOBAL          NULL + _get_action_name
  50: LOAD_FAST            action
  52: PRECALL              
  56: CALL                 
  66: LIST_APPEND          
  68: JUMP_BACKWARD        to 6
  70: RETURN_VALUE         
