# Disassembly for argparse.FileType.__repr__.<listcomp>
# From module file: argparse

## co_consts:
(None, '=')

## co_names:
()

## bytecode:

   0: RESUME               
   2: BUILD_LIST           
   4: LOAD_FAST            .0
   6: FOR_ITER             to 36
   8: UNPACK_SEQUENCE      
  12: STORE_FAST           kw
  14: STORE_FAST           arg
  16: LOAD_FAST            arg
  18: POP_JUMP_BACKWARD_IF_NONE to 6
  20: LOAD_FAST            kw
  22: FORMAT_VALUE         str
  24: LOAD_CONST           '='
  26: LOAD_FAST            arg
  28: FORMAT_VALUE         repr
  30: BUILD_STRING         
  32: LIST_APPEND          
  34: JUMP_BACKWARD        to 6
  36: RETURN_VALUE         
