# Disassembly for argparse.HelpFormatter._Section.__init__
# From module file: argparse

## co_consts:
(None,)

## co_names:
('formatter', 'parent', 'heading', 'items')

## bytecode:

   0: RESUME               
   2: LOAD_FAST            formatter
   4: LOAD_FAST            self
   6: STORE_ATTR           formatter
  16: LOAD_FAST            parent
  18: LOAD_FAST            self
  20: STORE_ATTR           parent
  30: LOAD_FAST            heading
  32: LOAD_FAST            self
  34: STORE_ATTR           heading
  44: BUILD_LIST           
  46: LOAD_FAST            self
  48: STORE_ATTR           items
  58: LOAD_CONST           None
  60: RETURN_VALUE         
