# Disassembly for argparse.BooleanOptionalAction
# From module file: argparse

## co_consts:
('BooleanOptionalAction', None, False, <code object __init__ at 0x0000024069498030, file "argparse.py", line 886>, <code object __call__ at 0x00000240693D2760, file "argparse.py", line 916>, <code object format_usage at 0x000002406945DB60, file "argparse.py", line 920>, (None, None, None, False, None, None), (None,))

## co_names:
('__name__', '__module__', '__qualname__', '__init__', '__call__', 'format_usage', '__classcell__')

## bytecode:

   0: MAKE_CELL            __class__
   2: RESUME               
   4: LOAD_NAME            __name__
   6: STORE_NAME           __module__
   8: LOAD_CONST           'BooleanOptionalAction'
  10: STORE_NAME           __qualname__
  12: NOP                  
  14: NOP                  
  16: NOP                  
  18: NOP                  
  20: NOP                  
  22: NOP                  
  24: LOAD_CONST           (None, None, None, False, None, None)
  26: LOAD_CLOSURE         __class__
  28: BUILD_TUPLE          
  30: LOAD_CONST           <code object __init__ at 0x0000024069498030, file "argparse.py", line 886>
  32: MAKE_FUNCTION        defaults, closure
  34: STORE_NAME           __init__
  36: LOAD_CONST           (None,)
  38: LOAD_CONST           <code object __call__ at 0x00000240693D2760, file "argparse.py", line 916>
  40: MAKE_FUNCTION        defaults
  42: STORE_NAME           __call__
  44: LOAD_CONST           <code object format_usage at 0x000002406945DB60, file "argparse.py", line 920>
  46: MAKE_FUNCTION        
  48: STORE_NAME           format_usage
  50: LOAD_CLOSURE         __class__
  52: COPY                 
  54: STORE_NAME           __classcell__
  56: RETURN_VALUE         
