# Disassembly for argparse.Namespace.__eq__
# From module file: argparse

## co_consts:
(None,)

## co_names:
('isinstance', 'Namespace', 'NotImplemented', 'vars')

## bytecode:

   0: RESUME               
   2: LOAD_GLOBAL          NULL + isinstance
  14: LOAD_FAST            other
  16: LOAD_GLOBAL          Namespace
  28: PRECALL              
  32: CALL                 
  42: POP_JUMP_FORWARD_IF_TRUE to 58
  44: LOAD_GLOBAL          NotImplemented
  56: RETURN_VALUE         
  58: LOAD_GLOBAL          NULL + vars
  70: LOAD_FAST            self
  72: PRECALL              
  76: CALL                 
  86: LOAD_GLOBAL          NULL + vars
  98: LOAD_FAST            other
 100: PRECALL              
 104: CALL                 
 114: COMPARE_OP           ==
 120: RETURN_VALUE         
