# Disassembly for argparse.ArgumentParser._parse_known_args.consume_positionals
# From module file: argparse

## co_consts:
(None,)

## co_names:
('_match_arguments_partial', 'zip', 'len')

## bytecode:

   0: COPY_FREE_VARS       
   2: RESUME               
   4: LOAD_DEREF           self
   6: LOAD_ATTR            _match_arguments_partial
  16: STORE_FAST           match_partial
  18: LOAD_DEREF           arg_strings_pattern
  20: LOAD_FAST            start_index
  22: LOAD_CONST           None
  24: BUILD_SLICE          
  26: BINARY_SUBSCR        
  36: STORE_FAST           selected_pattern
  38: PUSH_NULL            
  40: LOAD_FAST            match_partial
  42: LOAD_DEREF           positionals
  44: LOAD_FAST            selected_pattern
  46: PRECALL              
  50: CALL                 
  60: STORE_FAST           arg_counts
  62: LOAD_GLOBAL          NULL + zip
  74: LOAD_DEREF           positionals
  76: LOAD_FAST            arg_counts
  78: PRECALL              
  82: CALL                 
  92: GET_ITER             
  94: FOR_ITER             to 166
  96: UNPACK_SEQUENCE      
 100: STORE_FAST           action
 102: STORE_FAST           arg_count
 104: LOAD_DEREF           arg_strings
 106: LOAD_FAST            start_index
 108: LOAD_FAST            start_index
 110: LOAD_FAST            arg_count
 112: BINARY_OP            +
 116: BUILD_SLICE          
 118: BINARY_SUBSCR        
 128: STORE_FAST           args
 130: LOAD_FAST            start_index
 132: LOAD_FAST            arg_count
 134: BINARY_OP            +=
 138: STORE_FAST           start_index
 140: PUSH_NULL            
 142: LOAD_DEREF           take_action
 144: LOAD_FAST            action
 146: LOAD_FAST            args
 148: PRECALL              
 152: CALL                 
 162: POP_TOP              
 164: JUMP_BACKWARD        to 94
 166: LOAD_DEREF           positionals
 168: LOAD_GLOBAL          NULL + len
 180: LOAD_FAST            arg_counts
 182: PRECALL              
 186: CALL                 
 196: LOAD_CONST           None
 198: BUILD_SLICE          
 200: BINARY_SUBSCR        
 210: LOAD_DEREF           positionals
 212: LOAD_CONST           None
 214: LOAD_CONST           None
 216: BUILD_SLICE          
 218: STORE_SUBSCR         
 222: LOAD_FAST            start_index
 224: RETURN_VALUE         
