# Disassembly for argparse.ArgumentDefaultsHelpFormatter._get_help_string
# From module file: argparse

## co_consts:
("\n        Add the default value to the option help message.\n\n        ArgumentDefaultsHelpFormatter and BooleanOptionalAction when it isn't\n        already present. This code will do that, detecting cornercases to\n        prevent duplicates or cases where it wouldn't make sense to the end\n        user.\n        ", None, '', '%(default)', ' (default: %(default)s)')

## co_names:
('help', 'default', 'SUPPRESS', 'OPTIONAL', 'ZERO_OR_MORE', 'option_strings', 'nargs')

## bytecode:

   0: RESUME               
   2: LOAD_FAST            action
   4: LOAD_ATTR            help
  14: STORE_FAST           help
  16: LOAD_FAST            help
  18: POP_JUMP_FORWARD_IF_NOT_NONE to 24
  20: LOAD_CONST           ''
  22: STORE_FAST           help
  24: LOAD_CONST           '%(default)'
  26: LOAD_FAST            help
  28: CONTAINS_OP          
  30: POP_JUMP_FORWARD_IF_FALSE to 130
  32: LOAD_FAST            action
  34: LOAD_ATTR            default
  44: LOAD_GLOBAL          SUPPRESS
  56: IS_OP                
  58: POP_JUMP_FORWARD_IF_FALSE to 130
  60: LOAD_GLOBAL          OPTIONAL
  72: LOAD_GLOBAL          ZERO_OR_MORE
  84: BUILD_LIST           
  86: STORE_FAST           defaulting_nargs
  88: LOAD_FAST            action
  90: LOAD_ATTR            option_strings
 100: POP_JUMP_FORWARD_IF_TRUE to 120
 102: LOAD_FAST            action
 104: LOAD_ATTR            nargs
 114: LOAD_FAST            defaulting_nargs
 116: CONTAINS_OP          
 118: POP_JUMP_FORWARD_IF_FALSE to 130
 120: LOAD_FAST            help
 122: LOAD_CONST           ' (default: %(default)s)'
 124: BINARY_OP            +=
 128: STORE_FAST           help
 130: LOAD_FAST            help
 132: RETURN_VALUE         
