# Disassembly for argparse.ArgumentParser.error
# From module file: argparse

## co_consts:
('error(message: string)\n\n        Prints a usage message incorporating the message to stderr and\n        exits.\n\n        If you override this in a subclass, it should not return -- it\n        should either exit or raise an exception.\n        ', ('prog', 'message'), 2, '%(prog)s: error: %(message)s\n', None)

## co_names:
('print_usage', '_sys', 'stderr', 'prog', 'exit', '_')

## bytecode:

   0: RESUME               
   2: LOAD_FAST            self
   4: LOAD_METHOD          print_usage
  26: LOAD_GLOBAL          _sys
  38: LOAD_ATTR            stderr
  48: PRECALL              
  52: CALL                 
  62: POP_TOP              
  64: LOAD_FAST            self
  66: LOAD_ATTR            prog
  76: LOAD_FAST            message
  78: LOAD_CONST           ('prog', 'message')
  80: BUILD_CONST_KEY_MAP  
  82: STORE_FAST           args
  84: LOAD_FAST            self
  86: LOAD_METHOD          exit
 108: LOAD_CONST           2
 110: LOAD_GLOBAL          NULL + _
 122: LOAD_CONST           '%(prog)s: error: %(message)s\n'
 124: PRECALL              
 128: CALL                 
 138: LOAD_FAST            args
 140: BINARY_OP            %
 144: PRECALL              
 148: CALL                 
 158: POP_TOP              
 160: LOAD_CONST           None
 162: RETURN_VALUE         
