# Disassembly for argparse._SubParsersAction.__call__
# From module file: argparse

## co_consts:
(None, 0, 1, ', ', ('parser_name', 'choices'), 'unknown parser %(parser_name)r (choices: %(choices)s)')

## co_names:
('dest', 'SUPPRESS', 'setattr', '_name_parser_map', 'KeyError', 'join', '_', 'ArgumentError', 'parse_known_args', 'vars', 'items', 'setdefault', '_UNRECOGNIZED_ARGS_ATTR', 'getattr', 'extend')

## bytecode:

   0: RESUME               
   2: LOAD_FAST            values
   4: LOAD_CONST           0
   6: BINARY_SUBSCR        
  16: STORE_FAST           parser_name
  18: LOAD_FAST            values
  20: LOAD_CONST           1
  22: LOAD_CONST           None
  24: BUILD_SLICE          
  26: BINARY_SUBSCR        
  36: STORE_FAST           arg_strings
  38: LOAD_FAST            self
  40: LOAD_ATTR            dest
  50: LOAD_GLOBAL          SUPPRESS
  62: IS_OP                
  64: POP_JUMP_FORWARD_IF_FALSE to 110
  66: LOAD_GLOBAL          NULL + setattr
  78: LOAD_FAST            namespace
  80: LOAD_FAST            self
  82: LOAD_ATTR            dest
  92: LOAD_FAST            parser_name
  94: PRECALL              
  98: CALL                 
 108: POP_TOP              
 110: NOP                  
 112: LOAD_FAST            self
 114: LOAD_ATTR            _name_parser_map
 124: LOAD_FAST            parser_name
 126: BINARY_SUBSCR        
 136: STORE_FAST           parser
 138: JUMP_FORWARD         to 294
 140: PUSH_EXC_INFO        
 142: LOAD_GLOBAL          KeyError
 154: CHECK_EXC_MATCH      
 156: POP_JUMP_FORWARD_IF_FALSE to 286
 158: POP_TOP              
 160: LOAD_FAST            parser_name
 162: LOAD_CONST           ', '
 164: LOAD_METHOD          join
 186: LOAD_FAST            self
 188: LOAD_ATTR            _name_parser_map
 198: PRECALL              
 202: CALL                 
 212: LOAD_CONST           ('parser_name', 'choices')
 214: BUILD_CONST_KEY_MAP  
 216: STORE_FAST           args
 218: LOAD_GLOBAL          NULL + _
 230: LOAD_CONST           'unknown parser %(parser_name)r (choices: %(choices)s)'
 232: PRECALL              
 236: CALL                 
 246: LOAD_FAST            args
 248: BINARY_OP            %
 252: STORE_FAST           msg
 254: LOAD_GLOBAL          NULL + ArgumentError
 266: LOAD_FAST            self
 268: LOAD_FAST            msg
 270: PRECALL              
 274: CALL                 
 284: RAISE_VARARGS        
 286: RERAISE              
 288: COPY                 
 290: POP_EXCEPT           
 292: RERAISE              
 294: LOAD_FAST            parser
 296: LOAD_METHOD          parse_known_args
 318: LOAD_FAST            arg_strings
 320: LOAD_CONST           None
 322: PRECALL              
 326: CALL                 
 336: UNPACK_SEQUENCE      
 340: STORE_FAST           subnamespace
 342: STORE_FAST           arg_strings
 344: LOAD_GLOBAL          NULL + vars
 356: LOAD_FAST            subnamespace
 358: PRECALL              
 362: CALL                 
 372: LOAD_METHOD          items
 394: PRECALL              
 398: CALL                 
 408: GET_ITER             
 410: FOR_ITER             to 456
 412: UNPACK_SEQUENCE      
 416: STORE_FAST           key
 418: STORE_FAST           value
 420: LOAD_GLOBAL          NULL + setattr
 432: LOAD_FAST            namespace
 434: LOAD_FAST            key
 436: LOAD_FAST            value
 438: PRECALL              
 442: CALL                 
 452: POP_TOP              
 454: JUMP_BACKWARD        to 410
 456: LOAD_FAST            arg_strings
 458: POP_JUMP_FORWARD_IF_FALSE to 624
 460: LOAD_GLOBAL          NULL + vars
 472: LOAD_FAST            namespace
 474: PRECALL              
 478: CALL                 
 488: LOAD_METHOD          setdefault
 510: LOAD_GLOBAL          _UNRECOGNIZED_ARGS_ATTR
 522: BUILD_LIST           
 524: PRECALL              
 528: CALL                 
 538: POP_TOP              
 540: LOAD_GLOBAL          NULL + getattr
 552: LOAD_FAST            namespace
 554: LOAD_GLOBAL          _UNRECOGNIZED_ARGS_ATTR
 566: PRECALL              
 570: CALL                 
 580: LOAD_METHOD          extend
 602: LOAD_FAST            arg_strings
 604: PRECALL              
 608: CALL                 
 618: POP_TOP              
 620: LOAD_CONST           None
 622: RETURN_VALUE         
 624: LOAD_CONST           None
 626: RETURN_VALUE         
