# Disassembly for argparse.ArgumentParser._get_kwargs.<listcomp>
# From module file: argparse

## co_consts:
()

## co_names:
('getattr',)

## bytecode:

   0: COPY_FREE_VARS       
   2: RESUME               
   4: BUILD_LIST           
   6: LOAD_FAST            .0
   8: FOR_ITER             to 50
  10: STORE_FAST           name
  12: LOAD_FAST            name
  14: LOAD_GLOBAL          NULL + getattr
  26: LOAD_DEREF           self
  28: LOAD_FAST            name
  30: PRECALL              
  34: CALL                 
  44: BUILD_TUPLE          
  46: LIST_APPEND          
  48: JUMP_BACKWARD        to 8
  50: RETURN_VALUE         
