# Disassembly for argparse.HelpFormatter.add_arguments
# From module file: argparse

## co_consts:
(None,)

## co_names:
('add_argument',)

## bytecode:

   0: RESUME               
   2: LOAD_FAST            actions
   4: GET_ITER             
   6: FOR_ITER             to 54
   8: STORE_FAST           action
  10: LOAD_FAST            self
  12: LOAD_METHOD          add_argument
  34: LOAD_FAST            action
  36: PRECALL              
  40: CALL                 
  50: POP_TOP              
  52: JUMP_BACKWARD        to 6
  54: LOAD_CONST           None
  56: RETURN_VALUE         
