# Disassembly for argparse._ArgumentGroup.add_argument_group
# From module file: argparse

## co_consts:
(None, 'Nesting argument groups is deprecated.', 2, ('category', 'stacklevel'))

## co_names:
('warnings', 'warn', 'DeprecationWarning', 'super', 'add_argument_group')

## bytecode:

   0: COPY_FREE_VARS       
   2: RESUME               
   4: LOAD_GLOBAL          NULL + warnings
  16: LOAD_ATTR            warn
  26: LOAD_CONST           'Nesting argument groups is deprecated.'
  28: LOAD_GLOBAL          DeprecationWarning
  40: LOAD_CONST           2
  42: KW_NAMES             
  44: PRECALL              
  48: CALL                 
  58: POP_TOP              
  60: PUSH_NULL            
  62: LOAD_GLOBAL          NULL + super
  74: PRECALL              
  78: CALL                 
  88: LOAD_ATTR            add_argument_group
  98: LOAD_FAST            args
 100: BUILD_MAP            
 102: LOAD_FAST            kwargs
 104: DICT_MERGE           
 106: CALL_FUNCTION_EX     
 108: RETURN_VALUE         
