# Disassembly for argparse.ArgumentError.__str__
# From module file: argparse

## co_consts:
(None, '%(message)s', 'argument %(argument_name)s: %(message)s', ('message', 'argument_name'))

## co_names:
('argument_name', '_', 'dict', 'message')

## bytecode:

   0: RESUME               
   2: LOAD_FAST            self
   4: LOAD_ATTR            argument_name
  14: POP_JUMP_FORWARD_IF_NOT_NONE to 22
  16: LOAD_CONST           '%(message)s'
  18: STORE_FAST           format
  20: JUMP_FORWARD         to 52
  22: LOAD_GLOBAL          NULL + _
  34: LOAD_CONST           'argument %(argument_name)s: %(message)s'
  36: PRECALL              
  40: CALL                 
  50: STORE_FAST           format
  52: LOAD_FAST            format
  54: LOAD_GLOBAL          NULL + dict
  66: LOAD_FAST            self
  68: LOAD_ATTR            message
  78: LOAD_FAST            self
  80: LOAD_ATTR            argument_name
  90: KW_NAMES             
  92: PRECALL              
  96: CALL                 
 106: BINARY_OP            %
 110: RETURN_VALUE         
