# Disassembly for argparse._AppendConstAction.__init__
# From module file: argparse

## co_consts:
(None, 0, ('option_strings', 'dest', 'nargs', 'const', 'default', 'required', 'help', 'metavar'))

## co_names:
('super', '_AppendConstAction', '__init__')

## bytecode:

   0: COPY_FREE_VARS       
   2: RESUME               
   4: LOAD_GLOBAL          NULL + super
  16: LOAD_GLOBAL          _AppendConstAction
  28: LOAD_FAST            self
  30: PRECALL              
  34: CALL                 
  44: LOAD_METHOD          __init__
  66: LOAD_FAST            option_strings
  68: LOAD_FAST            dest
  70: LOAD_CONST           0
  72: LOAD_FAST            const
  74: LOAD_FAST            default
  76: LOAD_FAST            required
  78: LOAD_FAST            help
  80: LOAD_FAST            metavar
  82: KW_NAMES             
  84: PRECALL              
  88: CALL                 
  98: POP_TOP              
 100: LOAD_CONST           None
 102: RETURN_VALUE         
