# Disassembly for argparse.ArgumentParser._print_message
# From module file: argparse

## co_consts:
(None,)

## co_names:
('_sys', 'stderr', 'write', 'AttributeError', 'OSError')

## bytecode:

   0: RESUME               
   2: LOAD_FAST            message
   4: POP_JUMP_FORWARD_IF_FALSE to 130
   6: LOAD_FAST            file
   8: JUMP_IF_TRUE_OR_POP  to 32
  10: LOAD_GLOBAL          _sys
  22: LOAD_ATTR            stderr
  32: STORE_FAST           file
  34: NOP                  
  36: LOAD_FAST            file
  38: LOAD_METHOD          write
  60: LOAD_FAST            message
  62: PRECALL              
  66: CALL                 
  76: POP_TOP              
  78: LOAD_CONST           None
  80: RETURN_VALUE         
  82: PUSH_EXC_INFO        
  84: LOAD_GLOBAL          AttributeError
  96: LOAD_GLOBAL          OSError
 108: BUILD_TUPLE          
 110: CHECK_EXC_MATCH      
 112: POP_JUMP_FORWARD_IF_FALSE to 122
 114: POP_TOP              
 116: POP_EXCEPT           
 118: LOAD_CONST           None
 120: RETURN_VALUE         
 122: RERAISE              
 124: COPY                 
 126: POP_EXCEPT           
 128: RERAISE              
 130: LOAD_CONST           None
 132: RETURN_VALUE         
