# Disassembly for argparse.ArgumentParser._get_nargs_pattern
# From module file: argparse

## co_consts:
(None, '(-*A-*)', '(-*A?-*)', '(-*[A-]*)', '(-*A[A-]*)', '([-AO]*)', '(-*A[-AO]*)', '(-*-*)', '(-*%s-*)', '-*', 'A', '', '-')

## co_names:
('nargs', 'OPTIONAL', 'ZERO_OR_MORE', 'ONE_OR_MORE', 'REMAINDER', 'PARSER', 'SUPPRESS', 'join', 'option_strings', 'replace')

## bytecode:

   0: RESUME               
   2: LOAD_FAST            action
   4: LOAD_ATTR            nargs
  14: STORE_FAST           nargs
  16: LOAD_FAST            nargs
  18: POP_JUMP_FORWARD_IF_NOT_NONE to 26
  20: LOAD_CONST           '(-*A-*)'
  22: STORE_FAST           nargs_pattern
  24: JUMP_FORWARD         to 248
  26: LOAD_FAST            nargs
  28: LOAD_GLOBAL          OPTIONAL
  40: COMPARE_OP           ==
  46: POP_JUMP_FORWARD_IF_FALSE to 54
  48: LOAD_CONST           '(-*A?-*)'
  50: STORE_FAST           nargs_pattern
  52: JUMP_FORWARD         to 248
  54: LOAD_FAST            nargs
  56: LOAD_GLOBAL          ZERO_OR_MORE
  68: COMPARE_OP           ==
  74: POP_JUMP_FORWARD_IF_FALSE to 82
  76: LOAD_CONST           '(-*[A-]*)'
  78: STORE_FAST           nargs_pattern
  80: JUMP_FORWARD         to 248
  82: LOAD_FAST            nargs
  84: LOAD_GLOBAL          ONE_OR_MORE
  96: COMPARE_OP           ==
 102: POP_JUMP_FORWARD_IF_FALSE to 110
 104: LOAD_CONST           '(-*A[A-]*)'
 106: STORE_FAST           nargs_pattern
 108: JUMP_FORWARD         to 248
 110: LOAD_FAST            nargs
 112: LOAD_GLOBAL          REMAINDER
 124: COMPARE_OP           ==
 130: POP_JUMP_FORWARD_IF_FALSE to 138
 132: LOAD_CONST           '([-AO]*)'
 134: STORE_FAST           nargs_pattern
 136: JUMP_FORWARD         to 248
 138: LOAD_FAST            nargs
 140: LOAD_GLOBAL          PARSER
 152: COMPARE_OP           ==
 158: POP_JUMP_FORWARD_IF_FALSE to 166
 160: LOAD_CONST           '(-*A[-AO]*)'
 162: STORE_FAST           nargs_pattern
 164: JUMP_FORWARD         to 248
 166: LOAD_FAST            nargs
 168: LOAD_GLOBAL          SUPPRESS
 180: COMPARE_OP           ==
 186: POP_JUMP_FORWARD_IF_FALSE to 194
 188: LOAD_CONST           '(-*-*)'
 190: STORE_FAST           nargs_pattern
 192: JUMP_FORWARD         to 248
 194: LOAD_CONST           '(-*%s-*)'
 196: LOAD_CONST           '-*'
 198: LOAD_METHOD          join
 220: LOAD_CONST           'A'
 222: LOAD_FAST            nargs
 224: BINARY_OP            *
 228: PRECALL              
 232: CALL                 
 242: BINARY_OP            %
 246: STORE_FAST           nargs_pattern
 248: LOAD_FAST            action
 250: LOAD_ATTR            option_strings
 260: POP_JUMP_FORWARD_IF_FALSE to 350
 262: LOAD_FAST            nargs_pattern
 264: LOAD_METHOD          replace
 286: LOAD_CONST           '-*'
 288: LOAD_CONST           ''
 290: PRECALL              
 294: CALL                 
 304: STORE_FAST           nargs_pattern
 306: LOAD_FAST            nargs_pattern
 308: LOAD_METHOD          replace
 330: LOAD_CONST           '-'
 332: LOAD_CONST           ''
 334: PRECALL              
 338: CALL                 
 348: STORE_FAST           nargs_pattern
 350: LOAD_FAST            nargs_pattern
 352: RETURN_VALUE         
