# Disassembly for argparse._MutuallyExclusiveGroup.__init__
# From module file: argparse

## co_consts:
(None,)

## co_names:
('super', '_MutuallyExclusiveGroup', '__init__', 'required', '_container')

## bytecode:

   0: COPY_FREE_VARS       
   2: RESUME               
   4: LOAD_GLOBAL          NULL + super
  16: LOAD_GLOBAL          _MutuallyExclusiveGroup
  28: LOAD_FAST            self
  30: PRECALL              
  34: CALL                 
  44: LOAD_METHOD          __init__
  66: LOAD_FAST            container
  68: PRECALL              
  72: CALL                 
  82: POP_TOP              
  84: LOAD_FAST            required
  86: LOAD_FAST            self
  88: STORE_ATTR           required
  98: LOAD_FAST            container
 100: LOAD_FAST            self
 102: STORE_ATTR           _container
 112: LOAD_CONST           None
 114: RETURN_VALUE         
