# Disassembly for argparse._ActionsContainer.set_defaults
# From module file: argparse

## co_consts:
(None,)

## co_names:
('_defaults', 'update', '_actions', 'dest', 'default')

## bytecode:

   0: RESUME               
   2: LOAD_FAST            self
   4: LOAD_ATTR            _defaults
  14: LOAD_METHOD          update
  36: LOAD_FAST            kwargs
  38: PRECALL              
  42: CALL                 
  52: POP_TOP              
  54: LOAD_FAST            self
  56: LOAD_ATTR            _actions
  66: GET_ITER             
  68: FOR_ITER             to 128
  70: STORE_FAST           action
  72: LOAD_FAST            action
  74: LOAD_ATTR            dest
  84: LOAD_FAST            kwargs
  86: CONTAINS_OP          
  88: POP_JUMP_FORWARD_IF_FALSE to 126
  90: LOAD_FAST            kwargs
  92: LOAD_FAST            action
  94: LOAD_ATTR            dest
 104: BINARY_SUBSCR        
 114: LOAD_FAST            action
 116: STORE_ATTR           default
 126: JUMP_BACKWARD        to 68
 128: LOAD_CONST           None
 130: RETURN_VALUE         
