# Disassembly for argparse.ArgumentParser._parse_known_args.take_action
# From module file: argparse

## co_consts:
(None, 'not allowed with argument %s')

## co_names:
('add', '_get_values', 'default', 'get', '_', '_get_action_name', 'ArgumentError', 'SUPPRESS')

## bytecode:

   0: COPY_FREE_VARS       
   2: RESUME               
   4: LOAD_DEREF           seen_actions
   6: LOAD_METHOD          add
  28: LOAD_FAST            action
  30: PRECALL              
  34: CALL                 
  44: POP_TOP              
  46: LOAD_DEREF           self
  48: LOAD_METHOD          _get_values
  70: LOAD_FAST            action
  72: LOAD_FAST            argument_strings
  74: PRECALL              
  78: CALL                 
  88: STORE_FAST           argument_values
  90: LOAD_FAST            argument_values
  92: LOAD_FAST            action
  94: LOAD_ATTR            default
 104: IS_OP                
 106: POP_JUMP_FORWARD_IF_FALSE to 306
 108: LOAD_DEREF           seen_non_default_actions
 110: LOAD_METHOD          add
 132: LOAD_FAST            action
 134: PRECALL              
 138: CALL                 
 148: POP_TOP              
 150: LOAD_DEREF           action_conflicts
 152: LOAD_METHOD          get
 174: LOAD_FAST            action
 176: BUILD_LIST           
 178: PRECALL              
 182: CALL                 
 192: GET_ITER             
 194: FOR_ITER             to 306
 196: STORE_FAST           conflict_action
 198: LOAD_FAST            conflict_action
 200: LOAD_DEREF           seen_non_default_actions
 202: CONTAINS_OP          
 204: POP_JUMP_FORWARD_IF_FALSE to 304
 206: LOAD_GLOBAL          NULL + _
 218: LOAD_CONST           'not allowed with argument %s'
 220: PRECALL              
 224: CALL                 
 234: STORE_FAST           msg
 236: LOAD_GLOBAL          NULL + _get_action_name
 248: LOAD_FAST            conflict_action
 250: PRECALL              
 254: CALL                 
 264: STORE_FAST           action_name
 266: LOAD_GLOBAL          NULL + ArgumentError
 278: LOAD_FAST            action
 280: LOAD_FAST            msg
 282: LOAD_FAST            action_name
 284: BINARY_OP            %
 288: PRECALL              
 292: CALL                 
 302: RAISE_VARARGS        
 304: JUMP_BACKWARD        to 194
 306: LOAD_FAST            argument_values
 308: LOAD_GLOBAL          SUPPRESS
 320: IS_OP                
 322: POP_JUMP_FORWARD_IF_FALSE to 356
 324: PUSH_NULL            
 326: LOAD_FAST            action
 328: LOAD_DEREF           self
 330: LOAD_DEREF           namespace
 332: LOAD_FAST            argument_values
 334: LOAD_FAST            option_string
 336: PRECALL              
 340: CALL                 
 350: POP_TOP              
 352: LOAD_CONST           None
 354: RETURN_VALUE         
 356: LOAD_CONST           None
 358: RETURN_VALUE         
