# Disassembly for argparse._ArgumentGroup
# From module file: argparse

## co_consts:
('_ArgumentGroup', None, <code object __init__ at 0x0000024068C8D8F0, file "argparse.py", line 1647>, <code object _add_action at 0x000002406922C2D0, file "argparse.py", line 1669>, <code object _remove_action at 0x000002406922C420, file "argparse.py", line 1674>, <code object add_argument_group at 0x00000240693D2D50, file "argparse.py", line 1678>, (None, None))

## co_names:
('__name__', '__module__', '__qualname__', '__init__', '_add_action', '_remove_action', 'add_argument_group', '__classcell__')

## bytecode:

   0: MAKE_CELL            __class__
   2: RESUME               
   4: LOAD_NAME            __name__
   6: STORE_NAME           __module__
   8: LOAD_CONST           '_ArgumentGroup'
  10: STORE_NAME           __qualname__
  12: LOAD_CONST           (None, None)
  14: LOAD_CLOSURE         __class__
  16: BUILD_TUPLE          
  18: LOAD_CONST           <code object __init__ at 0x0000024068C8D8F0, file "argparse.py", line 1647>
  20: MAKE_FUNCTION        defaults, closure
  22: STORE_NAME           __init__
  24: LOAD_CLOSURE         __class__
  26: BUILD_TUPLE          
  28: LOAD_CONST           <code object _add_action at 0x000002406922C2D0, file "argparse.py", line 1669>
  30: MAKE_FUNCTION        closure
  32: STORE_NAME           _add_action
  34: LOAD_CLOSURE         __class__
  36: BUILD_TUPLE          
  38: LOAD_CONST           <code object _remove_action at 0x000002406922C420, file "argparse.py", line 1674>
  40: MAKE_FUNCTION        closure
  42: STORE_NAME           _remove_action
  44: LOAD_CLOSURE         __class__
  46: BUILD_TUPLE          
  48: LOAD_CONST           <code object add_argument_group at 0x00000240693D2D50, file "argparse.py", line 1678>
  50: MAKE_FUNCTION        closure
  52: STORE_NAME           add_argument_group
  54: LOAD_CLOSURE         __class__
  56: COPY                 
  58: STORE_NAME           __classcell__
  60: RETURN_VALUE         
