# Disassembly for argparse.ArgumentParser._match_arguments_partial.<listcomp>
# From module file: argparse

## co_consts:
()

## co_names:
('len',)

## bytecode:

   0: RESUME               
   2: BUILD_LIST           
   4: LOAD_FAST            .0
   6: FOR_ITER             to 42
   8: STORE_FAST           string
  10: LOAD_GLOBAL          NULL + len
  22: LOAD_FAST            string
  24: PRECALL              
  28: CALL                 
  38: LIST_APPEND          
  40: JUMP_BACKWARD        to 6
  42: RETURN_VALUE         
