# Disassembly for argparse.ArgumentParser
# From module file: argparse

## co_consts:
('ArgumentParser', 'Object for parsing command line strings into Python objects.\n\n    Keyword Arguments:\n        - prog -- The name of the program (default:\n            ``os.path.basename(sys.argv[0])``)\n        - usage -- A usage message (default: auto-generated from arguments)\n        - description -- A description of what the program does\n        - epilog -- Text following the argument descriptions\n        - parents -- Parsers whose arguments should be copied into this one\n        - formatter_class -- HelpFormatter class for printing help messages\n        - prefix_chars -- Characters that prefix optional arguments\n        - fromfile_prefix_chars -- Characters that prefix files containing\n            additional arguments\n        - argument_default -- The default value for all arguments\n        - conflict_handler -- String indicating how to handle conflicts\n        - add_help -- Add a -h/-help option\n        - allow_abbrev -- Allow long options to be abbreviated unambiguously\n        - exit_on_error -- Determines whether or not ArgumentParser exits with\n            error info when an error occurs\n    ', None, '-', 'error', True, <code object __init__ at 0x0000024068D60290, file "argparse.py", line 1737>, <code object _get_kwargs at 0x0000024069466950, file "argparse.py", line 1803>, <code object add_subparsers at 0x0000024069503630, file "argparse.py", line 1817>, <code object _add_action at 0x00000240693AABF0, file "argparse.py", line 1848>, <code object _get_optional_actions at 0x0000024069466B10, file "argparse.py", line 1855>, <code object _get_positional_actions at 0x0000024069466CD0, file "argparse.py", line 1860>, <code object parse_args at 0x000002406949C480, file "argparse.py", line 1868>, <code object parse_known_args at 0x0000024069583990, file "argparse.py", line 1875>, <code object _parse_known_args at 0x0000024068E94EF0, file "argparse.py", line 1913>, <code object _read_args_from_files at 0x0000024068BE4BC0, file "argparse.py", line 2163>, <code object convert_arg_line_to_args at 0x000002406943B630, file "argparse.py", line 2188>, <code object _match_argument at 0x0000024068E1BE80, file "argparse.py", line 2191>, <code object _match_arguments_partial at 0x0000024069365B50, file "argparse.py", line 2213>, <code object _parse_optional at 0x0000024068BFEA30, file "argparse.py", line 2229>, <code object _get_option_tuples at 0x0000024068DD3150, file "argparse.py", line 2287>, <code object _get_nargs_pattern at 0x0000024068C8E3E0, file "argparse.py", line 2332>, <code object parse_intermixed_args at 0x000002406949C5F0, file "argparse.py", line 2381>, <code object parse_known_intermixed_args at 0x0000024069585F20, file "argparse.py", line 2388>, <code object _get_values at 0x0000024068E17000, file "argparse.py", line 2465>, <code object _get_value at 0x0000024068B3E350, file "argparse.py", line 2521>, <code object _check_value at 0x000002406942D7A0, file "argparse.py", line 2547>, <code object format_usage at 0x00000240691C14D0, file "argparse.py", line 2558>, <code object format_help at 0x0000024068D2F6C0, file "argparse.py", line 2564>, <code object _get_formatter at 0x000002406945EE20, file "argparse.py", line 2587>, <code object print_usage at 0x00000240693D3210, file "argparse.py", line 2593>, <code object print_help at 0x00000240693D3340, file "argparse.py", line 2598>, <code object _print_message at 0x00000240693AAE70, file "argparse.py", line 2603>, 0, <code object exit at 0x00000240693D3470, file "argparse.py", line 2614>, <code object error at 0x00000240691C1790, file "argparse.py", line 2619>, (None, None), (None,), (0, None))

## co_names:
('__name__', '__module__', '__qualname__', '__doc__', 'HelpFormatter', '__init__', '_get_kwargs', 'add_subparsers', '_add_action', '_get_optional_actions', '_get_positional_actions', 'parse_args', 'parse_known_args', '_parse_known_args', '_read_args_from_files', 'convert_arg_line_to_args', '_match_argument', '_match_arguments_partial', '_parse_optional', '_get_option_tuples', '_get_nargs_pattern', 'parse_intermixed_args', 'parse_known_intermixed_args', '_get_values', '_get_value', '_check_value', 'format_usage', 'format_help', '_get_formatter', 'print_usage', 'print_help', '_print_message', 'exit', 'error', '__classcell__')

## bytecode:

   0: MAKE_CELL            __class__
   2: RESUME               
   4: LOAD_NAME            __name__
   6: STORE_NAME           __module__
   8: LOAD_CONST           'ArgumentParser'
  10: STORE_NAME           __qualname__
  12: LOAD_CONST           'Object for parsing command line strings into Python objects.\n\n    Keyword Arguments:\n        - prog -- The name of the program (default:\n            ``os.path.basename(sys.argv[0])``)\n        - usage -- A usage message (default: auto-generated from arguments)\n        - description -- A description of what the program does\n        - epilog -- Text following the argument descriptions\n        - parents -- Parsers whose arguments should be copied into this one\n        - formatter_class -- HelpFormatter class for printing help messages\n        - prefix_chars -- Characters that prefix optional arguments\n        - fromfile_prefix_chars -- Characters that prefix files containing\n            additional arguments\n        - argument_default -- The default value for all arguments\n        - conflict_handler -- String indicating how to handle conflicts\n        - add_help -- Add a -h/-help option\n        - allow_abbrev -- Allow long options to be abbreviated unambiguously\n        - exit_on_error -- Determines whether or not ArgumentParser exits with\n            error info when an error occurs\n    '
  14: STORE_NAME           __doc__
  16: LOAD_CONST           None
  18: LOAD_CONST           None
  20: LOAD_CONST           None
  22: LOAD_CONST           None
  24: BUILD_LIST           
  26: LOAD_NAME            HelpFormatter
  28: LOAD_CONST           '-'
  30: LOAD_CONST           None
  32: LOAD_CONST           None
  34: LOAD_CONST           'error'
  36: LOAD_CONST           True
  38: LOAD_CONST           True
  40: LOAD_CONST           True
  42: BUILD_TUPLE          
  44: LOAD_CLOSURE         __class__
  46: BUILD_TUPLE          
  48: LOAD_CONST           <code object __init__ at 0x0000024068D60290, file "argparse.py", line 1737>
  50: MAKE_FUNCTION        defaults, closure
  52: STORE_NAME           __init__
  54: LOAD_CONST           <code object _get_kwargs at 0x0000024069466950, file "argparse.py", line 1803>
  56: MAKE_FUNCTION        
  58: STORE_NAME           _get_kwargs
  60: LOAD_CONST           <code object add_subparsers at 0x0000024069503630, file "argparse.py", line 1817>
  62: MAKE_FUNCTION        
  64: STORE_NAME           add_subparsers
  66: LOAD_CONST           <code object _add_action at 0x00000240693AABF0, file "argparse.py", line 1848>
  68: MAKE_FUNCTION        
  70: STORE_NAME           _add_action
  72: LOAD_CONST           <code object _get_optional_actions at 0x0000024069466B10, file "argparse.py", line 1855>
  74: MAKE_FUNCTION        
  76: STORE_NAME           _get_optional_actions
  78: LOAD_CONST           <code object _get_positional_actions at 0x0000024069466CD0, file "argparse.py", line 1860>
  80: MAKE_FUNCTION        
  82: STORE_NAME           _get_positional_actions
  84: LOAD_CONST           (None, None)
  86: LOAD_CONST           <code object parse_args at 0x000002406949C480, file "argparse.py", line 1868>
  88: MAKE_FUNCTION        defaults
  90: STORE_NAME           parse_args
  92: LOAD_CONST           (None, None)
  94: LOAD_CONST           <code object parse_known_args at 0x0000024069583990, file "argparse.py", line 1875>
  96: MAKE_FUNCTION        defaults
  98: STORE_NAME           parse_known_args
 100: LOAD_CONST           <code object _parse_known_args at 0x0000024068E94EF0, file "argparse.py", line 1913>
 102: MAKE_FUNCTION        
 104: STORE_NAME           _parse_known_args
 106: LOAD_CONST           <code object _read_args_from_files at 0x0000024068BE4BC0, file "argparse.py", line 2163>
 108: MAKE_FUNCTION        
 110: STORE_NAME           _read_args_from_files
 112: LOAD_CONST           <code object convert_arg_line_to_args at 0x000002406943B630, file "argparse.py", line 2188>
 114: MAKE_FUNCTION        
 116: STORE_NAME           convert_arg_line_to_args
 118: LOAD_CONST           <code object _match_argument at 0x0000024068E1BE80, file "argparse.py", line 2191>
 120: MAKE_FUNCTION        
 122: STORE_NAME           _match_argument
 124: LOAD_CONST           <code object _match_arguments_partial at 0x0000024069365B50, file "argparse.py", line 2213>
 126: MAKE_FUNCTION        
 128: STORE_NAME           _match_arguments_partial
 130: LOAD_CONST           <code object _parse_optional at 0x0000024068BFEA30, file "argparse.py", line 2229>
 132: MAKE_FUNCTION        
 134: STORE_NAME           _parse_optional
 136: LOAD_CONST           <code object _get_option_tuples at 0x0000024068DD3150, file "argparse.py", line 2287>
 138: MAKE_FUNCTION        
 140: STORE_NAME           _get_option_tuples
 142: LOAD_CONST           <code object _get_nargs_pattern at 0x0000024068C8E3E0, file "argparse.py", line 2332>
 144: MAKE_FUNCTION        
 146: STORE_NAME           _get_nargs_pattern
 148: LOAD_CONST           (None, None)
 150: LOAD_CONST           <code object parse_intermixed_args at 0x000002406949C5F0, file "argparse.py", line 2381>
 152: MAKE_FUNCTION        defaults
 154: STORE_NAME           parse_intermixed_args
 156: LOAD_CONST           (None, None)
 158: LOAD_CONST           <code object parse_known_intermixed_args at 0x0000024069585F20, file "argparse.py", line 2388>
 160: MAKE_FUNCTION        defaults
 162: STORE_NAME           parse_known_intermixed_args
 164: LOAD_CONST           <code object _get_values at 0x0000024068E17000, file "argparse.py", line 2465>
 166: MAKE_FUNCTION        
 168: STORE_NAME           _get_values
 170: LOAD_CONST           <code object _get_value at 0x0000024068B3E350, file "argparse.py", line 2521>
 172: MAKE_FUNCTION        
 174: STORE_NAME           _get_value
 176: LOAD_CONST           <code object _check_value at 0x000002406942D7A0, file "argparse.py", line 2547>
 178: MAKE_FUNCTION        
 180: STORE_NAME           _check_value
 182: LOAD_CONST           <code object format_usage at 0x00000240691C14D0, file "argparse.py", line 2558>
 184: MAKE_FUNCTION        
 186: STORE_NAME           format_usage
 188: LOAD_CONST           <code object format_help at 0x0000024068D2F6C0, file "argparse.py", line 2564>
 190: MAKE_FUNCTION        
 192: STORE_NAME           format_help
 194: LOAD_CONST           <code object _get_formatter at 0x000002406945EE20, file "argparse.py", line 2587>
 196: MAKE_FUNCTION        
 198: STORE_NAME           _get_formatter
 200: LOAD_CONST           (None,)
 202: LOAD_CONST           <code object print_usage at 0x00000240693D3210, file "argparse.py", line 2593>
 204: MAKE_FUNCTION        defaults
 206: STORE_NAME           print_usage
 208: LOAD_CONST           (None,)
 210: LOAD_CONST           <code object print_help at 0x00000240693D3340, file "argparse.py", line 2598>
 212: MAKE_FUNCTION        defaults
 214: STORE_NAME           print_help
 216: LOAD_CONST           (None,)
 218: LOAD_CONST           <code object _print_message at 0x00000240693AAE70, file "argparse.py", line 2603>
 220: MAKE_FUNCTION        defaults
 222: STORE_NAME           _print_message
 224: LOAD_CONST           (0, None)
 226: LOAD_CONST           <code object exit at 0x00000240693D3470, file "argparse.py", line 2614>
 228: MAKE_FUNCTION        defaults
 230: STORE_NAME           exit
 232: LOAD_CONST           <code object error at 0x00000240691C1790, file "argparse.py", line 2619>
 234: MAKE_FUNCTION        
 236: STORE_NAME           error
 238: LOAD_CLOSURE         __class__
 240: COPY                 
 242: STORE_NAME           __classcell__
 244: RETURN_VALUE         
