# Disassembly for argparse._StoreConstAction.__call__
# From module file: argparse

## co_consts:
(None,)

## co_names:
('setattr', 'dest', 'const')

## bytecode:

   0: RESUME               
   2: LOAD_GLOBAL          NULL + setattr
  14: LOAD_FAST            namespace
  16: LOAD_FAST            self
  18: LOAD_ATTR            dest
  28: LOAD_FAST            self
  30: LOAD_ATTR            const
  40: PRECALL              
  44: CALL                 
  54: POP_TOP              
  56: LOAD_CONST           None
  58: RETURN_VALUE         
