# Disassembly for argparse.ArgumentParser._get_values
# From module file: argparse

## co_consts:
(None, '--', 1, <code object <listcomp> at 0x00000240693EBE30, file "argparse.py", line 2501>, <code object <listcomp> at 0x0000024069CC8030, file "argparse.py", line 2505>, 0, <code object <listcomp> at 0x0000024069CC8130, file "argparse.py", line 2514>)

## co_names:
('nargs', 'PARSER', 'REMAINDER', 'remove', 'ValueError', 'OPTIONAL', 'option_strings', 'const', 'default', 'isinstance', 'str', '_get_value', '_check_value', 'ZERO_OR_MORE', 'len', 'SUPPRESS')

## bytecode:

   0: MAKE_CELL            self
   2: MAKE_CELL            action
   4: RESUME               
   6: LOAD_DEREF           action
   8: LOAD_ATTR            nargs
  18: LOAD_GLOBAL          PARSER
  30: LOAD_GLOBAL          REMAINDER
  42: BUILD_TUPLE          
  44: CONTAINS_OP          
  46: POP_JUMP_FORWARD_IF_FALSE to 126
  48: NOP                  
  50: LOAD_FAST            arg_strings
  52: LOAD_METHOD          remove
  74: LOAD_CONST           '--'
  76: PRECALL              
  80: CALL                 
  90: POP_TOP              
  92: JUMP_FORWARD         to 126
  94: PUSH_EXC_INFO        
  96: LOAD_GLOBAL          ValueError
 108: CHECK_EXC_MATCH      
 110: POP_JUMP_FORWARD_IF_FALSE to 118
 112: POP_TOP              
 114: POP_EXCEPT           
 116: JUMP_FORWARD         to 126
 118: RERAISE              
 120: COPY                 
 122: POP_EXCEPT           
 124: RERAISE              
 126: LOAD_FAST            arg_strings
 128: POP_JUMP_FORWARD_IF_TRUE to 340
 130: LOAD_DEREF           action
 132: LOAD_ATTR            nargs
 142: LOAD_GLOBAL          OPTIONAL
 154: COMPARE_OP           ==
 160: POP_JUMP_FORWARD_IF_FALSE to 340
 162: LOAD_DEREF           action
 164: LOAD_ATTR            option_strings
 174: POP_JUMP_FORWARD_IF_FALSE to 192
 176: LOAD_DEREF           action
 178: LOAD_ATTR            const
 188: STORE_FAST           value
 190: JUMP_FORWARD         to 206
 192: LOAD_DEREF           action
 194: LOAD_ATTR            default
 204: STORE_FAST           value
 206: LOAD_GLOBAL          NULL + isinstance
 218: LOAD_FAST            value
 220: LOAD_GLOBAL          str
 232: PRECALL              
 236: CALL                 
 246: POP_JUMP_FORWARD_IF_FALSE to 336
 248: LOAD_DEREF           self
 250: LOAD_METHOD          _get_value
 272: LOAD_DEREF           action
 274: LOAD_FAST            value
 276: PRECALL              
 280: CALL                 
 290: STORE_FAST           value
 292: LOAD_DEREF           self
 294: LOAD_METHOD          _check_value
 316: LOAD_DEREF           action
 318: LOAD_FAST            value
 320: PRECALL              
 324: CALL                 
 334: POP_TOP              
 336: EXTENDED_ARG         
 338: JUMP_FORWARD         to 954
 340: LOAD_FAST            arg_strings
 342: POP_JUMP_FORWARD_IF_TRUE to 470
 344: LOAD_DEREF           action
 346: LOAD_ATTR            nargs
 356: LOAD_GLOBAL          ZERO_OR_MORE
 368: COMPARE_OP           ==
 374: POP_JUMP_FORWARD_IF_FALSE to 470
 376: LOAD_DEREF           action
 378: LOAD_ATTR            option_strings
 388: POP_JUMP_FORWARD_IF_TRUE to 470
 390: LOAD_DEREF           action
 392: LOAD_ATTR            default
 402: POP_JUMP_FORWARD_IF_NONE to 420
 404: LOAD_DEREF           action
 406: LOAD_ATTR            default
 416: STORE_FAST           value
 418: JUMP_FORWARD         to 424
 420: LOAD_FAST            arg_strings
 422: STORE_FAST           value
 424: LOAD_DEREF           self
 426: LOAD_METHOD          _check_value
 448: LOAD_DEREF           action
 450: LOAD_FAST            value
 452: PRECALL              
 456: CALL                 
 466: POP_TOP              
 468: JUMP_FORWARD         to 954
 470: LOAD_GLOBAL          NULL + len
 482: LOAD_FAST            arg_strings
 484: PRECALL              
 488: CALL                 
 498: LOAD_CONST           1
 500: COMPARE_OP           ==
 506: POP_JUMP_FORWARD_IF_FALSE to 638
 508: LOAD_DEREF           action
 510: LOAD_ATTR            nargs
 520: LOAD_CONST           None
 522: LOAD_GLOBAL          OPTIONAL
 534: BUILD_TUPLE          
 536: CONTAINS_OP          
 538: POP_JUMP_FORWARD_IF_FALSE to 638
 540: LOAD_FAST            arg_strings
 542: UNPACK_SEQUENCE      
 546: STORE_FAST           arg_string
 548: LOAD_DEREF           self
 550: LOAD_METHOD          _get_value
 572: LOAD_DEREF           action
 574: LOAD_FAST            arg_string
 576: PRECALL              
 580: CALL                 
 590: STORE_FAST           value
 592: LOAD_DEREF           self
 594: LOAD_METHOD          _check_value
 616: LOAD_DEREF           action
 618: LOAD_FAST            value
 620: PRECALL              
 624: CALL                 
 634: POP_TOP              
 636: JUMP_FORWARD         to 954
 638: LOAD_DEREF           action
 640: LOAD_ATTR            nargs
 650: LOAD_GLOBAL          REMAINDER
 662: COMPARE_OP           ==
 668: POP_JUMP_FORWARD_IF_FALSE to 702
 670: LOAD_CLOSURE         action
 672: LOAD_CLOSURE         self
 674: BUILD_TUPLE          
 676: LOAD_CONST           <code object <listcomp> at 0x00000240693EBE30, file "argparse.py", line 2501>
 678: MAKE_FUNCTION        closure
 680: LOAD_FAST            arg_strings
 682: GET_ITER             
 684: PRECALL              
 688: CALL                 
 698: STORE_FAST           value
 700: JUMP_FORWARD         to 954
 702: LOAD_DEREF           action
 704: LOAD_ATTR            nargs
 714: LOAD_GLOBAL          PARSER
 726: COMPARE_OP           ==
 732: POP_JUMP_FORWARD_IF_FALSE to 822
 734: LOAD_CLOSURE         action
 736: LOAD_CLOSURE         self
 738: BUILD_TUPLE          
 740: LOAD_CONST           <code object <listcomp> at 0x0000024069CC8030, file "argparse.py", line 2505>
 742: MAKE_FUNCTION        closure
 744: LOAD_FAST            arg_strings
 746: GET_ITER             
 748: PRECALL              
 752: CALL                 
 762: STORE_FAST           value
 764: LOAD_DEREF           self
 766: LOAD_METHOD          _check_value
 788: LOAD_DEREF           action
 790: LOAD_FAST            value
 792: LOAD_CONST           0
 794: BINARY_SUBSCR        
 804: PRECALL              
 808: CALL                 
 818: POP_TOP              
 820: JUMP_FORWARD         to 954
 822: LOAD_DEREF           action
 824: LOAD_ATTR            nargs
 834: LOAD_GLOBAL          SUPPRESS
 846: COMPARE_OP           ==
 852: POP_JUMP_FORWARD_IF_FALSE to 870
 854: LOAD_GLOBAL          SUPPRESS
 866: STORE_FAST           value
 868: JUMP_FORWARD         to 954
 870: LOAD_CLOSURE         action
 872: LOAD_CLOSURE         self
 874: BUILD_TUPLE          
 876: LOAD_CONST           <code object <listcomp> at 0x0000024069CC8130, file "argparse.py", line 2514>
 878: MAKE_FUNCTION        closure
 880: LOAD_FAST            arg_strings
 882: GET_ITER             
 884: PRECALL              
 888: CALL                 
 898: STORE_FAST           value
 900: LOAD_FAST            value
 902: GET_ITER             
 904: FOR_ITER             to 954
 906: STORE_FAST           v
 908: LOAD_DEREF           self
 910: LOAD_METHOD          _check_value
 932: LOAD_DEREF           action
 934: LOAD_FAST            v
 936: PRECALL              
 940: CALL                 
 950: POP_TOP              
 952: JUMP_BACKWARD        to 904
 954: LOAD_FAST            value
 956: RETURN_VALUE         
