# Disassembly for argparse.RawTextHelpFormatter
# From module file: argparse

## co_consts:
('RawTextHelpFormatter', 'Help message formatter which retains formatting of all help text.\n\n    Only the name of this class is considered a public API. All the methods\n    provided by the class are considered an implementation detail.\n    ', <code object _split_lines at 0x000002406945D980, file "argparse.py", line 694>, None)

## co_names:
('__name__', '__module__', '__qualname__', '__doc__', '_split_lines')

## bytecode:

   0: RESUME               
   2: LOAD_NAME            __name__
   4: STORE_NAME           __module__
   6: LOAD_CONST           'RawTextHelpFormatter'
   8: STORE_NAME           __qualname__
  10: LOAD_CONST           'Help message formatter which retains formatting of all help text.\n\n    Only the name of this class is considered a public API. All the methods\n    provided by the class are considered an implementation detail.\n    '
  12: STORE_NAME           __doc__
  14: LOAD_CONST           <code object _split_lines at 0x000002406945D980, file "argparse.py", line 694>
  16: MAKE_FUNCTION        
  18: STORE_NAME           _split_lines
  20: LOAD_CONST           None
  22: RETURN_VALUE         
