# Disassembly for argparse.ArgumentParser.exit
# From module file: argparse

## co_consts:
(None,)

## co_names:
('_print_message', '_sys', 'stderr', 'exit')

## bytecode:

   0: RESUME               
   2: LOAD_FAST            message
   4: POP_JUMP_FORWARD_IF_FALSE to 70
   6: LOAD_FAST            self
   8: LOAD_METHOD          _print_message
  30: LOAD_FAST            message
  32: LOAD_GLOBAL          _sys
  44: LOAD_ATTR            stderr
  54: PRECALL              
  58: CALL                 
  68: POP_TOP              
  70: LOAD_GLOBAL          NULL + _sys
  82: LOAD_ATTR            exit
  92: LOAD_FAST            status
  94: PRECALL              
  98: CALL                 
 108: POP_TOP              
 110: LOAD_CONST           None
 112: RETURN_VALUE         
