# Disassembly for argparse._StoreAction.__init__
# From module file: argparse

## co_consts:
(None, 0, 'nargs for store actions must be != 0; if you have nothing to store, actions such as store true or store const may be more appropriate', 'nargs must be %r to supply const', ('option_strings', 'dest', 'nargs', 'const', 'default', 'type', 'choices', 'required', 'help', 'metavar'))

## co_names:
('ValueError', 'OPTIONAL', 'super', '_StoreAction', '__init__')

## bytecode:

   0: COPY_FREE_VARS       
   2: RESUME               
   4: LOAD_FAST            nargs
   6: LOAD_CONST           0
   8: COMPARE_OP           ==
  14: POP_JUMP_FORWARD_IF_FALSE to 46
  16: LOAD_GLOBAL          NULL + ValueError
  28: LOAD_CONST           'nargs for store actions must be != 0; if you have nothing to store, actions such as store true or store const may be more appropriate'
  30: PRECALL              
  34: CALL                 
  44: RAISE_VARARGS        
  46: LOAD_FAST            const
  48: POP_JUMP_FORWARD_IF_NONE to 118
  50: LOAD_FAST            nargs
  52: LOAD_GLOBAL          OPTIONAL
  64: COMPARE_OP           !=
  70: POP_JUMP_FORWARD_IF_FALSE to 118
  72: LOAD_GLOBAL          NULL + ValueError
  84: LOAD_CONST           'nargs must be %r to supply const'
  86: LOAD_GLOBAL          OPTIONAL
  98: BINARY_OP            %
 102: PRECALL              
 106: CALL                 
 116: RAISE_VARARGS        
 118: LOAD_GLOBAL          NULL + super
 130: LOAD_GLOBAL          _StoreAction
 142: LOAD_FAST            self
 144: PRECALL              
 148: CALL                 
 158: LOAD_METHOD          __init__
 180: LOAD_FAST            option_strings
 182: LOAD_FAST            dest
 184: LOAD_FAST            nargs
 186: LOAD_FAST            const
 188: LOAD_FAST            default
 190: LOAD_FAST            type
 192: LOAD_FAST            choices
 194: LOAD_FAST            required
 196: LOAD_FAST            help
 198: LOAD_FAST            metavar
 200: KW_NAMES             
 202: PRECALL              
 206: CALL                 
 216: POP_TOP              
 218: LOAD_CONST           None
 220: RETURN_VALUE         
