# Disassembly for argparse.Action._get_kwargs
# From module file: argparse

## co_consts:
(None, ('option_strings', 'dest', 'nargs', 'const', 'default', 'type', 'choices', 'required', 'help', 'metavar'), <code object <listcomp> at 0x000002406945DA70, file "argparse.py", line 876>)

## co_names:
()

## bytecode:

   0: MAKE_CELL            self
   2: RESUME               
   4: BUILD_LIST           
   6: LOAD_CONST           ('option_strings', 'dest', 'nargs', 'const', 'default', 'type', 'choices', 'required', 'help', 'metavar')
   8: LIST_EXTEND          
  10: STORE_FAST           names
  12: LOAD_CLOSURE         self
  14: BUILD_TUPLE          
  16: LOAD_CONST           <code object <listcomp> at 0x000002406945DA70, file "argparse.py", line 876>
  18: MAKE_FUNCTION        closure
  20: LOAD_FAST            names
  22: GET_ITER             
  24: PRECALL              
  28: CALL                 
  38: RETURN_VALUE         
