# Disassembly for argparse._VersionAction.__init__
# From module file: argparse

## co_consts:
(None, 0, ('option_strings', 'dest', 'default', 'nargs', 'help'))

## co_names:
('super', '_VersionAction', '__init__', 'version')

## bytecode:

   0: COPY_FREE_VARS       
   2: RESUME               
   4: LOAD_GLOBAL          NULL + super
  16: LOAD_GLOBAL          _VersionAction
  28: LOAD_FAST            self
  30: PRECALL              
  34: CALL                 
  44: LOAD_METHOD          __init__
  66: LOAD_FAST            option_strings
  68: LOAD_FAST            dest
  70: LOAD_FAST            default
  72: LOAD_CONST           0
  74: LOAD_FAST            help
  76: KW_NAMES             
  78: PRECALL              
  82: CALL                 
  92: POP_TOP              
  94: LOAD_FAST            version
  96: LOAD_FAST            self
  98: STORE_ATTR           version
 108: LOAD_CONST           None
 110: RETURN_VALUE         
