# Disassembly for argparse._VersionAction
# From module file: argparse

## co_consts:
('_VersionAction', None, "show program's version number and exit", <code object __init__ at 0x00000240693D29C0, file "argparse.py", line 1125>, <code object __call__ at 0x00000240694981F0, file "argparse.py", line 1139>, (None,))

## co_names:
('__name__', '__module__', '__qualname__', 'SUPPRESS', '__init__', '__call__', '__classcell__')

## bytecode:

   0: MAKE_CELL            __class__
   2: RESUME               
   4: LOAD_NAME            __name__
   6: STORE_NAME           __module__
   8: LOAD_CONST           '_VersionAction'
  10: STORE_NAME           __qualname__
  12: LOAD_CONST           None
  14: LOAD_NAME            SUPPRESS
  16: LOAD_NAME            SUPPRESS
  18: LOAD_CONST           "show program's version number and exit"
  20: BUILD_TUPLE          
  22: LOAD_CLOSURE         __class__
  24: BUILD_TUPLE          
  26: LOAD_CONST           <code object __init__ at 0x00000240693D29C0, file "argparse.py", line 1125>
  28: MAKE_FUNCTION        defaults, closure
  30: STORE_NAME           __init__
  32: LOAD_CONST           (None,)
  34: LOAD_CONST           <code object __call__ at 0x00000240694981F0, file "argparse.py", line 1139>
  36: MAKE_FUNCTION        defaults
  38: STORE_NAME           __call__
  40: LOAD_CLOSURE         __class__
  42: COPY                 
  44: STORE_NAME           __classcell__
  46: RETURN_VALUE         
