# Disassembly for argparse.FileType.__call__
# From module file: argparse

## co_consts:
(None, '-', 'r', 'b', <code object <genexpr> at 0x000002406945E3D0, file "argparse.py", line 1288>, 'wax', 'argument "-" with mode %r', ('filename', 'error'), "can't open '%(filename)s': %(error)s")

## co_names:
('_mode', '_sys', 'stdin', 'buffer', 'any', 'stdout', '_', 'ValueError', 'open', '_bufsize', '_encoding', '_errors', 'OSError', 'ArgumentTypeError')

## bytecode:

   0: MAKE_CELL            self
   2: RESUME               
   4: LOAD_FAST            string
   6: LOAD_CONST           '-'
   8: COMPARE_OP           ==
  14: POP_JUMP_FORWARD_IF_FALSE to 316
  16: LOAD_CONST           'r'
  18: LOAD_DEREF           self
  20: LOAD_ATTR            _mode
  30: CONTAINS_OP          
  32: POP_JUMP_FORWARD_IF_FALSE to 110
  34: LOAD_CONST           'b'
  36: LOAD_DEREF           self
  38: LOAD_ATTR            _mode
  48: CONTAINS_OP          
  50: POP_JUMP_FORWARD_IF_FALSE to 86
  52: LOAD_GLOBAL          _sys
  64: LOAD_ATTR            stdin
  74: LOAD_ATTR            buffer
  84: JUMP_FORWARD         to 108
  86: LOAD_GLOBAL          _sys
  98: LOAD_ATTR            stdin
 108: RETURN_VALUE         
 110: LOAD_GLOBAL          NULL + any
 122: LOAD_CLOSURE         self
 124: BUILD_TUPLE          
 126: LOAD_CONST           <code object <genexpr> at 0x000002406945E3D0, file "argparse.py", line 1288>
 128: MAKE_FUNCTION        closure
 130: LOAD_CONST           'wax'
 132: GET_ITER             
 134: PRECALL              
 138: CALL                 
 148: PRECALL              
 152: CALL                 
 162: POP_JUMP_FORWARD_IF_FALSE to 240
 164: LOAD_CONST           'b'
 166: LOAD_DEREF           self
 168: LOAD_ATTR            _mode
 178: CONTAINS_OP          
 180: POP_JUMP_FORWARD_IF_FALSE to 216
 182: LOAD_GLOBAL          _sys
 194: LOAD_ATTR            stdout
 204: LOAD_ATTR            buffer
 214: JUMP_FORWARD         to 238
 216: LOAD_GLOBAL          _sys
 228: LOAD_ATTR            stdout
 238: RETURN_VALUE         
 240: LOAD_GLOBAL          NULL + _
 252: LOAD_CONST           'argument "-" with mode %r'
 254: PRECALL              
 258: CALL                 
 268: LOAD_DEREF           self
 270: LOAD_ATTR            _mode
 280: BINARY_OP            %
 284: STORE_FAST           msg
 286: LOAD_GLOBAL          NULL + ValueError
 298: LOAD_FAST            msg
 300: PRECALL              
 304: CALL                 
 314: RAISE_VARARGS        
 316: NOP                  
 318: LOAD_GLOBAL          NULL + open
 330: LOAD_FAST            string
 332: LOAD_DEREF           self
 334: LOAD_ATTR            _mode
 344: LOAD_DEREF           self
 346: LOAD_ATTR            _bufsize
 356: LOAD_DEREF           self
 358: LOAD_ATTR            _encoding
 368: LOAD_DEREF           self
 370: LOAD_ATTR            _errors
 380: PRECALL              
 384: CALL                 
 394: RETURN_VALUE         
 396: PUSH_EXC_INFO        
 398: LOAD_GLOBAL          OSError
 410: CHECK_EXC_MATCH      
 412: POP_JUMP_FORWARD_IF_FALSE to 500
 414: STORE_FAST           e
 416: LOAD_FAST            string
 418: LOAD_FAST            e
 420: LOAD_CONST           ('filename', 'error')
 422: BUILD_CONST_KEY_MAP  
 424: STORE_FAST           args
 426: LOAD_GLOBAL          NULL + _
 438: LOAD_CONST           "can't open '%(filename)s': %(error)s"
 440: PRECALL              
 444: CALL                 
 454: STORE_FAST           message
 456: LOAD_GLOBAL          NULL + ArgumentTypeError
 468: LOAD_FAST            message
 470: LOAD_FAST            args
 472: BINARY_OP            %
 476: PRECALL              
 480: CALL                 
 490: RAISE_VARARGS        
 492: LOAD_CONST           None
 494: STORE_FAST           e
 496: DELETE_FAST          e
 498: RERAISE              
 500: RERAISE              
 502: COPY                 
 504: POP_EXCEPT           
 506: RERAISE              
