# Disassembly for argparse.ArgumentParser._get_positional_actions.<listcomp>
# From module file: argparse

## co_consts:
()

## co_names:
('option_strings',)

## bytecode:

   0: RESUME               
   2: BUILD_LIST           
   4: LOAD_FAST            .0
   6: FOR_ITER             to 30
   8: STORE_FAST           action
  10: LOAD_FAST            action
  12: LOAD_ATTR            option_strings
  22: POP_JUMP_BACKWARD_IF_TRUE to 6
  24: LOAD_FAST            action
  26: LIST_APPEND          
  28: JUMP_BACKWARD        to 6
  30: RETURN_VALUE         
