# Disassembly for argparse.HelpFormatter._dedent
# From module file: argparse

## co_consts:
(None, 0, 'Indent decreased below 0.', 1)

## co_names:
('_current_indent', '_indent_increment', '_level')

## bytecode:

   0: RESUME               
   2: LOAD_FAST            self
   4: COPY                 
   6: LOAD_ATTR            _current_indent
  16: LOAD_FAST            self
  18: LOAD_ATTR            _indent_increment
  28: BINARY_OP            -=
  32: SWAP                 
  34: STORE_ATTR           _current_indent
  44: LOAD_FAST            self
  46: LOAD_ATTR            _current_indent
  56: LOAD_CONST           0
  58: COMPARE_OP           >=
  64: POP_JUMP_FORWARD_IF_TRUE to 86
  66: LOAD_ASSERTION_ERROR 
  68: LOAD_CONST           'Indent decreased below 0.'
  70: PRECALL              
  74: CALL                 
  84: RAISE_VARARGS        
  86: LOAD_FAST            self
  88: COPY                 
  90: LOAD_ATTR            _level
 100: LOAD_CONST           1
 102: BINARY_OP            -=
 106: SWAP                 
 108: STORE_ATTR           _level
 118: LOAD_CONST           None
 120: RETURN_VALUE         
