# Disassembly for argparse.HelpFormatter._metavar_formatter.format
# From module file: argparse

## co_consts:
(None,)

## co_names:
('isinstance', 'tuple')

## bytecode:

   0: COPY_FREE_VARS       
   2: RESUME               
   4: LOAD_GLOBAL          NULL + isinstance
  16: LOAD_DEREF           result
  18: LOAD_GLOBAL          tuple
  30: PRECALL              
  34: CALL                 
  44: POP_JUMP_FORWARD_IF_FALSE to 50
  46: LOAD_DEREF           result
  48: RETURN_VALUE         
  50: LOAD_DEREF           result
  52: BUILD_TUPLE          
  54: LOAD_FAST            tuple_size
  56: BINARY_OP            *
  60: RETURN_VALUE         
