# Disassembly for argparse.ArgumentParser.parse_known_args
# From module file: argparse

## co_consts:
(None, 1)

## co_names:
('_sys', 'argv', 'list', 'Namespace', '_actions', 'dest', 'SUPPRESS', 'hasattr', 'default', 'setattr', '_defaults', 'exit_on_error', '_parse_known_args', 'ArgumentError', 'error', 'str', '_UNRECOGNIZED_ARGS_ATTR', 'extend', 'getattr', 'delattr')

## bytecode:

   0: RESUME               
   2: LOAD_FAST            args
   4: POP_JUMP_FORWARD_IF_NOT_NONE to 48
   6: LOAD_GLOBAL          _sys
  18: LOAD_ATTR            argv
  28: LOAD_CONST           1
  30: LOAD_CONST           None
  32: BUILD_SLICE          
  34: BINARY_SUBSCR        
  44: STORE_FAST           args
  46: JUMP_FORWARD         to 78
  48: LOAD_GLOBAL          NULL + list
  60: LOAD_FAST            args
  62: PRECALL              
  66: CALL                 
  76: STORE_FAST           args
  78: LOAD_FAST            namespace
  80: POP_JUMP_FORWARD_IF_NOT_NONE to 110
  82: LOAD_GLOBAL          NULL + Namespace
  94: PRECALL              
  98: CALL                 
 108: STORE_FAST           namespace
 110: LOAD_FAST            self
 112: LOAD_ATTR            _actions
 122: GET_ITER             
 124: FOR_ITER             to 282
 126: STORE_FAST           action
 128: LOAD_FAST            action
 130: LOAD_ATTR            dest
 140: LOAD_GLOBAL          SUPPRESS
 152: IS_OP                
 154: POP_JUMP_FORWARD_IF_FALSE to 280
 156: LOAD_GLOBAL          NULL + hasattr
 168: LOAD_FAST            namespace
 170: LOAD_FAST            action
 172: LOAD_ATTR            dest
 182: PRECALL              
 186: CALL                 
 196: POP_JUMP_FORWARD_IF_TRUE to 280
 198: LOAD_FAST            action
 200: LOAD_ATTR            default
 210: LOAD_GLOBAL          SUPPRESS
 222: IS_OP                
 224: POP_JUMP_FORWARD_IF_FALSE to 280
 226: LOAD_GLOBAL          NULL + setattr
 238: LOAD_FAST            namespace
 240: LOAD_FAST            action
 242: LOAD_ATTR            dest
 252: LOAD_FAST            action
 254: LOAD_ATTR            default
 264: PRECALL              
 268: CALL                 
 278: POP_TOP              
 280: JUMP_BACKWARD        to 124
 282: LOAD_FAST            self
 284: LOAD_ATTR            _defaults
 294: GET_ITER             
 296: FOR_ITER             to 390
 298: STORE_FAST           dest
 300: LOAD_GLOBAL          NULL + hasattr
 312: LOAD_FAST            namespace
 314: LOAD_FAST            dest
 316: PRECALL              
 320: CALL                 
 330: POP_JUMP_FORWARD_IF_TRUE to 388
 332: LOAD_GLOBAL          NULL + setattr
 344: LOAD_FAST            namespace
 346: LOAD_FAST            dest
 348: LOAD_FAST            self
 350: LOAD_ATTR            _defaults
 360: LOAD_FAST            dest
 362: BINARY_SUBSCR        
 372: PRECALL              
 376: CALL                 
 386: POP_TOP              
 388: JUMP_BACKWARD        to 296
 390: LOAD_FAST            self
 392: LOAD_ATTR            exit_on_error
 402: POP_JUMP_FORWARD_IF_FALSE to 572
 404: NOP                  
 406: LOAD_FAST            self
 408: LOAD_METHOD          _parse_known_args
 430: LOAD_FAST            args
 432: LOAD_FAST            namespace
 434: PRECALL              
 438: CALL                 
 448: UNPACK_SEQUENCE      
 452: STORE_FAST           namespace
 454: STORE_FAST           args
 456: JUMP_FORWARD         to 622
 458: PUSH_EXC_INFO        
 460: LOAD_GLOBAL          ArgumentError
 472: CHECK_EXC_MATCH      
 474: POP_JUMP_FORWARD_IF_FALSE to 564
 476: STORE_FAST           err
 478: LOAD_FAST            self
 480: LOAD_METHOD          error
 502: LOAD_GLOBAL          NULL + str
 514: LOAD_FAST            err
 516: PRECALL              
 520: CALL                 
 530: PRECALL              
 534: CALL                 
 544: POP_TOP              
 546: POP_EXCEPT           
 548: LOAD_CONST           None
 550: STORE_FAST           err
 552: DELETE_FAST          err
 554: JUMP_FORWARD         to 622
 556: LOAD_CONST           None
 558: STORE_FAST           err
 560: DELETE_FAST          err
 562: RERAISE              
 564: RERAISE              
 566: COPY                 
 568: POP_EXCEPT           
 570: RERAISE              
 572: LOAD_FAST            self
 574: LOAD_METHOD          _parse_known_args
 596: LOAD_FAST            args
 598: LOAD_FAST            namespace
 600: PRECALL              
 604: CALL                 
 614: UNPACK_SEQUENCE      
 618: STORE_FAST           namespace
 620: STORE_FAST           args
 622: LOAD_GLOBAL          NULL + hasattr
 634: LOAD_FAST            namespace
 636: LOAD_GLOBAL          _UNRECOGNIZED_ARGS_ATTR
 648: PRECALL              
 652: CALL                 
 662: POP_JUMP_FORWARD_IF_FALSE to 786
 664: LOAD_FAST            args
 666: LOAD_METHOD          extend
 688: LOAD_GLOBAL          NULL + getattr
 700: LOAD_FAST            namespace
 702: LOAD_GLOBAL          _UNRECOGNIZED_ARGS_ATTR
 714: PRECALL              
 718: CALL                 
 728: PRECALL              
 732: CALL                 
 742: POP_TOP              
 744: LOAD_GLOBAL          NULL + delattr
 756: LOAD_FAST            namespace
 758: LOAD_GLOBAL          _UNRECOGNIZED_ARGS_ATTR
 770: PRECALL              
 774: CALL                 
 784: POP_TOP              
 786: LOAD_FAST            namespace
 788: LOAD_FAST            args
 790: BUILD_TUPLE          
 792: RETURN_VALUE         
