# Disassembly for argparse.Namespace.__init__
# From module file: argparse

## co_consts:
(None,)

## co_names:
('setattr',)

## bytecode:

   0: RESUME               
   2: LOAD_FAST            kwargs
   4: GET_ITER             
   6: FOR_ITER             to 58
   8: STORE_FAST           name
  10: LOAD_GLOBAL          NULL + setattr
  22: LOAD_FAST            self
  24: LOAD_FAST            name
  26: LOAD_FAST            kwargs
  28: LOAD_FAST            name
  30: BINARY_SUBSCR        
  40: PRECALL              
  44: CALL                 
  54: POP_TOP              
  56: JUMP_BACKWARD        to 6
  58: LOAD_CONST           None
  60: RETURN_VALUE         
