# Disassembly for argparse
# From module file: argparse

## co_consts:
("Command-line parsing library\n\nThis module is an optparse-inspired command-line parsing library that:\n\n    - handles both optional and positional arguments\n    - produces highly informative usage messages\n    - supports parsers that dispatch to sub-parsers\n\nThe following is a simple usage example that sums integers from the\ncommand-line and writes the result to a file::\n\n    parser = argparse.ArgumentParser(\n        description='sum the integers at the command line')\n    parser.add_argument(\n        'integers', metavar='int', nargs='+', type=int,\n        help='an integer to be summed')\n    parser.add_argument(\n        '--log', default=sys.stdout, type=argparse.FileType('w'),\n        help='the file where the sum should be written')\n    args = parser.parse_args()\n    args.log.write('%s' % sum(args.integers))\n    args.log.close()\n\nThe module contains the following public classes:\n\n    - ArgumentParser -- The main entry point for command-line parsing. As the\n        example above shows, the add_argument() method is used to populate\n        the parser with actions for optional and positional arguments. Then\n        the parse_args() method is invoked to convert the args at the\n        command-line into an object with attributes.\n\n    - ArgumentError -- The exception raised by ArgumentParser objects when\n        there are errors with the parser's actions. Errors raised while\n        parsing the command-line are caught by ArgumentParser and emitted\n        as command-line messages.\n\n    - FileType -- A factory for defining types of files to be created. As the\n        example above shows, instances of FileType are typically passed as\n        the type= argument of add_argument() calls.\n\n    - Action -- The base class for parser actions. Typically actions are\n        selected by passing strings like 'store_true' or 'append_const' to\n        the action= argument of add_argument(). However, for greater\n        customization of ArgumentParser actions, subclasses of Action may\n        be defined and passed as the action= argument.\n\n    - HelpFormatter, RawDescriptionHelpFormatter, RawTextHelpFormatter,\n        ArgumentDefaultsHelpFormatter -- Formatter classes which\n        may be passed as the formatter_class= argument to the\n        ArgumentParser constructor. HelpFormatter is the default,\n        RawDescriptionHelpFormatter and RawTextHelpFormatter tell the parser\n        not to change the formatting for help text, and\n        ArgumentDefaultsHelpFormatter adds information about argument defaults\n        to the help.\n\nAll other classes in this module are considered implementation details.\n(Also note that HelpFormatter and RawDescriptionHelpFormatter are only\nconsidered public as object names -- the API of the formatter objects is\nstill considered an implementation detail.)\n", '1.1', ('ArgumentParser', 'ArgumentError', 'ArgumentTypeError', 'BooleanOptionalAction', 'FileType', 'HelpFormatter', 'ArgumentDefaultsHelpFormatter', 'RawDescriptionHelpFormatter', 'RawTextHelpFormatter', 'MetavarTypeHelpFormatter', 'Namespace', 'Action', 'ONE_OR_MORE', 'OPTIONAL', 'PARSER', 'REMAINDER', 'SUPPRESS', 'ZERO_OR_MORE'), 0, None, ('gettext', 'ngettext'), '==SUPPRESS==', '?', '*', '+', 'A...', '...', '_unrecognized_args', <code object _AttributeHolder at 0x0000024069465610, file "argparse.py", line 109>, '_AttributeHolder', <code object _copy_items at 0x00000240693A9570, file "argparse.py", line 140>, <code object HelpFormatter at 0x000002406942D160, file "argparse.py", line 157>, 'HelpFormatter', <code object RawDescriptionHelpFormatter at 0x0000024069427EC0, file "argparse.py", line 676>, 'RawDescriptionHelpFormatter', <code object RawTextHelpFormatter at 0x0000024069494030, file "argparse.py", line 687>, 'RawTextHelpFormatter', <code object ArgumentDefaultsHelpFormatter at 0x0000024069494100, file "argparse.py", line 698>, 'ArgumentDefaultsHelpFormatter', <code object MetavarTypeHelpFormatter at 0x0000024069465A70, file "argparse.py", line 727>, 'MetavarTypeHelpFormatter', <code object _get_action_name at 0x00000240691A7D70, file "argparse.py", line 746>, <code object ArgumentError at 0x0000024069465B50, file "argparse.py", line 761>, 'ArgumentError', <code object ArgumentTypeError at 0x00000240694941D0, file "argparse.py", line 781>, 'ArgumentTypeError', <code object Action at 0x00000240693EAE30, file "argparse.py", line 790>, 'Action', <code object BooleanOptionalAction at 0x00000240693EAF30, file "argparse.py", line 885>, 'BooleanOptionalAction', <code object _StoreAction at 0x000002406945DD40, file "argparse.py", line 924>, '_StoreAction', <code object _StoreConstAction at 0x000002406945DE30, file "argparse.py", line 959>, '_StoreConstAction', <code object _StoreTrueAction at 0x0000024069465ED0, file "argparse.py", line 982>, '_StoreTrueAction', <code object _StoreFalseAction at 0x0000024069465FB0, file "argparse.py", line 999>, '_StoreFalseAction', <code object _AppendAction at 0x000002406945DF20, file "argparse.py", line 1016>, '_AppendAction', <code object _AppendConstAction at 0x000002406945E010, file "argparse.py", line 1054>, '_AppendConstAction', <code object _CountAction at 0x000002406945E100, file "argparse.py", line 1081>, '_CountAction', <code object _HelpAction at 0x000002406945E1F0, file "argparse.py", line 1104>, '_HelpAction', <code object _VersionAction at 0x000002406945E2E0, file "argparse.py", line 1123>, '_VersionAction', <code object _SubParsersAction at 0x000002406944A9A0, file "argparse.py", line 1149>, '_SubParsersAction', <code object _ExtendAction at 0x00000240694945E0, file "argparse.py", line 1249>, '_ExtendAction', <code object FileType at 0x00000240694664F0, file "argparse.py", line 1260>, 'FileType', <code object Namespace at 0x00000240694665D0, file "argparse.py", line 1315>, 'Namespace', <code object _ActionsContainer at 0x00000240693AAAB0, file "argparse.py", line 1335>, '_ActionsContainer', <code object _ArgumentGroup at 0x00000240693EB930, file "argparse.py", line 1645>, '_ArgumentGroup', <code object _MutuallyExclusiveGroup at 0x000002406945E880, file "argparse.py", line 1687>, '_MutuallyExclusiveGroup', <code object ArgumentParser at 0x000002406934F120, file "argparse.py", line 1715>, 'ArgumentParser')

## co_names:
('__doc__', '__version__', '__all__', 'os', '_os', 're', '_re', 'sys', '_sys', 'warnings', 'gettext', '_', 'ngettext', 'SUPPRESS', 'OPTIONAL', 'ZERO_OR_MORE', 'ONE_OR_MORE', 'PARSER', 'REMAINDER', '_UNRECOGNIZED_ARGS_ATTR', 'object', '_AttributeHolder', '_copy_items', 'HelpFormatter', 'RawDescriptionHelpFormatter', 'RawTextHelpFormatter', 'ArgumentDefaultsHelpFormatter', 'MetavarTypeHelpFormatter', '_get_action_name', 'Exception', 'ArgumentError', 'ArgumentTypeError', 'Action', 'BooleanOptionalAction', '_StoreAction', '_StoreConstAction', '_StoreTrueAction', '_StoreFalseAction', '_AppendAction', '_AppendConstAction', '_CountAction', '_HelpAction', '_VersionAction', '_SubParsersAction', '_ExtendAction', 'FileType', 'Namespace', '_ActionsContainer', '_ArgumentGroup', '_MutuallyExclusiveGroup', 'ArgumentParser')

## bytecode:

   0: RESUME               
   2: LOAD_CONST           "Command-line parsing library\n\nThis module is an optparse-inspired command-line parsing library that:\n\n    - handles both optional and positional arguments\n    - produces highly informative usage messages\n    - supports parsers that dispatch to sub-parsers\n\nThe following is a simple usage example that sums integers from the\ncommand-line and writes the result to a file::\n\n    parser = argparse.ArgumentParser(\n        description='sum the integers at the command line')\n    parser.add_argument(\n        'integers', metavar='int', nargs='+', type=int,\n        help='an integer to be summed')\n    parser.add_argument(\n        '--log', default=sys.stdout, type=argparse.FileType('w'),\n        help='the file where the sum should be written')\n    args = parser.parse_args()\n    args.log.write('%s' % sum(args.integers))\n    args.log.close()\n\nThe module contains the following public classes:\n\n    - ArgumentParser -- The main entry point for command-line parsing. As the\n        example above shows, the add_argument() method is used to populate\n        the parser with actions for optional and positional arguments. Then\n        the parse_args() method is invoked to convert the args at the\n        command-line into an object with attributes.\n\n    - ArgumentError -- The exception raised by ArgumentParser objects when\n        there are errors with the parser's actions. Errors raised while\n        parsing the command-line are caught by ArgumentParser and emitted\n        as command-line messages.\n\n    - FileType -- A factory for defining types of files to be created. As the\n        example above shows, instances of FileType are typically passed as\n        the type= argument of add_argument() calls.\n\n    - Action -- The base class for parser actions. Typically actions are\n        selected by passing strings like 'store_true' or 'append_const' to\n        the action= argument of add_argument(). However, for greater\n        customization of ArgumentParser actions, subclasses of Action may\n        be defined and passed as the action= argument.\n\n    - HelpFormatter, RawDescriptionHelpFormatter, RawTextHelpFormatter,\n        ArgumentDefaultsHelpFormatter -- Formatter classes which\n        may be passed as the formatter_class= argument to the\n        ArgumentParser constructor. HelpFormatter is the default,\n        RawDescriptionHelpFormatter and RawTextHelpFormatter tell the parser\n        not to change the formatting for help text, and\n        ArgumentDefaultsHelpFormatter adds information about argument defaults\n        to the help.\n\nAll other classes in this module are considered implementation details.\n(Also note that HelpFormatter and RawDescriptionHelpFormatter are only\nconsidered public as object names -- the API of the formatter objects is\nstill considered an implementation detail.)\n"
   4: STORE_NAME           __doc__
   6: LOAD_CONST           '1.1'
   8: STORE_NAME           __version__
  10: BUILD_LIST           
  12: LOAD_CONST           ('ArgumentParser', 'ArgumentError', 'ArgumentTypeError', 'BooleanOptionalAction', 'FileType', 'HelpFormatter', 'ArgumentDefaultsHelpFormatter', 'RawDescriptionHelpFormatter', 'RawTextHelpFormatter', 'MetavarTypeHelpFormatter', 'Namespace', 'Action', 'ONE_OR_MORE', 'OPTIONAL', 'PARSER', 'REMAINDER', 'SUPPRESS', 'ZERO_OR_MORE')
  14: LIST_EXTEND          
  16: STORE_NAME           __all__
  18: LOAD_CONST           0
  20: LOAD_CONST           None
  22: IMPORT_NAME          os
  24: STORE_NAME           _os
  26: LOAD_CONST           0
  28: LOAD_CONST           None
  30: IMPORT_NAME          re
  32: STORE_NAME           _re
  34: LOAD_CONST           0
  36: LOAD_CONST           None
  38: IMPORT_NAME          sys
  40: STORE_NAME           _sys
  42: LOAD_CONST           0
  44: LOAD_CONST           None
  46: IMPORT_NAME          warnings
  48: STORE_NAME           warnings
  50: LOAD_CONST           0
  52: LOAD_CONST           ('gettext', 'ngettext')
  54: IMPORT_NAME          gettext
  56: IMPORT_FROM          gettext
  58: STORE_NAME           _
  60: IMPORT_FROM          ngettext
  62: STORE_NAME           ngettext
  64: POP_TOP              
  66: LOAD_CONST           '==SUPPRESS=='
  68: STORE_NAME           SUPPRESS
  70: LOAD_CONST           '?'
  72: STORE_NAME           OPTIONAL
  74: LOAD_CONST           '*'
  76: STORE_NAME           ZERO_OR_MORE
  78: LOAD_CONST           '+'
  80: STORE_NAME           ONE_OR_MORE
  82: LOAD_CONST           'A...'
  84: STORE_NAME           PARSER
  86: LOAD_CONST           '...'
  88: STORE_NAME           REMAINDER
  90: LOAD_CONST           '_unrecognized_args'
  92: STORE_NAME           _UNRECOGNIZED_ARGS_ATTR
  94: PUSH_NULL            
  96: LOAD_BUILD_CLASS     
  98: LOAD_CONST           <code object _AttributeHolder at 0x0000024069465610, file "argparse.py", line 109>
 100: MAKE_FUNCTION        
 102: LOAD_CONST           '_AttributeHolder'
 104: LOAD_NAME            object
 106: PRECALL              
 110: CALL                 
 120: STORE_NAME           _AttributeHolder
 122: LOAD_CONST           <code object _copy_items at 0x00000240693A9570, file "argparse.py", line 140>
 124: MAKE_FUNCTION        
 126: STORE_NAME           _copy_items
 128: PUSH_NULL            
 130: LOAD_BUILD_CLASS     
 132: LOAD_CONST           <code object HelpFormatter at 0x000002406942D160, file "argparse.py", line 157>
 134: MAKE_FUNCTION        
 136: LOAD_CONST           'HelpFormatter'
 138: LOAD_NAME            object
 140: PRECALL              
 144: CALL                 
 154: STORE_NAME           HelpFormatter
 156: PUSH_NULL            
 158: LOAD_BUILD_CLASS     
 160: LOAD_CONST           <code object RawDescriptionHelpFormatter at 0x0000024069427EC0, file "argparse.py", line 676>
 162: MAKE_FUNCTION        
 164: LOAD_CONST           'RawDescriptionHelpFormatter'
 166: LOAD_NAME            HelpFormatter
 168: PRECALL              
 172: CALL                 
 182: STORE_NAME           RawDescriptionHelpFormatter
 184: PUSH_NULL            
 186: LOAD_BUILD_CLASS     
 188: LOAD_CONST           <code object RawTextHelpFormatter at 0x0000024069494030, file "argparse.py", line 687>
 190: MAKE_FUNCTION        
 192: LOAD_CONST           'RawTextHelpFormatter'
 194: LOAD_NAME            RawDescriptionHelpFormatter
 196: PRECALL              
 200: CALL                 
 210: STORE_NAME           RawTextHelpFormatter
 212: PUSH_NULL            
 214: LOAD_BUILD_CLASS     
 216: LOAD_CONST           <code object ArgumentDefaultsHelpFormatter at 0x0000024069494100, file "argparse.py", line 698>
 218: MAKE_FUNCTION        
 220: LOAD_CONST           'ArgumentDefaultsHelpFormatter'
 222: LOAD_NAME            HelpFormatter
 224: PRECALL              
 228: CALL                 
 238: STORE_NAME           ArgumentDefaultsHelpFormatter
 240: PUSH_NULL            
 242: LOAD_BUILD_CLASS     
 244: LOAD_CONST           <code object MetavarTypeHelpFormatter at 0x0000024069465A70, file "argparse.py", line 727>
 246: MAKE_FUNCTION        
 248: LOAD_CONST           'MetavarTypeHelpFormatter'
 250: LOAD_NAME            HelpFormatter
 252: PRECALL              
 256: CALL                 
 266: STORE_NAME           MetavarTypeHelpFormatter
 268: LOAD_CONST           <code object _get_action_name at 0x00000240691A7D70, file "argparse.py", line 746>
 270: MAKE_FUNCTION        
 272: STORE_NAME           _get_action_name
 274: PUSH_NULL            
 276: LOAD_BUILD_CLASS     
 278: LOAD_CONST           <code object ArgumentError at 0x0000024069465B50, file "argparse.py", line 761>
 280: MAKE_FUNCTION        
 282: LOAD_CONST           'ArgumentError'
 284: LOAD_NAME            Exception
 286: PRECALL              
 290: CALL                 
 300: STORE_NAME           ArgumentError
 302: PUSH_NULL            
 304: LOAD_BUILD_CLASS     
 306: LOAD_CONST           <code object ArgumentTypeError at 0x00000240694941D0, file "argparse.py", line 781>
 308: MAKE_FUNCTION        
 310: LOAD_CONST           'ArgumentTypeError'
 312: LOAD_NAME            Exception
 314: PRECALL              
 318: CALL                 
 328: STORE_NAME           ArgumentTypeError
 330: PUSH_NULL            
 332: LOAD_BUILD_CLASS     
 334: LOAD_CONST           <code object Action at 0x00000240693EAE30, file "argparse.py", line 790>
 336: MAKE_FUNCTION        
 338: LOAD_CONST           'Action'
 340: LOAD_NAME            _AttributeHolder
 342: PRECALL              
 346: CALL                 
 356: STORE_NAME           Action
 358: PUSH_NULL            
 360: LOAD_BUILD_CLASS     
 362: LOAD_CONST           <code object BooleanOptionalAction at 0x00000240693EAF30, file "argparse.py", line 885>
 364: MAKE_FUNCTION        
 366: LOAD_CONST           'BooleanOptionalAction'
 368: LOAD_NAME            Action
 370: PRECALL              
 374: CALL                 
 384: STORE_NAME           BooleanOptionalAction
 386: PUSH_NULL            
 388: LOAD_BUILD_CLASS     
 390: LOAD_CONST           <code object _StoreAction at 0x000002406945DD40, file "argparse.py", line 924>
 392: MAKE_FUNCTION        
 394: LOAD_CONST           '_StoreAction'
 396: LOAD_NAME            Action
 398: PRECALL              
 402: CALL                 
 412: STORE_NAME           _StoreAction
 414: PUSH_NULL            
 416: LOAD_BUILD_CLASS     
 418: LOAD_CONST           <code object _StoreConstAction at 0x000002406945DE30, file "argparse.py", line 959>
 420: MAKE_FUNCTION        
 422: LOAD_CONST           '_StoreConstAction'
 424: LOAD_NAME            Action
 426: PRECALL              
 430: CALL                 
 440: STORE_NAME           _StoreConstAction
 442: PUSH_NULL            
 444: LOAD_BUILD_CLASS     
 446: LOAD_CONST           <code object _StoreTrueAction at 0x0000024069465ED0, file "argparse.py", line 982>
 448: MAKE_FUNCTION        
 450: LOAD_CONST           '_StoreTrueAction'
 452: LOAD_NAME            _StoreConstAction
 454: PRECALL              
 458: CALL                 
 468: STORE_NAME           _StoreTrueAction
 470: PUSH_NULL            
 472: LOAD_BUILD_CLASS     
 474: LOAD_CONST           <code object _StoreFalseAction at 0x0000024069465FB0, file "argparse.py", line 999>
 476: MAKE_FUNCTION        
 478: LOAD_CONST           '_StoreFalseAction'
 480: LOAD_NAME            _StoreConstAction
 482: PRECALL              
 486: CALL                 
 496: STORE_NAME           _StoreFalseAction
 498: PUSH_NULL            
 500: LOAD_BUILD_CLASS     
 502: LOAD_CONST           <code object _AppendAction at 0x000002406945DF20, file "argparse.py", line 1016>
 504: MAKE_FUNCTION        
 506: LOAD_CONST           '_AppendAction'
 508: LOAD_NAME            Action
 510: PRECALL              
 514: CALL                 
 524: STORE_NAME           _AppendAction
 526: PUSH_NULL            
 528: LOAD_BUILD_CLASS     
 530: LOAD_CONST           <code object _AppendConstAction at 0x000002406945E010, file "argparse.py", line 1054>
 532: MAKE_FUNCTION        
 534: LOAD_CONST           '_AppendConstAction'
 536: LOAD_NAME            Action
 538: PRECALL              
 542: CALL                 
 552: STORE_NAME           _AppendConstAction
 554: PUSH_NULL            
 556: LOAD_BUILD_CLASS     
 558: LOAD_CONST           <code object _CountAction at 0x000002406945E100, file "argparse.py", line 1081>
 560: MAKE_FUNCTION        
 562: LOAD_CONST           '_CountAction'
 564: LOAD_NAME            Action
 566: PRECALL              
 570: CALL                 
 580: STORE_NAME           _CountAction
 582: PUSH_NULL            
 584: LOAD_BUILD_CLASS     
 586: LOAD_CONST           <code object _HelpAction at 0x000002406945E1F0, file "argparse.py", line 1104>
 588: MAKE_FUNCTION        
 590: LOAD_CONST           '_HelpAction'
 592: LOAD_NAME            Action
 594: PRECALL              
 598: CALL                 
 608: STORE_NAME           _HelpAction
 610: PUSH_NULL            
 612: LOAD_BUILD_CLASS     
 614: LOAD_CONST           <code object _VersionAction at 0x000002406945E2E0, file "argparse.py", line 1123>
 616: MAKE_FUNCTION        
 618: LOAD_CONST           '_VersionAction'
 620: LOAD_NAME            Action
 622: PRECALL              
 626: CALL                 
 636: STORE_NAME           _VersionAction
 638: PUSH_NULL            
 640: LOAD_BUILD_CLASS     
 642: LOAD_CONST           <code object _SubParsersAction at 0x000002406944A9A0, file "argparse.py", line 1149>
 644: MAKE_FUNCTION        
 646: LOAD_CONST           '_SubParsersAction'
 648: LOAD_NAME            Action
 650: PRECALL              
 654: CALL                 
 664: STORE_NAME           _SubParsersAction
 666: PUSH_NULL            
 668: LOAD_BUILD_CLASS     
 670: LOAD_CONST           <code object _ExtendAction at 0x00000240694945E0, file "argparse.py", line 1249>
 672: MAKE_FUNCTION        
 674: LOAD_CONST           '_ExtendAction'
 676: LOAD_NAME            _AppendAction
 678: PRECALL              
 682: CALL                 
 692: STORE_NAME           _ExtendAction
 694: PUSH_NULL            
 696: LOAD_BUILD_CLASS     
 698: LOAD_CONST           <code object FileType at 0x00000240694664F0, file "argparse.py", line 1260>
 700: MAKE_FUNCTION        
 702: LOAD_CONST           'FileType'
 704: LOAD_NAME            object
 706: PRECALL              
 710: CALL                 
 720: STORE_NAME           FileType
 722: PUSH_NULL            
 724: LOAD_BUILD_CLASS     
 726: LOAD_CONST           <code object Namespace at 0x00000240694665D0, file "argparse.py", line 1315>
 728: MAKE_FUNCTION        
 730: LOAD_CONST           'Namespace'
 732: LOAD_NAME            _AttributeHolder
 734: PRECALL              
 738: CALL                 
 748: STORE_NAME           Namespace
 750: PUSH_NULL            
 752: LOAD_BUILD_CLASS     
 754: LOAD_CONST           <code object _ActionsContainer at 0x00000240693AAAB0, file "argparse.py", line 1335>
 756: MAKE_FUNCTION        
 758: LOAD_CONST           '_ActionsContainer'
 760: LOAD_NAME            object
 762: PRECALL              
 766: CALL                 
 776: STORE_NAME           _ActionsContainer
 778: PUSH_NULL            
 780: LOAD_BUILD_CLASS     
 782: LOAD_CONST           <code object _ArgumentGroup at 0x00000240693EB930, file "argparse.py", line 1645>
 784: MAKE_FUNCTION        
 786: LOAD_CONST           '_ArgumentGroup'
 788: LOAD_NAME            _ActionsContainer
 790: PRECALL              
 794: CALL                 
 804: STORE_NAME           _ArgumentGroup
 806: PUSH_NULL            
 808: LOAD_BUILD_CLASS     
 810: LOAD_CONST           <code object _MutuallyExclusiveGroup at 0x000002406945E880, file "argparse.py", line 1687>
 812: MAKE_FUNCTION        
 814: LOAD_CONST           '_MutuallyExclusiveGroup'
 816: LOAD_NAME            _ArgumentGroup
 818: PRECALL              
 822: CALL                 
 832: STORE_NAME           _MutuallyExclusiveGroup
 834: PUSH_NULL            
 836: LOAD_BUILD_CLASS     
 838: LOAD_CONST           <code object ArgumentParser at 0x000002406934F120, file "argparse.py", line 1715>
 840: MAKE_FUNCTION        
 842: LOAD_CONST           'ArgumentParser'
 844: LOAD_NAME            _AttributeHolder
 846: LOAD_NAME            _ActionsContainer
 848: PRECALL              
 852: CALL                 
 862: STORE_NAME           ArgumentParser
 864: LOAD_CONST           None
 866: RETURN_VALUE         
