# Disassembly for argparse._SubParsersAction.__init__
# From module file: argparse

## co_consts:
(None, ('option_strings', 'dest', 'nargs', 'choices', 'required', 'help', 'metavar'))

## co_names:
('_prog_prefix', '_parser_class', '_name_parser_map', '_choices_actions', 'super', '_SubParsersAction', '__init__', 'PARSER')

## bytecode:

   0: COPY_FREE_VARS       
   2: RESUME               
   4: LOAD_FAST            prog
   6: LOAD_FAST            self
   8: STORE_ATTR           _prog_prefix
  18: LOAD_FAST            parser_class
  20: LOAD_FAST            self
  22: STORE_ATTR           _parser_class
  32: BUILD_MAP            
  34: LOAD_FAST            self
  36: STORE_ATTR           _name_parser_map
  46: BUILD_LIST           
  48: LOAD_FAST            self
  50: STORE_ATTR           _choices_actions
  60: LOAD_GLOBAL          NULL + super
  72: LOAD_GLOBAL          _SubParsersAction
  84: LOAD_FAST            self
  86: PRECALL              
  90: CALL                 
 100: LOAD_METHOD          __init__
 122: LOAD_FAST            option_strings
 124: LOAD_FAST            dest
 126: LOAD_GLOBAL          PARSER
 138: LOAD_FAST            self
 140: LOAD_ATTR            _name_parser_map
 150: LOAD_FAST            required
 152: LOAD_FAST            help
 154: LOAD_FAST            metavar
 156: KW_NAMES             
 158: PRECALL              
 162: CALL                 
 172: POP_TOP              
 174: LOAD_CONST           None
 176: RETURN_VALUE         
