# Disassembly for argparse._copy_items
# From module file: argparse

## co_consts:
(None, 0)

## co_names:
('type', 'list', 'copy')

## bytecode:

   0: RESUME               
   2: LOAD_FAST            items
   4: POP_JUMP_FORWARD_IF_NOT_NONE to 10
   6: BUILD_LIST           
   8: RETURN_VALUE         
  10: LOAD_GLOBAL          NULL + type
  22: LOAD_FAST            items
  24: PRECALL              
  28: CALL                 
  38: LOAD_GLOBAL          list
  50: IS_OP                
  52: POP_JUMP_FORWARD_IF_FALSE to 74
  54: LOAD_FAST            items
  56: LOAD_CONST           None
  58: LOAD_CONST           None
  60: BUILD_SLICE          
  62: BINARY_SUBSCR        
  72: RETURN_VALUE         
  74: LOAD_CONST           0
  76: LOAD_CONST           None
  78: IMPORT_NAME          copy
  80: STORE_FAST           copy
  82: LOAD_FAST            copy
  84: LOAD_METHOD          copy
 106: LOAD_FAST            items
 108: PRECALL              
 112: CALL                 
 122: RETURN_VALUE         
