# Disassembly for argparse.ArgumentParser.parse_args
# From module file: argparse

## co_consts:
(None, 'unrecognized arguments: %s', ' ')

## co_names:
('parse_known_args', '_', 'error', 'join')

## bytecode:

   0: RESUME               
   2: LOAD_FAST            self
   4: LOAD_METHOD          parse_known_args
  26: LOAD_FAST            args
  28: LOAD_FAST            namespace
  30: PRECALL              
  34: CALL                 
  44: UNPACK_SEQUENCE      
  48: STORE_FAST           args
  50: STORE_FAST           argv
  52: LOAD_FAST            argv
  54: POP_JUMP_FORWARD_IF_FALSE to 172
  56: LOAD_GLOBAL          NULL + _
  68: LOAD_CONST           'unrecognized arguments: %s'
  70: PRECALL              
  74: CALL                 
  84: STORE_FAST           msg
  86: LOAD_FAST            self
  88: LOAD_METHOD          error
 110: LOAD_FAST            msg
 112: LOAD_CONST           ' '
 114: LOAD_METHOD          join
 136: LOAD_FAST            argv
 138: PRECALL              
 142: CALL                 
 152: BINARY_OP            %
 156: PRECALL              
 160: CALL                 
 170: POP_TOP              
 172: LOAD_FAST            args
 174: RETURN_VALUE         
