# Disassembly for argparse.MetavarTypeHelpFormatter
# From module file: argparse

## co_consts:
('MetavarTypeHelpFormatter', "Help message formatter which uses the argument 'type' as the default\n    metavar value (instead of the argument 'dest')\n\n    Only the name of this class is considered a public API. All the methods\n    provided by the class are considered an implementation detail.\n    ", <code object _get_default_metavar_for_optional at 0x00000240694658B0, file "argparse.py", line 735>, <code object _get_default_metavar_for_positional at 0x0000024069465990, file "argparse.py", line 738>, None)

## co_names:
('__name__', '__module__', '__qualname__', '__doc__', '_get_default_metavar_for_optional', '_get_default_metavar_for_positional')

## bytecode:

   0: RESUME               
   2: LOAD_NAME            __name__
   4: STORE_NAME           __module__
   6: LOAD_CONST           'MetavarTypeHelpFormatter'
   8: STORE_NAME           __qualname__
  10: LOAD_CONST           "Help message formatter which uses the argument 'type' as the default\n    metavar value (instead of the argument 'dest')\n\n    Only the name of this class is considered a public API. All the methods\n    provided by the class are considered an implementation detail.\n    "
  12: STORE_NAME           __doc__
  14: LOAD_CONST           <code object _get_default_metavar_for_optional at 0x00000240694658B0, file "argparse.py", line 735>
  16: MAKE_FUNCTION        
  18: STORE_NAME           _get_default_metavar_for_optional
  20: LOAD_CONST           <code object _get_default_metavar_for_positional at 0x0000024069465990, file "argparse.py", line 738>
  22: MAKE_FUNCTION        
  24: STORE_NAME           _get_default_metavar_for_positional
  26: LOAD_CONST           None
  28: RETURN_VALUE         
