# Disassembly for argparse.ArgumentParser._parse_known_args.consume_optional
# From module file: argparse

## co_consts:
(None, True, 1, 'A', 0, '', 'ignored explicit argument %r')

## co_names:
('_match_argument', 'append', 'prefix_chars', '_option_string_actions', '_', 'ArgumentError')

## bytecode:

   0: COPY_FREE_VARS       
   2: RESUME               
   4: LOAD_DEREF           option_string_indices
   6: LOAD_FAST            start_index
   8: BINARY_SUBSCR        
  18: STORE_FAST           option_tuple
  20: LOAD_FAST            option_tuple
  22: UNPACK_SEQUENCE      
  26: STORE_FAST           action
  28: STORE_FAST           option_string
  30: STORE_FAST           explicit_arg
  32: LOAD_DEREF           self
  34: LOAD_ATTR            _match_argument
  44: STORE_FAST           match_argument
  46: BUILD_LIST           
  48: STORE_FAST           action_tuples
  50: NOP                  
  52: LOAD_FAST            action
  54: POP_JUMP_FORWARD_IF_NOT_NONE to 120
  56: LOAD_DEREF           extras
  58: LOAD_METHOD          append
  80: LOAD_DEREF           arg_strings
  82: LOAD_FAST            start_index
  84: BINARY_SUBSCR        
  94: PRECALL              
  98: CALL                 
 108: POP_TOP              
 110: LOAD_FAST            start_index
 112: LOAD_CONST           1
 114: BINARY_OP            +
 118: RETURN_VALUE         
 120: LOAD_FAST            explicit_arg
 122: POP_JUMP_FORWARD_IF_NONE to 574
 124: PUSH_NULL            
 126: LOAD_FAST            match_argument
 128: LOAD_FAST            action
 130: LOAD_CONST           'A'
 132: PRECALL              
 136: CALL                 
 146: STORE_FAST           arg_count
 148: LOAD_DEREF           self
 150: LOAD_ATTR            prefix_chars
 160: STORE_FAST           chars
 162: LOAD_FAST            arg_count
 164: LOAD_CONST           0
 166: COMPARE_OP           ==
 172: POP_JUMP_FORWARD_IF_FALSE to 428
 174: LOAD_FAST            option_string
 176: LOAD_CONST           1
 178: BINARY_SUBSCR        
 188: LOAD_FAST            chars
 190: CONTAINS_OP          
 192: POP_JUMP_FORWARD_IF_FALSE to 428
 194: LOAD_FAST            explicit_arg
 196: LOAD_CONST           ''
 198: COMPARE_OP           !=
 204: POP_JUMP_FORWARD_IF_FALSE to 428
 206: LOAD_FAST            action_tuples
 208: LOAD_METHOD          append
 230: LOAD_FAST            action
 232: BUILD_LIST           
 234: LOAD_FAST            option_string
 236: BUILD_TUPLE          
 238: PRECALL              
 242: CALL                 
 252: POP_TOP              
 254: LOAD_FAST            option_string
 256: LOAD_CONST           0
 258: BINARY_SUBSCR        
 268: STORE_FAST           char
 270: LOAD_FAST            char
 272: LOAD_FAST            explicit_arg
 274: LOAD_CONST           0
 276: BINARY_SUBSCR        
 286: BINARY_OP            +
 290: STORE_FAST           option_string
 292: LOAD_FAST            explicit_arg
 294: LOAD_CONST           1
 296: LOAD_CONST           None
 298: BUILD_SLICE          
 300: BINARY_SUBSCR        
 310: JUMP_IF_TRUE_OR_POP  to 314
 312: LOAD_CONST           None
 314: STORE_FAST           new_explicit_arg
 316: LOAD_DEREF           self
 318: LOAD_ATTR            _option_string_actions
 328: STORE_FAST           optionals_map
 330: LOAD_FAST            option_string
 332: LOAD_FAST            optionals_map
 334: CONTAINS_OP          
 336: POP_JUMP_FORWARD_IF_FALSE to 360
 338: LOAD_FAST            optionals_map
 340: LOAD_FAST            option_string
 342: BINARY_SUBSCR        
 352: STORE_FAST           action
 354: LOAD_FAST            new_explicit_arg
 356: STORE_FAST           explicit_arg
 358: JUMP_FORWARD         to 708
 360: LOAD_GLOBAL          NULL + _
 372: LOAD_CONST           'ignored explicit argument %r'
 374: PRECALL              
 378: CALL                 
 388: STORE_FAST           msg
 390: LOAD_GLOBAL          NULL + ArgumentError
 402: LOAD_FAST            action
 404: LOAD_FAST            msg
 406: LOAD_FAST            explicit_arg
 408: BINARY_OP            %
 412: PRECALL              
 416: CALL                 
 426: RAISE_VARARGS        
 428: LOAD_FAST            arg_count
 430: LOAD_CONST           1
 432: COMPARE_OP           ==
 438: POP_JUMP_FORWARD_IF_FALSE to 506
 440: LOAD_FAST            start_index
 442: LOAD_CONST           1
 444: BINARY_OP            +
 448: STORE_FAST           stop
 450: LOAD_FAST            explicit_arg
 452: BUILD_LIST           
 454: STORE_FAST           args
 456: LOAD_FAST            action_tuples
 458: LOAD_METHOD          append
 480: LOAD_FAST            action
 482: LOAD_FAST            args
 484: LOAD_FAST            option_string
 486: BUILD_TUPLE          
 488: PRECALL              
 492: CALL                 
 502: POP_TOP              
 504: JUMP_FORWARD         to 712
 506: LOAD_GLOBAL          NULL + _
 518: LOAD_CONST           'ignored explicit argument %r'
 520: PRECALL              
 524: CALL                 
 534: STORE_FAST           msg
 536: LOAD_GLOBAL          NULL + ArgumentError
 548: LOAD_FAST            action
 550: LOAD_FAST            msg
 552: LOAD_FAST            explicit_arg
 554: BINARY_OP            %
 558: PRECALL              
 562: CALL                 
 572: RAISE_VARARGS        
 574: LOAD_FAST            start_index
 576: LOAD_CONST           1
 578: BINARY_OP            +
 582: STORE_FAST           start
 584: LOAD_DEREF           arg_strings_pattern
 586: LOAD_FAST            start
 588: LOAD_CONST           None
 590: BUILD_SLICE          
 592: BINARY_SUBSCR        
 602: STORE_FAST           selected_patterns
 604: PUSH_NULL            
 606: LOAD_FAST            match_argument
 608: LOAD_FAST            action
 610: LOAD_FAST            selected_patterns
 612: PRECALL              
 616: CALL                 
 626: STORE_FAST           arg_count
 628: LOAD_FAST            start
 630: LOAD_FAST            arg_count
 632: BINARY_OP            +
 636: STORE_FAST           stop
 638: LOAD_DEREF           arg_strings
 640: LOAD_FAST            start
 642: LOAD_FAST            stop
 644: BUILD_SLICE          
 646: BINARY_SUBSCR        
 656: STORE_FAST           args
 658: LOAD_FAST            action_tuples
 660: LOAD_METHOD          append
 682: LOAD_FAST            action
 684: LOAD_FAST            args
 686: LOAD_FAST            option_string
 688: BUILD_TUPLE          
 690: PRECALL              
 694: CALL                 
 704: POP_TOP              
 706: JUMP_FORWARD         to 712
 708: EXTENDED_ARG         
 710: JUMP_BACKWARD        to 52
 712: LOAD_FAST            action_tuples
 714: POP_JUMP_FORWARD_IF_TRUE to 720
 716: LOAD_ASSERTION_ERROR 
 718: RAISE_VARARGS        
 720: LOAD_FAST            action_tuples
 722: GET_ITER             
 724: FOR_ITER             to 764
 726: UNPACK_SEQUENCE      
 730: STORE_FAST           action
 732: STORE_FAST           args
 734: STORE_FAST           option_string
 736: PUSH_NULL            
 738: LOAD_DEREF           take_action
 740: LOAD_FAST            action
 742: LOAD_FAST            args
 744: LOAD_FAST            option_string
 746: PRECALL              
 750: CALL                 
 760: POP_TOP              
 762: JUMP_BACKWARD        to 724
 764: LOAD_FAST            stop
 766: RETURN_VALUE         
