# Disassembly for argparse.ArgumentParser.print_usage
# From module file: argparse

## co_consts:
(None,)

## co_names:
('_sys', 'stdout', '_print_message', 'format_usage')

## bytecode:

   0: RESUME               
   2: LOAD_FAST            file
   4: POP_JUMP_FORWARD_IF_NOT_NONE to 30
   6: LOAD_GLOBAL          _sys
  18: LOAD_ATTR            stdout
  28: STORE_FAST           file
  30: LOAD_FAST            self
  32: LOAD_METHOD          _print_message
  54: LOAD_FAST            self
  56: LOAD_METHOD          format_usage
  78: PRECALL              
  82: CALL                 
  92: LOAD_FAST            file
  94: PRECALL              
  98: CALL                 
 108: POP_TOP              
 110: LOAD_CONST           None
 112: RETURN_VALUE         
