# Disassembly for argparse.ArgumentTypeError
# From module file: argparse

## co_consts:
('ArgumentTypeError', 'An error from trying to convert a command line string to a type.', None)

## co_names:
('__name__', '__module__', '__qualname__', '__doc__')

## bytecode:

   0: RESUME               
   2: LOAD_NAME            __name__
   4: STORE_NAME           __module__
   6: LOAD_CONST           'ArgumentTypeError'
   8: STORE_NAME           __qualname__
  10: LOAD_CONST           'An error from trying to convert a command line string to a type.'
  12: STORE_NAME           __doc__
  14: LOAD_CONST           None
  16: RETURN_VALUE         
