# Disassembly for email.LocalPart.value
# From module file: email._header_value_parser

## co_consts:
(None, 0, 'quoted-string')

## co_names:
('token_type', 'quoted_value', 'value')

## bytecode:

   0: RESUME               
   2: LOAD_FAST            self
   4: LOAD_CONST           0
   6: BINARY_SUBSCR        
  16: LOAD_ATTR            token_type
  26: LOAD_CONST           'quoted-string'
  28: COMPARE_OP           ==
  34: POP_JUMP_FORWARD_IF_FALSE to 62
  36: LOAD_FAST            self
  38: LOAD_CONST           0
  40: BINARY_SUBSCR        
  50: LOAD_ATTR            quoted_value
  60: RETURN_VALUE         
  62: LOAD_FAST            self
  64: LOAD_CONST           0
  66: BINARY_SUBSCR        
  76: LOAD_ATTR            value
  86: RETURN_VALUE         
