# Disassembly for email.MIMEVersionHeader
# From module file: email.headerregistry

## co_consts:
('MIMEVersionHeader', 1, <code object parse at 0x000002406931FA30, file "email\headerregistry.py", line 408>, <code object init at 0x000002406942E290, file "email\headerregistry.py", line 420>, <code object major at 0x0000024069494920, file "email\headerregistry.py", line 426>, <code object minor at 0x0000024069494030, file "email\headerregistry.py", line 430>, <code object version at 0x0000024069494100, file "email\headerregistry.py", line 434>)

## co_names:
('__name__', '__module__', '__qualname__', 'max_count', 'staticmethod', 'parser', 'parse_mime_version', 'value_parser', 'classmethod', 'parse', 'init', 'property', 'major', 'minor', 'version', '__classcell__')

## bytecode:

   0: MAKE_CELL            __class__
   2: RESUME               
   4: LOAD_NAME            __name__
   6: STORE_NAME           __module__
   8: LOAD_CONST           'MIMEVersionHeader'
  10: STORE_NAME           __qualname__
  12: LOAD_CONST           1
  14: STORE_NAME           max_count
  16: PUSH_NULL            
  18: LOAD_NAME            staticmethod
  20: LOAD_NAME            parser
  22: LOAD_ATTR            parse_mime_version
  32: PRECALL              
  36: CALL                 
  46: STORE_NAME           value_parser
  48: LOAD_NAME            classmethod
  50: LOAD_CONST           <code object parse at 0x000002406931FA30, file "email\headerregistry.py", line 408>
  52: MAKE_FUNCTION        
  54: PRECALL              
  58: CALL                 
  68: STORE_NAME           parse
  70: LOAD_CLOSURE         __class__
  72: BUILD_TUPLE          
  74: LOAD_CONST           <code object init at 0x000002406942E290, file "email\headerregistry.py", line 420>
  76: MAKE_FUNCTION        closure
  78: STORE_NAME           init
  80: LOAD_NAME            property
  82: LOAD_CONST           <code object major at 0x0000024069494920, file "email\headerregistry.py", line 426>
  84: MAKE_FUNCTION        
  86: PRECALL              
  90: CALL                 
 100: STORE_NAME           major
 102: LOAD_NAME            property
 104: LOAD_CONST           <code object minor at 0x0000024069494030, file "email\headerregistry.py", line 430>
 106: MAKE_FUNCTION        
 108: PRECALL              
 112: CALL                 
 122: STORE_NAME           minor
 124: LOAD_NAME            property
 126: LOAD_CONST           <code object version at 0x0000024069494100, file "email\headerregistry.py", line 434>
 128: MAKE_FUNCTION        
 130: PRECALL              
 134: CALL                 
 144: STORE_NAME           version
 146: LOAD_CLOSURE         __class__
 148: COPY                 
 150: STORE_NAME           __classcell__
 152: RETURN_VALUE         
