# Disassembly for email.WhiteSpaceTokenList
# From module file: email._header_value_parser

## co_consts:
('WhiteSpaceTokenList', <code object value at 0x000002406943B0F0, file "email\_header_value_parser.py", line 184>, <code object comments at 0x0000024069466330, file "email\_header_value_parser.py", line 188>, None)

## co_names:
('__name__', '__module__', '__qualname__', 'property', 'value', 'comments')

## bytecode:

   0: RESUME               
   2: LOAD_NAME            __name__
   4: STORE_NAME           __module__
   6: LOAD_CONST           'WhiteSpaceTokenList'
   8: STORE_NAME           __qualname__
  10: LOAD_NAME            property
  12: LOAD_CONST           <code object value at 0x000002406943B0F0, file "email\_header_value_parser.py", line 184>
  14: MAKE_FUNCTION        
  16: PRECALL              
  20: CALL                 
  30: STORE_NAME           value
  32: LOAD_NAME            property
  34: LOAD_CONST           <code object comments at 0x0000024069466330, file "email\_header_value_parser.py", line 188>
  36: MAKE_FUNCTION        
  38: PRECALL              
  42: CALL                 
  52: STORE_NAME           comments
  54: LOAD_CONST           None
  56: RETURN_VALUE         
