# Disassembly for email.parseaddr
# From module file: email.utils

## co_consts:
("\n    Parse addr into its constituent realname and email address parts.\n\n    Return a tuple of realname and email address, unless the parse fails, in\n    which case return a 2-tuple of ('', '').\n    ", ('', ''), 0)

## co_names:
('_AddressList', 'addresslist')

## bytecode:

   0: RESUME               
   2: LOAD_GLOBAL          NULL + _AddressList
  14: LOAD_FAST            addr
  16: PRECALL              
  20: CALL                 
  30: LOAD_ATTR            addresslist
  40: STORE_FAST           addrs
  42: LOAD_FAST            addrs
  44: POP_JUMP_FORWARD_IF_TRUE to 50
  46: LOAD_CONST           ('', '')
  48: RETURN_VALUE         
  50: LOAD_FAST            addrs
  52: LOAD_CONST           0
  54: BINARY_SUBSCR        
  64: RETURN_VALUE         
