# Disassembly for email.HeaderRegistry
# From module file: email.headerregistry

## co_consts:
('HeaderRegistry', 'A header_factory and header registry.', True, <code object __init__ at 0x00000240693D2E80, file "email\headerregistry.py", line 566>, <code object map_to_type at 0x00000240693EBB30, file "email\headerregistry.py", line 584>, <code object __getitem__ at 0x00000240691C1210, file "email\headerregistry.py", line 590>, <code object __call__ at 0x00000240694679F0, file "email\headerregistry.py", line 594>, None)

## co_names:
('__name__', '__module__', '__qualname__', '__doc__', 'BaseHeader', 'UnstructuredHeader', '__init__', 'map_to_type', '__getitem__', '__call__')

## bytecode:

   0: RESUME               
   2: LOAD_NAME            __name__
   4: STORE_NAME           __module__
   6: LOAD_CONST           'HeaderRegistry'
   8: STORE_NAME           __qualname__
  10: LOAD_CONST           'A header_factory and header registry.'
  12: STORE_NAME           __doc__
  14: LOAD_NAME            BaseHeader
  16: LOAD_NAME            UnstructuredHeader
  18: LOAD_CONST           True
  20: BUILD_TUPLE          
  22: LOAD_CONST           <code object __init__ at 0x00000240693D2E80, file "email\headerregistry.py", line 566>
  24: MAKE_FUNCTION        defaults
  26: STORE_NAME           __init__
  28: LOAD_CONST           <code object map_to_type at 0x00000240693EBB30, file "email\headerregistry.py", line 584>
  30: MAKE_FUNCTION        
  32: STORE_NAME           map_to_type
  34: LOAD_CONST           <code object __getitem__ at 0x00000240691C1210, file "email\headerregistry.py", line 590>
  36: MAKE_FUNCTION        
  38: STORE_NAME           __getitem__
  40: LOAD_CONST           <code object __call__ at 0x00000240694679F0, file "email\headerregistry.py", line 594>
  42: MAKE_FUNCTION        
  44: STORE_NAME           __call__
  46: LOAD_CONST           None
  48: RETURN_VALUE         
