# Disassembly for email.get_ttext
# From module file: email._header_value_parser

## co_consts:
("ttext = <matches _ttext_matcher>\n\n    We allow any non-TOKEN_ENDS in ttext, but add defects to the token's\n    defects list if we find non-ttext characters.  We also register defects for\n    *any* non-printables even though the RFC doesn't exclude all of them,\n    because we follow the spirit of RFC 5322.\n\n    ", "expected ttext but found '{}'", None, 'ttext')

## co_names:
('_non_token_end_matcher', 'errors', 'HeaderParseError', 'format', 'group', 'len', 'ValueTerminal', '_validate_xtext')

## bytecode:

   0: RESUME               
   2: LOAD_GLOBAL          NULL + _non_token_end_matcher
  14: LOAD_FAST            value
  16: PRECALL              
  20: CALL                 
  30: STORE_FAST           m
  32: LOAD_FAST            m
  34: POP_JUMP_FORWARD_IF_TRUE to 114
  36: LOAD_GLOBAL          NULL + errors
  48: LOAD_ATTR            HeaderParseError
  58: LOAD_CONST           "expected ttext but found '{}'"
  60: LOAD_METHOD          format
  82: LOAD_FAST            value
  84: PRECALL              
  88: CALL                 
  98: PRECALL              
 102: CALL                 
 112: RAISE_VARARGS        
 114: LOAD_FAST            m
 116: LOAD_METHOD          group
 138: PRECALL              
 142: CALL                 
 152: STORE_FAST           ttext
 154: LOAD_FAST            value
 156: LOAD_GLOBAL          NULL + len
 168: LOAD_FAST            ttext
 170: PRECALL              
 174: CALL                 
 184: LOAD_CONST           None
 186: BUILD_SLICE          
 188: BINARY_SUBSCR        
 198: STORE_FAST           value
 200: LOAD_GLOBAL          NULL + ValueTerminal
 212: LOAD_FAST            ttext
 214: LOAD_CONST           'ttext'
 216: PRECALL              
 220: CALL                 
 230: STORE_FAST           ttext
 232: LOAD_GLOBAL          NULL + _validate_xtext
 244: LOAD_FAST            ttext
 246: PRECALL              
 250: CALL                 
 260: POP_TOP              
 262: LOAD_FAST            ttext
 264: LOAD_FAST            value
 266: BUILD_TUPLE          
 268: RETURN_VALUE         
