# Disassembly for email.MIMEPart.__init__
# From module file: email.message

## co_consts:
(None, 0, ('default',))

## co_names:
('email.policy', 'default', 'super', '__init__')

## bytecode:

   0: COPY_FREE_VARS       
   2: RESUME               
   4: LOAD_FAST            policy
   6: POP_JUMP_FORWARD_IF_NOT_NONE to 24
   8: LOAD_CONST           0
  10: LOAD_CONST           ('default',)
  12: IMPORT_NAME          email.policy
  14: IMPORT_FROM          default
  16: STORE_FAST           default
  18: POP_TOP              
  20: LOAD_FAST            default
  22: STORE_FAST           policy
  24: LOAD_GLOBAL          NULL + super
  36: PRECALL              
  40: CALL                 
  50: LOAD_METHOD          __init__
  72: LOAD_FAST            policy
  74: PRECALL              
  78: CALL                 
  88: POP_TOP              
  90: LOAD_CONST           None
  92: RETURN_VALUE         
