# Disassembly for email.get_fws
# From module file: email._header_value_parser

## co_consts:
("FWS = 1*WSP\n\n    This isn't the RFC definition.  We're using fws to represent tokens where\n    folding can be done, but when we are parsing the *un*folding has already\n    been done so we don't need to watch out for CRLF.\n\n    ", None, 'fws')

## co_names:
('lstrip', 'WhiteSpaceTerminal', 'len')

## bytecode:

   0: RESUME               
   2: LOAD_FAST            value
   4: LOAD_METHOD          lstrip
  26: PRECALL              
  30: CALL                 
  40: STORE_FAST           newvalue
  42: LOAD_GLOBAL          NULL + WhiteSpaceTerminal
  54: LOAD_FAST            value
  56: LOAD_CONST           None
  58: LOAD_GLOBAL          NULL + len
  70: LOAD_FAST            value
  72: PRECALL              
  76: CALL                 
  86: LOAD_GLOBAL          NULL + len
  98: LOAD_FAST            newvalue
 100: PRECALL              
 104: CALL                 
 114: BINARY_OP            -
 118: BUILD_SLICE          
 120: BINARY_SUBSCR        
 130: LOAD_CONST           'fws'
 132: PRECALL              
 136: CALL                 
 146: STORE_FAST           fws
 148: LOAD_FAST            fws
 150: LOAD_FAST            newvalue
 152: BUILD_TUPLE          
 154: RETURN_VALUE         
