# Disassembly for email.MIMEVersionHeader.parse
# From module file: email.headerregistry

## co_consts:
(None, 'parse_tree', 'decoded', 'defects', 'major', 'minor', '{}.{}', 'version')

## co_names:
('value_parser', 'str', 'extend', 'all_defects', 'minor', 'major', 'format')

## bytecode:

   0: RESUME               
   2: LOAD_FAST            cls
   4: LOAD_METHOD          value_parser
  26: LOAD_FAST            value
  28: PRECALL              
  32: CALL                 
  42: COPY                 
  44: LOAD_FAST            kwds
  46: LOAD_CONST           'parse_tree'
  48: STORE_SUBSCR         
  52: STORE_FAST           parse_tree
  54: LOAD_GLOBAL          NULL + str
  66: LOAD_FAST            parse_tree
  68: PRECALL              
  72: CALL                 
  82: LOAD_FAST            kwds
  84: LOAD_CONST           'decoded'
  86: STORE_SUBSCR         
  90: LOAD_FAST            kwds
  92: LOAD_CONST           'defects'
  94: BINARY_SUBSCR        
 104: LOAD_METHOD          extend
 126: LOAD_FAST            parse_tree
 128: LOAD_ATTR            all_defects
 138: PRECALL              
 142: CALL                 
 152: POP_TOP              
 154: LOAD_FAST            parse_tree
 156: LOAD_ATTR            minor
 166: POP_JUMP_FORWARD_IF_NOT_NONE to 172
 168: LOAD_CONST           None
 170: JUMP_FORWARD         to 184
 172: LOAD_FAST            parse_tree
 174: LOAD_ATTR            major
 184: LOAD_FAST            kwds
 186: LOAD_CONST           'major'
 188: STORE_SUBSCR         
 192: LOAD_FAST            parse_tree
 194: LOAD_ATTR            minor
 204: LOAD_FAST            kwds
 206: LOAD_CONST           'minor'
 208: STORE_SUBSCR         
 212: LOAD_FAST            parse_tree
 214: LOAD_ATTR            minor
 224: POP_JUMP_FORWARD_IF_NONE to 304
 226: LOAD_CONST           '{}.{}'
 228: LOAD_METHOD          format
 250: LOAD_FAST            kwds
 252: LOAD_CONST           'major'
 254: BINARY_SUBSCR        
 264: LOAD_FAST            kwds
 266: LOAD_CONST           'minor'
 268: BINARY_SUBSCR        
 278: PRECALL              
 282: CALL                 
 292: LOAD_FAST            kwds
 294: LOAD_CONST           'version'
 296: STORE_SUBSCR         
 300: LOAD_CONST           None
 302: RETURN_VALUE         
 304: LOAD_CONST           None
 306: LOAD_FAST            kwds
 308: LOAD_CONST           'version'
 310: STORE_SUBSCR         
 314: LOAD_CONST           None
 316: RETURN_VALUE         
