# Disassembly for email.HeaderMissingRequiredValue
# From module file: email.errors

## co_consts:
('HeaderMissingRequiredValue', 'A header that must have a value had none', None)

## co_names:
('__name__', '__module__', '__qualname__', '__doc__')

## bytecode:

   0: RESUME               
   2: LOAD_NAME            __name__
   4: STORE_NAME           __module__
   6: LOAD_CONST           'HeaderMissingRequiredValue'
   8: STORE_NAME           __qualname__
  10: LOAD_CONST           'A header that must have a value had none'
  12: STORE_NAME           __doc__
  14: LOAD_CONST           None
  16: RETURN_VALUE         
