# Disassembly for email.DisplayName.value
# From module file: email._header_value_parser

## co_consts:
(None, False, True, 'quoted-string', 0, '', 'cfws', ' ', -1)

## co_names:
('defects', 'token_type', 'len', 'quote_string', 'display_name', 'super', 'value')

## bytecode:

   0: COPY_FREE_VARS       
   2: RESUME               
   4: LOAD_CONST           False
   6: STORE_FAST           quote
   8: LOAD_FAST            self
  10: LOAD_ATTR            defects
  20: POP_JUMP_FORWARD_IF_FALSE to 28
  22: LOAD_CONST           True
  24: STORE_FAST           quote
  26: JUMP_FORWARD         to 64
  28: LOAD_FAST            self
  30: GET_ITER             
  32: FOR_ITER             to 64
  34: STORE_FAST           x
  36: LOAD_FAST            x
  38: LOAD_ATTR            token_type
  48: LOAD_CONST           'quoted-string'
  50: COMPARE_OP           ==
  56: POP_JUMP_FORWARD_IF_FALSE to 62
  58: LOAD_CONST           True
  60: STORE_FAST           quote
  62: JUMP_BACKWARD        to 32
  64: LOAD_GLOBAL          NULL + len
  76: LOAD_FAST            self
  78: PRECALL              
  82: CALL                 
  92: LOAD_CONST           0
  94: COMPARE_OP           !=
 100: POP_JUMP_FORWARD_IF_FALSE to 334
 102: LOAD_FAST            quote
 104: POP_JUMP_FORWARD_IF_FALSE to 334
 106: LOAD_CONST           ''
 108: COPY                 
 110: STORE_FAST           pre
 112: STORE_FAST           post
 114: LOAD_FAST            self
 116: LOAD_CONST           0
 118: BINARY_SUBSCR        
 128: LOAD_ATTR            token_type
 138: LOAD_CONST           'cfws'
 140: COMPARE_OP           ==
 146: POP_JUMP_FORWARD_IF_TRUE to 194
 148: LOAD_FAST            self
 150: LOAD_CONST           0
 152: BINARY_SUBSCR        
 162: LOAD_CONST           0
 164: BINARY_SUBSCR        
 174: LOAD_ATTR            token_type
 184: LOAD_CONST           'cfws'
 186: COMPARE_OP           ==
 192: POP_JUMP_FORWARD_IF_FALSE to 198
 194: LOAD_CONST           ' '
 196: STORE_FAST           pre
 198: LOAD_FAST            self
 200: LOAD_CONST           -1
 202: BINARY_SUBSCR        
 212: LOAD_ATTR            token_type
 222: LOAD_CONST           'cfws'
 224: COMPARE_OP           ==
 230: POP_JUMP_FORWARD_IF_TRUE to 278
 232: LOAD_FAST            self
 234: LOAD_CONST           -1
 236: BINARY_SUBSCR        
 246: LOAD_CONST           -1
 248: BINARY_SUBSCR        
 258: LOAD_ATTR            token_type
 268: LOAD_CONST           'cfws'
 270: COMPARE_OP           ==
 276: POP_JUMP_FORWARD_IF_FALSE to 282
 278: LOAD_CONST           ' '
 280: STORE_FAST           post
 282: LOAD_FAST            pre
 284: LOAD_GLOBAL          NULL + quote_string
 296: LOAD_FAST            self
 298: LOAD_ATTR            display_name
 308: PRECALL              
 312: CALL                 
 322: BINARY_OP            +
 326: LOAD_FAST            post
 328: BINARY_OP            +
 332: RETURN_VALUE         
 334: LOAD_GLOBAL          NULL + super
 346: PRECALL              
 350: CALL                 
 360: LOAD_ATTR            value
 370: RETURN_VALUE         
