# Disassembly for email.TokenList.all_defects.<genexpr>
# From module file: email._header_value_parser

## co_consts:
(None,)

## co_names:
('all_defects',)

## bytecode:

   0: RETURN_GENERATOR     
   2: POP_TOP              
   4: RESUME               
   6: LOAD_FAST            .0
   8: FOR_ITER             to 32
  10: STORE_FAST           x
  12: LOAD_FAST            x
  14: LOAD_ATTR            all_defects
  24: YIELD_VALUE          
  26: RESUME               
  28: POP_TOP              
  30: JUMP_BACKWARD        to 8
  32: LOAD_CONST           None
  34: RETURN_VALUE         
