# Disassembly for email.FeedParser._call_parse
# From module file: email.feedparser

## co_consts:
(None,)

## co_names:
('_parse', 'StopIteration')

## bytecode:

   0: RESUME               
   2: NOP                  
   4: LOAD_FAST            self
   6: LOAD_METHOD          _parse
  28: PRECALL              
  32: CALL                 
  42: POP_TOP              
  44: LOAD_CONST           None
  46: RETURN_VALUE         
  48: PUSH_EXC_INFO        
  50: LOAD_GLOBAL          StopIteration
  62: CHECK_EXC_MATCH      
  64: POP_JUMP_FORWARD_IF_FALSE to 74
  66: POP_TOP              
  68: POP_EXCEPT           
  70: LOAD_CONST           None
  72: RETURN_VALUE         
  74: RERAISE              
  76: COPY                 
  78: POP_EXCEPT           
  80: RERAISE              
