# Disassembly for email.EmailPolicy.header_fetch_parse
# From module file: email.policy

## co_consts:
("+\n        If the value has a 'name' attribute, it is returned to unmodified.\n        Otherwise the name and the value with any linesep characters removed\n        are passed to the header_factory method, and the resulting custom\n        header object is returned.  Any surrogateescaped bytes get turned\n        into the unicode unknown-character glyph.\n\n        ", 'name', '')

## co_names:
('hasattr', 'join', 'linesep_splitter', 'split', 'header_factory')

## bytecode:

   0: RESUME               
   2: LOAD_GLOBAL          NULL + hasattr
  14: LOAD_FAST            value
  16: LOAD_CONST           'name'
  18: PRECALL              
  22: CALL                 
  32: POP_JUMP_FORWARD_IF_FALSE to 38
  34: LOAD_FAST            value
  36: RETURN_VALUE         
  38: LOAD_CONST           ''
  40: LOAD_METHOD          join
  62: LOAD_GLOBAL          linesep_splitter
  74: LOAD_METHOD          split
  96: LOAD_FAST            value
  98: PRECALL              
 102: CALL                 
 112: PRECALL              
 116: CALL                 
 126: STORE_FAST           value
 128: LOAD_FAST            self
 130: LOAD_METHOD          header_factory
 152: LOAD_FAST            name
 154: LOAD_FAST            value
 156: PRECALL              
 160: CALL                 
 170: RETURN_VALUE         
