# Disassembly for email.quote_string
# From module file: email._header_value_parser

## co_consts:
(None, '"', '\\', '\\\\', '\\"')

## co_names:
('str', 'replace')

## bytecode:

   0: RESUME               
   2: LOAD_CONST           '"'
   4: LOAD_GLOBAL          NULL + str
  16: LOAD_FAST            value
  18: PRECALL              
  22: CALL                 
  32: LOAD_METHOD          replace
  54: LOAD_CONST           '\\'
  56: LOAD_CONST           '\\\\'
  58: PRECALL              
  62: CALL                 
  72: LOAD_METHOD          replace
  94: LOAD_CONST           '"'
  96: LOAD_CONST           '\\"'
  98: PRECALL              
 102: CALL                 
 112: BINARY_OP            +
 116: LOAD_CONST           '"'
 118: BINARY_OP            +
 122: RETURN_VALUE         
