# Disassembly for email.Compat32._sanitize_header
# From module file: email._policybase

## co_consts:
(None, ('charset', 'header_name'))

## co_names:
('isinstance', 'str', '_has_surrogates', 'header', 'Header', '_charset', 'UNKNOWN8BIT')

## bytecode:

   0: RESUME               
   2: LOAD_GLOBAL          NULL + isinstance
  14: LOAD_FAST            value
  16: LOAD_GLOBAL          str
  28: PRECALL              
  32: CALL                 
  42: POP_JUMP_FORWARD_IF_TRUE to 48
  44: LOAD_FAST            value
  46: RETURN_VALUE         
  48: LOAD_GLOBAL          NULL + _has_surrogates
  60: LOAD_FAST            value
  62: PRECALL              
  66: CALL                 
  76: POP_JUMP_FORWARD_IF_FALSE to 144
  78: LOAD_GLOBAL          NULL + header
  90: LOAD_ATTR            Header
 100: LOAD_FAST            value
 102: LOAD_GLOBAL          _charset
 114: LOAD_ATTR            UNKNOWN8BIT
 124: LOAD_FAST            name
 126: KW_NAMES             
 128: PRECALL              
 132: CALL                 
 142: RETURN_VALUE         
 144: LOAD_FAST            value
 146: RETURN_VALUE         
