# Disassembly for email.FeedParser._pop_message
# From module file: email.feedparser

## co_consts:
(None, -1)

## co_names:
('_msgstack', 'pop', '_cur')

## bytecode:

   0: RESUME               
   2: LOAD_FAST            self
   4: LOAD_ATTR            _msgstack
  14: LOAD_METHOD          pop
  36: PRECALL              
  40: CALL                 
  50: STORE_FAST           retval
  52: LOAD_FAST            self
  54: LOAD_ATTR            _msgstack
  64: POP_JUMP_FORWARD_IF_FALSE to 104
  66: LOAD_FAST            self
  68: LOAD_ATTR            _msgstack
  78: LOAD_CONST           -1
  80: BINARY_SUBSCR        
  90: LOAD_FAST            self
  92: STORE_ATTR           _cur
 102: JUMP_FORWARD         to 118
 104: LOAD_CONST           None
 106: LOAD_FAST            self
 108: STORE_ATTR           _cur
 118: LOAD_FAST            retval
 120: RETURN_VALUE         
