# Disassembly for email.ObsRoute
# From module file: email._header_value_parser

## co_consts:
('ObsRoute', 'obs-route', <code object domains at 0x0000024069465610, file "email\_header_value_parser.py", line 450>, None)

## co_names:
('__name__', '__module__', '__qualname__', 'token_type', 'property', 'domains')

## bytecode:

   0: RESUME               
   2: LOAD_NAME            __name__
   4: STORE_NAME           __module__
   6: LOAD_CONST           'ObsRoute'
   8: STORE_NAME           __qualname__
  10: LOAD_CONST           'obs-route'
  12: STORE_NAME           token_type
  14: LOAD_NAME            property
  16: LOAD_CONST           <code object domains at 0x0000024069465610, file "email\_header_value_parser.py", line 450>
  18: MAKE_FUNCTION        
  20: PRECALL              
  24: CALL                 
  34: STORE_NAME           domains
  36: LOAD_CONST           None
  38: RETURN_VALUE         
