# Disassembly for email._PolicyBase.__init__
# From module file: email._policybase

## co_consts:
('Create new Policy, possibly overriding some defaults.\n\n        See class docstring for a list of overridable attributes.\n\n        ', '{!r} is an invalid keyword argument for {}', None)

## co_names:
('items', 'hasattr', 'super', '_PolicyBase', '__setattr__', 'TypeError', 'format', '__class__', '__name__')

## bytecode:

   0: COPY_FREE_VARS       
   2: RESUME               
   4: LOAD_FAST            kw
   6: LOAD_METHOD          items
  28: PRECALL              
  32: CALL                 
  42: GET_ITER             
  44: FOR_ITER             to 260
  46: UNPACK_SEQUENCE      
  50: STORE_FAST           name
  52: STORE_FAST           value
  54: LOAD_GLOBAL          NULL + hasattr
  66: LOAD_FAST            self
  68: LOAD_FAST            name
  70: PRECALL              
  74: CALL                 
  84: POP_JUMP_FORWARD_IF_FALSE to 170
  86: LOAD_GLOBAL          NULL + super
  98: LOAD_GLOBAL          _PolicyBase
 110: LOAD_FAST            self
 112: PRECALL              
 116: CALL                 
 126: LOAD_METHOD          __setattr__
 148: LOAD_FAST            name
 150: LOAD_FAST            value
 152: PRECALL              
 156: CALL                 
 166: POP_TOP              
 168: JUMP_BACKWARD        to 44
 170: LOAD_GLOBAL          NULL + TypeError
 182: LOAD_CONST           '{!r} is an invalid keyword argument for {}'
 184: LOAD_METHOD          format
 206: LOAD_FAST            name
 208: LOAD_FAST            self
 210: LOAD_ATTR            __class__
 220: LOAD_ATTR            __name__
 230: PRECALL              
 234: CALL                 
 244: PRECALL              
 248: CALL                 
 258: RAISE_VARARGS        
 260: LOAD_CONST           None
 262: RETURN_VALUE         
