# Disassembly for email.get_qp_ctext
# From module file: email._header_value_parser

## co_consts:
("ctext = <printable ascii except \\ ( )>\n\n    This is not the RFC ctext, since we are handling nested comments in comment\n    and unquoting quoted-pairs here.  We allow anything except the '()'\n    characters, but if we find any ASCII other than the RFC defined printable\n    ASCII, a NonPrintableDefect is added to the token's defects list.  Since\n    quoted pairs are converted to their unquoted values, what is returned is\n    a 'ptext' token.  In this case it is a WhiteSpaceTerminal, so it's value\n    is ' '.\n\n    ", '()', 'ptext')

## co_names:
('_get_ptext_to_endchars', 'WhiteSpaceTerminal', '_validate_xtext')

## bytecode:

   0: RESUME               
   2: LOAD_GLOBAL          NULL + _get_ptext_to_endchars
  14: LOAD_FAST            value
  16: LOAD_CONST           '()'
  18: PRECALL              
  22: CALL                 
  32: UNPACK_SEQUENCE      
  36: STORE_FAST           ptext
  38: STORE_FAST           value
  40: STORE_FAST           _
  42: LOAD_GLOBAL          NULL + WhiteSpaceTerminal
  54: LOAD_FAST            ptext
  56: LOAD_CONST           'ptext'
  58: PRECALL              
  62: CALL                 
  72: STORE_FAST           ptext
  74: LOAD_GLOBAL          NULL + _validate_xtext
  86: LOAD_FAST            ptext
  88: PRECALL              
  92: CALL                 
 102: POP_TOP              
 104: LOAD_FAST            ptext
 106: LOAD_FAST            value
 108: BUILD_TUPLE          
 110: RETURN_VALUE         
