# Disassembly for email.walk
# From module file: email.iterators

## co_consts:
('Walk over the message tree, yielding each subpart.\n\n    The walk is performed in depth-first order.  This method is a\n    generator.\n    ', None)

## co_names:
('is_multipart', 'get_payload', 'walk')

## bytecode:

   0: RETURN_GENERATOR     
   2: POP_TOP              
   4: RESUME               
   6: LOAD_FAST            self
   8: YIELD_VALUE          
  10: RESUME               
  12: POP_TOP              
  14: LOAD_FAST            self
  16: LOAD_METHOD          is_multipart
  38: PRECALL              
  42: CALL                 
  52: POP_JUMP_FORWARD_IF_FALSE to 152
  54: LOAD_FAST            self
  56: LOAD_METHOD          get_payload
  78: PRECALL              
  82: CALL                 
  92: GET_ITER             
  94: FOR_ITER             to 156
  96: STORE_FAST           subpart
  98: LOAD_FAST            subpart
 100: LOAD_METHOD          walk
 122: PRECALL              
 126: CALL                 
 136: GET_YIELD_FROM_ITER  
 138: LOAD_CONST           None
 140: SEND                 to 148
 142: YIELD_VALUE          
 144: RESUME               
 146: JUMP_BACKWARD_NO_INTERRUPT to 140
 148: POP_TOP              
 150: JUMP_BACKWARD        to 94
 152: LOAD_CONST           None
 154: RETURN_VALUE         
 156: LOAD_CONST           None
 158: RETURN_VALUE         
