# Disassembly for email._check_for_early_dl_end
# From module file: email._header_value_parser

## co_consts:
(None, False, 'end of input inside domain-literal', ']', 'domain-literal-end', True)

## co_names:
('append', 'errors', 'InvalidHeaderDefect', 'ValueTerminal')

## bytecode:

   0: RESUME               
   2: LOAD_FAST            value
   4: POP_JUMP_FORWARD_IF_FALSE to 10
   6: LOAD_CONST           False
   8: RETURN_VALUE         
  10: LOAD_FAST            domain_literal
  12: LOAD_METHOD          append
  34: LOAD_GLOBAL          NULL + errors
  46: LOAD_ATTR            InvalidHeaderDefect
  56: LOAD_CONST           'end of input inside domain-literal'
  58: PRECALL              
  62: CALL                 
  72: PRECALL              
  76: CALL                 
  86: POP_TOP              
  88: LOAD_FAST            domain_literal
  90: LOAD_METHOD          append
 112: LOAD_GLOBAL          NULL + ValueTerminal
 124: LOAD_CONST           ']'
 126: LOAD_CONST           'domain-literal-end'
 128: PRECALL              
 132: CALL                 
 142: PRECALL              
 146: CALL                 
 156: POP_TOP              
 158: LOAD_CONST           True
 160: RETURN_VALUE         
