# Disassembly for email.parsedate_tz
# From module file: email._parseaddr

## co_consts:
('Convert a date string to a time tuple.\n\n    Accounts for military timezones.\n    ', None, 9, 0)

## co_names:
('_parsedate_tz', 'tuple')

## bytecode:

   0: RESUME               
   2: LOAD_GLOBAL          NULL + _parsedate_tz
  14: LOAD_FAST            data
  16: PRECALL              
  20: CALL                 
  30: STORE_FAST           res
  32: LOAD_FAST            res
  34: POP_JUMP_FORWARD_IF_TRUE to 40
  36: LOAD_CONST           None
  38: RETURN_VALUE         
  40: LOAD_FAST            res
  42: LOAD_CONST           9
  44: BINARY_SUBSCR        
  54: POP_JUMP_FORWARD_IF_NOT_NONE to 66
  56: LOAD_CONST           0
  58: LOAD_FAST            res
  60: LOAD_CONST           9
  62: STORE_SUBSCR         
  66: LOAD_GLOBAL          NULL + tuple
  78: LOAD_FAST            res
  80: PRECALL              
  84: CALL                 
  94: RETURN_VALUE         
