# Disassembly for email.MIMEPart.set_content
# From module file: email.message

## co_consts:
(None,)

## co_names:
('policy', 'content_manager', 'set_content')

## bytecode:

   0: RESUME               
   2: LOAD_FAST            content_manager
   4: POP_JUMP_FORWARD_IF_NOT_NONE to 30
   6: LOAD_FAST            self
   8: LOAD_ATTR            policy
  18: LOAD_ATTR            content_manager
  28: STORE_FAST           content_manager
  30: PUSH_NULL            
  32: LOAD_FAST            content_manager
  34: LOAD_ATTR            set_content
  44: LOAD_FAST            self
  46: BUILD_LIST           
  48: LOAD_FAST            args
  50: LIST_EXTEND          
  52: LIST_TO_TUPLE        
  54: BUILD_MAP            
  56: LOAD_FAST            kw
  58: DICT_MERGE           
  60: CALL_FUNCTION_EX     
  62: POP_TOP              
  64: LOAD_CONST           None
  66: RETURN_VALUE         
