# Disassembly for email.Message.get_all
# From module file: email.message

## co_consts:
('Return a list of all the values for the named field.\n\n        These will be sorted in the order they appeared in the original\n        message, and may contain duplicates.  Any fields deleted and\n        re-inserted are always appended to the header list.\n\n        If no such fields exist, failobj is returned (defaults to None).\n        ',)

## co_names:
('lower', '_headers', 'append', 'policy', 'header_fetch_parse')

## bytecode:

   0: RESUME               
   2: BUILD_LIST           
   4: STORE_FAST           values
   6: LOAD_FAST            name
   8: LOAD_METHOD          lower
  30: PRECALL              
  34: CALL                 
  44: STORE_FAST           name
  46: LOAD_FAST            self
  48: LOAD_ATTR            _headers
  58: GET_ITER             
  60: FOR_ITER             to 212
  62: UNPACK_SEQUENCE      
  66: STORE_FAST           k
  68: STORE_FAST           v
  70: LOAD_FAST            k
  72: LOAD_METHOD          lower
  94: PRECALL              
  98: CALL                 
 108: LOAD_FAST            name
 110: COMPARE_OP           ==
 116: POP_JUMP_FORWARD_IF_FALSE to 210
 118: LOAD_FAST            values
 120: LOAD_METHOD          append
 142: LOAD_FAST            self
 144: LOAD_ATTR            policy
 154: LOAD_METHOD          header_fetch_parse
 176: LOAD_FAST            k
 178: LOAD_FAST            v
 180: PRECALL              
 184: CALL                 
 194: PRECALL              
 198: CALL                 
 208: POP_TOP              
 210: JUMP_BACKWARD        to 60
 212: LOAD_FAST            values
 214: POP_JUMP_FORWARD_IF_TRUE to 220
 216: LOAD_FAST            failobj
 218: RETURN_VALUE         
 220: LOAD_FAST            values
 222: RETURN_VALUE         
