# Disassembly for email.NonPrintableDefect
# From module file: email.errors

## co_consts:
('NonPrintableDefect', 'ASCII characters outside the ascii-printable range found', <code object __init__ at 0x000002406944B330, file "email\errors.py", line 96>, <code object __str__ at 0x000002406945E3D0, file "email\errors.py", line 100>)

## co_names:
('__name__', '__module__', '__qualname__', '__doc__', '__init__', '__str__', '__classcell__')

## bytecode:

   0: MAKE_CELL            __class__
   2: RESUME               
   4: LOAD_NAME            __name__
   6: STORE_NAME           __module__
   8: LOAD_CONST           'NonPrintableDefect'
  10: STORE_NAME           __qualname__
  12: LOAD_CONST           'ASCII characters outside the ascii-printable range found'
  14: STORE_NAME           __doc__
  16: LOAD_CLOSURE         __class__
  18: BUILD_TUPLE          
  20: LOAD_CONST           <code object __init__ at 0x000002406944B330, file "email\errors.py", line 96>
  22: MAKE_FUNCTION        closure
  24: STORE_NAME           __init__
  26: LOAD_CONST           <code object __str__ at 0x000002406945E3D0, file "email\errors.py", line 100>
  28: MAKE_FUNCTION        
  30: STORE_NAME           __str__
  32: LOAD_CLOSURE         __class__
  34: COPY                 
  36: STORE_NAME           __classcell__
  38: RETURN_VALUE         
