# Disassembly for email.Message.keys
# From module file: email.message

## co_consts:
("Return a list of all the message's header field names.\n\n        These will be sorted in the order they appeared in the original\n        message, or were added to the message, and may contain duplicates.\n        Any fields deleted and re-inserted are always appended to the header\n        list.\n        ", <code object <listcomp> at 0x00000240694957C0, file "email\message.py", line 465>)

## co_names:
('_headers',)

## bytecode:

   0: RESUME               
   2: LOAD_CONST           <code object <listcomp> at 0x00000240694957C0, file "email\message.py", line 465>
   4: MAKE_FUNCTION        
   6: LOAD_FAST            self
   8: LOAD_ATTR            _headers
  18: GET_ITER             
  20: PRECALL              
  24: CALL                 
  34: RETURN_VALUE         
