# Disassembly for email.MIMEPart.as_string
# From module file: email.message

## co_consts:
("Return the entire formatted message as a string.\n\n        Optional 'unixfrom', when true, means include the Unix From_ envelope\n        header.  maxheaderlen is retained for backward compatibility with the\n        base Message class, but defaults to None, meaning that the policy value\n        for max_line_length controls the header maximum length.  'policy' is\n        passed to the Generator instance used to serialize the message; if it\n        is not specified the policy associated with the message instance is\n        used.\n        ",)

## co_names:
('policy', 'max_line_length', 'super', 'as_string')

## bytecode:

   0: COPY_FREE_VARS       
   2: RESUME               
   4: LOAD_FAST            policy
   6: POP_JUMP_FORWARD_IF_NOT_NONE to 22
   8: LOAD_FAST            self
  10: LOAD_ATTR            policy
  20: JUMP_FORWARD         to 24
  22: LOAD_FAST            policy
  24: STORE_FAST           policy
  26: LOAD_FAST            maxheaderlen
  28: POP_JUMP_FORWARD_IF_NOT_NONE to 44
  30: LOAD_FAST            policy
  32: LOAD_ATTR            max_line_length
  42: STORE_FAST           maxheaderlen
  44: LOAD_GLOBAL          NULL + super
  56: PRECALL              
  60: CALL                 
  70: LOAD_METHOD          as_string
  92: LOAD_FAST            unixfrom
  94: LOAD_FAST            maxheaderlen
  96: LOAD_FAST            policy
  98: PRECALL              
 102: CALL                 
 112: RETURN_VALUE         
