# Disassembly for email.Compat32.fold
# From module file: email._policybase

## co_consts:
('+\n        Headers are folded using the Header folding algorithm, which preserves\n        existing line breaks in the value, and wraps each resulting line to the\n        max_line_length.  Non-ASCII binary data are CTE encoded using the\n        unknown-8bit charset.\n\n        ', True, ('sanitize',))

## co_names:
('_fold',)

## bytecode:

   0: RESUME               
   2: LOAD_FAST            self
   4: LOAD_METHOD          _fold
  26: LOAD_FAST            name
  28: LOAD_FAST            value
  30: LOAD_CONST           True
  32: KW_NAMES             
  34: PRECALL              
  38: CALL                 
  48: RETURN_VALUE         
