# Disassembly for email.TokenList.all_defects
# From module file: email._header_value_parser

## co_consts:
(None, <code object <genexpr> at 0x00000240694656F0, file "email\_header_value_parser.py", line 138>)

## co_names:
('sum', 'defects')

## bytecode:

   0: RESUME               
   2: LOAD_GLOBAL          NULL + sum
  14: LOAD_CONST           <code object <genexpr> at 0x00000240694656F0, file "email\_header_value_parser.py", line 138>
  16: MAKE_FUNCTION        
  18: LOAD_FAST            self
  20: GET_ITER             
  22: PRECALL              
  26: CALL                 
  36: LOAD_FAST            self
  38: LOAD_ATTR            defects
  48: PRECALL              
  52: CALL                 
  62: RETURN_VALUE         
