# Disassembly for email.parsedate
# From module file: email._parseaddr

## co_consts:
('Convert a time string to a time tuple.', None, 9)

## co_names:
('parsedate_tz', 'isinstance', 'tuple')

## bytecode:

   0: RESUME               
   2: LOAD_GLOBAL          NULL + parsedate_tz
  14: LOAD_FAST            data
  16: PRECALL              
  20: CALL                 
  30: STORE_FAST           t
  32: LOAD_GLOBAL          NULL + isinstance
  44: LOAD_FAST            t
  46: LOAD_GLOBAL          tuple
  58: PRECALL              
  62: CALL                 
  72: POP_JUMP_FORWARD_IF_FALSE to 94
  74: LOAD_FAST            t
  76: LOAD_CONST           None
  78: LOAD_CONST           9
  80: BUILD_SLICE          
  82: BINARY_SUBSCR        
  92: RETURN_VALUE         
  94: LOAD_FAST            t
  96: RETURN_VALUE         
