# Disassembly for email.AddrlistClass.getaddrlist
# From module file: email._parseaddr

## co_consts:
('Parse all addresses.\n\n        Returns a list containing all of the addresses.\n        ', ('', ''))

## co_names:
('pos', 'len', 'field', 'getaddress', 'append')

## bytecode:

   0: RESUME               
   2: BUILD_LIST           
   4: STORE_FAST           result
   6: LOAD_FAST            self
   8: LOAD_ATTR            pos
  18: LOAD_GLOBAL          NULL + len
  30: LOAD_FAST            self
  32: LOAD_ATTR            field
  42: PRECALL              
  46: CALL                 
  56: COMPARE_OP           <
  62: POP_JUMP_FORWARD_IF_FALSE to 220
  64: LOAD_FAST            self
  66: LOAD_METHOD          getaddress
  88: PRECALL              
  92: CALL                 
 102: STORE_FAST           ad
 104: LOAD_FAST            ad
 106: POP_JUMP_FORWARD_IF_FALSE to 120
 108: LOAD_FAST            result
 110: LOAD_FAST            ad
 112: BINARY_OP            +=
 116: STORE_FAST           result
 118: JUMP_FORWARD         to 162
 120: LOAD_FAST            result
 122: LOAD_METHOD          append
 144: LOAD_CONST           ('', '')
 146: PRECALL              
 150: CALL                 
 160: POP_TOP              
 162: LOAD_FAST            self
 164: LOAD_ATTR            pos
 174: LOAD_GLOBAL          NULL + len
 186: LOAD_FAST            self
 188: LOAD_ATTR            field
 198: PRECALL              
 202: CALL                 
 212: COMPARE_OP           <
 218: POP_JUMP_BACKWARD_IF_TRUE to 64
 220: LOAD_FAST            result
 222: RETURN_VALUE         
