# Disassembly for email.get_text_content
# From module file: email.contentmanager

## co_consts:
(None, True, ('decode',), 'charset', 'ASCII', ('errors',))

## co_names:
('get_payload', 'get_param', 'decode')

## bytecode:

   0: RESUME               
   2: LOAD_FAST            msg
   4: LOAD_METHOD          get_payload
  26: LOAD_CONST           True
  28: KW_NAMES             
  30: PRECALL              
  34: CALL                 
  44: STORE_FAST           content
  46: LOAD_FAST            msg
  48: LOAD_METHOD          get_param
  70: LOAD_CONST           'charset'
  72: LOAD_CONST           'ASCII'
  74: PRECALL              
  78: CALL                 
  88: STORE_FAST           charset
  90: LOAD_FAST            content
  92: LOAD_METHOD          decode
 114: LOAD_FAST            charset
 116: LOAD_FAST            errors
 118: KW_NAMES             
 120: PRECALL              
 124: CALL                 
 134: RETURN_VALUE         
