# Disassembly for email.Message.set_raw
# From module file: email.message

## co_consts:
('Store name and value in the model without modification.\n\n        This is an "internal" API, intended only for use by a parser.\n        ', None)

## co_names:
('_headers', 'append')

## bytecode:

   0: RESUME               
   2: LOAD_FAST            self
   4: LOAD_ATTR            _headers
  14: LOAD_METHOD          append
  36: LOAD_FAST            name
  38: LOAD_FAST            value
  40: BUILD_TUPLE          
  42: PRECALL              
  46: CALL                 
  56: POP_TOP              
  58: LOAD_CONST           None
  60: RETURN_VALUE         
