# Disassembly for email.Generator._handle_text
# From module file: email.generator

## co_consts:
(None, 'string payload expected: %s', 'charset', 'content-transfer-encoding', 'content-type', '>From ')

## co_names:
('get_payload', 'isinstance', 'str', 'TypeError', 'type', '_has_surrogates', '_payload', 'get_param', 'deepcopy', 'set_payload', '_munge_cte', '_mangle_from_', 'fcre', 'sub', '_write_lines')

## bytecode:

   0: RESUME               
   2: LOAD_FAST            msg
   4: LOAD_METHOD          get_payload
  26: PRECALL              
  30: CALL                 
  40: STORE_FAST           payload
  42: LOAD_FAST            payload
  44: POP_JUMP_FORWARD_IF_NOT_NONE to 50
  46: LOAD_CONST           None
  48: RETURN_VALUE         
  50: LOAD_GLOBAL          NULL + isinstance
  62: LOAD_FAST            payload
  64: LOAD_GLOBAL          str
  76: PRECALL              
  80: CALL                 
  90: POP_JUMP_FORWARD_IF_TRUE to 154
  92: LOAD_GLOBAL          NULL + TypeError
 104: LOAD_CONST           'string payload expected: %s'
 106: LOAD_GLOBAL          NULL + type
 118: LOAD_FAST            payload
 120: PRECALL              
 124: CALL                 
 134: BINARY_OP            %
 138: PRECALL              
 142: CALL                 
 152: RAISE_VARARGS        
 154: LOAD_GLOBAL          NULL + _has_surrogates
 166: LOAD_FAST            msg
 168: LOAD_ATTR            _payload
 178: PRECALL              
 182: CALL                 
 192: POP_JUMP_FORWARD_IF_FALSE to 402
 194: LOAD_FAST            msg
 196: LOAD_METHOD          get_param
 218: LOAD_CONST           'charset'
 220: PRECALL              
 224: CALL                 
 234: STORE_FAST           charset
 236: LOAD_FAST            charset
 238: POP_JUMP_FORWARD_IF_NONE to 402
 240: LOAD_GLOBAL          NULL + deepcopy
 252: LOAD_FAST            msg
 254: PRECALL              
 258: CALL                 
 268: STORE_FAST           msg
 270: LOAD_FAST            msg
 272: LOAD_CONST           'content-transfer-encoding'
 274: DELETE_SUBSCR        
 276: LOAD_FAST            msg
 278: LOAD_METHOD          set_payload
 300: LOAD_FAST            payload
 302: LOAD_FAST            charset
 304: PRECALL              
 308: CALL                 
 318: POP_TOP              
 320: LOAD_FAST            msg
 322: LOAD_METHOD          get_payload
 344: PRECALL              
 348: CALL                 
 358: STORE_FAST           payload
 360: LOAD_FAST            msg
 362: LOAD_CONST           'content-transfer-encoding'
 364: BINARY_SUBSCR        
 374: LOAD_FAST            msg
 376: LOAD_CONST           'content-type'
 378: BINARY_SUBSCR        
 388: BUILD_TUPLE          
 390: LOAD_FAST            self
 392: STORE_ATTR           _munge_cte
 402: LOAD_FAST            self
 404: LOAD_ATTR            _mangle_from_
 414: POP_JUMP_FORWARD_IF_FALSE to 470
 416: LOAD_GLOBAL          fcre
 428: LOAD_METHOD          sub
 450: LOAD_CONST           '>From '
 452: LOAD_FAST            payload
 454: PRECALL              
 458: CALL                 
 468: STORE_FAST           payload
 470: LOAD_FAST            self
 472: LOAD_METHOD          _write_lines
 494: LOAD_FAST            payload
 496: PRECALL              
 500: CALL                 
 510: POP_TOP              
 512: LOAD_CONST           None
 514: RETURN_VALUE         
