# Disassembly for email._Accumulator.pop_from
# From module file: email.header

## co_consts:
(None,)

## co_names:
()

## bytecode:

   0: RESUME               
   2: LOAD_FAST            self
   4: LOAD_FAST            i
   6: LOAD_CONST           None
   8: BUILD_SLICE          
  10: BINARY_SUBSCR        
  20: STORE_FAST           popped
  22: BUILD_LIST           
  24: LOAD_FAST            self
  26: LOAD_FAST            i
  28: LOAD_CONST           None
  30: BUILD_SLICE          
  32: STORE_SUBSCR         
  36: LOAD_FAST            popped
  38: RETURN_VALUE         
