# Disassembly for email.BytesParser.parse
# From module file: email.parser

## co_consts:
('Create a message structure from the data in a binary file.\n\n        Reads all the data from the file and returns the root of the message\n        structure.  Optional headersonly is a flag specifying whether to stop\n        parsing after reading the headers or not.  The default is False,\n        meaning it parses the entire contents of the file.\n        ', 'ascii', 'surrogateescape', ('encoding', 'errors'))

## co_names:
('TextIOWrapper', 'parser', 'parse', 'detach')

## bytecode:

   0: RESUME               
   2: LOAD_GLOBAL          NULL + TextIOWrapper
  14: LOAD_FAST            fp
  16: LOAD_CONST           'ascii'
  18: LOAD_CONST           'surrogateescape'
  20: KW_NAMES             
  22: PRECALL              
  26: CALL                 
  36: STORE_FAST           fp
  38: NOP                  
  40: LOAD_FAST            self
  42: LOAD_ATTR            parser
  52: LOAD_METHOD          parse
  74: LOAD_FAST            fp
  76: LOAD_FAST            headersonly
  78: PRECALL              
  82: CALL                 
  92: LOAD_FAST            fp
  94: LOAD_METHOD          detach
 116: PRECALL              
 120: CALL                 
 130: POP_TOP              
 132: RETURN_VALUE         
 134: PUSH_EXC_INFO        
 136: LOAD_FAST            fp
 138: LOAD_METHOD          detach
 160: PRECALL              
 164: CALL                 
 174: POP_TOP              
 176: RERAISE              
 178: COPY                 
 180: POP_EXCEPT           
 182: RERAISE              
