# Disassembly for email._parsedate_tz
# From module file: email._parseaddr

## co_consts:
('Convert date to extended time tuple.\n\n    The last (additional) element is the time zone offset in seconds, except if\n    the timezone was specified as -0000.  In that case the last element is\n    None.  This indicates a UTC timestamp that explicitly declaims knowledge of\n    the source timezone, as opposed to a +0000 timestamp that indicates the\n    source timezone really was UTC.\n\n    ', None, 0, ',', 1, 3, '-', 4, '+', -1, '', 5, 12, ':', 2, '0', '.', 100, 68, 1900, 2000, 3600, 60)

## co_names:
('split', 'endswith', 'lower', '_daynames', 'rfind', 'len', 'find', 'append', '_monthnames', 'index', 'isdigit', 'int', 'ValueError', 'upper', '_timezones', 'startswith')

## bytecode:

   0: RESUME               
   2: LOAD_FAST            data
   4: POP_JUMP_FORWARD_IF_TRUE to 10
   6: LOAD_CONST           None
   8: RETURN_VALUE         
  10: LOAD_FAST            data
  12: LOAD_METHOD          split
  34: PRECALL              
  38: CALL                 
  48: STORE_FAST           data
  50: LOAD_FAST            data
  52: POP_JUMP_FORWARD_IF_TRUE to 58
  54: LOAD_CONST           None
  56: RETURN_VALUE         
  58: LOAD_FAST            data
  60: LOAD_CONST           0
  62: BINARY_SUBSCR        
  72: LOAD_METHOD          endswith
  94: LOAD_CONST           ','
  96: PRECALL              
 100: CALL                 
 110: POP_JUMP_FORWARD_IF_TRUE to 178
 112: LOAD_FAST            data
 114: LOAD_CONST           0
 116: BINARY_SUBSCR        
 126: LOAD_METHOD          lower
 148: PRECALL              
 152: CALL                 
 162: LOAD_GLOBAL          _daynames
 174: CONTAINS_OP          
 176: POP_JUMP_FORWARD_IF_FALSE to 186
 178: LOAD_FAST            data
 180: LOAD_CONST           0
 182: DELETE_SUBSCR        
 184: JUMP_FORWARD         to 296
 186: LOAD_FAST            data
 188: LOAD_CONST           0
 190: BINARY_SUBSCR        
 200: LOAD_METHOD          rfind
 222: LOAD_CONST           ','
 224: PRECALL              
 228: CALL                 
 238: STORE_FAST           i
 240: LOAD_FAST            i
 242: LOAD_CONST           0
 244: COMPARE_OP           >=
 250: POP_JUMP_FORWARD_IF_FALSE to 296
 252: LOAD_FAST            data
 254: LOAD_CONST           0
 256: BINARY_SUBSCR        
 266: LOAD_FAST            i
 268: LOAD_CONST           1
 270: BINARY_OP            +
 274: LOAD_CONST           None
 276: BUILD_SLICE          
 278: BINARY_SUBSCR        
 288: LOAD_FAST            data
 290: LOAD_CONST           0
 292: STORE_SUBSCR         
 296: LOAD_GLOBAL          NULL + len
 308: LOAD_FAST            data
 310: PRECALL              
 314: CALL                 
 324: LOAD_CONST           3
 326: COMPARE_OP           ==
 332: POP_JUMP_FORWARD_IF_FALSE to 452
 334: LOAD_FAST            data
 336: LOAD_CONST           0
 338: BINARY_SUBSCR        
 348: LOAD_METHOD          split
 370: LOAD_CONST           '-'
 372: PRECALL              
 376: CALL                 
 386: STORE_FAST           stuff
 388: LOAD_GLOBAL          NULL + len
 400: LOAD_FAST            stuff
 402: PRECALL              
 406: CALL                 
 416: LOAD_CONST           3
 418: COMPARE_OP           ==
 424: POP_JUMP_FORWARD_IF_FALSE to 452
 426: LOAD_FAST            stuff
 428: LOAD_FAST            data
 430: LOAD_CONST           1
 432: LOAD_CONST           None
 434: BUILD_SLICE          
 436: BINARY_SUBSCR        
 446: BINARY_OP            +
 450: STORE_FAST           data
 452: LOAD_GLOBAL          NULL + len
 464: LOAD_FAST            data
 466: PRECALL              
 470: CALL                 
 480: LOAD_CONST           4
 482: COMPARE_OP           ==
 488: POP_JUMP_FORWARD_IF_FALSE to 708
 490: LOAD_FAST            data
 492: LOAD_CONST           3
 494: BINARY_SUBSCR        
 504: STORE_FAST           s
 506: LOAD_FAST            s
 508: LOAD_METHOD          find
 530: LOAD_CONST           '+'
 532: PRECALL              
 536: CALL                 
 546: STORE_FAST           i
 548: LOAD_FAST            i
 550: LOAD_CONST           -1
 552: COMPARE_OP           ==
 558: POP_JUMP_FORWARD_IF_FALSE to 602
 560: LOAD_FAST            s
 562: LOAD_METHOD          find
 584: LOAD_CONST           '-'
 586: PRECALL              
 590: CALL                 
 600: STORE_FAST           i
 602: LOAD_FAST            i
 604: LOAD_CONST           0
 606: COMPARE_OP           >
 612: POP_JUMP_FORWARD_IF_FALSE to 666
 614: LOAD_FAST            s
 616: LOAD_CONST           None
 618: LOAD_FAST            i
 620: BUILD_SLICE          
 622: BINARY_SUBSCR        
 632: LOAD_FAST            s
 634: LOAD_FAST            i
 636: LOAD_CONST           None
 638: BUILD_SLICE          
 640: BINARY_SUBSCR        
 650: BUILD_LIST           
 652: LOAD_FAST            data
 654: LOAD_CONST           3
 656: LOAD_CONST           None
 658: BUILD_SLICE          
 660: STORE_SUBSCR         
 664: JUMP_FORWARD         to 708
 666: LOAD_FAST            data
 668: LOAD_METHOD          append
 690: LOAD_CONST           ''
 692: PRECALL              
 696: CALL                 
 706: POP_TOP              
 708: LOAD_GLOBAL          NULL + len
 720: LOAD_FAST            data
 722: PRECALL              
 726: CALL                 
 736: LOAD_CONST           5
 738: COMPARE_OP           <
 744: POP_JUMP_FORWARD_IF_FALSE to 750
 746: LOAD_CONST           None
 748: RETURN_VALUE         
 750: LOAD_FAST            data
 752: LOAD_CONST           None
 754: LOAD_CONST           5
 756: BUILD_SLICE          
 758: BINARY_SUBSCR        
 768: STORE_FAST           data
 770: LOAD_FAST            data
 772: UNPACK_SEQUENCE      
 776: STORE_FAST           dd
 778: STORE_FAST           mm
 780: STORE_FAST           yy
 782: STORE_FAST           tm
 784: STORE_FAST           tz
 786: LOAD_FAST            dd
 788: POP_JUMP_FORWARD_IF_FALSE to 798
 790: LOAD_FAST            mm
 792: POP_JUMP_FORWARD_IF_FALSE to 798
 794: LOAD_FAST            yy
 796: POP_JUMP_FORWARD_IF_TRUE to 802
 798: LOAD_CONST           None
 800: RETURN_VALUE         
 802: LOAD_FAST            mm
 804: LOAD_METHOD          lower
 826: PRECALL              
 830: CALL                 
 840: STORE_FAST           mm
 842: LOAD_FAST            mm
 844: LOAD_GLOBAL          _monthnames
 856: CONTAINS_OP          
 858: POP_JUMP_FORWARD_IF_FALSE to 926
 860: LOAD_FAST            mm
 862: LOAD_FAST            dd
 864: LOAD_METHOD          lower
 886: PRECALL              
 890: CALL                 
 900: STORE_FAST           mm
 902: STORE_FAST           dd
 904: LOAD_FAST            mm
 906: LOAD_GLOBAL          _monthnames
 918: CONTAINS_OP          
 920: POP_JUMP_FORWARD_IF_FALSE to 926
 922: LOAD_CONST           None
 924: RETURN_VALUE         
 926: LOAD_GLOBAL          _monthnames
 938: LOAD_METHOD          index
 960: LOAD_FAST            mm
 962: PRECALL              
 966: CALL                 
 976: LOAD_CONST           1
 978: BINARY_OP            +
 982: STORE_FAST           mm
 984: LOAD_FAST            mm
 986: LOAD_CONST           12
 988: COMPARE_OP           >
 994: POP_JUMP_FORWARD_IF_FALSE to 1006
 996: LOAD_FAST            mm
 998: LOAD_CONST           12
1000: BINARY_OP            -=
1004: STORE_FAST           mm
1006: LOAD_FAST            dd
1008: LOAD_CONST           -1
1010: BINARY_SUBSCR        
1020: LOAD_CONST           ','
1022: COMPARE_OP           ==
1028: POP_JUMP_FORWARD_IF_FALSE to 1050
1030: LOAD_FAST            dd
1032: LOAD_CONST           None
1034: LOAD_CONST           -1
1036: BUILD_SLICE          
1038: BINARY_SUBSCR        
1048: STORE_FAST           dd
1050: LOAD_FAST            yy
1052: LOAD_METHOD          find
1074: LOAD_CONST           ':'
1076: PRECALL              
1080: CALL                 
1090: STORE_FAST           i
1092: LOAD_FAST            i
1094: LOAD_CONST           0
1096: COMPARE_OP           >
1102: POP_JUMP_FORWARD_IF_FALSE to 1112
1104: LOAD_FAST            tm
1106: LOAD_FAST            yy
1108: STORE_FAST           tm
1110: STORE_FAST           yy
1112: LOAD_FAST            yy
1114: LOAD_CONST           -1
1116: BINARY_SUBSCR        
1126: LOAD_CONST           ','
1128: COMPARE_OP           ==
1134: POP_JUMP_FORWARD_IF_FALSE to 1164
1136: LOAD_FAST            yy
1138: LOAD_CONST           None
1140: LOAD_CONST           -1
1142: BUILD_SLICE          
1144: BINARY_SUBSCR        
1154: STORE_FAST           yy
1156: LOAD_FAST            yy
1158: POP_JUMP_FORWARD_IF_TRUE to 1164
1160: LOAD_CONST           None
1162: RETURN_VALUE         
1164: LOAD_FAST            yy
1166: LOAD_CONST           0
1168: BINARY_SUBSCR        
1178: LOAD_METHOD          isdigit
1200: PRECALL              
1204: CALL                 
1214: POP_JUMP_FORWARD_IF_TRUE to 1224
1216: LOAD_FAST            tz
1218: LOAD_FAST            yy
1220: STORE_FAST           tz
1222: STORE_FAST           yy
1224: LOAD_FAST            tm
1226: LOAD_CONST           -1
1228: BINARY_SUBSCR        
1238: LOAD_CONST           ','
1240: COMPARE_OP           ==
1246: POP_JUMP_FORWARD_IF_FALSE to 1268
1248: LOAD_FAST            tm
1250: LOAD_CONST           None
1252: LOAD_CONST           -1
1254: BUILD_SLICE          
1256: BINARY_SUBSCR        
1266: STORE_FAST           tm
1268: LOAD_FAST            tm
1270: LOAD_METHOD          split
1292: LOAD_CONST           ':'
1294: PRECALL              
1298: CALL                 
1308: STORE_FAST           tm
1310: LOAD_GLOBAL          NULL + len
1322: LOAD_FAST            tm
1324: PRECALL              
1328: CALL                 
1338: LOAD_CONST           2
1340: COMPARE_OP           ==
1346: POP_JUMP_FORWARD_IF_FALSE to 1364
1348: LOAD_FAST            tm
1350: UNPACK_SEQUENCE      
1354: STORE_FAST           thh
1356: STORE_FAST           tmm
1358: LOAD_CONST           '0'
1360: STORE_FAST           tss
1362: JUMP_FORWARD         to 1642
1364: LOAD_GLOBAL          NULL + len
1376: LOAD_FAST            tm
1378: PRECALL              
1382: CALL                 
1392: LOAD_CONST           3
1394: COMPARE_OP           ==
1400: POP_JUMP_FORWARD_IF_FALSE to 1416
1402: LOAD_FAST            tm
1404: UNPACK_SEQUENCE      
1408: STORE_FAST           thh
1410: STORE_FAST           tmm
1412: STORE_FAST           tss
1414: JUMP_FORWARD         to 1642
1416: LOAD_GLOBAL          NULL + len
1428: LOAD_FAST            tm
1430: PRECALL              
1434: CALL                 
1444: LOAD_CONST           1
1446: COMPARE_OP           ==
1452: POP_JUMP_FORWARD_IF_FALSE to 1638
1454: LOAD_CONST           '.'
1456: LOAD_FAST            tm
1458: LOAD_CONST           0
1460: BINARY_SUBSCR        
1470: CONTAINS_OP          
1472: POP_JUMP_FORWARD_IF_FALSE to 1638
1474: LOAD_FAST            tm
1476: LOAD_CONST           0
1478: BINARY_SUBSCR        
1488: LOAD_METHOD          split
1510: LOAD_CONST           '.'
1512: PRECALL              
1516: CALL                 
1526: STORE_FAST           tm
1528: LOAD_GLOBAL          NULL + len
1540: LOAD_FAST            tm
1542: PRECALL              
1546: CALL                 
1556: LOAD_CONST           2
1558: COMPARE_OP           ==
1564: POP_JUMP_FORWARD_IF_FALSE to 1582
1566: LOAD_FAST            tm
1568: UNPACK_SEQUENCE      
1572: STORE_FAST           thh
1574: STORE_FAST           tmm
1576: LOAD_CONST           0
1578: STORE_FAST           tss
1580: JUMP_FORWARD         to 1642
1582: LOAD_GLOBAL          NULL + len
1594: LOAD_FAST            tm
1596: PRECALL              
1600: CALL                 
1610: LOAD_CONST           3
1612: COMPARE_OP           ==
1618: POP_JUMP_FORWARD_IF_FALSE to 1634
1620: LOAD_FAST            tm
1622: UNPACK_SEQUENCE      
1626: STORE_FAST           thh
1628: STORE_FAST           tmm
1630: STORE_FAST           tss
1632: JUMP_FORWARD         to 1642
1634: LOAD_CONST           None
1636: RETURN_VALUE         
1638: LOAD_CONST           None
1640: RETURN_VALUE         
1642: NOP                  
1644: LOAD_GLOBAL          NULL + int
1656: LOAD_FAST            yy
1658: PRECALL              
1662: CALL                 
1672: STORE_FAST           yy
1674: LOAD_GLOBAL          NULL + int
1686: LOAD_FAST            dd
1688: PRECALL              
1692: CALL                 
1702: STORE_FAST           dd
1704: LOAD_GLOBAL          NULL + int
1716: LOAD_FAST            thh
1718: PRECALL              
1722: CALL                 
1732: STORE_FAST           thh
1734: LOAD_GLOBAL          NULL + int
1746: LOAD_FAST            tmm
1748: PRECALL              
1752: CALL                 
1762: STORE_FAST           tmm
1764: LOAD_GLOBAL          NULL + int
1776: LOAD_FAST            tss
1778: PRECALL              
1782: CALL                 
1792: STORE_FAST           tss
1794: JUMP_FORWARD         to 1830
1796: PUSH_EXC_INFO        
1798: LOAD_GLOBAL          ValueError
1810: CHECK_EXC_MATCH      
1812: POP_JUMP_FORWARD_IF_FALSE to 1822
1814: POP_TOP              
1816: POP_EXCEPT           
1818: LOAD_CONST           None
1820: RETURN_VALUE         
1822: RERAISE              
1824: COPY                 
1826: POP_EXCEPT           
1828: RERAISE              
1830: LOAD_FAST            yy
1832: LOAD_CONST           100
1834: COMPARE_OP           <
1840: POP_JUMP_FORWARD_IF_FALSE to 1876
1842: LOAD_FAST            yy
1844: LOAD_CONST           68
1846: COMPARE_OP           >
1852: POP_JUMP_FORWARD_IF_FALSE to 1866
1854: LOAD_FAST            yy
1856: LOAD_CONST           1900
1858: BINARY_OP            +=
1862: STORE_FAST           yy
1864: JUMP_FORWARD         to 1876
1866: LOAD_FAST            yy
1868: LOAD_CONST           2000
1870: BINARY_OP            +=
1874: STORE_FAST           yy
1876: LOAD_CONST           None
1878: STORE_FAST           tzoffset
1880: LOAD_FAST            tz
1882: LOAD_METHOD          upper
1904: PRECALL              
1908: CALL                 
1918: STORE_FAST           tz
1920: LOAD_FAST            tz
1922: LOAD_GLOBAL          _timezones
1934: CONTAINS_OP          
1936: POP_JUMP_FORWARD_IF_FALSE to 1966
1938: LOAD_GLOBAL          _timezones
1950: LOAD_FAST            tz
1952: BINARY_SUBSCR        
1962: STORE_FAST           tzoffset
1964: JUMP_FORWARD         to 2090
1966: NOP                  
1968: LOAD_GLOBAL          NULL + int
1980: LOAD_FAST            tz
1982: PRECALL              
1986: CALL                 
1996: STORE_FAST           tzoffset
1998: JUMP_FORWARD         to 2032
2000: PUSH_EXC_INFO        
2002: LOAD_GLOBAL          ValueError
2014: CHECK_EXC_MATCH      
2016: POP_JUMP_FORWARD_IF_FALSE to 2024
2018: POP_TOP              
2020: POP_EXCEPT           
2022: JUMP_FORWARD         to 2032
2024: RERAISE              
2026: COPY                 
2028: POP_EXCEPT           
2030: RERAISE              
2032: LOAD_FAST            tzoffset
2034: LOAD_CONST           0
2036: COMPARE_OP           ==
2042: POP_JUMP_FORWARD_IF_FALSE to 2090
2044: LOAD_FAST            tz
2046: LOAD_METHOD          startswith
2068: LOAD_CONST           '-'
2070: PRECALL              
2074: CALL                 
2084: POP_JUMP_FORWARD_IF_FALSE to 2090
2086: LOAD_CONST           None
2088: STORE_FAST           tzoffset
2090: LOAD_FAST            tzoffset
2092: POP_JUMP_FORWARD_IF_FALSE to 2162
2094: LOAD_FAST            tzoffset
2096: LOAD_CONST           0
2098: COMPARE_OP           <
2104: POP_JUMP_FORWARD_IF_FALSE to 2118
2106: LOAD_CONST           -1
2108: STORE_FAST           tzsign
2110: LOAD_FAST            tzoffset
2112: UNARY_NEGATIVE       
2114: STORE_FAST           tzoffset
2116: JUMP_FORWARD         to 2122
2118: LOAD_CONST           1
2120: STORE_FAST           tzsign
2122: LOAD_FAST            tzsign
2124: LOAD_FAST            tzoffset
2126: LOAD_CONST           100
2128: BINARY_OP            //
2132: LOAD_CONST           3600
2134: BINARY_OP            *
2138: LOAD_FAST            tzoffset
2140: LOAD_CONST           100
2142: BINARY_OP            %
2146: LOAD_CONST           60
2148: BINARY_OP            *
2152: BINARY_OP            +
2156: BINARY_OP            *
2160: STORE_FAST           tzoffset
2162: LOAD_FAST            yy
2164: LOAD_FAST            mm
2166: LOAD_FAST            dd
2168: LOAD_FAST            thh
2170: LOAD_FAST            tmm
2172: LOAD_FAST            tss
2174: LOAD_CONST           0
2176: LOAD_CONST           1
2178: LOAD_CONST           -1
2180: LOAD_FAST            tzoffset
2182: BUILD_LIST           
2184: RETURN_VALUE         
