# Disassembly for email.BytesFeedParser.feed
# From module file: email.feedparser

## co_consts:
(None, 'ascii', 'surrogateescape')

## co_names:
('super', 'feed', 'decode')

## bytecode:

   0: COPY_FREE_VARS       
   2: RESUME               
   4: LOAD_GLOBAL          NULL + super
  16: PRECALL              
  20: CALL                 
  30: LOAD_METHOD          feed
  52: LOAD_FAST            data
  54: LOAD_METHOD          decode
  76: LOAD_CONST           'ascii'
  78: LOAD_CONST           'surrogateescape'
  80: PRECALL              
  84: CALL                 
  94: PRECALL              
  98: CALL                 
 108: POP_TOP              
 110: LOAD_CONST           None
 112: RETURN_VALUE         
