# Disassembly for email.Charset.get_body_encoding
# From module file: email.charset

## co_consts:
('Return the content-transfer-encoding used for body encoding.\n\n        This is either the string `quoted-printable\' or `base64\' depending on\n        the encoding used, or it is a function in which case you should call\n        the function with a single argument, the Message object being\n        encoded.  The function should then set the Content-Transfer-Encoding\n        header itself to whatever is appropriate.\n\n        Returns "quoted-printable" if self.body_encoding is QP.\n        Returns "base64" if self.body_encoding is BASE64.\n        Returns conversion function otherwise.\n        ', 'quoted-printable', 'base64')

## co_names:
('body_encoding', 'SHORTEST', 'QP', 'BASE64', 'encode_7or8bit')

## bytecode:

   0: RESUME               
   2: LOAD_FAST            self
   4: LOAD_ATTR            body_encoding
  14: LOAD_GLOBAL          SHORTEST
  26: COMPARE_OP           !=
  32: POP_JUMP_FORWARD_IF_TRUE to 38
  34: LOAD_ASSERTION_ERROR 
  36: RAISE_VARARGS        
  38: LOAD_FAST            self
  40: LOAD_ATTR            body_encoding
  50: LOAD_GLOBAL          QP
  62: COMPARE_OP           ==
  68: POP_JUMP_FORWARD_IF_FALSE to 74
  70: LOAD_CONST           'quoted-printable'
  72: RETURN_VALUE         
  74: LOAD_FAST            self
  76: LOAD_ATTR            body_encoding
  86: LOAD_GLOBAL          BASE64
  98: COMPARE_OP           ==
 104: POP_JUMP_FORWARD_IF_FALSE to 110
 106: LOAD_CONST           'base64'
 108: RETURN_VALUE         
 110: LOAD_GLOBAL          encode_7or8bit
 122: RETURN_VALUE         
