# Disassembly for email.TokenList._pp
# From module file: email._header_value_parser

## co_consts:
(None, '{}{}/{}(', '_pp', '    !! invalid element in token list: {!r}', '    ', ' Defects: {}', '', '{}){}')

## co_names:
('format', '__class__', '__name__', 'token_type', 'hasattr', '_pp', 'defects')

## bytecode:

   0: RETURN_GENERATOR     
   2: POP_TOP              
   4: RESUME               
   6: LOAD_CONST           '{}{}/{}('
   8: LOAD_METHOD          format
  30: LOAD_FAST            indent
  32: LOAD_FAST            self
  34: LOAD_ATTR            __class__
  44: LOAD_ATTR            __name__
  54: LOAD_FAST            self
  56: LOAD_ATTR            token_type
  66: PRECALL              
  70: CALL                 
  80: YIELD_VALUE          
  82: RESUME               
  84: POP_TOP              
  86: LOAD_FAST            self
  88: GET_ITER             
  90: FOR_ITER             to 242
  92: STORE_FAST           token
  94: LOAD_GLOBAL          NULL + hasattr
 106: LOAD_FAST            token
 108: LOAD_CONST           '_pp'
 110: PRECALL              
 114: CALL                 
 124: POP_JUMP_FORWARD_IF_TRUE to 180
 126: LOAD_FAST            indent
 128: LOAD_CONST           '    !! invalid element in token list: {!r}'
 130: LOAD_METHOD          format
 152: LOAD_FAST            token
 154: PRECALL              
 158: CALL                 
 168: BINARY_OP            +
 172: YIELD_VALUE          
 174: RESUME               
 176: POP_TOP              
 178: JUMP_BACKWARD        to 90
 180: LOAD_FAST            token
 182: LOAD_METHOD          _pp
 204: LOAD_FAST            indent
 206: LOAD_CONST           '    '
 208: BINARY_OP            +
 212: PRECALL              
 216: CALL                 
 226: GET_YIELD_FROM_ITER  
 228: LOAD_CONST           None
 230: SEND                 to 238
 232: YIELD_VALUE          
 234: RESUME               
 236: JUMP_BACKWARD_NO_INTERRUPT to 230
 238: POP_TOP              
 240: JUMP_BACKWARD        to 90
 242: LOAD_FAST            self
 244: LOAD_ATTR            defects
 254: POP_JUMP_FORWARD_IF_FALSE to 310
 256: LOAD_CONST           ' Defects: {}'
 258: LOAD_METHOD          format
 280: LOAD_FAST            self
 282: LOAD_ATTR            defects
 292: PRECALL              
 296: CALL                 
 306: STORE_FAST           extra
 308: JUMP_FORWARD         to 314
 310: LOAD_CONST           ''
 312: STORE_FAST           extra
 314: LOAD_CONST           '{}){}'
 316: LOAD_METHOD          format
 338: LOAD_FAST            indent
 340: LOAD_FAST            extra
 342: PRECALL              
 346: CALL                 
 356: YIELD_VALUE          
 358: RESUME               
 360: POP_TOP              
 362: LOAD_CONST           None
 364: RETURN_VALUE         
