# Disassembly for email.AddrlistClass.getdelimited
# From module file: email._parseaddr

## co_consts:
("Parse a header fragment delimited by special characters.\n\n        `beginchar' is the start character for the fragment.\n        If self is not looking at an instance of `beginchar' then\n        getdelimited returns the empty string.\n\n        `endchars' is a sequence of allowable end-delimiting characters.\n        Parsing stops when one of these is encountered.\n\n        If `allowcomments' is non-zero, embedded RFC 2822 comments are allowed\n        within the parsed fragment.\n        ", '', False, 1, '(', '\\', True)

## co_names:
('field', 'pos', 'len', 'append', 'getcomment', 'EMPTYSTRING', 'join')

## bytecode:

   0: RESUME               
   2: LOAD_FAST            self
   4: LOAD_ATTR            field
  14: LOAD_FAST            self
  16: LOAD_ATTR            pos
  26: BINARY_SUBSCR        
  36: LOAD_FAST            beginchar
  38: COMPARE_OP           !=
  44: POP_JUMP_FORWARD_IF_FALSE to 50
  46: LOAD_CONST           ''
  48: RETURN_VALUE         
  50: LOAD_CONST           ''
  52: BUILD_LIST           
  54: STORE_FAST           slist
  56: LOAD_CONST           False
  58: STORE_FAST           quote
  60: LOAD_FAST            self
  62: COPY                 
  64: LOAD_ATTR            pos
  74: LOAD_CONST           1
  76: BINARY_OP            +=
  80: SWAP                 
  82: STORE_ATTR           pos
  92: LOAD_FAST            self
  94: LOAD_ATTR            pos
 104: LOAD_GLOBAL          NULL + len
 116: LOAD_FAST            self
 118: LOAD_ATTR            field
 128: PRECALL              
 132: CALL                 
 142: COMPARE_OP           <
 148: POP_JUMP_FORWARD_IF_FALSE to 650
 150: LOAD_FAST            quote
 152: POP_JUMP_FORWARD_IF_FALSE to 234
 154: LOAD_FAST            slist
 156: LOAD_METHOD          append
 178: LOAD_FAST            self
 180: LOAD_ATTR            field
 190: LOAD_FAST            self
 192: LOAD_ATTR            pos
 202: BINARY_SUBSCR        
 212: PRECALL              
 216: CALL                 
 226: POP_TOP              
 228: LOAD_CONST           False
 230: STORE_FAST           quote
 232: JUMP_FORWARD         to 560
 234: LOAD_FAST            self
 236: LOAD_ATTR            field
 246: LOAD_FAST            self
 248: LOAD_ATTR            pos
 258: BINARY_SUBSCR        
 268: LOAD_FAST            endchars
 270: CONTAINS_OP          
 272: POP_JUMP_FORWARD_IF_FALSE to 308
 274: LOAD_FAST            self
 276: COPY                 
 278: LOAD_ATTR            pos
 288: LOAD_CONST           1
 290: BINARY_OP            +=
 294: SWAP                 
 296: STORE_ATTR           pos
 306: JUMP_FORWARD         to 650
 308: LOAD_FAST            allowcomments
 310: POP_JUMP_FORWARD_IF_FALSE to 436
 312: LOAD_FAST            self
 314: LOAD_ATTR            field
 324: LOAD_FAST            self
 326: LOAD_ATTR            pos
 336: BINARY_SUBSCR        
 346: LOAD_CONST           '('
 348: COMPARE_OP           ==
 354: POP_JUMP_FORWARD_IF_FALSE to 436
 356: LOAD_FAST            slist
 358: LOAD_METHOD          append
 380: LOAD_FAST            self
 382: LOAD_METHOD          getcomment
 404: PRECALL              
 408: CALL                 
 418: PRECALL              
 422: CALL                 
 432: POP_TOP              
 434: JUMP_BACKWARD        to 92
 436: LOAD_FAST            self
 438: LOAD_ATTR            field
 448: LOAD_FAST            self
 450: LOAD_ATTR            pos
 460: BINARY_SUBSCR        
 470: LOAD_CONST           '\\'
 472: COMPARE_OP           ==
 478: POP_JUMP_FORWARD_IF_FALSE to 486
 480: LOAD_CONST           True
 482: STORE_FAST           quote
 484: JUMP_FORWARD         to 560
 486: LOAD_FAST            slist
 488: LOAD_METHOD          append
 510: LOAD_FAST            self
 512: LOAD_ATTR            field
 522: LOAD_FAST            self
 524: LOAD_ATTR            pos
 534: BINARY_SUBSCR        
 544: PRECALL              
 548: CALL                 
 558: POP_TOP              
 560: LOAD_FAST            self
 562: COPY                 
 564: LOAD_ATTR            pos
 574: LOAD_CONST           1
 576: BINARY_OP            +=
 580: SWAP                 
 582: STORE_ATTR           pos
 592: LOAD_FAST            self
 594: LOAD_ATTR            pos
 604: LOAD_GLOBAL          NULL + len
 616: LOAD_FAST            self
 618: LOAD_ATTR            field
 628: PRECALL              
 632: CALL                 
 642: COMPARE_OP           <
 648: POP_JUMP_BACKWARD_IF_TRUE to 150
 650: LOAD_GLOBAL          EMPTYSTRING
 662: LOAD_METHOD          join
 684: LOAD_FAST            slist
 686: PRECALL              
 690: CALL                 
 700: RETURN_VALUE         
