# Disassembly for email.Compat32
# From module file: email._policybase

## co_consts:
('Compat32', '+\n    This particular policy is the backward compatibility Policy.  It\n    replicates the behavior of the email package version 5.1.\n    ', True, <code object _sanitize_header at 0x00000240691F39F0, file "email\_policybase.py", line 281>, <code object header_source_parse at 0x000002406942CFD0, file "email\_policybase.py", line 293>, <code object header_store_parse at 0x0000024069495A30, file "email\_policybase.py", line 305>, <code object header_fetch_parse at 0x000002406945D7A0, file "email\_policybase.py", line 311>, <code object fold at 0x000002406945D5C0, file "email\_policybase.py", line 318>, <code object fold_binary at 0x00000240693D2D50, file "email\_policybase.py", line 328>, <code object _fold at 0x0000024068DC4DD0, file "email\_policybase.py", line 340>, None)

## co_names:
('__name__', '__module__', '__qualname__', '__doc__', 'mangle_from_', '_sanitize_header', 'header_source_parse', 'header_store_parse', 'header_fetch_parse', 'fold', 'fold_binary', '_fold')

## bytecode:

   0: RESUME               
   2: LOAD_NAME            __name__
   4: STORE_NAME           __module__
   6: LOAD_CONST           'Compat32'
   8: STORE_NAME           __qualname__
  10: LOAD_CONST           '+\n    This particular policy is the backward compatibility Policy.  It\n    replicates the behavior of the email package version 5.1.\n    '
  12: STORE_NAME           __doc__
  14: LOAD_CONST           True
  16: STORE_NAME           mangle_from_
  18: LOAD_CONST           <code object _sanitize_header at 0x00000240691F39F0, file "email\_policybase.py", line 281>
  20: MAKE_FUNCTION        
  22: STORE_NAME           _sanitize_header
  24: LOAD_CONST           <code object header_source_parse at 0x000002406942CFD0, file "email\_policybase.py", line 293>
  26: MAKE_FUNCTION        
  28: STORE_NAME           header_source_parse
  30: LOAD_CONST           <code object header_store_parse at 0x0000024069495A30, file "email\_policybase.py", line 305>
  32: MAKE_FUNCTION        
  34: STORE_NAME           header_store_parse
  36: LOAD_CONST           <code object header_fetch_parse at 0x000002406945D7A0, file "email\_policybase.py", line 311>
  38: MAKE_FUNCTION        
  40: STORE_NAME           header_fetch_parse
  42: LOAD_CONST           <code object fold at 0x000002406945D5C0, file "email\_policybase.py", line 318>
  44: MAKE_FUNCTION        
  46: STORE_NAME           fold
  48: LOAD_CONST           <code object fold_binary at 0x00000240693D2D50, file "email\_policybase.py", line 328>
  50: MAKE_FUNCTION        
  52: STORE_NAME           fold_binary
  54: LOAD_CONST           <code object _fold at 0x0000024068DC4DD0, file "email\_policybase.py", line 340>
  56: MAKE_FUNCTION        
  58: STORE_NAME           _fold
  60: LOAD_CONST           None
  62: RETURN_VALUE         
