# Disassembly for email.QuotedString
# From module file: email._header_value_parser

## co_consts:
('QuotedString', 'quoted-string', <code object content at 0x000002406945DF20, file "email\_header_value_parser.py", line 228>, <code object quoted_value at 0x000002406942CFD0, file "email\_header_value_parser.py", line 234>, <code object stripped_value at 0x000002406945D2F0, file "email\_header_value_parser.py", line 244>, None)

## co_names:
('__name__', '__module__', '__qualname__', 'token_type', 'property', 'content', 'quoted_value', 'stripped_value')

## bytecode:

   0: RESUME               
   2: LOAD_NAME            __name__
   4: STORE_NAME           __module__
   6: LOAD_CONST           'QuotedString'
   8: STORE_NAME           __qualname__
  10: LOAD_CONST           'quoted-string'
  12: STORE_NAME           token_type
  14: LOAD_NAME            property
  16: LOAD_CONST           <code object content at 0x000002406945DF20, file "email\_header_value_parser.py", line 228>
  18: MAKE_FUNCTION        
  20: PRECALL              
  24: CALL                 
  34: STORE_NAME           content
  36: LOAD_NAME            property
  38: LOAD_CONST           <code object quoted_value at 0x000002406942CFD0, file "email\_header_value_parser.py", line 234>
  40: MAKE_FUNCTION        
  42: PRECALL              
  46: CALL                 
  56: STORE_NAME           quoted_value
  58: LOAD_NAME            property
  60: LOAD_CONST           <code object stripped_value at 0x000002406945D2F0, file "email\_header_value_parser.py", line 244>
  62: MAKE_FUNCTION        
  64: PRECALL              
  68: CALL                 
  78: STORE_NAME           stripped_value
  80: LOAD_CONST           None
  82: RETURN_VALUE         
