# Disassembly for email.MIMEPart.clear_content.<listcomp>
# From module file: email.message

## co_consts:
('content-',)

## co_names:
('lower', 'startswith')

## bytecode:

   0: RESUME               
   2: BUILD_LIST           
   4: LOAD_FAST            .0
   6: FOR_ITER             to 104
   8: UNPACK_SEQUENCE      
  12: STORE_FAST           n
  14: STORE_FAST           v
  16: LOAD_FAST            n
  18: LOAD_METHOD          lower
  40: PRECALL              
  44: CALL                 
  54: LOAD_METHOD          startswith
  76: LOAD_CONST           'content-'
  78: PRECALL              
  82: CALL                 
  92: POP_JUMP_BACKWARD_IF_TRUE to 6
  94: LOAD_FAST            n
  96: LOAD_FAST            v
  98: BUILD_TUPLE          
 100: LIST_APPEND          
 102: JUMP_BACKWARD        to 6
 104: RETURN_VALUE         
