# Disassembly for email._PolicyBase.__repr__.<listcomp>
# From module file: email._policybase

## co_consts:
('{}={!r}',)

## co_names:
('format',)

## bytecode:

   0: RESUME               
   2: BUILD_LIST           
   4: LOAD_FAST            .0
   6: FOR_ITER             to 62
   8: UNPACK_SEQUENCE      
  12: STORE_FAST           name
  14: STORE_FAST           value
  16: LOAD_CONST           '{}={!r}'
  18: LOAD_METHOD          format
  40: LOAD_FAST            name
  42: LOAD_FAST            value
  44: PRECALL              
  48: CALL                 
  58: LIST_APPEND          
  60: JUMP_BACKWARD        to 6
  62: RETURN_VALUE         
