# Disassembly for email.InvalidBase64LengthDefect
# From module file: email.errors

## co_consts:
('InvalidBase64LengthDefect', 'base64 encoded sequence had invalid length (1 mod 4)', None)

## co_names:
('__name__', '__module__', '__qualname__', '__doc__')

## bytecode:

   0: RESUME               
   2: LOAD_NAME            __name__
   4: STORE_NAME           __module__
   6: LOAD_CONST           'InvalidBase64LengthDefect'
   8: STORE_NAME           __qualname__
  10: LOAD_CONST           'base64 encoded sequence had invalid length (1 mod 4)'
  12: STORE_NAME           __doc__
  14: LOAD_CONST           None
  16: RETURN_VALUE         
