# Disassembly for email._encode
# From module file: email.charset

## co_consts:
(None, 'ascii', 'surrogateescape')

## co_names:
('UNKNOWN8BIT', 'encode')

## bytecode:

   0: RESUME               
   2: LOAD_FAST            codec
   4: LOAD_GLOBAL          UNKNOWN8BIT
  16: COMPARE_OP           ==
  22: POP_JUMP_FORWARD_IF_FALSE to 68
  24: LOAD_FAST            string
  26: LOAD_METHOD          encode
  48: LOAD_CONST           'ascii'
  50: LOAD_CONST           'surrogateescape'
  52: PRECALL              
  56: CALL                 
  66: RETURN_VALUE         
  68: LOAD_FAST            string
  70: LOAD_METHOD          encode
  92: LOAD_FAST            codec
  94: PRECALL              
  98: CALL                 
 108: RETURN_VALUE         
