# Disassembly for email._ValueFormatter.__init__
# From module file: email.header

## co_consts:
(None,)

## co_names:
('_maxlen', '_continuation_ws', 'len', '_continuation_ws_len', '_splitchars', '_lines', '_Accumulator', '_current_line')

## bytecode:

   0: RESUME               
   2: LOAD_FAST            maxlen
   4: LOAD_FAST            self
   6: STORE_ATTR           _maxlen
  16: LOAD_FAST            continuation_ws
  18: LOAD_FAST            self
  20: STORE_ATTR           _continuation_ws
  30: LOAD_GLOBAL          NULL + len
  42: LOAD_FAST            continuation_ws
  44: PRECALL              
  48: CALL                 
  58: LOAD_FAST            self
  60: STORE_ATTR           _continuation_ws_len
  70: LOAD_FAST            splitchars
  72: LOAD_FAST            self
  74: STORE_ATTR           _splitchars
  84: BUILD_LIST           
  86: LOAD_FAST            self
  88: STORE_ATTR           _lines
  98: LOAD_GLOBAL          NULL + _Accumulator
 110: LOAD_FAST            headerlen
 112: PRECALL              
 116: CALL                 
 126: LOAD_FAST            self
 128: STORE_ATTR           _current_line
 138: LOAD_CONST           None
 140: RETURN_VALUE         
