# Disassembly for email.EmailPolicy.header_store_parse
# From module file: email.policy

## co_consts:
("+\n        The name is returned unchanged.  If the input value has a 'name'\n        attribute and it matches the name ignoring case, the value is returned\n        unchanged.  Otherwise the name and value are passed to header_factory\n        method, and the resulting custom header object is returned as the\n        value.  In this case a ValueError is raised if the input value contains\n        CR or LF characters.\n\n        ", 'name', 1, 'Header values may not contain linefeed or carriage return characters')

## co_names:
('hasattr', 'name', 'lower', 'isinstance', 'str', 'len', 'splitlines', 'ValueError', 'header_factory')

## bytecode:

   0: RESUME               
   2: LOAD_GLOBAL          NULL + hasattr
  14: LOAD_FAST            value
  16: LOAD_CONST           'name'
  18: PRECALL              
  22: CALL                 
  32: POP_JUMP_FORWARD_IF_FALSE to 136
  34: LOAD_FAST            value
  36: LOAD_ATTR            name
  46: LOAD_METHOD          lower
  68: PRECALL              
  72: CALL                 
  82: LOAD_FAST            name
  84: LOAD_METHOD          lower
 106: PRECALL              
 110: CALL                 
 120: COMPARE_OP           ==
 126: POP_JUMP_FORWARD_IF_FALSE to 136
 128: LOAD_FAST            name
 130: LOAD_FAST            value
 132: BUILD_TUPLE          
 134: RETURN_VALUE         
 136: LOAD_GLOBAL          NULL + isinstance
 148: LOAD_FAST            value
 150: LOAD_GLOBAL          str
 162: PRECALL              
 166: CALL                 
 176: POP_JUMP_FORWARD_IF_FALSE to 282
 178: LOAD_GLOBAL          NULL + len
 190: LOAD_FAST            value
 192: LOAD_METHOD          splitlines
 214: PRECALL              
 218: CALL                 
 228: PRECALL              
 232: CALL                 
 242: LOAD_CONST           1
 244: COMPARE_OP           >
 250: POP_JUMP_FORWARD_IF_FALSE to 282
 252: LOAD_GLOBAL          NULL + ValueError
 264: LOAD_CONST           'Header values may not contain linefeed or carriage return characters'
 266: PRECALL              
 270: CALL                 
 280: RAISE_VARARGS        
 282: LOAD_FAST            name
 284: LOAD_FAST            self
 286: LOAD_METHOD          header_factory
 308: LOAD_FAST            name
 310: LOAD_FAST            value
 312: PRECALL              
 316: CALL                 
 326: BUILD_TUPLE          
 328: RETURN_VALUE         
