# Disassembly for email.DecodedGenerator
# From module file: email.generator

## co_consts:
('DecodedGenerator', 'Generates a text representation of a message.\n\n    Like the Generator base class, except that non-text parts are substituted\n    with a format string representing the part.\n    ', None, ('policy',), <code object __init__ at 0x00000240693D2890, file "email\generator.py", line 453>, <code object _dispatch at 0x0000024068C30CB0, file "email\generator.py", line 483>, (None, None, None))

## co_names:
('__name__', '__module__', '__qualname__', '__doc__', '__init__', '_dispatch')

## bytecode:

   0: RESUME               
   2: LOAD_NAME            __name__
   4: STORE_NAME           __module__
   6: LOAD_CONST           'DecodedGenerator'
   8: STORE_NAME           __qualname__
  10: LOAD_CONST           'Generates a text representation of a message.\n\n    Like the Generator base class, except that non-text parts are substituted\n    with a format string representing the part.\n    '
  12: STORE_NAME           __doc__
  14: LOAD_CONST           (None, None, None)
  16: LOAD_CONST           None
  18: LOAD_CONST           ('policy',)
  20: BUILD_CONST_KEY_MAP  
  22: LOAD_CONST           <code object __init__ at 0x00000240693D2890, file "email\generator.py", line 453>
  24: MAKE_FUNCTION        defaults, kwdefaults
  26: STORE_NAME           __init__
  28: LOAD_CONST           <code object _dispatch at 0x0000024068C30CB0, file "email\generator.py", line 483>
  30: MAKE_FUNCTION        
  32: STORE_NAME           _dispatch
  34: LOAD_CONST           None
  36: RETURN_VALUE         
