# Disassembly for email.HeaderRegistry.__call__
# From module file: email.headerregistry

## co_consts:
("Create a header instance for header 'name' from 'value'.\n\n        Creates a header instance by creating a specialized class for parsing\n        and representing the specified header by combining the factory\n        base_class with a specialized class from the registry or the\n        default_class, and passing the name and value to the constructed\n        class's constructor.\n\n        ",)

## co_names:
()

## bytecode:

   0: RESUME               
   2: PUSH_NULL            
   4: LOAD_FAST            self
   6: LOAD_FAST            name
   8: BINARY_SUBSCR        
  18: LOAD_FAST            name
  20: LOAD_FAST            value
  22: PRECALL              
  26: CALL                 
  36: RETURN_VALUE         
