# Disassembly for email.ParameterizedMIMEHeader
# From module file: email.headerregistry

## co_consts:
('ParameterizedMIMEHeader', 1, <code object parse at 0x00000240691F60B0, file "email\headerregistry.py", line 446>, <code object init at 0x00000240693D3800, file "email\headerregistry.py", line 459>, <code object params at 0x000002406945D5C0, file "email\headerregistry.py", line 463>)

## co_names:
('__name__', '__module__', '__qualname__', 'max_count', 'classmethod', 'parse', 'init', 'property', 'params', '__classcell__')

## bytecode:

   0: MAKE_CELL            __class__
   2: RESUME               
   4: LOAD_NAME            __name__
   6: STORE_NAME           __module__
   8: LOAD_CONST           'ParameterizedMIMEHeader'
  10: STORE_NAME           __qualname__
  12: LOAD_CONST           1
  14: STORE_NAME           max_count
  16: LOAD_NAME            classmethod
  18: LOAD_CONST           <code object parse at 0x00000240691F60B0, file "email\headerregistry.py", line 446>
  20: MAKE_FUNCTION        
  22: PRECALL              
  26: CALL                 
  36: STORE_NAME           parse
  38: LOAD_CLOSURE         __class__
  40: BUILD_TUPLE          
  42: LOAD_CONST           <code object init at 0x00000240693D3800, file "email\headerregistry.py", line 459>
  44: MAKE_FUNCTION        closure
  46: STORE_NAME           init
  48: LOAD_NAME            property
  50: LOAD_CONST           <code object params at 0x000002406945D5C0, file "email\headerregistry.py", line 463>
  52: MAKE_FUNCTION        
  54: PRECALL              
  58: CALL                 
  68: STORE_NAME           params
  70: LOAD_CLOSURE         __class__
  72: COPY                 
  74: STORE_NAME           __classcell__
  76: RETURN_VALUE         
