# Disassembly for email.Compat32.header_source_parse
# From module file: email._policybase

## co_consts:
("+\n        The name is parsed as everything up to the ':' and returned unmodified.\n        The value is determined by stripping leading whitespace off the\n        remainder of the first line, joining all subsequent lines together, and\n        stripping any trailing carriage return or linefeed characters.\n\n        ", 0, ':', 1, ' \t', '', None, '\r\n')

## co_names:
('split', 'lstrip', 'join', 'rstrip')

## bytecode:

   0: RESUME               
   2: LOAD_FAST            sourcelines
   4: LOAD_CONST           0
   6: BINARY_SUBSCR        
  16: LOAD_METHOD          split
  38: LOAD_CONST           ':'
  40: LOAD_CONST           1
  42: PRECALL              
  46: CALL                 
  56: UNPACK_SEQUENCE      
  60: STORE_FAST           name
  62: STORE_FAST           value
  64: LOAD_FAST            value
  66: LOAD_METHOD          lstrip
  88: LOAD_CONST           ' \t'
  90: PRECALL              
  94: CALL                 
 104: LOAD_CONST           ''
 106: LOAD_METHOD          join
 128: LOAD_FAST            sourcelines
 130: LOAD_CONST           1
 132: LOAD_CONST           None
 134: BUILD_SLICE          
 136: BINARY_SUBSCR        
 146: PRECALL              
 150: CALL                 
 160: BINARY_OP            +
 164: STORE_FAST           value
 166: LOAD_FAST            name
 168: LOAD_FAST            value
 170: LOAD_METHOD          rstrip
 192: LOAD_CONST           '\r\n'
 194: PRECALL              
 198: CALL                 
 208: BUILD_TUPLE          
 210: RETURN_VALUE         
