# Disassembly for email.BufferedSubFile.unreadline
# From module file: email.feedparser

## co_consts:
(None,)

## co_names:
('NeedMoreData', '_lines', 'appendleft')

## bytecode:

   0: RESUME               
   2: LOAD_FAST            line
   4: LOAD_GLOBAL          NeedMoreData
  16: IS_OP                
  18: POP_JUMP_FORWARD_IF_TRUE to 24
  20: LOAD_ASSERTION_ERROR 
  22: RAISE_VARARGS        
  24: LOAD_FAST            self
  26: LOAD_ATTR            _lines
  36: LOAD_METHOD          appendleft
  58: LOAD_FAST            line
  60: PRECALL              
  64: CALL                 
  74: POP_TOP              
  76: LOAD_CONST           None
  78: RETURN_VALUE         
