# Disassembly for email.EmailPolicy._fold.<genexpr>
# From module file: email.policy

## co_consts:
(None,)

## co_names:
('len',)

## bytecode:

   0: COPY_FREE_VARS       
   2: RETURN_GENERATOR     
   4: POP_TOP              
   6: RESUME               
   8: LOAD_FAST            .0
  10: FOR_ITER             to 58
  12: STORE_FAST           x
  14: LOAD_GLOBAL          NULL + len
  26: LOAD_FAST            x
  28: PRECALL              
  32: CALL                 
  42: LOAD_DEREF           maxlen
  44: COMPARE_OP           >
  50: YIELD_VALUE          
  52: RESUME               
  54: POP_TOP              
  56: JUMP_BACKWARD        to 10
  58: LOAD_CONST           None
  60: RETURN_VALUE         
