# Disassembly for email.len_q.<genexpr>
# From module file: email._encoded_words

## co_consts:
(None,)

## co_names:
('len', '_q_byte_map')

## bytecode:

   0: RETURN_GENERATOR     
   2: POP_TOP              
   4: RESUME               
   6: LOAD_FAST            .0
   8: FOR_ITER             to 70
  10: STORE_FAST           x
  12: LOAD_GLOBAL          NULL + len
  24: LOAD_GLOBAL          _q_byte_map
  36: LOAD_FAST            x
  38: BINARY_SUBSCR        
  48: PRECALL              
  52: CALL                 
  62: YIELD_VALUE          
  64: RESUME               
  66: POP_TOP              
  68: JUMP_BACKWARD        to 8
  70: LOAD_CONST           None
  72: RETURN_VALUE         
