# Disassembly for email._Accumulator.__init__
# From module file: email.header

## co_consts:
(None,)

## co_names:
('_initial_size', 'super', '__init__')

## bytecode:

   0: COPY_FREE_VARS       
   2: RESUME               
   4: LOAD_FAST            initial_size
   6: LOAD_FAST            self
   8: STORE_ATTR           _initial_size
  18: LOAD_GLOBAL          NULL + super
  30: PRECALL              
  34: CALL                 
  44: LOAD_METHOD          __init__
  66: PRECALL              
  70: CALL                 
  80: POP_TOP              
  82: LOAD_CONST           None
  84: RETURN_VALUE         
