# Disassembly for email.BaseHeader.__new__
# From module file: email.headerregistry

## co_consts:
(None, 'defects', 'decoded')

## co_names:
('parse', 'utils', '_has_surrogates', '_sanitize', 'str', '__new__', 'init')

## bytecode:

   0: RESUME               
   2: LOAD_CONST           'defects'
   4: BUILD_LIST           
   6: BUILD_MAP            
   8: STORE_FAST           kwds
  10: LOAD_FAST            cls
  12: LOAD_METHOD          parse
  34: LOAD_FAST            value
  36: LOAD_FAST            kwds
  38: PRECALL              
  42: CALL                 
  52: POP_TOP              
  54: LOAD_GLOBAL          NULL + utils
  66: LOAD_ATTR            _has_surrogates
  76: LOAD_FAST            kwds
  78: LOAD_CONST           'decoded'
  80: BINARY_SUBSCR        
  90: PRECALL              
  94: CALL                 
 104: POP_JUMP_FORWARD_IF_FALSE to 164
 106: LOAD_GLOBAL          NULL + utils
 118: LOAD_ATTR            _sanitize
 128: LOAD_FAST            kwds
 130: LOAD_CONST           'decoded'
 132: BINARY_SUBSCR        
 142: PRECALL              
 146: CALL                 
 156: LOAD_FAST            kwds
 158: LOAD_CONST           'decoded'
 160: STORE_SUBSCR         
 164: LOAD_GLOBAL          str
 176: LOAD_METHOD          __new__
 198: LOAD_FAST            cls
 200: LOAD_FAST            kwds
 202: LOAD_CONST           'decoded'
 204: BINARY_SUBSCR        
 214: PRECALL              
 218: CALL                 
 228: STORE_FAST           self
 230: LOAD_FAST            kwds
 232: LOAD_CONST           'decoded'
 234: DELETE_SUBSCR        
 236: PUSH_NULL            
 238: LOAD_FAST            self
 240: LOAD_ATTR            init
 250: LOAD_FAST            name
 252: BUILD_TUPLE          
 254: BUILD_MAP            
 256: LOAD_FAST            kwds
 258: DICT_MERGE           
 260: CALL_FUNCTION_EX     
 262: POP_TOP              
 264: LOAD_FAST            self
 266: RETURN_VALUE         
