# Disassembly for email._fold_mime_parameters
# From module file: email._header_value_parser

## co_consts:
("Fold TokenList 'part' into the 'lines' list as mime parameters.\n\n    Using the decoded list of parameters and values, format them according to\n    the RFC rules, including using RFC2231 encoding if the value cannot be\n    expressed in 'encoding' and/or the parameter+value is too long to fit\n    within 'maxlen'.\n\n    ", -1, ';', 'strict', False, True, 'unknown-8bit', 'surrogateescape', 'utf-8', '', ('safe', 'errors'), "{}*={}''{}", '{}={}', 1, ' ', 2, 0, "''", 3, 78, None, ' {}*{}*={}{}')

## co_names:
('params', 'rstrip', 'endswith', 'encode', 'UnicodeEncodeError', 'utils', '_has_surrogates', 'urllib', 'parse', 'quote', 'format', 'quote_string', 'len', 'append', 'str')

## bytecode:

   0: RESUME               
   2: LOAD_FAST            part
   4: LOAD_ATTR            params
  14: GET_ITER             
  16: EXTENDED_ARG         
  18: FOR_ITER             to 1202
  20: UNPACK_SEQUENCE      
  24: STORE_FAST           name
  26: STORE_FAST           value
  28: LOAD_FAST            lines
  30: LOAD_CONST           -1
  32: BINARY_SUBSCR        
  42: LOAD_METHOD          rstrip
  64: PRECALL              
  68: CALL                 
  78: LOAD_METHOD          endswith
 100: LOAD_CONST           ';'
 102: PRECALL              
 106: CALL                 
 116: POP_JUMP_FORWARD_IF_TRUE to 150
 118: LOAD_FAST            lines
 120: LOAD_CONST           -1
 122: COPY                 
 124: COPY                 
 126: BINARY_SUBSCR        
 136: LOAD_CONST           ';'
 138: BINARY_OP            +=
 142: SWAP                 
 144: SWAP                 
 146: STORE_SUBSCR         
 150: LOAD_FAST            encoding
 152: STORE_FAST           charset
 154: LOAD_CONST           'strict'
 156: STORE_FAST           error_handler
 158: NOP                  
 160: LOAD_FAST            value
 162: LOAD_METHOD          encode
 184: LOAD_FAST            encoding
 186: PRECALL              
 190: CALL                 
 200: POP_TOP              
 202: LOAD_CONST           False
 204: STORE_FAST           encoding_required
 206: JUMP_FORWARD         to 298
 208: PUSH_EXC_INFO        
 210: LOAD_GLOBAL          UnicodeEncodeError
 222: CHECK_EXC_MATCH      
 224: POP_JUMP_FORWARD_IF_FALSE to 290
 226: POP_TOP              
 228: LOAD_CONST           True
 230: STORE_FAST           encoding_required
 232: LOAD_GLOBAL          NULL + utils
 244: LOAD_ATTR            _has_surrogates
 254: LOAD_FAST            value
 256: PRECALL              
 260: CALL                 
 270: POP_JUMP_FORWARD_IF_FALSE to 282
 272: LOAD_CONST           'unknown-8bit'
 274: STORE_FAST           charset
 276: LOAD_CONST           'surrogateescape'
 278: STORE_FAST           error_handler
 280: JUMP_FORWARD         to 286
 282: LOAD_CONST           'utf-8'
 284: STORE_FAST           charset
 286: POP_EXCEPT           
 288: JUMP_FORWARD         to 298
 290: RERAISE              
 292: COPY                 
 294: POP_EXCEPT           
 296: RERAISE              
 298: LOAD_FAST            encoding_required
 300: POP_JUMP_FORWARD_IF_FALSE to 418
 302: LOAD_GLOBAL          urllib
 314: LOAD_ATTR            parse
 324: LOAD_METHOD          quote
 346: LOAD_FAST            value
 348: LOAD_CONST           ''
 350: LOAD_FAST            error_handler
 352: KW_NAMES             
 354: PRECALL              
 358: CALL                 
 368: STORE_FAST           encoded_value
 370: LOAD_CONST           "{}*={}''{}"
 372: LOAD_METHOD          format
 394: LOAD_FAST            name
 396: LOAD_FAST            charset
 398: LOAD_FAST            encoded_value
 400: PRECALL              
 404: CALL                 
 414: STORE_FAST           tstr
 416: JUMP_FORWARD         to 488
 418: LOAD_CONST           '{}={}'
 420: LOAD_METHOD          format
 442: LOAD_FAST            name
 444: LOAD_GLOBAL          NULL + quote_string
 456: LOAD_FAST            value
 458: PRECALL              
 462: CALL                 
 472: PRECALL              
 476: CALL                 
 486: STORE_FAST           tstr
 488: LOAD_GLOBAL          NULL + len
 500: LOAD_FAST            lines
 502: LOAD_CONST           -1
 504: BINARY_SUBSCR        
 514: PRECALL              
 518: CALL                 
 528: LOAD_GLOBAL          NULL + len
 540: LOAD_FAST            tstr
 542: PRECALL              
 546: CALL                 
 556: BINARY_OP            +
 560: LOAD_CONST           1
 562: BINARY_OP            +
 566: LOAD_FAST            maxlen
 568: COMPARE_OP           <
 574: POP_JUMP_FORWARD_IF_FALSE to 614
 576: LOAD_FAST            lines
 578: LOAD_CONST           -1
 580: BINARY_SUBSCR        
 590: LOAD_CONST           ' '
 592: BINARY_OP            +
 596: LOAD_FAST            tstr
 598: BINARY_OP            +
 602: LOAD_FAST            lines
 604: LOAD_CONST           -1
 606: STORE_SUBSCR         
 610: EXTENDED_ARG         
 612: JUMP_BACKWARD        to 16
 614: LOAD_GLOBAL          NULL + len
 626: LOAD_FAST            tstr
 628: PRECALL              
 632: CALL                 
 642: LOAD_CONST           2
 644: BINARY_OP            +
 648: LOAD_FAST            maxlen
 650: COMPARE_OP           <=
 656: POP_JUMP_FORWARD_IF_FALSE to 710
 658: LOAD_FAST            lines
 660: LOAD_METHOD          append
 682: LOAD_CONST           ' '
 684: LOAD_FAST            tstr
 686: BINARY_OP            +
 690: PRECALL              
 694: CALL                 
 704: POP_TOP              
 706: EXTENDED_ARG         
 708: JUMP_BACKWARD        to 16
 710: LOAD_CONST           0
 712: STORE_FAST           section
 714: LOAD_FAST            charset
 716: LOAD_CONST           "''"
 718: BINARY_OP            +
 722: STORE_FAST           extra_chrome
 724: LOAD_FAST            value
 726: POP_JUMP_FORWARD_IF_FALSE to 1198
 728: LOAD_GLOBAL          NULL + len
 740: LOAD_FAST            name
 742: PRECALL              
 746: CALL                 
 756: LOAD_GLOBAL          NULL + len
 768: LOAD_GLOBAL          NULL + str
 780: LOAD_FAST            section
 782: PRECALL              
 786: CALL                 
 796: PRECALL              
 800: CALL                 
 810: BINARY_OP            +
 814: LOAD_CONST           3
 816: BINARY_OP            +
 820: LOAD_GLOBAL          NULL + len
 832: LOAD_FAST            extra_chrome
 834: PRECALL              
 838: CALL                 
 848: BINARY_OP            +
 852: STORE_FAST           chrome_len
 854: LOAD_FAST            maxlen
 856: LOAD_FAST            chrome_len
 858: LOAD_CONST           3
 860: BINARY_OP            +
 864: COMPARE_OP           <=
 870: POP_JUMP_FORWARD_IF_FALSE to 876
 872: LOAD_CONST           78
 874: STORE_FAST           maxlen
 876: LOAD_FAST            maxlen
 878: LOAD_FAST            chrome_len
 880: BINARY_OP            -
 884: LOAD_CONST           2
 886: BINARY_OP            -
 890: COPY                 
 892: STORE_FAST           splitpoint
 894: STORE_FAST           maxchars
 896: NOP                  
 898: LOAD_FAST            value
 900: LOAD_CONST           None
 902: LOAD_FAST            splitpoint
 904: BUILD_SLICE          
 906: BINARY_SUBSCR        
 916: STORE_FAST           partial
 918: LOAD_GLOBAL          urllib
 930: LOAD_ATTR            parse
 940: LOAD_METHOD          quote
 962: LOAD_FAST            partial
 964: LOAD_CONST           ''
 966: LOAD_FAST            error_handler
 968: KW_NAMES             
 970: PRECALL              
 974: CALL                 
 984: STORE_FAST           encoded_value
 986: LOAD_GLOBAL          NULL + len
 998: LOAD_FAST            encoded_value
1000: PRECALL              
1004: CALL                 
1014: LOAD_FAST            maxchars
1016: COMPARE_OP           <=
1022: POP_JUMP_FORWARD_IF_FALSE to 1026
1024: JUMP_FORWARD         to 1038
1026: LOAD_FAST            splitpoint
1028: LOAD_CONST           1
1030: BINARY_OP            -=
1034: STORE_FAST           splitpoint
1036: JUMP_BACKWARD        to 898
1038: LOAD_FAST            lines
1040: LOAD_METHOD          append
1062: LOAD_CONST           ' {}*{}*={}{}'
1064: LOAD_METHOD          format
1086: LOAD_FAST            name
1088: LOAD_FAST            section
1090: LOAD_FAST            extra_chrome
1092: LOAD_FAST            encoded_value
1094: PRECALL              
1098: CALL                 
1108: PRECALL              
1112: CALL                 
1122: POP_TOP              
1124: LOAD_CONST           ''
1126: STORE_FAST           extra_chrome
1128: LOAD_FAST            section
1130: LOAD_CONST           1
1132: BINARY_OP            +=
1136: STORE_FAST           section
1138: LOAD_FAST            value
1140: LOAD_FAST            splitpoint
1142: LOAD_CONST           None
1144: BUILD_SLICE          
1146: BINARY_SUBSCR        
1156: STORE_FAST           value
1158: LOAD_FAST            value
1160: POP_JUMP_FORWARD_IF_FALSE to 1194
1162: LOAD_FAST            lines
1164: LOAD_CONST           -1
1166: COPY                 
1168: COPY                 
1170: BINARY_SUBSCR        
1180: LOAD_CONST           ';'
1182: BINARY_OP            +=
1186: SWAP                 
1188: SWAP                 
1190: STORE_SUBSCR         
1194: LOAD_FAST            value
1196: POP_JUMP_BACKWARD_IF_TRUE to 728
1198: EXTENDED_ARG         
1200: JUMP_BACKWARD        to 16
1202: LOAD_CONST           None
1204: RETURN_VALUE         
