# Disassembly for email.BaseHeader.fold
# From module file: email.headerregistry

## co_consts:
('Fold header according to policy.\n\n        The parsed representation of the header is folded according to\n        RFC5322 rules, as modified by the policy.  If the parse tree\n        contains surrogateescaped bytes, the bytes are CTE encoded using\n        the charset \'unknown-8bit".\n\n        Any non-ASCII characters in the parse tree are CTE encoded using\n        charset utf-8. XXX: make this a policy setting.\n\n        The returned value is an ASCII-only string possibly containing linesep\n        characters, and ending with a linesep character.  The string includes\n        the header name and the \': \' separator.\n\n        ', 'header-name', ':', 'header-sep', ' ', 'fws', ('policy',))

## co_names:
('parser', 'Header', 'HeaderLabel', 'ValueTerminal', 'name', '_parse_tree', 'append', 'CFWSList', 'WhiteSpaceTerminal', 'fold')

## bytecode:

   0: RESUME               
   2: LOAD_GLOBAL          NULL + parser
  14: LOAD_ATTR            Header
  24: LOAD_GLOBAL          NULL + parser
  36: LOAD_ATTR            HeaderLabel
  46: LOAD_GLOBAL          NULL + parser
  58: LOAD_ATTR            ValueTerminal
  68: LOAD_FAST            self
  70: LOAD_ATTR            name
  80: LOAD_CONST           'header-name'
  82: PRECALL              
  86: CALL                 
  96: LOAD_GLOBAL          NULL + parser
 108: LOAD_ATTR            ValueTerminal
 118: LOAD_CONST           ':'
 120: LOAD_CONST           'header-sep'
 122: PRECALL              
 126: CALL                 
 136: BUILD_LIST           
 138: PRECALL              
 142: CALL                 
 152: BUILD_LIST           
 154: PRECALL              
 158: CALL                 
 168: STORE_FAST           header
 170: LOAD_FAST            self
 172: LOAD_ATTR            _parse_tree
 182: POP_JUMP_FORWARD_IF_FALSE to 302
 184: LOAD_FAST            header
 186: LOAD_METHOD          append
 208: LOAD_GLOBAL          NULL + parser
 220: LOAD_ATTR            CFWSList
 230: LOAD_GLOBAL          NULL + parser
 242: LOAD_ATTR            WhiteSpaceTerminal
 252: LOAD_CONST           ' '
 254: LOAD_CONST           'fws'
 256: PRECALL              
 260: CALL                 
 270: BUILD_LIST           
 272: PRECALL              
 276: CALL                 
 286: PRECALL              
 290: CALL                 
 300: POP_TOP              
 302: LOAD_FAST            header
 304: LOAD_METHOD          append
 326: LOAD_FAST            self
 328: LOAD_ATTR            _parse_tree
 338: PRECALL              
 342: CALL                 
 352: POP_TOP              
 354: LOAD_FAST            header
 356: LOAD_METHOD          fold
 378: LOAD_FAST            policy
 380: KW_NAMES             
 382: PRECALL              
 386: CALL                 
 396: RETURN_VALUE         
