# Disassembly for email.Header._nonctext
# From module file: email.header

## co_consts:
('True if string s is not a ctext character of RFC822.\n        ', ('(', ')', '\\'))

## co_names:
('isspace',)

## bytecode:

   0: RESUME               
   2: LOAD_FAST            s
   4: LOAD_METHOD          isspace
  26: PRECALL              
  30: CALL                 
  40: JUMP_IF_TRUE_OR_POP  to 48
  42: LOAD_FAST            s
  44: LOAD_CONST           ('(', ')', '\\')
  46: CONTAINS_OP          
  48: RETURN_VALUE         
