# Disassembly for email.DecodedGenerator.__init__
# From module file: email.generator

## co_consts:
("Like Generator.__init__() except that an additional optional\n        argument is allowed.\n\n        Walks through all subparts of a message.  If the subpart is of main\n        type `text', then it prints the decoded payload of the subpart.\n\n        Otherwise, fmt is a format string that is used instead of the message\n        payload.  fmt is expanded with the following keywords (in\n        %(keyword)s format):\n\n        type       : Full MIME type of the non-text part\n        maintype   : Main MIME type of the non-text part\n        subtype    : Sub-MIME type of the non-text part\n        filename   : Filename of the non-text part\n        description: Description associated with the non-text part\n        encoding   : Content transfer encoding of the non-text part\n\n        The default value for fmt is None, meaning\n\n        [Non-text (%(type)s) part of message omitted, filename %(filename)s]\n        ", ('policy',), None)

## co_names:
('Generator', '__init__', '_FMT', '_fmt')

## bytecode:

   0: RESUME               
   2: LOAD_GLOBAL          Generator
  14: LOAD_METHOD          __init__
  36: LOAD_FAST            self
  38: LOAD_FAST            outfp
  40: LOAD_FAST            mangle_from_
  42: LOAD_FAST            maxheaderlen
  44: LOAD_FAST            policy
  46: KW_NAMES             
  48: PRECALL              
  52: CALL                 
  62: POP_TOP              
  64: LOAD_FAST            fmt
  66: POP_JUMP_FORWARD_IF_NOT_NONE to 96
  68: LOAD_GLOBAL          _FMT
  80: LOAD_FAST            self
  82: STORE_ATTR           _fmt
  92: LOAD_CONST           None
  94: RETURN_VALUE         
  96: LOAD_FAST            fmt
  98: LOAD_FAST            self
 100: STORE_ATTR           _fmt
 110: LOAD_CONST           None
 112: RETURN_VALUE         
