# Disassembly for email.BytesGenerator._compile_re
# From module file: email.generator

## co_consts:
(None, 'ascii')

## co_names:
('re', 'compile', 'encode')

## bytecode:

   0: RESUME               
   2: LOAD_GLOBAL          NULL + re
  14: LOAD_ATTR            compile
  24: LOAD_FAST            s
  26: LOAD_METHOD          encode
  48: LOAD_CONST           'ascii'
  50: PRECALL              
  54: CALL                 
  64: LOAD_FAST            flags
  66: PRECALL              
  70: CALL                 
  80: RETURN_VALUE         
