# Disassembly for email.Message.__delitem__
# From module file: email.message

## co_consts:
('Delete all occurrences of a header, if present.\n\n        Does not raise an exception if the header is missing.\n        ', None)

## co_names:
('lower', '_headers', 'append')

## bytecode:

   0: RESUME               
   2: LOAD_FAST            name
   4: LOAD_METHOD          lower
  26: PRECALL              
  30: CALL                 
  40: STORE_FAST           name
  42: BUILD_LIST           
  44: STORE_FAST           newheaders
  46: LOAD_FAST            self
  48: LOAD_ATTR            _headers
  58: GET_ITER             
  60: FOR_ITER             to 166
  62: UNPACK_SEQUENCE      
  66: STORE_FAST           k
  68: STORE_FAST           v
  70: LOAD_FAST            k
  72: LOAD_METHOD          lower
  94: PRECALL              
  98: CALL                 
 108: LOAD_FAST            name
 110: COMPARE_OP           !=
 116: POP_JUMP_FORWARD_IF_FALSE to 164
 118: LOAD_FAST            newheaders
 120: LOAD_METHOD          append
 142: LOAD_FAST            k
 144: LOAD_FAST            v
 146: BUILD_TUPLE          
 148: PRECALL              
 152: CALL                 
 162: POP_TOP              
 164: JUMP_BACKWARD        to 60
 166: LOAD_FAST            newheaders
 168: LOAD_FAST            self
 170: STORE_ATTR           _headers
 180: LOAD_CONST           None
 182: RETURN_VALUE         
