# Disassembly for email.mktime_tz
# From module file: email._parseaddr

## co_consts:
('Turn a 10-tuple as returned by parsedate_tz() into a POSIX timestamp.', 9, None, 8, (-1,))

## co_names:
('time', 'mktime', 'calendar', 'timegm')

## bytecode:

   0: RESUME               
   2: LOAD_FAST            data
   4: LOAD_CONST           9
   6: BINARY_SUBSCR        
  16: POP_JUMP_FORWARD_IF_NOT_NONE to 80
  18: LOAD_GLOBAL          NULL + time
  30: LOAD_ATTR            mktime
  40: LOAD_FAST            data
  42: LOAD_CONST           None
  44: LOAD_CONST           8
  46: BUILD_SLICE          
  48: BINARY_SUBSCR        
  58: LOAD_CONST           (-1,)
  60: BINARY_OP            +
  64: PRECALL              
  68: CALL                 
  78: RETURN_VALUE         
  80: LOAD_GLOBAL          NULL + calendar
  92: LOAD_ATTR            timegm
 102: LOAD_FAST            data
 104: PRECALL              
 108: CALL                 
 118: STORE_FAST           t
 120: LOAD_FAST            t
 122: LOAD_FAST            data
 124: LOAD_CONST           9
 126: BINARY_SUBSCR        
 136: BINARY_OP            -
 140: RETURN_VALUE         
