# Disassembly for email._prepare_set.<listcomp>
# From module file: email.contentmanager

## co_consts:
()

## co_names:
('header_factory', 'header_source_parse')

## bytecode:

   0: COPY_FREE_VARS       
   2: RESUME               
   4: BUILD_LIST           
   6: LOAD_FAST            .0
   8: FOR_ITER             to 74
  10: STORE_FAST           header
  12: PUSH_NULL            
  14: LOAD_DEREF           mp
  16: LOAD_ATTR            header_factory
  26: LOAD_DEREF           mp
  28: LOAD_METHOD          header_source_parse
  50: LOAD_FAST            header
  52: BUILD_LIST           
  54: PRECALL              
  58: CALL                 
  68: CALL_FUNCTION_EX     
  70: LIST_APPEND          
  72: JUMP_BACKWARD        to 8
  74: RETURN_VALUE         
