# Disassembly for email.Message.__iter__
# From module file: email.message

## co_consts:
(None,)

## co_names:
('_headers',)

## bytecode:

   0: RETURN_GENERATOR     
   2: POP_TOP              
   4: RESUME               
   6: LOAD_FAST            self
   8: LOAD_ATTR            _headers
  18: GET_ITER             
  20: FOR_ITER             to 40
  22: UNPACK_SEQUENCE      
  26: STORE_FAST           field
  28: STORE_FAST           value
  30: LOAD_FAST            field
  32: YIELD_VALUE          
  34: RESUME               
  36: POP_TOP              
  38: JUMP_BACKWARD        to 20
  40: LOAD_CONST           None
  42: RETURN_VALUE         
