# Disassembly for email.Terminal
# From module file: email._header_value_parser

## co_consts:
('Terminal', True, <code object __new__ at 0x0000024069419FB0, file "email\_header_value_parser.py", line 876>, <code object __repr__ at 0x00000240693ABAF0, file "email\_header_value_parser.py", line 882>, <code object pprint at 0x0000024069449F00, file "email\_header_value_parser.py", line 885>, <code object all_defects at 0x000002406945E2E0, file "email\_header_value_parser.py", line 888>, '', <code object _pp at 0x000002406942CB20, file "email\_header_value_parser.py", line 892>, <code object pop_trailing_ws at 0x000002406943AF70, file "email\_header_value_parser.py", line 901>, <code object comments at 0x000002406943BB70, file "email\_header_value_parser.py", line 905>, <code object __getnewargs__ at 0x000002406945EF10, file "email\_header_value_parser.py", line 909>, ('',))

## co_names:
('__name__', '__module__', '__qualname__', 'as_ew_allowed', 'ew_combine_allowed', 'syntactic_break', '__new__', '__repr__', 'pprint', 'property', 'all_defects', '_pp', 'pop_trailing_ws', 'comments', '__getnewargs__', '__classcell__')

## bytecode:

   0: MAKE_CELL            __class__
   2: RESUME               
   4: LOAD_NAME            __name__
   6: STORE_NAME           __module__
   8: LOAD_CONST           'Terminal'
  10: STORE_NAME           __qualname__
  12: LOAD_CONST           True
  14: STORE_NAME           as_ew_allowed
  16: LOAD_CONST           True
  18: STORE_NAME           ew_combine_allowed
  20: LOAD_CONST           True
  22: STORE_NAME           syntactic_break
  24: LOAD_CLOSURE         __class__
  26: BUILD_TUPLE          
  28: LOAD_CONST           <code object __new__ at 0x0000024069419FB0, file "email\_header_value_parser.py", line 876>
  30: MAKE_FUNCTION        closure
  32: STORE_NAME           __new__
  34: LOAD_CLOSURE         __class__
  36: BUILD_TUPLE          
  38: LOAD_CONST           <code object __repr__ at 0x00000240693ABAF0, file "email\_header_value_parser.py", line 882>
  40: MAKE_FUNCTION        closure
  42: STORE_NAME           __repr__
  44: LOAD_CONST           <code object pprint at 0x0000024069449F00, file "email\_header_value_parser.py", line 885>
  46: MAKE_FUNCTION        
  48: STORE_NAME           pprint
  50: LOAD_NAME            property
  52: LOAD_CONST           <code object all_defects at 0x000002406945E2E0, file "email\_header_value_parser.py", line 888>
  54: MAKE_FUNCTION        
  56: PRECALL              
  60: CALL                 
  70: STORE_NAME           all_defects
  72: LOAD_CONST           ('',)
  74: LOAD_CLOSURE         __class__
  76: BUILD_TUPLE          
  78: LOAD_CONST           <code object _pp at 0x000002406942CB20, file "email\_header_value_parser.py", line 892>
  80: MAKE_FUNCTION        defaults, closure
  82: STORE_NAME           _pp
  84: LOAD_CONST           <code object pop_trailing_ws at 0x000002406943AF70, file "email\_header_value_parser.py", line 901>
  86: MAKE_FUNCTION        
  88: STORE_NAME           pop_trailing_ws
  90: LOAD_NAME            property
  92: LOAD_CONST           <code object comments at 0x000002406943BB70, file "email\_header_value_parser.py", line 905>
  94: MAKE_FUNCTION        
  96: PRECALL              
 100: CALL                 
 110: STORE_NAME           comments
 112: LOAD_CONST           <code object __getnewargs__ at 0x000002406945EF10, file "email\_header_value_parser.py", line 909>
 114: MAKE_FUNCTION        
 116: STORE_NAME           __getnewargs__
 118: LOAD_CLOSURE         __class__
 120: COPY                 
 122: STORE_NAME           __classcell__
 124: RETURN_VALUE         
