# Disassembly for email.Parser.parse
# From module file: email.parser

## co_consts:
('Create a message structure from the data in a file.\n\n        Reads all the data from the file and returns the root of the message\n        structure.  Optional headersonly is a flag specifying whether to stop\n        parsing after reading the headers or not.  The default is False,\n        meaning it parses the entire contents of the file.\n        ', ('policy',), True, 8192)

## co_names:
('FeedParser', '_class', 'policy', '_set_headersonly', 'read', 'feed', 'close')

## bytecode:

   0: RESUME               
   2: LOAD_GLOBAL          NULL + FeedParser
  14: LOAD_FAST            self
  16: LOAD_ATTR            _class
  26: LOAD_FAST            self
  28: LOAD_ATTR            policy
  38: KW_NAMES             
  40: PRECALL              
  44: CALL                 
  54: STORE_FAST           feedparser
  56: LOAD_FAST            headersonly
  58: POP_JUMP_FORWARD_IF_FALSE to 100
  60: LOAD_FAST            feedparser
  62: LOAD_METHOD          _set_headersonly
  84: PRECALL              
  88: CALL                 
  98: POP_TOP              
 100: NOP                  
 102: LOAD_FAST            fp
 104: LOAD_METHOD          read
 126: LOAD_CONST           8192
 128: PRECALL              
 132: CALL                 
 142: STORE_FAST           data
 144: LOAD_FAST            data
 146: POP_JUMP_FORWARD_IF_TRUE to 150
 148: JUMP_FORWARD         to 194
 150: LOAD_FAST            feedparser
 152: LOAD_METHOD          feed
 174: LOAD_FAST            data
 176: PRECALL              
 180: CALL                 
 190: POP_TOP              
 192: JUMP_BACKWARD        to 102
 194: LOAD_FAST            feedparser
 196: LOAD_METHOD          close
 218: PRECALL              
 222: CALL                 
 232: RETURN_VALUE         
