# Disassembly for email._extend_docstrings.<genexpr>
# From module file: email._policybase

## co_consts:
(None,)

## co_names:
('mro',)

## bytecode:

   0: RETURN_GENERATOR     
   2: POP_TOP              
   4: RESUME               
   6: LOAD_FAST            .0
   8: FOR_ITER             to 68
  10: STORE_FAST           base
  12: LOAD_FAST            base
  14: LOAD_METHOD          mro
  36: PRECALL              
  40: CALL                 
  50: GET_ITER             
  52: FOR_ITER             to 66
  54: STORE_FAST           c
  56: LOAD_FAST            c
  58: YIELD_VALUE          
  60: RESUME               
  62: POP_TOP              
  64: JUMP_BACKWARD        to 52
  66: JUMP_BACKWARD        to 8
  68: LOAD_CONST           None
  70: RETURN_VALUE         
