# Disassembly for email._validate_xtext
# From module file: email._header_value_parser

## co_consts:
('If input token contains ASCII non-printables, register a defect.', 'Non-ASCII characters found in header token', None)

## co_names:
('_non_printable_finder', 'defects', 'append', 'errors', 'NonPrintableDefect', 'utils', '_has_surrogates', 'UndecodableBytesDefect')

## bytecode:

   0: RESUME               
   2: LOAD_GLOBAL          NULL + _non_printable_finder
  14: LOAD_FAST            xtext
  16: PRECALL              
  20: CALL                 
  30: STORE_FAST           non_printables
  32: LOAD_FAST            non_printables
  34: POP_JUMP_FORWARD_IF_FALSE to 124
  36: LOAD_FAST            xtext
  38: LOAD_ATTR            defects
  48: LOAD_METHOD          append
  70: LOAD_GLOBAL          NULL + errors
  82: LOAD_ATTR            NonPrintableDefect
  92: LOAD_FAST            non_printables
  94: PRECALL              
  98: CALL                 
 108: PRECALL              
 112: CALL                 
 122: POP_TOP              
 124: LOAD_GLOBAL          NULL + utils
 136: LOAD_ATTR            _has_surrogates
 146: LOAD_FAST            xtext
 148: PRECALL              
 152: CALL                 
 162: POP_JUMP_FORWARD_IF_FALSE to 256
 164: LOAD_FAST            xtext
 166: LOAD_ATTR            defects
 176: LOAD_METHOD          append
 198: LOAD_GLOBAL          NULL + errors
 210: LOAD_ATTR            UndecodableBytesDefect
 220: LOAD_CONST           'Non-ASCII characters found in header token'
 222: PRECALL              
 226: CALL                 
 236: PRECALL              
 240: CALL                 
 250: POP_TOP              
 252: LOAD_CONST           None
 254: RETURN_VALUE         
 256: LOAD_CONST           None
 258: RETURN_VALUE         
