# Disassembly for email.header_check
# From module file: email.quoprimime

## co_consts:
('Return True if the octet should be escaped with header quopri.',)

## co_names:
('chr', '_QUOPRI_HEADER_MAP')

## bytecode:

   0: RESUME               
   2: LOAD_GLOBAL          NULL + chr
  14: LOAD_FAST            octet
  16: PRECALL              
  20: CALL                 
  30: LOAD_GLOBAL          _QUOPRI_HEADER_MAP
  42: LOAD_FAST            octet
  44: BINARY_SUBSCR        
  54: COMPARE_OP           !=
  60: RETURN_VALUE         
