# Disassembly for email.Generator.__init__
# From module file: email.generator

## co_consts:
("Create the generator for message flattening.\n\n        outfp is the output file-like object for writing the message to.  It\n        must have a write() method.\n\n        Optional mangle_from_ is a flag that, when True (the default if policy\n        is not set), escapes From_ lines in the body of the message by putting\n        a `>' in front of them.\n\n        Optional maxheaderlen specifies the longest length for a non-continued\n        header.  When a header line is longer (in characters, with tabs\n        expanded to 8 spaces) than maxheaderlen, the header will split as\n        defined in the Header class.  Set maxheaderlen to zero to disable\n        header wrapping.  The default is 78, as recommended (but not required)\n        by RFC 2822.\n\n        The policy keyword specifies a policy object that controls a number of\n        aspects of the generator's operation.  If no policy is specified,\n        the policy associated with the Message object passed to the\n        flatten method is used.\n\n        ", None, True)

## co_names:
('mangle_from_', '_fp', '_mangle_from_', 'maxheaderlen', 'policy')

## bytecode:

   0: RESUME               
   2: LOAD_FAST            mangle_from_
   4: POP_JUMP_FORWARD_IF_NOT_NONE to 28
   6: LOAD_FAST            policy
   8: POP_JUMP_FORWARD_IF_NOT_NONE to 14
  10: LOAD_CONST           True
  12: JUMP_FORWARD         to 26
  14: LOAD_FAST            policy
  16: LOAD_ATTR            mangle_from_
  26: STORE_FAST           mangle_from_
  28: LOAD_FAST            outfp
  30: LOAD_FAST            self
  32: STORE_ATTR           _fp
  42: LOAD_FAST            mangle_from_
  44: LOAD_FAST            self
  46: STORE_ATTR           _mangle_from_
  56: LOAD_FAST            maxheaderlen
  58: LOAD_FAST            self
  60: STORE_ATTR           maxheaderlen
  70: LOAD_FAST            policy
  72: LOAD_FAST            self
  74: STORE_ATTR           policy
  84: LOAD_CONST           None
  86: RETURN_VALUE         
