# Disassembly for email.UnstructuredHeader.parse
# From module file: email.headerregistry

## co_consts:
(None, 'parse_tree', 'decoded')

## co_names:
('value_parser', 'str')

## bytecode:

   0: RESUME               
   2: LOAD_FAST            cls
   4: LOAD_METHOD          value_parser
  26: LOAD_FAST            value
  28: PRECALL              
  32: CALL                 
  42: LOAD_FAST            kwds
  44: LOAD_CONST           'parse_tree'
  46: STORE_SUBSCR         
  50: LOAD_GLOBAL          NULL + str
  62: LOAD_FAST            kwds
  64: LOAD_CONST           'parse_tree'
  66: BINARY_SUBSCR        
  76: PRECALL              
  80: CALL                 
  90: LOAD_FAST            kwds
  92: LOAD_CONST           'decoded'
  94: STORE_SUBSCR         
  98: LOAD_CONST           None
 100: RETURN_VALUE         
