# Disassembly for email.ParameterizedMIMEHeader.parse.<dictcomp>
# From module file: email.headerregistry

## co_consts:
()

## co_names:
('utils', '_sanitize', 'lower')

## bytecode:

   0: RESUME               
   2: BUILD_MAP            
   4: LOAD_FAST            .0
   6: FOR_ITER             to 132
   8: UNPACK_SEQUENCE      
  12: STORE_FAST           name
  14: STORE_FAST           value
  16: LOAD_GLOBAL          NULL + utils
  28: LOAD_ATTR            _sanitize
  38: LOAD_FAST            name
  40: PRECALL              
  44: CALL                 
  54: LOAD_METHOD          lower
  76: PRECALL              
  80: CALL                 
  90: LOAD_GLOBAL          NULL + utils
 102: LOAD_ATTR            _sanitize
 112: LOAD_FAST            value
 114: PRECALL              
 118: CALL                 
 128: MAP_ADD              
 130: JUMP_BACKWARD        to 6
 132: RETURN_VALUE         
