# Disassembly for email.Message.get_payload
# From module file: email.message

## co_consts:
("Return a reference to the payload.\n\n        The payload will either be a list object or a string.  If you mutate\n        the list object, you modify the message's payload in place.  Optional\n        i returns that index into the payload.\n\n        Optional decode is a flag indicating whether the payload should be\n        decoded or not, according to the Content-Transfer-Encoding header\n        (default is False).\n\n        When True and the message is not a multipart, the payload will be\n        decoded if this header's value is `quoted-printable' or `base64'.  If\n        some other encoding is used, or the header is missing, or if the\n        payload has bogus data (i.e. bogus base64 or uuencoded data), the\n        payload is returned as-is.\n\n        If the message is a multipart and the decode flag is True, then None\n        is returned.\n        ", None, 'Expected list, got %s', 'content-transfer-encoding', '', 'ascii', 'surrogateescape', 'charset', 'replace', 'raw-unicode-escape', 'quoted-printable', 'base64', b'', ('x-uuencode', 'uuencode', 'uue', 'x-uue'))

## co_names:
('is_multipart', '_payload', 'isinstance', 'list', 'TypeError', 'type', 'str', 'get', 'lower', 'utils', '_has_surrogates', 'encode', 'decode', 'get_param', 'LookupError', 'UnicodeError', 'quopri', 'decodestring', 'decode_b', 'join', 'splitlines', 'policy', 'handle_defect', '_decode_uu', 'ValueError')

## bytecode:

   0: RESUME               
   2: LOAD_FAST            self
   4: LOAD_METHOD          is_multipart
  26: PRECALL              
  30: CALL                 
  40: POP_JUMP_FORWARD_IF_FALSE to 94
  42: LOAD_FAST            decode
  44: POP_JUMP_FORWARD_IF_FALSE to 50
  46: LOAD_CONST           None
  48: RETURN_VALUE         
  50: LOAD_FAST            i
  52: POP_JUMP_FORWARD_IF_NOT_NONE to 68
  54: LOAD_FAST            self
  56: LOAD_ATTR            _payload
  66: RETURN_VALUE         
  68: LOAD_FAST            self
  70: LOAD_ATTR            _payload
  80: LOAD_FAST            i
  82: BINARY_SUBSCR        
  92: RETURN_VALUE         
  94: LOAD_FAST            i
  96: POP_JUMP_FORWARD_IF_NONE to 222
  98: LOAD_GLOBAL          NULL + isinstance
 110: LOAD_FAST            self
 112: LOAD_ATTR            _payload
 122: LOAD_GLOBAL          list
 134: PRECALL              
 138: CALL                 
 148: POP_JUMP_FORWARD_IF_TRUE to 222
 150: LOAD_GLOBAL          NULL + TypeError
 162: LOAD_CONST           'Expected list, got %s'
 164: LOAD_GLOBAL          NULL + type
 176: LOAD_FAST            self
 178: LOAD_ATTR            _payload
 188: PRECALL              
 192: CALL                 
 202: BINARY_OP            %
 206: PRECALL              
 210: CALL                 
 220: RAISE_VARARGS        
 222: LOAD_FAST            self
 224: LOAD_ATTR            _payload
 234: STORE_FAST           payload
 236: LOAD_GLOBAL          NULL + str
 248: LOAD_FAST            self
 250: LOAD_METHOD          get
 272: LOAD_CONST           'content-transfer-encoding'
 274: LOAD_CONST           ''
 276: PRECALL              
 280: CALL                 
 290: PRECALL              
 294: CALL                 
 304: LOAD_METHOD          lower
 326: PRECALL              
 330: CALL                 
 340: STORE_FAST           cte
 342: LOAD_GLOBAL          NULL + isinstance
 354: LOAD_FAST            payload
 356: LOAD_GLOBAL          str
 368: PRECALL              
 372: CALL                 
 382: POP_JUMP_FORWARD_IF_FALSE to 762
 384: LOAD_GLOBAL          NULL + utils
 396: LOAD_ATTR            _has_surrogates
 406: LOAD_FAST            payload
 408: PRECALL              
 412: CALL                 
 422: POP_JUMP_FORWARD_IF_FALSE to 638
 424: LOAD_FAST            payload
 426: LOAD_METHOD          encode
 448: LOAD_CONST           'ascii'
 450: LOAD_CONST           'surrogateescape'
 452: PRECALL              
 456: CALL                 
 466: STORE_FAST           bpayload
 468: LOAD_FAST            decode
 470: POP_JUMP_FORWARD_IF_TRUE to 636
 472: NOP                  
 474: LOAD_FAST            bpayload
 476: LOAD_METHOD          decode
 498: LOAD_FAST            self
 500: LOAD_METHOD          get_param
 522: LOAD_CONST           'charset'
 524: LOAD_CONST           'ascii'
 526: PRECALL              
 530: CALL                 
 540: LOAD_CONST           'replace'
 542: PRECALL              
 546: CALL                 
 556: STORE_FAST           payload
 558: JUMP_FORWARD         to 762
 560: PUSH_EXC_INFO        
 562: LOAD_GLOBAL          LookupError
 574: CHECK_EXC_MATCH      
 576: POP_JUMP_FORWARD_IF_FALSE to 628
 578: POP_TOP              
 580: LOAD_FAST            bpayload
 582: LOAD_METHOD          decode
 604: LOAD_CONST           'ascii'
 606: LOAD_CONST           'replace'
 608: PRECALL              
 612: CALL                 
 622: STORE_FAST           payload
 624: POP_EXCEPT           
 626: JUMP_FORWARD         to 762
 628: RERAISE              
 630: COPY                 
 632: POP_EXCEPT           
 634: RERAISE              
 636: JUMP_FORWARD         to 762
 638: LOAD_FAST            decode
 640: POP_JUMP_FORWARD_IF_FALSE to 762
 642: NOP                  
 644: LOAD_FAST            payload
 646: LOAD_METHOD          encode
 668: LOAD_CONST           'ascii'
 670: PRECALL              
 674: CALL                 
 684: STORE_FAST           bpayload
 686: JUMP_FORWARD         to 762
 688: PUSH_EXC_INFO        
 690: LOAD_GLOBAL          UnicodeError
 702: CHECK_EXC_MATCH      
 704: POP_JUMP_FORWARD_IF_FALSE to 754
 706: POP_TOP              
 708: LOAD_FAST            payload
 710: LOAD_METHOD          encode
 732: LOAD_CONST           'raw-unicode-escape'
 734: PRECALL              
 738: CALL                 
 748: STORE_FAST           bpayload
 750: POP_EXCEPT           
 752: JUMP_FORWARD         to 762
 754: RERAISE              
 756: COPY                 
 758: POP_EXCEPT           
 760: RERAISE              
 762: LOAD_FAST            decode
 764: POP_JUMP_FORWARD_IF_TRUE to 770
 766: LOAD_FAST            payload
 768: RETURN_VALUE         
 770: LOAD_FAST            cte
 772: LOAD_CONST           'quoted-printable'
 774: COMPARE_OP           ==
 780: POP_JUMP_FORWARD_IF_FALSE to 822
 782: LOAD_GLOBAL          NULL + quopri
 794: LOAD_ATTR            decodestring
 804: LOAD_FAST            bpayload
 806: PRECALL              
 810: CALL                 
 820: RETURN_VALUE         
 822: LOAD_FAST            cte
 824: LOAD_CONST           'base64'
 826: COMPARE_OP           ==
 832: POP_JUMP_FORWARD_IF_FALSE to 1012
 834: LOAD_GLOBAL          NULL + decode_b
 846: LOAD_CONST           b''
 848: LOAD_METHOD          join
 870: LOAD_FAST            bpayload
 872: LOAD_METHOD          splitlines
 894: PRECALL              
 898: CALL                 
 908: PRECALL              
 912: CALL                 
 922: PRECALL              
 926: CALL                 
 936: UNPACK_SEQUENCE      
 940: STORE_FAST           value
 942: STORE_FAST           defects
 944: LOAD_FAST            defects
 946: GET_ITER             
 948: FOR_ITER             to 1008
 950: STORE_FAST           defect
 952: LOAD_FAST            self
 954: LOAD_ATTR            policy
 964: LOAD_METHOD          handle_defect
 986: LOAD_FAST            self
 988: LOAD_FAST            defect
 990: PRECALL              
 994: CALL                 
1004: POP_TOP              
1006: JUMP_BACKWARD        to 948
1008: LOAD_FAST            value
1010: RETURN_VALUE         
1012: LOAD_FAST            cte
1014: LOAD_CONST           ('x-uuencode', 'uuencode', 'uue', 'x-uue')
1016: CONTAINS_OP          
1018: POP_JUMP_FORWARD_IF_FALSE to 1088
1020: NOP                  
1022: LOAD_GLOBAL          NULL + _decode_uu
1034: LOAD_FAST            bpayload
1036: PRECALL              
1040: CALL                 
1050: RETURN_VALUE         
1052: PUSH_EXC_INFO        
1054: LOAD_GLOBAL          ValueError
1066: CHECK_EXC_MATCH      
1068: POP_JUMP_FORWARD_IF_FALSE to 1080
1070: POP_TOP              
1072: LOAD_FAST            bpayload
1074: SWAP                 
1076: POP_EXCEPT           
1078: RETURN_VALUE         
1080: RERAISE              
1082: COPY                 
1084: POP_EXCEPT           
1086: RERAISE              
1088: LOAD_GLOBAL          NULL + isinstance
1100: LOAD_FAST            payload
1102: LOAD_GLOBAL          str
1114: PRECALL              
1118: CALL                 
1128: POP_JUMP_FORWARD_IF_FALSE to 1134
1130: LOAD_FAST            bpayload
1132: RETURN_VALUE         
1134: LOAD_FAST            payload
1136: RETURN_VALUE         
