# Disassembly for email.ContentTransferEncodingHeader
# From module file: email.headerregistry

## co_consts:
('ContentTransferEncodingHeader', 1, <code object parse at 0x00000240691C1BB0, file "email\headerregistry.py", line 510>, <code object init at 0x00000240693AB5F0, file "email\headerregistry.py", line 516>, <code object cte at 0x00000240694949F0, file "email\headerregistry.py", line 520>)

## co_names:
('__name__', '__module__', '__qualname__', 'max_count', 'staticmethod', 'parser', 'parse_content_transfer_encoding_header', 'value_parser', 'classmethod', 'parse', 'init', 'property', 'cte', '__classcell__')

## bytecode:

   0: MAKE_CELL            __class__
   2: RESUME               
   4: LOAD_NAME            __name__
   6: STORE_NAME           __module__
   8: LOAD_CONST           'ContentTransferEncodingHeader'
  10: STORE_NAME           __qualname__
  12: LOAD_CONST           1
  14: STORE_NAME           max_count
  16: PUSH_NULL            
  18: LOAD_NAME            staticmethod
  20: LOAD_NAME            parser
  22: LOAD_ATTR            parse_content_transfer_encoding_header
  32: PRECALL              
  36: CALL                 
  46: STORE_NAME           value_parser
  48: LOAD_NAME            classmethod
  50: LOAD_CONST           <code object parse at 0x00000240691C1BB0, file "email\headerregistry.py", line 510>
  52: MAKE_FUNCTION        
  54: PRECALL              
  58: CALL                 
  68: STORE_NAME           parse
  70: LOAD_CLOSURE         __class__
  72: BUILD_TUPLE          
  74: LOAD_CONST           <code object init at 0x00000240693AB5F0, file "email\headerregistry.py", line 516>
  76: MAKE_FUNCTION        closure
  78: STORE_NAME           init
  80: LOAD_NAME            property
  82: LOAD_CONST           <code object cte at 0x00000240694949F0, file "email\headerregistry.py", line 520>
  84: MAKE_FUNCTION        
  86: PRECALL              
  90: CALL                 
 100: STORE_NAME           cte
 102: LOAD_CLOSURE         __class__
 104: COPY                 
 106: STORE_NAME           __classcell__
 108: RETURN_VALUE         
