# Disassembly for email.Parameter.param_value
# From module file: email._header_value_parser

## co_consts:
(None, 'value', 'quoted-string', 'bare-quoted-string', '')

## co_names:
('token_type', 'stripped_value')

## bytecode:

   0: RESUME               
   2: LOAD_FAST            self
   4: GET_ITER             
   6: FOR_ITER             to 164
   8: STORE_FAST           token
  10: LOAD_FAST            token
  12: LOAD_ATTR            token_type
  22: LOAD_CONST           'value'
  24: COMPARE_OP           ==
  30: POP_JUMP_FORWARD_IF_FALSE to 50
  32: LOAD_FAST            token
  34: LOAD_ATTR            stripped_value
  44: SWAP                 
  46: POP_TOP              
  48: RETURN_VALUE         
  50: LOAD_FAST            token
  52: LOAD_ATTR            token_type
  62: LOAD_CONST           'quoted-string'
  64: COMPARE_OP           ==
  70: POP_JUMP_FORWARD_IF_FALSE to 162
  72: LOAD_FAST            token
  74: GET_ITER             
  76: FOR_ITER             to 162
  78: STORE_FAST           token
  80: LOAD_FAST            token
  82: LOAD_ATTR            token_type
  92: LOAD_CONST           'bare-quoted-string'
  94: COMPARE_OP           ==
 100: POP_JUMP_FORWARD_IF_FALSE to 160
 102: LOAD_FAST            token
 104: GET_ITER             
 106: FOR_ITER             to 160
 108: STORE_FAST           token
 110: LOAD_FAST            token
 112: LOAD_ATTR            token_type
 122: LOAD_CONST           'value'
 124: COMPARE_OP           ==
 130: POP_JUMP_FORWARD_IF_FALSE to 158
 132: LOAD_FAST            token
 134: LOAD_ATTR            stripped_value
 144: SWAP                 
 146: POP_TOP              
 148: SWAP                 
 150: POP_TOP              
 152: SWAP                 
 154: POP_TOP              
 156: RETURN_VALUE         
 158: JUMP_BACKWARD        to 106
 160: JUMP_BACKWARD        to 76
 162: JUMP_BACKWARD        to 6
 164: LOAD_CONST           ''
 166: RETURN_VALUE         
