# Disassembly for email._append_doc
# From module file: email._policybase

## co_consts:
(None, '\n', 1, 0)

## co_names:
('rsplit', 'split')

## bytecode:

   0: RESUME               
   2: LOAD_FAST            doc
   4: LOAD_METHOD          rsplit
  26: LOAD_CONST           '\n'
  28: LOAD_CONST           1
  30: PRECALL              
  34: CALL                 
  44: LOAD_CONST           0
  46: BINARY_SUBSCR        
  56: STORE_FAST           doc
  58: LOAD_FAST            added_doc
  60: LOAD_METHOD          split
  82: LOAD_CONST           '\n'
  84: LOAD_CONST           1
  86: PRECALL              
  90: CALL                 
 100: LOAD_CONST           1
 102: BINARY_SUBSCR        
 112: STORE_FAST           added_doc
 114: LOAD_FAST            doc
 116: LOAD_CONST           '\n'
 118: BINARY_OP            +
 122: LOAD_FAST            added_doc
 124: BINARY_OP            +
 128: RETURN_VALUE         
