# Disassembly for email.NoBoundaryInMultipartDefect
# From module file: email.errors

## co_consts:
('NoBoundaryInMultipartDefect', 'A message claimed to be a multipart but had no boundary parameter.', None)

## co_names:
('__name__', '__module__', '__qualname__', '__doc__')

## bytecode:

   0: RESUME               
   2: LOAD_NAME            __name__
   4: STORE_NAME           __module__
   6: LOAD_CONST           'NoBoundaryInMultipartDefect'
   8: STORE_NAME           __qualname__
  10: LOAD_CONST           'A message claimed to be a multipart but had no boundary parameter.'
  12: STORE_NAME           __doc__
  14: LOAD_CONST           None
  16: RETURN_VALUE         
