# Disassembly for email.AddressHeader.init
# From module file: email.headerregistry

## co_consts:
(None, 'groups')

## co_names:
('tuple', 'pop', '_groups', '_addresses', 'super', 'init')

## bytecode:

   0: COPY_FREE_VARS       
   2: RESUME               
   4: LOAD_GLOBAL          NULL + tuple
  16: LOAD_FAST            kw
  18: LOAD_METHOD          pop
  40: LOAD_CONST           'groups'
  42: PRECALL              
  46: CALL                 
  56: PRECALL              
  60: CALL                 
  70: LOAD_FAST            self
  72: STORE_ATTR           _groups
  82: LOAD_CONST           None
  84: LOAD_FAST            self
  86: STORE_ATTR           _addresses
  96: PUSH_NULL            
  98: LOAD_GLOBAL          NULL + super
 110: PRECALL              
 114: CALL                 
 124: LOAD_ATTR            init
 134: LOAD_FAST            args
 136: BUILD_MAP            
 138: LOAD_FAST            kw
 140: DICT_MERGE           
 142: CALL_FUNCTION_EX     
 144: POP_TOP              
 146: LOAD_CONST           None
 148: RETURN_VALUE         
