# Disassembly for email._prepare_set
# From module file: email.contentmanager

## co_consts:
(None, '/', 'Content-Type', 0, 'name', <code object <listcomp> at 0x000002406944B330, file "email\contentmanager.py", line 102>, 'Invalid header: {}', ('policy',))

## co_names:
('join', 'hasattr', 'policy', 'defects', 'name', 'email', 'errors', 'HeaderDefect', 'ValueError', 'format', 'fold')

## bytecode:

   0: MAKE_CELL            mp
   2: RESUME               
   4: LOAD_CONST           '/'
   6: LOAD_METHOD          join
  28: LOAD_FAST            maintype
  30: LOAD_FAST            subtype
  32: BUILD_TUPLE          
  34: PRECALL              
  38: CALL                 
  48: LOAD_FAST            msg
  50: LOAD_CONST           'Content-Type'
  52: STORE_SUBSCR         
  56: LOAD_FAST            headers
  58: POP_JUMP_FORWARD_IF_FALSE to 398
  60: LOAD_GLOBAL          NULL + hasattr
  72: LOAD_FAST            headers
  74: LOAD_CONST           0
  76: BINARY_SUBSCR        
  86: LOAD_CONST           'name'
  88: PRECALL              
  92: CALL                 
 102: POP_JUMP_FORWARD_IF_TRUE to 146
 104: LOAD_FAST            msg
 106: LOAD_ATTR            policy
 116: STORE_DEREF          mp
 118: LOAD_CLOSURE         mp
 120: BUILD_TUPLE          
 122: LOAD_CONST           <code object <listcomp> at 0x000002406944B330, file "email\contentmanager.py", line 102>
 124: MAKE_FUNCTION        closure
 126: LOAD_FAST            headers
 128: GET_ITER             
 130: PRECALL              
 134: CALL                 
 144: STORE_FAST           headers
 146: NOP                  
 148: LOAD_FAST            headers
 150: GET_ITER             
 152: FOR_ITER             to 218
 154: STORE_FAST           header
 156: LOAD_FAST            header
 158: LOAD_ATTR            defects
 168: POP_JUMP_FORWARD_IF_FALSE to 196
 170: LOAD_FAST            header
 172: LOAD_ATTR            defects
 182: LOAD_CONST           0
 184: BINARY_SUBSCR        
 194: RAISE_VARARGS        
 196: LOAD_FAST            header
 198: LOAD_FAST            msg
 200: LOAD_FAST            header
 202: LOAD_ATTR            name
 212: STORE_SUBSCR         
 216: JUMP_BACKWARD        to 152
 218: LOAD_CONST           None
 220: RETURN_VALUE         
 222: PUSH_EXC_INFO        
 224: LOAD_GLOBAL          email
 236: LOAD_ATTR            errors
 246: LOAD_ATTR            HeaderDefect
 256: CHECK_EXC_MATCH      
 258: POP_JUMP_FORWARD_IF_FALSE to 390
 260: STORE_FAST           exc
 262: LOAD_GLOBAL          NULL + ValueError
 274: LOAD_CONST           'Invalid header: {}'
 276: LOAD_METHOD          format
 298: LOAD_FAST            header
 300: LOAD_METHOD          fold
 322: LOAD_FAST            msg
 324: LOAD_ATTR            policy
 334: KW_NAMES             
 336: PRECALL              
 340: CALL                 
 350: PRECALL              
 354: CALL                 
 364: PRECALL              
 368: CALL                 
 378: LOAD_FAST            exc
 380: RAISE_VARARGS        
 382: LOAD_CONST           None
 384: STORE_FAST           exc
 386: DELETE_FAST          exc
 388: RERAISE              
 390: RERAISE              
 392: COPY                 
 394: POP_EXCEPT           
 396: RERAISE              
 398: LOAD_CONST           None
 400: RETURN_VALUE         
