# Disassembly for email.AddressHeader.parse.<listcomp>
# From module file: email.headerregistry

## co_consts:
()

## co_names:
('str',)

## bytecode:

   0: RESUME               
   2: BUILD_LIST           
   4: LOAD_FAST            .0
   6: FOR_ITER             to 42
   8: STORE_FAST           item
  10: LOAD_GLOBAL          NULL + str
  22: LOAD_FAST            item
  24: PRECALL              
  28: CALL                 
  38: LIST_APPEND          
  40: JUMP_BACKWARD        to 6
  42: RETURN_VALUE         
