# Disassembly for email.EmailPolicy._fold
# From module file: email.policy

## co_consts:
(None, 'name', ('policy',), 'all', 'long', 0, 2, <code object <genexpr> at 0x00000240693EB830, file "email\policy.py", line 212>, 1, '', ': ')

## co_names:
('hasattr', 'fold', 'max_line_length', 'sys', 'maxsize', 'splitlines', 'refold_source', 'len', 'any', '_has_surrogates', 'header_factory', 'join', 'linesep')

## bytecode:

   0: MAKE_CELL            maxlen
   2: RESUME               
   4: LOAD_GLOBAL          NULL + hasattr
  16: LOAD_FAST            value
  18: LOAD_CONST           'name'
  20: PRECALL              
  24: CALL                 
  34: POP_JUMP_FORWARD_IF_FALSE to 80
  36: LOAD_FAST            value
  38: LOAD_METHOD          fold
  60: LOAD_FAST            self
  62: KW_NAMES             
  64: PRECALL              
  68: CALL                 
  78: RETURN_VALUE         
  80: LOAD_FAST            self
  82: LOAD_ATTR            max_line_length
  92: POP_JUMP_FORWARD_IF_FALSE to 108
  94: LOAD_FAST            self
  96: LOAD_ATTR            max_line_length
 106: JUMP_FORWARD         to 130
 108: LOAD_GLOBAL          sys
 120: LOAD_ATTR            maxsize
 130: STORE_DEREF          maxlen
 132: LOAD_FAST            value
 134: LOAD_METHOD          splitlines
 156: PRECALL              
 160: CALL                 
 170: STORE_FAST           lines
 172: LOAD_FAST            self
 174: LOAD_ATTR            refold_source
 184: LOAD_CONST           'all'
 186: COMPARE_OP           ==
 192: JUMP_IF_TRUE_OR_POP  to 376
 194: LOAD_FAST            self
 196: LOAD_ATTR            refold_source
 206: LOAD_CONST           'long'
 208: COMPARE_OP           ==
 214: JUMP_IF_FALSE_OR_POP to 376
 216: LOAD_FAST            lines
 218: POP_JUMP_FORWARD_IF_FALSE to 308
 220: LOAD_GLOBAL          NULL + len
 232: LOAD_FAST            lines
 234: LOAD_CONST           0
 236: BINARY_SUBSCR        
 246: PRECALL              
 250: CALL                 
 260: LOAD_GLOBAL          NULL + len
 272: LOAD_FAST            name
 274: PRECALL              
 278: CALL                 
 288: BINARY_OP            +
 292: LOAD_CONST           2
 294: BINARY_OP            +
 298: LOAD_DEREF           maxlen
 300: COMPARE_OP           >
 306: JUMP_IF_TRUE_OR_POP  to 376
 308: LOAD_GLOBAL          NULL + any
 320: LOAD_CLOSURE         maxlen
 322: BUILD_TUPLE          
 324: LOAD_CONST           <code object <genexpr> at 0x00000240693EB830, file "email\policy.py", line 212>
 326: MAKE_FUNCTION        closure
 328: LOAD_FAST            lines
 330: LOAD_CONST           1
 332: LOAD_CONST           None
 334: BUILD_SLICE          
 336: BINARY_SUBSCR        
 346: GET_ITER             
 348: PRECALL              
 352: CALL                 
 362: PRECALL              
 366: CALL                 
 376: STORE_FAST           refold
 378: LOAD_FAST            refold
 380: POP_JUMP_FORWARD_IF_TRUE to 416
 382: LOAD_FAST            refold_binary
 384: POP_JUMP_FORWARD_IF_FALSE to 538
 386: LOAD_GLOBAL          NULL + _has_surrogates
 398: LOAD_FAST            value
 400: PRECALL              
 404: CALL                 
 414: POP_JUMP_FORWARD_IF_FALSE to 538
 416: LOAD_FAST            self
 418: LOAD_METHOD          header_factory
 440: LOAD_FAST            name
 442: LOAD_CONST           ''
 444: LOAD_METHOD          join
 466: LOAD_FAST            lines
 468: PRECALL              
 472: CALL                 
 482: PRECALL              
 486: CALL                 
 496: LOAD_METHOD          fold
 518: LOAD_FAST            self
 520: KW_NAMES             
 522: PRECALL              
 526: CALL                 
 536: RETURN_VALUE         
 538: LOAD_FAST            name
 540: LOAD_CONST           ': '
 542: BINARY_OP            +
 546: LOAD_FAST            self
 548: LOAD_ATTR            linesep
 558: LOAD_METHOD          join
 580: LOAD_FAST            lines
 582: PRECALL              
 586: CALL                 
 596: BINARY_OP            +
 600: LOAD_FAST            self
 602: LOAD_ATTR            linesep
 612: BINARY_OP            +
 616: RETURN_VALUE         
