# Disassembly for email.Message
# From module file: email.message

## co_consts:
('Message', "Basic message object.\n\n    A message object is defined as something that has a bunch of RFC 2822\n    headers and a payload.  It may optionally have an envelope header\n    (a.k.a. Unix-From or From_ header).  If the message is a container (i.e. a\n    multipart or a message/rfc822), then the payload is a list of Message\n    objects, otherwise it is a string.\n\n    Message objects implement part of the `mapping' interface, which assumes\n    there is exactly one occurrence of the header per message.  Some headers\n    do in fact appear multiple times (e.g. Received) and for those headers,\n    you must use the explicit API to set or get all the headers.  Not all of\n    the mapping methods are implemented.\n    ", <code object __init__ at 0x00000240693AA470, file "email\message.py", line 150>, <code object __str__ at 0x000002406945FF00, file "email\message.py", line 162>, False, 0, None, <code object as_string at 0x000002406921FB20, file "email\message.py", line 167>, <code object __bytes__ at 0x000002406945DB60, file "email\message.py", line 191>, <code object as_bytes at 0x000002406921F840, file "email\message.py", line 196>, <code object is_multipart at 0x000002406945E100, file "email\message.py", line 211>, <code object set_unixfrom at 0x0000024069427C50, file "email\message.py", line 218>, <code object get_unixfrom at 0x00000240694946B0, file "email\message.py", line 221>, <code object attach at 0x00000240691F23A0, file "email\message.py", line 227>, <code object get_payload at 0x0000024068D5FCF0, file "email\message.py", line 243>, <code object set_payload at 0x0000024068BF6C60, file "email\message.py", line 330>, <code object set_charset at 0x0000024066C3D9C0, file "email\message.py", line 350>, <code object get_charset at 0x0000024069495F10, file "email\message.py", line 397>, <code object __len__ at 0x000002406945D5C0, file "email\message.py", line 405>, <code object __getitem__ at 0x000002406945CF30, file "email\message.py", line 409>, <code object __setitem__ at 0x0000024068DB6A10, file "email\message.py", line 420>, <code object __delitem__ at 0x000002406921FC90, file "email\message.py", line 438>, <code object __contains__ at 0x000002406944A560, file "email\message.py", line 450>, <code object __iter__ at 0x000002406945D2F0, file "email\message.py", line 453>, <code object keys at 0x0000024069465DF0, file "email\message.py", line 457>, <code object values at 0x000002406945FC30, file "email\message.py", line 467>, <code object items at 0x000002406945D6B0, file "email\message.py", line 478>, <code object get at 0x000002406921FE00, file "email\message.py", line 489>, <code object set_raw at 0x00000240693EB830, file "email\message.py", line 506>, <code object raw_items at 0x000002406944AAB0, file "email\message.py", line 513>, <code object get_all at 0x00000240691F60B0, file "email\message.py", line 524>, <code object add_header at 0x0000024068C8DB20, file "email\message.py", line 542>, <code object replace_header at 0x000002406931FA30, file "email\message.py", line 572>, <code object get_content_type at 0x00000240691A7BB0, file "email\message.py", line 591>, <code object get_content_maintype at 0x000002406941AE50, file "email\message.py", line 615>, <code object get_content_subtype at 0x000002406941A9D0, file "email\message.py", line 624>, <code object get_default_type at 0x0000024069495890, file "email\message.py", line 633>, <code object set_default_type at 0x0000024069495BD0, file "email\message.py", line 642>, <code object _get_params_preserve at 0x0000024068E1E7F0, file "email\message.py", line 651>, 'content-type', True, <code object get_params at 0x00000240693D29C0, file "email\message.py", line 672>, <code object get_param at 0x000002406942DAC0, file "email\message.py", line 694>, 'Content-Type', '', <code object set_param at 0x0000024068CE2630, file "email\message.py", line 728>, <code object del_param at 0x0000024068C8E3E0, file "email\message.py", line 779>, <code object set_type at 0x0000024069365D40, file "email\message.py", line 801>, <code object get_filename at 0x00000240691F6250, file "email\message.py", line 833>, <code object get_boundary at 0x00000240691C02F0, file "email\message.py", line 849>, <code object set_boundary at 0x0000024068E40900, file "email\message.py", line 862>, <code object get_content_charset at 0x0000024068E1ECD0, file "email\message.py", line 908>, <code object get_charsets at 0x00000240693EA730, file "email\message.py", line 938>, <code object get_content_disposition at 0x00000240693AA5B0, file "email\message.py", line 956>, ('walk',), (False, 0, None), (False, None), (None, False), (None,), (None, 'content-type', True), ('Content-Type', True, None, '', False), ('content-type', True), ('Content-Type', True))

## co_names:
('__name__', '__module__', '__qualname__', '__doc__', 'compat32', '__init__', '__str__', 'as_string', '__bytes__', 'as_bytes', 'is_multipart', 'set_unixfrom', 'get_unixfrom', 'attach', 'get_payload', 'set_payload', 'set_charset', 'get_charset', '__len__', '__getitem__', '__setitem__', '__delitem__', '__contains__', '__iter__', 'keys', 'values', 'items', 'get', 'set_raw', 'raw_items', 'get_all', 'add_header', 'replace_header', 'get_content_type', 'get_content_maintype', 'get_content_subtype', 'get_default_type', 'set_default_type', '_get_params_preserve', 'get_params', 'get_param', 'set_param', 'del_param', 'set_type', 'get_filename', 'get_boundary', 'set_boundary', 'get_content_charset', 'get_charsets', 'get_content_disposition', 'email.iterators', 'walk')

## bytecode:

   0: RESUME               
   2: LOAD_NAME            __name__
   4: STORE_NAME           __module__
   6: LOAD_CONST           'Message'
   8: STORE_NAME           __qualname__
  10: LOAD_CONST           "Basic message object.\n\n    A message object is defined as something that has a bunch of RFC 2822\n    headers and a payload.  It may optionally have an envelope header\n    (a.k.a. Unix-From or From_ header).  If the message is a container (i.e. a\n    multipart or a message/rfc822), then the payload is a list of Message\n    objects, otherwise it is a string.\n\n    Message objects implement part of the `mapping' interface, which assumes\n    there is exactly one occurrence of the header per message.  Some headers\n    do in fact appear multiple times (e.g. Received) and for those headers,\n    you must use the explicit API to set or get all the headers.  Not all of\n    the mapping methods are implemented.\n    "
  12: STORE_NAME           __doc__
  14: LOAD_NAME            compat32
  16: BUILD_TUPLE          
  18: LOAD_CONST           <code object __init__ at 0x00000240693AA470, file "email\message.py", line 150>
  20: MAKE_FUNCTION        defaults
  22: STORE_NAME           __init__
  24: LOAD_CONST           <code object __str__ at 0x000002406945FF00, file "email\message.py", line 162>
  26: MAKE_FUNCTION        
  28: STORE_NAME           __str__
  30: LOAD_CONST           (False, 0, None)
  32: LOAD_CONST           <code object as_string at 0x000002406921FB20, file "email\message.py", line 167>
  34: MAKE_FUNCTION        defaults
  36: STORE_NAME           as_string
  38: LOAD_CONST           <code object __bytes__ at 0x000002406945DB60, file "email\message.py", line 191>
  40: MAKE_FUNCTION        
  42: STORE_NAME           __bytes__
  44: LOAD_CONST           (False, None)
  46: LOAD_CONST           <code object as_bytes at 0x000002406921F840, file "email\message.py", line 196>
  48: MAKE_FUNCTION        defaults
  50: STORE_NAME           as_bytes
  52: LOAD_CONST           <code object is_multipart at 0x000002406945E100, file "email\message.py", line 211>
  54: MAKE_FUNCTION        
  56: STORE_NAME           is_multipart
  58: LOAD_CONST           <code object set_unixfrom at 0x0000024069427C50, file "email\message.py", line 218>
  60: MAKE_FUNCTION        
  62: STORE_NAME           set_unixfrom
  64: LOAD_CONST           <code object get_unixfrom at 0x00000240694946B0, file "email\message.py", line 221>
  66: MAKE_FUNCTION        
  68: STORE_NAME           get_unixfrom
  70: LOAD_CONST           <code object attach at 0x00000240691F23A0, file "email\message.py", line 227>
  72: MAKE_FUNCTION        
  74: STORE_NAME           attach
  76: LOAD_CONST           (None, False)
  78: LOAD_CONST           <code object get_payload at 0x0000024068D5FCF0, file "email\message.py", line 243>
  80: MAKE_FUNCTION        defaults
  82: STORE_NAME           get_payload
  84: LOAD_CONST           (None,)
  86: LOAD_CONST           <code object set_payload at 0x0000024068BF6C60, file "email\message.py", line 330>
  88: MAKE_FUNCTION        defaults
  90: STORE_NAME           set_payload
  92: LOAD_CONST           <code object set_charset at 0x0000024066C3D9C0, file "email\message.py", line 350>
  94: MAKE_FUNCTION        
  96: STORE_NAME           set_charset
  98: LOAD_CONST           <code object get_charset at 0x0000024069495F10, file "email\message.py", line 397>
 100: MAKE_FUNCTION        
 102: STORE_NAME           get_charset
 104: LOAD_CONST           <code object __len__ at 0x000002406945D5C0, file "email\message.py", line 405>
 106: MAKE_FUNCTION        
 108: STORE_NAME           __len__
 110: LOAD_CONST           <code object __getitem__ at 0x000002406945CF30, file "email\message.py", line 409>
 112: MAKE_FUNCTION        
 114: STORE_NAME           __getitem__
 116: LOAD_CONST           <code object __setitem__ at 0x0000024068DB6A10, file "email\message.py", line 420>
 118: MAKE_FUNCTION        
 120: STORE_NAME           __setitem__
 122: LOAD_CONST           <code object __delitem__ at 0x000002406921FC90, file "email\message.py", line 438>
 124: MAKE_FUNCTION        
 126: STORE_NAME           __delitem__
 128: LOAD_CONST           <code object __contains__ at 0x000002406944A560, file "email\message.py", line 450>
 130: MAKE_FUNCTION        
 132: STORE_NAME           __contains__
 134: LOAD_CONST           <code object __iter__ at 0x000002406945D2F0, file "email\message.py", line 453>
 136: MAKE_FUNCTION        
 138: STORE_NAME           __iter__
 140: LOAD_CONST           <code object keys at 0x0000024069465DF0, file "email\message.py", line 457>
 142: MAKE_FUNCTION        
 144: STORE_NAME           keys
 146: LOAD_CONST           <code object values at 0x000002406945FC30, file "email\message.py", line 467>
 148: MAKE_FUNCTION        
 150: STORE_NAME           values
 152: LOAD_CONST           <code object items at 0x000002406945D6B0, file "email\message.py", line 478>
 154: MAKE_FUNCTION        
 156: STORE_NAME           items
 158: LOAD_CONST           (None,)
 160: LOAD_CONST           <code object get at 0x000002406921FE00, file "email\message.py", line 489>
 162: MAKE_FUNCTION        defaults
 164: STORE_NAME           get
 166: LOAD_CONST           <code object set_raw at 0x00000240693EB830, file "email\message.py", line 506>
 168: MAKE_FUNCTION        
 170: STORE_NAME           set_raw
 172: LOAD_CONST           <code object raw_items at 0x000002406944AAB0, file "email\message.py", line 513>
 174: MAKE_FUNCTION        
 176: STORE_NAME           raw_items
 178: LOAD_CONST           (None,)
 180: LOAD_CONST           <code object get_all at 0x00000240691F60B0, file "email\message.py", line 524>
 182: MAKE_FUNCTION        defaults
 184: STORE_NAME           get_all
 186: LOAD_CONST           <code object add_header at 0x0000024068C8DB20, file "email\message.py", line 542>
 188: MAKE_FUNCTION        
 190: STORE_NAME           add_header
 192: LOAD_CONST           <code object replace_header at 0x000002406931FA30, file "email\message.py", line 572>
 194: MAKE_FUNCTION        
 196: STORE_NAME           replace_header
 198: LOAD_CONST           <code object get_content_type at 0x00000240691A7BB0, file "email\message.py", line 591>
 200: MAKE_FUNCTION        
 202: STORE_NAME           get_content_type
 204: LOAD_CONST           <code object get_content_maintype at 0x000002406941AE50, file "email\message.py", line 615>
 206: MAKE_FUNCTION        
 208: STORE_NAME           get_content_maintype
 210: LOAD_CONST           <code object get_content_subtype at 0x000002406941A9D0, file "email\message.py", line 624>
 212: MAKE_FUNCTION        
 214: STORE_NAME           get_content_subtype
 216: LOAD_CONST           <code object get_default_type at 0x0000024069495890, file "email\message.py", line 633>
 218: MAKE_FUNCTION        
 220: STORE_NAME           get_default_type
 222: LOAD_CONST           <code object set_default_type at 0x0000024069495BD0, file "email\message.py", line 642>
 224: MAKE_FUNCTION        
 226: STORE_NAME           set_default_type
 228: LOAD_CONST           <code object _get_params_preserve at 0x0000024068E1E7F0, file "email\message.py", line 651>
 230: MAKE_FUNCTION        
 232: STORE_NAME           _get_params_preserve
 234: LOAD_CONST           (None, 'content-type', True)
 236: LOAD_CONST           <code object get_params at 0x00000240693D29C0, file "email\message.py", line 672>
 238: MAKE_FUNCTION        defaults
 240: STORE_NAME           get_params
 242: NOP                  
 244: NOP                  
 246: LOAD_CONST           (None, 'content-type', True)
 248: LOAD_CONST           <code object get_param at 0x000002406942DAC0, file "email\message.py", line 694>
 250: MAKE_FUNCTION        defaults
 252: STORE_NAME           get_param
 254: NOP                  
 256: NOP                  
 258: LOAD_CONST           ('Content-Type', True, None, '', False)
 260: LOAD_CONST           <code object set_param at 0x0000024068CE2630, file "email\message.py", line 728>
 262: MAKE_FUNCTION        defaults
 264: STORE_NAME           set_param
 266: LOAD_CONST           ('content-type', True)
 268: LOAD_CONST           <code object del_param at 0x0000024068C8E3E0, file "email\message.py", line 779>
 270: MAKE_FUNCTION        defaults
 272: STORE_NAME           del_param
 274: LOAD_CONST           ('Content-Type', True)
 276: LOAD_CONST           <code object set_type at 0x0000024069365D40, file "email\message.py", line 801>
 278: MAKE_FUNCTION        defaults
 280: STORE_NAME           set_type
 282: LOAD_CONST           (None,)
 284: LOAD_CONST           <code object get_filename at 0x00000240691F6250, file "email\message.py", line 833>
 286: MAKE_FUNCTION        defaults
 288: STORE_NAME           get_filename
 290: LOAD_CONST           (None,)
 292: LOAD_CONST           <code object get_boundary at 0x00000240691C02F0, file "email\message.py", line 849>
 294: MAKE_FUNCTION        defaults
 296: STORE_NAME           get_boundary
 298: LOAD_CONST           <code object set_boundary at 0x0000024068E40900, file "email\message.py", line 862>
 300: MAKE_FUNCTION        
 302: STORE_NAME           set_boundary
 304: LOAD_CONST           (None,)
 306: LOAD_CONST           <code object get_content_charset at 0x0000024068E1ECD0, file "email\message.py", line 908>
 308: MAKE_FUNCTION        defaults
 310: STORE_NAME           get_content_charset
 312: LOAD_CONST           (None,)
 314: LOAD_CONST           <code object get_charsets at 0x00000240693EA730, file "email\message.py", line 938>
 316: MAKE_FUNCTION        defaults
 318: STORE_NAME           get_charsets
 320: LOAD_CONST           <code object get_content_disposition at 0x00000240693AA5B0, file "email\message.py", line 956>
 322: MAKE_FUNCTION        
 324: STORE_NAME           get_content_disposition
 326: LOAD_CONST           0
 328: LOAD_CONST           ('walk',)
 330: IMPORT_NAME          email.iterators
 332: IMPORT_FROM          walk
 334: STORE_NAME           walk
 336: POP_TOP              
 338: LOAD_CONST           None
 340: RETURN_VALUE         
