# Disassembly for email.ParameterizedHeaderValue
# From module file: email._header_value_parser

## co_consts:
('ParameterizedHeaderValue', False, <code object params at 0x000002406944B770, file "email\_header_value_parser.py", line 813>, None)

## co_names:
('__name__', '__module__', '__qualname__', 'syntactic_break', 'property', 'params')

## bytecode:

   0: RESUME               
   2: LOAD_NAME            __name__
   4: STORE_NAME           __module__
   6: LOAD_CONST           'ParameterizedHeaderValue'
   8: STORE_NAME           __qualname__
  10: LOAD_CONST           False
  12: STORE_NAME           syntactic_break
  14: LOAD_NAME            property
  16: LOAD_CONST           <code object params at 0x000002406944B770, file "email\_header_value_parser.py", line 813>
  18: MAKE_FUNCTION        
  20: PRECALL              
  24: CALL                 
  34: STORE_NAME           params
  36: LOAD_CONST           None
  38: RETURN_VALUE         
