# Disassembly for email.get_no_fold_literal
# From module file: email._header_value_parser

## co_consts:
(' no-fold-literal = "[" *dtext "]"\n    ', "expected no-fold-literal but found '{}'", 0, '[', "expected '[' at the start of no-fold-literal but found '{}'", 'no-fold-literal-start', 1, None, ']', "expected ']' at the end of no-fold-literal but found '{}'", 'no-fold-literal-end')

## co_names:
('NoFoldLiteral', 'errors', 'HeaderParseError', 'format', 'append', 'ValueTerminal', 'get_dtext')

## bytecode:

   0: RESUME               
   2: LOAD_GLOBAL          NULL + NoFoldLiteral
  14: PRECALL              
  18: CALL                 
  28: STORE_FAST           no_fold_literal
  30: LOAD_FAST            value
  32: POP_JUMP_FORWARD_IF_TRUE to 112
  34: LOAD_GLOBAL          NULL + errors
  46: LOAD_ATTR            HeaderParseError
  56: LOAD_CONST           "expected no-fold-literal but found '{}'"
  58: LOAD_METHOD          format
  80: LOAD_FAST            value
  82: PRECALL              
  86: CALL                 
  96: PRECALL              
 100: CALL                 
 110: RAISE_VARARGS        
 112: LOAD_FAST            value
 114: LOAD_CONST           0
 116: BINARY_SUBSCR        
 126: LOAD_CONST           '['
 128: COMPARE_OP           !=
 134: POP_JUMP_FORWARD_IF_FALSE to 214
 136: LOAD_GLOBAL          NULL + errors
 148: LOAD_ATTR            HeaderParseError
 158: LOAD_CONST           "expected '[' at the start of no-fold-literal but found '{}'"
 160: LOAD_METHOD          format
 182: LOAD_FAST            value
 184: PRECALL              
 188: CALL                 
 198: PRECALL              
 202: CALL                 
 212: RAISE_VARARGS        
 214: LOAD_FAST            no_fold_literal
 216: LOAD_METHOD          append
 238: LOAD_GLOBAL          NULL + ValueTerminal
 250: LOAD_CONST           '['
 252: LOAD_CONST           'no-fold-literal-start'
 254: PRECALL              
 258: CALL                 
 268: PRECALL              
 272: CALL                 
 282: POP_TOP              
 284: LOAD_FAST            value
 286: LOAD_CONST           1
 288: LOAD_CONST           None
 290: BUILD_SLICE          
 292: BINARY_SUBSCR        
 302: STORE_FAST           value
 304: LOAD_GLOBAL          NULL + get_dtext
 316: LOAD_FAST            value
 318: PRECALL              
 322: CALL                 
 332: UNPACK_SEQUENCE      
 336: STORE_FAST           token
 338: STORE_FAST           value
 340: LOAD_FAST            no_fold_literal
 342: LOAD_METHOD          append
 364: LOAD_FAST            token
 366: PRECALL              
 370: CALL                 
 380: POP_TOP              
 382: LOAD_FAST            value
 384: POP_JUMP_FORWARD_IF_FALSE to 410
 386: LOAD_FAST            value
 388: LOAD_CONST           0
 390: BINARY_SUBSCR        
 400: LOAD_CONST           ']'
 402: COMPARE_OP           !=
 408: POP_JUMP_FORWARD_IF_FALSE to 488
 410: LOAD_GLOBAL          NULL + errors
 422: LOAD_ATTR            HeaderParseError
 432: LOAD_CONST           "expected ']' at the end of no-fold-literal but found '{}'"
 434: LOAD_METHOD          format
 456: LOAD_FAST            value
 458: PRECALL              
 462: CALL                 
 472: PRECALL              
 476: CALL                 
 486: RAISE_VARARGS        
 488: LOAD_FAST            no_fold_literal
 490: LOAD_METHOD          append
 512: LOAD_GLOBAL          NULL + ValueTerminal
 524: LOAD_CONST           ']'
 526: LOAD_CONST           'no-fold-literal-end'
 528: PRECALL              
 532: CALL                 
 542: PRECALL              
 546: CALL                 
 556: POP_TOP              
 558: LOAD_FAST            no_fold_literal
 560: LOAD_FAST            value
 562: LOAD_CONST           1
 564: LOAD_CONST           None
 566: BUILD_SLICE          
 568: BINARY_SUBSCR        
 578: BUILD_TUPLE          
 580: RETURN_VALUE         
