# Disassembly for email.BufferedSubFile.close
# From module file: email.feedparser

## co_consts:
(None, 0, True)

## co_names:
('_partial', 'seek', 'pushlines', 'readlines', 'truncate', '_closed')

## bytecode:

   0: RESUME               
   2: LOAD_FAST            self
   4: LOAD_ATTR            _partial
  14: LOAD_METHOD          seek
  36: LOAD_CONST           0
  38: PRECALL              
  42: CALL                 
  52: POP_TOP              
  54: LOAD_FAST            self
  56: LOAD_METHOD          pushlines
  78: LOAD_FAST            self
  80: LOAD_ATTR            _partial
  90: LOAD_METHOD          readlines
 112: PRECALL              
 116: CALL                 
 126: PRECALL              
 130: CALL                 
 140: POP_TOP              
 142: LOAD_FAST            self
 144: LOAD_ATTR            _partial
 154: LOAD_METHOD          seek
 176: LOAD_CONST           0
 178: PRECALL              
 182: CALL                 
 192: POP_TOP              
 194: LOAD_FAST            self
 196: LOAD_ATTR            _partial
 206: LOAD_METHOD          truncate
 228: PRECALL              
 232: CALL                 
 242: POP_TOP              
 244: LOAD_CONST           True
 246: LOAD_FAST            self
 248: STORE_ATTR           _closed
 258: LOAD_CONST           None
 260: RETURN_VALUE         
