# Disassembly for email.get_addr_spec
# From module file: email._header_value_parser

## co_consts:
(' addr-spec = local-part "@" domain\n\n    ', 0, '@', 'addr-spec local part with no domain', 'address-at-symbol', 1, None)

## co_names:
('AddrSpec', 'get_local_part', 'append', 'defects', 'errors', 'InvalidHeaderDefect', 'ValueTerminal', 'get_domain')

## bytecode:

   0: RESUME               
   2: LOAD_GLOBAL          NULL + AddrSpec
  14: PRECALL              
  18: CALL                 
  28: STORE_FAST           addr_spec
  30: LOAD_GLOBAL          NULL + get_local_part
  42: LOAD_FAST            value
  44: PRECALL              
  48: CALL                 
  58: UNPACK_SEQUENCE      
  62: STORE_FAST           token
  64: STORE_FAST           value
  66: LOAD_FAST            addr_spec
  68: LOAD_METHOD          append
  90: LOAD_FAST            token
  92: PRECALL              
  96: CALL                 
 106: POP_TOP              
 108: LOAD_FAST            value
 110: POP_JUMP_FORWARD_IF_FALSE to 136
 112: LOAD_FAST            value
 114: LOAD_CONST           0
 116: BINARY_SUBSCR        
 126: LOAD_CONST           '@'
 128: COMPARE_OP           !=
 134: POP_JUMP_FORWARD_IF_FALSE to 232
 136: LOAD_FAST            addr_spec
 138: LOAD_ATTR            defects
 148: LOAD_METHOD          append
 170: LOAD_GLOBAL          NULL + errors
 182: LOAD_ATTR            InvalidHeaderDefect
 192: LOAD_CONST           'addr-spec local part with no domain'
 194: PRECALL              
 198: CALL                 
 208: PRECALL              
 212: CALL                 
 222: POP_TOP              
 224: LOAD_FAST            addr_spec
 226: LOAD_FAST            value
 228: BUILD_TUPLE          
 230: RETURN_VALUE         
 232: LOAD_FAST            addr_spec
 234: LOAD_METHOD          append
 256: LOAD_GLOBAL          NULL + ValueTerminal
 268: LOAD_CONST           '@'
 270: LOAD_CONST           'address-at-symbol'
 272: PRECALL              
 276: CALL                 
 286: PRECALL              
 290: CALL                 
 300: POP_TOP              
 302: LOAD_GLOBAL          NULL + get_domain
 314: LOAD_FAST            value
 316: LOAD_CONST           1
 318: LOAD_CONST           None
 320: BUILD_SLICE          
 322: BINARY_SUBSCR        
 332: PRECALL              
 336: CALL                 
 346: UNPACK_SEQUENCE      
 350: STORE_FAST           token
 352: STORE_FAST           value
 354: LOAD_FAST            addr_spec
 356: LOAD_METHOD          append
 378: LOAD_FAST            token
 380: PRECALL              
 384: CALL                 
 394: POP_TOP              
 396: LOAD_FAST            addr_spec
 398: LOAD_FAST            value
 400: BUILD_TUPLE          
 402: RETURN_VALUE         
