# Disassembly for email.typed_subpart_iterator
# From module file: email.iterators

## co_consts:
('Iterate over the subparts with a given MIME type.\n\n    Use `maintype\' as the main MIME type to match against; this defaults to\n    "text".  Optional `subtype\' is the MIME subtype to match against; if\n    omitted, only the main type is matched.\n    ', None)

## co_names:
('walk', 'get_content_maintype', 'get_content_subtype')

## bytecode:

   0: RETURN_GENERATOR     
   2: POP_TOP              
   4: RESUME               
   6: LOAD_FAST            msg
   8: LOAD_METHOD          walk
  30: PRECALL              
  34: CALL                 
  44: GET_ITER             
  46: FOR_ITER             to 160
  48: STORE_FAST           subpart
  50: LOAD_FAST            subpart
  52: LOAD_METHOD          get_content_maintype
  74: PRECALL              
  78: CALL                 
  88: LOAD_FAST            maintype
  90: COMPARE_OP           ==
  96: POP_JUMP_FORWARD_IF_FALSE to 158
  98: LOAD_FAST            subtype
 100: POP_JUMP_FORWARD_IF_NONE to 150
 102: LOAD_FAST            subpart
 104: LOAD_METHOD          get_content_subtype
 126: PRECALL              
 130: CALL                 
 140: LOAD_FAST            subtype
 142: COMPARE_OP           ==
 148: POP_JUMP_FORWARD_IF_FALSE to 158
 150: LOAD_FAST            subpart
 152: YIELD_VALUE          
 154: RESUME               
 156: POP_TOP              
 158: JUMP_BACKWARD        to 46
 160: LOAD_CONST           None
 162: RETURN_VALUE         
