# Disassembly for email.header_encode
# From module file: email.quoprimime

## co_consts:
("Encode a single header line with quoted-printable (like) encoding.\n\n    Defined in RFC 2045, this `Q' encoding is similar to quoted-printable, but\n    used specifically for email header fields to allow charsets with mostly 7\n    bit characters (and some 8 bit) to remain more or less readable in non-RFC\n    2045 aware mail clients.\n\n    charset names the character set to use in the RFC 2046 header.  It\n    defaults to iso-8859-1.\n    ", '', 'latin1', '=?', '?q?', '?=')

## co_names:
('decode', 'translate', '_QUOPRI_HEADER_MAP')

## bytecode:

   0: RESUME               
   2: LOAD_FAST            header_bytes
   4: POP_JUMP_FORWARD_IF_TRUE to 10
   6: LOAD_CONST           ''
   8: RETURN_VALUE         
  10: LOAD_FAST            header_bytes
  12: LOAD_METHOD          decode
  34: LOAD_CONST           'latin1'
  36: PRECALL              
  40: CALL                 
  50: LOAD_METHOD          translate
  72: LOAD_GLOBAL          _QUOPRI_HEADER_MAP
  84: PRECALL              
  88: CALL                 
  98: STORE_FAST           encoded
 100: LOAD_CONST           '=?'
 102: LOAD_FAST            charset
 104: FORMAT_VALUE         str
 106: LOAD_CONST           '?q?'
 108: LOAD_FAST            encoded
 110: FORMAT_VALUE         str
 112: LOAD_CONST           '?='
 114: BUILD_STRING         
 116: RETURN_VALUE         
