# Disassembly for email.BufferedSubFile.__init__
# From module file: email.feedparser

## co_consts:
(None, '', ('newline',), False)

## co_names:
('StringIO', '_partial', 'deque', '_lines', '_eofstack', '_closed')

## bytecode:

   0: RESUME               
   2: LOAD_GLOBAL          NULL + StringIO
  14: LOAD_CONST           ''
  16: KW_NAMES             
  18: PRECALL              
  22: CALL                 
  32: LOAD_FAST            self
  34: STORE_ATTR           _partial
  44: LOAD_GLOBAL          NULL + deque
  56: PRECALL              
  60: CALL                 
  70: LOAD_FAST            self
  72: STORE_ATTR           _lines
  82: BUILD_LIST           
  84: LOAD_FAST            self
  86: STORE_ATTR           _eofstack
  96: LOAD_CONST           False
  98: LOAD_FAST            self
 100: STORE_ATTR           _closed
 110: LOAD_CONST           None
 112: RETURN_VALUE         
