# Disassembly for email.get_dtext
# From module file: email._header_value_parser

## co_consts:
(" dtext = <printable ascii except \\ [ ]> / obs-dtext\n        obs-dtext = obs-NO-WS-CTL / quoted-pair\n\n    We allow anything except the excluded characters, but if we find any\n    ASCII other than the RFC defined printable ASCII, a NonPrintableDefect is\n    added to the token's defects list.  Quoted pairs are converted to their\n    unquoted values, so what is returned is a ptext token, in this case a\n    ValueTerminal.  If there were quoted-printables, an ObsoleteHeaderDefect is\n    added to the returned token's defect list.\n\n    ", '[]', 'ptext', 'quoted printable found in domain-literal')

## co_names:
('_get_ptext_to_endchars', 'ValueTerminal', 'defects', 'append', 'errors', 'ObsoleteHeaderDefect', '_validate_xtext')

## bytecode:

   0: RESUME               
   2: LOAD_GLOBAL          NULL + _get_ptext_to_endchars
  14: LOAD_FAST            value
  16: LOAD_CONST           '[]'
  18: PRECALL              
  22: CALL                 
  32: UNPACK_SEQUENCE      
  36: STORE_FAST           ptext
  38: STORE_FAST           value
  40: STORE_FAST           had_qp
  42: LOAD_GLOBAL          NULL + ValueTerminal
  54: LOAD_FAST            ptext
  56: LOAD_CONST           'ptext'
  58: PRECALL              
  62: CALL                 
  72: STORE_FAST           ptext
  74: LOAD_FAST            had_qp
  76: POP_JUMP_FORWARD_IF_FALSE to 166
  78: LOAD_FAST            ptext
  80: LOAD_ATTR            defects
  90: LOAD_METHOD          append
 112: LOAD_GLOBAL          NULL + errors
 124: LOAD_ATTR            ObsoleteHeaderDefect
 134: LOAD_CONST           'quoted printable found in domain-literal'
 136: PRECALL              
 140: CALL                 
 150: PRECALL              
 154: CALL                 
 164: POP_TOP              
 166: LOAD_GLOBAL          NULL + _validate_xtext
 178: LOAD_FAST            ptext
 180: PRECALL              
 184: CALL                 
 194: POP_TOP              
 196: LOAD_FAST            ptext
 198: LOAD_FAST            value
 200: BUILD_TUPLE          
 202: RETURN_VALUE         
