# Disassembly for email.TokenList.__init__
# From module file: email._header_value_parser

## co_consts:
(None,)

## co_names:
('super', '__init__', 'defects')

## bytecode:

   0: COPY_FREE_VARS       
   2: RESUME               
   4: PUSH_NULL            
   6: LOAD_GLOBAL          NULL + super
  18: PRECALL              
  22: CALL                 
  32: LOAD_ATTR            __init__
  42: LOAD_FAST            args
  44: BUILD_MAP            
  46: LOAD_FAST            kw
  48: DICT_MERGE           
  50: CALL_FUNCTION_EX     
  52: POP_TOP              
  54: BUILD_LIST           
  56: LOAD_FAST            self
  58: STORE_ATTR           defects
  68: LOAD_CONST           None
  70: RETURN_VALUE         
