# Disassembly for email._PolicyBase.__add__
# From module file: email._policybase

## co_consts:
('Non-default values from right operand override those from left.\n\n        The object returned is a new instance of the subclass.\n\n        ', ())

## co_names:
('clone', '__dict__')

## bytecode:

   0: RESUME               
   2: PUSH_NULL            
   4: LOAD_FAST            self
   6: LOAD_ATTR            clone
  16: LOAD_CONST           ()
  18: BUILD_MAP            
  20: LOAD_FAST            other
  22: LOAD_ATTR            __dict__
  32: DICT_MERGE           
  34: CALL_FUNCTION_EX     
  36: RETURN_VALUE         
