# Disassembly for email.TokenList
# From module file: email._header_value_parser

## co_consts:
('TokenList', None, True, <code object __init__ at 0x00000240693EBA30, file "email\_header_value_parser.py", line 121>, <code object __str__ at 0x00000240693EB730, file "email\_header_value_parser.py", line 125>, <code object __repr__ at 0x00000240693AA470, file "email\_header_value_parser.py", line 128>, <code object value at 0x00000240693EA630, file "email\_header_value_parser.py", line 132>, <code object all_defects at 0x00000240693EA930, file "email\_header_value_parser.py", line 136>, <code object startswith_fws at 0x000002406945D7A0, file "email\_header_value_parser.py", line 140>, <code object as_ew_allowed at 0x000002406945D5C0, file "email\_header_value_parser.py", line 143>, <code object comments at 0x00000240693EB830, file "email\_header_value_parser.py", line 148>, <code object fold at 0x00000240694657D0, file "email\_header_value_parser.py", line 155>, '', <code object pprint at 0x000002406944A780, file "email\_header_value_parser.py", line 158>, <code object ppstr at 0x000002406944A560, file "email\_header_value_parser.py", line 161>, <code object _pp at 0x0000024068C8EED0, file "email\_header_value_parser.py", line 164>, ('',))

## co_names:
('__name__', '__module__', '__qualname__', 'token_type', 'syntactic_break', 'ew_combine_allowed', '__init__', '__str__', '__repr__', 'property', 'value', 'all_defects', 'startswith_fws', 'as_ew_allowed', 'comments', 'fold', 'pprint', 'ppstr', '_pp', '__classcell__')

## bytecode:

   0: MAKE_CELL            __class__
   2: RESUME               
   4: LOAD_NAME            __name__
   6: STORE_NAME           __module__
   8: LOAD_CONST           'TokenList'
  10: STORE_NAME           __qualname__
  12: LOAD_CONST           None
  14: STORE_NAME           token_type
  16: LOAD_CONST           True
  18: STORE_NAME           syntactic_break
  20: LOAD_CONST           True
  22: STORE_NAME           ew_combine_allowed
  24: LOAD_CLOSURE         __class__
  26: BUILD_TUPLE          
  28: LOAD_CONST           <code object __init__ at 0x00000240693EBA30, file "email\_header_value_parser.py", line 121>
  30: MAKE_FUNCTION        closure
  32: STORE_NAME           __init__
  34: LOAD_CONST           <code object __str__ at 0x00000240693EB730, file "email\_header_value_parser.py", line 125>
  36: MAKE_FUNCTION        
  38: STORE_NAME           __str__
  40: LOAD_CLOSURE         __class__
  42: BUILD_TUPLE          
  44: LOAD_CONST           <code object __repr__ at 0x00000240693AA470, file "email\_header_value_parser.py", line 128>
  46: MAKE_FUNCTION        closure
  48: STORE_NAME           __repr__
  50: LOAD_NAME            property
  52: LOAD_CONST           <code object value at 0x00000240693EA630, file "email\_header_value_parser.py", line 132>
  54: MAKE_FUNCTION        
  56: PRECALL              
  60: CALL                 
  70: STORE_NAME           value
  72: LOAD_NAME            property
  74: LOAD_CONST           <code object all_defects at 0x00000240693EA930, file "email\_header_value_parser.py", line 136>
  76: MAKE_FUNCTION        
  78: PRECALL              
  82: CALL                 
  92: STORE_NAME           all_defects
  94: LOAD_CONST           <code object startswith_fws at 0x000002406945D7A0, file "email\_header_value_parser.py", line 140>
  96: MAKE_FUNCTION        
  98: STORE_NAME           startswith_fws
 100: LOAD_NAME            property
 102: LOAD_CONST           <code object as_ew_allowed at 0x000002406945D5C0, file "email\_header_value_parser.py", line 143>
 104: MAKE_FUNCTION        
 106: PRECALL              
 110: CALL                 
 120: STORE_NAME           as_ew_allowed
 122: LOAD_NAME            property
 124: LOAD_CONST           <code object comments at 0x00000240693EB830, file "email\_header_value_parser.py", line 148>
 126: MAKE_FUNCTION        
 128: PRECALL              
 132: CALL                 
 142: STORE_NAME           comments
 144: LOAD_CONST           <code object fold at 0x00000240694657D0, file "email\_header_value_parser.py", line 155>
 146: MAKE_FUNCTION        
 148: STORE_NAME           fold
 150: LOAD_CONST           ('',)
 152: LOAD_CONST           <code object pprint at 0x000002406944A780, file "email\_header_value_parser.py", line 158>
 154: MAKE_FUNCTION        defaults
 156: STORE_NAME           pprint
 158: LOAD_CONST           ('',)
 160: LOAD_CONST           <code object ppstr at 0x000002406944A560, file "email\_header_value_parser.py", line 161>
 162: MAKE_FUNCTION        defaults
 164: STORE_NAME           ppstr
 166: LOAD_CONST           ('',)
 168: LOAD_CONST           <code object _pp at 0x0000024068C8EED0, file "email\_header_value_parser.py", line 164>
 170: MAKE_FUNCTION        defaults
 172: STORE_NAME           _pp
 174: LOAD_CLOSURE         __class__
 176: COPY                 
 178: STORE_NAME           __classcell__
 180: RETURN_VALUE         
