# Disassembly for email.BareQuotedString.__str__
# From module file: email._header_value_parser

## co_consts:
(None, '', <code object <genexpr> at 0x000002406945FC30, file "email\_header_value_parser.py", line 256>)

## co_names:
('quote_string', 'join')

## bytecode:

   0: RESUME               
   2: LOAD_GLOBAL          NULL + quote_string
  14: LOAD_CONST           ''
  16: LOAD_METHOD          join
  38: LOAD_CONST           <code object <genexpr> at 0x000002406945FC30, file "email\_header_value_parser.py", line 256>
  40: MAKE_FUNCTION        
  42: LOAD_FAST            self
  44: GET_ITER             
  46: PRECALL              
  50: CALL                 
  60: PRECALL              
  64: CALL                 
  74: PRECALL              
  78: CALL                 
  88: RETURN_VALUE         
