# Disassembly for email._InvalidEwError
# From module file: email._header_value_parser

## co_consts:
('_InvalidEwError', 'Invalid encoded word found while parsing headers.', None)

## co_names:
('__name__', '__module__', '__qualname__', '__doc__')

## bytecode:

   0: RESUME               
   2: LOAD_NAME            __name__
   4: STORE_NAME           __module__
   6: LOAD_CONST           '_InvalidEwError'
   8: STORE_NAME           __qualname__
  10: LOAD_CONST           'Invalid encoded word found while parsing headers.'
  12: STORE_NAME           __doc__
  14: LOAD_CONST           None
  16: RETURN_VALUE         
