# Disassembly for email.Compat32._fold
# From module file: email._policybase

## co_consts:
(None, '%s: ', ('charset', 'header_name'), ('header_name',), 0, ('linesep', 'maxlinelen'), '')

## co_names:
('append', 'isinstance', 'str', '_has_surrogates', 'header', 'Header', '_charset', 'UNKNOWN8BIT', 'max_line_length', 'encode', 'linesep', 'join')

## bytecode:

   0: RESUME               
   2: BUILD_LIST           
   4: STORE_FAST           parts
   6: LOAD_FAST            parts
   8: LOAD_METHOD          append
  30: LOAD_CONST           '%s: '
  32: LOAD_FAST            name
  34: BINARY_OP            %
  38: PRECALL              
  42: CALL                 
  52: POP_TOP              
  54: LOAD_GLOBAL          NULL + isinstance
  66: LOAD_FAST            value
  68: LOAD_GLOBAL          str
  80: PRECALL              
  84: CALL                 
  94: POP_JUMP_FORWARD_IF_FALSE to 292
  96: LOAD_GLOBAL          NULL + _has_surrogates
 108: LOAD_FAST            value
 110: PRECALL              
 114: CALL                 
 124: POP_JUMP_FORWARD_IF_FALSE to 246
 126: LOAD_FAST            sanitize
 128: POP_JUMP_FORWARD_IF_FALSE to 198
 130: LOAD_GLOBAL          NULL + header
 142: LOAD_ATTR            Header
 152: LOAD_FAST            value
 154: LOAD_GLOBAL          _charset
 166: LOAD_ATTR            UNKNOWN8BIT
 176: LOAD_FAST            name
 178: KW_NAMES             
 180: PRECALL              
 184: CALL                 
 194: STORE_FAST           h
 196: JUMP_FORWARD         to 296
 198: LOAD_FAST            parts
 200: LOAD_METHOD          append
 222: LOAD_FAST            value
 224: PRECALL              
 228: CALL                 
 238: POP_TOP              
 240: LOAD_CONST           None
 242: STORE_FAST           h
 244: JUMP_FORWARD         to 296
 246: LOAD_GLOBAL          NULL + header
 258: LOAD_ATTR            Header
 268: LOAD_FAST            value
 270: LOAD_FAST            name
 272: KW_NAMES             
 274: PRECALL              
 278: CALL                 
 288: STORE_FAST           h
 290: JUMP_FORWARD         to 296
 292: LOAD_FAST            value
 294: STORE_FAST           h
 296: LOAD_FAST            h
 298: POP_JUMP_FORWARD_IF_NONE to 426
 300: LOAD_CONST           0
 302: STORE_FAST           maxlinelen
 304: LOAD_FAST            self
 306: LOAD_ATTR            max_line_length
 316: POP_JUMP_FORWARD_IF_NONE to 332
 318: LOAD_FAST            self
 320: LOAD_ATTR            max_line_length
 330: STORE_FAST           maxlinelen
 332: LOAD_FAST            parts
 334: LOAD_METHOD          append
 356: LOAD_FAST            h
 358: LOAD_METHOD          encode
 380: LOAD_FAST            self
 382: LOAD_ATTR            linesep
 392: LOAD_FAST            maxlinelen
 394: KW_NAMES             
 396: PRECALL              
 400: CALL                 
 410: PRECALL              
 414: CALL                 
 424: POP_TOP              
 426: LOAD_FAST            parts
 428: LOAD_METHOD          append
 450: LOAD_FAST            self
 452: LOAD_ATTR            linesep
 462: PRECALL              
 466: CALL                 
 476: POP_TOP              
 478: LOAD_CONST           ''
 480: LOAD_METHOD          join
 502: LOAD_FAST            parts
 504: PRECALL              
 508: CALL                 
 518: RETURN_VALUE         
