# Disassembly for email.Message.set_payload
# From module file: email.message

## co_consts:
("Set the payload to the given value.\n\n        Optional charset sets the message's default character set.  See\n        set_charset() for details.\n        ", 'encode', None, 'decode', 'ascii', 'surrogateescape')

## co_names:
('hasattr', '_payload', 'isinstance', 'Charset', 'encode', 'output_charset', 'decode', 'set_charset')

## bytecode:

   0: RESUME               
   2: LOAD_GLOBAL          NULL + hasattr
  14: LOAD_FAST            payload
  16: LOAD_CONST           'encode'
  18: PRECALL              
  22: CALL                 
  32: POP_JUMP_FORWARD_IF_FALSE to 180
  34: LOAD_FAST            charset
  36: POP_JUMP_FORWARD_IF_NOT_NONE to 56
  38: LOAD_FAST            payload
  40: LOAD_FAST            self
  42: STORE_ATTR           _payload
  52: LOAD_CONST           None
  54: RETURN_VALUE         
  56: LOAD_GLOBAL          NULL + isinstance
  68: LOAD_FAST            charset
  70: LOAD_GLOBAL          Charset
  82: PRECALL              
  86: CALL                 
  96: POP_JUMP_FORWARD_IF_TRUE to 128
  98: LOAD_GLOBAL          NULL + Charset
 110: LOAD_FAST            charset
 112: PRECALL              
 116: CALL                 
 126: STORE_FAST           charset
 128: LOAD_FAST            payload
 130: LOAD_METHOD          encode
 152: LOAD_FAST            charset
 154: LOAD_ATTR            output_charset
 164: PRECALL              
 168: CALL                 
 178: STORE_FAST           payload
 180: LOAD_GLOBAL          NULL + hasattr
 192: LOAD_FAST            payload
 194: LOAD_CONST           'decode'
 196: PRECALL              
 200: CALL                 
 210: POP_JUMP_FORWARD_IF_FALSE to 268
 212: LOAD_FAST            payload
 214: LOAD_METHOD          decode
 236: LOAD_CONST           'ascii'
 238: LOAD_CONST           'surrogateescape'
 240: PRECALL              
 244: CALL                 
 254: LOAD_FAST            self
 256: STORE_ATTR           _payload
 266: JUMP_FORWARD         to 282
 268: LOAD_FAST            payload
 270: LOAD_FAST            self
 272: STORE_ATTR           _payload
 282: LOAD_FAST            charset
 284: POP_JUMP_FORWARD_IF_NONE to 332
 286: LOAD_FAST            self
 288: LOAD_METHOD          set_charset
 310: LOAD_FAST            charset
 312: PRECALL              
 316: CALL                 
 326: POP_TOP              
 328: LOAD_CONST           None
 330: RETURN_VALUE         
 332: LOAD_CONST           None
 334: RETURN_VALUE         
