# Disassembly for email.Message.get_params
# From module file: email.message

## co_consts:
("Return the message's Content-Type parameters, as a list.\n\n        The elements of the returned list are 2-tuples of key/value pairs, as\n        split on the `=' sign.  The left hand side of the `=' is the key,\n        while the right hand side is the value.  If there is no `=' sign in\n        the parameter the value is the empty string.  The value is as\n        described in the get_param() method.\n\n        Optional failobj is the object to return if there is no Content-Type\n        header.  Optional header is the header to search instead of\n        Content-Type.  If unquote is True, the value is unquoted.\n        ", <code object <listcomp> at 0x000002406945D4D0, file "email\message.py", line 690>)

## co_names:
('object', '_get_params_preserve')

## bytecode:

   0: RESUME               
   2: LOAD_GLOBAL          NULL + object
  14: PRECALL              
  18: CALL                 
  28: STORE_FAST           missing
  30: LOAD_FAST            self
  32: LOAD_METHOD          _get_params_preserve
  54: LOAD_FAST            missing
  56: LOAD_FAST            header
  58: PRECALL              
  62: CALL                 
  72: STORE_FAST           params
  74: LOAD_FAST            params
  76: LOAD_FAST            missing
  78: IS_OP                
  80: POP_JUMP_FORWARD_IF_FALSE to 86
  82: LOAD_FAST            failobj
  84: RETURN_VALUE         
  86: LOAD_FAST            unquote
  88: POP_JUMP_FORWARD_IF_FALSE to 114
  90: LOAD_CONST           <code object <listcomp> at 0x000002406945D4D0, file "email\message.py", line 690>
  92: MAKE_FUNCTION        
  94: LOAD_FAST            params
  96: GET_ITER             
  98: PRECALL              
 102: CALL                 
 112: RETURN_VALUE         
 114: LOAD_FAST            params
 116: RETURN_VALUE         
