# Disassembly for email.Address.__str__
# From module file: email.headerregistry

## co_consts:
(None, '<>', '', '{} <{}>')

## co_names:
('display_name', 'parser', 'SPECIALS', 'isdisjoint', 'quote_string', 'addr_spec', 'format')

## bytecode:

   0: RESUME               
   2: LOAD_FAST            self
   4: LOAD_ATTR            display_name
  14: STORE_FAST           disp
  16: LOAD_GLOBAL          parser
  28: LOAD_ATTR            SPECIALS
  38: LOAD_METHOD          isdisjoint
  60: LOAD_FAST            disp
  62: PRECALL              
  66: CALL                 
  76: POP_JUMP_FORWARD_IF_TRUE to 118
  78: LOAD_GLOBAL          NULL + parser
  90: LOAD_ATTR            quote_string
 100: LOAD_FAST            disp
 102: PRECALL              
 106: CALL                 
 116: STORE_FAST           disp
 118: LOAD_FAST            disp
 120: POP_JUMP_FORWARD_IF_FALSE to 206
 122: LOAD_FAST            self
 124: LOAD_ATTR            addr_spec
 134: LOAD_CONST           '<>'
 136: COMPARE_OP           ==
 142: POP_JUMP_FORWARD_IF_FALSE to 148
 144: LOAD_CONST           ''
 146: JUMP_FORWARD         to 160
 148: LOAD_FAST            self
 150: LOAD_ATTR            addr_spec
 160: STORE_FAST           addr_spec
 162: LOAD_CONST           '{} <{}>'
 164: LOAD_METHOD          format
 186: LOAD_FAST            disp
 188: LOAD_FAST            addr_spec
 190: PRECALL              
 194: CALL                 
 204: RETURN_VALUE         
 206: LOAD_FAST            self
 208: LOAD_ATTR            addr_spec
 218: RETURN_VALUE         
