# Disassembly for email.Attribute.stripped_value
# From module file: email._header_value_parser

## co_consts:
(None, 'attrtext')

## co_names:
('token_type', 'endswith', 'value')

## bytecode:

   0: RESUME               
   2: LOAD_FAST            self
   4: GET_ITER             
   6: FOR_ITER             to 82
   8: STORE_FAST           token
  10: LOAD_FAST            token
  12: LOAD_ATTR            token_type
  22: LOAD_METHOD          endswith
  44: LOAD_CONST           'attrtext'
  46: PRECALL              
  50: CALL                 
  60: POP_JUMP_FORWARD_IF_FALSE to 80
  62: LOAD_FAST            token
  64: LOAD_ATTR            value
  74: SWAP                 
  76: POP_TOP              
  78: RETURN_VALUE         
  80: JUMP_BACKWARD        to 6
  82: LOAD_CONST           None
  84: RETURN_VALUE         
