# Disassembly for email.get_dot_atom
# From module file: email._header_value_parser

## co_consts:
(' dot-atom = [CFWS] dot-atom-text [CFWS]\n\n    Any place we can have a dot atom, we could instead have an rfc2047 encoded\n    word.\n    ', 0, '=?')

## co_names:
('DotAtom', 'CFWS_LEADER', 'get_cfws', 'append', 'startswith', 'get_encoded_word', 'errors', 'HeaderParseError', 'get_dot_atom_text')

## bytecode:

   0: RESUME               
   2: LOAD_GLOBAL          NULL + DotAtom
  14: PRECALL              
  18: CALL                 
  28: STORE_FAST           dot_atom
  30: LOAD_FAST            value
  32: LOAD_CONST           0
  34: BINARY_SUBSCR        
  44: LOAD_GLOBAL          CFWS_LEADER
  56: CONTAINS_OP          
  58: POP_JUMP_FORWARD_IF_FALSE to 138
  60: LOAD_GLOBAL          NULL + get_cfws
  72: LOAD_FAST            value
  74: PRECALL              
  78: CALL                 
  88: UNPACK_SEQUENCE      
  92: STORE_FAST           token
  94: STORE_FAST           value
  96: LOAD_FAST            dot_atom
  98: LOAD_METHOD          append
 120: LOAD_FAST            token
 122: PRECALL              
 126: CALL                 
 136: POP_TOP              
 138: LOAD_FAST            value
 140: LOAD_METHOD          startswith
 162: LOAD_CONST           '=?'
 164: PRECALL              
 168: CALL                 
 178: POP_JUMP_FORWARD_IF_FALSE to 298
 180: NOP                  
 182: LOAD_GLOBAL          NULL + get_encoded_word
 194: LOAD_FAST            value
 196: PRECALL              
 200: CALL                 
 210: UNPACK_SEQUENCE      
 214: STORE_FAST           token
 216: STORE_FAST           value
 218: JUMP_FORWARD         to 334
 220: PUSH_EXC_INFO        
 222: LOAD_GLOBAL          errors
 234: LOAD_ATTR            HeaderParseError
 244: CHECK_EXC_MATCH      
 246: POP_JUMP_FORWARD_IF_FALSE to 290
 248: POP_TOP              
 250: LOAD_GLOBAL          NULL + get_dot_atom_text
 262: LOAD_FAST            value
 264: PRECALL              
 268: CALL                 
 278: UNPACK_SEQUENCE      
 282: STORE_FAST           token
 284: STORE_FAST           value
 286: POP_EXCEPT           
 288: JUMP_FORWARD         to 334
 290: RERAISE              
 292: COPY                 
 294: POP_EXCEPT           
 296: RERAISE              
 298: LOAD_GLOBAL          NULL + get_dot_atom_text
 310: LOAD_FAST            value
 312: PRECALL              
 316: CALL                 
 326: UNPACK_SEQUENCE      
 330: STORE_FAST           token
 332: STORE_FAST           value
 334: LOAD_FAST            dot_atom
 336: LOAD_METHOD          append
 358: LOAD_FAST            token
 360: PRECALL              
 364: CALL                 
 374: POP_TOP              
 376: LOAD_FAST            value
 378: POP_JUMP_FORWARD_IF_FALSE to 488
 380: LOAD_FAST            value
 382: LOAD_CONST           0
 384: BINARY_SUBSCR        
 394: LOAD_GLOBAL          CFWS_LEADER
 406: CONTAINS_OP          
 408: POP_JUMP_FORWARD_IF_FALSE to 488
 410: LOAD_GLOBAL          NULL + get_cfws
 422: LOAD_FAST            value
 424: PRECALL              
 428: CALL                 
 438: UNPACK_SEQUENCE      
 442: STORE_FAST           token
 444: STORE_FAST           value
 446: LOAD_FAST            dot_atom
 448: LOAD_METHOD          append
 470: LOAD_FAST            token
 472: PRECALL              
 476: CALL                 
 486: POP_TOP              
 488: LOAD_FAST            dot_atom
 490: LOAD_FAST            value
 492: BUILD_TUPLE          
 494: RETURN_VALUE         
