# Disassembly for email.BytesGenerator._write_headers
# From module file: email.generator

## co_consts:
(None,)

## co_names:
('raw_items', '_fp', 'write', 'policy', 'fold_binary', '_NL')

## bytecode:

   0: RESUME               
   2: LOAD_FAST            msg
   4: LOAD_METHOD          raw_items
  26: PRECALL              
  30: CALL                 
  40: GET_ITER             
  42: FOR_ITER             to 156
  44: UNPACK_SEQUENCE      
  48: STORE_FAST           h
  50: STORE_FAST           v
  52: LOAD_FAST            self
  54: LOAD_ATTR            _fp
  64: LOAD_METHOD          write
  86: LOAD_FAST            self
  88: LOAD_ATTR            policy
  98: LOAD_METHOD          fold_binary
 120: LOAD_FAST            h
 122: LOAD_FAST            v
 124: PRECALL              
 128: CALL                 
 138: PRECALL              
 142: CALL                 
 152: POP_TOP              
 154: JUMP_BACKWARD        to 42
 156: LOAD_FAST            self
 158: LOAD_METHOD          write
 180: LOAD_FAST            self
 182: LOAD_ATTR            _NL
 192: PRECALL              
 196: CALL                 
 206: POP_TOP              
 208: LOAD_CONST           None
 210: RETURN_VALUE         
