# Disassembly for email.Message.as_string
# From module file: email.message

## co_consts:
('Return the entire formatted message as a string.\n\n        Optional \'unixfrom\', when true, means include the Unix From_ envelope\n        header.  For backward compatibility reasons, if maxheaderlen is\n        not specified it defaults to 0, so you must override it explicitly\n        if you want a different maxheaderlen.  \'policy\' is passed to the\n        Generator instance used to serialize the message; if it is not\n        specified the policy associated with the message instance is used.\n\n        If the message object contains binary data that is not encoded\n        according to RFC standards, the non-compliant data will be replaced by\n        unicode "unknown character" code points.\n        ', 0, ('Generator',), None, False, ('mangle_from_', 'maxheaderlen', 'policy'), ('unixfrom',))

## co_names:
('email.generator', 'Generator', 'policy', 'StringIO', 'flatten', 'getvalue')

## bytecode:

   0: RESUME               
   2: LOAD_CONST           0
   4: LOAD_CONST           ('Generator',)
   6: IMPORT_NAME          email.generator
   8: IMPORT_FROM          Generator
  10: STORE_FAST           Generator
  12: POP_TOP              
  14: LOAD_FAST            policy
  16: POP_JUMP_FORWARD_IF_NOT_NONE to 32
  18: LOAD_FAST            self
  20: LOAD_ATTR            policy
  30: JUMP_FORWARD         to 34
  32: LOAD_FAST            policy
  34: STORE_FAST           policy
  36: LOAD_GLOBAL          NULL + StringIO
  48: PRECALL              
  52: CALL                 
  62: STORE_FAST           fp
  64: PUSH_NULL            
  66: LOAD_FAST            Generator
  68: LOAD_FAST            fp
  70: LOAD_CONST           False
  72: LOAD_FAST            maxheaderlen
  74: LOAD_FAST            policy
  76: KW_NAMES             
  78: PRECALL              
  82: CALL                 
  92: STORE_FAST           g
  94: LOAD_FAST            g
  96: LOAD_METHOD          flatten
 118: LOAD_FAST            self
 120: LOAD_FAST            unixfrom
 122: KW_NAMES             
 124: PRECALL              
 128: CALL                 
 138: POP_TOP              
 140: LOAD_FAST            fp
 142: LOAD_METHOD          getvalue
 164: PRECALL              
 168: CALL                 
 178: RETURN_VALUE         
