# Disassembly for email.MessageDefect
# From module file: email.errors

## co_consts:
('MessageDefect', 'Base class for a message defect.', None, <code object __init__ at 0x000002406941A9D0, file "email\errors.py", line 36>, (None,))

## co_names:
('__name__', '__module__', '__qualname__', '__doc__', '__init__', '__classcell__')

## bytecode:

   0: MAKE_CELL            __class__
   2: RESUME               
   4: LOAD_NAME            __name__
   6: STORE_NAME           __module__
   8: LOAD_CONST           'MessageDefect'
  10: STORE_NAME           __qualname__
  12: LOAD_CONST           'Base class for a message defect.'
  14: STORE_NAME           __doc__
  16: LOAD_CONST           (None,)
  18: LOAD_CLOSURE         __class__
  20: BUILD_TUPLE          
  22: LOAD_CONST           <code object __init__ at 0x000002406941A9D0, file "email\errors.py", line 36>
  24: MAKE_FUNCTION        defaults, closure
  26: STORE_NAME           __init__
  28: LOAD_CLOSURE         __class__
  30: COPY                 
  32: STORE_NAME           __classcell__
  34: RETURN_VALUE         
