# Disassembly for email.get_encoded_word
# From module file: email._header_value_parser

## co_consts:
(' encoded-word = "=?" charset "?" encoding "?" encoded-text "?="\n\n    ', '=?', 'expected encoded word but found {}', 2, None, '?=', 1, '', 0, '?', 'whitespace inside encoded word', "encoded word format invalid: '{}'", 'vtext', 'missing trailing whitespace after encoded-word')

## co_names:
('EncodedWord', 'startswith', 'errors', 'HeaderParseError', 'format', 'split', 'join', 'len', 'hexdigits', 'count', 'defects', 'append', 'InvalidHeaderDefect', 'cte', '_ew', 'decode', 'ValueError', 'KeyError', '_InvalidEwError', 'charset', 'lang', 'extend', 'WSP', 'get_fws', '_wsp_splitter', 'ValueTerminal', '_validate_xtext')

## bytecode:

   0: RESUME               
   2: LOAD_GLOBAL          NULL + EncodedWord
  14: PRECALL              
  18: CALL                 
  28: STORE_FAST           ew
  30: LOAD_FAST            value
  32: LOAD_METHOD          startswith
  54: LOAD_CONST           '=?'
  56: PRECALL              
  60: CALL                 
  70: POP_JUMP_FORWARD_IF_TRUE to 150
  72: LOAD_GLOBAL          NULL + errors
  84: LOAD_ATTR            HeaderParseError
  94: LOAD_CONST           'expected encoded word but found {}'
  96: LOAD_METHOD          format
 118: LOAD_FAST            value
 120: PRECALL              
 124: CALL                 
 134: PRECALL              
 138: CALL                 
 148: RAISE_VARARGS        
 150: LOAD_FAST            value
 152: LOAD_CONST           2
 154: LOAD_CONST           None
 156: BUILD_SLICE          
 158: BINARY_SUBSCR        
 168: LOAD_METHOD          split
 190: LOAD_CONST           '?='
 192: LOAD_CONST           1
 194: PRECALL              
 198: CALL                 
 208: UNPACK_EX            
 210: STORE_FAST           tok
 212: STORE_FAST           remainder
 214: LOAD_FAST            tok
 216: LOAD_FAST            value
 218: LOAD_CONST           2
 220: LOAD_CONST           None
 222: BUILD_SLICE          
 224: BINARY_SUBSCR        
 234: COMPARE_OP           ==
 240: POP_JUMP_FORWARD_IF_FALSE to 320
 242: LOAD_GLOBAL          NULL + errors
 254: LOAD_ATTR            HeaderParseError
 264: LOAD_CONST           'expected encoded word but found {}'
 266: LOAD_METHOD          format
 288: LOAD_FAST            value
 290: PRECALL              
 294: CALL                 
 304: PRECALL              
 308: CALL                 
 318: RAISE_VARARGS        
 320: LOAD_CONST           ''
 322: LOAD_METHOD          join
 344: LOAD_FAST            remainder
 346: PRECALL              
 350: CALL                 
 360: STORE_FAST           remstr
 362: LOAD_GLOBAL          NULL + len
 374: LOAD_FAST            remstr
 376: PRECALL              
 380: CALL                 
 390: LOAD_CONST           1
 392: COMPARE_OP           >
 398: POP_JUMP_FORWARD_IF_FALSE to 574
 400: LOAD_FAST            remstr
 402: LOAD_CONST           0
 404: BINARY_SUBSCR        
 414: LOAD_GLOBAL          hexdigits
 426: CONTAINS_OP          
 428: POP_JUMP_FORWARD_IF_FALSE to 574
 430: LOAD_FAST            remstr
 432: LOAD_CONST           1
 434: BINARY_SUBSCR        
 444: LOAD_GLOBAL          hexdigits
 456: CONTAINS_OP          
 458: POP_JUMP_FORWARD_IF_FALSE to 574
 460: LOAD_FAST            tok
 462: LOAD_METHOD          count
 484: LOAD_CONST           '?'
 486: PRECALL              
 490: CALL                 
 500: LOAD_CONST           2
 502: COMPARE_OP           <
 508: POP_JUMP_FORWARD_IF_FALSE to 574
 510: LOAD_FAST            remstr
 512: LOAD_METHOD          split
 534: LOAD_CONST           '?='
 536: LOAD_CONST           1
 538: PRECALL              
 542: CALL                 
 552: UNPACK_EX            
 554: STORE_FAST           rest
 556: STORE_FAST           remainder
 558: LOAD_FAST            tok
 560: LOAD_CONST           '?='
 562: BINARY_OP            +
 566: LOAD_FAST            rest
 568: BINARY_OP            +
 572: STORE_FAST           tok
 574: LOAD_GLOBAL          NULL + len
 586: LOAD_FAST            tok
 588: LOAD_METHOD          split
 610: PRECALL              
 614: CALL                 
 624: PRECALL              
 628: CALL                 
 638: LOAD_CONST           1
 640: COMPARE_OP           >
 646: POP_JUMP_FORWARD_IF_FALSE to 736
 648: LOAD_FAST            ew
 650: LOAD_ATTR            defects
 660: LOAD_METHOD          append
 682: LOAD_GLOBAL          NULL + errors
 694: LOAD_ATTR            InvalidHeaderDefect
 704: LOAD_CONST           'whitespace inside encoded word'
 706: PRECALL              
 710: CALL                 
 720: PRECALL              
 724: CALL                 
 734: POP_TOP              
 736: LOAD_FAST            value
 738: LOAD_FAST            ew
 740: STORE_ATTR           cte
 750: LOAD_CONST           ''
 752: LOAD_METHOD          join
 774: LOAD_FAST            remainder
 776: PRECALL              
 780: CALL                 
 790: STORE_FAST           value
 792: NOP                  
 794: LOAD_GLOBAL          NULL + _ew
 806: LOAD_ATTR            decode
 816: LOAD_CONST           '=?'
 818: LOAD_FAST            tok
 820: BINARY_OP            +
 824: LOAD_CONST           '?='
 826: BINARY_OP            +
 830: PRECALL              
 834: CALL                 
 844: UNPACK_SEQUENCE      
 848: STORE_FAST           text
 850: STORE_FAST           charset
 852: STORE_FAST           lang
 854: STORE_FAST           defects
 856: JUMP_FORWARD         to 978
 858: PUSH_EXC_INFO        
 860: LOAD_GLOBAL          ValueError
 872: LOAD_GLOBAL          KeyError
 884: BUILD_TUPLE          
 886: CHECK_EXC_MATCH      
 888: POP_JUMP_FORWARD_IF_FALSE to 970
 890: POP_TOP              
 892: LOAD_GLOBAL          NULL + _InvalidEwError
 904: LOAD_CONST           "encoded word format invalid: '{}'"
 906: LOAD_METHOD          format
 928: LOAD_FAST            ew
 930: LOAD_ATTR            cte
 940: PRECALL              
 944: CALL                 
 954: PRECALL              
 958: CALL                 
 968: RAISE_VARARGS        
 970: RERAISE              
 972: COPY                 
 974: POP_EXCEPT           
 976: RERAISE              
 978: LOAD_FAST            charset
 980: LOAD_FAST            ew
 982: STORE_ATTR           charset
 992: LOAD_FAST            lang
 994: LOAD_FAST            ew
 996: STORE_ATTR           lang
1006: LOAD_FAST            ew
1008: LOAD_ATTR            defects
1018: LOAD_METHOD          extend
1040: LOAD_FAST            defects
1042: PRECALL              
1046: CALL                 
1056: POP_TOP              
1058: LOAD_FAST            text
1060: POP_JUMP_FORWARD_IF_FALSE to 1358
1062: LOAD_FAST            text
1064: LOAD_CONST           0
1066: BINARY_SUBSCR        
1076: LOAD_GLOBAL          WSP
1088: CONTAINS_OP          
1090: POP_JUMP_FORWARD_IF_FALSE to 1172
1092: LOAD_GLOBAL          NULL + get_fws
1104: LOAD_FAST            text
1106: PRECALL              
1110: CALL                 
1120: UNPACK_SEQUENCE      
1124: STORE_FAST           token
1126: STORE_FAST           text
1128: LOAD_FAST            ew
1130: LOAD_METHOD          append
1152: LOAD_FAST            token
1154: PRECALL              
1158: CALL                 
1168: POP_TOP              
1170: JUMP_BACKWARD        to 1058
1172: LOAD_GLOBAL          NULL + _wsp_splitter
1184: LOAD_FAST            text
1186: LOAD_CONST           1
1188: PRECALL              
1192: CALL                 
1202: UNPACK_EX            
1204: STORE_FAST           chars
1206: STORE_FAST           remainder
1208: LOAD_GLOBAL          NULL + ValueTerminal
1220: LOAD_FAST            chars
1222: LOAD_CONST           'vtext'
1224: PRECALL              
1228: CALL                 
1238: STORE_FAST           vtext
1240: LOAD_GLOBAL          NULL + _validate_xtext
1252: LOAD_FAST            vtext
1254: PRECALL              
1258: CALL                 
1268: POP_TOP              
1270: LOAD_FAST            ew
1272: LOAD_METHOD          append
1294: LOAD_FAST            vtext
1296: PRECALL              
1300: CALL                 
1310: POP_TOP              
1312: LOAD_CONST           ''
1314: LOAD_METHOD          join
1336: LOAD_FAST            remainder
1338: PRECALL              
1342: CALL                 
1352: STORE_FAST           text
1354: LOAD_FAST            text
1356: POP_JUMP_BACKWARD_IF_TRUE to 1062
1358: LOAD_FAST            value
1360: POP_JUMP_FORWARD_IF_FALSE to 1480
1362: LOAD_FAST            value
1364: LOAD_CONST           0
1366: BINARY_SUBSCR        
1376: LOAD_GLOBAL          WSP
1388: CONTAINS_OP          
1390: POP_JUMP_FORWARD_IF_FALSE to 1480
1392: LOAD_FAST            ew
1394: LOAD_ATTR            defects
1404: LOAD_METHOD          append
1426: LOAD_GLOBAL          NULL + errors
1438: LOAD_ATTR            InvalidHeaderDefect
1448: LOAD_CONST           'missing trailing whitespace after encoded-word'
1450: PRECALL              
1454: CALL                 
1464: PRECALL              
1468: CALL                 
1478: POP_TOP              
1480: LOAD_FAST            ew
1482: LOAD_FAST            value
1484: BUILD_TUPLE          
1486: RETURN_VALUE         
