# Disassembly for email.BytesGenerator
# From module file: email.generator

## co_consts:
('BytesGenerator', 'Generates a bytes version of a Message object tree.\n\n    Functionally identical to the base Generator except that the output is\n    bytes and not string.  When surrogates were used in the input to encode\n    bytes, these are decoded back to bytes for output.  If the policy has\n    cte_type set to 7bit, then the message is transformed such that the\n    non-ASCII bytes are properly content transfer encoded, using the charset\n    unknown-8bit.\n\n    The outfp object must accept bytes in its write method.\n    ', <code object write at 0x000002406941A9D0, file "email\generator.py", line 408>, <code object _new_buffer at 0x0000024069465450, file "email\generator.py", line 411>, <code object _encode at 0x000002406945FF00, file "email\generator.py", line 414>, <code object _write_headers at 0x000002406942E290, file "email\generator.py", line 417>, <code object _handle_text at 0x000002406931FA30, file "email\generator.py", line 425>, <code object _compile_re at 0x000002406944A780, file "email\generator.py", line 440>)

## co_names:
('__name__', '__module__', '__qualname__', '__doc__', 'write', '_new_buffer', '_encode', '_write_headers', '_handle_text', '_writeBody', 'classmethod', '_compile_re', '__classcell__')

## bytecode:

   0: MAKE_CELL            __class__
   2: RESUME               
   4: LOAD_NAME            __name__
   6: STORE_NAME           __module__
   8: LOAD_CONST           'BytesGenerator'
  10: STORE_NAME           __qualname__
  12: LOAD_CONST           'Generates a bytes version of a Message object tree.\n\n    Functionally identical to the base Generator except that the output is\n    bytes and not string.  When surrogates were used in the input to encode\n    bytes, these are decoded back to bytes for output.  If the policy has\n    cte_type set to 7bit, then the message is transformed such that the\n    non-ASCII bytes are properly content transfer encoded, using the charset\n    unknown-8bit.\n\n    The outfp object must accept bytes in its write method.\n    '
  14: STORE_NAME           __doc__
  16: LOAD_CONST           <code object write at 0x000002406941A9D0, file "email\generator.py", line 408>
  18: MAKE_FUNCTION        
  20: STORE_NAME           write
  22: LOAD_CONST           <code object _new_buffer at 0x0000024069465450, file "email\generator.py", line 411>
  24: MAKE_FUNCTION        
  26: STORE_NAME           _new_buffer
  28: LOAD_CONST           <code object _encode at 0x000002406945FF00, file "email\generator.py", line 414>
  30: MAKE_FUNCTION        
  32: STORE_NAME           _encode
  34: LOAD_CONST           <code object _write_headers at 0x000002406942E290, file "email\generator.py", line 417>
  36: MAKE_FUNCTION        
  38: STORE_NAME           _write_headers
  40: LOAD_CLOSURE         __class__
  42: BUILD_TUPLE          
  44: LOAD_CONST           <code object _handle_text at 0x000002406931FA30, file "email\generator.py", line 425>
  46: MAKE_FUNCTION        closure
  48: STORE_NAME           _handle_text
  50: LOAD_NAME            _handle_text
  52: STORE_NAME           _writeBody
  54: LOAD_NAME            classmethod
  56: LOAD_CONST           <code object _compile_re at 0x000002406944A780, file "email\generator.py", line 440>
  58: MAKE_FUNCTION        
  60: PRECALL              
  64: CALL                 
  74: STORE_NAME           _compile_re
  76: LOAD_CLOSURE         __class__
  78: COPY                 
  80: STORE_NAME           __classcell__
  82: RETURN_VALUE         
