# Disassembly for email.EmailPolicy.fold_binary
# From module file: email.policy

## co_consts:
('+\n        The same as fold if cte_type is 7bit, except that the returned value is\n        bytes.\n\n        If cte_type is 8bit, non-ASCII binary data is converted back into\n        bytes.  Headers with binary data are not refolded, regardless of the\n        refold_header setting, since there is no way to know whether the binary\n        data consists of single byte characters or multibyte characters.\n\n        If utf8 is true, headers are encoded to utf8, otherwise to ascii with\n        non-ASCII unicode rendered as encoded words.\n\n        ', '7bit', ('refold_binary',), 'utf8', 'ascii', 'surrogateescape')

## co_names:
('_fold', 'cte_type', 'utf8', 'encode')

## bytecode:

   0: RESUME               
   2: LOAD_FAST            self
   4: LOAD_METHOD          _fold
  26: LOAD_FAST            name
  28: LOAD_FAST            value
  30: LOAD_FAST            self
  32: LOAD_ATTR            cte_type
  42: LOAD_CONST           '7bit'
  44: COMPARE_OP           ==
  50: KW_NAMES             
  52: PRECALL              
  56: CALL                 
  66: STORE_FAST           folded
  68: LOAD_FAST            self
  70: LOAD_ATTR            utf8
  80: POP_JUMP_FORWARD_IF_FALSE to 86
  82: LOAD_CONST           'utf8'
  84: JUMP_FORWARD         to 88
  86: LOAD_CONST           'ascii'
  88: STORE_FAST           charset
  90: LOAD_FAST            folded
  92: LOAD_METHOD          encode
 114: LOAD_FAST            charset
 116: LOAD_CONST           'surrogateescape'
 118: PRECALL              
 122: CALL                 
 132: RETURN_VALUE         
