# Disassembly for email.decode_header
# From module file: email.header

## co_consts:
('Decode a message header value without converting charset.\n\n    Returns a list of (string, charset) pairs containing each of the decoded\n    parts of the header.  Charset is None for non-encoded parts of the header,\n    otherwise a lower-case string containing the name of the character set\n    specified in the encoded string.\n\n    header may be a string that may or may not contain RFC2047 encoded words,\n    or it may be a Header object.\n\n    An email.errors.HeaderParseError may be raised when certain decoding error\n    occurs (e.g. a base64 decoding exception).\n    ', '_chunks', <code object <listcomp> at 0x00000240693D23D0, file "email\header.py", line 75>, None, True, 0, False, 1, 2, 'q', 'b', 4, '===', 'Base64 decoding error', 'Unexpected encoding: ', 'raw-unicode-escape')

## co_names:
('hasattr', '_chunks', 'ecre', 'search', 'splitlines', 'split', 'pop', 'lstrip', 'append', 'lower', 'enumerate', 'isspace', 'reversed', 'email', 'quoprimime', 'header_decode', 'len', 'base64mime', 'decode', 'binascii', 'Error', 'HeaderParseError', 'AssertionError', 'isinstance', 'str', 'bytes', 'BSPACE')

## bytecode:

   0: RESUME               
   2: LOAD_GLOBAL          NULL + hasattr
  14: LOAD_FAST            header
  16: LOAD_CONST           '_chunks'
  18: PRECALL              
  22: CALL                 
  32: POP_JUMP_FORWARD_IF_FALSE to 68
  34: LOAD_CONST           <code object <listcomp> at 0x00000240693D23D0, file "email\header.py", line 75>
  36: MAKE_FUNCTION        
  38: LOAD_FAST            header
  40: LOAD_ATTR            _chunks
  50: GET_ITER             
  52: PRECALL              
  56: CALL                 
  66: RETURN_VALUE         
  68: LOAD_GLOBAL          ecre
  80: LOAD_METHOD          search
 102: LOAD_FAST            header
 104: PRECALL              
 108: CALL                 
 118: POP_JUMP_FORWARD_IF_TRUE to 130
 120: LOAD_FAST            header
 122: LOAD_CONST           None
 124: BUILD_TUPLE          
 126: BUILD_LIST           
 128: RETURN_VALUE         
 130: BUILD_LIST           
 132: STORE_FAST           words
 134: LOAD_FAST            header
 136: LOAD_METHOD          splitlines
 158: PRECALL              
 162: CALL                 
 172: GET_ITER             
 174: FOR_ITER             to 636
 176: STORE_FAST           line
 178: LOAD_GLOBAL          ecre
 190: LOAD_METHOD          split
 212: LOAD_FAST            line
 214: PRECALL              
 218: CALL                 
 228: STORE_FAST           parts
 230: LOAD_CONST           True
 232: STORE_FAST           first
 234: LOAD_FAST            parts
 236: POP_JUMP_FORWARD_IF_FALSE to 634
 238: LOAD_FAST            parts
 240: LOAD_METHOD          pop
 262: LOAD_CONST           0
 264: PRECALL              
 268: CALL                 
 278: STORE_FAST           unencoded
 280: LOAD_FAST            first
 282: POP_JUMP_FORWARD_IF_FALSE to 328
 284: LOAD_FAST            unencoded
 286: LOAD_METHOD          lstrip
 308: PRECALL              
 312: CALL                 
 322: STORE_FAST           unencoded
 324: LOAD_CONST           False
 326: STORE_FAST           first
 328: LOAD_FAST            unencoded
 330: POP_JUMP_FORWARD_IF_FALSE to 380
 332: LOAD_FAST            words
 334: LOAD_METHOD          append
 356: LOAD_FAST            unencoded
 358: LOAD_CONST           None
 360: LOAD_CONST           None
 362: BUILD_TUPLE          
 364: PRECALL              
 368: CALL                 
 378: POP_TOP              
 380: LOAD_FAST            parts
 382: POP_JUMP_FORWARD_IF_FALSE to 630
 384: LOAD_FAST            parts
 386: LOAD_METHOD          pop
 408: LOAD_CONST           0
 410: PRECALL              
 414: CALL                 
 424: LOAD_METHOD          lower
 446: PRECALL              
 450: CALL                 
 460: STORE_FAST           charset
 462: LOAD_FAST            parts
 464: LOAD_METHOD          pop
 486: LOAD_CONST           0
 488: PRECALL              
 492: CALL                 
 502: LOAD_METHOD          lower
 524: PRECALL              
 528: CALL                 
 538: STORE_FAST           encoding
 540: LOAD_FAST            parts
 542: LOAD_METHOD          pop
 564: LOAD_CONST           0
 566: PRECALL              
 570: CALL                 
 580: STORE_FAST           encoded
 582: LOAD_FAST            words
 584: LOAD_METHOD          append
 606: LOAD_FAST            encoded
 608: LOAD_FAST            encoding
 610: LOAD_FAST            charset
 612: BUILD_TUPLE          
 614: PRECALL              
 618: CALL                 
 628: POP_TOP              
 630: LOAD_FAST            parts
 632: POP_JUMP_BACKWARD_IF_TRUE to 238
 634: JUMP_BACKWARD        to 174
 636: BUILD_LIST           
 638: STORE_FAST           droplist
 640: LOAD_GLOBAL          NULL + enumerate
 652: LOAD_FAST            words
 654: PRECALL              
 658: CALL                 
 668: GET_ITER             
 670: FOR_ITER             to 862
 672: UNPACK_SEQUENCE      
 676: STORE_FAST           n
 678: STORE_FAST           w
 680: LOAD_FAST            n
 682: LOAD_CONST           1
 684: COMPARE_OP           >
 690: POP_JUMP_FORWARD_IF_FALSE to 860
 692: LOAD_FAST            w
 694: LOAD_CONST           1
 696: BINARY_SUBSCR        
 706: POP_JUMP_FORWARD_IF_FALSE to 860
 708: LOAD_FAST            words
 710: LOAD_FAST            n
 712: LOAD_CONST           2
 714: BINARY_OP            -
 718: BINARY_SUBSCR        
 728: LOAD_CONST           1
 730: BINARY_SUBSCR        
 740: POP_JUMP_FORWARD_IF_FALSE to 860
 742: LOAD_FAST            words
 744: LOAD_FAST            n
 746: LOAD_CONST           1
 748: BINARY_OP            -
 752: BINARY_SUBSCR        
 762: LOAD_CONST           0
 764: BINARY_SUBSCR        
 774: LOAD_METHOD          isspace
 796: PRECALL              
 800: CALL                 
 810: POP_JUMP_FORWARD_IF_FALSE to 860
 812: LOAD_FAST            droplist
 814: LOAD_METHOD          append
 836: LOAD_FAST            n
 838: LOAD_CONST           1
 840: BINARY_OP            -
 844: PRECALL              
 848: CALL                 
 858: POP_TOP              
 860: JUMP_BACKWARD        to 670
 862: LOAD_GLOBAL          NULL + reversed
 874: LOAD_FAST            droplist
 876: PRECALL              
 880: CALL                 
 890: GET_ITER             
 892: FOR_ITER             to 904
 894: STORE_FAST           d
 896: LOAD_FAST            words
 898: LOAD_FAST            d
 900: DELETE_SUBSCR        
 902: JUMP_BACKWARD        to 892
 904: BUILD_LIST           
 906: STORE_FAST           decoded_words
 908: LOAD_FAST            words
 910: GET_ITER             
 912: FOR_ITER             to 1398
 914: UNPACK_SEQUENCE      
 918: STORE_FAST           encoded_string
 920: STORE_FAST           encoding
 922: STORE_FAST           charset
 924: LOAD_FAST            encoding
 926: POP_JUMP_FORWARD_IF_NOT_NONE to 976
 928: LOAD_FAST            decoded_words
 930: LOAD_METHOD          append
 952: LOAD_FAST            encoded_string
 954: LOAD_FAST            charset
 956: BUILD_TUPLE          
 958: PRECALL              
 962: CALL                 
 972: POP_TOP              
 974: JUMP_BACKWARD        to 912
 976: LOAD_FAST            encoding
 978: LOAD_CONST           'q'
 980: COMPARE_OP           ==
 986: POP_JUMP_FORWARD_IF_FALSE to 1098
 988: LOAD_GLOBAL          email
1000: LOAD_ATTR            quoprimime
1010: LOAD_METHOD          header_decode
1032: LOAD_FAST            encoded_string
1034: PRECALL              
1038: CALL                 
1048: STORE_FAST           word
1050: LOAD_FAST            decoded_words
1052: LOAD_METHOD          append
1074: LOAD_FAST            word
1076: LOAD_FAST            charset
1078: BUILD_TUPLE          
1080: PRECALL              
1084: CALL                 
1094: POP_TOP              
1096: JUMP_BACKWARD        to 912
1098: LOAD_FAST            encoding
1100: LOAD_CONST           'b'
1102: COMPARE_OP           ==
1108: POP_JUMP_FORWARD_IF_FALSE to 1362
1110: LOAD_GLOBAL          NULL + len
1122: LOAD_FAST            encoded_string
1124: PRECALL              
1128: CALL                 
1138: LOAD_CONST           4
1140: BINARY_OP            %
1144: STORE_FAST           paderr
1146: LOAD_FAST            paderr
1148: POP_JUMP_FORWARD_IF_FALSE to 1182
1150: LOAD_FAST            encoded_string
1152: LOAD_CONST           '==='
1154: LOAD_CONST           None
1156: LOAD_CONST           4
1158: LOAD_FAST            paderr
1160: BINARY_OP            -
1164: BUILD_SLICE          
1166: BINARY_SUBSCR        
1176: BINARY_OP            +=
1180: STORE_FAST           encoded_string
1182: NOP                  
1184: LOAD_GLOBAL          email
1196: LOAD_ATTR            base64mime
1206: LOAD_METHOD          decode
1228: LOAD_FAST            encoded_string
1230: PRECALL              
1234: CALL                 
1244: STORE_FAST           word
1246: LOAD_FAST            decoded_words
1248: LOAD_METHOD          append
1270: LOAD_FAST            word
1272: LOAD_FAST            charset
1274: BUILD_TUPLE          
1276: PRECALL              
1280: CALL                 
1290: POP_TOP              
1292: JUMP_BACKWARD        to 912
1294: PUSH_EXC_INFO        
1296: LOAD_GLOBAL          binascii
1308: LOAD_ATTR            Error
1318: CHECK_EXC_MATCH      
1320: POP_JUMP_FORWARD_IF_FALSE to 1354
1322: POP_TOP              
1324: LOAD_GLOBAL          NULL + HeaderParseError
1336: LOAD_CONST           'Base64 decoding error'
1338: PRECALL              
1342: CALL                 
1352: RAISE_VARARGS        
1354: RERAISE              
1356: COPY                 
1358: POP_EXCEPT           
1360: RERAISE              
1362: LOAD_GLOBAL          NULL + AssertionError
1374: LOAD_CONST           'Unexpected encoding: '
1376: LOAD_FAST            encoding
1378: BINARY_OP            +
1382: PRECALL              
1386: CALL                 
1396: RAISE_VARARGS        
1398: BUILD_LIST           
1400: STORE_FAST           collapsed
1402: LOAD_CONST           None
1404: COPY                 
1406: STORE_FAST           last_word
1408: STORE_FAST           last_charset
1410: LOAD_FAST            decoded_words
1412: GET_ITER             
1414: FOR_ITER             to 1624
1416: UNPACK_SEQUENCE      
1420: STORE_FAST           word
1422: STORE_FAST           charset
1424: LOAD_GLOBAL          NULL + isinstance
1436: LOAD_FAST            word
1438: LOAD_GLOBAL          str
1450: PRECALL              
1454: CALL                 
1464: POP_JUMP_FORWARD_IF_FALSE to 1498
1466: LOAD_GLOBAL          NULL + bytes
1478: LOAD_FAST            word
1480: LOAD_CONST           'raw-unicode-escape'
1482: PRECALL              
1486: CALL                 
1496: STORE_FAST           word
1498: LOAD_FAST            last_word
1500: POP_JUMP_FORWARD_IF_NOT_NONE to 1512
1502: LOAD_FAST            word
1504: STORE_FAST           last_word
1506: LOAD_FAST            charset
1508: STORE_FAST           last_charset
1510: JUMP_BACKWARD        to 1414
1512: LOAD_FAST            charset
1514: LOAD_FAST            last_charset
1516: COMPARE_OP           !=
1522: POP_JUMP_FORWARD_IF_FALSE to 1580
1524: LOAD_FAST            collapsed
1526: LOAD_METHOD          append
1548: LOAD_FAST            last_word
1550: LOAD_FAST            last_charset
1552: BUILD_TUPLE          
1554: PRECALL              
1558: CALL                 
1568: POP_TOP              
1570: LOAD_FAST            word
1572: STORE_FAST           last_word
1574: LOAD_FAST            charset
1576: STORE_FAST           last_charset
1578: JUMP_BACKWARD        to 1414
1580: LOAD_FAST            last_charset
1582: POP_JUMP_FORWARD_IF_NOT_NONE to 1612
1584: LOAD_FAST            last_word
1586: LOAD_GLOBAL          BSPACE
1598: LOAD_FAST            word
1600: BINARY_OP            +
1604: BINARY_OP            +=
1608: STORE_FAST           last_word
1610: JUMP_BACKWARD        to 1414
1612: LOAD_FAST            last_word
1614: LOAD_FAST            word
1616: BINARY_OP            +=
1620: STORE_FAST           last_word
1622: JUMP_BACKWARD        to 1414
1624: LOAD_FAST            collapsed
1626: LOAD_METHOD          append
1648: LOAD_FAST            last_word
1650: LOAD_FAST            last_charset
1652: BUILD_TUPLE          
1654: PRECALL              
1658: CALL                 
1668: POP_TOP              
1670: LOAD_FAST            collapsed
1672: RETURN_VALUE         
