# Disassembly for email.Address.__init__
# From module file: email.headerregistry

## co_consts:
("Create an object representing a full email address.\n\n        An address can have a 'display_name', a 'username', and a 'domain'.  In\n        addition to specifying the username and domain separately, they may be\n        specified together by using the addr_spec keyword *instead of* the\n        username and domain keywords.  If an addr_spec string is specified it\n        must be properly quoted according to RFC 5322 rules; an error will be\n        raised if it is not.\n\n        An Address object has display_name, username, domain, and addr_spec\n        attributes, all of which are read-only.  The addr_spec and the string\n        value of the object are both quoted according to RFC5322 rules, but\n        without any Content Transfer Encoding.\n\n        ", '', None, '\r', '\n', 'invalid arguments; address parts cannot contain CR or LF', 'addrspec specified when username and/or domain also specified', "Invalid addr_spec; only '{}' could be parsed from '{}'", 0)

## co_names:
('join', 'filter', 'ValueError', 'TypeError', 'parser', 'get_addr_spec', 'format', 'all_defects', 'local_part', 'domain', '_display_name', '_username', '_domain')

## bytecode:

   0: RESUME               
   2: LOAD_CONST           ''
   4: LOAD_METHOD          join
  26: LOAD_GLOBAL          NULL + filter
  38: LOAD_CONST           None
  40: LOAD_FAST            display_name
  42: LOAD_FAST            username
  44: LOAD_FAST            domain
  46: LOAD_FAST            addr_spec
  48: BUILD_TUPLE          
  50: PRECALL              
  54: CALL                 
  64: PRECALL              
  68: CALL                 
  78: STORE_FAST           inputs
  80: LOAD_CONST           '\r'
  82: LOAD_FAST            inputs
  84: CONTAINS_OP          
  86: POP_JUMP_FORWARD_IF_TRUE to 96
  88: LOAD_CONST           '\n'
  90: LOAD_FAST            inputs
  92: CONTAINS_OP          
  94: POP_JUMP_FORWARD_IF_FALSE to 126
  96: LOAD_GLOBAL          NULL + ValueError
 108: LOAD_CONST           'invalid arguments; address parts cannot contain CR or LF'
 110: PRECALL              
 114: CALL                 
 124: RAISE_VARARGS        
 126: LOAD_FAST            addr_spec
 128: POP_JUMP_FORWARD_IF_NONE to 356
 130: LOAD_FAST            username
 132: POP_JUMP_FORWARD_IF_TRUE to 138
 134: LOAD_FAST            domain
 136: POP_JUMP_FORWARD_IF_FALSE to 168
 138: LOAD_GLOBAL          NULL + TypeError
 150: LOAD_CONST           'addrspec specified when username and/or domain also specified'
 152: PRECALL              
 156: CALL                 
 166: RAISE_VARARGS        
 168: LOAD_GLOBAL          NULL + parser
 180: LOAD_ATTR            get_addr_spec
 190: LOAD_FAST            addr_spec
 192: PRECALL              
 196: CALL                 
 206: UNPACK_SEQUENCE      
 210: STORE_FAST           a_s
 212: STORE_FAST           rest
 214: LOAD_FAST            rest
 216: POP_JUMP_FORWARD_IF_FALSE to 288
 218: LOAD_GLOBAL          NULL + ValueError
 230: LOAD_CONST           "Invalid addr_spec; only '{}' could be parsed from '{}'"
 232: LOAD_METHOD          format
 254: LOAD_FAST            a_s
 256: LOAD_FAST            addr_spec
 258: PRECALL              
 262: CALL                 
 272: PRECALL              
 276: CALL                 
 286: RAISE_VARARGS        
 288: LOAD_FAST            a_s
 290: LOAD_ATTR            all_defects
 300: POP_JUMP_FORWARD_IF_FALSE to 328
 302: LOAD_FAST            a_s
 304: LOAD_ATTR            all_defects
 314: LOAD_CONST           0
 316: BINARY_SUBSCR        
 326: RAISE_VARARGS        
 328: LOAD_FAST            a_s
 330: LOAD_ATTR            local_part
 340: STORE_FAST           username
 342: LOAD_FAST            a_s
 344: LOAD_ATTR            domain
 354: STORE_FAST           domain
 356: LOAD_FAST            display_name
 358: LOAD_FAST            self
 360: STORE_ATTR           _display_name
 370: LOAD_FAST            username
 372: LOAD_FAST            self
 374: STORE_ATTR           _username
 384: LOAD_FAST            domain
 386: LOAD_FAST            self
 388: STORE_ATTR           _domain
 398: LOAD_CONST           None
 400: RETURN_VALUE         
