# Disassembly for email.Token
# From module file: email._header_value_parser

## co_consts:
('Token', 'token', False, None)

## co_names:
('__name__', '__module__', '__qualname__', 'token_type', 'encode_as_ew')

## bytecode:

   0: RESUME               
   2: LOAD_NAME            __name__
   4: STORE_NAME           __module__
   6: LOAD_CONST           'Token'
   8: STORE_NAME           __qualname__
  10: LOAD_CONST           'token'
  12: STORE_NAME           token_type
  14: LOAD_CONST           False
  16: STORE_NAME           encode_as_ew
  18: LOAD_CONST           None
  20: RETURN_VALUE         
