# Disassembly for email.Message.get_filename
# From module file: email.message

## co_consts:
("Return the filename associated with the payload if present.\n\n        The filename is extracted from the Content-Disposition header's\n        `filename' parameter, and it is unquoted.  If that header is missing\n        the `filename' parameter, this method falls back to looking for the\n        `name' parameter.\n        ", 'filename', 'content-disposition', 'name', 'content-type')

## co_names:
('object', 'get_param', 'utils', 'collapse_rfc2231_value', 'strip')

## bytecode:

   0: RESUME               
   2: LOAD_GLOBAL          NULL + object
  14: PRECALL              
  18: CALL                 
  28: STORE_FAST           missing
  30: LOAD_FAST            self
  32: LOAD_METHOD          get_param
  54: LOAD_CONST           'filename'
  56: LOAD_FAST            missing
  58: LOAD_CONST           'content-disposition'
  60: PRECALL              
  64: CALL                 
  74: STORE_FAST           filename
  76: LOAD_FAST            filename
  78: LOAD_FAST            missing
  80: IS_OP                
  82: POP_JUMP_FORWARD_IF_FALSE to 130
  84: LOAD_FAST            self
  86: LOAD_METHOD          get_param
 108: LOAD_CONST           'name'
 110: LOAD_FAST            missing
 112: LOAD_CONST           'content-type'
 114: PRECALL              
 118: CALL                 
 128: STORE_FAST           filename
 130: LOAD_FAST            filename
 132: LOAD_FAST            missing
 134: IS_OP                
 136: POP_JUMP_FORWARD_IF_FALSE to 142
 138: LOAD_FAST            failobj
 140: RETURN_VALUE         
 142: LOAD_GLOBAL          NULL + utils
 154: LOAD_ATTR            collapse_rfc2231_value
 164: LOAD_FAST            filename
 166: PRECALL              
 170: CALL                 
 180: LOAD_METHOD          strip
 202: PRECALL              
 206: CALL                 
 216: RETURN_VALUE         
