# Disassembly for email.LocalPart
# From module file: email._header_value_parser

## co_consts:
('LocalPart', 'local-part', False, <code object value at 0x000002406944A230, file "email\_header_value_parser.py", line 603>, <code object local_part at 0x0000024068DC3FC0, file "email\_header_value_parser.py", line 610>, None)

## co_names:
('__name__', '__module__', '__qualname__', 'token_type', 'as_ew_allowed', 'property', 'value', 'local_part')

## bytecode:

   0: RESUME               
   2: LOAD_NAME            __name__
   4: STORE_NAME           __module__
   6: LOAD_CONST           'LocalPart'
   8: STORE_NAME           __qualname__
  10: LOAD_CONST           'local-part'
  12: STORE_NAME           token_type
  14: LOAD_CONST           False
  16: STORE_NAME           as_ew_allowed
  18: LOAD_NAME            property
  20: LOAD_CONST           <code object value at 0x000002406944A230, file "email\_header_value_parser.py", line 603>
  22: MAKE_FUNCTION        
  24: PRECALL              
  28: CALL                 
  38: STORE_NAME           value
  40: LOAD_NAME            property
  42: LOAD_CONST           <code object local_part at 0x0000024068DC3FC0, file "email\_header_value_parser.py", line 610>
  44: MAKE_FUNCTION        
  46: PRECALL              
  50: CALL                 
  60: STORE_NAME           local_part
  62: LOAD_CONST           None
  64: RETURN_VALUE         
