# Disassembly for email.get_obs_route
# From module file: email._header_value_parser

## co_consts:
(' obs-route = obs-domain-list ":"\n        obs-domain-list = *(CFWS / ",") "@" domain *("," [CFWS] ["@" domain])\n\n        Returns an obs-route token with the appropriate sub-tokens (that is,\n        there is no obs-domain-list in the parse tree).\n    ', 0, ',', 1, None, '@', "expected obs-route domain but found '{}'", 'end of header while parsing obs-route', ':', "expected ':' marking end of obs-route but found '{}'", 'end-of-obs-route-marker')

## co_names:
('ObsRoute', 'CFWS_LEADER', 'get_cfws', 'append', 'ListSeparator', 'errors', 'HeaderParseError', 'format', 'RouteComponentMarker', 'get_domain', 'ValueTerminal')

## bytecode:

   0: RESUME               
   2: LOAD_GLOBAL          NULL + ObsRoute
  14: PRECALL              
  18: CALL                 
  28: STORE_FAST           obs_route
  30: LOAD_FAST            value
  32: POP_JUMP_FORWARD_IF_FALSE to 352
  34: LOAD_FAST            value
  36: LOAD_CONST           0
  38: BINARY_SUBSCR        
  48: LOAD_CONST           ','
  50: COMPARE_OP           ==
  56: POP_JUMP_FORWARD_IF_TRUE to 88
  58: LOAD_FAST            value
  60: LOAD_CONST           0
  62: BINARY_SUBSCR        
  72: LOAD_GLOBAL          CFWS_LEADER
  84: CONTAINS_OP          
  86: POP_JUMP_FORWARD_IF_FALSE to 352
  88: LOAD_FAST            value
  90: LOAD_CONST           0
  92: BINARY_SUBSCR        
 102: LOAD_GLOBAL          CFWS_LEADER
 114: CONTAINS_OP          
 116: POP_JUMP_FORWARD_IF_FALSE to 198
 118: LOAD_GLOBAL          NULL + get_cfws
 130: LOAD_FAST            value
 132: PRECALL              
 136: CALL                 
 146: UNPACK_SEQUENCE      
 150: STORE_FAST           token
 152: STORE_FAST           value
 154: LOAD_FAST            obs_route
 156: LOAD_METHOD          append
 178: LOAD_FAST            token
 180: PRECALL              
 184: CALL                 
 194: POP_TOP              
 196: JUMP_FORWARD         to 294
 198: LOAD_FAST            value
 200: LOAD_CONST           0
 202: BINARY_SUBSCR        
 212: LOAD_CONST           ','
 214: COMPARE_OP           ==
 220: POP_JUMP_FORWARD_IF_FALSE to 294
 222: LOAD_FAST            obs_route
 224: LOAD_METHOD          append
 246: LOAD_GLOBAL          ListSeparator
 258: PRECALL              
 262: CALL                 
 272: POP_TOP              
 274: LOAD_FAST            value
 276: LOAD_CONST           1
 278: LOAD_CONST           None
 280: BUILD_SLICE          
 282: BINARY_SUBSCR        
 292: STORE_FAST           value
 294: LOAD_FAST            value
 296: POP_JUMP_FORWARD_IF_FALSE to 352
 298: LOAD_FAST            value
 300: LOAD_CONST           0
 302: BINARY_SUBSCR        
 312: LOAD_CONST           ','
 314: COMPARE_OP           ==
 320: POP_JUMP_BACKWARD_IF_TRUE to 88
 322: LOAD_FAST            value
 324: LOAD_CONST           0
 326: BINARY_SUBSCR        
 336: LOAD_GLOBAL          CFWS_LEADER
 348: CONTAINS_OP          
 350: POP_JUMP_BACKWARD_IF_TRUE to 88
 352: LOAD_FAST            value
 354: POP_JUMP_FORWARD_IF_FALSE to 380
 356: LOAD_FAST            value
 358: LOAD_CONST           0
 360: BINARY_SUBSCR        
 370: LOAD_CONST           '@'
 372: COMPARE_OP           !=
 378: POP_JUMP_FORWARD_IF_FALSE to 458
 380: LOAD_GLOBAL          NULL + errors
 392: LOAD_ATTR            HeaderParseError
 402: LOAD_CONST           "expected obs-route domain but found '{}'"
 404: LOAD_METHOD          format
 426: LOAD_FAST            value
 428: PRECALL              
 432: CALL                 
 442: PRECALL              
 446: CALL                 
 456: RAISE_VARARGS        
 458: LOAD_FAST            obs_route
 460: LOAD_METHOD          append
 482: LOAD_GLOBAL          RouteComponentMarker
 494: PRECALL              
 498: CALL                 
 508: POP_TOP              
 510: LOAD_GLOBAL          NULL + get_domain
 522: LOAD_FAST            value
 524: LOAD_CONST           1
 526: LOAD_CONST           None
 528: BUILD_SLICE          
 530: BINARY_SUBSCR        
 540: PRECALL              
 544: CALL                 
 554: UNPACK_SEQUENCE      
 558: STORE_FAST           token
 560: STORE_FAST           value
 562: LOAD_FAST            obs_route
 564: LOAD_METHOD          append
 586: LOAD_FAST            token
 588: PRECALL              
 592: CALL                 
 602: POP_TOP              
 604: LOAD_FAST            value
 606: POP_JUMP_FORWARD_IF_FALSE to 1016
 608: LOAD_FAST            value
 610: LOAD_CONST           0
 612: BINARY_SUBSCR        
 622: LOAD_CONST           ','
 624: COMPARE_OP           ==
 630: POP_JUMP_FORWARD_IF_FALSE to 1016
 632: LOAD_FAST            obs_route
 634: LOAD_METHOD          append
 656: LOAD_GLOBAL          ListSeparator
 668: PRECALL              
 672: CALL                 
 682: POP_TOP              
 684: LOAD_FAST            value
 686: LOAD_CONST           1
 688: LOAD_CONST           None
 690: BUILD_SLICE          
 692: BINARY_SUBSCR        
 702: STORE_FAST           value
 704: LOAD_FAST            value
 706: POP_JUMP_FORWARD_IF_TRUE to 710
 708: JUMP_FORWARD         to 1016
 710: LOAD_FAST            value
 712: LOAD_CONST           0
 714: BINARY_SUBSCR        
 724: LOAD_GLOBAL          CFWS_LEADER
 736: CONTAINS_OP          
 738: POP_JUMP_FORWARD_IF_FALSE to 818
 740: LOAD_GLOBAL          NULL + get_cfws
 752: LOAD_FAST            value
 754: PRECALL              
 758: CALL                 
 768: UNPACK_SEQUENCE      
 772: STORE_FAST           token
 774: STORE_FAST           value
 776: LOAD_FAST            obs_route
 778: LOAD_METHOD          append
 800: LOAD_FAST            token
 802: PRECALL              
 806: CALL                 
 816: POP_TOP              
 818: LOAD_FAST            value
 820: LOAD_CONST           0
 822: BINARY_SUBSCR        
 832: LOAD_CONST           '@'
 834: COMPARE_OP           ==
 840: POP_JUMP_FORWARD_IF_FALSE to 988
 842: LOAD_FAST            obs_route
 844: LOAD_METHOD          append
 866: LOAD_GLOBAL          RouteComponentMarker
 878: PRECALL              
 882: CALL                 
 892: POP_TOP              
 894: LOAD_GLOBAL          NULL + get_domain
 906: LOAD_FAST            value
 908: LOAD_CONST           1
 910: LOAD_CONST           None
 912: BUILD_SLICE          
 914: BINARY_SUBSCR        
 924: PRECALL              
 928: CALL                 
 938: UNPACK_SEQUENCE      
 942: STORE_FAST           token
 944: STORE_FAST           value
 946: LOAD_FAST            obs_route
 948: LOAD_METHOD          append
 970: LOAD_FAST            token
 972: PRECALL              
 976: CALL                 
 986: POP_TOP              
 988: LOAD_FAST            value
 990: POP_JUMP_FORWARD_IF_FALSE to 1016
 992: LOAD_FAST            value
 994: LOAD_CONST           0
 996: BINARY_SUBSCR        
1006: LOAD_CONST           ','
1008: COMPARE_OP           ==
1014: POP_JUMP_BACKWARD_IF_TRUE to 632
1016: LOAD_FAST            value
1018: POP_JUMP_FORWARD_IF_TRUE to 1060
1020: LOAD_GLOBAL          NULL + errors
1032: LOAD_ATTR            HeaderParseError
1042: LOAD_CONST           'end of header while parsing obs-route'
1044: PRECALL              
1048: CALL                 
1058: RAISE_VARARGS        
1060: LOAD_FAST            value
1062: LOAD_CONST           0
1064: BINARY_SUBSCR        
1074: LOAD_CONST           ':'
1076: COMPARE_OP           !=
1082: POP_JUMP_FORWARD_IF_FALSE to 1162
1084: LOAD_GLOBAL          NULL + errors
1096: LOAD_ATTR            HeaderParseError
1106: LOAD_CONST           "expected ':' marking end of obs-route but found '{}'"
1108: LOAD_METHOD          format
1130: LOAD_FAST            value
1132: PRECALL              
1136: CALL                 
1146: PRECALL              
1150: CALL                 
1160: RAISE_VARARGS        
1162: LOAD_FAST            obs_route
1164: LOAD_METHOD          append
1186: LOAD_GLOBAL          NULL + ValueTerminal
1198: LOAD_CONST           ':'
1200: LOAD_CONST           'end-of-obs-route-marker'
1202: PRECALL              
1206: CALL                 
1216: PRECALL              
1220: CALL                 
1230: POP_TOP              
1232: LOAD_FAST            obs_route
1234: LOAD_FAST            value
1236: LOAD_CONST           1
1238: LOAD_CONST           None
1240: BUILD_SLICE          
1242: BINARY_SUBSCR        
1252: BUILD_TUPLE          
1254: RETURN_VALUE         
