# Disassembly for email.set_message_content
# From module file: email.contentmanager

## co_consts:
(None, 'partial', 'message/partial is not supported for Message objects', 'rfc822', (None, '7bit', '8bit', 'binary'), 'message/rfc822 parts do not support cte={}', '8bit', 'external-body', (None, '7bit'), 'message/external-body parts do not support cte={}', '7bit', 'message', 'Content-Transfer-Encoding')

## co_names:
('ValueError', 'format', '_prepare_set', 'set_payload', '_finalize_set')

## bytecode:

   0: RESUME               
   2: LOAD_FAST            subtype
   4: LOAD_CONST           'partial'
   6: COMPARE_OP           ==
  12: POP_JUMP_FORWARD_IF_FALSE to 44
  14: LOAD_GLOBAL          NULL + ValueError
  26: LOAD_CONST           'message/partial is not supported for Message objects'
  28: PRECALL              
  32: CALL                 
  42: RAISE_VARARGS        
  44: LOAD_FAST            subtype
  46: LOAD_CONST           'rfc822'
  48: COMPARE_OP           ==
  54: POP_JUMP_FORWARD_IF_FALSE to 146
  56: LOAD_FAST            cte
  58: LOAD_CONST           (None, '7bit', '8bit', 'binary')
  60: CONTAINS_OP          
  62: POP_JUMP_FORWARD_IF_FALSE to 132
  64: LOAD_GLOBAL          NULL + ValueError
  76: LOAD_CONST           'message/rfc822 parts do not support cte={}'
  78: LOAD_METHOD          format
 100: LOAD_FAST            cte
 102: PRECALL              
 106: CALL                 
 116: PRECALL              
 120: CALL                 
 130: RAISE_VARARGS        
 132: LOAD_FAST            cte
 134: POP_JUMP_FORWARD_IF_NOT_NONE to 140
 136: LOAD_CONST           '8bit'
 138: JUMP_FORWARD         to 142
 140: LOAD_FAST            cte
 142: STORE_FAST           cte
 144: JUMP_FORWARD         to 248
 146: LOAD_FAST            subtype
 148: LOAD_CONST           'external-body'
 150: COMPARE_OP           ==
 156: POP_JUMP_FORWARD_IF_FALSE to 240
 158: LOAD_FAST            cte
 160: LOAD_CONST           (None, '7bit')
 162: CONTAINS_OP          
 164: POP_JUMP_FORWARD_IF_FALSE to 234
 166: LOAD_GLOBAL          NULL + ValueError
 178: LOAD_CONST           'message/external-body parts do not support cte={}'
 180: LOAD_METHOD          format
 202: LOAD_FAST            cte
 204: PRECALL              
 208: CALL                 
 218: PRECALL              
 222: CALL                 
 232: RAISE_VARARGS        
 234: LOAD_CONST           '7bit'
 236: STORE_FAST           cte
 238: JUMP_FORWARD         to 248
 240: LOAD_FAST            cte
 242: POP_JUMP_FORWARD_IF_NOT_NONE to 248
 244: LOAD_CONST           '7bit'
 246: STORE_FAST           cte
 248: LOAD_GLOBAL          NULL + _prepare_set
 260: LOAD_FAST            msg
 262: LOAD_CONST           'message'
 264: LOAD_FAST            subtype
 266: LOAD_FAST            headers
 268: PRECALL              
 272: CALL                 
 282: POP_TOP              
 284: LOAD_FAST            msg
 286: LOAD_METHOD          set_payload
 308: LOAD_FAST            message
 310: BUILD_LIST           
 312: PRECALL              
 316: CALL                 
 326: POP_TOP              
 328: LOAD_FAST            cte
 330: LOAD_FAST            msg
 332: LOAD_CONST           'Content-Transfer-Encoding'
 334: STORE_SUBSCR         
 338: LOAD_GLOBAL          NULL + _finalize_set
 350: LOAD_FAST            msg
 352: LOAD_FAST            disposition
 354: LOAD_FAST            filename
 356: LOAD_FAST            cid
 358: LOAD_FAST            params
 360: PRECALL              
 364: CALL                 
 374: POP_TOP              
 376: LOAD_CONST           None
 378: RETURN_VALUE         
