# Disassembly for email.TokenList.comments
# From module file: email._header_value_parser

## co_consts:
(None,)

## co_names:
('extend', 'comments')

## bytecode:

   0: RESUME               
   2: BUILD_LIST           
   4: STORE_FAST           comments
   6: LOAD_FAST            self
   8: GET_ITER             
  10: FOR_ITER             to 68
  12: STORE_FAST           token
  14: LOAD_FAST            comments
  16: LOAD_METHOD          extend
  38: LOAD_FAST            token
  40: LOAD_ATTR            comments
  50: PRECALL              
  54: CALL                 
  64: POP_TOP              
  66: JUMP_BACKWARD        to 10
  68: LOAD_FAST            comments
  70: RETURN_VALUE         
