# Disassembly for email.MIMEPart.clear_content
# From module file: email.message

## co_consts:
(None, <code object <listcomp> at 0x00000240693D2E80, file "email\message.py", line 1190>)

## co_names:
('_headers', '_payload')

## bytecode:

   0: RESUME               
   2: LOAD_CONST           <code object <listcomp> at 0x00000240693D2E80, file "email\message.py", line 1190>
   4: MAKE_FUNCTION        
   6: LOAD_FAST            self
   8: LOAD_ATTR            _headers
  18: GET_ITER             
  20: PRECALL              
  24: CALL                 
  34: LOAD_FAST            self
  36: STORE_ATTR           _headers
  46: LOAD_CONST           None
  48: LOAD_FAST            self
  50: STORE_ATTR           _payload
  60: LOAD_CONST           None
  62: RETURN_VALUE         
