# Disassembly for email.HeaderRegistry.map_to_type
# From module file: email.headerregistry

## co_consts:
('Register cls as the specialized class for handling "name" headers.\n\n        ', None)

## co_names:
('registry', 'lower')

## bytecode:

   0: RESUME               
   2: LOAD_FAST            cls
   4: LOAD_FAST            self
   6: LOAD_ATTR            registry
  16: LOAD_FAST            name
  18: LOAD_METHOD          lower
  40: PRECALL              
  44: CALL                 
  54: STORE_SUBSCR         
  58: LOAD_CONST           None
  60: RETURN_VALUE         
