# Disassembly for email.Charset
# From module file: email.charset

## co_consts:
('Charset', "Map character sets to their email properties.\n\n    This class provides information about the requirements imposed on email\n    for a specific character set.  It also provides convenience routines for\n    converting between character sets, given the availability of the\n    applicable codecs.  Given a character set, it will do its best to provide\n    information on how to use that character set in an email in an\n    RFC-compliant way.\n\n    Certain character sets must be encoded with quoted-printable or base64\n    when used in email headers or bodies.  Certain character sets must be\n    converted outright, and are not allowed in email.  Instances of this\n    module expose the following information about a character set:\n\n    input_charset: The initial character set specified.  Common aliases\n                   are converted to their `official' email names (e.g. latin_1\n                   is converted to iso-8859-1).  Defaults to 7-bit us-ascii.\n\n    header_encoding: If the character set must be encoded before it can be\n                     used in an email header, this attribute will be set to\n                     Charset.QP (for quoted-printable), Charset.BASE64 (for\n                     base64 encoding), or Charset.SHORTEST for the shortest of\n                     QP or BASE64 encoding.  Otherwise, it will be None.\n\n    body_encoding: Same as header_encoding, but describes the encoding for the\n                   mail message's body, which indeed may be different than the\n                   header encoding.  Charset.SHORTEST is not allowed for\n                   body_encoding.\n\n    output_charset: Some character sets must be converted before they can be\n                    used in email headers or bodies.  If the input_charset is\n                    one of them, this attribute will contain the name of the\n                    charset output will be converted to.  Otherwise, it will\n                    be None.\n\n    input_codec: The name of the Python codec used to convert the\n                 input_charset to Unicode.  If no conversion codec is\n                 necessary, this attribute will be None.\n\n    output_codec: The name of the Python codec used to convert Unicode\n                  to the output_charset.  If no conversion codec is necessary,\n                  this attribute will have the same value as the input_codec.\n    ", <code object __init__ at 0x0000024068DD4960, file "email\charset.py", line 206>, <code object __repr__ at 0x000002406945E3D0, file "email\charset.py", line 239>, <code object __eq__ at 0x0000024069419110, file "email\charset.py", line 242>, <code object get_body_encoding at 0x00000240693AA470, file "email\charset.py", line 245>, <code object get_output_charset at 0x0000024069466090, file "email\charset.py", line 266>, <code object header_encode at 0x00000240691F3B40, file "email\charset.py", line 274>, <code object header_encode_lines at 0x0000024068D3EB50, file "email\charset.py", line 293>, <code object _get_encoder at 0x0000024068BF59D0, file "email\charset.py", line 355>, <code object body_encode at 0x0000024068DBCBB0, file "email\charset.py", line 370>, None)

## co_names:
('__name__', '__module__', '__qualname__', '__doc__', 'DEFAULT_CHARSET', '__init__', '__repr__', '__eq__', 'get_body_encoding', 'get_output_charset', 'header_encode', 'header_encode_lines', '_get_encoder', 'body_encode')

## bytecode:

   0: RESUME               
   2: LOAD_NAME            __name__
   4: STORE_NAME           __module__
   6: LOAD_CONST           'Charset'
   8: STORE_NAME           __qualname__
  10: LOAD_CONST           "Map character sets to their email properties.\n\n    This class provides information about the requirements imposed on email\n    for a specific character set.  It also provides convenience routines for\n    converting between character sets, given the availability of the\n    applicable codecs.  Given a character set, it will do its best to provide\n    information on how to use that character set in an email in an\n    RFC-compliant way.\n\n    Certain character sets must be encoded with quoted-printable or base64\n    when used in email headers or bodies.  Certain character sets must be\n    converted outright, and are not allowed in email.  Instances of this\n    module expose the following information about a character set:\n\n    input_charset: The initial character set specified.  Common aliases\n                   are converted to their `official' email names (e.g. latin_1\n                   is converted to iso-8859-1).  Defaults to 7-bit us-ascii.\n\n    header_encoding: If the character set must be encoded before it can be\n                     used in an email header, this attribute will be set to\n                     Charset.QP (for quoted-printable), Charset.BASE64 (for\n                     base64 encoding), or Charset.SHORTEST for the shortest of\n                     QP or BASE64 encoding.  Otherwise, it will be None.\n\n    body_encoding: Same as header_encoding, but describes the encoding for the\n                   mail message's body, which indeed may be different than the\n                   header encoding.  Charset.SHORTEST is not allowed for\n                   body_encoding.\n\n    output_charset: Some character sets must be converted before they can be\n                    used in email headers or bodies.  If the input_charset is\n                    one of them, this attribute will contain the name of the\n                    charset output will be converted to.  Otherwise, it will\n                    be None.\n\n    input_codec: The name of the Python codec used to convert the\n                 input_charset to Unicode.  If no conversion codec is\n                 necessary, this attribute will be None.\n\n    output_codec: The name of the Python codec used to convert Unicode\n                  to the output_charset.  If no conversion codec is necessary,\n                  this attribute will have the same value as the input_codec.\n    "
  12: STORE_NAME           __doc__
  14: LOAD_NAME            DEFAULT_CHARSET
  16: BUILD_TUPLE          
  18: LOAD_CONST           <code object __init__ at 0x0000024068DD4960, file "email\charset.py", line 206>
  20: MAKE_FUNCTION        defaults
  22: STORE_NAME           __init__
  24: LOAD_CONST           <code object __repr__ at 0x000002406945E3D0, file "email\charset.py", line 239>
  26: MAKE_FUNCTION        
  28: STORE_NAME           __repr__
  30: LOAD_CONST           <code object __eq__ at 0x0000024069419110, file "email\charset.py", line 242>
  32: MAKE_FUNCTION        
  34: STORE_NAME           __eq__
  36: LOAD_CONST           <code object get_body_encoding at 0x00000240693AA470, file "email\charset.py", line 245>
  38: MAKE_FUNCTION        
  40: STORE_NAME           get_body_encoding
  42: LOAD_CONST           <code object get_output_charset at 0x0000024069466090, file "email\charset.py", line 266>
  44: MAKE_FUNCTION        
  46: STORE_NAME           get_output_charset
  48: LOAD_CONST           <code object header_encode at 0x00000240691F3B40, file "email\charset.py", line 274>
  50: MAKE_FUNCTION        
  52: STORE_NAME           header_encode
  54: LOAD_CONST           <code object header_encode_lines at 0x0000024068D3EB50, file "email\charset.py", line 293>
  56: MAKE_FUNCTION        
  58: STORE_NAME           header_encode_lines
  60: LOAD_CONST           <code object _get_encoder at 0x0000024068BF59D0, file "email\charset.py", line 355>
  62: MAKE_FUNCTION        
  64: STORE_NAME           _get_encoder
  66: LOAD_CONST           <code object body_encode at 0x0000024068DBCBB0, file "email\charset.py", line 370>
  68: MAKE_FUNCTION        
  70: STORE_NAME           body_encode
  72: LOAD_CONST           None
  74: RETURN_VALUE         
