# Disassembly for email.UniqueSingleAddressHeader
# From module file: email.headerregistry

## co_consts:
('UniqueSingleAddressHeader', 1, None)

## co_names:
('__name__', '__module__', '__qualname__', 'max_count')

## bytecode:

   0: RESUME               
   2: LOAD_NAME            __name__
   4: STORE_NAME           __module__
   6: LOAD_CONST           'UniqueSingleAddressHeader'
   8: STORE_NAME           __qualname__
  10: LOAD_CONST           1
  12: STORE_NAME           max_count
  14: LOAD_CONST           None
  16: RETURN_VALUE         
