# Disassembly for email.encode_quopri
# From module file: email.encoders

## co_consts:
("Encode the message's payload in quoted-printable.\n\n    Also, add an appropriate Content-Transfer-Encoding header.\n    ", True, ('decode',), 'quoted-printable', 'Content-Transfer-Encoding', None)

## co_names:
('get_payload', '_qencode', 'set_payload')

## bytecode:

   0: RESUME               
   2: LOAD_FAST            msg
   4: LOAD_METHOD          get_payload
  26: LOAD_CONST           True
  28: KW_NAMES             
  30: PRECALL              
  34: CALL                 
  44: STORE_FAST           orig
  46: LOAD_GLOBAL          NULL + _qencode
  58: LOAD_FAST            orig
  60: PRECALL              
  64: CALL                 
  74: STORE_FAST           encdata
  76: LOAD_FAST            msg
  78: LOAD_METHOD          set_payload
 100: LOAD_FAST            encdata
 102: PRECALL              
 106: CALL                 
 116: POP_TOP              
 118: LOAD_CONST           'quoted-printable'
 120: LOAD_FAST            msg
 122: LOAD_CONST           'Content-Transfer-Encoding'
 124: STORE_SUBSCR         
 128: LOAD_CONST           None
 130: RETURN_VALUE         
