# Disassembly for email.FeedParser.feed
# From module file: email.feedparser

## co_consts:
('Push more data into the parser.', None)

## co_names:
('_input', 'push', '_call_parse')

## bytecode:

   0: RESUME               
   2: LOAD_FAST            self
   4: LOAD_ATTR            _input
  14: LOAD_METHOD          push
  36: LOAD_FAST            data
  38: PRECALL              
  42: CALL                 
  52: POP_TOP              
  54: LOAD_FAST            self
  56: LOAD_METHOD          _call_parse
  78: PRECALL              
  82: CALL                 
  92: POP_TOP              
  94: LOAD_CONST           None
  96: RETURN_VALUE         
