# Disassembly for email.DecodedGenerator._dispatch
# From module file: email.generator

## co_consts:
(None, 'text', False, ('decode',), ('file',), 'multipart', '[no filename]', 'Content-Description', '[no description]', 'Content-Transfer-Encoding', '[no encoding]', ('type', 'maintype', 'subtype', 'filename', 'description', 'encoding'))

## co_names:
('walk', 'get_content_maintype', 'print', 'get_payload', '_fmt', 'get_content_type', 'get_content_subtype', 'get_filename', 'get')

## bytecode:

   0: RESUME               
   2: LOAD_FAST            msg
   4: LOAD_METHOD          walk
  26: PRECALL              
  30: CALL                 
  40: GET_ITER             
  42: FOR_ITER             to 480
  44: STORE_FAST           part
  46: LOAD_FAST            part
  48: LOAD_METHOD          get_content_maintype
  70: PRECALL              
  74: CALL                 
  84: STORE_FAST           maintype
  86: LOAD_FAST            maintype
  88: LOAD_CONST           'text'
  90: COMPARE_OP           ==
  96: POP_JUMP_FORWARD_IF_FALSE to 174
  98: LOAD_GLOBAL          NULL + print
 110: LOAD_FAST            part
 112: LOAD_METHOD          get_payload
 134: LOAD_CONST           False
 136: KW_NAMES             
 138: PRECALL              
 142: CALL                 
 152: LOAD_FAST            self
 154: KW_NAMES             
 156: PRECALL              
 160: CALL                 
 170: POP_TOP              
 172: JUMP_BACKWARD        to 42
 174: LOAD_FAST            maintype
 176: LOAD_CONST           'multipart'
 178: COMPARE_OP           ==
 184: POP_JUMP_FORWARD_IF_FALSE to 188
 186: JUMP_BACKWARD        to 42
 188: LOAD_GLOBAL          NULL + print
 200: LOAD_FAST            self
 202: LOAD_ATTR            _fmt
 212: LOAD_FAST            part
 214: LOAD_METHOD          get_content_type
 236: PRECALL              
 240: CALL                 
 250: LOAD_FAST            part
 252: LOAD_METHOD          get_content_maintype
 274: PRECALL              
 278: CALL                 
 288: LOAD_FAST            part
 290: LOAD_METHOD          get_content_subtype
 312: PRECALL              
 316: CALL                 
 326: LOAD_FAST            part
 328: LOAD_METHOD          get_filename
 350: LOAD_CONST           '[no filename]'
 352: PRECALL              
 356: CALL                 
 366: LOAD_FAST            part
 368: LOAD_METHOD          get
 390: LOAD_CONST           'Content-Description'
 392: LOAD_CONST           '[no description]'
 394: PRECALL              
 398: CALL                 
 408: LOAD_FAST            part
 410: LOAD_METHOD          get
 432: LOAD_CONST           'Content-Transfer-Encoding'
 434: LOAD_CONST           '[no encoding]'
 436: PRECALL              
 440: CALL                 
 450: LOAD_CONST           ('type', 'maintype', 'subtype', 'filename', 'description', 'encoding')
 452: BUILD_CONST_KEY_MAP  
 454: BINARY_OP            %
 458: LOAD_FAST            self
 460: KW_NAMES             
 462: PRECALL              
 466: CALL                 
 476: POP_TOP              
 478: JUMP_BACKWARD        to 42
 480: LOAD_CONST           None
 482: RETURN_VALUE         
