# Disassembly for email._extend_docstrings
# From module file: email._policybase

## co_consts:
(None, '+', 0, <code object <genexpr> at 0x00000240693EA930, file "email\_policybase.py", line 104>, '__doc__')

## co_names:
('__doc__', 'startswith', '_append_doc', '__bases__', '__dict__', 'items', 'getattr')

## bytecode:

   0: RESUME               
   2: LOAD_FAST            cls
   4: LOAD_ATTR            __doc__
  14: POP_JUMP_FORWARD_IF_FALSE to 152
  16: LOAD_FAST            cls
  18: LOAD_ATTR            __doc__
  28: LOAD_METHOD          startswith
  50: LOAD_CONST           '+'
  52: PRECALL              
  56: CALL                 
  66: POP_JUMP_FORWARD_IF_FALSE to 152
  68: LOAD_GLOBAL          NULL + _append_doc
  80: LOAD_FAST            cls
  82: LOAD_ATTR            __bases__
  92: LOAD_CONST           0
  94: BINARY_SUBSCR        
 104: LOAD_ATTR            __doc__
 114: LOAD_FAST            cls
 116: LOAD_ATTR            __doc__
 126: PRECALL              
 130: CALL                 
 140: LOAD_FAST            cls
 142: STORE_ATTR           __doc__
 152: LOAD_FAST            cls
 154: LOAD_ATTR            __dict__
 164: LOAD_METHOD          items
 186: PRECALL              
 190: CALL                 
 200: GET_ITER             
 202: FOR_ITER             to 440
 204: UNPACK_SEQUENCE      
 208: STORE_FAST           name
 210: STORE_FAST           attr
 212: LOAD_FAST            attr
 214: LOAD_ATTR            __doc__
 224: POP_JUMP_FORWARD_IF_FALSE to 438
 226: LOAD_FAST            attr
 228: LOAD_ATTR            __doc__
 238: LOAD_METHOD          startswith
 260: LOAD_CONST           '+'
 262: PRECALL              
 266: CALL                 
 276: POP_JUMP_FORWARD_IF_FALSE to 438
 278: LOAD_CONST           <code object <genexpr> at 0x00000240693EA930, file "email\_policybase.py", line 104>
 280: MAKE_FUNCTION        
 282: LOAD_FAST            cls
 284: LOAD_ATTR            __bases__
 294: GET_ITER             
 296: PRECALL              
 300: CALL                 
 310: GET_ITER             
 312: FOR_ITER             to 438
 314: STORE_FAST           c
 316: LOAD_GLOBAL          NULL + getattr
 328: LOAD_GLOBAL          NULL + getattr
 340: LOAD_FAST            c
 342: LOAD_FAST            name
 344: PRECALL              
 348: CALL                 
 358: LOAD_CONST           '__doc__'
 360: PRECALL              
 364: CALL                 
 374: STORE_FAST           doc
 376: LOAD_FAST            doc
 378: POP_JUMP_FORWARD_IF_FALSE to 436
 380: LOAD_GLOBAL          NULL + _append_doc
 392: LOAD_FAST            doc
 394: LOAD_FAST            attr
 396: LOAD_ATTR            __doc__
 406: PRECALL              
 410: CALL                 
 420: LOAD_FAST            attr
 422: STORE_ATTR           __doc__
 432: POP_TOP              
 434: JUMP_FORWARD         to 438
 436: JUMP_BACKWARD        to 312
 438: JUMP_BACKWARD        to 202
 440: LOAD_FAST            cls
 442: RETURN_VALUE         
