# Disassembly for email.get_qcontent
# From module file: email._header_value_parser

## co_consts:
("qcontent = qtext / quoted-pair\n\n    We allow anything except the DQUOTE character, but if we find any ASCII\n    other than the RFC defined printable ASCII, a NonPrintableDefect is\n    added to the token's defects list.  Any quoted pairs are converted to their\n    unquoted values, so what is returned is a 'ptext' token.  In this case it\n    is a ValueTerminal.\n\n    ", '"', 'ptext')

## co_names:
('_get_ptext_to_endchars', 'ValueTerminal', '_validate_xtext')

## bytecode:

   0: RESUME               
   2: LOAD_GLOBAL          NULL + _get_ptext_to_endchars
  14: LOAD_FAST            value
  16: LOAD_CONST           '"'
  18: PRECALL              
  22: CALL                 
  32: UNPACK_SEQUENCE      
  36: STORE_FAST           ptext
  38: STORE_FAST           value
  40: STORE_FAST           _
  42: LOAD_GLOBAL          NULL + ValueTerminal
  54: LOAD_FAST            ptext
  56: LOAD_CONST           'ptext'
  58: PRECALL              
  62: CALL                 
  72: STORE_FAST           ptext
  74: LOAD_GLOBAL          NULL + _validate_xtext
  86: LOAD_FAST            ptext
  88: PRECALL              
  92: CALL                 
 102: POP_TOP              
 104: LOAD_FAST            ptext
 106: LOAD_FAST            value
 108: BUILD_TUPLE          
 110: RETURN_VALUE         
