# Disassembly for email._encode_text
# From module file: email.contentmanager

## co_consts:
(None, 'ascii', <code object embedded_body at 0x000002406945FD20, file "email\contentmanager.py", line 147>, <code object normal_body at 0x000002406945FE10, file "email\contentmanager.py", line 148>, <code object <genexpr> at 0x000002406945FF00, file "email\contentmanager.py", line 151>, 0, ('default',), '7bit', '8bit', 'surrogateescape', 10, 'latin-1', 'base64', 'quoted-printable', 'Unknown content transfer encoding {}')

## co_names:
('encode', 'splitlines', 'linesep', 'max', 'max_line_length', 'decode', 'UnicodeDecodeError', 'cte_type', 'quoprimime', 'body_encode', 'binascii', 'b2a_base64', 'len', '_encode_base64', 'ValueError', 'format')

## bytecode:

   0: MAKE_CELL            linesep
   2: RESUME               
   4: LOAD_FAST            string
   6: LOAD_METHOD          encode
  28: LOAD_FAST            charset
  30: PRECALL              
  34: CALL                 
  44: LOAD_METHOD          splitlines
  66: PRECALL              
  70: CALL                 
  80: STORE_FAST           lines
  82: LOAD_FAST            policy
  84: LOAD_ATTR            linesep
  94: LOAD_METHOD          encode
 116: LOAD_CONST           'ascii'
 118: PRECALL              
 122: CALL                 
 132: STORE_DEREF          linesep
 134: LOAD_CLOSURE         linesep
 136: BUILD_TUPLE          
 138: LOAD_CONST           <code object embedded_body at 0x000002406945FD20, file "email\contentmanager.py", line 147>
 140: MAKE_FUNCTION        closure
 142: STORE_FAST           embedded_body
 144: LOAD_CONST           <code object normal_body at 0x000002406945FE10, file "email\contentmanager.py", line 148>
 146: MAKE_FUNCTION        
 148: STORE_FAST           normal_body
 150: LOAD_FAST            cte
 152: EXTENDED_ARG         
 154: POP_JUMP_FORWARD_IF_NOT_NONE to 702
 156: LOAD_GLOBAL          NULL + max
 168: LOAD_CONST           <code object <genexpr> at 0x000002406945FF00, file "email\contentmanager.py", line 151>
 170: MAKE_FUNCTION        
 172: LOAD_FAST            lines
 174: GET_ITER             
 176: PRECALL              
 180: CALL                 
 190: LOAD_CONST           0
 192: KW_NAMES             
 194: PRECALL              
 198: CALL                 
 208: LOAD_FAST            policy
 210: LOAD_ATTR            max_line_length
 220: COMPARE_OP           <=
 226: POP_JUMP_FORWARD_IF_FALSE to 414
 228: NOP                  
 230: LOAD_CONST           '7bit'
 232: PUSH_NULL            
 234: LOAD_FAST            normal_body
 236: LOAD_FAST            lines
 238: PRECALL              
 242: CALL                 
 252: LOAD_METHOD          decode
 274: LOAD_CONST           'ascii'
 276: PRECALL              
 280: CALL                 
 290: BUILD_TUPLE          
 292: RETURN_VALUE         
 294: PUSH_EXC_INFO        
 296: LOAD_GLOBAL          UnicodeDecodeError
 308: CHECK_EXC_MATCH      
 310: POP_JUMP_FORWARD_IF_FALSE to 318
 312: POP_TOP              
 314: POP_EXCEPT           
 316: JUMP_FORWARD         to 326
 318: RERAISE              
 320: COPY                 
 322: POP_EXCEPT           
 324: RERAISE              
 326: LOAD_FAST            policy
 328: LOAD_ATTR            cte_type
 338: LOAD_CONST           '8bit'
 340: COMPARE_OP           ==
 346: POP_JUMP_FORWARD_IF_FALSE to 414
 348: LOAD_CONST           '8bit'
 350: PUSH_NULL            
 352: LOAD_FAST            normal_body
 354: LOAD_FAST            lines
 356: PRECALL              
 360: CALL                 
 370: LOAD_METHOD          decode
 392: LOAD_CONST           'ascii'
 394: LOAD_CONST           'surrogateescape'
 396: PRECALL              
 400: CALL                 
 410: BUILD_TUPLE          
 412: RETURN_VALUE         
 414: PUSH_NULL            
 416: LOAD_FAST            embedded_body
 418: LOAD_FAST            lines
 420: LOAD_CONST           None
 422: LOAD_CONST           10
 424: BUILD_SLICE          
 426: BINARY_SUBSCR        
 436: PRECALL              
 440: CALL                 
 450: STORE_FAST           sniff
 452: LOAD_GLOBAL          NULL + quoprimime
 464: LOAD_ATTR            body_encode
 474: LOAD_FAST            sniff
 476: LOAD_METHOD          decode
 498: LOAD_CONST           'latin-1'
 500: PRECALL              
 504: CALL                 
 514: LOAD_FAST            policy
 516: LOAD_ATTR            max_line_length
 526: PRECALL              
 530: CALL                 
 540: STORE_FAST           sniff_qp
 542: LOAD_GLOBAL          NULL + binascii
 554: LOAD_ATTR            b2a_base64
 564: LOAD_FAST            sniff
 566: PRECALL              
 570: CALL                 
 580: STORE_FAST           sniff_base64
 582: LOAD_GLOBAL          NULL + len
 594: LOAD_FAST            sniff_qp
 596: PRECALL              
 600: CALL                 
 610: LOAD_GLOBAL          NULL + len
 622: LOAD_FAST            sniff_base64
 624: PRECALL              
 628: CALL                 
 638: COMPARE_OP           >
 644: POP_JUMP_FORWARD_IF_FALSE to 652
 646: LOAD_CONST           'base64'
 648: STORE_FAST           cte
 650: JUMP_FORWARD         to 702
 652: LOAD_CONST           'quoted-printable'
 654: STORE_FAST           cte
 656: LOAD_GLOBAL          NULL + len
 668: LOAD_FAST            lines
 670: PRECALL              
 674: CALL                 
 684: LOAD_CONST           10
 686: COMPARE_OP           <=
 692: POP_JUMP_FORWARD_IF_FALSE to 702
 694: LOAD_FAST            cte
 696: LOAD_FAST            sniff_qp
 698: BUILD_TUPLE          
 700: RETURN_VALUE         
 702: LOAD_FAST            cte
 704: LOAD_CONST           '7bit'
 706: COMPARE_OP           ==
 712: POP_JUMP_FORWARD_IF_FALSE to 776
 714: PUSH_NULL            
 716: LOAD_FAST            normal_body
 718: LOAD_FAST            lines
 720: PRECALL              
 724: CALL                 
 734: LOAD_METHOD          decode
 756: LOAD_CONST           'ascii'
 758: PRECALL              
 762: CALL                 
 772: STORE_FAST           data
 774: JUMP_FORWARD         to 1116
 776: LOAD_FAST            cte
 778: LOAD_CONST           '8bit'
 780: COMPARE_OP           ==
 786: POP_JUMP_FORWARD_IF_FALSE to 852
 788: PUSH_NULL            
 790: LOAD_FAST            normal_body
 792: LOAD_FAST            lines
 794: PRECALL              
 798: CALL                 
 808: LOAD_METHOD          decode
 830: LOAD_CONST           'ascii'
 832: LOAD_CONST           'surrogateescape'
 834: PRECALL              
 838: CALL                 
 848: STORE_FAST           data
 850: JUMP_FORWARD         to 1116
 852: LOAD_FAST            cte
 854: LOAD_CONST           'quoted-printable'
 856: COMPARE_OP           ==
 862: POP_JUMP_FORWARD_IF_FALSE to 974
 864: LOAD_GLOBAL          NULL + quoprimime
 876: LOAD_ATTR            body_encode
 886: PUSH_NULL            
 888: LOAD_FAST            normal_body
 890: LOAD_FAST            lines
 892: PRECALL              
 896: CALL                 
 906: LOAD_METHOD          decode
 928: LOAD_CONST           'latin-1'
 930: PRECALL              
 934: CALL                 
 944: LOAD_FAST            policy
 946: LOAD_ATTR            max_line_length
 956: PRECALL              
 960: CALL                 
 970: STORE_FAST           data
 972: JUMP_FORWARD         to 1116
 974: LOAD_FAST            cte
 976: LOAD_CONST           'base64'
 978: COMPARE_OP           ==
 984: POP_JUMP_FORWARD_IF_FALSE to 1048
 986: LOAD_GLOBAL          NULL + _encode_base64
 998: PUSH_NULL            
1000: LOAD_FAST            embedded_body
1002: LOAD_FAST            lines
1004: PRECALL              
1008: CALL                 
1018: LOAD_FAST            policy
1020: LOAD_ATTR            max_line_length
1030: PRECALL              
1034: CALL                 
1044: STORE_FAST           data
1046: JUMP_FORWARD         to 1116
1048: LOAD_GLOBAL          NULL + ValueError
1060: LOAD_CONST           'Unknown content transfer encoding {}'
1062: LOAD_METHOD          format
1084: LOAD_FAST            cte
1086: PRECALL              
1090: CALL                 
1100: PRECALL              
1104: CALL                 
1114: RAISE_VARARGS        
1116: LOAD_FAST            cte
1118: LOAD_FAST            data
1120: BUILD_TUPLE          
1122: RETURN_VALUE         
