# Disassembly for email.MIMEPart.get_body
# From module file: email.message

## co_consts:
("Return best candidate mime part for display as 'body' of message.\n\n        Do a depth first search, starting with self, looking for the first part\n        matching each of the items in preferencelist, and return the part\n        corresponding to the first item that has a match, or None if no items\n        have a match.  If 'related' is not included in preferencelist, consider\n        the root part of any multipart/related encountered as a candidate\n        match.  Ignore parts with 'Content-Disposition: attachment'.\n        ", None, 0)

## co_names:
('len', '_find_body')

## bytecode:

   0: RESUME               
   2: LOAD_GLOBAL          NULL + len
  14: LOAD_FAST            preferencelist
  16: PRECALL              
  20: CALL                 
  30: STORE_FAST           best_prio
  32: LOAD_CONST           None
  34: STORE_FAST           body
  36: LOAD_FAST            self
  38: LOAD_METHOD          _find_body
  60: LOAD_FAST            self
  62: LOAD_FAST            preferencelist
  64: PRECALL              
  68: CALL                 
  78: GET_ITER             
  80: FOR_ITER             to 128
  82: UNPACK_SEQUENCE      
  86: STORE_FAST           prio
  88: STORE_FAST           part
  90: LOAD_FAST            prio
  92: LOAD_FAST            best_prio
  94: COMPARE_OP           <
 100: POP_JUMP_FORWARD_IF_FALSE to 126
 102: LOAD_FAST            prio
 104: STORE_FAST           best_prio
 106: LOAD_FAST            part
 108: STORE_FAST           body
 110: LOAD_FAST            prio
 112: LOAD_CONST           0
 114: COMPARE_OP           ==
 120: POP_JUMP_FORWARD_IF_FALSE to 126
 122: POP_TOP              
 124: JUMP_FORWARD         to 128
 126: JUMP_BACKWARD        to 80
 128: LOAD_FAST            body
 130: RETURN_VALUE         
