# Disassembly for email.NonPrintableDefect.__str__
# From module file: email.errors

## co_consts:
(None, 'the following ASCII non-printables found in header: {}')

## co_names:
('format', 'non_printables')

## bytecode:

   0: RESUME               
   2: LOAD_CONST           'the following ASCII non-printables found in header: {}'
   4: LOAD_METHOD          format
  26: LOAD_FAST            self
  28: LOAD_ATTR            non_printables
  38: PRECALL              
  42: CALL                 
  52: RETURN_VALUE         
