# Disassembly for email.AddressHeader.addresses.<genexpr>
# From module file: email.headerregistry

## co_consts:
(None,)

## co_names:
('addresses',)

## bytecode:

   0: RETURN_GENERATOR     
   2: POP_TOP              
   4: RESUME               
   6: LOAD_FAST            .0
   8: FOR_ITER             to 42
  10: STORE_FAST           group
  12: LOAD_FAST            group
  14: LOAD_ATTR            addresses
  24: GET_ITER             
  26: FOR_ITER             to 40
  28: STORE_FAST           address
  30: LOAD_FAST            address
  32: YIELD_VALUE          
  34: RESUME               
  36: POP_TOP              
  38: JUMP_BACKWARD        to 26
  40: JUMP_BACKWARD        to 8
  42: LOAD_CONST           None
  44: RETURN_VALUE         
