# Disassembly for email._reconstruct_header
# From module file: email.headerregistry

## co_consts:
(None,)

## co_names:
('type', '_reconstruct')

## bytecode:

   0: RESUME               
   2: LOAD_GLOBAL          NULL + type
  14: LOAD_FAST            cls_name
  16: LOAD_FAST            bases
  18: BUILD_MAP            
  20: PRECALL              
  24: CALL                 
  34: LOAD_METHOD          _reconstruct
  56: LOAD_FAST            value
  58: PRECALL              
  62: CALL                 
  72: RETURN_VALUE         
