# Disassembly for email.Parameter.section_number
# From module file: email._header_value_parser

## co_consts:
(None, 1, 0)

## co_names:
('sectioned', 'number')

## bytecode:

   0: RESUME               
   2: LOAD_FAST            self
   4: LOAD_ATTR            sectioned
  14: POP_JUMP_FORWARD_IF_FALSE to 42
  16: LOAD_FAST            self
  18: LOAD_CONST           1
  20: BINARY_SUBSCR        
  30: LOAD_ATTR            number
  40: JUMP_FORWARD         to 44
  42: LOAD_CONST           0
  44: RETURN_VALUE         
