# Disassembly for email.InvalidBase64CharactersDefect
# From module file: email.errors

## co_consts:
('InvalidBase64CharactersDefect', 'base64 encoded sequence had characters not in base64 alphabet', None)

## co_names:
('__name__', '__module__', '__qualname__', '__doc__')

## bytecode:

   0: RESUME               
   2: LOAD_NAME            __name__
   4: STORE_NAME           __module__
   6: LOAD_CONST           'InvalidBase64CharactersDefect'
   8: STORE_NAME           __qualname__
  10: LOAD_CONST           'base64 encoded sequence had characters not in base64 alphabet'
  12: STORE_NAME           __doc__
  14: LOAD_CONST           None
  16: RETURN_VALUE         
