# Disassembly for email.get_comment
# From module file: email._header_value_parser

## co_consts:
('comment = "(" *([FWS] ccontent) [FWS] ")"\n       ccontent = ctext / quoted-pair / comment\n\n    We handle nested comments here, and quoted-pair in our qp-ctext routine.\n    ', 0, '(', "expected '(' but found '{}'", 1, None, ')', 'end of header inside comment')

## co_names:
('errors', 'HeaderParseError', 'format', 'Comment', 'WSP', 'get_fws', 'get_comment', 'get_qp_ctext', 'append', 'defects', 'InvalidHeaderDefect')

## bytecode:

   0: RESUME               
   2: LOAD_FAST            value
   4: POP_JUMP_FORWARD_IF_FALSE to 108
   6: LOAD_FAST            value
   8: LOAD_CONST           0
  10: BINARY_SUBSCR        
  20: LOAD_CONST           '('
  22: COMPARE_OP           !=
  28: POP_JUMP_FORWARD_IF_FALSE to 108
  30: LOAD_GLOBAL          NULL + errors
  42: LOAD_ATTR            HeaderParseError
  52: LOAD_CONST           "expected '(' but found '{}'"
  54: LOAD_METHOD          format
  76: LOAD_FAST            value
  78: PRECALL              
  82: CALL                 
  92: PRECALL              
  96: CALL                 
 106: RAISE_VARARGS        
 108: LOAD_GLOBAL          NULL + Comment
 120: PRECALL              
 124: CALL                 
 134: STORE_FAST           comment
 136: LOAD_FAST            value
 138: LOAD_CONST           1
 140: LOAD_CONST           None
 142: BUILD_SLICE          
 144: BINARY_SUBSCR        
 154: STORE_FAST           value
 156: LOAD_FAST            value
 158: POP_JUMP_FORWARD_IF_FALSE to 420
 160: LOAD_FAST            value
 162: LOAD_CONST           0
 164: BINARY_SUBSCR        
 174: LOAD_CONST           ')'
 176: COMPARE_OP           !=
 182: POP_JUMP_FORWARD_IF_FALSE to 420
 184: LOAD_FAST            value
 186: LOAD_CONST           0
 188: BINARY_SUBSCR        
 198: LOAD_GLOBAL          WSP
 210: CONTAINS_OP          
 212: POP_JUMP_FORWARD_IF_FALSE to 252
 214: LOAD_GLOBAL          NULL + get_fws
 226: LOAD_FAST            value
 228: PRECALL              
 232: CALL                 
 242: UNPACK_SEQUENCE      
 246: STORE_FAST           token
 248: STORE_FAST           value
 250: JUMP_FORWARD         to 350
 252: LOAD_FAST            value
 254: LOAD_CONST           0
 256: BINARY_SUBSCR        
 266: LOAD_CONST           '('
 268: COMPARE_OP           ==
 274: POP_JUMP_FORWARD_IF_FALSE to 314
 276: LOAD_GLOBAL          NULL + get_comment
 288: LOAD_FAST            value
 290: PRECALL              
 294: CALL                 
 304: UNPACK_SEQUENCE      
 308: STORE_FAST           token
 310: STORE_FAST           value
 312: JUMP_FORWARD         to 350
 314: LOAD_GLOBAL          NULL + get_qp_ctext
 326: LOAD_FAST            value
 328: PRECALL              
 332: CALL                 
 342: UNPACK_SEQUENCE      
 346: STORE_FAST           token
 348: STORE_FAST           value
 350: LOAD_FAST            comment
 352: LOAD_METHOD          append
 374: LOAD_FAST            token
 376: PRECALL              
 380: CALL                 
 390: POP_TOP              
 392: LOAD_FAST            value
 394: POP_JUMP_FORWARD_IF_FALSE to 420
 396: LOAD_FAST            value
 398: LOAD_CONST           0
 400: BINARY_SUBSCR        
 410: LOAD_CONST           ')'
 412: COMPARE_OP           !=
 418: POP_JUMP_BACKWARD_IF_TRUE to 184
 420: LOAD_FAST            value
 422: POP_JUMP_FORWARD_IF_TRUE to 520
 424: LOAD_FAST            comment
 426: LOAD_ATTR            defects
 436: LOAD_METHOD          append
 458: LOAD_GLOBAL          NULL + errors
 470: LOAD_ATTR            InvalidHeaderDefect
 480: LOAD_CONST           'end of header inside comment'
 482: PRECALL              
 486: CALL                 
 496: PRECALL              
 500: CALL                 
 510: POP_TOP              
 512: LOAD_FAST            comment
 514: LOAD_FAST            value
 516: BUILD_TUPLE          
 518: RETURN_VALUE         
 520: LOAD_FAST            comment
 522: LOAD_FAST            value
 524: LOAD_CONST           1
 526: LOAD_CONST           None
 528: BUILD_SLICE          
 530: BINARY_SUBSCR        
 540: BUILD_TUPLE          
 542: RETURN_VALUE         
