# Disassembly for email.MIMEPart.iter_attachments
# From module file: email.message

## co_consts:
("Return an iterator over the non-main parts of a multipart.\n\n        Skip the first of each occurrence of text/plain, text/html,\n        multipart/related, or multipart/alternative in the multipart (unless\n        they have a 'Content-Disposition: attachment' header) and include all\n        remaining subparts in the returned iterator.  When applied to a\n        multipart/related, return all parts except the root part.  Return an\n        empty iterator when applied to a multipart/alternative or a\n        non-multipart.\n        ", '/', 'multipart', 'alternative', None, 'related', 'start', False, 'content-id', True, 0)

## co_names:
('get_content_type', 'split', 'get_payload', 'copy', 'AttributeError', 'get_param', 'get', 'append', 'pop', '_body_types', 'is_attachment')

## bytecode:

   0: RETURN_GENERATOR     
   2: POP_TOP              
   4: RESUME               
   6: LOAD_FAST            self
   8: LOAD_METHOD          get_content_type
  30: PRECALL              
  34: CALL                 
  44: LOAD_METHOD          split
  66: LOAD_CONST           '/'
  68: PRECALL              
  72: CALL                 
  82: UNPACK_SEQUENCE      
  86: STORE_FAST           maintype
  88: STORE_FAST           subtype
  90: LOAD_FAST            maintype
  92: LOAD_CONST           'multipart'
  94: COMPARE_OP           !=
 100: POP_JUMP_FORWARD_IF_TRUE to 114
 102: LOAD_FAST            subtype
 104: LOAD_CONST           'alternative'
 106: COMPARE_OP           ==
 112: POP_JUMP_FORWARD_IF_FALSE to 118
 114: LOAD_CONST           None
 116: RETURN_VALUE         
 118: LOAD_FAST            self
 120: LOAD_METHOD          get_payload
 142: PRECALL              
 146: CALL                 
 156: STORE_FAST           payload
 158: NOP                  
 160: LOAD_FAST            payload
 162: LOAD_METHOD          copy
 184: PRECALL              
 188: CALL                 
 198: STORE_FAST           parts
 200: JUMP_FORWARD         to 236
 202: PUSH_EXC_INFO        
 204: LOAD_GLOBAL          AttributeError
 216: CHECK_EXC_MATCH      
 218: POP_JUMP_FORWARD_IF_FALSE to 228
 220: POP_TOP              
 222: POP_EXCEPT           
 224: LOAD_CONST           None
 226: RETURN_VALUE         
 228: RERAISE              
 230: COPY                 
 232: POP_EXCEPT           
 234: RERAISE              
 236: LOAD_FAST            maintype
 238: LOAD_CONST           'multipart'
 240: COMPARE_OP           ==
 246: POP_JUMP_FORWARD_IF_FALSE to 508
 248: LOAD_FAST            subtype
 250: LOAD_CONST           'related'
 252: COMPARE_OP           ==
 258: POP_JUMP_FORWARD_IF_FALSE to 508
 260: LOAD_FAST            self
 262: LOAD_METHOD          get_param
 284: LOAD_CONST           'start'
 286: PRECALL              
 290: CALL                 
 300: STORE_FAST           start
 302: LOAD_FAST            start
 304: POP_JUMP_FORWARD_IF_FALSE to 446
 306: LOAD_CONST           False
 308: STORE_FAST           found
 310: BUILD_LIST           
 312: STORE_FAST           attachments
 314: LOAD_FAST            parts
 316: GET_ITER             
 318: FOR_ITER             to 422
 320: STORE_FAST           part
 322: LOAD_FAST            part
 324: LOAD_METHOD          get
 346: LOAD_CONST           'content-id'
 348: PRECALL              
 352: CALL                 
 362: LOAD_FAST            start
 364: COMPARE_OP           ==
 370: POP_JUMP_FORWARD_IF_FALSE to 378
 372: LOAD_CONST           True
 374: STORE_FAST           found
 376: JUMP_BACKWARD        to 318
 378: LOAD_FAST            attachments
 380: LOAD_METHOD          append
 402: LOAD_FAST            part
 404: PRECALL              
 408: CALL                 
 418: POP_TOP              
 420: JUMP_BACKWARD        to 318
 422: LOAD_FAST            found
 424: POP_JUMP_FORWARD_IF_FALSE to 446
 426: LOAD_FAST            attachments
 428: GET_YIELD_FROM_ITER  
 430: LOAD_CONST           None
 432: SEND                 to 440
 434: YIELD_VALUE          
 436: RESUME               
 438: JUMP_BACKWARD_NO_INTERRUPT to 432
 440: POP_TOP              
 442: LOAD_CONST           None
 444: RETURN_VALUE         
 446: LOAD_FAST            parts
 448: LOAD_METHOD          pop
 470: LOAD_CONST           0
 472: PRECALL              
 476: CALL                 
 486: POP_TOP              
 488: LOAD_FAST            parts
 490: GET_YIELD_FROM_ITER  
 492: LOAD_CONST           None
 494: SEND                 to 502
 496: YIELD_VALUE          
 498: RESUME               
 500: JUMP_BACKWARD_NO_INTERRUPT to 494
 502: POP_TOP              
 504: LOAD_CONST           None
 506: RETURN_VALUE         
 508: BUILD_LIST           
 510: STORE_FAST           seen
 512: LOAD_FAST            parts
 514: GET_ITER             
 516: FOR_ITER             to 728
 518: STORE_FAST           part
 520: LOAD_FAST            part
 522: LOAD_METHOD          get_content_type
 544: PRECALL              
 548: CALL                 
 558: LOAD_METHOD          split
 580: LOAD_CONST           '/'
 582: PRECALL              
 586: CALL                 
 596: UNPACK_SEQUENCE      
 600: STORE_FAST           maintype
 602: STORE_FAST           subtype
 604: LOAD_FAST            maintype
 606: LOAD_FAST            subtype
 608: BUILD_TUPLE          
 610: LOAD_FAST            self
 612: LOAD_ATTR            _body_types
 622: CONTAINS_OP          
 624: POP_JUMP_FORWARD_IF_FALSE to 718
 626: LOAD_FAST            part
 628: LOAD_METHOD          is_attachment
 650: PRECALL              
 654: CALL                 
 664: POP_JUMP_FORWARD_IF_TRUE to 718
 666: LOAD_FAST            subtype
 668: LOAD_FAST            seen
 670: CONTAINS_OP          
 672: POP_JUMP_FORWARD_IF_FALSE to 718
 674: LOAD_FAST            seen
 676: LOAD_METHOD          append
 698: LOAD_FAST            subtype
 700: PRECALL              
 704: CALL                 
 714: POP_TOP              
 716: JUMP_BACKWARD        to 516
 718: LOAD_FAST            part
 720: YIELD_VALUE          
 722: RESUME               
 724: POP_TOP              
 726: JUMP_BACKWARD        to 516
 728: LOAD_CONST           None
 730: RETURN_VALUE         
