# Disassembly for email.MIMEPart.add_alternative
# From module file: email.message

## co_consts:
(None, 'alternative')

## co_names:
('_add_multipart',)

## bytecode:

   0: RESUME               
   2: PUSH_NULL            
   4: LOAD_FAST            self
   6: LOAD_ATTR            _add_multipart
  16: LOAD_CONST           'alternative'
  18: BUILD_LIST           
  20: LOAD_FAST            args
  22: LIST_EXTEND          
  24: LIST_TO_TUPLE        
  26: BUILD_MAP            
  28: LOAD_FAST            kw
  30: DICT_MERGE           
  32: CALL_FUNCTION_EX     
  34: POP_TOP              
  36: LOAD_CONST           None
  38: RETURN_VALUE         
