# Disassembly for email.Generator._handle_multipart
# From module file: email.generator

## co_consts:
(None, False, ('unixfrom', 'linesep'), '>From ', '--', 0)

## co_names:
('get_payload', 'isinstance', 'str', 'write', 'list', '_new_buffer', 'clone', 'flatten', '_NL', 'append', 'getvalue', 'get_boundary', '_encoded_NL', 'join', '_make_boundary', 'set_boundary', 'preamble', '_mangle_from_', 'fcre', 'sub', '_write_lines', '_fp', 'pop', 'epilogue')

## bytecode:

   0: RESUME               
   2: BUILD_LIST           
   4: STORE_FAST           msgtexts
   6: LOAD_FAST            msg
   8: LOAD_METHOD          get_payload
  30: PRECALL              
  34: CALL                 
  44: STORE_FAST           subparts
  46: LOAD_FAST            subparts
  48: POP_JUMP_FORWARD_IF_NOT_NONE to 56
  50: BUILD_LIST           
  52: STORE_FAST           subparts
  54: JUMP_FORWARD         to 192
  56: LOAD_GLOBAL          NULL + isinstance
  68: LOAD_FAST            subparts
  70: LOAD_GLOBAL          str
  82: PRECALL              
  86: CALL                 
  96: POP_JUMP_FORWARD_IF_FALSE to 144
  98: LOAD_FAST            self
 100: LOAD_METHOD          write
 122: LOAD_FAST            subparts
 124: PRECALL              
 128: CALL                 
 138: POP_TOP              
 140: LOAD_CONST           None
 142: RETURN_VALUE         
 144: LOAD_GLOBAL          NULL + isinstance
 156: LOAD_FAST            subparts
 158: LOAD_GLOBAL          list
 170: PRECALL              
 174: CALL                 
 184: POP_JUMP_FORWARD_IF_TRUE to 192
 186: LOAD_FAST            subparts
 188: BUILD_LIST           
 190: STORE_FAST           subparts
 192: LOAD_FAST            subparts
 194: GET_ITER             
 196: FOR_ITER             to 420
 198: STORE_FAST           part
 200: LOAD_FAST            self
 202: LOAD_METHOD          _new_buffer
 224: PRECALL              
 228: CALL                 
 238: STORE_FAST           s
 240: LOAD_FAST            self
 242: LOAD_METHOD          clone
 264: LOAD_FAST            s
 266: PRECALL              
 270: CALL                 
 280: STORE_FAST           g
 282: LOAD_FAST            g
 284: LOAD_METHOD          flatten
 306: LOAD_FAST            part
 308: LOAD_CONST           False
 310: LOAD_FAST            self
 312: LOAD_ATTR            _NL
 322: KW_NAMES             
 324: PRECALL              
 328: CALL                 
 338: POP_TOP              
 340: LOAD_FAST            msgtexts
 342: LOAD_METHOD          append
 364: LOAD_FAST            s
 366: LOAD_METHOD          getvalue
 388: PRECALL              
 392: CALL                 
 402: PRECALL              
 406: CALL                 
 416: POP_TOP              
 418: JUMP_BACKWARD        to 196
 420: LOAD_FAST            msg
 422: LOAD_METHOD          get_boundary
 444: PRECALL              
 448: CALL                 
 458: STORE_FAST           boundary
 460: LOAD_FAST            boundary
 462: POP_JUMP_FORWARD_IF_TRUE to 600
 464: LOAD_FAST            self
 466: LOAD_ATTR            _encoded_NL
 476: LOAD_METHOD          join
 498: LOAD_FAST            msgtexts
 500: PRECALL              
 504: CALL                 
 514: STORE_FAST           alltext
 516: LOAD_FAST            self
 518: LOAD_METHOD          _make_boundary
 540: LOAD_FAST            alltext
 542: PRECALL              
 546: CALL                 
 556: STORE_FAST           boundary
 558: LOAD_FAST            msg
 560: LOAD_METHOD          set_boundary
 582: LOAD_FAST            boundary
 584: PRECALL              
 588: CALL                 
 598: POP_TOP              
 600: LOAD_FAST            msg
 602: LOAD_ATTR            preamble
 612: POP_JUMP_FORWARD_IF_NONE to 802
 614: LOAD_FAST            self
 616: LOAD_ATTR            _mangle_from_
 626: POP_JUMP_FORWARD_IF_FALSE to 694
 628: LOAD_GLOBAL          fcre
 640: LOAD_METHOD          sub
 662: LOAD_CONST           '>From '
 664: LOAD_FAST            msg
 666: LOAD_ATTR            preamble
 676: PRECALL              
 680: CALL                 
 690: STORE_FAST           preamble
 692: JUMP_FORWARD         to 708
 694: LOAD_FAST            msg
 696: LOAD_ATTR            preamble
 706: STORE_FAST           preamble
 708: LOAD_FAST            self
 710: LOAD_METHOD          _write_lines
 732: LOAD_FAST            preamble
 734: PRECALL              
 738: CALL                 
 748: POP_TOP              
 750: LOAD_FAST            self
 752: LOAD_METHOD          write
 774: LOAD_FAST            self
 776: LOAD_ATTR            _NL
 786: PRECALL              
 790: CALL                 
 800: POP_TOP              
 802: LOAD_FAST            self
 804: LOAD_METHOD          write
 826: LOAD_CONST           '--'
 828: LOAD_FAST            boundary
 830: BINARY_OP            +
 834: LOAD_FAST            self
 836: LOAD_ATTR            _NL
 846: BINARY_OP            +
 850: PRECALL              
 854: CALL                 
 864: POP_TOP              
 866: LOAD_FAST            msgtexts
 868: POP_JUMP_FORWARD_IF_FALSE to 960
 870: LOAD_FAST            self
 872: LOAD_ATTR            _fp
 882: LOAD_METHOD          write
 904: LOAD_FAST            msgtexts
 906: LOAD_METHOD          pop
 928: LOAD_CONST           0
 930: PRECALL              
 934: CALL                 
 944: PRECALL              
 948: CALL                 
 958: POP_TOP              
 960: LOAD_FAST            msgtexts
 962: GET_ITER             
 964: FOR_ITER             to 1102
 966: STORE_FAST           body_part
 968: LOAD_FAST            self
 970: LOAD_METHOD          write
 992: LOAD_FAST            self
 994: LOAD_ATTR            _NL
1004: LOAD_CONST           '--'
1006: BINARY_OP            +
1010: LOAD_FAST            boundary
1012: BINARY_OP            +
1016: LOAD_FAST            self
1018: LOAD_ATTR            _NL
1028: BINARY_OP            +
1032: PRECALL              
1036: CALL                 
1046: POP_TOP              
1048: LOAD_FAST            self
1050: LOAD_ATTR            _fp
1060: LOAD_METHOD          write
1082: LOAD_FAST            body_part
1084: PRECALL              
1088: CALL                 
1098: POP_TOP              
1100: JUMP_BACKWARD        to 964
1102: LOAD_FAST            self
1104: LOAD_METHOD          write
1126: LOAD_FAST            self
1128: LOAD_ATTR            _NL
1138: LOAD_CONST           '--'
1140: BINARY_OP            +
1144: LOAD_FAST            boundary
1146: BINARY_OP            +
1150: LOAD_CONST           '--'
1152: BINARY_OP            +
1156: LOAD_FAST            self
1158: LOAD_ATTR            _NL
1168: BINARY_OP            +
1172: PRECALL              
1176: CALL                 
1186: POP_TOP              
1188: LOAD_FAST            msg
1190: LOAD_ATTR            epilogue
1200: POP_JUMP_FORWARD_IF_NONE to 1342
1202: LOAD_FAST            self
1204: LOAD_ATTR            _mangle_from_
1214: POP_JUMP_FORWARD_IF_FALSE to 1282
1216: LOAD_GLOBAL          fcre
1228: LOAD_METHOD          sub
1250: LOAD_CONST           '>From '
1252: LOAD_FAST            msg
1254: LOAD_ATTR            epilogue
1264: PRECALL              
1268: CALL                 
1278: STORE_FAST           epilogue
1280: JUMP_FORWARD         to 1296
1282: LOAD_FAST            msg
1284: LOAD_ATTR            epilogue
1294: STORE_FAST           epilogue
1296: LOAD_FAST            self
1298: LOAD_METHOD          _write_lines
1320: LOAD_FAST            epilogue
1322: PRECALL              
1326: CALL                 
1336: POP_TOP              
1338: LOAD_CONST           None
1340: RETURN_VALUE         
1342: LOAD_CONST           None
1344: RETURN_VALUE         
