# Disassembly for email.Charset.header_encode
# From module file: email.charset

## co_consts:
("Header-encode a string by converting it first to bytes.\n\n        The type of encoding (base64 or quoted-printable) will be based on\n        this charset's `header_encoding`.\n\n        :param string: A unicode string for the header.  It must be possible\n            to encode this string to bytes using the character set's\n            output codec.\n        :return: The encoded string, with RFC 2047 chrome.\n        ", 'us-ascii')

## co_names:
('output_codec', '_encode', '_get_encoder', 'header_encode')

## bytecode:

   0: RESUME               
   2: LOAD_FAST            self
   4: LOAD_ATTR            output_codec
  14: JUMP_IF_TRUE_OR_POP  to 18
  16: LOAD_CONST           'us-ascii'
  18: STORE_FAST           codec
  20: LOAD_GLOBAL          NULL + _encode
  32: LOAD_FAST            string
  34: LOAD_FAST            codec
  36: PRECALL              
  40: CALL                 
  50: STORE_FAST           header_bytes
  52: LOAD_FAST            self
  54: LOAD_METHOD          _get_encoder
  76: LOAD_FAST            header_bytes
  78: PRECALL              
  82: CALL                 
  92: STORE_FAST           encoder_module
  94: LOAD_FAST            encoder_module
  96: POP_JUMP_FORWARD_IF_NOT_NONE to 102
  98: LOAD_FAST            string
 100: RETURN_VALUE         
 102: LOAD_FAST            encoder_module
 104: LOAD_METHOD          header_encode
 126: LOAD_FAST            header_bytes
 128: LOAD_FAST            codec
 130: PRECALL              
 134: CALL                 
 144: RETURN_VALUE         
