# Disassembly for email
# From module file: email._policybase

## co_consts:
('Policy framework for the email package.\n\nAllows fine grained feature control of how the package parses and emits data.\n', 0, None, ('header',), ('charset',), ('_has_surrogates',), ('Policy', 'Compat32', 'compat32'), <code object _PolicyBase at 0x00000240693EA630, file "email\_policybase.py", line 18>, '_PolicyBase', <code object _append_doc at 0x00000240693AA470, file "email\_policybase.py", line 94>, <code object _extend_docstrings at 0x0000024068DA8050, file "email\_policybase.py", line 99>, <code object Policy at 0x00000240691F5890, file "email\_policybase.py", line 112>, 'Policy', ('metaclass',), <code object Compat32 at 0x00000240693EA730, file "email\_policybase.py", line 271>, 'Compat32')

## co_names:
('__doc__', 'abc', 'email', 'header', 'charset', '_charset', 'email.utils', '_has_surrogates', '__all__', '_PolicyBase', '_append_doc', '_extend_docstrings', 'ABCMeta', 'Policy', 'Compat32', 'compat32')

## bytecode:

   0: RESUME               
   2: LOAD_CONST           'Policy framework for the email package.\n\nAllows fine grained feature control of how the package parses and emits data.\n'
   4: STORE_NAME           __doc__
   6: LOAD_CONST           0
   8: LOAD_CONST           None
  10: IMPORT_NAME          abc
  12: STORE_NAME           abc
  14: LOAD_CONST           0
  16: LOAD_CONST           ('header',)
  18: IMPORT_NAME          email
  20: IMPORT_FROM          header
  22: STORE_NAME           header
  24: POP_TOP              
  26: LOAD_CONST           0
  28: LOAD_CONST           ('charset',)
  30: IMPORT_NAME          email
  32: IMPORT_FROM          charset
  34: STORE_NAME           _charset
  36: POP_TOP              
  38: LOAD_CONST           0
  40: LOAD_CONST           ('_has_surrogates',)
  42: IMPORT_NAME          email.utils
  44: IMPORT_FROM          _has_surrogates
  46: STORE_NAME           _has_surrogates
  48: POP_TOP              
  50: BUILD_LIST           
  52: LOAD_CONST           ('Policy', 'Compat32', 'compat32')
  54: LIST_EXTEND          
  56: STORE_NAME           __all__
  58: PUSH_NULL            
  60: LOAD_BUILD_CLASS     
  62: LOAD_CONST           <code object _PolicyBase at 0x00000240693EA630, file "email\_policybase.py", line 18>
  64: MAKE_FUNCTION        
  66: LOAD_CONST           '_PolicyBase'
  68: PRECALL              
  72: CALL                 
  82: STORE_NAME           _PolicyBase
  84: LOAD_CONST           <code object _append_doc at 0x00000240693AA470, file "email\_policybase.py", line 94>
  86: MAKE_FUNCTION        
  88: STORE_NAME           _append_doc
  90: LOAD_CONST           <code object _extend_docstrings at 0x0000024068DA8050, file "email\_policybase.py", line 99>
  92: MAKE_FUNCTION        
  94: STORE_NAME           _extend_docstrings
  96: PUSH_NULL            
  98: LOAD_BUILD_CLASS     
 100: LOAD_CONST           <code object Policy at 0x00000240691F5890, file "email\_policybase.py", line 112>
 102: MAKE_FUNCTION        
 104: LOAD_CONST           'Policy'
 106: LOAD_NAME            _PolicyBase
 108: LOAD_NAME            abc
 110: LOAD_ATTR            ABCMeta
 120: KW_NAMES             
 122: PRECALL              
 126: CALL                 
 136: STORE_NAME           Policy
 138: LOAD_NAME            _extend_docstrings
 140: PUSH_NULL            
 142: LOAD_BUILD_CLASS     
 144: LOAD_CONST           <code object Compat32 at 0x00000240693EA730, file "email\_policybase.py", line 271>
 146: MAKE_FUNCTION        
 148: LOAD_CONST           'Compat32'
 150: LOAD_NAME            Policy
 152: PRECALL              
 156: CALL                 
 166: PRECALL              
 170: CALL                 
 180: STORE_NAME           Compat32
 182: PUSH_NULL            
 184: LOAD_NAME            Compat32
 186: PRECALL              
 190: CALL                 
 200: STORE_NAME           compat32
 202: LOAD_CONST           None
 204: RETURN_VALUE         
