# Disassembly for email.MIMEPart.iter_parts
# From module file: email.message

## co_consts:
('Return an iterator over all immediate subparts of a multipart.\n\n        Return an empty iterator for a non-multipart.\n        ', None)

## co_names:
('is_multipart', 'get_payload')

## bytecode:

   0: RETURN_GENERATOR     
   2: POP_TOP              
   4: RESUME               
   6: LOAD_FAST            self
   8: LOAD_METHOD          is_multipart
  30: PRECALL              
  34: CALL                 
  44: POP_JUMP_FORWARD_IF_FALSE to 102
  46: LOAD_FAST            self
  48: LOAD_METHOD          get_payload
  70: PRECALL              
  74: CALL                 
  84: GET_YIELD_FROM_ITER  
  86: LOAD_CONST           None
  88: SEND                 to 96
  90: YIELD_VALUE          
  92: RESUME               
  94: JUMP_BACKWARD_NO_INTERRUPT to 88
  96: POP_TOP              
  98: LOAD_CONST           None
 100: RETURN_VALUE         
 102: LOAD_CONST           None
 104: RETURN_VALUE         
