# Disassembly for email.message_from_binary_file
# From module file: email

## co_consts:
('Read a binary file and parse its contents into a Message object model.\n\n    Optional _class and strict are passed to the Parser constructor.\n    ', 0, ('BytesParser',))

## co_names:
('email.parser', 'BytesParser', 'parse')

## bytecode:

   0: RESUME               
   2: LOAD_CONST           0
   4: LOAD_CONST           ('BytesParser',)
   6: IMPORT_NAME          email.parser
   8: IMPORT_FROM          BytesParser
  10: STORE_FAST           BytesParser
  12: POP_TOP              
  14: PUSH_NULL            
  16: LOAD_FAST            BytesParser
  18: LOAD_FAST            args
  20: BUILD_MAP            
  22: LOAD_FAST            kws
  24: DICT_MERGE           
  26: CALL_FUNCTION_EX     
  28: LOAD_METHOD          parse
  50: LOAD_FAST            fp
  52: PRECALL              
  56: CALL                 
  66: RETURN_VALUE         
