# Disassembly for email.Header.encode
# From module file: email.header

## co_consts:
('Encode a message header into an RFC-compliant format.\n\n        There are many issues involved in converting a given string for use in\n        an email header.  Only certain character sets are readable in most\n        email clients, and as header strings can only contain a subset of\n        7-bit ASCII, care must be taken to properly convert and encode (with\n        Base64 or quoted-printable) header strings.  In addition, there is a\n        75-character length limit on any given encoded header field, so\n        line-wrapping must be performed, even with double-byte character sets.\n\n        Optional maxlinelen specifies the maximum length of each generated\n        line, exclusive of the linesep string.  Individual lines may be longer\n        than maxlinelen if a folding point cannot be found.  The first line\n        will be shorter by the length of the header name plus ": " if a header\n        name was specified at Header construction time.  The default value for\n        maxlinelen is determined at header construction time.\n\n        Optional splitchars is a string containing characters which should be\n        given extra weight by the splitting algorithm during normal header\n        wrapping.  This is in very rough support of RFC 2822\'s `higher level\n        syntactic breaks\':  split points preceded by a splitchar are preferred\n        during line splitting, with the characters preferred in the order in\n        which they appear in the string.  Space and tab may be included in the\n        string to indicate whether preference should be given to one over the\n        other as a split point when other split chars do not appear in the line\n        being split.  Splitchars does not affect RFC 2047 encoded lines.\n\n        Optional linesep is a string to be used to separate the lines of\n        the value.  The default value is the most useful for typical\n        Python applications, but it can be set to \\r\\n to produce RFC-compliant\n        line separators when needed.\n        ', None, 0, 1000000, (None, 'us-ascii'), -1, False, '', 1, ' ', 'header value appears to contain an embedded header: {!r}')

## co_names:
('_normalize', '_maxlinelen', '_ValueFormatter', '_headerlen', '_continuation_ws', '_chunks', '_nonctext', 'add_transition', 'splitlines', 'feed', 'newline', 'header_encoding', 'lstrip', 'len', '_str', '_embedded_header', 'search', 'HeaderParseError', 'format')

## bytecode:

   0: RESUME               
   2: LOAD_FAST            self
   4: LOAD_METHOD          _normalize
  26: PRECALL              
  30: CALL                 
  40: POP_TOP              
  42: LOAD_FAST            maxlinelen
  44: POP_JUMP_FORWARD_IF_NOT_NONE to 60
  46: LOAD_FAST            self
  48: LOAD_ATTR            _maxlinelen
  58: STORE_FAST           maxlinelen
  60: LOAD_FAST            maxlinelen
  62: LOAD_CONST           0
  64: COMPARE_OP           ==
  70: POP_JUMP_FORWARD_IF_FALSE to 76
  72: LOAD_CONST           1000000
  74: STORE_FAST           maxlinelen
  76: LOAD_GLOBAL          NULL + _ValueFormatter
  88: LOAD_FAST            self
  90: LOAD_ATTR            _headerlen
 100: LOAD_FAST            maxlinelen
 102: LOAD_FAST            self
 104: LOAD_ATTR            _continuation_ws
 114: LOAD_FAST            splitchars
 116: PRECALL              
 120: CALL                 
 130: STORE_FAST           formatter
 132: LOAD_CONST           None
 134: STORE_FAST           lastcs
 136: LOAD_CONST           None
 138: COPY                 
 140: STORE_FAST           hasspace
 142: STORE_FAST           lastspace
 144: LOAD_FAST            self
 146: LOAD_ATTR            _chunks
 156: GET_ITER             
 158: EXTENDED_ARG         
 160: FOR_ITER             to 988
 162: UNPACK_SEQUENCE      
 166: STORE_FAST           string
 168: STORE_FAST           charset
 170: LOAD_FAST            hasspace
 172: POP_JUMP_FORWARD_IF_NONE to 346
 174: LOAD_FAST            string
 176: JUMP_IF_FALSE_OR_POP to 230
 178: LOAD_FAST            self
 180: LOAD_METHOD          _nonctext
 202: LOAD_FAST            string
 204: LOAD_CONST           0
 206: BINARY_SUBSCR        
 216: PRECALL              
 220: CALL                 
 230: STORE_FAST           hasspace
 232: LOAD_FAST            lastcs
 234: LOAD_CONST           (None, 'us-ascii')
 236: CONTAINS_OP          
 238: POP_JUMP_FORWARD_IF_FALSE to 294
 240: LOAD_FAST            hasspace
 242: POP_JUMP_FORWARD_IF_FALSE to 252
 244: LOAD_FAST            charset
 246: LOAD_CONST           (None, 'us-ascii')
 248: CONTAINS_OP          
 250: POP_JUMP_FORWARD_IF_FALSE to 292
 252: LOAD_FAST            formatter
 254: LOAD_METHOD          add_transition
 276: PRECALL              
 280: CALL                 
 290: POP_TOP              
 292: JUMP_FORWARD         to 346
 294: LOAD_FAST            charset
 296: LOAD_CONST           (None, 'us-ascii')
 298: CONTAINS_OP          
 300: POP_JUMP_FORWARD_IF_FALSE to 346
 302: LOAD_FAST            lastspace
 304: POP_JUMP_FORWARD_IF_TRUE to 346
 306: LOAD_FAST            formatter
 308: LOAD_METHOD          add_transition
 330: PRECALL              
 334: CALL                 
 344: POP_TOP              
 346: LOAD_FAST            string
 348: JUMP_IF_FALSE_OR_POP to 402
 350: LOAD_FAST            self
 352: LOAD_METHOD          _nonctext
 374: LOAD_FAST            string
 376: LOAD_CONST           -1
 378: BINARY_SUBSCR        
 388: PRECALL              
 392: CALL                 
 402: STORE_FAST           lastspace
 404: LOAD_FAST            charset
 406: STORE_FAST           lastcs
 408: LOAD_CONST           False
 410: STORE_FAST           hasspace
 412: LOAD_FAST            string
 414: LOAD_METHOD          splitlines
 436: PRECALL              
 440: CALL                 
 450: STORE_FAST           lines
 452: LOAD_FAST            lines
 454: POP_JUMP_FORWARD_IF_FALSE to 516
 456: LOAD_FAST            formatter
 458: LOAD_METHOD          feed
 480: LOAD_CONST           ''
 482: LOAD_FAST            lines
 484: LOAD_CONST           0
 486: BINARY_SUBSCR        
 496: LOAD_FAST            charset
 498: PRECALL              
 502: CALL                 
 512: POP_TOP              
 514: JUMP_FORWARD         to 562
 516: LOAD_FAST            formatter
 518: LOAD_METHOD          feed
 540: LOAD_CONST           ''
 542: LOAD_CONST           ''
 544: LOAD_FAST            charset
 546: PRECALL              
 550: CALL                 
 560: POP_TOP              
 562: LOAD_FAST            lines
 564: LOAD_CONST           1
 566: LOAD_CONST           None
 568: BUILD_SLICE          
 570: BINARY_SUBSCR        
 580: GET_ITER             
 582: FOR_ITER             to 906
 584: STORE_FAST           line
 586: LOAD_FAST            formatter
 588: LOAD_METHOD          newline
 610: PRECALL              
 614: CALL                 
 624: POP_TOP              
 626: LOAD_FAST            charset
 628: LOAD_ATTR            header_encoding
 638: POP_JUMP_FORWARD_IF_NONE to 740
 640: LOAD_FAST            formatter
 642: LOAD_METHOD          feed
 664: LOAD_FAST            self
 666: LOAD_ATTR            _continuation_ws
 676: LOAD_CONST           ' '
 678: LOAD_FAST            line
 680: LOAD_METHOD          lstrip
 702: PRECALL              
 706: CALL                 
 716: BINARY_OP            +
 720: LOAD_FAST            charset
 722: PRECALL              
 726: CALL                 
 736: POP_TOP              
 738: JUMP_BACKWARD        to 582
 740: LOAD_FAST            line
 742: LOAD_METHOD          lstrip
 764: PRECALL              
 768: CALL                 
 778: STORE_FAST           sline
 780: LOAD_FAST            line
 782: LOAD_CONST           None
 784: LOAD_GLOBAL          NULL + len
 796: LOAD_FAST            line
 798: PRECALL              
 802: CALL                 
 812: LOAD_GLOBAL          NULL + len
 824: LOAD_FAST            sline
 826: PRECALL              
 830: CALL                 
 840: BINARY_OP            -
 844: BUILD_SLICE          
 846: BINARY_SUBSCR        
 856: STORE_FAST           fws
 858: LOAD_FAST            formatter
 860: LOAD_METHOD          feed
 882: LOAD_FAST            fws
 884: LOAD_FAST            sline
 886: LOAD_FAST            charset
 888: PRECALL              
 892: CALL                 
 902: POP_TOP              
 904: JUMP_BACKWARD        to 582
 906: LOAD_GLOBAL          NULL + len
 918: LOAD_FAST            lines
 920: PRECALL              
 924: CALL                 
 934: LOAD_CONST           1
 936: COMPARE_OP           >
 942: POP_JUMP_FORWARD_IF_FALSE to 984
 944: LOAD_FAST            formatter
 946: LOAD_METHOD          newline
 968: PRECALL              
 972: CALL                 
 982: POP_TOP              
 984: EXTENDED_ARG         
 986: JUMP_BACKWARD        to 158
 988: LOAD_FAST            self
 990: LOAD_ATTR            _chunks
1000: POP_JUMP_FORWARD_IF_FALSE to 1042
1002: LOAD_FAST            formatter
1004: LOAD_METHOD          add_transition
1026: PRECALL              
1030: CALL                 
1040: POP_TOP              
1042: LOAD_FAST            formatter
1044: LOAD_METHOD          _str
1066: LOAD_FAST            linesep
1068: PRECALL              
1072: CALL                 
1082: STORE_FAST           value
1084: LOAD_GLOBAL          _embedded_header
1096: LOAD_METHOD          search
1118: LOAD_FAST            value
1120: PRECALL              
1124: CALL                 
1134: POP_JUMP_FORWARD_IF_FALSE to 1204
1136: LOAD_GLOBAL          NULL + HeaderParseError
1148: LOAD_CONST           'header value appears to contain an embedded header: {!r}'
1150: LOAD_METHOD          format
1172: LOAD_FAST            value
1174: PRECALL              
1178: CALL                 
1188: PRECALL              
1192: CALL                 
1202: RAISE_VARARGS        
1204: LOAD_FAST            value
1206: RETURN_VALUE         
