# Disassembly for email.Group.__str__
# From module file: email.headerregistry

## co_consts:
(None, 1, 0, ', ', <code object <genexpr> at 0x000002406945FD20, file "email\headerregistry.py", line 143>, ' ', '{}:{};')

## co_names:
('display_name', 'len', 'addresses', 'str', 'parser', 'SPECIALS', 'isdisjoint', 'quote_string', 'join', 'format')

## bytecode:

   0: RESUME               
   2: LOAD_FAST            self
   4: LOAD_ATTR            display_name
  14: POP_JUMP_FORWARD_IF_NOT_NONE to 116
  16: LOAD_GLOBAL          NULL + len
  28: LOAD_FAST            self
  30: LOAD_ATTR            addresses
  40: PRECALL              
  44: CALL                 
  54: LOAD_CONST           1
  56: COMPARE_OP           ==
  62: POP_JUMP_FORWARD_IF_FALSE to 116
  64: LOAD_GLOBAL          NULL + str
  76: LOAD_FAST            self
  78: LOAD_ATTR            addresses
  88: LOAD_CONST           0
  90: BINARY_SUBSCR        
 100: PRECALL              
 104: CALL                 
 114: RETURN_VALUE         
 116: LOAD_FAST            self
 118: LOAD_ATTR            display_name
 128: STORE_FAST           disp
 130: LOAD_FAST            disp
 132: POP_JUMP_FORWARD_IF_NONE to 236
 134: LOAD_GLOBAL          parser
 146: LOAD_ATTR            SPECIALS
 156: LOAD_METHOD          isdisjoint
 178: LOAD_FAST            disp
 180: PRECALL              
 184: CALL                 
 194: POP_JUMP_FORWARD_IF_TRUE to 236
 196: LOAD_GLOBAL          NULL + parser
 208: LOAD_ATTR            quote_string
 218: LOAD_FAST            disp
 220: PRECALL              
 224: CALL                 
 234: STORE_FAST           disp
 236: LOAD_CONST           ', '
 238: LOAD_METHOD          join
 260: LOAD_CONST           <code object <genexpr> at 0x000002406945FD20, file "email\headerregistry.py", line 143>
 262: MAKE_FUNCTION        
 264: LOAD_FAST            self
 266: LOAD_ATTR            addresses
 276: GET_ITER             
 278: PRECALL              
 282: CALL                 
 292: PRECALL              
 296: CALL                 
 306: STORE_FAST           adrstr
 308: LOAD_FAST            adrstr
 310: POP_JUMP_FORWARD_IF_FALSE to 322
 312: LOAD_CONST           ' '
 314: LOAD_FAST            adrstr
 316: BINARY_OP            +
 320: JUMP_FORWARD         to 324
 322: LOAD_FAST            adrstr
 324: STORE_FAST           adrstr
 326: LOAD_CONST           '{}:{};'
 328: LOAD_METHOD          format
 350: LOAD_FAST            disp
 352: LOAD_FAST            adrstr
 354: PRECALL              
 358: CALL                 
 368: RETURN_VALUE         
