# Disassembly for email.Address.__repr__
# From module file: email.headerregistry

## co_consts:
(None, '{}(display_name={!r}, username={!r}, domain={!r})')

## co_names:
('format', '__class__', '__name__', 'display_name', 'username', 'domain')

## bytecode:

   0: RESUME               
   2: LOAD_CONST           '{}(display_name={!r}, username={!r}, domain={!r})'
   4: LOAD_METHOD          format
  26: LOAD_FAST            self
  28: LOAD_ATTR            __class__
  38: LOAD_ATTR            __name__
  48: LOAD_FAST            self
  50: LOAD_ATTR            display_name
  60: LOAD_FAST            self
  62: LOAD_ATTR            username
  72: LOAD_FAST            self
  74: LOAD_ATTR            domain
  84: PRECALL              
  88: CALL                 
  98: RETURN_VALUE         
