# Disassembly for email.Terminal.pprint
# From module file: email._header_value_parser

## co_consts:
(None, '/')

## co_names:
('print', '__class__', '__name__', 'token_type')

## bytecode:

   0: RESUME               
   2: LOAD_GLOBAL          NULL + print
  14: LOAD_FAST            self
  16: LOAD_ATTR            __class__
  26: LOAD_ATTR            __name__
  36: LOAD_CONST           '/'
  38: BINARY_OP            +
  42: LOAD_FAST            self
  44: LOAD_ATTR            token_type
  54: BINARY_OP            +
  58: PRECALL              
  62: CALL                 
  72: POP_TOP              
  74: LOAD_CONST           None
  76: RETURN_VALUE         
