# Disassembly for email.BufferedSubFile
# From module file: email.feedparser

## co_consts:
('BufferedSubFile', 'A file-ish object that can have new data loaded into it.\n\n    You can also push and pop line-matching predicates onto a stack.  When the\n    current predicate matches the current line, a false EOF response\n    (i.e. empty string) is returned instead.  This lets the parser adhere to a\n    simple abstraction -- it parses until EOF closes the current message.\n    ', <code object __init__ at 0x00000240693D23D0, file "email\feedparser.py", line 52>, <code object push_eof_matcher at 0x00000240693EB730, file "email\feedparser.py", line 63>, <code object pop_eof_matcher at 0x000002406945D4D0, file "email\feedparser.py", line 66>, <code object close at 0x00000240691A7BB0, file "email\feedparser.py", line 69>, <code object readline at 0x00000240691F60B0, file "email\feedparser.py", line 77>, <code object unreadline at 0x000002406944A9A0, file "email\feedparser.py", line 95>, <code object push at 0x0000024068D32DE0, file "email\feedparser.py", line 100>, <code object pushlines at 0x00000240693EBA30, file "email\feedparser.py", line 121>, <code object __iter__ at 0x000002406943B6F0, file "email\feedparser.py", line 124>, <code object __next__ at 0x00000240693EA930, file "email\feedparser.py", line 127>, None)

## co_names:
('__name__', '__module__', '__qualname__', '__doc__', '__init__', 'push_eof_matcher', 'pop_eof_matcher', 'close', 'readline', 'unreadline', 'push', 'pushlines', '__iter__', '__next__')

## bytecode:

   0: RESUME               
   2: LOAD_NAME            __name__
   4: STORE_NAME           __module__
   6: LOAD_CONST           'BufferedSubFile'
   8: STORE_NAME           __qualname__
  10: LOAD_CONST           'A file-ish object that can have new data loaded into it.\n\n    You can also push and pop line-matching predicates onto a stack.  When the\n    current predicate matches the current line, a false EOF response\n    (i.e. empty string) is returned instead.  This lets the parser adhere to a\n    simple abstraction -- it parses until EOF closes the current message.\n    '
  12: STORE_NAME           __doc__
  14: LOAD_CONST           <code object __init__ at 0x00000240693D23D0, file "email\feedparser.py", line 52>
  16: MAKE_FUNCTION        
  18: STORE_NAME           __init__
  20: LOAD_CONST           <code object push_eof_matcher at 0x00000240693EB730, file "email\feedparser.py", line 63>
  22: MAKE_FUNCTION        
  24: STORE_NAME           push_eof_matcher
  26: LOAD_CONST           <code object pop_eof_matcher at 0x000002406945D4D0, file "email\feedparser.py", line 66>
  28: MAKE_FUNCTION        
  30: STORE_NAME           pop_eof_matcher
  32: LOAD_CONST           <code object close at 0x00000240691A7BB0, file "email\feedparser.py", line 69>
  34: MAKE_FUNCTION        
  36: STORE_NAME           close
  38: LOAD_CONST           <code object readline at 0x00000240691F60B0, file "email\feedparser.py", line 77>
  40: MAKE_FUNCTION        
  42: STORE_NAME           readline
  44: LOAD_CONST           <code object unreadline at 0x000002406944A9A0, file "email\feedparser.py", line 95>
  46: MAKE_FUNCTION        
  48: STORE_NAME           unreadline
  50: LOAD_CONST           <code object push at 0x0000024068D32DE0, file "email\feedparser.py", line 100>
  52: MAKE_FUNCTION        
  54: STORE_NAME           push
  56: LOAD_CONST           <code object pushlines at 0x00000240693EBA30, file "email\feedparser.py", line 121>
  58: MAKE_FUNCTION        
  60: STORE_NAME           pushlines
  62: LOAD_CONST           <code object __iter__ at 0x000002406943B6F0, file "email\feedparser.py", line 124>
  64: MAKE_FUNCTION        
  66: STORE_NAME           __iter__
  68: LOAD_CONST           <code object __next__ at 0x00000240693EA930, file "email\feedparser.py", line 127>
  70: MAKE_FUNCTION        
  72: STORE_NAME           __next__
  74: LOAD_CONST           None
  76: RETURN_VALUE         
