# Disassembly for email.ContentManager.set_content
# From module file: email.contentmanager

## co_consts:
(None, 'multipart', 'set_content not valid on multipart')

## co_names:
('get_content_maintype', 'TypeError', '_find_set_handler', 'clear_content')

## bytecode:

   0: RESUME               
   2: LOAD_FAST            msg
   4: LOAD_METHOD          get_content_maintype
  26: PRECALL              
  30: CALL                 
  40: LOAD_CONST           'multipart'
  42: COMPARE_OP           ==
  48: POP_JUMP_FORWARD_IF_FALSE to 80
  50: LOAD_GLOBAL          NULL + TypeError
  62: LOAD_CONST           'set_content not valid on multipart'
  64: PRECALL              
  68: CALL                 
  78: RAISE_VARARGS        
  80: LOAD_FAST            self
  82: LOAD_METHOD          _find_set_handler
 104: LOAD_FAST            msg
 106: LOAD_FAST            obj
 108: PRECALL              
 112: CALL                 
 122: STORE_FAST           handler
 124: LOAD_FAST            msg
 126: LOAD_METHOD          clear_content
 148: PRECALL              
 152: CALL                 
 162: POP_TOP              
 164: PUSH_NULL            
 166: LOAD_FAST            handler
 168: LOAD_FAST            msg
 170: LOAD_FAST            obj
 172: BUILD_LIST           
 174: LOAD_FAST            args
 176: LIST_EXTEND          
 178: LIST_TO_TUPLE        
 180: BUILD_MAP            
 182: LOAD_FAST            kw
 184: DICT_MERGE           
 186: CALL_FUNCTION_EX     
 188: POP_TOP              
 190: LOAD_CONST           None
 192: RETURN_VALUE         
