# Disassembly for email.ContentDispositionHeader.init
# From module file: email.headerregistry

## co_consts:
(None,)

## co_names:
('super', 'init', '_parse_tree', 'content_disposition', 'utils', '_sanitize', '_content_disposition')

## bytecode:

   0: COPY_FREE_VARS       
   2: RESUME               
   4: PUSH_NULL            
   6: LOAD_GLOBAL          NULL + super
  18: PRECALL              
  22: CALL                 
  32: LOAD_ATTR            init
  42: LOAD_FAST            args
  44: BUILD_MAP            
  46: LOAD_FAST            kw
  48: DICT_MERGE           
  50: CALL_FUNCTION_EX     
  52: POP_TOP              
  54: LOAD_FAST            self
  56: LOAD_ATTR            _parse_tree
  66: LOAD_ATTR            content_disposition
  76: STORE_FAST           cd
  78: LOAD_FAST            cd
  80: POP_JUMP_FORWARD_IF_NOT_NONE to 86
  82: LOAD_FAST            cd
  84: JUMP_FORWARD         to 124
  86: LOAD_GLOBAL          NULL + utils
  98: LOAD_ATTR            _sanitize
 108: LOAD_FAST            cd
 110: PRECALL              
 114: CALL                 
 124: LOAD_FAST            self
 126: STORE_ATTR           _content_disposition
 136: LOAD_CONST           None
 138: RETURN_VALUE         
