# Disassembly for player.Player.__init__
# From module file: player

## co_consts:
(None, '', 0)

## co_names:
('super', '__init__', 'time', 'monotonic', 'start_time', 'favorite_color', 'age')

## bytecode:

   0: COPY_FREE_VARS       
   2: RESUME               
   4: LOAD_GLOBAL          NULL + super
  16: PRECALL              
  20: CALL                 
  30: LOAD_METHOD          __init__
  52: LOAD_FAST            name
  54: PRECALL              
  58: CALL                 
  68: POP_TOP              
  70: LOAD_GLOBAL          NULL + time
  82: LOAD_ATTR            monotonic
  92: PRECALL              
  96: CALL                 
 106: LOAD_FAST            self
 108: STORE_ATTR           start_time
 118: LOAD_CONST           ''
 120: LOAD_FAST            self
 122: STORE_ATTR           favorite_color
 132: LOAD_CONST           0
 134: LOAD_FAST            self
 136: STORE_ATTR           age
 146: LOAD_CONST           None
 148: RETURN_VALUE         
