# Disassembly for _compression.DecompressReader.close
# From module file: _compression

## co_consts:
(None,)

## co_names:
('_decompressor', 'super', 'close')

## bytecode:

   0: COPY_FREE_VARS       
   2: RESUME               
   4: LOAD_CONST           None
   6: LOAD_FAST            self
   8: STORE_ATTR           _decompressor
  18: LOAD_GLOBAL          NULL + super
  30: PRECALL              
  34: CALL                 
  44: LOAD_METHOD          close
  66: PRECALL              
  70: CALL                 
  80: RETURN_VALUE         
