# Disassembly for _compression.DecompressReader.__init__
# From module file: _compression

## co_consts:
(None, False, 0, -1, ())

## co_names:
('_fp', '_eof', '_pos', '_size', '_decomp_factory', '_decomp_args', '_decompressor', '_trailing_error')

## bytecode:

   0: RESUME               
   2: LOAD_FAST            fp
   4: LOAD_FAST            self
   6: STORE_ATTR           _fp
  16: LOAD_CONST           False
  18: LOAD_FAST            self
  20: STORE_ATTR           _eof
  30: LOAD_CONST           0
  32: LOAD_FAST            self
  34: STORE_ATTR           _pos
  44: LOAD_CONST           -1
  46: LOAD_FAST            self
  48: STORE_ATTR           _size
  58: LOAD_FAST            decomp_factory
  60: LOAD_FAST            self
  62: STORE_ATTR           _decomp_factory
  72: LOAD_FAST            decomp_args
  74: LOAD_FAST            self
  76: STORE_ATTR           _decomp_args
  86: PUSH_NULL            
  88: LOAD_FAST            self
  90: LOAD_ATTR            _decomp_factory
 100: LOAD_CONST           ()
 102: BUILD_MAP            
 104: LOAD_FAST            self
 106: LOAD_ATTR            _decomp_args
 116: DICT_MERGE           
 118: CALL_FUNCTION_EX     
 120: LOAD_FAST            self
 122: STORE_ATTR           _decompressor
 132: LOAD_FAST            trailing_error
 134: LOAD_FAST            self
 136: STORE_ATTR           _trailing_error
 146: LOAD_CONST           None
 148: RETURN_VALUE         
