# Disassembly for _compression.BaseStream._check_can_seek
# From module file: _compression

## co_consts:
(None, 'Seeking is only supported on files open for reading', 'The underlying file object does not support seeking')

## co_names:
('readable', 'io', 'UnsupportedOperation', 'seekable')

## bytecode:

   0: RESUME               
   2: LOAD_FAST            self
   4: LOAD_METHOD          readable
  26: PRECALL              
  30: CALL                 
  40: POP_JUMP_FORWARD_IF_TRUE to 82
  42: LOAD_GLOBAL          NULL + io
  54: LOAD_ATTR            UnsupportedOperation
  64: LOAD_CONST           'Seeking is only supported on files open for reading'
  66: PRECALL              
  70: CALL                 
  80: RAISE_VARARGS        
  82: LOAD_FAST            self
  84: LOAD_METHOD          seekable
 106: PRECALL              
 110: CALL                 
 120: POP_JUMP_FORWARD_IF_TRUE to 162
 122: LOAD_GLOBAL          NULL + io
 134: LOAD_ATTR            UnsupportedOperation
 144: LOAD_CONST           'The underlying file object does not support seeking'
 146: PRECALL              
 150: CALL                 
 160: RAISE_VARARGS        
 162: LOAD_CONST           None
 164: RETURN_VALUE         
