# Disassembly for contextlib.AbstractContextManager
# From module file: contextlib

## co_consts:
('AbstractContextManager', 'An abstract base class for context managers.', <code object __enter__ at 0x000002406943BB70, file "contextlib.py", line 23>, <code object __exit__ at 0x000002406943B930, file "contextlib.py", line 27>, <code object __subclasshook__ at 0x000002406944B330, file "contextlib.py", line 32>, None)

## co_names:
('__name__', '__module__', '__qualname__', '__doc__', 'classmethod', 'GenericAlias', '__class_getitem__', '__enter__', 'abc', 'abstractmethod', '__exit__', '__subclasshook__')

## bytecode:

   0: RESUME               
   2: LOAD_NAME            __name__
   4: STORE_NAME           __module__
   6: LOAD_CONST           'AbstractContextManager'
   8: STORE_NAME           __qualname__
  10: LOAD_CONST           'An abstract base class for context managers.'
  12: STORE_NAME           __doc__
  14: PUSH_NULL            
  16: LOAD_NAME            classmethod
  18: LOAD_NAME            GenericAlias
  20: PRECALL              
  24: CALL                 
  34: STORE_NAME           __class_getitem__
  36: LOAD_CONST           <code object __enter__ at 0x000002406943BB70, file "contextlib.py", line 23>
  38: MAKE_FUNCTION        
  40: STORE_NAME           __enter__
  42: LOAD_NAME            abc
  44: LOAD_ATTR            abstractmethod
  54: LOAD_CONST           <code object __exit__ at 0x000002406943B930, file "contextlib.py", line 27>
  56: MAKE_FUNCTION        
  58: PRECALL              
  62: CALL                 
  72: STORE_NAME           __exit__
  74: LOAD_NAME            classmethod
  76: LOAD_CONST           <code object __subclasshook__ at 0x000002406944B330, file "contextlib.py", line 32>
  78: MAKE_FUNCTION        
  80: PRECALL              
  84: CALL                 
  94: STORE_NAME           __subclasshook__
  96: LOAD_CONST           None
  98: RETURN_VALUE         
