# Disassembly for contextlib.AsyncExitStack.aclose
# From module file: contextlib

## co_consts:
('Immediately unwind the context stack.', None)

## co_names:
('__aexit__',)

## bytecode:

   0: RETURN_GENERATOR     
   2: POP_TOP              
   4: RESUME               
   6: LOAD_FAST            self
   8: LOAD_METHOD          __aexit__
  30: LOAD_CONST           None
  32: LOAD_CONST           None
  34: LOAD_CONST           None
  36: PRECALL              
  40: CALL                 
  50: GET_AWAITABLE        
  52: LOAD_CONST           None
  54: SEND                 to 62
  56: YIELD_VALUE          
  58: RESUME               
  60: JUMP_BACKWARD_NO_INTERRUPT to 54
  62: POP_TOP              
  64: LOAD_CONST           None
  66: RETURN_VALUE         
