# Disassembly for contextlib.asynccontextmanager
# From module file: contextlib

## co_consts:
('@asynccontextmanager decorator.\n\n    Typical usage:\n\n        @asynccontextmanager\n        async def some_async_generator(<arguments>):\n            <setup>\n            try:\n                yield <value>\n            finally:\n                <cleanup>\n\n    This makes this:\n\n        async with some_async_generator(<arguments>) as <variable>:\n            <body>\n\n    equivalent to this:\n\n        <setup>\n        try:\n            <variable> = <value>\n            <body>\n        finally:\n            <cleanup>\n    ', <code object helper at 0x00000240694658B0, file "contextlib.py", line 320>)

## co_names:
('wraps',)

## bytecode:

   0: MAKE_CELL            func
   2: RESUME               
   4: LOAD_GLOBAL          NULL + wraps
  16: LOAD_DEREF           func
  18: PRECALL              
  22: CALL                 
  32: LOAD_CLOSURE         func
  34: BUILD_TUPLE          
  36: LOAD_CONST           <code object helper at 0x00000240694658B0, file "contextlib.py", line 320>
  38: MAKE_FUNCTION        closure
  40: PRECALL              
  44: CALL                 
  54: STORE_FAST           helper
  56: LOAD_FAST            helper
  58: RETURN_VALUE         
