# Disassembly for contextlib._BaseExitStack._push_cm_exit
# From module file: contextlib

## co_consts:
('Helper to correctly register callbacks to __exit__ methods.', True, None)

## co_names:
('_create_exit_wrapper', '_push_exit_callback')

## bytecode:

   0: RESUME               
   2: LOAD_FAST            self
   4: LOAD_METHOD          _create_exit_wrapper
  26: LOAD_FAST            cm
  28: LOAD_FAST            cm_exit
  30: PRECALL              
  34: CALL                 
  44: STORE_FAST           _exit_wrapper
  46: LOAD_FAST            self
  48: LOAD_METHOD          _push_exit_callback
  70: LOAD_FAST            _exit_wrapper
  72: LOAD_CONST           True
  74: PRECALL              
  78: CALL                 
  88: POP_TOP              
  90: LOAD_CONST           None
  92: RETURN_VALUE         
