# Disassembly for contextlib._AsyncGeneratorContextManager.__aenter__
# From module file: contextlib

## co_consts:
(None, "generator didn't yield")

## co_names:
('args', 'kwds', 'func', 'anext', 'gen', 'StopAsyncIteration', 'RuntimeError')

## bytecode:

   0: RETURN_GENERATOR     
   2: POP_TOP              
   4: RESUME               
   6: LOAD_FAST            self
   8: DELETE_ATTR          args
  10: LOAD_FAST            self
  12: DELETE_ATTR          kwds
  14: LOAD_FAST            self
  16: DELETE_ATTR          func
  18: NOP                  
  20: LOAD_GLOBAL          NULL + anext
  32: LOAD_FAST            self
  34: LOAD_ATTR            gen
  44: PRECALL              
  48: CALL                 
  58: GET_AWAITABLE        
  60: LOAD_CONST           None
  62: SEND                 to 70
  64: YIELD_VALUE          
  66: RESUME               
  68: JUMP_BACKWARD_NO_INTERRUPT to 62
  70: RETURN_VALUE         
  72: PUSH_EXC_INFO        
  74: LOAD_GLOBAL          StopAsyncIteration
  86: CHECK_EXC_MATCH      
  88: POP_JUMP_FORWARD_IF_FALSE to 124
  90: POP_TOP              
  92: LOAD_GLOBAL          NULL + RuntimeError
 104: LOAD_CONST           "generator didn't yield"
 106: PRECALL              
 110: CALL                 
 120: LOAD_CONST           None
 122: RAISE_VARARGS        
 124: RERAISE              
 126: COPY                 
 128: POP_EXCEPT           
 130: RERAISE              
