# Disassembly for contextlib.closing
# From module file: contextlib

## co_consts:
('closing', 'Context to automatically close something at the end of a block.\n\n    Code like this:\n\n        with closing(<module>.open(<arguments>)) as f:\n            <block>\n\n    is equivalent to this:\n\n        f = <module>.open(<arguments>)\n        try:\n            <block>\n        finally:\n            f.close()\n\n    ', <code object __init__ at 0x0000024069427EC0, file "contextlib.py", line 343>, <code object __enter__ at 0x0000024069427DF0, file "contextlib.py", line 345>, <code object __exit__ at 0x000002406945DB60, file "contextlib.py", line 347>, None)

## co_names:
('__name__', '__module__', '__qualname__', '__doc__', '__init__', '__enter__', '__exit__')

## bytecode:

   0: RESUME               
   2: LOAD_NAME            __name__
   4: STORE_NAME           __module__
   6: LOAD_CONST           'closing'
   8: STORE_NAME           __qualname__
  10: LOAD_CONST           'Context to automatically close something at the end of a block.\n\n    Code like this:\n\n        with closing(<module>.open(<arguments>)) as f:\n            <block>\n\n    is equivalent to this:\n\n        f = <module>.open(<arguments>)\n        try:\n            <block>\n        finally:\n            f.close()\n\n    '
  12: STORE_NAME           __doc__
  14: LOAD_CONST           <code object __init__ at 0x0000024069427EC0, file "contextlib.py", line 343>
  16: MAKE_FUNCTION        
  18: STORE_NAME           __init__
  20: LOAD_CONST           <code object __enter__ at 0x0000024069427DF0, file "contextlib.py", line 345>
  22: MAKE_FUNCTION        
  24: STORE_NAME           __enter__
  26: LOAD_CONST           <code object __exit__ at 0x000002406945DB60, file "contextlib.py", line 347>
  28: MAKE_FUNCTION        
  30: STORE_NAME           __exit__
  32: LOAD_CONST           None
  34: RETURN_VALUE         
