# Disassembly for contextlib.chdir
# From module file: contextlib

## co_consts:
('chdir', 'Non thread-safe context manager to change the current working directory.', <code object __init__ at 0x0000024069465FB0, file "contextlib.py", line 770>, <code object __enter__ at 0x00000240691F3B40, file "contextlib.py", line 774>, <code object __exit__ at 0x000002406941B090, file "contextlib.py", line 778>, None)

## co_names:
('__name__', '__module__', '__qualname__', '__doc__', '__init__', '__enter__', '__exit__')

## bytecode:

   0: RESUME               
   2: LOAD_NAME            __name__
   4: STORE_NAME           __module__
   6: LOAD_CONST           'chdir'
   8: STORE_NAME           __qualname__
  10: LOAD_CONST           'Non thread-safe context manager to change the current working directory.'
  12: STORE_NAME           __doc__
  14: LOAD_CONST           <code object __init__ at 0x0000024069465FB0, file "contextlib.py", line 770>
  16: MAKE_FUNCTION        
  18: STORE_NAME           __init__
  20: LOAD_CONST           <code object __enter__ at 0x00000240691F3B40, file "contextlib.py", line 774>
  22: MAKE_FUNCTION        
  24: STORE_NAME           __enter__
  26: LOAD_CONST           <code object __exit__ at 0x000002406941B090, file "contextlib.py", line 778>
  28: MAKE_FUNCTION        
  30: STORE_NAME           __exit__
  32: LOAD_CONST           None
  34: RETURN_VALUE         
