# Disassembly for contextlib.nullcontext
# From module file: contextlib

## co_consts:
('nullcontext', 'Context manager that does no additional processing.\n\n    Used as a stand-in for a normal context manager, when a particular\n    block of code is only sometimes used with a normal context manager:\n\n    cm = optional_cm if condition else nullcontext()\n    with cm:\n        # Perform operation, using optional_cm if condition is True\n    ', None, <code object __init__ at 0x0000024069495960, file "contextlib.py", line 751>, <code object __enter__ at 0x00000240694941D0, file "contextlib.py", line 754>, <code object __exit__ at 0x000002406943BCF0, file "contextlib.py", line 757>, <code object __aenter__ at 0x0000024069495B00, file "contextlib.py", line 760>, <code object __aexit__ at 0x0000024069495BD0, file "contextlib.py", line 763>, (None,))

## co_names:
('__name__', '__module__', '__qualname__', '__doc__', '__init__', '__enter__', '__exit__', '__aenter__', '__aexit__')

## bytecode:

   0: RESUME               
   2: LOAD_NAME            __name__
   4: STORE_NAME           __module__
   6: LOAD_CONST           'nullcontext'
   8: STORE_NAME           __qualname__
  10: LOAD_CONST           'Context manager that does no additional processing.\n\n    Used as a stand-in for a normal context manager, when a particular\n    block of code is only sometimes used with a normal context manager:\n\n    cm = optional_cm if condition else nullcontext()\n    with cm:\n        # Perform operation, using optional_cm if condition is True\n    '
  12: STORE_NAME           __doc__
  14: LOAD_CONST           (None,)
  16: LOAD_CONST           <code object __init__ at 0x0000024069495960, file "contextlib.py", line 751>
  18: MAKE_FUNCTION        defaults
  20: STORE_NAME           __init__
  22: LOAD_CONST           <code object __enter__ at 0x00000240694941D0, file "contextlib.py", line 754>
  24: MAKE_FUNCTION        
  26: STORE_NAME           __enter__
  28: LOAD_CONST           <code object __exit__ at 0x000002406943BCF0, file "contextlib.py", line 757>
  30: MAKE_FUNCTION        
  32: STORE_NAME           __exit__
  34: LOAD_CONST           <code object __aenter__ at 0x0000024069495B00, file "contextlib.py", line 760>
  36: MAKE_FUNCTION        
  38: STORE_NAME           __aenter__
  40: LOAD_CONST           <code object __aexit__ at 0x0000024069495BD0, file "contextlib.py", line 763>
  42: MAKE_FUNCTION        
  44: STORE_NAME           __aexit__
  46: LOAD_CONST           None
  48: RETURN_VALUE         
