# Disassembly for contextlib.AsyncExitStack.push_async_callback
# From module file: contextlib

## co_consts:
('Registers an arbitrary coroutine function and arguments.\n\n        Cannot suppress exceptions.\n        ', False)

## co_names:
('_create_async_cb_wrapper', '__wrapped__', '_push_exit_callback')

## bytecode:

   0: RESUME               
   2: PUSH_NULL            
   4: LOAD_FAST            self
   6: LOAD_ATTR            _create_async_cb_wrapper
  16: LOAD_FAST            callback
  18: BUILD_LIST           
  20: LOAD_FAST            args
  22: LIST_EXTEND          
  24: LIST_TO_TUPLE        
  26: BUILD_MAP            
  28: LOAD_FAST            kwds
  30: DICT_MERGE           
  32: CALL_FUNCTION_EX     
  34: STORE_FAST           _exit_wrapper
  36: LOAD_FAST            callback
  38: LOAD_FAST            _exit_wrapper
  40: STORE_ATTR           __wrapped__
  50: LOAD_FAST            self
  52: LOAD_METHOD          _push_exit_callback
  74: LOAD_FAST            _exit_wrapper
  76: LOAD_CONST           False
  78: PRECALL              
  82: CALL                 
  92: POP_TOP              
  94: LOAD_FAST            callback
  96: RETURN_VALUE         
