# Disassembly for contextlib.suppress.__exit__
# From module file: contextlib

## co_consts:
(None,)

## co_names:
('issubclass', '_exceptions')

## bytecode:

   0: RESUME               
   2: LOAD_FAST            exctype
   4: LOAD_CONST           None
   6: IS_OP                
   8: JUMP_IF_FALSE_OR_POP to 50
  10: LOAD_GLOBAL          NULL + issubclass
  22: LOAD_FAST            exctype
  24: LOAD_FAST            self
  26: LOAD_ATTR            _exceptions
  36: PRECALL              
  40: CALL                 
  50: RETURN_VALUE         
