# Disassembly for contextlib._BaseExitStack._push_exit_callback
# From module file: contextlib

## co_consts:
(None,)

## co_names:
('_exit_callbacks', 'append')

## bytecode:

   0: RESUME               
   2: LOAD_FAST            self
   4: LOAD_ATTR            _exit_callbacks
  14: LOAD_METHOD          append
  36: LOAD_FAST            is_sync
  38: LOAD_FAST            callback
  40: BUILD_TUPLE          
  42: PRECALL              
  46: CALL                 
  56: POP_TOP              
  58: LOAD_CONST           None
  60: RETURN_VALUE         
