# Disassembly for contextlib._BaseExitStack.pop_all
# From module file: contextlib

## co_consts:
('Preserve the context stack by transferring it to a new instance.',)

## co_names:
('type', '_exit_callbacks', 'deque')

## bytecode:

   0: RESUME               
   2: PUSH_NULL            
   4: LOAD_GLOBAL          NULL + type
  16: LOAD_FAST            self
  18: PRECALL              
  22: CALL                 
  32: PRECALL              
  36: CALL                 
  46: STORE_FAST           new_stack
  48: LOAD_FAST            self
  50: LOAD_ATTR            _exit_callbacks
  60: LOAD_FAST            new_stack
  62: STORE_ATTR           _exit_callbacks
  72: LOAD_GLOBAL          NULL + deque
  84: PRECALL              
  88: CALL                 
  98: LOAD_FAST            self
 100: STORE_ATTR           _exit_callbacks
 110: LOAD_FAST            new_stack
 112: RETURN_VALUE         
