# Disassembly for contextlib._GeneratorContextManagerBase
# From module file: contextlib

## co_consts:
('_GeneratorContextManagerBase', 'Shared functionality for @contextmanager and @asynccontextmanager.', <code object __init__ at 0x00000240691C02F0, file "contextlib.py", line 104>, <code object _recreate_cm at 0x000002406944A010, file "contextlib.py", line 118>, None)

## co_names:
('__name__', '__module__', '__qualname__', '__doc__', '__init__', '_recreate_cm')

## bytecode:

   0: RESUME               
   2: LOAD_NAME            __name__
   4: STORE_NAME           __module__
   6: LOAD_CONST           '_GeneratorContextManagerBase'
   8: STORE_NAME           __qualname__
  10: LOAD_CONST           'Shared functionality for @contextmanager and @asynccontextmanager.'
  12: STORE_NAME           __doc__
  14: LOAD_CONST           <code object __init__ at 0x00000240691C02F0, file "contextlib.py", line 104>
  16: MAKE_FUNCTION        
  18: STORE_NAME           __init__
  20: LOAD_CONST           <code object _recreate_cm at 0x000002406944A010, file "contextlib.py", line 118>
  22: MAKE_FUNCTION        
  24: STORE_NAME           _recreate_cm
  26: LOAD_CONST           None
  28: RETURN_VALUE         
