# Disassembly for contextlib.redirect_stdout
# From module file: contextlib

## co_consts:
('redirect_stdout', "Context manager for temporarily redirecting stdout to another file.\n\n        # How to send help() to stderr\n        with redirect_stdout(sys.stderr):\n            help(dir)\n\n        # How to write help() to a file\n        with open('help.txt', 'w') as f:\n            with redirect_stdout(f):\n                help(pow)\n    ", 'stdout', None)

## co_names:
('__name__', '__module__', '__qualname__', '__doc__', '_stream')

## bytecode:

   0: RESUME               
   2: LOAD_NAME            __name__
   4: STORE_NAME           __module__
   6: LOAD_CONST           'redirect_stdout'
   8: STORE_NAME           __qualname__
  10: LOAD_CONST           "Context manager for temporarily redirecting stdout to another file.\n\n        # How to send help() to stderr\n        with redirect_stdout(sys.stderr):\n            help(dir)\n\n        # How to write help() to a file\n        with open('help.txt', 'w') as f:\n            with redirect_stdout(f):\n                help(pow)\n    "
  12: STORE_NAME           __doc__
  14: LOAD_CONST           'stdout'
  16: STORE_NAME           _stream
  18: LOAD_CONST           None
  20: RETURN_VALUE         
