# Disassembly for netrc.netrc.authenticators
# From module file: netrc

## co_consts:
('Return a (user, account, password) tuple for given host.', 'default', None)

## co_names:
('hosts',)

## bytecode:

   0: RESUME               
   2: LOAD_FAST            host
   4: LOAD_FAST            self
   6: LOAD_ATTR            hosts
  16: CONTAINS_OP          
  18: POP_JUMP_FORWARD_IF_FALSE to 46
  20: LOAD_FAST            self
  22: LOAD_ATTR            hosts
  32: LOAD_FAST            host
  34: BINARY_SUBSCR        
  44: RETURN_VALUE         
  46: LOAD_CONST           'default'
  48: LOAD_FAST            self
  50: LOAD_ATTR            hosts
  60: CONTAINS_OP          
  62: POP_JUMP_FORWARD_IF_FALSE to 90
  64: LOAD_FAST            self
  66: LOAD_ATTR            hosts
  76: LOAD_CONST           'default'
  78: BINARY_SUBSCR        
  88: RETURN_VALUE         
  90: LOAD_CONST           None
  92: RETURN_VALUE         
