# Disassembly for netrc.netrc.__repr__
# From module file: netrc

## co_consts:
('Dump the class data in the format of a .netrc file.', '', 'machine ', '\n\tlogin ', 0, '\n', 1, '\taccount ', '\tpassword ', 2, 'macdef ')

## co_names:
('hosts', 'keys', 'macros')

## bytecode:

   0: RESUME               
   2: LOAD_CONST           ''
   4: STORE_FAST           rep
   6: LOAD_FAST            self
   8: LOAD_ATTR            hosts
  18: LOAD_METHOD          keys
  40: PRECALL              
  44: CALL                 
  54: GET_ITER             
  56: FOR_ITER             to 200
  58: STORE_FAST           host
  60: LOAD_FAST            self
  62: LOAD_ATTR            hosts
  72: LOAD_FAST            host
  74: BINARY_SUBSCR        
  84: STORE_FAST           attrs
  86: LOAD_FAST            rep
  88: LOAD_CONST           'machine '
  90: LOAD_FAST            host
  92: FORMAT_VALUE         
  94: LOAD_CONST           '\n\tlogin '
  96: LOAD_FAST            attrs
  98: LOAD_CONST           0
 100: BINARY_SUBSCR        
 110: FORMAT_VALUE         
 112: LOAD_CONST           '\n'
 114: BUILD_STRING         
 116: BINARY_OP            +=
 120: STORE_FAST           rep
 122: LOAD_FAST            attrs
 124: LOAD_CONST           1
 126: BINARY_SUBSCR        
 136: POP_JUMP_FORWARD_IF_FALSE to 168
 138: LOAD_FAST            rep
 140: LOAD_CONST           '\taccount '
 142: LOAD_FAST            attrs
 144: LOAD_CONST           1
 146: BINARY_SUBSCR        
 156: FORMAT_VALUE         
 158: LOAD_CONST           '\n'
 160: BUILD_STRING         
 162: BINARY_OP            +=
 166: STORE_FAST           rep
 168: LOAD_FAST            rep
 170: LOAD_CONST           '\tpassword '
 172: LOAD_FAST            attrs
 174: LOAD_CONST           2
 176: BINARY_SUBSCR        
 186: FORMAT_VALUE         
 188: LOAD_CONST           '\n'
 190: BUILD_STRING         
 192: BINARY_OP            +=
 196: STORE_FAST           rep
 198: JUMP_BACKWARD        to 56
 200: LOAD_FAST            self
 202: LOAD_ATTR            macros
 212: LOAD_METHOD          keys
 234: PRECALL              
 238: CALL                 
 248: GET_ITER             
 250: FOR_ITER             to 326
 252: STORE_FAST           macro
 254: LOAD_FAST            rep
 256: LOAD_CONST           'macdef '
 258: LOAD_FAST            macro
 260: FORMAT_VALUE         
 262: LOAD_CONST           '\n'
 264: BUILD_STRING         
 266: BINARY_OP            +=
 270: STORE_FAST           rep
 272: LOAD_FAST            self
 274: LOAD_ATTR            macros
 284: LOAD_FAST            macro
 286: BINARY_SUBSCR        
 296: GET_ITER             
 298: FOR_ITER             to 314
 300: STORE_FAST           line
 302: LOAD_FAST            rep
 304: LOAD_FAST            line
 306: BINARY_OP            +=
 310: STORE_FAST           rep
 312: JUMP_BACKWARD        to 298
 314: LOAD_FAST            rep
 316: LOAD_CONST           '\n'
 318: BINARY_OP            +=
 322: STORE_FAST           rep
 324: JUMP_BACKWARD        to 250
 326: LOAD_FAST            rep
 328: RETURN_VALUE         
