# Disassembly for netrc.netrc._security_check
# From module file: netrc

## co_consts:
(None, 'posix', 'anonymous', 0, 'uid %s', '~/.netrc file owner (', ', ', ') does not match current user', '~/.netrc access too permissive: access permissions must restrict access to only the owner')

## co_names:
('os', 'name', 'fstat', 'fileno', 'st_uid', 'getuid', 'pwd', 'getpwuid', 'KeyError', 'NetrcParseError', 'st_mode', 'stat', 'S_IRWXG', 'S_IRWXO')

## bytecode:

   0: RESUME               
   2: LOAD_GLOBAL          os
  14: LOAD_ATTR            name
  24: LOAD_CONST           'posix'
  26: COMPARE_OP           ==
  32: EXTENDED_ARG         
  34: POP_JUMP_FORWARD_IF_FALSE to 624
  36: LOAD_FAST            default_netrc
  38: EXTENDED_ARG         
  40: POP_JUMP_FORWARD_IF_FALSE to 628
  42: LOAD_FAST            login
  44: LOAD_CONST           'anonymous'
  46: COMPARE_OP           !=
  52: EXTENDED_ARG         
  54: POP_JUMP_FORWARD_IF_FALSE to 632
  56: LOAD_GLOBAL          NULL + os
  68: LOAD_ATTR            fstat
  78: LOAD_FAST            fp
  80: LOAD_METHOD          fileno
 102: PRECALL              
 106: CALL                 
 116: PRECALL              
 120: CALL                 
 130: STORE_FAST           prop
 132: LOAD_FAST            prop
 134: LOAD_ATTR            st_uid
 144: LOAD_GLOBAL          NULL + os
 156: LOAD_ATTR            getuid
 166: PRECALL              
 170: CALL                 
 180: COMPARE_OP           !=
 186: POP_JUMP_FORWARD_IF_FALSE to 528
 188: LOAD_CONST           0
 190: LOAD_CONST           None
 192: IMPORT_NAME          pwd
 194: STORE_FAST           pwd
 196: NOP                  
 198: LOAD_FAST            pwd
 200: LOAD_METHOD          getpwuid
 222: LOAD_FAST            prop
 224: LOAD_ATTR            st_uid
 234: PRECALL              
 238: CALL                 
 248: LOAD_CONST           0
 250: BINARY_SUBSCR        
 260: STORE_FAST           fowner
 262: JUMP_FORWARD         to 316
 264: PUSH_EXC_INFO        
 266: LOAD_GLOBAL          KeyError
 278: CHECK_EXC_MATCH      
 280: POP_JUMP_FORWARD_IF_FALSE to 308
 282: POP_TOP              
 284: LOAD_CONST           'uid %s'
 286: LOAD_FAST            prop
 288: LOAD_ATTR            st_uid
 298: BINARY_OP            %
 302: STORE_FAST           fowner
 304: POP_EXCEPT           
 306: JUMP_FORWARD         to 316
 308: RERAISE              
 310: COPY                 
 312: POP_EXCEPT           
 314: RERAISE              
 316: NOP                  
 318: LOAD_FAST            pwd
 320: LOAD_METHOD          getpwuid
 342: LOAD_GLOBAL          NULL + os
 354: LOAD_ATTR            getuid
 364: PRECALL              
 368: CALL                 
 378: PRECALL              
 382: CALL                 
 392: LOAD_CONST           0
 394: BINARY_SUBSCR        
 404: STORE_FAST           user
 406: JUMP_FORWARD         to 484
 408: PUSH_EXC_INFO        
 410: LOAD_GLOBAL          KeyError
 422: CHECK_EXC_MATCH      
 424: POP_JUMP_FORWARD_IF_FALSE to 476
 426: POP_TOP              
 428: LOAD_CONST           'uid %s'
 430: LOAD_GLOBAL          NULL + os
 442: LOAD_ATTR            getuid
 452: PRECALL              
 456: CALL                 
 466: BINARY_OP            %
 470: STORE_FAST           user
 472: POP_EXCEPT           
 474: JUMP_FORWARD         to 484
 476: RERAISE              
 478: COPY                 
 480: POP_EXCEPT           
 482: RERAISE              
 484: LOAD_GLOBAL          NULL + NetrcParseError
 496: LOAD_CONST           '~/.netrc file owner ('
 498: LOAD_FAST            fowner
 500: FORMAT_VALUE         
 502: LOAD_CONST           ', '
 504: LOAD_FAST            user
 506: FORMAT_VALUE         
 508: LOAD_CONST           ') does not match current user'
 510: BUILD_STRING         
 512: PRECALL              
 516: CALL                 
 526: RAISE_VARARGS        
 528: LOAD_FAST            prop
 530: LOAD_ATTR            st_mode
 540: LOAD_GLOBAL          stat
 552: LOAD_ATTR            S_IRWXG
 562: LOAD_GLOBAL          stat
 574: LOAD_ATTR            S_IRWXO
 584: BINARY_OP            |
 588: BINARY_OP            &
 592: POP_JUMP_FORWARD_IF_FALSE to 636
 594: LOAD_GLOBAL          NULL + NetrcParseError
 606: LOAD_CONST           '~/.netrc access too permissive: access permissions must restrict access to only the owner'
 608: PRECALL              
 612: CALL                 
 622: RAISE_VARARGS        
 624: LOAD_CONST           None
 626: RETURN_VALUE         
 628: LOAD_CONST           None
 630: RETURN_VALUE         
 632: LOAD_CONST           None
 634: RETURN_VALUE         
 636: LOAD_CONST           None
 638: RETURN_VALUE         
