# Disassembly for netrc.netrc._parse
# From module file: netrc

## co_consts:
(None, 1, 0, '#', 'machine', 'default', 'macdef', 'Macro definition missing null line terminator.', '\n', 'bad toplevel token %r', 'missing %r name', '', frozenset({'', 'default', 'macdef', 'machine'}), 'login', 'user', 'account', 'password', 'bad follower token %r')

## co_names:
('_netrclex', 'lineno', 'get_token', 'len', 'instream', 'readline', 'macros', 'NetrcParseError', 'append', 'hosts', 'startswith', 'push_token', '_security_check')

## bytecode:

   0: RESUME               
   2: LOAD_GLOBAL          NULL + _netrclex
  14: LOAD_FAST            fp
  16: PRECALL              
  20: CALL                 
  30: STORE_FAST           lexer
  32: NOP                  
  34: LOAD_FAST            lexer
  36: LOAD_ATTR            lineno
  46: STORE_FAST           saved_lineno
  48: LOAD_FAST            lexer
  50: LOAD_METHOD          get_token
  72: PRECALL              
  76: CALL                 
  86: COPY                 
  88: STORE_FAST           toplevel
  90: STORE_FAST           tt
  92: LOAD_FAST            tt
  94: POP_JUMP_FORWARD_IF_TRUE to 100
  96: LOAD_CONST           None
  98: RETURN_VALUE         
 100: LOAD_FAST            tt
 102: LOAD_CONST           0
 104: BINARY_SUBSCR        
 114: LOAD_CONST           '#'
 116: COMPARE_OP           ==
 122: POP_JUMP_FORWARD_IF_FALSE to 236
 124: LOAD_FAST            lexer
 126: LOAD_ATTR            lineno
 136: LOAD_FAST            saved_lineno
 138: COMPARE_OP           ==
 144: POP_JUMP_FORWARD_IF_FALSE to 234
 146: LOAD_GLOBAL          NULL + len
 158: LOAD_FAST            tt
 160: PRECALL              
 164: CALL                 
 174: LOAD_CONST           1
 176: COMPARE_OP           ==
 182: POP_JUMP_FORWARD_IF_FALSE to 234
 184: LOAD_FAST            lexer
 186: LOAD_ATTR            instream
 196: LOAD_METHOD          readline
 218: PRECALL              
 222: CALL                 
 232: POP_TOP              
 234: JUMP_BACKWARD        to 32
 236: LOAD_FAST            tt
 238: LOAD_CONST           'machine'
 240: COMPARE_OP           ==
 246: POP_JUMP_FORWARD_IF_FALSE to 290
 248: LOAD_FAST            lexer
 250: LOAD_METHOD          get_token
 272: PRECALL              
 276: CALL                 
 286: STORE_FAST           entryname
 288: JUMP_FORWARD         to 614
 290: LOAD_FAST            tt
 292: LOAD_CONST           'default'
 294: COMPARE_OP           ==
 300: POP_JUMP_FORWARD_IF_FALSE to 308
 302: LOAD_CONST           'default'
 304: STORE_FAST           entryname
 306: JUMP_FORWARD         to 614
 308: LOAD_FAST            tt
 310: LOAD_CONST           'macdef'
 312: COMPARE_OP           ==
 318: POP_JUMP_FORWARD_IF_FALSE to 564
 320: LOAD_FAST            lexer
 322: LOAD_METHOD          get_token
 344: PRECALL              
 348: CALL                 
 358: STORE_FAST           entryname
 360: BUILD_LIST           
 362: LOAD_FAST            self
 364: LOAD_ATTR            macros
 374: LOAD_FAST            entryname
 376: STORE_SUBSCR         
 380: NOP                  
 382: LOAD_FAST            lexer
 384: LOAD_ATTR            instream
 394: LOAD_METHOD          readline
 416: PRECALL              
 420: CALL                 
 430: STORE_FAST           line
 432: LOAD_FAST            line
 434: POP_JUMP_FORWARD_IF_TRUE to 480
 436: LOAD_GLOBAL          NULL + NetrcParseError
 448: LOAD_CONST           'Macro definition missing null line terminator.'
 450: LOAD_FAST            file
 452: LOAD_FAST            lexer
 454: LOAD_ATTR            lineno
 464: PRECALL              
 468: CALL                 
 478: RAISE_VARARGS        
 480: LOAD_FAST            line
 482: LOAD_CONST           '\n'
 484: COMPARE_OP           ==
 490: POP_JUMP_FORWARD_IF_FALSE to 494
 492: JUMP_FORWARD         to 560
 494: LOAD_FAST            self
 496: LOAD_ATTR            macros
 506: LOAD_FAST            entryname
 508: BINARY_SUBSCR        
 518: LOAD_METHOD          append
 540: LOAD_FAST            line
 542: PRECALL              
 546: CALL                 
 556: POP_TOP              
 558: JUMP_BACKWARD        to 382
 560: EXTENDED_ARG         
 562: JUMP_BACKWARD        to 32
 564: LOAD_GLOBAL          NULL + NetrcParseError
 576: LOAD_CONST           'bad toplevel token %r'
 578: LOAD_FAST            tt
 580: BINARY_OP            %
 584: LOAD_FAST            file
 586: LOAD_FAST            lexer
 588: LOAD_ATTR            lineno
 598: PRECALL              
 602: CALL                 
 612: RAISE_VARARGS        
 614: LOAD_FAST            entryname
 616: POP_JUMP_FORWARD_IF_TRUE to 668
 618: LOAD_GLOBAL          NULL + NetrcParseError
 630: LOAD_CONST           'missing %r name'
 632: LOAD_FAST            tt
 634: BINARY_OP            %
 638: LOAD_FAST            file
 640: LOAD_FAST            lexer
 642: LOAD_ATTR            lineno
 652: PRECALL              
 656: CALL                 
 666: RAISE_VARARGS        
 668: LOAD_CONST           ''
 670: COPY                 
 672: STORE_FAST           login
 674: COPY                 
 676: STORE_FAST           account
 678: STORE_FAST           password
 680: BUILD_MAP            
 682: LOAD_FAST            self
 684: LOAD_ATTR            hosts
 694: LOAD_FAST            entryname
 696: STORE_SUBSCR         
 700: NOP                  
 702: LOAD_FAST            lexer
 704: LOAD_ATTR            lineno
 714: STORE_FAST           prev_lineno
 716: LOAD_FAST            lexer
 718: LOAD_METHOD          get_token
 740: PRECALL              
 744: CALL                 
 754: STORE_FAST           tt
 756: LOAD_FAST            tt
 758: LOAD_METHOD          startswith
 780: LOAD_CONST           '#'
 782: PRECALL              
 786: CALL                 
 796: POP_JUMP_FORWARD_IF_FALSE to 872
 798: LOAD_FAST            lexer
 800: LOAD_ATTR            lineno
 810: LOAD_FAST            prev_lineno
 812: COMPARE_OP           ==
 818: POP_JUMP_FORWARD_IF_FALSE to 870
 820: LOAD_FAST            lexer
 822: LOAD_ATTR            instream
 832: LOAD_METHOD          readline
 854: PRECALL              
 858: CALL                 
 868: POP_TOP              
 870: JUMP_BACKWARD        to 700
 872: LOAD_FAST            tt
 874: LOAD_CONST           frozenset({'', 'default', 'macdef', 'machine'})
 876: CONTAINS_OP          
 878: POP_JUMP_FORWARD_IF_FALSE to 950
 880: LOAD_FAST            login
 882: LOAD_FAST            account
 884: LOAD_FAST            password
 886: BUILD_TUPLE          
 888: LOAD_FAST            self
 890: LOAD_ATTR            hosts
 900: LOAD_FAST            entryname
 902: STORE_SUBSCR         
 906: LOAD_FAST            lexer
 908: LOAD_METHOD          push_token
 930: LOAD_FAST            tt
 932: PRECALL              
 936: CALL                 
 946: POP_TOP              
 948: JUMP_FORWARD         to 1176
 950: LOAD_FAST            tt
 952: LOAD_CONST           'login'
 954: COMPARE_OP           ==
 960: POP_JUMP_FORWARD_IF_TRUE to 974
 962: LOAD_FAST            tt
 964: LOAD_CONST           'user'
 966: COMPARE_OP           ==
 972: POP_JUMP_FORWARD_IF_FALSE to 1016
 974: LOAD_FAST            lexer
 976: LOAD_METHOD          get_token
 998: PRECALL              
1002: CALL                 
1012: STORE_FAST           login
1014: JUMP_FORWARD         to 1174
1016: LOAD_FAST            tt
1018: LOAD_CONST           'account'
1020: COMPARE_OP           ==
1026: POP_JUMP_FORWARD_IF_FALSE to 1070
1028: LOAD_FAST            lexer
1030: LOAD_METHOD          get_token
1052: PRECALL              
1056: CALL                 
1066: STORE_FAST           account
1068: JUMP_FORWARD         to 1174
1070: LOAD_FAST            tt
1072: LOAD_CONST           'password'
1074: COMPARE_OP           ==
1080: POP_JUMP_FORWARD_IF_FALSE to 1124
1082: LOAD_FAST            lexer
1084: LOAD_METHOD          get_token
1106: PRECALL              
1110: CALL                 
1120: STORE_FAST           password
1122: JUMP_FORWARD         to 1174
1124: LOAD_GLOBAL          NULL + NetrcParseError
1136: LOAD_CONST           'bad follower token %r'
1138: LOAD_FAST            tt
1140: BINARY_OP            %
1144: LOAD_FAST            file
1146: LOAD_FAST            lexer
1148: LOAD_ATTR            lineno
1158: PRECALL              
1162: CALL                 
1172: RAISE_VARARGS        
1174: JUMP_BACKWARD        to 702
1176: LOAD_FAST            self
1178: LOAD_METHOD          _security_check
1200: LOAD_FAST            fp
1202: LOAD_FAST            default_netrc
1204: LOAD_FAST            self
1206: LOAD_ATTR            hosts
1216: LOAD_FAST            entryname
1218: BINARY_SUBSCR        
1228: LOAD_CONST           0
1230: BINARY_SUBSCR        
1240: PRECALL              
1244: CALL                 
1254: POP_TOP              
1256: EXTENDED_ARG         
1258: JUMP_BACKWARD        to 34
