# Disassembly for netrc.NetrcParseError.__str__
# From module file: netrc

## co_consts:
(None, ' (', ', line ', ')')

## co_names:
('msg', 'filename', 'lineno')

## bytecode:

   0: RESUME               
   2: LOAD_FAST            self
   4: LOAD_ATTR            msg
  14: FORMAT_VALUE         str
  16: LOAD_CONST           ' ('
  18: LOAD_FAST            self
  20: LOAD_ATTR            filename
  30: FORMAT_VALUE         str
  32: LOAD_CONST           ', line '
  34: LOAD_FAST            self
  36: LOAD_ATTR            lineno
  46: FORMAT_VALUE         str
  48: LOAD_CONST           ')'
  50: BUILD_STRING         
  52: RETURN_VALUE         
