# Disassembly for netrc._netrclex._read_char
# From module file: netrc

## co_consts:
(None, 1, '\n')

## co_names:
('instream', 'read', 'lineno')

## bytecode:

   0: RESUME               
   2: LOAD_FAST            self
   4: LOAD_ATTR            instream
  14: LOAD_METHOD          read
  36: LOAD_CONST           1
  38: PRECALL              
  42: CALL                 
  52: STORE_FAST           ch
  54: LOAD_FAST            ch
  56: LOAD_CONST           '\n'
  58: COMPARE_OP           ==
  64: POP_JUMP_FORWARD_IF_FALSE to 98
  66: LOAD_FAST            self
  68: COPY                 
  70: LOAD_ATTR            lineno
  80: LOAD_CONST           1
  82: BINARY_OP            +=
  86: SWAP                 
  88: STORE_ATTR           lineno
  98: LOAD_FAST            ch
 100: RETURN_VALUE         
