# Disassembly for selectors.BaseSelector.modify
# From module file: selectors

## co_consts:
('Change a registered file object monitored events or attached data.\n\n        Parameters:\n        fileobj -- file object or file descriptor\n        events  -- events to monitor (bitwise mask of EVENT_READ|EVENT_WRITE)\n        data    -- attached data\n\n        Returns:\n        SelectorKey instance\n\n        Raises:\n        Anything that unregister() or register() raises\n        ',)

## co_names:
('unregister', 'register')

## bytecode:

   0: RESUME               
   2: LOAD_FAST            self
   4: LOAD_METHOD          unregister
  26: LOAD_FAST            fileobj
  28: PRECALL              
  32: CALL                 
  42: POP_TOP              
  44: LOAD_FAST            self
  46: LOAD_METHOD          register
  68: LOAD_FAST            fileobj
  70: LOAD_FAST            events
  72: LOAD_FAST            data
  74: PRECALL              
  78: CALL                 
  88: RETURN_VALUE         
