# Disassembly for selectors.SelectSelector.unregister
# From module file: selectors

## co_consts:
(None,)

## co_names:
('super', 'unregister', '_readers', 'discard', 'fd', '_writers')

## bytecode:

   0: COPY_FREE_VARS       
   2: RESUME               
   4: LOAD_GLOBAL          NULL + super
  16: PRECALL              
  20: CALL                 
  30: LOAD_METHOD          unregister
  52: LOAD_FAST            fileobj
  54: PRECALL              
  58: CALL                 
  68: STORE_FAST           key
  70: LOAD_FAST            self
  72: LOAD_ATTR            _readers
  82: LOAD_METHOD          discard
 104: LOAD_FAST            key
 106: LOAD_ATTR            fd
 116: PRECALL              
 120: CALL                 
 130: POP_TOP              
 132: LOAD_FAST            self
 134: LOAD_ATTR            _writers
 144: LOAD_METHOD          discard
 166: LOAD_FAST            key
 168: LOAD_ATTR            fd
 178: PRECALL              
 182: CALL                 
 192: POP_TOP              
 194: LOAD_FAST            key
 196: RETURN_VALUE         
