# Disassembly for selectors.BaseSelector.get_key
# From module file: selectors

## co_consts:
('Return the key associated to a registered file object.\n\n        Returns:\n        SelectorKey for this file object\n        ', None, 'Selector is closed', '{!r} is not registered')

## co_names:
('get_map', 'RuntimeError', 'KeyError', 'format')

## bytecode:

   0: RESUME               
   2: LOAD_FAST            self
   4: LOAD_METHOD          get_map
  26: PRECALL              
  30: CALL                 
  40: STORE_FAST           mapping
  42: LOAD_FAST            mapping
  44: POP_JUMP_FORWARD_IF_NOT_NONE to 76
  46: LOAD_GLOBAL          NULL + RuntimeError
  58: LOAD_CONST           'Selector is closed'
  60: PRECALL              
  64: CALL                 
  74: RAISE_VARARGS        
  76: NOP                  
  78: LOAD_FAST            mapping
  80: LOAD_FAST            fileobj
  82: BINARY_SUBSCR        
  92: RETURN_VALUE         
  94: PUSH_EXC_INFO        
  96: LOAD_GLOBAL          KeyError
 108: CHECK_EXC_MATCH      
 110: POP_JUMP_FORWARD_IF_FALSE to 184
 112: POP_TOP              
 114: LOAD_GLOBAL          NULL + KeyError
 126: LOAD_CONST           '{!r} is not registered'
 128: LOAD_METHOD          format
 150: LOAD_FAST            fileobj
 152: PRECALL              
 156: CALL                 
 166: PRECALL              
 170: CALL                 
 180: LOAD_CONST           None
 182: RAISE_VARARGS        
 184: RERAISE              
 186: COPY                 
 188: POP_EXCEPT           
 190: RERAISE              
