# Disassembly for selectors.SelectSelector.register
# From module file: selectors

## co_consts:
(None,)

## co_names:
('super', 'register', 'EVENT_READ', '_readers', 'add', 'fd', 'EVENT_WRITE', '_writers')

## bytecode:

   0: COPY_FREE_VARS       
   2: RESUME               
   4: LOAD_GLOBAL          NULL + super
  16: PRECALL              
  20: CALL                 
  30: LOAD_METHOD          register
  52: LOAD_FAST            fileobj
  54: LOAD_FAST            events
  56: LOAD_FAST            data
  58: PRECALL              
  62: CALL                 
  72: STORE_FAST           key
  74: LOAD_FAST            events
  76: LOAD_GLOBAL          EVENT_READ
  88: BINARY_OP            &
  92: POP_JUMP_FORWARD_IF_FALSE to 156
  94: LOAD_FAST            self
  96: LOAD_ATTR            _readers
 106: LOAD_METHOD          add
 128: LOAD_FAST            key
 130: LOAD_ATTR            fd
 140: PRECALL              
 144: CALL                 
 154: POP_TOP              
 156: LOAD_FAST            events
 158: LOAD_GLOBAL          EVENT_WRITE
 170: BINARY_OP            &
 174: POP_JUMP_FORWARD_IF_FALSE to 238
 176: LOAD_FAST            self
 178: LOAD_ATTR            _writers
 188: LOAD_METHOD          add
 210: LOAD_FAST            key
 212: LOAD_ATTR            fd
 222: PRECALL              
 226: CALL                 
 236: POP_TOP              
 238: LOAD_FAST            key
 240: RETURN_VALUE         
