# Disassembly for selectors._BaseSelectorImpl._fileobj_lookup
# From module file: selectors

## co_consts:
('Return a file descriptor from a file object.\n\n        This wraps _fileobj_to_fd() to do an exhaustive search in case\n        the object is invalid but we still have it in our map.  This\n        is used by unregister() so we can unregister an object that\n        was previously registered even if it is closed.  It is also\n        used by _SelectorMapping.\n        ',)

## co_names:
('_fileobj_to_fd', 'ValueError', '_fd_to_key', 'values', 'fileobj', 'fd')

## bytecode:

   0: RESUME               
   2: NOP                  
   4: LOAD_GLOBAL          NULL + _fileobj_to_fd
  16: LOAD_FAST            fileobj
  18: PRECALL              
  22: CALL                 
  32: RETURN_VALUE         
  34: PUSH_EXC_INFO        
  36: LOAD_GLOBAL          ValueError
  48: CHECK_EXC_MATCH      
  50: POP_JUMP_FORWARD_IF_FALSE to 152
  52: POP_TOP              
  54: LOAD_FAST            self
  56: LOAD_ATTR            _fd_to_key
  66: LOAD_METHOD          values
  88: PRECALL              
  92: CALL                 
 102: GET_ITER             
 104: FOR_ITER             to 150
 106: STORE_FAST           key
 108: LOAD_FAST            key
 110: LOAD_ATTR            fileobj
 120: LOAD_FAST            fileobj
 122: IS_OP                
 124: POP_JUMP_FORWARD_IF_FALSE to 148
 126: LOAD_FAST            key
 128: LOAD_ATTR            fd
 138: SWAP                 
 140: POP_TOP              
 142: SWAP                 
 144: POP_EXCEPT           
 146: RETURN_VALUE         
 148: JUMP_BACKWARD        to 104
 150: RAISE_VARARGS        
 152: RERAISE              
 154: COPY                 
 156: POP_EXCEPT           
 158: RERAISE              
