# Disassembly for selectors._BaseSelectorImpl.__init__
# From module file: selectors

## co_consts:
(None,)

## co_names:
('_fd_to_key', '_SelectorMapping', '_map')

## bytecode:

   0: RESUME               
   2: BUILD_MAP            
   4: LOAD_FAST            self
   6: STORE_ATTR           _fd_to_key
  16: LOAD_GLOBAL          NULL + _SelectorMapping
  28: LOAD_FAST            self
  30: PRECALL              
  34: CALL                 
  44: LOAD_FAST            self
  46: STORE_ATTR           _map
  56: LOAD_CONST           None
  58: RETURN_VALUE         
