# Disassembly for selectors._fileobj_to_fd
# From module file: selectors

## co_consts:
('Return a file descriptor from a file object.\n\n    Parameters:\n    fileobj -- file object or file descriptor\n\n    Returns:\n    corresponding file descriptor\n\n    Raises:\n    ValueError if the object is invalid\n    ', 'Invalid file object: {!r}', None, 0, 'Invalid file descriptor: {}')

## co_names:
('isinstance', 'int', 'fileno', 'AttributeError', 'TypeError', 'ValueError', 'format')

## bytecode:

   0: RESUME               
   2: LOAD_GLOBAL          NULL + isinstance
  14: LOAD_FAST            fileobj
  16: LOAD_GLOBAL          int
  28: PRECALL              
  32: CALL                 
  42: POP_JUMP_FORWARD_IF_FALSE to 50
  44: LOAD_FAST            fileobj
  46: STORE_FAST           fd
  48: JUMP_FORWARD         to 244
  50: NOP                  
  52: LOAD_GLOBAL          NULL + int
  64: LOAD_FAST            fileobj
  66: LOAD_METHOD          fileno
  88: PRECALL              
  92: CALL                 
 102: PRECALL              
 106: CALL                 
 116: STORE_FAST           fd
 118: JUMP_FORWARD         to 244
 120: PUSH_EXC_INFO        
 122: LOAD_GLOBAL          AttributeError
 134: LOAD_GLOBAL          TypeError
 146: LOAD_GLOBAL          ValueError
 158: BUILD_TUPLE          
 160: CHECK_EXC_MATCH      
 162: POP_JUMP_FORWARD_IF_FALSE to 236
 164: POP_TOP              
 166: LOAD_GLOBAL          NULL + ValueError
 178: LOAD_CONST           'Invalid file object: {!r}'
 180: LOAD_METHOD          format
 202: LOAD_FAST            fileobj
 204: PRECALL              
 208: CALL                 
 218: PRECALL              
 222: CALL                 
 232: LOAD_CONST           None
 234: RAISE_VARARGS        
 236: RERAISE              
 238: COPY                 
 240: POP_EXCEPT           
 242: RERAISE              
 244: LOAD_FAST            fd
 246: LOAD_CONST           0
 248: COMPARE_OP           <
 254: POP_JUMP_FORWARD_IF_FALSE to 324
 256: LOAD_GLOBAL          NULL + ValueError
 268: LOAD_CONST           'Invalid file descriptor: {}'
 270: LOAD_METHOD          format
 292: LOAD_FAST            fd
 294: PRECALL              
 298: CALL                 
 308: PRECALL              
 312: CALL                 
 322: RAISE_VARARGS        
 324: LOAD_FAST            fd
 326: RETURN_VALUE         
