# Disassembly for selectors.SelectSelector._select
# From module file: selectors

## co_consts:
(None,)

## co_names:
('select',)

## bytecode:

   0: RESUME               
   2: LOAD_GLOBAL          NULL + select
  14: LOAD_ATTR            select
  24: LOAD_FAST            r
  26: LOAD_FAST            w
  28: LOAD_FAST            w
  30: LOAD_FAST            timeout
  32: PRECALL              
  36: CALL                 
  46: UNPACK_SEQUENCE      
  50: STORE_FAST           r
  52: STORE_FAST           w
  54: STORE_FAST           x
  56: LOAD_FAST            r
  58: LOAD_FAST            w
  60: LOAD_FAST            x
  62: BINARY_OP            +
  66: BUILD_LIST           
  68: BUILD_TUPLE          
  70: RETURN_VALUE         
