# Disassembly for selectors.DevpollSelector
# From module file: selectors

## co_consts:
('DevpollSelector', 'Solaris /dev/poll selector.', <code object fileno at 0x000002406945FC30, file "selectors.py", line 496>, <code object close at 0x00000240693AA6F0, file "selectors.py", line 499>)

## co_names:
('__name__', '__module__', '__qualname__', '__doc__', 'select', 'devpoll', '_selector_cls', 'POLLIN', '_EVENT_READ', 'POLLOUT', '_EVENT_WRITE', 'fileno', 'close', '__classcell__')

## bytecode:

   0: MAKE_CELL            __class__
   2: RESUME               
   4: LOAD_NAME            __name__
   6: STORE_NAME           __module__
   8: LOAD_CONST           'DevpollSelector'
  10: STORE_NAME           __qualname__
  12: LOAD_CONST           'Solaris /dev/poll selector.'
  14: STORE_NAME           __doc__
  16: LOAD_NAME            select
  18: LOAD_ATTR            devpoll
  28: STORE_NAME           _selector_cls
  30: LOAD_NAME            select
  32: LOAD_ATTR            POLLIN
  42: STORE_NAME           _EVENT_READ
  44: LOAD_NAME            select
  46: LOAD_ATTR            POLLOUT
  56: STORE_NAME           _EVENT_WRITE
  58: LOAD_CONST           <code object fileno at 0x000002406945FC30, file "selectors.py", line 496>
  60: MAKE_FUNCTION        
  62: STORE_NAME           fileno
  64: LOAD_CLOSURE         __class__
  66: BUILD_TUPLE          
  68: LOAD_CONST           <code object close at 0x00000240693AA6F0, file "selectors.py", line 499>
  70: MAKE_FUNCTION        closure
  72: STORE_NAME           close
  74: LOAD_CLOSURE         __class__
  76: COPY                 
  78: STORE_NAME           __classcell__
  80: RETURN_VALUE         
