# Disassembly for selectors.SelectSelector.__init__
# From module file: selectors

## co_consts:
(None,)

## co_names:
('super', '__init__', 'set', '_readers', '_writers')

## bytecode:

   0: COPY_FREE_VARS       
   2: RESUME               
   4: LOAD_GLOBAL          NULL + super
  16: PRECALL              
  20: CALL                 
  30: LOAD_METHOD          __init__
  52: PRECALL              
  56: CALL                 
  66: POP_TOP              
  68: LOAD_GLOBAL          NULL + set
  80: PRECALL              
  84: CALL                 
  94: LOAD_FAST            self
  96: STORE_ATTR           _readers
 106: LOAD_GLOBAL          NULL + set
 118: PRECALL              
 122: CALL                 
 132: LOAD_FAST            self
 134: STORE_ATTR           _writers
 144: LOAD_CONST           None
 146: RETURN_VALUE         
