# Disassembly for py_compile.PyCompileError
# From module file: py_compile

## co_consts:
('PyCompileError', "Exception raised when an error occurs while attempting to\n    compile the file.\n\n    To raise this exception, use\n\n        raise PyCompileError(exc_type,exc_value,file[,msg])\n\n    where\n\n        exc_type:   exception type to be used in error message\n                    type name can be accesses as class variable\n                    'exc_type_name'\n\n        exc_value:  exception value to be used in error message\n                    can be accesses as class variable 'exc_value'\n\n        file:       name of file being compiled to be used in error message\n                    can be accesses as class variable 'file'\n\n        msg:        string message to be written as error message\n                    If no value is given, a default exception message will be\n                    given, consistent with 'standard' py_compile output.\n                    message (or default) can be accesses as class variable\n                    'msg'\n\n    ", '', <code object __init__ at 0x0000024069366AD0, file "py_compile.py", line 46>, <code object __str__ at 0x0000024069427C50, file "py_compile.py", line 62>, None, ('',))

## co_names:
('__name__', '__module__', '__qualname__', '__doc__', '__init__', '__str__')

## bytecode:

   0: RESUME               
   2: LOAD_NAME            __name__
   4: STORE_NAME           __module__
   6: LOAD_CONST           'PyCompileError'
   8: STORE_NAME           __qualname__
  10: LOAD_CONST           "Exception raised when an error occurs while attempting to\n    compile the file.\n\n    To raise this exception, use\n\n        raise PyCompileError(exc_type,exc_value,file[,msg])\n\n    where\n\n        exc_type:   exception type to be used in error message\n                    type name can be accesses as class variable\n                    'exc_type_name'\n\n        exc_value:  exception value to be used in error message\n                    can be accesses as class variable 'exc_value'\n\n        file:       name of file being compiled to be used in error message\n                    can be accesses as class variable 'file'\n\n        msg:        string message to be written as error message\n                    If no value is given, a default exception message will be\n                    given, consistent with 'standard' py_compile output.\n                    message (or default) can be accesses as class variable\n                    'msg'\n\n    "
  12: STORE_NAME           __doc__
  14: LOAD_CONST           ('',)
  16: LOAD_CONST           <code object __init__ at 0x0000024069366AD0, file "py_compile.py", line 46>
  18: MAKE_FUNCTION        defaults
  20: STORE_NAME           __init__
  22: LOAD_CONST           <code object __str__ at 0x0000024069427C50, file "py_compile.py", line 62>
  24: MAKE_FUNCTION        
  26: STORE_NAME           __str__
  28: LOAD_CONST           None
  30: RETURN_VALUE         
