# Disassembly for py_compile._get_default_invalidation_mode
# From module file: py_compile

## co_consts:
(None, 'SOURCE_DATE_EPOCH')

## co_names:
('os', 'environ', 'get', 'PycInvalidationMode', 'CHECKED_HASH', 'TIMESTAMP')

## bytecode:

   0: RESUME               
   2: LOAD_GLOBAL          os
  14: LOAD_ATTR            environ
  24: LOAD_METHOD          get
  46: LOAD_CONST           'SOURCE_DATE_EPOCH'
  48: PRECALL              
  52: CALL                 
  62: POP_JUMP_FORWARD_IF_FALSE to 88
  64: LOAD_GLOBAL          PycInvalidationMode
  76: LOAD_ATTR            CHECKED_HASH
  86: RETURN_VALUE         
  88: LOAD_GLOBAL          PycInvalidationMode
 100: LOAD_ATTR            TIMESTAMP
 110: RETURN_VALUE         
