# Disassembly for py_compile.compile
# From module file: py_compile

## co_consts:
("Byte-compile one Python source file to Python bytecode.\n\n    :param file: The source file name.\n    :param cfile: The target byte compiled file name.  When not given, this\n        defaults to the PEP 3147/PEP 488 location.\n    :param dfile: Purported file name, i.e. the file name that shows up in\n        error messages.  Defaults to the source file name.\n    :param doraise: Flag indicating whether or not an exception should be\n        raised when a compile error is found.  If an exception occurs and this\n        flag is set to False, a string indicating the nature of the exception\n        will be printed, and the function will return to the caller. If an\n        exception occurs and this flag is set to True, a PyCompileError\n        exception will be raised.\n    :param optimize: The optimization level for the compiler.  Valid values\n        are -1, 0, 1 and 2.  A value of -1 means to use the optimization\n        level of the current interpreter, as given by -O command line options.\n    :param invalidation_mode:\n    :param quiet: Return full output with False or 0, errors only with 1,\n        and no output with 2.\n\n    :return: Path to the resulting byte compiled file.\n\n    Note that it isn't necessary to byte-compile Python modules for\n    execution efficiency -- Python itself byte-compiles a module when\n    it is loaded, and if it can, writes out the bytecode to the\n    corresponding .pyc file.\n\n    However, if a Python installation is shared between users, it is a\n    good idea to byte-compile all modules upon installation, since\n    other users may not be able to write in the source directories,\n    and thus they won't be able to write the .pyc file, and then\n    they would be byte-compiling every module each time it is loaded.\n    This can slow down program start-up considerably.\n\n    See compileall.py for a script/module that uses this module to\n    byte-compile all installed files (or all files in selected\n    directories).\n\n    Do note that FileExistsError is raised if cfile ends up pointing at a\n    non-regular file or symlink. Because the compilation uses a file renaming,\n    the resulting file would be regular and thus not the same type of file as\n    it was previously.\n    ", None, 0, 1, '', ('optimization',), '{} is a symlink and will be changed into a regular file if import writes a byte-compiled file to it', '{} is a non-regular file and will be changed into a regular one if import writes a byte-compiled file to it', '<py_compile>', ('_optimize',), 2, '\n', 'mtime', 'size')

## co_names:
('_get_default_invalidation_mode', 'importlib', 'util', 'cache_from_source', 'os', 'path', 'islink', 'FileExistsError', 'format', 'exists', 'isfile', 'machinery', 'SourceFileLoader', 'get_data', 'source_to_code', 'Exception', 'PyCompileError', '__class__', 'sys', 'stderr', 'write', 'msg', 'dirname', 'makedirs', 'PycInvalidationMode', 'TIMESTAMP', 'path_stats', '_bootstrap_external', '_code_to_timestamp_pyc', 'source_hash', '_code_to_hash_pyc', 'CHECKED_HASH', '_calc_mode', '_write_atomic')

## bytecode:

   0: RESUME               
   2: LOAD_FAST            invalidation_mode
   4: POP_JUMP_FORWARD_IF_NOT_NONE to 34
   6: LOAD_GLOBAL          NULL + _get_default_invalidation_mode
  18: PRECALL              
  22: CALL                 
  32: STORE_FAST           invalidation_mode
  34: LOAD_FAST            cfile
  36: POP_JUMP_FORWARD_IF_NOT_NONE to 200
  38: LOAD_FAST            optimize
  40: LOAD_CONST           0
  42: COMPARE_OP           >=
  48: POP_JUMP_FORWARD_IF_FALSE to 138
  50: LOAD_FAST            optimize
  52: LOAD_CONST           1
  54: COMPARE_OP           >=
  60: POP_JUMP_FORWARD_IF_FALSE to 66
  62: LOAD_FAST            optimize
  64: JUMP_FORWARD         to 68
  66: LOAD_CONST           ''
  68: STORE_FAST           optimization
  70: LOAD_GLOBAL          importlib
  82: LOAD_ATTR            util
  92: LOAD_METHOD          cache_from_source
 114: LOAD_FAST            file
 116: LOAD_FAST            optimization
 118: KW_NAMES             
 120: PRECALL              
 124: CALL                 
 134: STORE_FAST           cfile
 136: JUMP_FORWARD         to 200
 138: LOAD_GLOBAL          importlib
 150: LOAD_ATTR            util
 160: LOAD_METHOD          cache_from_source
 182: LOAD_FAST            file
 184: PRECALL              
 188: CALL                 
 198: STORE_FAST           cfile
 200: LOAD_GLOBAL          os
 212: LOAD_ATTR            path
 222: LOAD_METHOD          islink
 244: LOAD_FAST            cfile
 246: PRECALL              
 250: CALL                 
 260: POP_JUMP_FORWARD_IF_FALSE to 334
 262: LOAD_CONST           '{} is a symlink and will be changed into a regular file if import writes a byte-compiled file to it'
 264: STORE_FAST           msg
 266: LOAD_GLOBAL          NULL + FileExistsError
 278: LOAD_FAST            msg
 280: LOAD_METHOD          format
 302: LOAD_FAST            cfile
 304: PRECALL              
 308: CALL                 
 318: PRECALL              
 322: CALL                 
 332: RAISE_VARARGS        
 334: LOAD_GLOBAL          os
 346: LOAD_ATTR            path
 356: LOAD_METHOD          exists
 378: LOAD_FAST            cfile
 380: PRECALL              
 384: CALL                 
 394: POP_JUMP_FORWARD_IF_FALSE to 530
 396: LOAD_GLOBAL          os
 408: LOAD_ATTR            path
 418: LOAD_METHOD          isfile
 440: LOAD_FAST            cfile
 442: PRECALL              
 446: CALL                 
 456: POP_JUMP_FORWARD_IF_TRUE to 530
 458: LOAD_CONST           '{} is a non-regular file and will be changed into a regular one if import writes a byte-compiled file to it'
 460: STORE_FAST           msg
 462: LOAD_GLOBAL          NULL + FileExistsError
 474: LOAD_FAST            msg
 476: LOAD_METHOD          format
 498: LOAD_FAST            cfile
 500: PRECALL              
 504: CALL                 
 514: PRECALL              
 518: CALL                 
 528: RAISE_VARARGS        
 530: LOAD_GLOBAL          importlib
 542: LOAD_ATTR            machinery
 552: LOAD_METHOD          SourceFileLoader
 574: LOAD_CONST           '<py_compile>'
 576: LOAD_FAST            file
 578: PRECALL              
 582: CALL                 
 592: STORE_FAST           loader
 594: LOAD_FAST            loader
 596: LOAD_METHOD          get_data
 618: LOAD_FAST            file
 620: PRECALL              
 624: CALL                 
 634: STORE_FAST           source_bytes
 636: NOP                  
 638: LOAD_FAST            loader
 640: LOAD_METHOD          source_to_code
 662: LOAD_FAST            source_bytes
 664: LOAD_FAST            dfile
 666: JUMP_IF_TRUE_OR_POP  to 670
 668: LOAD_FAST            file
 670: LOAD_FAST            optimize
 672: KW_NAMES             
 674: PRECALL              
 678: CALL                 
 688: STORE_FAST           code
 690: JUMP_FORWARD         to 886
 692: PUSH_EXC_INFO        
 694: LOAD_GLOBAL          Exception
 706: CHECK_EXC_MATCH      
 708: POP_JUMP_FORWARD_IF_FALSE to 878
 710: STORE_FAST           err
 712: LOAD_GLOBAL          NULL + PyCompileError
 724: LOAD_FAST            err
 726: LOAD_ATTR            __class__
 736: LOAD_FAST            err
 738: LOAD_FAST            dfile
 740: JUMP_IF_TRUE_OR_POP  to 744
 742: LOAD_FAST            file
 744: PRECALL              
 748: CALL                 
 758: STORE_FAST           py_exc
 760: LOAD_FAST            quiet
 762: LOAD_CONST           2
 764: COMPARE_OP           <
 770: POP_JUMP_FORWARD_IF_FALSE to 858
 772: LOAD_FAST            doraise
 774: POP_JUMP_FORWARD_IF_FALSE to 780
 776: LOAD_FAST            py_exc
 778: RAISE_VARARGS        
 780: LOAD_GLOBAL          sys
 792: LOAD_ATTR            stderr
 802: LOAD_METHOD          write
 824: LOAD_FAST            py_exc
 826: LOAD_ATTR            msg
 836: LOAD_CONST           '\n'
 838: BINARY_OP            +
 842: PRECALL              
 846: CALL                 
 856: POP_TOP              
 858: POP_EXCEPT           
 860: LOAD_CONST           None
 862: STORE_FAST           err
 864: DELETE_FAST          err
 866: LOAD_CONST           None
 868: RETURN_VALUE         
 870: LOAD_CONST           None
 872: STORE_FAST           err
 874: DELETE_FAST          err
 876: RERAISE              
 878: RERAISE              
 880: COPY                 
 882: POP_EXCEPT           
 884: RERAISE              
 886: NOP                  
 888: LOAD_GLOBAL          os
 900: LOAD_ATTR            path
 910: LOAD_METHOD          dirname
 932: LOAD_FAST            cfile
 934: PRECALL              
 938: CALL                 
 948: STORE_FAST           dirname
 950: LOAD_FAST            dirname
 952: POP_JUMP_FORWARD_IF_FALSE to 994
 954: LOAD_GLOBAL          NULL + os
 966: LOAD_ATTR            makedirs
 976: LOAD_FAST            dirname
 978: PRECALL              
 982: CALL                 
 992: POP_TOP              
 994: JUMP_FORWARD         to 1028
 996: PUSH_EXC_INFO        
 998: LOAD_GLOBAL          FileExistsError
1010: CHECK_EXC_MATCH      
1012: POP_JUMP_FORWARD_IF_FALSE to 1020
1014: POP_TOP              
1016: POP_EXCEPT           
1018: JUMP_FORWARD         to 1028
1020: RERAISE              
1022: COPY                 
1024: POP_EXCEPT           
1026: RERAISE              
1028: LOAD_FAST            invalidation_mode
1030: LOAD_GLOBAL          PycInvalidationMode
1042: LOAD_ATTR            TIMESTAMP
1052: COMPARE_OP           ==
1058: POP_JUMP_FORWARD_IF_FALSE to 1194
1060: LOAD_FAST            loader
1062: LOAD_METHOD          path_stats
1084: LOAD_FAST            file
1086: PRECALL              
1090: CALL                 
1100: STORE_FAST           source_stats
1102: LOAD_GLOBAL          importlib
1114: LOAD_ATTR            _bootstrap_external
1124: LOAD_METHOD          _code_to_timestamp_pyc
1146: LOAD_FAST            code
1148: LOAD_FAST            source_stats
1150: LOAD_CONST           'mtime'
1152: BINARY_SUBSCR        
1162: LOAD_FAST            source_stats
1164: LOAD_CONST           'size'
1166: BINARY_SUBSCR        
1176: PRECALL              
1180: CALL                 
1190: STORE_FAST           bytecode
1192: JUMP_FORWARD         to 1350
1194: LOAD_GLOBAL          importlib
1206: LOAD_ATTR            util
1216: LOAD_METHOD          source_hash
1238: LOAD_FAST            source_bytes
1240: PRECALL              
1244: CALL                 
1254: STORE_FAST           source_hash
1256: LOAD_GLOBAL          importlib
1268: LOAD_ATTR            _bootstrap_external
1278: LOAD_METHOD          _code_to_hash_pyc
1300: LOAD_FAST            code
1302: LOAD_FAST            source_hash
1304: LOAD_FAST            invalidation_mode
1306: LOAD_GLOBAL          PycInvalidationMode
1318: LOAD_ATTR            CHECKED_HASH
1328: COMPARE_OP           ==
1334: PRECALL              
1338: CALL                 
1348: STORE_FAST           bytecode
1350: LOAD_GLOBAL          importlib
1362: LOAD_ATTR            _bootstrap_external
1372: LOAD_METHOD          _calc_mode
1394: LOAD_FAST            file
1396: PRECALL              
1400: CALL                 
1410: STORE_FAST           mode
1412: LOAD_GLOBAL          importlib
1424: LOAD_ATTR            _bootstrap_external
1434: LOAD_METHOD          _write_atomic
1456: LOAD_FAST            cfile
1458: LOAD_FAST            bytecode
1460: LOAD_FAST            mode
1462: PRECALL              
1466: CALL                 
1476: POP_TOP              
1478: LOAD_FAST            cfile
1480: RETURN_VALUE         
