# Disassembly for py_compile
# From module file: py_compile

## co_consts:
('Routine to "compile" a .py file to a .pyc file.\n\nThis module has intimate knowledge of the format of .pyc files.\n', 0, None, ('compile', 'main', 'PyCompileError', 'PycInvalidationMode'), <code object PyCompileError at 0x0000024069467C90, file "py_compile.py", line 18>, 'PyCompileError', <code object PycInvalidationMode at 0x0000024069465610, file "py_compile.py", line 66>, 'PycInvalidationMode', <code object _get_default_invalidation_mode at 0x00000240693D2170, file "py_compile.py", line 72>, False, -1, <code object compile at 0x0000024068BBEAF0, file "py_compile.py", line 79>, <code object main at 0x0000024068DD3830, file "py_compile.py", line 176>, '__main__', (None, None, False, -1, None, 0))

## co_names:
('__doc__', 'enum', 'importlib._bootstrap_external', 'importlib', 'importlib.machinery', 'importlib.util', 'os', 'os.path', 'sys', 'traceback', '__all__', 'Exception', 'PyCompileError', 'Enum', 'PycInvalidationMode', '_get_default_invalidation_mode', 'compile', 'main', '__name__')

## bytecode:

   0: RESUME               
   2: LOAD_CONST           'Routine to "compile" a .py file to a .pyc file.\n\nThis module has intimate knowledge of the format of .pyc files.\n'
   4: STORE_NAME           __doc__
   6: LOAD_CONST           0
   8: LOAD_CONST           None
  10: IMPORT_NAME          enum
  12: STORE_NAME           enum
  14: LOAD_CONST           0
  16: LOAD_CONST           None
  18: IMPORT_NAME          importlib._bootstrap_external
  20: STORE_NAME           importlib
  22: LOAD_CONST           0
  24: LOAD_CONST           None
  26: IMPORT_NAME          importlib.machinery
  28: STORE_NAME           importlib
  30: LOAD_CONST           0
  32: LOAD_CONST           None
  34: IMPORT_NAME          importlib.util
  36: STORE_NAME           importlib
  38: LOAD_CONST           0
  40: LOAD_CONST           None
  42: IMPORT_NAME          os
  44: STORE_NAME           os
  46: LOAD_CONST           0
  48: LOAD_CONST           None
  50: IMPORT_NAME          os.path
  52: STORE_NAME           os
  54: LOAD_CONST           0
  56: LOAD_CONST           None
  58: IMPORT_NAME          sys
  60: STORE_NAME           sys
  62: LOAD_CONST           0
  64: LOAD_CONST           None
  66: IMPORT_NAME          traceback
  68: STORE_NAME           traceback
  70: BUILD_LIST           
  72: LOAD_CONST           ('compile', 'main', 'PyCompileError', 'PycInvalidationMode')
  74: LIST_EXTEND          
  76: STORE_NAME           __all__
  78: PUSH_NULL            
  80: LOAD_BUILD_CLASS     
  82: LOAD_CONST           <code object PyCompileError at 0x0000024069467C90, file "py_compile.py", line 18>
  84: MAKE_FUNCTION        
  86: LOAD_CONST           'PyCompileError'
  88: LOAD_NAME            Exception
  90: PRECALL              
  94: CALL                 
 104: STORE_NAME           PyCompileError
 106: PUSH_NULL            
 108: LOAD_BUILD_CLASS     
 110: LOAD_CONST           <code object PycInvalidationMode at 0x0000024069465610, file "py_compile.py", line 66>
 112: MAKE_FUNCTION        
 114: LOAD_CONST           'PycInvalidationMode'
 116: LOAD_NAME            enum
 118: LOAD_ATTR            Enum
 128: PRECALL              
 132: CALL                 
 142: STORE_NAME           PycInvalidationMode
 144: LOAD_CONST           <code object _get_default_invalidation_mode at 0x00000240693D2170, file "py_compile.py", line 72>
 146: MAKE_FUNCTION        
 148: STORE_NAME           _get_default_invalidation_mode
 150: NOP                  
 152: NOP                  
 154: LOAD_CONST           (None, None, False, -1, None, 0)
 156: LOAD_CONST           <code object compile at 0x0000024068BBEAF0, file "py_compile.py", line 79>
 158: MAKE_FUNCTION        defaults
 160: STORE_NAME           compile
 162: LOAD_CONST           <code object main at 0x0000024068DD3830, file "py_compile.py", line 176>
 164: MAKE_FUNCTION        
 166: STORE_NAME           main
 168: LOAD_NAME            __name__
 170: LOAD_CONST           '__main__'
 172: COMPARE_OP           ==
 178: POP_JUMP_FORWARD_IF_FALSE to 204
 180: PUSH_NULL            
 182: LOAD_NAME            main
 184: PRECALL              
 188: CALL                 
 198: POP_TOP              
 200: LOAD_CONST           None
 202: RETURN_VALUE         
 204: LOAD_CONST           None
 206: RETURN_VALUE         
