# Disassembly for mimetypes.read_mime_types
# From module file: mimetypes

## co_consts:
(None, 'utf-8', ('encoding',), True)

## co_names:
('open', 'OSError', 'MimeTypes', 'readfp', 'types_map')

## bytecode:

   0: RESUME               
   2: NOP                  
   4: LOAD_GLOBAL          NULL + open
  16: LOAD_FAST            file
  18: LOAD_CONST           'utf-8'
  20: KW_NAMES             
  22: PRECALL              
  26: CALL                 
  36: STORE_FAST           f
  38: JUMP_FORWARD         to 74
  40: PUSH_EXC_INFO        
  42: LOAD_GLOBAL          OSError
  54: CHECK_EXC_MATCH      
  56: POP_JUMP_FORWARD_IF_FALSE to 66
  58: POP_TOP              
  60: POP_EXCEPT           
  62: LOAD_CONST           None
  64: RETURN_VALUE         
  66: RERAISE              
  68: COPY                 
  70: POP_EXCEPT           
  72: RERAISE              
  74: LOAD_FAST            f
  76: BEFORE_WITH          
  78: POP_TOP              
  80: LOAD_GLOBAL          NULL + MimeTypes
  92: PRECALL              
  96: CALL                 
 106: STORE_FAST           db
 108: LOAD_FAST            db
 110: LOAD_METHOD          readfp
 132: LOAD_FAST            f
 134: LOAD_CONST           True
 136: PRECALL              
 140: CALL                 
 150: POP_TOP              
 152: LOAD_FAST            db
 154: LOAD_ATTR            types_map
 164: LOAD_CONST           True
 166: BINARY_SUBSCR        
 176: SWAP                 
 178: LOAD_CONST           None
 180: LOAD_CONST           None
 182: LOAD_CONST           None
 184: PRECALL              
 188: CALL                 
 198: POP_TOP              
 200: RETURN_VALUE         
 202: PUSH_EXC_INFO        
 204: WITH_EXCEPT_START    
 206: POP_JUMP_FORWARD_IF_TRUE to 216
 208: RERAISE              
 210: COPY                 
 212: POP_EXCEPT           
 214: RERAISE              
 216: POP_TOP              
 218: POP_EXCEPT           
 220: POP_TOP              
 222: POP_TOP              
 224: LOAD_CONST           None
 226: RETURN_VALUE         
