# Disassembly for mimetypes.MimeTypes.guess_all_extensions
# From module file: mimetypes

## co_consts:
("Guess the extensions for a file based on its MIME type.\n\n        Return value is a list of strings giving the possible filename\n        extensions, including the leading dot ('.').  The extension is not\n        guaranteed to have been associated with any particular data stream,\n        but would be mapped to the MIME type `type' by guess_type().\n\n        Optional `strict' argument when false adds a bunch of commonly found,\n        but non-standard types.\n        ", True, False)

## co_names:
('lower', 'list', 'types_map_inv', 'get', 'append')

## bytecode:

   0: RESUME               
   2: LOAD_FAST            type
   4: LOAD_METHOD          lower
  26: PRECALL              
  30: CALL                 
  40: STORE_FAST           type
  42: LOAD_GLOBAL          NULL + list
  54: LOAD_FAST            self
  56: LOAD_ATTR            types_map_inv
  66: LOAD_CONST           True
  68: BINARY_SUBSCR        
  78: LOAD_METHOD          get
 100: LOAD_FAST            type
 102: BUILD_LIST           
 104: PRECALL              
 108: CALL                 
 118: PRECALL              
 122: CALL                 
 132: STORE_FAST           extensions
 134: LOAD_FAST            strict
 136: POP_JUMP_FORWARD_IF_TRUE to 260
 138: LOAD_FAST            self
 140: LOAD_ATTR            types_map_inv
 150: LOAD_CONST           False
 152: BINARY_SUBSCR        
 162: LOAD_METHOD          get
 184: LOAD_FAST            type
 186: BUILD_LIST           
 188: PRECALL              
 192: CALL                 
 202: GET_ITER             
 204: FOR_ITER             to 260
 206: STORE_FAST           ext
 208: LOAD_FAST            ext
 210: LOAD_FAST            extensions
 212: CONTAINS_OP          
 214: POP_JUMP_FORWARD_IF_FALSE to 258
 216: LOAD_FAST            extensions
 218: LOAD_METHOD          append
 240: LOAD_FAST            ext
 242: PRECALL              
 246: CALL                 
 256: POP_TOP              
 258: JUMP_BACKWARD        to 204
 260: LOAD_FAST            extensions
 262: RETURN_VALUE         
