# Disassembly for mimetypes.MimeTypes.readfp
# From module file: mimetypes

## co_consts:
('\n        Read a single mime.types-format file.\n\n        If strict is true, information will be added to\n        list of standard types, else to the list of non-standard\n        types.\n        ', 1, 0, '#', None, '.')

## co_names:
('readline', 'split', 'range', 'len', 'add_type')

## bytecode:

   0: RESUME               
   2: NOP                  
   4: LOAD_FAST            fp
   6: LOAD_METHOD          readline
  28: PRECALL              
  32: CALL                 
  42: STORE_FAST           line
  44: LOAD_FAST            line
  46: POP_JUMP_FORWARD_IF_TRUE to 52
  48: LOAD_CONST           None
  50: RETURN_VALUE         
  52: LOAD_FAST            line
  54: LOAD_METHOD          split
  76: PRECALL              
  80: CALL                 
  90: STORE_FAST           words
  92: LOAD_GLOBAL          NULL + range
 104: LOAD_GLOBAL          NULL + len
 116: LOAD_FAST            words
 118: PRECALL              
 122: CALL                 
 132: PRECALL              
 136: CALL                 
 146: GET_ITER             
 148: FOR_ITER             to 204
 150: STORE_FAST           i
 152: LOAD_FAST            words
 154: LOAD_FAST            i
 156: BINARY_SUBSCR        
 166: LOAD_CONST           0
 168: BINARY_SUBSCR        
 178: LOAD_CONST           '#'
 180: COMPARE_OP           ==
 186: POP_JUMP_FORWARD_IF_FALSE to 202
 188: LOAD_FAST            words
 190: LOAD_FAST            i
 192: LOAD_CONST           None
 194: BUILD_SLICE          
 196: DELETE_SUBSCR        
 198: POP_TOP              
 200: JUMP_FORWARD         to 204
 202: JUMP_BACKWARD        to 148
 204: LOAD_FAST            words
 206: POP_JUMP_FORWARD_IF_TRUE to 210
 208: JUMP_BACKWARD        to 2
 210: LOAD_FAST            words
 212: LOAD_CONST           0
 214: BINARY_SUBSCR        
 224: LOAD_FAST            words
 226: LOAD_CONST           1
 228: LOAD_CONST           None
 230: BUILD_SLICE          
 232: BINARY_SUBSCR        
 242: STORE_FAST           suffixes
 244: STORE_FAST           type
 246: LOAD_FAST            suffixes
 248: GET_ITER             
 250: FOR_ITER             to 308
 252: STORE_FAST           suff
 254: LOAD_FAST            self
 256: LOAD_METHOD          add_type
 278: LOAD_FAST            type
 280: LOAD_CONST           '.'
 282: LOAD_FAST            suff
 284: BINARY_OP            +
 288: LOAD_FAST            strict
 290: PRECALL              
 294: CALL                 
 304: POP_TOP              
 306: JUMP_BACKWARD        to 250
 308: JUMP_BACKWARD        to 4
