# Disassembly for mimetypes.MimeTypes.add_type
# From module file: mimetypes

## co_consts:
('Add a mapping between a type and an extension.\n\n        When the extension is already known, the new\n        type will replace the old one. When the type\n        is already known the extension will be added\n        to the list of known extensions.\n\n        If strict is true, information will be added to\n        list of standard types, else to the list of non-standard\n        types.\n        ', None)

## co_names:
('types_map', 'types_map_inv', 'setdefault', 'append')

## bytecode:

   0: RESUME               
   2: LOAD_FAST            type
   4: LOAD_FAST            self
   6: LOAD_ATTR            types_map
  16: LOAD_FAST            strict
  18: BINARY_SUBSCR        
  28: LOAD_FAST            ext
  30: STORE_SUBSCR         
  34: LOAD_FAST            self
  36: LOAD_ATTR            types_map_inv
  46: LOAD_FAST            strict
  48: BINARY_SUBSCR        
  58: LOAD_METHOD          setdefault
  80: LOAD_FAST            type
  82: BUILD_LIST           
  84: PRECALL              
  88: CALL                 
  98: STORE_FAST           exts
 100: LOAD_FAST            ext
 102: LOAD_FAST            exts
 104: CONTAINS_OP          
 106: POP_JUMP_FORWARD_IF_FALSE to 154
 108: LOAD_FAST            exts
 110: LOAD_METHOD          append
 132: LOAD_FAST            ext
 134: PRECALL              
 138: CALL                 
 148: POP_TOP              
 150: LOAD_CONST           None
 152: RETURN_VALUE         
 154: LOAD_CONST           None
 156: RETURN_VALUE         
