# Disassembly for mimetypes
# From module file: mimetypes

## co_consts:
('Guess the MIME type of a file.\n\nThis module defines two useful functions:\n\nguess_type(url, strict=True) -- guess the MIME type and encoding of a URL.\n\nguess_extension(type, strict=True) -- guess the extension for a given MIME type.\n\nIt also contains the following, for tuning the behavior:\n\nData:\n\nknownfiles -- list of files to parse\ninited -- flag set when init() has been called\nsuffix_map -- dictionary mapping suffixes to suffixes\nencodings_map -- dictionary mapping suffixes to encodings\ntypes_map -- dictionary mapping suffixes to types\n\nFunctions:\n\ninit([files]) -- parse a list of files, default knownfiles (on Windows, the\n  default values are taken from the registry)\nread_mime_types(file) -- parse one file, return a dictionary or None\n', 0, None, ('_mimetypes_read_windows_registry',), ('knownfiles', 'inited', 'MimeTypes', 'guess_type', 'guess_all_extensions', 'guess_extension', 'add_type', 'init', 'read_mime_types', 'suffix_map', 'encodings_map', 'types_map', 'common_types'), ('/etc/mime.types', '/etc/httpd/mime.types', '/etc/httpd/conf/mime.types', '/etc/apache/mime.types', '/etc/apache2/mime.types', '/usr/local/etc/httpd/conf/mime.types', '/usr/local/lib/netscape/mime.types', '/usr/local/etc/httpd/conf/mime.types', '/usr/local/etc/mime.types'), False, <code object MimeTypes at 0x000002406941A550, file "mimetypes.py", line 64>, 'MimeTypes', True, <code object guess_type at 0x000002406941B2D0, file "mimetypes.py", line 287>, <code object guess_all_extensions at 0x0000024069419C50, file "mimetypes.py", line 310>, <code object guess_extension at 0x000002406941AAF0, file "mimetypes.py", line 327>, <code object add_type at 0x000002406941B090, file "mimetypes.py", line 343>, <code object init at 0x0000024068DB5390, file "mimetypes.py", line 360>, <code object read_mime_types at 0x00000240691F5BD0, file "mimetypes.py", line 388>, <code object _default_mime_types at 0x0000024068E13DD0, file "mimetypes.py", line 399>, <code object _main at 0x0000024068C043F0, file "mimetypes.py", line 601>, '__main__', (True,), (None,))

## co_names:
('__doc__', 'os', 'sys', 'posixpath', 'urllib.parse', 'urllib', '_winapi', '_mimetypes_read_windows_registry', 'ImportError', 'winreg', '_winreg', '__all__', 'knownfiles', 'inited', '_db', 'MimeTypes', 'guess_type', 'guess_all_extensions', 'guess_extension', 'add_type', 'init', 'read_mime_types', '_default_mime_types', '_main', '__name__')

## bytecode:

   0: RESUME               
   2: LOAD_CONST           'Guess the MIME type of a file.\n\nThis module defines two useful functions:\n\nguess_type(url, strict=True) -- guess the MIME type and encoding of a URL.\n\nguess_extension(type, strict=True) -- guess the extension for a given MIME type.\n\nIt also contains the following, for tuning the behavior:\n\nData:\n\nknownfiles -- list of files to parse\ninited -- flag set when init() has been called\nsuffix_map -- dictionary mapping suffixes to suffixes\nencodings_map -- dictionary mapping suffixes to encodings\ntypes_map -- dictionary mapping suffixes to types\n\nFunctions:\n\ninit([files]) -- parse a list of files, default knownfiles (on Windows, the\n  default values are taken from the registry)\nread_mime_types(file) -- parse one file, return a dictionary or None\n'
   4: STORE_NAME           __doc__
   6: LOAD_CONST           0
   8: LOAD_CONST           None
  10: IMPORT_NAME          os
  12: STORE_NAME           os
  14: LOAD_CONST           0
  16: LOAD_CONST           None
  18: IMPORT_NAME          sys
  20: STORE_NAME           sys
  22: LOAD_CONST           0
  24: LOAD_CONST           None
  26: IMPORT_NAME          posixpath
  28: STORE_NAME           posixpath
  30: LOAD_CONST           0
  32: LOAD_CONST           None
  34: IMPORT_NAME          urllib.parse
  36: STORE_NAME           urllib
  38: NOP                  
  40: LOAD_CONST           0
  42: LOAD_CONST           ('_mimetypes_read_windows_registry',)
  44: IMPORT_NAME          _winapi
  46: IMPORT_FROM          _mimetypes_read_windows_registry
  48: STORE_NAME           _mimetypes_read_windows_registry
  50: POP_TOP              
  52: JUMP_FORWARD         to 80
  54: PUSH_EXC_INFO        
  56: LOAD_NAME            ImportError
  58: CHECK_EXC_MATCH      
  60: POP_JUMP_FORWARD_IF_FALSE to 72
  62: POP_TOP              
  64: LOAD_CONST           None
  66: STORE_NAME           _mimetypes_read_windows_registry
  68: POP_EXCEPT           
  70: JUMP_FORWARD         to 80
  72: RERAISE              
  74: COPY                 
  76: POP_EXCEPT           
  78: RERAISE              
  80: NOP                  
  82: LOAD_CONST           0
  84: LOAD_CONST           None
  86: IMPORT_NAME          winreg
  88: STORE_NAME           _winreg
  90: JUMP_FORWARD         to 118
  92: PUSH_EXC_INFO        
  94: LOAD_NAME            ImportError
  96: CHECK_EXC_MATCH      
  98: POP_JUMP_FORWARD_IF_FALSE to 110
 100: POP_TOP              
 102: LOAD_CONST           None
 104: STORE_NAME           _winreg
 106: POP_EXCEPT           
 108: JUMP_FORWARD         to 118
 110: RERAISE              
 112: COPY                 
 114: POP_EXCEPT           
 116: RERAISE              
 118: BUILD_LIST           
 120: LOAD_CONST           ('knownfiles', 'inited', 'MimeTypes', 'guess_type', 'guess_all_extensions', 'guess_extension', 'add_type', 'init', 'read_mime_types', 'suffix_map', 'encodings_map', 'types_map', 'common_types')
 122: LIST_EXTEND          
 124: STORE_NAME           __all__
 126: BUILD_LIST           
 128: LOAD_CONST           ('/etc/mime.types', '/etc/httpd/mime.types', '/etc/httpd/conf/mime.types', '/etc/apache/mime.types', '/etc/apache2/mime.types', '/usr/local/etc/httpd/conf/mime.types', '/usr/local/lib/netscape/mime.types', '/usr/local/etc/httpd/conf/mime.types', '/usr/local/etc/mime.types')
 130: LIST_EXTEND          
 132: STORE_NAME           knownfiles
 134: LOAD_CONST           False
 136: STORE_GLOBAL         inited
 138: LOAD_CONST           None
 140: STORE_GLOBAL         _db
 142: PUSH_NULL            
 144: LOAD_BUILD_CLASS     
 146: LOAD_CONST           <code object MimeTypes at 0x000002406941A550, file "mimetypes.py", line 64>
 148: MAKE_FUNCTION        
 150: LOAD_CONST           'MimeTypes'
 152: PRECALL              
 156: CALL                 
 166: STORE_NAME           MimeTypes
 168: LOAD_CONST           (True,)
 170: LOAD_CONST           <code object guess_type at 0x000002406941B2D0, file "mimetypes.py", line 287>
 172: MAKE_FUNCTION        defaults
 174: STORE_NAME           guess_type
 176: LOAD_CONST           (True,)
 178: LOAD_CONST           <code object guess_all_extensions at 0x0000024069419C50, file "mimetypes.py", line 310>
 180: MAKE_FUNCTION        defaults
 182: STORE_NAME           guess_all_extensions
 184: LOAD_CONST           (True,)
 186: LOAD_CONST           <code object guess_extension at 0x000002406941AAF0, file "mimetypes.py", line 327>
 188: MAKE_FUNCTION        defaults
 190: STORE_NAME           guess_extension
 192: LOAD_CONST           (True,)
 194: LOAD_CONST           <code object add_type at 0x000002406941B090, file "mimetypes.py", line 343>
 196: MAKE_FUNCTION        defaults
 198: STORE_NAME           add_type
 200: LOAD_CONST           (None,)
 202: LOAD_CONST           <code object init at 0x0000024068DB5390, file "mimetypes.py", line 360>
 204: MAKE_FUNCTION        defaults
 206: STORE_NAME           init
 208: LOAD_CONST           <code object read_mime_types at 0x00000240691F5BD0, file "mimetypes.py", line 388>
 210: MAKE_FUNCTION        
 212: STORE_NAME           read_mime_types
 214: LOAD_CONST           <code object _default_mime_types at 0x0000024068E13DD0, file "mimetypes.py", line 399>
 216: MAKE_FUNCTION        
 218: STORE_NAME           _default_mime_types
 220: PUSH_NULL            
 222: LOAD_NAME            _default_mime_types
 224: PRECALL              
 228: CALL                 
 238: POP_TOP              
 240: LOAD_CONST           <code object _main at 0x0000024068C043F0, file "mimetypes.py", line 601>
 242: MAKE_FUNCTION        
 244: STORE_NAME           _main
 246: LOAD_NAME            __name__
 248: LOAD_CONST           '__main__'
 250: COMPARE_OP           ==
 256: POP_JUMP_FORWARD_IF_FALSE to 282
 258: PUSH_NULL            
 260: LOAD_NAME            _main
 262: PRECALL              
 266: CALL                 
 276: POP_TOP              
 278: LOAD_CONST           None
 280: RETURN_VALUE         
 282: LOAD_CONST           None
 284: RETURN_VALUE         
