# Disassembly for mimetypes.add_type
# From module file: mimetypes

## co_consts:
('Add a mapping between a type and an extension.\n\n    When the extension is already known, the new\n    type will replace the old one. When the type\n    is already known the extension will be added\n    to the list of known extensions.\n\n    If strict is true, information will be added to\n    list of standard types, else to the list of non-standard\n    types.\n    ',)

## co_names:
('_db', 'init', 'add_type')

## bytecode:

   0: RESUME               
   2: LOAD_GLOBAL          _db
  14: POP_JUMP_FORWARD_IF_NOT_NONE to 44
  16: LOAD_GLOBAL          NULL + init
  28: PRECALL              
  32: CALL                 
  42: POP_TOP              
  44: LOAD_GLOBAL          _db
  56: LOAD_METHOD          add_type
  78: LOAD_FAST            type
  80: LOAD_FAST            ext
  82: LOAD_FAST            strict
  84: PRECALL              
  88: CALL                 
  98: RETURN_VALUE         
