# Disassembly for mimetypes.guess_type
# From module file: mimetypes

## co_consts:
('Guess the type of a file based on its URL.\n\n    Return value is a tuple (type, encoding) where type is None if the\n    type can\'t be guessed (no or unknown suffix) or a string of the\n    form type/subtype, usable for a MIME Content-type header; and\n    encoding is None for no encoding or the name of the program used\n    to encode (e.g. compress or gzip).  The mappings are table\n    driven.  Encoding suffixes are case sensitive; type suffixes are\n    first tried case sensitive, then case insensitive.\n\n    The suffixes .tgz, .taz and .tz (case sensitive!) are all mapped\n    to ".tar.gz".  (This is table-driven too, using the dictionary\n    suffix_map).\n\n    Optional `strict\' argument when false adds a bunch of commonly found, but\n    non-standard types.\n    ',)

## co_names:
('_db', 'init', 'guess_type')

## bytecode:

   0: RESUME               
   2: LOAD_GLOBAL          _db
  14: POP_JUMP_FORWARD_IF_NOT_NONE to 44
  16: LOAD_GLOBAL          NULL + init
  28: PRECALL              
  32: CALL                 
  42: POP_TOP              
  44: LOAD_GLOBAL          _db
  56: LOAD_METHOD          guess_type
  78: LOAD_FAST            url
  80: LOAD_FAST            strict
  82: PRECALL              
  86: CALL                 
  96: RETURN_VALUE         
