# Disassembly for lzma.compress
# From module file: lzma

## co_consts:
("Compress a block of data.\n\n    Refer to LZMACompressor's docstring for a description of the\n    optional arguments *format*, *check*, *preset* and *filters*.\n\n    For incremental compression, use an LZMACompressor instead.\n    ",)

## co_names:
('LZMACompressor', 'compress', 'flush')

## bytecode:

   0: RESUME               
   2: LOAD_GLOBAL          NULL + LZMACompressor
  14: LOAD_FAST            format
  16: LOAD_FAST            check
  18: LOAD_FAST            preset
  20: LOAD_FAST            filters
  22: PRECALL              
  26: CALL                 
  36: STORE_FAST           comp
  38: LOAD_FAST            comp
  40: LOAD_METHOD          compress
  62: LOAD_FAST            data
  64: PRECALL              
  68: CALL                 
  78: LOAD_FAST            comp
  80: LOAD_METHOD          flush
 102: PRECALL              
 106: CALL                 
 116: BINARY_OP            +
 120: RETURN_VALUE         
