# Disassembly for lzma.LZMAFile
# From module file: lzma

## co_consts:
('LZMAFile', 'A file object providing transparent LZMA (de)compression.\n\n    An LZMAFile can act as a wrapper for an existing file object, or\n    refer directly to a named file on disk.\n\n    Note that LZMAFile provides a *binary* file interface - data read\n    is returned as bytes, and data to be written must be given as bytes.\n    ', None, 'r', -1, ('format', 'check', 'preset', 'filters'), <code object __init__ at 0x0000024068D03690, file "lzma.py", line 49>, <code object close at 0x0000024066347D50, file "lzma.py", line 134>, <code object closed at 0x0000024069467BB0, file "lzma.py", line 158>, <code object fileno at 0x000002406941A0D0, file "lzma.py", line 163>, <code object seekable at 0x000002406941A1F0, file "lzma.py", line 168>, <code object readable at 0x000002406944BEE0, file "lzma.py", line 172>, <code object writable at 0x000002406944A780, file "lzma.py", line 177>, <code object peek at 0x000002406941AC10, file "lzma.py", line 182>, <code object read at 0x000002406941A310, file "lzma.py", line 193>, <code object read1 at 0x00000240693AA6F0, file "lzma.py", line 202>, <code object readline at 0x000002406941B3F0, file "lzma.py", line 214>, <code object write at 0x000002406931F630, file "lzma.py", line 224>, <code object seek at 0x000002406941B510, file "lzma.py", line 245>, <code object tell at 0x00000240691F3B40, file "lzma.py", line 263>, (None, 'r'), (-1,))

## co_names:
('__name__', '__module__', '__qualname__', '__doc__', '__init__', 'close', 'property', 'closed', 'fileno', 'seekable', 'readable', 'writable', 'peek', 'read', 'read1', 'readline', 'write', 'io', 'SEEK_SET', 'seek', 'tell')

## bytecode:

   0: RESUME               
   2: LOAD_NAME            __name__
   4: STORE_NAME           __module__
   6: LOAD_CONST           'LZMAFile'
   8: STORE_NAME           __qualname__
  10: LOAD_CONST           'A file object providing transparent LZMA (de)compression.\n\n    An LZMAFile can act as a wrapper for an existing file object, or\n    refer directly to a named file on disk.\n\n    Note that LZMAFile provides a *binary* file interface - data read\n    is returned as bytes, and data to be written must be given as bytes.\n    '
  12: STORE_NAME           __doc__
  14: LOAD_CONST           (None, 'r')
  16: LOAD_CONST           None
  18: LOAD_CONST           -1
  20: LOAD_CONST           None
  22: LOAD_CONST           None
  24: LOAD_CONST           ('format', 'check', 'preset', 'filters')
  26: BUILD_CONST_KEY_MAP  
  28: LOAD_CONST           <code object __init__ at 0x0000024068D03690, file "lzma.py", line 49>
  30: MAKE_FUNCTION        defaults, kwdefaults
  32: STORE_NAME           __init__
  34: LOAD_CONST           <code object close at 0x0000024066347D50, file "lzma.py", line 134>
  36: MAKE_FUNCTION        
  38: STORE_NAME           close
  40: LOAD_NAME            property
  42: LOAD_CONST           <code object closed at 0x0000024069467BB0, file "lzma.py", line 158>
  44: MAKE_FUNCTION        
  46: PRECALL              
  50: CALL                 
  60: STORE_NAME           closed
  62: LOAD_CONST           <code object fileno at 0x000002406941A0D0, file "lzma.py", line 163>
  64: MAKE_FUNCTION        
  66: STORE_NAME           fileno
  68: LOAD_CONST           <code object seekable at 0x000002406941A1F0, file "lzma.py", line 168>
  70: MAKE_FUNCTION        
  72: STORE_NAME           seekable
  74: LOAD_CONST           <code object readable at 0x000002406944BEE0, file "lzma.py", line 172>
  76: MAKE_FUNCTION        
  78: STORE_NAME           readable
  80: LOAD_CONST           <code object writable at 0x000002406944A780, file "lzma.py", line 177>
  82: MAKE_FUNCTION        
  84: STORE_NAME           writable
  86: LOAD_CONST           (-1,)
  88: LOAD_CONST           <code object peek at 0x000002406941AC10, file "lzma.py", line 182>
  90: MAKE_FUNCTION        defaults
  92: STORE_NAME           peek
  94: LOAD_CONST           (-1,)
  96: LOAD_CONST           <code object read at 0x000002406941A310, file "lzma.py", line 193>
  98: MAKE_FUNCTION        defaults
 100: STORE_NAME           read
 102: LOAD_CONST           (-1,)
 104: LOAD_CONST           <code object read1 at 0x00000240693AA6F0, file "lzma.py", line 202>
 106: MAKE_FUNCTION        defaults
 108: STORE_NAME           read1
 110: LOAD_CONST           (-1,)
 112: LOAD_CONST           <code object readline at 0x000002406941B3F0, file "lzma.py", line 214>
 114: MAKE_FUNCTION        defaults
 116: STORE_NAME           readline
 118: LOAD_CONST           <code object write at 0x000002406931F630, file "lzma.py", line 224>
 120: MAKE_FUNCTION        
 122: STORE_NAME           write
 124: LOAD_NAME            io
 126: LOAD_ATTR            SEEK_SET
 136: BUILD_TUPLE          
 138: LOAD_CONST           <code object seek at 0x000002406941B510, file "lzma.py", line 245>
 140: MAKE_FUNCTION        defaults
 142: STORE_NAME           seek
 144: LOAD_CONST           <code object tell at 0x00000240691F3B40, file "lzma.py", line 263>
 146: MAKE_FUNCTION        
 148: STORE_NAME           tell
 150: LOAD_CONST           None
 152: RETURN_VALUE         
