# Disassembly for lzma.decompress
# From module file: lzma

## co_consts:
("Decompress a block of data.\n\n    Refer to LZMADecompressor's docstring for a description of the\n    optional arguments *format*, *check* and *filters*.\n\n    For incremental decompression, use an LZMADecompressor instead.\n    ", True, 'Compressed data ended before the end-of-stream marker was reached', b'')

## co_names:
('LZMADecompressor', 'decompress', 'LZMAError', 'append', 'eof', 'unused_data', 'join')

## bytecode:

   0: RESUME               
   2: BUILD_LIST           
   4: STORE_FAST           results
   6: NOP                  
   8: LOAD_GLOBAL          NULL + LZMADecompressor
  20: LOAD_FAST            format
  22: LOAD_FAST            memlimit
  24: LOAD_FAST            filters
  26: PRECALL              
  30: CALL                 
  40: STORE_FAST           decomp
  42: NOP                  
  44: LOAD_FAST            decomp
  46: LOAD_METHOD          decompress
  68: LOAD_FAST            data
  70: PRECALL              
  74: CALL                 
  84: STORE_FAST           res
  86: JUMP_FORWARD         to 126
  88: PUSH_EXC_INFO        
  90: LOAD_GLOBAL          LZMAError
 102: CHECK_EXC_MATCH      
 104: POP_JUMP_FORWARD_IF_FALSE to 118
 106: POP_TOP              
 108: LOAD_FAST            results
 110: POP_JUMP_FORWARD_IF_FALSE to 116
 112: POP_EXCEPT           
 114: JUMP_FORWARD         to 234
 116: RAISE_VARARGS        
 118: RERAISE              
 120: COPY                 
 122: POP_EXCEPT           
 124: RERAISE              
 126: LOAD_FAST            results
 128: LOAD_METHOD          append
 150: LOAD_FAST            res
 152: PRECALL              
 156: CALL                 
 166: POP_TOP              
 168: LOAD_FAST            decomp
 170: LOAD_ATTR            eof
 180: POP_JUMP_FORWARD_IF_TRUE to 212
 182: LOAD_GLOBAL          NULL + LZMAError
 194: LOAD_CONST           'Compressed data ended before the end-of-stream marker was reached'
 196: PRECALL              
 200: CALL                 
 210: RAISE_VARARGS        
 212: LOAD_FAST            decomp
 214: LOAD_ATTR            unused_data
 224: STORE_FAST           data
 226: LOAD_FAST            data
 228: POP_JUMP_FORWARD_IF_TRUE to 232
 230: JUMP_FORWARD         to 234
 232: JUMP_BACKWARD        to 8
 234: LOAD_CONST           b''
 236: LOAD_METHOD          join
 258: LOAD_FAST            results
 260: PRECALL              
 264: CALL                 
 274: RETURN_VALUE         
