# Disassembly for lzma
# From module file: lzma

## co_consts:
('Interface to the liblzma compression library.\n\nThis module provides a class for reading and writing compressed files,\nclasses for incremental (de)compression, and convenience functions for\none-shot (de)compression.\n\nThese classes and functions support both the XZ and legacy LZMA\ncontainer formats, as well as raw compressed data streams.\n', ('CHECK_NONE', 'CHECK_CRC32', 'CHECK_CRC64', 'CHECK_SHA256', 'CHECK_ID_MAX', 'CHECK_UNKNOWN', 'FILTER_LZMA1', 'FILTER_LZMA2', 'FILTER_DELTA', 'FILTER_X86', 'FILTER_IA64', 'FILTER_ARM', 'FILTER_ARMTHUMB', 'FILTER_POWERPC', 'FILTER_SPARC', 'FORMAT_AUTO', 'FORMAT_XZ', 'FORMAT_ALONE', 'FORMAT_RAW', 'MF_HC3', 'MF_HC4', 'MF_BT2', 'MF_BT3', 'MF_BT4', 'MODE_FAST', 'MODE_NORMAL', 'PRESET_DEFAULT', 'PRESET_EXTREME', 'LZMACompressor', 'LZMADecompressor', 'LZMAFile', 'LZMAError', 'open', 'compress', 'decompress', 'is_check_supported'), 0, None, ('*',), ('_encode_filter_properties', '_decode_filter_properties'), 1, 3, <code object LZMAFile at 0x00000240691C3470, file "lzma.py", line 38>, 'LZMAFile', 'rb', -1, ('format', 'check', 'preset', 'filters', 'encoding', 'errors', 'newline'), <code object open at 0x0000024068E24A20, file "lzma.py", line 271>, <code object compress at 0x00000240693AA0B0, file "lzma.py", line 319>, <code object decompress at 0x00000240691DBC00, file "lzma.py", line 331>, ('rb',))

## co_names:
('__doc__', '__all__', 'builtins', 'io', 'os', '_lzma', '_encode_filter_properties', '_decode_filter_properties', '_compression', '_MODE_CLOSED', '_MODE_READ', '_MODE_WRITE', 'BaseStream', 'LZMAFile', 'open', 'FORMAT_XZ', 'compress', 'FORMAT_AUTO', 'decompress')

## bytecode:

   0: RESUME               
   2: LOAD_CONST           'Interface to the liblzma compression library.\n\nThis module provides a class for reading and writing compressed files,\nclasses for incremental (de)compression, and convenience functions for\none-shot (de)compression.\n\nThese classes and functions support both the XZ and legacy LZMA\ncontainer formats, as well as raw compressed data streams.\n'
   4: STORE_NAME           __doc__
   6: BUILD_LIST           
   8: LOAD_CONST           ('CHECK_NONE', 'CHECK_CRC32', 'CHECK_CRC64', 'CHECK_SHA256', 'CHECK_ID_MAX', 'CHECK_UNKNOWN', 'FILTER_LZMA1', 'FILTER_LZMA2', 'FILTER_DELTA', 'FILTER_X86', 'FILTER_IA64', 'FILTER_ARM', 'FILTER_ARMTHUMB', 'FILTER_POWERPC', 'FILTER_SPARC', 'FORMAT_AUTO', 'FORMAT_XZ', 'FORMAT_ALONE', 'FORMAT_RAW', 'MF_HC3', 'MF_HC4', 'MF_BT2', 'MF_BT3', 'MF_BT4', 'MODE_FAST', 'MODE_NORMAL', 'PRESET_DEFAULT', 'PRESET_EXTREME', 'LZMACompressor', 'LZMADecompressor', 'LZMAFile', 'LZMAError', 'open', 'compress', 'decompress', 'is_check_supported')
  10: LIST_EXTEND          
  12: STORE_NAME           __all__
  14: LOAD_CONST           0
  16: LOAD_CONST           None
  18: IMPORT_NAME          builtins
  20: STORE_NAME           builtins
  22: LOAD_CONST           0
  24: LOAD_CONST           None
  26: IMPORT_NAME          io
  28: STORE_NAME           io
  30: LOAD_CONST           0
  32: LOAD_CONST           None
  34: IMPORT_NAME          os
  36: STORE_NAME           os
  38: LOAD_CONST           0
  40: LOAD_CONST           ('*',)
  42: IMPORT_NAME          _lzma
  44: IMPORT_STAR          
  46: LOAD_CONST           0
  48: LOAD_CONST           ('_encode_filter_properties', '_decode_filter_properties')
  50: IMPORT_NAME          _lzma
  52: IMPORT_FROM          _encode_filter_properties
  54: STORE_NAME           _encode_filter_properties
  56: IMPORT_FROM          _decode_filter_properties
  58: STORE_NAME           _decode_filter_properties
  60: POP_TOP              
  62: LOAD_CONST           0
  64: LOAD_CONST           None
  66: IMPORT_NAME          _compression
  68: STORE_NAME           _compression
  70: LOAD_CONST           0
  72: STORE_NAME           _MODE_CLOSED
  74: LOAD_CONST           1
  76: STORE_NAME           _MODE_READ
  78: LOAD_CONST           3
  80: STORE_NAME           _MODE_WRITE
  82: PUSH_NULL            
  84: LOAD_BUILD_CLASS     
  86: LOAD_CONST           <code object LZMAFile at 0x00000240691C3470, file "lzma.py", line 38>
  88: MAKE_FUNCTION        
  90: LOAD_CONST           'LZMAFile'
  92: LOAD_NAME            _compression
  94: LOAD_ATTR            BaseStream
 104: PRECALL              
 108: CALL                 
 118: STORE_NAME           LZMAFile
 120: LOAD_CONST           ('rb',)
 122: LOAD_CONST           None
 124: LOAD_CONST           -1
 126: LOAD_CONST           None
 128: LOAD_CONST           None
 130: LOAD_CONST           None
 132: LOAD_CONST           None
 134: LOAD_CONST           None
 136: LOAD_CONST           ('format', 'check', 'preset', 'filters', 'encoding', 'errors', 'newline')
 138: BUILD_CONST_KEY_MAP  
 140: LOAD_CONST           <code object open at 0x0000024068E24A20, file "lzma.py", line 271>
 142: MAKE_FUNCTION        defaults, kwdefaults
 144: STORE_NAME           open
 146: LOAD_NAME            FORMAT_XZ
 148: LOAD_CONST           -1
 150: LOAD_CONST           None
 152: LOAD_CONST           None
 154: BUILD_TUPLE          
 156: LOAD_CONST           <code object compress at 0x00000240693AA0B0, file "lzma.py", line 319>
 158: MAKE_FUNCTION        defaults
 160: STORE_NAME           compress
 162: LOAD_NAME            FORMAT_AUTO
 164: LOAD_CONST           None
 166: LOAD_CONST           None
 168: BUILD_TUPLE          
 170: LOAD_CONST           <code object decompress at 0x00000240691DBC00, file "lzma.py", line 331>
 172: MAKE_FUNCTION        defaults
 174: STORE_NAME           decompress
 176: LOAD_CONST           None
 178: RETURN_VALUE         
