# Disassembly for lzma.LZMAFile.readline
# From module file: lzma

## co_consts:
("Read a line of uncompressed bytes from the file.\n\n        The terminating newline (if present) is retained. If size is\n        non-negative, no more than size bytes will be read (in which\n        case the line may be incomplete). Returns b'' if already at EOF.\n        ",)

## co_names:
('_check_can_read', '_buffer', 'readline')

## bytecode:

   0: RESUME               
   2: LOAD_FAST            self
   4: LOAD_METHOD          _check_can_read
  26: PRECALL              
  30: CALL                 
  40: POP_TOP              
  42: LOAD_FAST            self
  44: LOAD_ATTR            _buffer
  54: LOAD_METHOD          readline
  76: LOAD_FAST            size
  78: PRECALL              
  82: CALL                 
  92: RETURN_VALUE         
