# Disassembly for lzma.LZMAFile.__init__
# From module file: lzma

## co_consts:
('Open an LZMA-compressed file in binary mode.\n\n        filename can be either an actual file name (given as a str,\n        bytes, or PathLike object), in which case the named file is\n        opened, or it can be an existing file object to read from or\n        write to.\n\n        mode can be "r" for reading (default), "w" for (over)writing,\n        "x" for creating exclusively, or "a" for appending. These can\n        equivalently be given as "rb", "wb", "xb" and "ab" respectively.\n\n        format specifies the container format to use for the file.\n        If mode is "r", this defaults to FORMAT_AUTO. Otherwise, the\n        default is FORMAT_XZ.\n\n        check specifies the integrity check to use. This argument can\n        only be used when opening a file for writing. For FORMAT_XZ,\n        the default is CHECK_CRC64. FORMAT_ALONE and FORMAT_RAW do not\n        support integrity checks - for these formats, check must be\n        omitted, or be CHECK_NONE.\n\n        When opening a file for reading, the *preset* argument is not\n        meaningful, and should be omitted. The *filters* argument should\n        also be omitted, except when format is FORMAT_RAW (in which case\n        it is required).\n\n        When opening a file for writing, the settings used by the\n        compressor can be specified either as a preset compression\n        level (with the *preset* argument), or in detail as a custom\n        filter chain (with the *filters* argument). For FORMAT_XZ and\n        FORMAT_ALONE, the default is to use the PRESET_DEFAULT preset\n        level. For FORMAT_RAW, the caller must always specify a filter\n        chain; the raw compressor does not support preset compression\n        levels.\n\n        preset (if provided) should be an integer in the range 0-9,\n        optionally OR-ed with the constant PRESET_EXTREME.\n\n        filters (if provided) should be a sequence of dicts. Each dict\n        should have an entry for "id" indicating ID of the filter, plus\n        additional entries for options to the filter.\n        ', None, False, ('r', 'rb'), -1, 'Cannot specify an integrity check when opening a file for reading', 'Cannot specify a preset compression level when opening a file for reading', ('w', 'wb', 'a', 'ab', 'x', 'xb'), ('format', 'check', 'preset', 'filters'), 0, 'Invalid mode: {!r}', 'b', True, 'read', 'write', 'filename must be a str, bytes, file or PathLike object', ('trailing_error', 'format', 'filters'))

## co_names:
('_fp', '_closefp', '_MODE_CLOSED', '_mode', 'ValueError', 'FORMAT_AUTO', '_MODE_READ', 'FORMAT_XZ', '_MODE_WRITE', 'LZMACompressor', '_compressor', '_pos', 'format', 'isinstance', 'str', 'bytes', 'os', 'PathLike', 'builtins', 'open', 'hasattr', 'TypeError', '_compression', 'DecompressReader', 'LZMADecompressor', 'LZMAError', 'io', 'BufferedReader', '_buffer')

## bytecode:

   0: RESUME               
   2: LOAD_CONST           None
   4: LOAD_FAST            self
   6: STORE_ATTR           _fp
  16: LOAD_CONST           False
  18: LOAD_FAST            self
  20: STORE_ATTR           _closefp
  30: LOAD_GLOBAL          _MODE_CLOSED
  42: LOAD_FAST            self
  44: STORE_ATTR           _mode
  54: LOAD_FAST            mode
  56: LOAD_CONST           ('r', 'rb')
  58: CONTAINS_OP          
  60: POP_JUMP_FORWARD_IF_FALSE to 172
  62: LOAD_FAST            check
  64: LOAD_CONST           -1
  66: COMPARE_OP           !=
  72: POP_JUMP_FORWARD_IF_FALSE to 104
  74: LOAD_GLOBAL          NULL + ValueError
  86: LOAD_CONST           'Cannot specify an integrity check when opening a file for reading'
  88: PRECALL              
  92: CALL                 
 102: RAISE_VARARGS        
 104: LOAD_FAST            preset
 106: POP_JUMP_FORWARD_IF_NONE to 138
 108: LOAD_GLOBAL          NULL + ValueError
 120: LOAD_CONST           'Cannot specify a preset compression level when opening a file for reading'
 122: PRECALL              
 126: CALL                 
 136: RAISE_VARARGS        
 138: LOAD_FAST            format
 140: POP_JUMP_FORWARD_IF_NOT_NONE to 156
 142: LOAD_GLOBAL          FORMAT_AUTO
 154: STORE_FAST           format
 156: LOAD_GLOBAL          _MODE_READ
 168: STORE_FAST           mode_code
 170: JUMP_FORWARD         to 344
 172: LOAD_FAST            mode
 174: LOAD_CONST           ('w', 'wb', 'a', 'ab', 'x', 'xb')
 176: CONTAINS_OP          
 178: POP_JUMP_FORWARD_IF_FALSE to 276
 180: LOAD_FAST            format
 182: POP_JUMP_FORWARD_IF_NOT_NONE to 198
 184: LOAD_GLOBAL          FORMAT_XZ
 196: STORE_FAST           format
 198: LOAD_GLOBAL          _MODE_WRITE
 210: STORE_FAST           mode_code
 212: LOAD_GLOBAL          NULL + LZMACompressor
 224: LOAD_FAST            format
 226: LOAD_FAST            check
 228: LOAD_FAST            preset
 230: LOAD_FAST            filters
 232: KW_NAMES             
 234: PRECALL              
 238: CALL                 
 248: LOAD_FAST            self
 250: STORE_ATTR           _compressor
 260: LOAD_CONST           0
 262: LOAD_FAST            self
 264: STORE_ATTR           _pos
 274: JUMP_FORWARD         to 344
 276: LOAD_GLOBAL          NULL + ValueError
 288: LOAD_CONST           'Invalid mode: {!r}'
 290: LOAD_METHOD          format
 312: LOAD_FAST            mode
 314: PRECALL              
 318: CALL                 
 328: PRECALL              
 332: CALL                 
 342: RAISE_VARARGS        
 344: LOAD_GLOBAL          NULL + isinstance
 356: LOAD_FAST            filename
 358: LOAD_GLOBAL          str
 370: LOAD_GLOBAL          bytes
 382: LOAD_GLOBAL          os
 394: LOAD_ATTR            PathLike
 404: BUILD_TUPLE          
 406: PRECALL              
 410: CALL                 
 420: POP_JUMP_FORWARD_IF_FALSE to 522
 422: LOAD_CONST           'b'
 424: LOAD_FAST            mode
 426: CONTAINS_OP          
 428: POP_JUMP_FORWARD_IF_FALSE to 440
 430: LOAD_FAST            mode
 432: LOAD_CONST           'b'
 434: BINARY_OP            +=
 438: STORE_FAST           mode
 440: LOAD_GLOBAL          NULL + builtins
 452: LOAD_ATTR            open
 462: LOAD_FAST            filename
 464: LOAD_FAST            mode
 466: PRECALL              
 470: CALL                 
 480: LOAD_FAST            self
 482: STORE_ATTR           _fp
 492: LOAD_CONST           True
 494: LOAD_FAST            self
 496: STORE_ATTR           _closefp
 506: LOAD_FAST            mode_code
 508: LOAD_FAST            self
 510: STORE_ATTR           _mode
 520: JUMP_FORWARD         to 646
 522: LOAD_GLOBAL          NULL + hasattr
 534: LOAD_FAST            filename
 536: LOAD_CONST           'read'
 538: PRECALL              
 542: CALL                 
 552: POP_JUMP_FORWARD_IF_TRUE to 586
 554: LOAD_GLOBAL          NULL + hasattr
 566: LOAD_FAST            filename
 568: LOAD_CONST           'write'
 570: PRECALL              
 574: CALL                 
 584: POP_JUMP_FORWARD_IF_FALSE to 616
 586: LOAD_FAST            filename
 588: LOAD_FAST            self
 590: STORE_ATTR           _fp
 600: LOAD_FAST            mode_code
 602: LOAD_FAST            self
 604: STORE_ATTR           _mode
 614: JUMP_FORWARD         to 646
 616: LOAD_GLOBAL          NULL + TypeError
 628: LOAD_CONST           'filename must be a str, bytes, file or PathLike object'
 630: PRECALL              
 634: CALL                 
 644: RAISE_VARARGS        
 646: LOAD_FAST            self
 648: LOAD_ATTR            _mode
 658: LOAD_GLOBAL          _MODE_READ
 670: COMPARE_OP           ==
 676: POP_JUMP_FORWARD_IF_FALSE to 812
 678: LOAD_GLOBAL          NULL + _compression
 690: LOAD_ATTR            DecompressReader
 700: LOAD_FAST            self
 702: LOAD_ATTR            _fp
 712: LOAD_GLOBAL          LZMADecompressor
 724: LOAD_GLOBAL          LZMAError
 736: LOAD_FAST            format
 738: LOAD_FAST            filters
 740: KW_NAMES             
 742: PRECALL              
 746: CALL                 
 756: STORE_FAST           raw
 758: LOAD_GLOBAL          NULL + io
 770: LOAD_ATTR            BufferedReader
 780: LOAD_FAST            raw
 782: PRECALL              
 786: CALL                 
 796: LOAD_FAST            self
 798: STORE_ATTR           _buffer
 808: LOAD_CONST           None
 810: RETURN_VALUE         
 812: LOAD_CONST           None
 814: RETURN_VALUE         
