# Disassembly for pprint.PrettyPrinter._pprint_mappingproxy
# From module file: pprint

## co_consts:
(None, 'mappingproxy(', 13, 1, ')')

## co_names:
('write', '_format', 'copy')

## bytecode:

   0: RESUME               
   2: LOAD_FAST            stream
   4: LOAD_METHOD          write
  26: LOAD_CONST           'mappingproxy('
  28: PRECALL              
  32: CALL                 
  42: POP_TOP              
  44: LOAD_FAST            self
  46: LOAD_METHOD          _format
  68: LOAD_FAST            object
  70: LOAD_METHOD          copy
  92: PRECALL              
  96: CALL                 
 106: LOAD_FAST            stream
 108: LOAD_FAST            indent
 110: LOAD_CONST           13
 112: BINARY_OP            +
 116: LOAD_FAST            allowance
 118: LOAD_CONST           1
 120: BINARY_OP            +
 124: LOAD_FAST            context
 126: LOAD_FAST            level
 128: PRECALL              
 132: CALL                 
 142: POP_TOP              
 144: LOAD_FAST            stream
 146: LOAD_METHOD          write
 168: LOAD_CONST           ')'
 170: PRECALL              
 174: CALL                 
 184: POP_TOP              
 186: LOAD_CONST           None
 188: RETURN_VALUE         
