# Disassembly for pprint.PrettyPrinter.isrecursive
# From module file: pprint

## co_consts:
(None, 0, 2)

## co_names:
('format',)

## bytecode:

   0: RESUME               
   2: LOAD_FAST            self
   4: LOAD_METHOD          format
  26: LOAD_FAST            object
  28: BUILD_MAP            
  30: LOAD_CONST           0
  32: LOAD_CONST           0
  34: PRECALL              
  38: CALL                 
  48: LOAD_CONST           2
  50: BINARY_SUBSCR        
  60: RETURN_VALUE         
