# Disassembly for pprint.PrettyPrinter._pprint_tuple
# From module file: pprint

## co_consts:
(None, '(', 1, ',)', ')')

## co_names:
('write', 'len', '_format_items')

## bytecode:

   0: RESUME               
   2: LOAD_FAST            stream
   4: LOAD_METHOD          write
  26: LOAD_CONST           '('
  28: PRECALL              
  32: CALL                 
  42: POP_TOP              
  44: LOAD_GLOBAL          NULL + len
  56: LOAD_FAST            object
  58: PRECALL              
  62: CALL                 
  72: LOAD_CONST           1
  74: COMPARE_OP           ==
  80: POP_JUMP_FORWARD_IF_FALSE to 86
  82: LOAD_CONST           ',)'
  84: JUMP_FORWARD         to 88
  86: LOAD_CONST           ')'
  88: STORE_FAST           endchar
  90: LOAD_FAST            self
  92: LOAD_METHOD          _format_items
 114: LOAD_FAST            object
 116: LOAD_FAST            stream
 118: LOAD_FAST            indent
 120: LOAD_FAST            allowance
 122: LOAD_GLOBAL          NULL + len
 134: LOAD_FAST            endchar
 136: PRECALL              
 140: CALL                 
 150: BINARY_OP            +
 154: LOAD_FAST            context
 156: LOAD_FAST            level
 158: PRECALL              
 162: CALL                 
 172: POP_TOP              
 174: LOAD_FAST            stream
 176: LOAD_METHOD          write
 198: LOAD_FAST            endchar
 200: PRECALL              
 204: CALL                 
 214: POP_TOP              
 216: LOAD_CONST           None
 218: RETURN_VALUE         
