# Disassembly for pprint.pformat
# From module file: pprint

## co_consts:
('Format a Python object into a pretty-printed representation.', ('indent', 'width', 'depth', 'compact', 'sort_dicts', 'underscore_numbers'))

## co_names:
('PrettyPrinter', 'pformat')

## bytecode:

   0: RESUME               
   2: LOAD_GLOBAL          NULL + PrettyPrinter
  14: LOAD_FAST            indent
  16: LOAD_FAST            width
  18: LOAD_FAST            depth
  20: LOAD_FAST            compact
  22: LOAD_FAST            sort_dicts
  24: LOAD_FAST            underscore_numbers
  26: KW_NAMES             
  28: PRECALL              
  32: CALL                 
  42: LOAD_METHOD          pformat
  64: LOAD_FAST            object
  66: PRECALL              
  70: CALL                 
  80: RETURN_VALUE         
