# Disassembly for pprint.PrettyPrinter._repr
# From module file: pprint

## co_consts:
(None, False, True)

## co_names:
('format', 'copy', '_depth', '_readable', '_recursive')

## bytecode:

   0: RESUME               
   2: LOAD_FAST            self
   4: LOAD_METHOD          format
  26: LOAD_FAST            object
  28: LOAD_FAST            context
  30: LOAD_METHOD          copy
  52: PRECALL              
  56: CALL                 
  66: LOAD_FAST            self
  68: LOAD_ATTR            _depth
  78: LOAD_FAST            level
  80: PRECALL              
  84: CALL                 
  94: UNPACK_SEQUENCE      
  98: STORE_FAST           repr
 100: STORE_FAST           readable
 102: STORE_FAST           recursive
 104: LOAD_FAST            readable
 106: POP_JUMP_FORWARD_IF_TRUE to 122
 108: LOAD_CONST           False
 110: LOAD_FAST            self
 112: STORE_ATTR           _readable
 122: LOAD_FAST            recursive
 124: POP_JUMP_FORWARD_IF_FALSE to 140
 126: LOAD_CONST           True
 128: LOAD_FAST            self
 130: STORE_ATTR           _recursive
 140: LOAD_FAST            repr
 142: RETURN_VALUE         
