# Disassembly for pprint.PrettyPrinter.isreadable
# From module file: pprint

## co_consts:
(None, 0)

## co_names:
('format',)

## bytecode:

   0: RESUME               
   2: LOAD_FAST            self
   4: LOAD_METHOD          format
  26: LOAD_FAST            object
  28: BUILD_MAP            
  30: LOAD_CONST           0
  32: LOAD_CONST           0
  34: PRECALL              
  38: CALL                 
  48: UNPACK_SEQUENCE      
  52: STORE_FAST           s
  54: STORE_FAST           readable
  56: STORE_FAST           recursive
  58: LOAD_FAST            readable
  60: JUMP_IF_FALSE_OR_POP to 66
  62: LOAD_FAST            recursive
  64: UNARY_NOT            
  66: RETURN_VALUE         
