# Disassembly for pprint.PrettyPrinter._pprint_str
# From module file: pprint

## co_consts:
(None, True, 1, '\\S*\\s*', -1, '', '(', 0, '\n', ' ', ')')

## co_names:
('write', 'len', 'repr', 'splitlines', '_width', 'enumerate', 'append', 're', 'findall', 'pop')

## bytecode:

   0: RESUME               
   2: LOAD_FAST            stream
   4: LOAD_ATTR            write
  14: STORE_FAST           write
  16: LOAD_GLOBAL          NULL + len
  28: LOAD_FAST            object
  30: PRECALL              
  34: CALL                 
  44: POP_JUMP_FORWARD_IF_TRUE to 98
  46: PUSH_NULL            
  48: LOAD_FAST            write
  50: LOAD_GLOBAL          NULL + repr
  62: LOAD_FAST            object
  64: PRECALL              
  68: CALL                 
  78: PRECALL              
  82: CALL                 
  92: POP_TOP              
  94: LOAD_CONST           None
  96: RETURN_VALUE         
  98: BUILD_LIST           
 100: STORE_FAST           chunks
 102: LOAD_FAST            object
 104: LOAD_METHOD          splitlines
 126: LOAD_CONST           True
 128: PRECALL              
 132: CALL                 
 142: STORE_FAST           lines
 144: LOAD_FAST            level
 146: LOAD_CONST           1
 148: COMPARE_OP           ==
 154: POP_JUMP_FORWARD_IF_FALSE to 176
 156: LOAD_FAST            indent
 158: LOAD_CONST           1
 160: BINARY_OP            +=
 164: STORE_FAST           indent
 166: LOAD_FAST            allowance
 168: LOAD_CONST           1
 170: BINARY_OP            +=
 174: STORE_FAST           allowance
 176: LOAD_FAST            self
 178: LOAD_ATTR            _width
 188: LOAD_FAST            indent
 190: BINARY_OP            -
 194: COPY                 
 196: STORE_FAST           max_width1
 198: STORE_FAST           max_width
 200: LOAD_GLOBAL          NULL + enumerate
 212: LOAD_FAST            lines
 214: PRECALL              
 218: CALL                 
 228: GET_ITER             
 230: EXTENDED_ARG         
 232: FOR_ITER             to 898
 234: UNPACK_SEQUENCE      
 238: STORE_FAST           i
 240: STORE_FAST           line
 242: LOAD_GLOBAL          NULL + repr
 254: LOAD_FAST            line
 256: PRECALL              
 260: CALL                 
 270: STORE_FAST           rep
 272: LOAD_FAST            i
 274: LOAD_GLOBAL          NULL + len
 286: LOAD_FAST            lines
 288: PRECALL              
 292: CALL                 
 302: LOAD_CONST           1
 304: BINARY_OP            -
 308: COMPARE_OP           ==
 314: POP_JUMP_FORWARD_IF_FALSE to 326
 316: LOAD_FAST            max_width1
 318: LOAD_FAST            allowance
 320: BINARY_OP            -=
 324: STORE_FAST           max_width1
 326: LOAD_GLOBAL          NULL + len
 338: LOAD_FAST            rep
 340: PRECALL              
 344: CALL                 
 354: LOAD_FAST            max_width1
 356: COMPARE_OP           <=
 362: POP_JUMP_FORWARD_IF_FALSE to 408
 364: LOAD_FAST            chunks
 366: LOAD_METHOD          append
 388: LOAD_FAST            rep
 390: PRECALL              
 394: CALL                 
 404: POP_TOP              
 406: JUMP_BACKWARD        to 230
 408: LOAD_GLOBAL          NULL + re
 420: LOAD_ATTR            findall
 430: LOAD_CONST           '\\S*\\s*'
 432: LOAD_FAST            line
 434: PRECALL              
 438: CALL                 
 448: STORE_FAST           parts
 450: LOAD_FAST            parts
 452: POP_JUMP_FORWARD_IF_TRUE to 458
 454: LOAD_ASSERTION_ERROR 
 456: RAISE_VARARGS        
 458: LOAD_FAST            parts
 460: LOAD_CONST           -1
 462: BINARY_SUBSCR        
 472: POP_JUMP_FORWARD_IF_FALSE to 478
 474: LOAD_ASSERTION_ERROR 
 476: RAISE_VARARGS        
 478: LOAD_FAST            parts
 480: LOAD_METHOD          pop
 502: PRECALL              
 506: CALL                 
 516: POP_TOP              
 518: LOAD_FAST            max_width
 520: STORE_FAST           max_width2
 522: LOAD_CONST           ''
 524: STORE_FAST           current
 526: LOAD_GLOBAL          NULL + enumerate
 538: LOAD_FAST            parts
 540: PRECALL              
 544: CALL                 
 554: GET_ITER             
 556: FOR_ITER             to 822
 558: UNPACK_SEQUENCE      
 562: STORE_FAST           j
 564: STORE_FAST           part
 566: LOAD_FAST            current
 568: LOAD_FAST            part
 570: BINARY_OP            +
 574: STORE_FAST           candidate
 576: LOAD_FAST            j
 578: LOAD_GLOBAL          NULL + len
 590: LOAD_FAST            parts
 592: PRECALL              
 596: CALL                 
 606: LOAD_CONST           1
 608: BINARY_OP            -
 612: COMPARE_OP           ==
 618: POP_JUMP_FORWARD_IF_FALSE to 674
 620: LOAD_FAST            i
 622: LOAD_GLOBAL          NULL + len
 634: LOAD_FAST            lines
 636: PRECALL              
 640: CALL                 
 650: LOAD_CONST           1
 652: BINARY_OP            -
 656: COMPARE_OP           ==
 662: POP_JUMP_FORWARD_IF_FALSE to 674
 664: LOAD_FAST            max_width2
 666: LOAD_FAST            allowance
 668: BINARY_OP            -=
 672: STORE_FAST           max_width2
 674: LOAD_GLOBAL          NULL + len
 686: LOAD_GLOBAL          NULL + repr
 698: LOAD_FAST            candidate
 700: PRECALL              
 704: CALL                 
 714: PRECALL              
 718: CALL                 
 728: LOAD_FAST            max_width2
 730: COMPARE_OP           >
 736: POP_JUMP_FORWARD_IF_FALSE to 816
 738: LOAD_FAST            current
 740: POP_JUMP_FORWARD_IF_FALSE to 810
 742: LOAD_FAST            chunks
 744: LOAD_METHOD          append
 766: LOAD_GLOBAL          NULL + repr
 778: LOAD_FAST            current
 780: PRECALL              
 784: CALL                 
 794: PRECALL              
 798: CALL                 
 808: POP_TOP              
 810: LOAD_FAST            part
 812: STORE_FAST           current
 814: JUMP_BACKWARD        to 556
 816: LOAD_FAST            candidate
 818: STORE_FAST           current
 820: JUMP_BACKWARD        to 556
 822: LOAD_FAST            current
 824: POP_JUMP_FORWARD_IF_FALSE to 894
 826: LOAD_FAST            chunks
 828: LOAD_METHOD          append
 850: LOAD_GLOBAL          NULL + repr
 862: LOAD_FAST            current
 864: PRECALL              
 868: CALL                 
 878: PRECALL              
 882: CALL                 
 892: POP_TOP              
 894: EXTENDED_ARG         
 896: JUMP_BACKWARD        to 230
 898: LOAD_GLOBAL          NULL + len
 910: LOAD_FAST            chunks
 912: PRECALL              
 916: CALL                 
 926: LOAD_CONST           1
 928: COMPARE_OP           ==
 934: POP_JUMP_FORWARD_IF_FALSE to 962
 936: PUSH_NULL            
 938: LOAD_FAST            write
 940: LOAD_FAST            rep
 942: PRECALL              
 946: CALL                 
 956: POP_TOP              
 958: LOAD_CONST           None
 960: RETURN_VALUE         
 962: LOAD_FAST            level
 964: LOAD_CONST           1
 966: COMPARE_OP           ==
 972: POP_JUMP_FORWARD_IF_FALSE to 996
 974: PUSH_NULL            
 976: LOAD_FAST            write
 978: LOAD_CONST           '('
 980: PRECALL              
 984: CALL                 
 994: POP_TOP              
 996: LOAD_GLOBAL          NULL + enumerate
1008: LOAD_FAST            chunks
1010: PRECALL              
1014: CALL                 
1024: GET_ITER             
1026: FOR_ITER             to 1106
1028: UNPACK_SEQUENCE      
1032: STORE_FAST           i
1034: STORE_FAST           rep
1036: LOAD_FAST            i
1038: LOAD_CONST           0
1040: COMPARE_OP           >
1046: POP_JUMP_FORWARD_IF_FALSE to 1082
1048: PUSH_NULL            
1050: LOAD_FAST            write
1052: LOAD_CONST           '\n'
1054: LOAD_CONST           ' '
1056: LOAD_FAST            indent
1058: BINARY_OP            *
1062: BINARY_OP            +
1066: PRECALL              
1070: CALL                 
1080: POP_TOP              
1082: PUSH_NULL            
1084: LOAD_FAST            write
1086: LOAD_FAST            rep
1088: PRECALL              
1092: CALL                 
1102: POP_TOP              
1104: JUMP_BACKWARD        to 1026
1106: LOAD_FAST            level
1108: LOAD_CONST           1
1110: COMPARE_OP           ==
1116: POP_JUMP_FORWARD_IF_FALSE to 1144
1118: PUSH_NULL            
1120: LOAD_FAST            write
1122: LOAD_CONST           ')'
1124: PRECALL              
1128: CALL                 
1138: POP_TOP              
1140: LOAD_CONST           None
1142: RETURN_VALUE         
1144: LOAD_CONST           None
1146: RETURN_VALUE         
