# Disassembly for pprint.PrettyPrinter._pprint_dict
# From module file: pprint

## co_consts:
(None, '{', 1, ' ', ('key',), '}')

## co_names:
('write', '_indent_per_level', 'len', '_sort_dicts', 'sorted', 'items', '_safe_tuple', '_format_dict_items')

## bytecode:

   0: RESUME               
   2: LOAD_FAST            stream
   4: LOAD_ATTR            write
  14: STORE_FAST           write
  16: PUSH_NULL            
  18: LOAD_FAST            write
  20: LOAD_CONST           '{'
  22: PRECALL              
  26: CALL                 
  36: POP_TOP              
  38: LOAD_FAST            self
  40: LOAD_ATTR            _indent_per_level
  50: LOAD_CONST           1
  52: COMPARE_OP           >
  58: POP_JUMP_FORWARD_IF_FALSE to 104
  60: PUSH_NULL            
  62: LOAD_FAST            write
  64: LOAD_FAST            self
  66: LOAD_ATTR            _indent_per_level
  76: LOAD_CONST           1
  78: BINARY_OP            -
  82: LOAD_CONST           ' '
  84: BINARY_OP            *
  88: PRECALL              
  92: CALL                 
 102: POP_TOP              
 104: LOAD_GLOBAL          NULL + len
 116: LOAD_FAST            object
 118: PRECALL              
 122: CALL                 
 132: STORE_FAST           length
 134: LOAD_FAST            length
 136: POP_JUMP_FORWARD_IF_FALSE to 332
 138: LOAD_FAST            self
 140: LOAD_ATTR            _sort_dicts
 150: POP_JUMP_FORWARD_IF_FALSE to 234
 152: LOAD_GLOBAL          NULL + sorted
 164: LOAD_FAST            object
 166: LOAD_METHOD          items
 188: PRECALL              
 192: CALL                 
 202: LOAD_GLOBAL          _safe_tuple
 214: KW_NAMES             
 216: PRECALL              
 220: CALL                 
 230: STORE_FAST           items
 232: JUMP_FORWARD         to 274
 234: LOAD_FAST            object
 236: LOAD_METHOD          items
 258: PRECALL              
 262: CALL                 
 272: STORE_FAST           items
 274: LOAD_FAST            self
 276: LOAD_METHOD          _format_dict_items
 298: LOAD_FAST            items
 300: LOAD_FAST            stream
 302: LOAD_FAST            indent
 304: LOAD_FAST            allowance
 306: LOAD_CONST           1
 308: BINARY_OP            +
 312: LOAD_FAST            context
 314: LOAD_FAST            level
 316: PRECALL              
 320: CALL                 
 330: POP_TOP              
 332: PUSH_NULL            
 334: LOAD_FAST            write
 336: LOAD_CONST           '}'
 338: PRECALL              
 342: CALL                 
 352: POP_TOP              
 354: LOAD_CONST           None
 356: RETURN_VALUE         
