# Disassembly for pprint.PrettyPrinter.__init__
# From module file: pprint

## co_consts:
('Handle pretty printing operations onto a stream using a set of\n        configured parameters.\n\n        indent\n            Number of spaces to indent for each level of nesting.\n\n        width\n            Attempted maximum number of columns in the output.\n\n        depth\n            The maximum depth to print out nested structures.\n\n        stream\n            The desired output stream.  If omitted (or false), the standard\n            output stream available at construction will be used.\n\n        compact\n            If true, several items will be combined in one line.\n\n        sort_dicts\n            If true, dict keys are sorted.\n\n        ', 0, 'indent must be >= 0', None, 'depth must be > 0', 'width must be != 0')

## co_names:
('int', 'ValueError', '_depth', '_indent_per_level', '_width', '_stream', '_sys', 'stdout', 'bool', '_compact', '_sort_dicts', '_underscore_numbers')

## bytecode:

   0: RESUME               
   2: LOAD_GLOBAL          NULL + int
  14: LOAD_FAST            indent
  16: PRECALL              
  20: CALL                 
  30: STORE_FAST           indent
  32: LOAD_GLOBAL          NULL + int
  44: LOAD_FAST            width
  46: PRECALL              
  50: CALL                 
  60: STORE_FAST           width
  62: LOAD_FAST            indent
  64: LOAD_CONST           0
  66: COMPARE_OP           <
  72: POP_JUMP_FORWARD_IF_FALSE to 104
  74: LOAD_GLOBAL          NULL + ValueError
  86: LOAD_CONST           'indent must be >= 0'
  88: PRECALL              
  92: CALL                 
 102: RAISE_VARARGS        
 104: LOAD_FAST            depth
 106: POP_JUMP_FORWARD_IF_NONE to 150
 108: LOAD_FAST            depth
 110: LOAD_CONST           0
 112: COMPARE_OP           <=
 118: POP_JUMP_FORWARD_IF_FALSE to 150
 120: LOAD_GLOBAL          NULL + ValueError
 132: LOAD_CONST           'depth must be > 0'
 134: PRECALL              
 138: CALL                 
 148: RAISE_VARARGS        
 150: LOAD_FAST            width
 152: POP_JUMP_FORWARD_IF_TRUE to 184
 154: LOAD_GLOBAL          NULL + ValueError
 166: LOAD_CONST           'width must be != 0'
 168: PRECALL              
 172: CALL                 
 182: RAISE_VARARGS        
 184: LOAD_FAST            depth
 186: LOAD_FAST            self
 188: STORE_ATTR           _depth
 198: LOAD_FAST            indent
 200: LOAD_FAST            self
 202: STORE_ATTR           _indent_per_level
 212: LOAD_FAST            width
 214: LOAD_FAST            self
 216: STORE_ATTR           _width
 226: LOAD_FAST            stream
 228: POP_JUMP_FORWARD_IF_NONE to 246
 230: LOAD_FAST            stream
 232: LOAD_FAST            self
 234: STORE_ATTR           _stream
 244: JUMP_FORWARD         to 280
 246: LOAD_GLOBAL          _sys
 258: LOAD_ATTR            stdout
 268: LOAD_FAST            self
 270: STORE_ATTR           _stream
 280: LOAD_GLOBAL          NULL + bool
 292: LOAD_FAST            compact
 294: PRECALL              
 298: CALL                 
 308: LOAD_FAST            self
 310: STORE_ATTR           _compact
 320: LOAD_FAST            sort_dicts
 322: LOAD_FAST            self
 324: STORE_ATTR           _sort_dicts
 334: LOAD_FAST            underscore_numbers
 336: LOAD_FAST            self
 338: STORE_ATTR           _underscore_numbers
 348: LOAD_CONST           None
 350: RETURN_VALUE         
