# Disassembly for pprint.PrettyPrinter._format_dict_items
# From module file: pprint

## co_consts:
(None, ',\n', ' ', 1, ': ', 2)

## co_names:
('write', '_indent_per_level', 'len', 'enumerate', '_repr', '_format')

## bytecode:

   0: RESUME               
   2: LOAD_FAST            stream
   4: LOAD_ATTR            write
  14: STORE_FAST           write
  16: LOAD_FAST            indent
  18: LOAD_FAST            self
  20: LOAD_ATTR            _indent_per_level
  30: BINARY_OP            +=
  34: STORE_FAST           indent
  36: LOAD_CONST           ',\n'
  38: LOAD_CONST           ' '
  40: LOAD_FAST            indent
  42: BINARY_OP            *
  46: BINARY_OP            +
  50: STORE_FAST           delimnl
  52: LOAD_GLOBAL          NULL + len
  64: LOAD_FAST            items
  66: PRECALL              
  70: CALL                 
  80: LOAD_CONST           1
  82: BINARY_OP            -
  86: STORE_FAST           last_index
  88: LOAD_GLOBAL          NULL + enumerate
 100: LOAD_FAST            items
 102: PRECALL              
 106: CALL                 
 116: GET_ITER             
 118: FOR_ITER             to 362
 120: UNPACK_SEQUENCE      
 124: STORE_FAST           i
 126: UNPACK_SEQUENCE      
 130: STORE_FAST           key
 132: STORE_FAST           ent
 134: LOAD_FAST            i
 136: LOAD_FAST            last_index
 138: COMPARE_OP           ==
 144: STORE_FAST           last
 146: LOAD_FAST            self
 148: LOAD_METHOD          _repr
 170: LOAD_FAST            key
 172: LOAD_FAST            context
 174: LOAD_FAST            level
 176: PRECALL              
 180: CALL                 
 190: STORE_FAST           rep
 192: PUSH_NULL            
 194: LOAD_FAST            write
 196: LOAD_FAST            rep
 198: PRECALL              
 202: CALL                 
 212: POP_TOP              
 214: PUSH_NULL            
 216: LOAD_FAST            write
 218: LOAD_CONST           ': '
 220: PRECALL              
 224: CALL                 
 234: POP_TOP              
 236: LOAD_FAST            self
 238: LOAD_METHOD          _format
 260: LOAD_FAST            ent
 262: LOAD_FAST            stream
 264: LOAD_FAST            indent
 266: LOAD_GLOBAL          NULL + len
 278: LOAD_FAST            rep
 280: PRECALL              
 284: CALL                 
 294: BINARY_OP            +
 298: LOAD_CONST           2
 300: BINARY_OP            +
 304: LOAD_FAST            last
 306: POP_JUMP_FORWARD_IF_FALSE to 312
 308: LOAD_FAST            allowance
 310: JUMP_FORWARD         to 314
 312: LOAD_CONST           1
 314: LOAD_FAST            context
 316: LOAD_FAST            level
 318: PRECALL              
 322: CALL                 
 332: POP_TOP              
 334: LOAD_FAST            last
 336: POP_JUMP_FORWARD_IF_TRUE to 360
 338: PUSH_NULL            
 340: LOAD_FAST            write
 342: LOAD_FAST            delimnl
 344: PRECALL              
 348: CALL                 
 358: POP_TOP              
 360: JUMP_BACKWARD        to 118
 362: LOAD_CONST           None
 364: RETURN_VALUE         
