# Disassembly for pprint.PrettyPrinter._pprint_bytes
# From module file: pprint

## co_consts:
(None, 4, 1, '(', '', '\n', ' ', ')')

## co_names:
('write', 'len', 'repr', '_wrap_bytes_repr', '_width')

## bytecode:

   0: RESUME               
   2: LOAD_FAST            stream
   4: LOAD_ATTR            write
  14: STORE_FAST           write
  16: LOAD_GLOBAL          NULL + len
  28: LOAD_FAST            object
  30: PRECALL              
  34: CALL                 
  44: LOAD_CONST           4
  46: COMPARE_OP           <=
  52: POP_JUMP_FORWARD_IF_FALSE to 106
  54: PUSH_NULL            
  56: LOAD_FAST            write
  58: LOAD_GLOBAL          NULL + repr
  70: LOAD_FAST            object
  72: PRECALL              
  76: CALL                 
  86: PRECALL              
  90: CALL                 
 100: POP_TOP              
 102: LOAD_CONST           None
 104: RETURN_VALUE         
 106: LOAD_FAST            level
 108: LOAD_CONST           1
 110: COMPARE_OP           ==
 116: STORE_FAST           parens
 118: LOAD_FAST            parens
 120: POP_JUMP_FORWARD_IF_FALSE to 164
 122: LOAD_FAST            indent
 124: LOAD_CONST           1
 126: BINARY_OP            +=
 130: STORE_FAST           indent
 132: LOAD_FAST            allowance
 134: LOAD_CONST           1
 136: BINARY_OP            +=
 140: STORE_FAST           allowance
 142: PUSH_NULL            
 144: LOAD_FAST            write
 146: LOAD_CONST           '('
 148: PRECALL              
 152: CALL                 
 162: POP_TOP              
 164: LOAD_CONST           ''
 166: STORE_FAST           delim
 168: LOAD_GLOBAL          NULL + _wrap_bytes_repr
 180: LOAD_FAST            object
 182: LOAD_FAST            self
 184: LOAD_ATTR            _width
 194: LOAD_FAST            indent
 196: BINARY_OP            -
 200: LOAD_FAST            allowance
 202: PRECALL              
 206: CALL                 
 216: GET_ITER             
 218: FOR_ITER             to 288
 220: STORE_FAST           rep
 222: PUSH_NULL            
 224: LOAD_FAST            write
 226: LOAD_FAST            delim
 228: PRECALL              
 232: CALL                 
 242: POP_TOP              
 244: PUSH_NULL            
 246: LOAD_FAST            write
 248: LOAD_FAST            rep
 250: PRECALL              
 254: CALL                 
 264: POP_TOP              
 266: LOAD_FAST            delim
 268: POP_JUMP_FORWARD_IF_TRUE to 286
 270: LOAD_CONST           '\n'
 272: LOAD_CONST           ' '
 274: LOAD_FAST            indent
 276: BINARY_OP            *
 280: BINARY_OP            +
 284: STORE_FAST           delim
 286: JUMP_BACKWARD        to 218
 288: LOAD_FAST            parens
 290: POP_JUMP_FORWARD_IF_FALSE to 318
 292: PUSH_NULL            
 294: LOAD_FAST            write
 296: LOAD_CONST           ')'
 298: PRECALL              
 302: CALL                 
 312: POP_TOP              
 314: LOAD_CONST           None
 316: RETURN_VALUE         
 318: LOAD_CONST           None
 320: RETURN_VALUE         
