# Disassembly for pprint.PrettyPrinter.pprint
# From module file: pprint

## co_consts:
(None, 0, '\n')

## co_names:
('_stream', '_format', 'write')

## bytecode:

   0: RESUME               
   2: LOAD_FAST            self
   4: LOAD_ATTR            _stream
  14: POP_JUMP_FORWARD_IF_NONE to 134
  16: LOAD_FAST            self
  18: LOAD_METHOD          _format
  40: LOAD_FAST            object
  42: LOAD_FAST            self
  44: LOAD_ATTR            _stream
  54: LOAD_CONST           0
  56: LOAD_CONST           0
  58: BUILD_MAP            
  60: LOAD_CONST           0
  62: PRECALL              
  66: CALL                 
  76: POP_TOP              
  78: LOAD_FAST            self
  80: LOAD_ATTR            _stream
  90: LOAD_METHOD          write
 112: LOAD_CONST           '\n'
 114: PRECALL              
 118: CALL                 
 128: POP_TOP              
 130: LOAD_CONST           None
 132: RETURN_VALUE         
 134: LOAD_CONST           None
 136: RETURN_VALUE         
