# Disassembly for pprint.pprint
# From module file: pprint

## co_consts:
('Pretty-print a Python object to a stream [default is sys.stdout].', ('stream', 'indent', 'width', 'depth', 'compact', 'sort_dicts', 'underscore_numbers'), None)

## co_names:
('PrettyPrinter', 'pprint')

## bytecode:

   0: RESUME               
   2: LOAD_GLOBAL          NULL + PrettyPrinter
  14: LOAD_FAST            stream
  16: LOAD_FAST            indent
  18: LOAD_FAST            width
  20: LOAD_FAST            depth
  22: LOAD_FAST            compact
  24: LOAD_FAST            sort_dicts
  26: LOAD_FAST            underscore_numbers
  28: KW_NAMES             
  30: PRECALL              
  34: CALL                 
  44: STORE_FAST           printer
  46: LOAD_FAST            printer
  48: LOAD_METHOD          pprint
  70: LOAD_FAST            object
  72: PRECALL              
  76: CALL                 
  86: POP_TOP              
  88: LOAD_CONST           None
  90: RETURN_VALUE         
