# Disassembly for importlib.metadata.pass_none.wrapper
# From module file: importlib.metadata._functools

## co_consts:
(None,)

## co_names:
()

## bytecode:

   0: COPY_FREE_VARS       
   2: RESUME               
   4: LOAD_FAST            param
   6: POP_JUMP_FORWARD_IF_NONE to 32
   8: PUSH_NULL            
  10: LOAD_DEREF           func
  12: LOAD_FAST            param
  14: BUILD_LIST           
  16: LOAD_FAST            args
  18: LIST_EXTEND          
  20: LIST_TO_TUPLE        
  22: BUILD_MAP            
  24: LOAD_FAST            kwargs
  26: DICT_MERGE           
  28: CALL_FUNCTION_EX     
  30: RETURN_VALUE         
  32: LOAD_CONST           None
  34: RETURN_VALUE         
