# Disassembly for importlib.metadata.unique_everseen
# From module file: importlib.metadata._itertools

## co_consts:
('List unique elements, preserving order. Remember all elements ever seen.', None)

## co_names:
('set', 'add', 'filterfalse', '__contains__')

## bytecode:

   0: RETURN_GENERATOR     
   2: POP_TOP              
   4: RESUME               
   6: LOAD_GLOBAL          NULL + set
  18: PRECALL              
  22: CALL                 
  32: STORE_FAST           seen
  34: LOAD_FAST            seen
  36: LOAD_ATTR            add
  46: STORE_FAST           seen_add
  48: LOAD_FAST            key
  50: POP_JUMP_FORWARD_IF_NOT_NONE to 134
  52: LOAD_GLOBAL          NULL + filterfalse
  64: LOAD_FAST            seen
  66: LOAD_ATTR            __contains__
  76: LOAD_FAST            iterable
  78: PRECALL              
  82: CALL                 
  92: GET_ITER             
  94: FOR_ITER             to 130
  96: STORE_FAST           element
  98: PUSH_NULL            
 100: LOAD_FAST            seen_add
 102: LOAD_FAST            element
 104: PRECALL              
 108: CALL                 
 118: POP_TOP              
 120: LOAD_FAST            element
 122: YIELD_VALUE          
 124: RESUME               
 126: POP_TOP              
 128: JUMP_BACKWARD        to 94
 130: LOAD_CONST           None
 132: RETURN_VALUE         
 134: LOAD_FAST            iterable
 136: GET_ITER             
 138: FOR_ITER             to 204
 140: STORE_FAST           element
 142: PUSH_NULL            
 144: LOAD_FAST            key
 146: LOAD_FAST            element
 148: PRECALL              
 152: CALL                 
 162: STORE_FAST           k
 164: LOAD_FAST            k
 166: LOAD_FAST            seen
 168: CONTAINS_OP          
 170: POP_JUMP_FORWARD_IF_FALSE to 202
 172: PUSH_NULL            
 174: LOAD_FAST            seen_add
 176: LOAD_FAST            k
 178: PRECALL              
 182: CALL                 
 192: POP_TOP              
 194: LOAD_FAST            element
 196: YIELD_VALUE          
 198: RESUME               
 200: POP_TOP              
 202: JUMP_BACKWARD        to 138
 204: LOAD_CONST           None
 206: RETURN_VALUE         
