# Disassembly for importlib.metadata.Message.json.transform
# From module file: importlib.metadata._adapters

## co_consts:
(None, 'Keywords', '\\s+', '-', '_')

## co_names:
('multiple_use_keys', 'get_all', 're', 'split', 'lower', 'replace')

## bytecode:

   0: COPY_FREE_VARS       
   2: RESUME               
   4: LOAD_FAST            key
   6: LOAD_DEREF           self
   8: LOAD_ATTR            multiple_use_keys
  18: CONTAINS_OP          
  20: POP_JUMP_FORWARD_IF_FALSE to 64
  22: LOAD_DEREF           self
  24: LOAD_METHOD          get_all
  46: LOAD_FAST            key
  48: PRECALL              
  52: CALL                 
  62: JUMP_FORWARD         to 78
  64: LOAD_DEREF           self
  66: LOAD_FAST            key
  68: BINARY_SUBSCR        
  78: STORE_FAST           value
  80: LOAD_FAST            key
  82: LOAD_CONST           'Keywords'
  84: COMPARE_OP           ==
  90: POP_JUMP_FORWARD_IF_FALSE to 134
  92: LOAD_GLOBAL          NULL + re
 104: LOAD_ATTR            split
 114: LOAD_CONST           '\\s+'
 116: LOAD_FAST            value
 118: PRECALL              
 122: CALL                 
 132: STORE_FAST           value
 134: LOAD_FAST            key
 136: LOAD_METHOD          lower
 158: PRECALL              
 162: CALL                 
 172: LOAD_METHOD          replace
 194: LOAD_CONST           '-'
 196: LOAD_CONST           '_'
 198: PRECALL              
 202: CALL                 
 212: STORE_FAST           tk
 214: LOAD_FAST            tk
 216: LOAD_FAST            value
 218: BUILD_TUPLE          
 220: RETURN_VALUE         
