# Disassembly for importlib.metadata.FreezableDefaultDict.__missing__
# From module file: importlib.metadata._collections

## co_consts:
(None, '_frozen')

## co_names:
('getattr', 'super', '__missing__')

## bytecode:

   0: COPY_FREE_VARS       
   2: RESUME               
   4: PUSH_NULL            
   6: LOAD_GLOBAL          NULL + getattr
  18: LOAD_FAST            self
  20: LOAD_CONST           '_frozen'
  22: LOAD_GLOBAL          NULL + super
  34: PRECALL              
  38: CALL                 
  48: LOAD_ATTR            __missing__
  58: PRECALL              
  62: CALL                 
  72: LOAD_FAST            key
  74: PRECALL              
  78: CALL                 
  88: RETURN_VALUE         
