# Disassembly for importlib.metadata.Message._repair_headers.redent
# From module file: importlib.metadata._adapters

## co_consts:
('Correct for RFC822 indentation', '\n', '        ')

## co_names:
('textwrap', 'dedent')

## bytecode:

   0: RESUME               
   2: LOAD_FAST            value
   4: POP_JUMP_FORWARD_IF_FALSE to 14
   6: LOAD_CONST           '\n'
   8: LOAD_FAST            value
  10: CONTAINS_OP          
  12: POP_JUMP_FORWARD_IF_FALSE to 18
  14: LOAD_FAST            value
  16: RETURN_VALUE         
  18: LOAD_GLOBAL          NULL + textwrap
  30: LOAD_ATTR            dedent
  40: LOAD_CONST           '        '
  42: LOAD_FAST            value
  44: BINARY_OP            +
  48: PRECALL              
  52: CALL                 
  62: RETURN_VALUE         
