# Disassembly for importlib.metadata.Message.json
# From module file: importlib.metadata._adapters

## co_consts:
('\n        Convert PackageMetadata to a JSON-compatible format\n        per PEP 0566.\n        ', <code object transform at 0x00000240691F5BD0, file "importlib\metadata\_adapters.py", line 61>)

## co_names:
('dict', 'map', 'FoldedCase')

## bytecode:

   0: MAKE_CELL            self
   2: RESUME               
   4: LOAD_CLOSURE         self
   6: BUILD_TUPLE          
   8: LOAD_CONST           <code object transform at 0x00000240691F5BD0, file "importlib\metadata\_adapters.py", line 61>
  10: MAKE_FUNCTION        closure
  12: STORE_FAST           transform
  14: LOAD_GLOBAL          NULL + dict
  26: LOAD_GLOBAL          NULL + map
  38: LOAD_FAST            transform
  40: LOAD_GLOBAL          NULL + map
  52: LOAD_GLOBAL          FoldedCase
  64: LOAD_DEREF           self
  66: PRECALL              
  70: CALL                 
  80: PRECALL              
  84: CALL                 
  94: PRECALL              
  98: CALL                 
 108: RETURN_VALUE         
