# Disassembly for importlib.metadata.FoldedCase.split
# From module file: importlib.metadata._text

## co_consts:
(None,)

## co_names:
('re', 'compile', 'escape', 'I', 'split')

## bytecode:

   0: RESUME               
   2: LOAD_GLOBAL          NULL + re
  14: LOAD_ATTR            compile
  24: LOAD_GLOBAL          NULL + re
  36: LOAD_ATTR            escape
  46: LOAD_FAST            splitter
  48: PRECALL              
  52: CALL                 
  62: LOAD_GLOBAL          re
  74: LOAD_ATTR            I
  84: PRECALL              
  88: CALL                 
  98: STORE_FAST           pattern
 100: LOAD_FAST            pattern
 102: LOAD_METHOD          split
 124: LOAD_FAST            self
 126: LOAD_FAST            maxsplit
 128: PRECALL              
 132: CALL                 
 142: RETURN_VALUE         
