# Disassembly for importlib.metadata.Message._repair_headers.<listcomp>
# From module file: importlib.metadata._adapters

## co_consts:
()

## co_names:
()

## bytecode:

   0: COPY_FREE_VARS       
   2: RESUME               
   4: BUILD_LIST           
   6: LOAD_FAST            .0
   8: FOR_ITER             to 46
  10: UNPACK_SEQUENCE      
  14: STORE_FAST           key
  16: STORE_FAST           value
  18: LOAD_FAST            key
  20: PUSH_NULL            
  22: LOAD_DEREF           redent
  24: LOAD_FAST            value
  26: PRECALL              
  30: CALL                 
  40: BUILD_TUPLE          
  42: LIST_APPEND          
  44: JUMP_BACKWARD        to 8
  46: RETURN_VALUE         
