# Disassembly for bz2.BZ2File.read1
# From module file: bz2

## co_consts:
("Read up to size uncompressed bytes, while trying to avoid\n        making multiple reads from the underlying stream. Reads up to a\n        buffer's worth of data if size is negative.\n\n        Returns b'' if the file is at EOF.\n        ", 0)

## co_names:
('_check_can_read', 'io', 'DEFAULT_BUFFER_SIZE', '_buffer', 'read1')

## bytecode:

   0: RESUME               
   2: LOAD_FAST            self
   4: LOAD_METHOD          _check_can_read
  26: PRECALL              
  30: CALL                 
  40: POP_TOP              
  42: LOAD_FAST            size
  44: LOAD_CONST           0
  46: COMPARE_OP           <
  52: POP_JUMP_FORWARD_IF_FALSE to 78
  54: LOAD_GLOBAL          io
  66: LOAD_ATTR            DEFAULT_BUFFER_SIZE
  76: STORE_FAST           size
  78: LOAD_FAST            self
  80: LOAD_ATTR            _buffer
  90: LOAD_METHOD          read1
 112: LOAD_FAST            size
 114: PRECALL              
 118: CALL                 
 128: RETURN_VALUE         
