# Disassembly for bz2.BZ2File.writelines
# From module file: bz2

## co_consts:
('Write a sequence of byte strings to the file.\n\n        Returns the number of uncompressed bytes written.\n        seq can be any iterable yielding byte strings.\n\n        Line separators are not added between the written byte strings.\n        ',)

## co_names:
('_compression', 'BaseStream', 'writelines')

## bytecode:

   0: RESUME               
   2: LOAD_GLOBAL          _compression
  14: LOAD_ATTR            BaseStream
  24: LOAD_METHOD          writelines
  46: LOAD_FAST            self
  48: LOAD_FAST            seq
  50: PRECALL              
  54: CALL                 
  64: RETURN_VALUE         
