# Disassembly for bz2.BZ2File.readinto
# From module file: bz2

## co_consts:
('Read bytes into b.\n\n        Returns the number of bytes read (0 for EOF).\n        ',)

## co_names:
('_check_can_read', '_buffer', 'readinto')

## bytecode:

   0: RESUME               
   2: LOAD_FAST            self
   4: LOAD_METHOD          _check_can_read
  26: PRECALL              
  30: CALL                 
  40: POP_TOP              
  42: LOAD_FAST            self
  44: LOAD_ATTR            _buffer
  54: LOAD_METHOD          readinto
  76: LOAD_FAST            b
  78: PRECALL              
  82: CALL                 
  92: RETURN_VALUE         
