# Disassembly for bz2.BZ2File.write
# From module file: bz2

## co_consts:
('Write a byte string to the file.\n\n        Returns the number of uncompressed bytes written, which is\n        always the length of data in bytes. Note that due to buffering,\n        the file on disk may not reflect the data written until close()\n        is called.\n        ',)

## co_names:
('_check_can_write', 'isinstance', 'bytes', 'bytearray', 'len', 'memoryview', 'nbytes', '_compressor', 'compress', '_fp', 'write', '_pos')

## bytecode:

   0: RESUME               
   2: LOAD_FAST            self
   4: LOAD_METHOD          _check_can_write
  26: PRECALL              
  30: CALL                 
  40: POP_TOP              
  42: LOAD_GLOBAL          NULL + isinstance
  54: LOAD_FAST            data
  56: LOAD_GLOBAL          bytes
  68: LOAD_GLOBAL          bytearray
  80: BUILD_TUPLE          
  82: PRECALL              
  86: CALL                 
  96: POP_JUMP_FORWARD_IF_FALSE to 130
  98: LOAD_GLOBAL          NULL + len
 110: LOAD_FAST            data
 112: PRECALL              
 116: CALL                 
 126: STORE_FAST           length
 128: JUMP_FORWARD         to 174
 130: LOAD_GLOBAL          NULL + memoryview
 142: LOAD_FAST            data
 144: PRECALL              
 148: CALL                 
 158: STORE_FAST           data
 160: LOAD_FAST            data
 162: LOAD_ATTR            nbytes
 172: STORE_FAST           length
 174: LOAD_FAST            self
 176: LOAD_ATTR            _compressor
 186: LOAD_METHOD          compress
 208: LOAD_FAST            data
 210: PRECALL              
 214: CALL                 
 224: STORE_FAST           compressed
 226: LOAD_FAST            self
 228: LOAD_ATTR            _fp
 238: LOAD_METHOD          write
 260: LOAD_FAST            compressed
 262: PRECALL              
 266: CALL                 
 276: POP_TOP              
 278: LOAD_FAST            self
 280: COPY                 
 282: LOAD_ATTR            _pos
 292: LOAD_FAST            length
 294: BINARY_OP            +=
 298: SWAP                 
 300: STORE_ATTR           _pos
 310: LOAD_FAST            length
 312: RETURN_VALUE         
