# Disassembly for threading.Thread._delete
# From module file: threading

## co_consts:
('Remove current thread from the dict of currently running threads.', None)

## co_names:
('_active_limbo_lock', '_active', 'get_ident')

## bytecode:

   0: RESUME               
   2: LOAD_GLOBAL          _active_limbo_lock
  14: BEFORE_WITH          
  16: POP_TOP              
  18: LOAD_GLOBAL          _active
  30: LOAD_GLOBAL          NULL + get_ident
  42: PRECALL              
  46: CALL                 
  56: DELETE_SUBSCR        
  58: LOAD_CONST           None
  60: LOAD_CONST           None
  62: LOAD_CONST           None
  64: PRECALL              
  68: CALL                 
  78: POP_TOP              
  80: LOAD_CONST           None
  82: RETURN_VALUE         
  84: PUSH_EXC_INFO        
  86: WITH_EXCEPT_START    
  88: POP_JUMP_FORWARD_IF_TRUE to 98
  90: RERAISE              
  92: COPY                 
  94: POP_EXCEPT           
  96: RERAISE              
  98: POP_TOP              
 100: POP_EXCEPT           
 102: POP_TOP              
 104: POP_TOP              
 106: LOAD_CONST           None
 108: RETURN_VALUE         
