# Disassembly for threading.RLock
# From module file: threading

## co_consts:
('Factory function that returns a new reentrant lock.\n\n    A reentrant lock must be released by the thread that acquired it. Once a\n    thread has acquired a reentrant lock, the same thread may acquire it again\n    without blocking; the thread must release it once for each time it has\n    acquired it.\n\n    ',)

## co_names:
('_CRLock', '_PyRLock')

## bytecode:

   0: RESUME               
   2: LOAD_GLOBAL          _CRLock
  14: POP_JUMP_FORWARD_IF_NOT_NONE to 40
  16: LOAD_GLOBAL          NULL + _PyRLock
  28: LOAD_FAST            args
  30: BUILD_MAP            
  32: LOAD_FAST            kwargs
  34: DICT_MERGE           
  36: CALL_FUNCTION_EX     
  38: RETURN_VALUE         
  40: LOAD_GLOBAL          NULL + _CRLock
  52: LOAD_FAST            args
  54: BUILD_MAP            
  56: LOAD_FAST            kwargs
  58: DICT_MERGE           
  60: CALL_FUNCTION_EX     
  62: RETURN_VALUE         
