# Disassembly for threading.Thread.__init__
# From module file: threading

## co_consts:
('This constructor should always be called with keyword arguments. Arguments are:\n\n        *group* should be None; reserved for future extension when a ThreadGroup\n        class is implemented.\n\n        *target* is the callable object to be invoked by the run()\n        method. Defaults to None, meaning nothing is called.\n\n        *name* is the thread name. By default, a unique name is constructed of\n        the form "Thread-N" where N is a small decimal number.\n\n        *args* is a list or tuple of arguments for the target invocation. Defaults to ().\n\n        *kwargs* is a dictionary of keyword arguments for the target\n        invocation. Defaults to {}.\n\n        If a subclass overrides the constructor, it must make sure to invoke\n        the base class constructor (Thread.__init__()) before doing anything\n        else to the thread.\n\n        ', None, 'group argument must be None for now', 'Thread-%d', ' (', ')', False, True)

## co_names:
('str', '_newname', '__name__', 'AttributeError', '_target', '_name', '_args', '_kwargs', '_daemonic', 'current_thread', 'daemon', '_ident', '_HAVE_THREAD_NATIVE_ID', '_native_id', '_tstate_lock', 'Event', '_started', '_is_stopped', '_initialized', '_sys', 'stderr', '_stderr', '_make_invoke_excepthook', '_invoke_excepthook', '_dangling', 'add')

## bytecode:

   0: RESUME               
   2: LOAD_FAST            group
   4: POP_JUMP_FORWARD_IF_NONE to 26
   6: LOAD_ASSERTION_ERROR 
   8: LOAD_CONST           'group argument must be None for now'
  10: PRECALL              
  14: CALL                 
  24: RAISE_VARARGS        
  26: LOAD_FAST            kwargs
  28: POP_JUMP_FORWARD_IF_NOT_NONE to 34
  30: BUILD_MAP            
  32: STORE_FAST           kwargs
  34: LOAD_FAST            name
  36: POP_JUMP_FORWARD_IF_FALSE to 70
  38: LOAD_GLOBAL          NULL + str
  50: LOAD_FAST            name
  52: PRECALL              
  56: CALL                 
  66: STORE_FAST           name
  68: JUMP_FORWARD         to 172
  70: LOAD_GLOBAL          NULL + _newname
  82: LOAD_CONST           'Thread-%d'
  84: PRECALL              
  88: CALL                 
  98: STORE_FAST           name
 100: LOAD_FAST            target
 102: POP_JUMP_FORWARD_IF_NONE to 172
 104: NOP                  
 106: LOAD_FAST            target
 108: LOAD_ATTR            __name__
 118: STORE_FAST           target_name
 120: LOAD_FAST            name
 122: LOAD_CONST           ' ('
 124: LOAD_FAST            target_name
 126: FORMAT_VALUE         
 128: LOAD_CONST           ')'
 130: BUILD_STRING         
 132: BINARY_OP            +=
 136: STORE_FAST           name
 138: JUMP_FORWARD         to 172
 140: PUSH_EXC_INFO        
 142: LOAD_GLOBAL          AttributeError
 154: CHECK_EXC_MATCH      
 156: POP_JUMP_FORWARD_IF_FALSE to 164
 158: POP_TOP              
 160: POP_EXCEPT           
 162: JUMP_FORWARD         to 172
 164: RERAISE              
 166: COPY                 
 168: POP_EXCEPT           
 170: RERAISE              
 172: LOAD_FAST            target
 174: LOAD_FAST            self
 176: STORE_ATTR           _target
 186: LOAD_FAST            name
 188: LOAD_FAST            self
 190: STORE_ATTR           _name
 200: LOAD_FAST            args
 202: LOAD_FAST            self
 204: STORE_ATTR           _args
 214: LOAD_FAST            kwargs
 216: LOAD_FAST            self
 218: STORE_ATTR           _kwargs
 228: LOAD_FAST            daemon
 230: POP_JUMP_FORWARD_IF_NONE to 248
 232: LOAD_FAST            daemon
 234: LOAD_FAST            self
 236: STORE_ATTR           _daemonic
 246: JUMP_FORWARD         to 296
 248: LOAD_GLOBAL          NULL + current_thread
 260: PRECALL              
 264: CALL                 
 274: LOAD_ATTR            daemon
 284: LOAD_FAST            self
 286: STORE_ATTR           _daemonic
 296: LOAD_CONST           None
 298: LOAD_FAST            self
 300: STORE_ATTR           _ident
 310: LOAD_GLOBAL          _HAVE_THREAD_NATIVE_ID
 322: POP_JUMP_FORWARD_IF_FALSE to 338
 324: LOAD_CONST           None
 326: LOAD_FAST            self
 328: STORE_ATTR           _native_id
 338: LOAD_CONST           None
 340: LOAD_FAST            self
 342: STORE_ATTR           _tstate_lock
 352: LOAD_GLOBAL          NULL + Event
 364: PRECALL              
 368: CALL                 
 378: LOAD_FAST            self
 380: STORE_ATTR           _started
 390: LOAD_CONST           False
 392: LOAD_FAST            self
 394: STORE_ATTR           _is_stopped
 404: LOAD_CONST           True
 406: LOAD_FAST            self
 408: STORE_ATTR           _initialized
 418: LOAD_GLOBAL          _sys
 430: LOAD_ATTR            stderr
 440: LOAD_FAST            self
 442: STORE_ATTR           _stderr
 452: LOAD_GLOBAL          NULL + _make_invoke_excepthook
 464: PRECALL              
 468: CALL                 
 478: LOAD_FAST            self
 480: STORE_ATTR           _invoke_excepthook
 490: LOAD_GLOBAL          _dangling
 502: LOAD_METHOD          add
 524: LOAD_FAST            self
 526: PRECALL              
 530: CALL                 
 540: POP_TOP              
 542: LOAD_CONST           None
 544: RETURN_VALUE         
