# Disassembly for threading.Thread.setDaemon
# From module file: threading

## co_consts:
('Set whether this thread is a daemon.\n\n        This method is deprecated, use the .daemon property instead.\n\n        ', 0, None, 'setDaemon() is deprecated, set the daemon attribute instead', 2, ('stacklevel',))

## co_names:
('warnings', 'warn', 'DeprecationWarning', 'daemon')

## bytecode:

   0: RESUME               
   2: LOAD_CONST           0
   4: LOAD_CONST           None
   6: IMPORT_NAME          warnings
   8: STORE_FAST           warnings
  10: LOAD_FAST            warnings
  12: LOAD_METHOD          warn
  34: LOAD_CONST           'setDaemon() is deprecated, set the daemon attribute instead'
  36: LOAD_GLOBAL          DeprecationWarning
  48: LOAD_CONST           2
  50: KW_NAMES             
  52: PRECALL              
  56: CALL                 
  66: POP_TOP              
  68: LOAD_FAST            daemonic
  70: LOAD_FAST            self
  72: STORE_ATTR           daemon
  82: LOAD_CONST           None
  84: RETURN_VALUE         
