# Disassembly for threading._RLock
# From module file: threading

## co_consts:
('_RLock', 'This class implements reentrant lock objects.\n\n    A reentrant lock must be released by the thread that acquired it. Once a\n    thread has acquired a reentrant lock, the same thread may acquire it\n    again without blocking; the thread must release it once for each time it\n    has acquired it.\n\n    ', <code object __init__ at 0x00000240693EB730, file "threading.py", line 113>, <code object __repr__ at 0x00000240691DABB0, file "threading.py", line 118>, <code object _at_fork_reinit at 0x000002406944A890, file "threading.py", line 133>, True, -1, <code object acquire at 0x000002406921FB20, file "threading.py", line 138>, <code object release at 0x00000240691E9E30, file "threading.py", line 176>, <code object __exit__ at 0x000002406945F780, file "threading.py", line 199>, <code object _acquire_restore at 0x000002406944A780, file "threading.py", line 204>, <code object _release_save at 0x00000240691C05B0, file "threading.py", line 208>, <code object _is_owned at 0x000002406945CF30, file "threading.py", line 218>, None, (True, -1))

## co_names:
('__name__', '__module__', '__qualname__', '__doc__', '__init__', '__repr__', '_at_fork_reinit', 'acquire', '__enter__', 'release', '__exit__', '_acquire_restore', '_release_save', '_is_owned')

## bytecode:

   0: RESUME               
   2: LOAD_NAME            __name__
   4: STORE_NAME           __module__
   6: LOAD_CONST           '_RLock'
   8: STORE_NAME           __qualname__
  10: LOAD_CONST           'This class implements reentrant lock objects.\n\n    A reentrant lock must be released by the thread that acquired it. Once a\n    thread has acquired a reentrant lock, the same thread may acquire it\n    again without blocking; the thread must release it once for each time it\n    has acquired it.\n\n    '
  12: STORE_NAME           __doc__
  14: LOAD_CONST           <code object __init__ at 0x00000240693EB730, file "threading.py", line 113>
  16: MAKE_FUNCTION        
  18: STORE_NAME           __init__
  20: LOAD_CONST           <code object __repr__ at 0x00000240691DABB0, file "threading.py", line 118>
  22: MAKE_FUNCTION        
  24: STORE_NAME           __repr__
  26: LOAD_CONST           <code object _at_fork_reinit at 0x000002406944A890, file "threading.py", line 133>
  28: MAKE_FUNCTION        
  30: STORE_NAME           _at_fork_reinit
  32: LOAD_CONST           (True, -1)
  34: LOAD_CONST           <code object acquire at 0x000002406921FB20, file "threading.py", line 138>
  36: MAKE_FUNCTION        defaults
  38: STORE_NAME           acquire
  40: LOAD_NAME            acquire
  42: STORE_NAME           __enter__
  44: LOAD_CONST           <code object release at 0x00000240691E9E30, file "threading.py", line 176>
  46: MAKE_FUNCTION        
  48: STORE_NAME           release
  50: LOAD_CONST           <code object __exit__ at 0x000002406945F780, file "threading.py", line 199>
  52: MAKE_FUNCTION        
  54: STORE_NAME           __exit__
  56: LOAD_CONST           <code object _acquire_restore at 0x000002406944A780, file "threading.py", line 204>
  58: MAKE_FUNCTION        
  60: STORE_NAME           _acquire_restore
  62: LOAD_CONST           <code object _release_save at 0x00000240691C05B0, file "threading.py", line 208>
  64: MAKE_FUNCTION        
  66: STORE_NAME           _release_save
  68: LOAD_CONST           <code object _is_owned at 0x000002406945CF30, file "threading.py", line 218>
  70: MAKE_FUNCTION        
  72: STORE_NAME           _is_owned
  74: LOAD_CONST           None
  76: RETURN_VALUE         
