# Disassembly for threading.Thread.name
# From module file: threading

## co_consts:
(None, 'Thread.__init__() not called')

## co_names:
('_initialized', 'str', '_name')

## bytecode:

   0: RESUME               
   2: LOAD_FAST            self
   4: LOAD_ATTR            _initialized
  14: POP_JUMP_FORWARD_IF_TRUE to 36
  16: LOAD_ASSERTION_ERROR 
  18: LOAD_CONST           'Thread.__init__() not called'
  20: PRECALL              
  24: CALL                 
  34: RAISE_VARARGS        
  36: LOAD_GLOBAL          NULL + str
  48: LOAD_FAST            name
  50: PRECALL              
  54: CALL                 
  64: LOAD_FAST            self
  66: STORE_ATTR           _name
  76: LOAD_CONST           None
  78: RETURN_VALUE         
