# Disassembly for threading.Thread.native_id
# From module file: threading

## co_consts:
('Native integral thread ID of this thread, or None if it has not been started.\n\n            This is a non-negative integer. See the get_native_id() function.\n            This represents the Thread ID as reported by the kernel.\n\n            ', 'Thread.__init__() not called')

## co_names:
('_initialized', '_native_id')

## bytecode:

   0: RESUME               
   2: LOAD_FAST            self
   4: LOAD_ATTR            _initialized
  14: POP_JUMP_FORWARD_IF_TRUE to 36
  16: LOAD_ASSERTION_ERROR 
  18: LOAD_CONST           'Thread.__init__() not called'
  20: PRECALL              
  24: CALL                 
  34: RAISE_VARARGS        
  36: LOAD_FAST            self
  38: LOAD_ATTR            _native_id
  48: RETURN_VALUE         
