# Disassembly for threading.currentThread
# From module file: threading

## co_consts:
("Return the current Thread object, corresponding to the caller's thread of control.\n\n    This function is deprecated, use current_thread() instead.\n\n    ", 0, None, 'currentThread() is deprecated, use current_thread() instead', 2, ('stacklevel',))

## co_names:
('warnings', 'warn', 'DeprecationWarning', 'current_thread')

## bytecode:

   0: RESUME               
   2: LOAD_CONST           0
   4: LOAD_CONST           None
   6: IMPORT_NAME          warnings
   8: STORE_FAST           warnings
  10: LOAD_FAST            warnings
  12: LOAD_METHOD          warn
  34: LOAD_CONST           'currentThread() is deprecated, use current_thread() instead'
  36: LOAD_GLOBAL          DeprecationWarning
  48: LOAD_CONST           2
  50: KW_NAMES             
  52: PRECALL              
  56: CALL                 
  66: POP_TOP              
  68: LOAD_GLOBAL          NULL + current_thread
  80: PRECALL              
  84: CALL                 
  94: RETURN_VALUE         
