# Disassembly for threading.BoundedSemaphore
# From module file: threading

## co_consts:
('BoundedSemaphore', "Implements a bounded semaphore.\n\n    A bounded semaphore checks to make sure its current value doesn't exceed its\n    initial value. If it does, ValueError is raised. In most situations\n    semaphores are used to guard resources with limited capacity.\n\n    If the semaphore is released too many times it's a sign of a bug. If not\n    given, value defaults to 1.\n\n    Like regular semaphores, bounded semaphores manage a counter representing\n    the number of release() calls minus the number of acquire() calls, plus an\n    initial value. The acquire() method blocks if necessary until it can return\n    without making the counter negative. If not given, value defaults to 1.\n\n    ", 1, <code object __init__ at 0x000002406944BCC0, file "threading.py", line 515>, <code object __repr__ at 0x00000240693D2890, file "threading.py", line 519>, <code object release at 0x0000024069365D40, file "threading.py", line 524>, None, (1,))

## co_names:
('__name__', '__module__', '__qualname__', '__doc__', '__init__', '__repr__', 'release')

## bytecode:

   0: RESUME               
   2: LOAD_NAME            __name__
   4: STORE_NAME           __module__
   6: LOAD_CONST           'BoundedSemaphore'
   8: STORE_NAME           __qualname__
  10: LOAD_CONST           "Implements a bounded semaphore.\n\n    A bounded semaphore checks to make sure its current value doesn't exceed its\n    initial value. If it does, ValueError is raised. In most situations\n    semaphores are used to guard resources with limited capacity.\n\n    If the semaphore is released too many times it's a sign of a bug. If not\n    given, value defaults to 1.\n\n    Like regular semaphores, bounded semaphores manage a counter representing\n    the number of release() calls minus the number of acquire() calls, plus an\n    initial value. The acquire() method blocks if necessary until it can return\n    without making the counter negative. If not given, value defaults to 1.\n\n    "
  12: STORE_NAME           __doc__
  14: LOAD_CONST           (1,)
  16: LOAD_CONST           <code object __init__ at 0x000002406944BCC0, file "threading.py", line 515>
  18: MAKE_FUNCTION        defaults
  20: STORE_NAME           __init__
  22: LOAD_CONST           <code object __repr__ at 0x00000240693D2890, file "threading.py", line 519>
  24: MAKE_FUNCTION        
  26: STORE_NAME           __repr__
  28: LOAD_CONST           (1,)
  30: LOAD_CONST           <code object release at 0x0000024069365D40, file "threading.py", line 524>
  32: MAKE_FUNCTION        defaults
  34: STORE_NAME           release
  36: LOAD_CONST           None
  38: RETURN_VALUE         
