# Disassembly for threading._RLock._at_fork_reinit
# From module file: threading

## co_consts:
(None, 0)

## co_names:
('_block', '_at_fork_reinit', '_owner', '_count')

## bytecode:

   0: RESUME               
   2: LOAD_FAST            self
   4: LOAD_ATTR            _block
  14: LOAD_METHOD          _at_fork_reinit
  36: PRECALL              
  40: CALL                 
  50: POP_TOP              
  52: LOAD_CONST           None
  54: LOAD_FAST            self
  56: STORE_ATTR           _owner
  66: LOAD_CONST           0
  68: LOAD_FAST            self
  70: STORE_ATTR           _count
  80: LOAD_CONST           None
  82: RETURN_VALUE         
