# Disassembly for threading.Thread.daemon
# From module file: threading

## co_consts:
(None, 'Thread.__init__() not called', 'cannot set daemon status of active thread')

## co_names:
('_initialized', 'RuntimeError', '_started', 'is_set', '_daemonic')

## bytecode:

   0: RESUME               
   2: LOAD_FAST            self
   4: LOAD_ATTR            _initialized
  14: POP_JUMP_FORWARD_IF_TRUE to 46
  16: LOAD_GLOBAL          NULL + RuntimeError
  28: LOAD_CONST           'Thread.__init__() not called'
  30: PRECALL              
  34: CALL                 
  44: RAISE_VARARGS        
  46: LOAD_FAST            self
  48: LOAD_ATTR            _started
  58: LOAD_METHOD          is_set
  80: PRECALL              
  84: CALL                 
  94: POP_JUMP_FORWARD_IF_FALSE to 126
  96: LOAD_GLOBAL          NULL + RuntimeError
 108: LOAD_CONST           'cannot set daemon status of active thread'
 110: PRECALL              
 114: CALL                 
 124: RAISE_VARARGS        
 126: LOAD_FAST            daemonic
 128: LOAD_FAST            self
 130: STORE_ATTR           _daemonic
 140: LOAD_CONST           None
 142: RETURN_VALUE         
