# Disassembly for threading.Condition.notifyAll
# From module file: threading

## co_consts:
('Wake up all threads waiting on this condition.\n\n        This method is deprecated, use notify_all() instead.\n\n        ', 0, None, 'notifyAll() is deprecated, use notify_all() instead', 2, ('stacklevel',))

## co_names:
('warnings', 'warn', 'DeprecationWarning', 'notify_all')

## bytecode:

   0: RESUME               
   2: LOAD_CONST           0
   4: LOAD_CONST           None
   6: IMPORT_NAME          warnings
   8: STORE_FAST           warnings
  10: LOAD_FAST            warnings
  12: LOAD_METHOD          warn
  34: LOAD_CONST           'notifyAll() is deprecated, use notify_all() instead'
  36: LOAD_GLOBAL          DeprecationWarning
  48: LOAD_CONST           2
  50: KW_NAMES             
  52: PRECALL              
  56: CALL                 
  66: POP_TOP              
  68: LOAD_FAST            self
  70: LOAD_METHOD          notify_all
  92: PRECALL              
  96: CALL                 
 106: POP_TOP              
 108: LOAD_CONST           None
 110: RETURN_VALUE         
