# Disassembly for threading.Event.clear
# From module file: threading

## co_consts:
('Reset the internal flag to false.\n\n        Subsequently, threads calling wait() will block until set() is called to\n        set the internal flag to true again.\n\n        ', False, None)

## co_names:
('_cond', '_flag')

## bytecode:

   0: RESUME               
   2: LOAD_FAST            self
   4: LOAD_ATTR            _cond
  14: BEFORE_WITH          
  16: POP_TOP              
  18: LOAD_CONST           False
  20: LOAD_FAST            self
  22: STORE_ATTR           _flag
  32: LOAD_CONST           None
  34: LOAD_CONST           None
  36: LOAD_CONST           None
  38: PRECALL              
  42: CALL                 
  52: POP_TOP              
  54: LOAD_CONST           None
  56: RETURN_VALUE         
  58: PUSH_EXC_INFO        
  60: WITH_EXCEPT_START    
  62: POP_JUMP_FORWARD_IF_TRUE to 72
  64: RERAISE              
  66: COPY                 
  68: POP_EXCEPT           
  70: RERAISE              
  72: POP_TOP              
  74: POP_EXCEPT           
  76: POP_TOP              
  78: POP_TOP              
  80: LOAD_CONST           None
  82: RETURN_VALUE         
