# Disassembly for threading.Thread.__repr__
# From module file: threading

## co_consts:
(None, 'Thread.__init__() was not called', 'initial', 'started', 'stopped', ' daemon', ' %s', '<', '(', ', ', ')>')

## co_names:
('_initialized', '_started', 'is_set', 'is_alive', '_is_stopped', '_daemonic', '_ident', '__class__', '__name__', '_name')

## bytecode:

   0: RESUME               
   2: LOAD_FAST            self
   4: LOAD_ATTR            _initialized
  14: POP_JUMP_FORWARD_IF_TRUE to 36
  16: LOAD_ASSERTION_ERROR 
  18: LOAD_CONST           'Thread.__init__() was not called'
  20: PRECALL              
  24: CALL                 
  34: RAISE_VARARGS        
  36: LOAD_CONST           'initial'
  38: STORE_FAST           status
  40: LOAD_FAST            self
  42: LOAD_ATTR            _started
  52: LOAD_METHOD          is_set
  74: PRECALL              
  78: CALL                 
  88: POP_JUMP_FORWARD_IF_FALSE to 94
  90: LOAD_CONST           'started'
  92: STORE_FAST           status
  94: LOAD_FAST            self
  96: LOAD_METHOD          is_alive
 118: PRECALL              
 122: CALL                 
 132: POP_TOP              
 134: LOAD_FAST            self
 136: LOAD_ATTR            _is_stopped
 146: POP_JUMP_FORWARD_IF_FALSE to 152
 148: LOAD_CONST           'stopped'
 150: STORE_FAST           status
 152: LOAD_FAST            self
 154: LOAD_ATTR            _daemonic
 164: POP_JUMP_FORWARD_IF_FALSE to 176
 166: LOAD_FAST            status
 168: LOAD_CONST           ' daemon'
 170: BINARY_OP            +=
 174: STORE_FAST           status
 176: LOAD_FAST            self
 178: LOAD_ATTR            _ident
 188: POP_JUMP_FORWARD_IF_NONE to 216
 190: LOAD_FAST            status
 192: LOAD_CONST           ' %s'
 194: LOAD_FAST            self
 196: LOAD_ATTR            _ident
 206: BINARY_OP            %
 210: BINARY_OP            +=
 214: STORE_FAST           status
 216: LOAD_CONST           '<'
 218: LOAD_FAST            self
 220: LOAD_ATTR            __class__
 230: LOAD_ATTR            __name__
 240: FORMAT_VALUE         str
 242: LOAD_CONST           '('
 244: LOAD_FAST            self
 246: LOAD_ATTR            _name
 256: FORMAT_VALUE         str
 258: LOAD_CONST           ', '
 260: LOAD_FAST            status
 262: FORMAT_VALUE         str
 264: LOAD_CONST           ')>'
 266: BUILD_STRING         
 268: RETURN_VALUE         
