# Disassembly for threading.Thread.ident
# From module file: threading

## co_consts:
('Thread identifier of this thread or None if it has not been started.\n\n        This is a nonzero integer. See the get_ident() function. Thread\n        identifiers may be recycled when a thread exits and another thread is\n        created. The identifier is available even after the thread has exited.\n\n        ', 'Thread.__init__() not called')

## co_names:
('_initialized', '_ident')

## bytecode:

   0: RESUME               
   2: LOAD_FAST            self
   4: LOAD_ATTR            _initialized
  14: POP_JUMP_FORWARD_IF_TRUE to 36
  16: LOAD_ASSERTION_ERROR 
  18: LOAD_CONST           'Thread.__init__() not called'
  20: PRECALL              
  24: CALL                 
  34: RAISE_VARARGS        
  36: LOAD_FAST            self
  38: LOAD_ATTR            _ident
  48: RETURN_VALUE         
