# Disassembly for threading.Thread._bootstrap
# From module file: threading

## co_consts:
(None,)

## co_names:
('_bootstrap_inner', '_daemonic', '_sys')

## bytecode:

   0: RESUME               
   2: NOP                  
   4: LOAD_FAST            self
   6: LOAD_METHOD          _bootstrap_inner
  28: PRECALL              
  32: CALL                 
  42: POP_TOP              
  44: LOAD_CONST           None
  46: RETURN_VALUE         
  48: PUSH_EXC_INFO        
  50: POP_TOP              
  52: LOAD_FAST            self
  54: LOAD_ATTR            _daemonic
  64: POP_JUMP_FORWARD_IF_FALSE to 86
  66: LOAD_GLOBAL          _sys
  78: POP_JUMP_FORWARD_IF_NOT_NONE to 86
  80: POP_EXCEPT           
  82: LOAD_CONST           None
  84: RETURN_VALUE         
  86: RAISE_VARARGS        
  88: COPY                 
  90: POP_EXCEPT           
  92: RERAISE              
