# Disassembly for threading.Thread.start
# From module file: threading

## co_consts:
("Start the thread's activity.\n\n        It must be called at most once per thread object. It arranges for the\n        object's run() method to be invoked in a separate thread of control.\n\n        This method will raise a RuntimeError if called more than once on the\n        same thread object.\n\n        ", 'thread.__init__() not called', 'threads can only be started once', None, ())

## co_names:
('_initialized', 'RuntimeError', '_started', 'is_set', '_active_limbo_lock', '_limbo', '_start_new_thread', '_bootstrap', 'Exception', 'wait')

## bytecode:

   0: RESUME               
   2: LOAD_FAST            self
   4: LOAD_ATTR            _initialized
  14: POP_JUMP_FORWARD_IF_TRUE to 46
  16: LOAD_GLOBAL          NULL + RuntimeError
  28: LOAD_CONST           'thread.__init__() not called'
  30: PRECALL              
  34: CALL                 
  44: RAISE_VARARGS        
  46: LOAD_FAST            self
  48: LOAD_ATTR            _started
  58: LOAD_METHOD          is_set
  80: PRECALL              
  84: CALL                 
  94: POP_JUMP_FORWARD_IF_FALSE to 126
  96: LOAD_GLOBAL          NULL + RuntimeError
 108: LOAD_CONST           'threads can only be started once'
 110: PRECALL              
 114: CALL                 
 124: RAISE_VARARGS        
 126: LOAD_GLOBAL          _active_limbo_lock
 138: BEFORE_WITH          
 140: POP_TOP              
 142: LOAD_FAST            self
 144: LOAD_GLOBAL          _limbo
 156: LOAD_FAST            self
 158: STORE_SUBSCR         
 162: LOAD_CONST           None
 164: LOAD_CONST           None
 166: LOAD_CONST           None
 168: PRECALL              
 172: CALL                 
 182: POP_TOP              
 184: JUMP_FORWARD         to 208
 186: PUSH_EXC_INFO        
 188: WITH_EXCEPT_START    
 190: POP_JUMP_FORWARD_IF_TRUE to 200
 192: RERAISE              
 194: COPY                 
 196: POP_EXCEPT           
 198: RERAISE              
 200: POP_TOP              
 202: POP_EXCEPT           
 204: POP_TOP              
 206: POP_TOP              
 208: NOP                  
 210: LOAD_GLOBAL          NULL + _start_new_thread
 222: LOAD_FAST            self
 224: LOAD_ATTR            _bootstrap
 234: LOAD_CONST           ()
 236: PRECALL              
 240: CALL                 
 250: POP_TOP              
 252: JUMP_FORWARD         to 362
 254: PUSH_EXC_INFO        
 256: LOAD_GLOBAL          Exception
 268: CHECK_EXC_MATCH      
 270: POP_JUMP_FORWARD_IF_FALSE to 354
 272: POP_TOP              
 274: LOAD_GLOBAL          _active_limbo_lock
 286: BEFORE_WITH          
 288: POP_TOP              
 290: LOAD_GLOBAL          _limbo
 302: LOAD_FAST            self
 304: DELETE_SUBSCR        
 306: LOAD_CONST           None
 308: LOAD_CONST           None
 310: LOAD_CONST           None
 312: PRECALL              
 316: CALL                 
 326: POP_TOP              
 328: JUMP_FORWARD         to 352
 330: PUSH_EXC_INFO        
 332: WITH_EXCEPT_START    
 334: POP_JUMP_FORWARD_IF_TRUE to 344
 336: RERAISE              
 338: COPY                 
 340: POP_EXCEPT           
 342: RERAISE              
 344: POP_TOP              
 346: POP_EXCEPT           
 348: POP_TOP              
 350: POP_TOP              
 352: RAISE_VARARGS        
 354: RERAISE              
 356: COPY                 
 358: POP_EXCEPT           
 360: RERAISE              
 362: LOAD_FAST            self
 364: LOAD_ATTR            _started
 374: LOAD_METHOD          wait
 396: PRECALL              
 400: CALL                 
 410: POP_TOP              
 412: LOAD_CONST           None
 414: RETURN_VALUE         
