# Disassembly for threading.Thread.run
# From module file: threading

## co_consts:
("Method representing the thread's activity.\n\n        You may override this method in a subclass. The standard run() method\n        invokes the callable object passed to the object's constructor as the\n        target argument, if any, with sequential and keyword arguments taken\n        from the args and kwargs arguments, respectively.\n\n        ", None)

## co_names:
('_target', '_args', '_kwargs')

## bytecode:

   0: RESUME               
   2: NOP                  
   4: LOAD_FAST            self
   6: LOAD_ATTR            _target
  16: POP_JUMP_FORWARD_IF_NONE to 64
  18: PUSH_NULL            
  20: LOAD_FAST            self
  22: LOAD_ATTR            _target
  32: LOAD_FAST            self
  34: LOAD_ATTR            _args
  44: BUILD_MAP            
  46: LOAD_FAST            self
  48: LOAD_ATTR            _kwargs
  58: DICT_MERGE           
  60: CALL_FUNCTION_EX     
  62: POP_TOP              
  64: LOAD_FAST            self
  66: DELETE_ATTR          _target
  68: LOAD_FAST            self
  70: DELETE_ATTR          _args
  72: LOAD_FAST            self
  74: DELETE_ATTR          _kwargs
  76: LOAD_CONST           None
  78: RETURN_VALUE         
  80: PUSH_EXC_INFO        
  82: LOAD_FAST            self
  84: DELETE_ATTR          _target
  86: LOAD_FAST            self
  88: DELETE_ATTR          _args
  90: LOAD_FAST            self
  92: DELETE_ATTR          _kwargs
  94: RERAISE              
  96: COPY                 
  98: POP_EXCEPT           
 100: RERAISE              
