# Disassembly for threading._maintain_shutdown_locks
# From module file: threading

## co_consts:
("\n    Drop any shutdown locks that don't correspond to running threads anymore.\n\n    Calling this from time to time avoids an ever-growing _shutdown_locks\n    set when Thread objects are not joined explicitly. See bpo-37788.\n\n    This must be called with _shutdown_locks_lock acquired.\n    ", <code object <listcomp> at 0x00000240693EAA30, file "threading.py", line 832>, None)

## co_names:
('_shutdown_locks', 'difference_update')

## bytecode:

   0: RESUME               
   2: LOAD_CONST           <code object <listcomp> at 0x00000240693EAA30, file "threading.py", line 832>
   4: MAKE_FUNCTION        
   6: LOAD_GLOBAL          _shutdown_locks
  18: GET_ITER             
  20: PRECALL              
  24: CALL                 
  34: STORE_FAST           to_remove
  36: LOAD_GLOBAL          _shutdown_locks
  48: LOAD_METHOD          difference_update
  70: LOAD_FAST            to_remove
  72: PRECALL              
  76: CALL                 
  86: POP_TOP              
  88: LOAD_CONST           None
  90: RETURN_VALUE         
