# Disassembly for threading.Barrier.reset
# From module file: threading

## co_consts:
('Reset the barrier to the initial state.\n\n        Any threads currently waiting will get the BrokenBarrier exception\n        raised.\n\n        ', 0, -1, -2, None)

## co_names:
('_cond', '_count', '_state', 'notify_all')

## bytecode:

   0: RESUME               
   2: LOAD_FAST            self
   4: LOAD_ATTR            _cond
  14: BEFORE_WITH          
  16: POP_TOP              
  18: LOAD_FAST            self
  20: LOAD_ATTR            _count
  30: LOAD_CONST           0
  32: COMPARE_OP           >
  38: POP_JUMP_FORWARD_IF_FALSE to 116
  40: LOAD_FAST            self
  42: LOAD_ATTR            _state
  52: LOAD_CONST           0
  54: COMPARE_OP           ==
  60: POP_JUMP_FORWARD_IF_FALSE to 78
  62: LOAD_CONST           -1
  64: LOAD_FAST            self
  66: STORE_ATTR           _state
  76: JUMP_FORWARD         to 130
  78: LOAD_FAST            self
  80: LOAD_ATTR            _state
  90: LOAD_CONST           -2
  92: COMPARE_OP           ==
  98: POP_JUMP_FORWARD_IF_FALSE to 114
 100: LOAD_CONST           -1
 102: LOAD_FAST            self
 104: STORE_ATTR           _state
 114: JUMP_FORWARD         to 130
 116: LOAD_CONST           0
 118: LOAD_FAST            self
 120: STORE_ATTR           _state
 130: LOAD_FAST            self
 132: LOAD_ATTR            _cond
 142: LOAD_METHOD          notify_all
 164: PRECALL              
 168: CALL                 
 178: POP_TOP              
 180: LOAD_CONST           None
 182: LOAD_CONST           None
 184: LOAD_CONST           None
 186: PRECALL              
 190: CALL                 
 200: POP_TOP              
 202: LOAD_CONST           None
 204: RETURN_VALUE         
 206: PUSH_EXC_INFO        
 208: WITH_EXCEPT_START    
 210: POP_JUMP_FORWARD_IF_TRUE to 220
 212: RERAISE              
 214: COPY                 
 216: POP_EXCEPT           
 218: RERAISE              
 220: POP_TOP              
 222: POP_EXCEPT           
 224: POP_TOP              
 226: POP_TOP              
 228: LOAD_CONST           None
 230: RETURN_VALUE         
