# Disassembly for threading.Condition.wait_for
# From module file: threading

## co_consts:
('Wait until a condition evaluates to True.\n\n        predicate should be a callable which result will be interpreted as a\n        boolean value.  A timeout may be provided giving the maximum time to\n        wait.\n\n        ', None, 0)

## co_names:
('_time', 'wait')

## bytecode:

   0: RESUME               
   2: LOAD_CONST           None
   4: STORE_FAST           endtime
   6: LOAD_FAST            timeout
   8: STORE_FAST           waittime
  10: PUSH_NULL            
  12: LOAD_FAST            predicate
  14: PRECALL              
  18: CALL                 
  28: STORE_FAST           result
  30: LOAD_FAST            result
  32: POP_JUMP_FORWARD_IF_TRUE to 192
  34: LOAD_FAST            waittime
  36: POP_JUMP_FORWARD_IF_NONE to 126
  38: LOAD_FAST            endtime
  40: POP_JUMP_FORWARD_IF_NOT_NONE to 78
  42: LOAD_GLOBAL          NULL + _time
  54: PRECALL              
  58: CALL                 
  68: LOAD_FAST            waittime
  70: BINARY_OP            +
  74: STORE_FAST           endtime
  76: JUMP_FORWARD         to 126
  78: LOAD_FAST            endtime
  80: LOAD_GLOBAL          NULL + _time
  92: PRECALL              
  96: CALL                 
 106: BINARY_OP            -
 110: STORE_FAST           waittime
 112: LOAD_FAST            waittime
 114: LOAD_CONST           0
 116: COMPARE_OP           <=
 122: POP_JUMP_FORWARD_IF_FALSE to 126
 124: JUMP_FORWARD         to 192
 126: LOAD_FAST            self
 128: LOAD_METHOD          wait
 150: LOAD_FAST            waittime
 152: PRECALL              
 156: CALL                 
 166: POP_TOP              
 168: PUSH_NULL            
 170: LOAD_FAST            predicate
 172: PRECALL              
 176: CALL                 
 186: STORE_FAST           result
 188: LOAD_FAST            result
 190: POP_JUMP_BACKWARD_IF_FALSE to 34
 192: LOAD_FAST            result
 194: RETURN_VALUE         
