# Disassembly for threading.Barrier.__init__
# From module file: threading

## co_consts:
("Create a barrier, initialised to 'parties' threads.\n\n        'action' is a callable which, when supplied, will be called by one of\n        the threads after they have all entered the barrier and just prior to\n        releasing them all. If a 'timeout' is provided, it is used as the\n        default for all subsequent 'wait()' calls.\n\n        ", 0, None)

## co_names:
('Condition', 'Lock', '_cond', '_action', '_timeout', '_parties', '_state', '_count')

## bytecode:

   0: RESUME               
   2: LOAD_GLOBAL          NULL + Condition
  14: LOAD_GLOBAL          NULL + Lock
  26: PRECALL              
  30: CALL                 
  40: PRECALL              
  44: CALL                 
  54: LOAD_FAST            self
  56: STORE_ATTR           _cond
  66: LOAD_FAST            action
  68: LOAD_FAST            self
  70: STORE_ATTR           _action
  80: LOAD_FAST            timeout
  82: LOAD_FAST            self
  84: STORE_ATTR           _timeout
  94: LOAD_FAST            parties
  96: LOAD_FAST            self
  98: STORE_ATTR           _parties
 108: LOAD_CONST           0
 110: LOAD_FAST            self
 112: STORE_ATTR           _state
 122: LOAD_CONST           0
 124: LOAD_FAST            self
 126: STORE_ATTR           _count
 136: LOAD_CONST           None
 138: RETURN_VALUE         
