# Disassembly for threading._DummyThread.is_alive
# From module file: threading

## co_consts:
(None, True)

## co_names:
('_is_stopped', '_started', 'is_set')

## bytecode:

   0: RESUME               
   2: LOAD_FAST            self
   4: LOAD_ATTR            _is_stopped
  14: POP_JUMP_FORWARD_IF_TRUE to 66
  16: LOAD_FAST            self
  18: LOAD_ATTR            _started
  28: LOAD_METHOD          is_set
  50: PRECALL              
  54: CALL                 
  64: POP_JUMP_FORWARD_IF_TRUE to 70
  66: LOAD_ASSERTION_ERROR 
  68: RAISE_VARARGS        
  70: LOAD_CONST           True
  72: RETURN_VALUE         
