# Disassembly for threading.Condition._at_fork_reinit
# From module file: threading

## co_consts:
(None,)

## co_names:
('_lock', '_at_fork_reinit', '_waiters', 'clear')

## bytecode:

   0: RESUME               
   2: LOAD_FAST            self
   4: LOAD_ATTR            _lock
  14: LOAD_METHOD          _at_fork_reinit
  36: PRECALL              
  40: CALL                 
  50: POP_TOP              
  52: LOAD_FAST            self
  54: LOAD_ATTR            _waiters
  64: LOAD_METHOD          clear
  86: PRECALL              
  90: CALL                 
 100: POP_TOP              
 102: LOAD_CONST           None
 104: RETURN_VALUE         
