# Disassembly for threading.Event.isSet
# From module file: threading

## co_consts:
('Return true if and only if the internal flag is true.\n\n        This method is deprecated, use is_set() instead.\n\n        ', 0, None, 'isSet() is deprecated, use is_set() instead', 2, ('stacklevel',))

## co_names:
('warnings', 'warn', 'DeprecationWarning', 'is_set')

## bytecode:

   0: RESUME               
   2: LOAD_CONST           0
   4: LOAD_CONST           None
   6: IMPORT_NAME          warnings
   8: STORE_FAST           warnings
  10: LOAD_FAST            warnings
  12: LOAD_METHOD          warn
  34: LOAD_CONST           'isSet() is deprecated, use is_set() instead'
  36: LOAD_GLOBAL          DeprecationWarning
  48: LOAD_CONST           2
  50: KW_NAMES             
  52: PRECALL              
  56: CALL                 
  66: POP_TOP              
  68: LOAD_FAST            self
  70: LOAD_METHOD          is_set
  92: PRECALL              
  96: CALL                 
 106: RETURN_VALUE         
