# Disassembly for threading.Condition.__repr__
# From module file: threading

## co_consts:
(None, '<Condition(%s, %d)>')

## co_names:
('_lock', 'len', '_waiters')

## bytecode:

   0: RESUME               
   2: LOAD_CONST           '<Condition(%s, %d)>'
   4: LOAD_FAST            self
   6: LOAD_ATTR            _lock
  16: LOAD_GLOBAL          NULL + len
  28: LOAD_FAST            self
  30: LOAD_ATTR            _waiters
  40: PRECALL              
  44: CALL                 
  54: BUILD_TUPLE          
  56: BINARY_OP            %
  60: RETURN_VALUE         
