# Disassembly for threading._RLock.release
# From module file: threading

## co_consts:
('Release a lock, decrementing the recursion level.\n\n        If after the decrement it is zero, reset the lock to unlocked (not owned\n        by any thread), and if any other threads are blocked waiting for the\n        lock to become unlocked, allow exactly one of them to proceed. If after\n        the decrement the recursion level is still nonzero, the lock remains\n        locked and owned by the calling thread.\n\n        Only call this method when the calling thread owns the lock. A\n        RuntimeError is raised if this method is called when the lock is\n        unlocked.\n\n        There is no return value.\n\n        ', 'cannot release un-acquired lock', 1, None)

## co_names:
('_owner', 'get_ident', 'RuntimeError', '_count', '_block', 'release')

## bytecode:

   0: RESUME               
   2: LOAD_FAST            self
   4: LOAD_ATTR            _owner
  14: LOAD_GLOBAL          NULL + get_ident
  26: PRECALL              
  30: CALL                 
  40: COMPARE_OP           !=
  46: POP_JUMP_FORWARD_IF_FALSE to 78
  48: LOAD_GLOBAL          NULL + RuntimeError
  60: LOAD_CONST           'cannot release un-acquired lock'
  62: PRECALL              
  66: CALL                 
  76: RAISE_VARARGS        
  78: LOAD_FAST            self
  80: LOAD_ATTR            _count
  90: LOAD_CONST           1
  92: BINARY_OP            -
  96: COPY                 
  98: LOAD_FAST            self
 100: STORE_ATTR           _count
 110: STORE_FAST           count
 112: LOAD_FAST            count
 114: POP_JUMP_FORWARD_IF_TRUE to 184
 116: LOAD_CONST           None
 118: LOAD_FAST            self
 120: STORE_ATTR           _owner
 130: LOAD_FAST            self
 132: LOAD_ATTR            _block
 142: LOAD_METHOD          release
 164: PRECALL              
 168: CALL                 
 178: POP_TOP              
 180: LOAD_CONST           None
 182: RETURN_VALUE         
 184: LOAD_CONST           None
 186: RETURN_VALUE         
