# Disassembly for threading._RLock.__init__
# From module file: threading

## co_consts:
(None, 0)

## co_names:
('_allocate_lock', '_block', '_owner', '_count')

## bytecode:

   0: RESUME               
   2: LOAD_GLOBAL          NULL + _allocate_lock
  14: PRECALL              
  18: CALL                 
  28: LOAD_FAST            self
  30: STORE_ATTR           _block
  40: LOAD_CONST           None
  42: LOAD_FAST            self
  44: STORE_ATTR           _owner
  54: LOAD_CONST           0
  56: LOAD_FAST            self
  58: STORE_ATTR           _count
  68: LOAD_CONST           None
  70: RETURN_VALUE         
