# Disassembly for threading.BoundedSemaphore.__repr__
# From module file: threading

## co_consts:
(None, '<', '.', ' at ', '#x', ': value=', '/', '>')

## co_names:
('__class__', '__module__', '__qualname__', 'id', '_value', '_initial_value')

## bytecode:

   0: RESUME               
   2: LOAD_FAST            self
   4: LOAD_ATTR            __class__
  14: STORE_FAST           cls
  16: LOAD_CONST           '<'
  18: LOAD_FAST            cls
  20: LOAD_ATTR            __module__
  30: FORMAT_VALUE         
  32: LOAD_CONST           '.'
  34: LOAD_FAST            cls
  36: LOAD_ATTR            __qualname__
  46: FORMAT_VALUE         
  48: LOAD_CONST           ' at '
  50: LOAD_GLOBAL          NULL + id
  62: LOAD_FAST            self
  64: PRECALL              
  68: CALL                 
  78: LOAD_CONST           '#x'
  80: FORMAT_VALUE         with format
  82: LOAD_CONST           ': value='
  84: LOAD_FAST            self
  86: LOAD_ATTR            _value
  96: FORMAT_VALUE         
  98: LOAD_CONST           '/'
 100: LOAD_FAST            self
 102: LOAD_ATTR            _initial_value
 112: FORMAT_VALUE         
 114: LOAD_CONST           '>'
 116: BUILD_STRING         
 118: RETURN_VALUE         
