# Disassembly for threading.activeCount
# From module file: threading

## co_consts:
('Return the number of Thread objects currently alive.\n\n    This function is deprecated, use active_count() instead.\n\n    ', 0, None, 'activeCount() is deprecated, use active_count() instead', 2, ('stacklevel',))

## co_names:
('warnings', 'warn', 'DeprecationWarning', 'active_count')

## bytecode:

   0: RESUME               
   2: LOAD_CONST           0
   4: LOAD_CONST           None
   6: IMPORT_NAME          warnings
   8: STORE_FAST           warnings
  10: LOAD_FAST            warnings
  12: LOAD_METHOD          warn
  34: LOAD_CONST           'activeCount() is deprecated, use active_count() instead'
  36: LOAD_GLOBAL          DeprecationWarning
  48: LOAD_CONST           2
  50: KW_NAMES             
  52: PRECALL              
  56: CALL                 
  66: POP_TOP              
  68: LOAD_GLOBAL          NULL + active_count
  80: PRECALL              
  84: CALL                 
  94: RETURN_VALUE         
