# Disassembly for threading._MainThread.__init__
# From module file: threading

## co_consts:
(None, 'MainThread', False, ('name', 'daemon'))

## co_names:
('Thread', '__init__', '_set_tstate_lock', '_started', 'set', '_set_ident', '_HAVE_THREAD_NATIVE_ID', '_set_native_id', '_active_limbo_lock', '_active', '_ident')

## bytecode:

   0: RESUME               
   2: LOAD_GLOBAL          Thread
  14: LOAD_METHOD          __init__
  36: LOAD_FAST            self
  38: LOAD_CONST           'MainThread'
  40: LOAD_CONST           False
  42: KW_NAMES             
  44: PRECALL              
  48: CALL                 
  58: POP_TOP              
  60: LOAD_FAST            self
  62: LOAD_METHOD          _set_tstate_lock
  84: PRECALL              
  88: CALL                 
  98: POP_TOP              
 100: LOAD_FAST            self
 102: LOAD_ATTR            _started
 112: LOAD_METHOD          set
 134: PRECALL              
 138: CALL                 
 148: POP_TOP              
 150: LOAD_FAST            self
 152: LOAD_METHOD          _set_ident
 174: PRECALL              
 178: CALL                 
 188: POP_TOP              
 190: LOAD_GLOBAL          _HAVE_THREAD_NATIVE_ID
 202: POP_JUMP_FORWARD_IF_FALSE to 244
 204: LOAD_FAST            self
 206: LOAD_METHOD          _set_native_id
 228: PRECALL              
 232: CALL                 
 242: POP_TOP              
 244: LOAD_GLOBAL          _active_limbo_lock
 256: BEFORE_WITH          
 258: POP_TOP              
 260: LOAD_FAST            self
 262: LOAD_GLOBAL          _active
 274: LOAD_FAST            self
 276: LOAD_ATTR            _ident
 286: STORE_SUBSCR         
 290: LOAD_CONST           None
 292: LOAD_CONST           None
 294: LOAD_CONST           None
 296: PRECALL              
 300: CALL                 
 310: POP_TOP              
 312: LOAD_CONST           None
 314: RETURN_VALUE         
 316: PUSH_EXC_INFO        
 318: WITH_EXCEPT_START    
 320: POP_JUMP_FORWARD_IF_TRUE to 330
 322: RERAISE              
 324: COPY                 
 326: POP_EXCEPT           
 328: RERAISE              
 330: POP_TOP              
 332: POP_EXCEPT           
 334: POP_TOP              
 336: POP_TOP              
 338: LOAD_CONST           None
 340: RETURN_VALUE         
