# Disassembly for threading._maintain_shutdown_locks.<listcomp>
# From module file: threading

## co_consts:
()

## co_names:
('locked',)

## bytecode:

   0: RESUME               
   2: BUILD_LIST           
   4: LOAD_FAST            .0
   6: FOR_ITER             to 56
   8: STORE_FAST           lock
  10: LOAD_FAST            lock
  12: LOAD_METHOD          locked
  34: PRECALL              
  38: CALL                 
  48: POP_JUMP_BACKWARD_IF_TRUE to 6
  50: LOAD_FAST            lock
  52: LIST_APPEND          
  54: JUMP_BACKWARD        to 6
  56: RETURN_VALUE         
