# Disassembly for bisect.insort_left
# From module file: bisect

## co_consts:
('Insert item x in list a, and keep it sorted assuming a is sorted.\n\n    If x is already in a, insert it to the left of the leftmost x.\n\n    Optional args lo (default 0) and hi (default len(a)) bound the\n    slice of a to be searched.\n    ', None, ('key',))

## co_names:
('bisect_left', 'insert')

## bytecode:

   0: RESUME               
   2: LOAD_FAST            key
   4: POP_JUMP_FORWARD_IF_NOT_NONE to 44
   6: LOAD_GLOBAL          NULL + bisect_left
  18: LOAD_FAST            a
  20: LOAD_FAST            x
  22: LOAD_FAST            lo
  24: LOAD_FAST            hi
  26: PRECALL              
  30: CALL                 
  40: STORE_FAST           lo
  42: JUMP_FORWARD         to 102
  44: LOAD_GLOBAL          NULL + bisect_left
  56: LOAD_FAST            a
  58: PUSH_NULL            
  60: LOAD_FAST            key
  62: LOAD_FAST            x
  64: PRECALL              
  68: CALL                 
  78: LOAD_FAST            lo
  80: LOAD_FAST            hi
  82: LOAD_FAST            key
  84: KW_NAMES             
  86: PRECALL              
  90: CALL                 
 100: STORE_FAST           lo
 102: LOAD_FAST            a
 104: LOAD_METHOD          insert
 126: LOAD_FAST            lo
 128: LOAD_FAST            x
 130: PRECALL              
 134: CALL                 
 144: POP_TOP              
 146: LOAD_CONST           None
 148: RETURN_VALUE         
