# Disassembly for _pydecimal.Overflow
# From module file: _pydecimal

## co_consts:
('Overflow', 'Numerical overflow.\n\n    This occurs and signals overflow if the adjusted exponent of a result\n    (from a conversion or from an operation that is not an attempt to divide\n    by zero), after rounding, would be greater than the largest value that\n    can be handled by the implementation (the value Emax).\n\n    The result depends on the rounding mode:\n\n    For round-half-up and round-half-even (and for round-half-down and\n    round-up, if implemented), the result of the operation is [sign,inf],\n    where sign is the sign of the intermediate result.  For round-down, the\n    result is the largest finite number that can be represented in the\n    current precision, with the sign of the intermediate result.  For\n    round-ceiling, the result is the same as for round-down if the sign of\n    the intermediate result is 1, or is [0,inf] otherwise.  For round-floor,\n    the result is the same as for round-down if the sign of the intermediate\n    result is 0, or is [1,inf] otherwise.  In all cases, Inexact and Rounded\n    will also be raised.\n    ', <code object handle at 0x0000024068C5ABD0, file "_pydecimal.py", line 375>, None)

## co_names:
('__name__', '__module__', '__qualname__', '__doc__', 'handle')

## bytecode:

   0: RESUME               
   2: LOAD_NAME            __name__
   4: STORE_NAME           __module__
   6: LOAD_CONST           'Overflow'
   8: STORE_NAME           __qualname__
  10: LOAD_CONST           'Numerical overflow.\n\n    This occurs and signals overflow if the adjusted exponent of a result\n    (from a conversion or from an operation that is not an attempt to divide\n    by zero), after rounding, would be greater than the largest value that\n    can be handled by the implementation (the value Emax).\n\n    The result depends on the rounding mode:\n\n    For round-half-up and round-half-even (and for round-half-down and\n    round-up, if implemented), the result of the operation is [sign,inf],\n    where sign is the sign of the intermediate result.  For round-down, the\n    result is the largest finite number that can be represented in the\n    current precision, with the sign of the intermediate result.  For\n    round-ceiling, the result is the same as for round-down if the sign of\n    the intermediate result is 1, or is [0,inf] otherwise.  For round-floor,\n    the result is the same as for round-down if the sign of the intermediate\n    result is 0, or is [1,inf] otherwise.  In all cases, Inexact and Rounded\n    will also be raised.\n    '
  12: STORE_NAME           __doc__
  14: LOAD_CONST           <code object handle at 0x0000024068C5ABD0, file "_pydecimal.py", line 375>
  16: MAKE_FUNCTION        
  18: STORE_NAME           handle
  20: LOAD_CONST           None
  22: RETURN_VALUE         
