# Disassembly for _pydecimal.Decimal.__int__
# From module file: _pydecimal

## co_consts:
('Converts self to an int, truncating if necessary.', 'Cannot convert NaN to integer', 'Cannot convert infinity to integer', -1, 0, 10, None, '0')

## co_names:
('_is_special', '_isnan', 'ValueError', '_isinfinity', 'OverflowError', '_sign', '_exp', 'int', '_int')

## bytecode:

   0: RESUME               
   2: LOAD_FAST            self
   4: LOAD_ATTR            _is_special
  14: POP_JUMP_FORWARD_IF_FALSE to 156
  16: LOAD_FAST            self
  18: LOAD_METHOD          _isnan
  40: PRECALL              
  44: CALL                 
  54: POP_JUMP_FORWARD_IF_FALSE to 86
  56: LOAD_GLOBAL          NULL + ValueError
  68: LOAD_CONST           'Cannot convert NaN to integer'
  70: PRECALL              
  74: CALL                 
  84: RAISE_VARARGS        
  86: LOAD_FAST            self
  88: LOAD_METHOD          _isinfinity
 110: PRECALL              
 114: CALL                 
 124: POP_JUMP_FORWARD_IF_FALSE to 156
 126: LOAD_GLOBAL          NULL + OverflowError
 138: LOAD_CONST           'Cannot convert infinity to integer'
 140: PRECALL              
 144: CALL                 
 154: RAISE_VARARGS        
 156: LOAD_CONST           -1
 158: LOAD_FAST            self
 160: LOAD_ATTR            _sign
 170: BINARY_OP            **
 174: STORE_FAST           s
 176: LOAD_FAST            self
 178: LOAD_ATTR            _exp
 188: LOAD_CONST           0
 190: COMPARE_OP           >=
 196: POP_JUMP_FORWARD_IF_FALSE to 266
 198: LOAD_FAST            s
 200: LOAD_GLOBAL          NULL + int
 212: LOAD_FAST            self
 214: LOAD_ATTR            _int
 224: PRECALL              
 228: CALL                 
 238: BINARY_OP            *
 242: LOAD_CONST           10
 244: LOAD_FAST            self
 246: LOAD_ATTR            _exp
 256: BINARY_OP            **
 260: BINARY_OP            *
 264: RETURN_VALUE         
 266: LOAD_FAST            s
 268: LOAD_GLOBAL          NULL + int
 280: LOAD_FAST            self
 282: LOAD_ATTR            _int
 292: LOAD_CONST           None
 294: LOAD_FAST            self
 296: LOAD_ATTR            _exp
 306: BUILD_SLICE          
 308: BINARY_SUBSCR        
 318: JUMP_IF_TRUE_OR_POP  to 322
 320: LOAD_CONST           '0'
 322: PRECALL              
 326: CALL                 
 336: BINARY_OP            *
 340: RETURN_VALUE         
