# Disassembly for _pydecimal.Decimal._round_half_up
# From module file: _pydecimal

## co_consts:
('Rounds 5 up (away from 0)', '56789', 1, 0, -1)

## co_names:
('_int', '_all_zeros')

## bytecode:

   0: RESUME               
   2: LOAD_FAST            self
   4: LOAD_ATTR            _int
  14: LOAD_FAST            prec
  16: BINARY_SUBSCR        
  26: LOAD_CONST           '56789'
  28: CONTAINS_OP          
  30: POP_JUMP_FORWARD_IF_FALSE to 36
  32: LOAD_CONST           1
  34: RETURN_VALUE         
  36: LOAD_GLOBAL          NULL + _all_zeros
  48: LOAD_FAST            self
  50: LOAD_ATTR            _int
  60: LOAD_FAST            prec
  62: PRECALL              
  66: CALL                 
  76: POP_JUMP_FORWARD_IF_FALSE to 82
  78: LOAD_CONST           0
  80: RETURN_VALUE         
  82: LOAD_CONST           -1
  84: RETURN_VALUE         
