# Disassembly for _pydecimal.Decimal.__float__
# From module file: _pydecimal

## co_consts:
('Float representation.', 'Cannot convert signaling NaN to float', '-nan', 'nan')

## co_names:
('_isnan', 'is_snan', 'ValueError', '_sign', 'str', 'float')

## bytecode:

   0: RESUME               
   2: LOAD_FAST            self
   4: LOAD_METHOD          _isnan
  26: PRECALL              
  30: CALL                 
  40: POP_JUMP_FORWARD_IF_FALSE to 136
  42: LOAD_FAST            self
  44: LOAD_METHOD          is_snan
  66: PRECALL              
  70: CALL                 
  80: POP_JUMP_FORWARD_IF_FALSE to 112
  82: LOAD_GLOBAL          NULL + ValueError
  94: LOAD_CONST           'Cannot convert signaling NaN to float'
  96: PRECALL              
 100: CALL                 
 110: RAISE_VARARGS        
 112: LOAD_FAST            self
 114: LOAD_ATTR            _sign
 124: POP_JUMP_FORWARD_IF_FALSE to 130
 126: LOAD_CONST           '-nan'
 128: JUMP_FORWARD         to 132
 130: LOAD_CONST           'nan'
 132: STORE_FAST           s
 134: JUMP_FORWARD         to 166
 136: LOAD_GLOBAL          NULL + str
 148: LOAD_FAST            self
 150: PRECALL              
 154: CALL                 
 164: STORE_FAST           s
 166: LOAD_GLOBAL          NULL + float
 178: LOAD_FAST            s
 180: PRECALL              
 184: CALL                 
 194: RETURN_VALUE         
