# Disassembly for _pydecimal.Decimal.compare_total
# From module file: _pydecimal

## co_consts:
('Compares self to other using the abstract representations.\n\n        This is not like the standard compare, which use their numerical\n        value. Note that a total ordering is defined for all possible abstract\n        representations.\n        ', True, ('raiseit',), 1, 2)

## co_names:
('_convert_other', '_sign', '_NegativeOne', '_One', '_isnan', 'len', '_int', '_Zero', '_exp')

## bytecode:

   0: RESUME               
   2: LOAD_GLOBAL          NULL + _convert_other
  14: LOAD_FAST            other
  16: LOAD_CONST           True
  18: KW_NAMES             
  20: PRECALL              
  24: CALL                 
  34: STORE_FAST           other
  36: LOAD_FAST            self
  38: LOAD_ATTR            _sign
  48: POP_JUMP_FORWARD_IF_FALSE to 78
  50: LOAD_FAST            other
  52: LOAD_ATTR            _sign
  62: POP_JUMP_FORWARD_IF_TRUE to 78
  64: LOAD_GLOBAL          _NegativeOne
  76: RETURN_VALUE         
  78: LOAD_FAST            self
  80: LOAD_ATTR            _sign
  90: POP_JUMP_FORWARD_IF_TRUE to 120
  92: LOAD_FAST            other
  94: LOAD_ATTR            _sign
 104: POP_JUMP_FORWARD_IF_FALSE to 120
 106: LOAD_GLOBAL          _One
 118: RETURN_VALUE         
 120: LOAD_FAST            self
 122: LOAD_ATTR            _sign
 132: STORE_FAST           sign
 134: LOAD_FAST            self
 136: LOAD_METHOD          _isnan
 158: PRECALL              
 162: CALL                 
 172: STORE_FAST           self_nan
 174: LOAD_FAST            other
 176: LOAD_METHOD          _isnan
 198: PRECALL              
 202: CALL                 
 212: STORE_FAST           other_nan
 214: LOAD_FAST            self_nan
 216: POP_JUMP_FORWARD_IF_TRUE to 222
 218: LOAD_FAST            other_nan
 220: POP_JUMP_FORWARD_IF_FALSE to 658
 222: LOAD_FAST            self_nan
 224: LOAD_FAST            other_nan
 226: COMPARE_OP           ==
 232: POP_JUMP_FORWARD_IF_FALSE to 444
 234: LOAD_GLOBAL          NULL + len
 246: LOAD_FAST            self
 248: LOAD_ATTR            _int
 258: PRECALL              
 262: CALL                 
 272: LOAD_FAST            self
 274: LOAD_ATTR            _int
 284: BUILD_TUPLE          
 286: STORE_FAST           self_key
 288: LOAD_GLOBAL          NULL + len
 300: LOAD_FAST            other
 302: LOAD_ATTR            _int
 312: PRECALL              
 316: CALL                 
 326: LOAD_FAST            other
 328: LOAD_ATTR            _int
 338: BUILD_TUPLE          
 340: STORE_FAST           other_key
 342: LOAD_FAST            self_key
 344: LOAD_FAST            other_key
 346: COMPARE_OP           <
 352: POP_JUMP_FORWARD_IF_FALSE to 386
 354: LOAD_FAST            sign
 356: POP_JUMP_FORWARD_IF_FALSE to 372
 358: LOAD_GLOBAL          _One
 370: RETURN_VALUE         
 372: LOAD_GLOBAL          _NegativeOne
 384: RETURN_VALUE         
 386: LOAD_FAST            self_key
 388: LOAD_FAST            other_key
 390: COMPARE_OP           >
 396: POP_JUMP_FORWARD_IF_FALSE to 430
 398: LOAD_FAST            sign
 400: POP_JUMP_FORWARD_IF_FALSE to 416
 402: LOAD_GLOBAL          _NegativeOne
 414: RETURN_VALUE         
 416: LOAD_GLOBAL          _One
 428: RETURN_VALUE         
 430: LOAD_GLOBAL          _Zero
 442: RETURN_VALUE         
 444: LOAD_FAST            sign
 446: POP_JUMP_FORWARD_IF_FALSE to 554
 448: LOAD_FAST            self_nan
 450: LOAD_CONST           1
 452: COMPARE_OP           ==
 458: POP_JUMP_FORWARD_IF_FALSE to 474
 460: LOAD_GLOBAL          _NegativeOne
 472: RETURN_VALUE         
 474: LOAD_FAST            other_nan
 476: LOAD_CONST           1
 478: COMPARE_OP           ==
 484: POP_JUMP_FORWARD_IF_FALSE to 500
 486: LOAD_GLOBAL          _One
 498: RETURN_VALUE         
 500: LOAD_FAST            self_nan
 502: LOAD_CONST           2
 504: COMPARE_OP           ==
 510: POP_JUMP_FORWARD_IF_FALSE to 526
 512: LOAD_GLOBAL          _NegativeOne
 524: RETURN_VALUE         
 526: LOAD_FAST            other_nan
 528: LOAD_CONST           2
 530: COMPARE_OP           ==
 536: POP_JUMP_FORWARD_IF_FALSE to 552
 538: LOAD_GLOBAL          _One
 550: RETURN_VALUE         
 552: JUMP_FORWARD         to 658
 554: LOAD_FAST            self_nan
 556: LOAD_CONST           1
 558: COMPARE_OP           ==
 564: POP_JUMP_FORWARD_IF_FALSE to 580
 566: LOAD_GLOBAL          _One
 578: RETURN_VALUE         
 580: LOAD_FAST            other_nan
 582: LOAD_CONST           1
 584: COMPARE_OP           ==
 590: POP_JUMP_FORWARD_IF_FALSE to 606
 592: LOAD_GLOBAL          _NegativeOne
 604: RETURN_VALUE         
 606: LOAD_FAST            self_nan
 608: LOAD_CONST           2
 610: COMPARE_OP           ==
 616: POP_JUMP_FORWARD_IF_FALSE to 632
 618: LOAD_GLOBAL          _One
 630: RETURN_VALUE         
 632: LOAD_FAST            other_nan
 634: LOAD_CONST           2
 636: COMPARE_OP           ==
 642: POP_JUMP_FORWARD_IF_FALSE to 658
 644: LOAD_GLOBAL          _NegativeOne
 656: RETURN_VALUE         
 658: LOAD_FAST            self
 660: LOAD_FAST            other
 662: COMPARE_OP           <
 668: POP_JUMP_FORWARD_IF_FALSE to 684
 670: LOAD_GLOBAL          _NegativeOne
 682: RETURN_VALUE         
 684: LOAD_FAST            self
 686: LOAD_FAST            other
 688: COMPARE_OP           >
 694: POP_JUMP_FORWARD_IF_FALSE to 710
 696: LOAD_GLOBAL          _One
 708: RETURN_VALUE         
 710: LOAD_FAST            self
 712: LOAD_ATTR            _exp
 722: LOAD_FAST            other
 724: LOAD_ATTR            _exp
 734: COMPARE_OP           <
 740: POP_JUMP_FORWARD_IF_FALSE to 774
 742: LOAD_FAST            sign
 744: POP_JUMP_FORWARD_IF_FALSE to 760
 746: LOAD_GLOBAL          _One
 758: RETURN_VALUE         
 760: LOAD_GLOBAL          _NegativeOne
 772: RETURN_VALUE         
 774: LOAD_FAST            self
 776: LOAD_ATTR            _exp
 786: LOAD_FAST            other
 788: LOAD_ATTR            _exp
 798: COMPARE_OP           >
 804: POP_JUMP_FORWARD_IF_FALSE to 838
 806: LOAD_FAST            sign
 808: POP_JUMP_FORWARD_IF_FALSE to 824
 810: LOAD_GLOBAL          _NegativeOne
 822: RETURN_VALUE         
 824: LOAD_GLOBAL          _One
 836: RETURN_VALUE         
 838: LOAD_GLOBAL          _Zero
 850: RETURN_VALUE         
