# Disassembly for _pydecimal.DivisionImpossible
# From module file: _pydecimal

## co_consts:
('DivisionImpossible', 'Cannot perform the division adequately.\n\n    This occurs and signals invalid-operation if the integer result of a\n    divide-integer or remainder operation had too many digits (would be\n    longer than precision).  The result is [0,qNaN].\n    ', <code object handle at 0x0000024069497020, file "_pydecimal.py", line 290>, None)

## co_names:
('__name__', '__module__', '__qualname__', '__doc__', 'handle')

## bytecode:

   0: RESUME               
   2: LOAD_NAME            __name__
   4: STORE_NAME           __module__
   6: LOAD_CONST           'DivisionImpossible'
   8: STORE_NAME           __qualname__
  10: LOAD_CONST           'Cannot perform the division adequately.\n\n    This occurs and signals invalid-operation if the integer result of a\n    divide-integer or remainder operation had too many digits (would be\n    longer than precision).  The result is [0,qNaN].\n    '
  12: STORE_NAME           __doc__
  14: LOAD_CONST           <code object handle at 0x0000024069497020, file "_pydecimal.py", line 290>
  16: MAKE_FUNCTION        
  18: STORE_NAME           handle
  20: LOAD_CONST           None
  22: RETURN_VALUE         
