# Disassembly for _pydecimal.Decimal.__divmod__
# From module file: _pydecimal

## co_consts:
('\n        Return (self // other, self % other)\n        ', None, 'divmod(INF, INF)', 'INF % x', 'divmod(0, 0)', 'x // 0', 'x % 0')

## co_names:
('_convert_other', 'NotImplemented', 'getcontext', '_check_nans', '_sign', '_isinfinity', '_raise_error', 'InvalidOperation', '_SignedInfinity', 'DivisionUndefined', 'DivisionByZero', '_divide', '_fix')

## bytecode:

   0: RESUME               
   2: LOAD_GLOBAL          NULL + _convert_other
  14: LOAD_FAST            other
  16: PRECALL              
  20: CALL                 
  30: STORE_FAST           other
  32: LOAD_FAST            other
  34: LOAD_GLOBAL          NotImplemented
  46: IS_OP                
  48: POP_JUMP_FORWARD_IF_FALSE to 54
  50: LOAD_FAST            other
  52: RETURN_VALUE         
  54: LOAD_FAST            context
  56: POP_JUMP_FORWARD_IF_NOT_NONE to 86
  58: LOAD_GLOBAL          NULL + getcontext
  70: PRECALL              
  74: CALL                 
  84: STORE_FAST           context
  86: LOAD_FAST            self
  88: LOAD_METHOD          _check_nans
 110: LOAD_FAST            other
 112: LOAD_FAST            context
 114: PRECALL              
 118: CALL                 
 128: STORE_FAST           ans
 130: LOAD_FAST            ans
 132: POP_JUMP_FORWARD_IF_FALSE to 142
 134: LOAD_FAST            ans
 136: LOAD_FAST            ans
 138: BUILD_TUPLE          
 140: RETURN_VALUE         
 142: LOAD_FAST            self
 144: LOAD_ATTR            _sign
 154: LOAD_FAST            other
 156: LOAD_ATTR            _sign
 166: BINARY_OP            ^
 170: STORE_FAST           sign
 172: LOAD_FAST            self
 174: LOAD_METHOD          _isinfinity
 196: PRECALL              
 200: CALL                 
 210: POP_JUMP_FORWARD_IF_FALSE to 394
 212: LOAD_FAST            other
 214: LOAD_METHOD          _isinfinity
 236: PRECALL              
 240: CALL                 
 250: POP_JUMP_FORWARD_IF_FALSE to 314
 252: LOAD_FAST            context
 254: LOAD_METHOD          _raise_error
 276: LOAD_GLOBAL          InvalidOperation
 288: LOAD_CONST           'divmod(INF, INF)'
 290: PRECALL              
 294: CALL                 
 304: STORE_FAST           ans
 306: LOAD_FAST            ans
 308: LOAD_FAST            ans
 310: BUILD_TUPLE          
 312: RETURN_VALUE         
 314: LOAD_GLOBAL          _SignedInfinity
 326: LOAD_FAST            sign
 328: BINARY_SUBSCR        
 338: LOAD_FAST            context
 340: LOAD_METHOD          _raise_error
 362: LOAD_GLOBAL          InvalidOperation
 374: LOAD_CONST           'INF % x'
 376: PRECALL              
 380: CALL                 
 390: BUILD_TUPLE          
 392: RETURN_VALUE         
 394: LOAD_FAST            other
 396: POP_JUMP_FORWARD_IF_TRUE to 574
 398: LOAD_FAST            self
 400: POP_JUMP_FORWARD_IF_TRUE to 464
 402: LOAD_FAST            context
 404: LOAD_METHOD          _raise_error
 426: LOAD_GLOBAL          DivisionUndefined
 438: LOAD_CONST           'divmod(0, 0)'
 440: PRECALL              
 444: CALL                 
 454: STORE_FAST           ans
 456: LOAD_FAST            ans
 458: LOAD_FAST            ans
 460: BUILD_TUPLE          
 462: RETURN_VALUE         
 464: LOAD_FAST            context
 466: LOAD_METHOD          _raise_error
 488: LOAD_GLOBAL          DivisionByZero
 500: LOAD_CONST           'x // 0'
 502: LOAD_FAST            sign
 504: PRECALL              
 508: CALL                 
 518: LOAD_FAST            context
 520: LOAD_METHOD          _raise_error
 542: LOAD_GLOBAL          InvalidOperation
 554: LOAD_CONST           'x % 0'
 556: PRECALL              
 560: CALL                 
 570: BUILD_TUPLE          
 572: RETURN_VALUE         
 574: LOAD_FAST            self
 576: LOAD_METHOD          _divide
 598: LOAD_FAST            other
 600: LOAD_FAST            context
 602: PRECALL              
 606: CALL                 
 616: UNPACK_SEQUENCE      
 620: STORE_FAST           quotient
 622: STORE_FAST           remainder
 624: LOAD_FAST            remainder
 626: LOAD_METHOD          _fix
 648: LOAD_FAST            context
 650: PRECALL              
 654: CALL                 
 664: STORE_FAST           remainder
 666: LOAD_FAST            quotient
 668: LOAD_FAST            remainder
 670: BUILD_TUPLE          
 672: RETURN_VALUE         
