# Disassembly for _pydecimal.Context.min
# From module file: _pydecimal

## co_consts:
("min compares two values numerically and returns the minimum.\n\n        If either operand is a NaN then the general rules apply.\n        Otherwise, the operands are compared as though by the compare\n        operation.  If they are numerically equal then the left-hand operand\n        is chosen as the result.  Otherwise the minimum (closer to negative\n        infinity) of the two operands is chosen as the result.\n\n        >>> ExtendedContext.min(Decimal('3'), Decimal('2'))\n        Decimal('2')\n        >>> ExtendedContext.min(Decimal('-10'), Decimal('3'))\n        Decimal('-10')\n        >>> ExtendedContext.min(Decimal('1.0'), Decimal('1'))\n        Decimal('1.0')\n        >>> ExtendedContext.min(Decimal('7'), Decimal('NaN'))\n        Decimal('7')\n        >>> ExtendedContext.min(1, 2)\n        Decimal('1')\n        >>> ExtendedContext.min(Decimal(1), 2)\n        Decimal('1')\n        >>> ExtendedContext.min(1, Decimal(29))\n        Decimal('1')\n        ", True, ('raiseit',), ('context',))

## co_names:
('_convert_other', 'min')

## bytecode:

   0: RESUME               
   2: LOAD_GLOBAL          NULL + _convert_other
  14: LOAD_FAST            a
  16: LOAD_CONST           True
  18: KW_NAMES             
  20: PRECALL              
  24: CALL                 
  34: STORE_FAST           a
  36: LOAD_FAST            a
  38: LOAD_METHOD          min
  60: LOAD_FAST            b
  62: LOAD_FAST            self
  64: KW_NAMES             
  66: PRECALL              
  70: CALL                 
  80: RETURN_VALUE         
