# Disassembly for _pydecimal.Subnormal
# From module file: _pydecimal

## co_consts:
('Subnormal', 'Exponent < Emin before rounding.\n\n    This occurs and signals subnormal whenever the result of a conversion or\n    operation is subnormal (that is, its adjusted exponent is less than\n    Emin, before any rounding).  The result in all cases is unchanged.\n\n    The subnormal signal may be tested (or trapped) to determine if a given\n    or operation (or sequence of operations) yielded a subnormal result.\n    ', None)

## co_names:
('__name__', '__module__', '__qualname__', '__doc__')

## bytecode:

   0: RESUME               
   2: LOAD_NAME            __name__
   4: STORE_NAME           __module__
   6: LOAD_CONST           'Subnormal'
   8: STORE_NAME           __qualname__
  10: LOAD_CONST           'Exponent < Emin before rounding.\n\n    This occurs and signals subnormal whenever the result of a conversion or\n    operation is subnormal (that is, its adjusted exponent is less than\n    Emin, before any rounding).  The result in all cases is unchanged.\n\n    The subnormal signal may be tested (or trapped) to determine if a given\n    or operation (or sequence of operations) yielded a subnormal result.\n    '
  12: STORE_NAME           __doc__
  14: LOAD_CONST           None
  16: RETURN_VALUE         
