# Disassembly for _pydecimal.Context.__init__.<genexpr>
# From module file: _pydecimal

## co_consts:
(None,)

## co_names:
('int',)

## bytecode:

   0: COPY_FREE_VARS       
   2: RETURN_GENERATOR     
   4: POP_TOP              
   6: RESUME               
   8: LOAD_FAST            .0
  10: FOR_ITER             to 58
  12: STORE_FAST           s
  14: LOAD_FAST            s
  16: LOAD_GLOBAL          NULL + int
  28: LOAD_FAST            s
  30: LOAD_DEREF           flags
  32: CONTAINS_OP          
  34: PRECALL              
  38: CALL                 
  48: BUILD_TUPLE          
  50: YIELD_VALUE          
  52: RESUME               
  54: POP_TOP              
  56: JUMP_BACKWARD        to 10
  58: LOAD_CONST           None
  60: RETURN_VALUE         
