# Disassembly for _pydecimal.Decimal._fill_logical
# From module file: _pydecimal

## co_consts:
(None, 0, '0')

## co_names:
('prec', 'len')

## bytecode:

   0: RESUME               
   2: LOAD_FAST            context
   4: LOAD_ATTR            prec
  14: LOAD_GLOBAL          NULL + len
  26: LOAD_FAST            opa
  28: PRECALL              
  32: CALL                 
  42: BINARY_OP            -
  46: STORE_FAST           dif
  48: LOAD_FAST            dif
  50: LOAD_CONST           0
  52: COMPARE_OP           >
  58: POP_JUMP_FORWARD_IF_FALSE to 78
  60: LOAD_CONST           '0'
  62: LOAD_FAST            dif
  64: BINARY_OP            *
  68: LOAD_FAST            opa
  70: BINARY_OP            +
  74: STORE_FAST           opa
  76: JUMP_FORWARD         to 122
  78: LOAD_FAST            dif
  80: LOAD_CONST           0
  82: COMPARE_OP           <
  88: POP_JUMP_FORWARD_IF_FALSE to 122
  90: LOAD_FAST            opa
  92: LOAD_FAST            context
  94: LOAD_ATTR            prec
 104: UNARY_NEGATIVE       
 106: LOAD_CONST           None
 108: BUILD_SLICE          
 110: BINARY_SUBSCR        
 120: STORE_FAST           opa
 122: LOAD_FAST            context
 124: LOAD_ATTR            prec
 134: LOAD_GLOBAL          NULL + len
 146: LOAD_FAST            opb
 148: PRECALL              
 152: CALL                 
 162: BINARY_OP            -
 166: STORE_FAST           dif
 168: LOAD_FAST            dif
 170: LOAD_CONST           0
 172: COMPARE_OP           >
 178: POP_JUMP_FORWARD_IF_FALSE to 198
 180: LOAD_CONST           '0'
 182: LOAD_FAST            dif
 184: BINARY_OP            *
 188: LOAD_FAST            opb
 190: BINARY_OP            +
 194: STORE_FAST           opb
 196: JUMP_FORWARD         to 242
 198: LOAD_FAST            dif
 200: LOAD_CONST           0
 202: COMPARE_OP           <
 208: POP_JUMP_FORWARD_IF_FALSE to 242
 210: LOAD_FAST            opb
 212: LOAD_FAST            context
 214: LOAD_ATTR            prec
 224: UNARY_NEGATIVE       
 226: LOAD_CONST           None
 228: BUILD_SLICE          
 230: BINARY_SUBSCR        
 240: STORE_FAST           opb
 242: LOAD_FAST            opa
 244: LOAD_FAST            opb
 246: BUILD_TUPLE          
 248: RETURN_VALUE         
