# Disassembly for _pydecimal.Context.to_sci_string
# From module file: _pydecimal

## co_consts:
('Converts a number to a string, using scientific notation.\n\n        The operation is not affected by the context.\n        ', True, ('raiseit',), ('context',))

## co_names:
('_convert_other', '__str__')

## bytecode:

   0: RESUME               
   2: LOAD_GLOBAL          NULL + _convert_other
  14: LOAD_FAST            a
  16: LOAD_CONST           True
  18: KW_NAMES             
  20: PRECALL              
  24: CALL                 
  34: STORE_FAST           a
  36: LOAD_FAST            a
  38: LOAD_METHOD          __str__
  60: LOAD_FAST            self
  62: KW_NAMES             
  64: PRECALL              
  68: CALL                 
  78: RETURN_VALUE         
