# Disassembly for _pydecimal.Decimal.__hash__
# From module file: _pydecimal

## co_consts:
('x.__hash__() <==> hash(x)', 'Cannot hash a signaling NaN value.', 0, 10, -1, -2)

## co_names:
('_is_special', 'is_snan', 'TypeError', 'is_nan', 'object', '__hash__', '_sign', '_PyHASH_INF', '_exp', 'pow', '_PyHASH_MODULUS', '_PyHASH_10INV', 'int', '_int')

## bytecode:

   0: RESUME               
   2: LOAD_FAST            self
   4: LOAD_ATTR            _is_special
  14: POP_JUMP_FORWARD_IF_FALSE to 222
  16: LOAD_FAST            self
  18: LOAD_METHOD          is_snan
  40: PRECALL              
  44: CALL                 
  54: POP_JUMP_FORWARD_IF_FALSE to 86
  56: LOAD_GLOBAL          NULL + TypeError
  68: LOAD_CONST           'Cannot hash a signaling NaN value.'
  70: PRECALL              
  74: CALL                 
  84: RAISE_VARARGS        
  86: LOAD_FAST            self
  88: LOAD_METHOD          is_nan
 110: PRECALL              
 114: CALL                 
 124: POP_JUMP_FORWARD_IF_FALSE to 178
 126: LOAD_GLOBAL          object
 138: LOAD_METHOD          __hash__
 160: LOAD_FAST            self
 162: PRECALL              
 166: CALL                 
 176: RETURN_VALUE         
 178: LOAD_FAST            self
 180: LOAD_ATTR            _sign
 190: POP_JUMP_FORWARD_IF_FALSE to 208
 192: LOAD_GLOBAL          _PyHASH_INF
 204: UNARY_NEGATIVE       
 206: RETURN_VALUE         
 208: LOAD_GLOBAL          _PyHASH_INF
 220: RETURN_VALUE         
 222: LOAD_FAST            self
 224: LOAD_ATTR            _exp
 234: LOAD_CONST           0
 236: COMPARE_OP           >=
 242: POP_JUMP_FORWARD_IF_FALSE to 300
 244: LOAD_GLOBAL          NULL + pow
 256: LOAD_CONST           10
 258: LOAD_FAST            self
 260: LOAD_ATTR            _exp
 270: LOAD_GLOBAL          _PyHASH_MODULUS
 282: PRECALL              
 286: CALL                 
 296: STORE_FAST           exp_hash
 298: JUMP_FORWARD         to 366
 300: LOAD_GLOBAL          NULL + pow
 312: LOAD_GLOBAL          _PyHASH_10INV
 324: LOAD_FAST            self
 326: LOAD_ATTR            _exp
 336: UNARY_NEGATIVE       
 338: LOAD_GLOBAL          _PyHASH_MODULUS
 350: PRECALL              
 354: CALL                 
 364: STORE_FAST           exp_hash
 366: LOAD_GLOBAL          NULL + int
 378: LOAD_FAST            self
 380: LOAD_ATTR            _int
 390: PRECALL              
 394: CALL                 
 404: LOAD_FAST            exp_hash
 406: BINARY_OP            *
 410: LOAD_GLOBAL          _PyHASH_MODULUS
 422: BINARY_OP            %
 426: STORE_FAST           hash_
 428: LOAD_FAST            self
 430: LOAD_CONST           0
 432: COMPARE_OP           >=
 438: POP_JUMP_FORWARD_IF_FALSE to 444
 440: LOAD_FAST            hash_
 442: JUMP_FORWARD         to 448
 444: LOAD_FAST            hash_
 446: UNARY_NEGATIVE       
 448: STORE_FAST           ans
 450: LOAD_FAST            ans
 452: LOAD_CONST           -1
 454: COMPARE_OP           ==
 460: POP_JUMP_FORWARD_IF_FALSE to 466
 462: LOAD_CONST           -2
 464: JUMP_FORWARD         to 468
 466: LOAD_FAST            ans
 468: RETURN_VALUE         
