# Disassembly for _pydecimal.setcontext
# From module file: _pydecimal

## co_consts:
("Set this thread's context to context.", None)

## co_names:
('DefaultContext', 'BasicContext', 'ExtendedContext', 'copy', 'clear_flags', '_current_context_var', 'set')

## bytecode:

   0: RESUME               
   2: LOAD_FAST            context
   4: LOAD_GLOBAL          DefaultContext
  16: LOAD_GLOBAL          BasicContext
  28: LOAD_GLOBAL          ExtendedContext
  40: BUILD_TUPLE          
  42: CONTAINS_OP          
  44: POP_JUMP_FORWARD_IF_FALSE to 126
  46: LOAD_FAST            context
  48: LOAD_METHOD          copy
  70: PRECALL              
  74: CALL                 
  84: STORE_FAST           context
  86: LOAD_FAST            context
  88: LOAD_METHOD          clear_flags
 110: PRECALL              
 114: CALL                 
 124: POP_TOP              
 126: LOAD_GLOBAL          _current_context_var
 138: LOAD_METHOD          set
 160: LOAD_FAST            context
 162: PRECALL              
 166: CALL                 
 176: POP_TOP              
 178: LOAD_CONST           None
 180: RETURN_VALUE         
