# Disassembly for _pydecimal.Decimal.__deepcopy__
# From module file: _pydecimal

## co_consts:
(None,)

## co_names:
('type', 'Decimal', '__class__', 'str')

## bytecode:

   0: RESUME               
   2: LOAD_GLOBAL          NULL + type
  14: LOAD_FAST            self
  16: PRECALL              
  20: CALL                 
  30: LOAD_GLOBAL          Decimal
  42: IS_OP                
  44: POP_JUMP_FORWARD_IF_FALSE to 50
  46: LOAD_FAST            self
  48: RETURN_VALUE         
  50: LOAD_FAST            self
  52: LOAD_METHOD          __class__
  74: LOAD_GLOBAL          NULL + str
  86: LOAD_FAST            self
  88: PRECALL              
  92: CALL                 
 102: PRECALL              
 106: CALL                 
 116: RETURN_VALUE         
