# Disassembly for _pydecimal.Decimal.next_plus
# From module file: _pydecimal

## co_consts:
('Returns the smallest representable number larger than itself.', None, ('context',), 1, -1, '9', 0, '1')

## co_names:
('getcontext', '_check_nans', '_isinfinity', '_Infinity', '_dec_from_triple', 'prec', 'Etop', 'copy', '_set_rounding', 'ROUND_CEILING', '_ignore_all_flags', '_fix', '__add__', 'Etiny')

## bytecode:

   0: RESUME               
   2: LOAD_FAST            context
   4: POP_JUMP_FORWARD_IF_NOT_NONE to 34
   6: LOAD_GLOBAL          NULL + getcontext
  18: PRECALL              
  22: CALL                 
  32: STORE_FAST           context
  34: LOAD_FAST            self
  36: LOAD_METHOD          _check_nans
  58: LOAD_FAST            context
  60: KW_NAMES             
  62: PRECALL              
  66: CALL                 
  76: STORE_FAST           ans
  78: LOAD_FAST            ans
  80: POP_JUMP_FORWARD_IF_FALSE to 86
  82: LOAD_FAST            ans
  84: RETURN_VALUE         
  86: LOAD_FAST            self
  88: LOAD_METHOD          _isinfinity
 110: PRECALL              
 114: CALL                 
 124: LOAD_CONST           1
 126: COMPARE_OP           ==
 132: POP_JUMP_FORWARD_IF_FALSE to 148
 134: LOAD_GLOBAL          _Infinity
 146: RETURN_VALUE         
 148: LOAD_FAST            self
 150: LOAD_METHOD          _isinfinity
 172: PRECALL              
 176: CALL                 
 186: LOAD_CONST           -1
 188: COMPARE_OP           ==
 194: POP_JUMP_FORWARD_IF_FALSE to 282
 196: LOAD_GLOBAL          NULL + _dec_from_triple
 208: LOAD_CONST           1
 210: LOAD_CONST           '9'
 212: LOAD_FAST            context
 214: LOAD_ATTR            prec
 224: BINARY_OP            *
 228: LOAD_FAST            context
 230: LOAD_METHOD          Etop
 252: PRECALL              
 256: CALL                 
 266: PRECALL              
 270: CALL                 
 280: RETURN_VALUE         
 282: LOAD_FAST            context
 284: LOAD_METHOD          copy
 306: PRECALL              
 310: CALL                 
 320: STORE_FAST           context
 322: LOAD_FAST            context
 324: LOAD_METHOD          _set_rounding
 346: LOAD_GLOBAL          ROUND_CEILING
 358: PRECALL              
 362: CALL                 
 372: POP_TOP              
 374: LOAD_FAST            context
 376: LOAD_METHOD          _ignore_all_flags
 398: PRECALL              
 402: CALL                 
 412: POP_TOP              
 414: LOAD_FAST            self
 416: LOAD_METHOD          _fix
 438: LOAD_FAST            context
 440: PRECALL              
 444: CALL                 
 454: STORE_FAST           new_self
 456: LOAD_FAST            new_self
 458: LOAD_FAST            self
 460: COMPARE_OP           !=
 466: POP_JUMP_FORWARD_IF_FALSE to 472
 468: LOAD_FAST            new_self
 470: RETURN_VALUE         
 472: LOAD_FAST            self
 474: LOAD_METHOD          __add__
 496: LOAD_GLOBAL          NULL + _dec_from_triple
 508: LOAD_CONST           0
 510: LOAD_CONST           '1'
 512: LOAD_FAST            context
 514: LOAD_METHOD          Etiny
 536: PRECALL              
 540: CALL                 
 550: LOAD_CONST           1
 552: BINARY_OP            -
 556: PRECALL              
 560: CALL                 
 570: LOAD_FAST            context
 572: PRECALL              
 576: CALL                 
 586: RETURN_VALUE         
