# Disassembly for _pydecimal.Context.canonical
# From module file: _pydecimal

## co_consts:
("Returns the same Decimal object.\n\n        As we do not have different encodings for the same number, the\n        received object already is in its canonical form.\n\n        >>> ExtendedContext.canonical(Decimal('2.50'))\n        Decimal('2.50')\n        ", 'canonical requires a Decimal as an argument.')

## co_names:
('isinstance', 'Decimal', 'TypeError', 'canonical')

## bytecode:

   0: RESUME               
   2: LOAD_GLOBAL          NULL + isinstance
  14: LOAD_FAST            a
  16: LOAD_GLOBAL          Decimal
  28: PRECALL              
  32: CALL                 
  42: POP_JUMP_FORWARD_IF_TRUE to 74
  44: LOAD_GLOBAL          NULL + TypeError
  56: LOAD_CONST           'canonical requires a Decimal as an argument.'
  58: PRECALL              
  62: CALL                 
  72: RAISE_VARARGS        
  74: LOAD_FAST            a
  76: LOAD_METHOD          canonical
  98: PRECALL              
 102: CALL                 
 112: RETURN_VALUE         
