# Disassembly for _pydecimal.Context.remainder
# From module file: _pydecimal

## co_consts:
("Returns the remainder from integer division.\n\n        The result is the residue of the dividend after the operation of\n        calculating integer division as described for divide-integer, rounded\n        to precision digits if necessary.  The sign of the result, if\n        non-zero, is the same as that of the original dividend.\n\n        This operation will fail under the same conditions as integer division\n        (that is, if integer division on the same two operands would fail, the\n        remainder cannot be calculated).\n\n        >>> ExtendedContext.remainder(Decimal('2.1'), Decimal('3'))\n        Decimal('2.1')\n        >>> ExtendedContext.remainder(Decimal('10'), Decimal('3'))\n        Decimal('1')\n        >>> ExtendedContext.remainder(Decimal('-10'), Decimal('3'))\n        Decimal('-1')\n        >>> ExtendedContext.remainder(Decimal('10.2'), Decimal('1'))\n        Decimal('0.2')\n        >>> ExtendedContext.remainder(Decimal('10'), Decimal('0.3'))\n        Decimal('0.1')\n        >>> ExtendedContext.remainder(Decimal('3.6'), Decimal('1.3'))\n        Decimal('1.0')\n        >>> ExtendedContext.remainder(22, 6)\n        Decimal('4')\n        >>> ExtendedContext.remainder(Decimal(22), 6)\n        Decimal('4')\n        >>> ExtendedContext.remainder(22, Decimal(6))\n        Decimal('4')\n        ", True, ('raiseit',), ('context',), 'Unable to convert %s to Decimal')

## co_names:
('_convert_other', '__mod__', 'NotImplemented', 'TypeError')

## bytecode:

   0: RESUME               
   2: LOAD_GLOBAL          NULL + _convert_other
  14: LOAD_FAST            a
  16: LOAD_CONST           True
  18: KW_NAMES             
  20: PRECALL              
  24: CALL                 
  34: STORE_FAST           a
  36: LOAD_FAST            a
  38: LOAD_METHOD          __mod__
  60: LOAD_FAST            b
  62: LOAD_FAST            self
  64: KW_NAMES             
  66: PRECALL              
  70: CALL                 
  80: STORE_FAST           r
  82: LOAD_FAST            r
  84: LOAD_GLOBAL          NotImplemented
  96: IS_OP                
  98: POP_JUMP_FORWARD_IF_FALSE to 136
 100: LOAD_GLOBAL          NULL + TypeError
 112: LOAD_CONST           'Unable to convert %s to Decimal'
 114: LOAD_FAST            b
 116: BINARY_OP            %
 120: PRECALL              
 124: CALL                 
 134: RAISE_VARARGS        
 136: LOAD_FAST            r
 138: RETURN_VALUE         
