# Disassembly for _pydecimal.Context.is_canonical
# From module file: _pydecimal

## co_consts:
("Return True if the operand is canonical; otherwise return False.\n\n        Currently, the encoding of a Decimal instance is always\n        canonical, so this method returns True for any Decimal.\n\n        >>> ExtendedContext.is_canonical(Decimal('2.50'))\n        True\n        ", 'is_canonical requires a Decimal as an argument.')

## co_names:
('isinstance', 'Decimal', 'TypeError', 'is_canonical')

## bytecode:

   0: RESUME               
   2: LOAD_GLOBAL          NULL + isinstance
  14: LOAD_FAST            a
  16: LOAD_GLOBAL          Decimal
  28: PRECALL              
  32: CALL                 
  42: POP_JUMP_FORWARD_IF_TRUE to 74
  44: LOAD_GLOBAL          NULL + TypeError
  56: LOAD_CONST           'is_canonical requires a Decimal as an argument.'
  58: PRECALL              
  62: CALL                 
  72: RAISE_VARARGS        
  74: LOAD_FAST            a
  76: LOAD_METHOD          is_canonical
  98: PRECALL              
 102: CALL                 
 112: RETURN_VALUE         
