# Disassembly for _pydecimal.Decimal.to_eng_string
# From module file: _pydecimal

## co_consts:
('Convert to a string, using engineering notation if an exponent is needed.\n\n        Engineering notation has an exponent which is a multiple of 3.  This\n        can leave up to 3 digits to the left of the decimal place and may\n        require the addition of either one or two trailing zeros.\n        ', True, ('eng', 'context'))

## co_names:
('__str__',)

## bytecode:

   0: RESUME               
   2: LOAD_FAST            self
   4: LOAD_METHOD          __str__
  26: LOAD_CONST           True
  28: LOAD_FAST            context
  30: KW_NAMES             
  32: PRECALL              
  36: CALL                 
  46: RETURN_VALUE         
