# Disassembly for _pydecimal.DivisionUndefined
# From module file: _pydecimal

## co_consts:
('DivisionUndefined', 'Undefined result of division.\n\n    This occurs and signals invalid-operation if division by zero was\n    attempted (during a divide-integer, divide, or remainder operation), and\n    the dividend is also zero.  The result is [0,qNaN].\n    ', <code object handle at 0x0000024069495B00, file "_pydecimal.py", line 301>, None)

## co_names:
('__name__', '__module__', '__qualname__', '__doc__', 'handle')

## bytecode:

   0: RESUME               
   2: LOAD_NAME            __name__
   4: STORE_NAME           __module__
   6: LOAD_CONST           'DivisionUndefined'
   8: STORE_NAME           __qualname__
  10: LOAD_CONST           'Undefined result of division.\n\n    This occurs and signals invalid-operation if division by zero was\n    attempted (during a divide-integer, divide, or remainder operation), and\n    the dividend is also zero.  The result is [0,qNaN].\n    '
  12: STORE_NAME           __doc__
  14: LOAD_CONST           <code object handle at 0x0000024069495B00, file "_pydecimal.py", line 301>
  16: MAKE_FUNCTION        
  18: STORE_NAME           handle
  20: LOAD_CONST           None
  22: RETURN_VALUE         
