# Disassembly for _pydecimal._ContextManager.__enter__
# From module file: _pydecimal

## co_consts:
(None,)

## co_names:
('getcontext', 'saved_context', 'setcontext', 'new_context')

## bytecode:

   0: RESUME               
   2: LOAD_GLOBAL          NULL + getcontext
  14: PRECALL              
  18: CALL                 
  28: LOAD_FAST            self
  30: STORE_ATTR           saved_context
  40: LOAD_GLOBAL          NULL + setcontext
  52: LOAD_FAST            self
  54: LOAD_ATTR            new_context
  64: PRECALL              
  68: CALL                 
  78: POP_TOP              
  80: LOAD_FAST            self
  82: LOAD_ATTR            new_context
  92: RETURN_VALUE         
