# Disassembly for _pydecimal.Decimal.same_quantum
# From module file: _pydecimal

## co_consts:
('Return True if self and other have the same exponent; otherwise\n        return False.\n\n        If either operand is a special value, the following rules are used:\n           * return True if both operands are infinities\n           * return True if both operands are NaNs\n           * otherwise, return False.\n        ', True, ('raiseit',))

## co_names:
('_convert_other', '_is_special', 'is_nan', 'is_infinite', '_exp')

## bytecode:

   0: RESUME               
   2: LOAD_GLOBAL          NULL + _convert_other
  14: LOAD_FAST            other
  16: LOAD_CONST           True
  18: KW_NAMES             
  20: PRECALL              
  24: CALL                 
  34: STORE_FAST           other
  36: LOAD_FAST            self
  38: LOAD_ATTR            _is_special
  48: POP_JUMP_FORWARD_IF_TRUE to 64
  50: LOAD_FAST            other
  52: LOAD_ATTR            _is_special
  62: POP_JUMP_FORWARD_IF_FALSE to 224
  64: LOAD_FAST            self
  66: LOAD_METHOD          is_nan
  88: PRECALL              
  92: CALL                 
 102: POP_JUMP_FORWARD_IF_FALSE to 144
 104: LOAD_FAST            other
 106: LOAD_METHOD          is_nan
 128: PRECALL              
 132: CALL                 
 142: JUMP_IF_TRUE_OR_POP  to 222
 144: LOAD_FAST            self
 146: LOAD_METHOD          is_infinite
 168: PRECALL              
 172: CALL                 
 182: JUMP_IF_FALSE_OR_POP to 222
 184: LOAD_FAST            other
 186: LOAD_METHOD          is_infinite
 208: PRECALL              
 212: CALL                 
 222: RETURN_VALUE         
 224: LOAD_FAST            self
 226: LOAD_ATTR            _exp
 236: LOAD_FAST            other
 238: LOAD_ATTR            _exp
 248: COMPARE_OP           ==
 254: RETURN_VALUE         
