# Disassembly for _pydecimal.Decimal._round_05up
# From module file: _pydecimal

## co_consts:
('Round down unless digit prec-1 is 0 or 5.', 1, '05')

## co_names:
('_int', '_round_down')

## bytecode:

   0: RESUME               
   2: LOAD_FAST            prec
   4: POP_JUMP_FORWARD_IF_FALSE to 84
   6: LOAD_FAST            self
   8: LOAD_ATTR            _int
  18: LOAD_FAST            prec
  20: LOAD_CONST           1
  22: BINARY_OP            -
  26: BINARY_SUBSCR        
  36: LOAD_CONST           '05'
  38: CONTAINS_OP          
  40: POP_JUMP_FORWARD_IF_FALSE to 84
  42: LOAD_FAST            self
  44: LOAD_METHOD          _round_down
  66: LOAD_FAST            prec
  68: PRECALL              
  72: CALL                 
  82: RETURN_VALUE         
  84: LOAD_FAST            self
  86: LOAD_METHOD          _round_down
 108: LOAD_FAST            prec
 110: PRECALL              
 114: CALL                 
 124: UNARY_NEGATIVE       
 126: RETURN_VALUE         
