# Disassembly for _pydecimal.Decimal.__bool__
# From module file: _pydecimal

## co_consts:
('Return True if self is nonzero; otherwise return False.\n\n        NaNs and infinities are considered nonzero.\n        ', '0')

## co_names:
('_is_special', '_int')

## bytecode:

   0: RESUME               
   2: LOAD_FAST            self
   4: LOAD_ATTR            _is_special
  14: JUMP_IF_TRUE_OR_POP  to 36
  16: LOAD_FAST            self
  18: LOAD_ATTR            _int
  28: LOAD_CONST           '0'
  30: COMPARE_OP           !=
  36: RETURN_VALUE         
