# Disassembly for _pydecimal.Context.copy_sign
# From module file: _pydecimal

## co_consts:
("Copies the second operand's sign to the first one.\n\n        In detail, it returns a copy of the first operand with the sign\n        equal to the sign of the second operand.\n\n        >>> ExtendedContext.copy_sign(Decimal( '1.50'), Decimal('7.33'))\n        Decimal('1.50')\n        >>> ExtendedContext.copy_sign(Decimal('-1.50'), Decimal('7.33'))\n        Decimal('1.50')\n        >>> ExtendedContext.copy_sign(Decimal( '1.50'), Decimal('-7.33'))\n        Decimal('-1.50')\n        >>> ExtendedContext.copy_sign(Decimal('-1.50'), Decimal('-7.33'))\n        Decimal('-1.50')\n        >>> ExtendedContext.copy_sign(1, -2)\n        Decimal('-1')\n        >>> ExtendedContext.copy_sign(Decimal(1), -2)\n        Decimal('-1')\n        >>> ExtendedContext.copy_sign(1, Decimal(-2))\n        Decimal('-1')\n        ", True, ('raiseit',))

## co_names:
('_convert_other', 'copy_sign')

## bytecode:

   0: RESUME               
   2: LOAD_GLOBAL          NULL + _convert_other
  14: LOAD_FAST            a
  16: LOAD_CONST           True
  18: KW_NAMES             
  20: PRECALL              
  24: CALL                 
  34: STORE_FAST           a
  36: LOAD_FAST            a
  38: LOAD_METHOD          copy_sign
  60: LOAD_FAST            b
  62: PRECALL              
  66: CALL                 
  76: RETURN_VALUE         
