# Disassembly for _pydecimal.Context._set_rounding
# From module file: _pydecimal

## co_consts:
("Sets the rounding type.\n\n        Sets the rounding type, and returns the current (previous)\n        rounding type.  Often used like:\n\n        context = context.copy()\n        # so you don't change the calling context\n        # if an error occurs in the middle.\n        rounding = context._set_rounding(ROUND_UP)\n        val = self.__sub__(other, context=context)\n        context._set_rounding(rounding)\n\n        This will make it round up for that operation.\n        ",)

## co_names:
('rounding',)

## bytecode:

   0: RESUME               
   2: LOAD_FAST            self
   4: LOAD_ATTR            rounding
  14: STORE_FAST           rounding
  16: LOAD_FAST            type
  18: LOAD_FAST            self
  20: STORE_ATTR           rounding
  30: LOAD_FAST            rounding
  32: RETURN_VALUE         
