# Disassembly for _pydecimal.Context.rotate
# From module file: _pydecimal

## co_consts:
("Returns a rotated copy of a, b times.\n\n        The coefficient of the result is a rotated copy of the digits in\n        the coefficient of the first operand.  The number of places of\n        rotation is taken from the absolute value of the second operand,\n        with the rotation being to the left if the second operand is\n        positive or to the right otherwise.\n\n        >>> ExtendedContext.rotate(Decimal('34'), Decimal('8'))\n        Decimal('400000003')\n        >>> ExtendedContext.rotate(Decimal('12'), Decimal('9'))\n        Decimal('12')\n        >>> ExtendedContext.rotate(Decimal('123456789'), Decimal('-2'))\n        Decimal('891234567')\n        >>> ExtendedContext.rotate(Decimal('123456789'), Decimal('0'))\n        Decimal('123456789')\n        >>> ExtendedContext.rotate(Decimal('123456789'), Decimal('+2'))\n        Decimal('345678912')\n        >>> ExtendedContext.rotate(1333333, 1)\n        Decimal('13333330')\n        >>> ExtendedContext.rotate(Decimal(1333333), 1)\n        Decimal('13333330')\n        >>> ExtendedContext.rotate(1333333, Decimal(1))\n        Decimal('13333330')\n        ", True, ('raiseit',), ('context',))

## co_names:
('_convert_other', 'rotate')

## bytecode:

   0: RESUME               
   2: LOAD_GLOBAL          NULL + _convert_other
  14: LOAD_FAST            a
  16: LOAD_CONST           True
  18: KW_NAMES             
  20: PRECALL              
  24: CALL                 
  34: STORE_FAST           a
  36: LOAD_FAST            a
  38: LOAD_METHOD          rotate
  60: LOAD_FAST            b
  62: LOAD_FAST            self
  64: KW_NAMES             
  66: PRECALL              
  70: CALL                 
  80: RETURN_VALUE         
