# Disassembly for _pydecimal.Decimal._cmp
# From module file: _pydecimal

## co_consts:
('Compare the two non-NaN decimal instances self and other.\n\n        Returns -1 if self < other, 0 if self == other and 1\n        if self > other.  This routine is for internal use only.', 0, -1, 1, '0')

## co_names:
('_is_special', '_isinfinity', '_sign', 'adjusted', '_int', '_exp')

## bytecode:

   0: RESUME               
   2: LOAD_FAST            self
   4: LOAD_ATTR            _is_special
  14: POP_JUMP_FORWARD_IF_TRUE to 30
  16: LOAD_FAST            other
  18: LOAD_ATTR            _is_special
  28: POP_JUMP_FORWARD_IF_FALSE to 146
  30: LOAD_FAST            self
  32: LOAD_METHOD          _isinfinity
  54: PRECALL              
  58: CALL                 
  68: STORE_FAST           self_inf
  70: LOAD_FAST            other
  72: LOAD_METHOD          _isinfinity
  94: PRECALL              
  98: CALL                 
 108: STORE_FAST           other_inf
 110: LOAD_FAST            self_inf
 112: LOAD_FAST            other_inf
 114: COMPARE_OP           ==
 120: POP_JUMP_FORWARD_IF_FALSE to 126
 122: LOAD_CONST           0
 124: RETURN_VALUE         
 126: LOAD_FAST            self_inf
 128: LOAD_FAST            other_inf
 130: COMPARE_OP           <
 136: POP_JUMP_FORWARD_IF_FALSE to 142
 138: LOAD_CONST           -1
 140: RETURN_VALUE         
 142: LOAD_CONST           1
 144: RETURN_VALUE         
 146: LOAD_FAST            self
 148: POP_JUMP_FORWARD_IF_TRUE to 180
 150: LOAD_FAST            other
 152: POP_JUMP_FORWARD_IF_TRUE to 158
 154: LOAD_CONST           0
 156: RETURN_VALUE         
 158: LOAD_CONST           -1
 160: LOAD_FAST            other
 162: LOAD_ATTR            _sign
 172: BINARY_OP            **
 176: UNARY_NEGATIVE       
 178: RETURN_VALUE         
 180: LOAD_FAST            other
 182: POP_JUMP_FORWARD_IF_TRUE to 204
 184: LOAD_CONST           -1
 186: LOAD_FAST            self
 188: LOAD_ATTR            _sign
 198: BINARY_OP            **
 202: RETURN_VALUE         
 204: LOAD_FAST            other
 206: LOAD_ATTR            _sign
 216: LOAD_FAST            self
 218: LOAD_ATTR            _sign
 228: COMPARE_OP           <
 234: POP_JUMP_FORWARD_IF_FALSE to 240
 236: LOAD_CONST           -1
 238: RETURN_VALUE         
 240: LOAD_FAST            self
 242: LOAD_ATTR            _sign
 252: LOAD_FAST            other
 254: LOAD_ATTR            _sign
 264: COMPARE_OP           <
 270: POP_JUMP_FORWARD_IF_FALSE to 276
 272: LOAD_CONST           1
 274: RETURN_VALUE         
 276: LOAD_FAST            self
 278: LOAD_METHOD          adjusted
 300: PRECALL              
 304: CALL                 
 314: STORE_FAST           self_adjusted
 316: LOAD_FAST            other
 318: LOAD_METHOD          adjusted
 340: PRECALL              
 344: CALL                 
 354: STORE_FAST           other_adjusted
 356: LOAD_FAST            self_adjusted
 358: LOAD_FAST            other_adjusted
 360: COMPARE_OP           ==
 366: POP_JUMP_FORWARD_IF_FALSE to 542
 368: LOAD_FAST            self
 370: LOAD_ATTR            _int
 380: LOAD_CONST           '0'
 382: LOAD_FAST            self
 384: LOAD_ATTR            _exp
 394: LOAD_FAST            other
 396: LOAD_ATTR            _exp
 406: BINARY_OP            -
 410: BINARY_OP            *
 414: BINARY_OP            +
 418: STORE_FAST           self_padded
 420: LOAD_FAST            other
 422: LOAD_ATTR            _int
 432: LOAD_CONST           '0'
 434: LOAD_FAST            other
 436: LOAD_ATTR            _exp
 446: LOAD_FAST            self
 448: LOAD_ATTR            _exp
 458: BINARY_OP            -
 462: BINARY_OP            *
 466: BINARY_OP            +
 470: STORE_FAST           other_padded
 472: LOAD_FAST            self_padded
 474: LOAD_FAST            other_padded
 476: COMPARE_OP           ==
 482: POP_JUMP_FORWARD_IF_FALSE to 488
 484: LOAD_CONST           0
 486: RETURN_VALUE         
 488: LOAD_FAST            self_padded
 490: LOAD_FAST            other_padded
 492: COMPARE_OP           <
 498: POP_JUMP_FORWARD_IF_FALSE to 522
 500: LOAD_CONST           -1
 502: LOAD_FAST            self
 504: LOAD_ATTR            _sign
 514: BINARY_OP            **
 518: UNARY_NEGATIVE       
 520: RETURN_VALUE         
 522: LOAD_CONST           -1
 524: LOAD_FAST            self
 526: LOAD_ATTR            _sign
 536: BINARY_OP            **
 540: RETURN_VALUE         
 542: LOAD_FAST            self_adjusted
 544: LOAD_FAST            other_adjusted
 546: COMPARE_OP           >
 552: POP_JUMP_FORWARD_IF_FALSE to 574
 554: LOAD_CONST           -1
 556: LOAD_FAST            self
 558: LOAD_ATTR            _sign
 568: BINARY_OP            **
 572: RETURN_VALUE         
 574: LOAD_CONST           -1
 576: LOAD_FAST            self
 578: LOAD_ATTR            _sign
 588: BINARY_OP            **
 592: UNARY_NEGATIVE       
 594: RETURN_VALUE         
