# Disassembly for _pydecimal.Context._ignore_flags
# From module file: _pydecimal

## co_consts:
('Ignore the flags, if they are raised',)

## co_names:
('_ignored_flags', 'list')

## bytecode:

   0: RESUME               
   2: LOAD_FAST            self
   4: LOAD_ATTR            _ignored_flags
  14: LOAD_GLOBAL          NULL + list
  26: LOAD_FAST            flags
  28: PRECALL              
  32: CALL                 
  42: BINARY_OP            +
  46: LOAD_FAST            self
  48: STORE_ATTR           _ignored_flags
  58: LOAD_GLOBAL          NULL + list
  70: LOAD_FAST            flags
  72: PRECALL              
  76: CALL                 
  86: RETURN_VALUE         
