# Disassembly for _pydecimal.Context.sqrt
# From module file: _pydecimal

## co_consts:
("Square root of a non-negative number to context precision.\n\n        If the result must be inexact, it is rounded using the round-half-even\n        algorithm.\n\n        >>> ExtendedContext.sqrt(Decimal('0'))\n        Decimal('0')\n        >>> ExtendedContext.sqrt(Decimal('-0'))\n        Decimal('-0')\n        >>> ExtendedContext.sqrt(Decimal('0.39'))\n        Decimal('0.624499800')\n        >>> ExtendedContext.sqrt(Decimal('100'))\n        Decimal('10')\n        >>> ExtendedContext.sqrt(Decimal('1'))\n        Decimal('1')\n        >>> ExtendedContext.sqrt(Decimal('1.0'))\n        Decimal('1.0')\n        >>> ExtendedContext.sqrt(Decimal('1.00'))\n        Decimal('1.0')\n        >>> ExtendedContext.sqrt(Decimal('7'))\n        Decimal('2.64575131')\n        >>> ExtendedContext.sqrt(Decimal('10'))\n        Decimal('3.16227766')\n        >>> ExtendedContext.sqrt(2)\n        Decimal('1.41421356')\n        >>> ExtendedContext.prec\n        9\n        ", True, ('raiseit',), ('context',))

## co_names:
('_convert_other', 'sqrt')

## bytecode:

   0: RESUME               
   2: LOAD_GLOBAL          NULL + _convert_other
  14: LOAD_FAST            a
  16: LOAD_CONST           True
  18: KW_NAMES             
  20: PRECALL              
  24: CALL                 
  34: STORE_FAST           a
  36: LOAD_FAST            a
  38: LOAD_METHOD          sqrt
  60: LOAD_FAST            self
  62: KW_NAMES             
  64: PRECALL              
  68: CALL                 
  78: RETURN_VALUE         
