# Disassembly for _pydecimal.Context.compare
# From module file: _pydecimal

## co_consts:
("Compares values numerically.\n\n        If the signs of the operands differ, a value representing each operand\n        ('-1' if the operand is less than zero, '0' if the operand is zero or\n        negative zero, or '1' if the operand is greater than zero) is used in\n        place of that operand for the comparison instead of the actual\n        operand.\n\n        The comparison is then effected by subtracting the second operand from\n        the first and then returning a value according to the result of the\n        subtraction: '-1' if the result is less than zero, '0' if the result is\n        zero or negative zero, or '1' if the result is greater than zero.\n\n        >>> ExtendedContext.compare(Decimal('2.1'), Decimal('3'))\n        Decimal('-1')\n        >>> ExtendedContext.compare(Decimal('2.1'), Decimal('2.1'))\n        Decimal('0')\n        >>> ExtendedContext.compare(Decimal('2.1'), Decimal('2.10'))\n        Decimal('0')\n        >>> ExtendedContext.compare(Decimal('3'), Decimal('2.1'))\n        Decimal('1')\n        >>> ExtendedContext.compare(Decimal('2.1'), Decimal('-3'))\n        Decimal('1')\n        >>> ExtendedContext.compare(Decimal('-3'), Decimal('2.1'))\n        Decimal('-1')\n        >>> ExtendedContext.compare(1, 2)\n        Decimal('-1')\n        >>> ExtendedContext.compare(Decimal(1), 2)\n        Decimal('-1')\n        >>> ExtendedContext.compare(1, Decimal(2))\n        Decimal('-1')\n        ", True, ('raiseit',), ('context',))

## co_names:
('_convert_other', 'compare')

## bytecode:

   0: RESUME               
   2: LOAD_GLOBAL          NULL + _convert_other
  14: LOAD_FAST            a
  16: LOAD_CONST           True
  18: KW_NAMES             
  20: PRECALL              
  24: CALL                 
  34: STORE_FAST           a
  36: LOAD_FAST            a
  38: LOAD_METHOD          compare
  60: LOAD_FAST            b
  62: LOAD_FAST            self
  64: KW_NAMES             
  66: PRECALL              
  70: CALL                 
  80: RETURN_VALUE         
