# Disassembly for _pydecimal.Context.is_finite
# From module file: _pydecimal

## co_consts:
("Return True if the operand is finite; otherwise return False.\n\n        A Decimal instance is considered finite if it is neither\n        infinite nor a NaN.\n\n        >>> ExtendedContext.is_finite(Decimal('2.50'))\n        True\n        >>> ExtendedContext.is_finite(Decimal('-0.3'))\n        True\n        >>> ExtendedContext.is_finite(Decimal('0'))\n        True\n        >>> ExtendedContext.is_finite(Decimal('Inf'))\n        False\n        >>> ExtendedContext.is_finite(Decimal('NaN'))\n        False\n        >>> ExtendedContext.is_finite(1)\n        True\n        ", True, ('raiseit',))

## co_names:
('_convert_other', 'is_finite')

## bytecode:

   0: RESUME               
   2: LOAD_GLOBAL          NULL + _convert_other
  14: LOAD_FAST            a
  16: LOAD_CONST           True
  18: KW_NAMES             
  20: PRECALL              
  24: CALL                 
  34: STORE_FAST           a
  36: LOAD_FAST            a
  38: LOAD_METHOD          is_finite
  60: PRECALL              
  64: CALL                 
  74: RETURN_VALUE         
