# Disassembly for _pydecimal.Decimal.__new__
# From module file: _pydecimal

## co_consts:
("Create a decimal point instance.\n\n        >>> Decimal('3.14')              # string input\n        Decimal('3.14')\n        >>> Decimal((0, (3, 1, 4), -2))  # tuple (sign, digit_tuple, exponent)\n        Decimal('3.14')\n        >>> Decimal(314)                 # int\n        Decimal('314')\n        >>> Decimal(Decimal(314))        # another decimal instance\n        Decimal('314')\n        >>> Decimal('  3.14  \\n')        # leading and trailing whitespace okay\n        Decimal('3.14')\n        ", '_', '', None, 'Invalid literal for Decimal: %r', 'sign', '-', 1, 0, 'int', 'frac', 'exp', '0', False, 'diag', 'signal', 'N', 'n', 'F', True, 3, 'Invalid tuple size in creation of Decimal from list or tuple.  The list or tuple should have exactly three elements.', (0, 1), 'Invalid sign.  The first value in the tuple should be an integer; either 0 for a positive number or 1 for a negative number.', 2, 9, 'The second value in the tuple must be composed of integers in the range 0 through 9.', ('n', 'N'), "The third value in the tuple must be an integer, or one of the strings 'F', 'n', 'N'.", 'strict semantics for mixing floats and Decimals are enabled', 'Cannot convert %r to Decimal')

## co_names:
('object', '__new__', 'isinstance', 'str', '_parser', 'strip', 'replace', 'getcontext', '_raise_error', 'ConversionSyntax', 'group', '_sign', 'int', '_int', 'len', '_exp', '_is_special', 'lstrip', 'abs', 'Decimal', '_WorkRep', 'sign', 'exp', 'list', 'tuple', 'ValueError', 'append', 'join', 'map', 'float', 'FloatOperation', 'from_float', 'TypeError')

## bytecode:

   0: RESUME               
   2: LOAD_GLOBAL          object
  14: LOAD_METHOD          __new__
  36: LOAD_FAST            cls
  38: PRECALL              
  42: CALL                 
  52: STORE_FAST           self
  54: LOAD_GLOBAL          NULL + isinstance
  66: LOAD_FAST            value
  68: LOAD_GLOBAL          str
  80: PRECALL              
  84: CALL                 
  94: EXTENDED_ARG         
  96: POP_JUMP_FORWARD_IF_FALSE to 952
  98: LOAD_GLOBAL          NULL + _parser
 110: LOAD_FAST            value
 112: LOAD_METHOD          strip
 134: PRECALL              
 138: CALL                 
 148: LOAD_METHOD          replace
 170: LOAD_CONST           '_'
 172: LOAD_CONST           ''
 174: PRECALL              
 178: CALL                 
 188: PRECALL              
 192: CALL                 
 202: STORE_FAST           m
 204: LOAD_FAST            m
 206: POP_JUMP_FORWARD_IF_NOT_NONE to 300
 208: LOAD_FAST            context
 210: POP_JUMP_FORWARD_IF_NOT_NONE to 240
 212: LOAD_GLOBAL          NULL + getcontext
 224: PRECALL              
 228: CALL                 
 238: STORE_FAST           context
 240: LOAD_FAST            context
 242: LOAD_METHOD          _raise_error
 264: LOAD_GLOBAL          ConversionSyntax
 276: LOAD_CONST           'Invalid literal for Decimal: %r'
 278: LOAD_FAST            value
 280: BINARY_OP            %
 284: PRECALL              
 288: CALL                 
 298: RETURN_VALUE         
 300: LOAD_FAST            m
 302: LOAD_METHOD          group
 324: LOAD_CONST           'sign'
 326: PRECALL              
 330: CALL                 
 340: LOAD_CONST           '-'
 342: COMPARE_OP           ==
 348: POP_JUMP_FORWARD_IF_FALSE to 366
 350: LOAD_CONST           1
 352: LOAD_FAST            self
 354: STORE_ATTR           _sign
 364: JUMP_FORWARD         to 380
 366: LOAD_CONST           0
 368: LOAD_FAST            self
 370: STORE_ATTR           _sign
 380: LOAD_FAST            m
 382: LOAD_METHOD          group
 404: LOAD_CONST           'int'
 406: PRECALL              
 410: CALL                 
 420: STORE_FAST           intpart
 422: LOAD_FAST            intpart
 424: POP_JUMP_FORWARD_IF_NONE to 678
 426: LOAD_FAST            m
 428: LOAD_METHOD          group
 450: LOAD_CONST           'frac'
 452: PRECALL              
 456: CALL                 
 466: JUMP_IF_TRUE_OR_POP  to 470
 468: LOAD_CONST           ''
 470: STORE_FAST           fracpart
 472: LOAD_GLOBAL          NULL + int
 484: LOAD_FAST            m
 486: LOAD_METHOD          group
 508: LOAD_CONST           'exp'
 510: PRECALL              
 514: CALL                 
 524: JUMP_IF_TRUE_OR_POP  to 528
 526: LOAD_CONST           '0'
 528: PRECALL              
 532: CALL                 
 542: STORE_FAST           exp
 544: LOAD_GLOBAL          NULL + str
 556: LOAD_GLOBAL          NULL + int
 568: LOAD_FAST            intpart
 570: LOAD_FAST            fracpart
 572: BINARY_OP            +
 576: PRECALL              
 580: CALL                 
 590: PRECALL              
 594: CALL                 
 604: LOAD_FAST            self
 606: STORE_ATTR           _int
 616: LOAD_FAST            exp
 618: LOAD_GLOBAL          NULL + len
 630: LOAD_FAST            fracpart
 632: PRECALL              
 636: CALL                 
 646: BINARY_OP            -
 650: LOAD_FAST            self
 652: STORE_ATTR           _exp
 662: LOAD_CONST           False
 664: LOAD_FAST            self
 666: STORE_ATTR           _is_special
 676: JUMP_FORWARD         to 948
 678: LOAD_FAST            m
 680: LOAD_METHOD          group
 702: LOAD_CONST           'diag'
 704: PRECALL              
 708: CALL                 
 718: STORE_FAST           diag
 720: LOAD_FAST            diag
 722: POP_JUMP_FORWARD_IF_NONE to 906
 724: LOAD_GLOBAL          NULL + str
 736: LOAD_GLOBAL          NULL + int
 748: LOAD_FAST            diag
 750: JUMP_IF_TRUE_OR_POP  to 754
 752: LOAD_CONST           '0'
 754: PRECALL              
 758: CALL                 
 768: PRECALL              
 772: CALL                 
 782: LOAD_METHOD          lstrip
 804: LOAD_CONST           '0'
 806: PRECALL              
 810: CALL                 
 820: LOAD_FAST            self
 822: STORE_ATTR           _int
 832: LOAD_FAST            m
 834: LOAD_METHOD          group
 856: LOAD_CONST           'signal'
 858: PRECALL              
 862: CALL                 
 872: POP_JUMP_FORWARD_IF_FALSE to 890
 874: LOAD_CONST           'N'
 876: LOAD_FAST            self
 878: STORE_ATTR           _exp
 888: JUMP_FORWARD         to 934
 890: LOAD_CONST           'n'
 892: LOAD_FAST            self
 894: STORE_ATTR           _exp
 904: JUMP_FORWARD         to 934
 906: LOAD_CONST           '0'
 908: LOAD_FAST            self
 910: STORE_ATTR           _int
 920: LOAD_CONST           'F'
 922: LOAD_FAST            self
 924: STORE_ATTR           _exp
 934: LOAD_CONST           True
 936: LOAD_FAST            self
 938: STORE_ATTR           _is_special
 948: LOAD_FAST            self
 950: RETURN_VALUE         
 952: LOAD_GLOBAL          NULL + isinstance
 964: LOAD_FAST            value
 966: LOAD_GLOBAL          int
 978: PRECALL              
 982: CALL                 
 992: POP_JUMP_FORWARD_IF_FALSE to 1134
 994: LOAD_FAST            value
 996: LOAD_CONST           0
 998: COMPARE_OP           >=
1004: POP_JUMP_FORWARD_IF_FALSE to 1022
1006: LOAD_CONST           0
1008: LOAD_FAST            self
1010: STORE_ATTR           _sign
1020: JUMP_FORWARD         to 1036
1022: LOAD_CONST           1
1024: LOAD_FAST            self
1026: STORE_ATTR           _sign
1036: LOAD_CONST           0
1038: LOAD_FAST            self
1040: STORE_ATTR           _exp
1050: LOAD_GLOBAL          NULL + str
1062: LOAD_GLOBAL          NULL + abs
1074: LOAD_FAST            value
1076: PRECALL              
1080: CALL                 
1090: PRECALL              
1094: CALL                 
1104: LOAD_FAST            self
1106: STORE_ATTR           _int
1116: LOAD_CONST           False
1118: LOAD_FAST            self
1120: STORE_ATTR           _is_special
1130: LOAD_FAST            self
1132: RETURN_VALUE         
1134: LOAD_GLOBAL          NULL + isinstance
1146: LOAD_FAST            value
1148: LOAD_GLOBAL          Decimal
1160: PRECALL              
1164: CALL                 
1174: POP_JUMP_FORWARD_IF_FALSE to 1276
1176: LOAD_FAST            value
1178: LOAD_ATTR            _exp
1188: LOAD_FAST            self
1190: STORE_ATTR           _exp
1200: LOAD_FAST            value
1202: LOAD_ATTR            _sign
1212: LOAD_FAST            self
1214: STORE_ATTR           _sign
1224: LOAD_FAST            value
1226: LOAD_ATTR            _int
1236: LOAD_FAST            self
1238: STORE_ATTR           _int
1248: LOAD_FAST            value
1250: LOAD_ATTR            _is_special
1260: LOAD_FAST            self
1262: STORE_ATTR           _is_special
1272: LOAD_FAST            self
1274: RETURN_VALUE         
1276: LOAD_GLOBAL          NULL + isinstance
1288: LOAD_FAST            value
1290: LOAD_GLOBAL          _WorkRep
1302: PRECALL              
1306: CALL                 
1316: POP_JUMP_FORWARD_IF_FALSE to 1460
1318: LOAD_FAST            value
1320: LOAD_ATTR            sign
1330: LOAD_FAST            self
1332: STORE_ATTR           _sign
1342: LOAD_GLOBAL          NULL + str
1354: LOAD_FAST            value
1356: LOAD_ATTR            int
1366: PRECALL              
1370: CALL                 
1380: LOAD_FAST            self
1382: STORE_ATTR           _int
1392: LOAD_GLOBAL          NULL + int
1404: LOAD_FAST            value
1406: LOAD_ATTR            exp
1416: PRECALL              
1420: CALL                 
1430: LOAD_FAST            self
1432: STORE_ATTR           _exp
1442: LOAD_CONST           False
1444: LOAD_FAST            self
1446: STORE_ATTR           _is_special
1456: LOAD_FAST            self
1458: RETURN_VALUE         
1460: LOAD_GLOBAL          NULL + isinstance
1472: LOAD_FAST            value
1474: LOAD_GLOBAL          list
1486: LOAD_GLOBAL          tuple
1498: BUILD_TUPLE          
1500: PRECALL              
1504: CALL                 
1514: EXTENDED_ARG         
1516: POP_JUMP_FORWARD_IF_FALSE to 2364
1518: LOAD_GLOBAL          NULL + len
1530: LOAD_FAST            value
1532: PRECALL              
1536: CALL                 
1546: LOAD_CONST           3
1548: COMPARE_OP           !=
1554: POP_JUMP_FORWARD_IF_FALSE to 1586
1556: LOAD_GLOBAL          NULL + ValueError
1568: LOAD_CONST           'Invalid tuple size in creation of Decimal from list or tuple.  The list or tuple should have exactly three elements.'
1570: PRECALL              
1574: CALL                 
1584: RAISE_VARARGS        
1586: LOAD_GLOBAL          NULL + isinstance
1598: LOAD_FAST            value
1600: LOAD_CONST           0
1602: BINARY_SUBSCR        
1612: LOAD_GLOBAL          int
1624: PRECALL              
1628: CALL                 
1638: POP_JUMP_FORWARD_IF_FALSE to 1660
1640: LOAD_FAST            value
1642: LOAD_CONST           0
1644: BINARY_SUBSCR        
1654: LOAD_CONST           (0, 1)
1656: CONTAINS_OP          
1658: POP_JUMP_FORWARD_IF_TRUE to 1690
1660: LOAD_GLOBAL          NULL + ValueError
1672: LOAD_CONST           'Invalid sign.  The first value in the tuple should be an integer; either 0 for a positive number or 1 for a negative number.'
1674: PRECALL              
1678: CALL                 
1688: RAISE_VARARGS        
1690: LOAD_FAST            value
1692: LOAD_CONST           0
1694: BINARY_SUBSCR        
1704: LOAD_FAST            self
1706: STORE_ATTR           _sign
1716: LOAD_FAST            value
1718: LOAD_CONST           2
1720: BINARY_SUBSCR        
1730: LOAD_CONST           'F'
1732: COMPARE_OP           ==
1738: POP_JUMP_FORWARD_IF_FALSE to 1798
1740: LOAD_CONST           '0'
1742: LOAD_FAST            self
1744: STORE_ATTR           _int
1754: LOAD_FAST            value
1756: LOAD_CONST           2
1758: BINARY_SUBSCR        
1768: LOAD_FAST            self
1770: STORE_ATTR           _exp
1780: LOAD_CONST           True
1782: LOAD_FAST            self
1784: STORE_ATTR           _is_special
1794: EXTENDED_ARG         
1796: JUMP_FORWARD         to 2360
1798: BUILD_LIST           
1800: STORE_FAST           digits
1802: LOAD_FAST            value
1804: LOAD_CONST           1
1806: BINARY_SUBSCR        
1816: GET_ITER             
1818: FOR_ITER             to 1986
1820: STORE_FAST           digit
1822: LOAD_GLOBAL          NULL + isinstance
1834: LOAD_FAST            digit
1836: LOAD_GLOBAL          int
1848: PRECALL              
1852: CALL                 
1862: POP_JUMP_FORWARD_IF_FALSE to 1956
1864: LOAD_CONST           0
1866: LOAD_FAST            digit
1868: SWAP                 
1870: COPY                 
1872: COMPARE_OP           <=
1878: POP_JUMP_FORWARD_IF_FALSE to 1892
1880: LOAD_CONST           9
1882: COMPARE_OP           <=
1888: POP_JUMP_FORWARD_IF_FALSE to 1956
1890: JUMP_FORWARD         to 1896
1892: POP_TOP              
1894: JUMP_FORWARD         to 1956
1896: LOAD_FAST            digits
1898: POP_JUMP_FORWARD_IF_TRUE to 1912
1900: LOAD_FAST            digit
1902: LOAD_CONST           0
1904: COMPARE_OP           !=
1910: POP_JUMP_FORWARD_IF_FALSE to 1954
1912: LOAD_FAST            digits
1914: LOAD_METHOD          append
1936: LOAD_FAST            digit
1938: PRECALL              
1942: CALL                 
1952: POP_TOP              
1954: JUMP_BACKWARD        to 1818
1956: LOAD_GLOBAL          NULL + ValueError
1968: LOAD_CONST           'The second value in the tuple must be composed of integers in the range 0 through 9.'
1970: PRECALL              
1974: CALL                 
1984: RAISE_VARARGS        
1986: LOAD_FAST            value
1988: LOAD_CONST           2
1990: BINARY_SUBSCR        
2000: LOAD_CONST           ('n', 'N')
2002: CONTAINS_OP          
2004: POP_JUMP_FORWARD_IF_FALSE to 2138
2006: LOAD_CONST           ''
2008: LOAD_METHOD          join
2030: LOAD_GLOBAL          NULL + map
2042: LOAD_GLOBAL          str
2054: LOAD_FAST            digits
2056: PRECALL              
2060: CALL                 
2070: PRECALL              
2074: CALL                 
2084: LOAD_FAST            self
2086: STORE_ATTR           _int
2096: LOAD_FAST            value
2098: LOAD_CONST           2
2100: BINARY_SUBSCR        
2110: LOAD_FAST            self
2112: STORE_ATTR           _exp
2122: LOAD_CONST           True
2124: LOAD_FAST            self
2126: STORE_ATTR           _is_special
2136: JUMP_FORWARD         to 2360
2138: LOAD_GLOBAL          NULL + isinstance
2150: LOAD_FAST            value
2152: LOAD_CONST           2
2154: BINARY_SUBSCR        
2164: LOAD_GLOBAL          int
2176: PRECALL              
2180: CALL                 
2190: POP_JUMP_FORWARD_IF_FALSE to 2330
2192: LOAD_CONST           ''
2194: LOAD_METHOD          join
2216: LOAD_GLOBAL          NULL + map
2228: LOAD_GLOBAL          str
2240: LOAD_FAST            digits
2242: JUMP_IF_TRUE_OR_POP  to 2248
2244: LOAD_CONST           0
2246: BUILD_LIST           
2248: PRECALL              
2252: CALL                 
2262: PRECALL              
2266: CALL                 
2276: LOAD_FAST            self
2278: STORE_ATTR           _int
2288: LOAD_FAST            value
2290: LOAD_CONST           2
2292: BINARY_SUBSCR        
2302: LOAD_FAST            self
2304: STORE_ATTR           _exp
2314: LOAD_CONST           False
2316: LOAD_FAST            self
2318: STORE_ATTR           _is_special
2328: JUMP_FORWARD         to 2360
2330: LOAD_GLOBAL          NULL + ValueError
2342: LOAD_CONST           "The third value in the tuple must be an integer, or one of the strings 'F', 'n', 'N'."
2344: PRECALL              
2348: CALL                 
2358: RAISE_VARARGS        
2360: LOAD_FAST            self
2362: RETURN_VALUE         
2364: LOAD_GLOBAL          NULL + isinstance
2376: LOAD_FAST            value
2378: LOAD_GLOBAL          float
2390: PRECALL              
2394: CALL                 
2404: POP_JUMP_FORWARD_IF_FALSE to 2644
2406: LOAD_FAST            context
2408: POP_JUMP_FORWARD_IF_NOT_NONE to 2438
2410: LOAD_GLOBAL          NULL + getcontext
2422: PRECALL              
2426: CALL                 
2436: STORE_FAST           context
2438: LOAD_FAST            context
2440: LOAD_METHOD          _raise_error
2462: LOAD_GLOBAL          FloatOperation
2474: LOAD_CONST           'strict semantics for mixing floats and Decimals are enabled'
2476: PRECALL              
2480: CALL                 
2490: POP_TOP              
2492: LOAD_GLOBAL          Decimal
2504: LOAD_METHOD          from_float
2526: LOAD_FAST            value
2528: PRECALL              
2532: CALL                 
2542: STORE_FAST           value
2544: LOAD_FAST            value
2546: LOAD_ATTR            _exp
2556: LOAD_FAST            self
2558: STORE_ATTR           _exp
2568: LOAD_FAST            value
2570: LOAD_ATTR            _sign
2580: LOAD_FAST            self
2582: STORE_ATTR           _sign
2592: LOAD_FAST            value
2594: LOAD_ATTR            _int
2604: LOAD_FAST            self
2606: STORE_ATTR           _int
2616: LOAD_FAST            value
2618: LOAD_ATTR            _is_special
2628: LOAD_FAST            self
2630: STORE_ATTR           _is_special
2640: LOAD_FAST            self
2642: RETURN_VALUE         
2644: LOAD_GLOBAL          NULL + TypeError
2656: LOAD_CONST           'Cannot convert %r to Decimal'
2658: LOAD_FAST            value
2660: BINARY_OP            %
2664: PRECALL              
2668: CALL                 
2678: RAISE_VARARGS        
