# Disassembly for _pydecimal.DivisionByZero
# From module file: _pydecimal

## co_consts:
('DivisionByZero', 'Division by 0.\n\n    This occurs and signals division-by-zero if division of a finite number\n    by zero was attempted (during a divide-integer or divide operation, or a\n    power operation with negative right-hand operand), and the dividend was\n    not zero.\n\n    The result of the operation is [sign,inf], where sign is the exclusive\n    or of the signs of the operands for divide, or is 1 for an odd power of\n    -0, for power.\n    ', <code object handle at 0x0000024069465610, file "_pydecimal.py", line 279>, None)

## co_names:
('__name__', '__module__', '__qualname__', '__doc__', 'handle')

## bytecode:

   0: RESUME               
   2: LOAD_NAME            __name__
   4: STORE_NAME           __module__
   6: LOAD_CONST           'DivisionByZero'
   8: STORE_NAME           __qualname__
  10: LOAD_CONST           'Division by 0.\n\n    This occurs and signals division-by-zero if division of a finite number\n    by zero was attempted (during a divide-integer or divide operation, or a\n    power operation with negative right-hand operand), and the dividend was\n    not zero.\n\n    The result of the operation is [sign,inf], where sign is the exclusive\n    or of the signs of the operands for divide, or is 1 for an odd power of\n    -0, for power.\n    '
  12: STORE_NAME           __doc__
  14: LOAD_CONST           <code object handle at 0x0000024069465610, file "_pydecimal.py", line 279>
  16: MAKE_FUNCTION        
  18: STORE_NAME           handle
  20: LOAD_CONST           None
  22: RETURN_VALUE         
