# Disassembly for _pydecimal.Clamped
# From module file: _pydecimal

## co_consts:
('Clamped', 'Exponent of a 0 changed to fit bounds.\n\n    This occurs and signals clamped if the exponent of a result has been\n    altered in order to fit the constraints of a specific concrete\n    representation.  This may occur when the exponent of a zero result would\n    be outside the bounds of a representation, or when a large normal\n    number would have an encoded exponent that cannot be represented.  In\n    this latter case, the exponent is reduced to fit and the corresponding\n    number of zero digits are appended to the coefficient ("fold-down").\n    ', None)

## co_names:
('__name__', '__module__', '__qualname__', '__doc__')

## bytecode:

   0: RESUME               
   2: LOAD_NAME            __name__
   4: STORE_NAME           __module__
   6: LOAD_CONST           'Clamped'
   8: STORE_NAME           __qualname__
  10: LOAD_CONST           'Exponent of a 0 changed to fit bounds.\n\n    This occurs and signals clamped if the exponent of a result has been\n    altered in order to fit the constraints of a specific concrete\n    representation.  This may occur when the exponent of a zero result would\n    be outside the bounds of a representation, or when a large normal\n    number would have an encoded exponent that cannot be represented.  In\n    this latter case, the exponent is reduced to fit and the corresponding\n    number of zero digits are appended to the coefficient ("fold-down").\n    '
  12: STORE_NAME           __doc__
  14: LOAD_CONST           None
  16: RETURN_VALUE         
