# Disassembly for _pydecimal.Decimal.copy_sign
# From module file: _pydecimal

## co_consts:
('Returns self with the sign of other.', True, ('raiseit',))

## co_names:
('_convert_other', '_dec_from_triple', '_sign', '_int', '_exp', '_is_special')

## bytecode:

   0: RESUME               
   2: LOAD_GLOBAL          NULL + _convert_other
  14: LOAD_FAST            other
  16: LOAD_CONST           True
  18: KW_NAMES             
  20: PRECALL              
  24: CALL                 
  34: STORE_FAST           other
  36: LOAD_GLOBAL          NULL + _dec_from_triple
  48: LOAD_FAST            other
  50: LOAD_ATTR            _sign
  60: LOAD_FAST            self
  62: LOAD_ATTR            _int
  72: LOAD_FAST            self
  74: LOAD_ATTR            _exp
  84: LOAD_FAST            self
  86: LOAD_ATTR            _is_special
  96: PRECALL              
 100: CALL                 
 110: RETURN_VALUE         
