# Disassembly for _pydecimal.Decimal.sqrt
# From module file: _pydecimal

## co_consts:
('Return the square root of self.', None, ('context',), 0, '0', 2, 1, 'sqrt(-x), x > 0', 10, 100, True, 5)

## co_names:
('getcontext', '_is_special', '_check_nans', '_isinfinity', '_sign', 'Decimal', '_dec_from_triple', '_exp', '_fix', '_raise_error', 'InvalidOperation', 'prec', '_WorkRep', 'exp', 'int', 'len', '_int', 'divmod', 'str', '_shallow_copy', '_set_rounding', 'ROUND_HALF_EVEN', 'rounding')

## bytecode:

   0: RESUME               
   2: LOAD_FAST            context
   4: POP_JUMP_FORWARD_IF_NOT_NONE to 34
   6: LOAD_GLOBAL          NULL + getcontext
  18: PRECALL              
  22: CALL                 
  32: STORE_FAST           context
  34: LOAD_FAST            self
  36: LOAD_ATTR            _is_special
  46: POP_JUMP_FORWARD_IF_FALSE to 192
  48: LOAD_FAST            self
  50: LOAD_METHOD          _check_nans
  72: LOAD_FAST            context
  74: KW_NAMES             
  76: PRECALL              
  80: CALL                 
  90: STORE_FAST           ans
  92: LOAD_FAST            ans
  94: POP_JUMP_FORWARD_IF_FALSE to 100
  96: LOAD_FAST            ans
  98: RETURN_VALUE         
 100: LOAD_FAST            self
 102: LOAD_METHOD          _isinfinity
 124: PRECALL              
 128: CALL                 
 138: POP_JUMP_FORWARD_IF_FALSE to 192
 140: LOAD_FAST            self
 142: LOAD_ATTR            _sign
 152: LOAD_CONST           0
 154: COMPARE_OP           ==
 160: POP_JUMP_FORWARD_IF_FALSE to 192
 162: LOAD_GLOBAL          NULL + Decimal
 174: LOAD_FAST            self
 176: PRECALL              
 180: CALL                 
 190: RETURN_VALUE         
 192: LOAD_FAST            self
 194: POP_JUMP_FORWARD_IF_TRUE to 298
 196: LOAD_GLOBAL          NULL + _dec_from_triple
 208: LOAD_FAST            self
 210: LOAD_ATTR            _sign
 220: LOAD_CONST           '0'
 222: LOAD_FAST            self
 224: LOAD_ATTR            _exp
 234: LOAD_CONST           2
 236: BINARY_OP            //
 240: PRECALL              
 244: CALL                 
 254: STORE_FAST           ans
 256: LOAD_FAST            ans
 258: LOAD_METHOD          _fix
 280: LOAD_FAST            context
 282: PRECALL              
 286: CALL                 
 296: RETURN_VALUE         
 298: LOAD_FAST            self
 300: LOAD_ATTR            _sign
 310: LOAD_CONST           1
 312: COMPARE_OP           ==
 318: POP_JUMP_FORWARD_IF_FALSE to 374
 320: LOAD_FAST            context
 322: LOAD_METHOD          _raise_error
 344: LOAD_GLOBAL          InvalidOperation
 356: LOAD_CONST           'sqrt(-x), x > 0'
 358: PRECALL              
 362: CALL                 
 372: RETURN_VALUE         
 374: LOAD_FAST            context
 376: LOAD_ATTR            prec
 386: LOAD_CONST           1
 388: BINARY_OP            +
 392: STORE_FAST           prec
 394: LOAD_GLOBAL          NULL + _WorkRep
 406: LOAD_FAST            self
 408: PRECALL              
 412: CALL                 
 422: STORE_FAST           op
 424: LOAD_FAST            op
 426: LOAD_ATTR            exp
 436: LOAD_CONST           1
 438: BINARY_OP            >>
 442: STORE_FAST           e
 444: LOAD_FAST            op
 446: LOAD_ATTR            exp
 456: LOAD_CONST           1
 458: BINARY_OP            &
 462: POP_JUMP_FORWARD_IF_FALSE to 538
 464: LOAD_FAST            op
 466: LOAD_ATTR            int
 476: LOAD_CONST           10
 478: BINARY_OP            *
 482: STORE_FAST           c
 484: LOAD_GLOBAL          NULL + len
 496: LOAD_FAST            self
 498: LOAD_ATTR            _int
 508: PRECALL              
 512: CALL                 
 522: LOAD_CONST           1
 524: BINARY_OP            >>
 528: LOAD_CONST           1
 530: BINARY_OP            +
 534: STORE_FAST           l
 536: JUMP_FORWARD         to 604
 538: LOAD_FAST            op
 540: LOAD_ATTR            int
 550: STORE_FAST           c
 552: LOAD_GLOBAL          NULL + len
 564: LOAD_FAST            self
 566: LOAD_ATTR            _int
 576: PRECALL              
 580: CALL                 
 590: LOAD_CONST           1
 592: BINARY_OP            +
 596: LOAD_CONST           1
 598: BINARY_OP            >>
 602: STORE_FAST           l
 604: LOAD_FAST            prec
 606: LOAD_FAST            l
 608: BINARY_OP            -
 612: STORE_FAST           shift
 614: LOAD_FAST            shift
 616: LOAD_CONST           0
 618: COMPARE_OP           >=
 624: POP_JUMP_FORWARD_IF_FALSE to 648
 626: LOAD_FAST            c
 628: LOAD_CONST           100
 630: LOAD_FAST            shift
 632: BINARY_OP            **
 636: BINARY_OP            *=
 640: STORE_FAST           c
 642: LOAD_CONST           True
 644: STORE_FAST           exact
 646: JUMP_FORWARD         to 700
 648: LOAD_GLOBAL          NULL + divmod
 660: LOAD_FAST            c
 662: LOAD_CONST           100
 664: LOAD_FAST            shift
 666: UNARY_NEGATIVE       
 668: BINARY_OP            **
 672: PRECALL              
 676: CALL                 
 686: UNPACK_SEQUENCE      
 690: STORE_FAST           c
 692: STORE_FAST           remainder
 694: LOAD_FAST            remainder
 696: UNARY_NOT            
 698: STORE_FAST           exact
 700: LOAD_FAST            e
 702: LOAD_FAST            shift
 704: BINARY_OP            -=
 708: STORE_FAST           e
 710: LOAD_CONST           10
 712: LOAD_FAST            prec
 714: BINARY_OP            **
 718: STORE_FAST           n
 720: NOP                  
 722: LOAD_FAST            c
 724: LOAD_FAST            n
 726: BINARY_OP            //
 730: STORE_FAST           q
 732: LOAD_FAST            n
 734: LOAD_FAST            q
 736: COMPARE_OP           <=
 742: POP_JUMP_FORWARD_IF_FALSE to 746
 744: JUMP_FORWARD         to 764
 746: LOAD_FAST            n
 748: LOAD_FAST            q
 750: BINARY_OP            +
 754: LOAD_CONST           1
 756: BINARY_OP            >>
 760: STORE_FAST           n
 762: JUMP_BACKWARD        to 722
 764: LOAD_FAST            exact
 766: JUMP_IF_FALSE_OR_POP to 784
 768: LOAD_FAST            n
 770: LOAD_FAST            n
 772: BINARY_OP            *
 776: LOAD_FAST            c
 778: COMPARE_OP           ==
 784: STORE_FAST           exact
 786: LOAD_FAST            exact
 788: POP_JUMP_FORWARD_IF_FALSE to 850
 790: LOAD_FAST            shift
 792: LOAD_CONST           0
 794: COMPARE_OP           >=
 800: POP_JUMP_FORWARD_IF_FALSE to 820
 802: LOAD_FAST            n
 804: LOAD_CONST           10
 806: LOAD_FAST            shift
 808: BINARY_OP            **
 812: BINARY_OP            //=
 816: STORE_FAST           n
 818: JUMP_FORWARD         to 838
 820: LOAD_FAST            n
 822: LOAD_CONST           10
 824: LOAD_FAST            shift
 826: UNARY_NEGATIVE       
 828: BINARY_OP            **
 832: BINARY_OP            *=
 836: STORE_FAST           n
 838: LOAD_FAST            e
 840: LOAD_FAST            shift
 842: BINARY_OP            +=
 846: STORE_FAST           e
 848: JUMP_FORWARD         to 878
 850: LOAD_FAST            n
 852: LOAD_CONST           5
 854: BINARY_OP            %
 858: LOAD_CONST           0
 860: COMPARE_OP           ==
 866: POP_JUMP_FORWARD_IF_FALSE to 878
 868: LOAD_FAST            n
 870: LOAD_CONST           1
 872: BINARY_OP            +=
 876: STORE_FAST           n
 878: LOAD_GLOBAL          NULL + _dec_from_triple
 890: LOAD_CONST           0
 892: LOAD_GLOBAL          NULL + str
 904: LOAD_FAST            n
 906: PRECALL              
 910: CALL                 
 920: LOAD_FAST            e
 922: PRECALL              
 926: CALL                 
 936: STORE_FAST           ans
 938: LOAD_FAST            context
 940: LOAD_METHOD          _shallow_copy
 962: PRECALL              
 966: CALL                 
 976: STORE_FAST           context
 978: LOAD_FAST            context
 980: LOAD_METHOD          _set_rounding
1002: LOAD_GLOBAL          ROUND_HALF_EVEN
1014: PRECALL              
1018: CALL                 
1028: STORE_FAST           rounding
1030: LOAD_FAST            ans
1032: LOAD_METHOD          _fix
1054: LOAD_FAST            context
1056: PRECALL              
1060: CALL                 
1070: STORE_FAST           ans
1072: LOAD_FAST            rounding
1074: LOAD_FAST            context
1076: STORE_ATTR           rounding
1086: LOAD_FAST            ans
1088: RETURN_VALUE         
