# Disassembly for _pydecimal.Context.shift
# From module file: _pydecimal

## co_consts:
("Returns a shifted copy of a, b times.\n\n        The coefficient of the result is a shifted copy of the digits\n        in the coefficient of the first operand.  The number of places\n        to shift is taken from the absolute value of the second operand,\n        with the shift being to the left if the second operand is\n        positive or to the right otherwise.  Digits shifted into the\n        coefficient are zeros.\n\n        >>> ExtendedContext.shift(Decimal('34'), Decimal('8'))\n        Decimal('400000000')\n        >>> ExtendedContext.shift(Decimal('12'), Decimal('9'))\n        Decimal('0')\n        >>> ExtendedContext.shift(Decimal('123456789'), Decimal('-2'))\n        Decimal('1234567')\n        >>> ExtendedContext.shift(Decimal('123456789'), Decimal('0'))\n        Decimal('123456789')\n        >>> ExtendedContext.shift(Decimal('123456789'), Decimal('+2'))\n        Decimal('345678900')\n        >>> ExtendedContext.shift(88888888, 2)\n        Decimal('888888800')\n        >>> ExtendedContext.shift(Decimal(88888888), 2)\n        Decimal('888888800')\n        >>> ExtendedContext.shift(88888888, Decimal(2))\n        Decimal('888888800')\n        ", True, ('raiseit',), ('context',))

## co_names:
('_convert_other', 'shift')

## bytecode:

   0: RESUME               
   2: LOAD_GLOBAL          NULL + _convert_other
  14: LOAD_FAST            a
  16: LOAD_CONST           True
  18: KW_NAMES             
  20: PRECALL              
  24: CALL                 
  34: STORE_FAST           a
  36: LOAD_FAST            a
  38: LOAD_METHOD          shift
  60: LOAD_FAST            b
  62: LOAD_FAST            self
  64: KW_NAMES             
  66: PRECALL              
  70: CALL                 
  80: RETURN_VALUE         
