# Disassembly for _pydecimal.Decimal.compare_total_mag
# From module file: _pydecimal

## co_consts:
("Compares self to other using abstract repr., ignoring sign.\n\n        Like compare_total, but with operand's sign ignored and assumed to be 0.\n        ", True, ('raiseit',))

## co_names:
('_convert_other', 'copy_abs', 'compare_total')

## bytecode:

   0: RESUME               
   2: LOAD_GLOBAL          NULL + _convert_other
  14: LOAD_FAST            other
  16: LOAD_CONST           True
  18: KW_NAMES             
  20: PRECALL              
  24: CALL                 
  34: STORE_FAST           other
  36: LOAD_FAST            self
  38: LOAD_METHOD          copy_abs
  60: PRECALL              
  64: CALL                 
  74: STORE_FAST           s
  76: LOAD_FAST            other
  78: LOAD_METHOD          copy_abs
 100: PRECALL              
 104: CALL                 
 114: STORE_FAST           o
 116: LOAD_FAST            s
 118: LOAD_METHOD          compare_total
 140: LOAD_FAST            o
 142: PRECALL              
 146: CALL                 
 156: RETURN_VALUE         
