# Disassembly for _pydecimal.ConversionSyntax
# From module file: _pydecimal

## co_consts:
('ConversionSyntax', 'Trying to convert badly formed string.\n\n    This occurs and signals invalid-operation if a string is being\n    converted to a number and it does not conform to the numeric string\n    syntax.  The result is [0,qNaN].\n    ', <code object handle at 0x0000024069496250, file "_pydecimal.py", line 263>, None)

## co_names:
('__name__', '__module__', '__qualname__', '__doc__', 'handle')

## bytecode:

   0: RESUME               
   2: LOAD_NAME            __name__
   4: STORE_NAME           __module__
   6: LOAD_CONST           'ConversionSyntax'
   8: STORE_NAME           __qualname__
  10: LOAD_CONST           'Trying to convert badly formed string.\n\n    This occurs and signals invalid-operation if a string is being\n    converted to a number and it does not conform to the numeric string\n    syntax.  The result is [0,qNaN].\n    '
  12: STORE_NAME           __doc__
  14: LOAD_CONST           <code object handle at 0x0000024069496250, file "_pydecimal.py", line 263>
  16: MAKE_FUNCTION        
  18: STORE_NAME           handle
  20: LOAD_CONST           None
  22: RETURN_VALUE         
