# Disassembly for _pydecimal.Inexact
# From module file: _pydecimal

## co_consts:
('Inexact', 'Had to round, losing information.\n\n    This occurs and signals inexact whenever the result of an operation is\n    not exact (that is, it needed to be rounded and any discarded digits\n    were non-zero), or if an overflow or underflow condition occurs.  The\n    result in all cases is unchanged.\n\n    The inexact signal may be tested (or trapped) to determine if a given\n    operation (or sequence of operations) was inexact.\n    ', None)

## co_names:
('__name__', '__module__', '__qualname__', '__doc__')

## bytecode:

   0: RESUME               
   2: LOAD_NAME            __name__
   4: STORE_NAME           __module__
   6: LOAD_CONST           'Inexact'
   8: STORE_NAME           __qualname__
  10: LOAD_CONST           'Had to round, losing information.\n\n    This occurs and signals inexact whenever the result of an operation is\n    not exact (that is, it needed to be rounded and any discarded digits\n    were non-zero), or if an overflow or underflow condition occurs.  The\n    result in all cases is unchanged.\n\n    The inexact signal may be tested (or trapped) to determine if a given\n    operation (or sequence of operations) was inexact.\n    '
  12: STORE_NAME           __doc__
  14: LOAD_CONST           None
  16: RETURN_VALUE         
