# Disassembly for _pydecimal.Context.logical_invert
# From module file: _pydecimal

## co_consts:
("Invert all the digits in the operand.\n\n        The operand must be a logical number.\n\n        >>> ExtendedContext.logical_invert(Decimal('0'))\n        Decimal('111111111')\n        >>> ExtendedContext.logical_invert(Decimal('1'))\n        Decimal('111111110')\n        >>> ExtendedContext.logical_invert(Decimal('111111111'))\n        Decimal('0')\n        >>> ExtendedContext.logical_invert(Decimal('101010101'))\n        Decimal('10101010')\n        >>> ExtendedContext.logical_invert(1101)\n        Decimal('111110010')\n        ", True, ('raiseit',), ('context',))

## co_names:
('_convert_other', 'logical_invert')

## bytecode:

   0: RESUME               
   2: LOAD_GLOBAL          NULL + _convert_other
  14: LOAD_FAST            a
  16: LOAD_CONST           True
  18: KW_NAMES             
  20: PRECALL              
  24: CALL                 
  34: STORE_FAST           a
  36: LOAD_FAST            a
  38: LOAD_METHOD          logical_invert
  60: LOAD_FAST            self
  62: KW_NAMES             
  64: PRECALL              
  68: CALL                 
  78: RETURN_VALUE         
