# Disassembly for _pydecimal.Context.max_mag
# From module file: _pydecimal

## co_consts:
("Compares the values numerically with their sign ignored.\n\n        >>> ExtendedContext.max_mag(Decimal('7'), Decimal('NaN'))\n        Decimal('7')\n        >>> ExtendedContext.max_mag(Decimal('7'), Decimal('-10'))\n        Decimal('-10')\n        >>> ExtendedContext.max_mag(1, -2)\n        Decimal('-2')\n        >>> ExtendedContext.max_mag(Decimal(1), -2)\n        Decimal('-2')\n        >>> ExtendedContext.max_mag(1, Decimal(-2))\n        Decimal('-2')\n        ", True, ('raiseit',), ('context',))

## co_names:
('_convert_other', 'max_mag')

## bytecode:

   0: RESUME               
   2: LOAD_GLOBAL          NULL + _convert_other
  14: LOAD_FAST            a
  16: LOAD_CONST           True
  18: KW_NAMES             
  20: PRECALL              
  24: CALL                 
  34: STORE_FAST           a
  36: LOAD_FAST            a
  38: LOAD_METHOD          max_mag
  60: LOAD_FAST            b
  62: LOAD_FAST            self
  64: KW_NAMES             
  66: PRECALL              
  70: CALL                 
  80: RETURN_VALUE         
