# Disassembly for _pydecimal.Context.normalize
# From module file: _pydecimal

## co_consts:
("normalize reduces an operand to its simplest form.\n\n        Essentially a plus operation with all trailing zeros removed from the\n        result.\n\n        >>> ExtendedContext.normalize(Decimal('2.1'))\n        Decimal('2.1')\n        >>> ExtendedContext.normalize(Decimal('-2.0'))\n        Decimal('-2')\n        >>> ExtendedContext.normalize(Decimal('1.200'))\n        Decimal('1.2')\n        >>> ExtendedContext.normalize(Decimal('-120'))\n        Decimal('-1.2E+2')\n        >>> ExtendedContext.normalize(Decimal('120.00'))\n        Decimal('1.2E+2')\n        >>> ExtendedContext.normalize(Decimal('0.00'))\n        Decimal('0')\n        >>> ExtendedContext.normalize(6)\n        Decimal('6')\n        ", True, ('raiseit',), ('context',))

## co_names:
('_convert_other', 'normalize')

## bytecode:

   0: RESUME               
   2: LOAD_GLOBAL          NULL + _convert_other
  14: LOAD_FAST            a
  16: LOAD_CONST           True
  18: KW_NAMES             
  20: PRECALL              
  24: CALL                 
  34: STORE_FAST           a
  36: LOAD_FAST            a
  38: LOAD_METHOD          normalize
  60: LOAD_FAST            self
  62: KW_NAMES             
  64: PRECALL              
  68: CALL                 
  78: RETURN_VALUE         
