# Disassembly for _pydecimal.Decimal.fma
# From module file: _pydecimal

## co_consts:
('Fused multiply-add.\n\n        Returns self*other+third with no rounding of the intermediate\n        product self*other.\n\n        self and other are multiplied together, with no rounding of\n        the result.  The third operand is then added to the result,\n        and a single final rounding is performed.\n        ', True, ('raiseit',), None, 'N', 'sNaN', 'n', 'F', 'INF * 0 in fma', '0 * INF in fma')

## co_names:
('_convert_other', '_is_special', 'getcontext', '_exp', '_raise_error', 'InvalidOperation', '_SignedInfinity', '_sign', '_dec_from_triple', 'str', 'int', '_int', '__add__')

## bytecode:

   0: RESUME               
   2: LOAD_GLOBAL          NULL + _convert_other
  14: LOAD_FAST            other
  16: LOAD_CONST           True
  18: KW_NAMES             
  20: PRECALL              
  24: CALL                 
  34: STORE_FAST           other
  36: LOAD_GLOBAL          NULL + _convert_other
  48: LOAD_FAST            third
  50: LOAD_CONST           True
  52: KW_NAMES             
  54: PRECALL              
  58: CALL                 
  68: STORE_FAST           third
  70: LOAD_FAST            self
  72: LOAD_ATTR            _is_special
  82: POP_JUMP_FORWARD_IF_TRUE to 100
  84: LOAD_FAST            other
  86: LOAD_ATTR            _is_special
  96: EXTENDED_ARG         
  98: POP_JUMP_FORWARD_IF_FALSE to 612
 100: LOAD_FAST            context
 102: POP_JUMP_FORWARD_IF_NOT_NONE to 132
 104: LOAD_GLOBAL          NULL + getcontext
 116: PRECALL              
 120: CALL                 
 130: STORE_FAST           context
 132: LOAD_FAST            self
 134: LOAD_ATTR            _exp
 144: LOAD_CONST           'N'
 146: COMPARE_OP           ==
 152: POP_JUMP_FORWARD_IF_FALSE to 210
 154: LOAD_FAST            context
 156: LOAD_METHOD          _raise_error
 178: LOAD_GLOBAL          InvalidOperation
 190: LOAD_CONST           'sNaN'
 192: LOAD_FAST            self
 194: PRECALL              
 198: CALL                 
 208: RETURN_VALUE         
 210: LOAD_FAST            other
 212: LOAD_ATTR            _exp
 222: LOAD_CONST           'N'
 224: COMPARE_OP           ==
 230: POP_JUMP_FORWARD_IF_FALSE to 288
 232: LOAD_FAST            context
 234: LOAD_METHOD          _raise_error
 256: LOAD_GLOBAL          InvalidOperation
 268: LOAD_CONST           'sNaN'
 270: LOAD_FAST            other
 272: PRECALL              
 276: CALL                 
 286: RETURN_VALUE         
 288: LOAD_FAST            self
 290: LOAD_ATTR            _exp
 300: LOAD_CONST           'n'
 302: COMPARE_OP           ==
 308: POP_JUMP_FORWARD_IF_FALSE to 316
 310: LOAD_FAST            self
 312: STORE_FAST           product
 314: JUMP_FORWARD         to 802
 316: LOAD_FAST            other
 318: LOAD_ATTR            _exp
 328: LOAD_CONST           'n'
 330: COMPARE_OP           ==
 336: POP_JUMP_FORWARD_IF_FALSE to 344
 338: LOAD_FAST            other
 340: STORE_FAST           product
 342: JUMP_FORWARD         to 802
 344: LOAD_FAST            self
 346: LOAD_ATTR            _exp
 356: LOAD_CONST           'F'
 358: COMPARE_OP           ==
 364: POP_JUMP_FORWARD_IF_FALSE to 478
 366: LOAD_FAST            other
 368: POP_JUMP_FORWARD_IF_TRUE to 424
 370: LOAD_FAST            context
 372: LOAD_METHOD          _raise_error
 394: LOAD_GLOBAL          InvalidOperation
 406: LOAD_CONST           'INF * 0 in fma'
 408: PRECALL              
 412: CALL                 
 422: RETURN_VALUE         
 424: LOAD_GLOBAL          _SignedInfinity
 436: LOAD_FAST            self
 438: LOAD_ATTR            _sign
 448: LOAD_FAST            other
 450: LOAD_ATTR            _sign
 460: BINARY_OP            ^
 464: BINARY_SUBSCR        
 474: STORE_FAST           product
 476: JUMP_FORWARD         to 802
 478: LOAD_FAST            other
 480: LOAD_ATTR            _exp
 490: LOAD_CONST           'F'
 492: COMPARE_OP           ==
 498: POP_JUMP_FORWARD_IF_FALSE to 610
 500: LOAD_FAST            self
 502: POP_JUMP_FORWARD_IF_TRUE to 558
 504: LOAD_FAST            context
 506: LOAD_METHOD          _raise_error
 528: LOAD_GLOBAL          InvalidOperation
 540: LOAD_CONST           '0 * INF in fma'
 542: PRECALL              
 546: CALL                 
 556: RETURN_VALUE         
 558: LOAD_GLOBAL          _SignedInfinity
 570: LOAD_FAST            self
 572: LOAD_ATTR            _sign
 582: LOAD_FAST            other
 584: LOAD_ATTR            _sign
 594: BINARY_OP            ^
 598: BINARY_SUBSCR        
 608: STORE_FAST           product
 610: JUMP_FORWARD         to 802
 612: LOAD_GLOBAL          NULL + _dec_from_triple
 624: LOAD_FAST            self
 626: LOAD_ATTR            _sign
 636: LOAD_FAST            other
 638: LOAD_ATTR            _sign
 648: BINARY_OP            ^
 652: LOAD_GLOBAL          NULL + str
 664: LOAD_GLOBAL          NULL + int
 676: LOAD_FAST            self
 678: LOAD_ATTR            _int
 688: PRECALL              
 692: CALL                 
 702: LOAD_GLOBAL          NULL + int
 714: LOAD_FAST            other
 716: LOAD_ATTR            _int
 726: PRECALL              
 730: CALL                 
 740: BINARY_OP            *
 744: PRECALL              
 748: CALL                 
 758: LOAD_FAST            self
 760: LOAD_ATTR            _exp
 770: LOAD_FAST            other
 772: LOAD_ATTR            _exp
 782: BINARY_OP            +
 786: PRECALL              
 790: CALL                 
 800: STORE_FAST           product
 802: LOAD_FAST            product
 804: LOAD_METHOD          __add__
 826: LOAD_FAST            third
 828: LOAD_FAST            context
 830: PRECALL              
 834: CALL                 
 844: RETURN_VALUE         
