# Disassembly for _pydecimal._dec_from_triple
# From module file: _pydecimal

## co_consts:
('Create a decimal instance directly, without any validation,\n    normalization (e.g. removal of leading zeros) or argument\n    conversion.\n\n    This function is for *internal use only*.\n    ',)

## co_names:
('object', '__new__', 'Decimal', '_sign', '_int', '_exp', '_is_special')

## bytecode:

   0: RESUME               
   2: LOAD_GLOBAL          object
  14: LOAD_METHOD          __new__
  36: LOAD_GLOBAL          Decimal
  48: PRECALL              
  52: CALL                 
  62: STORE_FAST           self
  64: LOAD_FAST            sign
  66: LOAD_FAST            self
  68: STORE_ATTR           _sign
  78: LOAD_FAST            coefficient
  80: LOAD_FAST            self
  82: STORE_ATTR           _int
  92: LOAD_FAST            exponent
  94: LOAD_FAST            self
  96: STORE_ATTR           _exp
 106: LOAD_FAST            special
 108: LOAD_FAST            self
 110: STORE_ATTR           _is_special
 120: LOAD_FAST            self
 122: RETURN_VALUE         
