# Disassembly for _pydecimal.Context
# From module file: _pydecimal

## co_consts:
('Context', 'Contains the context for a Decimal instance.\n\n    Contains:\n    prec - precision (for use in rounding, division, square roots..)\n    rounding - rounding type (how you round)\n    traps - If traps[exception] = 1, then the exception is\n                    raised when it is caused.  Otherwise, a value is\n                    substituted in.\n    flags  - When an exception is caused, flags[exception] is set.\n             (Whether or not the trap_enabler is set)\n             Should be reset by user of Decimal instance.\n    Emin -   Minimum exponent\n    Emax -   Maximum exponent\n    capitals -      If 1, 1*10^1 is printed as 1E+1.\n                    If 0, printed as 1e1\n    clamp -  If 1, change exponents if too high (Default 0)\n    ', None, <code object __init__ at 0x0000024068C2A210, file "_pydecimal.py", line 3902>, <code object _set_integer_check at 0x0000024068E21720, file "_pydecimal.py", line 3938>, <code object _set_signal_dict at 0x0000024069498E30, file "_pydecimal.py", line 3952>, <code object __setattr__ at 0x0000024068C54340, file "_pydecimal.py", line 3963>, <code object __delattr__ at 0x0000024069465530, file "_pydecimal.py", line 3988>, <code object __reduce__ at 0x000002406934FB40, file "_pydecimal.py", line 3992>, <code object __repr__ at 0x0000024066C25170, file "_pydecimal.py", line 3999>, <code object clear_flags at 0x000002406945F870, file "_pydecimal.py", line 4012>, <code object clear_traps at 0x000002406945E1F0, file "_pydecimal.py", line 4017>, <code object _shallow_copy at 0x000002406922C2D0, file "_pydecimal.py", line 4022>, <code object copy at 0x000002406942E8D0, file "_pydecimal.py", line 4029>, <code object _raise_error at 0x00000240691F6C10, file "_pydecimal.py", line 4038>, <code object _ignore_all_flags at 0x0000024069465990, file "_pydecimal.py", line 4060>, <code object _ignore_flags at 0x000002406944ADE0, file "_pydecimal.py", line 4064>, <code object _regard_flags at 0x00000240691C3470, file "_pydecimal.py", line 4071>, <code object Etiny at 0x00000240693EB530, file "_pydecimal.py", line 4081>, <code object Etop at 0x00000240693EA230, file "_pydecimal.py", line 4085>, <code object _set_rounding at 0x0000024069465290, file "_pydecimal.py", line 4089>, '0', <code object create_decimal at 0x0000024068D6D540, file "_pydecimal.py", line 4108>, <code object create_decimal_from_float at 0x00000240694196B0, file "_pydecimal.py", line 4125>, <code object abs at 0x000002406944B330, file "_pydecimal.py", line 4143>, <code object add at 0x000002406922D290, file "_pydecimal.py", line 4164>, <code object _apply at 0x00000240693EB430, file "_pydecimal.py", line 4185>, <code object canonical at 0x00000240693D3930, file "_pydecimal.py", line 4188>, <code object compare at 0x000002406944B660, file "_pydecimal.py", line 4201>, <code object compare_signal at 0x000002406944BCC0, file "_pydecimal.py", line 4237>, <code object compare_total at 0x000002406944B550, file "_pydecimal.py", line 4272>, <code object compare_total_mag at 0x000002406944A010, file "_pydecimal.py", line 4301>, <code object copy_abs at 0x000002406944BEE0, file "_pydecimal.py", line 4309>, <code object copy_decimal at 0x00000240693EB730, file "_pydecimal.py", line 4322>, <code object copy_negate at 0x000002406944B770, file "_pydecimal.py", line 4335>, <code object copy_sign at 0x000002406944B990, file "_pydecimal.py", line 4348>, <code object divide at 0x000002406922D7D0, file "_pydecimal.py", line 4372>, <code object divide_int at 0x000002406922C570, file "_pydecimal.py", line 4409>, <code object divmod at 0x000002406922D3E0, file "_pydecimal.py", line 4432>, <code object exp at 0x0000024069449F00, file "_pydecimal.py", line 4453>, <code object fma at 0x000002406944BDD0, file "_pydecimal.py", line 4477>, <code object is_canonical at 0x00000240693D3340, file "_pydecimal.py", line 4500>, <code object is_finite at 0x000002406944A340, file "_pydecimal.py", line 4513>, <code object is_infinite at 0x000002406944B440, file "_pydecimal.py", line 4535>, <code object is_nan at 0x000002406944A230, file "_pydecimal.py", line 4550>, <code object is_normal at 0x000002406944A670, file "_pydecimal.py", line 4566>, <code object is_qnan at 0x000002406944B110, file "_pydecimal.py", line 4589>, <code object is_signed at 0x000002406944BAA0, file "_pydecimal.py", line 4604>, <code object is_snan at 0x000002406944BBB0, file "_pydecimal.py", line 4621>, <code object is_subnormal at 0x0000024069CD8030, file "_pydecimal.py", line 4637>, <code object is_zero at 0x0000024069CD8140, file "_pydecimal.py", line 4659>, <code object ln at 0x0000024069CD8250, file "_pydecimal.py", line 4676>, <code object log10 at 0x0000024069CD8360, file "_pydecimal.py", line 4698>, <code object logb at 0x0000024069CD8470, file "_pydecimal.py", line 4726>, <code object logical_and at 0x0000024069CD8580, file "_pydecimal.py", line 4752>, <code object logical_invert at 0x0000024069CD8690, file "_pydecimal.py", line 4779>, <code object logical_or at 0x0000024069CD87A0, file "_pydecimal.py", line 4798>, <code object logical_xor at 0x0000024069CD88B0, file "_pydecimal.py", line 4825>, <code object max at 0x0000024069CD89C0, file "_pydecimal.py", line 4852>, <code object max_mag at 0x0000024069CD8AD0, file "_pydecimal.py", line 4879>, <code object min at 0x0000024069CD8BE0, file "_pydecimal.py", line 4896>, <code object min_mag at 0x0000024069CD8CF0, file "_pydecimal.py", line 4923>, <code object minus at 0x0000024069CD8E00, file "_pydecimal.py", line 4940>, <code object multiply at 0x000002406922CEA0, file "_pydecimal.py", line 4957>, <code object next_minus at 0x0000024069CD8F10, file "_pydecimal.py", line 4989>, <code object next_plus at 0x0000024069CD9020, file "_pydecimal.py", line 5009>, <code object next_toward at 0x0000024069CD9130, file "_pydecimal.py", line 5029>, <code object normalize at 0x0000024069CD9240, file "_pydecimal.py", line 5064>, <code object number_class at 0x0000024069CD9350, file "_pydecimal.py", line 5088>, <code object plus at 0x0000024069CD9460, file "_pydecimal.py", line 5138>, <code object power at 0x000002406922CAB0, file "_pydecimal.py", line 5155>, <code object quantize at 0x0000024069CD9570, file "_pydecimal.py", line 5235>, <code object radix at 0x0000024069467130, file "_pydecimal.py", line 5293>, <code object remainder at 0x000002406922C030, file "_pydecimal.py", line 5301>, <code object remainder_near at 0x0000024069CD9680, file "_pydecimal.py", line 5339>, <code object rotate at 0x0000024069CD9790, file "_pydecimal.py", line 5373>, <code object same_quantum at 0x0000024069CD98A0, file "_pydecimal.py", line 5402>, <code object scaleb at 0x0000024069CD99B0, file "_pydecimal.py", line 5426>, <code object shift at 0x0000024069CD9AC0, file "_pydecimal.py", line 5445>, <code object sqrt at 0x0000024069CD9BD0, file "_pydecimal.py", line 5475>, <code object subtract at 0x000002406922DBC0, file "_pydecimal.py", line 5507>, <code object to_eng_string at 0x0000024069CD9CE0, file "_pydecimal.py", line 5530>, <code object to_sci_string at 0x0000024069CD9DF0, file "_pydecimal.py", line 5558>, <code object to_integral_exact at 0x0000024069CD9F00, file "_pydecimal.py", line 5566>, <code object to_integral_value at 0x0000024069CDA010, file "_pydecimal.py", line 5596>, (None, None, None, None, None, None, None, None, None), (None,), ('0',))

## co_names:
('__name__', '__module__', '__qualname__', '__doc__', '__init__', '_set_integer_check', '_set_signal_dict', '__setattr__', '__delattr__', '__reduce__', '__repr__', 'clear_flags', 'clear_traps', '_shallow_copy', 'copy', '__copy__', '_raise_error', '_ignore_all_flags', '_ignore_flags', '_regard_flags', '__hash__', 'Etiny', 'Etop', '_set_rounding', 'create_decimal', 'create_decimal_from_float', 'abs', 'add', '_apply', 'canonical', 'compare', 'compare_signal', 'compare_total', 'compare_total_mag', 'copy_abs', 'copy_decimal', 'copy_negate', 'copy_sign', 'divide', 'divide_int', 'divmod', 'exp', 'fma', 'is_canonical', 'is_finite', 'is_infinite', 'is_nan', 'is_normal', 'is_qnan', 'is_signed', 'is_snan', 'is_subnormal', 'is_zero', 'ln', 'log10', 'logb', 'logical_and', 'logical_invert', 'logical_or', 'logical_xor', 'max', 'max_mag', 'min', 'min_mag', 'minus', 'multiply', 'next_minus', 'next_plus', 'next_toward', 'normalize', 'number_class', 'plus', 'power', 'quantize', 'radix', 'remainder', 'remainder_near', 'rotate', 'same_quantum', 'scaleb', 'shift', 'sqrt', 'subtract', 'to_eng_string', 'to_sci_string', 'to_integral_exact', 'to_integral_value', 'to_integral')

## bytecode:

   0: RESUME               
   2: LOAD_NAME            __name__
   4: STORE_NAME           __module__
   6: LOAD_CONST           'Context'
   8: STORE_NAME           __qualname__
  10: LOAD_CONST           'Contains the context for a Decimal instance.\n\n    Contains:\n    prec - precision (for use in rounding, division, square roots..)\n    rounding - rounding type (how you round)\n    traps - If traps[exception] = 1, then the exception is\n                    raised when it is caused.  Otherwise, a value is\n                    substituted in.\n    flags  - When an exception is caused, flags[exception] is set.\n             (Whether or not the trap_enabler is set)\n             Should be reset by user of Decimal instance.\n    Emin -   Minimum exponent\n    Emax -   Maximum exponent\n    capitals -      If 1, 1*10^1 is printed as 1E+1.\n                    If 0, printed as 1e1\n    clamp -  If 1, change exponents if too high (Default 0)\n    '
  12: STORE_NAME           __doc__
  14: NOP                  
  16: NOP                  
  18: NOP                  
  20: LOAD_CONST           (None, None, None, None, None, None, None, None, None)
  22: LOAD_CONST           <code object __init__ at 0x0000024068C2A210, file "_pydecimal.py", line 3902>
  24: MAKE_FUNCTION        defaults
  26: STORE_NAME           __init__
  28: LOAD_CONST           <code object _set_integer_check at 0x0000024068E21720, file "_pydecimal.py", line 3938>
  30: MAKE_FUNCTION        
  32: STORE_NAME           _set_integer_check
  34: LOAD_CONST           <code object _set_signal_dict at 0x0000024069498E30, file "_pydecimal.py", line 3952>
  36: MAKE_FUNCTION        
  38: STORE_NAME           _set_signal_dict
  40: LOAD_CONST           <code object __setattr__ at 0x0000024068C54340, file "_pydecimal.py", line 3963>
  42: MAKE_FUNCTION        
  44: STORE_NAME           __setattr__
  46: LOAD_CONST           <code object __delattr__ at 0x0000024069465530, file "_pydecimal.py", line 3988>
  48: MAKE_FUNCTION        
  50: STORE_NAME           __delattr__
  52: LOAD_CONST           <code object __reduce__ at 0x000002406934FB40, file "_pydecimal.py", line 3992>
  54: MAKE_FUNCTION        
  56: STORE_NAME           __reduce__
  58: LOAD_CONST           <code object __repr__ at 0x0000024066C25170, file "_pydecimal.py", line 3999>
  60: MAKE_FUNCTION        
  62: STORE_NAME           __repr__
  64: LOAD_CONST           <code object clear_flags at 0x000002406945F870, file "_pydecimal.py", line 4012>
  66: MAKE_FUNCTION        
  68: STORE_NAME           clear_flags
  70: LOAD_CONST           <code object clear_traps at 0x000002406945E1F0, file "_pydecimal.py", line 4017>
  72: MAKE_FUNCTION        
  74: STORE_NAME           clear_traps
  76: LOAD_CONST           <code object _shallow_copy at 0x000002406922C2D0, file "_pydecimal.py", line 4022>
  78: MAKE_FUNCTION        
  80: STORE_NAME           _shallow_copy
  82: LOAD_CONST           <code object copy at 0x000002406942E8D0, file "_pydecimal.py", line 4029>
  84: MAKE_FUNCTION        
  86: STORE_NAME           copy
  88: LOAD_NAME            copy
  90: STORE_NAME           __copy__
  92: LOAD_CONST           (None,)
  94: LOAD_CONST           <code object _raise_error at 0x00000240691F6C10, file "_pydecimal.py", line 4038>
  96: MAKE_FUNCTION        defaults
  98: STORE_NAME           _raise_error
 100: LOAD_CONST           <code object _ignore_all_flags at 0x0000024069465990, file "_pydecimal.py", line 4060>
 102: MAKE_FUNCTION        
 104: STORE_NAME           _ignore_all_flags
 106: LOAD_CONST           <code object _ignore_flags at 0x000002406944ADE0, file "_pydecimal.py", line 4064>
 108: MAKE_FUNCTION        
 110: STORE_NAME           _ignore_flags
 112: LOAD_CONST           <code object _regard_flags at 0x00000240691C3470, file "_pydecimal.py", line 4071>
 114: MAKE_FUNCTION        
 116: STORE_NAME           _regard_flags
 118: LOAD_CONST           None
 120: STORE_NAME           __hash__
 122: LOAD_CONST           <code object Etiny at 0x00000240693EB530, file "_pydecimal.py", line 4081>
 124: MAKE_FUNCTION        
 126: STORE_NAME           Etiny
 128: LOAD_CONST           <code object Etop at 0x00000240693EA230, file "_pydecimal.py", line 4085>
 130: MAKE_FUNCTION        
 132: STORE_NAME           Etop
 134: LOAD_CONST           <code object _set_rounding at 0x0000024069465290, file "_pydecimal.py", line 4089>
 136: MAKE_FUNCTION        
 138: STORE_NAME           _set_rounding
 140: LOAD_CONST           ('0',)
 142: LOAD_CONST           <code object create_decimal at 0x0000024068D6D540, file "_pydecimal.py", line 4108>
 144: MAKE_FUNCTION        defaults
 146: STORE_NAME           create_decimal
 148: LOAD_CONST           <code object create_decimal_from_float at 0x00000240694196B0, file "_pydecimal.py", line 4125>
 150: MAKE_FUNCTION        
 152: STORE_NAME           create_decimal_from_float
 154: LOAD_CONST           <code object abs at 0x000002406944B330, file "_pydecimal.py", line 4143>
 156: MAKE_FUNCTION        
 158: STORE_NAME           abs
 160: LOAD_CONST           <code object add at 0x000002406922D290, file "_pydecimal.py", line 4164>
 162: MAKE_FUNCTION        
 164: STORE_NAME           add
 166: LOAD_CONST           <code object _apply at 0x00000240693EB430, file "_pydecimal.py", line 4185>
 168: MAKE_FUNCTION        
 170: STORE_NAME           _apply
 172: LOAD_CONST           <code object canonical at 0x00000240693D3930, file "_pydecimal.py", line 4188>
 174: MAKE_FUNCTION        
 176: STORE_NAME           canonical
 178: LOAD_CONST           <code object compare at 0x000002406944B660, file "_pydecimal.py", line 4201>
 180: MAKE_FUNCTION        
 182: STORE_NAME           compare
 184: LOAD_CONST           <code object compare_signal at 0x000002406944BCC0, file "_pydecimal.py", line 4237>
 186: MAKE_FUNCTION        
 188: STORE_NAME           compare_signal
 190: LOAD_CONST           <code object compare_total at 0x000002406944B550, file "_pydecimal.py", line 4272>
 192: MAKE_FUNCTION        
 194: STORE_NAME           compare_total
 196: LOAD_CONST           <code object compare_total_mag at 0x000002406944A010, file "_pydecimal.py", line 4301>
 198: MAKE_FUNCTION        
 200: STORE_NAME           compare_total_mag
 202: LOAD_CONST           <code object copy_abs at 0x000002406944BEE0, file "_pydecimal.py", line 4309>
 204: MAKE_FUNCTION        
 206: STORE_NAME           copy_abs
 208: LOAD_CONST           <code object copy_decimal at 0x00000240693EB730, file "_pydecimal.py", line 4322>
 210: MAKE_FUNCTION        
 212: STORE_NAME           copy_decimal
 214: LOAD_CONST           <code object copy_negate at 0x000002406944B770, file "_pydecimal.py", line 4335>
 216: MAKE_FUNCTION        
 218: STORE_NAME           copy_negate
 220: LOAD_CONST           <code object copy_sign at 0x000002406944B990, file "_pydecimal.py", line 4348>
 222: MAKE_FUNCTION        
 224: STORE_NAME           copy_sign
 226: LOAD_CONST           <code object divide at 0x000002406922D7D0, file "_pydecimal.py", line 4372>
 228: MAKE_FUNCTION        
 230: STORE_NAME           divide
 232: LOAD_CONST           <code object divide_int at 0x000002406922C570, file "_pydecimal.py", line 4409>
 234: MAKE_FUNCTION        
 236: STORE_NAME           divide_int
 238: LOAD_CONST           <code object divmod at 0x000002406922D3E0, file "_pydecimal.py", line 4432>
 240: MAKE_FUNCTION        
 242: STORE_NAME           divmod
 244: LOAD_CONST           <code object exp at 0x0000024069449F00, file "_pydecimal.py", line 4453>
 246: MAKE_FUNCTION        
 248: STORE_NAME           exp
 250: LOAD_CONST           <code object fma at 0x000002406944BDD0, file "_pydecimal.py", line 4477>
 252: MAKE_FUNCTION        
 254: STORE_NAME           fma
 256: LOAD_CONST           <code object is_canonical at 0x00000240693D3340, file "_pydecimal.py", line 4500>
 258: MAKE_FUNCTION        
 260: STORE_NAME           is_canonical
 262: LOAD_CONST           <code object is_finite at 0x000002406944A340, file "_pydecimal.py", line 4513>
 264: MAKE_FUNCTION        
 266: STORE_NAME           is_finite
 268: LOAD_CONST           <code object is_infinite at 0x000002406944B440, file "_pydecimal.py", line 4535>
 270: MAKE_FUNCTION        
 272: STORE_NAME           is_infinite
 274: LOAD_CONST           <code object is_nan at 0x000002406944A230, file "_pydecimal.py", line 4550>
 276: MAKE_FUNCTION        
 278: STORE_NAME           is_nan
 280: LOAD_CONST           <code object is_normal at 0x000002406944A670, file "_pydecimal.py", line 4566>
 282: MAKE_FUNCTION        
 284: STORE_NAME           is_normal
 286: LOAD_CONST           <code object is_qnan at 0x000002406944B110, file "_pydecimal.py", line 4589>
 288: MAKE_FUNCTION        
 290: STORE_NAME           is_qnan
 292: LOAD_CONST           <code object is_signed at 0x000002406944BAA0, file "_pydecimal.py", line 4604>
 294: MAKE_FUNCTION        
 296: STORE_NAME           is_signed
 298: LOAD_CONST           <code object is_snan at 0x000002406944BBB0, file "_pydecimal.py", line 4621>
 300: MAKE_FUNCTION        
 302: STORE_NAME           is_snan
 304: LOAD_CONST           <code object is_subnormal at 0x0000024069CD8030, file "_pydecimal.py", line 4637>
 306: MAKE_FUNCTION        
 308: STORE_NAME           is_subnormal
 310: LOAD_CONST           <code object is_zero at 0x0000024069CD8140, file "_pydecimal.py", line 4659>
 312: MAKE_FUNCTION        
 314: STORE_NAME           is_zero
 316: LOAD_CONST           <code object ln at 0x0000024069CD8250, file "_pydecimal.py", line 4676>
 318: MAKE_FUNCTION        
 320: STORE_NAME           ln
 322: LOAD_CONST           <code object log10 at 0x0000024069CD8360, file "_pydecimal.py", line 4698>
 324: MAKE_FUNCTION        
 326: STORE_NAME           log10
 328: LOAD_CONST           <code object logb at 0x0000024069CD8470, file "_pydecimal.py", line 4726>
 330: MAKE_FUNCTION        
 332: STORE_NAME           logb
 334: LOAD_CONST           <code object logical_and at 0x0000024069CD8580, file "_pydecimal.py", line 4752>
 336: MAKE_FUNCTION        
 338: STORE_NAME           logical_and
 340: LOAD_CONST           <code object logical_invert at 0x0000024069CD8690, file "_pydecimal.py", line 4779>
 342: MAKE_FUNCTION        
 344: STORE_NAME           logical_invert
 346: LOAD_CONST           <code object logical_or at 0x0000024069CD87A0, file "_pydecimal.py", line 4798>
 348: MAKE_FUNCTION        
 350: STORE_NAME           logical_or
 352: LOAD_CONST           <code object logical_xor at 0x0000024069CD88B0, file "_pydecimal.py", line 4825>
 354: MAKE_FUNCTION        
 356: STORE_NAME           logical_xor
 358: LOAD_CONST           <code object max at 0x0000024069CD89C0, file "_pydecimal.py", line 4852>
 360: MAKE_FUNCTION        
 362: STORE_NAME           max
 364: LOAD_CONST           <code object max_mag at 0x0000024069CD8AD0, file "_pydecimal.py", line 4879>
 366: MAKE_FUNCTION        
 368: STORE_NAME           max_mag
 370: LOAD_CONST           <code object min at 0x0000024069CD8BE0, file "_pydecimal.py", line 4896>
 372: MAKE_FUNCTION        
 374: STORE_NAME           min
 376: LOAD_CONST           <code object min_mag at 0x0000024069CD8CF0, file "_pydecimal.py", line 4923>
 378: MAKE_FUNCTION        
 380: STORE_NAME           min_mag
 382: LOAD_CONST           <code object minus at 0x0000024069CD8E00, file "_pydecimal.py", line 4940>
 384: MAKE_FUNCTION        
 386: STORE_NAME           minus
 388: LOAD_CONST           <code object multiply at 0x000002406922CEA0, file "_pydecimal.py", line 4957>
 390: MAKE_FUNCTION        
 392: STORE_NAME           multiply
 394: LOAD_CONST           <code object next_minus at 0x0000024069CD8F10, file "_pydecimal.py", line 4989>
 396: MAKE_FUNCTION        
 398: STORE_NAME           next_minus
 400: LOAD_CONST           <code object next_plus at 0x0000024069CD9020, file "_pydecimal.py", line 5009>
 402: MAKE_FUNCTION        
 404: STORE_NAME           next_plus
 406: LOAD_CONST           <code object next_toward at 0x0000024069CD9130, file "_pydecimal.py", line 5029>
 408: MAKE_FUNCTION        
 410: STORE_NAME           next_toward
 412: LOAD_CONST           <code object normalize at 0x0000024069CD9240, file "_pydecimal.py", line 5064>
 414: MAKE_FUNCTION        
 416: STORE_NAME           normalize
 418: LOAD_CONST           <code object number_class at 0x0000024069CD9350, file "_pydecimal.py", line 5088>
 420: MAKE_FUNCTION        
 422: STORE_NAME           number_class
 424: LOAD_CONST           <code object plus at 0x0000024069CD9460, file "_pydecimal.py", line 5138>
 426: MAKE_FUNCTION        
 428: STORE_NAME           plus
 430: LOAD_CONST           (None,)
 432: LOAD_CONST           <code object power at 0x000002406922CAB0, file "_pydecimal.py", line 5155>
 434: MAKE_FUNCTION        defaults
 436: STORE_NAME           power
 438: LOAD_CONST           <code object quantize at 0x0000024069CD9570, file "_pydecimal.py", line 5235>
 440: MAKE_FUNCTION        
 442: STORE_NAME           quantize
 444: LOAD_CONST           <code object radix at 0x0000024069467130, file "_pydecimal.py", line 5293>
 446: MAKE_FUNCTION        
 448: STORE_NAME           radix
 450: LOAD_CONST           <code object remainder at 0x000002406922C030, file "_pydecimal.py", line 5301>
 452: MAKE_FUNCTION        
 454: STORE_NAME           remainder
 456: LOAD_CONST           <code object remainder_near at 0x0000024069CD9680, file "_pydecimal.py", line 5339>
 458: MAKE_FUNCTION        
 460: STORE_NAME           remainder_near
 462: LOAD_CONST           <code object rotate at 0x0000024069CD9790, file "_pydecimal.py", line 5373>
 464: MAKE_FUNCTION        
 466: STORE_NAME           rotate
 468: LOAD_CONST           <code object same_quantum at 0x0000024069CD98A0, file "_pydecimal.py", line 5402>
 470: MAKE_FUNCTION        
 472: STORE_NAME           same_quantum
 474: LOAD_CONST           <code object scaleb at 0x0000024069CD99B0, file "_pydecimal.py", line 5426>
 476: MAKE_FUNCTION        
 478: STORE_NAME           scaleb
 480: LOAD_CONST           <code object shift at 0x0000024069CD9AC0, file "_pydecimal.py", line 5445>
 482: MAKE_FUNCTION        
 484: STORE_NAME           shift
 486: LOAD_CONST           <code object sqrt at 0x0000024069CD9BD0, file "_pydecimal.py", line 5475>
 488: MAKE_FUNCTION        
 490: STORE_NAME           sqrt
 492: LOAD_CONST           <code object subtract at 0x000002406922DBC0, file "_pydecimal.py", line 5507>
 494: MAKE_FUNCTION        
 496: STORE_NAME           subtract
 498: LOAD_CONST           <code object to_eng_string at 0x0000024069CD9CE0, file "_pydecimal.py", line 5530>
 500: MAKE_FUNCTION        
 502: STORE_NAME           to_eng_string
 504: LOAD_CONST           <code object to_sci_string at 0x0000024069CD9DF0, file "_pydecimal.py", line 5558>
 506: MAKE_FUNCTION        
 508: STORE_NAME           to_sci_string
 510: LOAD_CONST           <code object to_integral_exact at 0x0000024069CD9F00, file "_pydecimal.py", line 5566>
 512: MAKE_FUNCTION        
 514: STORE_NAME           to_integral_exact
 516: LOAD_CONST           <code object to_integral_value at 0x0000024069CDA010, file "_pydecimal.py", line 5596>
 518: MAKE_FUNCTION        
 520: STORE_NAME           to_integral_value
 522: LOAD_NAME            to_integral_value
 524: STORE_NAME           to_integral
 526: LOAD_CONST           None
 528: RETURN_VALUE         
