# Disassembly for _pydecimal.Context.exp
# From module file: _pydecimal

## co_consts:
("Returns e ** a.\n\n        >>> c = ExtendedContext.copy()\n        >>> c.Emin = -999\n        >>> c.Emax = 999\n        >>> c.exp(Decimal('-Infinity'))\n        Decimal('0')\n        >>> c.exp(Decimal('-1'))\n        Decimal('0.367879441')\n        >>> c.exp(Decimal('0'))\n        Decimal('1')\n        >>> c.exp(Decimal('1'))\n        Decimal('2.71828183')\n        >>> c.exp(Decimal('0.693147181'))\n        Decimal('2.00000000')\n        >>> c.exp(Decimal('+Infinity'))\n        Decimal('Infinity')\n        >>> c.exp(10)\n        Decimal('22026.4658')\n        ", True, ('raiseit',), ('context',))

## co_names:
('_convert_other', 'exp')

## bytecode:

   0: RESUME               
   2: LOAD_GLOBAL          NULL + _convert_other
  14: LOAD_FAST            a
  16: LOAD_CONST           True
  18: KW_NAMES             
  20: PRECALL              
  24: CALL                 
  34: STORE_FAST           a
  36: LOAD_FAST            a
  38: LOAD_METHOD          exp
  60: LOAD_FAST            self
  62: KW_NAMES             
  64: PRECALL              
  68: CALL                 
  78: RETURN_VALUE         
