# Disassembly for _pydecimal.Decimal.__rdivmod__
# From module file: _pydecimal

## co_consts:
('Swaps self/other and returns __divmod__.', ('context',))

## co_names:
('_convert_other', 'NotImplemented', '__divmod__')

## bytecode:

   0: RESUME               
   2: LOAD_GLOBAL          NULL + _convert_other
  14: LOAD_FAST            other
  16: PRECALL              
  20: CALL                 
  30: STORE_FAST           other
  32: LOAD_FAST            other
  34: LOAD_GLOBAL          NotImplemented
  46: IS_OP                
  48: POP_JUMP_FORWARD_IF_FALSE to 54
  50: LOAD_FAST            other
  52: RETURN_VALUE         
  54: LOAD_FAST            other
  56: LOAD_METHOD          __divmod__
  78: LOAD_FAST            self
  80: LOAD_FAST            context
  82: KW_NAMES             
  84: PRECALL              
  88: CALL                 
  98: RETURN_VALUE         
