# Disassembly for _pydecimal.Context.next_toward
# From module file: _pydecimal

## co_consts:
("Returns the number closest to a, in direction towards b.\n\n        The result is the closest representable number from the first\n        operand (but not the first operand) that is in the direction\n        towards the second operand, unless the operands have the same\n        value.\n\n        >>> c = ExtendedContext.copy()\n        >>> c.Emin = -999\n        >>> c.Emax = 999\n        >>> c.next_toward(Decimal('1'), Decimal('2'))\n        Decimal('1.00000001')\n        >>> c.next_toward(Decimal('-1E-1007'), Decimal('1'))\n        Decimal('-0E-1007')\n        >>> c.next_toward(Decimal('-1.00000003'), Decimal('0'))\n        Decimal('-1.00000002')\n        >>> c.next_toward(Decimal('1'), Decimal('0'))\n        Decimal('0.999999999')\n        >>> c.next_toward(Decimal('1E-1007'), Decimal('-100'))\n        Decimal('0E-1007')\n        >>> c.next_toward(Decimal('-1.00000003'), Decimal('-10'))\n        Decimal('-1.00000004')\n        >>> c.next_toward(Decimal('0.00'), Decimal('-0.0000'))\n        Decimal('-0.00')\n        >>> c.next_toward(0, 1)\n        Decimal('1E-1007')\n        >>> c.next_toward(Decimal(0), 1)\n        Decimal('1E-1007')\n        >>> c.next_toward(0, Decimal(1))\n        Decimal('1E-1007')\n        ", True, ('raiseit',), ('context',))

## co_names:
('_convert_other', 'next_toward')

## bytecode:

   0: RESUME               
   2: LOAD_GLOBAL          NULL + _convert_other
  14: LOAD_FAST            a
  16: LOAD_CONST           True
  18: KW_NAMES             
  20: PRECALL              
  24: CALL                 
  34: STORE_FAST           a
  36: LOAD_FAST            a
  38: LOAD_METHOD          next_toward
  60: LOAD_FAST            b
  62: LOAD_FAST            self
  64: KW_NAMES             
  66: PRECALL              
  70: CALL                 
  80: RETURN_VALUE         
