# Disassembly for _pydecimal.Rounded
# From module file: _pydecimal

## co_consts:
('Rounded', 'Number got rounded (not  necessarily changed during rounding).\n\n    This occurs and signals rounded whenever the result of an operation is\n    rounded (that is, some zero or non-zero digits were discarded from the\n    coefficient), or if an overflow or underflow condition occurs.  The\n    result in all cases is unchanged.\n\n    The rounded signal may be tested (or trapped) to determine if a given\n    operation (or sequence of operations) caused a loss of precision.\n    ', None)

## co_names:
('__name__', '__module__', '__qualname__', '__doc__')

## bytecode:

   0: RESUME               
   2: LOAD_NAME            __name__
   4: STORE_NAME           __module__
   6: LOAD_CONST           'Rounded'
   8: STORE_NAME           __qualname__
  10: LOAD_CONST           'Number got rounded (not  necessarily changed during rounding).\n\n    This occurs and signals rounded whenever the result of an operation is\n    rounded (that is, some zero or non-zero digits were discarded from the\n    coefficient), or if an overflow or underflow condition occurs.  The\n    result in all cases is unchanged.\n\n    The rounded signal may be tested (or trapped) to determine if a given\n    operation (or sequence of operations) caused a loss of precision.\n    '
  12: STORE_NAME           __doc__
  14: LOAD_CONST           None
  16: RETURN_VALUE         
