# Disassembly for _pydecimal.Overflow.handle
# From module file: _pydecimal

## co_consts:
(None, 0, '9', 1)

## co_names:
('rounding', 'ROUND_HALF_UP', 'ROUND_HALF_EVEN', 'ROUND_HALF_DOWN', 'ROUND_UP', '_SignedInfinity', 'ROUND_CEILING', '_dec_from_triple', 'prec', 'Emax', 'ROUND_FLOOR')

## bytecode:

   0: RESUME               
   2: LOAD_FAST            context
   4: LOAD_ATTR            rounding
  14: LOAD_GLOBAL          ROUND_HALF_UP
  26: LOAD_GLOBAL          ROUND_HALF_EVEN
  38: LOAD_GLOBAL          ROUND_HALF_DOWN
  50: LOAD_GLOBAL          ROUND_UP
  62: BUILD_TUPLE          
  64: CONTAINS_OP          
  66: POP_JUMP_FORWARD_IF_FALSE to 94
  68: LOAD_GLOBAL          _SignedInfinity
  80: LOAD_FAST            sign
  82: BINARY_SUBSCR        
  92: RETURN_VALUE         
  94: LOAD_FAST            sign
  96: LOAD_CONST           0
  98: COMPARE_OP           ==
 104: POP_JUMP_FORWARD_IF_FALSE to 246
 106: LOAD_FAST            context
 108: LOAD_ATTR            rounding
 118: LOAD_GLOBAL          ROUND_CEILING
 130: COMPARE_OP           ==
 136: POP_JUMP_FORWARD_IF_FALSE to 164
 138: LOAD_GLOBAL          _SignedInfinity
 150: LOAD_FAST            sign
 152: BINARY_SUBSCR        
 162: RETURN_VALUE         
 164: LOAD_GLOBAL          NULL + _dec_from_triple
 176: LOAD_FAST            sign
 178: LOAD_CONST           '9'
 180: LOAD_FAST            context
 182: LOAD_ATTR            prec
 192: BINARY_OP            *
 196: LOAD_FAST            context
 198: LOAD_ATTR            Emax
 208: LOAD_FAST            context
 210: LOAD_ATTR            prec
 220: BINARY_OP            -
 224: LOAD_CONST           1
 226: BINARY_OP            +
 230: PRECALL              
 234: CALL                 
 244: RETURN_VALUE         
 246: LOAD_FAST            sign
 248: LOAD_CONST           1
 250: COMPARE_OP           ==
 256: POP_JUMP_FORWARD_IF_FALSE to 398
 258: LOAD_FAST            context
 260: LOAD_ATTR            rounding
 270: LOAD_GLOBAL          ROUND_FLOOR
 282: COMPARE_OP           ==
 288: POP_JUMP_FORWARD_IF_FALSE to 316
 290: LOAD_GLOBAL          _SignedInfinity
 302: LOAD_FAST            sign
 304: BINARY_SUBSCR        
 314: RETURN_VALUE         
 316: LOAD_GLOBAL          NULL + _dec_from_triple
 328: LOAD_FAST            sign
 330: LOAD_CONST           '9'
 332: LOAD_FAST            context
 334: LOAD_ATTR            prec
 344: BINARY_OP            *
 348: LOAD_FAST            context
 350: LOAD_ATTR            Emax
 360: LOAD_FAST            context
 362: LOAD_ATTR            prec
 372: BINARY_OP            -
 376: LOAD_CONST           1
 378: BINARY_OP            +
 382: PRECALL              
 386: CALL                 
 396: RETURN_VALUE         
 398: LOAD_CONST           None
 400: RETURN_VALUE         
