# Disassembly for _pydecimal.Decimal.quantize
# From module file: _pydecimal

## co_consts:
('Quantize self so its exponent is the same as that of exp.\n\n        Similar to self._rescale(exp._exp) but with error checking.\n        ', True, ('raiseit',), None, 'quantize with one INF', 'target exponent out of bounds in quantize', '0', 'exponent of quantize result too large for current context', 1, 'quantize result has too many digits for current context')

## co_names:
('_convert_other', 'getcontext', 'rounding', '_is_special', '_check_nans', '_isinfinity', 'Decimal', '_raise_error', 'InvalidOperation', 'Etiny', '_exp', 'Emax', '_dec_from_triple', '_sign', '_fix', 'adjusted', 'prec', '_rescale', 'len', '_int', 'Emin', 'Subnormal', 'Inexact', 'Rounded')

## bytecode:

   0: RESUME               
   2: LOAD_GLOBAL          NULL + _convert_other
  14: LOAD_FAST            exp
  16: LOAD_CONST           True
  18: KW_NAMES             
  20: PRECALL              
  24: CALL                 
  34: STORE_FAST           exp
  36: LOAD_FAST            context
  38: POP_JUMP_FORWARD_IF_NOT_NONE to 68
  40: LOAD_GLOBAL          NULL + getcontext
  52: PRECALL              
  56: CALL                 
  66: STORE_FAST           context
  68: LOAD_FAST            rounding
  70: POP_JUMP_FORWARD_IF_NOT_NONE to 86
  72: LOAD_FAST            context
  74: LOAD_ATTR            rounding
  84: STORE_FAST           rounding
  86: LOAD_FAST            self
  88: LOAD_ATTR            _is_special
  98: POP_JUMP_FORWARD_IF_TRUE to 114
 100: LOAD_FAST            exp
 102: LOAD_ATTR            _is_special
 112: POP_JUMP_FORWARD_IF_FALSE to 410
 114: LOAD_FAST            self
 116: LOAD_METHOD          _check_nans
 138: LOAD_FAST            exp
 140: LOAD_FAST            context
 142: PRECALL              
 146: CALL                 
 156: STORE_FAST           ans
 158: LOAD_FAST            ans
 160: POP_JUMP_FORWARD_IF_FALSE to 166
 162: LOAD_FAST            ans
 164: RETURN_VALUE         
 166: LOAD_FAST            exp
 168: LOAD_METHOD          _isinfinity
 190: PRECALL              
 194: CALL                 
 204: POP_JUMP_FORWARD_IF_TRUE to 246
 206: LOAD_FAST            self
 208: LOAD_METHOD          _isinfinity
 230: PRECALL              
 234: CALL                 
 244: POP_JUMP_FORWARD_IF_FALSE to 410
 246: LOAD_FAST            exp
 248: LOAD_METHOD          _isinfinity
 270: PRECALL              
 274: CALL                 
 284: POP_JUMP_FORWARD_IF_FALSE to 356
 286: LOAD_FAST            self
 288: LOAD_METHOD          _isinfinity
 310: PRECALL              
 314: CALL                 
 324: POP_JUMP_FORWARD_IF_FALSE to 356
 326: LOAD_GLOBAL          NULL + Decimal
 338: LOAD_FAST            self
 340: PRECALL              
 344: CALL                 
 354: RETURN_VALUE         
 356: LOAD_FAST            context
 358: LOAD_METHOD          _raise_error
 380: LOAD_GLOBAL          InvalidOperation
 392: LOAD_CONST           'quantize with one INF'
 394: PRECALL              
 398: CALL                 
 408: RETURN_VALUE         
 410: LOAD_FAST            context
 412: LOAD_METHOD          Etiny
 434: PRECALL              
 438: CALL                 
 448: LOAD_FAST            exp
 450: LOAD_ATTR            _exp
 460: SWAP                 
 462: COPY                 
 464: COMPARE_OP           <=
 470: POP_JUMP_FORWARD_IF_FALSE to 494
 472: LOAD_FAST            context
 474: LOAD_ATTR            Emax
 484: COMPARE_OP           <=
 490: POP_JUMP_FORWARD_IF_TRUE to 550
 492: JUMP_FORWARD         to 496
 494: POP_TOP              
 496: LOAD_FAST            context
 498: LOAD_METHOD          _raise_error
 520: LOAD_GLOBAL          InvalidOperation
 532: LOAD_CONST           'target exponent out of bounds in quantize'
 534: PRECALL              
 538: CALL                 
 548: RETURN_VALUE         
 550: LOAD_FAST            self
 552: POP_JUMP_FORWARD_IF_TRUE to 650
 554: LOAD_GLOBAL          NULL + _dec_from_triple
 566: LOAD_FAST            self
 568: LOAD_ATTR            _sign
 578: LOAD_CONST           '0'
 580: LOAD_FAST            exp
 582: LOAD_ATTR            _exp
 592: PRECALL              
 596: CALL                 
 606: STORE_FAST           ans
 608: LOAD_FAST            ans
 610: LOAD_METHOD          _fix
 632: LOAD_FAST            context
 634: PRECALL              
 638: CALL                 
 648: RETURN_VALUE         
 650: LOAD_FAST            self
 652: LOAD_METHOD          adjusted
 674: PRECALL              
 678: CALL                 
 688: STORE_FAST           self_adjusted
 690: LOAD_FAST            self_adjusted
 692: LOAD_FAST            context
 694: LOAD_ATTR            Emax
 704: COMPARE_OP           >
 710: POP_JUMP_FORWARD_IF_FALSE to 766
 712: LOAD_FAST            context
 714: LOAD_METHOD          _raise_error
 736: LOAD_GLOBAL          InvalidOperation
 748: LOAD_CONST           'exponent of quantize result too large for current context'
 750: PRECALL              
 754: CALL                 
 764: RETURN_VALUE         
 766: LOAD_FAST            self_adjusted
 768: LOAD_FAST            exp
 770: LOAD_ATTR            _exp
 780: BINARY_OP            -
 784: LOAD_CONST           1
 786: BINARY_OP            +
 790: LOAD_FAST            context
 792: LOAD_ATTR            prec
 802: COMPARE_OP           >
 808: POP_JUMP_FORWARD_IF_FALSE to 864
 810: LOAD_FAST            context
 812: LOAD_METHOD          _raise_error
 834: LOAD_GLOBAL          InvalidOperation
 846: LOAD_CONST           'quantize result has too many digits for current context'
 848: PRECALL              
 852: CALL                 
 862: RETURN_VALUE         
 864: LOAD_FAST            self
 866: LOAD_METHOD          _rescale
 888: LOAD_FAST            exp
 890: LOAD_ATTR            _exp
 900: LOAD_FAST            rounding
 902: PRECALL              
 906: CALL                 
 916: STORE_FAST           ans
 918: LOAD_FAST            ans
 920: LOAD_METHOD          adjusted
 942: PRECALL              
 946: CALL                 
 956: LOAD_FAST            context
 958: LOAD_ATTR            Emax
 968: COMPARE_OP           >
 974: POP_JUMP_FORWARD_IF_FALSE to 1030
 976: LOAD_FAST            context
 978: LOAD_METHOD          _raise_error
1000: LOAD_GLOBAL          InvalidOperation
1012: LOAD_CONST           'exponent of quantize result too large for current context'
1014: PRECALL              
1018: CALL                 
1028: RETURN_VALUE         
1030: LOAD_GLOBAL          NULL + len
1042: LOAD_FAST            ans
1044: LOAD_ATTR            _int
1054: PRECALL              
1058: CALL                 
1068: LOAD_FAST            context
1070: LOAD_ATTR            prec
1080: COMPARE_OP           >
1086: POP_JUMP_FORWARD_IF_FALSE to 1142
1088: LOAD_FAST            context
1090: LOAD_METHOD          _raise_error
1112: LOAD_GLOBAL          InvalidOperation
1124: LOAD_CONST           'quantize result has too many digits for current context'
1126: PRECALL              
1130: CALL                 
1140: RETURN_VALUE         
1142: LOAD_FAST            ans
1144: POP_JUMP_FORWARD_IF_FALSE to 1256
1146: LOAD_FAST            ans
1148: LOAD_METHOD          adjusted
1170: PRECALL              
1174: CALL                 
1184: LOAD_FAST            context
1186: LOAD_ATTR            Emin
1196: COMPARE_OP           <
1202: POP_JUMP_FORWARD_IF_FALSE to 1256
1204: LOAD_FAST            context
1206: LOAD_METHOD          _raise_error
1228: LOAD_GLOBAL          Subnormal
1240: PRECALL              
1244: CALL                 
1254: POP_TOP              
1256: LOAD_FAST            ans
1258: LOAD_ATTR            _exp
1268: LOAD_FAST            self
1270: LOAD_ATTR            _exp
1280: COMPARE_OP           >
1286: POP_JUMP_FORWARD_IF_FALSE to 1404
1288: LOAD_FAST            ans
1290: LOAD_FAST            self
1292: COMPARE_OP           !=
1298: POP_JUMP_FORWARD_IF_FALSE to 1352
1300: LOAD_FAST            context
1302: LOAD_METHOD          _raise_error
1324: LOAD_GLOBAL          Inexact
1336: PRECALL              
1340: CALL                 
1350: POP_TOP              
1352: LOAD_FAST            context
1354: LOAD_METHOD          _raise_error
1376: LOAD_GLOBAL          Rounded
1388: PRECALL              
1392: CALL                 
1402: POP_TOP              
1404: LOAD_FAST            ans
1406: LOAD_METHOD          _fix
1428: LOAD_FAST            context
1430: PRECALL              
1434: CALL                 
1444: STORE_FAST           ans
1446: LOAD_FAST            ans
1448: RETURN_VALUE         
