# Disassembly for _pydecimal.InvalidOperation
# From module file: _pydecimal

## co_consts:
('InvalidOperation', 'An invalid operation was performed.\n\n    Various bad things cause this:\n\n    Something creates a signaling NaN\n    -INF + INF\n    0 * (+-)INF\n    (+-)INF / (+-)INF\n    x % 0\n    (+-)INF % x\n    x._rescale( non-integer )\n    sqrt(-x) , x > 0\n    0 ** 0\n    x ** (non-integer)\n    x ** (+-)INF\n    An operand is invalid\n\n    The result of the operation after these is a quiet positive NaN,\n    except when the cause is a signaling NaN, in which case the result is\n    also a quiet NaN, but with the original sign, and an optional\n    diagnostic information.\n    ', <code object handle at 0x00000240691F13E0, file "_pydecimal.py", line 250>, None)

## co_names:
('__name__', '__module__', '__qualname__', '__doc__', 'handle')

## bytecode:

   0: RESUME               
   2: LOAD_NAME            __name__
   4: STORE_NAME           __module__
   6: LOAD_CONST           'InvalidOperation'
   8: STORE_NAME           __qualname__
  10: LOAD_CONST           'An invalid operation was performed.\n\n    Various bad things cause this:\n\n    Something creates a signaling NaN\n    -INF + INF\n    0 * (+-)INF\n    (+-)INF / (+-)INF\n    x % 0\n    (+-)INF % x\n    x._rescale( non-integer )\n    sqrt(-x) , x > 0\n    0 ** 0\n    x ** (non-integer)\n    x ** (+-)INF\n    An operand is invalid\n\n    The result of the operation after these is a quiet positive NaN,\n    except when the cause is a signaling NaN, in which case the result is\n    also a quiet NaN, but with the original sign, and an optional\n    diagnostic information.\n    '
  12: STORE_NAME           __doc__
  14: LOAD_CONST           <code object handle at 0x00000240691F13E0, file "_pydecimal.py", line 250>
  16: MAKE_FUNCTION        
  18: STORE_NAME           handle
  20: LOAD_CONST           None
  22: RETURN_VALUE         
