# Disassembly for _pydecimal.Context._set_integer_check
# From module file: _pydecimal

## co_consts:
(None, '%s must be an integer', '-inf', '%s must be in [%s, %d]. got: %s', 'inf', '%s must be in [%d, %s]. got: %s', '%s must be in [%d, %d]. got %s')

## co_names:
('isinstance', 'int', 'TypeError', 'ValueError', 'object', '__setattr__')

## bytecode:

   0: RESUME               
   2: LOAD_GLOBAL          NULL + isinstance
  14: LOAD_FAST            value
  16: LOAD_GLOBAL          int
  28: PRECALL              
  32: CALL                 
  42: POP_JUMP_FORWARD_IF_TRUE to 80
  44: LOAD_GLOBAL          NULL + TypeError
  56: LOAD_CONST           '%s must be an integer'
  58: LOAD_FAST            name
  60: BINARY_OP            %
  64: PRECALL              
  68: CALL                 
  78: RAISE_VARARGS        
  80: LOAD_FAST            vmin
  82: LOAD_CONST           '-inf'
  84: COMPARE_OP           ==
  90: POP_JUMP_FORWARD_IF_FALSE to 150
  92: LOAD_FAST            value
  94: LOAD_FAST            vmax
  96: COMPARE_OP           >
 102: POP_JUMP_FORWARD_IF_FALSE to 148
 104: LOAD_GLOBAL          NULL + ValueError
 116: LOAD_CONST           '%s must be in [%s, %d]. got: %s'
 118: LOAD_FAST            name
 120: LOAD_FAST            vmin
 122: LOAD_FAST            vmax
 124: LOAD_FAST            value
 126: BUILD_TUPLE          
 128: BINARY_OP            %
 132: PRECALL              
 136: CALL                 
 146: RAISE_VARARGS        
 148: JUMP_FORWARD         to 288
 150: LOAD_FAST            vmax
 152: LOAD_CONST           'inf'
 154: COMPARE_OP           ==
 160: POP_JUMP_FORWARD_IF_FALSE to 220
 162: LOAD_FAST            value
 164: LOAD_FAST            vmin
 166: COMPARE_OP           <
 172: POP_JUMP_FORWARD_IF_FALSE to 218
 174: LOAD_GLOBAL          NULL + ValueError
 186: LOAD_CONST           '%s must be in [%d, %s]. got: %s'
 188: LOAD_FAST            name
 190: LOAD_FAST            vmin
 192: LOAD_FAST            vmax
 194: LOAD_FAST            value
 196: BUILD_TUPLE          
 198: BINARY_OP            %
 202: PRECALL              
 206: CALL                 
 216: RAISE_VARARGS        
 218: JUMP_FORWARD         to 288
 220: LOAD_FAST            value
 222: LOAD_FAST            vmin
 224: COMPARE_OP           <
 230: POP_JUMP_FORWARD_IF_TRUE to 244
 232: LOAD_FAST            value
 234: LOAD_FAST            vmax
 236: COMPARE_OP           >
 242: POP_JUMP_FORWARD_IF_FALSE to 288
 244: LOAD_GLOBAL          NULL + ValueError
 256: LOAD_CONST           '%s must be in [%d, %d]. got %s'
 258: LOAD_FAST            name
 260: LOAD_FAST            vmin
 262: LOAD_FAST            vmax
 264: LOAD_FAST            value
 266: BUILD_TUPLE          
 268: BINARY_OP            %
 272: PRECALL              
 276: CALL                 
 286: RAISE_VARARGS        
 288: LOAD_GLOBAL          object
 300: LOAD_METHOD          __setattr__
 322: LOAD_FAST            self
 324: LOAD_FAST            name
 326: LOAD_FAST            value
 328: PRECALL              
 332: CALL                 
 342: RETURN_VALUE         
