# Disassembly for _pydecimal.Decimal.compare_signal
# From module file: _pydecimal

## co_consts:
("Compares self to the other operand numerically.\n\n        It's pretty much like compare(), but all NaNs signal, with signaling\n        NaNs taking precedence over quiet NaNs.\n        ", True, ('raiseit',), ('context',))

## co_names:
('_convert_other', '_compare_check_nans', 'compare')

## bytecode:

   0: RESUME               
   2: LOAD_GLOBAL          NULL + _convert_other
  14: LOAD_FAST            other
  16: LOAD_CONST           True
  18: KW_NAMES             
  20: PRECALL              
  24: CALL                 
  34: STORE_FAST           other
  36: LOAD_FAST            self
  38: LOAD_METHOD          _compare_check_nans
  60: LOAD_FAST            other
  62: LOAD_FAST            context
  64: PRECALL              
  68: CALL                 
  78: STORE_FAST           ans
  80: LOAD_FAST            ans
  82: POP_JUMP_FORWARD_IF_FALSE to 88
  84: LOAD_FAST            ans
  86: RETURN_VALUE         
  88: LOAD_FAST            self
  90: LOAD_METHOD          compare
 112: LOAD_FAST            other
 114: LOAD_FAST            context
 116: KW_NAMES             
 118: PRECALL              
 122: CALL                 
 132: RETURN_VALUE         
