# Disassembly for _pydecimal.Decimal.__floor__
# From module file: _pydecimal

## co_consts:
('Return the floor of self, as an integer.\n\n        For a finite Decimal instance self, return the greatest\n        integer n such that n <= self.  If self is infinite or a NaN\n        then a Python exception is raised.\n\n        ', 'cannot round a NaN', 'cannot round an infinity', 0)

## co_names:
('_is_special', 'is_nan', 'ValueError', 'OverflowError', 'int', '_rescale', 'ROUND_FLOOR')

## bytecode:

   0: RESUME               
   2: LOAD_FAST            self
   4: LOAD_ATTR            _is_special
  14: POP_JUMP_FORWARD_IF_FALSE to 116
  16: LOAD_FAST            self
  18: LOAD_METHOD          is_nan
  40: PRECALL              
  44: CALL                 
  54: POP_JUMP_FORWARD_IF_FALSE to 86
  56: LOAD_GLOBAL          NULL + ValueError
  68: LOAD_CONST           'cannot round a NaN'
  70: PRECALL              
  74: CALL                 
  84: RAISE_VARARGS        
  86: LOAD_GLOBAL          NULL + OverflowError
  98: LOAD_CONST           'cannot round an infinity'
 100: PRECALL              
 104: CALL                 
 114: RAISE_VARARGS        
 116: LOAD_GLOBAL          NULL + int
 128: LOAD_FAST            self
 130: LOAD_METHOD          _rescale
 152: LOAD_CONST           0
 154: LOAD_GLOBAL          ROUND_FLOOR
 166: PRECALL              
 170: CALL                 
 180: PRECALL              
 184: CALL                 
 194: RETURN_VALUE         
