# Disassembly for _pydecimal
# From module file: _pydecimal

## co_consts:
('\nThis is an implementation of decimal floating point arithmetic based on\nthe General Decimal Arithmetic Specification:\n\n    http://speleotrove.com/decimal/decarith.html\n\nand IEEE standard 854-1987:\n\n    http://en.wikipedia.org/wiki/IEEE_854-1987\n\nDecimal floating point has finite precision with arbitrarily large bounds.\n\nThe purpose of this module is to support arithmetic using familiar\n"schoolhouse" rules and to avoid some of the tricky representation\nissues associated with binary floating point.  The package is especially\nuseful for financial applications or for contexts where users have\nexpectations that are at odds with binary floating point (for instance,\nin binary floating point, 1.00 % 0.1 gives 0.09999999999999995 instead\nof 0.0; Decimal(\'1.00\') % Decimal(\'0.1\') returns the expected\nDecimal(\'0.00\')).\n\nHere are some examples of using the decimal module:\n\n>>> from decimal import *\n>>> setcontext(ExtendedContext)\n>>> Decimal(0)\nDecimal(\'0\')\n>>> Decimal(\'1\')\nDecimal(\'1\')\n>>> Decimal(\'-.0123\')\nDecimal(\'-0.0123\')\n>>> Decimal(123456)\nDecimal(\'123456\')\n>>> Decimal(\'123.45e12345678\')\nDecimal(\'1.2345E+12345680\')\n>>> Decimal(\'1.33\') + Decimal(\'1.27\')\nDecimal(\'2.60\')\n>>> Decimal(\'12.34\') + Decimal(\'3.87\') - Decimal(\'18.41\')\nDecimal(\'-2.20\')\n>>> dig = Decimal(1)\n>>> print(dig / Decimal(3))\n0.333333333\n>>> getcontext().prec = 18\n>>> print(dig / Decimal(3))\n0.333333333333333333\n>>> print(dig.sqrt())\n1\n>>> print(Decimal(3).sqrt())\n1.73205080756887729\n>>> print(Decimal(3) ** 123)\n4.85192780976896427E+58\n>>> inf = Decimal(1) / Decimal(0)\n>>> print(inf)\nInfinity\n>>> neginf = Decimal(-1) / Decimal(0)\n>>> print(neginf)\n-Infinity\n>>> print(neginf + inf)\nNaN\n>>> print(neginf * inf)\n-Infinity\n>>> print(dig / 0)\nInfinity\n>>> getcontext().traps[DivisionByZero] = 1\n>>> print(dig / 0)\nTraceback (most recent call last):\n  ...\n  ...\n  ...\ndecimal.DivisionByZero: x / 0\n>>> c = Context()\n>>> c.traps[InvalidOperation] = 0\n>>> print(c.flags[InvalidOperation])\n0\n>>> c.divide(Decimal(0), Decimal(0))\nDecimal(\'NaN\')\n>>> c.traps[InvalidOperation] = 1\n>>> print(c.flags[InvalidOperation])\n1\n>>> c.flags[InvalidOperation] = 0\n>>> print(c.flags[InvalidOperation])\n0\n>>> print(c.divide(Decimal(0), Decimal(0)))\nTraceback (most recent call last):\n  ...\n  ...\n  ...\ndecimal.InvalidOperation: 0 / 0\n>>> print(c.flags[InvalidOperation])\n1\n>>> c.flags[InvalidOperation] = 0\n>>> c.traps[InvalidOperation] = 0\n>>> print(c.divide(Decimal(0), Decimal(0)))\nNaN\n>>> print(c.flags[InvalidOperation])\n1\n>>>\n', ('Decimal', 'Context', 'DecimalTuple', 'DefaultContext', 'BasicContext', 'ExtendedContext', 'DecimalException', 'Clamped', 'InvalidOperation', 'DivisionByZero', 'Inexact', 'Rounded', 'Subnormal', 'Overflow', 'Underflow', 'FloatOperation', 'DivisionImpossible', 'InvalidContext', 'ConversionSyntax', 'DivisionUndefined', 'ROUND_DOWN', 'ROUND_HALF_UP', 'ROUND_HALF_EVEN', 'ROUND_CEILING', 'ROUND_FLOOR', 'ROUND_UP', 'ROUND_HALF_DOWN', 'ROUND_05UP', 'setcontext', 'getcontext', 'localcontext', 'MAX_PREC', 'MAX_EMAX', 'MIN_EMIN', 'MIN_ETINY', 'HAVE_THREADS', 'HAVE_CONTEXTVAR'), 'decimal', '1.70', '2.4.2', 0, None, ('namedtuple',), 'DecimalTuple', 'sign digits exponent', <code object <lambda> at 0x000002406943B270, file "_pydecimal.py", line 164>, 'ROUND_DOWN', 'ROUND_HALF_UP', 'ROUND_HALF_EVEN', 'ROUND_CEILING', 'ROUND_FLOOR', 'ROUND_UP', 'ROUND_HALF_DOWN', 'ROUND_05UP', True, 9223372036854775807, 999999999999999999, -999999999999999999, 425000000, -425000000, 1, <code object DecimalException at 0x0000024069496DB0, file "_pydecimal.py", line 192>, 'DecimalException', <code object Clamped at 0x0000024069496F50, file "_pydecimal.py", line 215>, 'Clamped', <code object InvalidOperation at 0x0000024069494440, file "_pydecimal.py", line 227>, 'InvalidOperation', <code object ConversionSyntax at 0x0000024069496800, file "_pydecimal.py", line 256>, 'ConversionSyntax', <code object DivisionByZero at 0x0000024069494370, file "_pydecimal.py", line 266>, 'DivisionByZero', <code object DivisionImpossible at 0x0000024069494ED0, file "_pydecimal.py", line 282>, 'DivisionImpossible', <code object DivisionUndefined at 0x0000024069497360, file "_pydecimal.py", line 293>, 'DivisionUndefined', <code object Inexact at 0x0000024069497430, file "_pydecimal.py", line 304>, 'Inexact', <code object InvalidContext at 0x00000240694960B0, file "_pydecimal.py", line 316>, 'InvalidContext', <code object Rounded at 0x0000024069496590, file "_pydecimal.py", line 330>, 'Rounded', <code object Subnormal at 0x0000024069497840, file "_pydecimal.py", line 342>, 'Subnormal', <code object Overflow at 0x0000024069496CE0, file "_pydecimal.py", line 353>, 'Overflow', <code object Underflow at 0x0000024069494920, file "_pydecimal.py", line 391>, 'Underflow', <code object FloatOperation at 0x0000024069495D70, file "_pydecimal.py", line 406>, 'FloatOperation', 'decimal_context', ('prec', 'Emin', 'Emax', 'capitals', 'clamp', 'rounding', 'flags', 'traps'), <code object getcontext at 0x000002406921FB20, file "_pydecimal.py", line 448>, <code object setcontext at 0x000002406921F9B0, file "_pydecimal.py", line 462>, <code object localcontext at 0x00000240691F60B0, file "_pydecimal.py", line 471>, <code object Decimal at 0x0000024068E134B0, file "_pydecimal.py", line 523>, 'Decimal', False, <code object _dec_from_triple at 0x00000240693AA470, file "_pydecimal.py", line 3844>, <code object _ContextManager at 0x0000024069467AD0, file "_pydecimal.py", line 3868>, '_ContextManager', <code object Context at 0x0000024068C0AF60, file "_pydecimal.py", line 3883>, 'Context', <code object _WorkRep at 0x0000024069465ED0, file "_pydecimal.py", line 5628>, '_WorkRep', <code object _normalize at 0x0000024068E7E700, file "_pydecimal.py", line 5654>, <code object _decimal_lshift_exact at 0x0000024069CF41E0, file "_pydecimal.py", line 5686>, <code object _sqrt_nearest at 0x00000240693D29C0, file "_pydecimal.py", line 5707>, <code object _rshift_nearest at 0x00000240693EAD30, file "_pydecimal.py", line 5722>, <code object _div_nearest at 0x0000024069CDA230, file "_pydecimal.py", line 5730>, 8, <code object _ilog at 0x0000024068C27750, file "_pydecimal.py", line 5738>, <code object _dlog10 at 0x0000024068D6E320, file "_pydecimal.py", line 5786>, <code object _dlog at 0x0000024068D31640, file "_pydecimal.py", line 5820>, <code object _Log10Memoize at 0x0000024069466B10, file "_pydecimal.py", line 5864>, '_Log10Memoize', <code object _iexp at 0x0000024068D6C2C0, file "_pydecimal.py", line 5901>, <code object _dexp at 0x000002406958EAA0, file "_pydecimal.py", line 5938>, <code object _dpower at 0x0000024068E5DD90, file "_pydecimal.py", line 5974>, 100, 70, 53, 40, 31, 23, 16, 10, 5, ('1', '2', '3', '4', '5', '6', '7', '8', '9'), <code object _log10_lb at 0x000002406922DE60, file "_pydecimal.py", line 6016>, <code object _convert_other at 0x00000240691DB2F0, file "_pydecimal.py", line 6027>, <code object _convert_for_comparison at 0x0000024068BFD370, file "_pydecimal.py", line 6046>, 28, 999999, -999999, ('prec', 'rounding', 'traps', 'flags', 'Emax', 'Emin', 'capitals', 'clamp'), 9, ('prec', 'rounding', 'traps', 'flags'), '        # A numeric string consists of:\n#    \\s*\n    (?P<sign>[-+])?              # an optional sign, followed by either...\n    (\n        (?=\\d|\\.\\d)              # ...a number (with at least one digit)\n        (?P<int>\\d*)             # having a (possibly empty) integer part\n        (\\.(?P<frac>\\d*))?       # followed by an optional fractional part\n        (E(?P<exp>[-+]?\\d+))?    # followed by an optional exponent, or...\n    |\n        Inf(inity)?              # ...an infinity, or...\n    |\n        (?P<signal>s)?           # ...an (optionally signaling)\n        NaN                      # NaN\n        (?P<diag>\\d*)            # with (possibly empty) diagnostic info.\n    )\n#    \\s*\n    \\Z\n', '0*$', '50*$', '\\A\n(?:\n   (?P<fill>.)?\n   (?P<align>[<>=^])\n)?\n(?P<sign>[-+ ])?\n(?P<no_neg_0>z)?\n(?P<alt>\\#)?\n(?P<zeropad>0)?\n(?P<minimumwidth>(?!0)\\d+)?\n(?P<thousands_sep>,)?\n(?:\\.(?P<precision>0|(?!0)\\d+))?\n(?P<type>[eEfFgGn%])?\n\\Z\n', <code object _parse_format_specifier at 0x0000024068E3F5F0, file "_pydecimal.py", line 6188>, <code object _format_align at 0x0000024068E22A40, file "_pydecimal.py", line 6268>, <code object _group_lengths at 0x00000240694996F0, file "_pydecimal.py", line 6295>, <code object _insert_thousands_sep at 0x0000024068BFEA30, file "_pydecimal.py", line 6318>, <code object _format_sign at 0x000002406945D980, file "_pydecimal.py", line 6355>, <code object _format_number at 0x0000024068E7DD80, file "_pydecimal.py", line 6365>, 'Inf', '-Inf', 'NaN', -1, 2, (None,), (False,), (0,), (8,), (False, False), (1,))

## co_names:
('__doc__', '__all__', '__name__', '__xname__', '__version__', '__libmpdec_version__', 'math', '_math', 'numbers', '_numbers', 'sys', 'collections', 'namedtuple', '_namedtuple', 'DecimalTuple', 'ImportError', 'ROUND_DOWN', 'ROUND_HALF_UP', 'ROUND_HALF_EVEN', 'ROUND_CEILING', 'ROUND_FLOOR', 'ROUND_UP', 'ROUND_HALF_DOWN', 'ROUND_05UP', 'HAVE_THREADS', 'HAVE_CONTEXTVAR', 'maxsize', 'MAX_PREC', 'MAX_EMAX', 'MIN_EMIN', 'MIN_ETINY', 'ArithmeticError', 'DecimalException', 'Clamped', 'InvalidOperation', 'ConversionSyntax', 'ZeroDivisionError', 'DivisionByZero', 'DivisionImpossible', 'DivisionUndefined', 'Inexact', 'InvalidContext', 'Rounded', 'Subnormal', 'Overflow', 'Underflow', 'TypeError', 'FloatOperation', '_signals', '_condition_map', '_rounding_modes', 'contextvars', 'ContextVar', '_current_context_var', 'frozenset', '_context_attributes', 'getcontext', 'setcontext', 'localcontext', 'object', 'Decimal', '_dec_from_triple', 'Number', 'register', '_ContextManager', 'Context', '_WorkRep', '_normalize', 'int', 'bit_length', '_nbits', '_decimal_lshift_exact', '_sqrt_nearest', '_rshift_nearest', '_div_nearest', '_ilog', '_dlog10', '_dlog', '_Log10Memoize', 'getdigits', '_log10_digits', '_iexp', '_dexp', '_dpower', '_log10_lb', '_convert_other', '_convert_for_comparison', 'DefaultContext', 'BasicContext', 'ExtendedContext', 're', 'compile', 'VERBOSE', 'IGNORECASE', 'match', '_parser', '_all_zeros', '_exact_half', 'DOTALL', '_parse_format_specifier_regex', 'locale', '_locale', '_parse_format_specifier', '_format_align', '_group_lengths', '_insert_thousands_sep', '_format_sign', '_format_number', '_Infinity', '_NegativeInfinity', '_NaN', '_Zero', '_One', '_NegativeOne', '_SignedInfinity', 'hash_info', 'modulus', '_PyHASH_MODULUS', 'inf', '_PyHASH_INF', 'nan', '_PyHASH_NAN', 'pow', '_PyHASH_10INV')

## bytecode:

   0: RESUME               
   2: LOAD_CONST           '\nThis is an implementation of decimal floating point arithmetic based on\nthe General Decimal Arithmetic Specification:\n\n    http://speleotrove.com/decimal/decarith.html\n\nand IEEE standard 854-1987:\n\n    http://en.wikipedia.org/wiki/IEEE_854-1987\n\nDecimal floating point has finite precision with arbitrarily large bounds.\n\nThe purpose of this module is to support arithmetic using familiar\n"schoolhouse" rules and to avoid some of the tricky representation\nissues associated with binary floating point.  The package is especially\nuseful for financial applications or for contexts where users have\nexpectations that are at odds with binary floating point (for instance,\nin binary floating point, 1.00 % 0.1 gives 0.09999999999999995 instead\nof 0.0; Decimal(\'1.00\') % Decimal(\'0.1\') returns the expected\nDecimal(\'0.00\')).\n\nHere are some examples of using the decimal module:\n\n>>> from decimal import *\n>>> setcontext(ExtendedContext)\n>>> Decimal(0)\nDecimal(\'0\')\n>>> Decimal(\'1\')\nDecimal(\'1\')\n>>> Decimal(\'-.0123\')\nDecimal(\'-0.0123\')\n>>> Decimal(123456)\nDecimal(\'123456\')\n>>> Decimal(\'123.45e12345678\')\nDecimal(\'1.2345E+12345680\')\n>>> Decimal(\'1.33\') + Decimal(\'1.27\')\nDecimal(\'2.60\')\n>>> Decimal(\'12.34\') + Decimal(\'3.87\') - Decimal(\'18.41\')\nDecimal(\'-2.20\')\n>>> dig = Decimal(1)\n>>> print(dig / Decimal(3))\n0.333333333\n>>> getcontext().prec = 18\n>>> print(dig / Decimal(3))\n0.333333333333333333\n>>> print(dig.sqrt())\n1\n>>> print(Decimal(3).sqrt())\n1.73205080756887729\n>>> print(Decimal(3) ** 123)\n4.85192780976896427E+58\n>>> inf = Decimal(1) / Decimal(0)\n>>> print(inf)\nInfinity\n>>> neginf = Decimal(-1) / Decimal(0)\n>>> print(neginf)\n-Infinity\n>>> print(neginf + inf)\nNaN\n>>> print(neginf * inf)\n-Infinity\n>>> print(dig / 0)\nInfinity\n>>> getcontext().traps[DivisionByZero] = 1\n>>> print(dig / 0)\nTraceback (most recent call last):\n  ...\n  ...\n  ...\ndecimal.DivisionByZero: x / 0\n>>> c = Context()\n>>> c.traps[InvalidOperation] = 0\n>>> print(c.flags[InvalidOperation])\n0\n>>> c.divide(Decimal(0), Decimal(0))\nDecimal(\'NaN\')\n>>> c.traps[InvalidOperation] = 1\n>>> print(c.flags[InvalidOperation])\n1\n>>> c.flags[InvalidOperation] = 0\n>>> print(c.flags[InvalidOperation])\n0\n>>> print(c.divide(Decimal(0), Decimal(0)))\nTraceback (most recent call last):\n  ...\n  ...\n  ...\ndecimal.InvalidOperation: 0 / 0\n>>> print(c.flags[InvalidOperation])\n1\n>>> c.flags[InvalidOperation] = 0\n>>> c.traps[InvalidOperation] = 0\n>>> print(c.divide(Decimal(0), Decimal(0)))\nNaN\n>>> print(c.flags[InvalidOperation])\n1\n>>>\n'
   4: STORE_NAME           __doc__
   6: BUILD_LIST           
   8: LOAD_CONST           ('Decimal', 'Context', 'DecimalTuple', 'DefaultContext', 'BasicContext', 'ExtendedContext', 'DecimalException', 'Clamped', 'InvalidOperation', 'DivisionByZero', 'Inexact', 'Rounded', 'Subnormal', 'Overflow', 'Underflow', 'FloatOperation', 'DivisionImpossible', 'InvalidContext', 'ConversionSyntax', 'DivisionUndefined', 'ROUND_DOWN', 'ROUND_HALF_UP', 'ROUND_HALF_EVEN', 'ROUND_CEILING', 'ROUND_FLOOR', 'ROUND_UP', 'ROUND_HALF_DOWN', 'ROUND_05UP', 'setcontext', 'getcontext', 'localcontext', 'MAX_PREC', 'MAX_EMAX', 'MIN_EMIN', 'MIN_ETINY', 'HAVE_THREADS', 'HAVE_CONTEXTVAR')
  10: LIST_EXTEND          
  12: STORE_NAME           __all__
  14: LOAD_NAME            __name__
  16: STORE_NAME           __xname__
  18: LOAD_CONST           'decimal'
  20: STORE_NAME           __name__
  22: LOAD_CONST           '1.70'
  24: STORE_NAME           __version__
  26: LOAD_CONST           '2.4.2'
  28: STORE_NAME           __libmpdec_version__
  30: LOAD_CONST           0
  32: LOAD_CONST           None
  34: IMPORT_NAME          math
  36: STORE_NAME           _math
  38: LOAD_CONST           0
  40: LOAD_CONST           None
  42: IMPORT_NAME          numbers
  44: STORE_NAME           _numbers
  46: LOAD_CONST           0
  48: LOAD_CONST           None
  50: IMPORT_NAME          sys
  52: STORE_NAME           sys
  54: NOP                  
  56: LOAD_CONST           0
  58: LOAD_CONST           ('namedtuple',)
  60: IMPORT_NAME          collections
  62: IMPORT_FROM          namedtuple
  64: STORE_NAME           _namedtuple
  66: POP_TOP              
  68: PUSH_NULL            
  70: LOAD_NAME            _namedtuple
  72: LOAD_CONST           'DecimalTuple'
  74: LOAD_CONST           'sign digits exponent'
  76: PRECALL              
  80: CALL                 
  90: STORE_NAME           DecimalTuple
  92: JUMP_FORWARD         to 122
  94: PUSH_EXC_INFO        
  96: LOAD_NAME            ImportError
  98: CHECK_EXC_MATCH      
 100: POP_JUMP_FORWARD_IF_FALSE to 114
 102: POP_TOP              
 104: LOAD_CONST           <code object <lambda> at 0x000002406943B270, file "_pydecimal.py", line 164>
 106: MAKE_FUNCTION        
 108: STORE_NAME           DecimalTuple
 110: POP_EXCEPT           
 112: JUMP_FORWARD         to 122
 114: RERAISE              
 116: COPY                 
 118: POP_EXCEPT           
 120: RERAISE              
 122: LOAD_CONST           'ROUND_DOWN'
 124: STORE_NAME           ROUND_DOWN
 126: LOAD_CONST           'ROUND_HALF_UP'
 128: STORE_NAME           ROUND_HALF_UP
 130: LOAD_CONST           'ROUND_HALF_EVEN'
 132: STORE_NAME           ROUND_HALF_EVEN
 134: LOAD_CONST           'ROUND_CEILING'
 136: STORE_NAME           ROUND_CEILING
 138: LOAD_CONST           'ROUND_FLOOR'
 140: STORE_NAME           ROUND_FLOOR
 142: LOAD_CONST           'ROUND_UP'
 144: STORE_NAME           ROUND_UP
 146: LOAD_CONST           'ROUND_HALF_DOWN'
 148: STORE_NAME           ROUND_HALF_DOWN
 150: LOAD_CONST           'ROUND_05UP'
 152: STORE_NAME           ROUND_05UP
 154: LOAD_CONST           True
 156: STORE_NAME           HAVE_THREADS
 158: LOAD_CONST           True
 160: STORE_NAME           HAVE_CONTEXTVAR
 162: LOAD_NAME            sys
 164: LOAD_ATTR            maxsize
 174: LOAD_CONST           9223372036854775807
 176: COMPARE_OP           ==
 182: POP_JUMP_FORWARD_IF_FALSE to 198
 184: LOAD_CONST           999999999999999999
 186: STORE_NAME           MAX_PREC
 188: LOAD_CONST           999999999999999999
 190: STORE_NAME           MAX_EMAX
 192: LOAD_CONST           -999999999999999999
 194: STORE_NAME           MIN_EMIN
 196: JUMP_FORWARD         to 210
 198: LOAD_CONST           425000000
 200: STORE_NAME           MAX_PREC
 202: LOAD_CONST           425000000
 204: STORE_NAME           MAX_EMAX
 206: LOAD_CONST           -425000000
 208: STORE_NAME           MIN_EMIN
 210: LOAD_NAME            MIN_EMIN
 212: LOAD_NAME            MAX_PREC
 214: LOAD_CONST           1
 216: BINARY_OP            -
 220: BINARY_OP            -
 224: STORE_NAME           MIN_ETINY
 226: PUSH_NULL            
 228: LOAD_BUILD_CLASS     
 230: LOAD_CONST           <code object DecimalException at 0x0000024069496DB0, file "_pydecimal.py", line 192>
 232: MAKE_FUNCTION        
 234: LOAD_CONST           'DecimalException'
 236: LOAD_NAME            ArithmeticError
 238: PRECALL              
 242: CALL                 
 252: STORE_NAME           DecimalException
 254: PUSH_NULL            
 256: LOAD_BUILD_CLASS     
 258: LOAD_CONST           <code object Clamped at 0x0000024069496F50, file "_pydecimal.py", line 215>
 260: MAKE_FUNCTION        
 262: LOAD_CONST           'Clamped'
 264: LOAD_NAME            DecimalException
 266: PRECALL              
 270: CALL                 
 280: STORE_NAME           Clamped
 282: PUSH_NULL            
 284: LOAD_BUILD_CLASS     
 286: LOAD_CONST           <code object InvalidOperation at 0x0000024069494440, file "_pydecimal.py", line 227>
 288: MAKE_FUNCTION        
 290: LOAD_CONST           'InvalidOperation'
 292: LOAD_NAME            DecimalException
 294: PRECALL              
 298: CALL                 
 308: STORE_NAME           InvalidOperation
 310: PUSH_NULL            
 312: LOAD_BUILD_CLASS     
 314: LOAD_CONST           <code object ConversionSyntax at 0x0000024069496800, file "_pydecimal.py", line 256>
 316: MAKE_FUNCTION        
 318: LOAD_CONST           'ConversionSyntax'
 320: LOAD_NAME            InvalidOperation
 322: PRECALL              
 326: CALL                 
 336: STORE_NAME           ConversionSyntax
 338: PUSH_NULL            
 340: LOAD_BUILD_CLASS     
 342: LOAD_CONST           <code object DivisionByZero at 0x0000024069494370, file "_pydecimal.py", line 266>
 344: MAKE_FUNCTION        
 346: LOAD_CONST           'DivisionByZero'
 348: LOAD_NAME            DecimalException
 350: LOAD_NAME            ZeroDivisionError
 352: PRECALL              
 356: CALL                 
 366: STORE_NAME           DivisionByZero
 368: PUSH_NULL            
 370: LOAD_BUILD_CLASS     
 372: LOAD_CONST           <code object DivisionImpossible at 0x0000024069494ED0, file "_pydecimal.py", line 282>
 374: MAKE_FUNCTION        
 376: LOAD_CONST           'DivisionImpossible'
 378: LOAD_NAME            InvalidOperation
 380: PRECALL              
 384: CALL                 
 394: STORE_NAME           DivisionImpossible
 396: PUSH_NULL            
 398: LOAD_BUILD_CLASS     
 400: LOAD_CONST           <code object DivisionUndefined at 0x0000024069497360, file "_pydecimal.py", line 293>
 402: MAKE_FUNCTION        
 404: LOAD_CONST           'DivisionUndefined'
 406: LOAD_NAME            InvalidOperation
 408: LOAD_NAME            ZeroDivisionError
 410: PRECALL              
 414: CALL                 
 424: STORE_NAME           DivisionUndefined
 426: PUSH_NULL            
 428: LOAD_BUILD_CLASS     
 430: LOAD_CONST           <code object Inexact at 0x0000024069497430, file "_pydecimal.py", line 304>
 432: MAKE_FUNCTION        
 434: LOAD_CONST           'Inexact'
 436: LOAD_NAME            DecimalException
 438: PRECALL              
 442: CALL                 
 452: STORE_NAME           Inexact
 454: PUSH_NULL            
 456: LOAD_BUILD_CLASS     
 458: LOAD_CONST           <code object InvalidContext at 0x00000240694960B0, file "_pydecimal.py", line 316>
 460: MAKE_FUNCTION        
 462: LOAD_CONST           'InvalidContext'
 464: LOAD_NAME            InvalidOperation
 466: PRECALL              
 470: CALL                 
 480: STORE_NAME           InvalidContext
 482: PUSH_NULL            
 484: LOAD_BUILD_CLASS     
 486: LOAD_CONST           <code object Rounded at 0x0000024069496590, file "_pydecimal.py", line 330>
 488: MAKE_FUNCTION        
 490: LOAD_CONST           'Rounded'
 492: LOAD_NAME            DecimalException
 494: PRECALL              
 498: CALL                 
 508: STORE_NAME           Rounded
 510: PUSH_NULL            
 512: LOAD_BUILD_CLASS     
 514: LOAD_CONST           <code object Subnormal at 0x0000024069497840, file "_pydecimal.py", line 342>
 516: MAKE_FUNCTION        
 518: LOAD_CONST           'Subnormal'
 520: LOAD_NAME            DecimalException
 522: PRECALL              
 526: CALL                 
 536: STORE_NAME           Subnormal
 538: PUSH_NULL            
 540: LOAD_BUILD_CLASS     
 542: LOAD_CONST           <code object Overflow at 0x0000024069496CE0, file "_pydecimal.py", line 353>
 544: MAKE_FUNCTION        
 546: LOAD_CONST           'Overflow'
 548: LOAD_NAME            Inexact
 550: LOAD_NAME            Rounded
 552: PRECALL              
 556: CALL                 
 566: STORE_NAME           Overflow
 568: PUSH_NULL            
 570: LOAD_BUILD_CLASS     
 572: LOAD_CONST           <code object Underflow at 0x0000024069494920, file "_pydecimal.py", line 391>
 574: MAKE_FUNCTION        
 576: LOAD_CONST           'Underflow'
 578: LOAD_NAME            Inexact
 580: LOAD_NAME            Rounded
 582: LOAD_NAME            Subnormal
 584: PRECALL              
 588: CALL                 
 598: STORE_NAME           Underflow
 600: PUSH_NULL            
 602: LOAD_BUILD_CLASS     
 604: LOAD_CONST           <code object FloatOperation at 0x0000024069495D70, file "_pydecimal.py", line 406>
 606: MAKE_FUNCTION        
 608: LOAD_CONST           'FloatOperation'
 610: LOAD_NAME            DecimalException
 612: LOAD_NAME            TypeError
 614: PRECALL              
 618: CALL                 
 628: STORE_NAME           FloatOperation
 630: LOAD_NAME            Clamped
 632: LOAD_NAME            DivisionByZero
 634: LOAD_NAME            Inexact
 636: LOAD_NAME            Overflow
 638: LOAD_NAME            Rounded
 640: LOAD_NAME            Underflow
 642: LOAD_NAME            InvalidOperation
 644: LOAD_NAME            Subnormal
 646: LOAD_NAME            FloatOperation
 648: BUILD_LIST           
 650: STORE_NAME           _signals
 652: LOAD_NAME            ConversionSyntax
 654: LOAD_NAME            InvalidOperation
 656: LOAD_NAME            DivisionImpossible
 658: LOAD_NAME            InvalidOperation
 660: LOAD_NAME            DivisionUndefined
 662: LOAD_NAME            InvalidOperation
 664: LOAD_NAME            InvalidContext
 666: LOAD_NAME            InvalidOperation
 668: BUILD_MAP            
 670: STORE_NAME           _condition_map
 672: LOAD_NAME            ROUND_DOWN
 674: LOAD_NAME            ROUND_HALF_UP
 676: LOAD_NAME            ROUND_HALF_EVEN
 678: LOAD_NAME            ROUND_CEILING
 680: LOAD_NAME            ROUND_FLOOR
 682: LOAD_NAME            ROUND_UP
 684: LOAD_NAME            ROUND_HALF_DOWN
 686: LOAD_NAME            ROUND_05UP
 688: BUILD_TUPLE          
 690: STORE_NAME           _rounding_modes
 692: LOAD_CONST           0
 694: LOAD_CONST           None
 696: IMPORT_NAME          contextvars
 698: STORE_NAME           contextvars
 700: PUSH_NULL            
 702: LOAD_NAME            contextvars
 704: LOAD_ATTR            ContextVar
 714: LOAD_CONST           'decimal_context'
 716: PRECALL              
 720: CALL                 
 730: STORE_NAME           _current_context_var
 732: PUSH_NULL            
 734: LOAD_NAME            frozenset
 736: BUILD_LIST           
 738: LOAD_CONST           ('prec', 'Emin', 'Emax', 'capitals', 'clamp', 'rounding', 'flags', 'traps')
 740: LIST_EXTEND          
 742: PRECALL              
 746: CALL                 
 756: STORE_NAME           _context_attributes
 758: LOAD_CONST           <code object getcontext at 0x000002406921FB20, file "_pydecimal.py", line 448>
 760: MAKE_FUNCTION        
 762: STORE_NAME           getcontext
 764: LOAD_CONST           <code object setcontext at 0x000002406921F9B0, file "_pydecimal.py", line 462>
 766: MAKE_FUNCTION        
 768: STORE_NAME           setcontext
 770: DELETE_NAME          contextvars
 772: LOAD_CONST           (None,)
 774: LOAD_CONST           <code object localcontext at 0x00000240691F60B0, file "_pydecimal.py", line 471>
 776: MAKE_FUNCTION        defaults
 778: STORE_NAME           localcontext
 780: PUSH_NULL            
 782: LOAD_BUILD_CLASS     
 784: LOAD_CONST           <code object Decimal at 0x0000024068E134B0, file "_pydecimal.py", line 523>
 786: MAKE_FUNCTION        
 788: LOAD_CONST           'Decimal'
 790: LOAD_NAME            object
 792: PRECALL              
 796: CALL                 
 806: STORE_NAME           Decimal
 808: LOAD_CONST           (False,)
 810: LOAD_CONST           <code object _dec_from_triple at 0x00000240693AA470, file "_pydecimal.py", line 3844>
 812: MAKE_FUNCTION        defaults
 814: STORE_NAME           _dec_from_triple
 816: LOAD_NAME            _numbers
 818: LOAD_ATTR            Number
 828: LOAD_METHOD          register
 850: LOAD_NAME            Decimal
 852: PRECALL              
 856: CALL                 
 866: POP_TOP              
 868: PUSH_NULL            
 870: LOAD_BUILD_CLASS     
 872: LOAD_CONST           <code object _ContextManager at 0x0000024069467AD0, file "_pydecimal.py", line 3868>
 874: MAKE_FUNCTION        
 876: LOAD_CONST           '_ContextManager'
 878: LOAD_NAME            object
 880: PRECALL              
 884: CALL                 
 894: STORE_NAME           _ContextManager
 896: PUSH_NULL            
 898: LOAD_BUILD_CLASS     
 900: LOAD_CONST           <code object Context at 0x0000024068C0AF60, file "_pydecimal.py", line 3883>
 902: MAKE_FUNCTION        
 904: LOAD_CONST           'Context'
 906: LOAD_NAME            object
 908: PRECALL              
 912: CALL                 
 922: STORE_NAME           Context
 924: PUSH_NULL            
 926: LOAD_BUILD_CLASS     
 928: LOAD_CONST           <code object _WorkRep at 0x0000024069465ED0, file "_pydecimal.py", line 5628>
 930: MAKE_FUNCTION        
 932: LOAD_CONST           '_WorkRep'
 934: LOAD_NAME            object
 936: PRECALL              
 940: CALL                 
 950: STORE_NAME           _WorkRep
 952: LOAD_CONST           (0,)
 954: LOAD_CONST           <code object _normalize at 0x0000024068E7E700, file "_pydecimal.py", line 5654>
 956: MAKE_FUNCTION        defaults
 958: STORE_NAME           _normalize
 960: LOAD_NAME            int
 962: LOAD_ATTR            bit_length
 972: STORE_NAME           _nbits
 974: LOAD_CONST           <code object _decimal_lshift_exact at 0x0000024069CF41E0, file "_pydecimal.py", line 5686>
 976: MAKE_FUNCTION        
 978: STORE_NAME           _decimal_lshift_exact
 980: LOAD_CONST           <code object _sqrt_nearest at 0x00000240693D29C0, file "_pydecimal.py", line 5707>
 982: MAKE_FUNCTION        
 984: STORE_NAME           _sqrt_nearest
 986: LOAD_CONST           <code object _rshift_nearest at 0x00000240693EAD30, file "_pydecimal.py", line 5722>
 988: MAKE_FUNCTION        
 990: STORE_NAME           _rshift_nearest
 992: LOAD_CONST           <code object _div_nearest at 0x0000024069CDA230, file "_pydecimal.py", line 5730>
 994: MAKE_FUNCTION        
 996: STORE_NAME           _div_nearest
 998: LOAD_CONST           (8,)
1000: LOAD_CONST           <code object _ilog at 0x0000024068C27750, file "_pydecimal.py", line 5738>
1002: MAKE_FUNCTION        defaults
1004: STORE_NAME           _ilog
1006: LOAD_CONST           <code object _dlog10 at 0x0000024068D6E320, file "_pydecimal.py", line 5786>
1008: MAKE_FUNCTION        
1010: STORE_NAME           _dlog10
1012: LOAD_CONST           <code object _dlog at 0x0000024068D31640, file "_pydecimal.py", line 5820>
1014: MAKE_FUNCTION        
1016: STORE_NAME           _dlog
1018: PUSH_NULL            
1020: LOAD_BUILD_CLASS     
1022: LOAD_CONST           <code object _Log10Memoize at 0x0000024069466B10, file "_pydecimal.py", line 5864>
1024: MAKE_FUNCTION        
1026: LOAD_CONST           '_Log10Memoize'
1028: LOAD_NAME            object
1030: PRECALL              
1034: CALL                 
1044: STORE_NAME           _Log10Memoize
1046: PUSH_NULL            
1048: LOAD_NAME            _Log10Memoize
1050: PRECALL              
1054: CALL                 
1064: LOAD_ATTR            getdigits
1074: STORE_NAME           _log10_digits
1076: LOAD_CONST           (8,)
1078: LOAD_CONST           <code object _iexp at 0x0000024068D6C2C0, file "_pydecimal.py", line 5901>
1080: MAKE_FUNCTION        defaults
1082: STORE_NAME           _iexp
1084: LOAD_CONST           <code object _dexp at 0x000002406958EAA0, file "_pydecimal.py", line 5938>
1086: MAKE_FUNCTION        
1088: STORE_NAME           _dexp
1090: LOAD_CONST           <code object _dpower at 0x0000024068E5DD90, file "_pydecimal.py", line 5974>
1092: MAKE_FUNCTION        
1094: STORE_NAME           _dpower
1096: LOAD_CONST           100
1098: LOAD_CONST           70
1100: LOAD_CONST           53
1102: LOAD_CONST           40
1104: LOAD_CONST           31
1106: LOAD_CONST           23
1108: LOAD_CONST           16
1110: LOAD_CONST           10
1112: LOAD_CONST           5
1114: LOAD_CONST           ('1', '2', '3', '4', '5', '6', '7', '8', '9')
1116: BUILD_CONST_KEY_MAP  
1118: BUILD_TUPLE          
1120: LOAD_CONST           <code object _log10_lb at 0x000002406922DE60, file "_pydecimal.py", line 6016>
1122: MAKE_FUNCTION        defaults
1124: STORE_NAME           _log10_lb
1126: LOAD_CONST           (False, False)
1128: LOAD_CONST           <code object _convert_other at 0x00000240691DB2F0, file "_pydecimal.py", line 6027>
1130: MAKE_FUNCTION        defaults
1132: STORE_NAME           _convert_other
1134: LOAD_CONST           (False,)
1136: LOAD_CONST           <code object _convert_for_comparison at 0x0000024068BFD370, file "_pydecimal.py", line 6046>
1138: MAKE_FUNCTION        defaults
1140: STORE_NAME           _convert_for_comparison
1142: PUSH_NULL            
1144: LOAD_NAME            Context
1146: LOAD_CONST           28
1148: LOAD_NAME            ROUND_HALF_EVEN
1150: LOAD_NAME            DivisionByZero
1152: LOAD_NAME            Overflow
1154: LOAD_NAME            InvalidOperation
1156: BUILD_LIST           
1158: BUILD_LIST           
1160: LOAD_CONST           999999
1162: LOAD_CONST           -999999
1164: LOAD_CONST           1
1166: LOAD_CONST           0
1168: KW_NAMES             
1170: PRECALL              
1174: CALL                 
1184: STORE_NAME           DefaultContext
1186: PUSH_NULL            
1188: LOAD_NAME            Context
1190: LOAD_CONST           9
1192: LOAD_NAME            ROUND_HALF_UP
1194: LOAD_NAME            DivisionByZero
1196: LOAD_NAME            Overflow
1198: LOAD_NAME            InvalidOperation
1200: LOAD_NAME            Clamped
1202: LOAD_NAME            Underflow
1204: BUILD_LIST           
1206: BUILD_LIST           
1208: KW_NAMES             
1210: PRECALL              
1214: CALL                 
1224: STORE_NAME           BasicContext
1226: PUSH_NULL            
1228: LOAD_NAME            Context
1230: LOAD_CONST           9
1232: LOAD_NAME            ROUND_HALF_EVEN
1234: BUILD_LIST           
1236: BUILD_LIST           
1238: KW_NAMES             
1240: PRECALL              
1244: CALL                 
1254: STORE_NAME           ExtendedContext
1256: LOAD_CONST           0
1258: LOAD_CONST           None
1260: IMPORT_NAME          re
1262: STORE_NAME           re
1264: PUSH_NULL            
1266: LOAD_NAME            re
1268: LOAD_ATTR            compile
1278: LOAD_CONST           '        # A numeric string consists of:\n#    \\s*\n    (?P<sign>[-+])?              # an optional sign, followed by either...\n    (\n        (?=\\d|\\.\\d)              # ...a number (with at least one digit)\n        (?P<int>\\d*)             # having a (possibly empty) integer part\n        (\\.(?P<frac>\\d*))?       # followed by an optional fractional part\n        (E(?P<exp>[-+]?\\d+))?    # followed by an optional exponent, or...\n    |\n        Inf(inity)?              # ...an infinity, or...\n    |\n        (?P<signal>s)?           # ...an (optionally signaling)\n        NaN                      # NaN\n        (?P<diag>\\d*)            # with (possibly empty) diagnostic info.\n    )\n#    \\s*\n    \\Z\n'
1280: LOAD_NAME            re
1282: LOAD_ATTR            VERBOSE
1292: LOAD_NAME            re
1294: LOAD_ATTR            IGNORECASE
1304: BINARY_OP            |
1308: PRECALL              
1312: CALL                 
1322: LOAD_ATTR            match
1332: STORE_NAME           _parser
1334: PUSH_NULL            
1336: LOAD_NAME            re
1338: LOAD_ATTR            compile
1348: LOAD_CONST           '0*$'
1350: PRECALL              
1354: CALL                 
1364: LOAD_ATTR            match
1374: STORE_NAME           _all_zeros
1376: PUSH_NULL            
1378: LOAD_NAME            re
1380: LOAD_ATTR            compile
1390: LOAD_CONST           '50*$'
1392: PRECALL              
1396: CALL                 
1406: LOAD_ATTR            match
1416: STORE_NAME           _exact_half
1418: PUSH_NULL            
1420: LOAD_NAME            re
1422: LOAD_ATTR            compile
1432: LOAD_CONST           '\\A\n(?:\n   (?P<fill>.)?\n   (?P<align>[<>=^])\n)?\n(?P<sign>[-+ ])?\n(?P<no_neg_0>z)?\n(?P<alt>\\#)?\n(?P<zeropad>0)?\n(?P<minimumwidth>(?!0)\\d+)?\n(?P<thousands_sep>,)?\n(?:\\.(?P<precision>0|(?!0)\\d+))?\n(?P<type>[eEfFgGn%])?\n\\Z\n'
1434: LOAD_NAME            re
1436: LOAD_ATTR            VERBOSE
1446: LOAD_NAME            re
1448: LOAD_ATTR            DOTALL
1458: BINARY_OP            |
1462: PRECALL              
1466: CALL                 
1476: STORE_NAME           _parse_format_specifier_regex
1478: DELETE_NAME          re
1480: NOP                  
1482: LOAD_CONST           0
1484: LOAD_CONST           None
1486: IMPORT_NAME          locale
1488: STORE_NAME           _locale
1490: JUMP_FORWARD         to 1514
1492: PUSH_EXC_INFO        
1494: LOAD_NAME            ImportError
1496: CHECK_EXC_MATCH      
1498: POP_JUMP_FORWARD_IF_FALSE to 1506
1500: POP_TOP              
1502: POP_EXCEPT           
1504: JUMP_FORWARD         to 1514
1506: RERAISE              
1508: COPY                 
1510: POP_EXCEPT           
1512: RERAISE              
1514: LOAD_CONST           (None,)
1516: LOAD_CONST           <code object _parse_format_specifier at 0x0000024068E3F5F0, file "_pydecimal.py", line 6188>
1518: MAKE_FUNCTION        defaults
1520: STORE_NAME           _parse_format_specifier
1522: LOAD_CONST           <code object _format_align at 0x0000024068E22A40, file "_pydecimal.py", line 6268>
1524: MAKE_FUNCTION        
1526: STORE_NAME           _format_align
1528: LOAD_CONST           <code object _group_lengths at 0x00000240694996F0, file "_pydecimal.py", line 6295>
1530: MAKE_FUNCTION        
1532: STORE_NAME           _group_lengths
1534: LOAD_CONST           (1,)
1536: LOAD_CONST           <code object _insert_thousands_sep at 0x0000024068BFEA30, file "_pydecimal.py", line 6318>
1538: MAKE_FUNCTION        defaults
1540: STORE_NAME           _insert_thousands_sep
1542: LOAD_CONST           <code object _format_sign at 0x000002406945D980, file "_pydecimal.py", line 6355>
1544: MAKE_FUNCTION        
1546: STORE_NAME           _format_sign
1548: LOAD_CONST           <code object _format_number at 0x0000024068E7DD80, file "_pydecimal.py", line 6365>
1550: MAKE_FUNCTION        
1552: STORE_NAME           _format_number
1554: PUSH_NULL            
1556: LOAD_NAME            Decimal
1558: LOAD_CONST           'Inf'
1560: PRECALL              
1564: CALL                 
1574: STORE_NAME           _Infinity
1576: PUSH_NULL            
1578: LOAD_NAME            Decimal
1580: LOAD_CONST           '-Inf'
1582: PRECALL              
1586: CALL                 
1596: STORE_NAME           _NegativeInfinity
1598: PUSH_NULL            
1600: LOAD_NAME            Decimal
1602: LOAD_CONST           'NaN'
1604: PRECALL              
1608: CALL                 
1618: STORE_NAME           _NaN
1620: PUSH_NULL            
1622: LOAD_NAME            Decimal
1624: LOAD_CONST           0
1626: PRECALL              
1630: CALL                 
1640: STORE_NAME           _Zero
1642: PUSH_NULL            
1644: LOAD_NAME            Decimal
1646: LOAD_CONST           1
1648: PRECALL              
1652: CALL                 
1662: STORE_NAME           _One
1664: PUSH_NULL            
1666: LOAD_NAME            Decimal
1668: LOAD_CONST           -1
1670: PRECALL              
1674: CALL                 
1684: STORE_NAME           _NegativeOne
1686: LOAD_NAME            _Infinity
1688: LOAD_NAME            _NegativeInfinity
1690: BUILD_TUPLE          
1692: STORE_NAME           _SignedInfinity
1694: LOAD_NAME            sys
1696: LOAD_ATTR            hash_info
1706: LOAD_ATTR            modulus
1716: STORE_NAME           _PyHASH_MODULUS
1718: LOAD_NAME            sys
1720: LOAD_ATTR            hash_info
1730: LOAD_ATTR            inf
1740: STORE_NAME           _PyHASH_INF
1742: LOAD_NAME            sys
1744: LOAD_ATTR            hash_info
1754: LOAD_ATTR            nan
1764: STORE_NAME           _PyHASH_NAN
1766: PUSH_NULL            
1768: LOAD_NAME            pow
1770: LOAD_CONST           10
1772: LOAD_NAME            _PyHASH_MODULUS
1774: LOAD_CONST           2
1776: BINARY_OP            -
1780: LOAD_NAME            _PyHASH_MODULUS
1782: PRECALL              
1786: CALL                 
1796: STORE_NAME           _PyHASH_10INV
1798: DELETE_NAME          sys
1800: LOAD_CONST           None
1802: RETURN_VALUE         
