# Disassembly for _pydecimal.Context.to_integral_value
# From module file: _pydecimal

## co_consts:
("Rounds to an integer.\n\n        When the operand has a negative exponent, the result is the same\n        as using the quantize() operation using the given operand as the\n        left-hand-operand, 1E+0 as the right-hand-operand, and the precision\n        of the operand as the precision setting, except that no flags will\n        be set.  The rounding mode is taken from the context.\n\n        >>> ExtendedContext.to_integral_value(Decimal('2.1'))\n        Decimal('2')\n        >>> ExtendedContext.to_integral_value(Decimal('100'))\n        Decimal('100')\n        >>> ExtendedContext.to_integral_value(Decimal('100.0'))\n        Decimal('100')\n        >>> ExtendedContext.to_integral_value(Decimal('101.5'))\n        Decimal('102')\n        >>> ExtendedContext.to_integral_value(Decimal('-101.5'))\n        Decimal('-102')\n        >>> ExtendedContext.to_integral_value(Decimal('10E+5'))\n        Decimal('1.0E+6')\n        >>> ExtendedContext.to_integral_value(Decimal('7.89E+77'))\n        Decimal('7.89E+77')\n        >>> ExtendedContext.to_integral_value(Decimal('-Inf'))\n        Decimal('-Infinity')\n        ", True, ('raiseit',), ('context',))

## co_names:
('_convert_other', 'to_integral_value')

## bytecode:

   0: RESUME               
   2: LOAD_GLOBAL          NULL + _convert_other
  14: LOAD_FAST            a
  16: LOAD_CONST           True
  18: KW_NAMES             
  20: PRECALL              
  24: CALL                 
  34: STORE_FAST           a
  36: LOAD_FAST            a
  38: LOAD_METHOD          to_integral_value
  60: LOAD_FAST            self
  62: KW_NAMES             
  64: PRECALL              
  68: CALL                 
  78: RETURN_VALUE         
