# Disassembly for importlib.EntryPoints.select.<genexpr>
# From module file: importlib.metadata

## co_consts:
(None, ())

## co_names:
('matches',)

## bytecode:

   0: COPY_FREE_VARS       
   2: RETURN_GENERATOR     
   4: POP_TOP              
   6: RESUME               
   8: LOAD_FAST            .0
  10: FOR_ITER             to 50
  12: STORE_FAST           ep
  14: PUSH_NULL            
  16: LOAD_FAST            ep
  18: LOAD_ATTR            matches
  28: LOAD_CONST           ()
  30: BUILD_MAP            
  32: LOAD_DEREF           params
  34: DICT_MERGE           
  36: CALL_FUNCTION_EX     
  38: POP_JUMP_BACKWARD_IF_FALSE to 10
  40: LOAD_FAST            ep
  42: YIELD_VALUE          
  44: RESUME               
  46: POP_TOP              
  48: JUMP_BACKWARD        to 10
  50: LOAD_CONST           None
  52: RETURN_VALUE         
