# Disassembly for importlib.Distribution.discover
# From module file: importlib.metadata

## co_consts:
('Return an iterable of Distribution objects for all packages.\n\n        Pass a ``context`` or pass keyword arguments for constructing\n        a context.\n\n        :context: A ``DistributionFinder.Context`` object.\n        :return: Iterable of Distribution objects for all packages.\n        ', 'context', None, 'cannot accept context and kwargs', <code object <genexpr> at 0x000002406945CF30, file "importlib\metadata\__init__.py", line 581>, ())

## co_names:
('pop', 'ValueError', 'DistributionFinder', 'Context', 'itertools', 'chain', 'from_iterable', '_discover_resolvers')

## bytecode:

   0: MAKE_CELL            context
   2: RESUME               
   4: LOAD_FAST            kwargs
   6: LOAD_METHOD          pop
  28: LOAD_CONST           'context'
  30: LOAD_CONST           None
  32: PRECALL              
  36: CALL                 
  46: STORE_DEREF          context
  48: LOAD_DEREF           context
  50: POP_JUMP_FORWARD_IF_FALSE to 86
  52: LOAD_FAST            kwargs
  54: POP_JUMP_FORWARD_IF_FALSE to 86
  56: LOAD_GLOBAL          NULL + ValueError
  68: LOAD_CONST           'cannot accept context and kwargs'
  70: PRECALL              
  74: CALL                 
  84: RAISE_VARARGS        
  86: LOAD_DEREF           context
  88: JUMP_IF_TRUE_OR_POP  to 122
  90: LOAD_GLOBAL          NULL + DistributionFinder
 102: LOAD_ATTR            Context
 112: LOAD_CONST           ()
 114: BUILD_MAP            
 116: LOAD_FAST            kwargs
 118: DICT_MERGE           
 120: CALL_FUNCTION_EX     
 122: STORE_DEREF          context
 124: LOAD_GLOBAL          itertools
 136: LOAD_ATTR            chain
 146: LOAD_METHOD          from_iterable
 168: LOAD_CLOSURE         context
 170: BUILD_TUPLE          
 172: LOAD_CONST           <code object <genexpr> at 0x000002406945CF30, file "importlib\metadata\__init__.py", line 581>
 174: MAKE_FUNCTION        closure
 176: LOAD_FAST            cls
 178: LOAD_METHOD          _discover_resolvers
 200: PRECALL              
 204: CALL                 
 214: GET_ITER             
 216: PRECALL              
 220: CALL                 
 230: PRECALL              
 234: CALL                 
 244: RETURN_VALUE         
