# Disassembly for importlib.EntryPoint.attr
# From module file: importlib.metadata

## co_consts:
(None, 'attr')

## co_names:
('pattern', 'match', 'value', 'group')

## bytecode:

   0: RESUME               
   2: LOAD_FAST            self
   4: LOAD_ATTR            pattern
  14: LOAD_METHOD          match
  36: LOAD_FAST            self
  38: LOAD_ATTR            value
  48: PRECALL              
  52: CALL                 
  62: STORE_FAST           match
  64: LOAD_FAST            match
  66: LOAD_METHOD          group
  88: LOAD_CONST           'attr'
  90: PRECALL              
  94: CALL                 
 104: RETURN_VALUE         
