# Disassembly for importlib._unpack_uint32
# From module file: importlib._bootstrap_external

## co_consts:
('Convert 4 bytes in little-endian to an integer.', 4, 'little')

## co_names:
('len', 'int', 'from_bytes')

## bytecode:

   0: RESUME               
   2: LOAD_GLOBAL          NULL + len
  14: LOAD_FAST            data
  16: PRECALL              
  20: CALL                 
  30: LOAD_CONST           4
  32: COMPARE_OP           ==
  38: POP_JUMP_FORWARD_IF_TRUE to 44
  40: LOAD_ASSERTION_ERROR 
  42: RAISE_VARARGS        
  44: LOAD_GLOBAL          int
  56: LOAD_METHOD          from_bytes
  78: LOAD_FAST            data
  80: LOAD_CONST           'little'
  82: PRECALL              
  86: CALL                 
  96: RETURN_VALUE         
