# Disassembly for importlib.Distribution._convert_egg_info_reqs_to_simple_reqs
# From module file: importlib.metadata

## co_consts:
("\n        Historically, setuptools would solicit and store 'extra'\n        requirements, including those with environment markers,\n        in separate sections. More modern tools expect each\n        dependency to be defined separately, with any relevant\n        extras and environment markers attached directly to that\n        requirement. This method converts the former to the\n        latter. See _test_deps_from_requires_text for an example.\n        ", <code object make_condition at 0x0000024069495070, file "importlib\metadata\__init__.py", line 707>, <code object quoted_marker at 0x00000240691F5890, file "importlib\metadata\__init__.py", line 710>, <code object url_req_space at 0x00000240694952E0, file "importlib\metadata\__init__.py", line 718>, None)

## co_names:
('value', 'name')

## bytecode:

   0: MAKE_CELL            make_condition
   2: RETURN_GENERATOR     
   4: POP_TOP              
   6: RESUME               
   8: LOAD_CONST           <code object make_condition at 0x0000024069495070, file "importlib\metadata\__init__.py", line 707>
  10: MAKE_FUNCTION        
  12: STORE_DEREF          make_condition
  14: LOAD_CLOSURE         make_condition
  16: BUILD_TUPLE          
  18: LOAD_CONST           <code object quoted_marker at 0x00000240691F5890, file "importlib\metadata\__init__.py", line 710>
  20: MAKE_FUNCTION        closure
  22: STORE_FAST           quoted_marker
  24: LOAD_CONST           <code object url_req_space at 0x00000240694952E0, file "importlib\metadata\__init__.py", line 718>
  26: MAKE_FUNCTION        
  28: STORE_FAST           url_req_space
  30: LOAD_FAST            sections
  32: GET_ITER             
  34: FOR_ITER             to 130
  36: STORE_FAST           section
  38: PUSH_NULL            
  40: LOAD_FAST            url_req_space
  42: LOAD_FAST            section
  44: LOAD_ATTR            value
  54: PRECALL              
  58: CALL                 
  68: STORE_FAST           space
  70: LOAD_FAST            section
  72: LOAD_ATTR            value
  82: LOAD_FAST            space
  84: BINARY_OP            +
  88: PUSH_NULL            
  90: LOAD_FAST            quoted_marker
  92: LOAD_FAST            section
  94: LOAD_ATTR            name
 104: PRECALL              
 108: CALL                 
 118: BINARY_OP            +
 122: YIELD_VALUE          
 124: RESUME               
 126: POP_TOP              
 128: JUMP_BACKWARD        to 34
 130: LOAD_CONST           None
 132: RETURN_VALUE         
