# Disassembly for importlib.DistributionFinder
# From module file: importlib.metadata

## co_consts:
('DistributionFinder', '\n    A MetaPathFinder capable of discovering installed distributions.\n    ', <code object Context at 0x000002406945DF20, file "importlib\metadata\__init__.py", line 736>, 'Context', <code object find_distributions at 0x000002406943BF30, file "importlib\metadata\__init__.py", line 768>, None)

## co_names:
('__name__', '__module__', '__qualname__', '__doc__', 'Context', 'abc', 'abstractmethod', 'find_distributions')

## bytecode:

   0: RESUME               
   2: LOAD_NAME            __name__
   4: STORE_NAME           __module__
   6: LOAD_CONST           'DistributionFinder'
   8: STORE_NAME           __qualname__
  10: LOAD_CONST           '\n    A MetaPathFinder capable of discovering installed distributions.\n    '
  12: STORE_NAME           __doc__
  14: PUSH_NULL            
  16: LOAD_BUILD_CLASS     
  18: LOAD_CONST           <code object Context at 0x000002406945DF20, file "importlib\metadata\__init__.py", line 736>
  20: MAKE_FUNCTION        
  22: LOAD_CONST           'Context'
  24: PRECALL              
  28: CALL                 
  38: STORE_NAME           Context
  40: LOAD_NAME            abc
  42: LOAD_ATTR            abstractmethod
  52: PUSH_NULL            
  54: LOAD_NAME            Context
  56: PRECALL              
  60: CALL                 
  70: BUILD_TUPLE          
  72: LOAD_CONST           <code object find_distributions at 0x000002406943BF30, file "importlib\metadata\__init__.py", line 768>
  74: MAKE_FUNCTION        defaults
  76: PRECALL              
  80: CALL                 
  90: STORE_NAME           find_distributions
  92: LOAD_CONST           None
  94: RETURN_VALUE         
