# Disassembly for importlib._call_with_frames_removed
# From module file: importlib._bootstrap

## co_consts:
('remove_importlib_frames in import.c will always remove sequences\n    of importlib frames that end with a call to this function\n\n    Use it instead of a normal call in places where including the importlib\n    frames introduces unwanted noise into the traceback (e.g. when executing\n    module code)\n    ',)

## co_names:
()

## bytecode:

   0: RESUME               
   2: PUSH_NULL            
   4: LOAD_FAST            f
   6: LOAD_FAST            args
   8: BUILD_MAP            
  10: LOAD_FAST            kwds
  12: DICT_MERGE           
  14: CALL_FUNCTION_EX     
  16: RETURN_VALUE         
