# Disassembly for importlib._LazyModule.__delattr__
# From module file: importlib.util

## co_consts:
('Trigger the load and then perform the deletion.', None)

## co_names:
('__getattribute__', 'delattr')

## bytecode:

   0: RESUME               
   2: LOAD_FAST            self
   4: LOAD_METHOD          __getattribute__
  26: LOAD_FAST            attr
  28: PRECALL              
  32: CALL                 
  42: POP_TOP              
  44: LOAD_GLOBAL          NULL + delattr
  56: LOAD_FAST            self
  58: LOAD_FAST            attr
  60: PRECALL              
  64: CALL                 
  74: POP_TOP              
  76: LOAD_CONST           None
  78: RETURN_VALUE         
