# Disassembly for importlib._path_join.<listcomp>
# From module file: importlib._bootstrap_external

## co_consts:
()

## co_names:
('rstrip', 'path_separators')

## bytecode:

   0: RESUME               
   2: BUILD_LIST           
   4: LOAD_FAST            .0
   6: FOR_ITER             to 68
   8: STORE_FAST           part
  10: LOAD_FAST            part
  12: POP_JUMP_BACKWARD_IF_FALSE to 6
  14: LOAD_FAST            part
  16: LOAD_METHOD          rstrip
  38: LOAD_GLOBAL          path_separators
  50: PRECALL              
  54: CALL                 
  64: LIST_APPEND          
  66: JUMP_BACKWARD        to 6
  68: RETURN_VALUE         
