# Disassembly for importlib._get_sourcefile
# From module file: importlib._bootstrap_external

## co_consts:
('Convert a bytecode file path to a source path (if possible).\n\n    This function exists purely for backwards-compatibility for\n    PyImport_ExecCodeModuleWithFilenames() in the C API.\n\n    ', 0, None, '.', -3, -1, 'py')

## co_names:
('len', 'rpartition', 'lower', 'source_from_cache', 'NotImplementedError', 'ValueError', '_path_isfile')

## bytecode:

   0: RESUME               
   2: LOAD_GLOBAL          NULL + len
  14: LOAD_FAST            bytecode_path
  16: PRECALL              
  20: CALL                 
  30: LOAD_CONST           0
  32: COMPARE_OP           ==
  38: POP_JUMP_FORWARD_IF_FALSE to 44
  40: LOAD_CONST           None
  42: RETURN_VALUE         
  44: LOAD_FAST            bytecode_path
  46: LOAD_METHOD          rpartition
  68: LOAD_CONST           '.'
  70: PRECALL              
  74: CALL                 
  84: UNPACK_SEQUENCE      
  88: STORE_FAST           rest
  90: STORE_FAST           _
  92: STORE_FAST           extension
  94: LOAD_FAST            rest
  96: POP_JUMP_FORWARD_IF_FALSE to 162
  98: LOAD_FAST            extension
 100: LOAD_METHOD          lower
 122: PRECALL              
 126: CALL                 
 136: LOAD_CONST           -3
 138: LOAD_CONST           -1
 140: BUILD_SLICE          
 142: BINARY_SUBSCR        
 152: LOAD_CONST           'py'
 154: COMPARE_OP           !=
 160: POP_JUMP_FORWARD_IF_FALSE to 166
 162: LOAD_FAST            bytecode_path
 164: RETURN_VALUE         
 166: NOP                  
 168: LOAD_GLOBAL          NULL + source_from_cache
 180: LOAD_FAST            bytecode_path
 182: PRECALL              
 186: CALL                 
 196: STORE_FAST           source_path
 198: JUMP_FORWARD         to 266
 200: PUSH_EXC_INFO        
 202: LOAD_GLOBAL          NotImplementedError
 214: LOAD_GLOBAL          ValueError
 226: BUILD_TUPLE          
 228: CHECK_EXC_MATCH      
 230: POP_JUMP_FORWARD_IF_FALSE to 258
 232: POP_TOP              
 234: LOAD_FAST            bytecode_path
 236: LOAD_CONST           None
 238: LOAD_CONST           -1
 240: BUILD_SLICE          
 242: BINARY_SUBSCR        
 252: STORE_FAST           source_path
 254: POP_EXCEPT           
 256: JUMP_FORWARD         to 266
 258: RERAISE              
 260: COPY                 
 262: POP_EXCEPT           
 264: RERAISE              
 266: LOAD_GLOBAL          NULL + _path_isfile
 278: LOAD_FAST            source_path
 280: PRECALL              
 284: CALL                 
 294: POP_JUMP_FORWARD_IF_FALSE to 300
 296: LOAD_FAST            source_path
 298: JUMP_FORWARD         to 302
 300: LOAD_FAST            bytecode_path
 302: RETURN_VALUE         
