# Disassembly for importlib.SourceLoader.path_stats
# From module file: importlib._bootstrap_external

## co_consts:
("Optional method returning a metadata dict for the specified\n        path (a str).\n\n        Possible keys:\n        - 'mtime' (mandatory) is the numeric timestamp of last source\n          code modification;\n        - 'size' (optional) is the size in bytes of the source code.\n\n        Implementing this method allows the loader to read bytecode files.\n        Raises OSError when the path cannot be handled.\n        ", 'mtime')

## co_names:
('path_mtime',)

## bytecode:

   0: RESUME               
   2: LOAD_CONST           'mtime'
   4: LOAD_FAST            self
   6: LOAD_METHOD          path_mtime
  28: LOAD_FAST            path
  30: PRECALL              
  34: CALL                 
  44: BUILD_MAP            
  46: RETURN_VALUE         
