# Disassembly for importlib._NamespacePath._find_parent_path_names
# From module file: importlib._bootstrap_external

## co_consts:
('Returns a tuple of (parent-module-name, parent-path-attr-name)', '.', '', ('sys', 'path'), '__path__')

## co_names:
('_name', 'rpartition')

## bytecode:

   0: RESUME               
   2: LOAD_FAST            self
   4: LOAD_ATTR            _name
  14: LOAD_METHOD          rpartition
  36: LOAD_CONST           '.'
  38: PRECALL              
  42: CALL                 
  52: UNPACK_SEQUENCE      
  56: STORE_FAST           parent
  58: STORE_FAST           dot
  60: STORE_FAST           me
  62: LOAD_FAST            dot
  64: LOAD_CONST           ''
  66: COMPARE_OP           ==
  72: POP_JUMP_FORWARD_IF_FALSE to 78
  74: LOAD_CONST           ('sys', 'path')
  76: RETURN_VALUE         
  78: LOAD_FAST            parent
  80: LOAD_CONST           '__path__'
  82: BUILD_TUPLE          
  84: RETURN_VALUE         
