# Disassembly for importlib.entry_points.<genexpr>
# From module file: importlib.metadata

## co_consts:
(None,)

## co_names:
('entry_points',)

## bytecode:

   0: RETURN_GENERATOR     
   2: POP_TOP              
   4: RESUME               
   6: LOAD_FAST            .0
   8: FOR_ITER             to 32
  10: STORE_FAST           dist
  12: LOAD_FAST            dist
  14: LOAD_ATTR            entry_points
  24: YIELD_VALUE          
  26: RESUME               
  28: POP_TOP              
  30: JUMP_BACKWARD        to 8
  32: LOAD_CONST           None
  34: RETURN_VALUE         
