# Disassembly for importlib._setup
# From module file: importlib._bootstrap

## co_consts:
('Setup importlib by importing needed built-in modules and injecting them\n    into the global namespace.\n\n    As sys is needed for sys.modules access and _imp is needed to load built-in\n    modules, those two modules must be explicitly passed in.\n\n    ', ('_thread', '_warnings', '_weakref'), None)

## co_names:
('_imp', 'sys', 'type', 'modules', 'items', 'isinstance', 'builtin_module_names', 'BuiltinImporter', 'is_frozen', 'FrozenImporter', '_spec_from_module', '_init_module_attrs', '_fix_up_module', '__name__', '_builtin_from_name', 'setattr')

## bytecode:

   0: RESUME               
   2: LOAD_FAST            _imp_module
   4: STORE_GLOBAL         _imp
   6: LOAD_FAST            sys_module
   8: STORE_GLOBAL         sys
  10: LOAD_GLOBAL          NULL + type
  22: LOAD_GLOBAL          sys
  34: PRECALL              
  38: CALL                 
  48: STORE_FAST           module_type
  50: LOAD_GLOBAL          sys
  62: LOAD_ATTR            modules
  72: LOAD_METHOD          items
  94: PRECALL              
  98: CALL                 
 108: GET_ITER             
 110: FOR_ITER             to 392
 112: UNPACK_SEQUENCE      
 116: STORE_FAST           name
 118: STORE_FAST           module
 120: LOAD_GLOBAL          NULL + isinstance
 132: LOAD_FAST            module
 134: LOAD_FAST            module_type
 136: PRECALL              
 140: CALL                 
 150: POP_JUMP_FORWARD_IF_FALSE to 390
 152: LOAD_FAST            name
 154: LOAD_GLOBAL          sys
 166: LOAD_ATTR            builtin_module_names
 176: CONTAINS_OP          
 178: POP_JUMP_FORWARD_IF_FALSE to 196
 180: LOAD_GLOBAL          BuiltinImporter
 192: STORE_FAST           loader
 194: JUMP_FORWARD         to 266
 196: LOAD_GLOBAL          _imp
 208: LOAD_METHOD          is_frozen
 230: LOAD_FAST            name
 232: PRECALL              
 236: CALL                 
 246: POP_JUMP_FORWARD_IF_FALSE to 264
 248: LOAD_GLOBAL          FrozenImporter
 260: STORE_FAST           loader
 262: JUMP_FORWARD         to 266
 264: JUMP_BACKWARD        to 110
 266: LOAD_GLOBAL          NULL + _spec_from_module
 278: LOAD_FAST            module
 280: LOAD_FAST            loader
 282: PRECALL              
 286: CALL                 
 296: STORE_FAST           spec
 298: LOAD_GLOBAL          NULL + _init_module_attrs
 310: LOAD_FAST            spec
 312: LOAD_FAST            module
 314: PRECALL              
 318: CALL                 
 328: POP_TOP              
 330: LOAD_FAST            loader
 332: LOAD_GLOBAL          FrozenImporter
 344: IS_OP                
 346: POP_JUMP_FORWARD_IF_FALSE to 390
 348: LOAD_FAST            loader
 350: LOAD_METHOD          _fix_up_module
 372: LOAD_FAST            module
 374: PRECALL              
 378: CALL                 
 388: POP_TOP              
 390: JUMP_BACKWARD        to 110
 392: LOAD_GLOBAL          sys
 404: LOAD_ATTR            modules
 414: LOAD_GLOBAL          __name__
 426: BINARY_SUBSCR        
 436: STORE_FAST           self_module
 438: LOAD_CONST           ('_thread', '_warnings', '_weakref')
 440: GET_ITER             
 442: FOR_ITER             to 578
 444: STORE_FAST           builtin_name
 446: LOAD_FAST            builtin_name
 448: LOAD_GLOBAL          sys
 460: LOAD_ATTR            modules
 470: CONTAINS_OP          
 472: POP_JUMP_FORWARD_IF_FALSE to 506
 474: LOAD_GLOBAL          NULL + _builtin_from_name
 486: LOAD_FAST            builtin_name
 488: PRECALL              
 492: CALL                 
 502: STORE_FAST           builtin_module
 504: JUMP_FORWARD         to 542
 506: LOAD_GLOBAL          sys
 518: LOAD_ATTR            modules
 528: LOAD_FAST            builtin_name
 530: BINARY_SUBSCR        
 540: STORE_FAST           builtin_module
 542: LOAD_GLOBAL          NULL + setattr
 554: LOAD_FAST            self_module
 556: LOAD_FAST            builtin_name
 558: LOAD_FAST            builtin_module
 560: PRECALL              
 564: CALL                 
 574: POP_TOP              
 576: JUMP_BACKWARD        to 442
 578: LOAD_CONST           None
 580: RETURN_VALUE         
