# Disassembly for importlib.PathFinder.find_distributions
# From module file: importlib._bootstrap_external

## co_consts:
('\n        Find distributions.\n\n        Return an iterable of all Distribution instances capable of\n        loading the metadata for packages matching ``context.name``\n        (or all names if ``None`` indicated) along the paths in the list\n        of directories ``context.path``.\n        ', 0, ('MetadataPathFinder',))

## co_names:
('importlib.metadata', 'MetadataPathFinder', 'find_distributions')

## bytecode:

   0: RESUME               
   2: LOAD_CONST           0
   4: LOAD_CONST           ('MetadataPathFinder',)
   6: IMPORT_NAME          importlib.metadata
   8: IMPORT_FROM          MetadataPathFinder
  10: STORE_FAST           MetadataPathFinder
  12: POP_TOP              
  14: PUSH_NULL            
  16: LOAD_FAST            MetadataPathFinder
  18: LOAD_ATTR            find_distributions
  28: LOAD_FAST            args
  30: BUILD_MAP            
  32: LOAD_FAST            kwargs
  34: DICT_MERGE           
  36: CALL_FUNCTION_EX     
  38: RETURN_VALUE         
