# Disassembly for importlib.ExtensionFileLoader.exec_module
# From module file: importlib._bootstrap_external

## co_consts:
('Initialize an extension module', 'extension module {!r} executed from {!r}', None)

## co_names:
('_bootstrap', '_call_with_frames_removed', '_imp', 'exec_dynamic', '_verbose_message', 'name', 'path')

## bytecode:

   0: RESUME               
   2: LOAD_GLOBAL          _bootstrap
  14: LOAD_METHOD          _call_with_frames_removed
  36: LOAD_GLOBAL          _imp
  48: LOAD_ATTR            exec_dynamic
  58: LOAD_FAST            module
  60: PRECALL              
  64: CALL                 
  74: POP_TOP              
  76: LOAD_GLOBAL          _bootstrap
  88: LOAD_METHOD          _verbose_message
 110: LOAD_CONST           'extension module {!r} executed from {!r}'
 112: LOAD_FAST            self
 114: LOAD_ATTR            name
 124: LOAD_FAST            self
 126: LOAD_ATTR            path
 136: PRECALL              
 140: CALL                 
 150: POP_TOP              
 152: LOAD_CONST           None
 154: RETURN_VALUE         
