# Disassembly for importlib._requires_builtin
# From module file: importlib._bootstrap

## co_consts:
('Decorator to verify the named module is built-in.', <code object _requires_builtin_wrapper at 0x00000240693AB5F0, file "importlib\_bootstrap.py", line 254>)

## co_names:
('_wrap',)

## bytecode:

   0: MAKE_CELL            fxn
   2: RESUME               
   4: LOAD_CLOSURE         fxn
   6: BUILD_TUPLE          
   8: LOAD_CONST           <code object _requires_builtin_wrapper at 0x00000240693AB5F0, file "importlib\_bootstrap.py", line 254>
  10: MAKE_FUNCTION        closure
  12: STORE_FAST           _requires_builtin_wrapper
  14: LOAD_GLOBAL          NULL + _wrap
  26: LOAD_FAST            _requires_builtin_wrapper
  28: LOAD_DEREF           fxn
  30: PRECALL              
  34: CALL                 
  44: POP_TOP              
  46: LOAD_FAST            _requires_builtin_wrapper
  48: RETURN_VALUE         
