# Disassembly for importlib.FileLoader.load_module
# From module file: importlib._bootstrap_external

## co_consts:
('Load a module from a file.\n\n        This method is deprecated.  Use exec_module() instead.\n\n        ',)

## co_names:
('super', 'FileLoader', 'load_module')

## bytecode:

   0: COPY_FREE_VARS       
   2: RESUME               
   4: LOAD_GLOBAL          NULL + super
  16: LOAD_GLOBAL          FileLoader
  28: LOAD_FAST            self
  30: PRECALL              
  34: CALL                 
  44: LOAD_METHOD          load_module
  66: LOAD_FAST            fullname
  68: PRECALL              
  72: CALL                 
  82: RETURN_VALUE         
