# Disassembly for importlib.LazyLoader.__check_eager_loader
# From module file: importlib.util

## co_consts:
(None, 'exec_module', 'loader must define exec_module()')

## co_names:
('hasattr', 'TypeError')

## bytecode:

   0: RESUME               
   2: LOAD_GLOBAL          NULL + hasattr
  14: LOAD_FAST            loader
  16: LOAD_CONST           'exec_module'
  18: PRECALL              
  22: CALL                 
  32: POP_JUMP_FORWARD_IF_TRUE to 64
  34: LOAD_GLOBAL          NULL + TypeError
  46: LOAD_CONST           'loader must define exec_module()'
  48: PRECALL              
  52: CALL                 
  62: RAISE_VARARGS        
  64: LOAD_CONST           None
  66: RETURN_VALUE         
