# Disassembly for importlib.ModuleSpec.__eq__
# From module file: importlib._bootstrap

## co_consts:
(None,)

## co_names:
('submodule_search_locations', 'name', 'loader', 'origin', 'cached', 'has_location', 'AttributeError', 'NotImplemented')

## bytecode:

   0: RESUME               
   2: LOAD_FAST            self
   4: LOAD_ATTR            submodule_search_locations
  14: STORE_FAST           smsl
  16: NOP                  
  18: LOAD_FAST            self
  20: LOAD_ATTR            name
  30: LOAD_FAST            other
  32: LOAD_ATTR            name
  42: COMPARE_OP           ==
  48: JUMP_IF_FALSE_OR_POP to 198
  50: LOAD_FAST            self
  52: LOAD_ATTR            loader
  62: LOAD_FAST            other
  64: LOAD_ATTR            loader
  74: COMPARE_OP           ==
  80: JUMP_IF_FALSE_OR_POP to 198
  82: LOAD_FAST            self
  84: LOAD_ATTR            origin
  94: LOAD_FAST            other
  96: LOAD_ATTR            origin
 106: COMPARE_OP           ==
 112: JUMP_IF_FALSE_OR_POP to 198
 114: LOAD_FAST            smsl
 116: LOAD_FAST            other
 118: LOAD_ATTR            submodule_search_locations
 128: COMPARE_OP           ==
 134: JUMP_IF_FALSE_OR_POP to 198
 136: LOAD_FAST            self
 138: LOAD_ATTR            cached
 148: LOAD_FAST            other
 150: LOAD_ATTR            cached
 160: COMPARE_OP           ==
 166: JUMP_IF_FALSE_OR_POP to 198
 168: LOAD_FAST            self
 170: LOAD_ATTR            has_location
 180: LOAD_FAST            other
 182: LOAD_ATTR            has_location
 192: COMPARE_OP           ==
 198: RETURN_VALUE         
 200: PUSH_EXC_INFO        
 202: LOAD_GLOBAL          AttributeError
 214: CHECK_EXC_MATCH      
 216: POP_JUMP_FORWARD_IF_FALSE to 238
 218: POP_TOP              
 220: LOAD_GLOBAL          NotImplemented
 232: SWAP                 
 234: POP_EXCEPT           
 236: RETURN_VALUE         
 238: RERAISE              
 240: COPY                 
 242: POP_EXCEPT           
 244: RERAISE              
