# Disassembly for importlib.Distribution._discover_resolvers.<genexpr>
# From module file: importlib.metadata

## co_consts:
('find_distributions', None)

## co_names:
('getattr',)

## bytecode:

   0: RETURN_GENERATOR     
   2: POP_TOP              
   4: RESUME               
   6: LOAD_FAST            .0
   8: FOR_ITER             to 52
  10: STORE_FAST           finder
  12: LOAD_GLOBAL          NULL + getattr
  24: LOAD_FAST            finder
  26: LOAD_CONST           'find_distributions'
  28: LOAD_CONST           None
  30: PRECALL              
  34: CALL                 
  44: YIELD_VALUE          
  46: RESUME               
  48: POP_TOP              
  50: JUMP_BACKWARD        to 8
  52: LOAD_CONST           None
  54: RETURN_VALUE         
