# Disassembly for importlib._module_repr_from_spec
# From module file: importlib._bootstrap

## co_consts:
('Return the repr to use for the module.', None, '?', '<module {!r}>', '<module {!r} ({!r})>', '<module {!r} from {!r}>', '<module {!r} ({})>')

## co_names:
('name', 'origin', 'loader', 'format', 'has_location')

## bytecode:

   0: RESUME               
   2: LOAD_FAST            spec
   4: LOAD_ATTR            name
  14: POP_JUMP_FORWARD_IF_NOT_NONE to 20
  16: LOAD_CONST           '?'
  18: JUMP_FORWARD         to 32
  20: LOAD_FAST            spec
  22: LOAD_ATTR            name
  32: STORE_FAST           name
  34: LOAD_FAST            spec
  36: LOAD_ATTR            origin
  46: POP_JUMP_FORWARD_IF_NOT_NONE to 158
  48: LOAD_FAST            spec
  50: LOAD_ATTR            loader
  60: POP_JUMP_FORWARD_IF_NOT_NONE to 104
  62: LOAD_CONST           '<module {!r}>'
  64: LOAD_METHOD          format
  86: LOAD_FAST            name
  88: PRECALL              
  92: CALL                 
 102: RETURN_VALUE         
 104: LOAD_CONST           '<module {!r} ({!r})>'
 106: LOAD_METHOD          format
 128: LOAD_FAST            name
 130: LOAD_FAST            spec
 132: LOAD_ATTR            loader
 142: PRECALL              
 146: CALL                 
 156: RETURN_VALUE         
 158: LOAD_FAST            spec
 160: LOAD_ATTR            has_location
 170: POP_JUMP_FORWARD_IF_FALSE to 226
 172: LOAD_CONST           '<module {!r} from {!r}>'
 174: LOAD_METHOD          format
 196: LOAD_FAST            name
 198: LOAD_FAST            spec
 200: LOAD_ATTR            origin
 210: PRECALL              
 214: CALL                 
 224: RETURN_VALUE         
 226: LOAD_CONST           '<module {!r} ({})>'
 228: LOAD_METHOD          format
 250: LOAD_FAST            spec
 252: LOAD_ATTR            name
 262: LOAD_FAST            spec
 264: LOAD_ATTR            origin
 274: PRECALL              
 278: CALL                 
 288: RETURN_VALUE         
