# Disassembly for importlib.EntryPoint
# From module file: importlib.metadata

## co_consts:
('EntryPoint', "An entry point as defined by Python packaging conventions.\n\n    See `the packaging docs on entry points\n    <https://packaging.python.org/specifications/entry-points/>`_\n    for more information.\n\n    >>> ep = EntryPoint(\n    ...     name=None, group=None, value='package.module:attr [extra1, extra2]')\n    >>> ep.module\n    'package.module'\n    >>> ep.attr\n    'attr'\n    >>> ep.extras\n    ['extra1', 'extra2']\n    ", '(?P<module>[\\w.]+)\\s*(:\\s*(?P<attr>[\\w.]+)\\s*)?((?P<extras>\\[.*\\])\\s*)?$', 'name', 'value', 'group', None, 'Distribution', 'dist', <code object __init__ at 0x000002406944A010, file "importlib\metadata\__init__.py", line 193>, <code object load at 0x0000024069365F30, file "importlib\metadata\__init__.py", line 196>, <code object module at 0x00000240693D35A0, file "importlib\metadata\__init__.py", line 206>, <code object attr at 0x00000240693D2760, file "importlib\metadata\__init__.py", line 211>, <code object extras at 0x00000240691F23A0, file "importlib\metadata\__init__.py", line 216>, <code object _for at 0x000002406944AEF0, file "importlib\metadata\__init__.py", line 221>, <code object __iter__ at 0x000002406941AC10, file "importlib\metadata\__init__.py", line 225>, <code object matches at 0x000002406922D530, file "importlib\metadata\__init__.py", line 236>, <code object _key at 0x000002406945E6A0, file "importlib\metadata\__init__.py", line 259>, <code object __lt__ at 0x000002406944A230, file "importlib\metadata\__init__.py", line 262>, <code object __eq__ at 0x000002406944B000, file "importlib\metadata\__init__.py", line 265>, <code object __setattr__ at 0x0000024069465A70, file "importlib\metadata\__init__.py", line 268>, <code object __repr__ at 0x000002406945E880, file "importlib\metadata\__init__.py", line 271>, <code object __hash__ at 0x00000240693EA530, file "importlib\metadata\__init__.py", line 277>)

## co_names:
('__name__', '__module__', '__qualname__', '__doc__', 're', 'compile', 'pattern', 'str', '__annotations__', 'dist', 'Optional', '__init__', 'load', 'property', 'module', 'attr', 'extras', '_for', '__iter__', 'matches', '_key', '__lt__', '__eq__', '__setattr__', '__repr__', '__hash__')

## bytecode:

   0: RESUME               
   2: LOAD_NAME            __name__
   4: STORE_NAME           __module__
   6: LOAD_CONST           'EntryPoint'
   8: STORE_NAME           __qualname__
  10: SETUP_ANNOTATIONS    
  12: LOAD_CONST           "An entry point as defined by Python packaging conventions.\n\n    See `the packaging docs on entry points\n    <https://packaging.python.org/specifications/entry-points/>`_\n    for more information.\n\n    >>> ep = EntryPoint(\n    ...     name=None, group=None, value='package.module:attr [extra1, extra2]')\n    >>> ep.module\n    'package.module'\n    >>> ep.attr\n    'attr'\n    >>> ep.extras\n    ['extra1', 'extra2']\n    "
  14: STORE_NAME           __doc__
  16: PUSH_NULL            
  18: LOAD_NAME            re
  20: LOAD_ATTR            compile
  30: LOAD_CONST           '(?P<module>[\\w.]+)\\s*(:\\s*(?P<attr>[\\w.]+)\\s*)?((?P<extras>\\[.*\\])\\s*)?$'
  32: PRECALL              
  36: CALL                 
  46: STORE_NAME           pattern
  48: NOP                  
  50: LOAD_NAME            str
  52: LOAD_NAME            __annotations__
  54: LOAD_CONST           'name'
  56: STORE_SUBSCR         
  60: LOAD_NAME            str
  62: LOAD_NAME            __annotations__
  64: LOAD_CONST           'value'
  66: STORE_SUBSCR         
  70: LOAD_NAME            str
  72: LOAD_NAME            __annotations__
  74: LOAD_CONST           'group'
  76: STORE_SUBSCR         
  80: LOAD_CONST           None
  82: STORE_NAME           dist
  84: LOAD_NAME            Optional
  86: LOAD_CONST           'Distribution'
  88: BINARY_SUBSCR        
  98: LOAD_NAME            __annotations__
 100: LOAD_CONST           'dist'
 102: STORE_SUBSCR         
 106: LOAD_CONST           <code object __init__ at 0x000002406944A010, file "importlib\metadata\__init__.py", line 193>
 108: MAKE_FUNCTION        
 110: STORE_NAME           __init__
 112: LOAD_CONST           <code object load at 0x0000024069365F30, file "importlib\metadata\__init__.py", line 196>
 114: MAKE_FUNCTION        
 116: STORE_NAME           load
 118: LOAD_NAME            property
 120: LOAD_CONST           <code object module at 0x00000240693D35A0, file "importlib\metadata\__init__.py", line 206>
 122: MAKE_FUNCTION        
 124: PRECALL              
 128: CALL                 
 138: STORE_NAME           module
 140: LOAD_NAME            property
 142: LOAD_CONST           <code object attr at 0x00000240693D2760, file "importlib\metadata\__init__.py", line 211>
 144: MAKE_FUNCTION        
 146: PRECALL              
 150: CALL                 
 160: STORE_NAME           attr
 162: LOAD_NAME            property
 164: LOAD_CONST           <code object extras at 0x00000240691F23A0, file "importlib\metadata\__init__.py", line 216>
 166: MAKE_FUNCTION        
 168: PRECALL              
 172: CALL                 
 182: STORE_NAME           extras
 184: LOAD_CONST           <code object _for at 0x000002406944AEF0, file "importlib\metadata\__init__.py", line 221>
 186: MAKE_FUNCTION        
 188: STORE_NAME           _for
 190: LOAD_CONST           <code object __iter__ at 0x000002406941AC10, file "importlib\metadata\__init__.py", line 225>
 192: MAKE_FUNCTION        
 194: STORE_NAME           __iter__
 196: LOAD_CONST           <code object matches at 0x000002406922D530, file "importlib\metadata\__init__.py", line 236>
 198: MAKE_FUNCTION        
 200: STORE_NAME           matches
 202: LOAD_CONST           <code object _key at 0x000002406945E6A0, file "importlib\metadata\__init__.py", line 259>
 204: MAKE_FUNCTION        
 206: STORE_NAME           _key
 208: LOAD_CONST           <code object __lt__ at 0x000002406944A230, file "importlib\metadata\__init__.py", line 262>
 210: MAKE_FUNCTION        
 212: STORE_NAME           __lt__
 214: LOAD_CONST           <code object __eq__ at 0x000002406944B000, file "importlib\metadata\__init__.py", line 265>
 216: MAKE_FUNCTION        
 218: STORE_NAME           __eq__
 220: LOAD_CONST           <code object __setattr__ at 0x0000024069465A70, file "importlib\metadata\__init__.py", line 268>
 222: MAKE_FUNCTION        
 224: STORE_NAME           __setattr__
 226: LOAD_CONST           <code object __repr__ at 0x000002406945E880, file "importlib\metadata\__init__.py", line 271>
 228: MAKE_FUNCTION        
 230: STORE_NAME           __repr__
 232: LOAD_CONST           <code object __hash__ at 0x00000240693EA530, file "importlib\metadata\__init__.py", line 277>
 234: MAKE_FUNCTION        
 236: STORE_NAME           __hash__
 238: LOAD_CONST           None
 240: RETURN_VALUE         
