# Disassembly for importlib.PathFinder.find_spec
# From module file: importlib._bootstrap_external

## co_consts:
("Try to find a spec for 'fullname' on sys.path or 'path'.\n\n        The search is based on sys.path_hooks and sys.path_importer_cache.\n        ", None)

## co_names:
('sys', 'path', '_get_spec', 'loader', 'submodule_search_locations', 'origin', '_NamespacePath')

## bytecode:

   0: RESUME               
   2: LOAD_FAST            path
   4: POP_JUMP_FORWARD_IF_NOT_NONE to 30
   6: LOAD_GLOBAL          sys
  18: LOAD_ATTR            path
  28: STORE_FAST           path
  30: LOAD_FAST            cls
  32: LOAD_METHOD          _get_spec
  54: LOAD_FAST            fullname
  56: LOAD_FAST            path
  58: LOAD_FAST            target
  60: PRECALL              
  64: CALL                 
  74: STORE_FAST           spec
  76: LOAD_FAST            spec
  78: POP_JUMP_FORWARD_IF_NOT_NONE to 84
  80: LOAD_CONST           None
  82: RETURN_VALUE         
  84: LOAD_FAST            spec
  86: LOAD_ATTR            loader
  96: POP_JUMP_FORWARD_IF_NOT_NONE to 192
  98: LOAD_FAST            spec
 100: LOAD_ATTR            submodule_search_locations
 110: STORE_FAST           namespace_path
 112: LOAD_FAST            namespace_path
 114: POP_JUMP_FORWARD_IF_FALSE to 188
 116: LOAD_CONST           None
 118: LOAD_FAST            spec
 120: STORE_ATTR           origin
 130: LOAD_GLOBAL          NULL + _NamespacePath
 142: LOAD_FAST            fullname
 144: LOAD_FAST            namespace_path
 146: LOAD_FAST            cls
 148: LOAD_ATTR            _get_spec
 158: PRECALL              
 162: CALL                 
 172: LOAD_FAST            spec
 174: STORE_ATTR           submodule_search_locations
 184: LOAD_FAST            spec
 186: RETURN_VALUE         
 188: LOAD_CONST           None
 190: RETURN_VALUE         
 192: LOAD_FAST            spec
 194: RETURN_VALUE         
