# Disassembly for importlib.SelectableGroups.load.<genexpr>
# From module file: importlib.metadata

## co_consts:
(None,)

## co_names:
('EntryPoints',)

## bytecode:

   0: RETURN_GENERATOR     
   2: POP_TOP              
   4: RESUME               
   6: LOAD_FAST            .0
   8: FOR_ITER             to 58
  10: UNPACK_SEQUENCE      
  14: STORE_FAST           group
  16: STORE_FAST           eps
  18: LOAD_FAST            group
  20: LOAD_GLOBAL          NULL + EntryPoints
  32: LOAD_FAST            eps
  34: PRECALL              
  38: CALL                 
  48: BUILD_TUPLE          
  50: YIELD_VALUE          
  52: RESUME               
  54: POP_TOP              
  56: JUMP_BACKWARD        to 8
  58: LOAD_CONST           None
  60: RETURN_VALUE         
