# Disassembly for importlib._calc___package__
# From module file: importlib._bootstrap

## co_consts:
('Calculate what __package__ should be.\n\n    __package__ is not guaranteed to be defined or could be set to None\n    to represent that its proper value is unknown.\n\n    ', '__package__', '__spec__', None, '__package__ != __spec__.parent (', ' != ', ')', 3, ('stacklevel',), "can't resolve package from __spec__ or __package__, falling back on __name__ and __path__", '__name__', '__path__', '.', 0)

## co_names:
('get', 'parent', '_warnings', 'warn', 'ImportWarning', 'rpartition')

## bytecode:

   0: RESUME               
   2: LOAD_FAST            globals
   4: LOAD_METHOD          get
  26: LOAD_CONST           '__package__'
  28: PRECALL              
  32: CALL                 
  42: STORE_FAST           package
  44: LOAD_FAST            globals
  46: LOAD_METHOD          get
  68: LOAD_CONST           '__spec__'
  70: PRECALL              
  74: CALL                 
  84: STORE_FAST           spec
  86: LOAD_FAST            package
  88: POP_JUMP_FORWARD_IF_NONE to 212
  90: LOAD_FAST            spec
  92: POP_JUMP_FORWARD_IF_NONE to 208
  94: LOAD_FAST            package
  96: LOAD_FAST            spec
  98: LOAD_ATTR            parent
 108: COMPARE_OP           !=
 114: POP_JUMP_FORWARD_IF_FALSE to 208
 116: LOAD_GLOBAL          _warnings
 128: LOAD_METHOD          warn
 150: LOAD_CONST           '__package__ != __spec__.parent ('
 152: LOAD_FAST            package
 154: FORMAT_VALUE         repr
 156: LOAD_CONST           ' != '
 158: LOAD_FAST            spec
 160: LOAD_ATTR            parent
 170: FORMAT_VALUE         repr
 172: LOAD_CONST           ')'
 174: BUILD_STRING         
 176: LOAD_GLOBAL          ImportWarning
 188: LOAD_CONST           3
 190: KW_NAMES             
 192: PRECALL              
 196: CALL                 
 206: POP_TOP              
 208: LOAD_FAST            package
 210: RETURN_VALUE         
 212: LOAD_FAST            spec
 214: POP_JUMP_FORWARD_IF_NONE to 230
 216: LOAD_FAST            spec
 218: LOAD_ATTR            parent
 228: RETURN_VALUE         
 230: LOAD_GLOBAL          _warnings
 242: LOAD_METHOD          warn
 264: LOAD_CONST           "can't resolve package from __spec__ or __package__, falling back on __name__ and __path__"
 266: LOAD_GLOBAL          ImportWarning
 278: LOAD_CONST           3
 280: KW_NAMES             
 282: PRECALL              
 286: CALL                 
 296: POP_TOP              
 298: LOAD_FAST            globals
 300: LOAD_CONST           '__name__'
 302: BINARY_SUBSCR        
 312: STORE_FAST           package
 314: LOAD_CONST           '__path__'
 316: LOAD_FAST            globals
 318: CONTAINS_OP          
 320: POP_JUMP_FORWARD_IF_FALSE to 376
 322: LOAD_FAST            package
 324: LOAD_METHOD          rpartition
 346: LOAD_CONST           '.'
 348: PRECALL              
 352: CALL                 
 362: LOAD_CONST           0
 364: BINARY_SUBSCR        
 374: STORE_FAST           package
 376: LOAD_FAST            package
 378: RETURN_VALUE         
