# Disassembly for importlib.Distribution.at
# From module file: importlib.metadata

## co_consts:
('Return a Distribution for the indicated metadata path\n\n        :param path: a string or path-like object\n        :return: a concrete Distribution instance for the path\n        ',)

## co_names:
('PathDistribution', 'pathlib', 'Path')

## bytecode:

   0: RESUME               
   2: LOAD_GLOBAL          NULL + PathDistribution
  14: LOAD_GLOBAL          NULL + pathlib
  26: LOAD_ATTR            Path
  36: LOAD_FAST            path
  38: PRECALL              
  42: CALL                 
  52: PRECALL              
  56: CALL                 
  66: RETURN_VALUE         
