# Disassembly for importlib.MetadataPathFinder._search_paths
# From module file: importlib.metadata

## co_consts:
('Find metadata directories in paths heuristically.', <code object <genexpr> at 0x00000240693EB530, file "importlib\metadata\__init__.py", line 914>)

## co_names:
('Prepared', 'itertools', 'chain', 'from_iterable', 'map', 'FastPath')

## bytecode:

   0: MAKE_CELL            prepared
   2: RESUME               
   4: LOAD_GLOBAL          NULL + Prepared
  16: LOAD_FAST            name
  18: PRECALL              
  22: CALL                 
  32: STORE_DEREF          prepared
  34: LOAD_GLOBAL          itertools
  46: LOAD_ATTR            chain
  56: LOAD_METHOD          from_iterable
  78: LOAD_CLOSURE         prepared
  80: BUILD_TUPLE          
  82: LOAD_CONST           <code object <genexpr> at 0x00000240693EB530, file "importlib\metadata\__init__.py", line 914>
  84: MAKE_FUNCTION        closure
  86: LOAD_GLOBAL          NULL + map
  98: LOAD_GLOBAL          FastPath
 110: LOAD_FAST            paths
 112: PRECALL              
 116: CALL                 
 126: GET_ITER             
 128: PRECALL              
 132: CALL                 
 142: PRECALL              
 146: CALL                 
 156: RETURN_VALUE         
