# Disassembly for importlib._sanity_check
# From module file: importlib._bootstrap

## co_consts:
('Verify arguments are "sane".', 'module name must be str, not {}', 0, 'level must be >= 0', '__package__ not set to a string', 'attempted relative import with no known parent package', 'Empty module name', None)

## co_names:
('isinstance', 'str', 'TypeError', 'format', 'type', 'ValueError', 'ImportError')

## bytecode:

   0: RESUME               
   2: LOAD_GLOBAL          NULL + isinstance
  14: LOAD_FAST            name
  16: LOAD_GLOBAL          str
  28: PRECALL              
  32: CALL                 
  42: POP_JUMP_FORWARD_IF_TRUE to 138
  44: LOAD_GLOBAL          NULL + TypeError
  56: LOAD_CONST           'module name must be str, not {}'
  58: LOAD_METHOD          format
  80: LOAD_GLOBAL          NULL + type
  92: LOAD_FAST            name
  94: PRECALL              
  98: CALL                 
 108: PRECALL              
 112: CALL                 
 122: PRECALL              
 126: CALL                 
 136: RAISE_VARARGS        
 138: LOAD_FAST            level
 140: LOAD_CONST           0
 142: COMPARE_OP           <
 148: POP_JUMP_FORWARD_IF_FALSE to 180
 150: LOAD_GLOBAL          NULL + ValueError
 162: LOAD_CONST           'level must be >= 0'
 164: PRECALL              
 168: CALL                 
 178: RAISE_VARARGS        
 180: LOAD_FAST            level
 182: LOAD_CONST           0
 184: COMPARE_OP           >
 190: POP_JUMP_FORWARD_IF_FALSE to 298
 192: LOAD_GLOBAL          NULL + isinstance
 204: LOAD_FAST            package
 206: LOAD_GLOBAL          str
 218: PRECALL              
 222: CALL                 
 232: POP_JUMP_FORWARD_IF_TRUE to 264
 234: LOAD_GLOBAL          NULL + TypeError
 246: LOAD_CONST           '__package__ not set to a string'
 248: PRECALL              
 252: CALL                 
 262: RAISE_VARARGS        
 264: LOAD_FAST            package
 266: POP_JUMP_FORWARD_IF_TRUE to 298
 268: LOAD_GLOBAL          NULL + ImportError
 280: LOAD_CONST           'attempted relative import with no known parent package'
 282: PRECALL              
 286: CALL                 
 296: RAISE_VARARGS        
 298: LOAD_FAST            name
 300: POP_JUMP_FORWARD_IF_TRUE to 344
 302: LOAD_FAST            level
 304: LOAD_CONST           0
 306: COMPARE_OP           ==
 312: POP_JUMP_FORWARD_IF_FALSE to 348
 314: LOAD_GLOBAL          NULL + ValueError
 326: LOAD_CONST           'Empty module name'
 328: PRECALL              
 332: CALL                 
 342: RAISE_VARARGS        
 344: LOAD_CONST           None
 346: RETURN_VALUE         
 348: LOAD_CONST           None
 350: RETURN_VALUE         
