# Disassembly for importlib._load_module_shim
# From module file: importlib._bootstrap

## co_consts:
('Load the specified module into sys.modules and return it.\n\n    This method is deprecated.  Use loader.exec_module() instead.\n\n    ', 'the load_module() method is deprecated and slated for removal in Python 3.12; use exec_module() instead')

## co_names:
('_warnings', 'warn', 'DeprecationWarning', 'spec_from_loader', 'sys', 'modules', '_exec', '_load')

## bytecode:

   0: RESUME               
   2: LOAD_CONST           'the load_module() method is deprecated and slated for removal in Python 3.12; use exec_module() instead'
   4: STORE_FAST           msg
   6: LOAD_GLOBAL          _warnings
  18: LOAD_METHOD          warn
  40: LOAD_FAST            msg
  42: LOAD_GLOBAL          DeprecationWarning
  54: PRECALL              
  58: CALL                 
  68: POP_TOP              
  70: LOAD_GLOBAL          NULL + spec_from_loader
  82: LOAD_FAST            fullname
  84: LOAD_FAST            self
  86: PRECALL              
  90: CALL                 
 100: STORE_FAST           spec
 102: LOAD_FAST            fullname
 104: LOAD_GLOBAL          sys
 116: LOAD_ATTR            modules
 126: CONTAINS_OP          
 128: POP_JUMP_FORWARD_IF_FALSE to 234
 130: LOAD_GLOBAL          sys
 142: LOAD_ATTR            modules
 152: LOAD_FAST            fullname
 154: BINARY_SUBSCR        
 164: STORE_FAST           module
 166: LOAD_GLOBAL          NULL + _exec
 178: LOAD_FAST            spec
 180: LOAD_FAST            module
 182: PRECALL              
 186: CALL                 
 196: POP_TOP              
 198: LOAD_GLOBAL          sys
 210: LOAD_ATTR            modules
 220: LOAD_FAST            fullname
 222: BINARY_SUBSCR        
 232: RETURN_VALUE         
 234: LOAD_GLOBAL          NULL + _load
 246: LOAD_FAST            spec
 248: PRECALL              
 252: CALL                 
 262: RETURN_VALUE         
