# Disassembly for importlib.SourceFileLoader._cache_bytecode
# From module file: importlib._bootstrap_external

## co_consts:
(None, ('_mode',))

## co_names:
('_calc_mode', 'set_data')

## bytecode:

   0: RESUME               
   2: LOAD_GLOBAL          NULL + _calc_mode
  14: LOAD_FAST            source_path
  16: PRECALL              
  20: CALL                 
  30: STORE_FAST           mode
  32: LOAD_FAST            self
  34: LOAD_METHOD          set_data
  56: LOAD_FAST            bytecode_path
  58: LOAD_FAST            data
  60: LOAD_FAST            mode
  62: KW_NAMES             
  64: PRECALL              
  68: CALL                 
  78: RETURN_VALUE         
