# Disassembly for importlib.BuiltinImporter.find_module
# From module file: importlib._bootstrap

## co_consts:
("Find the built-in module.\n\n        If 'path' is ever specified then the search is considered a failure.\n\n        This method is deprecated.  Use find_spec() instead.\n\n        ", 'BuiltinImporter.find_module() is deprecated and slated for removal in Python 3.12; use find_spec() instead', None)

## co_names:
('_warnings', 'warn', 'DeprecationWarning', 'find_spec', 'loader')

## bytecode:

   0: RESUME               
   2: LOAD_GLOBAL          _warnings
  14: LOAD_METHOD          warn
  36: LOAD_CONST           'BuiltinImporter.find_module() is deprecated and slated for removal in Python 3.12; use find_spec() instead'
  38: LOAD_GLOBAL          DeprecationWarning
  50: PRECALL              
  54: CALL                 
  64: POP_TOP              
  66: LOAD_FAST            cls
  68: LOAD_METHOD          find_spec
  90: LOAD_FAST            fullname
  92: LOAD_FAST            path
  94: PRECALL              
  98: CALL                 
 108: STORE_FAST           spec
 110: LOAD_FAST            spec
 112: POP_JUMP_FORWARD_IF_NONE to 128
 114: LOAD_FAST            spec
 116: LOAD_ATTR            loader
 126: JUMP_FORWARD         to 130
 128: LOAD_CONST           None
 130: RETURN_VALUE         
