# Disassembly for importlib.Prepared.legacy_normalize
# From module file: importlib.metadata

## co_consts:
('\n        Normalize the package name as found in the convention in\n        older packaging tools versions and specs.\n        ', '-', '_')

## co_names:
('lower', 'replace')

## bytecode:

   0: RESUME               
   2: LOAD_FAST            name
   4: LOAD_METHOD          lower
  26: PRECALL              
  30: CALL                 
  40: LOAD_METHOD          replace
  62: LOAD_CONST           '-'
  64: LOAD_CONST           '_'
  66: PRECALL              
  70: CALL                 
  80: RETURN_VALUE         
