# Disassembly for importlib._pack_uint32
# From module file: importlib._bootstrap_external

## co_consts:
('Convert a 32-bit integer to little-endian.', 4294967295, 4, 'little')

## co_names:
('int', 'to_bytes')

## bytecode:

   0: RESUME               
   2: LOAD_GLOBAL          NULL + int
  14: LOAD_FAST            x
  16: PRECALL              
  20: CALL                 
  30: LOAD_CONST           4294967295
  32: BINARY_OP            &
  36: LOAD_METHOD          to_bytes
  58: LOAD_CONST           4
  60: LOAD_CONST           'little'
  62: PRECALL              
  66: CALL                 
  76: RETURN_VALUE         
