# Disassembly for importlib.EntryPoints._from_text_for
# From module file: importlib.metadata

## co_consts:
(None, <code object <genexpr> at 0x00000240693EB430, file "importlib\metadata\__init__.py", line 402>)

## co_names:
('_from_text',)

## bytecode:

   0: MAKE_CELL            dist
   2: RESUME               
   4: PUSH_NULL            
   6: LOAD_FAST            cls
   8: LOAD_CLOSURE         dist
  10: BUILD_TUPLE          
  12: LOAD_CONST           <code object <genexpr> at 0x00000240693EB430, file "importlib\metadata\__init__.py", line 402>
  14: MAKE_FUNCTION        closure
  16: LOAD_FAST            cls
  18: LOAD_METHOD          _from_text
  40: LOAD_FAST            text
  42: PRECALL              
  46: CALL                 
  56: GET_ITER             
  58: PRECALL              
  62: CALL                 
  72: PRECALL              
  76: CALL                 
  86: RETURN_VALUE         
