# Disassembly for importlib.NamespaceLoader.get_resource_reader
# From module file: importlib._bootstrap_external

## co_consts:
(None, 0, ('NamespaceReader',))

## co_names:
('importlib.readers', 'NamespaceReader', '_path')

## bytecode:

   0: RESUME               
   2: LOAD_CONST           0
   4: LOAD_CONST           ('NamespaceReader',)
   6: IMPORT_NAME          importlib.readers
   8: IMPORT_FROM          NamespaceReader
  10: STORE_FAST           NamespaceReader
  12: POP_TOP              
  14: PUSH_NULL            
  16: LOAD_FAST            NamespaceReader
  18: LOAD_FAST            self
  20: LOAD_ATTR            _path
  30: PRECALL              
  34: CALL                 
  44: RETURN_VALUE         
