# Disassembly for importlib._validate_hash_pyc
# From module file: importlib._bootstrap_external

## co_consts:
('Validate a hash-based pyc by checking the real source hash against the one in\n    the pyc header.\n\n    *data* is the contents of the pyc file. (Only the first 16 bytes are\n    required.)\n\n    *source_hash* is the importlib.util.source_hash() of the source file.\n\n    *name* is the name of the module being imported. It is used for logging.\n\n    *exc_details* is a dictionary passed to ImportError if it raised for\n    improved debugging.\n\n    An ImportError is raised if the bytecode is stale.\n\n    ', 8, 16, "hash in bytecode doesn't match hash of source ", None)

## co_names:
('ImportError',)

## bytecode:

   0: RESUME               
   2: LOAD_FAST            data
   4: LOAD_CONST           8
   6: LOAD_CONST           16
   8: BUILD_SLICE          
  10: BINARY_SUBSCR        
  20: LOAD_FAST            source_hash
  22: COMPARE_OP           !=
  28: POP_JUMP_FORWARD_IF_FALSE to 62
  30: LOAD_GLOBAL          NULL + ImportError
  42: LOAD_CONST           "hash in bytecode doesn't match hash of source "
  44: LOAD_FAST            name
  46: FORMAT_VALUE         repr
  48: BUILD_STRING         
  50: BUILD_TUPLE          
  52: BUILD_MAP            
  54: LOAD_FAST            exc_details
  56: DICT_MERGE           
  58: CALL_FUNCTION_EX     
  60: RAISE_VARARGS        
  62: LOAD_CONST           None
  64: RETURN_VALUE         
