# Disassembly for importlib._get_supported_file_loaders
# From module file: importlib._bootstrap_external

## co_consts:
('Returns a list of file-based module loaders.\n\n    Each item is a tuple (loader, suffixes).\n    ',)

## co_names:
('ExtensionFileLoader', '_imp', 'extension_suffixes', 'SourceFileLoader', 'SOURCE_SUFFIXES', 'SourcelessFileLoader', 'BYTECODE_SUFFIXES')

## bytecode:

   0: RESUME               
   2: LOAD_GLOBAL          ExtensionFileLoader
  14: LOAD_GLOBAL          NULL + _imp
  26: LOAD_ATTR            extension_suffixes
  36: PRECALL              
  40: CALL                 
  50: BUILD_TUPLE          
  52: STORE_FAST           extensions
  54: LOAD_GLOBAL          SourceFileLoader
  66: LOAD_GLOBAL          SOURCE_SUFFIXES
  78: BUILD_TUPLE          
  80: STORE_FAST           source
  82: LOAD_GLOBAL          SourcelessFileLoader
  94: LOAD_GLOBAL          BYTECODE_SUFFIXES
 106: BUILD_TUPLE          
 108: STORE_FAST           bytecode
 110: LOAD_FAST            extensions
 112: LOAD_FAST            source
 114: LOAD_FAST            bytecode
 116: BUILD_LIST           
 118: RETURN_VALUE         
