# Disassembly for importlib._module_repr
# From module file: importlib._bootstrap

## co_consts:
('The implementation of ModuleType.__repr__().', '__loader__', None, '__spec__', 'module_repr', '?', '<module {!r} from {!r}>', '<module {!r}>', '<module {!r} ({!r})>')

## co_names:
('getattr', '_module_repr_from_spec', 'hasattr', 'module_repr', 'Exception', '__name__', 'AttributeError', '__file__', 'format')

## bytecode:

   0: RESUME               
   2: LOAD_GLOBAL          NULL + getattr
  14: LOAD_FAST            module
  16: LOAD_CONST           '__loader__'
  18: LOAD_CONST           None
  20: PRECALL              
  24: CALL                 
  34: STORE_FAST           loader
  36: LOAD_GLOBAL          NULL + getattr
  48: LOAD_FAST            module
  50: LOAD_CONST           '__spec__'
  52: LOAD_CONST           None
  54: PRECALL              
  58: CALL                 
  68: COPY                 
  70: STORE_FAST           spec
  72: POP_JUMP_FORWARD_IF_FALSE to 104
  74: LOAD_GLOBAL          NULL + _module_repr_from_spec
  86: LOAD_FAST            spec
  88: PRECALL              
  92: CALL                 
 102: RETURN_VALUE         
 104: LOAD_GLOBAL          NULL + hasattr
 116: LOAD_FAST            loader
 118: LOAD_CONST           'module_repr'
 120: PRECALL              
 124: CALL                 
 134: POP_JUMP_FORWARD_IF_FALSE to 212
 136: NOP                  
 138: LOAD_FAST            loader
 140: LOAD_METHOD          module_repr
 162: LOAD_FAST            module
 164: PRECALL              
 168: CALL                 
 178: RETURN_VALUE         
 180: PUSH_EXC_INFO        
 182: LOAD_GLOBAL          Exception
 194: CHECK_EXC_MATCH      
 196: POP_JUMP_FORWARD_IF_FALSE to 204
 198: POP_TOP              
 200: POP_EXCEPT           
 202: JUMP_FORWARD         to 212
 204: RERAISE              
 206: COPY                 
 208: POP_EXCEPT           
 210: RERAISE              
 212: NOP                  
 214: LOAD_FAST            module
 216: LOAD_ATTR            __name__
 226: STORE_FAST           name
 228: JUMP_FORWARD         to 266
 230: PUSH_EXC_INFO        
 232: LOAD_GLOBAL          AttributeError
 244: CHECK_EXC_MATCH      
 246: POP_JUMP_FORWARD_IF_FALSE to 258
 248: POP_TOP              
 250: LOAD_CONST           '?'
 252: STORE_FAST           name
 254: POP_EXCEPT           
 256: JUMP_FORWARD         to 266
 258: RERAISE              
 260: COPY                 
 262: POP_EXCEPT           
 264: RERAISE              
 266: NOP                  
 268: LOAD_FAST            module
 270: LOAD_ATTR            __file__
 280: STORE_FAST           filename
 282: LOAD_CONST           '<module {!r} from {!r}>'
 284: LOAD_METHOD          format
 306: LOAD_FAST            name
 308: LOAD_FAST            filename
 310: PRECALL              
 314: CALL                 
 324: RETURN_VALUE         
 326: PUSH_EXC_INFO        
 328: LOAD_GLOBAL          AttributeError
 340: CHECK_EXC_MATCH      
 342: POP_JUMP_FORWARD_IF_FALSE to 444
 344: POP_TOP              
 346: LOAD_FAST            loader
 348: POP_JUMP_FORWARD_IF_NOT_NONE to 396
 350: LOAD_CONST           '<module {!r}>'
 352: LOAD_METHOD          format
 374: LOAD_FAST            name
 376: PRECALL              
 380: CALL                 
 390: SWAP                 
 392: POP_EXCEPT           
 394: RETURN_VALUE         
 396: LOAD_CONST           '<module {!r} ({!r})>'
 398: LOAD_METHOD          format
 420: LOAD_FAST            name
 422: LOAD_FAST            loader
 424: PRECALL              
 428: CALL                 
 438: SWAP                 
 440: POP_EXCEPT           
 442: RETURN_VALUE         
 444: RERAISE              
 446: COPY                 
 448: POP_EXCEPT           
 450: RERAISE              
