# Disassembly for importlib.InspectLoader.get_code
# From module file: importlib.abc

## co_consts:
('Method which returns the code object for the module.\n\n        The fullname is a str.  Returns a types.CodeType if possible, else\n        returns None if a code object does not make sense\n        (e.g. built-in module). Raises ImportError if the module cannot be\n        found.\n        ', None)

## co_names:
('get_source', 'source_to_code')

## bytecode:

   0: RESUME               
   2: LOAD_FAST            self
   4: LOAD_METHOD          get_source
  26: LOAD_FAST            fullname
  28: PRECALL              
  32: CALL                 
  42: STORE_FAST           source
  44: LOAD_FAST            source
  46: POP_JUMP_FORWARD_IF_NOT_NONE to 52
  48: LOAD_CONST           None
  50: RETURN_VALUE         
  52: LOAD_FAST            self
  54: LOAD_METHOD          source_to_code
  76: LOAD_FAST            source
  78: PRECALL              
  82: CALL                 
  92: RETURN_VALUE         
