# Disassembly for importlib.<genexpr>
# From module file: importlib._bootstrap_external

## co_consts:
(1, None)

## co_names:
('len',)

## bytecode:

   0: RETURN_GENERATOR     
   2: POP_TOP              
   4: RESUME               
   6: LOAD_FAST            .0
   8: FOR_ITER             to 56
  10: STORE_FAST           sep
  12: LOAD_GLOBAL          NULL + len
  24: LOAD_FAST            sep
  26: PRECALL              
  30: CALL                 
  40: LOAD_CONST           1
  42: COMPARE_OP           ==
  48: YIELD_VALUE          
  50: RESUME               
  52: POP_TOP              
  54: JUMP_BACKWARD        to 8
  56: LOAD_CONST           None
  58: RETURN_VALUE         
