# Disassembly for importlib.SourceFileLoader.path_stats
# From module file: importlib._bootstrap_external

## co_consts:
('Return the metadata for the path.', ('mtime', 'size'))

## co_names:
('_path_stat', 'st_mtime', 'st_size')

## bytecode:

   0: RESUME               
   2: LOAD_GLOBAL          NULL + _path_stat
  14: LOAD_FAST            path
  16: PRECALL              
  20: CALL                 
  30: STORE_FAST           st
  32: LOAD_FAST            st
  34: LOAD_ATTR            st_mtime
  44: LOAD_FAST            st
  46: LOAD_ATTR            st_size
  56: LOAD_CONST           ('mtime', 'size')
  58: BUILD_CONST_KEY_MAP  
  60: RETURN_VALUE         
