# Disassembly for importlib.DeprecatedList
# From module file: importlib.metadata

## co_consts:
('DeprecatedList', "\n    Allow an otherwise immutable object to implement mutability\n    for compatibility.\n\n    >>> recwarn = getfixture('recwarn')\n    >>> dl = DeprecatedList(range(3))\n    >>> dl[0] = 1\n    >>> dl.append(3)\n    >>> del dl[3]\n    >>> dl.reverse()\n    >>> dl.sort()\n    >>> dl.extend([4])\n    >>> dl.pop(-1)\n    4\n    >>> dl.remove(1)\n    >>> dl += [5]\n    >>> dl + [6]\n    [1, 2, 5, 6]\n    >>> dl + (6,)\n    [1, 2, 5, 6]\n    >>> dl.insert(0, 0)\n    >>> dl\n    [0, 1, 2, 5]\n    >>> dl == [0, 1, 2, 5]\n    True\n    >>> dl == (0, 1, 2, 5)\n    True\n    >>> len(recwarn)\n    1\n    ", (), 'EntryPoints list interface is deprecated. Cast to list if needed.', 2, ('stacklevel',), 'method_name', <code object _wrap_deprecated_method at 0x0000024069465610, file "importlib\metadata\__init__.py", line 322>, '__setitem__ __delitem__ append reverse extend pop remove __iadd__ insert sort', <code object __add__ at 0x00000240691EA730, file "importlib\metadata\__init__.py", line 337>, <code object __eq__ at 0x000002406921FB20, file "importlib\metadata\__init__.py", line 343>)

## co_names:
('__name__', '__module__', '__qualname__', '__doc__', '__slots__', 'functools', 'partial', 'warnings', 'warn', 'DeprecationWarning', '_warn', 'str', '_wrap_deprecated_method', 'locals', 'update', 'map', 'split', '__add__', '__eq__', '__classcell__')

## bytecode:

   0: MAKE_CELL            __class__
   2: RESUME               
   4: LOAD_NAME            __name__
   6: STORE_NAME           __module__
   8: LOAD_CONST           'DeprecatedList'
  10: STORE_NAME           __qualname__
  12: LOAD_CONST           "\n    Allow an otherwise immutable object to implement mutability\n    for compatibility.\n\n    >>> recwarn = getfixture('recwarn')\n    >>> dl = DeprecatedList(range(3))\n    >>> dl[0] = 1\n    >>> dl.append(3)\n    >>> del dl[3]\n    >>> dl.reverse()\n    >>> dl.sort()\n    >>> dl.extend([4])\n    >>> dl.pop(-1)\n    4\n    >>> dl.remove(1)\n    >>> dl += [5]\n    >>> dl + [6]\n    [1, 2, 5, 6]\n    >>> dl + (6,)\n    [1, 2, 5, 6]\n    >>> dl.insert(0, 0)\n    >>> dl\n    [0, 1, 2, 5]\n    >>> dl == [0, 1, 2, 5]\n    True\n    >>> dl == (0, 1, 2, 5)\n    True\n    >>> len(recwarn)\n    1\n    "
  14: STORE_NAME           __doc__
  16: LOAD_CONST           ()
  18: STORE_NAME           __slots__
  20: PUSH_NULL            
  22: LOAD_NAME            functools
  24: LOAD_ATTR            partial
  34: LOAD_NAME            warnings
  36: LOAD_ATTR            warn
  46: LOAD_CONST           'EntryPoints list interface is deprecated. Cast to list if needed.'
  48: LOAD_NAME            DeprecationWarning
  50: LOAD_CONST           2
  52: KW_NAMES             
  54: PRECALL              
  58: CALL                 
  68: STORE_NAME           _warn
  70: LOAD_CONST           'method_name'
  72: LOAD_NAME            str
  74: BUILD_TUPLE          
  76: LOAD_CLOSURE         __class__
  78: BUILD_TUPLE          
  80: LOAD_CONST           <code object _wrap_deprecated_method at 0x0000024069465610, file "importlib\metadata\__init__.py", line 322>
  82: MAKE_FUNCTION        annotations, closure
  84: STORE_NAME           _wrap_deprecated_method
  86: PUSH_NULL            
  88: LOAD_NAME            locals
  90: PRECALL              
  94: CALL                 
 104: LOAD_METHOD          update
 126: PUSH_NULL            
 128: LOAD_NAME            map
 130: LOAD_NAME            _wrap_deprecated_method
 132: LOAD_CONST           '__setitem__ __delitem__ append reverse extend pop remove __iadd__ insert sort'
 134: LOAD_METHOD          split
 156: PRECALL              
 160: CALL                 
 170: PRECALL              
 174: CALL                 
 184: PRECALL              
 188: CALL                 
 198: POP_TOP              
 200: LOAD_CONST           <code object __add__ at 0x00000240691EA730, file "importlib\metadata\__init__.py", line 337>
 202: MAKE_FUNCTION        
 204: STORE_NAME           __add__
 206: LOAD_CONST           <code object __eq__ at 0x000002406921FB20, file "importlib\metadata\__init__.py", line 343>
 208: MAKE_FUNCTION        
 210: STORE_NAME           __eq__
 212: LOAD_CLOSURE         __class__
 214: COPY                 
 216: STORE_NAME           __classcell__
 218: RETURN_VALUE         
