# Disassembly for importlib.ExecutionLoader.get_code
# From module file: importlib.abc

## co_consts:
('Method to return the code object for fullname.\n\n        Should return None if not applicable (e.g. built-in module).\n        Raise ImportError if the module cannot be found.\n        ', None)

## co_names:
('get_source', 'get_filename', 'source_to_code', 'ImportError')

## bytecode:

   0: RESUME               
   2: LOAD_FAST            self
   4: LOAD_METHOD          get_source
  26: LOAD_FAST            fullname
  28: PRECALL              
  32: CALL                 
  42: STORE_FAST           source
  44: LOAD_FAST            source
  46: POP_JUMP_FORWARD_IF_NOT_NONE to 52
  48: LOAD_CONST           None
  50: RETURN_VALUE         
  52: NOP                  
  54: LOAD_FAST            self
  56: LOAD_METHOD          get_filename
  78: LOAD_FAST            fullname
  80: PRECALL              
  84: CALL                 
  94: STORE_FAST           path
  96: LOAD_FAST            self
  98: LOAD_METHOD          source_to_code
 120: LOAD_FAST            source
 122: LOAD_FAST            path
 124: PRECALL              
 128: CALL                 
 138: RETURN_VALUE         
 140: PUSH_EXC_INFO        
 142: LOAD_GLOBAL          ImportError
 154: CHECK_EXC_MATCH      
 156: POP_JUMP_FORWARD_IF_FALSE to 206
 158: POP_TOP              
 160: LOAD_FAST            self
 162: LOAD_METHOD          source_to_code
 184: LOAD_FAST            source
 186: PRECALL              
 190: CALL                 
 200: SWAP                 
 202: POP_EXCEPT           
 204: RETURN_VALUE         
 206: RERAISE              
 208: COPY                 
 210: POP_EXCEPT           
 212: RERAISE              
