# Disassembly for importlib.PathFinder.find_module
# From module file: importlib._bootstrap_external

## co_consts:
("find the module on sys.path or 'path' based on sys.path_hooks and\n        sys.path_importer_cache.\n\n        This method is deprecated.  Use find_spec() instead.\n\n        ", 'PathFinder.find_module() is deprecated and slated for removal in Python 3.12; use find_spec() instead', None)

## co_names:
('_warnings', 'warn', 'DeprecationWarning', 'find_spec', 'loader')

## bytecode:

   0: RESUME               
   2: LOAD_GLOBAL          NULL + _warnings
  14: LOAD_ATTR            warn
  24: LOAD_CONST           'PathFinder.find_module() is deprecated and slated for removal in Python 3.12; use find_spec() instead'
  26: LOAD_GLOBAL          DeprecationWarning
  38: PRECALL              
  42: CALL                 
  52: POP_TOP              
  54: LOAD_FAST            cls
  56: LOAD_METHOD          find_spec
  78: LOAD_FAST            fullname
  80: LOAD_FAST            path
  82: PRECALL              
  86: CALL                 
  96: STORE_FAST           spec
  98: LOAD_FAST            spec
 100: POP_JUMP_FORWARD_IF_NOT_NONE to 106
 102: LOAD_CONST           None
 104: RETURN_VALUE         
 106: LOAD_FAST            spec
 108: LOAD_ATTR            loader
 118: RETURN_VALUE         
