# Disassembly for importlib.Finder
# From module file: importlib.abc

## co_consts:
('Finder', 'Legacy abstract base class for import finders.\n\n    It may be subclassed for compatibility with legacy third party\n    reimplementations of the import system.  Otherwise, finder\n    implementations should derive from the more specific MetaPathFinder\n    or PathEntryFinder ABCs.\n\n    Deprecated since Python 3.3\n    ', <code object __init__ at 0x00000240693EB330, file "importlib\abc.py", line 55>, None, <code object find_module at 0x00000240693EB730, file "importlib\abc.py", line 61>, (None,))

## co_names:
('__name__', '__module__', '__qualname__', '__doc__', '__init__', 'abc', 'abstractmethod', 'find_module')

## bytecode:

   0: RESUME               
   2: LOAD_NAME            __name__
   4: STORE_NAME           __module__
   6: LOAD_CONST           'Finder'
   8: STORE_NAME           __qualname__
  10: LOAD_CONST           'Legacy abstract base class for import finders.\n\n    It may be subclassed for compatibility with legacy third party\n    reimplementations of the import system.  Otherwise, finder\n    implementations should derive from the more specific MetaPathFinder\n    or PathEntryFinder ABCs.\n\n    Deprecated since Python 3.3\n    '
  12: STORE_NAME           __doc__
  14: LOAD_CONST           <code object __init__ at 0x00000240693EB330, file "importlib\abc.py", line 55>
  16: MAKE_FUNCTION        
  18: STORE_NAME           __init__
  20: LOAD_NAME            abc
  22: LOAD_ATTR            abstractmethod
  32: LOAD_CONST           (None,)
  34: LOAD_CONST           <code object find_module at 0x00000240693EB730, file "importlib\abc.py", line 61>
  36: MAKE_FUNCTION        defaults
  38: PRECALL              
  42: CALL                 
  52: STORE_NAME           find_module
  54: LOAD_CONST           None
  56: RETURN_VALUE         
