# Disassembly for importlib.Loader.load_module
# From module file: importlib._abc

## co_consts:
('Return the loaded module.\n\n        The module must be added to sys.modules and have import-related\n        attributes set properly.  The fullname is a str.\n\n        ImportError is raised on failure.\n\n        This method is deprecated in favor of loader.exec_module(). If\n        exec_module() exists then it is used to provide a backwards-compatible\n        functionality for this method.\n\n        ', 'exec_module')

## co_names:
('hasattr', 'ImportError', '_bootstrap', '_load_module_shim')

## bytecode:

   0: RESUME               
   2: LOAD_GLOBAL          NULL + hasattr
  14: LOAD_FAST            self
  16: LOAD_CONST           'exec_module'
  18: PRECALL              
  22: CALL                 
  32: POP_JUMP_FORWARD_IF_TRUE to 48
  34: LOAD_GLOBAL          ImportError
  46: RAISE_VARARGS        
  48: LOAD_GLOBAL          NULL + _bootstrap
  60: LOAD_ATTR            _load_module_shim
  70: LOAD_FAST            self
  72: LOAD_FAST            fullname
  74: PRECALL              
  78: CALL                 
  88: RETURN_VALUE         
