# Disassembly for importlib.module_for_loader
# From module file: importlib.util

## co_consts:
('Decorator to handle selecting the proper module for loaders.\n\n    The decorated function is passed the module to use instead of the module\n    name. The module passed in to the function is either from sys.modules if\n    it already exists or is a new module. If the module is new, then __name__\n    is set the first argument to the method, __loader__ is set to self, and\n    __package__ is set accordingly (if self.is_package() is defined) will be set\n    before it is passed to the decorated function (if self.is_package() does\n    not work for the module it will be set post-load).\n\n    If an exception is raised and the decorator created the module it is\n    subsequently removed from sys.modules.\n\n    The decorator assumes that the decorated function takes the module name as\n    the second argument.\n\n    ', 'The import system now takes care of this automatically; this decorator is slated for removal in Python 3.12', 2, ('stacklevel',), <code object module_for_loader_wrapper at 0x0000024069365770, file "importlib\util.py", line 203>)

## co_names:
('warnings', 'warn', 'DeprecationWarning', 'functools', 'wraps')

## bytecode:

   0: MAKE_CELL            fxn
   2: RESUME               
   4: LOAD_GLOBAL          NULL + warnings
  16: LOAD_ATTR            warn
  26: LOAD_CONST           'The import system now takes care of this automatically; this decorator is slated for removal in Python 3.12'
  28: LOAD_GLOBAL          DeprecationWarning
  40: LOAD_CONST           2
  42: KW_NAMES             
  44: PRECALL              
  48: CALL                 
  58: POP_TOP              
  60: LOAD_GLOBAL          NULL + functools
  72: LOAD_ATTR            wraps
  82: LOAD_DEREF           fxn
  84: PRECALL              
  88: CALL                 
  98: LOAD_CLOSURE         fxn
 100: BUILD_TUPLE          
 102: LOAD_CONST           <code object module_for_loader_wrapper at 0x0000024069365770, file "importlib\util.py", line 203>
 104: MAKE_FUNCTION        closure
 106: PRECALL              
 110: CALL                 
 120: STORE_FAST           module_for_loader_wrapper
 122: LOAD_FAST            module_for_loader_wrapper
 124: RETURN_VALUE         
