# Disassembly for importlib.PackageNotFoundError
# From module file: importlib.metadata

## co_consts:
('PackageNotFoundError', 'The package was not found.', <code object __str__ at 0x0000024069427770, file "importlib\metadata\__init__.py", line 49>, <code object name at 0x0000024069494FA0, file "importlib\metadata\__init__.py", line 52>, None)

## co_names:
('__name__', '__module__', '__qualname__', '__doc__', '__str__', 'property', 'name')

## bytecode:

   0: RESUME               
   2: LOAD_NAME            __name__
   4: STORE_NAME           __module__
   6: LOAD_CONST           'PackageNotFoundError'
   8: STORE_NAME           __qualname__
  10: LOAD_CONST           'The package was not found.'
  12: STORE_NAME           __doc__
  14: LOAD_CONST           <code object __str__ at 0x0000024069427770, file "importlib\metadata\__init__.py", line 49>
  16: MAKE_FUNCTION        
  18: STORE_NAME           __str__
  20: LOAD_NAME            property
  22: LOAD_CONST           <code object name at 0x0000024069494FA0, file "importlib\metadata\__init__.py", line 52>
  24: MAKE_FUNCTION        
  26: PRECALL              
  30: CALL                 
  40: STORE_NAME           name
  42: LOAD_CONST           None
  44: RETURN_VALUE         
