# Disassembly for importlib.entry_points
# From module file: importlib.metadata

## co_consts:
('Return EntryPoint objects for all installed packages.\n\n    Pass selection parameters (group or name) to filter the\n    result to entry points matching those properties (see\n    EntryPoints.select()).\n\n    For compatibility, returns ``SelectableGroups`` object unless\n    selection parameters are supplied. In the future, this function\n    will return ``EntryPoints`` instead of ``SelectableGroups``\n    even when no selection parameters are supplied.\n\n    For maximum future compatibility, pass selection parameters\n    or invoke ``.select`` with parameters on the result.\n\n    :return: EntryPoints or SelectableGroups for all installed packages.\n    ', <code object <genexpr> at 0x0000024069467BB0, file "importlib\metadata\__init__.py", line 1037>, ())

## co_names:
('itertools', 'chain', 'from_iterable', '_unique', 'distributions', 'SelectableGroups', 'load', 'select')

## bytecode:

   0: RESUME               
   2: LOAD_GLOBAL          itertools
  14: LOAD_ATTR            chain
  24: LOAD_METHOD          from_iterable
  46: LOAD_CONST           <code object <genexpr> at 0x0000024069467BB0, file "importlib\metadata\__init__.py", line 1037>
  48: MAKE_FUNCTION        
  50: LOAD_GLOBAL          NULL + _unique
  62: LOAD_GLOBAL          NULL + distributions
  74: PRECALL              
  78: CALL                 
  88: PRECALL              
  92: CALL                 
 102: GET_ITER             
 104: PRECALL              
 108: CALL                 
 118: PRECALL              
 122: CALL                 
 132: STORE_FAST           eps
 134: LOAD_GLOBAL          NULL + SelectableGroups
 146: LOAD_METHOD          load
 168: LOAD_FAST            eps
 170: PRECALL              
 174: CALL                 
 184: LOAD_ATTR            select
 194: LOAD_CONST           ()
 196: BUILD_MAP            
 198: LOAD_FAST            params
 200: DICT_MERGE           
 202: CALL_FUNCTION_EX     
 204: RETURN_VALUE         
