# Disassembly for importlib.FastPath.search
# From module file: importlib.metadata

## co_consts:
(None,)

## co_names:
('lookup', 'mtime', 'search')

## bytecode:

   0: RESUME               
   2: LOAD_FAST            self
   4: LOAD_METHOD          lookup
  26: LOAD_FAST            self
  28: LOAD_ATTR            mtime
  38: PRECALL              
  42: CALL                 
  52: LOAD_METHOD          search
  74: LOAD_FAST            name
  76: PRECALL              
  80: CALL                 
  90: RETURN_VALUE         
