# Disassembly for importlib.spec_from_loader
# From module file: importlib._bootstrap

## co_consts:
('Return a module spec based on various loader methods.', None, '_ORIGIN', 'get_filename', ('loader',), ('loader', 'submodule_search_locations'), 'is_package', False, ('origin', 'is_package'))

## co_names:
('getattr', 'hasattr', '_bootstrap_external', 'NotImplementedError', 'spec_from_file_location', 'is_package', 'ImportError', 'ModuleSpec')

## bytecode:

   0: RESUME               
   2: LOAD_FAST            origin
   4: POP_JUMP_FORWARD_IF_NOT_NONE to 40
   6: LOAD_GLOBAL          NULL + getattr
  18: LOAD_FAST            loader
  20: LOAD_CONST           '_ORIGIN'
  22: LOAD_CONST           None
  24: PRECALL              
  28: CALL                 
  38: STORE_FAST           origin
  40: LOAD_FAST            origin
  42: POP_JUMP_FORWARD_IF_TRUE to 198
  44: LOAD_GLOBAL          NULL + hasattr
  56: LOAD_FAST            loader
  58: LOAD_CONST           'get_filename'
  60: PRECALL              
  64: CALL                 
  74: POP_JUMP_FORWARD_IF_FALSE to 198
  76: LOAD_GLOBAL          _bootstrap_external
  88: POP_JUMP_FORWARD_IF_NOT_NONE to 104
  90: LOAD_GLOBAL          NotImplementedError
 102: RAISE_VARARGS        
 104: LOAD_GLOBAL          _bootstrap_external
 116: LOAD_ATTR            spec_from_file_location
 126: STORE_FAST           spec_from_file_location
 128: LOAD_FAST            is_package
 130: POP_JUMP_FORWARD_IF_NOT_NONE to 158
 132: PUSH_NULL            
 134: LOAD_FAST            spec_from_file_location
 136: LOAD_FAST            name
 138: LOAD_FAST            loader
 140: KW_NAMES             
 142: PRECALL              
 146: CALL                 
 156: RETURN_VALUE         
 158: LOAD_FAST            is_package
 160: POP_JUMP_FORWARD_IF_FALSE to 166
 162: BUILD_LIST           
 164: JUMP_FORWARD         to 168
 166: LOAD_CONST           None
 168: STORE_FAST           search
 170: PUSH_NULL            
 172: LOAD_FAST            spec_from_file_location
 174: LOAD_FAST            name
 176: LOAD_FAST            loader
 178: LOAD_FAST            search
 180: KW_NAMES             
 182: PRECALL              
 186: CALL                 
 196: RETURN_VALUE         
 198: LOAD_FAST            is_package
 200: POP_JUMP_FORWARD_IF_NOT_NONE to 320
 202: LOAD_GLOBAL          NULL + hasattr
 214: LOAD_FAST            loader
 216: LOAD_CONST           'is_package'
 218: PRECALL              
 222: CALL                 
 232: POP_JUMP_FORWARD_IF_FALSE to 316
 234: NOP                  
 236: LOAD_FAST            loader
 238: LOAD_METHOD          is_package
 260: LOAD_FAST            name
 262: PRECALL              
 266: CALL                 
 276: STORE_FAST           is_package
 278: JUMP_FORWARD         to 320
 280: PUSH_EXC_INFO        
 282: LOAD_GLOBAL          ImportError
 294: CHECK_EXC_MATCH      
 296: POP_JUMP_FORWARD_IF_FALSE to 308
 298: POP_TOP              
 300: LOAD_CONST           None
 302: STORE_FAST           is_package
 304: POP_EXCEPT           
 306: JUMP_FORWARD         to 320
 308: RERAISE              
 310: COPY                 
 312: POP_EXCEPT           
 314: RERAISE              
 316: LOAD_CONST           False
 318: STORE_FAST           is_package
 320: LOAD_GLOBAL          NULL + ModuleSpec
 332: LOAD_FAST            name
 334: LOAD_FAST            loader
 336: LOAD_FAST            origin
 338: LOAD_FAST            is_package
 340: KW_NAMES             
 342: PRECALL              
 346: CALL                 
 356: RETURN_VALUE         
