# Disassembly for importlib.import_module
# From module file: importlib

## co_consts:
("Import a module.\n\n    The 'package' argument is required when performing a relative import. It\n    specifies the package to use as the anchor point from which to resolve the\n    relative import to an absolute import.\n\n    ", 0, '.', "the 'package' argument is required to perform a relative import for {!r}", 1, None)

## co_names:
('startswith', 'TypeError', 'format', '_bootstrap', '_gcd_import')

## bytecode:

   0: RESUME               
   2: LOAD_CONST           0
   4: STORE_FAST           level
   6: LOAD_FAST            name
   8: LOAD_METHOD          startswith
  30: LOAD_CONST           '.'
  32: PRECALL              
  36: CALL                 
  46: POP_JUMP_FORWARD_IF_FALSE to 160
  48: LOAD_FAST            package
  50: POP_JUMP_FORWARD_IF_TRUE to 124
  52: LOAD_CONST           "the 'package' argument is required to perform a relative import for {!r}"
  54: STORE_FAST           msg
  56: LOAD_GLOBAL          NULL + TypeError
  68: LOAD_FAST            msg
  70: LOAD_METHOD          format
  92: LOAD_FAST            name
  94: PRECALL              
  98: CALL                 
 108: PRECALL              
 112: CALL                 
 122: RAISE_VARARGS        
 124: LOAD_FAST            name
 126: GET_ITER             
 128: FOR_ITER             to 160
 130: STORE_FAST           character
 132: LOAD_FAST            character
 134: LOAD_CONST           '.'
 136: COMPARE_OP           !=
 142: POP_JUMP_FORWARD_IF_FALSE to 148
 144: POP_TOP              
 146: JUMP_FORWARD         to 160
 148: LOAD_FAST            level
 150: LOAD_CONST           1
 152: BINARY_OP            +=
 156: STORE_FAST           level
 158: JUMP_BACKWARD        to 128
 160: LOAD_GLOBAL          NULL + _bootstrap
 172: LOAD_ATTR            _gcd_import
 182: LOAD_FAST            name
 184: LOAD_FAST            level
 186: LOAD_CONST           None
 188: BUILD_SLICE          
 190: BINARY_SUBSCR        
 200: LOAD_FAST            package
 202: LOAD_FAST            level
 204: PRECALL              
 208: CALL                 
 218: RETURN_VALUE         
