# Disassembly for importlib.FrozenImporter.find_module
# From module file: importlib._bootstrap

## co_consts:
('Find a frozen module.\n\n        This method is deprecated.  Use find_spec() instead.\n\n        ', 'FrozenImporter.find_module() is deprecated and slated for removal in Python 3.12; use find_spec() instead', None)

## co_names:
('_warnings', 'warn', 'DeprecationWarning', '_imp', 'is_frozen')

## bytecode:

   0: RESUME               
   2: LOAD_GLOBAL          _warnings
  14: LOAD_METHOD          warn
  36: LOAD_CONST           'FrozenImporter.find_module() is deprecated and slated for removal in Python 3.12; use find_spec() instead'
  38: LOAD_GLOBAL          DeprecationWarning
  50: PRECALL              
  54: CALL                 
  64: POP_TOP              
  66: LOAD_GLOBAL          _imp
  78: LOAD_METHOD          is_frozen
 100: LOAD_FAST            fullname
 102: PRECALL              
 106: CALL                 
 116: POP_JUMP_FORWARD_IF_FALSE to 122
 118: LOAD_FAST            cls
 120: JUMP_FORWARD         to 124
 122: LOAD_CONST           None
 124: RETURN_VALUE         
