# Disassembly for importlib.Finder.find_module
# From module file: importlib.abc

## co_consts:
('An abstract method that should find a module.\n        The fullname is a str and the optional path is a str or None.\n        Returns a Loader object or None.\n        ', 'importlib.abc.Finder along with its find_module() method are deprecated and slated for removal in Python 3.12; use MetaPathFinder.find_spec() or PathEntryFinder.find_spec() instead', None)

## co_names:
('warnings', 'warn', 'DeprecationWarning')

## bytecode:

   0: RESUME               
   2: LOAD_GLOBAL          NULL + warnings
  14: LOAD_ATTR            warn
  24: LOAD_CONST           'importlib.abc.Finder along with its find_module() method are deprecated and slated for removal in Python 3.12; use MetaPathFinder.find_spec() or PathEntryFinder.find_spec() instead'
  26: LOAD_GLOBAL          DeprecationWarning
  38: PRECALL              
  42: CALL                 
  52: POP_TOP              
  54: LOAD_CONST           None
  56: RETURN_VALUE         
