# Disassembly for importlib.SelectableGroups
# From module file: importlib.metadata

## co_consts:
('SelectableGroups', '\n    A backward- and forward-compatible result from\n    entry_points that fully implements the dict interface.\n    ', <code object load at 0x00000240691C0F50, file "importlib\metadata\__init__.py", line 473>, <code object _all at 0x000002406921FC90, file "importlib\metadata\__init__.py", line 480>, <code object groups at 0x0000024069465FB0, file "importlib\metadata\__init__.py", line 488>, <code object names at 0x0000024069465D10, file "importlib\metadata\__init__.py", line 492>, <code object select at 0x000002406945D890, file "importlib\metadata\__init__.py", line 501>)

## co_names:
('__name__', '__module__', '__qualname__', '__doc__', 'classmethod', 'load', 'property', '_all', 'groups', 'names', 'select', '__classcell__')

## bytecode:

   0: MAKE_CELL            __class__
   2: RESUME               
   4: LOAD_NAME            __name__
   6: STORE_NAME           __module__
   8: LOAD_CONST           'SelectableGroups'
  10: STORE_NAME           __qualname__
  12: LOAD_CONST           '\n    A backward- and forward-compatible result from\n    entry_points that fully implements the dict interface.\n    '
  14: STORE_NAME           __doc__
  16: LOAD_NAME            classmethod
  18: LOAD_CONST           <code object load at 0x00000240691C0F50, file "importlib\metadata\__init__.py", line 473>
  20: MAKE_FUNCTION        
  22: PRECALL              
  26: CALL                 
  36: STORE_NAME           load
  38: LOAD_NAME            property
  40: LOAD_CLOSURE         __class__
  42: BUILD_TUPLE          
  44: LOAD_CONST           <code object _all at 0x000002406921FC90, file "importlib\metadata\__init__.py", line 480>
  46: MAKE_FUNCTION        closure
  48: PRECALL              
  52: CALL                 
  62: STORE_NAME           _all
  64: LOAD_NAME            property
  66: LOAD_CONST           <code object groups at 0x0000024069465FB0, file "importlib\metadata\__init__.py", line 488>
  68: MAKE_FUNCTION        
  70: PRECALL              
  74: CALL                 
  84: STORE_NAME           groups
  86: LOAD_NAME            property
  88: LOAD_CONST           <code object names at 0x0000024069465D10, file "importlib\metadata\__init__.py", line 492>
  90: MAKE_FUNCTION        
  92: PRECALL              
  96: CALL                 
 106: STORE_NAME           names
 108: LOAD_CONST           <code object select at 0x000002406945D890, file "importlib\metadata\__init__.py", line 501>
 110: MAKE_FUNCTION        
 112: STORE_NAME           select
 114: LOAD_CLOSURE         __class__
 116: COPY                 
 118: STORE_NAME           __classcell__
 120: RETURN_VALUE         
