# Disassembly for importlib._requires_frozen._requires_frozen_wrapper
# From module file: importlib._bootstrap

## co_consts:
(None, '{!r} is not a frozen module', ('name',))

## co_names:
('_imp', 'is_frozen', 'ImportError', 'format')

## bytecode:

   0: COPY_FREE_VARS       
   2: RESUME               
   4: LOAD_GLOBAL          _imp
  16: LOAD_METHOD          is_frozen
  38: LOAD_FAST            fullname
  40: PRECALL              
  44: CALL                 
  54: POP_JUMP_FORWARD_IF_TRUE to 128
  56: LOAD_GLOBAL          NULL + ImportError
  68: LOAD_CONST           '{!r} is not a frozen module'
  70: LOAD_METHOD          format
  92: LOAD_FAST            fullname
  94: PRECALL              
  98: CALL                 
 108: LOAD_FAST            fullname
 110: KW_NAMES             
 112: PRECALL              
 116: CALL                 
 126: RAISE_VARARGS        
 128: PUSH_NULL            
 130: LOAD_DEREF           fxn
 132: LOAD_FAST            self
 134: LOAD_FAST            fullname
 136: PRECALL              
 140: CALL                 
 150: RETURN_VALUE         
