# Disassembly for importlib._LoaderBasics.exec_module
# From module file: importlib._bootstrap_external

## co_consts:
('Execute the module.', None, 'cannot load module {!r} when get_code() returns None')

## co_names:
('get_code', '__name__', 'ImportError', 'format', '_bootstrap', '_call_with_frames_removed', 'exec', '__dict__')

## bytecode:

   0: RESUME               
   2: LOAD_FAST            self
   4: LOAD_METHOD          get_code
  26: LOAD_FAST            module
  28: LOAD_ATTR            __name__
  38: PRECALL              
  42: CALL                 
  52: STORE_FAST           code
  54: LOAD_FAST            code
  56: POP_JUMP_FORWARD_IF_NOT_NONE to 136
  58: LOAD_GLOBAL          NULL + ImportError
  70: LOAD_CONST           'cannot load module {!r} when get_code() returns None'
  72: LOAD_METHOD          format
  94: LOAD_FAST            module
  96: LOAD_ATTR            __name__
 106: PRECALL              
 110: CALL                 
 120: PRECALL              
 124: CALL                 
 134: RAISE_VARARGS        
 136: LOAD_GLOBAL          _bootstrap
 148: LOAD_METHOD          _call_with_frames_removed
 170: LOAD_GLOBAL          exec
 182: LOAD_FAST            code
 184: LOAD_FAST            module
 186: LOAD_ATTR            __dict__
 196: PRECALL              
 200: CALL                 
 210: POP_TOP              
 212: LOAD_CONST           None
 214: RETURN_VALUE         
