# Disassembly for importlib.FileLoader.__init__
# From module file: importlib._bootstrap_external

## co_consts:
('Cache the module name and the path to the file found by the\n        finder.', None)

## co_names:
('name', 'path')

## bytecode:

   0: RESUME               
   2: LOAD_FAST            fullname
   4: LOAD_FAST            self
   6: STORE_ATTR           name
  16: LOAD_FAST            path
  18: LOAD_FAST            self
  20: STORE_ATTR           path
  30: LOAD_CONST           None
  32: RETURN_VALUE         
