# Disassembly for importlib.SelectableGroups.load
# From module file: importlib.metadata

## co_consts:
(None, 'group', ('key',), <code object <genexpr> at 0x00000240693EBE30, file "importlib\metadata\__init__.py", line 478>)

## co_names:
('operator', 'attrgetter', 'sorted', 'itertools', 'groupby')

## bytecode:

   0: RESUME               
   2: LOAD_GLOBAL          NULL + operator
  14: LOAD_ATTR            attrgetter
  24: LOAD_CONST           'group'
  26: PRECALL              
  30: CALL                 
  40: STORE_FAST           by_group
  42: LOAD_GLOBAL          NULL + sorted
  54: LOAD_FAST            eps
  56: LOAD_FAST            by_group
  58: KW_NAMES             
  60: PRECALL              
  64: CALL                 
  74: STORE_FAST           ordered
  76: LOAD_GLOBAL          NULL + itertools
  88: LOAD_ATTR            groupby
  98: LOAD_FAST            ordered
 100: LOAD_FAST            by_group
 102: PRECALL              
 106: CALL                 
 116: STORE_FAST           grouped
 118: PUSH_NULL            
 120: LOAD_FAST            cls
 122: LOAD_CONST           <code object <genexpr> at 0x00000240693EBE30, file "importlib\metadata\__init__.py", line 478>
 124: MAKE_FUNCTION        
 126: LOAD_FAST            grouped
 128: GET_ITER             
 130: PRECALL              
 134: CALL                 
 144: PRECALL              
 148: CALL                 
 158: RETURN_VALUE         
