# Disassembly for importlib.EntryPoints._from_text.<genexpr>
# From module file: importlib.metadata

## co_consts:
(('name', 'value', 'group'), None)

## co_names:
('EntryPoint', 'value', 'name')

## bytecode:

   0: RETURN_GENERATOR     
   2: POP_TOP              
   4: RESUME               
   6: LOAD_FAST            .0
   8: FOR_ITER             to 104
  10: STORE_FAST           item
  12: LOAD_GLOBAL          NULL + EntryPoint
  24: LOAD_FAST            item
  26: LOAD_ATTR            value
  36: LOAD_ATTR            name
  46: LOAD_FAST            item
  48: LOAD_ATTR            value
  58: LOAD_ATTR            value
  68: LOAD_FAST            item
  70: LOAD_ATTR            name
  80: KW_NAMES             
  82: PRECALL              
  86: CALL                 
  96: YIELD_VALUE          
  98: RESUME               
 100: POP_TOP              
 102: JUMP_BACKWARD        to 8
 104: LOAD_CONST           None
 106: RETURN_VALUE         
