# Disassembly for importlib.spec_from_file_location
# From module file: importlib._bootstrap_external

## co_consts:
('Return a module spec based on a file location.\n\n    To indicate that the module is a package, set\n    submodule_search_locations to a list of directory paths.  An\n    empty list is sufficient, though its not otherwise useful to the\n    import system.\n\n    The loader must take a spec as its only __init__() arg.\n\n    ', None, '<unknown>', 'get_filename', ('origin',), True, 'is_package', 0)

## co_names:
('hasattr', 'get_filename', 'ImportError', '_os', 'fspath', '_path_isabs', '_path_join', 'getcwd', 'OSError', '_bootstrap', 'ModuleSpec', '_set_fileattr', '_get_supported_file_loaders', 'endswith', 'tuple', 'loader', '_POPULATE', 'is_package', 'submodule_search_locations', '_path_split', 'append')

## bytecode:

   0: RESUME               
   2: LOAD_FAST            location
   4: POP_JUMP_FORWARD_IF_NOT_NONE to 122
   6: LOAD_CONST           '<unknown>'
   8: STORE_FAST           location
  10: LOAD_GLOBAL          NULL + hasattr
  22: LOAD_FAST            loader
  24: LOAD_CONST           'get_filename'
  26: PRECALL              
  30: CALL                 
  40: POP_JUMP_FORWARD_IF_FALSE to 120
  42: NOP                  
  44: LOAD_FAST            loader
  46: LOAD_METHOD          get_filename
  68: LOAD_FAST            name
  70: PRECALL              
  74: CALL                 
  84: STORE_FAST           location
  86: JUMP_FORWARD         to 294
  88: PUSH_EXC_INFO        
  90: LOAD_GLOBAL          ImportError
 102: CHECK_EXC_MATCH      
 104: POP_JUMP_FORWARD_IF_FALSE to 112
 106: POP_TOP              
 108: POP_EXCEPT           
 110: JUMP_FORWARD         to 294
 112: RERAISE              
 114: COPY                 
 116: POP_EXCEPT           
 118: RERAISE              
 120: JUMP_FORWARD         to 294
 122: LOAD_GLOBAL          NULL + _os
 134: LOAD_ATTR            fspath
 144: LOAD_FAST            location
 146: PRECALL              
 150: CALL                 
 160: STORE_FAST           location
 162: LOAD_GLOBAL          NULL + _path_isabs
 174: LOAD_FAST            location
 176: PRECALL              
 180: CALL                 
 190: POP_JUMP_FORWARD_IF_TRUE to 294
 192: NOP                  
 194: LOAD_GLOBAL          NULL + _path_join
 206: LOAD_GLOBAL          NULL + _os
 218: LOAD_ATTR            getcwd
 228: PRECALL              
 232: CALL                 
 242: LOAD_FAST            location
 244: PRECALL              
 248: CALL                 
 258: STORE_FAST           location
 260: JUMP_FORWARD         to 294
 262: PUSH_EXC_INFO        
 264: LOAD_GLOBAL          OSError
 276: CHECK_EXC_MATCH      
 278: POP_JUMP_FORWARD_IF_FALSE to 286
 280: POP_TOP              
 282: POP_EXCEPT           
 284: JUMP_FORWARD         to 294
 286: RERAISE              
 288: COPY                 
 290: POP_EXCEPT           
 292: RERAISE              
 294: LOAD_GLOBAL          _bootstrap
 306: LOAD_METHOD          ModuleSpec
 328: LOAD_FAST            name
 330: LOAD_FAST            loader
 332: LOAD_FAST            location
 334: KW_NAMES             
 336: PRECALL              
 340: CALL                 
 350: STORE_FAST           spec
 352: LOAD_CONST           True
 354: LOAD_FAST            spec
 356: STORE_ATTR           _set_fileattr
 366: LOAD_FAST            loader
 368: POP_JUMP_FORWARD_IF_NOT_NONE to 524
 370: LOAD_GLOBAL          NULL + _get_supported_file_loaders
 382: PRECALL              
 386: CALL                 
 396: GET_ITER             
 398: FOR_ITER             to 520
 400: UNPACK_SEQUENCE      
 404: STORE_FAST           loader_class
 406: STORE_FAST           suffixes
 408: LOAD_FAST            location
 410: LOAD_METHOD          endswith
 432: LOAD_GLOBAL          NULL + tuple
 444: LOAD_FAST            suffixes
 446: PRECALL              
 450: CALL                 
 460: PRECALL              
 464: CALL                 
 474: POP_JUMP_FORWARD_IF_FALSE to 518
 476: PUSH_NULL            
 478: LOAD_FAST            loader_class
 480: LOAD_FAST            name
 482: LOAD_FAST            location
 484: PRECALL              
 488: CALL                 
 498: STORE_FAST           loader
 500: LOAD_FAST            loader
 502: LOAD_FAST            spec
 504: STORE_ATTR           loader
 514: POP_TOP              
 516: JUMP_FORWARD         to 524
 518: JUMP_BACKWARD        to 398
 520: LOAD_CONST           None
 522: RETURN_VALUE         
 524: LOAD_FAST            submodule_search_locations
 526: LOAD_GLOBAL          _POPULATE
 538: IS_OP                
 540: POP_JUMP_FORWARD_IF_FALSE to 672
 542: LOAD_GLOBAL          NULL + hasattr
 554: LOAD_FAST            loader
 556: LOAD_CONST           'is_package'
 558: PRECALL              
 562: CALL                 
 572: POP_JUMP_FORWARD_IF_FALSE to 670
 574: NOP                  
 576: LOAD_FAST            loader
 578: LOAD_METHOD          is_package
 600: LOAD_FAST            name
 602: PRECALL              
 606: CALL                 
 616: STORE_FAST           is_package
 618: LOAD_FAST            is_package
 620: POP_JUMP_FORWARD_IF_FALSE to 636
 622: BUILD_LIST           
 624: LOAD_FAST            spec
 626: STORE_ATTR           submodule_search_locations
 636: JUMP_FORWARD         to 686
 638: PUSH_EXC_INFO        
 640: LOAD_GLOBAL          ImportError
 652: CHECK_EXC_MATCH      
 654: POP_JUMP_FORWARD_IF_FALSE to 662
 656: POP_TOP              
 658: POP_EXCEPT           
 660: JUMP_FORWARD         to 686
 662: RERAISE              
 664: COPY                 
 666: POP_EXCEPT           
 668: RERAISE              
 670: JUMP_FORWARD         to 686
 672: LOAD_FAST            submodule_search_locations
 674: LOAD_FAST            spec
 676: STORE_ATTR           submodule_search_locations
 686: LOAD_FAST            spec
 688: LOAD_ATTR            submodule_search_locations
 698: BUILD_LIST           
 700: COMPARE_OP           ==
 706: POP_JUMP_FORWARD_IF_FALSE to 806
 708: LOAD_FAST            location
 710: POP_JUMP_FORWARD_IF_FALSE to 806
 712: LOAD_GLOBAL          NULL + _path_split
 724: LOAD_FAST            location
 726: PRECALL              
 730: CALL                 
 740: LOAD_CONST           0
 742: BINARY_SUBSCR        
 752: STORE_FAST           dirname
 754: LOAD_FAST            spec
 756: LOAD_ATTR            submodule_search_locations
 766: LOAD_METHOD          append
 788: LOAD_FAST            dirname
 790: PRECALL              
 794: CALL                 
 804: POP_TOP              
 806: LOAD_FAST            spec
 808: RETURN_VALUE         
