# Disassembly for importlib._check_name._check_name_wrapper
# From module file: importlib._bootstrap_external

## co_consts:
(None, 'loader for ', ' cannot handle ', ('name',))

## co_names:
('name', 'ImportError')

## bytecode:

   0: COPY_FREE_VARS       
   2: RESUME               
   4: LOAD_FAST            name
   6: POP_JUMP_FORWARD_IF_NOT_NONE to 24
   8: LOAD_FAST            self
  10: LOAD_ATTR            name
  20: STORE_FAST           name
  22: JUMP_FORWARD         to 102
  24: LOAD_FAST            self
  26: LOAD_ATTR            name
  36: LOAD_FAST            name
  38: COMPARE_OP           !=
  44: POP_JUMP_FORWARD_IF_FALSE to 102
  46: LOAD_GLOBAL          NULL + ImportError
  58: LOAD_CONST           'loader for '
  60: LOAD_FAST            self
  62: LOAD_ATTR            name
  72: FORMAT_VALUE         str
  74: LOAD_CONST           ' cannot handle '
  76: LOAD_FAST            name
  78: FORMAT_VALUE         str
  80: BUILD_STRING         
  82: LOAD_FAST            name
  84: KW_NAMES             
  86: PRECALL              
  90: CALL                 
 100: RAISE_VARARGS        
 102: PUSH_NULL            
 104: LOAD_DEREF           method
 106: LOAD_FAST            self
 108: LOAD_FAST            name
 110: BUILD_LIST           
 112: LOAD_FAST            args
 114: LIST_EXTEND          
 116: LIST_TO_TUPLE        
 118: BUILD_MAP            
 120: LOAD_FAST            kwargs
 122: DICT_MERGE           
 124: CALL_FUNCTION_EX     
 126: RETURN_VALUE         
