# Disassembly for importlib.EntryPoint.__iter__
# From module file: importlib.metadata

## co_consts:
('\n        Supply iter so one may construct dicts of EntryPoints by name.\n        ', 'Construction of dict of EntryPoints is deprecated in favor of EntryPoints.')

## co_names:
('warnings', 'warn', 'DeprecationWarning', 'iter', 'name')

## bytecode:

   0: RESUME               
   2: LOAD_CONST           'Construction of dict of EntryPoints is deprecated in favor of EntryPoints.'
   4: STORE_FAST           msg
   6: LOAD_GLOBAL          NULL + warnings
  18: LOAD_ATTR            warn
  28: LOAD_FAST            msg
  30: LOAD_GLOBAL          DeprecationWarning
  42: PRECALL              
  46: CALL                 
  56: POP_TOP              
  58: LOAD_GLOBAL          NULL + iter
  70: LOAD_FAST            self
  72: LOAD_ATTR            name
  82: LOAD_FAST            self
  84: BUILD_TUPLE          
  86: PRECALL              
  90: CALL                 
 100: RETURN_VALUE         
