# Disassembly for importlib.BuiltinImporter.module_repr
# From module file: importlib._bootstrap

## co_consts:
('Return repr for the module.\n\n        The method is deprecated.  The import machinery does the job itself.\n\n        ', 'BuiltinImporter.module_repr() is deprecated and slated for removal in Python 3.12', '<module ', ' (', ')>')

## co_names:
('_warnings', 'warn', 'DeprecationWarning', '__name__', 'BuiltinImporter', '_ORIGIN')

## bytecode:

   0: RESUME               
   2: LOAD_GLOBAL          _warnings
  14: LOAD_METHOD          warn
  36: LOAD_CONST           'BuiltinImporter.module_repr() is deprecated and slated for removal in Python 3.12'
  38: LOAD_GLOBAL          DeprecationWarning
  50: PRECALL              
  54: CALL                 
  64: POP_TOP              
  66: LOAD_CONST           '<module '
  68: LOAD_FAST            module
  70: LOAD_ATTR            __name__
  80: FORMAT_VALUE         repr
  82: LOAD_CONST           ' ('
  84: LOAD_GLOBAL          BuiltinImporter
  96: LOAD_ATTR            _ORIGIN
 106: FORMAT_VALUE         
 108: LOAD_CONST           ')>'
 110: BUILD_STRING         
 112: RETURN_VALUE         
