# Disassembly for importlib.ModuleSpec.parent
# From module file: importlib._bootstrap

## co_consts:
("The name of the module's parent.", None, '.', 0)

## co_names:
('submodule_search_locations', 'name', 'rpartition')

## bytecode:

   0: RESUME               
   2: LOAD_FAST            self
   4: LOAD_ATTR            submodule_search_locations
  14: POP_JUMP_FORWARD_IF_NOT_NONE to 80
  16: LOAD_FAST            self
  18: LOAD_ATTR            name
  28: LOAD_METHOD          rpartition
  50: LOAD_CONST           '.'
  52: PRECALL              
  56: CALL                 
  66: LOAD_CONST           0
  68: BINARY_SUBSCR        
  78: RETURN_VALUE         
  80: LOAD_FAST            self
  82: LOAD_ATTR            name
  92: RETURN_VALUE         
