# Disassembly for importlib.FrozenImporter.load_module
# From module file: importlib._bootstrap

## co_consts:
('Load a frozen module.\n\n        This method is deprecated.  Use exec_module() instead.\n\n        ', None, '__file__')

## co_names:
('_load_module_shim', '_imp', 'find_frozen', '__origname__', 'vars', 'pop', '__path__', '_fix_up_module')

## bytecode:

   0: RESUME               
   2: LOAD_GLOBAL          NULL + _load_module_shim
  14: LOAD_FAST            cls
  16: LOAD_FAST            fullname
  18: PRECALL              
  22: CALL                 
  32: STORE_FAST           module
  34: LOAD_GLOBAL          _imp
  46: LOAD_METHOD          find_frozen
  68: LOAD_FAST            fullname
  70: PRECALL              
  74: CALL                 
  84: STORE_FAST           info
  86: LOAD_FAST            info
  88: POP_JUMP_FORWARD_IF_NOT_NONE to 94
  90: LOAD_ASSERTION_ERROR 
  92: RAISE_VARARGS        
  94: LOAD_FAST            info
  96: UNPACK_SEQUENCE      
 100: STORE_FAST           _
 102: STORE_FAST           ispkg
 104: STORE_FAST           origname
 106: LOAD_FAST            origname
 108: LOAD_FAST            module
 110: STORE_ATTR           __origname__
 120: LOAD_GLOBAL          NULL + vars
 132: LOAD_FAST            module
 134: PRECALL              
 138: CALL                 
 148: LOAD_METHOD          pop
 170: LOAD_CONST           '__file__'
 172: LOAD_CONST           None
 174: PRECALL              
 178: CALL                 
 188: POP_TOP              
 190: LOAD_FAST            ispkg
 192: POP_JUMP_FORWARD_IF_FALSE to 208
 194: BUILD_LIST           
 196: LOAD_FAST            module
 198: STORE_ATTR           __path__
 208: LOAD_FAST            cls
 210: LOAD_METHOD          _fix_up_module
 232: LOAD_FAST            module
 234: PRECALL              
 238: CALL                 
 248: POP_TOP              
 250: LOAD_FAST            module
 252: RETURN_VALUE         
