# Disassembly for importlib._top_level_declared
# From module file: importlib.metadata

## co_consts:
(None, 'top_level.txt', '')

## co_names:
('read_text', 'split')

## bytecode:

   0: RESUME               
   2: LOAD_FAST            dist
   4: LOAD_METHOD          read_text
  26: LOAD_CONST           'top_level.txt'
  28: PRECALL              
  32: CALL                 
  42: JUMP_IF_TRUE_OR_POP  to 46
  44: LOAD_CONST           ''
  46: LOAD_METHOD          split
  68: PRECALL              
  72: CALL                 
  82: RETURN_VALUE         
