# Disassembly for importlib.ModuleSpec
# From module file: importlib._bootstrap

## co_consts:
('ModuleSpec', 'The specification for a module, used for loading.\n\n    A module\'s spec is the source for information about the module.  For\n    data associated with the module, including source, use the spec\'s\n    loader.\n\n    `name` is the absolute name of the module.  `loader` is the loader\n    to use when loading the module.  `parent` is the name of the\n    package the module is in.  The parent is derived from the name.\n\n    `is_package` determines if the module is considered a package or\n    not.  On modules this is reflected by the `__path__` attribute.\n\n    `origin` is the specific location used by the loader from which to\n    load the module, if that information is available.  When filename is\n    set, origin will match.\n\n    `has_location` indicates that a spec\'s "origin" reflects a location.\n    When this is True, `__file__` attribute of the module is set.\n\n    `cached` is the location of the cached bytecode file, if any.  It\n    corresponds to the `__cached__` attribute.\n\n    `submodule_search_locations` is the sequence of path entries to\n    search when importing submodules.  If set, is_package should be\n    True--and False otherwise.\n\n    Packages are simply modules that (may) have submodules.  If a spec\n    has a non-None value in `submodule_search_locations`, the import\n    system will consider modules loaded from the spec as packages.\n\n    Only finders (see importlib.abc.MetaPathFinder and\n    importlib.abc.PathEntryFinder) should modify ModuleSpec instances.\n\n    ', None, ('origin', 'loader_state', 'is_package'), <code object __init__ at 0x00000240693AB4B0, file "importlib\_bootstrap.py", line 357>, <code object __repr__ at 0x0000024068BB6BE0, file "importlib\_bootstrap.py", line 370>, <code object __eq__ at 0x000002406934FCF0, file "importlib\_bootstrap.py", line 380>, <code object cached at 0x00000240691C0F50, file "importlib\_bootstrap.py", line 392>, <code object cached at 0x00000240694941D0, file "importlib\_bootstrap.py", line 401>, <code object parent at 0x000002406941AAF0, file "importlib\_bootstrap.py", line 405>, <code object has_location at 0x0000024069495550, file "importlib\_bootstrap.py", line 413>, <code object has_location at 0x000002406945ED30, file "importlib\_bootstrap.py", line 417>)

## co_names:
('__name__', '__module__', '__qualname__', '__doc__', '__init__', '__repr__', '__eq__', 'property', 'cached', 'setter', 'parent', 'has_location')

## bytecode:

   0: RESUME               
   2: LOAD_NAME            __name__
   4: STORE_NAME           __module__
   6: LOAD_CONST           'ModuleSpec'
   8: STORE_NAME           __qualname__
  10: LOAD_CONST           'The specification for a module, used for loading.\n\n    A module\'s spec is the source for information about the module.  For\n    data associated with the module, including source, use the spec\'s\n    loader.\n\n    `name` is the absolute name of the module.  `loader` is the loader\n    to use when loading the module.  `parent` is the name of the\n    package the module is in.  The parent is derived from the name.\n\n    `is_package` determines if the module is considered a package or\n    not.  On modules this is reflected by the `__path__` attribute.\n\n    `origin` is the specific location used by the loader from which to\n    load the module, if that information is available.  When filename is\n    set, origin will match.\n\n    `has_location` indicates that a spec\'s "origin" reflects a location.\n    When this is True, `__file__` attribute of the module is set.\n\n    `cached` is the location of the cached bytecode file, if any.  It\n    corresponds to the `__cached__` attribute.\n\n    `submodule_search_locations` is the sequence of path entries to\n    search when importing submodules.  If set, is_package should be\n    True--and False otherwise.\n\n    Packages are simply modules that (may) have submodules.  If a spec\n    has a non-None value in `submodule_search_locations`, the import\n    system will consider modules loaded from the spec as packages.\n\n    Only finders (see importlib.abc.MetaPathFinder and\n    importlib.abc.PathEntryFinder) should modify ModuleSpec instances.\n\n    '
  12: STORE_NAME           __doc__
  14: LOAD_CONST           None
  16: LOAD_CONST           None
  18: LOAD_CONST           None
  20: LOAD_CONST           ('origin', 'loader_state', 'is_package')
  22: BUILD_CONST_KEY_MAP  
  24: LOAD_CONST           <code object __init__ at 0x00000240693AB4B0, file "importlib\_bootstrap.py", line 357>
  26: MAKE_FUNCTION        kwdefaults
  28: STORE_NAME           __init__
  30: LOAD_CONST           <code object __repr__ at 0x0000024068BB6BE0, file "importlib\_bootstrap.py", line 370>
  32: MAKE_FUNCTION        
  34: STORE_NAME           __repr__
  36: LOAD_CONST           <code object __eq__ at 0x000002406934FCF0, file "importlib\_bootstrap.py", line 380>
  38: MAKE_FUNCTION        
  40: STORE_NAME           __eq__
  42: LOAD_NAME            property
  44: LOAD_CONST           <code object cached at 0x00000240691C0F50, file "importlib\_bootstrap.py", line 392>
  46: MAKE_FUNCTION        
  48: PRECALL              
  52: CALL                 
  62: STORE_NAME           cached
  64: LOAD_NAME            cached
  66: LOAD_ATTR            setter
  76: LOAD_CONST           <code object cached at 0x00000240694941D0, file "importlib\_bootstrap.py", line 401>
  78: MAKE_FUNCTION        
  80: PRECALL              
  84: CALL                 
  94: STORE_NAME           cached
  96: LOAD_NAME            property
  98: LOAD_CONST           <code object parent at 0x000002406941AAF0, file "importlib\_bootstrap.py", line 405>
 100: MAKE_FUNCTION        
 102: PRECALL              
 106: CALL                 
 116: STORE_NAME           parent
 118: LOAD_NAME            property
 120: LOAD_CONST           <code object has_location at 0x0000024069495550, file "importlib\_bootstrap.py", line 413>
 122: MAKE_FUNCTION        
 124: PRECALL              
 128: CALL                 
 138: STORE_NAME           has_location
 140: LOAD_NAME            has_location
 142: LOAD_ATTR            setter
 152: LOAD_CONST           <code object has_location at 0x000002406945ED30, file "importlib\_bootstrap.py", line 417>
 154: MAKE_FUNCTION        
 156: PRECALL              
 160: CALL                 
 170: STORE_NAME           has_location
 172: LOAD_CONST           None
 174: RETURN_VALUE         
