# Disassembly for importlib.Distribution._read_files_distinfo
# From module file: importlib.metadata

## co_consts:
('\n        Read the lines of RECORD\n        ', 'RECORD')

## co_names:
('read_text', 'splitlines')

## bytecode:

   0: RESUME               
   2: LOAD_FAST            self
   4: LOAD_METHOD          read_text
  26: LOAD_CONST           'RECORD'
  28: PRECALL              
  32: CALL                 
  42: STORE_FAST           text
  44: LOAD_FAST            text
  46: JUMP_IF_FALSE_OR_POP to 86
  48: LOAD_FAST            text
  50: LOAD_METHOD          splitlines
  72: PRECALL              
  76: CALL                 
  86: RETURN_VALUE         
