# Disassembly for importlib._compile_bytecode
# From module file: importlib._bootstrap_external

## co_consts:
('Compile bytecode as found in a pyc.', 'code object from {!r}', None, 'Non-code object in {!r}', ('name', 'path'))

## co_names:
('marshal', 'loads', 'isinstance', '_code_type', '_bootstrap', '_verbose_message', '_imp', '_fix_co_filename', 'ImportError', 'format')

## bytecode:

   0: RESUME               
   2: LOAD_GLOBAL          NULL + marshal
  14: LOAD_ATTR            loads
  24: LOAD_FAST            data
  26: PRECALL              
  30: CALL                 
  40: STORE_FAST           code
  42: LOAD_GLOBAL          NULL + isinstance
  54: LOAD_FAST            code
  56: LOAD_GLOBAL          _code_type
  68: PRECALL              
  72: CALL                 
  82: POP_JUMP_FORWARD_IF_FALSE to 188
  84: LOAD_GLOBAL          _bootstrap
  96: LOAD_METHOD          _verbose_message
 118: LOAD_CONST           'code object from {!r}'
 120: LOAD_FAST            bytecode_path
 122: PRECALL              
 126: CALL                 
 136: POP_TOP              
 138: LOAD_FAST            source_path
 140: POP_JUMP_FORWARD_IF_NONE to 184
 142: LOAD_GLOBAL          NULL + _imp
 154: LOAD_ATTR            _fix_co_filename
 164: LOAD_FAST            code
 166: LOAD_FAST            source_path
 168: PRECALL              
 172: CALL                 
 182: POP_TOP              
 184: LOAD_FAST            code
 186: RETURN_VALUE         
 188: LOAD_GLOBAL          NULL + ImportError
 200: LOAD_CONST           'Non-code object in {!r}'
 202: LOAD_METHOD          format
 224: LOAD_FAST            bytecode_path
 226: PRECALL              
 230: CALL                 
 240: LOAD_FAST            name
 242: LOAD_FAST            bytecode_path
 244: KW_NAMES             
 246: PRECALL              
 250: CALL                 
 260: RAISE_VARARGS        
