# Disassembly for importlib._builtin_from_name
# From module file: importlib._bootstrap

## co_consts:
(None, 'no built-in module named ')

## co_names:
('BuiltinImporter', 'find_spec', 'ImportError', '_load_unlocked')

## bytecode:

   0: RESUME               
   2: LOAD_GLOBAL          BuiltinImporter
  14: LOAD_METHOD          find_spec
  36: LOAD_FAST            name
  38: PRECALL              
  42: CALL                 
  52: STORE_FAST           spec
  54: LOAD_FAST            spec
  56: POP_JUMP_FORWARD_IF_NOT_NONE to 94
  58: LOAD_GLOBAL          NULL + ImportError
  70: LOAD_CONST           'no built-in module named '
  72: LOAD_FAST            name
  74: BINARY_OP            +
  78: PRECALL              
  82: CALL                 
  92: RAISE_VARARGS        
  94: LOAD_GLOBAL          NULL + _load_unlocked
 106: LOAD_FAST            spec
 108: PRECALL              
 112: CALL                 
 122: RETURN_VALUE         
