# Disassembly for importlib._LazyModule
# From module file: importlib.util

## co_consts:
('_LazyModule', 'A subclass of the module type which triggers loading upon attribute access.', <code object __getattribute__ at 0x0000024068DE6180, file "importlib\util.py", line 226>, <code object __delattr__ at 0x000002406944A9A0, file "importlib\util.py", line 260>, None)

## co_names:
('__name__', '__module__', '__qualname__', '__doc__', '__getattribute__', '__delattr__')

## bytecode:

   0: RESUME               
   2: LOAD_NAME            __name__
   4: STORE_NAME           __module__
   6: LOAD_CONST           '_LazyModule'
   8: STORE_NAME           __qualname__
  10: LOAD_CONST           'A subclass of the module type which triggers loading upon attribute access.'
  12: STORE_NAME           __doc__
  14: LOAD_CONST           <code object __getattribute__ at 0x0000024068DE6180, file "importlib\util.py", line 226>
  16: MAKE_FUNCTION        
  18: STORE_NAME           __getattribute__
  20: LOAD_CONST           <code object __delattr__ at 0x000002406944A9A0, file "importlib\util.py", line 260>
  22: MAKE_FUNCTION        
  24: STORE_NAME           __delattr__
  26: LOAD_CONST           None
  28: RETURN_VALUE         
