# Disassembly for importlib.metadata
# From module file: importlib.metadata

## co_consts:
('Get the metadata for the named package.\n\n    :param distribution_name: The name of the distribution package to query.\n    :return: A PackageMetadata containing the parsed metadata.\n    ',)

## co_names:
('Distribution', 'from_name', 'metadata')

## bytecode:

   0: RESUME               
   2: LOAD_GLOBAL          Distribution
  14: LOAD_METHOD          from_name
  36: LOAD_FAST            distribution_name
  38: PRECALL              
  42: CALL                 
  52: LOAD_ATTR            metadata
  62: RETURN_VALUE         
