# Disassembly for importlib.EntryPoint.matches
# From module file: importlib.metadata

## co_consts:
("\n        EntryPoint matches the given parameters.\n\n        >>> ep = EntryPoint(group='foo', name='bar', value='bing:bong [extra1, extra2]')\n        >>> ep.matches(group='foo')\n        True\n        >>> ep.matches(name='bar', value='bing:bong [extra1, extra2]')\n        True\n        >>> ep.matches(group='foo', name='other')\n        False\n        >>> ep.matches()\n        True\n        >>> ep.matches(extras=['extra1', 'extra2'])\n        True\n        >>> ep.matches(module='bing')\n        True\n        >>> ep.matches(attr='bong')\n        True\n        ", <code object <genexpr> at 0x000002406945E4C0, file "importlib\metadata\__init__.py", line 256>)

## co_names:
('all', 'map', 'operator', 'eq', 'values')

## bytecode:

   0: MAKE_CELL            self
   2: RESUME               
   4: LOAD_CLOSURE         self
   6: BUILD_TUPLE          
   8: LOAD_CONST           <code object <genexpr> at 0x000002406945E4C0, file "importlib\metadata\__init__.py", line 256>
  10: MAKE_FUNCTION        closure
  12: LOAD_FAST            params
  14: GET_ITER             
  16: PRECALL              
  20: CALL                 
  30: STORE_FAST           attrs
  32: LOAD_GLOBAL          NULL + all
  44: LOAD_GLOBAL          NULL + map
  56: LOAD_GLOBAL          operator
  68: LOAD_ATTR            eq
  78: LOAD_FAST            params
  80: LOAD_METHOD          values
 102: PRECALL              
 106: CALL                 
 116: LOAD_FAST            attrs
 118: PRECALL              
 122: CALL                 
 132: PRECALL              
 136: CALL                 
 146: RETURN_VALUE         
