# Disassembly for importlib.MetadataPathFinder.find_distributions
# From module file: importlib.metadata

## co_consts:
('\n        Find distributions.\n\n        Return an iterable of all Distribution instances capable of\n        loading the metadata for packages matching ``context.name``\n        (or all names if ``None`` indicated) along the paths in the list\n        of directories ``context.path``.\n        ',)

## co_names:
('_search_paths', 'name', 'path', 'map', 'PathDistribution')

## bytecode:

   0: RESUME               
   2: LOAD_FAST            cls
   4: LOAD_METHOD          _search_paths
  26: LOAD_FAST            context
  28: LOAD_ATTR            name
  38: LOAD_FAST            context
  40: LOAD_ATTR            path
  50: PRECALL              
  54: CALL                 
  64: STORE_FAST           found
  66: LOAD_GLOBAL          NULL + map
  78: LOAD_GLOBAL          PathDistribution
  90: LOAD_FAST            found
  92: PRECALL              
  96: CALL                 
 106: RETURN_VALUE         
