# Disassembly for importlib.Finder.__init__
# From module file: importlib.abc

## co_consts:
(None, 'the Finder ABC is deprecated and slated for removal in Python 3.12; use MetaPathFinder or PathEntryFinder instead')

## co_names:
('warnings', 'warn', 'DeprecationWarning')

## bytecode:

   0: RESUME               
   2: LOAD_GLOBAL          NULL + warnings
  14: LOAD_ATTR            warn
  24: LOAD_CONST           'the Finder ABC is deprecated and slated for removal in Python 3.12; use MetaPathFinder or PathEntryFinder instead'
  26: LOAD_GLOBAL          DeprecationWarning
  38: PRECALL              
  42: CALL                 
  52: POP_TOP              
  54: LOAD_CONST           None
  56: RETURN_VALUE         
