# Disassembly for importlib.BuiltinImporter.find_spec
# From module file: importlib._bootstrap

## co_consts:
(None, ('origin',))

## co_names:
('_imp', 'is_builtin', 'spec_from_loader', '_ORIGIN')

## bytecode:

   0: RESUME               
   2: LOAD_GLOBAL          _imp
  14: LOAD_METHOD          is_builtin
  36: LOAD_FAST            fullname
  38: PRECALL              
  42: CALL                 
  52: POP_JUMP_FORWARD_IF_FALSE to 100
  54: LOAD_GLOBAL          NULL + spec_from_loader
  66: LOAD_FAST            fullname
  68: LOAD_FAST            cls
  70: LOAD_FAST            cls
  72: LOAD_ATTR            _ORIGIN
  82: KW_NAMES             
  84: PRECALL              
  88: CALL                 
  98: RETURN_VALUE         
 100: LOAD_CONST           None
 102: RETURN_VALUE         
