# Disassembly for importlib.FrozenImporter.module_repr
# From module file: importlib._bootstrap

## co_consts:
('Return repr for the module.\n\n        The method is deprecated.  The import machinery does the job itself.\n\n        ', 'FrozenImporter.module_repr() is deprecated and slated for removal in Python 3.12', '<module {!r} ({})>')

## co_names:
('_warnings', 'warn', 'DeprecationWarning', 'format', '__name__', 'FrozenImporter', '_ORIGIN')

## bytecode:

   0: RESUME               
   2: LOAD_GLOBAL          _warnings
  14: LOAD_METHOD          warn
  36: LOAD_CONST           'FrozenImporter.module_repr() is deprecated and slated for removal in Python 3.12'
  38: LOAD_GLOBAL          DeprecationWarning
  50: PRECALL              
  54: CALL                 
  64: POP_TOP              
  66: LOAD_CONST           '<module {!r} ({})>'
  68: LOAD_METHOD          format
  90: LOAD_FAST            m
  92: LOAD_ATTR            __name__
 102: LOAD_GLOBAL          FrozenImporter
 114: LOAD_ATTR            _ORIGIN
 124: PRECALL              
 128: CALL                 
 138: RETURN_VALUE         
