# Disassembly for importlib.FastPath.zip_children
# From module file: importlib.metadata

## co_consts:
(None, <code object <genexpr> at 0x000002406941AD30, file "importlib\metadata\__init__.py", line 810>)

## co_names:
('zipfile', 'Path', 'root', 'namelist', 'joinpath', 'dict', 'fromkeys')

## bytecode:

   0: RESUME               
   2: LOAD_GLOBAL          NULL + zipfile
  14: LOAD_ATTR            Path
  24: LOAD_FAST            self
  26: LOAD_ATTR            root
  36: PRECALL              
  40: CALL                 
  50: STORE_FAST           zip_path
  52: LOAD_FAST            zip_path
  54: LOAD_ATTR            root
  64: LOAD_METHOD          namelist
  86: PRECALL              
  90: CALL                 
 100: STORE_FAST           names
 102: LOAD_FAST            zip_path
 104: LOAD_ATTR            joinpath
 114: LOAD_FAST            self
 116: STORE_ATTR           joinpath
 126: LOAD_GLOBAL          dict
 138: LOAD_METHOD          fromkeys
 160: LOAD_CONST           <code object <genexpr> at 0x000002406941AD30, file "importlib\metadata\__init__.py", line 810>
 162: MAKE_FUNCTION        
 164: LOAD_FAST            names
 166: GET_ITER             
 168: PRECALL              
 172: CALL                 
 182: PRECALL              
 186: CALL                 
 196: RETURN_VALUE         
