# Disassembly for importlib.SelectableGroups._all
# From module file: importlib.metadata

## co_consts:
('\n        Reconstruct a list of all entrypoints from the groups.\n        ',)

## co_names:
('super', 'Deprecated', 'values', 'EntryPoints', 'itertools', 'chain', 'from_iterable')

## bytecode:

   0: COPY_FREE_VARS       
   2: RESUME               
   4: LOAD_GLOBAL          NULL + super
  16: LOAD_GLOBAL          Deprecated
  28: LOAD_FAST            self
  30: PRECALL              
  34: CALL                 
  44: LOAD_METHOD          values
  66: PRECALL              
  70: CALL                 
  80: STORE_FAST           groups
  82: LOAD_GLOBAL          NULL + EntryPoints
  94: LOAD_GLOBAL          itertools
 106: LOAD_ATTR            chain
 116: LOAD_METHOD          from_iterable
 138: LOAD_FAST            groups
 140: PRECALL              
 144: CALL                 
 154: PRECALL              
 158: CALL                 
 168: RETURN_VALUE         
