# Disassembly for importlib.ExtensionFileLoader.__hash__
# From module file: importlib._bootstrap_external

## co_consts:
(None,)

## co_names:
('hash', 'name', 'path')

## bytecode:

   0: RESUME               
   2: LOAD_GLOBAL          NULL + hash
  14: LOAD_FAST            self
  16: LOAD_ATTR            name
  26: PRECALL              
  30: CALL                 
  40: LOAD_GLOBAL          NULL + hash
  52: LOAD_FAST            self
  54: LOAD_ATTR            path
  64: PRECALL              
  68: CALL                 
  78: BINARY_OP            ^
  82: RETURN_VALUE         
