# Disassembly for importlib._gcd_import
# From module file: importlib._bootstrap

## co_consts:
('Import and return the module based on its name, the package the call is\n    being made from, and the level adjustment.\n\n    This function represents the greatest common denominator of functionality\n    between import_module and __import__. This includes setting __package__ if\n    the loader did not.\n\n    ', 0)

## co_names:
('_sanity_check', '_resolve_name', '_find_and_load', '_gcd_import')

## bytecode:

   0: RESUME               
   2: LOAD_GLOBAL          NULL + _sanity_check
  14: LOAD_FAST            name
  16: LOAD_FAST            package
  18: LOAD_FAST            level
  20: PRECALL              
  24: CALL                 
  34: POP_TOP              
  36: LOAD_FAST            level
  38: LOAD_CONST           0
  40: COMPARE_OP           >
  46: POP_JUMP_FORWARD_IF_FALSE to 82
  48: LOAD_GLOBAL          NULL + _resolve_name
  60: LOAD_FAST            name
  62: LOAD_FAST            package
  64: LOAD_FAST            level
  66: PRECALL              
  70: CALL                 
  80: STORE_FAST           name
  82: LOAD_GLOBAL          NULL + _find_and_load
  94: LOAD_FAST            name
  96: LOAD_GLOBAL          _gcd_import
 108: PRECALL              
 112: CALL                 
 122: RETURN_VALUE         
