# Disassembly for importlib.set_package.set_package_wrapper
# From module file: importlib.util

## co_consts:
(None, 'The import system now takes care of this automatically; this decorator is slated for removal in Python 3.12', 2, ('stacklevel',), '__package__', '__path__', '.', 0)

## co_names:
('warnings', 'warn', 'DeprecationWarning', 'getattr', '__name__', '__package__', 'hasattr', 'rpartition')

## bytecode:

   0: COPY_FREE_VARS       
   2: RESUME               
   4: LOAD_GLOBAL          NULL + warnings
  16: LOAD_ATTR            warn
  26: LOAD_CONST           'The import system now takes care of this automatically; this decorator is slated for removal in Python 3.12'
  28: LOAD_GLOBAL          DeprecationWarning
  40: LOAD_CONST           2
  42: KW_NAMES             
  44: PRECALL              
  48: CALL                 
  58: POP_TOP              
  60: PUSH_NULL            
  62: LOAD_DEREF           fxn
  64: LOAD_FAST            args
  66: BUILD_MAP            
  68: LOAD_FAST            kwargs
  70: DICT_MERGE           
  72: CALL_FUNCTION_EX     
  74: STORE_FAST           module
  76: LOAD_GLOBAL          NULL + getattr
  88: LOAD_FAST            module
  90: LOAD_CONST           '__package__'
  92: LOAD_CONST           None
  94: PRECALL              
  98: CALL                 
 108: POP_JUMP_FORWARD_IF_NOT_NONE to 240
 110: LOAD_FAST            module
 112: LOAD_ATTR            __name__
 122: LOAD_FAST            module
 124: STORE_ATTR           __package__
 134: LOAD_GLOBAL          NULL + hasattr
 146: LOAD_FAST            module
 148: LOAD_CONST           '__path__'
 150: PRECALL              
 154: CALL                 
 164: POP_JUMP_FORWARD_IF_TRUE to 240
 166: LOAD_FAST            module
 168: LOAD_ATTR            __package__
 178: LOAD_METHOD          rpartition
 200: LOAD_CONST           '.'
 202: PRECALL              
 206: CALL                 
 216: LOAD_CONST           0
 218: BINARY_SUBSCR        
 228: LOAD_FAST            module
 230: STORE_ATTR           __package__
 240: LOAD_FAST            module
 242: RETURN_VALUE         
