# Disassembly for importlib.MetaPathFinder.find_module
# From module file: importlib.abc

## co_consts:
('Return a loader for the module.\n\n        If no module is found, return None.  The fullname is a str and\n        the path is a list of strings or None.\n\n        This method is deprecated since Python 3.4 in favor of\n        finder.find_spec(). If find_spec() exists then backwards-compatible\n        functionality is provided for this method.\n\n        ', 'MetaPathFinder.find_module() is deprecated since Python 3.4 in favor of MetaPathFinder.find_spec() and is slated for removal in Python 3.12', 2, ('stacklevel',), 'find_spec', None)

## co_names:
('warnings', 'warn', 'DeprecationWarning', 'hasattr', 'find_spec', 'loader')

## bytecode:

   0: RESUME               
   2: LOAD_GLOBAL          NULL + warnings
  14: LOAD_ATTR            warn
  24: LOAD_CONST           'MetaPathFinder.find_module() is deprecated since Python 3.4 in favor of MetaPathFinder.find_spec() and is slated for removal in Python 3.12'
  26: LOAD_GLOBAL          DeprecationWarning
  38: LOAD_CONST           2
  40: KW_NAMES             
  42: PRECALL              
  46: CALL                 
  56: POP_TOP              
  58: LOAD_GLOBAL          NULL + hasattr
  70: LOAD_FAST            self
  72: LOAD_CONST           'find_spec'
  74: PRECALL              
  78: CALL                 
  88: POP_JUMP_FORWARD_IF_TRUE to 94
  90: LOAD_CONST           None
  92: RETURN_VALUE         
  94: LOAD_FAST            self
  96: LOAD_METHOD          find_spec
 118: LOAD_FAST            fullname
 120: LOAD_FAST            path
 122: PRECALL              
 126: CALL                 
 136: STORE_FAST           found
 138: LOAD_FAST            found
 140: POP_JUMP_FORWARD_IF_NONE to 156
 142: LOAD_FAST            found
 144: LOAD_ATTR            loader
 154: JUMP_FORWARD         to 158
 156: LOAD_CONST           None
 158: RETURN_VALUE         
