# Disassembly for signal._enum_to_int
# From module file: signal

## co_consts:
("Convert an IntEnum member to a numeric value.\n    If it's not an IntEnum member return the value itself.\n    ",)

## co_names:
('int', 'ValueError', 'TypeError')

## bytecode:

   0: RESUME               
   2: NOP                  
   4: LOAD_GLOBAL          NULL + int
  16: LOAD_FAST            value
  18: PRECALL              
  22: CALL                 
  32: RETURN_VALUE         
  34: PUSH_EXC_INFO        
  36: LOAD_GLOBAL          ValueError
  48: LOAD_GLOBAL          TypeError
  60: BUILD_TUPLE          
  62: CHECK_EXC_MATCH      
  64: POP_JUMP_FORWARD_IF_FALSE to 76
  66: POP_TOP              
  68: LOAD_FAST            value
  70: SWAP                 
  72: POP_EXCEPT           
  74: RETURN_VALUE         
  76: RERAISE              
  78: COPY                 
  80: POP_EXCEPT           
  82: RERAISE              
