# Disassembly for signal.sigwait
# From module file: signal

## co_consts:
(None,)

## co_names:
('_signal', 'sigwait', '_int_to_enum', 'Signals')

## bytecode:

   0: RESUME               
   2: LOAD_GLOBAL          NULL + _signal
  14: LOAD_ATTR            sigwait
  24: LOAD_FAST            sigset
  26: PRECALL              
  30: CALL                 
  40: STORE_FAST           retsig
  42: LOAD_GLOBAL          NULL + _int_to_enum
  54: LOAD_FAST            retsig
  56: LOAD_GLOBAL          Signals
  68: PRECALL              
  72: CALL                 
  82: RETURN_VALUE         
