# Disassembly for signal.getsignal
# From module file: signal

## co_consts:
(None,)

## co_names:
('_signal', 'getsignal', '_int_to_enum', 'Handlers')

## bytecode:

   0: RESUME               
   2: LOAD_GLOBAL          NULL + _signal
  14: LOAD_ATTR            getsignal
  24: LOAD_FAST            signalnum
  26: PRECALL              
  30: CALL                 
  40: STORE_FAST           handler
  42: LOAD_GLOBAL          NULL + _int_to_enum
  54: LOAD_FAST            handler
  56: LOAD_GLOBAL          Handlers
  68: PRECALL              
  72: CALL                 
  82: RETURN_VALUE         
