# Disassembly for signal
# From module file: signal

## co_consts:
(0, None, ('*',), ('IntEnum',), 'Signals', <code object <lambda> at 0x000002406921F9B0, file "signal.py", line 9>, 'Handlers', <code object <lambda> at 0x0000024069494850, file "signal.py", line 16>, 'pthread_sigmask', 'Sigmasks', <code object <lambda> at 0x0000024069495140, file "signal.py", line 21>, <code object _int_to_enum at 0x00000240693EBA30, file "signal.py", line 24>, <code object _enum_to_int at 0x000002406944ABC0, file "signal.py", line 34>, <code object _wraps at 0x00000240694949F0, file "signal.py", line 48>, <code object signal at 0x00000240691F39F0, file "signal.py", line 54>, <code object getsignal at 0x000002406944A890, file "signal.py", line 60>, <code object pthread_sigmask at 0x000002406941B2D0, file "signal.py", line 67>, 'sigpending', <code object sigpending at 0x00000240693EB230, file "signal.py", line 74>, 'sigwait', <code object sigwait at 0x000002406944B110, file "signal.py", line 80>, 'valid_signals', <code object valid_signals at 0x00000240693EA930, file "signal.py", line 87>)

## co_names:
('_signal', 'enum', 'IntEnum', '_IntEnum', 'globals', '_globals', '_convert_', '__name__', '_int_to_enum', '_enum_to_int', '_wraps', 'signal', 'getsignal', 'pthread_sigmask', 'sigpending', 'sigwait', 'valid_signals')

## bytecode:

   0: RESUME               
   2: LOAD_CONST           0
   4: LOAD_CONST           None
   6: IMPORT_NAME          _signal
   8: STORE_NAME           _signal
  10: LOAD_CONST           0
  12: LOAD_CONST           ('*',)
  14: IMPORT_NAME          _signal
  16: IMPORT_STAR          
  18: LOAD_CONST           0
  20: LOAD_CONST           ('IntEnum',)
  22: IMPORT_NAME          enum
  24: IMPORT_FROM          IntEnum
  26: STORE_NAME           _IntEnum
  28: POP_TOP              
  30: PUSH_NULL            
  32: LOAD_NAME            globals
  34: PRECALL              
  38: CALL                 
  48: STORE_NAME           _globals
  50: PUSH_NULL            
  52: LOAD_NAME            _IntEnum
  54: LOAD_ATTR            _convert_
  64: LOAD_CONST           'Signals'
  66: LOAD_NAME            __name__
  68: LOAD_CONST           <code object <lambda> at 0x000002406921F9B0, file "signal.py", line 9>
  70: MAKE_FUNCTION        
  72: PRECALL              
  76: CALL                 
  86: POP_TOP              
  88: PUSH_NULL            
  90: LOAD_NAME            _IntEnum
  92: LOAD_ATTR            _convert_
 102: LOAD_CONST           'Handlers'
 104: LOAD_NAME            __name__
 106: LOAD_CONST           <code object <lambda> at 0x0000024069494850, file "signal.py", line 16>
 108: MAKE_FUNCTION        
 110: PRECALL              
 114: CALL                 
 124: POP_TOP              
 126: LOAD_CONST           'pthread_sigmask'
 128: LOAD_NAME            _globals
 130: CONTAINS_OP          
 132: POP_JUMP_FORWARD_IF_FALSE to 172
 134: PUSH_NULL            
 136: LOAD_NAME            _IntEnum
 138: LOAD_ATTR            _convert_
 148: LOAD_CONST           'Sigmasks'
 150: LOAD_NAME            __name__
 152: LOAD_CONST           <code object <lambda> at 0x0000024069495140, file "signal.py", line 21>
 154: MAKE_FUNCTION        
 156: PRECALL              
 160: CALL                 
 170: POP_TOP              
 172: LOAD_CONST           <code object _int_to_enum at 0x00000240693EBA30, file "signal.py", line 24>
 174: MAKE_FUNCTION        
 176: STORE_NAME           _int_to_enum
 178: LOAD_CONST           <code object _enum_to_int at 0x000002406944ABC0, file "signal.py", line 34>
 180: MAKE_FUNCTION        
 182: STORE_NAME           _enum_to_int
 184: LOAD_CONST           <code object _wraps at 0x00000240694949F0, file "signal.py", line 48>
 186: MAKE_FUNCTION        
 188: STORE_NAME           _wraps
 190: PUSH_NULL            
 192: LOAD_NAME            _wraps
 194: LOAD_NAME            _signal
 196: LOAD_ATTR            signal
 206: PRECALL              
 210: CALL                 
 220: LOAD_CONST           <code object signal at 0x00000240691F39F0, file "signal.py", line 54>
 222: MAKE_FUNCTION        
 224: PRECALL              
 228: CALL                 
 238: STORE_NAME           signal
 240: PUSH_NULL            
 242: LOAD_NAME            _wraps
 244: LOAD_NAME            _signal
 246: LOAD_ATTR            getsignal
 256: PRECALL              
 260: CALL                 
 270: LOAD_CONST           <code object getsignal at 0x000002406944A890, file "signal.py", line 60>
 272: MAKE_FUNCTION        
 274: PRECALL              
 278: CALL                 
 288: STORE_NAME           getsignal
 290: LOAD_CONST           'pthread_sigmask'
 292: LOAD_NAME            _globals
 294: CONTAINS_OP          
 296: POP_JUMP_FORWARD_IF_FALSE to 348
 298: PUSH_NULL            
 300: LOAD_NAME            _wraps
 302: LOAD_NAME            _signal
 304: LOAD_ATTR            pthread_sigmask
 314: PRECALL              
 318: CALL                 
 328: LOAD_CONST           <code object pthread_sigmask at 0x000002406941B2D0, file "signal.py", line 67>
 330: MAKE_FUNCTION        
 332: PRECALL              
 336: CALL                 
 346: STORE_NAME           pthread_sigmask
 348: LOAD_CONST           'sigpending'
 350: LOAD_NAME            _globals
 352: CONTAINS_OP          
 354: POP_JUMP_FORWARD_IF_FALSE to 406
 356: PUSH_NULL            
 358: LOAD_NAME            _wraps
 360: LOAD_NAME            _signal
 362: LOAD_ATTR            sigpending
 372: PRECALL              
 376: CALL                 
 386: LOAD_CONST           <code object sigpending at 0x00000240693EB230, file "signal.py", line 74>
 388: MAKE_FUNCTION        
 390: PRECALL              
 394: CALL                 
 404: STORE_NAME           sigpending
 406: LOAD_CONST           'sigwait'
 408: LOAD_NAME            _globals
 410: CONTAINS_OP          
 412: POP_JUMP_FORWARD_IF_FALSE to 464
 414: PUSH_NULL            
 416: LOAD_NAME            _wraps
 418: LOAD_NAME            _signal
 420: LOAD_ATTR            sigwait
 430: PRECALL              
 434: CALL                 
 444: LOAD_CONST           <code object sigwait at 0x000002406944B110, file "signal.py", line 80>
 446: MAKE_FUNCTION        
 448: PRECALL              
 452: CALL                 
 462: STORE_NAME           sigwait
 464: LOAD_CONST           'valid_signals'
 466: LOAD_NAME            _globals
 468: CONTAINS_OP          
 470: POP_JUMP_FORWARD_IF_FALSE to 522
 472: PUSH_NULL            
 474: LOAD_NAME            _wraps
 476: LOAD_NAME            _signal
 478: LOAD_ATTR            valid_signals
 488: PRECALL              
 492: CALL                 
 502: LOAD_CONST           <code object valid_signals at 0x00000240693EA930, file "signal.py", line 87>
 504: MAKE_FUNCTION        
 506: PRECALL              
 510: CALL                 
 520: STORE_NAME           valid_signals
 522: DELETE_NAME          _globals
 524: DELETE_NAME          _wraps
 526: LOAD_CONST           None
 528: RETURN_VALUE         
