# Disassembly for quopri.needsquoting
# From module file: quopri

## co_consts:
("Decide whether a particular byte ordinal needs to be quoted.\n\n    The 'quotetabs' flag indicates whether embedded tabs and spaces should be\n    quoted.  Note that line-ending tabs and spaces are always encoded, as per\n    RFC 1521.\n    ", b' \t', b'_', b' ', b'~')

## co_names:
('isinstance', 'bytes', 'ESCAPE')

## bytecode:

   0: RESUME               
   2: LOAD_GLOBAL          NULL + isinstance
  14: LOAD_FAST            c
  16: LOAD_GLOBAL          bytes
  28: PRECALL              
  32: CALL                 
  42: POP_JUMP_FORWARD_IF_TRUE to 48
  44: LOAD_ASSERTION_ERROR 
  46: RAISE_VARARGS        
  48: LOAD_FAST            c
  50: LOAD_CONST           b' \t'
  52: CONTAINS_OP          
  54: POP_JUMP_FORWARD_IF_FALSE to 60
  56: LOAD_FAST            quotetabs
  58: RETURN_VALUE         
  60: LOAD_FAST            c
  62: LOAD_CONST           b'_'
  64: COMPARE_OP           ==
  70: POP_JUMP_FORWARD_IF_FALSE to 76
  72: LOAD_FAST            header
  74: RETURN_VALUE         
  76: LOAD_FAST            c
  78: LOAD_GLOBAL          ESCAPE
  90: COMPARE_OP           ==
  96: JUMP_IF_TRUE_OR_POP  to 130
  98: LOAD_CONST           b' '
 100: LOAD_FAST            c
 102: SWAP                 
 104: COPY                 
 106: COMPARE_OP           <=
 112: JUMP_IF_FALSE_OR_POP to 124
 114: LOAD_CONST           b'~'
 116: COMPARE_OP           <=
 122: JUMP_FORWARD         to 128
 124: SWAP                 
 126: POP_TOP              
 128: UNARY_NOT            
 130: RETURN_VALUE         
