# Disassembly for tracemalloc.Statistic.__repr__
# From module file: tracemalloc

## co_consts:
(None, '<Statistic traceback=%r size=%i count=%i>')

## co_names:
('traceback', 'size', 'count')

## bytecode:

   0: RESUME               
   2: LOAD_CONST           '<Statistic traceback=%r size=%i count=%i>'
   4: LOAD_FAST            self
   6: LOAD_ATTR            traceback
  16: LOAD_FAST            self
  18: LOAD_ATTR            size
  28: LOAD_FAST            self
  30: LOAD_ATTR            count
  40: BUILD_TUPLE          
  42: BINARY_OP            %
  46: RETURN_VALUE         
