# Disassembly for tracemalloc.Snapshot.filter_traces.<listcomp>
# From module file: tracemalloc

## co_consts:
()

## co_names:
('_filter_trace',)

## bytecode:

   0: COPY_FREE_VARS       
   2: RESUME               
   4: BUILD_LIST           
   6: LOAD_FAST            .0
   8: FOR_ITER             to 64
  10: STORE_FAST           trace
  12: LOAD_DEREF           self
  14: LOAD_METHOD          _filter_trace
  36: LOAD_DEREF           include_filters
  38: LOAD_DEREF           exclude_filters
  40: LOAD_FAST            trace
  42: PRECALL              
  46: CALL                 
  56: POP_JUMP_BACKWARD_IF_FALSE to 8
  58: LOAD_FAST            trace
  60: LIST_APPEND          
  62: JUMP_BACKWARD        to 8
  64: RETURN_VALUE         
