# Disassembly for tracemalloc.get_object_traceback
# From module file: tracemalloc

## co_consts:
('\n    Get the traceback where the Python object *obj* was allocated.\n    Return a Traceback instance.\n\n    Return None if the tracemalloc module is not tracing memory allocations or\n    did not trace the allocation of the object.\n    ', None)

## co_names:
('_get_object_traceback', 'Traceback')

## bytecode:

   0: RESUME               
   2: LOAD_GLOBAL          NULL + _get_object_traceback
  14: LOAD_FAST            obj
  16: PRECALL              
  20: CALL                 
  30: STORE_FAST           frames
  32: LOAD_FAST            frames
  34: POP_JUMP_FORWARD_IF_NONE to 66
  36: LOAD_GLOBAL          NULL + Traceback
  48: LOAD_FAST            frames
  50: PRECALL              
  54: CALL                 
  64: RETURN_VALUE         
  66: LOAD_CONST           None
  68: RETURN_VALUE         
