# Disassembly for tracemalloc.StatisticDiff.__repr__
# From module file: tracemalloc

## co_consts:
(None, '<StatisticDiff traceback=%r size=%i (%+i) count=%i (%+i)>')

## co_names:
('traceback', 'size', 'size_diff', 'count', 'count_diff')

## bytecode:

   0: RESUME               
   2: LOAD_CONST           '<StatisticDiff traceback=%r size=%i (%+i) count=%i (%+i)>'
   4: LOAD_FAST            self
   6: LOAD_ATTR            traceback
  16: LOAD_FAST            self
  18: LOAD_ATTR            size
  28: LOAD_FAST            self
  30: LOAD_ATTR            size_diff
  40: LOAD_FAST            self
  42: LOAD_ATTR            count
  52: LOAD_FAST            self
  54: LOAD_ATTR            count_diff
  64: BUILD_TUPLE          
  66: BINARY_OP            %
  70: RETURN_VALUE         
