# Disassembly for tracemalloc.Snapshot
# From module file: tracemalloc

## co_consts:
('Snapshot', '\n    Snapshot of traces of memory blocks allocated by Python.\n    ', <code object __init__ at 0x00000240693EBB30, file "tracemalloc.py", line 420>, <code object dump at 0x00000240691F3B40, file "tracemalloc.py", line 426>, <code object load at 0x00000240693AAAB0, file "tracemalloc.py", line 433>, <code object _filter_trace at 0x00000240693AB9B0, file "tracemalloc.py", line 441>, <code object filter_traces at 0x0000024068D6C2C0, file "tracemalloc.py", line 452>, <code object _group_by at 0x000002406959EE00, file "tracemalloc.py", line 477>, False, <code object statistics at 0x000002406949D8A0, file "tracemalloc.py", line 528>, <code object compare_to at 0x00000240691E9530, file "tracemalloc.py", line 538>, None, (False,))

## co_names:
('__name__', '__module__', '__qualname__', '__doc__', '__init__', 'dump', 'staticmethod', 'load', '_filter_trace', 'filter_traces', '_group_by', 'statistics', 'compare_to')

## bytecode:

   0: RESUME               
   2: LOAD_NAME            __name__
   4: STORE_NAME           __module__
   6: LOAD_CONST           'Snapshot'
   8: STORE_NAME           __qualname__
  10: LOAD_CONST           '\n    Snapshot of traces of memory blocks allocated by Python.\n    '
  12: STORE_NAME           __doc__
  14: LOAD_CONST           <code object __init__ at 0x00000240693EBB30, file "tracemalloc.py", line 420>
  16: MAKE_FUNCTION        
  18: STORE_NAME           __init__
  20: LOAD_CONST           <code object dump at 0x00000240691F3B40, file "tracemalloc.py", line 426>
  22: MAKE_FUNCTION        
  24: STORE_NAME           dump
  26: LOAD_NAME            staticmethod
  28: LOAD_CONST           <code object load at 0x00000240693AAAB0, file "tracemalloc.py", line 433>
  30: MAKE_FUNCTION        
  32: PRECALL              
  36: CALL                 
  46: STORE_NAME           load
  48: LOAD_CONST           <code object _filter_trace at 0x00000240693AB9B0, file "tracemalloc.py", line 441>
  50: MAKE_FUNCTION        
  52: STORE_NAME           _filter_trace
  54: LOAD_CONST           <code object filter_traces at 0x0000024068D6C2C0, file "tracemalloc.py", line 452>
  56: MAKE_FUNCTION        
  58: STORE_NAME           filter_traces
  60: LOAD_CONST           <code object _group_by at 0x000002406959EE00, file "tracemalloc.py", line 477>
  62: MAKE_FUNCTION        
  64: STORE_NAME           _group_by
  66: LOAD_CONST           (False,)
  68: LOAD_CONST           <code object statistics at 0x000002406949D8A0, file "tracemalloc.py", line 528>
  70: MAKE_FUNCTION        defaults
  72: STORE_NAME           statistics
  74: LOAD_CONST           (False,)
  76: LOAD_CONST           <code object compare_to at 0x00000240691E9530, file "tracemalloc.py", line 538>
  78: MAKE_FUNCTION        defaults
  80: STORE_NAME           compare_to
  82: LOAD_CONST           None
  84: RETURN_VALUE         
