# Disassembly for tracemalloc.Snapshot.compare_to
# From module file: tracemalloc

## co_consts:
('\n        Compute the differences with an old snapshot old_snapshot. Get\n        statistics as a sorted list of StatisticDiff instances, grouped by\n        group_by.\n        ', True, ('reverse', 'key'))

## co_names:
('_group_by', '_compare_grouped_stats', 'sort', 'StatisticDiff', '_sort_key')

## bytecode:

   0: RESUME               
   2: LOAD_FAST            self
   4: LOAD_METHOD          _group_by
  26: LOAD_FAST            key_type
  28: LOAD_FAST            cumulative
  30: PRECALL              
  34: CALL                 
  44: STORE_FAST           new_group
  46: LOAD_FAST            old_snapshot
  48: LOAD_METHOD          _group_by
  70: LOAD_FAST            key_type
  72: LOAD_FAST            cumulative
  74: PRECALL              
  78: CALL                 
  88: STORE_FAST           old_group
  90: LOAD_GLOBAL          NULL + _compare_grouped_stats
 102: LOAD_FAST            old_group
 104: LOAD_FAST            new_group
 106: PRECALL              
 110: CALL                 
 120: STORE_FAST           statistics
 122: LOAD_FAST            statistics
 124: LOAD_METHOD          sort
 146: LOAD_CONST           True
 148: LOAD_GLOBAL          StatisticDiff
 160: LOAD_ATTR            _sort_key
 170: KW_NAMES             
 172: PRECALL              
 176: CALL                 
 186: POP_TOP              
 188: LOAD_FAST            statistics
 190: RETURN_VALUE         
