# Disassembly for tracemalloc.DomainFilter
# From module file: tracemalloc

## co_consts:
('DomainFilter', <code object __init__ at 0x000002406944A450, file "tracemalloc.py", line 402>, <code object domain at 0x0000024069494030, file "tracemalloc.py", line 406>, <code object _match at 0x000002406945E2E0, file "tracemalloc.py", line 410>)

## co_names:
('__name__', '__module__', '__qualname__', '__init__', 'property', 'domain', '_match', '__classcell__')

## bytecode:

   0: MAKE_CELL            __class__
   2: RESUME               
   4: LOAD_NAME            __name__
   6: STORE_NAME           __module__
   8: LOAD_CONST           'DomainFilter'
  10: STORE_NAME           __qualname__
  12: LOAD_CLOSURE         __class__
  14: BUILD_TUPLE          
  16: LOAD_CONST           <code object __init__ at 0x000002406944A450, file "tracemalloc.py", line 402>
  18: MAKE_FUNCTION        closure
  20: STORE_NAME           __init__
  22: LOAD_NAME            property
  24: LOAD_CONST           <code object domain at 0x0000024069494030, file "tracemalloc.py", line 406>
  26: MAKE_FUNCTION        
  28: PRECALL              
  32: CALL                 
  42: STORE_NAME           domain
  44: LOAD_CONST           <code object _match at 0x000002406945E2E0, file "tracemalloc.py", line 410>
  46: MAKE_FUNCTION        
  48: STORE_NAME           _match
  50: LOAD_CLOSURE         __class__
  52: COPY                 
  54: STORE_NAME           __classcell__
  56: RETURN_VALUE         
