# Disassembly for tracemalloc.StatisticDiff.__hash__
# From module file: tracemalloc

## co_consts:
(None,)

## co_names:
('hash', 'traceback', 'size', 'size_diff', 'count', 'count_diff')

## bytecode:

   0: RESUME               
   2: LOAD_GLOBAL          NULL + hash
  14: LOAD_FAST            self
  16: LOAD_ATTR            traceback
  26: LOAD_FAST            self
  28: LOAD_ATTR            size
  38: LOAD_FAST            self
  40: LOAD_ATTR            size_diff
  50: LOAD_FAST            self
  52: LOAD_ATTR            count
  62: LOAD_FAST            self
  64: LOAD_ATTR            count_diff
  74: BUILD_TUPLE          
  76: PRECALL              
  80: CALL                 
  90: RETURN_VALUE         
