# Disassembly for tracemalloc.take_snapshot
# From module file: tracemalloc

## co_consts:
('\n    Take a snapshot of traces of memory blocks allocated by Python.\n    ', 'the tracemalloc module must be tracing memory allocations to take a snapshot')

## co_names:
('is_tracing', 'RuntimeError', '_get_traces', 'get_traceback_limit', 'Snapshot')

## bytecode:

   0: RESUME               
   2: LOAD_GLOBAL          NULL + is_tracing
  14: PRECALL              
  18: CALL                 
  28: POP_JUMP_FORWARD_IF_TRUE to 60
  30: LOAD_GLOBAL          NULL + RuntimeError
  42: LOAD_CONST           'the tracemalloc module must be tracing memory allocations to take a snapshot'
  44: PRECALL              
  48: CALL                 
  58: RAISE_VARARGS        
  60: LOAD_GLOBAL          NULL + _get_traces
  72: PRECALL              
  76: CALL                 
  86: STORE_FAST           traces
  88: LOAD_GLOBAL          NULL + get_traceback_limit
 100: PRECALL              
 104: CALL                 
 114: STORE_FAST           traceback_limit
 116: LOAD_GLOBAL          NULL + Snapshot
 128: LOAD_FAST            traces
 130: LOAD_FAST            traceback_limit
 132: PRECALL              
 136: CALL                 
 146: RETURN_VALUE         
