# Disassembly for tracemalloc.DomainFilter._match
# From module file: tracemalloc

## co_consts:
(None,)

## co_names:
('domain', 'inclusive')

## bytecode:

   0: RESUME               
   2: LOAD_FAST            trace
   4: UNPACK_SEQUENCE      
   8: STORE_FAST           domain
  10: STORE_FAST           size
  12: STORE_FAST           traceback
  14: STORE_FAST           total_nframe
  16: LOAD_FAST            domain
  18: LOAD_FAST            self
  20: LOAD_ATTR            domain
  30: COMPARE_OP           ==
  36: LOAD_FAST            self
  38: LOAD_ATTR            inclusive
  48: UNARY_NOT            
  50: BINARY_OP            ^
  54: RETURN_VALUE         
