# Disassembly for tracemalloc.StatisticDiff.__eq__
# From module file: tracemalloc

## co_consts:
(None,)

## co_names:
('isinstance', 'StatisticDiff', 'NotImplemented', 'traceback', 'size', 'size_diff', 'count', 'count_diff')

## bytecode:

   0: RESUME               
   2: LOAD_GLOBAL          NULL + isinstance
  14: LOAD_FAST            other
  16: LOAD_GLOBAL          StatisticDiff
  28: PRECALL              
  32: CALL                 
  42: POP_JUMP_FORWARD_IF_TRUE to 58
  44: LOAD_GLOBAL          NotImplemented
  56: RETURN_VALUE         
  58: LOAD_FAST            self
  60: LOAD_ATTR            traceback
  70: LOAD_FAST            other
  72: LOAD_ATTR            traceback
  82: COMPARE_OP           ==
  88: JUMP_IF_FALSE_OR_POP to 216
  90: LOAD_FAST            self
  92: LOAD_ATTR            size
 102: LOAD_FAST            other
 104: LOAD_ATTR            size
 114: COMPARE_OP           ==
 120: JUMP_IF_FALSE_OR_POP to 216
 122: LOAD_FAST            self
 124: LOAD_ATTR            size_diff
 134: LOAD_FAST            other
 136: LOAD_ATTR            size_diff
 146: COMPARE_OP           ==
 152: JUMP_IF_FALSE_OR_POP to 216
 154: LOAD_FAST            self
 156: LOAD_ATTR            count
 166: LOAD_FAST            other
 168: LOAD_ATTR            count
 178: COMPARE_OP           ==
 184: JUMP_IF_FALSE_OR_POP to 216
 186: LOAD_FAST            self
 188: LOAD_ATTR            count_diff
 198: LOAD_FAST            other
 200: LOAD_ATTR            count_diff
 210: COMPARE_OP           ==
 216: RETURN_VALUE         
