# Disassembly for tracemalloc.Filter._match_frame
# From module file: tracemalloc

## co_consts:
(None,)

## co_names:
('_match_frame_impl', 'inclusive')

## bytecode:

   0: RESUME               
   2: LOAD_FAST            self
   4: LOAD_METHOD          _match_frame_impl
  26: LOAD_FAST            filename
  28: LOAD_FAST            lineno
  30: PRECALL              
  34: CALL                 
  44: LOAD_FAST            self
  46: LOAD_ATTR            inclusive
  56: UNARY_NOT            
  58: BINARY_OP            ^
  62: RETURN_VALUE         
