# Disassembly for tracemalloc.Snapshot._filter_trace.<genexpr>
# From module file: tracemalloc

## co_consts:
(None,)

## co_names:
('_match',)

## bytecode:

   0: COPY_FREE_VARS       
   2: RETURN_GENERATOR     
   4: POP_TOP              
   6: RESUME               
   8: LOAD_FAST            .0
  10: FOR_ITER             to 64
  12: STORE_FAST           trace_filter
  14: LOAD_FAST            trace_filter
  16: LOAD_METHOD          _match
  38: LOAD_DEREF           trace
  40: PRECALL              
  44: CALL                 
  54: UNARY_NOT            
  56: YIELD_VALUE          
  58: RESUME               
  60: POP_TOP              
  62: JUMP_BACKWARD        to 10
  64: LOAD_CONST           None
  66: RETURN_VALUE         
