# Disassembly for tracemalloc.StatisticDiff.__init__
# From module file: tracemalloc

## co_consts:
(None,)

## co_names:
('traceback', 'size', 'size_diff', 'count', 'count_diff')

## bytecode:

   0: RESUME               
   2: LOAD_FAST            traceback
   4: LOAD_FAST            self
   6: STORE_ATTR           traceback
  16: LOAD_FAST            size
  18: LOAD_FAST            self
  20: STORE_ATTR           size
  30: LOAD_FAST            size_diff
  32: LOAD_FAST            self
  34: STORE_ATTR           size_diff
  44: LOAD_FAST            count
  46: LOAD_FAST            self
  48: STORE_ATTR           count
  58: LOAD_FAST            count_diff
  60: LOAD_FAST            self
  62: STORE_ATTR           count_diff
  72: LOAD_CONST           None
  74: RETURN_VALUE         
