# Disassembly for tracemalloc.Filter._match_traceback.<genexpr>
# From module file: tracemalloc

## co_consts:
(None,)

## co_names:
('_match_frame_impl',)

## bytecode:

   0: COPY_FREE_VARS       
   2: RETURN_GENERATOR     
   4: POP_TOP              
   6: RESUME               
   8: LOAD_FAST            .0
  10: FOR_ITER             to 70
  12: UNPACK_SEQUENCE      
  16: STORE_FAST           filename
  18: STORE_FAST           lineno
  20: LOAD_DEREF           self
  22: LOAD_METHOD          _match_frame_impl
  44: LOAD_FAST            filename
  46: LOAD_FAST            lineno
  48: PRECALL              
  52: CALL                 
  62: YIELD_VALUE          
  64: RESUME               
  66: POP_TOP              
  68: JUMP_BACKWARD        to 10
  70: LOAD_CONST           None
  72: RETURN_VALUE         
