# Disassembly for logging.Logger.setLevel
# From module file: logging

## co_consts:
('\n        Set the logging level of this logger.  level must be an int or a str.\n        ', None)

## co_names:
('_checkLevel', 'level', 'manager', '_clear_cache')

## bytecode:

   0: RESUME               
   2: LOAD_GLOBAL          NULL + _checkLevel
  14: LOAD_FAST            level
  16: PRECALL              
  20: CALL                 
  30: LOAD_FAST            self
  32: STORE_ATTR           level
  42: LOAD_FAST            self
  44: LOAD_ATTR            manager
  54: LOAD_METHOD          _clear_cache
  76: PRECALL              
  80: CALL                 
  90: POP_TOP              
  92: LOAD_CONST           None
  94: RETURN_VALUE         
