# Disassembly for logging.Logger.hasHandlers
# From module file: logging

## co_consts:
('\n        See if this logger has any handlers configured.\n\n        Loop through all handlers for this logger and its parents in the\n        logger hierarchy. Return True if a handler was found, else False.\n        Stop searching up the hierarchy whenever a logger with the "propagate"\n        attribute set to zero is found - that will be the last logger which\n        is checked for the existence of handlers.\n        ', False, True)

## co_names:
('handlers', 'propagate', 'parent')

## bytecode:

   0: RESUME               
   2: LOAD_FAST            self
   4: STORE_FAST           c
   6: LOAD_CONST           False
   8: STORE_FAST           rv
  10: LOAD_FAST            c
  12: POP_JUMP_FORWARD_IF_FALSE to 68
  14: LOAD_FAST            c
  16: LOAD_ATTR            handlers
  26: POP_JUMP_FORWARD_IF_FALSE to 34
  28: LOAD_CONST           True
  30: STORE_FAST           rv
  32: JUMP_FORWARD         to 68
  34: LOAD_FAST            c
  36: LOAD_ATTR            propagate
  46: POP_JUMP_FORWARD_IF_TRUE to 50
  48: JUMP_FORWARD         to 68
  50: LOAD_FAST            c
  52: LOAD_ATTR            parent
  62: STORE_FAST           c
  64: LOAD_FAST            c
  66: POP_JUMP_BACKWARD_IF_TRUE to 14
  68: LOAD_FAST            rv
  70: RETURN_VALUE         
