# Disassembly for logging.StreamHandler.flush
# From module file: logging

## co_consts:
('\n        Flushes the stream.\n        ', 'flush', None)

## co_names:
('acquire', 'stream', 'hasattr', 'flush', 'release')

## bytecode:

   0: RESUME               
   2: LOAD_FAST            self
   4: LOAD_METHOD          acquire
  26: PRECALL              
  30: CALL                 
  40: POP_TOP              
  42: NOP                  
  44: LOAD_FAST            self
  46: LOAD_ATTR            stream
  56: POP_JUMP_FORWARD_IF_FALSE to 150
  58: LOAD_GLOBAL          NULL + hasattr
  70: LOAD_FAST            self
  72: LOAD_ATTR            stream
  82: LOAD_CONST           'flush'
  84: PRECALL              
  88: CALL                 
  98: POP_JUMP_FORWARD_IF_FALSE to 150
 100: LOAD_FAST            self
 102: LOAD_ATTR            stream
 112: LOAD_METHOD          flush
 134: PRECALL              
 138: CALL                 
 148: POP_TOP              
 150: LOAD_FAST            self
 152: LOAD_METHOD          release
 174: PRECALL              
 178: CALL                 
 188: POP_TOP              
 190: LOAD_CONST           None
 192: RETURN_VALUE         
 194: PUSH_EXC_INFO        
 196: LOAD_FAST            self
 198: LOAD_METHOD          release
 220: PRECALL              
 224: CALL                 
 234: POP_TOP              
 236: RERAISE              
 238: COPY                 
 240: POP_EXCEPT           
 242: RERAISE              
