# Disassembly for logging.Logger.makeRecord
# From module file: logging

## co_consts:
('\n        A factory method which can be overridden in subclasses to create\n        specialized LogRecords.\n        ', None, ('message', 'asctime'), 'Attempt to overwrite %r in LogRecord')

## co_names:
('_logRecordFactory', '__dict__', 'KeyError')

## bytecode:

   0: RESUME               
   2: LOAD_GLOBAL          NULL + _logRecordFactory
  14: LOAD_FAST            name
  16: LOAD_FAST            level
  18: LOAD_FAST            fn
  20: LOAD_FAST            lno
  22: LOAD_FAST            msg
  24: LOAD_FAST            args
  26: LOAD_FAST            exc_info
  28: LOAD_FAST            func
  30: LOAD_FAST            sinfo
  32: PRECALL              
  36: CALL                 
  46: STORE_FAST           rv
  48: LOAD_FAST            extra
  50: POP_JUMP_FORWARD_IF_NONE to 156
  52: LOAD_FAST            extra
  54: GET_ITER             
  56: FOR_ITER             to 156
  58: STORE_FAST           key
  60: LOAD_FAST            key
  62: LOAD_CONST           ('message', 'asctime')
  64: CONTAINS_OP          
  66: POP_JUMP_FORWARD_IF_TRUE to 86
  68: LOAD_FAST            key
  70: LOAD_FAST            rv
  72: LOAD_ATTR            __dict__
  82: CONTAINS_OP          
  84: POP_JUMP_FORWARD_IF_FALSE to 122
  86: LOAD_GLOBAL          NULL + KeyError
  98: LOAD_CONST           'Attempt to overwrite %r in LogRecord'
 100: LOAD_FAST            key
 102: BINARY_OP            %
 106: PRECALL              
 110: CALL                 
 120: RAISE_VARARGS        
 122: LOAD_FAST            extra
 124: LOAD_FAST            key
 126: BINARY_SUBSCR        
 136: LOAD_FAST            rv
 138: LOAD_ATTR            __dict__
 148: LOAD_FAST            key
 150: STORE_SUBSCR         
 154: JUMP_BACKWARD        to 56
 156: LOAD_FAST            rv
 158: RETURN_VALUE         
