# Disassembly for logging.Logger.getEffectiveLevel
# From module file: logging

## co_consts:
('\n        Get the effective level for this logger.\n\n        Loop through this logger and its parents in the logger hierarchy,\n        looking for a non-zero logging level. Return the first one found.\n        ',)

## co_names:
('level', 'parent', 'NOTSET')

## bytecode:

   0: RESUME               
   2: LOAD_FAST            self
   4: STORE_FAST           logger
   6: LOAD_FAST            logger
   8: POP_JUMP_FORWARD_IF_FALSE to 56
  10: LOAD_FAST            logger
  12: LOAD_ATTR            level
  22: POP_JUMP_FORWARD_IF_FALSE to 38
  24: LOAD_FAST            logger
  26: LOAD_ATTR            level
  36: RETURN_VALUE         
  38: LOAD_FAST            logger
  40: LOAD_ATTR            parent
  50: STORE_FAST           logger
  52: LOAD_FAST            logger
  54: POP_JUMP_BACKWARD_IF_TRUE to 10
  56: LOAD_GLOBAL          NOTSET
  68: RETURN_VALUE         
