# Disassembly for logging.LoggerAdapter.exception
# From module file: logging

## co_consts:
('\n        Delegate an exception call to the underlying logger.\n        ', 'exc_info', None)

## co_names:
('log', 'ERROR')

## bytecode:

   0: RESUME               
   2: PUSH_NULL            
   4: LOAD_FAST            self
   6: LOAD_ATTR            log
  16: LOAD_GLOBAL          ERROR
  28: LOAD_FAST            msg
  30: BUILD_LIST           
  32: LOAD_FAST            args
  34: LIST_EXTEND          
  36: LIST_TO_TUPLE        
  38: LOAD_CONST           'exc_info'
  40: LOAD_FAST            exc_info
  42: BUILD_MAP            
  44: LOAD_FAST            kwargs
  46: DICT_MERGE           
  48: CALL_FUNCTION_EX     
  50: POP_TOP              
  52: LOAD_CONST           None
  54: RETURN_VALUE         
