# Disassembly for logging.basicConfig
# From module file: logging

## co_consts:
("\n    Do basic configuration for the logging system.\n\n    This function does nothing if the root logger already has handlers\n    configured, unless the keyword argument *force* is set to ``True``.\n    It is a convenience method intended for use by simple scripts\n    to do one-shot configuration of the logging package.\n\n    The default behaviour is to create a StreamHandler which writes to\n    sys.stderr, set a formatter using the BASIC_FORMAT format string, and\n    add the handler to the root logger.\n\n    A number of optional keyword arguments may be specified, which can alter\n    the default behaviour.\n\n    filename  Specifies that a FileHandler be created, using the specified\n              filename, rather than a StreamHandler.\n    filemode  Specifies the mode to open the file, if filename is specified\n              (if filemode is unspecified, it defaults to 'a').\n    format    Use the specified format string for the handler.\n    datefmt   Use the specified date/time format.\n    style     If a format string is specified, use this to specify the\n              type of format string (possible values '%', '{', '$', for\n              %-formatting, :meth:`str.format` and :class:`string.Template`\n              - defaults to '%').\n    level     Set the root logger level to the specified level.\n    stream    Use the specified stream to initialize the StreamHandler. Note\n              that this argument is incompatible with 'filename' - if both\n              are present, 'stream' is ignored.\n    handlers  If specified, this should be an iterable of already created\n              handlers, which will be added to the root handler. Any handler\n              in the list which does not have a formatter assigned will be\n              assigned the formatter created in this function.\n    force     If this keyword  is specified as true, any existing handlers\n              attached to the root logger are removed and closed, before\n              carrying out the configuration as specified by the other\n              arguments.\n    encoding  If specified together with a filename, this encoding is passed to\n              the created FileHandler, causing it to be used when the file is\n              opened.\n    errors    If specified together with a filename, this value is passed to the\n              created FileHandler, causing it to be used when the file is\n              opened in text mode. If not specified, the default value is\n              `backslashreplace`.\n\n    Note that you could specify a stream created using open(filename, mode)\n    rather than passing the filename and mode in. However, it should be\n    remembered that StreamHandler does not close its stream (since it may be\n    using sys.stdout or sys.stderr), whereas FileHandler closes its stream\n    when the handler is closed.\n\n    .. versionchanged:: 3.2\n       Added the ``style`` parameter.\n\n    .. versionchanged:: 3.3\n       Added the ``handlers`` parameter. A ``ValueError`` is now thrown for\n       incompatible arguments (e.g. ``handlers`` specified together with\n       ``filename``/``filemode``, or ``filename``/``filemode`` specified\n       together with ``stream``, or ``handlers`` specified together with\n       ``stream``.\n\n    .. versionchanged:: 3.8\n       Added the ``force`` parameter.\n\n    .. versionchanged:: 3.9\n       Added the ``encoding`` and ``errors`` parameters.\n    ", 'force', False, 'encoding', None, 'errors', 'backslashreplace', 0, 'handlers', 'stream', 'filename', "'stream' and 'filename' should not be specified together", "'stream' or 'filename' should not be specified together with 'handlers'", 'filemode', 'a', 'b', ('encoding', 'errors'), 'datefmt', 'style', '%', 'Style must be one of: %s', ',', 'format', 1, 'level', ', ', 'Unrecognised argument(s): %s')

## co_names:
('_acquireLock', 'pop', 'root', 'handlers', 'removeHandler', 'close', 'len', 'ValueError', 'io', 'text_encoding', 'FileHandler', 'StreamHandler', '_STYLES', 'join', 'keys', 'Formatter', 'formatter', 'setFormatter', 'addHandler', 'setLevel', '_releaseLock')

## bytecode:

   0: RESUME               
   2: LOAD_GLOBAL          NULL + _acquireLock
  14: PRECALL              
  18: CALL                 
  28: POP_TOP              
  30: NOP                  
  32: LOAD_FAST            kwargs
  34: LOAD_METHOD          pop
  56: LOAD_CONST           'force'
  58: LOAD_CONST           False
  60: PRECALL              
  64: CALL                 
  74: STORE_FAST           force
  76: LOAD_FAST            kwargs
  78: LOAD_METHOD          pop
 100: LOAD_CONST           'encoding'
 102: LOAD_CONST           None
 104: PRECALL              
 108: CALL                 
 118: STORE_FAST           encoding
 120: LOAD_FAST            kwargs
 122: LOAD_METHOD          pop
 144: LOAD_CONST           'errors'
 146: LOAD_CONST           'backslashreplace'
 148: PRECALL              
 152: CALL                 
 162: STORE_FAST           errors
 164: LOAD_FAST            force
 166: POP_JUMP_FORWARD_IF_FALSE to 306
 168: LOAD_GLOBAL          root
 180: LOAD_ATTR            handlers
 190: LOAD_CONST           None
 192: LOAD_CONST           None
 194: BUILD_SLICE          
 196: BINARY_SUBSCR        
 206: GET_ITER             
 208: FOR_ITER             to 306
 210: STORE_FAST           h
 212: LOAD_GLOBAL          root
 224: LOAD_METHOD          removeHandler
 246: LOAD_FAST            h
 248: PRECALL              
 252: CALL                 
 262: POP_TOP              
 264: LOAD_FAST            h
 266: LOAD_METHOD          close
 288: PRECALL              
 292: CALL                 
 302: POP_TOP              
 304: JUMP_BACKWARD        to 208
 306: LOAD_GLOBAL          NULL + len
 318: LOAD_GLOBAL          root
 330: LOAD_ATTR            handlers
 340: PRECALL              
 344: CALL                 
 354: LOAD_CONST           0
 356: COMPARE_OP           ==
 362: EXTENDED_ARG         
 364: POP_JUMP_FORWARD_IF_FALSE to 1452
 366: LOAD_FAST            kwargs
 368: LOAD_METHOD          pop
 390: LOAD_CONST           'handlers'
 392: LOAD_CONST           None
 394: PRECALL              
 398: CALL                 
 408: STORE_FAST           handlers
 410: LOAD_FAST            handlers
 412: POP_JUMP_FORWARD_IF_NOT_NONE to 462
 414: LOAD_CONST           'stream'
 416: LOAD_FAST            kwargs
 418: CONTAINS_OP          
 420: POP_JUMP_FORWARD_IF_FALSE to 460
 422: LOAD_CONST           'filename'
 424: LOAD_FAST            kwargs
 426: CONTAINS_OP          
 428: POP_JUMP_FORWARD_IF_FALSE to 460
 430: LOAD_GLOBAL          NULL + ValueError
 442: LOAD_CONST           "'stream' and 'filename' should not be specified together"
 444: PRECALL              
 448: CALL                 
 458: RAISE_VARARGS        
 460: JUMP_FORWARD         to 508
 462: LOAD_CONST           'stream'
 464: LOAD_FAST            kwargs
 466: CONTAINS_OP          
 468: POP_JUMP_FORWARD_IF_TRUE to 478
 470: LOAD_CONST           'filename'
 472: LOAD_FAST            kwargs
 474: CONTAINS_OP          
 476: POP_JUMP_FORWARD_IF_FALSE to 508
 478: LOAD_GLOBAL          NULL + ValueError
 490: LOAD_CONST           "'stream' or 'filename' should not be specified together with 'handlers'"
 492: PRECALL              
 496: CALL                 
 506: RAISE_VARARGS        
 508: LOAD_FAST            handlers
 510: POP_JUMP_FORWARD_IF_NOT_NONE to 778
 512: LOAD_FAST            kwargs
 514: LOAD_METHOD          pop
 536: LOAD_CONST           'filename'
 538: LOAD_CONST           None
 540: PRECALL              
 544: CALL                 
 554: STORE_FAST           filename
 556: LOAD_FAST            kwargs
 558: LOAD_METHOD          pop
 580: LOAD_CONST           'filemode'
 582: LOAD_CONST           'a'
 584: PRECALL              
 588: CALL                 
 598: STORE_FAST           mode
 600: LOAD_FAST            filename
 602: POP_JUMP_FORWARD_IF_FALSE to 698
 604: LOAD_CONST           'b'
 606: LOAD_FAST            mode
 608: CONTAINS_OP          
 610: POP_JUMP_FORWARD_IF_FALSE to 618
 612: LOAD_CONST           None
 614: STORE_FAST           errors
 616: JUMP_FORWARD         to 658
 618: LOAD_GLOBAL          NULL + io
 630: LOAD_ATTR            text_encoding
 640: LOAD_FAST            encoding
 642: PRECALL              
 646: CALL                 
 656: STORE_FAST           encoding
 658: LOAD_GLOBAL          NULL + FileHandler
 670: LOAD_FAST            filename
 672: LOAD_FAST            mode
 674: LOAD_FAST            encoding
 676: LOAD_FAST            errors
 678: KW_NAMES             
 680: PRECALL              
 684: CALL                 
 694: STORE_FAST           h
 696: JUMP_FORWARD         to 772
 698: LOAD_FAST            kwargs
 700: LOAD_METHOD          pop
 722: LOAD_CONST           'stream'
 724: LOAD_CONST           None
 726: PRECALL              
 730: CALL                 
 740: STORE_FAST           stream
 742: LOAD_GLOBAL          NULL + StreamHandler
 754: LOAD_FAST            stream
 756: PRECALL              
 760: CALL                 
 770: STORE_FAST           h
 772: LOAD_FAST            h
 774: BUILD_LIST           
 776: STORE_FAST           handlers
 778: LOAD_FAST            kwargs
 780: LOAD_METHOD          pop
 802: LOAD_CONST           'datefmt'
 804: LOAD_CONST           None
 806: PRECALL              
 810: CALL                 
 820: STORE_FAST           dfs
 822: LOAD_FAST            kwargs
 824: LOAD_METHOD          pop
 846: LOAD_CONST           'style'
 848: LOAD_CONST           '%'
 850: PRECALL              
 854: CALL                 
 864: STORE_FAST           style
 866: LOAD_FAST            style
 868: LOAD_GLOBAL          _STYLES
 880: CONTAINS_OP          
 882: POP_JUMP_FORWARD_IF_FALSE to 1004
 884: LOAD_GLOBAL          NULL + ValueError
 896: LOAD_CONST           'Style must be one of: %s'
 898: LOAD_CONST           ','
 900: LOAD_METHOD          join
 922: LOAD_GLOBAL          _STYLES
 934: LOAD_METHOD          keys
 956: PRECALL              
 960: CALL                 
 970: PRECALL              
 974: CALL                 
 984: BINARY_OP            %
 988: PRECALL              
 992: CALL                 
1002: RAISE_VARARGS        
1004: LOAD_FAST            kwargs
1006: LOAD_METHOD          pop
1028: LOAD_CONST           'format'
1030: LOAD_GLOBAL          _STYLES
1042: LOAD_FAST            style
1044: BINARY_SUBSCR        
1054: LOAD_CONST           1
1056: BINARY_SUBSCR        
1066: PRECALL              
1070: CALL                 
1080: STORE_FAST           fs
1082: LOAD_GLOBAL          NULL + Formatter
1094: LOAD_FAST            fs
1096: LOAD_FAST            dfs
1098: LOAD_FAST            style
1100: PRECALL              
1104: CALL                 
1114: STORE_FAST           fmt
1116: LOAD_FAST            handlers
1118: GET_ITER             
1120: FOR_ITER             to 1234
1122: STORE_FAST           h
1124: LOAD_FAST            h
1126: LOAD_ATTR            formatter
1136: POP_JUMP_FORWARD_IF_NOT_NONE to 1180
1138: LOAD_FAST            h
1140: LOAD_METHOD          setFormatter
1162: LOAD_FAST            fmt
1164: PRECALL              
1168: CALL                 
1178: POP_TOP              
1180: LOAD_GLOBAL          root
1192: LOAD_METHOD          addHandler
1214: LOAD_FAST            h
1216: PRECALL              
1220: CALL                 
1230: POP_TOP              
1232: JUMP_BACKWARD        to 1120
1234: LOAD_FAST            kwargs
1236: LOAD_METHOD          pop
1258: LOAD_CONST           'level'
1260: LOAD_CONST           None
1262: PRECALL              
1266: CALL                 
1276: STORE_FAST           level
1278: LOAD_FAST            level
1280: POP_JUMP_FORWARD_IF_NONE to 1334
1282: LOAD_GLOBAL          root
1294: LOAD_METHOD          setLevel
1316: LOAD_FAST            level
1318: PRECALL              
1322: CALL                 
1332: POP_TOP              
1334: LOAD_FAST            kwargs
1336: POP_JUMP_FORWARD_IF_FALSE to 1452
1338: LOAD_CONST           ', '
1340: LOAD_METHOD          join
1362: LOAD_FAST            kwargs
1364: LOAD_METHOD          keys
1386: PRECALL              
1390: CALL                 
1400: PRECALL              
1404: CALL                 
1414: STORE_FAST           keys
1416: LOAD_GLOBAL          NULL + ValueError
1428: LOAD_CONST           'Unrecognised argument(s): %s'
1430: LOAD_FAST            keys
1432: BINARY_OP            %
1436: PRECALL              
1440: CALL                 
1450: RAISE_VARARGS        
1452: LOAD_GLOBAL          NULL + _releaseLock
1464: PRECALL              
1468: CALL                 
1478: POP_TOP              
1480: LOAD_CONST           None
1482: RETURN_VALUE         
1484: PUSH_EXC_INFO        
1486: LOAD_GLOBAL          NULL + _releaseLock
1498: PRECALL              
1502: CALL                 
1512: POP_TOP              
1514: RERAISE              
1516: COPY                 
1518: POP_EXCEPT           
1520: RERAISE              
