# Disassembly for logging.Formatter.formatException
# From module file: logging

## co_consts:
('\n        Format and return the specified exception information as a string.\n\n        This default implementation just uses\n        traceback.print_exception()\n        ', 2, 0, 1, None, -1, '\n')

## co_names:
('io', 'StringIO', 'traceback', 'print_exception', 'getvalue', 'close')

## bytecode:

   0: RESUME               
   2: LOAD_GLOBAL          NULL + io
  14: LOAD_ATTR            StringIO
  24: PRECALL              
  28: CALL                 
  38: STORE_FAST           sio
  40: LOAD_FAST            ei
  42: LOAD_CONST           2
  44: BINARY_SUBSCR        
  54: STORE_FAST           tb
  56: LOAD_GLOBAL          NULL + traceback
  68: LOAD_ATTR            print_exception
  78: LOAD_FAST            ei
  80: LOAD_CONST           0
  82: BINARY_SUBSCR        
  92: LOAD_FAST            ei
  94: LOAD_CONST           1
  96: BINARY_SUBSCR        
 106: LOAD_FAST            tb
 108: LOAD_CONST           None
 110: LOAD_FAST            sio
 112: PRECALL              
 116: CALL                 
 126: POP_TOP              
 128: LOAD_FAST            sio
 130: LOAD_METHOD          getvalue
 152: PRECALL              
 156: CALL                 
 166: STORE_FAST           s
 168: LOAD_FAST            sio
 170: LOAD_METHOD          close
 192: PRECALL              
 196: CALL                 
 206: POP_TOP              
 208: LOAD_FAST            s
 210: LOAD_CONST           -1
 212: LOAD_CONST           None
 214: BUILD_SLICE          
 216: BINARY_SUBSCR        
 226: LOAD_CONST           '\n'
 228: COMPARE_OP           ==
 234: POP_JUMP_FORWARD_IF_FALSE to 256
 236: LOAD_FAST            s
 238: LOAD_CONST           None
 240: LOAD_CONST           -1
 242: BUILD_SLICE          
 244: BINARY_SUBSCR        
 254: STORE_FAST           s
 256: LOAD_FAST            s
 258: RETURN_VALUE         
