# Disassembly for logging.makeLogRecord
# From module file: logging

## co_consts:
('\n    Make a LogRecord whose attributes are defined by the specified dictionary,\n    This function is useful for converting a logging event received over\n    a socket connection (which is sent as a dictionary) into a LogRecord\n    instance.\n    ', None, '', 0, ())

## co_names:
('_logRecordFactory', '__dict__', 'update')

## bytecode:

   0: RESUME               
   2: LOAD_GLOBAL          NULL + _logRecordFactory
  14: LOAD_CONST           None
  16: LOAD_CONST           None
  18: LOAD_CONST           ''
  20: LOAD_CONST           0
  22: LOAD_CONST           ''
  24: LOAD_CONST           ()
  26: LOAD_CONST           None
  28: LOAD_CONST           None
  30: PRECALL              
  34: CALL                 
  44: STORE_FAST           rv
  46: LOAD_FAST            rv
  48: LOAD_ATTR            __dict__
  58: LOAD_METHOD          update
  80: LOAD_FAST            dict
  82: PRECALL              
  86: CALL                 
  96: POP_TOP              
  98: LOAD_FAST            rv
 100: RETURN_VALUE         
