# Disassembly for logging.getLogger
# From module file: logging

## co_consts:
('\n    Return a logger with the specified name, creating it if necessary.\n\n    If no name is specified, return the root logger.\n    ',)

## co_names:
('isinstance', 'str', 'root', 'name', 'Logger', 'manager', 'getLogger')

## bytecode:

   0: RESUME               
   2: LOAD_FAST            name
   4: POP_JUMP_FORWARD_IF_FALSE to 80
   6: LOAD_GLOBAL          NULL + isinstance
  18: LOAD_FAST            name
  20: LOAD_GLOBAL          str
  32: PRECALL              
  36: CALL                 
  46: POP_JUMP_FORWARD_IF_FALSE to 94
  48: LOAD_FAST            name
  50: LOAD_GLOBAL          root
  62: LOAD_ATTR            name
  72: COMPARE_OP           ==
  78: POP_JUMP_FORWARD_IF_FALSE to 94
  80: LOAD_GLOBAL          root
  92: RETURN_VALUE         
  94: LOAD_GLOBAL          Logger
 106: LOAD_ATTR            manager
 116: LOAD_METHOD          getLogger
 138: LOAD_FAST            name
 140: PRECALL              
 144: CALL                 
 154: RETURN_VALUE         
