# Disassembly for logging.Logger.callHandlers
# From module file: logging

## co_consts:
('\n        Pass a record to all relevant handlers.\n\n        Loop through all handlers for this logger and its parents in the\n        logger hierarchy. If no handler was found, output a one-off error\n        message to sys.stderr. Stop searching up the hierarchy whenever a\n        logger with the "propagate" attribute set to zero is found - that\n        will be the last logger whose handlers are called.\n        ', 0, 1, None, 'No handlers could be found for logger "%s"\n', True)

## co_names:
('handlers', 'levelno', 'level', 'handle', 'propagate', 'parent', 'lastResort', 'raiseExceptions', 'manager', 'emittedNoHandlerWarning', 'sys', 'stderr', 'write', 'name')

## bytecode:

   0: RESUME               
   2: LOAD_FAST            self
   4: STORE_FAST           c
   6: LOAD_CONST           0
   8: STORE_FAST           found
  10: LOAD_FAST            c
  12: POP_JUMP_FORWARD_IF_FALSE to 156
  14: LOAD_FAST            c
  16: LOAD_ATTR            handlers
  26: GET_ITER             
  28: FOR_ITER             to 118
  30: STORE_FAST           hdlr
  32: LOAD_FAST            found
  34: LOAD_CONST           1
  36: BINARY_OP            +
  40: STORE_FAST           found
  42: LOAD_FAST            record
  44: LOAD_ATTR            levelno
  54: LOAD_FAST            hdlr
  56: LOAD_ATTR            level
  66: COMPARE_OP           >=
  72: POP_JUMP_FORWARD_IF_FALSE to 116
  74: LOAD_FAST            hdlr
  76: LOAD_METHOD          handle
  98: LOAD_FAST            record
 100: PRECALL              
 104: CALL                 
 114: POP_TOP              
 116: JUMP_BACKWARD        to 28
 118: LOAD_FAST            c
 120: LOAD_ATTR            propagate
 130: POP_JUMP_FORWARD_IF_TRUE to 138
 132: LOAD_CONST           None
 134: STORE_FAST           c
 136: JUMP_FORWARD         to 152
 138: LOAD_FAST            c
 140: LOAD_ATTR            parent
 150: STORE_FAST           c
 152: LOAD_FAST            c
 154: POP_JUMP_BACKWARD_IF_TRUE to 14
 156: LOAD_FAST            found
 158: LOAD_CONST           0
 160: COMPARE_OP           ==
 166: POP_JUMP_FORWARD_IF_FALSE to 428
 168: LOAD_GLOBAL          lastResort
 180: POP_JUMP_FORWARD_IF_FALSE to 284
 182: LOAD_FAST            record
 184: LOAD_ATTR            levelno
 194: LOAD_GLOBAL          lastResort
 206: LOAD_ATTR            level
 216: COMPARE_OP           >=
 222: POP_JUMP_FORWARD_IF_FALSE to 280
 224: LOAD_GLOBAL          lastResort
 236: LOAD_METHOD          handle
 258: LOAD_FAST            record
 260: PRECALL              
 264: CALL                 
 274: POP_TOP              
 276: LOAD_CONST           None
 278: RETURN_VALUE         
 280: LOAD_CONST           None
 282: RETURN_VALUE         
 284: LOAD_GLOBAL          raiseExceptions
 296: POP_JUMP_FORWARD_IF_FALSE to 432
 298: LOAD_FAST            self
 300: LOAD_ATTR            manager
 310: LOAD_ATTR            emittedNoHandlerWarning
 320: POP_JUMP_FORWARD_IF_TRUE to 436
 322: LOAD_GLOBAL          sys
 334: LOAD_ATTR            stderr
 344: LOAD_METHOD          write
 366: LOAD_CONST           'No handlers could be found for logger "%s"\n'
 368: LOAD_FAST            self
 370: LOAD_ATTR            name
 380: BINARY_OP            %
 384: PRECALL              
 388: CALL                 
 398: POP_TOP              
 400: LOAD_CONST           True
 402: LOAD_FAST            self
 404: LOAD_ATTR            manager
 414: STORE_ATTR           emittedNoHandlerWarning
 424: LOAD_CONST           None
 426: RETURN_VALUE         
 428: LOAD_CONST           None
 430: RETURN_VALUE         
 432: LOAD_CONST           None
 434: RETURN_VALUE         
 436: LOAD_CONST           None
 438: RETURN_VALUE         
