# Disassembly for logging.Filterer.removeFilter
# From module file: logging

## co_consts:
('\n        Remove the specified filter from this handler.\n        ', None)

## co_names:
('filters', 'remove')

## bytecode:

   0: RESUME               
   2: LOAD_FAST            filter
   4: LOAD_FAST            self
   6: LOAD_ATTR            filters
  16: CONTAINS_OP          
  18: POP_JUMP_FORWARD_IF_FALSE to 76
  20: LOAD_FAST            self
  22: LOAD_ATTR            filters
  32: LOAD_METHOD          remove
  54: LOAD_FAST            filter
  56: PRECALL              
  60: CALL                 
  70: POP_TOP              
  72: LOAD_CONST           None
  74: RETURN_VALUE         
  76: LOAD_CONST           None
  78: RETURN_VALUE         
