# Disassembly for logging.StrFormatStyle.validate
# From module file: logging

## co_consts:
('Validate the input format, ensure it is the correct string formatting style', 'invalid field name/expression: %r', 'rsa', 'invalid conversion: %r', 'bad specifier: %r', 'invalid format: %s', None, 'invalid format: no fields')

## co_names:
('set', '_str_formatter', 'parse', '_fmt', 'field_spec', 'match', 'ValueError', 'add', 'fmt_spec')

## bytecode:

   0: RESUME               
   2: LOAD_GLOBAL          NULL + set
  14: PRECALL              
  18: CALL                 
  28: STORE_FAST           fields
  30: NOP                  
  32: LOAD_GLOBAL          _str_formatter
  44: LOAD_METHOD          parse
  66: LOAD_FAST            self
  68: LOAD_ATTR            _fmt
  78: PRECALL              
  82: CALL                 
  92: GET_ITER             
  94: FOR_ITER             to 384
  96: UNPACK_SEQUENCE      
 100: STORE_FAST           _
 102: STORE_FAST           fieldname
 104: STORE_FAST           spec
 106: STORE_FAST           conversion
 108: LOAD_FAST            fieldname
 110: POP_JUMP_FORWARD_IF_FALSE to 242
 112: LOAD_FAST            self
 114: LOAD_ATTR            field_spec
 124: LOAD_METHOD          match
 146: LOAD_FAST            fieldname
 148: PRECALL              
 152: CALL                 
 162: POP_JUMP_FORWARD_IF_TRUE to 200
 164: LOAD_GLOBAL          NULL + ValueError
 176: LOAD_CONST           'invalid field name/expression: %r'
 178: LOAD_FAST            fieldname
 180: BINARY_OP            %
 184: PRECALL              
 188: CALL                 
 198: RAISE_VARARGS        
 200: LOAD_FAST            fields
 202: LOAD_METHOD          add
 224: LOAD_FAST            fieldname
 226: PRECALL              
 230: CALL                 
 240: POP_TOP              
 242: LOAD_FAST            conversion
 244: POP_JUMP_FORWARD_IF_FALSE to 290
 246: LOAD_FAST            conversion
 248: LOAD_CONST           'rsa'
 250: CONTAINS_OP          
 252: POP_JUMP_FORWARD_IF_FALSE to 290
 254: LOAD_GLOBAL          NULL + ValueError
 266: LOAD_CONST           'invalid conversion: %r'
 268: LOAD_FAST            conversion
 270: BINARY_OP            %
 274: PRECALL              
 278: CALL                 
 288: RAISE_VARARGS        
 290: LOAD_FAST            spec
 292: POP_JUMP_FORWARD_IF_FALSE to 382
 294: LOAD_FAST            self
 296: LOAD_ATTR            fmt_spec
 306: LOAD_METHOD          match
 328: LOAD_FAST            spec
 330: PRECALL              
 334: CALL                 
 344: POP_JUMP_FORWARD_IF_TRUE to 382
 346: LOAD_GLOBAL          NULL + ValueError
 358: LOAD_CONST           'bad specifier: %r'
 360: LOAD_FAST            spec
 362: BINARY_OP            %
 366: PRECALL              
 370: CALL                 
 380: RAISE_VARARGS        
 382: JUMP_BACKWARD        to 94
 384: JUMP_FORWARD         to 458
 386: PUSH_EXC_INFO        
 388: LOAD_GLOBAL          ValueError
 400: CHECK_EXC_MATCH      
 402: POP_JUMP_FORWARD_IF_FALSE to 450
 404: STORE_FAST           e
 406: LOAD_GLOBAL          NULL + ValueError
 418: LOAD_CONST           'invalid format: %s'
 420: LOAD_FAST            e
 422: BINARY_OP            %
 426: PRECALL              
 430: CALL                 
 440: RAISE_VARARGS        
 442: LOAD_CONST           None
 444: STORE_FAST           e
 446: DELETE_FAST          e
 448: RERAISE              
 450: RERAISE              
 452: COPY                 
 454: POP_EXCEPT           
 456: RERAISE              
 458: LOAD_FAST            fields
 460: POP_JUMP_FORWARD_IF_TRUE to 492
 462: LOAD_GLOBAL          NULL + ValueError
 474: LOAD_CONST           'invalid format: no fields'
 476: PRECALL              
 480: CALL                 
 490: RAISE_VARARGS        
 492: LOAD_CONST           None
 494: RETURN_VALUE         
