# Disassembly for logging.Formatter.format
# From module file: logging

## co_consts:
("\n        Format the specified record as text.\n\n        The record's attribute dictionary is used as the operand to a\n        string formatting operation which yields the returned string.\n        Before formatting the dictionary, a couple of preparatory steps\n        are carried out. The message attribute of the record is computed\n        using LogRecord.getMessage(). If the formatting string uses the\n        time (as determined by a call to usesTime(), formatTime() is\n        called to format the event time. If there is exception information,\n        it is formatted using formatException() and appended to the message.\n        ", -1, None, '\n')

## co_names:
('getMessage', 'message', 'usesTime', 'formatTime', 'datefmt', 'asctime', 'formatMessage', 'exc_info', 'exc_text', 'formatException', 'stack_info', 'formatStack')

## bytecode:

   0: RESUME               
   2: LOAD_FAST            record
   4: LOAD_METHOD          getMessage
  26: PRECALL              
  30: CALL                 
  40: LOAD_FAST            record
  42: STORE_ATTR           message
  52: LOAD_FAST            self
  54: LOAD_METHOD          usesTime
  76: PRECALL              
  80: CALL                 
  90: POP_JUMP_FORWARD_IF_FALSE to 156
  92: LOAD_FAST            self
  94: LOAD_METHOD          formatTime
 116: LOAD_FAST            record
 118: LOAD_FAST            self
 120: LOAD_ATTR            datefmt
 130: PRECALL              
 134: CALL                 
 144: LOAD_FAST            record
 146: STORE_ATTR           asctime
 156: LOAD_FAST            self
 158: LOAD_METHOD          formatMessage
 180: LOAD_FAST            record
 182: PRECALL              
 186: CALL                 
 196: STORE_FAST           s
 198: LOAD_FAST            record
 200: LOAD_ATTR            exc_info
 210: POP_JUMP_FORWARD_IF_FALSE to 288
 212: LOAD_FAST            record
 214: LOAD_ATTR            exc_text
 224: POP_JUMP_FORWARD_IF_TRUE to 288
 226: LOAD_FAST            self
 228: LOAD_METHOD          formatException
 250: LOAD_FAST            record
 252: LOAD_ATTR            exc_info
 262: PRECALL              
 266: CALL                 
 276: LOAD_FAST            record
 278: STORE_ATTR           exc_text
 288: LOAD_FAST            record
 290: LOAD_ATTR            exc_text
 300: POP_JUMP_FORWARD_IF_FALSE to 360
 302: LOAD_FAST            s
 304: LOAD_CONST           -1
 306: LOAD_CONST           None
 308: BUILD_SLICE          
 310: BINARY_SUBSCR        
 320: LOAD_CONST           '\n'
 322: COMPARE_OP           !=
 328: POP_JUMP_FORWARD_IF_FALSE to 340
 330: LOAD_FAST            s
 332: LOAD_CONST           '\n'
 334: BINARY_OP            +
 338: STORE_FAST           s
 340: LOAD_FAST            s
 342: LOAD_FAST            record
 344: LOAD_ATTR            exc_text
 354: BINARY_OP            +
 358: STORE_FAST           s
 360: LOAD_FAST            record
 362: LOAD_ATTR            stack_info
 372: POP_JUMP_FORWARD_IF_FALSE to 470
 374: LOAD_FAST            s
 376: LOAD_CONST           -1
 378: LOAD_CONST           None
 380: BUILD_SLICE          
 382: BINARY_SUBSCR        
 392: LOAD_CONST           '\n'
 394: COMPARE_OP           !=
 400: POP_JUMP_FORWARD_IF_FALSE to 412
 402: LOAD_FAST            s
 404: LOAD_CONST           '\n'
 406: BINARY_OP            +
 410: STORE_FAST           s
 412: LOAD_FAST            s
 414: LOAD_FAST            self
 416: LOAD_METHOD          formatStack
 438: LOAD_FAST            record
 440: LOAD_ATTR            stack_info
 450: PRECALL              
 454: CALL                 
 464: BINARY_OP            +
 468: STORE_FAST           s
 470: LOAD_FAST            s
 472: RETURN_VALUE         
