# Disassembly for logging._acquireLock
# From module file: logging

## co_consts:
('\n    Acquire the module-level lock for serializing access to shared data.\n\n    This should be released with _releaseLock().\n    ', None)

## co_names:
('_lock', 'acquire')

## bytecode:

   0: RESUME               
   2: LOAD_GLOBAL          _lock
  14: POP_JUMP_FORWARD_IF_FALSE to 70
  16: LOAD_GLOBAL          _lock
  28: LOAD_METHOD          acquire
  50: PRECALL              
  54: CALL                 
  64: POP_TOP              
  66: LOAD_CONST           None
  68: RETURN_VALUE         
  70: LOAD_CONST           None
  72: RETURN_VALUE         
