# Disassembly for logging.Logger.log
# From module file: logging

## co_consts:
('\n        Log \'msg % args\' with the integer severity \'level\'.\n\n        To pass exception information, use the keyword argument exc_info with\n        a true value, e.g.\n\n        logger.log(level, "We have a %s", "mysterious problem", exc_info=1)\n        ', 'level must be an integer', None)

## co_names:
('isinstance', 'int', 'raiseExceptions', 'TypeError', 'isEnabledFor', '_log')

## bytecode:

   0: RESUME               
   2: LOAD_GLOBAL          NULL + isinstance
  14: LOAD_FAST            level
  16: LOAD_GLOBAL          int
  28: PRECALL              
  32: CALL                 
  42: POP_JUMP_FORWARD_IF_TRUE to 92
  44: LOAD_GLOBAL          raiseExceptions
  56: POP_JUMP_FORWARD_IF_FALSE to 88
  58: LOAD_GLOBAL          NULL + TypeError
  70: LOAD_CONST           'level must be an integer'
  72: PRECALL              
  76: CALL                 
  86: RAISE_VARARGS        
  88: LOAD_CONST           None
  90: RETURN_VALUE         
  92: LOAD_FAST            self
  94: LOAD_METHOD          isEnabledFor
 116: LOAD_FAST            level
 118: PRECALL              
 122: CALL                 
 132: POP_JUMP_FORWARD_IF_FALSE to 170
 134: PUSH_NULL            
 136: LOAD_FAST            self
 138: LOAD_ATTR            _log
 148: LOAD_FAST            level
 150: LOAD_FAST            msg
 152: LOAD_FAST            args
 154: BUILD_TUPLE          
 156: BUILD_MAP            
 158: LOAD_FAST            kwargs
 160: DICT_MERGE           
 162: CALL_FUNCTION_EX     
 164: POP_TOP              
 166: LOAD_CONST           None
 168: RETURN_VALUE         
 170: LOAD_CONST           None
 172: RETURN_VALUE         
