# Disassembly for logging.Handler.acquire
# From module file: logging

## co_consts:
('\n        Acquire the I/O thread lock.\n        ', None)

## co_names:
('lock', 'acquire')

## bytecode:

   0: RESUME               
   2: LOAD_FAST            self
   4: LOAD_ATTR            lock
  14: POP_JUMP_FORWARD_IF_FALSE to 70
  16: LOAD_FAST            self
  18: LOAD_ATTR            lock
  28: LOAD_METHOD          acquire
  50: PRECALL              
  54: CALL                 
  64: POP_TOP              
  66: LOAD_CONST           None
  68: RETURN_VALUE         
  70: LOAD_CONST           None
  72: RETURN_VALUE         
