# Disassembly for logging.BufferingFormatter.__init__
# From module file: logging

## co_consts:
('\n        Optionally specify a formatter which will be used to format each\n        individual record.\n        ', None)

## co_names:
('linefmt', '_defaultFormatter')

## bytecode:

   0: RESUME               
   2: LOAD_FAST            linefmt
   4: POP_JUMP_FORWARD_IF_FALSE to 24
   6: LOAD_FAST            linefmt
   8: LOAD_FAST            self
  10: STORE_ATTR           linefmt
  20: LOAD_CONST           None
  22: RETURN_VALUE         
  24: LOAD_GLOBAL          _defaultFormatter
  36: LOAD_FAST            self
  38: STORE_ATTR           linefmt
  48: LOAD_CONST           None
  50: RETURN_VALUE         
