# Disassembly for logging.LogRecord
# From module file: logging

## co_consts:
('LogRecord', '\n    A LogRecord instance represents an event being logged.\n\n    LogRecord instances are created every time something is logged. They\n    contain all the information pertinent to the event being logged. The\n    main information passed in is in msg and args, which are combined\n    using str(msg) % args to create the message field of the record. The\n    record also includes information such as when the record was created,\n    the source line where the logging call was made, and any exception\n    information to be logged.\n    ', None, <code object __init__ at 0x0000024068D5FCF0, file "logging\__init__.py", line 292>, <code object __repr__ at 0x000002406944B110, file "logging\__init__.py", line 364>, <code object getMessage at 0x000002406944A010, file "logging\__init__.py", line 368>, (None, None))

## co_names:
('__name__', '__module__', '__qualname__', '__doc__', '__init__', '__repr__', 'getMessage')

## bytecode:

   0: RESUME               
   2: LOAD_NAME            __name__
   4: STORE_NAME           __module__
   6: LOAD_CONST           'LogRecord'
   8: STORE_NAME           __qualname__
  10: LOAD_CONST           '\n    A LogRecord instance represents an event being logged.\n\n    LogRecord instances are created every time something is logged. They\n    contain all the information pertinent to the event being logged. The\n    main information passed in is in msg and args, which are combined\n    using str(msg) % args to create the message field of the record. The\n    record also includes information such as when the record was created,\n    the source line where the logging call was made, and any exception\n    information to be logged.\n    '
  12: STORE_NAME           __doc__
  14: NOP                  
  16: LOAD_CONST           (None, None)
  18: LOAD_CONST           <code object __init__ at 0x0000024068D5FCF0, file "logging\__init__.py", line 292>
  20: MAKE_FUNCTION        defaults
  22: STORE_NAME           __init__
  24: LOAD_CONST           <code object __repr__ at 0x000002406944B110, file "logging\__init__.py", line 364>
  26: MAKE_FUNCTION        
  28: STORE_NAME           __repr__
  30: LOAD_CONST           <code object getMessage at 0x000002406944A010, file "logging\__init__.py", line 368>
  32: MAKE_FUNCTION        
  34: STORE_NAME           getMessage
  36: LOAD_CONST           None
  38: RETURN_VALUE         
