# Disassembly for logging.Formatter.formatTime
# From module file: logging

## co_consts:
("\n        Return the creation time of the specified LogRecord as formatted text.\n\n        This method should be called from format() by a formatter which\n        wants to make use of a formatted time. This method can be overridden\n        in formatters to provide for any specific requirement, but the\n        basic behaviour is as follows: if datefmt (a string) is specified,\n        it is used with time.strftime() to format the creation time of the\n        record. Otherwise, an ISO8601-like (or RFC 3339-like) format is used.\n        The resulting string is returned. This function uses a user-configurable\n        function to convert the creation time to a tuple. By default,\n        time.localtime() is used; to change this for a particular formatter\n        instance, set the 'converter' attribute to a function with the same\n        signature as time.localtime() or time.gmtime(). To change it for all\n        formatters, for example if you want all logging times to be shown in GMT,\n        set the 'converter' attribute in the Formatter class.\n        ",)

## co_names:
('converter', 'created', 'time', 'strftime', 'default_time_format', 'default_msec_format', 'msecs')

## bytecode:

   0: RESUME               
   2: LOAD_FAST            self
   4: LOAD_METHOD          converter
  26: LOAD_FAST            record
  28: LOAD_ATTR            created
  38: PRECALL              
  42: CALL                 
  52: STORE_FAST           ct
  54: LOAD_FAST            datefmt
  56: POP_JUMP_FORWARD_IF_FALSE to 102
  58: LOAD_GLOBAL          NULL + time
  70: LOAD_ATTR            strftime
  80: LOAD_FAST            datefmt
  82: LOAD_FAST            ct
  84: PRECALL              
  88: CALL                 
  98: STORE_FAST           s
 100: JUMP_FORWARD         to 202
 102: LOAD_GLOBAL          NULL + time
 114: LOAD_ATTR            strftime
 124: LOAD_FAST            self
 126: LOAD_ATTR            default_time_format
 136: LOAD_FAST            ct
 138: PRECALL              
 142: CALL                 
 152: STORE_FAST           s
 154: LOAD_FAST            self
 156: LOAD_ATTR            default_msec_format
 166: POP_JUMP_FORWARD_IF_FALSE to 202
 168: LOAD_FAST            self
 170: LOAD_ATTR            default_msec_format
 180: LOAD_FAST            s
 182: LOAD_FAST            record
 184: LOAD_ATTR            msecs
 194: BUILD_TUPLE          
 196: BINARY_OP            %
 200: STORE_FAST           s
 202: LOAD_FAST            s
 204: RETURN_VALUE         
