# Disassembly for logging.BufferingFormatter.format
# From module file: logging

## co_consts:
('\n        Format the specified records and return the result as a string.\n        ', '', 0)

## co_names:
('len', 'formatHeader', 'linefmt', 'format', 'formatFooter')

## bytecode:

   0: RESUME               
   2: LOAD_CONST           ''
   4: STORE_FAST           rv
   6: LOAD_GLOBAL          NULL + len
  18: LOAD_FAST            records
  20: PRECALL              
  24: CALL                 
  34: LOAD_CONST           0
  36: COMPARE_OP           >
  42: POP_JUMP_FORWARD_IF_FALSE to 208
  44: LOAD_FAST            rv
  46: LOAD_FAST            self
  48: LOAD_METHOD          formatHeader
  70: LOAD_FAST            records
  72: PRECALL              
  76: CALL                 
  86: BINARY_OP            +
  90: STORE_FAST           rv
  92: LOAD_FAST            records
  94: GET_ITER             
  96: FOR_ITER             to 160
  98: STORE_FAST           record
 100: LOAD_FAST            rv
 102: LOAD_FAST            self
 104: LOAD_ATTR            linefmt
 114: LOAD_METHOD          format
 136: LOAD_FAST            record
 138: PRECALL              
 142: CALL                 
 152: BINARY_OP            +
 156: STORE_FAST           rv
 158: JUMP_BACKWARD        to 96
 160: LOAD_FAST            rv
 162: LOAD_FAST            self
 164: LOAD_METHOD          formatFooter
 186: LOAD_FAST            records
 188: PRECALL              
 192: CALL                 
 202: BINARY_OP            +
 206: STORE_FAST           rv
 208: LOAD_FAST            rv
 210: RETURN_VALUE         
