# Disassembly for logging.Logger.handle
# From module file: logging

## co_consts:
('\n        Call the handlers for the specified record.\n\n        This method is used for unpickled records received from a socket, as\n        well as those created locally. Logger-level filtering is applied.\n        ', None)

## co_names:
('disabled', 'filter', 'callHandlers')

## bytecode:

   0: RESUME               
   2: LOAD_FAST            self
   4: LOAD_ATTR            disabled
  14: POP_JUMP_FORWARD_IF_TRUE to 104
  16: LOAD_FAST            self
  18: LOAD_METHOD          filter
  40: LOAD_FAST            record
  42: PRECALL              
  46: CALL                 
  56: POP_JUMP_FORWARD_IF_FALSE to 108
  58: LOAD_FAST            self
  60: LOAD_METHOD          callHandlers
  82: LOAD_FAST            record
  84: PRECALL              
  88: CALL                 
  98: POP_TOP              
 100: LOAD_CONST           None
 102: RETURN_VALUE         
 104: LOAD_CONST           None
 106: RETURN_VALUE         
 108: LOAD_CONST           None
 110: RETURN_VALUE         
