# Disassembly for logging.LoggerAdapter.__init__
# From module file: logging

## co_consts:
('\n        Initialize the adapter with a logger and a dict-like object which\n        provides contextual information. This constructor signature allows\n        easy stacking of LoggerAdapters, if so desired.\n\n        You can effectively pass keyword arguments as shown in the\n        following example:\n\n        adapter = LoggerAdapter(someLogger, dict(p1=v1, p2="v2"))\n        ', None)

## co_names:
('logger', 'extra')

## bytecode:

   0: RESUME               
   2: LOAD_FAST            logger
   4: LOAD_FAST            self
   6: STORE_ATTR           logger
  16: LOAD_FAST            extra
  18: LOAD_FAST            self
  20: STORE_ATTR           extra
  30: LOAD_CONST           None
  32: RETURN_VALUE         
