# Disassembly for logging.Handler.format
# From module file: logging

## co_consts:
('\n        Format the specified record.\n\n        If a formatter is set, use it. Otherwise, use the default formatter\n        for the module.\n        ',)

## co_names:
('formatter', '_defaultFormatter', 'format')

## bytecode:

   0: RESUME               
   2: LOAD_FAST            self
   4: LOAD_ATTR            formatter
  14: POP_JUMP_FORWARD_IF_FALSE to 32
  16: LOAD_FAST            self
  18: LOAD_ATTR            formatter
  28: STORE_FAST           fmt
  30: JUMP_FORWARD         to 46
  32: LOAD_GLOBAL          _defaultFormatter
  44: STORE_FAST           fmt
  46: LOAD_FAST            fmt
  48: LOAD_METHOD          format
  70: LOAD_FAST            record
  72: PRECALL              
  76: CALL                 
  86: RETURN_VALUE         
