# Disassembly for logging._showwarning
# From module file: logging

## co_consts:
('\n    Implementation of showwarnings which redirects to logging, which will first\n    check to see if the file parameter is None. If a file is specified, it will\n    delegate to the original warnings implementation of showwarning. Otherwise,\n    it will call warnings.formatwarning and will log the resulting string to a\n    warnings logger named "py.warnings" with level logging.WARNING.\n    ', None, 'py.warnings')

## co_names:
('_warnings_showwarning', 'warnings', 'formatwarning', 'getLogger', 'handlers', 'addHandler', 'NullHandler', 'warning', 'str')

## bytecode:

   0: RESUME               
   2: LOAD_FAST            file
   4: POP_JUMP_FORWARD_IF_NONE to 68
   6: LOAD_GLOBAL          _warnings_showwarning
  18: POP_JUMP_FORWARD_IF_NONE to 64
  20: LOAD_GLOBAL          NULL + _warnings_showwarning
  32: LOAD_FAST            message
  34: LOAD_FAST            category
  36: LOAD_FAST            filename
  38: LOAD_FAST            lineno
  40: LOAD_FAST            file
  42: LOAD_FAST            line
  44: PRECALL              
  48: CALL                 
  58: POP_TOP              
  60: LOAD_CONST           None
  62: RETURN_VALUE         
  64: LOAD_CONST           None
  66: RETURN_VALUE         
  68: LOAD_GLOBAL          NULL + warnings
  80: LOAD_ATTR            formatwarning
  90: LOAD_FAST            message
  92: LOAD_FAST            category
  94: LOAD_FAST            filename
  96: LOAD_FAST            lineno
  98: LOAD_FAST            line
 100: PRECALL              
 104: CALL                 
 114: STORE_FAST           s
 116: LOAD_GLOBAL          NULL + getLogger
 128: LOAD_CONST           'py.warnings'
 130: PRECALL              
 134: CALL                 
 144: STORE_FAST           logger
 146: LOAD_FAST            logger
 148: LOAD_ATTR            handlers
 158: POP_JUMP_FORWARD_IF_TRUE to 226
 160: LOAD_FAST            logger
 162: LOAD_METHOD          addHandler
 184: LOAD_GLOBAL          NULL + NullHandler
 196: PRECALL              
 200: CALL                 
 210: PRECALL              
 214: CALL                 
 224: POP_TOP              
 226: LOAD_FAST            logger
 228: LOAD_METHOD          warning
 250: LOAD_GLOBAL          NULL + str
 262: LOAD_FAST            s
 264: PRECALL              
 268: CALL                 
 278: PRECALL              
 282: CALL                 
 292: POP_TOP              
 294: LOAD_CONST           None
 296: RETURN_VALUE         
