# Disassembly for logging.getLevelName
# From module file: logging

## co_consts:
("\n    Return the textual or numeric representation of logging level 'level'.\n\n    If the level is one of the predefined levels (CRITICAL, ERROR, WARNING,\n    INFO, DEBUG) then you get the corresponding string. If you have\n    associated levels with names using addLevelName then the name you have\n    associated with 'level' is returned.\n\n    If a numeric value corresponding to one of the defined levels is passed\n    in, the corresponding string representation is returned.\n\n    If a string representation of the level is passed in, the corresponding\n    numeric value is returned.\n\n    If no matching numeric or string value is passed in, the string\n    'Level %s' % level is returned.\n    ", None, 'Level %s')

## co_names:
('_levelToName', 'get', '_nameToLevel')

## bytecode:

   0: RESUME               
   2: LOAD_GLOBAL          _levelToName
  14: LOAD_METHOD          get
  36: LOAD_FAST            level
  38: PRECALL              
  42: CALL                 
  52: STORE_FAST           result
  54: LOAD_FAST            result
  56: POP_JUMP_FORWARD_IF_NONE to 62
  58: LOAD_FAST            result
  60: RETURN_VALUE         
  62: LOAD_GLOBAL          _nameToLevel
  74: LOAD_METHOD          get
  96: LOAD_FAST            level
  98: PRECALL              
 102: CALL                 
 112: STORE_FAST           result
 114: LOAD_FAST            result
 116: POP_JUMP_FORWARD_IF_NONE to 122
 118: LOAD_FAST            result
 120: RETURN_VALUE         
 122: LOAD_CONST           'Level %s'
 124: LOAD_FAST            level
 126: BINARY_OP            %
 130: RETURN_VALUE         
