# Disassembly for logging._StderrHandler
# From module file: logging

## co_consts:
('_StderrHandler', '\n    This class is like a StreamHandler using sys.stderr, but always uses\n    whatever sys.stderr is currently set to rather than the value of\n    sys.stderr at handler construction time.\n    ', <code object __init__ at 0x00000240693EB930, file "logging\__init__.py", line 1243>, <code object stream at 0x0000024069465530, file "logging\__init__.py", line 1249>, None)

## co_names:
('__name__', '__module__', '__qualname__', '__doc__', 'NOTSET', '__init__', 'property', 'stream')

## bytecode:

   0: RESUME               
   2: LOAD_NAME            __name__
   4: STORE_NAME           __module__
   6: LOAD_CONST           '_StderrHandler'
   8: STORE_NAME           __qualname__
  10: LOAD_CONST           '\n    This class is like a StreamHandler using sys.stderr, but always uses\n    whatever sys.stderr is currently set to rather than the value of\n    sys.stderr at handler construction time.\n    '
  12: STORE_NAME           __doc__
  14: LOAD_NAME            NOTSET
  16: BUILD_TUPLE          
  18: LOAD_CONST           <code object __init__ at 0x00000240693EB930, file "logging\__init__.py", line 1243>
  20: MAKE_FUNCTION        defaults
  22: STORE_NAME           __init__
  24: LOAD_NAME            property
  26: LOAD_CONST           <code object stream at 0x0000024069465530, file "logging\__init__.py", line 1249>
  28: MAKE_FUNCTION        
  30: PRECALL              
  34: CALL                 
  44: STORE_NAME           stream
  46: LOAD_CONST           None
  48: RETURN_VALUE         
