# Disassembly for logging.LoggerAdapter.__repr__
# From module file: logging

## co_consts:
(None, '<', ' ', ' (', ')>')

## co_names:
('logger', 'getLevelName', 'getEffectiveLevel', '__class__', '__name__', 'name')

## bytecode:

   0: RESUME               
   2: LOAD_FAST            self
   4: LOAD_ATTR            logger
  14: STORE_FAST           logger
  16: LOAD_GLOBAL          NULL + getLevelName
  28: LOAD_FAST            logger
  30: LOAD_METHOD          getEffectiveLevel
  52: PRECALL              
  56: CALL                 
  66: PRECALL              
  70: CALL                 
  80: STORE_FAST           level
  82: LOAD_CONST           '<'
  84: LOAD_FAST            self
  86: LOAD_ATTR            __class__
  96: LOAD_ATTR            __name__
 106: FORMAT_VALUE         str
 108: LOAD_CONST           ' '
 110: LOAD_FAST            logger
 112: LOAD_ATTR            name
 122: FORMAT_VALUE         str
 124: LOAD_CONST           ' ('
 126: LOAD_FAST            level
 128: FORMAT_VALUE         str
 130: LOAD_CONST           ')>'
 132: BUILD_STRING         
 134: RETURN_VALUE         
