# Disassembly for logging.Handler.createLock
# From module file: logging

## co_consts:
('\n        Acquire a thread lock for serializing access to the underlying I/O.\n        ', None)

## co_names:
('threading', 'RLock', 'lock', '_register_at_fork_reinit_lock')

## bytecode:

   0: RESUME               
   2: LOAD_GLOBAL          NULL + threading
  14: LOAD_ATTR            RLock
  24: PRECALL              
  28: CALL                 
  38: LOAD_FAST            self
  40: STORE_ATTR           lock
  50: LOAD_GLOBAL          NULL + _register_at_fork_reinit_lock
  62: LOAD_FAST            self
  64: PRECALL              
  68: CALL                 
  78: POP_TOP              
  80: LOAD_CONST           None
  82: RETURN_VALUE         
