# Disassembly for logging.Formatter.__init__
# From module file: logging

## co_consts:
("\n        Initialize the formatter with specified format strings.\n\n        Initialize the formatter either with the specified format string, or a\n        default as described above. Allow for specialized date formatting with\n        the optional datefmt argument. If datefmt is omitted, you get an\n        ISO8601-like (or RFC 3339-like) format.\n\n        Use a style parameter of '%', '{' or '$' to specify that you want to\n        use one of %-formatting, :meth:`str.format` (``{}``) formatting or\n        :class:`string.Template` formatting in your format string.\n\n        .. versionchanged:: 3.2\n           Added the ``style`` parameter.\n        ", 'Style must be one of: %s', ',', 0, ('defaults',), None)

## co_names:
('_STYLES', 'ValueError', 'join', 'keys', '_style', 'validate', '_fmt', 'datefmt')

## bytecode:

   0: RESUME               
   2: LOAD_FAST            style
   4: LOAD_GLOBAL          _STYLES
  16: CONTAINS_OP          
  18: POP_JUMP_FORWARD_IF_FALSE to 140
  20: LOAD_GLOBAL          NULL + ValueError
  32: LOAD_CONST           'Style must be one of: %s'
  34: LOAD_CONST           ','
  36: LOAD_METHOD          join
  58: LOAD_GLOBAL          _STYLES
  70: LOAD_METHOD          keys
  92: PRECALL              
  96: CALL                 
 106: PRECALL              
 110: CALL                 
 120: BINARY_OP            %
 124: PRECALL              
 128: CALL                 
 138: RAISE_VARARGS        
 140: LOAD_GLOBAL          NULL + _STYLES
 152: LOAD_FAST            style
 154: BINARY_SUBSCR        
 164: LOAD_CONST           0
 166: BINARY_SUBSCR        
 176: LOAD_FAST            fmt
 178: LOAD_FAST            defaults
 180: KW_NAMES             
 182: PRECALL              
 186: CALL                 
 196: LOAD_FAST            self
 198: STORE_ATTR           _style
 208: LOAD_FAST            validate
 210: POP_JUMP_FORWARD_IF_FALSE to 262
 212: LOAD_FAST            self
 214: LOAD_ATTR            _style
 224: LOAD_METHOD          validate
 246: PRECALL              
 250: CALL                 
 260: POP_TOP              
 262: LOAD_FAST            self
 264: LOAD_ATTR            _style
 274: LOAD_ATTR            _fmt
 284: LOAD_FAST            self
 286: STORE_ATTR           _fmt
 296: LOAD_FAST            datefmt
 298: LOAD_FAST            self
 300: STORE_ATTR           datefmt
 310: LOAD_CONST           None
 312: RETURN_VALUE         
