# Disassembly for logging.shutdown
# From module file: logging

## co_consts:
('\n    Perform any cleanup actions in the logging system (e.g. flushing\n    buffers).\n\n    Should be called at application exit.\n    ', None)

## co_names:
('reversed', 'acquire', 'flush', 'close', 'OSError', 'ValueError', 'release', 'raiseExceptions')

## bytecode:

   0: RESUME               
   2: LOAD_GLOBAL          NULL + reversed
  14: LOAD_FAST            handlerList
  16: LOAD_CONST           None
  18: LOAD_CONST           None
  20: BUILD_SLICE          
  22: BINARY_SUBSCR        
  32: PRECALL              
  36: CALL                 
  46: GET_ITER             
  48: FOR_ITER             to 372
  50: STORE_FAST           wr
  52: NOP                  
  54: PUSH_NULL            
  56: LOAD_FAST            wr
  58: PRECALL              
  62: CALL                 
  72: STORE_FAST           h
  74: LOAD_FAST            h
  76: POP_JUMP_FORWARD_IF_FALSE to 340
  78: NOP                  
  80: LOAD_FAST            h
  82: LOAD_METHOD          acquire
 104: PRECALL              
 108: CALL                 
 118: POP_TOP              
 120: LOAD_FAST            h
 122: LOAD_METHOD          flush
 144: PRECALL              
 148: CALL                 
 158: POP_TOP              
 160: LOAD_FAST            h
 162: LOAD_METHOD          close
 184: PRECALL              
 188: CALL                 
 198: POP_TOP              
 200: JUMP_FORWARD         to 248
 202: PUSH_EXC_INFO        
 204: LOAD_GLOBAL          OSError
 216: LOAD_GLOBAL          ValueError
 228: BUILD_TUPLE          
 230: CHECK_EXC_MATCH      
 232: POP_JUMP_FORWARD_IF_FALSE to 240
 234: POP_TOP              
 236: POP_EXCEPT           
 238: JUMP_FORWARD         to 248
 240: RERAISE              
 242: COPY                 
 244: POP_EXCEPT           
 246: RERAISE              
 248: LOAD_FAST            h
 250: LOAD_METHOD          release
 272: PRECALL              
 276: CALL                 
 286: POP_TOP              
 288: JUMP_FORWARD         to 340
 290: PUSH_EXC_INFO        
 292: LOAD_FAST            h
 294: LOAD_METHOD          release
 316: PRECALL              
 320: CALL                 
 330: POP_TOP              
 332: RERAISE              
 334: COPY                 
 336: POP_EXCEPT           
 338: RERAISE              
 340: JUMP_BACKWARD        to 48
 342: PUSH_EXC_INFO        
 344: POP_TOP              
 346: LOAD_GLOBAL          raiseExceptions
 358: POP_JUMP_FORWARD_IF_FALSE to 362
 360: RAISE_VARARGS        
 362: POP_EXCEPT           
 364: JUMP_BACKWARD        to 48
 366: COPY                 
 368: POP_EXCEPT           
 370: RERAISE              
 372: LOAD_CONST           None
 374: RETURN_VALUE         
