# Disassembly for logging._after_at_fork_child_reinit_locks
# From module file: logging

## co_consts:
(None,)

## co_names:
('_at_fork_reinit_lock_weakset', '_at_fork_reinit', '_lock')

## bytecode:

   0: RESUME               
   2: LOAD_GLOBAL          _at_fork_reinit_lock_weakset
  14: GET_ITER             
  16: FOR_ITER             to 62
  18: STORE_FAST           handler
  20: LOAD_FAST            handler
  22: LOAD_METHOD          _at_fork_reinit
  44: PRECALL              
  48: CALL                 
  58: POP_TOP              
  60: JUMP_BACKWARD        to 16
  62: LOAD_GLOBAL          _lock
  74: LOAD_METHOD          _at_fork_reinit
  96: PRECALL              
 100: CALL                 
 110: POP_TOP              
 112: LOAD_CONST           None
 114: RETURN_VALUE         
