# Disassembly for logging.exception
# From module file: logging

## co_consts:
("\n    Log a message with severity 'ERROR' on the root logger, with exception\n    information. If the logger has no handlers, basicConfig() is called to add\n    a console handler with a pre-defined format.\n    ", 'exc_info', None)

## co_names:
('error',)

## bytecode:

   0: RESUME               
   2: LOAD_GLOBAL          NULL + error
  14: LOAD_FAST            msg
  16: BUILD_LIST           
  18: LOAD_FAST            args
  20: LIST_EXTEND          
  22: LIST_TO_TUPLE        
  24: LOAD_CONST           'exc_info'
  26: LOAD_FAST            exc_info
  28: BUILD_MAP            
  30: LOAD_FAST            kwargs
  32: DICT_MERGE           
  34: CALL_FUNCTION_EX     
  36: POP_TOP              
  38: LOAD_CONST           None
  40: RETURN_VALUE         
