# Disassembly for logging.PlaceHolder
# From module file: logging

## co_consts:
('PlaceHolder', '\n    PlaceHolder instances are used in the Manager logger hierarchy to take\n    the place of nodes for which no loggers have been defined. This class is\n    intended for internal use only and not as part of the public API.\n    ', <code object __init__ at 0x0000024069495070, file "logging\__init__.py", line 1267>, <code object append at 0x000002406945FE10, file "logging\__init__.py", line 1273>, None)

## co_names:
('__name__', '__module__', '__qualname__', '__doc__', '__init__', 'append')

## bytecode:

   0: RESUME               
   2: LOAD_NAME            __name__
   4: STORE_NAME           __module__
   6: LOAD_CONST           'PlaceHolder'
   8: STORE_NAME           __qualname__
  10: LOAD_CONST           '\n    PlaceHolder instances are used in the Manager logger hierarchy to take\n    the place of nodes for which no loggers have been defined. This class is\n    intended for internal use only and not as part of the public API.\n    '
  12: STORE_NAME           __doc__
  14: LOAD_CONST           <code object __init__ at 0x0000024069495070, file "logging\__init__.py", line 1267>
  16: MAKE_FUNCTION        
  18: STORE_NAME           __init__
  20: LOAD_CONST           <code object append at 0x000002406945FE10, file "logging\__init__.py", line 1273>
  22: MAKE_FUNCTION        
  24: STORE_NAME           append
  26: LOAD_CONST           None
  28: RETURN_VALUE         
