# Disassembly for logging.StringTemplateStyle
# From module file: logging

## co_consts:
('StringTemplateStyle', '${message}', '${asctime}', <code object __init__ at 0x00000240693D2C20, file "logging\__init__.py", line 493>, <code object usesTime at 0x00000240693AB9B0, file "logging\__init__.py", line 497>, <code object validate at 0x0000024068C5ABD0, file "logging\__init__.py", line 501>, <code object _format at 0x000002406941A550, file "logging\__init__.py", line 515>)

## co_names:
('__name__', '__module__', '__qualname__', 'default_format', 'asctime_format', 'asctime_search', '__init__', 'usesTime', 'validate', '_format', '__classcell__')

## bytecode:

   0: MAKE_CELL            __class__
   2: RESUME               
   4: LOAD_NAME            __name__
   6: STORE_NAME           __module__
   8: LOAD_CONST           'StringTemplateStyle'
  10: STORE_NAME           __qualname__
  12: LOAD_CONST           '${message}'
  14: STORE_NAME           default_format
  16: LOAD_CONST           '${asctime}'
  18: STORE_NAME           asctime_format
  20: LOAD_CONST           '${asctime}'
  22: STORE_NAME           asctime_search
  24: LOAD_CLOSURE         __class__
  26: BUILD_TUPLE          
  28: LOAD_CONST           <code object __init__ at 0x00000240693D2C20, file "logging\__init__.py", line 493>
  30: MAKE_FUNCTION        closure
  32: STORE_NAME           __init__
  34: LOAD_CONST           <code object usesTime at 0x00000240693AB9B0, file "logging\__init__.py", line 497>
  36: MAKE_FUNCTION        
  38: STORE_NAME           usesTime
  40: LOAD_CONST           <code object validate at 0x0000024068C5ABD0, file "logging\__init__.py", line 501>
  42: MAKE_FUNCTION        
  44: STORE_NAME           validate
  46: LOAD_CONST           <code object _format at 0x000002406941A550, file "logging\__init__.py", line 515>
  48: MAKE_FUNCTION        
  50: STORE_NAME           _format
  52: LOAD_CLOSURE         __class__
  54: COPY                 
  56: STORE_NAME           __classcell__
  58: RETURN_VALUE         
