# Disassembly for logging.addLevelName
# From module file: logging

## co_consts:
("\n    Associate 'levelName' with 'level'.\n\n    This is used when converting levels to text during message formatting.\n    ", None)

## co_names:
('_acquireLock', '_levelToName', '_nameToLevel', '_releaseLock')

## bytecode:

   0: RESUME               
   2: LOAD_GLOBAL          NULL + _acquireLock
  14: PRECALL              
  18: CALL                 
  28: POP_TOP              
  30: NOP                  
  32: LOAD_FAST            levelName
  34: LOAD_GLOBAL          _levelToName
  46: LOAD_FAST            level
  48: STORE_SUBSCR         
  52: LOAD_FAST            level
  54: LOAD_GLOBAL          _nameToLevel
  66: LOAD_FAST            levelName
  68: STORE_SUBSCR         
  72: LOAD_GLOBAL          NULL + _releaseLock
  84: PRECALL              
  88: CALL                 
  98: POP_TOP              
 100: LOAD_CONST           None
 102: RETURN_VALUE         
 104: PUSH_EXC_INFO        
 106: LOAD_GLOBAL          NULL + _releaseLock
 118: PRECALL              
 122: CALL                 
 132: POP_TOP              
 134: RERAISE              
 136: COPY                 
 138: POP_EXCEPT           
 140: RERAISE              
