# Disassembly for logging.LoggerAdapter.setLevel
# From module file: logging

## co_consts:
('\n        Set the specified level on the underlying logger.\n        ', None)

## co_names:
('logger', 'setLevel')

## bytecode:

   0: RESUME               
   2: LOAD_FAST            self
   4: LOAD_ATTR            logger
  14: LOAD_METHOD          setLevel
  36: LOAD_FAST            level
  38: PRECALL              
  42: CALL                 
  52: POP_TOP              
  54: LOAD_CONST           None
  56: RETURN_VALUE         
