# Disassembly for logging.LoggerAdapter.log
# From module file: logging

## co_consts:
('\n        Delegate a log call to the underlying logger, after adding\n        contextual information from this adapter instance.\n        ', None)

## co_names:
('isEnabledFor', 'process', 'logger', 'log')

## bytecode:

   0: RESUME               
   2: LOAD_FAST            self
   4: LOAD_METHOD          isEnabledFor
  26: LOAD_FAST            level
  28: PRECALL              
  32: CALL                 
  42: POP_JUMP_FORWARD_IF_FALSE to 144
  44: LOAD_FAST            self
  46: LOAD_METHOD          process
  68: LOAD_FAST            msg
  70: LOAD_FAST            kwargs
  72: PRECALL              
  76: CALL                 
  86: UNPACK_SEQUENCE      
  90: STORE_FAST           msg
  92: STORE_FAST           kwargs
  94: PUSH_NULL            
  96: LOAD_FAST            self
  98: LOAD_ATTR            logger
 108: LOAD_ATTR            log
 118: LOAD_FAST            level
 120: LOAD_FAST            msg
 122: BUILD_LIST           
 124: LOAD_FAST            args
 126: LIST_EXTEND          
 128: LIST_TO_TUPLE        
 130: BUILD_MAP            
 132: LOAD_FAST            kwargs
 134: DICT_MERGE           
 136: CALL_FUNCTION_EX     
 138: POP_TOP              
 140: LOAD_CONST           None
 142: RETURN_VALUE         
 144: LOAD_CONST           None
 146: RETURN_VALUE         
