# Disassembly for logging.FileHandler._open
# From module file: logging

## co_consts:
('\n        Open the current base file with the (original) mode and encoding.\n        Return the resulting stream.\n        ', ('encoding', 'errors'))

## co_names:
('_builtin_open', 'baseFilename', 'mode', 'encoding', 'errors')

## bytecode:

   0: RESUME               
   2: LOAD_FAST            self
   4: LOAD_ATTR            _builtin_open
  14: STORE_FAST           open_func
  16: PUSH_NULL            
  18: LOAD_FAST            open_func
  20: LOAD_FAST            self
  22: LOAD_ATTR            baseFilename
  32: LOAD_FAST            self
  34: LOAD_ATTR            mode
  44: LOAD_FAST            self
  46: LOAD_ATTR            encoding
  56: LOAD_FAST            self
  58: LOAD_ATTR            errors
  68: KW_NAMES             
  70: PRECALL              
  74: CALL                 
  84: RETURN_VALUE         
