# Disassembly for logging.PlaceHolder.append
# From module file: logging

## co_consts:
('\n        Add the specified logger as a child of this placeholder.\n        ', None)

## co_names:
('loggerMap',)

## bytecode:

   0: RESUME               
   2: LOAD_FAST            alogger
   4: LOAD_FAST            self
   6: LOAD_ATTR            loggerMap
  16: CONTAINS_OP          
  18: POP_JUMP_FORWARD_IF_FALSE to 44
  20: LOAD_CONST           None
  22: LOAD_FAST            self
  24: LOAD_ATTR            loggerMap
  34: LOAD_FAST            alogger
  36: STORE_SUBSCR         
  40: LOAD_CONST           None
  42: RETURN_VALUE         
  44: LOAD_CONST           None
  46: RETURN_VALUE         
