# Disassembly for right.ColorWheel.get_options
# From module file: right

## co_consts:
(None, <code object <lambda> at 0x000002406945D890, file "right.py", line 22>, 'Check the color wheel.')

## co_names:
()

## bytecode:

   0: MAKE_CELL            self
   2: RESUME               
   4: LOAD_CLOSURE         self
   6: BUILD_TUPLE          
   8: LOAD_CONST           <code object <lambda> at 0x000002406945D890, file "right.py", line 22>
  10: MAKE_FUNCTION        closure
  12: LOAD_CONST           'Check the color wheel.'
  14: BUILD_TUPLE          
  16: BUILD_LIST           
  18: STORE_FAST           options
  20: LOAD_FAST            options
  22: RETURN_VALUE         
