# Disassembly for right.ColorButtons.press
# From module file: right

## co_consts:
(None, 'name', 'Press a colored button', False, 'You press the %s button and it lights up.', 'compliment', True, 'Breakroom', 'The colored buttons all light up and a celebratory tune plays\non the piano behind you.\n\n<A LOUD CHIME COMES FROM THE BREAKROOM>', 'You hear a simple click and all of the buttons turn off.', "You hear a buzzer.  Maybe that wasn't the color expected.\nAll of the buttons turn off.")

## co_names:
('colors', 'keys', 'append', 'ask_option', 'send_message', 'compliment_expected', 'world', 'player', 'favorite_color', 'rooms', 'central_right_unlocked')

## bytecode:

   0: RESUME               
   2: BUILD_LIST           
   4: STORE_FAST           options
   6: LOAD_GLOBAL          colors
  18: LOAD_METHOD          keys
  40: PRECALL              
  44: CALL                 
  54: GET_ITER             
  56: FOR_ITER             to 142
  58: STORE_FAST           color_id
  60: LOAD_FAST            options
  62: LOAD_METHOD          append
  84: LOAD_FAST            color_id
  86: LOAD_GLOBAL          colors
  98: LOAD_FAST            color_id
 100: BINARY_SUBSCR        
 110: LOAD_CONST           'name'
 112: BINARY_SUBSCR        
 122: BUILD_TUPLE          
 124: PRECALL              
 128: CALL                 
 138: POP_TOP              
 140: JUMP_BACKWARD        to 56
 142: LOAD_FAST            self
 144: LOAD_METHOD          ask_option
 166: LOAD_CONST           'Press a colored button'
 168: LOAD_FAST            options
 170: LOAD_CONST           False
 172: PRECALL              
 176: CALL                 
 186: STORE_FAST           color
 188: LOAD_FAST            self
 190: LOAD_METHOD          send_message
 212: LOAD_CONST           'You press the %s button and it lights up.'
 214: LOAD_FAST            color
 216: BINARY_OP            %
 220: PRECALL              
 224: CALL                 
 234: POP_TOP              
 236: LOAD_FAST            self
 238: LOAD_ATTR            compliment_expected
 248: POP_JUMP_FORWARD_IF_NONE to 542
 250: LOAD_FAST            color
 252: LOAD_FAST            self
 254: LOAD_ATTR            compliment_expected
 264: COMPARE_OP           ==
 270: POP_JUMP_FORWARD_IF_FALSE to 482
 272: LOAD_FAST            color
 274: LOAD_GLOBAL          colors
 286: LOAD_FAST            self
 288: LOAD_ATTR            world
 298: LOAD_ATTR            player
 308: LOAD_ATTR            favorite_color
 318: BINARY_SUBSCR        
 328: LOAD_CONST           'compliment'
 330: BINARY_SUBSCR        
 340: COMPARE_OP           ==
 346: POP_JUMP_FORWARD_IF_FALSE to 438
 348: LOAD_CONST           True
 350: LOAD_FAST            self
 352: LOAD_ATTR            world
 362: LOAD_ATTR            rooms
 372: LOAD_CONST           'Breakroom'
 374: BINARY_SUBSCR        
 384: STORE_ATTR           central_right_unlocked
 394: LOAD_FAST            self
 396: LOAD_METHOD          send_message
 418: LOAD_CONST           'The colored buttons all light up and a celebratory tune plays\non the piano behind you.\n\n<A LOUD CHIME COMES FROM THE BREAKROOM>'
 420: PRECALL              
 424: CALL                 
 434: POP_TOP              
 436: JUMP_FORWARD         to 524
 438: LOAD_FAST            self
 440: LOAD_METHOD          send_message
 462: LOAD_CONST           'You hear a simple click and all of the buttons turn off.'
 464: PRECALL              
 468: CALL                 
 478: POP_TOP              
 480: JUMP_FORWARD         to 524
 482: LOAD_FAST            self
 484: LOAD_METHOD          send_message
 506: LOAD_CONST           "You hear a buzzer.  Maybe that wasn't the color expected.\nAll of the buttons turn off."
 508: PRECALL              
 512: CALL                 
 522: POP_TOP              
 524: LOAD_CONST           None
 526: LOAD_FAST            self
 528: STORE_ATTR           compliment_expected
 538: LOAD_CONST           None
 540: RETURN_VALUE         
 542: LOAD_GLOBAL          colors
 554: LOAD_FAST            color
 556: BINARY_SUBSCR        
 566: LOAD_CONST           'compliment'
 568: BINARY_SUBSCR        
 578: LOAD_FAST            self
 580: STORE_ATTR           compliment_expected
 590: LOAD_CONST           None
 592: RETURN_VALUE         
