# Disassembly for gettext.install
# From module file: gettext

## co_consts:
(None, True, ('fallback',))

## co_names:
('translation', 'install')

## bytecode:

   0: RESUME               
   2: LOAD_GLOBAL          NULL + translation
  14: LOAD_FAST            domain
  16: LOAD_FAST            localedir
  18: LOAD_CONST           True
  20: KW_NAMES             
  22: PRECALL              
  26: CALL                 
  36: STORE_FAST           t
  38: LOAD_FAST            t
  40: LOAD_METHOD          install
  62: LOAD_FAST            names
  64: PRECALL              
  68: CALL                 
  78: POP_TOP              
  80: LOAD_CONST           None
  82: RETURN_VALUE         
