# Disassembly for gettext._error
# From module file: gettext

## co_consts:
(None, 'unexpected token in plural form: %s', 'unexpected end of plural form')

## co_names:
('ValueError',)

## bytecode:

   0: RESUME               
   2: LOAD_FAST            value
   4: POP_JUMP_FORWARD_IF_FALSE to 42
   6: LOAD_GLOBAL          NULL + ValueError
  18: LOAD_CONST           'unexpected token in plural form: %s'
  20: LOAD_FAST            value
  22: BINARY_OP            %
  26: PRECALL              
  30: CALL                 
  40: RETURN_VALUE         
  42: LOAD_GLOBAL          NULL + ValueError
  54: LOAD_CONST           'unexpected end of plural form'
  56: PRECALL              
  60: CALL                 
  70: RETURN_VALUE         
