# Disassembly for gettext.GNUTranslations._parse
# From module file: gettext

## co_consts:
('Override this method to support alternative .mo formats.', 0, ('unpack',), 'name', '', <code object <lambda> at 0x00000240694679F0, file "gettext.py", line 341>, '<I', None, 4, '<4I', 20, '<II', '>4I', '>II', 'Bad magic number', 'Bad version number ', 8, 'File is corrupt', b'\n', '#-#-#-#-#', ':', 1, '\n', 'content-type', 'charset=', 'plural-forms', ';', 'plural=', 'ascii', b'\x00')

## co_names:
('struct', 'unpack', 'getattr', '_catalog', 'plural', 'read', 'len', 'LE_MAGIC', 'BE_MAGIC', 'OSError', '_get_versions', 'VERSIONS', 'str', 'range', 'split', 'decode', 'strip', 'startswith', 'endswith', 'lower', '_info', '_charset', 'c2py', 'enumerate')

## bytecode:

   0: RESUME               
   2: LOAD_CONST           0
   4: LOAD_CONST           ('unpack',)
   6: IMPORT_NAME          struct
   8: IMPORT_FROM          unpack
  10: STORE_FAST           unpack
  12: POP_TOP              
  14: LOAD_GLOBAL          NULL + getattr
  26: LOAD_FAST            fp
  28: LOAD_CONST           'name'
  30: LOAD_CONST           ''
  32: PRECALL              
  36: CALL                 
  46: STORE_FAST           filename
  48: BUILD_MAP            
  50: COPY                 
  52: LOAD_FAST            self
  54: STORE_ATTR           _catalog
  64: STORE_FAST           catalog
  66: LOAD_CONST           <code object <lambda> at 0x00000240694679F0, file "gettext.py", line 341>
  68: MAKE_FUNCTION        
  70: LOAD_FAST            self
  72: STORE_ATTR           plural
  82: LOAD_FAST            fp
  84: LOAD_METHOD          read
 106: PRECALL              
 110: CALL                 
 120: STORE_FAST           buf
 122: LOAD_GLOBAL          NULL + len
 134: LOAD_FAST            buf
 136: PRECALL              
 140: CALL                 
 150: STORE_FAST           buflen
 152: PUSH_NULL            
 154: LOAD_FAST            unpack
 156: LOAD_CONST           '<I'
 158: LOAD_FAST            buf
 160: LOAD_CONST           None
 162: LOAD_CONST           4
 164: BUILD_SLICE          
 166: BINARY_SUBSCR        
 176: PRECALL              
 180: CALL                 
 190: LOAD_CONST           0
 192: BINARY_SUBSCR        
 202: STORE_FAST           magic
 204: LOAD_FAST            magic
 206: LOAD_FAST            self
 208: LOAD_ATTR            LE_MAGIC
 218: COMPARE_OP           ==
 224: POP_JUMP_FORWARD_IF_FALSE to 282
 226: PUSH_NULL            
 228: LOAD_FAST            unpack
 230: LOAD_CONST           '<4I'
 232: LOAD_FAST            buf
 234: LOAD_CONST           4
 236: LOAD_CONST           20
 238: BUILD_SLICE          
 240: BINARY_SUBSCR        
 250: PRECALL              
 254: CALL                 
 264: UNPACK_SEQUENCE      
 268: STORE_FAST           version
 270: STORE_FAST           msgcount
 272: STORE_FAST           masteridx
 274: STORE_FAST           transidx
 276: LOAD_CONST           '<II'
 278: STORE_FAST           ii
 280: JUMP_FORWARD         to 394
 282: LOAD_FAST            magic
 284: LOAD_FAST            self
 286: LOAD_ATTR            BE_MAGIC
 296: COMPARE_OP           ==
 302: POP_JUMP_FORWARD_IF_FALSE to 360
 304: PUSH_NULL            
 306: LOAD_FAST            unpack
 308: LOAD_CONST           '>4I'
 310: LOAD_FAST            buf
 312: LOAD_CONST           4
 314: LOAD_CONST           20
 316: BUILD_SLICE          
 318: BINARY_SUBSCR        
 328: PRECALL              
 332: CALL                 
 342: UNPACK_SEQUENCE      
 346: STORE_FAST           version
 348: STORE_FAST           msgcount
 350: STORE_FAST           masteridx
 352: STORE_FAST           transidx
 354: LOAD_CONST           '>II'
 356: STORE_FAST           ii
 358: JUMP_FORWARD         to 394
 360: LOAD_GLOBAL          NULL + OSError
 372: LOAD_CONST           0
 374: LOAD_CONST           'Bad magic number'
 376: LOAD_FAST            filename
 378: PRECALL              
 382: CALL                 
 392: RAISE_VARARGS        
 394: LOAD_FAST            self
 396: LOAD_METHOD          _get_versions
 418: LOAD_FAST            version
 420: PRECALL              
 424: CALL                 
 434: UNPACK_SEQUENCE      
 438: STORE_FAST           major_version
 440: STORE_FAST           minor_version
 442: LOAD_FAST            major_version
 444: LOAD_FAST            self
 446: LOAD_ATTR            VERSIONS
 456: CONTAINS_OP          
 458: POP_JUMP_FORWARD_IF_FALSE to 526
 460: LOAD_GLOBAL          NULL + OSError
 472: LOAD_CONST           0
 474: LOAD_CONST           'Bad version number '
 476: LOAD_GLOBAL          NULL + str
 488: LOAD_FAST            major_version
 490: PRECALL              
 494: CALL                 
 504: BINARY_OP            +
 508: LOAD_FAST            filename
 510: PRECALL              
 514: CALL                 
 524: RAISE_VARARGS        
 526: LOAD_GLOBAL          NULL + range
 538: LOAD_CONST           0
 540: LOAD_FAST            msgcount
 542: PRECALL              
 546: CALL                 
 556: GET_ITER             
 558: EXTENDED_ARG         
 560: FOR_ITER             to 1850
 562: STORE_FAST           i
 564: PUSH_NULL            
 566: LOAD_FAST            unpack
 568: LOAD_FAST            ii
 570: LOAD_FAST            buf
 572: LOAD_FAST            masteridx
 574: LOAD_FAST            masteridx
 576: LOAD_CONST           8
 578: BINARY_OP            +
 582: BUILD_SLICE          
 584: BINARY_SUBSCR        
 594: PRECALL              
 598: CALL                 
 608: UNPACK_SEQUENCE      
 612: STORE_FAST           mlen
 614: STORE_FAST           moff
 616: LOAD_FAST            moff
 618: LOAD_FAST            mlen
 620: BINARY_OP            +
 624: STORE_FAST           mend
 626: PUSH_NULL            
 628: LOAD_FAST            unpack
 630: LOAD_FAST            ii
 632: LOAD_FAST            buf
 634: LOAD_FAST            transidx
 636: LOAD_FAST            transidx
 638: LOAD_CONST           8
 640: BINARY_OP            +
 644: BUILD_SLICE          
 646: BINARY_SUBSCR        
 656: PRECALL              
 660: CALL                 
 670: UNPACK_SEQUENCE      
 674: STORE_FAST           tlen
 676: STORE_FAST           toff
 678: LOAD_FAST            toff
 680: LOAD_FAST            tlen
 682: BINARY_OP            +
 686: STORE_FAST           tend
 688: LOAD_FAST            mend
 690: LOAD_FAST            buflen
 692: COMPARE_OP           <
 698: POP_JUMP_FORWARD_IF_FALSE to 754
 700: LOAD_FAST            tend
 702: LOAD_FAST            buflen
 704: COMPARE_OP           <
 710: POP_JUMP_FORWARD_IF_FALSE to 754
 712: LOAD_FAST            buf
 714: LOAD_FAST            moff
 716: LOAD_FAST            mend
 718: BUILD_SLICE          
 720: BINARY_SUBSCR        
 730: STORE_FAST           msg
 732: LOAD_FAST            buf
 734: LOAD_FAST            toff
 736: LOAD_FAST            tend
 738: BUILD_SLICE          
 740: BINARY_SUBSCR        
 750: STORE_FAST           tmsg
 752: JUMP_FORWARD         to 788
 754: LOAD_GLOBAL          NULL + OSError
 766: LOAD_CONST           0
 768: LOAD_CONST           'File is corrupt'
 770: LOAD_FAST            filename
 772: PRECALL              
 776: CALL                 
 786: RAISE_VARARGS        
 788: LOAD_FAST            mlen
 790: LOAD_CONST           0
 792: COMPARE_OP           ==
 798: EXTENDED_ARG         
 800: POP_JUMP_FORWARD_IF_FALSE to 1526
 802: LOAD_CONST           None
 804: STORE_FAST           lastk
 806: LOAD_FAST            tmsg
 808: LOAD_METHOD          split
 830: LOAD_CONST           b'\n'
 832: PRECALL              
 836: CALL                 
 846: GET_ITER             
 848: EXTENDED_ARG         
 850: FOR_ITER             to 1526
 852: STORE_FAST           b_item
 854: LOAD_FAST            b_item
 856: LOAD_METHOD          decode
 878: PRECALL              
 882: CALL                 
 892: LOAD_METHOD          strip
 914: PRECALL              
 918: CALL                 
 928: STORE_FAST           item
 930: LOAD_FAST            item
 932: POP_JUMP_FORWARD_IF_TRUE to 936
 934: JUMP_BACKWARD        to 848
 936: LOAD_FAST            item
 938: LOAD_METHOD          startswith
 960: LOAD_CONST           '#-#-#-#-#'
 962: PRECALL              
 966: CALL                 
 976: POP_JUMP_FORWARD_IF_FALSE to 1022
 978: LOAD_FAST            item
 980: LOAD_METHOD          endswith
1002: LOAD_CONST           '#-#-#-#-#'
1004: PRECALL              
1008: CALL                 
1018: POP_JUMP_FORWARD_IF_FALSE to 1022
1020: JUMP_BACKWARD        to 848
1022: LOAD_CONST           None
1024: COPY                 
1026: STORE_FAST           k
1028: STORE_FAST           v
1030: LOAD_CONST           ':'
1032: LOAD_FAST            item
1034: CONTAINS_OP          
1036: POP_JUMP_FORWARD_IF_FALSE to 1230
1038: LOAD_FAST            item
1040: LOAD_METHOD          split
1062: LOAD_CONST           ':'
1064: LOAD_CONST           1
1066: PRECALL              
1070: CALL                 
1080: UNPACK_SEQUENCE      
1084: STORE_FAST           k
1086: STORE_FAST           v
1088: LOAD_FAST            k
1090: LOAD_METHOD          strip
1112: PRECALL              
1116: CALL                 
1126: LOAD_METHOD          lower
1148: PRECALL              
1152: CALL                 
1162: STORE_FAST           k
1164: LOAD_FAST            v
1166: LOAD_METHOD          strip
1188: PRECALL              
1192: CALL                 
1202: STORE_FAST           v
1204: LOAD_FAST            v
1206: LOAD_FAST            self
1208: LOAD_ATTR            _info
1218: LOAD_FAST            k
1220: STORE_SUBSCR         
1224: LOAD_FAST            k
1226: STORE_FAST           lastk
1228: JUMP_FORWARD         to 1282
1230: LOAD_FAST            lastk
1232: POP_JUMP_FORWARD_IF_FALSE to 1282
1234: LOAD_FAST            self
1236: LOAD_ATTR            _info
1246: LOAD_FAST            lastk
1248: COPY                 
1250: COPY                 
1252: BINARY_SUBSCR        
1262: LOAD_CONST           '\n'
1264: LOAD_FAST            item
1266: BINARY_OP            +
1270: BINARY_OP            +=
1274: SWAP                 
1276: SWAP                 
1278: STORE_SUBSCR         
1282: LOAD_FAST            k
1284: LOAD_CONST           'content-type'
1286: COMPARE_OP           ==
1292: POP_JUMP_FORWARD_IF_FALSE to 1362
1294: LOAD_FAST            v
1296: LOAD_METHOD          split
1318: LOAD_CONST           'charset='
1320: PRECALL              
1324: CALL                 
1334: LOAD_CONST           1
1336: BINARY_SUBSCR        
1346: LOAD_FAST            self
1348: STORE_ATTR           _charset
1358: EXTENDED_ARG         
1360: JUMP_BACKWARD        to 848
1362: LOAD_FAST            k
1364: LOAD_CONST           'plural-forms'
1366: COMPARE_OP           ==
1372: POP_JUMP_FORWARD_IF_FALSE to 1522
1374: LOAD_FAST            v
1376: LOAD_METHOD          split
1398: LOAD_CONST           ';'
1400: PRECALL              
1404: CALL                 
1414: STORE_FAST           v
1416: LOAD_FAST            v
1418: LOAD_CONST           1
1420: BINARY_SUBSCR        
1430: LOAD_METHOD          split
1452: LOAD_CONST           'plural='
1454: PRECALL              
1458: CALL                 
1468: LOAD_CONST           1
1470: BINARY_SUBSCR        
1480: STORE_FAST           plural
1482: LOAD_GLOBAL          NULL + c2py
1494: LOAD_FAST            plural
1496: PRECALL              
1500: CALL                 
1510: LOAD_FAST            self
1512: STORE_ATTR           plural
1522: EXTENDED_ARG         
1524: JUMP_BACKWARD        to 848
1526: LOAD_FAST            self
1528: LOAD_ATTR            _charset
1538: JUMP_IF_TRUE_OR_POP  to 1542
1540: LOAD_CONST           'ascii'
1542: STORE_FAST           charset
1544: LOAD_CONST           b'\x00'
1546: LOAD_FAST            msg
1548: CONTAINS_OP          
1550: POP_JUMP_FORWARD_IF_FALSE to 1760
1552: LOAD_FAST            msg
1554: LOAD_METHOD          split
1576: LOAD_CONST           b'\x00'
1578: PRECALL              
1582: CALL                 
1592: UNPACK_SEQUENCE      
1596: STORE_FAST           msgid1
1598: STORE_FAST           msgid2
1600: LOAD_FAST            tmsg
1602: LOAD_METHOD          split
1624: LOAD_CONST           b'\x00'
1626: PRECALL              
1630: CALL                 
1640: STORE_FAST           tmsg
1642: LOAD_GLOBAL          NULL + str
1654: LOAD_FAST            msgid1
1656: LOAD_FAST            charset
1658: PRECALL              
1662: CALL                 
1672: STORE_FAST           msgid1
1674: LOAD_GLOBAL          NULL + enumerate
1686: LOAD_FAST            tmsg
1688: PRECALL              
1692: CALL                 
1702: GET_ITER             
1704: FOR_ITER             to 1758
1706: UNPACK_SEQUENCE      
1710: STORE_FAST           i
1712: STORE_FAST           x
1714: LOAD_GLOBAL          NULL + str
1726: LOAD_FAST            x
1728: LOAD_FAST            charset
1730: PRECALL              
1734: CALL                 
1744: LOAD_FAST            catalog
1746: LOAD_FAST            msgid1
1748: LOAD_FAST            i
1750: BUILD_TUPLE          
1752: STORE_SUBSCR         
1756: JUMP_BACKWARD        to 1704
1758: JUMP_FORWARD         to 1826
1760: LOAD_GLOBAL          NULL + str
1772: LOAD_FAST            tmsg
1774: LOAD_FAST            charset
1776: PRECALL              
1780: CALL                 
1790: LOAD_FAST            catalog
1792: LOAD_GLOBAL          NULL + str
1804: LOAD_FAST            msg
1806: LOAD_FAST            charset
1808: PRECALL              
1812: CALL                 
1822: STORE_SUBSCR         
1826: LOAD_FAST            masteridx
1828: LOAD_CONST           8
1830: BINARY_OP            +=
1834: STORE_FAST           masteridx
1836: LOAD_FAST            transidx
1838: LOAD_CONST           8
1840: BINARY_OP            +=
1844: STORE_FAST           transidx
1846: EXTENDED_ARG         
1848: JUMP_BACKWARD        to 558
1850: LOAD_CONST           None
1852: RETURN_VALUE         
