# Disassembly for gettext.NullTranslations.pgettext
# From module file: gettext

## co_consts:
(None,)

## co_names:
('_fallback', 'pgettext')

## bytecode:

   0: RESUME               
   2: LOAD_FAST            self
   4: LOAD_ATTR            _fallback
  14: POP_JUMP_FORWARD_IF_FALSE to 70
  16: LOAD_FAST            self
  18: LOAD_ATTR            _fallback
  28: LOAD_METHOD          pgettext
  50: LOAD_FAST            context
  52: LOAD_FAST            message
  54: PRECALL              
  58: CALL                 
  68: RETURN_VALUE         
  70: LOAD_FAST            message
  72: RETURN_VALUE         
