# Disassembly for inspect.getabsfile
# From module file: inspect

## co_consts:
('Return an absolute path to the source or compiled file for an object.\n\n    The idea is for each object to have a unique origin, so this routine\n    normalizes the result as much as possible.',)

## co_names:
('getsourcefile', 'getfile', 'os', 'path', 'normcase', 'abspath')

## bytecode:

   0: RESUME               
   2: LOAD_FAST            _filename
   4: POP_JUMP_FORWARD_IF_NOT_NONE to 66
   6: LOAD_GLOBAL          NULL + getsourcefile
  18: LOAD_FAST            object
  20: PRECALL              
  24: CALL                 
  34: JUMP_IF_TRUE_OR_POP  to 64
  36: LOAD_GLOBAL          NULL + getfile
  48: LOAD_FAST            object
  50: PRECALL              
  54: CALL                 
  64: STORE_FAST           _filename
  66: LOAD_GLOBAL          os
  78: LOAD_ATTR            path
  88: LOAD_METHOD          normcase
 110: LOAD_GLOBAL          os
 122: LOAD_ATTR            path
 132: LOAD_METHOD          abspath
 154: LOAD_FAST            _filename
 156: PRECALL              
 160: CALL                 
 170: PRECALL              
 174: CALL                 
 184: RETURN_VALUE         
