# Disassembly for inspect.Signature.from_callable
# From module file: inspect

## co_consts:
('Constructs Signature for the given callable object.', ('sigcls', 'follow_wrapper_chains', 'globals', 'locals', 'eval_str'))

## co_names:
('_signature_from_callable',)

## bytecode:

   0: RESUME               
   2: LOAD_GLOBAL          NULL + _signature_from_callable
  14: LOAD_FAST            obj
  16: LOAD_FAST            cls
  18: LOAD_FAST            follow_wrapped
  20: LOAD_FAST            globals
  22: LOAD_FAST            locals
  24: LOAD_FAST            eval_str
  26: KW_NAMES             
  28: PRECALL              
  32: CALL                 
  42: RETURN_VALUE         
