# Disassembly for inspect.trace
# From module file: inspect

## co_consts:
('Return a list of records for the stack below the current exception.', 2)

## co_names:
('getinnerframes', 'sys', 'exc_info')

## bytecode:

   0: RESUME               
   2: LOAD_GLOBAL          NULL + getinnerframes
  14: LOAD_GLOBAL          NULL + sys
  26: LOAD_ATTR            exc_info
  36: PRECALL              
  40: CALL                 
  50: LOAD_CONST           2
  52: BINARY_SUBSCR        
  62: LOAD_FAST            context
  64: PRECALL              
  68: CALL                 
  78: RETURN_VALUE         
