# Disassembly for inspect._getmembers
# From module file: inspect

## co_consts:
(None, (), <code object <lambda> at 0x0000024069496180, file "inspect.py", line 589>, ('key',))

## co_names:
('set', 'dir', 'isclass', 'getmro', '__bases__', '__dict__', 'items', 'isinstance', 'types', 'DynamicClassAttribute', 'append', 'AttributeError', 'add', 'sort')

## bytecode:

   0: RESUME               
   2: BUILD_LIST           
   4: STORE_FAST           results
   6: LOAD_GLOBAL          NULL + set
  18: PRECALL              
  22: CALL                 
  32: STORE_FAST           processed
  34: LOAD_GLOBAL          NULL + dir
  46: LOAD_FAST            object
  48: PRECALL              
  52: CALL                 
  62: STORE_FAST           names
  64: LOAD_GLOBAL          NULL + isclass
  76: LOAD_FAST            object
  78: PRECALL              
  82: CALL                 
  92: POP_JUMP_FORWARD_IF_FALSE to 344
  94: LOAD_FAST            object
  96: BUILD_TUPLE          
  98: LOAD_GLOBAL          NULL + getmro
 110: LOAD_FAST            object
 112: PRECALL              
 116: CALL                 
 126: BINARY_OP            +
 130: STORE_FAST           mro
 132: NOP                  
 134: LOAD_FAST            object
 136: LOAD_ATTR            __bases__
 146: GET_ITER             
 148: FOR_ITER             to 310
 150: STORE_FAST           base
 152: LOAD_FAST            base
 154: LOAD_ATTR            __dict__
 164: LOAD_METHOD          items
 186: PRECALL              
 190: CALL                 
 200: GET_ITER             
 202: FOR_ITER             to 308
 204: UNPACK_SEQUENCE      
 208: STORE_FAST           k
 210: STORE_FAST           v
 212: LOAD_GLOBAL          NULL + isinstance
 224: LOAD_FAST            v
 226: LOAD_GLOBAL          types
 238: LOAD_ATTR            DynamicClassAttribute
 248: PRECALL              
 252: CALL                 
 262: POP_JUMP_FORWARD_IF_FALSE to 306
 264: LOAD_FAST            names
 266: LOAD_METHOD          append
 288: LOAD_FAST            k
 290: PRECALL              
 294: CALL                 
 304: POP_TOP              
 306: JUMP_BACKWARD        to 202
 308: JUMP_BACKWARD        to 148
 310: JUMP_FORWARD         to 348
 312: PUSH_EXC_INFO        
 314: LOAD_GLOBAL          AttributeError
 326: CHECK_EXC_MATCH      
 328: POP_JUMP_FORWARD_IF_FALSE to 336
 330: POP_TOP              
 332: POP_EXCEPT           
 334: JUMP_FORWARD         to 348
 336: RERAISE              
 338: COPY                 
 340: POP_EXCEPT           
 342: RERAISE              
 344: LOAD_CONST           ()
 346: STORE_FAST           mro
 348: LOAD_FAST            names
 350: GET_ITER             
 352: FOR_ITER             to 616
 354: STORE_FAST           key
 356: NOP                  
 358: PUSH_NULL            
 360: LOAD_FAST            getter
 362: LOAD_FAST            object
 364: LOAD_FAST            key
 366: PRECALL              
 370: CALL                 
 380: STORE_FAST           value
 382: LOAD_FAST            key
 384: LOAD_FAST            processed
 386: CONTAINS_OP          
 388: POP_JUMP_FORWARD_IF_FALSE to 404
 390: LOAD_GLOBAL          AttributeError
 402: RAISE_VARARGS        
 404: JUMP_FORWARD         to 500
 406: PUSH_EXC_INFO        
 408: LOAD_GLOBAL          AttributeError
 420: CHECK_EXC_MATCH      
 422: POP_JUMP_FORWARD_IF_FALSE to 492
 424: POP_TOP              
 426: LOAD_FAST            mro
 428: GET_ITER             
 430: FOR_ITER             to 484
 432: STORE_FAST           base
 434: LOAD_FAST            key
 436: LOAD_FAST            base
 438: LOAD_ATTR            __dict__
 448: CONTAINS_OP          
 450: POP_JUMP_FORWARD_IF_FALSE to 482
 452: LOAD_FAST            base
 454: LOAD_ATTR            __dict__
 464: LOAD_FAST            key
 466: BINARY_SUBSCR        
 476: STORE_FAST           value
 478: POP_TOP              
 480: JUMP_FORWARD         to 488
 482: JUMP_BACKWARD        to 430
 484: POP_EXCEPT           
 486: JUMP_BACKWARD        to 352
 488: POP_EXCEPT           
 490: JUMP_FORWARD         to 500
 492: RERAISE              
 494: COPY                 
 496: POP_EXCEPT           
 498: RERAISE              
 500: LOAD_FAST            predicate
 502: POP_JUMP_FORWARD_IF_FALSE to 526
 504: PUSH_NULL            
 506: LOAD_FAST            predicate
 508: LOAD_FAST            value
 510: PRECALL              
 514: CALL                 
 524: POP_JUMP_FORWARD_IF_FALSE to 572
 526: LOAD_FAST            results
 528: LOAD_METHOD          append
 550: LOAD_FAST            key
 552: LOAD_FAST            value
 554: BUILD_TUPLE          
 556: PRECALL              
 560: CALL                 
 570: POP_TOP              
 572: LOAD_FAST            processed
 574: LOAD_METHOD          add
 596: LOAD_FAST            key
 598: PRECALL              
 602: CALL                 
 612: POP_TOP              
 614: JUMP_BACKWARD        to 352
 616: LOAD_FAST            results
 618: LOAD_METHOD          sort
 640: LOAD_CONST           <code object <lambda> at 0x0000024069496180, file "inspect.py", line 589>
 642: MAKE_FUNCTION        
 644: KW_NAMES             
 646: PRECALL              
 650: CALL                 
 660: POP_TOP              
 662: LOAD_FAST            results
 664: RETURN_VALUE         
