# Disassembly for inspect.Signature.bind
# From module file: inspect

## co_consts:
("Get a BoundArguments object, that maps the passed `args`\n        and `kwargs` to the function's signature.  Raises `TypeError`\n        if the passed arguments can not be bound.\n        ",)

## co_names:
('_bind',)

## bytecode:

   0: RESUME               
   2: LOAD_FAST            self
   4: LOAD_METHOD          _bind
  26: LOAD_FAST            args
  28: LOAD_FAST            kwargs
  30: PRECALL              
  34: CALL                 
  44: RETURN_VALUE         
