# Disassembly for inspect.stack
# From module file: inspect

## co_consts:
("Return a list of records for the stack above the caller's frame.", 1)

## co_names:
('getouterframes', 'sys', '_getframe')

## bytecode:

   0: RESUME               
   2: LOAD_GLOBAL          NULL + getouterframes
  14: LOAD_GLOBAL          NULL + sys
  26: LOAD_ATTR            _getframe
  36: LOAD_CONST           1
  38: PRECALL              
  42: CALL                 
  52: LOAD_FAST            context
  54: PRECALL              
  58: CALL                 
  68: RETURN_VALUE         
