# Disassembly for inspect.getgeneratorstate
# From module file: inspect

## co_consts:
('Get current state of a generator-iterator.\n\n    Possible states are:\n      GEN_CREATED: Waiting to start execution.\n      GEN_RUNNING: Currently being executed by the interpreter.\n      GEN_SUSPENDED: Currently suspended at a yield expression.\n      GEN_CLOSED: Execution has completed.\n    ',)

## co_names:
('gi_running', 'GEN_RUNNING', 'gi_suspended', 'GEN_SUSPENDED', 'gi_frame', 'GEN_CLOSED', 'GEN_CREATED')

## bytecode:

   0: RESUME               
   2: LOAD_FAST            generator
   4: LOAD_ATTR            gi_running
  14: POP_JUMP_FORWARD_IF_FALSE to 30
  16: LOAD_GLOBAL          GEN_RUNNING
  28: RETURN_VALUE         
  30: LOAD_FAST            generator
  32: LOAD_ATTR            gi_suspended
  42: POP_JUMP_FORWARD_IF_FALSE to 58
  44: LOAD_GLOBAL          GEN_SUSPENDED
  56: RETURN_VALUE         
  58: LOAD_FAST            generator
  60: LOAD_ATTR            gi_frame
  70: POP_JUMP_FORWARD_IF_NOT_NONE to 86
  72: LOAD_GLOBAL          GEN_CLOSED
  84: RETURN_VALUE         
  86: LOAD_GLOBAL          GEN_CREATED
  98: RETURN_VALUE         
