# Disassembly for inspect.BoundArguments.kwargs
# From module file: inspect

## co_consts:
(None, False, True)

## co_names:
('_signature', 'parameters', 'items', 'kind', '_VAR_KEYWORD', '_KEYWORD_ONLY', 'arguments', 'update', 'KeyError')

## bytecode:

   0: RESUME               
   2: BUILD_MAP            
   4: STORE_FAST           kwargs
   6: LOAD_CONST           False
   8: STORE_FAST           kwargs_started
  10: LOAD_FAST            self
  12: LOAD_ATTR            _signature
  22: LOAD_ATTR            parameters
  32: LOAD_METHOD          items
  54: PRECALL              
  58: CALL                 
  68: GET_ITER             
  70: FOR_ITER             to 310
  72: UNPACK_SEQUENCE      
  76: STORE_FAST           param_name
  78: STORE_FAST           param
  80: LOAD_FAST            kwargs_started
  82: POP_JUMP_FORWARD_IF_TRUE to 156
  84: LOAD_FAST            param
  86: LOAD_ATTR            kind
  96: LOAD_GLOBAL          _VAR_KEYWORD
 108: LOAD_GLOBAL          _KEYWORD_ONLY
 120: BUILD_TUPLE          
 122: CONTAINS_OP          
 124: POP_JUMP_FORWARD_IF_FALSE to 132
 126: LOAD_CONST           True
 128: STORE_FAST           kwargs_started
 130: JUMP_FORWARD         to 156
 132: LOAD_FAST            param_name
 134: LOAD_FAST            self
 136: LOAD_ATTR            arguments
 146: CONTAINS_OP          
 148: POP_JUMP_FORWARD_IF_FALSE to 156
 150: LOAD_CONST           True
 152: STORE_FAST           kwargs_started
 154: JUMP_BACKWARD        to 70
 156: LOAD_FAST            kwargs_started
 158: POP_JUMP_FORWARD_IF_TRUE to 162
 160: JUMP_BACKWARD        to 70
 162: NOP                  
 164: LOAD_FAST            self
 166: LOAD_ATTR            arguments
 176: LOAD_FAST            param_name
 178: BINARY_SUBSCR        
 188: STORE_FAST           arg
 190: LOAD_FAST            param
 192: LOAD_ATTR            kind
 202: LOAD_GLOBAL          _VAR_KEYWORD
 214: COMPARE_OP           ==
 220: POP_JUMP_FORWARD_IF_FALSE to 266
 222: LOAD_FAST            kwargs
 224: LOAD_METHOD          update
 246: LOAD_FAST            arg
 248: PRECALL              
 252: CALL                 
 262: POP_TOP              
 264: JUMP_BACKWARD        to 70
 266: LOAD_FAST            arg
 268: LOAD_FAST            kwargs
 270: LOAD_FAST            param_name
 272: STORE_SUBSCR         
 276: JUMP_BACKWARD        to 70
 278: PUSH_EXC_INFO        
 280: LOAD_GLOBAL          KeyError
 292: CHECK_EXC_MATCH      
 294: POP_JUMP_FORWARD_IF_FALSE to 302
 296: POP_TOP              
 298: POP_EXCEPT           
 300: JUMP_BACKWARD        to 70
 302: RERAISE              
 304: COPY                 
 306: POP_EXCEPT           
 308: RERAISE              
 310: LOAD_FAST            kwargs
 312: RETURN_VALUE         
