# Disassembly for inspect._has_code_flag
# From module file: inspect

## co_consts:
('Return true if ``f`` is a function (or a method or functools.partial\n    wrapper wrapping a function) whose code object has the given ``flag``\n    set in its flags.', False)

## co_names:
('ismethod', '__func__', 'functools', '_unwrap_partial', 'isfunction', '_signature_is_functionlike', 'bool', '__code__', 'co_flags')

## bytecode:

   0: RESUME               
   2: LOAD_GLOBAL          NULL + ismethod
  14: LOAD_FAST            f
  16: PRECALL              
  20: CALL                 
  30: POP_JUMP_FORWARD_IF_FALSE to 76
  32: LOAD_FAST            f
  34: LOAD_ATTR            __func__
  44: STORE_FAST           f
  46: LOAD_GLOBAL          NULL + ismethod
  58: LOAD_FAST            f
  60: PRECALL              
  64: CALL                 
  74: POP_JUMP_BACKWARD_IF_TRUE to 32
  76: LOAD_GLOBAL          NULL + functools
  88: LOAD_ATTR            _unwrap_partial
  98: LOAD_FAST            f
 100: PRECALL              
 104: CALL                 
 114: STORE_FAST           f
 116: LOAD_GLOBAL          NULL + isfunction
 128: LOAD_FAST            f
 130: PRECALL              
 134: CALL                 
 144: POP_JUMP_FORWARD_IF_TRUE to 180
 146: LOAD_GLOBAL          NULL + _signature_is_functionlike
 158: LOAD_FAST            f
 160: PRECALL              
 164: CALL                 
 174: POP_JUMP_FORWARD_IF_TRUE to 180
 176: LOAD_CONST           False
 178: RETURN_VALUE         
 180: LOAD_GLOBAL          NULL + bool
 192: LOAD_FAST            f
 194: LOAD_ATTR            __code__
 204: LOAD_ATTR            co_flags
 214: LOAD_FAST            flag
 216: BINARY_OP            &
 220: PRECALL              
 224: CALL                 
 234: RETURN_VALUE         
