# Disassembly for inspect._signature_fromstr.p
# From module file: inspect

## co_consts:
(None, '{!r} builtin has invalid signature', ('default', 'annotation'))

## co_names:
('_empty', 'visit', 'ast', 'literal_eval', 'ValueError', 'format', 'append')

## bytecode:

   0: COPY_FREE_VARS       
   2: RESUME               
   4: PUSH_NULL            
   6: LOAD_DEREF           parse_name
   8: LOAD_FAST            name_node
  10: PRECALL              
  14: CALL                 
  24: STORE_FAST           name
  26: LOAD_FAST            default_node
  28: POP_JUMP_FORWARD_IF_FALSE to 248
  30: LOAD_FAST            default_node
  32: LOAD_GLOBAL          _empty
  44: IS_OP                
  46: POP_JUMP_FORWARD_IF_FALSE to 248
  48: NOP                  
  50: PUSH_NULL            
  52: LOAD_DEREF           RewriteSymbolics
  54: PRECALL              
  58: CALL                 
  68: LOAD_METHOD          visit
  90: LOAD_FAST            default_node
  92: PRECALL              
  96: CALL                 
 106: STORE_FAST           default_node
 108: LOAD_GLOBAL          NULL + ast
 120: LOAD_ATTR            literal_eval
 130: LOAD_FAST            default_node
 132: PRECALL              
 136: CALL                 
 146: STORE_FAST           default
 148: JUMP_FORWARD         to 248
 150: PUSH_EXC_INFO        
 152: LOAD_GLOBAL          ValueError
 164: CHECK_EXC_MATCH      
 166: POP_JUMP_FORWARD_IF_FALSE to 240
 168: POP_TOP              
 170: LOAD_GLOBAL          NULL + ValueError
 182: LOAD_CONST           '{!r} builtin has invalid signature'
 184: LOAD_METHOD          format
 206: LOAD_DEREF           obj
 208: PRECALL              
 212: CALL                 
 222: PRECALL              
 226: CALL                 
 236: LOAD_CONST           None
 238: RAISE_VARARGS        
 240: RERAISE              
 242: COPY                 
 244: POP_EXCEPT           
 246: RERAISE              
 248: LOAD_DEREF           parameters
 250: LOAD_METHOD          append
 272: PUSH_NULL            
 274: LOAD_DEREF           Parameter
 276: LOAD_FAST            name
 278: LOAD_DEREF           kind
 280: LOAD_FAST            default
 282: LOAD_DEREF           empty
 284: KW_NAMES             
 286: PRECALL              
 290: CALL                 
 300: PRECALL              
 304: CALL                 
 314: POP_TOP              
 316: LOAD_CONST           None
 318: RETURN_VALUE         
