# Disassembly for inspect.BlockFinder
# From module file: inspect

## co_consts:
('BlockFinder', 'Provide a tokeneater() method to detect the end of a code block.', <code object __init__ at 0x000002406941A790, file "inspect.py", line 1172>, <code object tokeneater at 0x0000024068DCB540, file "inspect.py", line 1181>, None)

## co_names:
('__name__', '__module__', '__qualname__', '__doc__', '__init__', 'tokeneater')

## bytecode:

   0: RESUME               
   2: LOAD_NAME            __name__
   4: STORE_NAME           __module__
   6: LOAD_CONST           'BlockFinder'
   8: STORE_NAME           __qualname__
  10: LOAD_CONST           'Provide a tokeneater() method to detect the end of a code block.'
  12: STORE_NAME           __doc__
  14: LOAD_CONST           <code object __init__ at 0x000002406941A790, file "inspect.py", line 1172>
  16: MAKE_FUNCTION        
  18: STORE_NAME           __init__
  20: LOAD_CONST           <code object tokeneater at 0x0000024068DCB540, file "inspect.py", line 1181>
  22: MAKE_FUNCTION        
  24: STORE_NAME           tokeneater
  26: LOAD_CONST           None
  28: RETURN_VALUE         
