# Disassembly for inspect.isfunction
# From module file: inspect

## co_consts:
('Return true if the object is a user-defined function.\n\n    Function objects provide these attributes:\n        __doc__         documentation string\n        __name__        name with which this function was defined\n        __code__        code object containing compiled function bytecode\n        __defaults__    tuple of any default values for arguments\n        __globals__     global namespace in which this function was defined\n        __annotations__ dict of parameter annotations\n        __kwdefaults__  dict of keyword only parameters with defaults',)

## co_names:
('isinstance', 'types', 'FunctionType')

## bytecode:

   0: RESUME               
   2: LOAD_GLOBAL          NULL + isinstance
  14: LOAD_FAST            object
  16: LOAD_GLOBAL          types
  28: LOAD_ATTR            FunctionType
  38: PRECALL              
  42: CALL                 
  52: RETURN_VALUE         
