# Disassembly for inspect._main
# From module file: inspect

## co_consts:
(' Logic for inspecting an object given at command line ', 0, None, 'object', "The object to be analysed. It supports the 'module:qualname' syntax", ('help',), '-d', '--details', 'store_true', 'Display info about the module rather than its source code', ('action', 'help'), ':', 'Failed to import {} ({}: {})', ('file',), 2, '.', "Can't get info for builtin modules.", 1, 'Target: {}', 'Origin: {}', 'Cached: {}', 'Loader: {}', '__path__', 'Submodule search path: {}', 'Line: {}', '\n')

## co_names:
('argparse', 'importlib', 'ArgumentParser', 'add_argument', 'parse_args', 'object', 'partition', 'import_module', 'Exception', 'format', 'type', '__name__', 'print', 'sys', 'stderr', 'exit', 'split', 'getattr', 'builtin_module_names', 'details', 'getsourcefile', '__cached__', 'repr', '__loader__', 'hasattr', '__path__', 'findsource', 'getsource')

## bytecode:

   0: RESUME               
   2: LOAD_CONST           0
   4: LOAD_CONST           None
   6: IMPORT_NAME          argparse
   8: STORE_FAST           argparse
  10: LOAD_CONST           0
  12: LOAD_CONST           None
  14: IMPORT_NAME          importlib
  16: STORE_FAST           importlib
  18: LOAD_FAST            argparse
  20: LOAD_METHOD          ArgumentParser
  42: PRECALL              
  46: CALL                 
  56: STORE_FAST           parser
  58: LOAD_FAST            parser
  60: LOAD_METHOD          add_argument
  82: LOAD_CONST           'object'
  84: LOAD_CONST           "The object to be analysed. It supports the 'module:qualname' syntax"
  86: KW_NAMES             
  88: PRECALL              
  92: CALL                 
 102: POP_TOP              
 104: LOAD_FAST            parser
 106: LOAD_METHOD          add_argument
 128: LOAD_CONST           '-d'
 130: LOAD_CONST           '--details'
 132: LOAD_CONST           'store_true'
 134: LOAD_CONST           'Display info about the module rather than its source code'
 136: KW_NAMES             
 138: PRECALL              
 142: CALL                 
 152: POP_TOP              
 154: LOAD_FAST            parser
 156: LOAD_METHOD          parse_args
 178: PRECALL              
 182: CALL                 
 192: STORE_FAST           args
 194: LOAD_FAST            args
 196: LOAD_ATTR            object
 206: STORE_FAST           target
 208: LOAD_FAST            target
 210: LOAD_METHOD          partition
 232: LOAD_CONST           ':'
 234: PRECALL              
 238: CALL                 
 248: UNPACK_SEQUENCE      
 252: STORE_FAST           mod_name
 254: STORE_FAST           has_attrs
 256: STORE_FAST           attrs
 258: NOP                  
 260: PUSH_NULL            
 262: LOAD_FAST            importlib
 264: LOAD_ATTR            import_module
 274: LOAD_FAST            mod_name
 276: PRECALL              
 280: CALL                 
 290: COPY                 
 292: STORE_FAST           obj
 294: STORE_FAST           module
 296: JUMP_FORWARD         to 520
 298: PUSH_EXC_INFO        
 300: LOAD_GLOBAL          Exception
 312: CHECK_EXC_MATCH      
 314: POP_JUMP_FORWARD_IF_FALSE to 512
 316: STORE_FAST           exc
 318: LOAD_CONST           'Failed to import {} ({}: {})'
 320: LOAD_METHOD          format
 342: LOAD_FAST            mod_name
 344: LOAD_GLOBAL          NULL + type
 356: LOAD_FAST            exc
 358: PRECALL              
 362: CALL                 
 372: LOAD_ATTR            __name__
 382: LOAD_FAST            exc
 384: PRECALL              
 388: CALL                 
 398: STORE_FAST           msg
 400: LOAD_GLOBAL          NULL + print
 412: LOAD_FAST            msg
 414: LOAD_GLOBAL          sys
 426: LOAD_ATTR            stderr
 436: KW_NAMES             
 438: PRECALL              
 442: CALL                 
 452: POP_TOP              
 454: LOAD_GLOBAL          NULL + sys
 466: LOAD_ATTR            exit
 476: LOAD_CONST           2
 478: PRECALL              
 482: CALL                 
 492: POP_TOP              
 494: POP_EXCEPT           
 496: LOAD_CONST           None
 498: STORE_FAST           exc
 500: DELETE_FAST          exc
 502: JUMP_FORWARD         to 520
 504: LOAD_CONST           None
 506: STORE_FAST           exc
 508: DELETE_FAST          exc
 510: RERAISE              
 512: RERAISE              
 514: COPY                 
 516: POP_EXCEPT           
 518: RERAISE              
 520: LOAD_FAST            has_attrs
 522: POP_JUMP_FORWARD_IF_FALSE to 612
 524: LOAD_FAST            attrs
 526: LOAD_METHOD          split
 548: LOAD_CONST           '.'
 550: PRECALL              
 554: CALL                 
 564: STORE_FAST           parts
 566: LOAD_FAST            module
 568: STORE_FAST           obj
 570: LOAD_FAST            parts
 572: GET_ITER             
 574: FOR_ITER             to 612
 576: STORE_FAST           part
 578: LOAD_GLOBAL          NULL + getattr
 590: LOAD_FAST            obj
 592: LOAD_FAST            part
 594: PRECALL              
 598: CALL                 
 608: STORE_FAST           obj
 610: JUMP_BACKWARD        to 574
 612: LOAD_FAST            module
 614: LOAD_ATTR            __name__
 624: LOAD_GLOBAL          sys
 636: LOAD_ATTR            builtin_module_names
 646: CONTAINS_OP          
 648: POP_JUMP_FORWARD_IF_FALSE to 744
 650: LOAD_GLOBAL          NULL + print
 662: LOAD_CONST           "Can't get info for builtin modules."
 664: LOAD_GLOBAL          sys
 676: LOAD_ATTR            stderr
 686: KW_NAMES             
 688: PRECALL              
 692: CALL                 
 702: POP_TOP              
 704: LOAD_GLOBAL          NULL + sys
 716: LOAD_ATTR            exit
 726: LOAD_CONST           1
 728: PRECALL              
 732: CALL                 
 742: POP_TOP              
 744: LOAD_FAST            args
 746: LOAD_ATTR            details
 756: EXTENDED_ARG         
 758: POP_JUMP_FORWARD_IF_FALSE to 1398
 760: LOAD_GLOBAL          NULL + print
 772: LOAD_CONST           'Target: {}'
 774: LOAD_METHOD          format
 796: LOAD_FAST            target
 798: PRECALL              
 802: CALL                 
 812: PRECALL              
 816: CALL                 
 826: POP_TOP              
 828: LOAD_GLOBAL          NULL + print
 840: LOAD_CONST           'Origin: {}'
 842: LOAD_METHOD          format
 864: LOAD_GLOBAL          NULL + getsourcefile
 876: LOAD_FAST            module
 878: PRECALL              
 882: CALL                 
 892: PRECALL              
 896: CALL                 
 906: PRECALL              
 910: CALL                 
 920: POP_TOP              
 922: LOAD_GLOBAL          NULL + print
 934: LOAD_CONST           'Cached: {}'
 936: LOAD_METHOD          format
 958: LOAD_FAST            module
 960: LOAD_ATTR            __cached__
 970: PRECALL              
 974: CALL                 
 984: PRECALL              
 988: CALL                 
 998: POP_TOP              
1000: LOAD_FAST            obj
1002: LOAD_FAST            module
1004: IS_OP                
1006: POP_JUMP_FORWARD_IF_FALSE to 1224
1008: LOAD_GLOBAL          NULL + print
1020: LOAD_CONST           'Loader: {}'
1022: LOAD_METHOD          format
1044: LOAD_GLOBAL          NULL + repr
1056: LOAD_FAST            module
1058: LOAD_ATTR            __loader__
1068: PRECALL              
1072: CALL                 
1082: PRECALL              
1086: CALL                 
1096: PRECALL              
1100: CALL                 
1110: POP_TOP              
1112: LOAD_GLOBAL          NULL + hasattr
1124: LOAD_FAST            module
1126: LOAD_CONST           '__path__'
1128: PRECALL              
1132: CALL                 
1142: POP_JUMP_FORWARD_IF_FALSE to 1222
1144: LOAD_GLOBAL          NULL + print
1156: LOAD_CONST           'Submodule search path: {}'
1158: LOAD_METHOD          format
1180: LOAD_FAST            module
1182: LOAD_ATTR            __path__
1192: PRECALL              
1196: CALL                 
1206: PRECALL              
1210: CALL                 
1220: POP_TOP              
1222: JUMP_FORWARD         to 1364
1224: NOP                  
1226: LOAD_GLOBAL          NULL + findsource
1238: LOAD_FAST            obj
1240: PRECALL              
1244: CALL                 
1254: UNPACK_SEQUENCE      
1258: STORE_FAST           __
1260: STORE_FAST           lineno
1262: LOAD_GLOBAL          NULL + print
1274: LOAD_CONST           'Line: {}'
1276: LOAD_METHOD          format
1298: LOAD_FAST            lineno
1300: PRECALL              
1304: CALL                 
1314: PRECALL              
1318: CALL                 
1328: POP_TOP              
1330: JUMP_FORWARD         to 1364
1332: PUSH_EXC_INFO        
1334: LOAD_GLOBAL          Exception
1346: CHECK_EXC_MATCH      
1348: POP_JUMP_FORWARD_IF_FALSE to 1356
1350: POP_TOP              
1352: POP_EXCEPT           
1354: JUMP_FORWARD         to 1364
1356: RERAISE              
1358: COPY                 
1360: POP_EXCEPT           
1362: RERAISE              
1364: LOAD_GLOBAL          NULL + print
1376: LOAD_CONST           '\n'
1378: PRECALL              
1382: CALL                 
1392: POP_TOP              
1394: LOAD_CONST           None
1396: RETURN_VALUE         
1398: LOAD_GLOBAL          NULL + print
1410: LOAD_GLOBAL          NULL + getsource
1422: LOAD_FAST            obj
1424: PRECALL              
1428: CALL                 
1438: PRECALL              
1442: CALL                 
1452: POP_TOP              
1454: LOAD_CONST           None
1456: RETURN_VALUE         
