# Disassembly for inspect.formatargvalues.convert
# From module file: inspect

## co_consts:
(None,)

## co_names:
()

## bytecode:

   0: RESUME               
   2: PUSH_NULL            
   4: LOAD_FAST            formatarg
   6: LOAD_FAST            name
   8: PRECALL              
  12: CALL                 
  22: PUSH_NULL            
  24: LOAD_FAST            formatvalue
  26: LOAD_FAST            locals
  28: LOAD_FAST            name
  30: BINARY_SUBSCR        
  40: PRECALL              
  44: CALL                 
  54: BINARY_OP            +
  58: RETURN_VALUE         
