# Disassembly for inspect.getsourcefile
# From module file: inspect

## co_consts:
("Return the filename that can be used to locate an object's source.\n    Return None if no way can be identified to get the source.\n    ", None, <code object <genexpr> at 0x00000240693EA230, file "inspect.py", line 943>, 0, <code object <genexpr> at 0x00000240693EA430, file "inspect.py", line 946>, '__loader__', '__spec__', 'loader')

## co_names:
('getfile', 'importlib', 'machinery', 'DEBUG_BYTECODE_SUFFIXES', 'OPTIMIZED_BYTECODE_SUFFIXES', 'any', 'os', 'path', 'splitext', 'SOURCE_SUFFIXES', 'EXTENSION_SUFFIXES', 'exists', 'getmodule', 'getattr', 'linecache', 'cache')

## bytecode:

   0: MAKE_CELL            filename
   2: RESUME               
   4: LOAD_GLOBAL          NULL + getfile
  16: LOAD_FAST            object
  18: PRECALL              
  22: CALL                 
  32: STORE_DEREF          filename
  34: LOAD_GLOBAL          importlib
  46: LOAD_ATTR            machinery
  56: LOAD_ATTR            DEBUG_BYTECODE_SUFFIXES
  66: LOAD_CONST           None
  68: LOAD_CONST           None
  70: BUILD_SLICE          
  72: BINARY_SUBSCR        
  82: STORE_FAST           all_bytecode_suffixes
  84: LOAD_FAST            all_bytecode_suffixes
  86: LOAD_GLOBAL          importlib
  98: LOAD_ATTR            machinery
 108: LOAD_ATTR            OPTIMIZED_BYTECODE_SUFFIXES
 118: LOAD_CONST           None
 120: LOAD_CONST           None
 122: BUILD_SLICE          
 124: BINARY_SUBSCR        
 134: BINARY_OP            +=
 138: STORE_FAST           all_bytecode_suffixes
 140: LOAD_GLOBAL          NULL + any
 152: LOAD_CLOSURE         filename
 154: BUILD_TUPLE          
 156: LOAD_CONST           <code object <genexpr> at 0x00000240693EA230, file "inspect.py", line 943>
 158: MAKE_FUNCTION        closure
 160: LOAD_FAST            all_bytecode_suffixes
 162: GET_ITER             
 164: PRECALL              
 168: CALL                 
 178: PRECALL              
 182: CALL                 
 192: POP_JUMP_FORWARD_IF_FALSE to 318
 194: LOAD_GLOBAL          os
 206: LOAD_ATTR            path
 216: LOAD_METHOD          splitext
 238: LOAD_DEREF           filename
 240: PRECALL              
 244: CALL                 
 254: LOAD_CONST           0
 256: BINARY_SUBSCR        
 266: LOAD_GLOBAL          importlib
 278: LOAD_ATTR            machinery
 288: LOAD_ATTR            SOURCE_SUFFIXES
 298: LOAD_CONST           0
 300: BINARY_SUBSCR        
 310: BINARY_OP            +
 314: STORE_DEREF          filename
 316: JUMP_FORWARD         to 406
 318: LOAD_GLOBAL          NULL + any
 330: LOAD_CLOSURE         filename
 332: BUILD_TUPLE          
 334: LOAD_CONST           <code object <genexpr> at 0x00000240693EA430, file "inspect.py", line 946>
 336: MAKE_FUNCTION        closure
 338: LOAD_GLOBAL          importlib
 350: LOAD_ATTR            machinery
 360: LOAD_ATTR            EXTENSION_SUFFIXES
 370: GET_ITER             
 372: PRECALL              
 376: CALL                 
 386: PRECALL              
 390: CALL                 
 400: POP_JUMP_FORWARD_IF_FALSE to 406
 402: LOAD_CONST           None
 404: RETURN_VALUE         
 406: LOAD_GLOBAL          os
 418: LOAD_ATTR            path
 428: LOAD_METHOD          exists
 450: LOAD_DEREF           filename
 452: PRECALL              
 456: CALL                 
 466: POP_JUMP_FORWARD_IF_FALSE to 472
 468: LOAD_DEREF           filename
 470: RETURN_VALUE         
 472: LOAD_GLOBAL          NULL + getmodule
 484: LOAD_FAST            object
 486: LOAD_DEREF           filename
 488: PRECALL              
 492: CALL                 
 502: STORE_FAST           module
 504: LOAD_GLOBAL          NULL + getattr
 516: LOAD_FAST            module
 518: LOAD_CONST           '__loader__'
 520: LOAD_CONST           None
 522: PRECALL              
 526: CALL                 
 536: POP_JUMP_FORWARD_IF_NONE to 542
 538: LOAD_DEREF           filename
 540: RETURN_VALUE         
 542: LOAD_GLOBAL          NULL + getattr
 554: LOAD_GLOBAL          NULL + getattr
 566: LOAD_FAST            module
 568: LOAD_CONST           '__spec__'
 570: LOAD_CONST           None
 572: PRECALL              
 576: CALL                 
 586: LOAD_CONST           'loader'
 588: LOAD_CONST           None
 590: PRECALL              
 594: CALL                 
 604: POP_JUMP_FORWARD_IF_NONE to 610
 606: LOAD_DEREF           filename
 608: RETURN_VALUE         
 610: LOAD_DEREF           filename
 612: LOAD_GLOBAL          linecache
 624: LOAD_ATTR            cache
 634: CONTAINS_OP          
 636: POP_JUMP_FORWARD_IF_FALSE to 642
 638: LOAD_DEREF           filename
 640: RETURN_VALUE         
 642: LOAD_CONST           None
 644: RETURN_VALUE         
