# Disassembly for inspect.get_annotations
# From module file: inspect

## co_consts:
('Compute the annotations dict for an object.\n\n    obj may be a callable, class, or module.\n    Passing in an object of any other type raises TypeError.\n\n    Returns a dict.  get_annotations() returns a new dict every time\n    it\'s called; calling it twice on the same object will return two\n    different but equivalent dicts.\n\n    This function handles several details for you:\n\n      * If eval_str is true, values of type str will\n        be un-stringized using eval().  This is intended\n        for use with stringized annotations\n        ("from __future__ import annotations").\n      * If obj doesn\'t have an annotations dict, returns an\n        empty dict.  (Functions and methods always have an\n        annotations dict; classes, modules, and other types of\n        callables may not.)\n      * Ignores inherited annotations on classes.  If a class\n        doesn\'t have its own annotations dict, returns an empty dict.\n      * All accesses to object members and dict values are done\n        using getattr() and dict.get() for safety.\n      * Always, always, always returns a freshly-created dict.\n\n    eval_str controls whether or not values of type str are replaced\n    with the result of calling eval() on those values:\n\n      * If eval_str is true, eval() is called on values of type str.\n      * If eval_str is false (the default), values of type str are unchanged.\n\n    globals and locals are passed in to eval(); see the documentation\n    for eval() for more information.  If either globals or locals is\n    None, this function may replace that value with a context-specific\n    default, contingent on type(obj):\n\n      * If obj is a module, globals defaults to obj.__dict__.\n      * If obj is a class, globals defaults to\n        sys.modules[obj.__module__].__dict__ and locals\n        defaults to the obj class namespace.\n      * If obj is a callable, globals defaults to obj.__globals__,\n        although if obj is a wrapped function (using\n        functools.update_wrapper()) it is first unwrapped.\n    ', '__dict__', None, 'get', '__annotations__', '__module__', '__globals__', ' is not a module, class, or callable.', '.__annotations__ is neither a dict nor None', True, '__wrapped__', <code object <dictcomp> at 0x000002406941AC10, file "inspect.py", line 276>)

## co_names:
('isinstance', 'type', 'getattr', 'hasattr', 'get', 'types', 'GetSetDescriptorType', 'sys', 'modules', 'dict', 'vars', 'ModuleType', 'callable', 'TypeError', 'ValueError', '__wrapped__', 'functools', 'partial', 'func', '__globals__', 'items')

## bytecode:

   0: MAKE_CELL            globals
   2: MAKE_CELL            locals
   4: RESUME               
   6: LOAD_GLOBAL          NULL + isinstance
  18: LOAD_FAST            obj
  20: LOAD_GLOBAL          type
  32: PRECALL              
  36: CALL                 
  46: POP_JUMP_FORWARD_IF_FALSE to 430
  48: LOAD_GLOBAL          NULL + getattr
  60: LOAD_FAST            obj
  62: LOAD_CONST           '__dict__'
  64: LOAD_CONST           None
  66: PRECALL              
  70: CALL                 
  80: STORE_FAST           obj_dict
  82: LOAD_FAST            obj_dict
  84: POP_JUMP_FORWARD_IF_FALSE to 220
  86: LOAD_GLOBAL          NULL + hasattr
  98: LOAD_FAST            obj_dict
 100: LOAD_CONST           'get'
 102: PRECALL              
 106: CALL                 
 116: POP_JUMP_FORWARD_IF_FALSE to 220
 118: LOAD_FAST            obj_dict
 120: LOAD_METHOD          get
 142: LOAD_CONST           '__annotations__'
 144: LOAD_CONST           None
 146: PRECALL              
 150: CALL                 
 160: STORE_FAST           ann
 162: LOAD_GLOBAL          NULL + isinstance
 174: LOAD_FAST            ann
 176: LOAD_GLOBAL          types
 188: LOAD_ATTR            GetSetDescriptorType
 198: PRECALL              
 202: CALL                 
 212: POP_JUMP_FORWARD_IF_FALSE to 218
 214: LOAD_CONST           None
 216: STORE_FAST           ann
 218: JUMP_FORWARD         to 224
 220: LOAD_CONST           None
 222: STORE_FAST           ann
 224: LOAD_CONST           None
 226: STORE_FAST           obj_globals
 228: LOAD_GLOBAL          NULL + getattr
 240: LOAD_FAST            obj
 242: LOAD_CONST           '__module__'
 244: LOAD_CONST           None
 246: PRECALL              
 250: CALL                 
 260: STORE_FAST           module_name
 262: LOAD_FAST            module_name
 264: POP_JUMP_FORWARD_IF_FALSE to 368
 266: LOAD_GLOBAL          sys
 278: LOAD_ATTR            modules
 288: LOAD_METHOD          get
 310: LOAD_FAST            module_name
 312: LOAD_CONST           None
 314: PRECALL              
 318: CALL                 
 328: STORE_FAST           module
 330: LOAD_FAST            module
 332: POP_JUMP_FORWARD_IF_FALSE to 368
 334: LOAD_GLOBAL          NULL + getattr
 346: LOAD_FAST            module
 348: LOAD_CONST           '__dict__'
 350: LOAD_CONST           None
 352: PRECALL              
 356: CALL                 
 366: STORE_FAST           obj_globals
 368: LOAD_GLOBAL          NULL + dict
 380: LOAD_GLOBAL          NULL + vars
 392: LOAD_FAST            obj
 394: PRECALL              
 398: CALL                 
 408: PRECALL              
 412: CALL                 
 422: STORE_FAST           obj_locals
 424: LOAD_FAST            obj
 426: STORE_FAST           unwrap
 428: JUMP_FORWARD         to 702
 430: LOAD_GLOBAL          NULL + isinstance
 442: LOAD_FAST            obj
 444: LOAD_GLOBAL          types
 456: LOAD_ATTR            ModuleType
 466: PRECALL              
 470: CALL                 
 480: POP_JUMP_FORWARD_IF_FALSE to 558
 482: LOAD_GLOBAL          NULL + getattr
 494: LOAD_FAST            obj
 496: LOAD_CONST           '__annotations__'
 498: LOAD_CONST           None
 500: PRECALL              
 504: CALL                 
 514: STORE_FAST           ann
 516: LOAD_GLOBAL          NULL + getattr
 528: LOAD_FAST            obj
 530: LOAD_CONST           '__dict__'
 532: PRECALL              
 536: CALL                 
 546: STORE_FAST           obj_globals
 548: LOAD_CONST           None
 550: STORE_FAST           obj_locals
 552: LOAD_CONST           None
 554: STORE_FAST           unwrap
 556: JUMP_FORWARD         to 702
 558: LOAD_GLOBAL          NULL + callable
 570: LOAD_FAST            obj
 572: PRECALL              
 576: CALL                 
 586: POP_JUMP_FORWARD_IF_FALSE to 666
 588: LOAD_GLOBAL          NULL + getattr
 600: LOAD_FAST            obj
 602: LOAD_CONST           '__annotations__'
 604: LOAD_CONST           None
 606: PRECALL              
 610: CALL                 
 620: STORE_FAST           ann
 622: LOAD_GLOBAL          NULL + getattr
 634: LOAD_FAST            obj
 636: LOAD_CONST           '__globals__'
 638: LOAD_CONST           None
 640: PRECALL              
 644: CALL                 
 654: STORE_FAST           obj_globals
 656: LOAD_CONST           None
 658: STORE_FAST           obj_locals
 660: LOAD_FAST            obj
 662: STORE_FAST           unwrap
 664: JUMP_FORWARD         to 702
 666: LOAD_GLOBAL          NULL + TypeError
 678: LOAD_FAST            obj
 680: FORMAT_VALUE         repr
 682: LOAD_CONST           ' is not a module, class, or callable.'
 684: BUILD_STRING         
 686: PRECALL              
 690: CALL                 
 700: RAISE_VARARGS        
 702: LOAD_FAST            ann
 704: POP_JUMP_FORWARD_IF_NOT_NONE to 710
 706: BUILD_MAP            
 708: RETURN_VALUE         
 710: LOAD_GLOBAL          NULL + isinstance
 722: LOAD_FAST            ann
 724: LOAD_GLOBAL          dict
 736: PRECALL              
 740: CALL                 
 750: POP_JUMP_FORWARD_IF_TRUE to 788
 752: LOAD_GLOBAL          NULL + ValueError
 764: LOAD_FAST            obj
 766: FORMAT_VALUE         repr
 768: LOAD_CONST           '.__annotations__ is neither a dict nor None'
 770: BUILD_STRING         
 772: PRECALL              
 776: CALL                 
 786: RAISE_VARARGS        
 788: LOAD_FAST            ann
 790: POP_JUMP_FORWARD_IF_TRUE to 796
 792: BUILD_MAP            
 794: RETURN_VALUE         
 796: LOAD_FAST            eval_str
 798: POP_JUMP_FORWARD_IF_TRUE to 830
 800: LOAD_GLOBAL          NULL + dict
 812: LOAD_FAST            ann
 814: PRECALL              
 818: CALL                 
 828: RETURN_VALUE         
 830: LOAD_FAST            unwrap
 832: POP_JUMP_FORWARD_IF_NONE to 1000
 834: NOP                  
 836: LOAD_GLOBAL          NULL + hasattr
 848: LOAD_FAST            unwrap
 850: LOAD_CONST           '__wrapped__'
 852: PRECALL              
 856: CALL                 
 866: POP_JUMP_FORWARD_IF_FALSE to 884
 868: LOAD_FAST            unwrap
 870: LOAD_ATTR            __wrapped__
 880: STORE_FAST           unwrap
 882: JUMP_BACKWARD        to 834
 884: LOAD_GLOBAL          NULL + isinstance
 896: LOAD_FAST            unwrap
 898: LOAD_GLOBAL          functools
 910: LOAD_ATTR            partial
 920: PRECALL              
 924: CALL                 
 934: POP_JUMP_FORWARD_IF_FALSE to 952
 936: LOAD_FAST            unwrap
 938: LOAD_ATTR            func
 948: STORE_FAST           unwrap
 950: JUMP_BACKWARD        to 834
 952: NOP                  
 954: LOAD_GLOBAL          NULL + hasattr
 966: LOAD_FAST            unwrap
 968: LOAD_CONST           '__globals__'
 970: PRECALL              
 974: CALL                 
 984: POP_JUMP_FORWARD_IF_FALSE to 1000
 986: LOAD_FAST            unwrap
 988: LOAD_ATTR            __globals__
 998: STORE_FAST           obj_globals
1000: LOAD_DEREF           globals
1002: POP_JUMP_FORWARD_IF_NOT_NONE to 1008
1004: LOAD_FAST            obj_globals
1006: STORE_DEREF          globals
1008: LOAD_DEREF           locals
1010: POP_JUMP_FORWARD_IF_NOT_NONE to 1016
1012: LOAD_FAST            obj_locals
1014: STORE_DEREF          locals
1016: LOAD_CLOSURE         globals
1018: LOAD_CLOSURE         locals
1020: BUILD_TUPLE          
1022: LOAD_CONST           <code object <dictcomp> at 0x000002406941AC10, file "inspect.py", line 276>
1024: MAKE_FUNCTION        closure
1026: LOAD_FAST            ann
1028: LOAD_METHOD          items
1050: PRECALL              
1054: CALL                 
1064: GET_ITER             
1066: PRECALL              
1070: CALL                 
1080: STORE_FAST           return_value
1082: LOAD_FAST            return_value
1084: RETURN_VALUE         
