# Disassembly for inspect.getsource
# From module file: inspect

## co_consts:
('Return the text of the source code for an object.\n\n    The argument may be a module, class, method, function, traceback, frame,\n    or code object.  The source code is returned as a single string.  An\n    OSError is raised if the source code cannot be retrieved.', '')

## co_names:
('getsourcelines', 'join')

## bytecode:

   0: RESUME               
   2: LOAD_GLOBAL          NULL + getsourcelines
  14: LOAD_FAST            object
  16: PRECALL              
  20: CALL                 
  30: UNPACK_SEQUENCE      
  34: STORE_FAST           lines
  36: STORE_FAST           lnum
  38: LOAD_CONST           ''
  40: LOAD_METHOD          join
  62: LOAD_FAST            lines
  64: PRECALL              
  68: CALL                 
  78: RETURN_VALUE         
