# Disassembly for inspect.isdatadescriptor
# From module file: inspect

## co_consts:
('Return true if the object is a data descriptor.\n\n    Data descriptors have a __set__ or a __delete__ attribute.  Examples are\n    properties (defined in Python) and getsets and members (defined in C).\n    Typically, data descriptors will also have __name__ and __doc__ attributes\n    (properties, getsets, and members have both of these attributes), but this\n    is not guaranteed.', False, '__set__', '__delete__')

## co_names:
('isclass', 'ismethod', 'isfunction', 'type', 'hasattr')

## bytecode:

   0: RESUME               
   2: LOAD_GLOBAL          NULL + isclass
  14: LOAD_FAST            object
  16: PRECALL              
  20: CALL                 
  30: POP_JUMP_FORWARD_IF_TRUE to 92
  32: LOAD_GLOBAL          NULL + ismethod
  44: LOAD_FAST            object
  46: PRECALL              
  50: CALL                 
  60: POP_JUMP_FORWARD_IF_TRUE to 92
  62: LOAD_GLOBAL          NULL + isfunction
  74: LOAD_FAST            object
  76: PRECALL              
  80: CALL                 
  90: POP_JUMP_FORWARD_IF_FALSE to 96
  92: LOAD_CONST           False
  94: RETURN_VALUE         
  96: LOAD_GLOBAL          NULL + type
 108: LOAD_FAST            object
 110: PRECALL              
 114: CALL                 
 124: STORE_FAST           tp
 126: LOAD_GLOBAL          NULL + hasattr
 138: LOAD_FAST            tp
 140: LOAD_CONST           '__set__'
 142: PRECALL              
 146: CALL                 
 156: JUMP_IF_TRUE_OR_POP  to 188
 158: LOAD_GLOBAL          NULL + hasattr
 170: LOAD_FAST            tp
 172: LOAD_CONST           '__delete__'
 174: PRECALL              
 178: CALL                 
 188: RETURN_VALUE         
