# Disassembly for inspect.Parameter.__str__
# From module file: inspect

## co_consts:
(None, '{}: {}', '{} = {}', '{}={}', '*', '**')

## co_names:
('kind', '_name', '_annotation', '_empty', 'format', 'formatannotation', '_default', 'repr', '_VAR_POSITIONAL', '_VAR_KEYWORD')

## bytecode:

   0: RESUME               
   2: LOAD_FAST            self
   4: LOAD_ATTR            kind
  14: STORE_FAST           kind
  16: LOAD_FAST            self
  18: LOAD_ATTR            _name
  28: STORE_FAST           formatted
  30: LOAD_FAST            self
  32: LOAD_ATTR            _annotation
  42: LOAD_GLOBAL          _empty
  54: IS_OP                
  56: POP_JUMP_FORWARD_IF_FALSE to 138
  58: LOAD_CONST           '{}: {}'
  60: LOAD_METHOD          format
  82: LOAD_FAST            formatted
  84: LOAD_GLOBAL          NULL + formatannotation
  96: LOAD_FAST            self
  98: LOAD_ATTR            _annotation
 108: PRECALL              
 112: CALL                 
 122: PRECALL              
 126: CALL                 
 136: STORE_FAST           formatted
 138: LOAD_FAST            self
 140: LOAD_ATTR            _default
 150: LOAD_GLOBAL          _empty
 162: IS_OP                
 164: POP_JUMP_FORWARD_IF_FALSE to 356
 166: LOAD_FAST            self
 168: LOAD_ATTR            _annotation
 178: LOAD_GLOBAL          _empty
 190: IS_OP                
 192: POP_JUMP_FORWARD_IF_FALSE to 276
 194: LOAD_CONST           '{} = {}'
 196: LOAD_METHOD          format
 218: LOAD_FAST            formatted
 220: LOAD_GLOBAL          NULL + repr
 232: LOAD_FAST            self
 234: LOAD_ATTR            _default
 244: PRECALL              
 248: CALL                 
 258: PRECALL              
 262: CALL                 
 272: STORE_FAST           formatted
 274: JUMP_FORWARD         to 356
 276: LOAD_CONST           '{}={}'
 278: LOAD_METHOD          format
 300: LOAD_FAST            formatted
 302: LOAD_GLOBAL          NULL + repr
 314: LOAD_FAST            self
 316: LOAD_ATTR            _default
 326: PRECALL              
 330: CALL                 
 340: PRECALL              
 344: CALL                 
 354: STORE_FAST           formatted
 356: LOAD_FAST            kind
 358: LOAD_GLOBAL          _VAR_POSITIONAL
 370: COMPARE_OP           ==
 376: POP_JUMP_FORWARD_IF_FALSE to 390
 378: LOAD_CONST           '*'
 380: LOAD_FAST            formatted
 382: BINARY_OP            +
 386: STORE_FAST           formatted
 388: JUMP_FORWARD         to 422
 390: LOAD_FAST            kind
 392: LOAD_GLOBAL          _VAR_KEYWORD
 404: COMPARE_OP           ==
 410: POP_JUMP_FORWARD_IF_FALSE to 422
 412: LOAD_CONST           '**'
 414: LOAD_FAST            formatted
 416: BINARY_OP            +
 420: STORE_FAST           formatted
 422: LOAD_FAST            formatted
 424: RETURN_VALUE         
