# Disassembly for inspect.getdoc
# From module file: inspect

## co_consts:
('Get the documentation string for an object.\n\n    All tabs are expanded to spaces.  To clean up docstrings that are\n    indented to line up with blocks of code, any whitespace than can be\n    uniformly removed from the second line onwards is removed.', None)

## co_names:
('__doc__', 'AttributeError', '_finddoc', 'TypeError', 'isinstance', 'str', 'cleandoc')

## bytecode:

   0: RESUME               
   2: NOP                  
   4: LOAD_FAST            object
   6: LOAD_ATTR            __doc__
  16: STORE_FAST           doc
  18: JUMP_FORWARD         to 54
  20: PUSH_EXC_INFO        
  22: LOAD_GLOBAL          AttributeError
  34: CHECK_EXC_MATCH      
  36: POP_JUMP_FORWARD_IF_FALSE to 46
  38: POP_TOP              
  40: POP_EXCEPT           
  42: LOAD_CONST           None
  44: RETURN_VALUE         
  46: RERAISE              
  48: COPY                 
  50: POP_EXCEPT           
  52: RERAISE              
  54: LOAD_FAST            doc
  56: POP_JUMP_FORWARD_IF_NOT_NONE to 140
  58: NOP                  
  60: LOAD_GLOBAL          NULL + _finddoc
  72: LOAD_FAST            object
  74: PRECALL              
  78: CALL                 
  88: STORE_FAST           doc
  90: JUMP_FORWARD         to 140
  92: PUSH_EXC_INFO        
  94: LOAD_GLOBAL          AttributeError
 106: LOAD_GLOBAL          TypeError
 118: BUILD_TUPLE          
 120: CHECK_EXC_MATCH      
 122: POP_JUMP_FORWARD_IF_FALSE to 132
 124: POP_TOP              
 126: POP_EXCEPT           
 128: LOAD_CONST           None
 130: RETURN_VALUE         
 132: RERAISE              
 134: COPY                 
 136: POP_EXCEPT           
 138: RERAISE              
 140: LOAD_GLOBAL          NULL + isinstance
 152: LOAD_FAST            doc
 154: LOAD_GLOBAL          str
 166: PRECALL              
 170: CALL                 
 180: POP_JUMP_FORWARD_IF_TRUE to 186
 182: LOAD_CONST           None
 184: RETURN_VALUE         
 186: LOAD_GLOBAL          NULL + cleandoc
 198: LOAD_FAST            doc
 200: PRECALL              
 204: CALL                 
 214: RETURN_VALUE         
