# Disassembly for inspect._missing_arguments.<listcomp>
# From module file: inspect

## co_consts:
()

## co_names:
('repr',)

## bytecode:

   0: COPY_FREE_VARS       
   2: RESUME               
   4: BUILD_LIST           
   6: LOAD_FAST            .0
   8: FOR_ITER             to 52
  10: STORE_FAST           name
  12: LOAD_FAST            name
  14: LOAD_DEREF           values
  16: CONTAINS_OP          
  18: POP_JUMP_BACKWARD_IF_FALSE to 8
  20: LOAD_GLOBAL          NULL + repr
  32: LOAD_FAST            name
  34: PRECALL              
  38: CALL                 
  48: LIST_APPEND          
  50: JUMP_BACKWARD        to 8
  52: RETURN_VALUE         
