# Disassembly for inspect.Parameter.__setstate__
# From module file: inspect

## co_consts:
(None, '_default', '_annotation')

## co_names:
('_default', '_annotation')

## bytecode:

   0: RESUME               
   2: LOAD_FAST            state
   4: LOAD_CONST           '_default'
   6: BINARY_SUBSCR        
  16: LOAD_FAST            self
  18: STORE_ATTR           _default
  28: LOAD_FAST            state
  30: LOAD_CONST           '_annotation'
  32: BINARY_SUBSCR        
  42: LOAD_FAST            self
  44: STORE_ATTR           _annotation
  54: LOAD_CONST           None
  56: RETURN_VALUE         
