# Disassembly for inspect.unwrap._is_wrapper
# From module file: inspect

## co_consts:
(None, '__wrapped__')

## co_names:
('hasattr',)

## bytecode:

   0: COPY_FREE_VARS       
   2: RESUME               
   4: LOAD_GLOBAL          NULL + hasattr
  16: LOAD_FAST            f
  18: LOAD_CONST           '__wrapped__'
  20: PRECALL              
  24: CALL                 
  34: JUMP_IF_FALSE_OR_POP to 58
  36: PUSH_NULL            
  38: LOAD_DEREF           stop
  40: LOAD_FAST            f
  42: PRECALL              
  46: CALL                 
  56: UNARY_NOT            
  58: RETURN_VALUE         
