# Disassembly for inspect.iscode
# From module file: inspect

## co_consts:
('Return true if the object is a code object.\n\n    Code objects provide these attributes:\n        co_argcount         number of arguments (not including *, ** args\n                            or keyword only arguments)\n        co_code             string of raw compiled bytecode\n        co_cellvars         tuple of names of cell variables\n        co_consts           tuple of constants used in the bytecode\n        co_filename         name of file in which this code object was created\n        co_firstlineno      number of first line in Python source code\n        co_flags            bitmap: 1=optimized | 2=newlocals | 4=*arg | 8=**arg\n                            | 16=nested | 32=generator | 64=nofree | 128=coroutine\n                            | 256=iterable_coroutine | 512=async_generator\n        co_freevars         tuple of names of free variables\n        co_posonlyargcount  number of positional only arguments\n        co_kwonlyargcount   number of keyword only arguments (not including ** arg)\n        co_lnotab           encoded mapping of line numbers to bytecode indices\n        co_name             name with which this code object was defined\n        co_names            tuple of names other than arguments and function locals\n        co_nlocals          number of local variables\n        co_stacksize        virtual machine stack space required\n        co_varnames         tuple of names of arguments and local variables',)

## co_names:
('isinstance', 'types', 'CodeType')

## bytecode:

   0: RESUME               
   2: LOAD_GLOBAL          NULL + isinstance
  14: LOAD_FAST            object
  16: LOAD_GLOBAL          types
  28: LOAD_ATTR            CodeType
  38: PRECALL              
  42: CALL                 
  52: RETURN_VALUE         
