# Disassembly for inspect._finddoc
# From module file: inspect

## co_consts:
(None, '__func__', '.', '__slots__')

## co_names:
('isclass', '__mro__', 'object', '__doc__', 'AttributeError', 'ismethod', '__func__', '__name__', '__self__', 'getattr', '__class__', 'isfunction', '_findclass', 'isbuiltin', '__qualname__', 'isinstance', 'property', 'fget', 'ismethoddescriptor', 'isdatadescriptor', '__objclass__', 'ismemberdescriptor', 'dict')

## bytecode:

   0: RESUME               
   2: LOAD_GLOBAL          NULL + isclass
  14: LOAD_FAST            obj
  16: PRECALL              
  20: CALL                 
  30: POP_JUMP_FORWARD_IF_FALSE to 136
  32: LOAD_FAST            obj
  34: LOAD_ATTR            __mro__
  44: GET_ITER             
  46: FOR_ITER             to 132
  48: STORE_FAST           base
  50: LOAD_FAST            base
  52: LOAD_GLOBAL          object
  64: IS_OP                
  66: POP_JUMP_FORWARD_IF_FALSE to 130
  68: NOP                  
  70: LOAD_FAST            base
  72: LOAD_ATTR            __doc__
  82: STORE_FAST           doc
  84: JUMP_FORWARD         to 118
  86: PUSH_EXC_INFO        
  88: LOAD_GLOBAL          AttributeError
 100: CHECK_EXC_MATCH      
 102: POP_JUMP_FORWARD_IF_FALSE to 110
 104: POP_TOP              
 106: POP_EXCEPT           
 108: JUMP_BACKWARD        to 46
 110: RERAISE              
 112: COPY                 
 114: POP_EXCEPT           
 116: RERAISE              
 118: LOAD_FAST            doc
 120: POP_JUMP_FORWARD_IF_NONE to 130
 122: LOAD_FAST            doc
 124: SWAP                 
 126: POP_TOP              
 128: RETURN_VALUE         
 130: JUMP_BACKWARD        to 46
 132: LOAD_CONST           None
 134: RETURN_VALUE         
 136: LOAD_GLOBAL          NULL + ismethod
 148: LOAD_FAST            obj
 150: PRECALL              
 154: CALL                 
 164: POP_JUMP_FORWARD_IF_FALSE to 336
 166: LOAD_FAST            obj
 168: LOAD_ATTR            __func__
 178: LOAD_ATTR            __name__
 188: STORE_FAST           name
 190: LOAD_FAST            obj
 192: LOAD_ATTR            __self__
 202: STORE_FAST           self
 204: LOAD_GLOBAL          NULL + isclass
 216: LOAD_FAST            self
 218: PRECALL              
 222: CALL                 
 232: POP_JUMP_FORWARD_IF_FALSE to 318
 234: LOAD_GLOBAL          NULL + getattr
 246: LOAD_GLOBAL          NULL + getattr
 258: LOAD_FAST            self
 260: LOAD_FAST            name
 262: LOAD_CONST           None
 264: PRECALL              
 268: CALL                 
 278: LOAD_CONST           '__func__'
 280: PRECALL              
 284: CALL                 
 294: LOAD_FAST            obj
 296: LOAD_ATTR            __func__
 306: IS_OP                
 308: POP_JUMP_FORWARD_IF_FALSE to 318
 310: LOAD_FAST            self
 312: STORE_FAST           cls
 314: EXTENDED_ARG         
 316: JUMP_FORWARD         to 1022
 318: LOAD_FAST            self
 320: LOAD_ATTR            __class__
 330: STORE_FAST           cls
 332: EXTENDED_ARG         
 334: JUMP_FORWARD         to 1022
 336: LOAD_GLOBAL          NULL + isfunction
 348: LOAD_FAST            obj
 350: PRECALL              
 354: CALL                 
 364: POP_JUMP_FORWARD_IF_FALSE to 458
 366: LOAD_FAST            obj
 368: LOAD_ATTR            __name__
 378: STORE_FAST           name
 380: LOAD_GLOBAL          NULL + _findclass
 392: LOAD_FAST            obj
 394: PRECALL              
 398: CALL                 
 408: STORE_FAST           cls
 410: LOAD_FAST            cls
 412: POP_JUMP_FORWARD_IF_NONE to 450
 414: LOAD_GLOBAL          NULL + getattr
 426: LOAD_FAST            cls
 428: LOAD_FAST            name
 430: PRECALL              
 434: CALL                 
 444: LOAD_FAST            obj
 446: IS_OP                
 448: POP_JUMP_FORWARD_IF_FALSE to 454
 450: LOAD_CONST           None
 452: RETURN_VALUE         
 454: EXTENDED_ARG         
 456: JUMP_FORWARD         to 1022
 458: LOAD_GLOBAL          NULL + isbuiltin
 470: LOAD_FAST            obj
 472: PRECALL              
 476: CALL                 
 486: POP_JUMP_FORWARD_IF_FALSE to 612
 488: LOAD_FAST            obj
 490: LOAD_ATTR            __name__
 500: STORE_FAST           name
 502: LOAD_FAST            obj
 504: LOAD_ATTR            __self__
 514: STORE_FAST           self
 516: LOAD_GLOBAL          NULL + isclass
 528: LOAD_FAST            self
 530: PRECALL              
 534: CALL                 
 544: POP_JUMP_FORWARD_IF_FALSE to 596
 546: LOAD_FAST            self
 548: LOAD_ATTR            __qualname__
 558: LOAD_CONST           '.'
 560: BINARY_OP            +
 564: LOAD_FAST            name
 566: BINARY_OP            +
 570: LOAD_FAST            obj
 572: LOAD_ATTR            __qualname__
 582: COMPARE_OP           ==
 588: POP_JUMP_FORWARD_IF_FALSE to 596
 590: LOAD_FAST            self
 592: STORE_FAST           cls
 594: JUMP_FORWARD         to 1022
 596: LOAD_FAST            self
 598: LOAD_ATTR            __class__
 608: STORE_FAST           cls
 610: JUMP_FORWARD         to 1022
 612: LOAD_GLOBAL          NULL + isinstance
 624: LOAD_FAST            obj
 626: LOAD_GLOBAL          property
 638: PRECALL              
 642: CALL                 
 652: POP_JUMP_FORWARD_IF_FALSE to 758
 654: LOAD_FAST            obj
 656: LOAD_ATTR            fget
 666: STORE_FAST           func
 668: LOAD_FAST            func
 670: LOAD_ATTR            __name__
 680: STORE_FAST           name
 682: LOAD_GLOBAL          NULL + _findclass
 694: LOAD_FAST            func
 696: PRECALL              
 700: CALL                 
 710: STORE_FAST           cls
 712: LOAD_FAST            cls
 714: POP_JUMP_FORWARD_IF_NONE to 752
 716: LOAD_GLOBAL          NULL + getattr
 728: LOAD_FAST            cls
 730: LOAD_FAST            name
 732: PRECALL              
 736: CALL                 
 746: LOAD_FAST            obj
 748: IS_OP                
 750: POP_JUMP_FORWARD_IF_FALSE to 756
 752: LOAD_CONST           None
 754: RETURN_VALUE         
 756: JUMP_FORWARD         to 1022
 758: LOAD_GLOBAL          NULL + ismethoddescriptor
 770: LOAD_FAST            obj
 772: PRECALL              
 776: CALL                 
 786: POP_JUMP_FORWARD_IF_TRUE to 818
 788: LOAD_GLOBAL          NULL + isdatadescriptor
 800: LOAD_FAST            obj
 802: PRECALL              
 806: CALL                 
 816: POP_JUMP_FORWARD_IF_FALSE to 1018
 818: LOAD_FAST            obj
 820: LOAD_ATTR            __name__
 830: STORE_FAST           name
 832: LOAD_FAST            obj
 834: LOAD_ATTR            __objclass__
 844: STORE_FAST           cls
 846: LOAD_GLOBAL          NULL + getattr
 858: LOAD_FAST            cls
 860: LOAD_FAST            name
 862: PRECALL              
 866: CALL                 
 876: LOAD_FAST            obj
 878: IS_OP                
 880: POP_JUMP_FORWARD_IF_FALSE to 886
 882: LOAD_CONST           None
 884: RETURN_VALUE         
 886: LOAD_GLOBAL          NULL + ismemberdescriptor
 898: LOAD_FAST            obj
 900: PRECALL              
 904: CALL                 
 914: POP_JUMP_FORWARD_IF_FALSE to 1016
 916: LOAD_GLOBAL          NULL + getattr
 928: LOAD_FAST            cls
 930: LOAD_CONST           '__slots__'
 932: LOAD_CONST           None
 934: PRECALL              
 938: CALL                 
 948: STORE_FAST           slots
 950: LOAD_GLOBAL          NULL + isinstance
 962: LOAD_FAST            slots
 964: LOAD_GLOBAL          dict
 976: PRECALL              
 980: CALL                 
 990: POP_JUMP_FORWARD_IF_FALSE to 1016
 992: LOAD_FAST            name
 994: LOAD_FAST            slots
 996: CONTAINS_OP          
 998: POP_JUMP_FORWARD_IF_FALSE to 1016
1000: LOAD_FAST            slots
1002: LOAD_FAST            name
1004: BINARY_SUBSCR        
1014: RETURN_VALUE         
1016: JUMP_FORWARD         to 1022
1018: LOAD_CONST           None
1020: RETURN_VALUE         
1022: LOAD_FAST            cls
1024: LOAD_ATTR            __mro__
1034: GET_ITER             
1036: FOR_ITER             to 1132
1038: STORE_FAST           base
1040: NOP                  
1042: LOAD_GLOBAL          NULL + getattr
1054: LOAD_FAST            base
1056: LOAD_FAST            name
1058: PRECALL              
1062: CALL                 
1072: LOAD_ATTR            __doc__
1082: STORE_FAST           doc
1084: JUMP_FORWARD         to 1118
1086: PUSH_EXC_INFO        
1088: LOAD_GLOBAL          AttributeError
1100: CHECK_EXC_MATCH      
1102: POP_JUMP_FORWARD_IF_FALSE to 1110
1104: POP_TOP              
1106: POP_EXCEPT           
1108: JUMP_BACKWARD        to 1036
1110: RERAISE              
1112: COPY                 
1114: POP_EXCEPT           
1116: RERAISE              
1118: LOAD_FAST            doc
1120: POP_JUMP_FORWARD_IF_NONE to 1130
1122: LOAD_FAST            doc
1124: SWAP                 
1126: POP_TOP              
1128: RETURN_VALUE         
1130: JUMP_BACKWARD        to 1036
1132: LOAD_CONST           None
1134: RETURN_VALUE         
