# Disassembly for inspect.isgenerator
# From module file: inspect

## co_consts:
('Return true if the object is a generator.\n\n    Generator objects provide these attributes:\n        __iter__        defined to support iteration over container\n        close           raises a new GeneratorExit exception inside the\n                        generator to terminate the iteration\n        gi_code         code object\n        gi_frame        frame object or possibly None once the generator has\n                        been exhausted\n        gi_running      set to 1 when generator is executing, 0 otherwise\n        next            return the next item from the container\n        send            resumes the generator and "sends" a value that becomes\n                        the result of the current yield-expression\n        throw           used to raise an exception inside the generator',)

## co_names:
('isinstance', 'types', 'GeneratorType')

## bytecode:

   0: RESUME               
   2: LOAD_GLOBAL          NULL + isinstance
  14: LOAD_FAST            object
  16: LOAD_GLOBAL          types
  28: LOAD_ATTR            GeneratorType
  38: PRECALL              
  42: CALL                 
  52: RETURN_VALUE         
