# Disassembly for inspect.getcoroutinelocals
# From module file: inspect

## co_consts:
('\n    Get the mapping of coroutine local variables to their current values.\n\n    A dict is returned, with the keys the local variable names and values the\n    bound values.', 'cr_frame', None)

## co_names:
('getattr', 'f_locals')

## bytecode:

   0: RESUME               
   2: LOAD_GLOBAL          NULL + getattr
  14: LOAD_FAST            coroutine
  16: LOAD_CONST           'cr_frame'
  18: LOAD_CONST           None
  20: PRECALL              
  24: CALL                 
  34: STORE_FAST           frame
  36: LOAD_FAST            frame
  38: POP_JUMP_FORWARD_IF_NONE to 54
  40: LOAD_FAST            frame
  42: LOAD_ATTR            f_locals
  52: RETURN_VALUE         
  54: BUILD_MAP            
  56: RETURN_VALUE         
