# Disassembly for inspect.Parameter.__eq__
# From module file: inspect

## co_consts:
(None, True)

## co_names:
('isinstance', 'Parameter', 'NotImplemented', '_name', '_kind', '_default', '_annotation')

## bytecode:

   0: RESUME               
   2: LOAD_FAST            self
   4: LOAD_FAST            other
   6: IS_OP                
   8: POP_JUMP_FORWARD_IF_FALSE to 14
  10: LOAD_CONST           True
  12: RETURN_VALUE         
  14: LOAD_GLOBAL          NULL + isinstance
  26: LOAD_FAST            other
  28: LOAD_GLOBAL          Parameter
  40: PRECALL              
  44: CALL                 
  54: POP_JUMP_FORWARD_IF_TRUE to 70
  56: LOAD_GLOBAL          NotImplemented
  68: RETURN_VALUE         
  70: LOAD_FAST            self
  72: LOAD_ATTR            _name
  82: LOAD_FAST            other
  84: LOAD_ATTR            _name
  94: COMPARE_OP           ==
 100: JUMP_IF_FALSE_OR_POP to 196
 102: LOAD_FAST            self
 104: LOAD_ATTR            _kind
 114: LOAD_FAST            other
 116: LOAD_ATTR            _kind
 126: COMPARE_OP           ==
 132: JUMP_IF_FALSE_OR_POP to 196
 134: LOAD_FAST            self
 136: LOAD_ATTR            _default
 146: LOAD_FAST            other
 148: LOAD_ATTR            _default
 158: COMPARE_OP           ==
 164: JUMP_IF_FALSE_OR_POP to 196
 166: LOAD_FAST            self
 168: LOAD_ATTR            _annotation
 178: LOAD_FAST            other
 180: LOAD_ATTR            _annotation
 190: COMPARE_OP           ==
 196: RETURN_VALUE         
