# Disassembly for inspect.ismodule
# From module file: inspect

## co_consts:
('Return true if the object is a module.\n\n    Module objects provide these attributes:\n        __cached__      pathname to byte compiled file\n        __doc__         documentation string\n        __file__        filename (missing for built-in modules)',)

## co_names:
('isinstance', 'types', 'ModuleType')

## bytecode:

   0: RESUME               
   2: LOAD_GLOBAL          NULL + isinstance
  14: LOAD_FAST            object
  16: LOAD_GLOBAL          types
  28: LOAD_ATTR            ModuleType
  38: PRECALL              
  42: CALL                 
  52: RETURN_VALUE         
