# Disassembly for inspect.isbuiltin
# From module file: inspect

## co_consts:
('Return true if the object is a built-in function or method.\n\n    Built-in functions and methods provide these attributes:\n        __doc__         documentation string\n        __name__        original name of this function or method\n        __self__        instance to which a method is bound, or None',)

## co_names:
('isinstance', 'types', 'BuiltinFunctionType')

## bytecode:

   0: RESUME               
   2: LOAD_GLOBAL          NULL + isinstance
  14: LOAD_FAST            object
  16: LOAD_GLOBAL          types
  28: LOAD_ATTR            BuiltinFunctionType
  38: PRECALL              
  42: CALL                 
  52: RETURN_VALUE         
