# Disassembly for inspect.FrameInfo.__repr__
# From module file: inspect

## co_consts:
(None, 'FrameInfo(frame={!r}, filename={!r}, lineno={!r}, function={!r}, code_context={!r}, index={!r}, positions={!r})')

## co_names:
('format', 'frame', 'filename', 'lineno', 'function', 'code_context', 'index', 'positions')

## bytecode:

   0: RESUME               
   2: LOAD_CONST           'FrameInfo(frame={!r}, filename={!r}, lineno={!r}, function={!r}, code_context={!r}, index={!r}, positions={!r})'
   4: LOAD_METHOD          format
  26: LOAD_FAST            self
  28: LOAD_ATTR            frame
  38: LOAD_FAST            self
  40: LOAD_ATTR            filename
  50: LOAD_FAST            self
  52: LOAD_ATTR            lineno
  62: LOAD_FAST            self
  64: LOAD_ATTR            function
  74: LOAD_FAST            self
  76: LOAD_ATTR            code_context
  86: LOAD_FAST            self
  88: LOAD_ATTR            index
  98: LOAD_FAST            self
 100: LOAD_ATTR            positions
 110: PRECALL              
 114: CALL                 
 124: RETURN_VALUE         
