# Disassembly for inspect.getmodulename.<listcomp>
# From module file: inspect

## co_consts:
()

## co_names:
('len',)

## bytecode:

   0: RESUME               
   2: BUILD_LIST           
   4: LOAD_FAST            .0
   6: FOR_ITER             to 48
   8: STORE_FAST           suffix
  10: LOAD_GLOBAL          NULL + len
  22: LOAD_FAST            suffix
  24: PRECALL              
  28: CALL                 
  38: UNARY_NEGATIVE       
  40: LOAD_FAST            suffix
  42: BUILD_TUPLE          
  44: LIST_APPEND          
  46: JUMP_BACKWARD        to 6
  48: RETURN_VALUE         
