# Disassembly for inspect.signature
# From module file: inspect

## co_consts:
('Get a signature object for the passed callable.', ('follow_wrapped', 'globals', 'locals', 'eval_str'))

## co_names:
('Signature', 'from_callable')

## bytecode:

   0: RESUME               
   2: LOAD_GLOBAL          Signature
  14: LOAD_METHOD          from_callable
  36: LOAD_FAST            obj
  38: LOAD_FAST            follow_wrapped
  40: LOAD_FAST            globals
  42: LOAD_FAST            locals
  44: LOAD_FAST            eval_str
  46: KW_NAMES             
  48: PRECALL              
  52: CALL                 
  62: RETURN_VALUE         
