# Disassembly for inspect.Signature.bind_partial
# From module file: inspect

## co_consts:
("Get a BoundArguments object, that partially maps the\n        passed `args` and `kwargs` to the function's signature.\n        Raises `TypeError` if the passed arguments can not be bound.\n        ", True, ('partial',))

## co_names:
('_bind',)

## bytecode:

   0: RESUME               
   2: LOAD_FAST            self
   4: LOAD_METHOD          _bind
  26: LOAD_FAST            args
  28: LOAD_FAST            kwargs
  30: LOAD_CONST           True
  32: KW_NAMES             
  34: PRECALL              
  38: CALL                 
  48: RETURN_VALUE         
