# Disassembly for inspect.isframe
# From module file: inspect

## co_consts:
("Return true if the object is a frame object.\n\n    Frame objects provide these attributes:\n        f_back          next outer frame object (this frame's caller)\n        f_builtins      built-in namespace seen by this frame\n        f_code          code object being executed in this frame\n        f_globals       global namespace seen by this frame\n        f_lasti         index of last attempted instruction in bytecode\n        f_lineno        current line number in Python source code\n        f_locals        local namespace seen by this frame\n        f_trace         tracing function for this frame, or None",)

## co_names:
('isinstance', 'types', 'FrameType')

## bytecode:

   0: RESUME               
   2: LOAD_GLOBAL          NULL + isinstance
  14: LOAD_FAST            object
  16: LOAD_GLOBAL          types
  28: LOAD_ATTR            FrameType
  38: PRECALL              
  42: CALL                 
  52: RETURN_VALUE         
