# Disassembly for inspect.Signature._hash_basis.<genexpr>
# From module file: inspect

## co_consts:
(None,)

## co_names:
('kind', '_KEYWORD_ONLY')

## bytecode:

   0: RETURN_GENERATOR     
   2: POP_TOP              
   4: RESUME               
   6: LOAD_FAST            .0
   8: FOR_ITER             to 54
  10: STORE_FAST           param
  12: LOAD_FAST            param
  14: LOAD_ATTR            kind
  24: LOAD_GLOBAL          _KEYWORD_ONLY
  36: COMPARE_OP           !=
  42: POP_JUMP_BACKWARD_IF_FALSE to 8
  44: LOAD_FAST            param
  46: YIELD_VALUE          
  48: RESUME               
  50: POP_TOP              
  52: JUMP_BACKWARD        to 8
  54: LOAD_CONST           None
  56: RETURN_VALUE         
