# Disassembly for inspect._signature_is_builtin
# From module file: inspect

## co_consts:
("Private helper to test if `obj` is a callable that might\n    support Argument Clinic's __text_signature__ protocol.\n    ",)

## co_names:
('isbuiltin', 'ismethoddescriptor', 'isinstance', '_NonUserDefinedCallables', 'type', 'object')

## bytecode:

   0: RESUME               
   2: LOAD_GLOBAL          NULL + isbuiltin
  14: LOAD_FAST            obj
  16: PRECALL              
  20: CALL                 
  30: JUMP_IF_TRUE_OR_POP  to 134
  32: LOAD_GLOBAL          NULL + ismethoddescriptor
  44: LOAD_FAST            obj
  46: PRECALL              
  50: CALL                 
  60: JUMP_IF_TRUE_OR_POP  to 134
  62: LOAD_GLOBAL          NULL + isinstance
  74: LOAD_FAST            obj
  76: LOAD_GLOBAL          _NonUserDefinedCallables
  88: PRECALL              
  92: CALL                 
 102: JUMP_IF_TRUE_OR_POP  to 134
 104: LOAD_FAST            obj
 106: LOAD_GLOBAL          type
 118: LOAD_GLOBAL          object
 130: BUILD_TUPLE          
 132: CONTAINS_OP          
 134: RETURN_VALUE         
