# Disassembly for inspect._ClassFinder.visit_FunctionDef
# From module file: inspect

## co_consts:
(None, '<locals>')

## co_names:
('stack', 'append', 'name', 'generic_visit', 'pop')

## bytecode:

   0: RESUME               
   2: LOAD_FAST            self
   4: LOAD_ATTR            stack
  14: LOAD_METHOD          append
  36: LOAD_FAST            node
  38: LOAD_ATTR            name
  48: PRECALL              
  52: CALL                 
  62: POP_TOP              
  64: LOAD_FAST            self
  66: LOAD_ATTR            stack
  76: LOAD_METHOD          append
  98: LOAD_CONST           '<locals>'
 100: PRECALL              
 104: CALL                 
 114: POP_TOP              
 116: LOAD_FAST            self
 118: LOAD_METHOD          generic_visit
 140: LOAD_FAST            node
 142: PRECALL              
 146: CALL                 
 156: POP_TOP              
 158: LOAD_FAST            self
 160: LOAD_ATTR            stack
 170: LOAD_METHOD          pop
 192: PRECALL              
 196: CALL                 
 206: POP_TOP              
 208: LOAD_FAST            self
 210: LOAD_ATTR            stack
 220: LOAD_METHOD          pop
 242: PRECALL              
 246: CALL                 
 256: POP_TOP              
 258: LOAD_CONST           None
 260: RETURN_VALUE         
