# Disassembly for inspect.ismethoddescriptor
# From module file: inspect

## co_consts:
('Return true if the object is a method descriptor.\n\n    But not if ismethod() or isclass() or isfunction() are true.\n\n    This is new in Python 2.2, and, for example, is true of int.__add__.\n    An object passing this test has a __get__ attribute but not a __set__\n    attribute, but beyond that the set of attributes varies.  __name__ is\n    usually sensible, and __doc__ often is.\n\n    Methods implemented via descriptors that also pass one of the other\n    tests return false from the ismethoddescriptor() test, simply because\n    the other tests promise more -- you can, e.g., count on having the\n    __func__ attribute (etc) when an object passes ismethod().', False, '__get__', '__set__')

## co_names:
('isclass', 'ismethod', 'isfunction', 'type', 'hasattr')

## bytecode:

   0: RESUME               
   2: LOAD_GLOBAL          NULL + isclass
  14: LOAD_FAST            object
  16: PRECALL              
  20: CALL                 
  30: POP_JUMP_FORWARD_IF_TRUE to 92
  32: LOAD_GLOBAL          NULL + ismethod
  44: LOAD_FAST            object
  46: PRECALL              
  50: CALL                 
  60: POP_JUMP_FORWARD_IF_TRUE to 92
  62: LOAD_GLOBAL          NULL + isfunction
  74: LOAD_FAST            object
  76: PRECALL              
  80: CALL                 
  90: POP_JUMP_FORWARD_IF_FALSE to 96
  92: LOAD_CONST           False
  94: RETURN_VALUE         
  96: LOAD_GLOBAL          NULL + type
 108: LOAD_FAST            object
 110: PRECALL              
 114: CALL                 
 124: STORE_FAST           tp
 126: LOAD_GLOBAL          NULL + hasattr
 138: LOAD_FAST            tp
 140: LOAD_CONST           '__get__'
 142: PRECALL              
 146: CALL                 
 156: JUMP_IF_FALSE_OR_POP to 190
 158: LOAD_GLOBAL          NULL + hasattr
 170: LOAD_FAST            tp
 172: LOAD_CONST           '__set__'
 174: PRECALL              
 178: CALL                 
 188: UNARY_NOT            
 190: RETURN_VALUE         
