# Disassembly for inspect._signature_fromstr.RewriteSymbolics.visit_Name
# From module file: inspect

## co_consts:
(None,)

## co_names:
('isinstance', 'ctx', 'ast', 'Load', 'ValueError', 'id')

## bytecode:

   0: COPY_FREE_VARS       
   2: RESUME               
   4: LOAD_GLOBAL          NULL + isinstance
  16: LOAD_FAST            node
  18: LOAD_ATTR            ctx
  28: LOAD_GLOBAL          ast
  40: LOAD_ATTR            Load
  50: PRECALL              
  54: CALL                 
  64: POP_JUMP_FORWARD_IF_TRUE to 94
  66: LOAD_GLOBAL          NULL + ValueError
  78: PRECALL              
  82: CALL                 
  92: RAISE_VARARGS        
  94: PUSH_NULL            
  96: LOAD_DEREF           wrap_value
  98: LOAD_FAST            node
 100: LOAD_ATTR            id
 110: PRECALL              
 114: CALL                 
 124: RETURN_VALUE         
