# Disassembly for inspect
# From module file: inspect

## co_consts:
("Get useful information from live Python objects.\n\nThis module encapsulates the interface provided by the internal special\nattributes (co_*, im_*, tb_*, etc.) in a friendlier fashion.\nIt also provides some help for examining source code and class layout.\n\nHere are some of the useful functions provided by this module:\n\n    ismodule(), isclass(), ismethod(), isfunction(), isgeneratorfunction(),\n        isgenerator(), istraceback(), isframe(), iscode(), isbuiltin(),\n        isroutine() - check object types\n    getmembers() - get members of an object that satisfy a given condition\n\n    getfile(), getsourcefile(), getsource() - find an object's source code\n    getdoc(), getcomments() - get documentation on an object\n    getmodule() - determine the module that an object came from\n    getclasstree() - arrange classes so as to represent their hierarchy\n\n    getargvalues(), getcallargs() - get info about function arguments\n    getfullargspec() - same, with support for Python 3 features\n    formatargvalues() - format an argument spec\n    getouterframes(), getinnerframes() - get info about frames\n    currentframe() - get the current stack frame\n    stack(), trace() - get info about frames on the stack or in a traceback\n\n    signature() - get a Signature object for the callable\n\n    get_annotations() - safely compute an object's annotations\n", ('Ka-Ping Yee <ping@lfw.org>', 'Yury Selivanov <yselivanov@sprymix.com>'), ('ArgInfo', 'Arguments', 'Attribute', 'BlockFinder', 'BoundArguments', 'CORO_CLOSED', 'CORO_CREATED', 'CORO_RUNNING', 'CORO_SUSPENDED', 'CO_ASYNC_GENERATOR', 'CO_COROUTINE', 'CO_GENERATOR', 'CO_ITERABLE_COROUTINE', 'CO_NESTED', 'CO_NEWLOCALS', 'CO_NOFREE', 'CO_OPTIMIZED', 'CO_VARARGS', 'CO_VARKEYWORDS', 'ClassFoundException', 'ClosureVars', 'EndOfBlock', 'FrameInfo', 'FullArgSpec', 'GEN_CLOSED', 'GEN_CREATED', 'GEN_RUNNING', 'GEN_SUSPENDED', 'Parameter', 'Signature', 'TPFLAGS_IS_ABSTRACT', 'Traceback', 'classify_class_attrs', 'cleandoc', 'currentframe', 'findsource', 'formatannotation', 'formatannotationrelativeto', 'formatargvalues', 'get_annotations', 'getabsfile', 'getargs', 'getargvalues', 'getattr_static', 'getblock', 'getcallargs', 'getclasstree', 'getclosurevars', 'getcomments', 'getcoroutinelocals', 'getcoroutinestate', 'getdoc', 'getfile', 'getframeinfo', 'getfullargspec', 'getgeneratorlocals', 'getgeneratorstate', 'getinnerframes', 'getlineno', 'getmembers', 'getmembers_static', 'getmodule', 'getmodulename', 'getmro', 'getouterframes', 'getsource', 'getsourcefile', 'getsourcelines', 'indentsize', 'isabstract', 'isasyncgen', 'isasyncgenfunction', 'isawaitable', 'isbuiltin', 'isclass', 'iscode', 'iscoroutine', 'iscoroutinefunction', 'isdatadescriptor', 'isframe', 'isfunction', 'isgenerator', 'isgeneratorfunction', 'isgetsetdescriptor', 'ismemberdescriptor', 'ismethod', 'ismethoddescriptor', 'ismethodwrapper', 'ismodule', 'isroutine', 'istraceback', 'signature', 'stack', 'trace', 'unwrap', 'walktree'), 0, None, ('iskeyword',), ('attrgetter',), ('namedtuple', 'OrderedDict'), 'CO_', 1048576, False, ('globals', 'locals', 'eval_str'), <code object get_annotations at 0x000002406953A900, file "inspect.py", line 167>, <code object ismodule at 0x000002406945DE30, file "inspect.py", line 283>, <code object isclass at 0x000002406945D890, file "inspect.py", line 292>, <code object ismethod at 0x000002406945ED30, file "inspect.py", line 300>, <code object ismethoddescriptor at 0x00000240691E8AB0, file "inspect.py", line 310>, <code object isdatadescriptor at 0x00000240691EA730, file "inspect.py", line 330>, 'MemberDescriptorType', <code object ismemberdescriptor at 0x000002406945EA60, file "inspect.py", line 346>, <code object ismemberdescriptor at 0x000002406943BF30, file "inspect.py", line 354>, 'GetSetDescriptorType', <code object isgetsetdescriptor at 0x000002406945E100, file "inspect.py", line 363>, <code object isgetsetdescriptor at 0x000002406943B0F0, file "inspect.py", line 371>, <code object isfunction at 0x000002406945F0F0, file "inspect.py", line 378>, <code object _has_code_flag at 0x000002406934FCF0, file "inspect.py", line 391>, <code object isgeneratorfunction at 0x000002406945E3D0, file "inspect.py", line 402>, <code object iscoroutinefunction at 0x000002406945F690, file "inspect.py", line 409>, <code object isasyncgenfunction at 0x000002406945F3C0, file "inspect.py", line 416>, <code object isasyncgen at 0x000002406945F4B0, file "inspect.py", line 424>, <code object isgenerator at 0x000002406945F5A0, file "inspect.py", line 428>, <code object iscoroutine at 0x000002406945FA50, file "inspect.py", line 445>, <code object isawaitable at 0x000002406934F480, file "inspect.py", line 449>, <code object istraceback at 0x000002406945FB40, file "inspect.py", line 456>, <code object isframe at 0x000002406945E1F0, file "inspect.py", line 466>, <code object iscode at 0x000002406945D980, file "inspect.py", line 480>, <code object isbuiltin at 0x000002406945EB50, file "inspect.py", line 505>, <code object ismethodwrapper at 0x000002406945EE20, file "inspect.py", line 514>, <code object isroutine at 0x00000240691F13E0, file "inspect.py", line 518>, <code object isabstract at 0x0000024068DA7150, file "inspect.py", line 526>, <code object _getmembers at 0x0000024066348E30, file "inspect.py", line 550>, <code object getmembers at 0x000002406945E790, file "inspect.py", line 592>, <code object getmembers_static at 0x000002406945F000, file "inspect.py", line 597>, 'Attribute', 'name kind defining_class object', <code object classify_class_attrs at 0x0000024068E11050, file "inspect.py", line 613>, <code object getmro at 0x00000240694941D0, file "inspect.py", line 729>, ('stop',), <code object unwrap at 0x000002406931FC30, file "inspect.py", line 735>, <code object indentsize at 0x00000240691F39F0, file "inspect.py", line 771>, <code object _findclass at 0x00000240691F5890, file "inspect.py", line 776>, <code object _finddoc at 0x0000024068D336D0, file "inspect.py", line 786>, <code object getdoc at 0x000002406942E100, file "inspect.py", line 848>, <code object cleandoc at 0x0000024068C37930, file "inspect.py", line 867>, <code object getfile at 0x0000024068E3EE50, file "inspect.py", line 896>, <code object getmodulename at 0x00000240691DABB0, file "inspect.py", line 924>, <code object getsourcefile at 0x0000024068B39060, file "inspect.py", line 936>, <code object getabsfile at 0x00000240691E9E30, file "inspect.py", line 961>, <code object getmodule at 0x0000024068E115E0, file "inspect.py", line 973>, <code object ClassFoundException at 0x0000024069495550, file "inspect.py", line 1020>, 'ClassFoundException', <code object _ClassFinder at 0x0000024069466DB0, file "inspect.py", line 1024>, '_ClassFinder', <code object findsource at 0x0000024068E11B80, file "inspect.py", line 1055>, <code object getcomments at 0x0000024068E12870, file "inspect.py", line 1123>, <code object EndOfBlock at 0x0000024069495480, file "inspect.py", line 1168>, 'EndOfBlock', <code object BlockFinder at 0x0000024069466A30, file "inspect.py", line 1170>, 'BlockFinder', <code object getblock at 0x000002406942CFD0, file "inspect.py", line 1224>, <code object getsourcelines at 0x00000240691DA9E0, file "inspect.py", line 1235>, <code object getsource at 0x000002406944BDD0, file "inspect.py", line 1256>, <code object walktree at 0x0000024069CE4030, file "inspect.py", line 1266>, <code object getclasstree at 0x0000024069366AD0, file "inspect.py", line 1276>, 'Arguments', 'args, varargs, varkw', <code object getargs at 0x0000024068E1DE30, file "inspect.py", line 1305>, 'FullArgSpec', 'args, varargs, varkw, defaults, kwonlyargs, kwonlydefaults, annotations', <code object getfullargspec at 0x0000024068E41C10, file "inspect.py", line 1336>, 'ArgInfo', 'args varargs keywords locals', <code object getargvalues at 0x0000024069419C50, file "inspect.py", line 1431>, <code object formatannotation at 0x0000024068E223E0, file "inspect.py", line 1441>, <code object formatannotationrelativeto at 0x0000024069CDC300, file "inspect.py", line 1455>, <code object <lambda> at 0x0000024069494FA0, file "inspect.py", line 1464>, <code object <lambda> at 0x0000024069494AC0, file "inspect.py", line 1465>, <code object <lambda> at 0x0000024069465450, file "inspect.py", line 1466>, <code object formatargvalues at 0x0000024068C5ABD0, file "inspect.py", line 1462>, <code object _missing_arguments at 0x000002406947C7B0, file "inspect.py", line 1485>, <code object _too_many at 0x0000024068BBD1F0, file "inspect.py", line 1501>, <code object getcallargs at 0x0000024069591600, file "inspect.py", line 1522>, 'ClosureVars', 'nonlocals globals builtins unbound', <code object getclosurevars at 0x0000024068BFD9F0, file "inspect.py", line 1584>, '_Traceback', 'filename lineno function code_context index', <code object Traceback at 0x0000024069CDC6C0, file "inspect.py", line 1639>, 'Traceback', <code object _get_code_position_from_tb at 0x0000024069CF0130, file "inspect.py", line 1651>, <code object _get_code_position at 0x00000240693AA5B0, file "inspect.py", line 1655>, 1, <code object getframeinfo at 0x0000024068CDF640, file "inspect.py", line 1662>, <code object getlineno at 0x00000240694963F0, file "inspect.py", line 1705>, '_FrameInfo', ('frame',), <code object FrameInfo at 0x0000024069CDC7B0, file "inspect.py", line 1711>, 'FrameInfo', <code object getouterframes at 0x000002406922D7D0, file "inspect.py", line 1723>, <code object getinnerframes at 0x00000240691C14D0, file "inspect.py", line 1736>, <code object currentframe at 0x0000024069CF4250, file "inspect.py", line 1749>, <code object stack at 0x0000024069CF0230, file "inspect.py", line 1753>, <code object trace at 0x0000024069CF4360, file "inspect.py", line 1757>, <code object _static_getmro at 0x0000024069CF4470, file "inspect.py", line 1766>, <code object _check_instance at 0x00000240691C1FD0, file "inspect.py", line 1769>, <code object _check_class at 0x00000240691E84B0, file "inspect.py", line 1778>, <code object _is_type at 0x0000024069CF4580, file "inspect.py", line 1787>, <code object _shadowed_dict at 0x00000240691DAD80, file "inspect.py", line 1794>, <code object getattr_static at 0x0000024068D03690, file "inspect.py", line 1808>, 'GEN_CREATED', 'GEN_RUNNING', 'GEN_SUSPENDED', 'GEN_CLOSED', <code object getgeneratorstate at 0x000002406941AE50, file "inspect.py", line 1863>, <code object getgeneratorlocals at 0x00000240691C2970, file "inspect.py", line 1881>, 'CORO_CREATED', 'CORO_RUNNING', 'CORO_SUSPENDED', 'CORO_CLOSED', <code object getcoroutinestate at 0x0000024069419110, file "inspect.py", line 1905>, <code object getcoroutinelocals at 0x0000024069CF0330, file "inspect.py", line 1923>, <code object _signature_get_user_defined_method at 0x00000240693D2890, file "inspect.py", line 1947>, (), <code object _signature_get_partial at 0x0000024068D33C20, file "inspect.py", line 1963>, <code object _signature_bound_method at 0x0000024068E232C0, file "inspect.py", line 2039>, <code object _signature_is_builtin at 0x00000240693A9570, file "inspect.py", line 2065>, <code object _signature_is_functionlike at 0x0000024068C05CB0, file "inspect.py", line 2077>, <code object _signature_strip_non_python_syntax at 0x0000024066346C70, file "inspect.py", line 2102>, True, <code object _signature_fromstr at 0x0000024069591AA0, file "inspect.py", line 2174>, <code object _signature_from_builtin at 0x0000024069CE4390, file "inspect.py", line 2317>, <code object _signature_from_function at 0x00000240695927A0, file "inspect.py", line 2333>, ('follow_wrapper_chains', 'skip_bound_arg', 'globals', 'locals', 'eval_str'), <code object _signature_from_callable at 0x000002406951A640, file "inspect.py", line 2428>, <code object _void at 0x0000024069494440, file "inspect.py", line 2622>, '_void', <code object _empty at 0x00000240694964C0, file "inspect.py", line 2626>, '_empty', <code object _ParameterKind at 0x0000024069CDCA80, file "inspect.py", line 2630>, '_ParameterKind', <code object Parameter at 0x000002406942CB20, file "inspect.py", line 2654>, 'Parameter', <code object BoundArguments at 0x00000240693AA830, file "inspect.py", line 2812>, 'BoundArguments', <code object Signature at 0x000002406942E290, file "inspect.py", line 2942>, 'Signature', ('follow_wrapped', 'globals', 'locals', 'eval_str'), <code object signature at 0x0000024069CF1130, file "inspect.py", line 3278>, <code object _main at 0x000002406951BDF0, file "inspect.py", line 3284>, '__main__', (None,), (False,), (1,), ((),), (True,), (True, None, None, False))

## co_names:
('__doc__', '__author__', '__all__', 'abc', 'ast', 'dis', 'collections.abc', 'collections', 'enum', 'importlib.machinery', 'importlib', 'itertools', 'linecache', 'os', 're', 'sys', 'tokenize', 'token', 'types', 'functools', 'builtins', 'keyword', 'iskeyword', 'operator', 'attrgetter', 'namedtuple', 'OrderedDict', 'globals', 'mod_dict', 'COMPILER_FLAG_NAMES', 'items', 'k', 'v', 'TPFLAGS_IS_ABSTRACT', 'get_annotations', 'ismodule', 'isclass', 'ismethod', 'ismethoddescriptor', 'isdatadescriptor', 'hasattr', 'ismemberdescriptor', 'isgetsetdescriptor', 'isfunction', '_has_code_flag', 'isgeneratorfunction', 'iscoroutinefunction', 'isasyncgenfunction', 'isasyncgen', 'isgenerator', 'iscoroutine', 'isawaitable', 'istraceback', 'isframe', 'iscode', 'isbuiltin', 'ismethodwrapper', 'isroutine', 'isabstract', '_getmembers', 'getmembers', 'getmembers_static', 'Attribute', 'classify_class_attrs', 'getmro', 'unwrap', 'indentsize', '_findclass', '_finddoc', 'getdoc', 'cleandoc', 'getfile', 'getmodulename', 'getsourcefile', 'getabsfile', 'modulesbyfile', '_filesbymodname', 'getmodule', 'Exception', 'ClassFoundException', 'NodeVisitor', '_ClassFinder', 'findsource', 'getcomments', 'EndOfBlock', 'BlockFinder', 'getblock', 'getsourcelines', 'getsource', 'walktree', 'getclasstree', 'Arguments', 'getargs', 'FullArgSpec', 'getfullargspec', 'ArgInfo', 'getargvalues', 'formatannotation', 'formatannotationrelativeto', 'str', 'formatargvalues', '_missing_arguments', '_too_many', 'getcallargs', 'ClosureVars', 'getclosurevars', '_Traceback', 'Traceback', '_get_code_position_from_tb', '_get_code_position', 'getframeinfo', 'getlineno', '_fields', '_FrameInfo', 'FrameInfo', 'getouterframes', 'getinnerframes', 'currentframe', 'stack', 'trace', 'object', '_sentinel', '_static_getmro', '_check_instance', '_check_class', '_is_type', '_shadowed_dict', 'getattr_static', 'GEN_CREATED', 'GEN_RUNNING', 'GEN_SUSPENDED', 'GEN_CLOSED', 'getgeneratorstate', 'getgeneratorlocals', 'CORO_CREATED', 'CORO_RUNNING', 'CORO_SUSPENDED', 'CORO_CLOSED', 'getcoroutinestate', 'getcoroutinelocals', 'WrapperDescriptorType', 'MethodWrapperType', 'ClassMethodDescriptorType', 'BuiltinFunctionType', '_NonUserDefinedCallables', '_signature_get_user_defined_method', '_signature_get_partial', '_signature_bound_method', '_signature_is_builtin', '_signature_is_functionlike', '_signature_strip_non_python_syntax', '_signature_fromstr', '_signature_from_builtin', '_signature_from_function', '_signature_from_callable', '_void', '_empty', 'IntEnum', '_ParameterKind', 'POSITIONAL_ONLY', '_POSITIONAL_ONLY', 'POSITIONAL_OR_KEYWORD', '_POSITIONAL_OR_KEYWORD', 'VAR_POSITIONAL', '_VAR_POSITIONAL', 'KEYWORD_ONLY', '_KEYWORD_ONLY', 'VAR_KEYWORD', '_VAR_KEYWORD', 'Parameter', 'BoundArguments', 'Signature', 'signature', '_main', '__name__')

## bytecode:

   0: RESUME               
   2: LOAD_CONST           "Get useful information from live Python objects.\n\nThis module encapsulates the interface provided by the internal special\nattributes (co_*, im_*, tb_*, etc.) in a friendlier fashion.\nIt also provides some help for examining source code and class layout.\n\nHere are some of the useful functions provided by this module:\n\n    ismodule(), isclass(), ismethod(), isfunction(), isgeneratorfunction(),\n        isgenerator(), istraceback(), isframe(), iscode(), isbuiltin(),\n        isroutine() - check object types\n    getmembers() - get members of an object that satisfy a given condition\n\n    getfile(), getsourcefile(), getsource() - find an object's source code\n    getdoc(), getcomments() - get documentation on an object\n    getmodule() - determine the module that an object came from\n    getclasstree() - arrange classes so as to represent their hierarchy\n\n    getargvalues(), getcallargs() - get info about function arguments\n    getfullargspec() - same, with support for Python 3 features\n    formatargvalues() - format an argument spec\n    getouterframes(), getinnerframes() - get info about frames\n    currentframe() - get the current stack frame\n    stack(), trace() - get info about frames on the stack or in a traceback\n\n    signature() - get a Signature object for the callable\n\n    get_annotations() - safely compute an object's annotations\n"
   4: STORE_NAME           __doc__
   6: LOAD_CONST           ('Ka-Ping Yee <ping@lfw.org>', 'Yury Selivanov <yselivanov@sprymix.com>')
   8: STORE_NAME           __author__
  10: BUILD_LIST           
  12: LOAD_CONST           ('ArgInfo', 'Arguments', 'Attribute', 'BlockFinder', 'BoundArguments', 'CORO_CLOSED', 'CORO_CREATED', 'CORO_RUNNING', 'CORO_SUSPENDED', 'CO_ASYNC_GENERATOR', 'CO_COROUTINE', 'CO_GENERATOR', 'CO_ITERABLE_COROUTINE', 'CO_NESTED', 'CO_NEWLOCALS', 'CO_NOFREE', 'CO_OPTIMIZED', 'CO_VARARGS', 'CO_VARKEYWORDS', 'ClassFoundException', 'ClosureVars', 'EndOfBlock', 'FrameInfo', 'FullArgSpec', 'GEN_CLOSED', 'GEN_CREATED', 'GEN_RUNNING', 'GEN_SUSPENDED', 'Parameter', 'Signature', 'TPFLAGS_IS_ABSTRACT', 'Traceback', 'classify_class_attrs', 'cleandoc', 'currentframe', 'findsource', 'formatannotation', 'formatannotationrelativeto', 'formatargvalues', 'get_annotations', 'getabsfile', 'getargs', 'getargvalues', 'getattr_static', 'getblock', 'getcallargs', 'getclasstree', 'getclosurevars', 'getcomments', 'getcoroutinelocals', 'getcoroutinestate', 'getdoc', 'getfile', 'getframeinfo', 'getfullargspec', 'getgeneratorlocals', 'getgeneratorstate', 'getinnerframes', 'getlineno', 'getmembers', 'getmembers_static', 'getmodule', 'getmodulename', 'getmro', 'getouterframes', 'getsource', 'getsourcefile', 'getsourcelines', 'indentsize', 'isabstract', 'isasyncgen', 'isasyncgenfunction', 'isawaitable', 'isbuiltin', 'isclass', 'iscode', 'iscoroutine', 'iscoroutinefunction', 'isdatadescriptor', 'isframe', 'isfunction', 'isgenerator', 'isgeneratorfunction', 'isgetsetdescriptor', 'ismemberdescriptor', 'ismethod', 'ismethoddescriptor', 'ismethodwrapper', 'ismodule', 'isroutine', 'istraceback', 'signature', 'stack', 'trace', 'unwrap', 'walktree')
  14: LIST_EXTEND          
  16: STORE_NAME           __all__
  18: LOAD_CONST           0
  20: LOAD_CONST           None
  22: IMPORT_NAME          abc
  24: STORE_NAME           abc
  26: LOAD_CONST           0
  28: LOAD_CONST           None
  30: IMPORT_NAME          ast
  32: STORE_NAME           ast
  34: LOAD_CONST           0
  36: LOAD_CONST           None
  38: IMPORT_NAME          dis
  40: STORE_NAME           dis
  42: LOAD_CONST           0
  44: LOAD_CONST           None
  46: IMPORT_NAME          collections.abc
  48: STORE_NAME           collections
  50: LOAD_CONST           0
  52: LOAD_CONST           None
  54: IMPORT_NAME          enum
  56: STORE_NAME           enum
  58: LOAD_CONST           0
  60: LOAD_CONST           None
  62: IMPORT_NAME          importlib.machinery
  64: STORE_NAME           importlib
  66: LOAD_CONST           0
  68: LOAD_CONST           None
  70: IMPORT_NAME          itertools
  72: STORE_NAME           itertools
  74: LOAD_CONST           0
  76: LOAD_CONST           None
  78: IMPORT_NAME          linecache
  80: STORE_NAME           linecache
  82: LOAD_CONST           0
  84: LOAD_CONST           None
  86: IMPORT_NAME          os
  88: STORE_NAME           os
  90: LOAD_CONST           0
  92: LOAD_CONST           None
  94: IMPORT_NAME          re
  96: STORE_NAME           re
  98: LOAD_CONST           0
 100: LOAD_CONST           None
 102: IMPORT_NAME          sys
 104: STORE_NAME           sys
 106: LOAD_CONST           0
 108: LOAD_CONST           None
 110: IMPORT_NAME          tokenize
 112: STORE_NAME           tokenize
 114: LOAD_CONST           0
 116: LOAD_CONST           None
 118: IMPORT_NAME          token
 120: STORE_NAME           token
 122: LOAD_CONST           0
 124: LOAD_CONST           None
 126: IMPORT_NAME          types
 128: STORE_NAME           types
 130: LOAD_CONST           0
 132: LOAD_CONST           None
 134: IMPORT_NAME          functools
 136: STORE_NAME           functools
 138: LOAD_CONST           0
 140: LOAD_CONST           None
 142: IMPORT_NAME          builtins
 144: STORE_NAME           builtins
 146: LOAD_CONST           0
 148: LOAD_CONST           ('iskeyword',)
 150: IMPORT_NAME          keyword
 152: IMPORT_FROM          iskeyword
 154: STORE_NAME           iskeyword
 156: POP_TOP              
 158: LOAD_CONST           0
 160: LOAD_CONST           ('attrgetter',)
 162: IMPORT_NAME          operator
 164: IMPORT_FROM          attrgetter
 166: STORE_NAME           attrgetter
 168: POP_TOP              
 170: LOAD_CONST           0
 172: LOAD_CONST           ('namedtuple', 'OrderedDict')
 174: IMPORT_NAME          collections
 176: IMPORT_FROM          namedtuple
 178: STORE_NAME           namedtuple
 180: IMPORT_FROM          OrderedDict
 182: STORE_NAME           OrderedDict
 184: POP_TOP              
 186: PUSH_NULL            
 188: LOAD_NAME            globals
 190: PRECALL              
 194: CALL                 
 204: STORE_NAME           mod_dict
 206: LOAD_NAME            dis
 208: LOAD_ATTR            COMPILER_FLAG_NAMES
 218: LOAD_METHOD          items
 240: PRECALL              
 244: CALL                 
 254: GET_ITER             
 256: FOR_ITER             to 284
 258: UNPACK_SEQUENCE      
 262: STORE_NAME           k
 264: STORE_NAME           v
 266: LOAD_NAME            k
 268: LOAD_NAME            mod_dict
 270: LOAD_CONST           'CO_'
 272: LOAD_NAME            v
 274: BINARY_OP            +
 278: STORE_SUBSCR         
 282: JUMP_BACKWARD        to 256
 284: DELETE_NAME          k
 286: DELETE_NAME          v
 288: DELETE_NAME          mod_dict
 290: LOAD_CONST           1048576
 292: STORE_NAME           TPFLAGS_IS_ABSTRACT
 294: LOAD_CONST           None
 296: LOAD_CONST           None
 298: LOAD_CONST           False
 300: LOAD_CONST           ('globals', 'locals', 'eval_str')
 302: BUILD_CONST_KEY_MAP  
 304: LOAD_CONST           <code object get_annotations at 0x000002406953A900, file "inspect.py", line 167>
 306: MAKE_FUNCTION        kwdefaults
 308: STORE_NAME           get_annotations
 310: LOAD_CONST           <code object ismodule at 0x000002406945DE30, file "inspect.py", line 283>
 312: MAKE_FUNCTION        
 314: STORE_NAME           ismodule
 316: LOAD_CONST           <code object isclass at 0x000002406945D890, file "inspect.py", line 292>
 318: MAKE_FUNCTION        
 320: STORE_NAME           isclass
 322: LOAD_CONST           <code object ismethod at 0x000002406945ED30, file "inspect.py", line 300>
 324: MAKE_FUNCTION        
 326: STORE_NAME           ismethod
 328: LOAD_CONST           <code object ismethoddescriptor at 0x00000240691E8AB0, file "inspect.py", line 310>
 330: MAKE_FUNCTION        
 332: STORE_NAME           ismethoddescriptor
 334: LOAD_CONST           <code object isdatadescriptor at 0x00000240691EA730, file "inspect.py", line 330>
 336: MAKE_FUNCTION        
 338: STORE_NAME           isdatadescriptor
 340: PUSH_NULL            
 342: LOAD_NAME            hasattr
 344: LOAD_NAME            types
 346: LOAD_CONST           'MemberDescriptorType'
 348: PRECALL              
 352: CALL                 
 362: POP_JUMP_FORWARD_IF_FALSE to 372
 364: LOAD_CONST           <code object ismemberdescriptor at 0x000002406945EA60, file "inspect.py", line 346>
 366: MAKE_FUNCTION        
 368: STORE_NAME           ismemberdescriptor
 370: JUMP_FORWARD         to 378
 372: LOAD_CONST           <code object ismemberdescriptor at 0x000002406943BF30, file "inspect.py", line 354>
 374: MAKE_FUNCTION        
 376: STORE_NAME           ismemberdescriptor
 378: PUSH_NULL            
 380: LOAD_NAME            hasattr
 382: LOAD_NAME            types
 384: LOAD_CONST           'GetSetDescriptorType'
 386: PRECALL              
 390: CALL                 
 400: POP_JUMP_FORWARD_IF_FALSE to 410
 402: LOAD_CONST           <code object isgetsetdescriptor at 0x000002406945E100, file "inspect.py", line 363>
 404: MAKE_FUNCTION        
 406: STORE_NAME           isgetsetdescriptor
 408: JUMP_FORWARD         to 416
 410: LOAD_CONST           <code object isgetsetdescriptor at 0x000002406943B0F0, file "inspect.py", line 371>
 412: MAKE_FUNCTION        
 414: STORE_NAME           isgetsetdescriptor
 416: LOAD_CONST           <code object isfunction at 0x000002406945F0F0, file "inspect.py", line 378>
 418: MAKE_FUNCTION        
 420: STORE_NAME           isfunction
 422: LOAD_CONST           <code object _has_code_flag at 0x000002406934FCF0, file "inspect.py", line 391>
 424: MAKE_FUNCTION        
 426: STORE_NAME           _has_code_flag
 428: LOAD_CONST           <code object isgeneratorfunction at 0x000002406945E3D0, file "inspect.py", line 402>
 430: MAKE_FUNCTION        
 432: STORE_NAME           isgeneratorfunction
 434: LOAD_CONST           <code object iscoroutinefunction at 0x000002406945F690, file "inspect.py", line 409>
 436: MAKE_FUNCTION        
 438: STORE_NAME           iscoroutinefunction
 440: LOAD_CONST           <code object isasyncgenfunction at 0x000002406945F3C0, file "inspect.py", line 416>
 442: MAKE_FUNCTION        
 444: STORE_NAME           isasyncgenfunction
 446: LOAD_CONST           <code object isasyncgen at 0x000002406945F4B0, file "inspect.py", line 424>
 448: MAKE_FUNCTION        
 450: STORE_NAME           isasyncgen
 452: LOAD_CONST           <code object isgenerator at 0x000002406945F5A0, file "inspect.py", line 428>
 454: MAKE_FUNCTION        
 456: STORE_NAME           isgenerator
 458: LOAD_CONST           <code object iscoroutine at 0x000002406945FA50, file "inspect.py", line 445>
 460: MAKE_FUNCTION        
 462: STORE_NAME           iscoroutine
 464: LOAD_CONST           <code object isawaitable at 0x000002406934F480, file "inspect.py", line 449>
 466: MAKE_FUNCTION        
 468: STORE_NAME           isawaitable
 470: LOAD_CONST           <code object istraceback at 0x000002406945FB40, file "inspect.py", line 456>
 472: MAKE_FUNCTION        
 474: STORE_NAME           istraceback
 476: LOAD_CONST           <code object isframe at 0x000002406945E1F0, file "inspect.py", line 466>
 478: MAKE_FUNCTION        
 480: STORE_NAME           isframe
 482: LOAD_CONST           <code object iscode at 0x000002406945D980, file "inspect.py", line 480>
 484: MAKE_FUNCTION        
 486: STORE_NAME           iscode
 488: LOAD_CONST           <code object isbuiltin at 0x000002406945EB50, file "inspect.py", line 505>
 490: MAKE_FUNCTION        
 492: STORE_NAME           isbuiltin
 494: LOAD_CONST           <code object ismethodwrapper at 0x000002406945EE20, file "inspect.py", line 514>
 496: MAKE_FUNCTION        
 498: STORE_NAME           ismethodwrapper
 500: LOAD_CONST           <code object isroutine at 0x00000240691F13E0, file "inspect.py", line 518>
 502: MAKE_FUNCTION        
 504: STORE_NAME           isroutine
 506: LOAD_CONST           <code object isabstract at 0x0000024068DA7150, file "inspect.py", line 526>
 508: MAKE_FUNCTION        
 510: STORE_NAME           isabstract
 512: LOAD_CONST           <code object _getmembers at 0x0000024066348E30, file "inspect.py", line 550>
 514: MAKE_FUNCTION        
 516: STORE_NAME           _getmembers
 518: LOAD_CONST           (None,)
 520: LOAD_CONST           <code object getmembers at 0x000002406945E790, file "inspect.py", line 592>
 522: MAKE_FUNCTION        defaults
 524: STORE_NAME           getmembers
 526: LOAD_CONST           (None,)
 528: LOAD_CONST           <code object getmembers_static at 0x000002406945F000, file "inspect.py", line 597>
 530: MAKE_FUNCTION        defaults
 532: STORE_NAME           getmembers_static
 534: PUSH_NULL            
 536: LOAD_NAME            namedtuple
 538: LOAD_CONST           'Attribute'
 540: LOAD_CONST           'name kind defining_class object'
 542: PRECALL              
 546: CALL                 
 556: STORE_NAME           Attribute
 558: LOAD_CONST           <code object classify_class_attrs at 0x0000024068E11050, file "inspect.py", line 613>
 560: MAKE_FUNCTION        
 562: STORE_NAME           classify_class_attrs
 564: LOAD_CONST           <code object getmro at 0x00000240694941D0, file "inspect.py", line 729>
 566: MAKE_FUNCTION        
 568: STORE_NAME           getmro
 570: LOAD_CONST           None
 572: LOAD_CONST           ('stop',)
 574: BUILD_CONST_KEY_MAP  
 576: LOAD_CONST           <code object unwrap at 0x000002406931FC30, file "inspect.py", line 735>
 578: MAKE_FUNCTION        kwdefaults
 580: STORE_NAME           unwrap
 582: LOAD_CONST           <code object indentsize at 0x00000240691F39F0, file "inspect.py", line 771>
 584: MAKE_FUNCTION        
 586: STORE_NAME           indentsize
 588: LOAD_CONST           <code object _findclass at 0x00000240691F5890, file "inspect.py", line 776>
 590: MAKE_FUNCTION        
 592: STORE_NAME           _findclass
 594: LOAD_CONST           <code object _finddoc at 0x0000024068D336D0, file "inspect.py", line 786>
 596: MAKE_FUNCTION        
 598: STORE_NAME           _finddoc
 600: LOAD_CONST           <code object getdoc at 0x000002406942E100, file "inspect.py", line 848>
 602: MAKE_FUNCTION        
 604: STORE_NAME           getdoc
 606: LOAD_CONST           <code object cleandoc at 0x0000024068C37930, file "inspect.py", line 867>
 608: MAKE_FUNCTION        
 610: STORE_NAME           cleandoc
 612: LOAD_CONST           <code object getfile at 0x0000024068E3EE50, file "inspect.py", line 896>
 614: MAKE_FUNCTION        
 616: STORE_NAME           getfile
 618: LOAD_CONST           <code object getmodulename at 0x00000240691DABB0, file "inspect.py", line 924>
 620: MAKE_FUNCTION        
 622: STORE_NAME           getmodulename
 624: LOAD_CONST           <code object getsourcefile at 0x0000024068B39060, file "inspect.py", line 936>
 626: MAKE_FUNCTION        
 628: STORE_NAME           getsourcefile
 630: LOAD_CONST           (None,)
 632: LOAD_CONST           <code object getabsfile at 0x00000240691E9E30, file "inspect.py", line 961>
 634: MAKE_FUNCTION        defaults
 636: STORE_NAME           getabsfile
 638: BUILD_MAP            
 640: STORE_NAME           modulesbyfile
 642: BUILD_MAP            
 644: STORE_NAME           _filesbymodname
 646: LOAD_CONST           (None,)
 648: LOAD_CONST           <code object getmodule at 0x0000024068E115E0, file "inspect.py", line 973>
 650: MAKE_FUNCTION        defaults
 652: STORE_NAME           getmodule
 654: PUSH_NULL            
 656: LOAD_BUILD_CLASS     
 658: LOAD_CONST           <code object ClassFoundException at 0x0000024069495550, file "inspect.py", line 1020>
 660: MAKE_FUNCTION        
 662: LOAD_CONST           'ClassFoundException'
 664: LOAD_NAME            Exception
 666: PRECALL              
 670: CALL                 
 680: STORE_NAME           ClassFoundException
 682: PUSH_NULL            
 684: LOAD_BUILD_CLASS     
 686: LOAD_CONST           <code object _ClassFinder at 0x0000024069466DB0, file "inspect.py", line 1024>
 688: MAKE_FUNCTION        
 690: LOAD_CONST           '_ClassFinder'
 692: LOAD_NAME            ast
 694: LOAD_ATTR            NodeVisitor
 704: PRECALL              
 708: CALL                 
 718: STORE_NAME           _ClassFinder
 720: LOAD_CONST           <code object findsource at 0x0000024068E11B80, file "inspect.py", line 1055>
 722: MAKE_FUNCTION        
 724: STORE_NAME           findsource
 726: LOAD_CONST           <code object getcomments at 0x0000024068E12870, file "inspect.py", line 1123>
 728: MAKE_FUNCTION        
 730: STORE_NAME           getcomments
 732: PUSH_NULL            
 734: LOAD_BUILD_CLASS     
 736: LOAD_CONST           <code object EndOfBlock at 0x0000024069495480, file "inspect.py", line 1168>
 738: MAKE_FUNCTION        
 740: LOAD_CONST           'EndOfBlock'
 742: LOAD_NAME            Exception
 744: PRECALL              
 748: CALL                 
 758: STORE_NAME           EndOfBlock
 760: PUSH_NULL            
 762: LOAD_BUILD_CLASS     
 764: LOAD_CONST           <code object BlockFinder at 0x0000024069466A30, file "inspect.py", line 1170>
 766: MAKE_FUNCTION        
 768: LOAD_CONST           'BlockFinder'
 770: PRECALL              
 774: CALL                 
 784: STORE_NAME           BlockFinder
 786: LOAD_CONST           <code object getblock at 0x000002406942CFD0, file "inspect.py", line 1224>
 788: MAKE_FUNCTION        
 790: STORE_NAME           getblock
 792: LOAD_CONST           <code object getsourcelines at 0x00000240691DA9E0, file "inspect.py", line 1235>
 794: MAKE_FUNCTION        
 796: STORE_NAME           getsourcelines
 798: LOAD_CONST           <code object getsource at 0x000002406944BDD0, file "inspect.py", line 1256>
 800: MAKE_FUNCTION        
 802: STORE_NAME           getsource
 804: LOAD_CONST           <code object walktree at 0x0000024069CE4030, file "inspect.py", line 1266>
 806: MAKE_FUNCTION        
 808: STORE_NAME           walktree
 810: LOAD_CONST           (False,)
 812: LOAD_CONST           <code object getclasstree at 0x0000024069366AD0, file "inspect.py", line 1276>
 814: MAKE_FUNCTION        defaults
 816: STORE_NAME           getclasstree
 818: PUSH_NULL            
 820: LOAD_NAME            namedtuple
 822: LOAD_CONST           'Arguments'
 824: LOAD_CONST           'args, varargs, varkw'
 826: PRECALL              
 830: CALL                 
 840: STORE_NAME           Arguments
 842: LOAD_CONST           <code object getargs at 0x0000024068E1DE30, file "inspect.py", line 1305>
 844: MAKE_FUNCTION        
 846: STORE_NAME           getargs
 848: PUSH_NULL            
 850: LOAD_NAME            namedtuple
 852: LOAD_CONST           'FullArgSpec'
 854: LOAD_CONST           'args, varargs, varkw, defaults, kwonlyargs, kwonlydefaults, annotations'
 856: PRECALL              
 860: CALL                 
 870: STORE_NAME           FullArgSpec
 872: LOAD_CONST           <code object getfullargspec at 0x0000024068E41C10, file "inspect.py", line 1336>
 874: MAKE_FUNCTION        
 876: STORE_NAME           getfullargspec
 878: PUSH_NULL            
 880: LOAD_NAME            namedtuple
 882: LOAD_CONST           'ArgInfo'
 884: LOAD_CONST           'args varargs keywords locals'
 886: PRECALL              
 890: CALL                 
 900: STORE_NAME           ArgInfo
 902: LOAD_CONST           <code object getargvalues at 0x0000024069419C50, file "inspect.py", line 1431>
 904: MAKE_FUNCTION        
 906: STORE_NAME           getargvalues
 908: LOAD_CONST           (None,)
 910: LOAD_CONST           <code object formatannotation at 0x0000024068E223E0, file "inspect.py", line 1441>
 912: MAKE_FUNCTION        defaults
 914: STORE_NAME           formatannotation
 916: LOAD_CONST           <code object formatannotationrelativeto at 0x0000024069CDC300, file "inspect.py", line 1455>
 918: MAKE_FUNCTION        
 920: STORE_NAME           formatannotationrelativeto
 922: LOAD_NAME            str
 924: LOAD_CONST           <code object <lambda> at 0x0000024069494FA0, file "inspect.py", line 1464>
 926: MAKE_FUNCTION        
 928: LOAD_CONST           <code object <lambda> at 0x0000024069494AC0, file "inspect.py", line 1465>
 930: MAKE_FUNCTION        
 932: LOAD_CONST           <code object <lambda> at 0x0000024069465450, file "inspect.py", line 1466>
 934: MAKE_FUNCTION        
 936: BUILD_TUPLE          
 938: LOAD_CONST           <code object formatargvalues at 0x0000024068C5ABD0, file "inspect.py", line 1462>
 940: MAKE_FUNCTION        defaults
 942: STORE_NAME           formatargvalues
 944: LOAD_CONST           <code object _missing_arguments at 0x000002406947C7B0, file "inspect.py", line 1485>
 946: MAKE_FUNCTION        
 948: STORE_NAME           _missing_arguments
 950: LOAD_CONST           <code object _too_many at 0x0000024068BBD1F0, file "inspect.py", line 1501>
 952: MAKE_FUNCTION        
 954: STORE_NAME           _too_many
 956: LOAD_CONST           <code object getcallargs at 0x0000024069591600, file "inspect.py", line 1522>
 958: MAKE_FUNCTION        
 960: STORE_NAME           getcallargs
 962: PUSH_NULL            
 964: LOAD_NAME            namedtuple
 966: LOAD_CONST           'ClosureVars'
 968: LOAD_CONST           'nonlocals globals builtins unbound'
 970: PRECALL              
 974: CALL                 
 984: STORE_NAME           ClosureVars
 986: LOAD_CONST           <code object getclosurevars at 0x0000024068BFD9F0, file "inspect.py", line 1584>
 988: MAKE_FUNCTION        
 990: STORE_NAME           getclosurevars
 992: PUSH_NULL            
 994: LOAD_NAME            namedtuple
 996: LOAD_CONST           '_Traceback'
 998: LOAD_CONST           'filename lineno function code_context index'
1000: PRECALL              
1004: CALL                 
1014: STORE_NAME           _Traceback
1016: PUSH_NULL            
1018: LOAD_BUILD_CLASS     
1020: LOAD_CONST           <code object Traceback at 0x0000024069CDC6C0, file "inspect.py", line 1639>
1022: MAKE_FUNCTION        
1024: LOAD_CONST           'Traceback'
1026: LOAD_NAME            _Traceback
1028: PRECALL              
1032: CALL                 
1042: STORE_NAME           Traceback
1044: LOAD_CONST           <code object _get_code_position_from_tb at 0x0000024069CF0130, file "inspect.py", line 1651>
1046: MAKE_FUNCTION        
1048: STORE_NAME           _get_code_position_from_tb
1050: LOAD_CONST           <code object _get_code_position at 0x00000240693AA5B0, file "inspect.py", line 1655>
1052: MAKE_FUNCTION        
1054: STORE_NAME           _get_code_position
1056: LOAD_CONST           (1,)
1058: LOAD_CONST           <code object getframeinfo at 0x0000024068CDF640, file "inspect.py", line 1662>
1060: MAKE_FUNCTION        defaults
1062: STORE_NAME           getframeinfo
1064: LOAD_CONST           <code object getlineno at 0x00000240694963F0, file "inspect.py", line 1705>
1066: MAKE_FUNCTION        
1068: STORE_NAME           getlineno
1070: PUSH_NULL            
1072: LOAD_NAME            namedtuple
1074: LOAD_CONST           '_FrameInfo'
1076: LOAD_CONST           ('frame',)
1078: LOAD_NAME            Traceback
1080: LOAD_ATTR            _fields
1090: BINARY_OP            +
1094: PRECALL              
1098: CALL                 
1108: STORE_NAME           _FrameInfo
1110: PUSH_NULL            
1112: LOAD_BUILD_CLASS     
1114: LOAD_CONST           <code object FrameInfo at 0x0000024069CDC7B0, file "inspect.py", line 1711>
1116: MAKE_FUNCTION        
1118: LOAD_CONST           'FrameInfo'
1120: LOAD_NAME            _FrameInfo
1122: PRECALL              
1126: CALL                 
1136: STORE_NAME           FrameInfo
1138: LOAD_CONST           (1,)
1140: LOAD_CONST           <code object getouterframes at 0x000002406922D7D0, file "inspect.py", line 1723>
1142: MAKE_FUNCTION        defaults
1144: STORE_NAME           getouterframes
1146: LOAD_CONST           (1,)
1148: LOAD_CONST           <code object getinnerframes at 0x00000240691C14D0, file "inspect.py", line 1736>
1150: MAKE_FUNCTION        defaults
1152: STORE_NAME           getinnerframes
1154: LOAD_CONST           <code object currentframe at 0x0000024069CF4250, file "inspect.py", line 1749>
1156: MAKE_FUNCTION        
1158: STORE_NAME           currentframe
1160: LOAD_CONST           (1,)
1162: LOAD_CONST           <code object stack at 0x0000024069CF0230, file "inspect.py", line 1753>
1164: MAKE_FUNCTION        defaults
1166: STORE_NAME           stack
1168: LOAD_CONST           (1,)
1170: LOAD_CONST           <code object trace at 0x0000024069CF4360, file "inspect.py", line 1757>
1172: MAKE_FUNCTION        defaults
1174: STORE_NAME           trace
1176: PUSH_NULL            
1178: LOAD_NAME            object
1180: PRECALL              
1184: CALL                 
1194: STORE_NAME           _sentinel
1196: LOAD_CONST           <code object _static_getmro at 0x0000024069CF4470, file "inspect.py", line 1766>
1198: MAKE_FUNCTION        
1200: STORE_NAME           _static_getmro
1202: LOAD_CONST           <code object _check_instance at 0x00000240691C1FD0, file "inspect.py", line 1769>
1204: MAKE_FUNCTION        
1206: STORE_NAME           _check_instance
1208: LOAD_CONST           <code object _check_class at 0x00000240691E84B0, file "inspect.py", line 1778>
1210: MAKE_FUNCTION        
1212: STORE_NAME           _check_class
1214: LOAD_CONST           <code object _is_type at 0x0000024069CF4580, file "inspect.py", line 1787>
1216: MAKE_FUNCTION        
1218: STORE_NAME           _is_type
1220: LOAD_CONST           <code object _shadowed_dict at 0x00000240691DAD80, file "inspect.py", line 1794>
1222: MAKE_FUNCTION        
1224: STORE_NAME           _shadowed_dict
1226: LOAD_NAME            _sentinel
1228: BUILD_TUPLE          
1230: LOAD_CONST           <code object getattr_static at 0x0000024068D03690, file "inspect.py", line 1808>
1232: MAKE_FUNCTION        defaults
1234: STORE_NAME           getattr_static
1236: LOAD_CONST           'GEN_CREATED'
1238: STORE_NAME           GEN_CREATED
1240: LOAD_CONST           'GEN_RUNNING'
1242: STORE_NAME           GEN_RUNNING
1244: LOAD_CONST           'GEN_SUSPENDED'
1246: STORE_NAME           GEN_SUSPENDED
1248: LOAD_CONST           'GEN_CLOSED'
1250: STORE_NAME           GEN_CLOSED
1252: LOAD_CONST           <code object getgeneratorstate at 0x000002406941AE50, file "inspect.py", line 1863>
1254: MAKE_FUNCTION        
1256: STORE_NAME           getgeneratorstate
1258: LOAD_CONST           <code object getgeneratorlocals at 0x00000240691C2970, file "inspect.py", line 1881>
1260: MAKE_FUNCTION        
1262: STORE_NAME           getgeneratorlocals
1264: LOAD_CONST           'CORO_CREATED'
1266: STORE_NAME           CORO_CREATED
1268: LOAD_CONST           'CORO_RUNNING'
1270: STORE_NAME           CORO_RUNNING
1272: LOAD_CONST           'CORO_SUSPENDED'
1274: STORE_NAME           CORO_SUSPENDED
1276: LOAD_CONST           'CORO_CLOSED'
1278: STORE_NAME           CORO_CLOSED
1280: LOAD_CONST           <code object getcoroutinestate at 0x0000024069419110, file "inspect.py", line 1905>
1282: MAKE_FUNCTION        
1284: STORE_NAME           getcoroutinestate
1286: LOAD_CONST           <code object getcoroutinelocals at 0x0000024069CF0330, file "inspect.py", line 1923>
1288: MAKE_FUNCTION        
1290: STORE_NAME           getcoroutinelocals
1292: LOAD_NAME            types
1294: LOAD_ATTR            WrapperDescriptorType
1304: LOAD_NAME            types
1306: LOAD_ATTR            MethodWrapperType
1316: LOAD_NAME            types
1318: LOAD_ATTR            ClassMethodDescriptorType
1328: LOAD_NAME            types
1330: LOAD_ATTR            BuiltinFunctionType
1340: BUILD_TUPLE          
1342: STORE_NAME           _NonUserDefinedCallables
1344: LOAD_CONST           <code object _signature_get_user_defined_method at 0x00000240693D2890, file "inspect.py", line 1947>
1346: MAKE_FUNCTION        
1348: STORE_NAME           _signature_get_user_defined_method
1350: LOAD_CONST           ((),)
1352: LOAD_CONST           <code object _signature_get_partial at 0x0000024068D33C20, file "inspect.py", line 1963>
1354: MAKE_FUNCTION        defaults
1356: STORE_NAME           _signature_get_partial
1358: LOAD_CONST           <code object _signature_bound_method at 0x0000024068E232C0, file "inspect.py", line 2039>
1360: MAKE_FUNCTION        
1362: STORE_NAME           _signature_bound_method
1364: LOAD_CONST           <code object _signature_is_builtin at 0x00000240693A9570, file "inspect.py", line 2065>
1366: MAKE_FUNCTION        
1368: STORE_NAME           _signature_is_builtin
1370: LOAD_CONST           <code object _signature_is_functionlike at 0x0000024068C05CB0, file "inspect.py", line 2077>
1372: MAKE_FUNCTION        
1374: STORE_NAME           _signature_is_functionlike
1376: LOAD_CONST           <code object _signature_strip_non_python_syntax at 0x0000024066346C70, file "inspect.py", line 2102>
1378: MAKE_FUNCTION        
1380: STORE_NAME           _signature_strip_non_python_syntax
1382: LOAD_CONST           (True,)
1384: LOAD_CONST           <code object _signature_fromstr at 0x0000024069591AA0, file "inspect.py", line 2174>
1386: MAKE_FUNCTION        defaults
1388: STORE_NAME           _signature_fromstr
1390: LOAD_CONST           (True,)
1392: LOAD_CONST           <code object _signature_from_builtin at 0x0000024069CE4390, file "inspect.py", line 2317>
1394: MAKE_FUNCTION        defaults
1396: STORE_NAME           _signature_from_builtin
1398: NOP                  
1400: NOP                  
1402: LOAD_CONST           (True, None, None, False)
1404: LOAD_CONST           <code object _signature_from_function at 0x00000240695927A0, file "inspect.py", line 2333>
1406: MAKE_FUNCTION        defaults
1408: STORE_NAME           _signature_from_function
1410: LOAD_CONST           True
1412: LOAD_CONST           True
1414: LOAD_CONST           None
1416: LOAD_CONST           None
1418: LOAD_CONST           False
1420: LOAD_CONST           ('follow_wrapper_chains', 'skip_bound_arg', 'globals', 'locals', 'eval_str')
1422: BUILD_CONST_KEY_MAP  
1424: LOAD_CONST           <code object _signature_from_callable at 0x000002406951A640, file "inspect.py", line 2428>
1426: MAKE_FUNCTION        kwdefaults
1428: STORE_NAME           _signature_from_callable
1430: PUSH_NULL            
1432: LOAD_BUILD_CLASS     
1434: LOAD_CONST           <code object _void at 0x0000024069494440, file "inspect.py", line 2622>
1436: MAKE_FUNCTION        
1438: LOAD_CONST           '_void'
1440: PRECALL              
1444: CALL                 
1454: STORE_NAME           _void
1456: PUSH_NULL            
1458: LOAD_BUILD_CLASS     
1460: LOAD_CONST           <code object _empty at 0x00000240694964C0, file "inspect.py", line 2626>
1462: MAKE_FUNCTION        
1464: LOAD_CONST           '_empty'
1466: PRECALL              
1470: CALL                 
1480: STORE_NAME           _empty
1482: PUSH_NULL            
1484: LOAD_BUILD_CLASS     
1486: LOAD_CONST           <code object _ParameterKind at 0x0000024069CDCA80, file "inspect.py", line 2630>
1488: MAKE_FUNCTION        
1490: LOAD_CONST           '_ParameterKind'
1492: LOAD_NAME            enum
1494: LOAD_ATTR            IntEnum
1504: PRECALL              
1508: CALL                 
1518: STORE_NAME           _ParameterKind
1520: LOAD_NAME            _ParameterKind
1522: LOAD_ATTR            POSITIONAL_ONLY
1532: STORE_NAME           _POSITIONAL_ONLY
1534: LOAD_NAME            _ParameterKind
1536: LOAD_ATTR            POSITIONAL_OR_KEYWORD
1546: STORE_NAME           _POSITIONAL_OR_KEYWORD
1548: LOAD_NAME            _ParameterKind
1550: LOAD_ATTR            VAR_POSITIONAL
1560: STORE_NAME           _VAR_POSITIONAL
1562: LOAD_NAME            _ParameterKind
1564: LOAD_ATTR            KEYWORD_ONLY
1574: STORE_NAME           _KEYWORD_ONLY
1576: LOAD_NAME            _ParameterKind
1578: LOAD_ATTR            VAR_KEYWORD
1588: STORE_NAME           _VAR_KEYWORD
1590: PUSH_NULL            
1592: LOAD_BUILD_CLASS     
1594: LOAD_CONST           <code object Parameter at 0x000002406942CB20, file "inspect.py", line 2654>
1596: MAKE_FUNCTION        
1598: LOAD_CONST           'Parameter'
1600: PRECALL              
1604: CALL                 
1614: STORE_NAME           Parameter
1616: PUSH_NULL            
1618: LOAD_BUILD_CLASS     
1620: LOAD_CONST           <code object BoundArguments at 0x00000240693AA830, file "inspect.py", line 2812>
1622: MAKE_FUNCTION        
1624: LOAD_CONST           'BoundArguments'
1626: PRECALL              
1630: CALL                 
1640: STORE_NAME           BoundArguments
1642: PUSH_NULL            
1644: LOAD_BUILD_CLASS     
1646: LOAD_CONST           <code object Signature at 0x000002406942E290, file "inspect.py", line 2942>
1648: MAKE_FUNCTION        
1650: LOAD_CONST           'Signature'
1652: PRECALL              
1656: CALL                 
1666: STORE_NAME           Signature
1668: LOAD_CONST           True
1670: LOAD_CONST           None
1672: LOAD_CONST           None
1674: LOAD_CONST           False
1676: LOAD_CONST           ('follow_wrapped', 'globals', 'locals', 'eval_str')
1678: BUILD_CONST_KEY_MAP  
1680: LOAD_CONST           <code object signature at 0x0000024069CF1130, file "inspect.py", line 3278>
1682: MAKE_FUNCTION        kwdefaults
1684: STORE_NAME           signature
1686: LOAD_CONST           <code object _main at 0x000002406951BDF0, file "inspect.py", line 3284>
1688: MAKE_FUNCTION        
1690: STORE_NAME           _main
1692: LOAD_NAME            __name__
1694: LOAD_CONST           '__main__'
1696: COMPARE_OP           ==
1702: POP_JUMP_FORWARD_IF_FALSE to 1728
1704: PUSH_NULL            
1706: LOAD_NAME            _main
1708: PRECALL              
1712: CALL                 
1722: POP_TOP              
1724: LOAD_CONST           None
1726: RETURN_VALUE         
1728: LOAD_CONST           None
1730: RETURN_VALUE         
