# Disassembly for inspect.FrameInfo.__new__
# From module file: inspect

## co_consts:
(None,)

## co_names:
('super', '__new__', 'positions')

## bytecode:

   0: COPY_FREE_VARS       
   2: RESUME               
   4: LOAD_GLOBAL          NULL + super
  16: PRECALL              
  20: CALL                 
  30: LOAD_METHOD          __new__
  52: LOAD_FAST            cls
  54: LOAD_FAST            frame
  56: LOAD_FAST            filename
  58: LOAD_FAST            lineno
  60: LOAD_FAST            function
  62: LOAD_FAST            code_context
  64: LOAD_FAST            index
  66: PRECALL              
  70: CALL                 
  80: STORE_FAST           instance
  82: LOAD_FAST            positions
  84: LOAD_FAST            instance
  86: STORE_ATTR           positions
  96: LOAD_FAST            instance
  98: RETURN_VALUE         
