# Disassembly for inspect.getsourcelines
# From module file: inspect

## co_consts:
('Return a list of source lines and starting line number for an object.\n\n    The argument may be a module, class, method, function, traceback, frame,\n    or code object.  The source code is returned as a list of the lines\n    corresponding to the object and the line number indicates where in the\n    original source file the first line of code was found.  An OSError is\n    raised if the source code cannot be retrieved.', '<module>', 0, None, 1)

## co_names:
('unwrap', 'findsource', 'istraceback', 'tb_frame', 'ismodule', 'isframe', 'f_code', 'co_name', 'getblock')

## bytecode:

   0: RESUME               
   2: LOAD_GLOBAL          NULL + unwrap
  14: LOAD_FAST            object
  16: PRECALL              
  20: CALL                 
  30: STORE_FAST           object
  32: LOAD_GLOBAL          NULL + findsource
  44: LOAD_FAST            object
  46: PRECALL              
  50: CALL                 
  60: UNPACK_SEQUENCE      
  64: STORE_FAST           lines
  66: STORE_FAST           lnum
  68: LOAD_GLOBAL          NULL + istraceback
  80: LOAD_FAST            object
  82: PRECALL              
  86: CALL                 
  96: POP_JUMP_FORWARD_IF_FALSE to 112
  98: LOAD_FAST            object
 100: LOAD_ATTR            tb_frame
 110: STORE_FAST           object
 112: LOAD_GLOBAL          NULL + ismodule
 124: LOAD_FAST            object
 126: PRECALL              
 130: CALL                 
 140: POP_JUMP_FORWARD_IF_TRUE to 204
 142: LOAD_GLOBAL          NULL + isframe
 154: LOAD_FAST            object
 156: PRECALL              
 160: CALL                 
 170: POP_JUMP_FORWARD_IF_FALSE to 212
 172: LOAD_FAST            object
 174: LOAD_ATTR            f_code
 184: LOAD_ATTR            co_name
 194: LOAD_CONST           '<module>'
 196: COMPARE_OP           ==
 202: POP_JUMP_FORWARD_IF_FALSE to 212
 204: LOAD_FAST            lines
 206: LOAD_CONST           0
 208: BUILD_TUPLE          
 210: RETURN_VALUE         
 212: LOAD_GLOBAL          NULL + getblock
 224: LOAD_FAST            lines
 226: LOAD_FAST            lnum
 228: LOAD_CONST           None
 230: BUILD_SLICE          
 232: BINARY_SUBSCR        
 242: PRECALL              
 246: CALL                 
 256: LOAD_FAST            lnum
 258: LOAD_CONST           1
 260: BINARY_OP            +
 264: BUILD_TUPLE          
 266: RETURN_VALUE         
