# Disassembly for inspect.BlockFinder.tokeneater
# From module file: inspect

## co_consts:
(None, '@', True, ('def', 'class', 'lambda'), 'lambda', False, 0, 1)

## co_names:
('started', 'indecorator', 'islambda', 'passline', 'tokenize', 'NEWLINE', 'last', 'EndOfBlock', 'INDENT', 'body_col0', 'indent', 'DEDENT', 'COMMENT', 'NL')

## bytecode:

   0: RESUME               
   2: LOAD_FAST            self
   4: LOAD_ATTR            started
  14: POP_JUMP_FORWARD_IF_TRUE to 124
  16: LOAD_FAST            self
  18: LOAD_ATTR            indecorator
  28: POP_JUMP_FORWARD_IF_TRUE to 124
  30: LOAD_FAST            token
  32: LOAD_CONST           '@'
  34: COMPARE_OP           ==
  40: POP_JUMP_FORWARD_IF_FALSE to 58
  42: LOAD_CONST           True
  44: LOAD_FAST            self
  46: STORE_ATTR           indecorator
  56: JUMP_FORWARD         to 106
  58: LOAD_FAST            token
  60: LOAD_CONST           ('def', 'class', 'lambda')
  62: CONTAINS_OP          
  64: POP_JUMP_FORWARD_IF_FALSE to 106
  66: LOAD_FAST            token
  68: LOAD_CONST           'lambda'
  70: COMPARE_OP           ==
  76: POP_JUMP_FORWARD_IF_FALSE to 92
  78: LOAD_CONST           True
  80: LOAD_FAST            self
  82: STORE_ATTR           islambda
  92: LOAD_CONST           True
  94: LOAD_FAST            self
  96: STORE_ATTR           started
 106: LOAD_CONST           True
 108: LOAD_FAST            self
 110: STORE_ATTR           passline
 120: LOAD_CONST           None
 122: RETURN_VALUE         
 124: LOAD_FAST            type
 126: LOAD_GLOBAL          tokenize
 138: LOAD_ATTR            NEWLINE
 148: COMPARE_OP           ==
 154: POP_JUMP_FORWARD_IF_FALSE to 260
 156: LOAD_CONST           False
 158: LOAD_FAST            self
 160: STORE_ATTR           passline
 170: LOAD_FAST            srowcol
 172: LOAD_CONST           0
 174: BINARY_SUBSCR        
 184: LOAD_FAST            self
 186: STORE_ATTR           last
 196: LOAD_FAST            self
 198: LOAD_ATTR            islambda
 208: POP_JUMP_FORWARD_IF_FALSE to 224
 210: LOAD_GLOBAL          EndOfBlock
 222: RAISE_VARARGS        
 224: LOAD_FAST            self
 226: LOAD_ATTR            indecorator
 236: POP_JUMP_FORWARD_IF_FALSE to 256
 238: LOAD_CONST           False
 240: LOAD_FAST            self
 242: STORE_ATTR           indecorator
 252: LOAD_CONST           None
 254: RETURN_VALUE         
 256: LOAD_CONST           None
 258: RETURN_VALUE         
 260: LOAD_FAST            self
 262: LOAD_ATTR            passline
 272: POP_JUMP_FORWARD_IF_FALSE to 278
 274: LOAD_CONST           None
 276: RETURN_VALUE         
 278: LOAD_FAST            type
 280: LOAD_GLOBAL          tokenize
 292: LOAD_ATTR            INDENT
 302: COMPARE_OP           ==
 308: POP_JUMP_FORWARD_IF_FALSE to 412
 310: LOAD_FAST            self
 312: LOAD_ATTR            body_col0
 322: POP_JUMP_FORWARD_IF_NOT_NONE to 364
 324: LOAD_FAST            self
 326: LOAD_ATTR            started
 336: POP_JUMP_FORWARD_IF_FALSE to 364
 338: LOAD_FAST            erowcol
 340: LOAD_CONST           1
 342: BINARY_SUBSCR        
 352: LOAD_FAST            self
 354: STORE_ATTR           body_col0
 364: LOAD_FAST            self
 366: LOAD_ATTR            indent
 376: LOAD_CONST           1
 378: BINARY_OP            +
 382: LOAD_FAST            self
 384: STORE_ATTR           indent
 394: LOAD_CONST           True
 396: LOAD_FAST            self
 398: STORE_ATTR           passline
 408: LOAD_CONST           None
 410: RETURN_VALUE         
 412: LOAD_FAST            type
 414: LOAD_GLOBAL          tokenize
 426: LOAD_ATTR            DEDENT
 436: COMPARE_OP           ==
 442: POP_JUMP_FORWARD_IF_FALSE to 514
 444: LOAD_FAST            self
 446: LOAD_ATTR            indent
 456: LOAD_CONST           1
 458: BINARY_OP            -
 462: LOAD_FAST            self
 464: STORE_ATTR           indent
 474: LOAD_FAST            self
 476: LOAD_ATTR            indent
 486: LOAD_CONST           0
 488: COMPARE_OP           <=
 494: POP_JUMP_FORWARD_IF_FALSE to 510
 496: LOAD_GLOBAL          EndOfBlock
 508: RAISE_VARARGS        
 510: LOAD_CONST           None
 512: RETURN_VALUE         
 514: LOAD_FAST            type
 516: LOAD_GLOBAL          tokenize
 528: LOAD_ATTR            COMMENT
 538: COMPARE_OP           ==
 544: POP_JUMP_FORWARD_IF_FALSE to 632
 546: LOAD_FAST            self
 548: LOAD_ATTR            body_col0
 558: POP_JUMP_FORWARD_IF_NONE to 624
 560: LOAD_FAST            srowcol
 562: LOAD_CONST           1
 564: BINARY_SUBSCR        
 574: LOAD_FAST            self
 576: LOAD_ATTR            body_col0
 586: COMPARE_OP           >=
 592: POP_JUMP_FORWARD_IF_FALSE to 628
 594: LOAD_FAST            srowcol
 596: LOAD_CONST           0
 598: BINARY_SUBSCR        
 608: LOAD_FAST            self
 610: STORE_ATTR           last
 620: LOAD_CONST           None
 622: RETURN_VALUE         
 624: LOAD_CONST           None
 626: RETURN_VALUE         
 628: LOAD_CONST           None
 630: RETURN_VALUE         
 632: LOAD_FAST            self
 634: LOAD_ATTR            indent
 644: LOAD_CONST           0
 646: COMPARE_OP           ==
 652: POP_JUMP_FORWARD_IF_FALSE to 720
 654: LOAD_FAST            type
 656: LOAD_GLOBAL          tokenize
 668: LOAD_ATTR            COMMENT
 678: LOAD_GLOBAL          tokenize
 690: LOAD_ATTR            NL
 700: BUILD_TUPLE          
 702: CONTAINS_OP          
 704: POP_JUMP_FORWARD_IF_FALSE to 724
 706: LOAD_GLOBAL          EndOfBlock
 718: RAISE_VARARGS        
 720: LOAD_CONST           None
 722: RETURN_VALUE         
 724: LOAD_CONST           None
 726: RETURN_VALUE         
