# Disassembly for inspect.Signature._hash_basis.<dictcomp>
# From module file: inspect

## co_consts:
()

## co_names:
('kind', '_KEYWORD_ONLY', 'name')

## bytecode:

   0: RESUME               
   2: BUILD_MAP            
   4: LOAD_FAST            .0
   6: FOR_ITER             to 60
   8: STORE_FAST           param
  10: LOAD_FAST            param
  12: LOAD_ATTR            kind
  22: LOAD_GLOBAL          _KEYWORD_ONLY
  34: COMPARE_OP           ==
  40: POP_JUMP_BACKWARD_IF_FALSE to 6
  42: LOAD_FAST            param
  44: LOAD_ATTR            name
  54: LOAD_FAST            param
  56: MAP_ADD              
  58: JUMP_BACKWARD        to 6
  60: RETURN_VALUE         
