# Disassembly for inspect.istraceback
# From module file: inspect

## co_consts:
('Return true if the object is a traceback.\n\n    Traceback objects provide these attributes:\n        tb_frame        frame object at this level\n        tb_lasti        index of last attempted instruction in bytecode\n        tb_lineno       current line number in Python source code\n        tb_next         next inner traceback object (called by this level)',)

## co_names:
('isinstance', 'types', 'TracebackType')

## bytecode:

   0: RESUME               
   2: LOAD_GLOBAL          NULL + isinstance
  14: LOAD_FAST            object
  16: LOAD_GLOBAL          types
  28: LOAD_ATTR            TracebackType
  38: PRECALL              
  42: CALL                 
  52: RETURN_VALUE         
