# Disassembly for inspect.get_annotations.<dictcomp>
# From module file: inspect

## co_consts:
()

## co_names:
('isinstance', 'str', 'eval')

## bytecode:

   0: COPY_FREE_VARS       
   2: RESUME               
   4: BUILD_MAP            
   6: LOAD_FAST            .0
   8: FOR_ITER             to 102
  10: UNPACK_SEQUENCE      
  14: STORE_FAST           key
  16: STORE_FAST           value
  18: LOAD_FAST            key
  20: LOAD_GLOBAL          NULL + isinstance
  32: LOAD_FAST            value
  34: LOAD_GLOBAL          str
  46: PRECALL              
  50: CALL                 
  60: POP_JUMP_FORWARD_IF_TRUE to 66
  62: LOAD_FAST            value
  64: JUMP_FORWARD         to 98
  66: LOAD_GLOBAL          NULL + eval
  78: LOAD_FAST            value
  80: LOAD_DEREF           globals
  82: LOAD_DEREF           locals
  84: PRECALL              
  88: CALL                 
  98: MAP_ADD              
 100: JUMP_BACKWARD        to 8
 102: RETURN_VALUE         
