# Disassembly for inspect.BoundArguments.__repr__
# From module file: inspect

## co_consts:
(None, '{}={!r}', '<{} ({})>', ', ')

## co_names:
('arguments', 'items', 'append', 'format', '__class__', '__name__', 'join')

## bytecode:

   0: RESUME               
   2: BUILD_LIST           
   4: STORE_FAST           args
   6: LOAD_FAST            self
   8: LOAD_ATTR            arguments
  18: LOAD_METHOD          items
  40: PRECALL              
  44: CALL                 
  54: GET_ITER             
  56: FOR_ITER             to 150
  58: UNPACK_SEQUENCE      
  62: STORE_FAST           arg
  64: STORE_FAST           value
  66: LOAD_FAST            args
  68: LOAD_METHOD          append
  90: LOAD_CONST           '{}={!r}'
  92: LOAD_METHOD          format
 114: LOAD_FAST            arg
 116: LOAD_FAST            value
 118: PRECALL              
 122: CALL                 
 132: PRECALL              
 136: CALL                 
 146: POP_TOP              
 148: JUMP_BACKWARD        to 56
 150: LOAD_CONST           '<{} ({})>'
 152: LOAD_METHOD          format
 174: LOAD_FAST            self
 176: LOAD_ATTR            __class__
 186: LOAD_ATTR            __name__
 196: LOAD_CONST           ', '
 198: LOAD_METHOD          join
 220: LOAD_FAST            args
 222: PRECALL              
 226: CALL                 
 236: PRECALL              
 240: CALL                 
 250: RETURN_VALUE         
