# Disassembly for inspect.BoundArguments.__setstate__
# From module file: inspect

## co_consts:
(None, '_signature', 'arguments')

## co_names:
('_signature', 'arguments')

## bytecode:

   0: RESUME               
   2: LOAD_FAST            state
   4: LOAD_CONST           '_signature'
   6: BINARY_SUBSCR        
  16: LOAD_FAST            self
  18: STORE_ATTR           _signature
  28: LOAD_FAST            state
  30: LOAD_CONST           'arguments'
  32: BINARY_SUBSCR        
  42: LOAD_FAST            self
  44: STORE_ATTR           arguments
  54: LOAD_CONST           None
  56: RETURN_VALUE         
