# Disassembly for statistics.NormalDist.__truediv__
# From module file: statistics

## co_consts:
('Divide both mu and sigma by a constant.\n\n        Used for rescaling, perhaps to change measurement units.\n        Sigma is scaled with the absolute value of the constant.\n        ',)

## co_names:
('NormalDist', '_mu', '_sigma', 'fabs')

## bytecode:

   0: RESUME               
   2: LOAD_GLOBAL          NULL + NormalDist
  14: LOAD_FAST            x1
  16: LOAD_ATTR            _mu
  26: LOAD_FAST            x2
  28: BINARY_OP            /
  32: LOAD_FAST            x1
  34: LOAD_ATTR            _sigma
  44: LOAD_GLOBAL          NULL + fabs
  56: LOAD_FAST            x2
  58: PRECALL              
  62: CALL                 
  72: BINARY_OP            /
  76: PRECALL              
  80: CALL                 
  90: RETURN_VALUE         
