# Disassembly for statistics.NormalDist.pdf
# From module file: statistics

## co_consts:
('Probability density function.  P(x <= X < x+dx) / dx', 'pdf() not defined when sigma is zero', -2.0)

## co_names:
('_sigma', 'StatisticsError', '_mu', 'exp', 'sqrt', 'tau')

## bytecode:

   0: RESUME               
   2: LOAD_FAST            self
   4: LOAD_ATTR            _sigma
  14: LOAD_FAST            self
  16: LOAD_ATTR            _sigma
  26: BINARY_OP            *
  30: STORE_FAST           variance
  32: LOAD_FAST            variance
  34: POP_JUMP_FORWARD_IF_TRUE to 66
  36: LOAD_GLOBAL          NULL + StatisticsError
  48: LOAD_CONST           'pdf() not defined when sigma is zero'
  50: PRECALL              
  54: CALL                 
  64: RAISE_VARARGS        
  66: LOAD_FAST            x
  68: LOAD_FAST            self
  70: LOAD_ATTR            _mu
  80: BINARY_OP            -
  84: STORE_FAST           diff
  86: LOAD_GLOBAL          NULL + exp
  98: LOAD_FAST            diff
 100: LOAD_FAST            diff
 102: BINARY_OP            *
 106: LOAD_CONST           -2.0
 108: LOAD_FAST            variance
 110: BINARY_OP            *
 114: BINARY_OP            /
 118: PRECALL              
 122: CALL                 
 132: LOAD_GLOBAL          NULL + sqrt
 144: LOAD_GLOBAL          tau
 156: LOAD_FAST            variance
 158: BINARY_OP            *
 162: PRECALL              
 166: CALL                 
 176: BINARY_OP            /
 180: RETURN_VALUE         
