# Disassembly for statistics.NormalDist.__add__
# From module file: statistics

## co_consts:
('Add a constant or another NormalDist instance.\n\n        If *other* is a constant, translate mu by the constant,\n        leaving sigma unchanged.\n\n        If *other* is a NormalDist, add both the means and the variances.\n        Mathematically, this works only if the two distributions are\n        independent or if they are jointly normally distributed.\n        ',)

## co_names:
('isinstance', 'NormalDist', '_mu', 'hypot', '_sigma')

## bytecode:

   0: RESUME               
   2: LOAD_GLOBAL          NULL + isinstance
  14: LOAD_FAST            x2
  16: LOAD_GLOBAL          NormalDist
  28: PRECALL              
  32: CALL                 
  42: POP_JUMP_FORWARD_IF_FALSE to 150
  44: LOAD_GLOBAL          NULL + NormalDist
  56: LOAD_FAST            x1
  58: LOAD_ATTR            _mu
  68: LOAD_FAST            x2
  70: LOAD_ATTR            _mu
  80: BINARY_OP            +
  84: LOAD_GLOBAL          NULL + hypot
  96: LOAD_FAST            x1
  98: LOAD_ATTR            _sigma
 108: LOAD_FAST            x2
 110: LOAD_ATTR            _sigma
 120: PRECALL              
 124: CALL                 
 134: PRECALL              
 138: CALL                 
 148: RETURN_VALUE         
 150: LOAD_GLOBAL          NULL + NormalDist
 162: LOAD_FAST            x1
 164: LOAD_ATTR            _mu
 174: LOAD_FAST            x2
 176: BINARY_OP            +
 180: LOAD_FAST            x1
 182: LOAD_ATTR            _sigma
 192: PRECALL              
 196: CALL                 
 206: RETURN_VALUE         
