# Disassembly for statistics.NormalDist.cdf
# From module file: statistics

## co_consts:
('Cumulative distribution function.  P(X <= x)', 'cdf() not defined when sigma is zero', 0.5, 1.0)

## co_names:
('_sigma', 'StatisticsError', 'erf', '_mu', '_SQRT2')

## bytecode:

   0: RESUME               
   2: LOAD_FAST            self
   4: LOAD_ATTR            _sigma
  14: POP_JUMP_FORWARD_IF_TRUE to 46
  16: LOAD_GLOBAL          NULL + StatisticsError
  28: LOAD_CONST           'cdf() not defined when sigma is zero'
  30: PRECALL              
  34: CALL                 
  44: RAISE_VARARGS        
  46: LOAD_CONST           0.5
  48: LOAD_CONST           1.0
  50: LOAD_GLOBAL          NULL + erf
  62: LOAD_FAST            x
  64: LOAD_FAST            self
  66: LOAD_ATTR            _mu
  76: BINARY_OP            -
  80: LOAD_FAST            self
  82: LOAD_ATTR            _sigma
  92: LOAD_GLOBAL          _SQRT2
 104: BINARY_OP            *
 108: BINARY_OP            /
 112: PRECALL              
 116: CALL                 
 126: BINARY_OP            +
 130: BINARY_OP            *
 134: RETURN_VALUE         
