# Disassembly for statistics.NormalDist.inv_cdf
# From module file: statistics

## co_consts:
('Inverse cumulative distribution function.  x : P(X <= x) = p\n\n        Finds the value of the random variable such that the probability of\n        the variable being less than or equal to that value equals the given\n        probability.\n\n        This function is also called the percent point function or quantile\n        function.\n        ', 0.0, 1.0, 'p must be in the range 0.0 < p < 1.0', 'cdf() not defined when sigma at or below zero')

## co_names:
('StatisticsError', '_sigma', '_normal_dist_inv_cdf', '_mu')

## bytecode:

   0: RESUME               
   2: LOAD_FAST            p
   4: LOAD_CONST           0.0
   6: COMPARE_OP           <=
  12: POP_JUMP_FORWARD_IF_TRUE to 26
  14: LOAD_FAST            p
  16: LOAD_CONST           1.0
  18: COMPARE_OP           >=
  24: POP_JUMP_FORWARD_IF_FALSE to 56
  26: LOAD_GLOBAL          NULL + StatisticsError
  38: LOAD_CONST           'p must be in the range 0.0 < p < 1.0'
  40: PRECALL              
  44: CALL                 
  54: RAISE_VARARGS        
  56: LOAD_FAST            self
  58: LOAD_ATTR            _sigma
  68: LOAD_CONST           0.0
  70: COMPARE_OP           <=
  76: POP_JUMP_FORWARD_IF_FALSE to 108
  78: LOAD_GLOBAL          NULL + StatisticsError
  90: LOAD_CONST           'cdf() not defined when sigma at or below zero'
  92: PRECALL              
  96: CALL                 
 106: RAISE_VARARGS        
 108: LOAD_GLOBAL          NULL + _normal_dist_inv_cdf
 120: LOAD_FAST            p
 122: LOAD_FAST            self
 124: LOAD_ATTR            _mu
 134: LOAD_FAST            self
 136: LOAD_ATTR            _sigma
 146: PRECALL              
 150: CALL                 
 160: RETURN_VALUE         
