# Disassembly for statistics.multimode.<listcomp>
# From module file: statistics

## co_consts:
()

## co_names:
()

## bytecode:

   0: COPY_FREE_VARS       
   2: RESUME               
   4: BUILD_LIST           
   6: LOAD_FAST            .0
   8: FOR_ITER             to 36
  10: UNPACK_SEQUENCE      
  14: STORE_FAST           value
  16: STORE_FAST           count
  18: LOAD_FAST            count
  20: LOAD_DEREF           maxcount
  22: COMPARE_OP           ==
  28: POP_JUMP_BACKWARD_IF_FALSE to 8
  30: LOAD_FAST            value
  32: LIST_APPEND          
  34: JUMP_BACKWARD        to 8
  36: RETURN_VALUE         
