# Disassembly for statistics.NormalDist.__neg__
# From module file: statistics

## co_consts:
('Negates mu while keeping sigma the same.',)

## co_names:
('NormalDist', '_mu', '_sigma')

## bytecode:

   0: RESUME               
   2: LOAD_GLOBAL          NULL + NormalDist
  14: LOAD_FAST            x1
  16: LOAD_ATTR            _mu
  26: UNARY_NEGATIVE       
  28: LOAD_FAST            x1
  30: LOAD_ATTR            _sigma
  40: PRECALL              
  44: CALL                 
  54: RETURN_VALUE         
