# Disassembly for statistics.NormalDist.samples
# From module file: statistics

## co_consts:
('Generate *n* samples for a given mean and standard deviation.', None, <code object <listcomp> at 0x0000024069465FB0, file "statistics.py", line 1196>)

## co_names:
('random', 'gauss', 'Random', '_mu', '_sigma', 'range')

## bytecode:

   0: MAKE_CELL            gauss
   2: MAKE_CELL            mu
   4: MAKE_CELL            sigma
   6: RESUME               
   8: LOAD_FAST            seed
  10: POP_JUMP_FORWARD_IF_NOT_NONE to 36
  12: LOAD_GLOBAL          random
  24: LOAD_ATTR            gauss
  34: JUMP_FORWARD         to 84
  36: LOAD_GLOBAL          NULL + random
  48: LOAD_ATTR            Random
  58: LOAD_FAST            seed
  60: PRECALL              
  64: CALL                 
  74: LOAD_ATTR            gauss
  84: STORE_DEREF          gauss
  86: LOAD_FAST            self
  88: LOAD_ATTR            _mu
  98: LOAD_FAST            self
 100: LOAD_ATTR            _sigma
 110: SWAP                 
 112: STORE_DEREF          mu
 114: STORE_DEREF          sigma
 116: LOAD_CLOSURE         gauss
 118: LOAD_CLOSURE         mu
 120: LOAD_CLOSURE         sigma
 122: BUILD_TUPLE          
 124: LOAD_CONST           <code object <listcomp> at 0x0000024069465FB0, file "statistics.py", line 1196>
 126: MAKE_FUNCTION        closure
 128: LOAD_GLOBAL          NULL + range
 140: LOAD_FAST            n
 142: PRECALL              
 146: CALL                 
 156: GET_ITER             
 158: PRECALL              
 162: CALL                 
 172: RETURN_VALUE         
