# Disassembly for statistics.correlation
# From module file: statistics

## co_consts:
("Pearson's correlation coefficient\n\n    Return the Pearson's correlation coefficient for two inputs. Pearson's\n    correlation coefficient *r* takes values between -1 and +1. It measures the\n    strength and direction of the linear relationship, where +1 means very\n    strong, positive linear relationship, -1 very strong, negative linear\n    relationship, and 0 no linear relationship.\n\n    >>> x = [1, 2, 3, 4, 5, 6, 7, 8, 9]\n    >>> y = [9, 8, 7, 6, 5, 4, 3, 2, 1]\n    >>> correlation(x, x)\n    1.0\n    >>> correlation(x, y)\n    -1.0\n\n    ", 'correlation requires that both inputs have same number of data points', 2, 'correlation requires at least two data points', <code object <genexpr> at 0x0000024069CF0030, file "statistics.py", line 1015>, <code object <genexpr> at 0x0000024069CF0120, file "statistics.py", line 1016>, <code object <genexpr> at 0x0000024069CF0210, file "statistics.py", line 1017>, 'at least one of the inputs is constant')

## co_names:
('len', 'StatisticsError', 'fsum', 'zip', 'sqrt', 'ZeroDivisionError')

## bytecode:

   0: MAKE_CELL            d
   2: MAKE_CELL            xbar
   4: MAKE_CELL            ybar
   6: RESUME               
   8: LOAD_GLOBAL          NULL + len
  20: LOAD_FAST            x
  22: PRECALL              
  26: CALL                 
  36: STORE_FAST           n
  38: LOAD_GLOBAL          NULL + len
  50: LOAD_FAST            y
  52: PRECALL              
  56: CALL                 
  66: LOAD_FAST            n
  68: COMPARE_OP           !=
  74: POP_JUMP_FORWARD_IF_FALSE to 106
  76: LOAD_GLOBAL          NULL + StatisticsError
  88: LOAD_CONST           'correlation requires that both inputs have same number of data points'
  90: PRECALL              
  94: CALL                 
 104: RAISE_VARARGS        
 106: LOAD_FAST            n
 108: LOAD_CONST           2
 110: COMPARE_OP           <
 116: POP_JUMP_FORWARD_IF_FALSE to 148
 118: LOAD_GLOBAL          NULL + StatisticsError
 130: LOAD_CONST           'correlation requires at least two data points'
 132: PRECALL              
 136: CALL                 
 146: RAISE_VARARGS        
 148: LOAD_GLOBAL          NULL + fsum
 160: LOAD_FAST            x
 162: PRECALL              
 166: CALL                 
 176: LOAD_FAST            n
 178: BINARY_OP            /
 182: STORE_DEREF          xbar
 184: LOAD_GLOBAL          NULL + fsum
 196: LOAD_FAST            y
 198: PRECALL              
 202: CALL                 
 212: LOAD_FAST            n
 214: BINARY_OP            /
 218: STORE_DEREF          ybar
 220: LOAD_GLOBAL          NULL + fsum
 232: LOAD_CLOSURE         xbar
 234: LOAD_CLOSURE         ybar
 236: BUILD_TUPLE          
 238: LOAD_CONST           <code object <genexpr> at 0x0000024069CF0030, file "statistics.py", line 1015>
 240: MAKE_FUNCTION        closure
 242: LOAD_GLOBAL          NULL + zip
 254: LOAD_FAST            x
 256: LOAD_FAST            y
 258: PRECALL              
 262: CALL                 
 272: GET_ITER             
 274: PRECALL              
 278: CALL                 
 288: PRECALL              
 292: CALL                 
 302: STORE_FAST           sxy
 304: LOAD_GLOBAL          NULL + fsum
 316: LOAD_CLOSURE         d
 318: LOAD_CLOSURE         xbar
 320: BUILD_TUPLE          
 322: LOAD_CONST           <code object <genexpr> at 0x0000024069CF0120, file "statistics.py", line 1016>
 324: MAKE_FUNCTION        closure
 326: LOAD_FAST            x
 328: GET_ITER             
 330: PRECALL              
 334: CALL                 
 344: PRECALL              
 348: CALL                 
 358: STORE_FAST           sxx
 360: LOAD_GLOBAL          NULL + fsum
 372: LOAD_CLOSURE         d
 374: LOAD_CLOSURE         ybar
 376: BUILD_TUPLE          
 378: LOAD_CONST           <code object <genexpr> at 0x0000024069CF0210, file "statistics.py", line 1017>
 380: MAKE_FUNCTION        closure
 382: LOAD_FAST            y
 384: GET_ITER             
 386: PRECALL              
 390: CALL                 
 400: PRECALL              
 404: CALL                 
 414: STORE_FAST           syy
 416: NOP                  
 418: LOAD_FAST            sxy
 420: LOAD_GLOBAL          NULL + sqrt
 432: LOAD_FAST            sxx
 434: LOAD_FAST            syy
 436: BINARY_OP            *
 440: PRECALL              
 444: CALL                 
 454: BINARY_OP            /
 458: RETURN_VALUE         
 460: PUSH_EXC_INFO        
 462: LOAD_GLOBAL          ZeroDivisionError
 474: CHECK_EXC_MATCH      
 476: POP_JUMP_FORWARD_IF_FALSE to 510
 478: POP_TOP              
 480: LOAD_GLOBAL          NULL + StatisticsError
 492: LOAD_CONST           'at least one of the inputs is constant'
 494: PRECALL              
 498: CALL                 
 508: RAISE_VARARGS        
 510: RERAISE              
 512: COPY                 
 514: POP_EXCEPT           
 516: RERAISE              
