# Disassembly for statistics.NormalDist.overlap
# From module file: statistics

## co_consts:
('Compute the overlapping coefficient (OVL) between two normal distributions.\n\n        Measures the agreement between two normal probability distributions.\n        Returns a value between 0.0 and 1.0 giving the overlapping area in\n        the two underlying probability density functions.\n\n            >>> N1 = NormalDist(2.4, 1.6)\n            >>> N2 = NormalDist(3.2, 2.0)\n            >>> N1.overlap(N2)\n            0.8035050657330205\n        ', 'Expected another NormalDist instance', 'overlap() not defined when sigma is zero', 1.0, 2.0)

## co_names:
('isinstance', 'NormalDist', 'TypeError', '_sigma', '_mu', 'variance', 'StatisticsError', 'fabs', 'erf', '_SQRT2', 'sqrt', 'log', 'cdf')

## bytecode:

   0: RESUME               
   2: LOAD_GLOBAL          NULL + isinstance
  14: LOAD_FAST            other
  16: LOAD_GLOBAL          NormalDist
  28: PRECALL              
  32: CALL                 
  42: POP_JUMP_FORWARD_IF_TRUE to 74
  44: LOAD_GLOBAL          NULL + TypeError
  56: LOAD_CONST           'Expected another NormalDist instance'
  58: PRECALL              
  62: CALL                 
  72: RAISE_VARARGS        
  74: LOAD_FAST            self
  76: LOAD_FAST            other
  78: STORE_FAST           Y
  80: STORE_FAST           X
  82: LOAD_FAST            Y
  84: LOAD_ATTR            _sigma
  94: LOAD_FAST            Y
  96: LOAD_ATTR            _mu
 106: BUILD_TUPLE          
 108: LOAD_FAST            X
 110: LOAD_ATTR            _sigma
 120: LOAD_FAST            X
 122: LOAD_ATTR            _mu
 132: BUILD_TUPLE          
 134: COMPARE_OP           <
 140: POP_JUMP_FORWARD_IF_FALSE to 150
 142: LOAD_FAST            Y
 144: LOAD_FAST            X
 146: STORE_FAST           Y
 148: STORE_FAST           X
 150: LOAD_FAST            X
 152: LOAD_ATTR            variance
 162: LOAD_FAST            Y
 164: LOAD_ATTR            variance
 174: STORE_FAST           Y_var
 176: STORE_FAST           X_var
 178: LOAD_FAST            X_var
 180: POP_JUMP_FORWARD_IF_FALSE to 186
 182: LOAD_FAST            Y_var
 184: POP_JUMP_FORWARD_IF_TRUE to 216
 186: LOAD_GLOBAL          NULL + StatisticsError
 198: LOAD_CONST           'overlap() not defined when sigma is zero'
 200: PRECALL              
 204: CALL                 
 214: RAISE_VARARGS        
 216: LOAD_FAST            Y_var
 218: LOAD_FAST            X_var
 220: BINARY_OP            -
 224: STORE_FAST           dv
 226: LOAD_GLOBAL          NULL + fabs
 238: LOAD_FAST            Y
 240: LOAD_ATTR            _mu
 250: LOAD_FAST            X
 252: LOAD_ATTR            _mu
 262: BINARY_OP            -
 266: PRECALL              
 270: CALL                 
 280: STORE_FAST           dm
 282: LOAD_FAST            dv
 284: POP_JUMP_FORWARD_IF_TRUE to 360
 286: LOAD_CONST           1.0
 288: LOAD_GLOBAL          NULL + erf
 300: LOAD_FAST            dm
 302: LOAD_CONST           2.0
 304: LOAD_FAST            X
 306: LOAD_ATTR            _sigma
 316: BINARY_OP            *
 320: LOAD_GLOBAL          _SQRT2
 332: BINARY_OP            *
 336: BINARY_OP            /
 340: PRECALL              
 344: CALL                 
 354: BINARY_OP            -
 358: RETURN_VALUE         
 360: LOAD_FAST            X
 362: LOAD_ATTR            _mu
 372: LOAD_FAST            Y_var
 374: BINARY_OP            *
 378: LOAD_FAST            Y
 380: LOAD_ATTR            _mu
 390: LOAD_FAST            X_var
 392: BINARY_OP            *
 396: BINARY_OP            -
 400: STORE_FAST           a
 402: LOAD_FAST            X
 404: LOAD_ATTR            _sigma
 414: LOAD_FAST            Y
 416: LOAD_ATTR            _sigma
 426: BINARY_OP            *
 430: LOAD_GLOBAL          NULL + sqrt
 442: LOAD_FAST            dm
 444: LOAD_FAST            dm
 446: BINARY_OP            *
 450: LOAD_FAST            dv
 452: LOAD_GLOBAL          NULL + log
 464: LOAD_FAST            Y_var
 466: LOAD_FAST            X_var
 468: BINARY_OP            /
 472: PRECALL              
 476: CALL                 
 486: BINARY_OP            *
 490: BINARY_OP            +
 494: PRECALL              
 498: CALL                 
 508: BINARY_OP            *
 512: STORE_FAST           b
 514: LOAD_FAST            a
 516: LOAD_FAST            b
 518: BINARY_OP            +
 522: LOAD_FAST            dv
 524: BINARY_OP            /
 528: STORE_FAST           x1
 530: LOAD_FAST            a
 532: LOAD_FAST            b
 534: BINARY_OP            -
 538: LOAD_FAST            dv
 540: BINARY_OP            /
 544: STORE_FAST           x2
 546: LOAD_CONST           1.0
 548: LOAD_GLOBAL          NULL + fabs
 560: LOAD_FAST            Y
 562: LOAD_METHOD          cdf
 584: LOAD_FAST            x1
 586: PRECALL              
 590: CALL                 
 600: LOAD_FAST            X
 602: LOAD_METHOD          cdf
 624: LOAD_FAST            x1
 626: PRECALL              
 630: CALL                 
 640: BINARY_OP            -
 644: PRECALL              
 648: CALL                 
 658: LOAD_GLOBAL          NULL + fabs
 670: LOAD_FAST            Y
 672: LOAD_METHOD          cdf
 694: LOAD_FAST            x2
 696: PRECALL              
 700: CALL                 
 710: LOAD_FAST            X
 712: LOAD_METHOD          cdf
 734: LOAD_FAST            x2
 736: PRECALL              
 740: CALL                 
 750: BINARY_OP            -
 754: PRECALL              
 758: CALL                 
 768: BINARY_OP            +
 772: BINARY_OP            -
 776: RETURN_VALUE         
