# Disassembly for statistics.fmean
# From module file: statistics

## co_consts:
('Convert data to floats and compute the arithmetic mean.\n\n    This runs faster than the mean() function and it always returns a float.\n    If the input dataset is empty, it raises a StatisticsError.\n\n    >>> fmean([3.5, 4.0, 5.25])\n    4.25\n    ', 0, <code object count at 0x00000240693EAF30, file "statistics.py", line 450>, None, 'fmean requires at least one data point', 'data and weights must be the same length', 'sum of weights must be non-zero')

## co_names:
('len', 'TypeError', 'fsum', 'StatisticsError', 'list', 'map', 'mul')

## bytecode:

   0: MAKE_CELL            n
   2: RESUME               
   4: NOP                  
   6: LOAD_GLOBAL          NULL + len
  18: LOAD_FAST            data
  20: PRECALL              
  24: CALL                 
  34: STORE_DEREF          n
  36: JUMP_FORWARD         to 106
  38: PUSH_EXC_INFO        
  40: LOAD_GLOBAL          TypeError
  52: CHECK_EXC_MATCH      
  54: POP_JUMP_FORWARD_IF_FALSE to 98
  56: POP_TOP              
  58: LOAD_CONST           0
  60: STORE_DEREF          n
  62: LOAD_CLOSURE         n
  64: BUILD_TUPLE          
  66: LOAD_CONST           <code object count at 0x00000240693EAF30, file "statistics.py", line 450>
  68: MAKE_FUNCTION        closure
  70: STORE_FAST           count
  72: PUSH_NULL            
  74: LOAD_FAST            count
  76: LOAD_FAST            data
  78: PRECALL              
  82: CALL                 
  92: STORE_FAST           data
  94: POP_EXCEPT           
  96: JUMP_FORWARD         to 106
  98: RERAISE              
 100: COPY                 
 102: POP_EXCEPT           
 104: RERAISE              
 106: LOAD_FAST            weights
 108: POP_JUMP_FORWARD_IF_NOT_NONE to 184
 110: LOAD_GLOBAL          NULL + fsum
 122: LOAD_FAST            data
 124: PRECALL              
 128: CALL                 
 138: STORE_FAST           total
 140: LOAD_DEREF           n
 142: POP_JUMP_FORWARD_IF_TRUE to 174
 144: LOAD_GLOBAL          NULL + StatisticsError
 156: LOAD_CONST           'fmean requires at least one data point'
 158: PRECALL              
 162: CALL                 
 172: RAISE_VARARGS        
 174: LOAD_FAST            total
 176: LOAD_DEREF           n
 178: BINARY_OP            /
 182: RETURN_VALUE         
 184: NOP                  
 186: LOAD_GLOBAL          NULL + len
 198: LOAD_FAST            weights
 200: PRECALL              
 204: CALL                 
 214: STORE_FAST           num_weights
 216: JUMP_FORWARD         to 310
 218: PUSH_EXC_INFO        
 220: LOAD_GLOBAL          TypeError
 232: CHECK_EXC_MATCH      
 234: POP_JUMP_FORWARD_IF_FALSE to 302
 236: POP_TOP              
 238: LOAD_GLOBAL          NULL + list
 250: LOAD_FAST            weights
 252: PRECALL              
 256: CALL                 
 266: STORE_FAST           weights
 268: LOAD_GLOBAL          NULL + len
 280: LOAD_FAST            weights
 282: PRECALL              
 286: CALL                 
 296: STORE_FAST           num_weights
 298: POP_EXCEPT           
 300: JUMP_FORWARD         to 310
 302: RERAISE              
 304: COPY                 
 306: POP_EXCEPT           
 308: RERAISE              
 310: LOAD_GLOBAL          NULL + fsum
 322: LOAD_GLOBAL          NULL + map
 334: LOAD_GLOBAL          mul
 346: LOAD_FAST            data
 348: LOAD_FAST            weights
 350: PRECALL              
 354: CALL                 
 364: PRECALL              
 368: CALL                 
 378: STORE_FAST           num
 380: LOAD_DEREF           n
 382: LOAD_FAST            num_weights
 384: COMPARE_OP           !=
 390: POP_JUMP_FORWARD_IF_FALSE to 422
 392: LOAD_GLOBAL          NULL + StatisticsError
 404: LOAD_CONST           'data and weights must be the same length'
 406: PRECALL              
 410: CALL                 
 420: RAISE_VARARGS        
 422: LOAD_GLOBAL          NULL + fsum
 434: LOAD_FAST            weights
 436: PRECALL              
 440: CALL                 
 450: STORE_FAST           den
 452: LOAD_FAST            den
 454: POP_JUMP_FORWARD_IF_TRUE to 486
 456: LOAD_GLOBAL          NULL + StatisticsError
 468: LOAD_CONST           'sum of weights must be non-zero'
 470: PRECALL              
 474: CALL                 
 484: RAISE_VARARGS        
 486: LOAD_FAST            num
 488: LOAD_FAST            den
 490: BINARY_OP            /
 494: RETURN_VALUE         
