# Disassembly for statistics._ss
# From module file: statistics

## co_consts:
('Return the exact mean and sum of square deviations of sequence data.\n\n    Calculations are done in a single pass, allowing the input to be an iterator.\n\n    If given *c* is used the mean; otherwise, it is calculated from the data.\n    Use the *c* argument with care, as it can lead to garbage results.\n\n    ', None, <code object <genexpr> at 0x000002406945F3C0, file "statistics.py", line 218>, 0, 1, <code object <genexpr> at 0x00000240693EB730, file "statistics.py", line 239>, <code object <genexpr> at 0x00000240693EA730, file "statistics.py", line 240>)

## co_names:
('_sum', 'set', 'add', 'defaultdict', 'int', 'groupby', 'type', 'map', '_exact_ratio', 'Fraction', '_isfinite', 'sum', 'items', 'reduce', '_coerce')

## bytecode:

   0: MAKE_CELL            c
   2: MAKE_CELL            d
   4: RESUME               
   6: LOAD_DEREF           c
   8: POP_JUMP_FORWARD_IF_NONE to 86
  10: LOAD_GLOBAL          NULL + _sum
  22: LOAD_CLOSURE         c
  24: LOAD_CLOSURE         d
  26: BUILD_TUPLE          
  28: LOAD_CONST           <code object <genexpr> at 0x000002406945F3C0, file "statistics.py", line 218>
  30: MAKE_FUNCTION        closure
  32: LOAD_FAST            data
  34: GET_ITER             
  36: PRECALL              
  40: CALL                 
  50: PRECALL              
  54: CALL                 
  64: UNPACK_SEQUENCE      
  68: STORE_FAST           T
  70: STORE_FAST           ssd
  72: STORE_FAST           count
  74: LOAD_FAST            T
  76: LOAD_FAST            ssd
  78: LOAD_DEREF           c
  80: LOAD_FAST            count
  82: BUILD_TUPLE          
  84: RETURN_VALUE         
  86: LOAD_CONST           0
  88: STORE_FAST           count
  90: LOAD_GLOBAL          NULL + set
 102: PRECALL              
 106: CALL                 
 116: STORE_FAST           types
 118: LOAD_FAST            types
 120: LOAD_ATTR            add
 130: STORE_FAST           types_add
 132: LOAD_GLOBAL          NULL + defaultdict
 144: LOAD_GLOBAL          int
 156: PRECALL              
 160: CALL                 
 170: STORE_FAST           sx_partials
 172: LOAD_GLOBAL          NULL + defaultdict
 184: LOAD_GLOBAL          int
 196: PRECALL              
 200: CALL                 
 210: STORE_FAST           sxx_partials
 212: LOAD_GLOBAL          NULL + groupby
 224: LOAD_FAST            data
 226: LOAD_GLOBAL          type
 238: PRECALL              
 242: CALL                 
 252: GET_ITER             
 254: FOR_ITER             to 422
 256: UNPACK_SEQUENCE      
 260: STORE_FAST           typ
 262: STORE_FAST           values
 264: PUSH_NULL            
 266: LOAD_FAST            types_add
 268: LOAD_FAST            typ
 270: PRECALL              
 274: CALL                 
 284: POP_TOP              
 286: LOAD_GLOBAL          NULL + map
 298: LOAD_GLOBAL          _exact_ratio
 310: LOAD_FAST            values
 312: PRECALL              
 316: CALL                 
 326: GET_ITER             
 328: FOR_ITER             to 420
 330: UNPACK_SEQUENCE      
 334: STORE_FAST           n
 336: STORE_DEREF          d
 338: LOAD_FAST            count
 340: LOAD_CONST           1
 342: BINARY_OP            +=
 346: STORE_FAST           count
 348: LOAD_FAST            sx_partials
 350: LOAD_DEREF           d
 352: COPY                 
 354: COPY                 
 356: BINARY_SUBSCR        
 366: LOAD_FAST            n
 368: BINARY_OP            +=
 372: SWAP                 
 374: SWAP                 
 376: STORE_SUBSCR         
 380: LOAD_FAST            sxx_partials
 382: LOAD_DEREF           d
 384: COPY                 
 386: COPY                 
 388: BINARY_SUBSCR        
 398: LOAD_FAST            n
 400: LOAD_FAST            n
 402: BINARY_OP            *
 406: BINARY_OP            +=
 410: SWAP                 
 412: SWAP                 
 414: STORE_SUBSCR         
 418: JUMP_BACKWARD        to 328
 420: JUMP_BACKWARD        to 254
 422: LOAD_FAST            count
 424: POP_JUMP_FORWARD_IF_TRUE to 462
 426: LOAD_GLOBAL          NULL + Fraction
 438: LOAD_CONST           0
 440: PRECALL              
 444: CALL                 
 454: COPY                 
 456: STORE_FAST           ssd
 458: STORE_DEREF          c
 460: JUMP_FORWARD         to 736
 462: LOAD_CONST           None
 464: LOAD_FAST            sx_partials
 466: CONTAINS_OP          
 468: POP_JUMP_FORWARD_IF_FALSE to 526
 470: LOAD_FAST            sx_partials
 472: LOAD_CONST           None
 474: BINARY_SUBSCR        
 484: COPY                 
 486: STORE_FAST           ssd
 488: STORE_DEREF          c
 490: LOAD_GLOBAL          NULL + _isfinite
 502: LOAD_FAST            ssd
 504: PRECALL              
 508: CALL                 
 518: POP_JUMP_FORWARD_IF_FALSE to 524
 520: LOAD_ASSERTION_ERROR 
 522: RAISE_VARARGS        
 524: JUMP_FORWARD         to 736
 526: LOAD_GLOBAL          NULL + sum
 538: LOAD_CONST           <code object <genexpr> at 0x00000240693EB730, file "statistics.py", line 239>
 540: MAKE_FUNCTION        
 542: LOAD_FAST            sx_partials
 544: LOAD_METHOD          items
 566: PRECALL              
 570: CALL                 
 580: GET_ITER             
 582: PRECALL              
 586: CALL                 
 596: PRECALL              
 600: CALL                 
 610: STORE_FAST           sx
 612: LOAD_GLOBAL          NULL + sum
 624: LOAD_CONST           <code object <genexpr> at 0x00000240693EA730, file "statistics.py", line 240>
 626: MAKE_FUNCTION        
 628: LOAD_FAST            sxx_partials
 630: LOAD_METHOD          items
 652: PRECALL              
 656: CALL                 
 666: GET_ITER             
 668: PRECALL              
 672: CALL                 
 682: PRECALL              
 686: CALL                 
 696: STORE_FAST           sxx
 698: LOAD_FAST            count
 700: LOAD_FAST            sxx
 702: BINARY_OP            *
 706: LOAD_FAST            sx
 708: LOAD_FAST            sx
 710: BINARY_OP            *
 714: BINARY_OP            -
 718: LOAD_FAST            count
 720: BINARY_OP            /
 724: STORE_FAST           ssd
 726: LOAD_FAST            sx
 728: LOAD_FAST            count
 730: BINARY_OP            /
 734: STORE_DEREF          c
 736: LOAD_GLOBAL          NULL + reduce
 748: LOAD_GLOBAL          _coerce
 760: LOAD_FAST            types
 762: LOAD_GLOBAL          int
 774: PRECALL              
 778: CALL                 
 788: STORE_FAST           T
 790: LOAD_FAST            T
 792: LOAD_FAST            ssd
 794: LOAD_DEREF           c
 796: LOAD_FAST            count
 798: BUILD_TUPLE          
 800: RETURN_VALUE         
