# Disassembly for statistics.mode
# From module file: statistics

## co_consts:
('Return the most common data point from discrete or nominal data.\n\n    ``mode`` assumes discrete data, and returns a single value. This is the\n    standard treatment of the mode as commonly taught in schools:\n\n        >>> mode([1, 1, 2, 3, 3, 3, 3, 4])\n        3\n\n    This also works with nominal (non-numeric) data:\n\n        >>> mode(["red", "blue", "blue", "red", "green", "red", "red"])\n        \'red\'\n\n    If there are multiple modes with same frequency, return the first one\n    encountered:\n\n        >>> mode([\'red\', \'red\', \'green\', \'blue\', \'blue\'])\n        \'red\'\n\n    If *data* is empty, ``mode``, raises StatisticsError.\n\n    ', 1, 0, 'no mode for empty data', None)

## co_names:
('Counter', 'iter', 'most_common', 'IndexError', 'StatisticsError')

## bytecode:

   0: RESUME               
   2: LOAD_GLOBAL          NULL + Counter
  14: LOAD_GLOBAL          NULL + iter
  26: LOAD_FAST            data
  28: PRECALL              
  32: CALL                 
  42: PRECALL              
  46: CALL                 
  56: LOAD_METHOD          most_common
  78: LOAD_CONST           1
  80: PRECALL              
  84: CALL                 
  94: STORE_FAST           pairs
  96: NOP                  
  98: LOAD_FAST            pairs
 100: LOAD_CONST           0
 102: BINARY_SUBSCR        
 112: LOAD_CONST           0
 114: BINARY_SUBSCR        
 124: RETURN_VALUE         
 126: PUSH_EXC_INFO        
 128: LOAD_GLOBAL          IndexError
 140: CHECK_EXC_MATCH      
 142: POP_JUMP_FORWARD_IF_FALSE to 178
 144: POP_TOP              
 146: LOAD_GLOBAL          NULL + StatisticsError
 158: LOAD_CONST           'no mode for empty data'
 160: PRECALL              
 164: CALL                 
 174: LOAD_CONST           None
 176: RAISE_VARARGS        
 178: RERAISE              
 180: COPY                 
 182: POP_EXCEPT           
 184: RERAISE              
