# Disassembly for statistics.geometric_mean
# From module file: statistics

## co_consts:
('Convert data to floats and compute the geometric mean.\n\n    Raises a StatisticsError if the input dataset is empty,\n    if it contains a zero, or if it contains a negative value.\n\n    No special efforts are made to achieve exact results.\n    (However, this may change in the future.)\n\n    >>> round(geometric_mean([54, 24, 36]), 9)\n    36.0\n    ', 'geometric mean requires a non-empty dataset containing positive numbers', None)

## co_names:
('exp', 'fmean', 'map', 'log', 'ValueError', 'StatisticsError')

## bytecode:

   0: RESUME               
   2: NOP                  
   4: LOAD_GLOBAL          NULL + exp
  16: LOAD_GLOBAL          NULL + fmean
  28: LOAD_GLOBAL          NULL + map
  40: LOAD_GLOBAL          log
  52: LOAD_FAST            data
  54: PRECALL              
  58: CALL                 
  68: PRECALL              
  72: CALL                 
  82: PRECALL              
  86: CALL                 
  96: RETURN_VALUE         
  98: PUSH_EXC_INFO        
 100: LOAD_GLOBAL          ValueError
 112: CHECK_EXC_MATCH      
 114: POP_JUMP_FORWARD_IF_FALSE to 150
 116: POP_TOP              
 118: LOAD_GLOBAL          NULL + StatisticsError
 130: LOAD_CONST           'geometric mean requires a non-empty dataset containing positive numbers'
 132: PRECALL              
 136: CALL                 
 146: LOAD_CONST           None
 148: RAISE_VARARGS        
 150: RERAISE              
 152: COPY                 
 154: POP_EXCEPT           
 156: RERAISE              
