# Disassembly for statistics._mean_stdev
# From module file: statistics

## co_consts:
('In one pass, compute the mean and sample standard deviation as floats.', 2, 'stdev requires at least two data points', 1)

## co_names:
('_ss', 'StatisticsError', 'float', '_float_sqrt_of_frac', 'numerator', 'denominator', 'AttributeError')

## bytecode:

   0: RESUME               
   2: LOAD_GLOBAL          NULL + _ss
  14: LOAD_FAST            data
  16: PRECALL              
  20: CALL                 
  30: UNPACK_SEQUENCE      
  34: STORE_FAST           T
  36: STORE_FAST           ss
  38: STORE_FAST           xbar
  40: STORE_FAST           n
  42: LOAD_FAST            n
  44: LOAD_CONST           2
  46: COMPARE_OP           <
  52: POP_JUMP_FORWARD_IF_FALSE to 84
  54: LOAD_GLOBAL          NULL + StatisticsError
  66: LOAD_CONST           'stdev requires at least two data points'
  68: PRECALL              
  72: CALL                 
  82: RAISE_VARARGS        
  84: LOAD_FAST            ss
  86: LOAD_FAST            n
  88: LOAD_CONST           1
  90: BINARY_OP            -
  94: BINARY_OP            /
  98: STORE_FAST           mss
 100: NOP                  
 102: LOAD_GLOBAL          NULL + float
 114: LOAD_FAST            xbar
 116: PRECALL              
 120: CALL                 
 130: LOAD_GLOBAL          NULL + _float_sqrt_of_frac
 142: LOAD_FAST            mss
 144: LOAD_ATTR            numerator
 154: LOAD_FAST            mss
 156: LOAD_ATTR            denominator
 166: PRECALL              
 170: CALL                 
 180: BUILD_TUPLE          
 182: RETURN_VALUE         
 184: PUSH_EXC_INFO        
 186: LOAD_GLOBAL          AttributeError
 198: CHECK_EXC_MATCH      
 200: POP_JUMP_FORWARD_IF_FALSE to 300
 202: POP_TOP              
 204: LOAD_GLOBAL          NULL + float
 216: LOAD_FAST            xbar
 218: PRECALL              
 222: CALL                 
 232: LOAD_GLOBAL          NULL + float
 244: LOAD_FAST            xbar
 246: PRECALL              
 250: CALL                 
 260: LOAD_GLOBAL          NULL + float
 272: LOAD_FAST            ss
 274: PRECALL              
 278: CALL                 
 288: BINARY_OP            /
 292: BUILD_TUPLE          
 294: SWAP                 
 296: POP_EXCEPT           
 298: RETURN_VALUE         
 300: RERAISE              
 302: COPY                 
 304: POP_EXCEPT           
 306: RERAISE              
