# Disassembly for statistics._fail_neg
# From module file: statistics

## co_consts:
('Iterate over values, failing if any are less than zero.', 0, None)

## co_names:
('StatisticsError',)

## bytecode:

   0: RETURN_GENERATOR     
   2: POP_TOP              
   4: RESUME               
   6: LOAD_FAST            values
   8: GET_ITER             
  10: FOR_ITER             to 66
  12: STORE_FAST           x
  14: LOAD_FAST            x
  16: LOAD_CONST           0
  18: COMPARE_OP           <
  24: POP_JUMP_FORWARD_IF_FALSE to 56
  26: LOAD_GLOBAL          NULL + StatisticsError
  38: LOAD_FAST            errmsg
  40: PRECALL              
  44: CALL                 
  54: RAISE_VARARGS        
  56: LOAD_FAST            x
  58: YIELD_VALUE          
  60: RESUME               
  62: POP_TOP              
  64: JUMP_BACKWARD        to 10
  66: LOAD_CONST           None
  68: RETURN_VALUE         
