# Disassembly for statistics._isfinite
# From module file: statistics

## co_consts:
(None,)

## co_names:
('is_finite', 'AttributeError', 'math', 'isfinite')

## bytecode:

   0: RESUME               
   2: NOP                  
   4: LOAD_FAST            x
   6: LOAD_METHOD          is_finite
  28: PRECALL              
  32: CALL                 
  42: RETURN_VALUE         
  44: PUSH_EXC_INFO        
  46: LOAD_GLOBAL          AttributeError
  58: CHECK_EXC_MATCH      
  60: POP_JUMP_FORWARD_IF_FALSE to 108
  62: POP_TOP              
  64: LOAD_GLOBAL          NULL + math
  76: LOAD_ATTR            isfinite
  86: LOAD_FAST            x
  88: PRECALL              
  92: CALL                 
 102: SWAP                 
 104: POP_EXCEPT           
 106: RETURN_VALUE         
 108: RERAISE              
 110: COPY                 
 112: POP_EXCEPT           
 114: RERAISE              
