# Disassembly for statistics.NormalDist.__hash__
# From module file: statistics

## co_consts:
('NormalDist objects hash equal if their mu and sigma are both equal.',)

## co_names:
('hash', '_mu', '_sigma')

## bytecode:

   0: RESUME               
   2: LOAD_GLOBAL          NULL + hash
  14: LOAD_FAST            self
  16: LOAD_ATTR            _mu
  26: LOAD_FAST            self
  28: LOAD_ATTR            _sigma
  38: BUILD_TUPLE          
  40: PRECALL              
  44: CALL                 
  54: RETURN_VALUE         
