# Disassembly for opcode
# From module file: opcode

## co_consts:
('\nopcode module - potentially shared between dis and other modules which\noperate on bytecodes (e.g. peephole optimizers).\n', ('cmp_op', 'hasconst', 'hasname', 'hasjrel', 'hasjabs', 'haslocal', 'hascompare', 'hasfree', 'opname', 'opmap', 'HAVE_ARGUMENT', 'EXTENDED_ARG', 'hasnargs'), 0, ('stack_effect',), 'stack_effect', ('<', '<=', '==', '!=', '>', '>='), <code object <listcomp> at 0x0000024069467130, file "opcode.py", line 36>, 256, <code object def_op at 0x000002406945DD40, file "opcode.py", line 38>, <code object name_op at 0x000002406941A0D0, file "opcode.py", line 42>, <code object jrel_op at 0x000002406941A1F0, file "opcode.py", line 46>, <code object jabs_op at 0x000002406941AC10, file "opcode.py", line 50>, 'CACHE', 'POP_TOP', 1, 'PUSH_NULL', 2, 'NOP', 9, 'UNARY_POSITIVE', 10, 'UNARY_NEGATIVE', 11, 'UNARY_NOT', 12, 'UNARY_INVERT', 15, 'BINARY_SUBSCR', 25, 'GET_LEN', 30, 'MATCH_MAPPING', 31, 'MATCH_SEQUENCE', 32, 'MATCH_KEYS', 33, 'PUSH_EXC_INFO', 35, 'CHECK_EXC_MATCH', 36, 'CHECK_EG_MATCH', 37, 'WITH_EXCEPT_START', 49, 'GET_AITER', 50, 'GET_ANEXT', 51, 'BEFORE_ASYNC_WITH', 52, 'BEFORE_WITH', 53, 'END_ASYNC_FOR', 54, 'STORE_SUBSCR', 60, 'DELETE_SUBSCR', 61, 'GET_ITER', 68, 'GET_YIELD_FROM_ITER', 69, 'PRINT_EXPR', 70, 'LOAD_BUILD_CLASS', 71, 'LOAD_ASSERTION_ERROR', 74, 'RETURN_GENERATOR', 75, 'LIST_TO_TUPLE', 82, 'RETURN_VALUE', 83, 'IMPORT_STAR', 84, 'SETUP_ANNOTATIONS', 85, 'YIELD_VALUE', 86, 'ASYNC_GEN_WRAP', 87, 'PREP_RERAISE_STAR', 88, 'POP_EXCEPT', 89, 90, 'STORE_NAME', 'DELETE_NAME', 91, 'UNPACK_SEQUENCE', 92, 'FOR_ITER', 93, 'UNPACK_EX', 94, 'STORE_ATTR', 95, 'DELETE_ATTR', 96, 'STORE_GLOBAL', 97, 'DELETE_GLOBAL', 98, 'SWAP', 99, 'LOAD_CONST', 100, 'LOAD_NAME', 101, 'BUILD_TUPLE', 102, 'BUILD_LIST', 103, 'BUILD_SET', 104, 'BUILD_MAP', 105, 'LOAD_ATTR', 106, 'COMPARE_OP', 107, 'IMPORT_NAME', 108, 'IMPORT_FROM', 109, 'JUMP_FORWARD', 110, 'JUMP_IF_FALSE_OR_POP', 111, 'JUMP_IF_TRUE_OR_POP', 112, 'POP_JUMP_FORWARD_IF_FALSE', 114, 'POP_JUMP_FORWARD_IF_TRUE', 115, 'LOAD_GLOBAL', 116, 'IS_OP', 117, 'CONTAINS_OP', 118, 'RERAISE', 119, 'COPY', 120, 'BINARY_OP', 122, 'SEND', 123, 'LOAD_FAST', 124, 'STORE_FAST', 125, 'DELETE_FAST', 126, 'POP_JUMP_FORWARD_IF_NOT_NONE', 128, 'POP_JUMP_FORWARD_IF_NONE', 129, 'RAISE_VARARGS', 130, 'GET_AWAITABLE', 131, 'MAKE_FUNCTION', 132, 'BUILD_SLICE', 133, 'JUMP_BACKWARD_NO_INTERRUPT', 134, 'MAKE_CELL', 135, 'LOAD_CLOSURE', 136, 'LOAD_DEREF', 137, 'STORE_DEREF', 138, 'DELETE_DEREF', 139, 'JUMP_BACKWARD', 140, 'CALL_FUNCTION_EX', 142, 'EXTENDED_ARG', 144, 'LIST_APPEND', 145, 'SET_ADD', 146, 'MAP_ADD', 147, 'LOAD_CLASSDEREF', 148, 'COPY_FREE_VARS', 149, 'RESUME', 151, 'MATCH_CLASS', 152, 'FORMAT_VALUE', 155, 'BUILD_CONST_KEY_MAP', 156, 'BUILD_STRING', 157, 'LOAD_METHOD', 160, 'LIST_EXTEND', 162, 'SET_UPDATE', 163, 'DICT_MERGE', 164, 'DICT_UPDATE', 165, 'PRECALL', 166, 'CALL', 171, 'KW_NAMES', 172, 'POP_JUMP_BACKWARD_IF_NOT_NONE', 173, 'POP_JUMP_BACKWARD_IF_NONE', 174, 'POP_JUMP_BACKWARD_IF_FALSE', 175, 'POP_JUMP_BACKWARD_IF_TRUE', 176, (('NB_ADD', '+'), ('NB_AND', '&'), ('NB_FLOOR_DIVIDE', '//'), ('NB_LSHIFT', '<<'), ('NB_MATRIX_MULTIPLY', '@'), ('NB_MULTIPLY', '*'), ('NB_REMAINDER', '%'), ('NB_OR', '|'), ('NB_POWER', '**'), ('NB_RSHIFT', '>>'), ('NB_SUBTRACT', '-'), ('NB_TRUE_DIVIDE', '/'), ('NB_XOR', '^'), ('NB_INPLACE_ADD', '+='), ('NB_INPLACE_AND', '&='), ('NB_INPLACE_FLOOR_DIVIDE', '//='), ('NB_INPLACE_LSHIFT', '<<='), ('NB_INPLACE_MATRIX_MULTIPLY', '@='), ('NB_INPLACE_MULTIPLY', '*='), ('NB_INPLACE_REMAINDER', '%='), ('NB_INPLACE_OR', '|='), ('NB_INPLACE_POWER', '**='), ('NB_INPLACE_RSHIFT', '>>='), ('NB_INPLACE_SUBTRACT', '-='), ('NB_INPLACE_TRUE_DIVIDE', '/='), ('NB_INPLACE_XOR', '^=')), ('BINARY_OP_ADAPTIVE', 'BINARY_OP_ADD_FLOAT', 'BINARY_OP_ADD_INT', 'BINARY_OP_ADD_UNICODE', 'BINARY_OP_INPLACE_ADD_UNICODE', 'BINARY_OP_MULTIPLY_FLOAT', 'BINARY_OP_MULTIPLY_INT', 'BINARY_OP_SUBTRACT_FLOAT', 'BINARY_OP_SUBTRACT_INT'), ('BINARY_SUBSCR_ADAPTIVE', 'BINARY_SUBSCR_DICT', 'BINARY_SUBSCR_GETITEM', 'BINARY_SUBSCR_LIST_INT', 'BINARY_SUBSCR_TUPLE_INT'), ('CALL_ADAPTIVE', 'CALL_PY_EXACT_ARGS', 'CALL_PY_WITH_DEFAULTS'), ('COMPARE_OP_ADAPTIVE', 'COMPARE_OP_FLOAT_JUMP', 'COMPARE_OP_INT_JUMP', 'COMPARE_OP_STR_JUMP'), 'EXTENDED_ARG_QUICK', 'JUMP_BACKWARD_QUICK', ('LOAD_ATTR_ADAPTIVE', 'LOAD_ATTR_INSTANCE_VALUE', 'LOAD_ATTR_MODULE', 'LOAD_ATTR_SLOT', 'LOAD_ATTR_WITH_HINT'), 'LOAD_CONST__LOAD_FAST', 'LOAD_FAST__LOAD_CONST', 'LOAD_FAST__LOAD_FAST', ('LOAD_GLOBAL_ADAPTIVE', 'LOAD_GLOBAL_BUILTIN', 'LOAD_GLOBAL_MODULE'), ('LOAD_METHOD_ADAPTIVE', 'LOAD_METHOD_CLASS', 'LOAD_METHOD_MODULE', 'LOAD_METHOD_NO_DICT', 'LOAD_METHOD_WITH_DICT', 'LOAD_METHOD_WITH_VALUES'), ('PRECALL_ADAPTIVE', 'PRECALL_BOUND_METHOD', 'PRECALL_BUILTIN_CLASS', 'PRECALL_BUILTIN_FAST_WITH_KEYWORDS', 'PRECALL_METHOD_DESCRIPTOR_FAST_WITH_KEYWORDS', 'PRECALL_NO_KW_BUILTIN_FAST', 'PRECALL_NO_KW_BUILTIN_O', 'PRECALL_NO_KW_ISINSTANCE', 'PRECALL_NO_KW_LEN', 'PRECALL_NO_KW_LIST_APPEND', 'PRECALL_NO_KW_METHOD_DESCRIPTOR_FAST', 'PRECALL_NO_KW_METHOD_DESCRIPTOR_NOARGS', 'PRECALL_NO_KW_METHOD_DESCRIPTOR_O', 'PRECALL_NO_KW_STR_1', 'PRECALL_NO_KW_TUPLE_1', 'PRECALL_NO_KW_TYPE_1', 'PRECALL_PYFUNC'), 'RESUME_QUICK', ('STORE_ATTR_ADAPTIVE', 'STORE_ATTR_INSTANCE_VALUE', 'STORE_ATTR_SLOT', 'STORE_ATTR_WITH_HINT'), 'STORE_FAST__LOAD_FAST', 'STORE_FAST__STORE_FAST', ('STORE_SUBSCR_ADAPTIVE', 'STORE_SUBSCR_DICT', 'STORE_SUBSCR_LIST_INT'), ('UNPACK_SEQUENCE_ADAPTIVE', 'UNPACK_SEQUENCE_LIST', 'UNPACK_SEQUENCE_TUPLE', 'UNPACK_SEQUENCE_TWO_TUPLE'), <code object <listcomp> at 0x0000024069467BB0, file "opcode.py", line 341>, ('success', 'failure', 'hit', 'deferred', 'miss', 'deopt'), ('counter', 'index', 'module_keys_version', 'builtin_keys_version'), 'counter', ('counter', 'mask'), ('counter', 'type_version', 'func_version'), ('counter', 'version', 'index'), 4, ('counter', 'type_version', 'dict_offset', 'keys_version', 'descr'), ('counter', 'func_version', 'min_args'), ('LOAD_GLOBAL', 'BINARY_OP', 'UNPACK_SEQUENCE', 'COMPARE_OP', 'BINARY_SUBSCR', 'LOAD_ATTR', 'STORE_ATTR', 'LOAD_METHOD', 'CALL', 'PRECALL', 'STORE_SUBSCR'), <code object <listcomp> at 0x00000240691F23A0, file "opcode.py", line 405>, None)

## co_names:
('__doc__', '__all__', '_opcode', 'stack_effect', 'append', 'ImportError', 'cmp_op', 'hasconst', 'hasname', 'hasjrel', 'hasjabs', 'haslocal', 'hascompare', 'hasfree', 'hasnargs', 'opmap', 'range', 'opname', 'def_op', 'name_op', 'jrel_op', 'jabs_op', 'HAVE_ARGUMENT', 'EXTENDED_ARG', '_nb_ops', '_specializations', 'values', '_specialized_instructions', '_specialization_stats', '_cache_format', '_inline_cache_entries')

## bytecode:

   0: RESUME               
   2: LOAD_CONST           '\nopcode module - potentially shared between dis and other modules which\noperate on bytecodes (e.g. peephole optimizers).\n'
   4: STORE_NAME           __doc__
   6: BUILD_LIST           
   8: LOAD_CONST           ('cmp_op', 'hasconst', 'hasname', 'hasjrel', 'hasjabs', 'haslocal', 'hascompare', 'hasfree', 'opname', 'opmap', 'HAVE_ARGUMENT', 'EXTENDED_ARG', 'hasnargs')
  10: LIST_EXTEND          
  12: STORE_NAME           __all__
  14: NOP                  
  16: LOAD_CONST           0
  18: LOAD_CONST           ('stack_effect',)
  20: IMPORT_NAME          _opcode
  22: IMPORT_FROM          stack_effect
  24: STORE_NAME           stack_effect
  26: POP_TOP              
  28: LOAD_NAME            __all__
  30: LOAD_METHOD          append
  52: LOAD_CONST           'stack_effect'
  54: PRECALL              
  58: CALL                 
  68: POP_TOP              
  70: JUMP_FORWARD         to 94
  72: PUSH_EXC_INFO        
  74: LOAD_NAME            ImportError
  76: CHECK_EXC_MATCH      
  78: POP_JUMP_FORWARD_IF_FALSE to 86
  80: POP_TOP              
  82: POP_EXCEPT           
  84: JUMP_FORWARD         to 94
  86: RERAISE              
  88: COPY                 
  90: POP_EXCEPT           
  92: RERAISE              
  94: LOAD_CONST           ('<', '<=', '==', '!=', '>', '>=')
  96: STORE_NAME           cmp_op
  98: BUILD_LIST           
 100: STORE_NAME           hasconst
 102: BUILD_LIST           
 104: STORE_NAME           hasname
 106: BUILD_LIST           
 108: STORE_NAME           hasjrel
 110: BUILD_LIST           
 112: STORE_NAME           hasjabs
 114: BUILD_LIST           
 116: STORE_NAME           haslocal
 118: BUILD_LIST           
 120: STORE_NAME           hascompare
 122: BUILD_LIST           
 124: STORE_NAME           hasfree
 126: BUILD_LIST           
 128: STORE_NAME           hasnargs
 130: BUILD_MAP            
 132: STORE_NAME           opmap
 134: LOAD_CONST           <code object <listcomp> at 0x0000024069467130, file "opcode.py", line 36>
 136: MAKE_FUNCTION        
 138: PUSH_NULL            
 140: LOAD_NAME            range
 142: LOAD_CONST           256
 144: PRECALL              
 148: CALL                 
 158: GET_ITER             
 160: PRECALL              
 164: CALL                 
 174: STORE_NAME           opname
 176: LOAD_CONST           <code object def_op at 0x000002406945DD40, file "opcode.py", line 38>
 178: MAKE_FUNCTION        
 180: STORE_NAME           def_op
 182: LOAD_CONST           <code object name_op at 0x000002406941A0D0, file "opcode.py", line 42>
 184: MAKE_FUNCTION        
 186: STORE_NAME           name_op
 188: LOAD_CONST           <code object jrel_op at 0x000002406941A1F0, file "opcode.py", line 46>
 190: MAKE_FUNCTION        
 192: STORE_NAME           jrel_op
 194: LOAD_CONST           <code object jabs_op at 0x000002406941AC10, file "opcode.py", line 50>
 196: MAKE_FUNCTION        
 198: STORE_NAME           jabs_op
 200: PUSH_NULL            
 202: LOAD_NAME            def_op
 204: LOAD_CONST           'CACHE'
 206: LOAD_CONST           0
 208: PRECALL              
 212: CALL                 
 222: POP_TOP              
 224: PUSH_NULL            
 226: LOAD_NAME            def_op
 228: LOAD_CONST           'POP_TOP'
 230: LOAD_CONST           1
 232: PRECALL              
 236: CALL                 
 246: POP_TOP              
 248: PUSH_NULL            
 250: LOAD_NAME            def_op
 252: LOAD_CONST           'PUSH_NULL'
 254: LOAD_CONST           2
 256: PRECALL              
 260: CALL                 
 270: POP_TOP              
 272: PUSH_NULL            
 274: LOAD_NAME            def_op
 276: LOAD_CONST           'NOP'
 278: LOAD_CONST           9
 280: PRECALL              
 284: CALL                 
 294: POP_TOP              
 296: PUSH_NULL            
 298: LOAD_NAME            def_op
 300: LOAD_CONST           'UNARY_POSITIVE'
 302: LOAD_CONST           10
 304: PRECALL              
 308: CALL                 
 318: POP_TOP              
 320: PUSH_NULL            
 322: LOAD_NAME            def_op
 324: LOAD_CONST           'UNARY_NEGATIVE'
 326: LOAD_CONST           11
 328: PRECALL              
 332: CALL                 
 342: POP_TOP              
 344: PUSH_NULL            
 346: LOAD_NAME            def_op
 348: LOAD_CONST           'UNARY_NOT'
 350: LOAD_CONST           12
 352: PRECALL              
 356: CALL                 
 366: POP_TOP              
 368: PUSH_NULL            
 370: LOAD_NAME            def_op
 372: LOAD_CONST           'UNARY_INVERT'
 374: LOAD_CONST           15
 376: PRECALL              
 380: CALL                 
 390: POP_TOP              
 392: PUSH_NULL            
 394: LOAD_NAME            def_op
 396: LOAD_CONST           'BINARY_SUBSCR'
 398: LOAD_CONST           25
 400: PRECALL              
 404: CALL                 
 414: POP_TOP              
 416: PUSH_NULL            
 418: LOAD_NAME            def_op
 420: LOAD_CONST           'GET_LEN'
 422: LOAD_CONST           30
 424: PRECALL              
 428: CALL                 
 438: POP_TOP              
 440: PUSH_NULL            
 442: LOAD_NAME            def_op
 444: LOAD_CONST           'MATCH_MAPPING'
 446: LOAD_CONST           31
 448: PRECALL              
 452: CALL                 
 462: POP_TOP              
 464: PUSH_NULL            
 466: LOAD_NAME            def_op
 468: LOAD_CONST           'MATCH_SEQUENCE'
 470: LOAD_CONST           32
 472: PRECALL              
 476: CALL                 
 486: POP_TOP              
 488: PUSH_NULL            
 490: LOAD_NAME            def_op
 492: LOAD_CONST           'MATCH_KEYS'
 494: LOAD_CONST           33
 496: PRECALL              
 500: CALL                 
 510: POP_TOP              
 512: PUSH_NULL            
 514: LOAD_NAME            def_op
 516: LOAD_CONST           'PUSH_EXC_INFO'
 518: LOAD_CONST           35
 520: PRECALL              
 524: CALL                 
 534: POP_TOP              
 536: PUSH_NULL            
 538: LOAD_NAME            def_op
 540: LOAD_CONST           'CHECK_EXC_MATCH'
 542: LOAD_CONST           36
 544: PRECALL              
 548: CALL                 
 558: POP_TOP              
 560: PUSH_NULL            
 562: LOAD_NAME            def_op
 564: LOAD_CONST           'CHECK_EG_MATCH'
 566: LOAD_CONST           37
 568: PRECALL              
 572: CALL                 
 582: POP_TOP              
 584: PUSH_NULL            
 586: LOAD_NAME            def_op
 588: LOAD_CONST           'WITH_EXCEPT_START'
 590: LOAD_CONST           49
 592: PRECALL              
 596: CALL                 
 606: POP_TOP              
 608: PUSH_NULL            
 610: LOAD_NAME            def_op
 612: LOAD_CONST           'GET_AITER'
 614: LOAD_CONST           50
 616: PRECALL              
 620: CALL                 
 630: POP_TOP              
 632: PUSH_NULL            
 634: LOAD_NAME            def_op
 636: LOAD_CONST           'GET_ANEXT'
 638: LOAD_CONST           51
 640: PRECALL              
 644: CALL                 
 654: POP_TOP              
 656: PUSH_NULL            
 658: LOAD_NAME            def_op
 660: LOAD_CONST           'BEFORE_ASYNC_WITH'
 662: LOAD_CONST           52
 664: PRECALL              
 668: CALL                 
 678: POP_TOP              
 680: PUSH_NULL            
 682: LOAD_NAME            def_op
 684: LOAD_CONST           'BEFORE_WITH'
 686: LOAD_CONST           53
 688: PRECALL              
 692: CALL                 
 702: POP_TOP              
 704: PUSH_NULL            
 706: LOAD_NAME            def_op
 708: LOAD_CONST           'END_ASYNC_FOR'
 710: LOAD_CONST           54
 712: PRECALL              
 716: CALL                 
 726: POP_TOP              
 728: PUSH_NULL            
 730: LOAD_NAME            def_op
 732: LOAD_CONST           'STORE_SUBSCR'
 734: LOAD_CONST           60
 736: PRECALL              
 740: CALL                 
 750: POP_TOP              
 752: PUSH_NULL            
 754: LOAD_NAME            def_op
 756: LOAD_CONST           'DELETE_SUBSCR'
 758: LOAD_CONST           61
 760: PRECALL              
 764: CALL                 
 774: POP_TOP              
 776: PUSH_NULL            
 778: LOAD_NAME            def_op
 780: LOAD_CONST           'GET_ITER'
 782: LOAD_CONST           68
 784: PRECALL              
 788: CALL                 
 798: POP_TOP              
 800: PUSH_NULL            
 802: LOAD_NAME            def_op
 804: LOAD_CONST           'GET_YIELD_FROM_ITER'
 806: LOAD_CONST           69
 808: PRECALL              
 812: CALL                 
 822: POP_TOP              
 824: PUSH_NULL            
 826: LOAD_NAME            def_op
 828: LOAD_CONST           'PRINT_EXPR'
 830: LOAD_CONST           70
 832: PRECALL              
 836: CALL                 
 846: POP_TOP              
 848: PUSH_NULL            
 850: LOAD_NAME            def_op
 852: LOAD_CONST           'LOAD_BUILD_CLASS'
 854: LOAD_CONST           71
 856: PRECALL              
 860: CALL                 
 870: POP_TOP              
 872: PUSH_NULL            
 874: LOAD_NAME            def_op
 876: LOAD_CONST           'LOAD_ASSERTION_ERROR'
 878: LOAD_CONST           74
 880: PRECALL              
 884: CALL                 
 894: POP_TOP              
 896: PUSH_NULL            
 898: LOAD_NAME            def_op
 900: LOAD_CONST           'RETURN_GENERATOR'
 902: LOAD_CONST           75
 904: PRECALL              
 908: CALL                 
 918: POP_TOP              
 920: PUSH_NULL            
 922: LOAD_NAME            def_op
 924: LOAD_CONST           'LIST_TO_TUPLE'
 926: LOAD_CONST           82
 928: PRECALL              
 932: CALL                 
 942: POP_TOP              
 944: PUSH_NULL            
 946: LOAD_NAME            def_op
 948: LOAD_CONST           'RETURN_VALUE'
 950: LOAD_CONST           83
 952: PRECALL              
 956: CALL                 
 966: POP_TOP              
 968: PUSH_NULL            
 970: LOAD_NAME            def_op
 972: LOAD_CONST           'IMPORT_STAR'
 974: LOAD_CONST           84
 976: PRECALL              
 980: CALL                 
 990: POP_TOP              
 992: PUSH_NULL            
 994: LOAD_NAME            def_op
 996: LOAD_CONST           'SETUP_ANNOTATIONS'
 998: LOAD_CONST           85
1000: PRECALL              
1004: CALL                 
1014: POP_TOP              
1016: PUSH_NULL            
1018: LOAD_NAME            def_op
1020: LOAD_CONST           'YIELD_VALUE'
1022: LOAD_CONST           86
1024: PRECALL              
1028: CALL                 
1038: POP_TOP              
1040: PUSH_NULL            
1042: LOAD_NAME            def_op
1044: LOAD_CONST           'ASYNC_GEN_WRAP'
1046: LOAD_CONST           87
1048: PRECALL              
1052: CALL                 
1062: POP_TOP              
1064: PUSH_NULL            
1066: LOAD_NAME            def_op
1068: LOAD_CONST           'PREP_RERAISE_STAR'
1070: LOAD_CONST           88
1072: PRECALL              
1076: CALL                 
1086: POP_TOP              
1088: PUSH_NULL            
1090: LOAD_NAME            def_op
1092: LOAD_CONST           'POP_EXCEPT'
1094: LOAD_CONST           89
1096: PRECALL              
1100: CALL                 
1110: POP_TOP              
1112: LOAD_CONST           90
1114: STORE_NAME           HAVE_ARGUMENT
1116: PUSH_NULL            
1118: LOAD_NAME            name_op
1120: LOAD_CONST           'STORE_NAME'
1122: LOAD_CONST           90
1124: PRECALL              
1128: CALL                 
1138: POP_TOP              
1140: PUSH_NULL            
1142: LOAD_NAME            name_op
1144: LOAD_CONST           'DELETE_NAME'
1146: LOAD_CONST           91
1148: PRECALL              
1152: CALL                 
1162: POP_TOP              
1164: PUSH_NULL            
1166: LOAD_NAME            def_op
1168: LOAD_CONST           'UNPACK_SEQUENCE'
1170: LOAD_CONST           92
1172: PRECALL              
1176: CALL                 
1186: POP_TOP              
1188: PUSH_NULL            
1190: LOAD_NAME            jrel_op
1192: LOAD_CONST           'FOR_ITER'
1194: LOAD_CONST           93
1196: PRECALL              
1200: CALL                 
1210: POP_TOP              
1212: PUSH_NULL            
1214: LOAD_NAME            def_op
1216: LOAD_CONST           'UNPACK_EX'
1218: LOAD_CONST           94
1220: PRECALL              
1224: CALL                 
1234: POP_TOP              
1236: PUSH_NULL            
1238: LOAD_NAME            name_op
1240: LOAD_CONST           'STORE_ATTR'
1242: LOAD_CONST           95
1244: PRECALL              
1248: CALL                 
1258: POP_TOP              
1260: PUSH_NULL            
1262: LOAD_NAME            name_op
1264: LOAD_CONST           'DELETE_ATTR'
1266: LOAD_CONST           96
1268: PRECALL              
1272: CALL                 
1282: POP_TOP              
1284: PUSH_NULL            
1286: LOAD_NAME            name_op
1288: LOAD_CONST           'STORE_GLOBAL'
1290: LOAD_CONST           97
1292: PRECALL              
1296: CALL                 
1306: POP_TOP              
1308: PUSH_NULL            
1310: LOAD_NAME            name_op
1312: LOAD_CONST           'DELETE_GLOBAL'
1314: LOAD_CONST           98
1316: PRECALL              
1320: CALL                 
1330: POP_TOP              
1332: PUSH_NULL            
1334: LOAD_NAME            def_op
1336: LOAD_CONST           'SWAP'
1338: LOAD_CONST           99
1340: PRECALL              
1344: CALL                 
1354: POP_TOP              
1356: PUSH_NULL            
1358: LOAD_NAME            def_op
1360: LOAD_CONST           'LOAD_CONST'
1362: LOAD_CONST           100
1364: PRECALL              
1368: CALL                 
1378: POP_TOP              
1380: LOAD_NAME            hasconst
1382: LOAD_METHOD          append
1404: LOAD_CONST           100
1406: PRECALL              
1410: CALL                 
1420: POP_TOP              
1422: PUSH_NULL            
1424: LOAD_NAME            name_op
1426: LOAD_CONST           'LOAD_NAME'
1428: LOAD_CONST           101
1430: PRECALL              
1434: CALL                 
1444: POP_TOP              
1446: PUSH_NULL            
1448: LOAD_NAME            def_op
1450: LOAD_CONST           'BUILD_TUPLE'
1452: LOAD_CONST           102
1454: PRECALL              
1458: CALL                 
1468: POP_TOP              
1470: PUSH_NULL            
1472: LOAD_NAME            def_op
1474: LOAD_CONST           'BUILD_LIST'
1476: LOAD_CONST           103
1478: PRECALL              
1482: CALL                 
1492: POP_TOP              
1494: PUSH_NULL            
1496: LOAD_NAME            def_op
1498: LOAD_CONST           'BUILD_SET'
1500: LOAD_CONST           104
1502: PRECALL              
1506: CALL                 
1516: POP_TOP              
1518: PUSH_NULL            
1520: LOAD_NAME            def_op
1522: LOAD_CONST           'BUILD_MAP'
1524: LOAD_CONST           105
1526: PRECALL              
1530: CALL                 
1540: POP_TOP              
1542: PUSH_NULL            
1544: LOAD_NAME            name_op
1546: LOAD_CONST           'LOAD_ATTR'
1548: LOAD_CONST           106
1550: PRECALL              
1554: CALL                 
1564: POP_TOP              
1566: PUSH_NULL            
1568: LOAD_NAME            def_op
1570: LOAD_CONST           'COMPARE_OP'
1572: LOAD_CONST           107
1574: PRECALL              
1578: CALL                 
1588: POP_TOP              
1590: LOAD_NAME            hascompare
1592: LOAD_METHOD          append
1614: LOAD_CONST           107
1616: PRECALL              
1620: CALL                 
1630: POP_TOP              
1632: PUSH_NULL            
1634: LOAD_NAME            name_op
1636: LOAD_CONST           'IMPORT_NAME'
1638: LOAD_CONST           108
1640: PRECALL              
1644: CALL                 
1654: POP_TOP              
1656: PUSH_NULL            
1658: LOAD_NAME            name_op
1660: LOAD_CONST           'IMPORT_FROM'
1662: LOAD_CONST           109
1664: PRECALL              
1668: CALL                 
1678: POP_TOP              
1680: PUSH_NULL            
1682: LOAD_NAME            jrel_op
1684: LOAD_CONST           'JUMP_FORWARD'
1686: LOAD_CONST           110
1688: PRECALL              
1692: CALL                 
1702: POP_TOP              
1704: PUSH_NULL            
1706: LOAD_NAME            jrel_op
1708: LOAD_CONST           'JUMP_IF_FALSE_OR_POP'
1710: LOAD_CONST           111
1712: PRECALL              
1716: CALL                 
1726: POP_TOP              
1728: PUSH_NULL            
1730: LOAD_NAME            jrel_op
1732: LOAD_CONST           'JUMP_IF_TRUE_OR_POP'
1734: LOAD_CONST           112
1736: PRECALL              
1740: CALL                 
1750: POP_TOP              
1752: PUSH_NULL            
1754: LOAD_NAME            jrel_op
1756: LOAD_CONST           'POP_JUMP_FORWARD_IF_FALSE'
1758: LOAD_CONST           114
1760: PRECALL              
1764: CALL                 
1774: POP_TOP              
1776: PUSH_NULL            
1778: LOAD_NAME            jrel_op
1780: LOAD_CONST           'POP_JUMP_FORWARD_IF_TRUE'
1782: LOAD_CONST           115
1784: PRECALL              
1788: CALL                 
1798: POP_TOP              
1800: PUSH_NULL            
1802: LOAD_NAME            name_op
1804: LOAD_CONST           'LOAD_GLOBAL'
1806: LOAD_CONST           116
1808: PRECALL              
1812: CALL                 
1822: POP_TOP              
1824: PUSH_NULL            
1826: LOAD_NAME            def_op
1828: LOAD_CONST           'IS_OP'
1830: LOAD_CONST           117
1832: PRECALL              
1836: CALL                 
1846: POP_TOP              
1848: PUSH_NULL            
1850: LOAD_NAME            def_op
1852: LOAD_CONST           'CONTAINS_OP'
1854: LOAD_CONST           118
1856: PRECALL              
1860: CALL                 
1870: POP_TOP              
1872: PUSH_NULL            
1874: LOAD_NAME            def_op
1876: LOAD_CONST           'RERAISE'
1878: LOAD_CONST           119
1880: PRECALL              
1884: CALL                 
1894: POP_TOP              
1896: PUSH_NULL            
1898: LOAD_NAME            def_op
1900: LOAD_CONST           'COPY'
1902: LOAD_CONST           120
1904: PRECALL              
1908: CALL                 
1918: POP_TOP              
1920: PUSH_NULL            
1922: LOAD_NAME            def_op
1924: LOAD_CONST           'BINARY_OP'
1926: LOAD_CONST           122
1928: PRECALL              
1932: CALL                 
1942: POP_TOP              
1944: PUSH_NULL            
1946: LOAD_NAME            jrel_op
1948: LOAD_CONST           'SEND'
1950: LOAD_CONST           123
1952: PRECALL              
1956: CALL                 
1966: POP_TOP              
1968: PUSH_NULL            
1970: LOAD_NAME            def_op
1972: LOAD_CONST           'LOAD_FAST'
1974: LOAD_CONST           124
1976: PRECALL              
1980: CALL                 
1990: POP_TOP              
1992: LOAD_NAME            haslocal
1994: LOAD_METHOD          append
2016: LOAD_CONST           124
2018: PRECALL              
2022: CALL                 
2032: POP_TOP              
2034: PUSH_NULL            
2036: LOAD_NAME            def_op
2038: LOAD_CONST           'STORE_FAST'
2040: LOAD_CONST           125
2042: PRECALL              
2046: CALL                 
2056: POP_TOP              
2058: LOAD_NAME            haslocal
2060: LOAD_METHOD          append
2082: LOAD_CONST           125
2084: PRECALL              
2088: CALL                 
2098: POP_TOP              
2100: PUSH_NULL            
2102: LOAD_NAME            def_op
2104: LOAD_CONST           'DELETE_FAST'
2106: LOAD_CONST           126
2108: PRECALL              
2112: CALL                 
2122: POP_TOP              
2124: LOAD_NAME            haslocal
2126: LOAD_METHOD          append
2148: LOAD_CONST           126
2150: PRECALL              
2154: CALL                 
2164: POP_TOP              
2166: PUSH_NULL            
2168: LOAD_NAME            jrel_op
2170: LOAD_CONST           'POP_JUMP_FORWARD_IF_NOT_NONE'
2172: LOAD_CONST           128
2174: PRECALL              
2178: CALL                 
2188: POP_TOP              
2190: PUSH_NULL            
2192: LOAD_NAME            jrel_op
2194: LOAD_CONST           'POP_JUMP_FORWARD_IF_NONE'
2196: LOAD_CONST           129
2198: PRECALL              
2202: CALL                 
2212: POP_TOP              
2214: PUSH_NULL            
2216: LOAD_NAME            def_op
2218: LOAD_CONST           'RAISE_VARARGS'
2220: LOAD_CONST           130
2222: PRECALL              
2226: CALL                 
2236: POP_TOP              
2238: PUSH_NULL            
2240: LOAD_NAME            def_op
2242: LOAD_CONST           'GET_AWAITABLE'
2244: LOAD_CONST           131
2246: PRECALL              
2250: CALL                 
2260: POP_TOP              
2262: PUSH_NULL            
2264: LOAD_NAME            def_op
2266: LOAD_CONST           'MAKE_FUNCTION'
2268: LOAD_CONST           132
2270: PRECALL              
2274: CALL                 
2284: POP_TOP              
2286: PUSH_NULL            
2288: LOAD_NAME            def_op
2290: LOAD_CONST           'BUILD_SLICE'
2292: LOAD_CONST           133
2294: PRECALL              
2298: CALL                 
2308: POP_TOP              
2310: PUSH_NULL            
2312: LOAD_NAME            jrel_op
2314: LOAD_CONST           'JUMP_BACKWARD_NO_INTERRUPT'
2316: LOAD_CONST           134
2318: PRECALL              
2322: CALL                 
2332: POP_TOP              
2334: PUSH_NULL            
2336: LOAD_NAME            def_op
2338: LOAD_CONST           'MAKE_CELL'
2340: LOAD_CONST           135
2342: PRECALL              
2346: CALL                 
2356: POP_TOP              
2358: LOAD_NAME            hasfree
2360: LOAD_METHOD          append
2382: LOAD_CONST           135
2384: PRECALL              
2388: CALL                 
2398: POP_TOP              
2400: PUSH_NULL            
2402: LOAD_NAME            def_op
2404: LOAD_CONST           'LOAD_CLOSURE'
2406: LOAD_CONST           136
2408: PRECALL              
2412: CALL                 
2422: POP_TOP              
2424: LOAD_NAME            hasfree
2426: LOAD_METHOD          append
2448: LOAD_CONST           136
2450: PRECALL              
2454: CALL                 
2464: POP_TOP              
2466: PUSH_NULL            
2468: LOAD_NAME            def_op
2470: LOAD_CONST           'LOAD_DEREF'
2472: LOAD_CONST           137
2474: PRECALL              
2478: CALL                 
2488: POP_TOP              
2490: LOAD_NAME            hasfree
2492: LOAD_METHOD          append
2514: LOAD_CONST           137
2516: PRECALL              
2520: CALL                 
2530: POP_TOP              
2532: PUSH_NULL            
2534: LOAD_NAME            def_op
2536: LOAD_CONST           'STORE_DEREF'
2538: LOAD_CONST           138
2540: PRECALL              
2544: CALL                 
2554: POP_TOP              
2556: LOAD_NAME            hasfree
2558: LOAD_METHOD          append
2580: LOAD_CONST           138
2582: PRECALL              
2586: CALL                 
2596: POP_TOP              
2598: PUSH_NULL            
2600: LOAD_NAME            def_op
2602: LOAD_CONST           'DELETE_DEREF'
2604: LOAD_CONST           139
2606: PRECALL              
2610: CALL                 
2620: POP_TOP              
2622: LOAD_NAME            hasfree
2624: LOAD_METHOD          append
2646: LOAD_CONST           139
2648: PRECALL              
2652: CALL                 
2662: POP_TOP              
2664: PUSH_NULL            
2666: LOAD_NAME            jrel_op
2668: LOAD_CONST           'JUMP_BACKWARD'
2670: LOAD_CONST           140
2672: PRECALL              
2676: CALL                 
2686: POP_TOP              
2688: PUSH_NULL            
2690: LOAD_NAME            def_op
2692: LOAD_CONST           'CALL_FUNCTION_EX'
2694: LOAD_CONST           142
2696: PRECALL              
2700: CALL                 
2710: POP_TOP              
2712: PUSH_NULL            
2714: LOAD_NAME            def_op
2716: LOAD_CONST           'EXTENDED_ARG'
2718: LOAD_CONST           144
2720: PRECALL              
2724: CALL                 
2734: POP_TOP              
2736: LOAD_CONST           144
2738: STORE_NAME           EXTENDED_ARG
2740: PUSH_NULL            
2742: LOAD_NAME            def_op
2744: LOAD_CONST           'LIST_APPEND'
2746: LOAD_CONST           145
2748: PRECALL              
2752: CALL                 
2762: POP_TOP              
2764: PUSH_NULL            
2766: LOAD_NAME            def_op
2768: LOAD_CONST           'SET_ADD'
2770: LOAD_CONST           146
2772: PRECALL              
2776: CALL                 
2786: POP_TOP              
2788: PUSH_NULL            
2790: LOAD_NAME            def_op
2792: LOAD_CONST           'MAP_ADD'
2794: LOAD_CONST           147
2796: PRECALL              
2800: CALL                 
2810: POP_TOP              
2812: PUSH_NULL            
2814: LOAD_NAME            def_op
2816: LOAD_CONST           'LOAD_CLASSDEREF'
2818: LOAD_CONST           148
2820: PRECALL              
2824: CALL                 
2834: POP_TOP              
2836: LOAD_NAME            hasfree
2838: LOAD_METHOD          append
2860: LOAD_CONST           148
2862: PRECALL              
2866: CALL                 
2876: POP_TOP              
2878: PUSH_NULL            
2880: LOAD_NAME            def_op
2882: LOAD_CONST           'COPY_FREE_VARS'
2884: LOAD_CONST           149
2886: PRECALL              
2890: CALL                 
2900: POP_TOP              
2902: PUSH_NULL            
2904: LOAD_NAME            def_op
2906: LOAD_CONST           'RESUME'
2908: LOAD_CONST           151
2910: PRECALL              
2914: CALL                 
2924: POP_TOP              
2926: PUSH_NULL            
2928: LOAD_NAME            def_op
2930: LOAD_CONST           'MATCH_CLASS'
2932: LOAD_CONST           152
2934: PRECALL              
2938: CALL                 
2948: POP_TOP              
2950: PUSH_NULL            
2952: LOAD_NAME            def_op
2954: LOAD_CONST           'FORMAT_VALUE'
2956: LOAD_CONST           155
2958: PRECALL              
2962: CALL                 
2972: POP_TOP              
2974: PUSH_NULL            
2976: LOAD_NAME            def_op
2978: LOAD_CONST           'BUILD_CONST_KEY_MAP'
2980: LOAD_CONST           156
2982: PRECALL              
2986: CALL                 
2996: POP_TOP              
2998: PUSH_NULL            
3000: LOAD_NAME            def_op
3002: LOAD_CONST           'BUILD_STRING'
3004: LOAD_CONST           157
3006: PRECALL              
3010: CALL                 
3020: POP_TOP              
3022: PUSH_NULL            
3024: LOAD_NAME            name_op
3026: LOAD_CONST           'LOAD_METHOD'
3028: LOAD_CONST           160
3030: PRECALL              
3034: CALL                 
3044: POP_TOP              
3046: PUSH_NULL            
3048: LOAD_NAME            def_op
3050: LOAD_CONST           'LIST_EXTEND'
3052: LOAD_CONST           162
3054: PRECALL              
3058: CALL                 
3068: POP_TOP              
3070: PUSH_NULL            
3072: LOAD_NAME            def_op
3074: LOAD_CONST           'SET_UPDATE'
3076: LOAD_CONST           163
3078: PRECALL              
3082: CALL                 
3092: POP_TOP              
3094: PUSH_NULL            
3096: LOAD_NAME            def_op
3098: LOAD_CONST           'DICT_MERGE'
3100: LOAD_CONST           164
3102: PRECALL              
3106: CALL                 
3116: POP_TOP              
3118: PUSH_NULL            
3120: LOAD_NAME            def_op
3122: LOAD_CONST           'DICT_UPDATE'
3124: LOAD_CONST           165
3126: PRECALL              
3130: CALL                 
3140: POP_TOP              
3142: PUSH_NULL            
3144: LOAD_NAME            def_op
3146: LOAD_CONST           'PRECALL'
3148: LOAD_CONST           166
3150: PRECALL              
3154: CALL                 
3164: POP_TOP              
3166: PUSH_NULL            
3168: LOAD_NAME            def_op
3170: LOAD_CONST           'CALL'
3172: LOAD_CONST           171
3174: PRECALL              
3178: CALL                 
3188: POP_TOP              
3190: PUSH_NULL            
3192: LOAD_NAME            def_op
3194: LOAD_CONST           'KW_NAMES'
3196: LOAD_CONST           172
3198: PRECALL              
3202: CALL                 
3212: POP_TOP              
3214: LOAD_NAME            hasconst
3216: LOAD_METHOD          append
3238: LOAD_CONST           172
3240: PRECALL              
3244: CALL                 
3254: POP_TOP              
3256: PUSH_NULL            
3258: LOAD_NAME            jrel_op
3260: LOAD_CONST           'POP_JUMP_BACKWARD_IF_NOT_NONE'
3262: LOAD_CONST           173
3264: PRECALL              
3268: CALL                 
3278: POP_TOP              
3280: PUSH_NULL            
3282: LOAD_NAME            jrel_op
3284: LOAD_CONST           'POP_JUMP_BACKWARD_IF_NONE'
3286: LOAD_CONST           174
3288: PRECALL              
3292: CALL                 
3302: POP_TOP              
3304: PUSH_NULL            
3306: LOAD_NAME            jrel_op
3308: LOAD_CONST           'POP_JUMP_BACKWARD_IF_FALSE'
3310: LOAD_CONST           175
3312: PRECALL              
3316: CALL                 
3326: POP_TOP              
3328: PUSH_NULL            
3330: LOAD_NAME            jrel_op
3332: LOAD_CONST           'POP_JUMP_BACKWARD_IF_TRUE'
3334: LOAD_CONST           176
3336: PRECALL              
3340: CALL                 
3350: POP_TOP              
3352: DELETE_NAME          def_op
3354: DELETE_NAME          name_op
3356: DELETE_NAME          jrel_op
3358: DELETE_NAME          jabs_op
3360: BUILD_LIST           
3362: LOAD_CONST           (('NB_ADD', '+'), ('NB_AND', '&'), ('NB_FLOOR_DIVIDE', '//'), ('NB_LSHIFT', '<<'), ('NB_MATRIX_MULTIPLY', '@'), ('NB_MULTIPLY', '*'), ('NB_REMAINDER', '%'), ('NB_OR', '|'), ('NB_POWER', '**'), ('NB_RSHIFT', '>>'), ('NB_SUBTRACT', '-'), ('NB_TRUE_DIVIDE', '/'), ('NB_XOR', '^'), ('NB_INPLACE_ADD', '+='), ('NB_INPLACE_AND', '&='), ('NB_INPLACE_FLOOR_DIVIDE', '//='), ('NB_INPLACE_LSHIFT', '<<='), ('NB_INPLACE_MATRIX_MULTIPLY', '@='), ('NB_INPLACE_MULTIPLY', '*='), ('NB_INPLACE_REMAINDER', '%='), ('NB_INPLACE_OR', '|='), ('NB_INPLACE_POWER', '**='), ('NB_INPLACE_RSHIFT', '>>='), ('NB_INPLACE_SUBTRACT', '-='), ('NB_INPLACE_TRUE_DIVIDE', '/='), ('NB_INPLACE_XOR', '^='))
3364: LIST_EXTEND          
3366: STORE_NAME           _nb_ops
3368: BUILD_MAP            
3370: LOAD_CONST           'BINARY_OP'
3372: BUILD_LIST           
3374: LOAD_CONST           ('BINARY_OP_ADAPTIVE', 'BINARY_OP_ADD_FLOAT', 'BINARY_OP_ADD_INT', 'BINARY_OP_ADD_UNICODE', 'BINARY_OP_INPLACE_ADD_UNICODE', 'BINARY_OP_MULTIPLY_FLOAT', 'BINARY_OP_MULTIPLY_INT', 'BINARY_OP_SUBTRACT_FLOAT', 'BINARY_OP_SUBTRACT_INT')
3376: LIST_EXTEND          
3378: MAP_ADD              
3380: LOAD_CONST           'BINARY_SUBSCR'
3382: BUILD_LIST           
3384: LOAD_CONST           ('BINARY_SUBSCR_ADAPTIVE', 'BINARY_SUBSCR_DICT', 'BINARY_SUBSCR_GETITEM', 'BINARY_SUBSCR_LIST_INT', 'BINARY_SUBSCR_TUPLE_INT')
3386: LIST_EXTEND          
3388: MAP_ADD              
3390: LOAD_CONST           'CALL'
3392: BUILD_LIST           
3394: LOAD_CONST           ('CALL_ADAPTIVE', 'CALL_PY_EXACT_ARGS', 'CALL_PY_WITH_DEFAULTS')
3396: LIST_EXTEND          
3398: MAP_ADD              
3400: LOAD_CONST           'COMPARE_OP'
3402: BUILD_LIST           
3404: LOAD_CONST           ('COMPARE_OP_ADAPTIVE', 'COMPARE_OP_FLOAT_JUMP', 'COMPARE_OP_INT_JUMP', 'COMPARE_OP_STR_JUMP')
3406: LIST_EXTEND          
3408: MAP_ADD              
3410: LOAD_CONST           'EXTENDED_ARG'
3412: LOAD_CONST           'EXTENDED_ARG_QUICK'
3414: BUILD_LIST           
3416: MAP_ADD              
3418: LOAD_CONST           'JUMP_BACKWARD'
3420: LOAD_CONST           'JUMP_BACKWARD_QUICK'
3422: BUILD_LIST           
3424: MAP_ADD              
3426: LOAD_CONST           'LOAD_ATTR'
3428: BUILD_LIST           
3430: LOAD_CONST           ('LOAD_ATTR_ADAPTIVE', 'LOAD_ATTR_INSTANCE_VALUE', 'LOAD_ATTR_MODULE', 'LOAD_ATTR_SLOT', 'LOAD_ATTR_WITH_HINT')
3432: LIST_EXTEND          
3434: MAP_ADD              
3436: LOAD_CONST           'LOAD_CONST'
3438: LOAD_CONST           'LOAD_CONST__LOAD_FAST'
3440: BUILD_LIST           
3442: MAP_ADD              
3444: LOAD_CONST           'LOAD_FAST'
3446: LOAD_CONST           'LOAD_FAST__LOAD_CONST'
3448: LOAD_CONST           'LOAD_FAST__LOAD_FAST'
3450: BUILD_LIST           
3452: MAP_ADD              
3454: LOAD_CONST           'LOAD_GLOBAL'
3456: BUILD_LIST           
3458: LOAD_CONST           ('LOAD_GLOBAL_ADAPTIVE', 'LOAD_GLOBAL_BUILTIN', 'LOAD_GLOBAL_MODULE')
3460: LIST_EXTEND          
3462: MAP_ADD              
3464: LOAD_CONST           'LOAD_METHOD'
3466: BUILD_LIST           
3468: LOAD_CONST           ('LOAD_METHOD_ADAPTIVE', 'LOAD_METHOD_CLASS', 'LOAD_METHOD_MODULE', 'LOAD_METHOD_NO_DICT', 'LOAD_METHOD_WITH_DICT', 'LOAD_METHOD_WITH_VALUES')
3470: LIST_EXTEND          
3472: MAP_ADD              
3474: LOAD_CONST           'PRECALL'
3476: BUILD_LIST           
3478: LOAD_CONST           ('PRECALL_ADAPTIVE', 'PRECALL_BOUND_METHOD', 'PRECALL_BUILTIN_CLASS', 'PRECALL_BUILTIN_FAST_WITH_KEYWORDS', 'PRECALL_METHOD_DESCRIPTOR_FAST_WITH_KEYWORDS', 'PRECALL_NO_KW_BUILTIN_FAST', 'PRECALL_NO_KW_BUILTIN_O', 'PRECALL_NO_KW_ISINSTANCE', 'PRECALL_NO_KW_LEN', 'PRECALL_NO_KW_LIST_APPEND', 'PRECALL_NO_KW_METHOD_DESCRIPTOR_FAST', 'PRECALL_NO_KW_METHOD_DESCRIPTOR_NOARGS', 'PRECALL_NO_KW_METHOD_DESCRIPTOR_O', 'PRECALL_NO_KW_STR_1', 'PRECALL_NO_KW_TUPLE_1', 'PRECALL_NO_KW_TYPE_1', 'PRECALL_PYFUNC')
3480: LIST_EXTEND          
3482: MAP_ADD              
3484: LOAD_CONST           'RESUME'
3486: LOAD_CONST           'RESUME_QUICK'
3488: BUILD_LIST           
3490: MAP_ADD              
3492: LOAD_CONST           'STORE_ATTR'
3494: BUILD_LIST           
3496: LOAD_CONST           ('STORE_ATTR_ADAPTIVE', 'STORE_ATTR_INSTANCE_VALUE', 'STORE_ATTR_SLOT', 'STORE_ATTR_WITH_HINT')
3498: LIST_EXTEND          
3500: MAP_ADD              
3502: LOAD_CONST           'STORE_FAST'
3504: LOAD_CONST           'STORE_FAST__LOAD_FAST'
3506: LOAD_CONST           'STORE_FAST__STORE_FAST'
3508: BUILD_LIST           
3510: MAP_ADD              
3512: LOAD_CONST           'STORE_SUBSCR'
3514: BUILD_LIST           
3516: LOAD_CONST           ('STORE_SUBSCR_ADAPTIVE', 'STORE_SUBSCR_DICT', 'STORE_SUBSCR_LIST_INT')
3518: LIST_EXTEND          
3520: MAP_ADD              
3522: LOAD_CONST           'UNPACK_SEQUENCE'
3524: BUILD_LIST           
3526: LOAD_CONST           ('UNPACK_SEQUENCE_ADAPTIVE', 'UNPACK_SEQUENCE_LIST', 'UNPACK_SEQUENCE_TUPLE', 'UNPACK_SEQUENCE_TWO_TUPLE')
3528: LIST_EXTEND          
3530: MAP_ADD              
3532: STORE_NAME           _specializations
3534: LOAD_CONST           <code object <listcomp> at 0x0000024069467BB0, file "opcode.py", line 341>
3536: MAKE_FUNCTION        
3538: LOAD_NAME            _specializations
3540: LOAD_METHOD          values
3562: PRECALL              
3566: CALL                 
3576: GET_ITER             
3578: PRECALL              
3582: CALL                 
3592: STORE_NAME           _specialized_instructions
3594: BUILD_LIST           
3596: LOAD_CONST           ('success', 'failure', 'hit', 'deferred', 'miss', 'deopt')
3598: LIST_EXTEND          
3600: STORE_NAME           _specialization_stats
3602: LOAD_CONST           1
3604: LOAD_CONST           1
3606: LOAD_CONST           2
3608: LOAD_CONST           1
3610: LOAD_CONST           ('counter', 'index', 'module_keys_version', 'builtin_keys_version')
3612: BUILD_CONST_KEY_MAP  
3614: LOAD_CONST           'counter'
3616: LOAD_CONST           1
3618: BUILD_MAP            
3620: LOAD_CONST           'counter'
3622: LOAD_CONST           1
3624: BUILD_MAP            
3626: LOAD_CONST           1
3628: LOAD_CONST           1
3630: LOAD_CONST           ('counter', 'mask')
3632: BUILD_CONST_KEY_MAP  
3634: LOAD_CONST           1
3636: LOAD_CONST           2
3638: LOAD_CONST           1
3640: EXTENDED_ARG         
3642: LOAD_CONST           ('counter', 'type_version', 'func_version')
3644: BUILD_CONST_KEY_MAP  
3646: LOAD_CONST           1
3648: LOAD_CONST           2
3650: LOAD_CONST           1
3652: EXTENDED_ARG         
3654: LOAD_CONST           ('counter', 'version', 'index')
3656: BUILD_CONST_KEY_MAP  
3658: LOAD_CONST           1
3660: LOAD_CONST           2
3662: LOAD_CONST           1
3664: EXTENDED_ARG         
3666: LOAD_CONST           ('counter', 'version', 'index')
3668: BUILD_CONST_KEY_MAP  
3670: LOAD_CONST           1
3672: LOAD_CONST           2
3674: LOAD_CONST           1
3676: LOAD_CONST           2
3678: EXTENDED_ARG         
3680: LOAD_CONST           4
3682: EXTENDED_ARG         
3684: LOAD_CONST           ('counter', 'type_version', 'dict_offset', 'keys_version', 'descr')
3686: BUILD_CONST_KEY_MAP  
3688: LOAD_CONST           1
3690: LOAD_CONST           2
3692: LOAD_CONST           1
3694: EXTENDED_ARG         
3696: LOAD_CONST           ('counter', 'func_version', 'min_args')
3698: BUILD_CONST_KEY_MAP  
3700: LOAD_CONST           'counter'
3702: LOAD_CONST           1
3704: BUILD_MAP            
3706: LOAD_CONST           'counter'
3708: LOAD_CONST           1
3710: BUILD_MAP            
3712: EXTENDED_ARG         
3714: LOAD_CONST           ('LOAD_GLOBAL', 'BINARY_OP', 'UNPACK_SEQUENCE', 'COMPARE_OP', 'BINARY_SUBSCR', 'LOAD_ATTR', 'STORE_ATTR', 'LOAD_METHOD', 'CALL', 'PRECALL', 'STORE_SUBSCR')
3716: BUILD_CONST_KEY_MAP  
3718: STORE_NAME           _cache_format
3720: EXTENDED_ARG         
3722: LOAD_CONST           <code object <listcomp> at 0x00000240691F23A0, file "opcode.py", line 405>
3724: MAKE_FUNCTION        
3726: PUSH_NULL            
3728: LOAD_NAME            range
3730: LOAD_CONST           256
3732: PRECALL              
3736: CALL                 
3746: GET_ITER             
3748: PRECALL              
3752: CALL                 
3762: STORE_NAME           _inline_cache_entries
3764: EXTENDED_ARG         
3766: LOAD_CONST           None
3768: RETURN_VALUE         
