# Disassembly for _strptime._strptime
# From module file: _strptime

## co_consts:
('Return a 2-tuple consisting of a time struct and an int containing\n    the number of microseconds based on the input string and the\n    format string.', 'strptime() argument {} must be str, not {}', 0, '\\', '%', "'", "' is a bad directive in format '", None, "stray %% in format '%s'", 'time data ', ' does not match format ', 'unconverted data remains: %s', 1, -1, 'y', 68, 2000, 1900, 'Y', 'G', 'm', 'B', 'b', 'd', 'H', 'I', 'p', '', 12, 'M', 'S', 'f', '0', 6, 'A', 'a', 'w', 'u', 'j', ('U', 'W'), 'U', 'V', 'z', 'Z', 3, ':', 4, 5, 'Inconsistent use of : in ', 7, 60, 8, '-', ('utc', 'gmt'), "ISO year directive '%G' must be used with the ISO week directive '%V' and a weekday directive ('%A', '%a', '%w', or '%u').", "Day of the year directive '%j' is not compatible with ISO year directive '%G'. Use '%Y' instead.", "ISO week directive '%V' must be used with the ISO year directive '%G' and a weekday directive ('%A', '%a', '%w', or '%u').", "ISO week directive '%V' is incompatible with the year directive '%Y'. Use the ISO year '%G' instead.", False, 2, 29, 1904, True, 366, 365)

## co_names:
('enumerate', 'isinstance', 'str', 'TypeError', 'format', 'type', '_cache_lock', '_TimeRE_cache', 'locale_time', '_getlang', 'lang', 'time', 'tzname', 'daylight', 'TimeRE', '_regex_cache', 'clear', 'len', '_CACHE_MAX_SIZE', 'get', 'compile', 'KeyError', 'args', 'ValueError', 'IndexError', 'match', 'end', 'groupdict', 'keys', 'int', 'f_month', 'index', 'lower', 'a_month', 'am_pm', 'f_weekday', 'a_weekday', 'startswith', 'timezone', '_calc_julian_from_U_or_W', '_calc_julian_from_V', 'calendar', 'isleap', 'datetime_date', 'toordinal', 'fromordinal', 'year', 'month', 'day', 'weekday')

## bytecode:

   0: RESUME               
   2: LOAD_GLOBAL          NULL + enumerate
  14: LOAD_FAST            data_string
  16: LOAD_FAST            format
  18: BUILD_LIST           
  20: PRECALL              
  24: CALL                 
  34: GET_ITER             
  36: FOR_ITER             to 190
  38: UNPACK_SEQUENCE      
  42: STORE_FAST           index
  44: STORE_FAST           arg
  46: LOAD_GLOBAL          NULL + isinstance
  58: LOAD_FAST            arg
  60: LOAD_GLOBAL          str
  72: PRECALL              
  76: CALL                 
  86: POP_JUMP_FORWARD_IF_TRUE to 188
  88: LOAD_CONST           'strptime() argument {} must be str, not {}'
  90: STORE_FAST           msg
  92: LOAD_GLOBAL          NULL + TypeError
 104: LOAD_FAST            msg
 106: LOAD_METHOD          format
 128: LOAD_FAST            index
 130: LOAD_GLOBAL          NULL + type
 142: LOAD_FAST            arg
 144: PRECALL              
 148: CALL                 
 158: PRECALL              
 162: CALL                 
 172: PRECALL              
 176: CALL                 
 186: RAISE_VARARGS        
 188: JUMP_BACKWARD        to 36
 190: LOAD_GLOBAL          _cache_lock
 202: BEFORE_WITH          
 204: POP_TOP              
 206: LOAD_GLOBAL          _TimeRE_cache
 218: LOAD_ATTR            locale_time
 228: STORE_FAST           locale_time
 230: LOAD_GLOBAL          NULL + _getlang
 242: PRECALL              
 246: CALL                 
 256: LOAD_FAST            locale_time
 258: LOAD_ATTR            lang
 268: COMPARE_OP           !=
 274: POP_JUMP_FORWARD_IF_TRUE to 360
 276: LOAD_GLOBAL          time
 288: LOAD_ATTR            tzname
 298: LOAD_FAST            locale_time
 300: LOAD_ATTR            tzname
 310: COMPARE_OP           !=
 316: POP_JUMP_FORWARD_IF_TRUE to 360
 318: LOAD_GLOBAL          time
 330: LOAD_ATTR            daylight
 340: LOAD_FAST            locale_time
 342: LOAD_ATTR            daylight
 352: COMPARE_OP           !=
 358: POP_JUMP_FORWARD_IF_FALSE to 462
 360: LOAD_GLOBAL          NULL + TimeRE
 372: PRECALL              
 376: CALL                 
 386: STORE_GLOBAL         _TimeRE_cache
 388: LOAD_GLOBAL          _regex_cache
 400: LOAD_METHOD          clear
 422: PRECALL              
 426: CALL                 
 436: POP_TOP              
 438: LOAD_GLOBAL          _TimeRE_cache
 450: LOAD_ATTR            locale_time
 460: STORE_FAST           locale_time
 462: LOAD_GLOBAL          NULL + len
 474: LOAD_GLOBAL          _regex_cache
 486: PRECALL              
 490: CALL                 
 500: LOAD_GLOBAL          _CACHE_MAX_SIZE
 512: COMPARE_OP           >
 518: POP_JUMP_FORWARD_IF_FALSE to 570
 520: LOAD_GLOBAL          _regex_cache
 532: LOAD_METHOD          clear
 554: PRECALL              
 558: CALL                 
 568: POP_TOP              
 570: LOAD_GLOBAL          _regex_cache
 582: LOAD_METHOD          get
 604: LOAD_FAST            format
 606: PRECALL              
 610: CALL                 
 620: STORE_FAST           format_regex
 622: LOAD_FAST            format_regex
 624: POP_JUMP_FORWARD_IF_TRUE to 884
 626: NOP                  
 628: LOAD_GLOBAL          _TimeRE_cache
 640: LOAD_METHOD          compile
 662: LOAD_FAST            format
 664: PRECALL              
 668: CALL                 
 678: STORE_FAST           format_regex
 680: JUMP_FORWARD         to 864
 682: PUSH_EXC_INFO        
 684: LOAD_GLOBAL          KeyError
 696: CHECK_EXC_MATCH      
 698: POP_JUMP_FORWARD_IF_FALSE to 800
 700: STORE_FAST           err
 702: LOAD_FAST            err
 704: LOAD_ATTR            args
 714: LOAD_CONST           0
 716: BINARY_SUBSCR        
 726: STORE_FAST           bad_directive
 728: LOAD_FAST            bad_directive
 730: LOAD_CONST           '\\'
 732: COMPARE_OP           ==
 738: POP_JUMP_FORWARD_IF_FALSE to 744
 740: LOAD_CONST           '%'
 742: STORE_FAST           bad_directive
 744: DELETE_FAST          err
 746: LOAD_GLOBAL          NULL + ValueError
 758: LOAD_CONST           "'"
 760: LOAD_FAST            bad_directive
 762: FORMAT_VALUE         str
 764: LOAD_CONST           "' is a bad directive in format '"
 766: LOAD_FAST            format
 768: FORMAT_VALUE         str
 770: LOAD_CONST           "'"
 772: BUILD_STRING         
 774: PRECALL              
 778: CALL                 
 788: LOAD_CONST           None
 790: RAISE_VARARGS        
 792: LOAD_CONST           None
 794: STORE_FAST           err
 796: DELETE_FAST          err
 798: RERAISE              
 800: LOAD_GLOBAL          IndexError
 812: CHECK_EXC_MATCH      
 814: POP_JUMP_FORWARD_IF_FALSE to 856
 816: POP_TOP              
 818: LOAD_GLOBAL          NULL + ValueError
 830: LOAD_CONST           "stray %% in format '%s'"
 832: LOAD_FAST            format
 834: BINARY_OP            %
 838: PRECALL              
 842: CALL                 
 852: LOAD_CONST           None
 854: RAISE_VARARGS        
 856: RERAISE              
 858: COPY                 
 860: POP_EXCEPT           
 862: RERAISE              
 864: LOAD_FAST            format_regex
 866: LOAD_GLOBAL          _regex_cache
 878: LOAD_FAST            format
 880: STORE_SUBSCR         
 884: LOAD_CONST           None
 886: LOAD_CONST           None
 888: LOAD_CONST           None
 890: PRECALL              
 894: CALL                 
 904: POP_TOP              
 906: JUMP_FORWARD         to 930
 908: PUSH_EXC_INFO        
 910: WITH_EXCEPT_START    
 912: POP_JUMP_FORWARD_IF_TRUE to 922
 914: RERAISE              
 916: COPY                 
 918: POP_EXCEPT           
 920: RERAISE              
 922: POP_TOP              
 924: POP_EXCEPT           
 926: POP_TOP              
 928: POP_TOP              
 930: LOAD_FAST            format_regex
 932: LOAD_METHOD          match
 954: LOAD_FAST            data_string
 956: PRECALL              
 960: CALL                 
 970: STORE_FAST           found
 972: LOAD_FAST            found
 974: POP_JUMP_FORWARD_IF_TRUE to 1018
 976: LOAD_GLOBAL          NULL + ValueError
 988: LOAD_CONST           'time data '
 990: LOAD_FAST            data_string
 992: FORMAT_VALUE         repr
 994: LOAD_CONST           ' does not match format '
 996: LOAD_FAST            format
 998: FORMAT_VALUE         repr
1000: BUILD_STRING         
1002: PRECALL              
1006: CALL                 
1016: RAISE_VARARGS        
1018: LOAD_GLOBAL          NULL + len
1030: LOAD_FAST            data_string
1032: PRECALL              
1036: CALL                 
1046: LOAD_FAST            found
1048: LOAD_METHOD          end
1070: PRECALL              
1074: CALL                 
1084: COMPARE_OP           !=
1090: POP_JUMP_FORWARD_IF_FALSE to 1180
1092: LOAD_GLOBAL          NULL + ValueError
1104: LOAD_CONST           'unconverted data remains: %s'
1106: LOAD_FAST            data_string
1108: LOAD_FAST            found
1110: LOAD_METHOD          end
1132: PRECALL              
1136: CALL                 
1146: LOAD_CONST           None
1148: BUILD_SLICE          
1150: BINARY_SUBSCR        
1160: BINARY_OP            %
1164: PRECALL              
1168: CALL                 
1178: RAISE_VARARGS        
1180: LOAD_CONST           None
1182: COPY                 
1184: STORE_FAST           iso_year
1186: STORE_FAST           year
1188: LOAD_CONST           1
1190: COPY                 
1192: STORE_FAST           month
1194: STORE_FAST           day
1196: LOAD_CONST           0
1198: COPY                 
1200: STORE_FAST           hour
1202: COPY                 
1204: STORE_FAST           minute
1206: COPY                 
1208: STORE_FAST           second
1210: STORE_FAST           fraction
1212: LOAD_CONST           -1
1214: STORE_FAST           tz
1216: LOAD_CONST           None
1218: STORE_FAST           gmtoff
1220: LOAD_CONST           0
1222: STORE_FAST           gmtoff_fraction
1224: LOAD_CONST           None
1226: COPY                 
1228: STORE_FAST           iso_week
1230: STORE_FAST           week_of_year
1232: LOAD_CONST           None
1234: STORE_FAST           week_of_year_start
1236: LOAD_CONST           None
1238: COPY                 
1240: STORE_FAST           weekday
1242: STORE_FAST           julian
1244: LOAD_FAST            found
1246: LOAD_METHOD          groupdict
1268: PRECALL              
1272: CALL                 
1282: STORE_FAST           found_dict
1284: LOAD_FAST            found_dict
1286: LOAD_METHOD          keys
1308: PRECALL              
1312: CALL                 
1322: GET_ITER             
1324: EXTENDED_ARG         
1326: FOR_ITER             to 3840
1328: STORE_FAST           group_key
1330: LOAD_FAST            group_key
1332: LOAD_CONST           'y'
1334: COMPARE_OP           ==
1340: POP_JUMP_FORWARD_IF_FALSE to 1420
1342: LOAD_GLOBAL          NULL + int
1354: LOAD_FAST            found_dict
1356: LOAD_CONST           'y'
1358: BINARY_SUBSCR        
1368: PRECALL              
1372: CALL                 
1382: STORE_FAST           year
1384: LOAD_FAST            year
1386: LOAD_CONST           68
1388: COMPARE_OP           <=
1394: POP_JUMP_FORWARD_IF_FALSE to 1408
1396: LOAD_FAST            year
1398: LOAD_CONST           2000
1400: BINARY_OP            +=
1404: STORE_FAST           year
1406: JUMP_BACKWARD        to 1324
1408: LOAD_FAST            year
1410: LOAD_CONST           1900
1412: BINARY_OP            +=
1416: STORE_FAST           year
1418: JUMP_BACKWARD        to 1324
1420: LOAD_FAST            group_key
1422: LOAD_CONST           'Y'
1424: COMPARE_OP           ==
1430: POP_JUMP_FORWARD_IF_FALSE to 1476
1432: LOAD_GLOBAL          NULL + int
1444: LOAD_FAST            found_dict
1446: LOAD_CONST           'Y'
1448: BINARY_SUBSCR        
1458: PRECALL              
1462: CALL                 
1472: STORE_FAST           year
1474: JUMP_BACKWARD        to 1324
1476: LOAD_FAST            group_key
1478: LOAD_CONST           'G'
1480: COMPARE_OP           ==
1486: POP_JUMP_FORWARD_IF_FALSE to 1532
1488: LOAD_GLOBAL          NULL + int
1500: LOAD_FAST            found_dict
1502: LOAD_CONST           'G'
1504: BINARY_SUBSCR        
1514: PRECALL              
1518: CALL                 
1528: STORE_FAST           iso_year
1530: JUMP_BACKWARD        to 1324
1532: LOAD_FAST            group_key
1534: LOAD_CONST           'm'
1536: COMPARE_OP           ==
1542: POP_JUMP_FORWARD_IF_FALSE to 1588
1544: LOAD_GLOBAL          NULL + int
1556: LOAD_FAST            found_dict
1558: LOAD_CONST           'm'
1560: BINARY_SUBSCR        
1570: PRECALL              
1574: CALL                 
1584: STORE_FAST           month
1586: JUMP_BACKWARD        to 1324
1588: LOAD_FAST            group_key
1590: LOAD_CONST           'B'
1592: COMPARE_OP           ==
1598: POP_JUMP_FORWARD_IF_FALSE to 1702
1600: LOAD_FAST            locale_time
1602: LOAD_ATTR            f_month
1612: LOAD_METHOD          index
1634: LOAD_FAST            found_dict
1636: LOAD_CONST           'B'
1638: BINARY_SUBSCR        
1648: LOAD_METHOD          lower
1670: PRECALL              
1674: CALL                 
1684: PRECALL              
1688: CALL                 
1698: STORE_FAST           month
1700: JUMP_BACKWARD        to 1324
1702: LOAD_FAST            group_key
1704: LOAD_CONST           'b'
1706: COMPARE_OP           ==
1712: POP_JUMP_FORWARD_IF_FALSE to 1816
1714: LOAD_FAST            locale_time
1716: LOAD_ATTR            a_month
1726: LOAD_METHOD          index
1748: LOAD_FAST            found_dict
1750: LOAD_CONST           'b'
1752: BINARY_SUBSCR        
1762: LOAD_METHOD          lower
1784: PRECALL              
1788: CALL                 
1798: PRECALL              
1802: CALL                 
1812: STORE_FAST           month
1814: JUMP_BACKWARD        to 1324
1816: LOAD_FAST            group_key
1818: LOAD_CONST           'd'
1820: COMPARE_OP           ==
1826: POP_JUMP_FORWARD_IF_FALSE to 1874
1828: LOAD_GLOBAL          NULL + int
1840: LOAD_FAST            found_dict
1842: LOAD_CONST           'd'
1844: BINARY_SUBSCR        
1854: PRECALL              
1858: CALL                 
1868: STORE_FAST           day
1870: EXTENDED_ARG         
1872: JUMP_BACKWARD        to 1324
1874: LOAD_FAST            group_key
1876: LOAD_CONST           'H'
1878: COMPARE_OP           ==
1884: POP_JUMP_FORWARD_IF_FALSE to 1932
1886: LOAD_GLOBAL          NULL + int
1898: LOAD_FAST            found_dict
1900: LOAD_CONST           'H'
1902: BINARY_SUBSCR        
1912: PRECALL              
1916: CALL                 
1926: STORE_FAST           hour
1928: EXTENDED_ARG         
1930: JUMP_BACKWARD        to 1324
1932: LOAD_FAST            group_key
1934: LOAD_CONST           'I'
1936: COMPARE_OP           ==
1942: POP_JUMP_FORWARD_IF_FALSE to 2180
1944: LOAD_GLOBAL          NULL + int
1956: LOAD_FAST            found_dict
1958: LOAD_CONST           'I'
1960: BINARY_SUBSCR        
1970: PRECALL              
1974: CALL                 
1984: STORE_FAST           hour
1986: LOAD_FAST            found_dict
1988: LOAD_METHOD          get
2010: LOAD_CONST           'p'
2012: LOAD_CONST           ''
2014: PRECALL              
2018: CALL                 
2028: LOAD_METHOD          lower
2050: PRECALL              
2054: CALL                 
2064: STORE_FAST           ampm
2066: LOAD_FAST            ampm
2068: LOAD_CONST           ''
2070: LOAD_FAST            locale_time
2072: LOAD_ATTR            am_pm
2082: LOAD_CONST           0
2084: BINARY_SUBSCR        
2094: BUILD_TUPLE          
2096: CONTAINS_OP          
2098: POP_JUMP_FORWARD_IF_FALSE to 2120
2100: LOAD_FAST            hour
2102: LOAD_CONST           12
2104: COMPARE_OP           ==
2110: POP_JUMP_FORWARD_IF_FALSE to 2116
2112: LOAD_CONST           0
2114: STORE_FAST           hour
2116: EXTENDED_ARG         
2118: JUMP_BACKWARD        to 1324
2120: LOAD_FAST            ampm
2122: LOAD_FAST            locale_time
2124: LOAD_ATTR            am_pm
2134: LOAD_CONST           1
2136: BINARY_SUBSCR        
2146: COMPARE_OP           ==
2152: POP_JUMP_FORWARD_IF_FALSE to 2176
2154: LOAD_FAST            hour
2156: LOAD_CONST           12
2158: COMPARE_OP           !=
2164: POP_JUMP_FORWARD_IF_FALSE to 2176
2166: LOAD_FAST            hour
2168: LOAD_CONST           12
2170: BINARY_OP            +=
2174: STORE_FAST           hour
2176: EXTENDED_ARG         
2178: JUMP_BACKWARD        to 1324
2180: LOAD_FAST            group_key
2182: LOAD_CONST           'M'
2184: COMPARE_OP           ==
2190: POP_JUMP_FORWARD_IF_FALSE to 2238
2192: LOAD_GLOBAL          NULL + int
2204: LOAD_FAST            found_dict
2206: LOAD_CONST           'M'
2208: BINARY_SUBSCR        
2218: PRECALL              
2222: CALL                 
2232: STORE_FAST           minute
2234: EXTENDED_ARG         
2236: JUMP_BACKWARD        to 1324
2238: LOAD_FAST            group_key
2240: LOAD_CONST           'S'
2242: COMPARE_OP           ==
2248: POP_JUMP_FORWARD_IF_FALSE to 2296
2250: LOAD_GLOBAL          NULL + int
2262: LOAD_FAST            found_dict
2264: LOAD_CONST           'S'
2266: BINARY_SUBSCR        
2276: PRECALL              
2280: CALL                 
2290: STORE_FAST           second
2292: EXTENDED_ARG         
2294: JUMP_BACKWARD        to 1324
2296: LOAD_FAST            group_key
2298: LOAD_CONST           'f'
2300: COMPARE_OP           ==
2306: POP_JUMP_FORWARD_IF_FALSE to 2406
2308: LOAD_FAST            found_dict
2310: LOAD_CONST           'f'
2312: BINARY_SUBSCR        
2322: STORE_FAST           s
2324: LOAD_FAST            s
2326: LOAD_CONST           '0'
2328: LOAD_CONST           6
2330: LOAD_GLOBAL          NULL + len
2342: LOAD_FAST            s
2344: PRECALL              
2348: CALL                 
2358: BINARY_OP            -
2362: BINARY_OP            *
2366: BINARY_OP            +=
2370: STORE_FAST           s
2372: LOAD_GLOBAL          NULL + int
2384: LOAD_FAST            s
2386: PRECALL              
2390: CALL                 
2400: STORE_FAST           fraction
2402: EXTENDED_ARG         
2404: JUMP_BACKWARD        to 1324
2406: LOAD_FAST            group_key
2408: LOAD_CONST           'A'
2410: COMPARE_OP           ==
2416: POP_JUMP_FORWARD_IF_FALSE to 2522
2418: LOAD_FAST            locale_time
2420: LOAD_ATTR            f_weekday
2430: LOAD_METHOD          index
2452: LOAD_FAST            found_dict
2454: LOAD_CONST           'A'
2456: BINARY_SUBSCR        
2466: LOAD_METHOD          lower
2488: PRECALL              
2492: CALL                 
2502: PRECALL              
2506: CALL                 
2516: STORE_FAST           weekday
2518: EXTENDED_ARG         
2520: JUMP_BACKWARD        to 1324
2522: LOAD_FAST            group_key
2524: LOAD_CONST           'a'
2526: COMPARE_OP           ==
2532: POP_JUMP_FORWARD_IF_FALSE to 2638
2534: LOAD_FAST            locale_time
2536: LOAD_ATTR            a_weekday
2546: LOAD_METHOD          index
2568: LOAD_FAST            found_dict
2570: LOAD_CONST           'a'
2572: BINARY_SUBSCR        
2582: LOAD_METHOD          lower
2604: PRECALL              
2608: CALL                 
2618: PRECALL              
2622: CALL                 
2632: STORE_FAST           weekday
2634: EXTENDED_ARG         
2636: JUMP_BACKWARD        to 1324
2638: LOAD_FAST            group_key
2640: LOAD_CONST           'w'
2642: COMPARE_OP           ==
2648: POP_JUMP_FORWARD_IF_FALSE to 2726
2650: LOAD_GLOBAL          NULL + int
2662: LOAD_FAST            found_dict
2664: LOAD_CONST           'w'
2666: BINARY_SUBSCR        
2676: PRECALL              
2680: CALL                 
2690: STORE_FAST           weekday
2692: LOAD_FAST            weekday
2694: LOAD_CONST           0
2696: COMPARE_OP           ==
2702: POP_JUMP_FORWARD_IF_FALSE to 2712
2704: LOAD_CONST           6
2706: STORE_FAST           weekday
2708: EXTENDED_ARG         
2710: JUMP_BACKWARD        to 1324
2712: LOAD_FAST            weekday
2714: LOAD_CONST           1
2716: BINARY_OP            -=
2720: STORE_FAST           weekday
2722: EXTENDED_ARG         
2724: JUMP_BACKWARD        to 1324
2726: LOAD_FAST            group_key
2728: LOAD_CONST           'u'
2730: COMPARE_OP           ==
2736: POP_JUMP_FORWARD_IF_FALSE to 2794
2738: LOAD_GLOBAL          NULL + int
2750: LOAD_FAST            found_dict
2752: LOAD_CONST           'u'
2754: BINARY_SUBSCR        
2764: PRECALL              
2768: CALL                 
2778: STORE_FAST           weekday
2780: LOAD_FAST            weekday
2782: LOAD_CONST           1
2784: BINARY_OP            -=
2788: STORE_FAST           weekday
2790: EXTENDED_ARG         
2792: JUMP_BACKWARD        to 1324
2794: LOAD_FAST            group_key
2796: LOAD_CONST           'j'
2798: COMPARE_OP           ==
2804: POP_JUMP_FORWARD_IF_FALSE to 2852
2806: LOAD_GLOBAL          NULL + int
2818: LOAD_FAST            found_dict
2820: LOAD_CONST           'j'
2822: BINARY_SUBSCR        
2832: PRECALL              
2836: CALL                 
2846: STORE_FAST           julian
2848: EXTENDED_ARG         
2850: JUMP_BACKWARD        to 1324
2852: LOAD_FAST            group_key
2854: LOAD_CONST           ('U', 'W')
2856: CONTAINS_OP          
2858: POP_JUMP_FORWARD_IF_FALSE to 2930
2860: LOAD_GLOBAL          NULL + int
2872: LOAD_FAST            found_dict
2874: LOAD_FAST            group_key
2876: BINARY_SUBSCR        
2886: PRECALL              
2890: CALL                 
2900: STORE_FAST           week_of_year
2902: LOAD_FAST            group_key
2904: LOAD_CONST           'U'
2906: COMPARE_OP           ==
2912: POP_JUMP_FORWARD_IF_FALSE to 2922
2914: LOAD_CONST           6
2916: STORE_FAST           week_of_year_start
2918: EXTENDED_ARG         
2920: JUMP_BACKWARD        to 1324
2922: LOAD_CONST           0
2924: STORE_FAST           week_of_year_start
2926: EXTENDED_ARG         
2928: JUMP_BACKWARD        to 1324
2930: LOAD_FAST            group_key
2932: LOAD_CONST           'V'
2934: COMPARE_OP           ==
2940: POP_JUMP_FORWARD_IF_FALSE to 2988
2942: LOAD_GLOBAL          NULL + int
2954: LOAD_FAST            found_dict
2956: LOAD_CONST           'V'
2958: BINARY_SUBSCR        
2968: PRECALL              
2972: CALL                 
2982: STORE_FAST           iso_week
2984: EXTENDED_ARG         
2986: JUMP_BACKWARD        to 1324
2988: LOAD_FAST            group_key
2990: LOAD_CONST           'z'
2992: COMPARE_OP           ==
2998: EXTENDED_ARG         
3000: POP_JUMP_FORWARD_IF_FALSE to 3592
3002: LOAD_FAST            found_dict
3004: LOAD_CONST           'z'
3006: BINARY_SUBSCR        
3016: STORE_FAST           z
3018: LOAD_FAST            z
3020: LOAD_CONST           'Z'
3022: COMPARE_OP           ==
3028: POP_JUMP_FORWARD_IF_FALSE to 3038
3030: LOAD_CONST           0
3032: STORE_FAST           gmtoff
3034: EXTENDED_ARG         
3036: JUMP_BACKWARD        to 1324
3038: LOAD_FAST            z
3040: LOAD_CONST           3
3042: BINARY_SUBSCR        
3052: LOAD_CONST           ':'
3054: COMPARE_OP           ==
3060: POP_JUMP_FORWARD_IF_FALSE to 3260
3062: LOAD_FAST            z
3064: LOAD_CONST           None
3066: LOAD_CONST           3
3068: BUILD_SLICE          
3070: BINARY_SUBSCR        
3080: LOAD_FAST            z
3082: LOAD_CONST           4
3084: LOAD_CONST           None
3086: BUILD_SLICE          
3088: BINARY_SUBSCR        
3098: BINARY_OP            +
3102: STORE_FAST           z
3104: LOAD_GLOBAL          NULL + len
3116: LOAD_FAST            z
3118: PRECALL              
3122: CALL                 
3132: LOAD_CONST           5
3134: COMPARE_OP           >
3140: POP_JUMP_FORWARD_IF_FALSE to 3260
3142: LOAD_FAST            z
3144: LOAD_CONST           5
3146: BINARY_SUBSCR        
3156: LOAD_CONST           ':'
3158: COMPARE_OP           !=
3164: POP_JUMP_FORWARD_IF_FALSE to 3218
3166: LOAD_CONST           'Inconsistent use of : in '
3168: LOAD_FAST            found_dict
3170: LOAD_CONST           'z'
3172: BINARY_SUBSCR        
3182: FORMAT_VALUE         
3184: BUILD_STRING         
3186: STORE_FAST           msg
3188: LOAD_GLOBAL          NULL + ValueError
3200: LOAD_FAST            msg
3202: PRECALL              
3206: CALL                 
3216: RAISE_VARARGS        
3218: LOAD_FAST            z
3220: LOAD_CONST           None
3222: LOAD_CONST           5
3224: BUILD_SLICE          
3226: BINARY_SUBSCR        
3236: LOAD_FAST            z
3238: LOAD_CONST           6
3240: LOAD_CONST           None
3242: BUILD_SLICE          
3244: BINARY_SUBSCR        
3254: BINARY_OP            +
3258: STORE_FAST           z
3260: LOAD_GLOBAL          NULL + int
3272: LOAD_FAST            z
3274: LOAD_CONST           1
3276: LOAD_CONST           3
3278: BUILD_SLICE          
3280: BINARY_SUBSCR        
3290: PRECALL              
3294: CALL                 
3304: STORE_FAST           hours
3306: LOAD_GLOBAL          NULL + int
3318: LOAD_FAST            z
3320: LOAD_CONST           3
3322: LOAD_CONST           5
3324: BUILD_SLICE          
3326: BINARY_SUBSCR        
3336: PRECALL              
3340: CALL                 
3350: STORE_FAST           minutes
3352: LOAD_GLOBAL          NULL + int
3364: LOAD_FAST            z
3366: LOAD_CONST           5
3368: LOAD_CONST           7
3370: BUILD_SLICE          
3372: BINARY_SUBSCR        
3382: JUMP_IF_TRUE_OR_POP  to 3386
3384: LOAD_CONST           0
3386: PRECALL              
3390: CALL                 
3400: STORE_FAST           seconds
3402: LOAD_FAST            hours
3404: LOAD_CONST           60
3406: BINARY_OP            *
3410: LOAD_CONST           60
3412: BINARY_OP            *
3416: LOAD_FAST            minutes
3418: LOAD_CONST           60
3420: BINARY_OP            *
3424: BINARY_OP            +
3428: LOAD_FAST            seconds
3430: BINARY_OP            +
3434: STORE_FAST           gmtoff
3436: LOAD_FAST            z
3438: LOAD_CONST           8
3440: LOAD_CONST           None
3442: BUILD_SLICE          
3444: BINARY_SUBSCR        
3454: STORE_FAST           gmtoff_remainder
3456: LOAD_CONST           '0'
3458: LOAD_CONST           6
3460: LOAD_GLOBAL          NULL + len
3472: LOAD_FAST            gmtoff_remainder
3474: PRECALL              
3478: CALL                 
3488: BINARY_OP            -
3492: BINARY_OP            *
3496: STORE_FAST           gmtoff_remainder_padding
3498: LOAD_GLOBAL          NULL + int
3510: LOAD_FAST            gmtoff_remainder
3512: LOAD_FAST            gmtoff_remainder_padding
3514: BINARY_OP            +
3518: PRECALL              
3522: CALL                 
3532: STORE_FAST           gmtoff_fraction
3534: LOAD_FAST            z
3536: LOAD_METHOD          startswith
3558: LOAD_CONST           '-'
3560: PRECALL              
3564: CALL                 
3574: POP_JUMP_FORWARD_IF_FALSE to 3588
3576: LOAD_FAST            gmtoff
3578: UNARY_NEGATIVE       
3580: STORE_FAST           gmtoff
3582: LOAD_FAST            gmtoff_fraction
3584: UNARY_NEGATIVE       
3586: STORE_FAST           gmtoff_fraction
3588: EXTENDED_ARG         
3590: JUMP_BACKWARD        to 1324
3592: LOAD_FAST            group_key
3594: LOAD_CONST           'Z'
3596: COMPARE_OP           ==
3602: POP_JUMP_FORWARD_IF_FALSE to 3836
3604: LOAD_FAST            found_dict
3606: LOAD_CONST           'Z'
3608: BINARY_SUBSCR        
3618: LOAD_METHOD          lower
3640: PRECALL              
3644: CALL                 
3654: STORE_FAST           found_zone
3656: LOAD_GLOBAL          NULL + enumerate
3668: LOAD_FAST            locale_time
3670: LOAD_ATTR            timezone
3680: PRECALL              
3684: CALL                 
3694: GET_ITER             
3696: FOR_ITER             to 3836
3698: UNPACK_SEQUENCE      
3702: STORE_FAST           value
3704: STORE_FAST           tz_values
3706: LOAD_FAST            found_zone
3708: LOAD_FAST            tz_values
3710: CONTAINS_OP          
3712: POP_JUMP_FORWARD_IF_FALSE to 3834
3714: LOAD_GLOBAL          time
3726: LOAD_ATTR            tzname
3736: LOAD_CONST           0
3738: BINARY_SUBSCR        
3748: LOAD_GLOBAL          time
3760: LOAD_ATTR            tzname
3770: LOAD_CONST           1
3772: BINARY_SUBSCR        
3782: COMPARE_OP           ==
3788: POP_JUMP_FORWARD_IF_FALSE to 3826
3790: LOAD_GLOBAL          time
3802: LOAD_ATTR            daylight
3812: POP_JUMP_FORWARD_IF_FALSE to 3826
3814: LOAD_FAST            found_zone
3816: LOAD_CONST           ('utc', 'gmt')
3818: CONTAINS_OP          
3820: POP_JUMP_FORWARD_IF_FALSE to 3826
3822: POP_TOP              
3824: JUMP_FORWARD         to 3836
3826: LOAD_FAST            value
3828: STORE_FAST           tz
3830: POP_TOP              
3832: JUMP_FORWARD         to 3836
3834: JUMP_BACKWARD        to 3696
3836: EXTENDED_ARG         
3838: JUMP_BACKWARD        to 1324
3840: LOAD_FAST            year
3842: POP_JUMP_FORWARD_IF_NOT_NONE to 3922
3844: LOAD_FAST            iso_year
3846: POP_JUMP_FORWARD_IF_NONE to 3922
3848: LOAD_FAST            iso_week
3850: POP_JUMP_FORWARD_IF_NONE to 3856
3852: LOAD_FAST            weekday
3854: POP_JUMP_FORWARD_IF_NOT_NONE to 3886
3856: LOAD_GLOBAL          NULL + ValueError
3868: LOAD_CONST           "ISO year directive '%G' must be used with the ISO week directive '%V' and a weekday directive ('%A', '%a', '%w', or '%u')."
3870: PRECALL              
3874: CALL                 
3884: RAISE_VARARGS        
3886: LOAD_FAST            julian
3888: POP_JUMP_FORWARD_IF_NONE to 3920
3890: LOAD_GLOBAL          NULL + ValueError
3902: LOAD_CONST           "Day of the year directive '%j' is not compatible with ISO year directive '%G'. Use '%Y' instead."
3904: PRECALL              
3908: CALL                 
3918: RAISE_VARARGS        
3920: JUMP_FORWARD         to 3994
3922: LOAD_FAST            week_of_year
3924: POP_JUMP_FORWARD_IF_NOT_NONE to 3994
3926: LOAD_FAST            iso_week
3928: POP_JUMP_FORWARD_IF_NONE to 3994
3930: LOAD_FAST            weekday
3932: POP_JUMP_FORWARD_IF_NOT_NONE to 3964
3934: LOAD_GLOBAL          NULL + ValueError
3946: LOAD_CONST           "ISO week directive '%V' must be used with the ISO year directive '%G' and a weekday directive ('%A', '%a', '%w', or '%u')."
3948: PRECALL              
3952: CALL                 
3962: RAISE_VARARGS        
3964: LOAD_GLOBAL          NULL + ValueError
3976: LOAD_CONST           "ISO week directive '%V' is incompatible with the year directive '%Y'. Use the ISO year '%G' instead."
3978: PRECALL              
3982: CALL                 
3992: RAISE_VARARGS        
3994: LOAD_CONST           False
3996: STORE_FAST           leap_year_fix
3998: LOAD_FAST            year
4000: POP_JUMP_FORWARD_IF_NOT_NONE to 4036
4002: LOAD_FAST            month
4004: LOAD_CONST           2
4006: COMPARE_OP           ==
4012: POP_JUMP_FORWARD_IF_FALSE to 4036
4014: LOAD_FAST            day
4016: LOAD_CONST           29
4018: COMPARE_OP           ==
4024: POP_JUMP_FORWARD_IF_FALSE to 4036
4026: LOAD_CONST           1904
4028: STORE_FAST           year
4030: LOAD_CONST           True
4032: STORE_FAST           leap_year_fix
4034: JUMP_FORWARD         to 4044
4036: LOAD_FAST            year
4038: POP_JUMP_FORWARD_IF_NOT_NONE to 4044
4040: LOAD_CONST           1900
4042: STORE_FAST           year
4044: LOAD_FAST            julian
4046: POP_JUMP_FORWARD_IF_NOT_NONE to 4252
4048: LOAD_FAST            weekday
4050: POP_JUMP_FORWARD_IF_NONE to 4252
4052: LOAD_FAST            week_of_year
4054: POP_JUMP_FORWARD_IF_NONE to 4114
4056: LOAD_FAST            week_of_year_start
4058: LOAD_CONST           0
4060: COMPARE_OP           ==
4066: POP_JUMP_FORWARD_IF_FALSE to 4072
4068: LOAD_CONST           True
4070: JUMP_FORWARD         to 4074
4072: LOAD_CONST           False
4074: STORE_FAST           week_starts_Mon
4076: LOAD_GLOBAL          NULL + _calc_julian_from_U_or_W
4088: LOAD_FAST            year
4090: LOAD_FAST            week_of_year
4092: LOAD_FAST            weekday
4094: LOAD_FAST            week_starts_Mon
4096: PRECALL              
4100: CALL                 
4110: STORE_FAST           julian
4112: JUMP_FORWARD         to 4168
4114: LOAD_FAST            iso_year
4116: POP_JUMP_FORWARD_IF_NONE to 4168
4118: LOAD_FAST            iso_week
4120: POP_JUMP_FORWARD_IF_NONE to 4168
4122: LOAD_GLOBAL          NULL + _calc_julian_from_V
4134: LOAD_FAST            iso_year
4136: LOAD_FAST            iso_week
4138: LOAD_FAST            weekday
4140: LOAD_CONST           1
4142: BINARY_OP            +
4146: PRECALL              
4150: CALL                 
4160: UNPACK_SEQUENCE      
4164: STORE_FAST           year
4166: STORE_FAST           julian
4168: LOAD_FAST            julian
4170: POP_JUMP_FORWARD_IF_NONE to 4252
4172: LOAD_FAST            julian
4174: LOAD_CONST           0
4176: COMPARE_OP           <=
4182: POP_JUMP_FORWARD_IF_FALSE to 4252
4184: LOAD_FAST            year
4186: LOAD_CONST           1
4188: BINARY_OP            -=
4192: STORE_FAST           year
4194: LOAD_GLOBAL          NULL + calendar
4206: LOAD_ATTR            isleap
4216: LOAD_FAST            year
4218: PRECALL              
4222: CALL                 
4232: POP_JUMP_FORWARD_IF_FALSE to 4238
4234: LOAD_CONST           366
4236: JUMP_FORWARD         to 4240
4238: LOAD_CONST           365
4240: STORE_FAST           yday
4242: LOAD_FAST            julian
4244: LOAD_FAST            yday
4246: BINARY_OP            +=
4250: STORE_FAST           julian
4252: LOAD_FAST            julian
4254: POP_JUMP_FORWARD_IF_NOT_NONE to 4406
4256: LOAD_GLOBAL          NULL + datetime_date
4268: LOAD_FAST            year
4270: LOAD_FAST            month
4272: LOAD_FAST            day
4274: PRECALL              
4278: CALL                 
4288: LOAD_METHOD          toordinal
4310: PRECALL              
4314: CALL                 
4324: LOAD_GLOBAL          NULL + datetime_date
4336: LOAD_FAST            year
4338: LOAD_CONST           1
4340: LOAD_CONST           1
4342: PRECALL              
4346: CALL                 
4356: LOAD_METHOD          toordinal
4378: PRECALL              
4382: CALL                 
4392: BINARY_OP            -
4396: LOAD_CONST           1
4398: BINARY_OP            +
4402: STORE_FAST           julian
4404: JUMP_FORWARD         to 4566
4406: LOAD_GLOBAL          NULL + datetime_date
4418: LOAD_ATTR            fromordinal
4428: LOAD_FAST            julian
4430: LOAD_CONST           1
4432: BINARY_OP            -
4436: LOAD_GLOBAL          NULL + datetime_date
4448: LOAD_FAST            year
4450: LOAD_CONST           1
4452: LOAD_CONST           1
4454: PRECALL              
4458: CALL                 
4468: LOAD_METHOD          toordinal
4490: PRECALL              
4494: CALL                 
4504: BINARY_OP            +
4508: PRECALL              
4512: CALL                 
4522: STORE_FAST           datetime_result
4524: LOAD_FAST            datetime_result
4526: LOAD_ATTR            year
4536: STORE_FAST           year
4538: LOAD_FAST            datetime_result
4540: LOAD_ATTR            month
4550: STORE_FAST           month
4552: LOAD_FAST            datetime_result
4554: LOAD_ATTR            day
4564: STORE_FAST           day
4566: LOAD_FAST            weekday
4568: POP_JUMP_FORWARD_IF_NOT_NONE to 4640
4570: LOAD_GLOBAL          NULL + datetime_date
4582: LOAD_FAST            year
4584: LOAD_FAST            month
4586: LOAD_FAST            day
4588: PRECALL              
4592: CALL                 
4602: LOAD_METHOD          weekday
4624: PRECALL              
4628: CALL                 
4638: STORE_FAST           weekday
4640: LOAD_FAST            found_dict
4642: LOAD_METHOD          get
4664: LOAD_CONST           'Z'
4666: PRECALL              
4670: CALL                 
4680: STORE_FAST           tzname
4682: LOAD_FAST            leap_year_fix
4684: POP_JUMP_FORWARD_IF_FALSE to 4690
4686: LOAD_CONST           1900
4688: STORE_FAST           year
4690: LOAD_FAST            year
4692: LOAD_FAST            month
4694: LOAD_FAST            day
4696: LOAD_FAST            hour
4698: LOAD_FAST            minute
4700: LOAD_FAST            second
4702: LOAD_FAST            weekday
4704: LOAD_FAST            julian
4706: LOAD_FAST            tz
4708: LOAD_FAST            tzname
4710: LOAD_FAST            gmtoff
4712: BUILD_TUPLE          
4714: LOAD_FAST            fraction
4716: LOAD_FAST            gmtoff_fraction
4718: BUILD_TUPLE          
4720: RETURN_VALUE         
