# Disassembly for _strptime.TimeRE.pattern
# From module file: _strptime

## co_consts:
('Return regex pattern for the format string.\n\n        Need to make sure that any characters that might be interpreted as\n        regex syntax are escaped.\n\n        ', '', '([\\\\.^$*+?\\(\\){}\\[\\]|])', '\\\\\\1', '\\s+', '\\\\s+', '%', 1, None)

## co_names:
('re_compile', 'sub', 'index')

## bytecode:

   0: RESUME               
   2: LOAD_CONST           ''
   4: STORE_FAST           processed_format
   6: LOAD_GLOBAL          NULL + re_compile
  18: LOAD_CONST           '([\\\\.^$*+?\\(\\){}\\[\\]|])'
  20: PRECALL              
  24: CALL                 
  34: STORE_FAST           regex_chars
  36: LOAD_FAST            regex_chars
  38: LOAD_METHOD          sub
  60: LOAD_CONST           '\\\\\\1'
  62: LOAD_FAST            format
  64: PRECALL              
  68: CALL                 
  78: STORE_FAST           format
  80: LOAD_GLOBAL          NULL + re_compile
  92: LOAD_CONST           '\\s+'
  94: PRECALL              
  98: CALL                 
 108: STORE_FAST           whitespace_replacement
 110: LOAD_FAST            whitespace_replacement
 112: LOAD_METHOD          sub
 134: LOAD_CONST           '\\\\s+'
 136: LOAD_FAST            format
 138: PRECALL              
 142: CALL                 
 152: STORE_FAST           format
 154: LOAD_CONST           '%'
 156: LOAD_FAST            format
 158: CONTAINS_OP          
 160: POP_JUMP_FORWARD_IF_FALSE to 306
 162: LOAD_FAST            format
 164: LOAD_METHOD          index
 186: LOAD_CONST           '%'
 188: PRECALL              
 192: CALL                 
 202: LOAD_CONST           1
 204: BINARY_OP            +
 208: STORE_FAST           directive_index
 210: LOAD_FAST            processed_format
 212: FORMAT_VALUE         str
 214: LOAD_FAST            format
 216: LOAD_CONST           None
 218: LOAD_FAST            directive_index
 220: LOAD_CONST           1
 222: BINARY_OP            -
 226: BUILD_SLICE          
 228: BINARY_SUBSCR        
 238: FORMAT_VALUE         str
 240: LOAD_FAST            self
 242: LOAD_FAST            format
 244: LOAD_FAST            directive_index
 246: BINARY_SUBSCR        
 256: BINARY_SUBSCR        
 266: FORMAT_VALUE         str
 268: BUILD_STRING         
 270: STORE_FAST           processed_format
 272: LOAD_FAST            format
 274: LOAD_FAST            directive_index
 276: LOAD_CONST           1
 278: BINARY_OP            +
 282: LOAD_CONST           None
 284: BUILD_SLICE          
 286: BINARY_SUBSCR        
 296: STORE_FAST           format
 298: LOAD_CONST           '%'
 300: LOAD_FAST            format
 302: CONTAINS_OP          
 304: POP_JUMP_BACKWARD_IF_TRUE to 162
 306: LOAD_FAST            processed_format
 308: FORMAT_VALUE         str
 310: LOAD_FAST            format
 312: FORMAT_VALUE         str
 314: BUILD_STRING         
 316: RETURN_VALUE         
