# Disassembly for _strptime.TimeRE.compile
# From module file: _strptime

## co_consts:
('Return a compiled re object for the format string.',)

## co_names:
('re_compile', 'pattern', 'IGNORECASE')

## bytecode:

   0: RESUME               
   2: LOAD_GLOBAL          NULL + re_compile
  14: LOAD_FAST            self
  16: LOAD_METHOD          pattern
  38: LOAD_FAST            format
  40: PRECALL              
  44: CALL                 
  54: LOAD_GLOBAL          IGNORECASE
  66: PRECALL              
  70: CALL                 
  80: RETURN_VALUE         
