# Disassembly for _strptime.LocaleTime.__calc_date_time
# From module file: _strptime

## co_consts:
(None, (1999, 3, 17, 22, 44, 55, 2, 76, 0), (None, None, None), '%c', 0, '%x', 1, '%X', 2, ('%', '%%'), '%A', 3, '%B', '%a', '%b', '%p', ('1999', '%Y'), ('99', '%y'), ('22', '%H'), ('44', '%M'), ('55', '%S'), ('76', '%j'), ('17', '%d'), ('03', '%m'), ('3', '%m'), ('2', '%w'), ('10', '%I'), <code object <listcomp> at 0x00000240694665D0, file "_strptime.py", line 128>, ((0, '%c'), (1, '%x'), (2, '%X')), (1999, 1, 3, 1, 1, 1, 6, 3, 0), '00', '%W', '%U', '11')

## co_names:
('time', 'struct_time', 'strftime', 'lower', 'f_weekday', 'f_month', 'a_weekday', 'a_month', 'am_pm', 'extend', 'timezone', 'replace', 'LC_date_time', 'LC_date', 'LC_time')

## bytecode:

   0: RESUME               
   2: LOAD_GLOBAL          NULL + time
  14: LOAD_ATTR            struct_time
  24: LOAD_CONST           (1999, 3, 17, 22, 44, 55, 2, 76, 0)
  26: PRECALL              
  30: CALL                 
  40: STORE_FAST           time_tuple
  42: BUILD_LIST           
  44: LOAD_CONST           (None, None, None)
  46: LIST_EXTEND          
  48: STORE_FAST           date_time
  50: LOAD_GLOBAL          NULL + time
  62: LOAD_ATTR            strftime
  72: LOAD_CONST           '%c'
  74: LOAD_FAST            time_tuple
  76: PRECALL              
  80: CALL                 
  90: LOAD_METHOD          lower
 112: PRECALL              
 116: CALL                 
 126: LOAD_FAST            date_time
 128: LOAD_CONST           0
 130: STORE_SUBSCR         
 134: LOAD_GLOBAL          NULL + time
 146: LOAD_ATTR            strftime
 156: LOAD_CONST           '%x'
 158: LOAD_FAST            time_tuple
 160: PRECALL              
 164: CALL                 
 174: LOAD_METHOD          lower
 196: PRECALL              
 200: CALL                 
 210: LOAD_FAST            date_time
 212: LOAD_CONST           1
 214: STORE_SUBSCR         
 218: LOAD_GLOBAL          NULL + time
 230: LOAD_ATTR            strftime
 240: LOAD_CONST           '%X'
 242: LOAD_FAST            time_tuple
 244: PRECALL              
 248: CALL                 
 258: LOAD_METHOD          lower
 280: PRECALL              
 284: CALL                 
 294: LOAD_FAST            date_time
 296: LOAD_CONST           2
 298: STORE_SUBSCR         
 302: LOAD_CONST           ('%', '%%')
 304: LOAD_FAST            self
 306: LOAD_ATTR            f_weekday
 316: LOAD_CONST           2
 318: BINARY_SUBSCR        
 328: LOAD_CONST           '%A'
 330: BUILD_TUPLE          
 332: LOAD_FAST            self
 334: LOAD_ATTR            f_month
 344: LOAD_CONST           3
 346: BINARY_SUBSCR        
 356: LOAD_CONST           '%B'
 358: BUILD_TUPLE          
 360: LOAD_FAST            self
 362: LOAD_ATTR            a_weekday
 372: LOAD_CONST           2
 374: BINARY_SUBSCR        
 384: LOAD_CONST           '%a'
 386: BUILD_TUPLE          
 388: LOAD_FAST            self
 390: LOAD_ATTR            a_month
 400: LOAD_CONST           3
 402: BINARY_SUBSCR        
 412: LOAD_CONST           '%b'
 414: BUILD_TUPLE          
 416: LOAD_FAST            self
 418: LOAD_ATTR            am_pm
 428: LOAD_CONST           1
 430: BINARY_SUBSCR        
 440: LOAD_CONST           '%p'
 442: BUILD_TUPLE          
 444: LOAD_CONST           ('1999', '%Y')
 446: LOAD_CONST           ('99', '%y')
 448: LOAD_CONST           ('22', '%H')
 450: LOAD_CONST           ('44', '%M')
 452: LOAD_CONST           ('55', '%S')
 454: LOAD_CONST           ('76', '%j')
 456: LOAD_CONST           ('17', '%d')
 458: LOAD_CONST           ('03', '%m')
 460: LOAD_CONST           ('3', '%m')
 462: LOAD_CONST           ('2', '%w')
 464: LOAD_CONST           ('10', '%I')
 466: BUILD_LIST           
 468: STORE_FAST           replacement_pairs
 470: LOAD_FAST            replacement_pairs
 472: LOAD_METHOD          extend
 494: LOAD_CONST           <code object <listcomp> at 0x00000240694665D0, file "_strptime.py", line 128>
 496: MAKE_FUNCTION        
 498: LOAD_FAST            self
 500: LOAD_ATTR            timezone
 510: GET_ITER             
 512: PRECALL              
 516: CALL                 
 526: PRECALL              
 530: CALL                 
 540: POP_TOP              
 542: LOAD_CONST           ((0, '%c'), (1, '%x'), (2, '%X'))
 544: GET_ITER             
 546: FOR_ITER             to 784
 548: UNPACK_SEQUENCE      
 552: STORE_FAST           offset
 554: STORE_FAST           directive
 556: LOAD_FAST            date_time
 558: LOAD_FAST            offset
 560: BINARY_SUBSCR        
 570: STORE_FAST           current_format
 572: LOAD_FAST            replacement_pairs
 574: GET_ITER             
 576: FOR_ITER             to 636
 578: UNPACK_SEQUENCE      
 582: STORE_FAST           old
 584: STORE_FAST           new
 586: LOAD_FAST            old
 588: POP_JUMP_FORWARD_IF_FALSE to 634
 590: LOAD_FAST            current_format
 592: LOAD_METHOD          replace
 614: LOAD_FAST            old
 616: LOAD_FAST            new
 618: PRECALL              
 622: CALL                 
 632: STORE_FAST           current_format
 634: JUMP_BACKWARD        to 576
 636: LOAD_GLOBAL          NULL + time
 648: LOAD_ATTR            struct_time
 658: LOAD_CONST           (1999, 1, 3, 1, 1, 1, 6, 3, 0)
 660: PRECALL              
 664: CALL                 
 674: STORE_FAST           time_tuple
 676: LOAD_CONST           '00'
 678: LOAD_GLOBAL          NULL + time
 690: LOAD_ATTR            strftime
 700: LOAD_FAST            directive
 702: LOAD_FAST            time_tuple
 704: PRECALL              
 708: CALL                 
 718: CONTAINS_OP          
 720: POP_JUMP_FORWARD_IF_FALSE to 728
 722: LOAD_CONST           '%W'
 724: STORE_FAST           U_W
 726: JUMP_FORWARD         to 732
 728: LOAD_CONST           '%U'
 730: STORE_FAST           U_W
 732: LOAD_FAST            current_format
 734: LOAD_METHOD          replace
 756: LOAD_CONST           '11'
 758: LOAD_FAST            U_W
 760: PRECALL              
 764: CALL                 
 774: LOAD_FAST            date_time
 776: LOAD_FAST            offset
 778: STORE_SUBSCR         
 782: JUMP_BACKWARD        to 546
 784: LOAD_FAST            date_time
 786: LOAD_CONST           0
 788: BINARY_SUBSCR        
 798: LOAD_FAST            self
 800: STORE_ATTR           LC_date_time
 810: LOAD_FAST            date_time
 812: LOAD_CONST           1
 814: BINARY_SUBSCR        
 824: LOAD_FAST            self
 826: STORE_ATTR           LC_date
 836: LOAD_FAST            date_time
 838: LOAD_CONST           2
 840: BINARY_SUBSCR        
 850: LOAD_FAST            self
 852: STORE_ATTR           LC_time
 862: LOAD_CONST           None
 864: RETURN_VALUE         
