# Disassembly for _strptime.LocaleTime.__calc_weekday
# From module file: _strptime

## co_consts:
(None, <code object <listcomp> at 0x000002406944AEF0, file "_strptime.py", line 83>, 7, <code object <listcomp> at 0x000002406944AAB0, file "_strptime.py", line 84>)

## co_names:
('range', 'a_weekday', 'f_weekday')

## bytecode:

   0: RESUME               
   2: LOAD_CONST           <code object <listcomp> at 0x000002406944AEF0, file "_strptime.py", line 83>
   4: MAKE_FUNCTION        
   6: LOAD_GLOBAL          NULL + range
  18: LOAD_CONST           7
  20: PRECALL              
  24: CALL                 
  34: GET_ITER             
  36: PRECALL              
  40: CALL                 
  50: STORE_FAST           a_weekday
  52: LOAD_CONST           <code object <listcomp> at 0x000002406944AAB0, file "_strptime.py", line 84>
  54: MAKE_FUNCTION        
  56: LOAD_GLOBAL          NULL + range
  68: LOAD_CONST           7
  70: PRECALL              
  74: CALL                 
  84: GET_ITER             
  86: PRECALL              
  90: CALL                 
 100: STORE_FAST           f_weekday
 102: LOAD_FAST            a_weekday
 104: LOAD_FAST            self
 106: STORE_ATTR           a_weekday
 116: LOAD_FAST            f_weekday
 118: LOAD_FAST            self
 120: STORE_ATTR           f_weekday
 130: LOAD_CONST           None
 132: RETURN_VALUE         
