# Disassembly for _strptime.LocaleTime.__init__
# From module file: _strptime

## co_consts:
('Set all attributes.\n\n        Order of methods called matters for dependency reasons.\n\n        The locale language is set at the offset and then checked again before\n        exiting.  This is to make sure that the attributes were not set with a\n        mix of information from more than one locale.  This would most likely\n        happen when using threads where one thread calls a locale-dependent\n        function while another thread changes the locale while the function in\n        the other thread is still running.  Proper coding would call for\n        locks to prevent changing the locale while locale-dependent code is\n        running.  The check here is done in case someone does not think about\n        doing this.\n\n        Only other possible issue is if someone changed the timezone and did\n        not call tz.tzset .  That is an issue for the programmer, though,\n        since changing the timezone is worthless without that call.\n\n        ', 'locale changed during initialization', 'timezone changed during initialization', None)

## co_names:
('_getlang', 'lang', '_LocaleTime__calc_weekday', '_LocaleTime__calc_month', '_LocaleTime__calc_am_pm', '_LocaleTime__calc_timezone', '_LocaleTime__calc_date_time', 'ValueError', 'time', 'tzname', 'daylight')

## bytecode:

   0: RESUME               
   2: LOAD_GLOBAL          NULL + _getlang
  14: PRECALL              
  18: CALL                 
  28: LOAD_FAST            self
  30: STORE_ATTR           lang
  40: LOAD_FAST            self
  42: LOAD_METHOD          _LocaleTime__calc_weekday
  64: PRECALL              
  68: CALL                 
  78: POP_TOP              
  80: LOAD_FAST            self
  82: LOAD_METHOD          _LocaleTime__calc_month
 104: PRECALL              
 108: CALL                 
 118: POP_TOP              
 120: LOAD_FAST            self
 122: LOAD_METHOD          _LocaleTime__calc_am_pm
 144: PRECALL              
 148: CALL                 
 158: POP_TOP              
 160: LOAD_FAST            self
 162: LOAD_METHOD          _LocaleTime__calc_timezone
 184: PRECALL              
 188: CALL                 
 198: POP_TOP              
 200: LOAD_FAST            self
 202: LOAD_METHOD          _LocaleTime__calc_date_time
 224: PRECALL              
 228: CALL                 
 238: POP_TOP              
 240: LOAD_GLOBAL          NULL + _getlang
 252: PRECALL              
 256: CALL                 
 266: LOAD_FAST            self
 268: LOAD_ATTR            lang
 278: COMPARE_OP           !=
 284: POP_JUMP_FORWARD_IF_FALSE to 316
 286: LOAD_GLOBAL          NULL + ValueError
 298: LOAD_CONST           'locale changed during initialization'
 300: PRECALL              
 304: CALL                 
 314: RAISE_VARARGS        
 316: LOAD_GLOBAL          time
 328: LOAD_ATTR            tzname
 338: LOAD_FAST            self
 340: LOAD_ATTR            tzname
 350: COMPARE_OP           !=
 356: POP_JUMP_FORWARD_IF_TRUE to 400
 358: LOAD_GLOBAL          time
 370: LOAD_ATTR            daylight
 380: LOAD_FAST            self
 382: LOAD_ATTR            daylight
 392: COMPARE_OP           !=
 398: POP_JUMP_FORWARD_IF_FALSE to 430
 400: LOAD_GLOBAL          NULL + ValueError
 412: LOAD_CONST           'timezone changed during initialization'
 414: PRECALL              
 418: CALL                 
 428: RAISE_VARARGS        
 430: LOAD_CONST           None
 432: RETURN_VALUE         
