# Disassembly for _strptime.TimeRE.__init__.<genexpr>
# From module file: _strptime

## co_consts:
(None,)

## co_names:
()

## bytecode:

   0: RETURN_GENERATOR     
   2: POP_TOP              
   4: RESUME               
   6: LOAD_FAST            .0
   8: FOR_ITER             to 32
  10: STORE_FAST           tz_names
  12: LOAD_FAST            tz_names
  14: GET_ITER             
  16: FOR_ITER             to 30
  18: STORE_FAST           tz
  20: LOAD_FAST            tz
  22: YIELD_VALUE          
  24: RESUME               
  26: POP_TOP              
  28: JUMP_BACKWARD        to 16
  30: JUMP_BACKWARD        to 8
  32: LOAD_CONST           None
  34: RETURN_VALUE         
