# Disassembly for ast._Unparser.visit_FormattedValue
# From module file: ast

## co_consts:
(None, <code object unparse_inner at 0x00000240691EA430, file "ast.py", line 1204>, '{', '}', '\\', 'Unable to avoid backslash in f-string expression part', ' ', -1, '!', ':')

## co_names:
('delimit', 'value', 'ValueError', 'startswith', 'write', 'conversion', 'chr', 'format_spec', '_write_fstring_inner')

## bytecode:

   0: MAKE_CELL            self
   2: RESUME               
   4: LOAD_CLOSURE         self
   6: BUILD_TUPLE          
   8: LOAD_CONST           <code object unparse_inner at 0x00000240691EA430, file "ast.py", line 1204>
  10: MAKE_FUNCTION        closure
  12: STORE_FAST           unparse_inner
  14: LOAD_DEREF           self
  16: LOAD_METHOD          delimit
  38: LOAD_CONST           '{'
  40: LOAD_CONST           '}'
  42: PRECALL              
  46: CALL                 
  56: BEFORE_WITH          
  58: POP_TOP              
  60: PUSH_NULL            
  62: LOAD_FAST            unparse_inner
  64: LOAD_FAST            node
  66: LOAD_ATTR            value
  76: PRECALL              
  80: CALL                 
  90: STORE_FAST           expr
  92: LOAD_CONST           '\\'
  94: LOAD_FAST            expr
  96: CONTAINS_OP          
  98: POP_JUMP_FORWARD_IF_FALSE to 130
 100: LOAD_GLOBAL          NULL + ValueError
 112: LOAD_CONST           'Unable to avoid backslash in f-string expression part'
 114: PRECALL              
 118: CALL                 
 128: RAISE_VARARGS        
 130: LOAD_FAST            expr
 132: LOAD_METHOD          startswith
 154: LOAD_CONST           '{'
 156: PRECALL              
 160: CALL                 
 170: POP_JUMP_FORWARD_IF_FALSE to 214
 172: LOAD_DEREF           self
 174: LOAD_METHOD          write
 196: LOAD_CONST           ' '
 198: PRECALL              
 202: CALL                 
 212: POP_TOP              
 214: LOAD_DEREF           self
 216: LOAD_METHOD          write
 238: LOAD_FAST            expr
 240: PRECALL              
 244: CALL                 
 254: POP_TOP              
 256: LOAD_FAST            node
 258: LOAD_ATTR            conversion
 268: LOAD_CONST           -1
 270: COMPARE_OP           !=
 276: POP_JUMP_FORWARD_IF_FALSE to 362
 278: LOAD_DEREF           self
 280: LOAD_METHOD          write
 302: LOAD_CONST           '!'
 304: LOAD_GLOBAL          NULL + chr
 316: LOAD_FAST            node
 318: LOAD_ATTR            conversion
 328: PRECALL              
 332: CALL                 
 342: FORMAT_VALUE         
 344: BUILD_STRING         
 346: PRECALL              
 350: CALL                 
 360: POP_TOP              
 362: LOAD_FAST            node
 364: LOAD_ATTR            format_spec
 374: POP_JUMP_FORWARD_IF_FALSE to 470
 376: LOAD_DEREF           self
 378: LOAD_METHOD          write
 400: LOAD_CONST           ':'
 402: PRECALL              
 406: CALL                 
 416: POP_TOP              
 418: LOAD_DEREF           self
 420: LOAD_METHOD          _write_fstring_inner
 442: LOAD_FAST            node
 444: LOAD_ATTR            format_spec
 454: PRECALL              
 458: CALL                 
 468: POP_TOP              
 470: LOAD_CONST           None
 472: LOAD_CONST           None
 474: LOAD_CONST           None
 476: PRECALL              
 480: CALL                 
 490: POP_TOP              
 492: LOAD_CONST           None
 494: RETURN_VALUE         
 496: PUSH_EXC_INFO        
 498: WITH_EXCEPT_START    
 500: POP_JUMP_FORWARD_IF_TRUE to 510
 502: RERAISE              
 504: COPY                 
 506: POP_EXCEPT           
 508: RERAISE              
 510: POP_TOP              
 512: POP_EXCEPT           
 514: POP_TOP              
 516: POP_TOP              
 518: LOAD_CONST           None
 520: RETURN_VALUE         
