# Disassembly for ast.dump
# From module file: ast

## co_consts:
('\n    Return a formatted dump of the tree in node.  This is mainly useful for\n    debugging purposes.  If annotate_fields is true (by default),\n    the returned string will show the names and the values for fields.\n    If annotate_fields is false, the result string will be more compact by\n    omitting unambiguous field names.  Attributes such as line\n    numbers and column offsets are not dumped by default.  If this is wanted,\n    include_attributes can be set to true.  If indent is a non-negative\n    integer or string, then the tree will be pretty-printed with that indent\n    level. None (the default) selects the single line representation.\n    ', 0, <code object _format at 0x0000024068E96730, file "ast.py", line 125>, 'expected AST, got %r', None, ' ', (0,))

## co_names:
('isinstance', 'AST', 'TypeError', '__class__', '__name__', 'str')

## bytecode:

   0: MAKE_CELL            annotate_fields
   2: MAKE_CELL            include_attributes
   4: MAKE_CELL            indent
   6: MAKE_CELL            _format
   8: RESUME               
  10: LOAD_CONST           (0,)
  12: LOAD_CLOSURE         _format
  14: LOAD_CLOSURE         annotate_fields
  16: LOAD_CLOSURE         include_attributes
  18: LOAD_CLOSURE         indent
  20: BUILD_TUPLE          
  22: LOAD_CONST           <code object _format at 0x0000024068E96730, file "ast.py", line 125>
  24: MAKE_FUNCTION        defaults, closure
  26: STORE_DEREF          _format
  28: LOAD_GLOBAL          NULL + isinstance
  40: LOAD_FAST            node
  42: LOAD_GLOBAL          AST
  54: PRECALL              
  58: CALL                 
  68: POP_JUMP_FORWARD_IF_TRUE to 126
  70: LOAD_GLOBAL          NULL + TypeError
  82: LOAD_CONST           'expected AST, got %r'
  84: LOAD_FAST            node
  86: LOAD_ATTR            __class__
  96: LOAD_ATTR            __name__
 106: BINARY_OP            %
 110: PRECALL              
 114: CALL                 
 124: RAISE_VARARGS        
 126: LOAD_DEREF           indent
 128: POP_JUMP_FORWARD_IF_NONE to 182
 130: LOAD_GLOBAL          NULL + isinstance
 142: LOAD_DEREF           indent
 144: LOAD_GLOBAL          str
 156: PRECALL              
 160: CALL                 
 170: POP_JUMP_FORWARD_IF_TRUE to 182
 172: LOAD_CONST           ' '
 174: LOAD_DEREF           indent
 176: BINARY_OP            *
 180: STORE_DEREF          indent
 182: PUSH_NULL            
 184: LOAD_DEREF           _format
 186: LOAD_FAST            node
 188: PRECALL              
 192: CALL                 
 202: LOAD_CONST           0
 204: BINARY_SUBSCR        
 214: RETURN_VALUE         
