# Disassembly for ast._Unparser.visit_Match
# From module file: ast

## co_consts:
(None, 'match ')

## co_names:
('fill', 'traverse', 'subject', 'block', 'cases')

## bytecode:

   0: RESUME               
   2: LOAD_FAST            self
   4: LOAD_METHOD          fill
  26: LOAD_CONST           'match '
  28: PRECALL              
  32: CALL                 
  42: POP_TOP              
  44: LOAD_FAST            self
  46: LOAD_METHOD          traverse
  68: LOAD_FAST            node
  70: LOAD_ATTR            subject
  80: PRECALL              
  84: CALL                 
  94: POP_TOP              
  96: LOAD_FAST            self
  98: LOAD_METHOD          block
 120: PRECALL              
 124: CALL                 
 134: BEFORE_WITH          
 136: POP_TOP              
 138: LOAD_FAST            node
 140: LOAD_ATTR            cases
 150: GET_ITER             
 152: FOR_ITER             to 200
 154: STORE_FAST           case
 156: LOAD_FAST            self
 158: LOAD_METHOD          traverse
 180: LOAD_FAST            case
 182: PRECALL              
 186: CALL                 
 196: POP_TOP              
 198: JUMP_BACKWARD        to 152
 200: NOP                  
 202: LOAD_CONST           None
 204: LOAD_CONST           None
 206: LOAD_CONST           None
 208: PRECALL              
 212: CALL                 
 222: POP_TOP              
 224: LOAD_CONST           None
 226: RETURN_VALUE         
 228: PUSH_EXC_INFO        
 230: WITH_EXCEPT_START    
 232: POP_JUMP_FORWARD_IF_TRUE to 242
 234: RERAISE              
 236: COPY                 
 238: POP_EXCEPT           
 240: RERAISE              
 242: POP_TOP              
 244: POP_EXCEPT           
 246: POP_TOP              
 248: POP_TOP              
 250: LOAD_CONST           None
 252: RETURN_VALUE         
