# Disassembly for ast.literal_eval
# From module file: ast

## co_consts:
('\n    Evaluate an expression node or a string containing only a Python\n    expression.  The string or node provided may only consist of the following\n    Python literal structures: strings, bytes, numbers, tuples, lists, dicts,\n    sets, booleans, and None.\n\n    Caution: A complex expression can overflow the C stack and cause a crash.\n    ', ' \t', 'eval', ('mode',), <code object _raise_malformed_node at 0x000002406941A550, file "ast.py", line 67>, <code object _convert_num at 0x00000240691C1BB0, file "ast.py", line 72>, <code object _convert_signed_num at 0x00000240691F60B0, file "ast.py", line 76>, <code object _convert at 0x00000240695B0950, file "ast.py", line 84>)

## co_names:
('isinstance', 'str', 'parse', 'lstrip', 'Expression', 'body')

## bytecode:

   0: MAKE_CELL            _convert
   2: MAKE_CELL            _convert_num
   4: MAKE_CELL            _convert_signed_num
   6: MAKE_CELL            _raise_malformed_node
   8: RESUME               
  10: LOAD_GLOBAL          NULL + isinstance
  22: LOAD_FAST            node_or_string
  24: LOAD_GLOBAL          str
  36: PRECALL              
  40: CALL                 
  50: POP_JUMP_FORWARD_IF_FALSE to 124
  52: LOAD_GLOBAL          NULL + parse
  64: LOAD_FAST            node_or_string
  66: LOAD_METHOD          lstrip
  88: LOAD_CONST           ' \t'
  90: PRECALL              
  94: CALL                 
 104: LOAD_CONST           'eval'
 106: KW_NAMES             
 108: PRECALL              
 112: CALL                 
 122: STORE_FAST           node_or_string
 124: LOAD_GLOBAL          NULL + isinstance
 136: LOAD_FAST            node_or_string
 138: LOAD_GLOBAL          Expression
 150: PRECALL              
 154: CALL                 
 164: POP_JUMP_FORWARD_IF_FALSE to 180
 166: LOAD_FAST            node_or_string
 168: LOAD_ATTR            body
 178: STORE_FAST           node_or_string
 180: LOAD_CONST           <code object _raise_malformed_node at 0x000002406941A550, file "ast.py", line 67>
 182: MAKE_FUNCTION        
 184: STORE_DEREF          _raise_malformed_node
 186: LOAD_CLOSURE         _raise_malformed_node
 188: BUILD_TUPLE          
 190: LOAD_CONST           <code object _convert_num at 0x00000240691C1BB0, file "ast.py", line 72>
 192: MAKE_FUNCTION        closure
 194: STORE_DEREF          _convert_num
 196: LOAD_CLOSURE         _convert_num
 198: BUILD_TUPLE          
 200: LOAD_CONST           <code object _convert_signed_num at 0x00000240691F60B0, file "ast.py", line 76>
 202: MAKE_FUNCTION        closure
 204: STORE_DEREF          _convert_signed_num
 206: LOAD_CLOSURE         _convert
 208: LOAD_CLOSURE         _convert_num
 210: LOAD_CLOSURE         _convert_signed_num
 212: LOAD_CLOSURE         _raise_malformed_node
 214: BUILD_TUPLE          
 216: LOAD_CONST           <code object _convert at 0x00000240695B0950, file "ast.py", line 84>
 218: MAKE_FUNCTION        closure
 220: STORE_DEREF          _convert
 222: PUSH_NULL            
 224: LOAD_DEREF           _convert
 226: LOAD_FAST            node_or_string
 228: PRECALL              
 232: CALL                 
 242: RETURN_VALUE         
