# Disassembly for ast._Unparser.visit_FormattedValue.unparse_inner
# From module file: ast

## co_consts:
(None, True, ('_avoid_backslashes',))

## co_names:
('type', 'set_precedence', '_Precedence', 'TEST', 'next', 'visit')

## bytecode:

   0: COPY_FREE_VARS       
   2: RESUME               
   4: PUSH_NULL            
   6: LOAD_GLOBAL          NULL + type
  18: LOAD_DEREF           self
  20: PRECALL              
  24: CALL                 
  34: LOAD_CONST           True
  36: KW_NAMES             
  38: PRECALL              
  42: CALL                 
  52: STORE_FAST           unparser
  54: LOAD_FAST            unparser
  56: LOAD_METHOD          set_precedence
  78: LOAD_GLOBAL          _Precedence
  90: LOAD_ATTR            TEST
 100: LOAD_METHOD          next
 122: PRECALL              
 126: CALL                 
 136: LOAD_FAST            inner
 138: PRECALL              
 142: CALL                 
 152: POP_TOP              
 154: LOAD_FAST            unparser
 156: LOAD_METHOD          visit
 178: LOAD_FAST            inner
 180: PRECALL              
 184: CALL                 
 194: RETURN_VALUE         
