# Disassembly for ast._Unparser.visit_Subscript
# From module file: ast

## co_consts:
(None, <code object is_non_empty_tuple at 0x0000024069CC9530, file "ast.py", line 1491>, '[', ']')

## co_names:
('set_precedence', '_Precedence', 'ATOM', 'value', 'traverse', 'delimit', 'slice', 'items_view', 'elts')

## bytecode:

   0: RESUME               
   2: LOAD_CONST           <code object is_non_empty_tuple at 0x0000024069CC9530, file "ast.py", line 1491>
   4: MAKE_FUNCTION        
   6: STORE_FAST           is_non_empty_tuple
   8: LOAD_FAST            self
  10: LOAD_METHOD          set_precedence
  32: LOAD_GLOBAL          _Precedence
  44: LOAD_ATTR            ATOM
  54: LOAD_FAST            node
  56: LOAD_ATTR            value
  66: PRECALL              
  70: CALL                 
  80: POP_TOP              
  82: LOAD_FAST            self
  84: LOAD_METHOD          traverse
 106: LOAD_FAST            node
 108: LOAD_ATTR            value
 118: PRECALL              
 122: CALL                 
 132: POP_TOP              
 134: LOAD_FAST            self
 136: LOAD_METHOD          delimit
 158: LOAD_CONST           '['
 160: LOAD_CONST           ']'
 162: PRECALL              
 166: CALL                 
 176: BEFORE_WITH          
 178: POP_TOP              
 180: PUSH_NULL            
 182: LOAD_FAST            is_non_empty_tuple
 184: LOAD_FAST            node
 186: LOAD_ATTR            slice
 196: PRECALL              
 200: CALL                 
 210: POP_JUMP_FORWARD_IF_FALSE to 288
 212: LOAD_FAST            self
 214: LOAD_METHOD          items_view
 236: LOAD_FAST            self
 238: LOAD_ATTR            traverse
 248: LOAD_FAST            node
 250: LOAD_ATTR            slice
 260: LOAD_ATTR            elts
 270: PRECALL              
 274: CALL                 
 284: POP_TOP              
 286: JUMP_FORWARD         to 340
 288: LOAD_FAST            self
 290: LOAD_METHOD          traverse
 312: LOAD_FAST            node
 314: LOAD_ATTR            slice
 324: PRECALL              
 328: CALL                 
 338: POP_TOP              
 340: LOAD_CONST           None
 342: LOAD_CONST           None
 344: LOAD_CONST           None
 346: PRECALL              
 350: CALL                 
 360: POP_TOP              
 362: LOAD_CONST           None
 364: RETURN_VALUE         
 366: PUSH_EXC_INFO        
 368: WITH_EXCEPT_START    
 370: POP_JUMP_FORWARD_IF_TRUE to 380
 372: RERAISE              
 374: COPY                 
 376: POP_EXCEPT           
 378: RERAISE              
 380: POP_TOP              
 382: POP_EXCEPT           
 384: POP_TOP              
 386: POP_TOP              
 388: LOAD_CONST           None
 390: RETURN_VALUE         
