# Disassembly for ast.fix_missing_locations
# From module file: ast

## co_consts:
('\n    When you compile a node tree with compile(), the compiler expects lineno and\n    col_offset attributes for every node that supports them.  This is rather\n    tedious to fill in for generated nodes, so this helper adds these attributes\n    recursively where not already set, by setting them to the values of the\n    parent node.  It works recursively starting at *node*.\n    ', <code object _fix at 0x0000024068D6F7F0, file "ast.py", line 205>, 1, 0)

## co_names:
()

## bytecode:

   0: MAKE_CELL            _fix
   2: RESUME               
   4: LOAD_CLOSURE         _fix
   6: BUILD_TUPLE          
   8: LOAD_CONST           <code object _fix at 0x0000024068D6F7F0, file "ast.py", line 205>
  10: MAKE_FUNCTION        closure
  12: STORE_DEREF          _fix
  14: PUSH_NULL            
  16: LOAD_DEREF           _fix
  18: LOAD_FAST            node
  20: LOAD_CONST           1
  22: LOAD_CONST           0
  24: LOAD_CONST           1
  26: LOAD_CONST           0
  28: PRECALL              
  32: CALL                 
  42: POP_TOP              
  44: LOAD_FAST            node
  46: RETURN_VALUE         
