# Disassembly for ast.literal_eval._convert_signed_num
# From module file: ast

## co_consts:
(None,)

## co_names:
('isinstance', 'UnaryOp', 'op', 'UAdd', 'USub', 'operand')

## bytecode:

   0: COPY_FREE_VARS       
   2: RESUME               
   4: LOAD_GLOBAL          NULL + isinstance
  16: LOAD_FAST            node
  18: LOAD_GLOBAL          UnaryOp
  30: PRECALL              
  34: CALL                 
  44: POP_JUMP_FORWARD_IF_FALSE to 208
  46: LOAD_GLOBAL          NULL + isinstance
  58: LOAD_FAST            node
  60: LOAD_ATTR            op
  70: LOAD_GLOBAL          UAdd
  82: LOAD_GLOBAL          USub
  94: BUILD_TUPLE          
  96: PRECALL              
 100: CALL                 
 110: POP_JUMP_FORWARD_IF_FALSE to 208
 112: PUSH_NULL            
 114: LOAD_DEREF           _convert_num
 116: LOAD_FAST            node
 118: LOAD_ATTR            operand
 128: PRECALL              
 132: CALL                 
 142: STORE_FAST           operand
 144: LOAD_GLOBAL          NULL + isinstance
 156: LOAD_FAST            node
 158: LOAD_ATTR            op
 168: LOAD_GLOBAL          UAdd
 180: PRECALL              
 184: CALL                 
 194: POP_JUMP_FORWARD_IF_FALSE to 202
 196: LOAD_FAST            operand
 198: UNARY_POSITIVE       
 200: RETURN_VALUE         
 202: LOAD_FAST            operand
 204: UNARY_NEGATIVE       
 206: RETURN_VALUE         
 208: PUSH_NULL            
 210: LOAD_DEREF           _convert_num
 212: LOAD_FAST            node
 214: PRECALL              
 218: CALL                 
 228: RETURN_VALUE         
