# Disassembly for ast._Unparser
# From module file: ast

## co_consts:
('_Unparser', 'Methods in this class recursively traverse an AST and\n    output source code for the abstract syntax; original formatting\n    is disregarded.', False, ('_avoid_backslashes',), <code object __init__ at 0x000002406941AC10, file "ast.py", line 688>, <code object interleave at 0x000002406949CBB0, file "ast.py", line 696>, <code object items_view at 0x000002406949CD20, file "ast.py", line 708>, <code object maybe_newline at 0x0000024069CC8530, file "ast.py", line 718>, '', <code object fill at 0x00000240693D3DF0, file "ast.py", line 723>, <code object write at 0x0000024069CC8630, file "ast.py", line 729>, None, <code object buffered at 0x0000024069CC8730, file "ast.py", line 733>, ('extra',), <code object block at 0x000002406949CE90, file "ast.py", line 743>, <code object delimit at 0x000002406941AD30, file "ast.py", line 757>, <code object delimit_if at 0x000002406944B660, file "ast.py", line 766>, <code object require_parens at 0x000002406941AE50, file "ast.py", line 772>, <code object get_precedence at 0x000002406944B770, file "ast.py", line 776>, <code object set_precedence at 0x0000024069467830, file "ast.py", line 779>, <code object get_raw_docstring at 0x0000024069CD8030, file "ast.py", line 783>, <code object get_type_comment at 0x000002406941AF70, file "ast.py", line 799>, <code object traverse at 0x000002406949D170, file "ast.py", line 804>, <code object visit at 0x0000024069CDC030, file "ast.py", line 814>, <code object _write_docstring_and_traverse_body at 0x00000240691F6250, file "ast.py", line 821>, <code object visit_Module at 0x000002406922CAB0, file "ast.py", line 828>, <code object visit_FunctionType at 0x00000240691DB2F0, file "ast.py", line 836>, <code object visit_Expr at 0x000002406949D2E0, file "ast.py", line 845>, <code object visit_NamedExpr at 0x0000024068E21B60, file "ast.py", line 850>, <code object visit_Import at 0x00000240693AB5F0, file "ast.py", line 857>, <code object visit_ImportFrom at 0x000002406947C7B0, file "ast.py", line 861>, <code object visit_Assign at 0x0000024068C8F100, file "ast.py", line 869>, <code object visit_AugAssign at 0x0000024069498E30, file "ast.py", line 879>, <code object visit_AnnAssign at 0x0000024066C249C0, file "ast.py", line 885>, <code object visit_Return at 0x00000240691C1FD0, file "ast.py", line 895>, <code object visit_Pass at 0x000002406945FC30, file "ast.py", line 901>, <code object visit_Break at 0x000002406945FD20, file "ast.py", line 904>, <code object visit_Continue at 0x000002406945FE10, file "ast.py", line 907>, <code object visit_Delete at 0x00000240693AB730, file "ast.py", line 910>, <code object visit_Assert at 0x000002406942E100, file "ast.py", line 914>, <code object visit_Global at 0x00000240693AB870, file "ast.py", line 921>, <code object visit_Nonlocal at 0x00000240693AB9B0, file "ast.py", line 925>, <code object visit_Await at 0x0000024068E20EA0, file "ast.py", line 929>, <code object visit_Yield at 0x0000024068E21720, file "ast.py", line 937>, <code object visit_YieldFrom at 0x0000024068BF6C60, file "ast.py", line 945>, <code object visit_Raise at 0x0000024069CD8230, file "ast.py", line 953>, <code object do_visit_try at 0x000002406957FD20, file "ast.py", line 965>, <code object visit_Try at 0x0000024069CDC4F0, file "ast.py", line 980>, <code object visit_TryStar at 0x0000024069CDC620, file "ast.py", line 988>, <code object visit_ExceptHandler at 0x0000024068E1DBC0, file "ast.py", line 996>, <code object visit_ClassDef at 0x0000024068C359B0, file "ast.py", line 1007>, <code object visit_FunctionDef at 0x0000024069CE4210, file "ast.py", line 1031>, <code object visit_AsyncFunctionDef at 0x0000024069CE4300, file "ast.py", line 1034>, <code object _function_helper at 0x0000024069580A60, file "ast.py", line 1037>, <code object visit_For at 0x0000024069CE43F0, file "ast.py", line 1052>, <code object visit_AsyncFor at 0x0000024069CE44E0, file "ast.py", line 1055>, <code object _for_helper at 0x0000024069581450, file "ast.py", line 1058>, <code object visit_If at 0x0000024068E17490, file "ast.py", line 1071>, <code object visit_While at 0x0000024068DA8CD0, file "ast.py", line 1089>, <code object visit_With at 0x0000024069366310, file "ast.py", line 1099>, <code object visit_AsyncWith at 0x0000024069366500, file "ast.py", line 1105>, ('quote_types', 'escape_special_whitespace'), <code object _str_literal_helper at 0x0000024068E7CE80, file "ast.py", line 1111>, ('quote_types',), <code object _write_str_avoiding_backslashes at 0x00000240693ABAF0, file "ast.py", line 1149>, <code object visit_JoinedStr at 0x0000024068D03690, file "ast.py", line 1155>, <code object _write_fstring_inner at 0x0000024068D30140, file "ast.py", line 1190>, <code object visit_FormattedValue at 0x0000024068DC1E00, file "ast.py", line 1203>, <code object visit_Name at 0x0000024069CC8F30, file "ast.py", line 1225>, <code object _write_docstring at 0x000002406949D730, file "ast.py", line 1228>, <code object _write_constant at 0x0000024068E1E0A0, file "ast.py", line 1234>, <code object visit_Constant at 0x0000024068BD5780, file "ast.py", line 1248>, <code object visit_List at 0x000002406949D8A0, file "ast.py", line 1260>, <code object visit_ListComp at 0x000002406942E290, file "ast.py", line 1264>, <code object visit_GeneratorExp at 0x000002406942E420, file "ast.py", line 1270>, <code object visit_SetComp at 0x000002406942E5B0, file "ast.py", line 1276>, <code object visit_DictComp at 0x00000240693666F0, file "ast.py", line 1282>, <code object visit_comprehension at 0x0000024068C09860, file "ast.py", line 1290>, <code object visit_IfExp at 0x0000024068DBE910, file "ast.py", line 1304>, <code object visit_Set at 0x000002406934FCF0, file "ast.py", line 1314>, <code object visit_Dict at 0x00000240691F63F0, file "ast.py", line 1323>, <code object visit_Tuple at 0x00000240691DB860, file "ast.py", line 1345>, '~', 'not', '+', '-', ('Invert', 'Not', 'UAdd', 'USub'), ('not', '~', '+', '-'), <code object visit_UnaryOp at 0x0000024068D6CC00, file "ast.py", line 1361>, '*', '@', '/', '%', '<<', '>>', '|', '^', '&', '//', '**', ('Add', 'Sub', 'Mult', 'MatMult', 'Div', 'Mod', 'LShift', 'RShift', 'BitOr', 'BitXor', 'BitAnd', 'FloorDiv', 'Pow'), ('+', '-', '*', '@', '/', '%', '<<', '>>', '|', '^', '&', '//', '**'), ('**',), <code object visit_BinOp at 0x0000024068DBFDA0, file "ast.py", line 1406>, '==', '!=', '<', '<=', '>', '>=', 'is', 'is not', 'in', 'not in', ('Eq', 'NotEq', 'Lt', 'LtE', 'Gt', 'GtE', 'Is', 'IsNot', 'In', 'NotIn'), <code object visit_Compare at 0x0000024068E7D130, file "ast.py", line 1436>, 'and', 'or', ('And', 'Or'), ('and', 'or'), <code object visit_BoolOp at 0x00000240691DBA30, file "ast.py", line 1447>, <code object visit_Attribute at 0x0000024068DB6A10, file "ast.py", line 1461>, <code object visit_Call at 0x0000024066C27550, file "ast.py", line 1472>, <code object visit_Subscript at 0x0000024068D6FC90, file "ast.py", line 1490>, <code object visit_Starred at 0x000002406949DB80, file "ast.py", line 1506>, <code object visit_Ellipsis at 0x0000024069CE5020, file "ast.py", line 1511>, <code object visit_Slice at 0x000002406947CD50, file "ast.py", line 1514>, <code object visit_Match at 0x0000024069499370, file "ast.py", line 1524>, <code object visit_arg at 0x000002406949DCF0, file "ast.py", line 1531>, <code object visit_arguments at 0x0000024068CF54C0, file "ast.py", line 1537>, <code object visit_keyword at 0x000002406942E740, file "ast.py", line 1588>, <code object visit_Lambda at 0x0000024068C07570, file "ast.py", line 1596>, <code object visit_alias at 0x0000024069CF4170, file "ast.py", line 1607>, <code object visit_withitem at 0x000002406949DE60, file "ast.py", line 1612>, <code object visit_match_case at 0x0000024068E22820, file "ast.py", line 1618>, <code object visit_MatchValue at 0x0000024069CC9830, file "ast.py", line 1627>, <code object visit_MatchSingleton at 0x0000024069CC9930, file "ast.py", line 1630>, <code object visit_MatchSequence at 0x000002406949DFD0, file "ast.py", line 1633>, <code object visit_MatchStar at 0x000002406944BBB0, file "ast.py", line 1639>, <code object visit_MatchMapping at 0x0000024068BB8E50, file "ast.py", line 1645>, <code object visit_MatchClass at 0x0000024068D33320, file "ast.py", line 1665>, <code object visit_MatchAs at 0x0000024068DA87D0, file "ast.py", line 1688>, <code object visit_MatchOr at 0x000002406947D110, file "ast.py", line 1701>, ('',), (None,))

## co_names:
('__name__', '__module__', '__qualname__', '__doc__', '__init__', 'interleave', 'items_view', 'maybe_newline', 'fill', 'write', 'contextmanager', 'buffered', 'block', 'delimit', 'delimit_if', 'require_parens', 'get_precedence', 'set_precedence', 'get_raw_docstring', 'get_type_comment', 'traverse', 'visit', '_write_docstring_and_traverse_body', 'visit_Module', 'visit_FunctionType', 'visit_Expr', 'visit_NamedExpr', 'visit_Import', 'visit_ImportFrom', 'visit_Assign', 'visit_AugAssign', 'visit_AnnAssign', 'visit_Return', 'visit_Pass', 'visit_Break', 'visit_Continue', 'visit_Delete', 'visit_Assert', 'visit_Global', 'visit_Nonlocal', 'visit_Await', 'visit_Yield', 'visit_YieldFrom', 'visit_Raise', 'do_visit_try', 'visit_Try', 'visit_TryStar', 'visit_ExceptHandler', 'visit_ClassDef', 'visit_FunctionDef', 'visit_AsyncFunctionDef', '_function_helper', 'visit_For', 'visit_AsyncFor', '_for_helper', 'visit_If', 'visit_While', 'visit_With', 'visit_AsyncWith', '_ALL_QUOTES', '_str_literal_helper', '_write_str_avoiding_backslashes', 'visit_JoinedStr', '_write_fstring_inner', 'visit_FormattedValue', 'visit_Name', '_write_docstring', '_write_constant', 'visit_Constant', 'visit_List', 'visit_ListComp', 'visit_GeneratorExp', 'visit_SetComp', 'visit_DictComp', 'visit_comprehension', 'visit_IfExp', 'visit_Set', 'visit_Dict', 'visit_Tuple', 'unop', '_Precedence', 'NOT', 'FACTOR', 'unop_precedence', 'visit_UnaryOp', 'binop', 'ARITH', 'TERM', 'SHIFT', 'BOR', 'BXOR', 'BAND', 'POWER', 'binop_precedence', 'frozenset', 'binop_rassoc', 'visit_BinOp', 'cmpops', 'visit_Compare', 'boolops', 'AND', 'OR', 'boolop_precedence', 'visit_BoolOp', 'visit_Attribute', 'visit_Call', 'visit_Subscript', 'visit_Starred', 'visit_Ellipsis', 'visit_Slice', 'visit_Match', 'visit_arg', 'visit_arguments', 'visit_keyword', 'visit_Lambda', 'visit_alias', 'visit_withitem', 'visit_match_case', 'visit_MatchValue', 'visit_MatchSingleton', 'visit_MatchSequence', 'visit_MatchStar', 'visit_MatchMapping', 'visit_MatchClass', 'visit_MatchAs', 'visit_MatchOr', '__classcell__')

## bytecode:

   0: MAKE_CELL            __class__
   2: RESUME               
   4: LOAD_NAME            __name__
   6: STORE_NAME           __module__
   8: LOAD_CONST           '_Unparser'
  10: STORE_NAME           __qualname__
  12: LOAD_CONST           'Methods in this class recursively traverse an AST and\n    output source code for the abstract syntax; original formatting\n    is disregarded.'
  14: STORE_NAME           __doc__
  16: LOAD_CONST           False
  18: LOAD_CONST           ('_avoid_backslashes',)
  20: BUILD_CONST_KEY_MAP  
  22: LOAD_CONST           <code object __init__ at 0x000002406941AC10, file "ast.py", line 688>
  24: MAKE_FUNCTION        kwdefaults
  26: STORE_NAME           __init__
  28: LOAD_CONST           <code object interleave at 0x000002406949CBB0, file "ast.py", line 696>
  30: MAKE_FUNCTION        
  32: STORE_NAME           interleave
  34: LOAD_CONST           <code object items_view at 0x000002406949CD20, file "ast.py", line 708>
  36: MAKE_FUNCTION        
  38: STORE_NAME           items_view
  40: LOAD_CONST           <code object maybe_newline at 0x0000024069CC8530, file "ast.py", line 718>
  42: MAKE_FUNCTION        
  44: STORE_NAME           maybe_newline
  46: LOAD_CONST           ('',)
  48: LOAD_CONST           <code object fill at 0x00000240693D3DF0, file "ast.py", line 723>
  50: MAKE_FUNCTION        defaults
  52: STORE_NAME           fill
  54: LOAD_CONST           <code object write at 0x0000024069CC8630, file "ast.py", line 729>
  56: MAKE_FUNCTION        
  58: STORE_NAME           write
  60: LOAD_NAME            contextmanager
  62: LOAD_CONST           (None,)
  64: LOAD_CONST           <code object buffered at 0x0000024069CC8730, file "ast.py", line 733>
  66: MAKE_FUNCTION        defaults
  68: PRECALL              
  72: CALL                 
  82: STORE_NAME           buffered
  84: LOAD_NAME            contextmanager
  86: LOAD_CONST           None
  88: LOAD_CONST           ('extra',)
  90: BUILD_CONST_KEY_MAP  
  92: LOAD_CONST           <code object block at 0x000002406949CE90, file "ast.py", line 743>
  94: MAKE_FUNCTION        kwdefaults
  96: PRECALL              
 100: CALL                 
 110: STORE_NAME           block
 112: LOAD_NAME            contextmanager
 114: LOAD_CONST           <code object delimit at 0x000002406941AD30, file "ast.py", line 757>
 116: MAKE_FUNCTION        
 118: PRECALL              
 122: CALL                 
 132: STORE_NAME           delimit
 134: LOAD_CONST           <code object delimit_if at 0x000002406944B660, file "ast.py", line 766>
 136: MAKE_FUNCTION        
 138: STORE_NAME           delimit_if
 140: LOAD_CONST           <code object require_parens at 0x000002406941AE50, file "ast.py", line 772>
 142: MAKE_FUNCTION        
 144: STORE_NAME           require_parens
 146: LOAD_CONST           <code object get_precedence at 0x000002406944B770, file "ast.py", line 776>
 148: MAKE_FUNCTION        
 150: STORE_NAME           get_precedence
 152: LOAD_CONST           <code object set_precedence at 0x0000024069467830, file "ast.py", line 779>
 154: MAKE_FUNCTION        
 156: STORE_NAME           set_precedence
 158: LOAD_CONST           <code object get_raw_docstring at 0x0000024069CD8030, file "ast.py", line 783>
 160: MAKE_FUNCTION        
 162: STORE_NAME           get_raw_docstring
 164: LOAD_CONST           <code object get_type_comment at 0x000002406941AF70, file "ast.py", line 799>
 166: MAKE_FUNCTION        
 168: STORE_NAME           get_type_comment
 170: LOAD_CLOSURE         __class__
 172: BUILD_TUPLE          
 174: LOAD_CONST           <code object traverse at 0x000002406949D170, file "ast.py", line 804>
 176: MAKE_FUNCTION        closure
 178: STORE_NAME           traverse
 180: LOAD_CONST           <code object visit at 0x0000024069CDC030, file "ast.py", line 814>
 182: MAKE_FUNCTION        
 184: STORE_NAME           visit
 186: LOAD_CONST           <code object _write_docstring_and_traverse_body at 0x00000240691F6250, file "ast.py", line 821>
 188: MAKE_FUNCTION        
 190: STORE_NAME           _write_docstring_and_traverse_body
 192: LOAD_CONST           <code object visit_Module at 0x000002406922CAB0, file "ast.py", line 828>
 194: MAKE_FUNCTION        
 196: STORE_NAME           visit_Module
 198: LOAD_CONST           <code object visit_FunctionType at 0x00000240691DB2F0, file "ast.py", line 836>
 200: MAKE_FUNCTION        
 202: STORE_NAME           visit_FunctionType
 204: LOAD_CONST           <code object visit_Expr at 0x000002406949D2E0, file "ast.py", line 845>
 206: MAKE_FUNCTION        
 208: STORE_NAME           visit_Expr
 210: LOAD_CONST           <code object visit_NamedExpr at 0x0000024068E21B60, file "ast.py", line 850>
 212: MAKE_FUNCTION        
 214: STORE_NAME           visit_NamedExpr
 216: LOAD_CONST           <code object visit_Import at 0x00000240693AB5F0, file "ast.py", line 857>
 218: MAKE_FUNCTION        
 220: STORE_NAME           visit_Import
 222: LOAD_CONST           <code object visit_ImportFrom at 0x000002406947C7B0, file "ast.py", line 861>
 224: MAKE_FUNCTION        
 226: STORE_NAME           visit_ImportFrom
 228: LOAD_CONST           <code object visit_Assign at 0x0000024068C8F100, file "ast.py", line 869>
 230: MAKE_FUNCTION        
 232: STORE_NAME           visit_Assign
 234: LOAD_CONST           <code object visit_AugAssign at 0x0000024069498E30, file "ast.py", line 879>
 236: MAKE_FUNCTION        
 238: STORE_NAME           visit_AugAssign
 240: LOAD_CONST           <code object visit_AnnAssign at 0x0000024066C249C0, file "ast.py", line 885>
 242: MAKE_FUNCTION        
 244: STORE_NAME           visit_AnnAssign
 246: LOAD_CONST           <code object visit_Return at 0x00000240691C1FD0, file "ast.py", line 895>
 248: MAKE_FUNCTION        
 250: STORE_NAME           visit_Return
 252: LOAD_CONST           <code object visit_Pass at 0x000002406945FC30, file "ast.py", line 901>
 254: MAKE_FUNCTION        
 256: STORE_NAME           visit_Pass
 258: LOAD_CONST           <code object visit_Break at 0x000002406945FD20, file "ast.py", line 904>
 260: MAKE_FUNCTION        
 262: STORE_NAME           visit_Break
 264: LOAD_CONST           <code object visit_Continue at 0x000002406945FE10, file "ast.py", line 907>
 266: MAKE_FUNCTION        
 268: STORE_NAME           visit_Continue
 270: LOAD_CONST           <code object visit_Delete at 0x00000240693AB730, file "ast.py", line 910>
 272: MAKE_FUNCTION        
 274: STORE_NAME           visit_Delete
 276: LOAD_CONST           <code object visit_Assert at 0x000002406942E100, file "ast.py", line 914>
 278: MAKE_FUNCTION        
 280: STORE_NAME           visit_Assert
 282: LOAD_CONST           <code object visit_Global at 0x00000240693AB870, file "ast.py", line 921>
 284: MAKE_FUNCTION        
 286: STORE_NAME           visit_Global
 288: LOAD_CONST           <code object visit_Nonlocal at 0x00000240693AB9B0, file "ast.py", line 925>
 290: MAKE_FUNCTION        
 292: STORE_NAME           visit_Nonlocal
 294: LOAD_CONST           <code object visit_Await at 0x0000024068E20EA0, file "ast.py", line 929>
 296: MAKE_FUNCTION        
 298: STORE_NAME           visit_Await
 300: LOAD_CONST           <code object visit_Yield at 0x0000024068E21720, file "ast.py", line 937>
 302: MAKE_FUNCTION        
 304: STORE_NAME           visit_Yield
 306: LOAD_CONST           <code object visit_YieldFrom at 0x0000024068BF6C60, file "ast.py", line 945>
 308: MAKE_FUNCTION        
 310: STORE_NAME           visit_YieldFrom
 312: LOAD_CONST           <code object visit_Raise at 0x0000024069CD8230, file "ast.py", line 953>
 314: MAKE_FUNCTION        
 316: STORE_NAME           visit_Raise
 318: LOAD_CONST           <code object do_visit_try at 0x000002406957FD20, file "ast.py", line 965>
 320: MAKE_FUNCTION        
 322: STORE_NAME           do_visit_try
 324: LOAD_CONST           <code object visit_Try at 0x0000024069CDC4F0, file "ast.py", line 980>
 326: MAKE_FUNCTION        
 328: STORE_NAME           visit_Try
 330: LOAD_CONST           <code object visit_TryStar at 0x0000024069CDC620, file "ast.py", line 988>
 332: MAKE_FUNCTION        
 334: STORE_NAME           visit_TryStar
 336: LOAD_CONST           <code object visit_ExceptHandler at 0x0000024068E1DBC0, file "ast.py", line 996>
 338: MAKE_FUNCTION        
 340: STORE_NAME           visit_ExceptHandler
 342: LOAD_CONST           <code object visit_ClassDef at 0x0000024068C359B0, file "ast.py", line 1007>
 344: MAKE_FUNCTION        
 346: STORE_NAME           visit_ClassDef
 348: LOAD_CONST           <code object visit_FunctionDef at 0x0000024069CE4210, file "ast.py", line 1031>
 350: MAKE_FUNCTION        
 352: STORE_NAME           visit_FunctionDef
 354: LOAD_CONST           <code object visit_AsyncFunctionDef at 0x0000024069CE4300, file "ast.py", line 1034>
 356: MAKE_FUNCTION        
 358: STORE_NAME           visit_AsyncFunctionDef
 360: LOAD_CONST           <code object _function_helper at 0x0000024069580A60, file "ast.py", line 1037>
 362: MAKE_FUNCTION        
 364: STORE_NAME           _function_helper
 366: LOAD_CONST           <code object visit_For at 0x0000024069CE43F0, file "ast.py", line 1052>
 368: MAKE_FUNCTION        
 370: STORE_NAME           visit_For
 372: LOAD_CONST           <code object visit_AsyncFor at 0x0000024069CE44E0, file "ast.py", line 1055>
 374: MAKE_FUNCTION        
 376: STORE_NAME           visit_AsyncFor
 378: LOAD_CONST           <code object _for_helper at 0x0000024069581450, file "ast.py", line 1058>
 380: MAKE_FUNCTION        
 382: STORE_NAME           _for_helper
 384: LOAD_CONST           <code object visit_If at 0x0000024068E17490, file "ast.py", line 1071>
 386: MAKE_FUNCTION        
 388: STORE_NAME           visit_If
 390: LOAD_CONST           <code object visit_While at 0x0000024068DA8CD0, file "ast.py", line 1089>
 392: MAKE_FUNCTION        
 394: STORE_NAME           visit_While
 396: LOAD_CONST           <code object visit_With at 0x0000024069366310, file "ast.py", line 1099>
 398: MAKE_FUNCTION        
 400: STORE_NAME           visit_With
 402: LOAD_CONST           <code object visit_AsyncWith at 0x0000024069366500, file "ast.py", line 1105>
 404: MAKE_FUNCTION        
 406: STORE_NAME           visit_AsyncWith
 408: LOAD_NAME            _ALL_QUOTES
 410: LOAD_CONST           False
 412: LOAD_CONST           ('quote_types', 'escape_special_whitespace')
 414: BUILD_CONST_KEY_MAP  
 416: LOAD_CONST           <code object _str_literal_helper at 0x0000024068E7CE80, file "ast.py", line 1111>
 418: MAKE_FUNCTION        kwdefaults
 420: STORE_NAME           _str_literal_helper
 422: LOAD_NAME            _ALL_QUOTES
 424: LOAD_CONST           ('quote_types',)
 426: BUILD_CONST_KEY_MAP  
 428: LOAD_CONST           <code object _write_str_avoiding_backslashes at 0x00000240693ABAF0, file "ast.py", line 1149>
 430: MAKE_FUNCTION        kwdefaults
 432: STORE_NAME           _write_str_avoiding_backslashes
 434: LOAD_CONST           <code object visit_JoinedStr at 0x0000024068D03690, file "ast.py", line 1155>
 436: MAKE_FUNCTION        
 438: STORE_NAME           visit_JoinedStr
 440: LOAD_CONST           <code object _write_fstring_inner at 0x0000024068D30140, file "ast.py", line 1190>
 442: MAKE_FUNCTION        
 444: STORE_NAME           _write_fstring_inner
 446: LOAD_CONST           <code object visit_FormattedValue at 0x0000024068DC1E00, file "ast.py", line 1203>
 448: MAKE_FUNCTION        
 450: STORE_NAME           visit_FormattedValue
 452: LOAD_CONST           <code object visit_Name at 0x0000024069CC8F30, file "ast.py", line 1225>
 454: MAKE_FUNCTION        
 456: STORE_NAME           visit_Name
 458: LOAD_CONST           <code object _write_docstring at 0x000002406949D730, file "ast.py", line 1228>
 460: MAKE_FUNCTION        
 462: STORE_NAME           _write_docstring
 464: LOAD_CONST           <code object _write_constant at 0x0000024068E1E0A0, file "ast.py", line 1234>
 466: MAKE_FUNCTION        
 468: STORE_NAME           _write_constant
 470: LOAD_CONST           <code object visit_Constant at 0x0000024068BD5780, file "ast.py", line 1248>
 472: MAKE_FUNCTION        
 474: STORE_NAME           visit_Constant
 476: LOAD_CONST           <code object visit_List at 0x000002406949D8A0, file "ast.py", line 1260>
 478: MAKE_FUNCTION        
 480: STORE_NAME           visit_List
 482: LOAD_CONST           <code object visit_ListComp at 0x000002406942E290, file "ast.py", line 1264>
 484: MAKE_FUNCTION        
 486: STORE_NAME           visit_ListComp
 488: LOAD_CONST           <code object visit_GeneratorExp at 0x000002406942E420, file "ast.py", line 1270>
 490: MAKE_FUNCTION        
 492: STORE_NAME           visit_GeneratorExp
 494: LOAD_CONST           <code object visit_SetComp at 0x000002406942E5B0, file "ast.py", line 1276>
 496: MAKE_FUNCTION        
 498: STORE_NAME           visit_SetComp
 500: LOAD_CONST           <code object visit_DictComp at 0x00000240693666F0, file "ast.py", line 1282>
 502: MAKE_FUNCTION        
 504: STORE_NAME           visit_DictComp
 506: LOAD_CONST           <code object visit_comprehension at 0x0000024068C09860, file "ast.py", line 1290>
 508: MAKE_FUNCTION        
 510: STORE_NAME           visit_comprehension
 512: LOAD_CONST           <code object visit_IfExp at 0x0000024068DBE910, file "ast.py", line 1304>
 514: MAKE_FUNCTION        
 516: STORE_NAME           visit_IfExp
 518: LOAD_CONST           <code object visit_Set at 0x000002406934FCF0, file "ast.py", line 1314>
 520: MAKE_FUNCTION        
 522: STORE_NAME           visit_Set
 524: LOAD_CONST           <code object visit_Dict at 0x00000240691F63F0, file "ast.py", line 1323>
 526: MAKE_FUNCTION        
 528: STORE_NAME           visit_Dict
 530: LOAD_CONST           <code object visit_Tuple at 0x00000240691DB860, file "ast.py", line 1345>
 532: MAKE_FUNCTION        
 534: STORE_NAME           visit_Tuple
 536: LOAD_CONST           '~'
 538: LOAD_CONST           'not'
 540: LOAD_CONST           '+'
 542: LOAD_CONST           '-'
 544: LOAD_CONST           ('Invert', 'Not', 'UAdd', 'USub')
 546: BUILD_CONST_KEY_MAP  
 548: STORE_NAME           unop
 550: LOAD_NAME            _Precedence
 552: LOAD_ATTR            NOT
 562: LOAD_NAME            _Precedence
 564: LOAD_ATTR            FACTOR
 574: LOAD_NAME            _Precedence
 576: LOAD_ATTR            FACTOR
 586: LOAD_NAME            _Precedence
 588: LOAD_ATTR            FACTOR
 598: LOAD_CONST           ('not', '~', '+', '-')
 600: BUILD_CONST_KEY_MAP  
 602: STORE_NAME           unop_precedence
 604: LOAD_CONST           <code object visit_UnaryOp at 0x0000024068D6CC00, file "ast.py", line 1361>
 606: MAKE_FUNCTION        
 608: STORE_NAME           visit_UnaryOp
 610: LOAD_CONST           '+'
 612: LOAD_CONST           '-'
 614: LOAD_CONST           '*'
 616: LOAD_CONST           '@'
 618: LOAD_CONST           '/'
 620: LOAD_CONST           '%'
 622: LOAD_CONST           '<<'
 624: LOAD_CONST           '>>'
 626: LOAD_CONST           '|'
 628: LOAD_CONST           '^'
 630: LOAD_CONST           '&'
 632: LOAD_CONST           '//'
 634: LOAD_CONST           '**'
 636: LOAD_CONST           ('Add', 'Sub', 'Mult', 'MatMult', 'Div', 'Mod', 'LShift', 'RShift', 'BitOr', 'BitXor', 'BitAnd', 'FloorDiv', 'Pow')
 638: BUILD_CONST_KEY_MAP  
 640: STORE_NAME           binop
 642: LOAD_NAME            _Precedence
 644: LOAD_ATTR            ARITH
 654: LOAD_NAME            _Precedence
 656: LOAD_ATTR            ARITH
 666: LOAD_NAME            _Precedence
 668: LOAD_ATTR            TERM
 678: LOAD_NAME            _Precedence
 680: LOAD_ATTR            TERM
 690: LOAD_NAME            _Precedence
 692: LOAD_ATTR            TERM
 702: LOAD_NAME            _Precedence
 704: LOAD_ATTR            TERM
 714: LOAD_NAME            _Precedence
 716: LOAD_ATTR            SHIFT
 726: LOAD_NAME            _Precedence
 728: LOAD_ATTR            SHIFT
 738: LOAD_NAME            _Precedence
 740: LOAD_ATTR            BOR
 750: LOAD_NAME            _Precedence
 752: LOAD_ATTR            BXOR
 762: LOAD_NAME            _Precedence
 764: LOAD_ATTR            BAND
 774: LOAD_NAME            _Precedence
 776: LOAD_ATTR            TERM
 786: LOAD_NAME            _Precedence
 788: LOAD_ATTR            POWER
 798: LOAD_CONST           ('+', '-', '*', '@', '/', '%', '<<', '>>', '|', '^', '&', '//', '**')
 800: BUILD_CONST_KEY_MAP  
 802: STORE_NAME           binop_precedence
 804: PUSH_NULL            
 806: LOAD_NAME            frozenset
 808: LOAD_CONST           ('**',)
 810: PRECALL              
 814: CALL                 
 824: STORE_NAME           binop_rassoc
 826: LOAD_CONST           <code object visit_BinOp at 0x0000024068DBFDA0, file "ast.py", line 1406>
 828: MAKE_FUNCTION        
 830: STORE_NAME           visit_BinOp
 832: LOAD_CONST           '=='
 834: LOAD_CONST           '!='
 836: LOAD_CONST           '<'
 838: LOAD_CONST           '<='
 840: LOAD_CONST           '>'
 842: LOAD_CONST           '>='
 844: LOAD_CONST           'is'
 846: LOAD_CONST           'is not'
 848: LOAD_CONST           'in'
 850: LOAD_CONST           'not in'
 852: LOAD_CONST           ('Eq', 'NotEq', 'Lt', 'LtE', 'Gt', 'GtE', 'Is', 'IsNot', 'In', 'NotIn')
 854: BUILD_CONST_KEY_MAP  
 856: STORE_NAME           cmpops
 858: LOAD_CONST           <code object visit_Compare at 0x0000024068E7D130, file "ast.py", line 1436>
 860: MAKE_FUNCTION        
 862: STORE_NAME           visit_Compare
 864: LOAD_CONST           'and'
 866: LOAD_CONST           'or'
 868: LOAD_CONST           ('And', 'Or')
 870: BUILD_CONST_KEY_MAP  
 872: STORE_NAME           boolops
 874: LOAD_NAME            _Precedence
 876: LOAD_ATTR            AND
 886: LOAD_NAME            _Precedence
 888: LOAD_ATTR            OR
 898: LOAD_CONST           ('and', 'or')
 900: BUILD_CONST_KEY_MAP  
 902: STORE_NAME           boolop_precedence
 904: LOAD_CONST           <code object visit_BoolOp at 0x00000240691DBA30, file "ast.py", line 1447>
 906: MAKE_FUNCTION        
 908: STORE_NAME           visit_BoolOp
 910: LOAD_CONST           <code object visit_Attribute at 0x0000024068DB6A10, file "ast.py", line 1461>
 912: MAKE_FUNCTION        
 914: STORE_NAME           visit_Attribute
 916: LOAD_CONST           <code object visit_Call at 0x0000024066C27550, file "ast.py", line 1472>
 918: MAKE_FUNCTION        
 920: STORE_NAME           visit_Call
 922: LOAD_CONST           <code object visit_Subscript at 0x0000024068D6FC90, file "ast.py", line 1490>
 924: MAKE_FUNCTION        
 926: STORE_NAME           visit_Subscript
 928: LOAD_CONST           <code object visit_Starred at 0x000002406949DB80, file "ast.py", line 1506>
 930: MAKE_FUNCTION        
 932: STORE_NAME           visit_Starred
 934: LOAD_CONST           <code object visit_Ellipsis at 0x0000024069CE5020, file "ast.py", line 1511>
 936: MAKE_FUNCTION        
 938: STORE_NAME           visit_Ellipsis
 940: LOAD_CONST           <code object visit_Slice at 0x000002406947CD50, file "ast.py", line 1514>
 942: MAKE_FUNCTION        
 944: STORE_NAME           visit_Slice
 946: LOAD_CONST           <code object visit_Match at 0x0000024069499370, file "ast.py", line 1524>
 948: MAKE_FUNCTION        
 950: STORE_NAME           visit_Match
 952: LOAD_CONST           <code object visit_arg at 0x000002406949DCF0, file "ast.py", line 1531>
 954: MAKE_FUNCTION        
 956: STORE_NAME           visit_arg
 958: LOAD_CONST           <code object visit_arguments at 0x0000024068CF54C0, file "ast.py", line 1537>
 960: MAKE_FUNCTION        
 962: STORE_NAME           visit_arguments
 964: LOAD_CONST           <code object visit_keyword at 0x000002406942E740, file "ast.py", line 1588>
 966: MAKE_FUNCTION        
 968: STORE_NAME           visit_keyword
 970: LOAD_CONST           <code object visit_Lambda at 0x0000024068C07570, file "ast.py", line 1596>
 972: MAKE_FUNCTION        
 974: STORE_NAME           visit_Lambda
 976: LOAD_CONST           <code object visit_alias at 0x0000024069CF4170, file "ast.py", line 1607>
 978: MAKE_FUNCTION        
 980: STORE_NAME           visit_alias
 982: LOAD_CONST           <code object visit_withitem at 0x000002406949DE60, file "ast.py", line 1612>
 984: MAKE_FUNCTION        
 986: STORE_NAME           visit_withitem
 988: LOAD_CONST           <code object visit_match_case at 0x0000024068E22820, file "ast.py", line 1618>
 990: MAKE_FUNCTION        
 992: STORE_NAME           visit_match_case
 994: LOAD_CONST           <code object visit_MatchValue at 0x0000024069CC9830, file "ast.py", line 1627>
 996: MAKE_FUNCTION        
 998: STORE_NAME           visit_MatchValue
1000: LOAD_CONST           <code object visit_MatchSingleton at 0x0000024069CC9930, file "ast.py", line 1630>
1002: MAKE_FUNCTION        
1004: STORE_NAME           visit_MatchSingleton
1006: LOAD_CONST           <code object visit_MatchSequence at 0x000002406949DFD0, file "ast.py", line 1633>
1008: MAKE_FUNCTION        
1010: STORE_NAME           visit_MatchSequence
1012: LOAD_CONST           <code object visit_MatchStar at 0x000002406944BBB0, file "ast.py", line 1639>
1014: MAKE_FUNCTION        
1016: STORE_NAME           visit_MatchStar
1018: LOAD_CONST           <code object visit_MatchMapping at 0x0000024068BB8E50, file "ast.py", line 1645>
1020: MAKE_FUNCTION        
1022: STORE_NAME           visit_MatchMapping
1024: LOAD_CONST           <code object visit_MatchClass at 0x0000024068D33320, file "ast.py", line 1665>
1026: MAKE_FUNCTION        
1028: STORE_NAME           visit_MatchClass
1030: LOAD_CONST           <code object visit_MatchAs at 0x0000024068DA87D0, file "ast.py", line 1688>
1032: MAKE_FUNCTION        
1034: STORE_NAME           visit_MatchAs
1036: LOAD_CONST           <code object visit_MatchOr at 0x000002406947D110, file "ast.py", line 1701>
1038: MAKE_FUNCTION        
1040: STORE_NAME           visit_MatchOr
1042: LOAD_CLOSURE         __class__
1044: COPY                 
1046: STORE_NAME           __classcell__
1048: RETURN_VALUE         
