# Disassembly for ast.Ellipsis
# From module file: ast

## co_consts:
('Ellipsis', (), <code object __new__ at 0x000002406941A9D0, file "ast.py", line 576>, None)

## co_names:
('__name__', '__module__', '__qualname__', '_fields', '__new__')

## bytecode:

   0: RESUME               
   2: LOAD_NAME            __name__
   4: STORE_NAME           __module__
   6: LOAD_CONST           'Ellipsis'
   8: STORE_NAME           __qualname__
  10: LOAD_CONST           ()
  12: STORE_NAME           _fields
  14: LOAD_CONST           <code object __new__ at 0x000002406941A9D0, file "ast.py", line 576>
  16: MAKE_FUNCTION        
  18: STORE_NAME           __new__
  20: LOAD_CONST           None
  22: RETURN_VALUE         
