# Disassembly for ast._Unparser.do_visit_try
# From module file: ast

## co_consts:
(None, 'try', 'else', 'finally')

## co_names:
('fill', 'block', 'traverse', 'body', 'handlers', 'orelse', 'finalbody')

## bytecode:

   0: RESUME               
   2: LOAD_FAST            self
   4: LOAD_METHOD          fill
  26: LOAD_CONST           'try'
  28: PRECALL              
  32: CALL                 
  42: POP_TOP              
  44: LOAD_FAST            self
  46: LOAD_METHOD          block
  68: PRECALL              
  72: CALL                 
  82: BEFORE_WITH          
  84: POP_TOP              
  86: LOAD_FAST            self
  88: LOAD_METHOD          traverse
 110: LOAD_FAST            node
 112: LOAD_ATTR            body
 122: PRECALL              
 126: CALL                 
 136: POP_TOP              
 138: LOAD_CONST           None
 140: LOAD_CONST           None
 142: LOAD_CONST           None
 144: PRECALL              
 148: CALL                 
 158: POP_TOP              
 160: JUMP_FORWARD         to 184
 162: PUSH_EXC_INFO        
 164: WITH_EXCEPT_START    
 166: POP_JUMP_FORWARD_IF_TRUE to 176
 168: RERAISE              
 170: COPY                 
 172: POP_EXCEPT           
 174: RERAISE              
 176: POP_TOP              
 178: POP_EXCEPT           
 180: POP_TOP              
 182: POP_TOP              
 184: LOAD_FAST            node
 186: LOAD_ATTR            handlers
 196: GET_ITER             
 198: FOR_ITER             to 246
 200: STORE_FAST           ex
 202: LOAD_FAST            self
 204: LOAD_METHOD          traverse
 226: LOAD_FAST            ex
 228: PRECALL              
 232: CALL                 
 242: POP_TOP              
 244: JUMP_BACKWARD        to 198
 246: LOAD_FAST            node
 248: LOAD_ATTR            orelse
 258: POP_JUMP_FORWARD_IF_FALSE to 442
 260: LOAD_FAST            self
 262: LOAD_METHOD          fill
 284: LOAD_CONST           'else'
 286: PRECALL              
 290: CALL                 
 300: POP_TOP              
 302: LOAD_FAST            self
 304: LOAD_METHOD          block
 326: PRECALL              
 330: CALL                 
 340: BEFORE_WITH          
 342: POP_TOP              
 344: LOAD_FAST            self
 346: LOAD_METHOD          traverse
 368: LOAD_FAST            node
 370: LOAD_ATTR            orelse
 380: PRECALL              
 384: CALL                 
 394: POP_TOP              
 396: LOAD_CONST           None
 398: LOAD_CONST           None
 400: LOAD_CONST           None
 402: PRECALL              
 406: CALL                 
 416: POP_TOP              
 418: JUMP_FORWARD         to 442
 420: PUSH_EXC_INFO        
 422: WITH_EXCEPT_START    
 424: POP_JUMP_FORWARD_IF_TRUE to 434
 426: RERAISE              
 428: COPY                 
 430: POP_EXCEPT           
 432: RERAISE              
 434: POP_TOP              
 436: POP_EXCEPT           
 438: POP_TOP              
 440: POP_TOP              
 442: LOAD_FAST            node
 444: LOAD_ATTR            finalbody
 454: POP_JUMP_FORWARD_IF_FALSE to 644
 456: LOAD_FAST            self
 458: LOAD_METHOD          fill
 480: LOAD_CONST           'finally'
 482: PRECALL              
 486: CALL                 
 496: POP_TOP              
 498: LOAD_FAST            self
 500: LOAD_METHOD          block
 522: PRECALL              
 526: CALL                 
 536: BEFORE_WITH          
 538: POP_TOP              
 540: LOAD_FAST            self
 542: LOAD_METHOD          traverse
 564: LOAD_FAST            node
 566: LOAD_ATTR            finalbody
 576: PRECALL              
 580: CALL                 
 590: POP_TOP              
 592: LOAD_CONST           None
 594: LOAD_CONST           None
 596: LOAD_CONST           None
 598: PRECALL              
 602: CALL                 
 612: POP_TOP              
 614: LOAD_CONST           None
 616: RETURN_VALUE         
 618: PUSH_EXC_INFO        
 620: WITH_EXCEPT_START    
 622: POP_JUMP_FORWARD_IF_TRUE to 632
 624: RERAISE              
 626: COPY                 
 628: POP_EXCEPT           
 630: RERAISE              
 632: POP_TOP              
 634: POP_EXCEPT           
 636: POP_TOP              
 638: POP_TOP              
 640: LOAD_CONST           None
 642: RETURN_VALUE         
 644: LOAD_CONST           None
 646: RETURN_VALUE         
