# Disassembly for ast.dump._format.<genexpr>
# From module file: ast

## co_consts:
(0, None)

## co_names:
()

## bytecode:

   0: COPY_FREE_VARS       
   2: RETURN_GENERATOR     
   4: POP_TOP              
   6: RESUME               
   8: LOAD_FAST            .0
  10: FOR_ITER             to 56
  12: STORE_FAST           x
  14: PUSH_NULL            
  16: LOAD_DEREF           _format
  18: LOAD_FAST            x
  20: LOAD_DEREF           level
  22: PRECALL              
  26: CALL                 
  36: LOAD_CONST           0
  38: BINARY_SUBSCR        
  48: YIELD_VALUE          
  50: RESUME               
  52: POP_TOP              
  54: JUMP_BACKWARD        to 10
  56: LOAD_CONST           None
  58: RETURN_VALUE         
