# Disassembly for ast._Unparser.visit_Delete
# From module file: ast

## co_consts:
(None, 'del ', <code object <lambda> at 0x000002406945FF00, file "ast.py", line 912>)

## co_names:
('fill', 'interleave', 'traverse', 'targets')

## bytecode:

   0: MAKE_CELL            self
   2: RESUME               
   4: LOAD_DEREF           self
   6: LOAD_METHOD          fill
  28: LOAD_CONST           'del '
  30: PRECALL              
  34: CALL                 
  44: POP_TOP              
  46: LOAD_DEREF           self
  48: LOAD_METHOD          interleave
  70: LOAD_CLOSURE         self
  72: BUILD_TUPLE          
  74: LOAD_CONST           <code object <lambda> at 0x000002406945FF00, file "ast.py", line 912>
  76: MAKE_FUNCTION        closure
  78: LOAD_DEREF           self
  80: LOAD_ATTR            traverse
  90: LOAD_FAST            node
  92: LOAD_ATTR            targets
 102: PRECALL              
 106: CALL                 
 116: POP_TOP              
 118: LOAD_CONST           None
 120: RETURN_VALUE         
