# Disassembly for ast._Unparser.maybe_newline
# From module file: ast

## co_consts:
("Adds a newline if it isn't the start of generated source", '\n', None)

## co_names:
('_source', 'write')

## bytecode:

   0: RESUME               
   2: LOAD_FAST            self
   4: LOAD_ATTR            _source
  14: POP_JUMP_FORWARD_IF_FALSE to 62
  16: LOAD_FAST            self
  18: LOAD_METHOD          write
  40: LOAD_CONST           '\n'
  42: PRECALL              
  46: CALL                 
  56: POP_TOP              
  58: LOAD_CONST           None
  60: RETURN_VALUE         
  62: LOAD_CONST           None
  64: RETURN_VALUE         
