# Disassembly for ast._Unparser.fill
# From module file: ast

## co_consts:
('Indent a piece of text and append it, according to the current\n        indentation level', '    ', None)

## co_names:
('maybe_newline', 'write', '_indent')

## bytecode:

   0: RESUME               
   2: LOAD_FAST            self
   4: LOAD_METHOD          maybe_newline
  26: PRECALL              
  30: CALL                 
  40: POP_TOP              
  42: LOAD_FAST            self
  44: LOAD_METHOD          write
  66: LOAD_CONST           '    '
  68: LOAD_FAST            self
  70: LOAD_ATTR            _indent
  80: BINARY_OP            *
  84: LOAD_FAST            text
  86: BINARY_OP            +
  90: PRECALL              
  94: CALL                 
 104: POP_TOP              
 106: LOAD_CONST           None
 108: RETURN_VALUE         
