# Disassembly for ast._Unparser.get_raw_docstring
# From module file: ast

## co_consts:
('If a docstring node is found in the body of the *node* parameter,\n        return that docstring node, None otherwise.\n\n        Logic mirrored from ``_PyAST_GetDocString``.', 1, None, 0)

## co_names:
('isinstance', 'AsyncFunctionDef', 'FunctionDef', 'ClassDef', 'Module', 'len', 'body', 'Expr', 'value', 'Constant', 'str')

## bytecode:

   0: RESUME               
   2: LOAD_GLOBAL          NULL + isinstance
  14: LOAD_FAST            node
  16: LOAD_GLOBAL          AsyncFunctionDef
  28: LOAD_GLOBAL          FunctionDef
  40: LOAD_GLOBAL          ClassDef
  52: LOAD_GLOBAL          Module
  64: BUILD_TUPLE          
  66: PRECALL              
  70: CALL                 
  80: POP_JUMP_FORWARD_IF_FALSE to 130
  82: LOAD_GLOBAL          NULL + len
  94: LOAD_FAST            node
  96: LOAD_ATTR            body
 106: PRECALL              
 110: CALL                 
 120: LOAD_CONST           1
 122: COMPARE_OP           <
 128: POP_JUMP_FORWARD_IF_FALSE to 134
 130: LOAD_CONST           None
 132: RETURN_VALUE         
 134: LOAD_FAST            node
 136: LOAD_ATTR            body
 146: LOAD_CONST           0
 148: BINARY_SUBSCR        
 158: STORE_FAST           node
 160: LOAD_GLOBAL          NULL + isinstance
 172: LOAD_FAST            node
 174: LOAD_GLOBAL          Expr
 186: PRECALL              
 190: CALL                 
 200: POP_JUMP_FORWARD_IF_TRUE to 206
 202: LOAD_CONST           None
 204: RETURN_VALUE         
 206: LOAD_FAST            node
 208: LOAD_ATTR            value
 218: STORE_FAST           node
 220: LOAD_GLOBAL          NULL + isinstance
 232: LOAD_FAST            node
 234: LOAD_GLOBAL          Constant
 246: PRECALL              
 250: CALL                 
 260: POP_JUMP_FORWARD_IF_FALSE to 318
 262: LOAD_GLOBAL          NULL + isinstance
 274: LOAD_FAST            node
 276: LOAD_ATTR            value
 286: LOAD_GLOBAL          str
 298: PRECALL              
 302: CALL                 
 312: POP_JUMP_FORWARD_IF_FALSE to 322
 314: LOAD_FAST            node
 316: RETURN_VALUE         
 318: LOAD_CONST           None
 320: RETURN_VALUE         
 322: LOAD_CONST           None
 324: RETURN_VALUE         
