# Disassembly for ast._Unparser._str_literal_helper.escape_char
# From module file: ast

## co_consts:
(None, '\n\t', '\\', 'unicode_escape', 'ascii')

## co_names:
('isprintable', 'encode', 'decode')

## bytecode:

   0: COPY_FREE_VARS       
   2: RESUME               
   4: LOAD_DEREF           escape_special_whitespace
   6: POP_JUMP_FORWARD_IF_TRUE to 20
   8: LOAD_FAST            c
  10: LOAD_CONST           '\n\t'
  12: CONTAINS_OP          
  14: POP_JUMP_FORWARD_IF_FALSE to 20
  16: LOAD_FAST            c
  18: RETURN_VALUE         
  20: LOAD_FAST            c
  22: LOAD_CONST           '\\'
  24: COMPARE_OP           ==
  30: POP_JUMP_FORWARD_IF_TRUE to 72
  32: LOAD_FAST            c
  34: LOAD_METHOD          isprintable
  56: PRECALL              
  60: CALL                 
  70: POP_JUMP_FORWARD_IF_TRUE to 152
  72: LOAD_FAST            c
  74: LOAD_METHOD          encode
  96: LOAD_CONST           'unicode_escape'
  98: PRECALL              
 102: CALL                 
 112: LOAD_METHOD          decode
 134: LOAD_CONST           'ascii'
 136: PRECALL              
 140: CALL                 
 150: RETURN_VALUE         
 152: LOAD_FAST            c
 154: RETURN_VALUE         
