# Disassembly for ast._pad_whitespace
# From module file: ast

## co_consts:
("Replace all chars except '\\f\\t' in a line with spaces.", '', '\x0c\t', ' ')

## co_names:
()

## bytecode:

   0: RESUME               
   2: LOAD_CONST           ''
   4: STORE_FAST           result
   6: LOAD_FAST            source
   8: GET_ITER             
  10: FOR_ITER             to 46
  12: STORE_FAST           c
  14: LOAD_FAST            c
  16: LOAD_CONST           '\x0c\t'
  18: CONTAINS_OP          
  20: POP_JUMP_FORWARD_IF_FALSE to 34
  22: LOAD_FAST            result
  24: LOAD_FAST            c
  26: BINARY_OP            +=
  30: STORE_FAST           result
  32: JUMP_BACKWARD        to 10
  34: LOAD_FAST            result
  36: LOAD_CONST           ' '
  38: BINARY_OP            +=
  42: STORE_FAST           result
  44: JUMP_BACKWARD        to 10
  46: LOAD_FAST            result
  48: RETURN_VALUE         
