# Disassembly for ast.walk
# From module file: ast

## co_consts:
("\n    Recursively yield all descendant nodes in the tree starting at *node*\n    (including *node* itself), in no specified order.  This is useful if you\n    only want to modify nodes in place and don't care about the context.\n    ", 0, ('deque',), None)

## co_names:
('collections', 'deque', 'popleft', 'extend', 'iter_child_nodes')

## bytecode:

   0: RETURN_GENERATOR     
   2: POP_TOP              
   4: RESUME               
   6: LOAD_CONST           0
   8: LOAD_CONST           ('deque',)
  10: IMPORT_NAME          collections
  12: IMPORT_FROM          deque
  14: STORE_FAST           deque
  16: POP_TOP              
  18: PUSH_NULL            
  20: LOAD_FAST            deque
  22: LOAD_FAST            node
  24: BUILD_LIST           
  26: PRECALL              
  30: CALL                 
  40: STORE_FAST           todo
  42: LOAD_FAST            todo
  44: POP_JUMP_FORWARD_IF_FALSE to 170
  46: LOAD_FAST            todo
  48: LOAD_METHOD          popleft
  70: PRECALL              
  74: CALL                 
  84: STORE_FAST           node
  86: LOAD_FAST            todo
  88: LOAD_METHOD          extend
 110: LOAD_GLOBAL          NULL + iter_child_nodes
 122: LOAD_FAST            node
 124: PRECALL              
 128: CALL                 
 138: PRECALL              
 142: CALL                 
 152: POP_TOP              
 154: LOAD_FAST            node
 156: YIELD_VALUE          
 158: RESUME               
 160: POP_TOP              
 162: LOAD_FAST            todo
 164: POP_JUMP_BACKWARD_IF_TRUE to 46
 166: LOAD_CONST           None
 168: RETURN_VALUE         
 170: LOAD_CONST           None
 172: RETURN_VALUE         
