# Disassembly for ast._Unparser.visit_BoolOp.increasing_level_traverse
# From module file: ast

## co_consts:
(None,)

## co_names:
('next', 'set_precedence', 'traverse')

## bytecode:

   0: COPY_FREE_VARS       
   2: RESUME               
   4: LOAD_DEREF           operator_precedence
   6: LOAD_METHOD          next
  28: PRECALL              
  32: CALL                 
  42: STORE_DEREF          operator_precedence
  44: LOAD_DEREF           self
  46: LOAD_METHOD          set_precedence
  68: LOAD_DEREF           operator_precedence
  70: LOAD_FAST            node
  72: PRECALL              
  76: CALL                 
  86: POP_TOP              
  88: LOAD_DEREF           self
  90: LOAD_METHOD          traverse
 112: LOAD_FAST            node
 114: PRECALL              
 118: CALL                 
 128: POP_TOP              
 130: LOAD_CONST           None
 132: RETURN_VALUE         
