# Disassembly for ast._Unparser.visit_arguments
# From module file: ast

## co_consts:
(None, True, 1, False, ', ', '=', ', /', '*', ': ', '**')

## co_names:
('posonlyargs', 'args', 'len', 'defaults', 'enumerate', 'zip', 'write', 'traverse', 'vararg', 'kwonlyargs', 'arg', 'annotation', 'kw_defaults', 'kwarg')

## bytecode:

   0: RESUME               
   2: LOAD_CONST           True
   4: STORE_FAST           first
   6: LOAD_FAST            node
   8: LOAD_ATTR            posonlyargs
  18: LOAD_FAST            node
  20: LOAD_ATTR            args
  30: BINARY_OP            +
  34: STORE_FAST           all_args
  36: LOAD_CONST           None
  38: BUILD_LIST           
  40: LOAD_GLOBAL          NULL + len
  52: LOAD_FAST            all_args
  54: PRECALL              
  58: CALL                 
  68: LOAD_GLOBAL          NULL + len
  80: LOAD_FAST            node
  82: LOAD_ATTR            defaults
  92: PRECALL              
  96: CALL                 
 106: BINARY_OP            -
 110: BINARY_OP            *
 114: LOAD_FAST            node
 116: LOAD_ATTR            defaults
 126: BINARY_OP            +
 130: STORE_FAST           defaults
 132: LOAD_GLOBAL          NULL + enumerate
 144: LOAD_GLOBAL          NULL + zip
 156: LOAD_FAST            all_args
 158: LOAD_FAST            defaults
 160: PRECALL              
 164: CALL                 
 174: LOAD_CONST           1
 176: PRECALL              
 180: CALL                 
 190: GET_ITER             
 192: FOR_ITER             to 486
 194: UNPACK_SEQUENCE      
 198: STORE_FAST           index
 200: STORE_FAST           elements
 202: LOAD_FAST            elements
 204: UNPACK_SEQUENCE      
 208: STORE_FAST           a
 210: STORE_FAST           d
 212: LOAD_FAST            first
 214: POP_JUMP_FORWARD_IF_FALSE to 222
 216: LOAD_CONST           False
 218: STORE_FAST           first
 220: JUMP_FORWARD         to 264
 222: LOAD_FAST            self
 224: LOAD_METHOD          write
 246: LOAD_CONST           ', '
 248: PRECALL              
 252: CALL                 
 262: POP_TOP              
 264: LOAD_FAST            self
 266: LOAD_METHOD          traverse
 288: LOAD_FAST            a
 290: PRECALL              
 294: CALL                 
 304: POP_TOP              
 306: LOAD_FAST            d
 308: POP_JUMP_FORWARD_IF_FALSE to 394
 310: LOAD_FAST            self
 312: LOAD_METHOD          write
 334: LOAD_CONST           '='
 336: PRECALL              
 340: CALL                 
 350: POP_TOP              
 352: LOAD_FAST            self
 354: LOAD_METHOD          traverse
 376: LOAD_FAST            d
 378: PRECALL              
 382: CALL                 
 392: POP_TOP              
 394: LOAD_FAST            index
 396: LOAD_GLOBAL          NULL + len
 408: LOAD_FAST            node
 410: LOAD_ATTR            posonlyargs
 420: PRECALL              
 424: CALL                 
 434: COMPARE_OP           ==
 440: POP_JUMP_FORWARD_IF_FALSE to 484
 442: LOAD_FAST            self
 444: LOAD_METHOD          write
 466: LOAD_CONST           ', /'
 468: PRECALL              
 472: CALL                 
 482: POP_TOP              
 484: JUMP_BACKWARD        to 192
 486: LOAD_FAST            node
 488: LOAD_ATTR            vararg
 498: POP_JUMP_FORWARD_IF_TRUE to 514
 500: LOAD_FAST            node
 502: LOAD_ATTR            kwonlyargs
 512: POP_JUMP_FORWARD_IF_FALSE to 812
 514: LOAD_FAST            first
 516: POP_JUMP_FORWARD_IF_FALSE to 524
 518: LOAD_CONST           False
 520: STORE_FAST           first
 522: JUMP_FORWARD         to 566
 524: LOAD_FAST            self
 526: LOAD_METHOD          write
 548: LOAD_CONST           ', '
 550: PRECALL              
 554: CALL                 
 564: POP_TOP              
 566: LOAD_FAST            self
 568: LOAD_METHOD          write
 590: LOAD_CONST           '*'
 592: PRECALL              
 596: CALL                 
 606: POP_TOP              
 608: LOAD_FAST            node
 610: LOAD_ATTR            vararg
 620: POP_JUMP_FORWARD_IF_FALSE to 812
 622: LOAD_FAST            self
 624: LOAD_METHOD          write
 646: LOAD_FAST            node
 648: LOAD_ATTR            vararg
 658: LOAD_ATTR            arg
 668: PRECALL              
 672: CALL                 
 682: POP_TOP              
 684: LOAD_FAST            node
 686: LOAD_ATTR            vararg
 696: LOAD_ATTR            annotation
 706: POP_JUMP_FORWARD_IF_FALSE to 812
 708: LOAD_FAST            self
 710: LOAD_METHOD          write
 732: LOAD_CONST           ': '
 734: PRECALL              
 738: CALL                 
 748: POP_TOP              
 750: LOAD_FAST            self
 752: LOAD_METHOD          traverse
 774: LOAD_FAST            node
 776: LOAD_ATTR            vararg
 786: LOAD_ATTR            annotation
 796: PRECALL              
 800: CALL                 
 810: POP_TOP              
 812: LOAD_FAST            node
 814: LOAD_ATTR            kwonlyargs
 824: POP_JUMP_FORWARD_IF_FALSE to 1062
 826: LOAD_GLOBAL          NULL + zip
 838: LOAD_FAST            node
 840: LOAD_ATTR            kwonlyargs
 850: LOAD_FAST            node
 852: LOAD_ATTR            kw_defaults
 862: PRECALL              
 866: CALL                 
 876: GET_ITER             
 878: FOR_ITER             to 1062
 880: UNPACK_SEQUENCE      
 884: STORE_FAST           a
 886: STORE_FAST           d
 888: LOAD_FAST            self
 890: LOAD_METHOD          write
 912: LOAD_CONST           ', '
 914: PRECALL              
 918: CALL                 
 928: POP_TOP              
 930: LOAD_FAST            self
 932: LOAD_METHOD          traverse
 954: LOAD_FAST            a
 956: PRECALL              
 960: CALL                 
 970: POP_TOP              
 972: LOAD_FAST            d
 974: POP_JUMP_FORWARD_IF_FALSE to 1060
 976: LOAD_FAST            self
 978: LOAD_METHOD          write
1000: LOAD_CONST           '='
1002: PRECALL              
1006: CALL                 
1016: POP_TOP              
1018: LOAD_FAST            self
1020: LOAD_METHOD          traverse
1042: LOAD_FAST            d
1044: PRECALL              
1048: CALL                 
1058: POP_TOP              
1060: JUMP_BACKWARD        to 878
1062: LOAD_FAST            node
1064: LOAD_ATTR            kwarg
1074: POP_JUMP_FORWARD_IF_FALSE to 1328
1076: LOAD_FAST            first
1078: POP_JUMP_FORWARD_IF_FALSE to 1086
1080: LOAD_CONST           False
1082: STORE_FAST           first
1084: JUMP_FORWARD         to 1128
1086: LOAD_FAST            self
1088: LOAD_METHOD          write
1110: LOAD_CONST           ', '
1112: PRECALL              
1116: CALL                 
1126: POP_TOP              
1128: LOAD_FAST            self
1130: LOAD_METHOD          write
1152: LOAD_CONST           '**'
1154: LOAD_FAST            node
1156: LOAD_ATTR            kwarg
1166: LOAD_ATTR            arg
1176: BINARY_OP            +
1180: PRECALL              
1184: CALL                 
1194: POP_TOP              
1196: LOAD_FAST            node
1198: LOAD_ATTR            kwarg
1208: LOAD_ATTR            annotation
1218: POP_JUMP_FORWARD_IF_FALSE to 1332
1220: LOAD_FAST            self
1222: LOAD_METHOD          write
1244: LOAD_CONST           ': '
1246: PRECALL              
1250: CALL                 
1260: POP_TOP              
1262: LOAD_FAST            self
1264: LOAD_METHOD          traverse
1286: LOAD_FAST            node
1288: LOAD_ATTR            kwarg
1298: LOAD_ATTR            annotation
1308: PRECALL              
1312: CALL                 
1322: POP_TOP              
1324: LOAD_CONST           None
1326: RETURN_VALUE         
1328: LOAD_CONST           None
1330: RETURN_VALUE         
1332: LOAD_CONST           None
1334: RETURN_VALUE         
