# Disassembly for ast._Unparser.visit_TryStar
# From module file: ast

## co_consts:
(None, True)

## co_names:
('_in_try_star', 'do_visit_try')

## bytecode:

   0: RESUME               
   2: LOAD_FAST            self
   4: LOAD_ATTR            _in_try_star
  14: STORE_FAST           prev_in_try_star
  16: NOP                  
  18: LOAD_CONST           True
  20: LOAD_FAST            self
  22: STORE_ATTR           _in_try_star
  32: LOAD_FAST            self
  34: LOAD_METHOD          do_visit_try
  56: LOAD_FAST            node
  58: PRECALL              
  62: CALL                 
  72: POP_TOP              
  74: LOAD_FAST            prev_in_try_star
  76: LOAD_FAST            self
  78: STORE_ATTR           _in_try_star
  88: LOAD_CONST           None
  90: RETURN_VALUE         
  92: PUSH_EXC_INFO        
  94: LOAD_FAST            prev_in_try_star
  96: LOAD_FAST            self
  98: STORE_ATTR           _in_try_star
 108: RERAISE              
 110: COPY                 
 112: POP_EXCEPT           
 114: RERAISE              
