# Disassembly for ast._Unparser.visit_ImportFrom
# From module file: ast

## co_consts:
(None, 'from ', '.', 0, ' import ', <code object <lambda> at 0x000002406945FB40, file "ast.py", line 867>)

## co_names:
('fill', 'write', 'level', 'module', 'interleave', 'traverse', 'names')

## bytecode:

   0: MAKE_CELL            self
   2: RESUME               
   4: LOAD_DEREF           self
   6: LOAD_METHOD          fill
  28: LOAD_CONST           'from '
  30: PRECALL              
  34: CALL                 
  44: POP_TOP              
  46: LOAD_DEREF           self
  48: LOAD_METHOD          write
  70: LOAD_CONST           '.'
  72: LOAD_FAST            node
  74: LOAD_ATTR            level
  84: JUMP_IF_TRUE_OR_POP  to 88
  86: LOAD_CONST           0
  88: BINARY_OP            *
  92: PRECALL              
  96: CALL                 
 106: POP_TOP              
 108: LOAD_FAST            node
 110: LOAD_ATTR            module
 120: POP_JUMP_FORWARD_IF_FALSE to 174
 122: LOAD_DEREF           self
 124: LOAD_METHOD          write
 146: LOAD_FAST            node
 148: LOAD_ATTR            module
 158: PRECALL              
 162: CALL                 
 172: POP_TOP              
 174: LOAD_DEREF           self
 176: LOAD_METHOD          write
 198: LOAD_CONST           ' import '
 200: PRECALL              
 204: CALL                 
 214: POP_TOP              
 216: LOAD_DEREF           self
 218: LOAD_METHOD          interleave
 240: LOAD_CLOSURE         self
 242: BUILD_TUPLE          
 244: LOAD_CONST           <code object <lambda> at 0x000002406945FB40, file "ast.py", line 867>
 246: MAKE_FUNCTION        closure
 248: LOAD_DEREF           self
 250: LOAD_ATTR            traverse
 260: LOAD_FAST            node
 262: LOAD_ATTR            names
 272: PRECALL              
 276: CALL                 
 286: POP_TOP              
 288: LOAD_CONST           None
 290: RETURN_VALUE         
