# Disassembly for ast._Unparser._str_literal_helper.<listcomp>
# From module file: ast

## co_consts:
()

## co_names:
()

## bytecode:

   0: COPY_FREE_VARS       
   2: RESUME               
   4: BUILD_LIST           
   6: LOAD_FAST            .0
   8: FOR_ITER             to 26
  10: STORE_FAST           q
  12: LOAD_FAST            q
  14: LOAD_DEREF           escaped_string
  16: CONTAINS_OP          
  18: POP_JUMP_BACKWARD_IF_FALSE to 8
  20: LOAD_FAST            q
  22: LIST_APPEND          
  24: JUMP_BACKWARD        to 8
  26: RETURN_VALUE         
