# Disassembly for ast._Unparser.get_type_comment
# From module file: ast

## co_consts:
(None, ' # type: ')

## co_names:
('_type_ignores', 'get', 'lineno', 'type_comment')

## bytecode:

   0: RESUME               
   2: LOAD_FAST            self
   4: LOAD_ATTR            _type_ignores
  14: LOAD_METHOD          get
  36: LOAD_FAST            node
  38: LOAD_ATTR            lineno
  48: PRECALL              
  52: CALL                 
  62: JUMP_IF_TRUE_OR_POP  to 76
  64: LOAD_FAST            node
  66: LOAD_ATTR            type_comment
  76: STORE_FAST           comment
  78: LOAD_FAST            comment
  80: POP_JUMP_FORWARD_IF_NONE to 92
  82: LOAD_CONST           ' # type: '
  84: LOAD_FAST            comment
  86: FORMAT_VALUE         
  88: BUILD_STRING         
  90: RETURN_VALUE         
  92: LOAD_CONST           None
  94: RETURN_VALUE         
