# Disassembly for ast.increment_lineno
# From module file: ast

## co_consts:
('\n    Increment the line number and end line number of each node in the tree\n    starting at *node* by *n*. This is useful to "move code" to a different\n    location in a file.\n    ', 'lineno', 0, 'end_lineno')

## co_names:
('walk', 'isinstance', 'TypeIgnore', 'getattr', 'lineno', '_attributes', 'end_lineno')

## bytecode:

   0: RESUME               
   2: LOAD_GLOBAL          NULL + walk
  14: LOAD_FAST            node
  16: PRECALL              
  20: CALL                 
  30: GET_ITER             
  32: FOR_ITER             to 276
  34: STORE_FAST           child
  36: LOAD_GLOBAL          NULL + isinstance
  48: LOAD_FAST            child
  50: LOAD_GLOBAL          TypeIgnore
  62: PRECALL              
  66: CALL                 
  76: POP_JUMP_FORWARD_IF_FALSE to 130
  78: LOAD_GLOBAL          NULL + getattr
  90: LOAD_FAST            child
  92: LOAD_CONST           'lineno'
  94: LOAD_CONST           0
  96: PRECALL              
 100: CALL                 
 110: LOAD_FAST            n
 112: BINARY_OP            +
 116: LOAD_FAST            child
 118: STORE_ATTR           lineno
 128: JUMP_BACKWARD        to 32
 130: LOAD_CONST           'lineno'
 132: LOAD_FAST            child
 134: LOAD_ATTR            _attributes
 144: CONTAINS_OP          
 146: POP_JUMP_FORWARD_IF_FALSE to 198
 148: LOAD_GLOBAL          NULL + getattr
 160: LOAD_FAST            child
 162: LOAD_CONST           'lineno'
 164: LOAD_CONST           0
 166: PRECALL              
 170: CALL                 
 180: LOAD_FAST            n
 182: BINARY_OP            +
 186: LOAD_FAST            child
 188: STORE_ATTR           lineno
 198: LOAD_CONST           'end_lineno'
 200: LOAD_FAST            child
 202: LOAD_ATTR            _attributes
 212: CONTAINS_OP          
 214: POP_JUMP_FORWARD_IF_FALSE to 274
 216: LOAD_GLOBAL          NULL + getattr
 228: LOAD_FAST            child
 230: LOAD_CONST           'end_lineno'
 232: LOAD_CONST           0
 234: PRECALL              
 238: CALL                 
 248: COPY                 
 250: STORE_FAST           end_lineno
 252: POP_JUMP_FORWARD_IF_NONE to 274
 254: LOAD_FAST            end_lineno
 256: LOAD_FAST            n
 258: BINARY_OP            +
 262: LOAD_FAST            child
 264: STORE_ATTR           end_lineno
 274: JUMP_BACKWARD        to 32
 276: LOAD_FAST            node
 278: RETURN_VALUE         
