# Disassembly for ast.literal_eval._convert_num
# From module file: ast

## co_consts:
(None,)

## co_names:
('isinstance', 'Constant', 'type', 'value', 'int', 'float', 'complex')

## bytecode:

   0: COPY_FREE_VARS       
   2: RESUME               
   4: LOAD_GLOBAL          NULL + isinstance
  16: LOAD_FAST            node
  18: LOAD_GLOBAL          Constant
  30: PRECALL              
  34: CALL                 
  44: POP_JUMP_FORWARD_IF_FALSE to 126
  46: LOAD_GLOBAL          NULL + type
  58: LOAD_FAST            node
  60: LOAD_ATTR            value
  70: PRECALL              
  74: CALL                 
  84: LOAD_GLOBAL          int
  96: LOAD_GLOBAL          float
 108: LOAD_GLOBAL          complex
 120: BUILD_TUPLE          
 122: CONTAINS_OP          
 124: POP_JUMP_FORWARD_IF_FALSE to 148
 126: PUSH_NULL            
 128: LOAD_DEREF           _raise_malformed_node
 130: LOAD_FAST            node
 132: PRECALL              
 136: CALL                 
 146: POP_TOP              
 148: LOAD_FAST            node
 150: LOAD_ATTR            value
 160: RETURN_VALUE         
