# Disassembly for ast.parse
# From module file: ast

## co_consts:
('\n    Parse the source into an AST node.\n    Equivalent to compile(source, filename, mode, PyCF_ONLY_AST).\n    Pass type_comments=True to get back type comments where the syntax allows.\n    ', 3, None, -1, ('_feature_version',))

## co_names:
('PyCF_ONLY_AST', 'PyCF_TYPE_COMMENTS', 'isinstance', 'tuple', 'compile')

## bytecode:

   0: RESUME               
   2: LOAD_GLOBAL          PyCF_ONLY_AST
  14: STORE_FAST           flags
  16: LOAD_FAST            type_comments
  18: POP_JUMP_FORWARD_IF_FALSE to 40
  20: LOAD_FAST            flags
  22: LOAD_GLOBAL          PyCF_TYPE_COMMENTS
  34: BINARY_OP            |=
  38: STORE_FAST           flags
  40: LOAD_GLOBAL          NULL + isinstance
  52: LOAD_FAST            feature_version
  54: LOAD_GLOBAL          tuple
  66: PRECALL              
  70: CALL                 
  80: POP_JUMP_FORWARD_IF_FALSE to 114
  82: LOAD_FAST            feature_version
  84: UNPACK_SEQUENCE      
  88: STORE_FAST           major
  90: STORE_FAST           minor
  92: LOAD_FAST            major
  94: LOAD_CONST           3
  96: COMPARE_OP           ==
 102: POP_JUMP_FORWARD_IF_TRUE to 108
 104: LOAD_ASSERTION_ERROR 
 106: RAISE_VARARGS        
 108: LOAD_FAST            minor
 110: STORE_FAST           feature_version
 112: JUMP_FORWARD         to 122
 114: LOAD_FAST            feature_version
 116: POP_JUMP_FORWARD_IF_NOT_NONE to 122
 118: LOAD_CONST           -1
 120: STORE_FAST           feature_version
 122: LOAD_GLOBAL          NULL + compile
 134: LOAD_FAST            source
 136: LOAD_FAST            filename
 138: LOAD_FAST            mode
 140: LOAD_FAST            flags
 142: LOAD_FAST            feature_version
 144: KW_NAMES             
 146: PRECALL              
 150: CALL                 
 160: RETURN_VALUE         
