# Disassembly for ast._Unparser.visit_Assign
# From module file: ast

## co_consts:
(None, ' = ')

## co_names:
('fill', 'targets', 'set_precedence', '_Precedence', 'TUPLE', 'traverse', 'write', 'value', 'get_type_comment')

## bytecode:

   0: RESUME               
   2: LOAD_FAST            self
   4: LOAD_METHOD          fill
  26: PRECALL              
  30: CALL                 
  40: POP_TOP              
  42: LOAD_FAST            node
  44: LOAD_ATTR            targets
  54: GET_ITER             
  56: FOR_ITER             to 210
  58: STORE_FAST           target
  60: LOAD_FAST            self
  62: LOAD_METHOD          set_precedence
  84: LOAD_GLOBAL          _Precedence
  96: LOAD_ATTR            TUPLE
 106: LOAD_FAST            target
 108: PRECALL              
 112: CALL                 
 122: POP_TOP              
 124: LOAD_FAST            self
 126: LOAD_METHOD          traverse
 148: LOAD_FAST            target
 150: PRECALL              
 154: CALL                 
 164: POP_TOP              
 166: LOAD_FAST            self
 168: LOAD_METHOD          write
 190: LOAD_CONST           ' = '
 192: PRECALL              
 196: CALL                 
 206: POP_TOP              
 208: JUMP_BACKWARD        to 56
 210: LOAD_FAST            self
 212: LOAD_METHOD          traverse
 234: LOAD_FAST            node
 236: LOAD_ATTR            value
 246: PRECALL              
 250: CALL                 
 260: POP_TOP              
 262: LOAD_FAST            self
 264: LOAD_METHOD          get_type_comment
 286: LOAD_FAST            node
 288: PRECALL              
 292: CALL                 
 302: COPY                 
 304: STORE_FAST           type_comment
 306: POP_JUMP_FORWARD_IF_FALSE to 354
 308: LOAD_FAST            self
 310: LOAD_METHOD          write
 332: LOAD_FAST            type_comment
 334: PRECALL              
 338: CALL                 
 348: POP_TOP              
 350: LOAD_CONST           None
 352: RETURN_VALUE         
 354: LOAD_CONST           None
 356: RETURN_VALUE         
