# Disassembly for ast._Unparser.traverse
# From module file: ast

## co_consts:
(None,)

## co_names:
('isinstance', 'list', 'traverse', 'super', 'visit')

## bytecode:

   0: COPY_FREE_VARS       
   2: RESUME               
   4: LOAD_GLOBAL          NULL + isinstance
  16: LOAD_FAST            node
  18: LOAD_GLOBAL          list
  30: PRECALL              
  34: CALL                 
  44: POP_JUMP_FORWARD_IF_FALSE to 102
  46: LOAD_FAST            node
  48: GET_ITER             
  50: FOR_ITER             to 98
  52: STORE_FAST           item
  54: LOAD_FAST            self
  56: LOAD_METHOD          traverse
  78: LOAD_FAST            item
  80: PRECALL              
  84: CALL                 
  94: POP_TOP              
  96: JUMP_BACKWARD        to 50
  98: LOAD_CONST           None
 100: RETURN_VALUE         
 102: LOAD_GLOBAL          NULL + super
 114: PRECALL              
 118: CALL                 
 128: LOAD_METHOD          visit
 150: LOAD_FAST            node
 152: PRECALL              
 156: CALL                 
 166: POP_TOP              
 168: LOAD_CONST           None
 170: RETURN_VALUE         
