# Disassembly for ast.literal_eval._convert
# From module file: ast

## co_consts:
(None, 'set')

## co_names:
('isinstance', 'Constant', 'value', 'Tuple', 'tuple', 'map', 'elts', 'List', 'list', 'Set', 'set', 'Call', 'func', 'Name', 'id', 'args', 'keywords', 'Dict', 'len', 'keys', 'values', 'dict', 'zip', 'BinOp', 'op', 'Add', 'Sub', 'left', 'right', 'int', 'float', 'complex')

## bytecode:

   0: COPY_FREE_VARS       
   2: RESUME               
   4: LOAD_GLOBAL          NULL + isinstance
  16: LOAD_FAST            node
  18: LOAD_GLOBAL          Constant
  30: PRECALL              
  34: CALL                 
  44: POP_JUMP_FORWARD_IF_FALSE to 60
  46: LOAD_FAST            node
  48: LOAD_ATTR            value
  58: RETURN_VALUE         
  60: LOAD_GLOBAL          NULL + isinstance
  72: LOAD_FAST            node
  74: LOAD_GLOBAL          Tuple
  86: PRECALL              
  90: CALL                 
 100: POP_JUMP_FORWARD_IF_FALSE to 170
 102: LOAD_GLOBAL          NULL + tuple
 114: LOAD_GLOBAL          NULL + map
 126: LOAD_DEREF           _convert
 128: LOAD_FAST            node
 130: LOAD_ATTR            elts
 140: PRECALL              
 144: CALL                 
 154: PRECALL              
 158: CALL                 
 168: RETURN_VALUE         
 170: LOAD_GLOBAL          NULL + isinstance
 182: LOAD_FAST            node
 184: LOAD_GLOBAL          List
 196: PRECALL              
 200: CALL                 
 210: POP_JUMP_FORWARD_IF_FALSE to 280
 212: LOAD_GLOBAL          NULL + list
 224: LOAD_GLOBAL          NULL + map
 236: LOAD_DEREF           _convert
 238: LOAD_FAST            node
 240: LOAD_ATTR            elts
 250: PRECALL              
 254: CALL                 
 264: PRECALL              
 268: CALL                 
 278: RETURN_VALUE         
 280: LOAD_GLOBAL          NULL + isinstance
 292: LOAD_FAST            node
 294: LOAD_GLOBAL          Set
 306: PRECALL              
 310: CALL                 
 320: POP_JUMP_FORWARD_IF_FALSE to 390
 322: LOAD_GLOBAL          NULL + set
 334: LOAD_GLOBAL          NULL + map
 346: LOAD_DEREF           _convert
 348: LOAD_FAST            node
 350: LOAD_ATTR            elts
 360: PRECALL              
 364: CALL                 
 374: PRECALL              
 378: CALL                 
 388: RETURN_VALUE         
 390: LOAD_GLOBAL          NULL + isinstance
 402: LOAD_FAST            node
 404: LOAD_GLOBAL          Call
 416: PRECALL              
 420: CALL                 
 430: POP_JUMP_FORWARD_IF_FALSE to 596
 432: LOAD_GLOBAL          NULL + isinstance
 444: LOAD_FAST            node
 446: LOAD_ATTR            func
 456: LOAD_GLOBAL          Name
 468: PRECALL              
 472: CALL                 
 482: POP_JUMP_FORWARD_IF_FALSE to 596
 484: LOAD_FAST            node
 486: LOAD_ATTR            func
 496: LOAD_ATTR            id
 506: LOAD_CONST           'set'
 508: COMPARE_OP           ==
 514: POP_JUMP_FORWARD_IF_FALSE to 596
 516: LOAD_FAST            node
 518: LOAD_ATTR            args
 528: LOAD_FAST            node
 530: LOAD_ATTR            keywords
 540: SWAP                 
 542: COPY                 
 544: COMPARE_OP           ==
 550: POP_JUMP_FORWARD_IF_FALSE to 564
 552: BUILD_LIST           
 554: COMPARE_OP           ==
 560: POP_JUMP_FORWARD_IF_FALSE to 596
 562: JUMP_FORWARD         to 568
 564: POP_TOP              
 566: JUMP_FORWARD         to 596
 568: LOAD_GLOBAL          NULL + set
 580: PRECALL              
 584: CALL                 
 594: RETURN_VALUE         
 596: LOAD_GLOBAL          NULL + isinstance
 608: LOAD_FAST            node
 610: LOAD_GLOBAL          Dict
 622: PRECALL              
 626: CALL                 
 636: POP_JUMP_FORWARD_IF_FALSE to 878
 638: LOAD_GLOBAL          NULL + len
 650: LOAD_FAST            node
 652: LOAD_ATTR            keys
 662: PRECALL              
 666: CALL                 
 676: LOAD_GLOBAL          NULL + len
 688: LOAD_FAST            node
 690: LOAD_ATTR            values
 700: PRECALL              
 704: CALL                 
 714: COMPARE_OP           !=
 720: POP_JUMP_FORWARD_IF_FALSE to 744
 722: PUSH_NULL            
 724: LOAD_DEREF           _raise_malformed_node
 726: LOAD_FAST            node
 728: PRECALL              
 732: CALL                 
 742: POP_TOP              
 744: LOAD_GLOBAL          NULL + dict
 756: LOAD_GLOBAL          NULL + zip
 768: LOAD_GLOBAL          NULL + map
 780: LOAD_DEREF           _convert
 782: LOAD_FAST            node
 784: LOAD_ATTR            keys
 794: PRECALL              
 798: CALL                 
 808: LOAD_GLOBAL          NULL + map
 820: LOAD_DEREF           _convert
 822: LOAD_FAST            node
 824: LOAD_ATTR            values
 834: PRECALL              
 838: CALL                 
 848: PRECALL              
 852: CALL                 
 862: PRECALL              
 866: CALL                 
 876: RETURN_VALUE         
 878: LOAD_GLOBAL          NULL + isinstance
 890: LOAD_FAST            node
 892: LOAD_GLOBAL          BinOp
 904: PRECALL              
 908: CALL                 
 918: POP_JUMP_FORWARD_IF_FALSE to 1220
 920: LOAD_GLOBAL          NULL + isinstance
 932: LOAD_FAST            node
 934: LOAD_ATTR            op
 944: LOAD_GLOBAL          Add
 956: LOAD_GLOBAL          Sub
 968: BUILD_TUPLE          
 970: PRECALL              
 974: CALL                 
 984: POP_JUMP_FORWARD_IF_FALSE to 1220
 986: PUSH_NULL            
 988: LOAD_DEREF           _convert_signed_num
 990: LOAD_FAST            node
 992: LOAD_ATTR            left
1002: PRECALL              
1006: CALL                 
1016: STORE_FAST           left
1018: PUSH_NULL            
1020: LOAD_DEREF           _convert_num
1022: LOAD_FAST            node
1024: LOAD_ATTR            right
1034: PRECALL              
1038: CALL                 
1048: STORE_FAST           right
1050: LOAD_GLOBAL          NULL + isinstance
1062: LOAD_FAST            left
1064: LOAD_GLOBAL          int
1076: LOAD_GLOBAL          float
1088: BUILD_TUPLE          
1090: PRECALL              
1094: CALL                 
1104: POP_JUMP_FORWARD_IF_FALSE to 1220
1106: LOAD_GLOBAL          NULL + isinstance
1118: LOAD_FAST            right
1120: LOAD_GLOBAL          complex
1132: PRECALL              
1136: CALL                 
1146: POP_JUMP_FORWARD_IF_FALSE to 1220
1148: LOAD_GLOBAL          NULL + isinstance
1160: LOAD_FAST            node
1162: LOAD_ATTR            op
1172: LOAD_GLOBAL          Add
1184: PRECALL              
1188: CALL                 
1198: POP_JUMP_FORWARD_IF_FALSE to 1210
1200: LOAD_FAST            left
1202: LOAD_FAST            right
1204: BINARY_OP            +
1208: RETURN_VALUE         
1210: LOAD_FAST            left
1212: LOAD_FAST            right
1214: BINARY_OP            -
1218: RETURN_VALUE         
1220: PUSH_NULL            
1222: LOAD_DEREF           _convert_signed_num
1224: LOAD_FAST            node
1226: PRECALL              
1230: CALL                 
1240: RETURN_VALUE         
