# Disassembly for ast._Unparser.visit_MatchMapping.write_key_pattern_pair
# From module file: ast

## co_consts:
(None, ': ')

## co_names:
('traverse', 'write')

## bytecode:

   0: COPY_FREE_VARS       
   2: RESUME               
   4: LOAD_FAST            pair
   6: UNPACK_SEQUENCE      
  10: STORE_FAST           k
  12: STORE_FAST           p
  14: LOAD_DEREF           self
  16: LOAD_METHOD          traverse
  38: LOAD_FAST            k
  40: PRECALL              
  44: CALL                 
  54: POP_TOP              
  56: LOAD_DEREF           self
  58: LOAD_METHOD          write
  80: LOAD_CONST           ': '
  82: PRECALL              
  86: CALL                 
  96: POP_TOP              
  98: LOAD_DEREF           self
 100: LOAD_METHOD          traverse
 122: LOAD_FAST            p
 124: PRECALL              
 128: CALL                 
 138: POP_TOP              
 140: LOAD_CONST           None
 142: RETURN_VALUE         
