# Disassembly for ast._new
# From module file: ast

## co_consts:
(None, ' got multiple values for argument ')

## co_names:
('_fields', 'index', 'len', 'TypeError', '__name__', '_const_types', 'Constant', '__new__')

## bytecode:

   0: RESUME               
   2: LOAD_FAST            kwargs
   4: GET_ITER             
   6: FOR_ITER             to 172
   8: STORE_FAST           key
  10: LOAD_FAST            key
  12: LOAD_FAST            cls
  14: LOAD_ATTR            _fields
  24: CONTAINS_OP          
  26: POP_JUMP_FORWARD_IF_FALSE to 30
  28: JUMP_BACKWARD        to 6
  30: LOAD_FAST            cls
  32: LOAD_ATTR            _fields
  42: LOAD_METHOD          index
  64: LOAD_FAST            key
  66: PRECALL              
  70: CALL                 
  80: STORE_FAST           pos
  82: LOAD_FAST            pos
  84: LOAD_GLOBAL          NULL + len
  96: LOAD_FAST            args
  98: PRECALL              
 102: CALL                 
 112: COMPARE_OP           <
 118: POP_JUMP_FORWARD_IF_FALSE to 170
 120: LOAD_GLOBAL          NULL + TypeError
 132: LOAD_FAST            cls
 134: LOAD_ATTR            __name__
 144: FORMAT_VALUE         
 146: LOAD_CONST           ' got multiple values for argument '
 148: LOAD_FAST            key
 150: FORMAT_VALUE         repr
 152: BUILD_STRING         
 154: PRECALL              
 158: CALL                 
 168: RAISE_VARARGS        
 170: JUMP_BACKWARD        to 6
 172: LOAD_FAST            cls
 174: LOAD_GLOBAL          _const_types
 186: CONTAINS_OP          
 188: POP_JUMP_FORWARD_IF_FALSE to 214
 190: LOAD_GLOBAL          NULL + Constant
 202: LOAD_FAST            args
 204: BUILD_MAP            
 206: LOAD_FAST            kwargs
 208: DICT_MERGE           
 210: CALL_FUNCTION_EX     
 212: RETURN_VALUE         
 214: LOAD_GLOBAL          NULL + Constant
 226: LOAD_ATTR            __new__
 236: LOAD_FAST            cls
 238: BUILD_LIST           
 240: LOAD_FAST            args
 242: LIST_EXTEND          
 244: LIST_TO_TUPLE        
 246: BUILD_MAP            
 248: LOAD_FAST            kwargs
 250: DICT_MERGE           
 252: CALL_FUNCTION_EX     
 254: RETURN_VALUE         
