# Disassembly for ast.NodeTransformer
# From module file: ast

## co_consts:
('NodeTransformer', "\n    A :class:`NodeVisitor` subclass that walks the abstract syntax tree and\n    allows modification of nodes.\n\n    The `NodeTransformer` will walk the AST and use the return value of the\n    visitor methods to replace or remove the old node.  If the return value of\n    the visitor method is ``None``, the node will be removed from its location,\n    otherwise it is replaced with the return value.  The return value may be the\n    original node in which case no replacement takes place.\n\n    Here is an example transformer that rewrites all occurrences of name lookups\n    (``foo``) to ``data['foo']``::\n\n       class RewriteName(NodeTransformer):\n\n           def visit_Name(self, node):\n               return Subscript(\n                   value=Name(id='data', ctx=Load()),\n                   slice=Constant(value=node.id),\n                   ctx=node.ctx\n               )\n\n    Keep in mind that if the node you're operating on has child nodes you must\n    either transform the child nodes yourself or call the :meth:`generic_visit`\n    method for the node first.\n\n    For nodes that were part of a collection of statements (that applies to all\n    statement nodes), the visitor may also return a list of nodes rather than\n    just a single node.\n\n    Usually you use the transformer like this::\n\n       node = YourTransformer().visit(node)\n    ", <code object generic_visit at 0x0000024068E7B3A0, file "ast.py", line 488>, None)

## co_names:
('__name__', '__module__', '__qualname__', '__doc__', 'generic_visit')

## bytecode:

   0: RESUME               
   2: LOAD_NAME            __name__
   4: STORE_NAME           __module__
   6: LOAD_CONST           'NodeTransformer'
   8: STORE_NAME           __qualname__
  10: LOAD_CONST           "\n    A :class:`NodeVisitor` subclass that walks the abstract syntax tree and\n    allows modification of nodes.\n\n    The `NodeTransformer` will walk the AST and use the return value of the\n    visitor methods to replace or remove the old node.  If the return value of\n    the visitor method is ``None``, the node will be removed from its location,\n    otherwise it is replaced with the return value.  The return value may be the\n    original node in which case no replacement takes place.\n\n    Here is an example transformer that rewrites all occurrences of name lookups\n    (``foo``) to ``data['foo']``::\n\n       class RewriteName(NodeTransformer):\n\n           def visit_Name(self, node):\n               return Subscript(\n                   value=Name(id='data', ctx=Load()),\n                   slice=Constant(value=node.id),\n                   ctx=node.ctx\n               )\n\n    Keep in mind that if the node you're operating on has child nodes you must\n    either transform the child nodes yourself or call the :meth:`generic_visit`\n    method for the node first.\n\n    For nodes that were part of a collection of statements (that applies to all\n    statement nodes), the visitor may also return a list of nodes rather than\n    just a single node.\n\n    Usually you use the transformer like this::\n\n       node = YourTransformer().visit(node)\n    "
  12: STORE_NAME           __doc__
  14: LOAD_CONST           <code object generic_visit at 0x0000024068E7B3A0, file "ast.py", line 488>
  16: MAKE_FUNCTION        
  18: STORE_NAME           generic_visit
  20: LOAD_CONST           None
  22: RETURN_VALUE         
