# Disassembly for ast._Unparser.visit_AugAssign
# From module file: ast

## co_consts:
(None, ' ', '= ')

## co_names:
('fill', 'traverse', 'target', 'write', 'binop', 'op', '__class__', '__name__', 'value')

## bytecode:

   0: RESUME               
   2: LOAD_FAST            self
   4: LOAD_METHOD          fill
  26: PRECALL              
  30: CALL                 
  40: POP_TOP              
  42: LOAD_FAST            self
  44: LOAD_METHOD          traverse
  66: LOAD_FAST            node
  68: LOAD_ATTR            target
  78: PRECALL              
  82: CALL                 
  92: POP_TOP              
  94: LOAD_FAST            self
  96: LOAD_METHOD          write
 118: LOAD_CONST           ' '
 120: LOAD_FAST            self
 122: LOAD_ATTR            binop
 132: LOAD_FAST            node
 134: LOAD_ATTR            op
 144: LOAD_ATTR            __class__
 154: LOAD_ATTR            __name__
 164: BINARY_SUBSCR        
 174: BINARY_OP            +
 178: LOAD_CONST           '= '
 180: BINARY_OP            +
 184: PRECALL              
 188: CALL                 
 198: POP_TOP              
 200: LOAD_FAST            self
 202: LOAD_METHOD          traverse
 224: LOAD_FAST            node
 226: LOAD_ATTR            value
 236: PRECALL              
 240: CALL                 
 250: POP_TOP              
 252: LOAD_CONST           None
 254: RETURN_VALUE         
