# Disassembly for ast.iter_fields
# From module file: ast

## co_consts:
('\n    Yield a tuple of ``(fieldname, value)`` for each field in ``node._fields``\n    that is present on *node*.\n    ', None)

## co_names:
('_fields', 'getattr', 'AttributeError')

## bytecode:

   0: RETURN_GENERATOR     
   2: POP_TOP              
   4: RESUME               
   6: LOAD_FAST            node
   8: LOAD_ATTR            _fields
  18: GET_ITER             
  20: FOR_ITER             to 100
  22: STORE_FAST           field
  24: NOP                  
  26: LOAD_FAST            field
  28: LOAD_GLOBAL          NULL + getattr
  40: LOAD_FAST            node
  42: LOAD_FAST            field
  44: PRECALL              
  48: CALL                 
  58: BUILD_TUPLE          
  60: YIELD_VALUE          
  62: RESUME               
  64: POP_TOP              
  66: JUMP_BACKWARD        to 20
  68: PUSH_EXC_INFO        
  70: LOAD_GLOBAL          AttributeError
  82: CHECK_EXC_MATCH      
  84: POP_JUMP_FORWARD_IF_FALSE to 92
  86: POP_TOP              
  88: POP_EXCEPT           
  90: JUMP_BACKWARD        to 20
  92: RERAISE              
  94: COPY                 
  96: POP_EXCEPT           
  98: RERAISE              
 100: LOAD_CONST           None
 102: RETURN_VALUE         
