# Disassembly for ast._Unparser.visit
# From module file: ast

## co_consts:
('Outputs a source code string that, if converted back to an ast\n        (using ast.parse) will generate an AST equivalent to *node*', '')

## co_names:
('_source', 'traverse', 'join')

## bytecode:

   0: RESUME               
   2: BUILD_LIST           
   4: LOAD_FAST            self
   6: STORE_ATTR           _source
  16: LOAD_FAST            self
  18: LOAD_METHOD          traverse
  40: LOAD_FAST            node
  42: PRECALL              
  46: CALL                 
  56: POP_TOP              
  58: LOAD_CONST           ''
  60: LOAD_METHOD          join
  82: LOAD_FAST            self
  84: LOAD_ATTR            _source
  94: PRECALL              
  98: CALL                 
 108: RETURN_VALUE         
