# Disassembly for ast.NodeVisitor.visit_Constant
# From module file: ast

## co_consts:
(None, 'visit_', 0, ' is deprecated; add visit_Constant', 2)

## co_names:
('value', '_const_node_type_names', 'get', 'type', 'items', 'isinstance', 'getattr', 'warnings', 'warn', 'DeprecationWarning', 'AttributeError', 'generic_visit')

## bytecode:

   0: RESUME               
   2: LOAD_FAST            node
   4: LOAD_ATTR            value
  14: STORE_FAST           value
  16: LOAD_GLOBAL          _const_node_type_names
  28: LOAD_METHOD          get
  50: LOAD_GLOBAL          NULL + type
  62: LOAD_FAST            value
  64: PRECALL              
  68: CALL                 
  78: PRECALL              
  82: CALL                 
  92: STORE_FAST           type_name
  94: LOAD_FAST            type_name
  96: POP_JUMP_FORWARD_IF_NOT_NONE to 200
  98: LOAD_GLOBAL          _const_node_type_names
 110: LOAD_METHOD          items
 132: PRECALL              
 136: CALL                 
 146: GET_ITER             
 148: FOR_ITER             to 200
 150: UNPACK_SEQUENCE      
 154: STORE_FAST           cls
 156: STORE_FAST           name
 158: LOAD_GLOBAL          NULL + isinstance
 170: LOAD_FAST            value
 172: LOAD_FAST            cls
 174: PRECALL              
 178: CALL                 
 188: POP_JUMP_FORWARD_IF_FALSE to 198
 190: LOAD_FAST            name
 192: STORE_FAST           type_name
 194: POP_TOP              
 196: JUMP_FORWARD         to 200
 198: JUMP_BACKWARD        to 148
 200: LOAD_FAST            type_name
 202: POP_JUMP_FORWARD_IF_NONE to 372
 204: LOAD_CONST           'visit_'
 206: LOAD_FAST            type_name
 208: BINARY_OP            +
 212: STORE_FAST           method
 214: NOP                  
 216: LOAD_GLOBAL          NULL + getattr
 228: LOAD_FAST            self
 230: LOAD_FAST            method
 232: PRECALL              
 236: CALL                 
 246: STORE_FAST           visitor
 248: LOAD_CONST           0
 250: LOAD_CONST           None
 252: IMPORT_NAME          warnings
 254: STORE_FAST           warnings
 256: LOAD_FAST            warnings
 258: LOAD_METHOD          warn
 280: LOAD_FAST            method
 282: FORMAT_VALUE         
 284: LOAD_CONST           ' is deprecated; add visit_Constant'
 286: BUILD_STRING         
 288: LOAD_GLOBAL          DeprecationWarning
 300: LOAD_CONST           2
 302: PRECALL              
 306: CALL                 
 316: POP_TOP              
 318: PUSH_NULL            
 320: LOAD_FAST            visitor
 322: LOAD_FAST            node
 324: PRECALL              
 328: CALL                 
 338: RETURN_VALUE         
 340: PUSH_EXC_INFO        
 342: LOAD_GLOBAL          AttributeError
 354: CHECK_EXC_MATCH      
 356: POP_JUMP_FORWARD_IF_FALSE to 364
 358: POP_TOP              
 360: POP_EXCEPT           
 362: JUMP_FORWARD         to 372
 364: RERAISE              
 366: COPY                 
 368: POP_EXCEPT           
 370: RERAISE              
 372: LOAD_FAST            self
 374: LOAD_METHOD          generic_visit
 396: LOAD_FAST            node
 398: PRECALL              
 402: CALL                 
 412: RETURN_VALUE         
