# Disassembly for ast.dump._format
# From module file: ast

## co_consts:
(None, 1, '\n', ',\n', '', ', ', True, Ellipsis, '=', 3, '(', ')', False, ('[]', True), '[', <code object <genexpr> at 0x0000024069CC8430, file "ast.py", line 170>, ']')

## co_names:
('isinstance', 'AST', 'type', '_fields', 'getattr', 'AttributeError', 'append', '_attributes', 'len', '__class__', '__name__', 'join', 'list', 'repr')

## bytecode:

   0: COPY_FREE_VARS       
   2: MAKE_CELL            level
   4: RESUME               
   6: LOAD_DEREF           indent
   8: POP_JUMP_FORWARD_IF_NONE to 54
  10: LOAD_DEREF           level
  12: LOAD_CONST           1
  14: BINARY_OP            +=
  18: STORE_DEREF          level
  20: LOAD_CONST           '\n'
  22: LOAD_DEREF           indent
  24: LOAD_DEREF           level
  26: BINARY_OP            *
  30: BINARY_OP            +
  34: STORE_FAST           prefix
  36: LOAD_CONST           ',\n'
  38: LOAD_DEREF           indent
  40: LOAD_DEREF           level
  42: BINARY_OP            *
  46: BINARY_OP            +
  50: STORE_FAST           sep
  52: JUMP_FORWARD         to 62
  54: LOAD_CONST           ''
  56: STORE_FAST           prefix
  58: LOAD_CONST           ', '
  60: STORE_FAST           sep
  62: LOAD_GLOBAL          NULL + isinstance
  74: LOAD_FAST            node
  76: LOAD_GLOBAL          AST
  88: PRECALL              
  92: CALL                 
 102: EXTENDED_ARG         
 104: POP_JUMP_FORWARD_IF_FALSE to 862
 106: LOAD_GLOBAL          NULL + type
 118: LOAD_FAST            node
 120: PRECALL              
 124: CALL                 
 134: STORE_FAST           cls
 136: BUILD_LIST           
 138: STORE_FAST           args
 140: LOAD_CONST           True
 142: STORE_FAST           allsimple
 144: LOAD_DEREF           annotate_fields
 146: STORE_FAST           keywords
 148: LOAD_FAST            node
 150: LOAD_ATTR            _fields
 160: GET_ITER             
 162: FOR_ITER             to 422
 164: STORE_FAST           name
 166: NOP                  
 168: LOAD_GLOBAL          NULL + getattr
 180: LOAD_FAST            node
 182: LOAD_FAST            name
 184: PRECALL              
 188: CALL                 
 198: STORE_FAST           value
 200: JUMP_FORWARD         to 238
 202: PUSH_EXC_INFO        
 204: LOAD_GLOBAL          AttributeError
 216: CHECK_EXC_MATCH      
 218: POP_JUMP_FORWARD_IF_FALSE to 230
 220: POP_TOP              
 222: LOAD_CONST           True
 224: STORE_FAST           keywords
 226: POP_EXCEPT           
 228: JUMP_BACKWARD        to 162
 230: RERAISE              
 232: COPY                 
 234: POP_EXCEPT           
 236: RERAISE              
 238: LOAD_FAST            value
 240: POP_JUMP_FORWARD_IF_NOT_NONE to 282
 242: LOAD_GLOBAL          NULL + getattr
 254: LOAD_FAST            cls
 256: LOAD_FAST            name
 258: LOAD_CONST           Ellipsis
 260: PRECALL              
 264: CALL                 
 274: POP_JUMP_FORWARD_IF_NOT_NONE to 282
 276: LOAD_CONST           True
 278: STORE_FAST           keywords
 280: JUMP_BACKWARD        to 162
 282: PUSH_NULL            
 284: LOAD_DEREF           _format
 286: LOAD_FAST            value
 288: LOAD_DEREF           level
 290: PRECALL              
 294: CALL                 
 304: UNPACK_SEQUENCE      
 308: STORE_FAST           value
 310: STORE_FAST           simple
 312: LOAD_FAST            allsimple
 314: JUMP_IF_FALSE_OR_POP to 318
 316: LOAD_FAST            simple
 318: STORE_FAST           allsimple
 320: LOAD_FAST            keywords
 322: POP_JUMP_FORWARD_IF_FALSE to 378
 324: LOAD_FAST            args
 326: LOAD_METHOD          append
 348: LOAD_FAST            name
 350: FORMAT_VALUE         str
 352: LOAD_CONST           '='
 354: LOAD_FAST            value
 356: FORMAT_VALUE         str
 358: BUILD_STRING         
 360: PRECALL              
 364: CALL                 
 374: POP_TOP              
 376: JUMP_BACKWARD        to 162
 378: LOAD_FAST            args
 380: LOAD_METHOD          append
 402: LOAD_FAST            value
 404: PRECALL              
 408: CALL                 
 418: POP_TOP              
 420: JUMP_BACKWARD        to 162
 422: LOAD_DEREF           include_attributes
 424: POP_JUMP_FORWARD_IF_FALSE to 658
 426: LOAD_FAST            node
 428: LOAD_ATTR            _attributes
 438: POP_JUMP_FORWARD_IF_FALSE to 658
 440: LOAD_FAST            node
 442: LOAD_ATTR            _attributes
 452: GET_ITER             
 454: FOR_ITER             to 658
 456: STORE_FAST           name
 458: NOP                  
 460: LOAD_GLOBAL          NULL + getattr
 472: LOAD_FAST            node
 474: LOAD_FAST            name
 476: PRECALL              
 480: CALL                 
 490: STORE_FAST           value
 492: JUMP_FORWARD         to 526
 494: PUSH_EXC_INFO        
 496: LOAD_GLOBAL          AttributeError
 508: CHECK_EXC_MATCH      
 510: POP_JUMP_FORWARD_IF_FALSE to 518
 512: POP_TOP              
 514: POP_EXCEPT           
 516: JUMP_BACKWARD        to 454
 518: RERAISE              
 520: COPY                 
 522: POP_EXCEPT           
 524: RERAISE              
 526: LOAD_FAST            value
 528: POP_JUMP_FORWARD_IF_NOT_NONE to 566
 530: LOAD_GLOBAL          NULL + getattr
 542: LOAD_FAST            cls
 544: LOAD_FAST            name
 546: LOAD_CONST           Ellipsis
 548: PRECALL              
 552: CALL                 
 562: POP_JUMP_FORWARD_IF_NOT_NONE to 566
 564: JUMP_BACKWARD        to 454
 566: PUSH_NULL            
 568: LOAD_DEREF           _format
 570: LOAD_FAST            value
 572: LOAD_DEREF           level
 574: PRECALL              
 578: CALL                 
 588: UNPACK_SEQUENCE      
 592: STORE_FAST           value
 594: STORE_FAST           simple
 596: LOAD_FAST            allsimple
 598: JUMP_IF_FALSE_OR_POP to 602
 600: LOAD_FAST            simple
 602: STORE_FAST           allsimple
 604: LOAD_FAST            args
 606: LOAD_METHOD          append
 628: LOAD_FAST            name
 630: FORMAT_VALUE         str
 632: LOAD_CONST           '='
 634: LOAD_FAST            value
 636: FORMAT_VALUE         str
 638: BUILD_STRING         
 640: PRECALL              
 644: CALL                 
 654: POP_TOP              
 656: JUMP_BACKWARD        to 454
 658: LOAD_FAST            allsimple
 660: POP_JUMP_FORWARD_IF_FALSE to 780
 662: LOAD_GLOBAL          NULL + len
 674: LOAD_FAST            args
 676: PRECALL              
 680: CALL                 
 690: LOAD_CONST           3
 692: COMPARE_OP           <=
 698: POP_JUMP_FORWARD_IF_FALSE to 780
 700: LOAD_FAST            node
 702: LOAD_ATTR            __class__
 712: LOAD_ATTR            __name__
 722: FORMAT_VALUE         str
 724: LOAD_CONST           '('
 726: LOAD_CONST           ', '
 728: LOAD_METHOD          join
 750: LOAD_FAST            args
 752: PRECALL              
 756: CALL                 
 766: FORMAT_VALUE         str
 768: LOAD_CONST           ')'
 770: BUILD_STRING         
 772: LOAD_FAST            args
 774: UNARY_NOT            
 776: BUILD_TUPLE          
 778: RETURN_VALUE         
 780: LOAD_FAST            node
 782: LOAD_ATTR            __class__
 792: LOAD_ATTR            __name__
 802: FORMAT_VALUE         str
 804: LOAD_CONST           '('
 806: LOAD_FAST            prefix
 808: FORMAT_VALUE         str
 810: LOAD_FAST            sep
 812: LOAD_METHOD          join
 834: LOAD_FAST            args
 836: PRECALL              
 840: CALL                 
 850: FORMAT_VALUE         str
 852: LOAD_CONST           ')'
 854: BUILD_STRING         
 856: LOAD_CONST           False
 858: BUILD_TUPLE          
 860: RETURN_VALUE         
 862: LOAD_GLOBAL          NULL + isinstance
 874: LOAD_FAST            node
 876: LOAD_GLOBAL          list
 888: PRECALL              
 892: CALL                 
 902: POP_JUMP_FORWARD_IF_FALSE to 996
 904: LOAD_FAST            node
 906: POP_JUMP_FORWARD_IF_TRUE to 912
 908: LOAD_CONST           ('[]', True)
 910: RETURN_VALUE         
 912: LOAD_CONST           '['
 914: LOAD_FAST            prefix
 916: FORMAT_VALUE         str
 918: LOAD_FAST            sep
 920: LOAD_METHOD          join
 942: LOAD_CLOSURE         _format
 944: LOAD_CLOSURE         level
 946: BUILD_TUPLE          
 948: LOAD_CONST           <code object <genexpr> at 0x0000024069CC8430, file "ast.py", line 170>
 950: MAKE_FUNCTION        closure
 952: LOAD_FAST            node
 954: GET_ITER             
 956: PRECALL              
 960: CALL                 
 970: PRECALL              
 974: CALL                 
 984: FORMAT_VALUE         str
 986: LOAD_CONST           ']'
 988: BUILD_STRING         
 990: LOAD_CONST           False
 992: BUILD_TUPLE          
 994: RETURN_VALUE         
 996: LOAD_GLOBAL          NULL + repr
1008: LOAD_FAST            node
1010: PRECALL              
1014: CALL                 
1024: LOAD_CONST           True
1026: BUILD_TUPLE          
1028: RETURN_VALUE         
