# Disassembly for ast._Unparser.buffered
# From module file: ast

## co_consts:
(None,)

## co_names:
('_source',)

## bytecode:

   0: RETURN_GENERATOR     
   2: POP_TOP              
   4: RESUME               
   6: LOAD_FAST            buffer
   8: POP_JUMP_FORWARD_IF_NOT_NONE to 14
  10: BUILD_LIST           
  12: STORE_FAST           buffer
  14: LOAD_FAST            self
  16: LOAD_ATTR            _source
  26: STORE_FAST           original_source
  28: LOAD_FAST            buffer
  30: LOAD_FAST            self
  32: STORE_ATTR           _source
  42: LOAD_FAST            buffer
  44: YIELD_VALUE          
  46: RESUME               
  48: POP_TOP              
  50: LOAD_FAST            original_source
  52: LOAD_FAST            self
  54: STORE_ATTR           _source
  64: LOAD_CONST           None
  66: RETURN_VALUE         
