# Disassembly for ast._Unparser.items_view
# From module file: ast

## co_consts:
('Traverse and separate the given *items* with a comma and append it to\n        the buffer. If *items* is a single item sequence, a trailing comma\n        will be added.', 1, 0, ',', <code object <lambda> at 0x000002406945F690, file "ast.py", line 716>, None)

## co_names:
('len', 'write', 'interleave')

## bytecode:

   0: MAKE_CELL            self
   2: RESUME               
   4: LOAD_GLOBAL          NULL + len
  16: LOAD_FAST            items
  18: PRECALL              
  22: CALL                 
  32: LOAD_CONST           1
  34: COMPARE_OP           ==
  40: POP_JUMP_FORWARD_IF_FALSE to 122
  42: PUSH_NULL            
  44: LOAD_FAST            traverser
  46: LOAD_FAST            items
  48: LOAD_CONST           0
  50: BINARY_SUBSCR        
  60: PRECALL              
  64: CALL                 
  74: POP_TOP              
  76: LOAD_DEREF           self
  78: LOAD_METHOD          write
 100: LOAD_CONST           ','
 102: PRECALL              
 106: CALL                 
 116: POP_TOP              
 118: LOAD_CONST           None
 120: RETURN_VALUE         
 122: LOAD_DEREF           self
 124: LOAD_METHOD          interleave
 146: LOAD_CLOSURE         self
 148: BUILD_TUPLE          
 150: LOAD_CONST           <code object <lambda> at 0x000002406945F690, file "ast.py", line 716>
 152: MAKE_FUNCTION        closure
 154: LOAD_FAST            traverser
 156: LOAD_FAST            items
 158: PRECALL              
 162: CALL                 
 172: POP_TOP              
 174: LOAD_CONST           None
 176: RETURN_VALUE         
