# Disassembly for shutil.copymode
# From module file: shutil

## co_consts:
("Copy mode bits from src to dst.\n\n    If follow_symlinks is not set, symlinks aren't followed if and only\n    if both `src` and `dst` are symlinks.  If `lchmod` isn't available\n    (e.g. Linux) this method does nothing.\n\n    ", 'shutil.copymode', 'lchmod', None)

## co_names:
('sys', 'audit', '_islink', 'os', 'path', 'islink', 'hasattr', 'lstat', 'lchmod', '_stat', 'chmod', 'stat', 'S_IMODE', 'st_mode')

## bytecode:

   0: RESUME               
   2: LOAD_GLOBAL          NULL + sys
  14: LOAD_ATTR            audit
  24: LOAD_CONST           'shutil.copymode'
  26: LOAD_FAST            src
  28: LOAD_FAST            dst
  30: PRECALL              
  34: CALL                 
  44: POP_TOP              
  46: LOAD_FAST            follow_symlinks
  48: POP_JUMP_FORWARD_IF_TRUE to 238
  50: LOAD_GLOBAL          NULL + _islink
  62: LOAD_FAST            src
  64: PRECALL              
  68: CALL                 
  78: POP_JUMP_FORWARD_IF_FALSE to 238
  80: LOAD_GLOBAL          os
  92: LOAD_ATTR            path
 102: LOAD_METHOD          islink
 124: LOAD_FAST            dst
 126: PRECALL              
 130: CALL                 
 140: POP_JUMP_FORWARD_IF_FALSE to 238
 142: LOAD_GLOBAL          NULL + hasattr
 154: LOAD_GLOBAL          os
 166: LOAD_CONST           'lchmod'
 168: PRECALL              
 172: CALL                 
 182: POP_JUMP_FORWARD_IF_FALSE to 234
 184: LOAD_GLOBAL          os
 196: LOAD_ATTR            lstat
 206: LOAD_GLOBAL          os
 218: LOAD_ATTR            lchmod
 228: STORE_FAST           chmod_func
 230: STORE_FAST           stat_func
 232: JUMP_FORWARD         to 276
 234: LOAD_CONST           None
 236: RETURN_VALUE         
 238: LOAD_GLOBAL          _stat
 250: LOAD_GLOBAL          os
 262: LOAD_ATTR            chmod
 272: STORE_FAST           chmod_func
 274: STORE_FAST           stat_func
 276: PUSH_NULL            
 278: LOAD_FAST            stat_func
 280: LOAD_FAST            src
 282: PRECALL              
 286: CALL                 
 296: STORE_FAST           st
 298: PUSH_NULL            
 300: LOAD_FAST            chmod_func
 302: LOAD_FAST            dst
 304: LOAD_GLOBAL          NULL + stat
 316: LOAD_ATTR            S_IMODE
 326: LOAD_FAST            st
 328: LOAD_ATTR            st_mode
 338: PRECALL              
 342: CALL                 
 352: PRECALL              
 356: CALL                 
 366: POP_TOP              
 368: LOAD_CONST           None
 370: RETURN_VALUE         
