# Disassembly for shutil.copystat.lookup
# From module file: shutil

## co_consts:
(None,)

## co_names:
('getattr', 'os', 'supports_follow_symlinks')

## bytecode:

   0: COPY_FREE_VARS       
   2: RESUME               
   4: LOAD_GLOBAL          NULL + getattr
  16: LOAD_GLOBAL          os
  28: LOAD_FAST            name
  30: LOAD_DEREF           _nop
  32: PRECALL              
  36: CALL                 
  46: STORE_FAST           fn
  48: LOAD_FAST            fn
  50: LOAD_GLOBAL          os
  62: LOAD_ATTR            supports_follow_symlinks
  72: CONTAINS_OP          
  74: POP_JUMP_FORWARD_IF_FALSE to 80
  76: LOAD_FAST            fn
  78: RETURN_VALUE         
  80: LOAD_DEREF           _nop
  82: RETURN_VALUE         
