# Disassembly for shutil._fastcopy_sendfile
# From module file: shutil

## co_consts:
('Copy data from one regular mmap-like fd to another by using\n    high-performance sendfile(2) syscall.\n    This should work on Linux >= 2.6.33 only.\n    ', None, 8388608, 134217728, 4294967296, 1073741824, 0, True, False)

## co_names:
('fileno', 'Exception', '_GiveupOnFastCopy', 'max', 'os', 'fstat', 'st_size', 'OSError', 'sys', 'maxsize', 'min', 'sendfile', 'name', 'filename', 'filename2', 'errno', 'ENOTSOCK', '_USE_CP_SENDFILE', 'ENOSPC', 'lseek', 'SEEK_CUR')

## bytecode:

   0: RESUME               
   2: NOP                  
   4: LOAD_FAST            fsrc
   6: LOAD_METHOD          fileno
  28: PRECALL              
  32: CALL                 
  42: STORE_FAST           infd
  44: LOAD_FAST            fdst
  46: LOAD_METHOD          fileno
  68: PRECALL              
  72: CALL                 
  82: STORE_FAST           outfd
  84: JUMP_FORWARD         to 152
  86: PUSH_EXC_INFO        
  88: LOAD_GLOBAL          Exception
 100: CHECK_EXC_MATCH      
 102: POP_JUMP_FORWARD_IF_FALSE to 144
 104: STORE_FAST           err
 106: LOAD_GLOBAL          NULL + _GiveupOnFastCopy
 118: LOAD_FAST            err
 120: PRECALL              
 124: CALL                 
 134: RAISE_VARARGS        
 136: LOAD_CONST           None
 138: STORE_FAST           err
 140: DELETE_FAST          err
 142: RERAISE              
 144: RERAISE              
 146: COPY                 
 148: POP_EXCEPT           
 150: RERAISE              
 152: NOP                  
 154: LOAD_GLOBAL          NULL + max
 166: LOAD_GLOBAL          NULL + os
 178: LOAD_ATTR            fstat
 188: LOAD_FAST            infd
 190: PRECALL              
 194: CALL                 
 204: LOAD_ATTR            st_size
 214: LOAD_CONST           8388608
 216: PRECALL              
 220: CALL                 
 230: STORE_FAST           blocksize
 232: JUMP_FORWARD         to 270
 234: PUSH_EXC_INFO        
 236: LOAD_GLOBAL          OSError
 248: CHECK_EXC_MATCH      
 250: POP_JUMP_FORWARD_IF_FALSE to 262
 252: POP_TOP              
 254: LOAD_CONST           134217728
 256: STORE_FAST           blocksize
 258: POP_EXCEPT           
 260: JUMP_FORWARD         to 270
 262: RERAISE              
 264: COPY                 
 266: POP_EXCEPT           
 268: RERAISE              
 270: LOAD_GLOBAL          sys
 282: LOAD_ATTR            maxsize
 292: LOAD_CONST           4294967296
 294: COMPARE_OP           <
 300: POP_JUMP_FORWARD_IF_FALSE to 334
 302: LOAD_GLOBAL          NULL + min
 314: LOAD_FAST            blocksize
 316: LOAD_CONST           1073741824
 318: PRECALL              
 322: CALL                 
 332: STORE_FAST           blocksize
 334: LOAD_CONST           0
 336: STORE_FAST           offset
 338: NOP                  
 340: NOP                  
 342: LOAD_GLOBAL          NULL + os
 354: LOAD_ATTR            sendfile
 364: LOAD_FAST            outfd
 366: LOAD_FAST            infd
 368: LOAD_FAST            offset
 370: LOAD_FAST            blocksize
 372: PRECALL              
 376: CALL                 
 386: STORE_FAST           sent
 388: LOAD_FAST            sent
 390: LOAD_CONST           0
 392: COMPARE_OP           ==
 398: POP_JUMP_FORWARD_IF_FALSE to 404
 400: LOAD_CONST           None
 402: RETURN_VALUE         
 404: LOAD_FAST            offset
 406: LOAD_FAST            sent
 408: BINARY_OP            +=
 412: STORE_FAST           offset
 414: JUMP_FORWARD         to 742
 416: PUSH_EXC_INFO        
 418: LOAD_GLOBAL          OSError
 430: CHECK_EXC_MATCH      
 432: POP_JUMP_FORWARD_IF_FALSE to 734
 434: STORE_FAST           err
 436: LOAD_FAST            fsrc
 438: LOAD_ATTR            name
 448: LOAD_FAST            err
 450: STORE_ATTR           filename
 460: LOAD_FAST            fdst
 462: LOAD_ATTR            name
 472: LOAD_FAST            err
 474: STORE_ATTR           filename2
 484: LOAD_FAST            err
 486: LOAD_ATTR            errno
 496: LOAD_GLOBAL          errno
 508: LOAD_ATTR            ENOTSOCK
 518: COMPARE_OP           ==
 524: POP_JUMP_FORWARD_IF_FALSE to 560
 526: LOAD_CONST           False
 528: STORE_GLOBAL         _USE_CP_SENDFILE
 530: LOAD_GLOBAL          NULL + _GiveupOnFastCopy
 542: LOAD_FAST            err
 544: PRECALL              
 548: CALL                 
 558: RAISE_VARARGS        
 560: LOAD_FAST            err
 562: LOAD_ATTR            errno
 572: LOAD_GLOBAL          errno
 584: LOAD_ATTR            ENOSPC
 594: COMPARE_OP           ==
 600: POP_JUMP_FORWARD_IF_FALSE to 608
 602: LOAD_FAST            err
 604: LOAD_CONST           None
 606: RAISE_VARARGS        
 608: LOAD_FAST            offset
 610: LOAD_CONST           0
 612: COMPARE_OP           ==
 618: POP_JUMP_FORWARD_IF_FALSE to 722
 620: LOAD_GLOBAL          NULL + os
 632: LOAD_ATTR            lseek
 642: LOAD_FAST            outfd
 644: LOAD_CONST           0
 646: LOAD_GLOBAL          os
 658: LOAD_ATTR            SEEK_CUR
 668: PRECALL              
 672: CALL                 
 682: LOAD_CONST           0
 684: COMPARE_OP           ==
 690: POP_JUMP_FORWARD_IF_FALSE to 722
 692: LOAD_GLOBAL          NULL + _GiveupOnFastCopy
 704: LOAD_FAST            err
 706: PRECALL              
 710: CALL                 
 720: RAISE_VARARGS        
 722: LOAD_FAST            err
 724: RAISE_VARARGS        
 726: LOAD_CONST           None
 728: STORE_FAST           err
 730: DELETE_FAST          err
 732: RERAISE              
 734: RERAISE              
 736: COPY                 
 738: POP_EXCEPT           
 740: RERAISE              
 742: JUMP_BACKWARD        to 340
