# Disassembly for shutil._is_immutable
# From module file: shutil

## co_consts:
(None, 'st_flags')

## co_names:
('_stat', 'stat', 'UF_IMMUTABLE', 'SF_IMMUTABLE', 'hasattr', 'st_flags')

## bytecode:

   0: RESUME               
   2: LOAD_GLOBAL          NULL + _stat
  14: LOAD_FAST            src
  16: PRECALL              
  20: CALL                 
  30: STORE_FAST           st
  32: LOAD_GLOBAL          stat
  44: LOAD_ATTR            UF_IMMUTABLE
  54: LOAD_GLOBAL          stat
  66: LOAD_ATTR            SF_IMMUTABLE
  76: BUILD_LIST           
  78: STORE_FAST           immutable_states
  80: LOAD_GLOBAL          NULL + hasattr
  92: LOAD_FAST            st
  94: LOAD_CONST           'st_flags'
  96: PRECALL              
 100: CALL                 
 110: JUMP_IF_FALSE_OR_POP to 128
 112: LOAD_FAST            st
 114: LOAD_ATTR            st_flags
 124: LOAD_FAST            immutable_states
 126: CONTAINS_OP          
 128: RETURN_VALUE         
