# Disassembly for shutil.SpecialFileError
# From module file: shutil

## co_consts:
('SpecialFileError', 'Raised when trying to do a kind of operation (e.g. copying) which is\n    not supported on a special file (e.g. a named pipe)', None)

## co_names:
('__name__', '__module__', '__qualname__', '__doc__')

## bytecode:

   0: RESUME               
   2: LOAD_NAME            __name__
   4: STORE_NAME           __module__
   6: LOAD_CONST           'SpecialFileError'
   8: STORE_NAME           __qualname__
  10: LOAD_CONST           'Raised when trying to do a kind of operation (e.g. copying) which is\n    not supported on a special file (e.g. a named pipe)'
  12: STORE_NAME           __doc__
  14: LOAD_CONST           None
  16: RETURN_VALUE         
