# Disassembly for shutil.copystat
# From module file: shutil

## co_consts:
('Copy file metadata\n\n    Copy the permission bits, last access time, last modification time, and\n    flags from `src` to `dst`. On Linux, copystat() also copies the "extended\n    attributes" where possible. The file contents, owner, and group are\n    unaffected. `src` and `dst` are path-like objects or path names given as\n    strings.\n\n    If the optional flag `follow_symlinks` is not set, symlinks aren\'t\n    followed if and only if both `src` and `dst` are symlinks.\n    ', 'shutil.copystat', None, ('ns', 'follow_symlinks'), <code object _nop at 0x000002406943B270, file "shutil.py", line 353>, <code object lookup at 0x000002406945F3C0, file "shutil.py", line 360>, <code object lookup at 0x000002406944BEE0, file "shutil.py", line 365>, ('follow_symlinks',), 'stat', 'utime', 'chmod', 'st_flags', 'chflags', ('EOPNOTSUPP', 'ENOTSUP'))

## co_names:
('sys', 'audit', '_islink', 'os', 'path', 'islink', 'isinstance', 'DirEntry', 'stat', 'S_IMODE', 'st_mode', 'st_atime_ns', 'st_mtime_ns', '_copyxattr', 'NotImplementedError', 'hasattr', 'st_flags', 'OSError', 'errno', 'getattr')

## bytecode:

   0: MAKE_CELL            _nop
   2: RESUME               
   4: LOAD_GLOBAL          NULL + sys
  16: LOAD_ATTR            audit
  26: LOAD_CONST           'shutil.copystat'
  28: LOAD_FAST            src
  30: LOAD_FAST            dst
  32: PRECALL              
  36: CALL                 
  46: POP_TOP              
  48: LOAD_CONST           None
  50: LOAD_CONST           None
  52: LOAD_CONST           ('ns', 'follow_symlinks')
  54: BUILD_CONST_KEY_MAP  
  56: LOAD_CONST           <code object _nop at 0x000002406943B270, file "shutil.py", line 353>
  58: MAKE_FUNCTION        kwdefaults
  60: STORE_DEREF          _nop
  62: LOAD_FAST            follow_symlinks
  64: JUMP_IF_TRUE_OR_POP  to 158
  66: LOAD_GLOBAL          NULL + _islink
  78: LOAD_FAST            src
  80: PRECALL              
  84: CALL                 
  94: JUMP_IF_FALSE_OR_POP to 156
  96: LOAD_GLOBAL          os
 108: LOAD_ATTR            path
 118: LOAD_METHOD          islink
 140: LOAD_FAST            dst
 142: PRECALL              
 146: CALL                 
 156: UNARY_NOT            
 158: STORE_FAST           follow
 160: LOAD_FAST            follow
 162: POP_JUMP_FORWARD_IF_FALSE to 176
 164: LOAD_CLOSURE         _nop
 166: BUILD_TUPLE          
 168: LOAD_CONST           <code object lookup at 0x000002406945F3C0, file "shutil.py", line 360>
 170: MAKE_FUNCTION        closure
 172: STORE_FAST           lookup
 174: JUMP_FORWARD         to 186
 176: LOAD_CLOSURE         _nop
 178: BUILD_TUPLE          
 180: LOAD_CONST           <code object lookup at 0x000002406944BEE0, file "shutil.py", line 365>
 182: MAKE_FUNCTION        closure
 184: STORE_FAST           lookup
 186: LOAD_GLOBAL          NULL + isinstance
 198: LOAD_FAST            src
 200: LOAD_GLOBAL          os
 212: LOAD_ATTR            DirEntry
 222: PRECALL              
 226: CALL                 
 236: POP_JUMP_FORWARD_IF_FALSE to 284
 238: LOAD_FAST            src
 240: LOAD_METHOD          stat
 262: LOAD_FAST            follow
 264: KW_NAMES             
 266: PRECALL              
 270: CALL                 
 280: STORE_FAST           st
 282: JUMP_FORWARD         to 328
 284: PUSH_NULL            
 286: PUSH_NULL            
 288: LOAD_FAST            lookup
 290: LOAD_CONST           'stat'
 292: PRECALL              
 296: CALL                 
 306: LOAD_FAST            src
 308: LOAD_FAST            follow
 310: KW_NAMES             
 312: PRECALL              
 316: CALL                 
 326: STORE_FAST           st
 328: LOAD_GLOBAL          NULL + stat
 340: LOAD_ATTR            S_IMODE
 350: LOAD_FAST            st
 352: LOAD_ATTR            st_mode
 362: PRECALL              
 366: CALL                 
 376: STORE_FAST           mode
 378: PUSH_NULL            
 380: PUSH_NULL            
 382: LOAD_FAST            lookup
 384: LOAD_CONST           'utime'
 386: PRECALL              
 390: CALL                 
 400: LOAD_FAST            dst
 402: LOAD_FAST            st
 404: LOAD_ATTR            st_atime_ns
 414: LOAD_FAST            st
 416: LOAD_ATTR            st_mtime_ns
 426: BUILD_TUPLE          
 428: LOAD_FAST            follow
 430: KW_NAMES             
 432: PRECALL              
 436: CALL                 
 446: POP_TOP              
 448: LOAD_GLOBAL          NULL + _copyxattr
 460: LOAD_FAST            src
 462: LOAD_FAST            dst
 464: LOAD_FAST            follow
 466: KW_NAMES             
 468: PRECALL              
 472: CALL                 
 482: POP_TOP              
 484: NOP                  
 486: PUSH_NULL            
 488: PUSH_NULL            
 490: LOAD_FAST            lookup
 492: LOAD_CONST           'chmod'
 494: PRECALL              
 498: CALL                 
 508: LOAD_FAST            dst
 510: LOAD_FAST            mode
 512: LOAD_FAST            follow
 514: KW_NAMES             
 516: PRECALL              
 520: CALL                 
 530: POP_TOP              
 532: JUMP_FORWARD         to 566
 534: PUSH_EXC_INFO        
 536: LOAD_GLOBAL          NotImplementedError
 548: CHECK_EXC_MATCH      
 550: POP_JUMP_FORWARD_IF_FALSE to 558
 552: POP_TOP              
 554: POP_EXCEPT           
 556: JUMP_FORWARD         to 566
 558: RERAISE              
 560: COPY                 
 562: POP_EXCEPT           
 564: RERAISE              
 566: LOAD_GLOBAL          NULL + hasattr
 578: LOAD_FAST            st
 580: LOAD_CONST           'st_flags'
 582: PRECALL              
 586: CALL                 
 596: POP_JUMP_FORWARD_IF_FALSE to 826
 598: NOP                  
 600: PUSH_NULL            
 602: PUSH_NULL            
 604: LOAD_FAST            lookup
 606: LOAD_CONST           'chflags'
 608: PRECALL              
 612: CALL                 
 622: LOAD_FAST            dst
 624: LOAD_FAST            st
 626: LOAD_ATTR            st_flags
 636: LOAD_FAST            follow
 638: KW_NAMES             
 640: PRECALL              
 644: CALL                 
 654: POP_TOP              
 656: LOAD_CONST           None
 658: RETURN_VALUE         
 660: PUSH_EXC_INFO        
 662: LOAD_GLOBAL          OSError
 674: CHECK_EXC_MATCH      
 676: POP_JUMP_FORWARD_IF_FALSE to 818
 678: STORE_FAST           why
 680: LOAD_CONST           ('EOPNOTSUPP', 'ENOTSUP')
 682: GET_ITER             
 684: FOR_ITER             to 796
 686: STORE_FAST           err
 688: LOAD_GLOBAL          NULL + hasattr
 700: LOAD_GLOBAL          errno
 712: LOAD_FAST            err
 714: PRECALL              
 718: CALL                 
 728: POP_JUMP_FORWARD_IF_FALSE to 794
 730: LOAD_FAST            why
 732: LOAD_ATTR            errno
 742: LOAD_GLOBAL          NULL + getattr
 754: LOAD_GLOBAL          errno
 766: LOAD_FAST            err
 768: PRECALL              
 772: CALL                 
 782: COMPARE_OP           ==
 788: POP_JUMP_FORWARD_IF_FALSE to 794
 790: POP_TOP              
 792: JUMP_FORWARD         to 798
 794: JUMP_BACKWARD        to 684
 796: RAISE_VARARGS        
 798: POP_EXCEPT           
 800: LOAD_CONST           None
 802: STORE_FAST           why
 804: DELETE_FAST          why
 806: LOAD_CONST           None
 808: RETURN_VALUE         
 810: LOAD_CONST           None
 812: STORE_FAST           why
 814: DELETE_FAST          why
 816: RERAISE              
 818: RERAISE              
 820: COPY                 
 822: POP_EXCEPT           
 824: RERAISE              
 826: LOAD_CONST           None
 828: RETURN_VALUE         
