# Disassembly for shutil.copy2
# From module file: shutil

## co_consts:
('Copy data and metadata. Return the file\'s destination.\n\n    Metadata is copied with copystat(). Please see the copystat function\n    for more information.\n\n    The destination may be a directory.\n\n    If follow_symlinks is false, symlinks won\'t be followed. This\n    resembles GNU\'s "cp -P src dst".\n    ', ('follow_symlinks',))

## co_names:
('os', 'path', 'isdir', 'join', 'basename', 'copyfile', 'copystat')

## bytecode:

   0: RESUME               
   2: LOAD_GLOBAL          os
  14: LOAD_ATTR            path
  24: LOAD_METHOD          isdir
  46: LOAD_FAST            dst
  48: PRECALL              
  52: CALL                 
  62: POP_JUMP_FORWARD_IF_FALSE to 186
  64: LOAD_GLOBAL          os
  76: LOAD_ATTR            path
  86: LOAD_METHOD          join
 108: LOAD_FAST            dst
 110: LOAD_GLOBAL          os
 122: LOAD_ATTR            path
 132: LOAD_METHOD          basename
 154: LOAD_FAST            src
 156: PRECALL              
 160: CALL                 
 170: PRECALL              
 174: CALL                 
 184: STORE_FAST           dst
 186: LOAD_GLOBAL          NULL + copyfile
 198: LOAD_FAST            src
 200: LOAD_FAST            dst
 202: LOAD_FAST            follow_symlinks
 204: KW_NAMES             
 206: PRECALL              
 210: CALL                 
 220: POP_TOP              
 222: LOAD_GLOBAL          NULL + copystat
 234: LOAD_FAST            src
 236: LOAD_FAST            dst
 238: LOAD_FAST            follow_symlinks
 240: KW_NAMES             
 242: PRECALL              
 246: CALL                 
 256: POP_TOP              
 258: LOAD_FAST            dst
 260: RETURN_VALUE         
