# Disassembly for shutil.ignore_patterns._ignore_patterns
# From module file: shutil

## co_consts:
(None,)

## co_names:
('extend', 'fnmatch', 'filter', 'set')

## bytecode:

   0: COPY_FREE_VARS       
   2: RESUME               
   4: BUILD_LIST           
   6: STORE_FAST           ignored_names
   8: LOAD_DEREF           patterns
  10: GET_ITER             
  12: FOR_ITER             to 98
  14: STORE_FAST           pattern
  16: LOAD_FAST            ignored_names
  18: LOAD_METHOD          extend
  40: LOAD_GLOBAL          NULL + fnmatch
  52: LOAD_ATTR            filter
  62: LOAD_FAST            names
  64: LOAD_FAST            pattern
  66: PRECALL              
  70: CALL                 
  80: PRECALL              
  84: CALL                 
  94: POP_TOP              
  96: JUMP_BACKWARD        to 12
  98: LOAD_GLOBAL          NULL + set
 110: LOAD_FAST            ignored_names
 112: PRECALL              
 116: CALL                 
 126: RETURN_VALUE         
