# Disassembly for shutil._islink
# From module file: shutil

## co_consts:
(None,)

## co_names:
('isinstance', 'os', 'DirEntry', 'is_symlink', 'path', 'islink')

## bytecode:

   0: RESUME               
   2: LOAD_GLOBAL          NULL + isinstance
  14: LOAD_FAST            fn
  16: LOAD_GLOBAL          os
  28: LOAD_ATTR            DirEntry
  38: PRECALL              
  42: CALL                 
  52: POP_JUMP_FORWARD_IF_FALSE to 94
  54: LOAD_FAST            fn
  56: LOAD_METHOD          is_symlink
  78: PRECALL              
  82: CALL                 
  92: JUMP_FORWARD         to 154
  94: LOAD_GLOBAL          os
 106: LOAD_ATTR            path
 116: LOAD_METHOD          islink
 138: LOAD_FAST            fn
 140: PRECALL              
 144: CALL                 
 154: RETURN_VALUE         
