# Disassembly for shutil.disk_usage
# From module file: shutil

## co_consts:
("Return disk usage statistics about the given path.\n\n        Returned values is a named tuple with attributes 'total', 'used' and\n        'free', which are the amount of total, used and free space, in bytes.\n        ",)

## co_names:
('nt', '_getdiskusage', '_ntuple_diskusage')

## bytecode:

   0: RESUME               
   2: LOAD_GLOBAL          NULL + nt
  14: LOAD_ATTR            _getdiskusage
  24: LOAD_FAST            path
  26: PRECALL              
  30: CALL                 
  40: UNPACK_SEQUENCE      
  44: STORE_FAST           total
  46: STORE_FAST           free
  48: LOAD_FAST            total
  50: LOAD_FAST            free
  52: BINARY_OP            -
  56: STORE_FAST           used
  58: LOAD_GLOBAL          NULL + _ntuple_diskusage
  70: LOAD_FAST            total
  72: LOAD_FAST            used
  74: LOAD_FAST            free
  76: PRECALL              
  80: CALL                 
  90: RETURN_VALUE         
