# Disassembly for shutil._rmtree_unsafe
# From module file: shutil

## co_consts:
(None, 'Cannot call rmtree on a symbolic link')

## co_names:
('os', 'scandir', 'list', 'OSError', 'sys', 'exc_info', 'path', '_rmtree_isdir', 'is_symlink', 'islink', '_rmtree_unsafe', 'unlink', 'rmdir')

## bytecode:

   0: RESUME               
   2: NOP                  
   4: LOAD_GLOBAL          NULL + os
  16: LOAD_ATTR            scandir
  26: LOAD_FAST            path
  28: PRECALL              
  32: CALL                 
  42: BEFORE_WITH          
  44: STORE_FAST           scandir_it
  46: LOAD_GLOBAL          NULL + list
  58: LOAD_FAST            scandir_it
  60: PRECALL              
  64: CALL                 
  74: STORE_FAST           entries
  76: LOAD_CONST           None
  78: LOAD_CONST           None
  80: LOAD_CONST           None
  82: PRECALL              
  86: CALL                 
  96: POP_TOP              
  98: JUMP_FORWARD         to 122
 100: PUSH_EXC_INFO        
 102: WITH_EXCEPT_START    
 104: POP_JUMP_FORWARD_IF_TRUE to 114
 106: RERAISE              
 108: COPY                 
 110: POP_EXCEPT           
 112: RERAISE              
 114: POP_TOP              
 116: POP_EXCEPT           
 118: POP_TOP              
 120: POP_TOP              
 122: JUMP_FORWARD         to 240
 124: PUSH_EXC_INFO        
 126: LOAD_GLOBAL          OSError
 138: CHECK_EXC_MATCH      
 140: POP_JUMP_FORWARD_IF_FALSE to 232
 142: POP_TOP              
 144: PUSH_NULL            
 146: LOAD_FAST            onerror
 148: LOAD_GLOBAL          os
 160: LOAD_ATTR            scandir
 170: LOAD_FAST            path
 172: LOAD_GLOBAL          NULL + sys
 184: LOAD_ATTR            exc_info
 194: PRECALL              
 198: CALL                 
 208: PRECALL              
 212: CALL                 
 222: POP_TOP              
 224: BUILD_LIST           
 226: STORE_FAST           entries
 228: POP_EXCEPT           
 230: JUMP_FORWARD         to 240
 232: RERAISE              
 234: COPY                 
 236: POP_EXCEPT           
 238: RERAISE              
 240: LOAD_FAST            entries
 242: GET_ITER             
 244: FOR_ITER             to 678
 246: STORE_FAST           entry
 248: LOAD_FAST            entry
 250: LOAD_ATTR            path
 260: STORE_FAST           fullname
 262: LOAD_GLOBAL          NULL + _rmtree_isdir
 274: LOAD_FAST            entry
 276: PRECALL              
 280: CALL                 
 290: POP_JUMP_FORWARD_IF_FALSE to 522
 292: NOP                  
 294: LOAD_FAST            entry
 296: LOAD_METHOD          is_symlink
 318: PRECALL              
 322: CALL                 
 332: POP_JUMP_FORWARD_IF_FALSE to 364
 334: LOAD_GLOBAL          NULL + OSError
 346: LOAD_CONST           'Cannot call rmtree on a symbolic link'
 348: PRECALL              
 352: CALL                 
 362: RAISE_VARARGS        
 364: JUMP_FORWARD         to 488
 366: PUSH_EXC_INFO        
 368: LOAD_GLOBAL          OSError
 380: CHECK_EXC_MATCH      
 382: POP_JUMP_FORWARD_IF_FALSE to 480
 384: POP_TOP              
 386: PUSH_NULL            
 388: LOAD_FAST            onerror
 390: LOAD_GLOBAL          os
 402: LOAD_ATTR            path
 412: LOAD_ATTR            islink
 422: LOAD_FAST            fullname
 424: LOAD_GLOBAL          NULL + sys
 436: LOAD_ATTR            exc_info
 446: PRECALL              
 450: CALL                 
 460: PRECALL              
 464: CALL                 
 474: POP_TOP              
 476: POP_EXCEPT           
 478: JUMP_BACKWARD        to 244
 480: RERAISE              
 482: COPY                 
 484: POP_EXCEPT           
 486: RERAISE              
 488: LOAD_GLOBAL          NULL + _rmtree_unsafe
 500: LOAD_FAST            fullname
 502: LOAD_FAST            onerror
 504: PRECALL              
 508: CALL                 
 518: POP_TOP              
 520: JUMP_BACKWARD        to 244
 522: NOP                  
 524: LOAD_GLOBAL          NULL + os
 536: LOAD_ATTR            unlink
 546: LOAD_FAST            fullname
 548: PRECALL              
 552: CALL                 
 562: POP_TOP              
 564: JUMP_BACKWARD        to 244
 566: PUSH_EXC_INFO        
 568: LOAD_GLOBAL          OSError
 580: CHECK_EXC_MATCH      
 582: POP_JUMP_FORWARD_IF_FALSE to 670
 584: POP_TOP              
 586: PUSH_NULL            
 588: LOAD_FAST            onerror
 590: LOAD_GLOBAL          os
 602: LOAD_ATTR            unlink
 612: LOAD_FAST            fullname
 614: LOAD_GLOBAL          NULL + sys
 626: LOAD_ATTR            exc_info
 636: PRECALL              
 640: CALL                 
 650: PRECALL              
 654: CALL                 
 664: POP_TOP              
 666: POP_EXCEPT           
 668: JUMP_BACKWARD        to 244
 670: RERAISE              
 672: COPY                 
 674: POP_EXCEPT           
 676: RERAISE              
 678: NOP                  
 680: LOAD_GLOBAL          NULL + os
 692: LOAD_ATTR            rmdir
 702: LOAD_FAST            path
 704: PRECALL              
 708: CALL                 
 718: POP_TOP              
 720: LOAD_CONST           None
 722: RETURN_VALUE         
 724: PUSH_EXC_INFO        
 726: LOAD_GLOBAL          OSError
 738: CHECK_EXC_MATCH      
 740: POP_JUMP_FORWARD_IF_FALSE to 830
 742: POP_TOP              
 744: PUSH_NULL            
 746: LOAD_FAST            onerror
 748: LOAD_GLOBAL          os
 760: LOAD_ATTR            rmdir
 770: LOAD_FAST            path
 772: LOAD_GLOBAL          NULL + sys
 784: LOAD_ATTR            exc_info
 794: PRECALL              
 798: CALL                 
 808: PRECALL              
 812: CALL                 
 822: POP_TOP              
 824: POP_EXCEPT           
 826: LOAD_CONST           None
 828: RETURN_VALUE         
 830: RERAISE              
 832: COPY                 
 834: POP_EXCEPT           
 836: RERAISE              
