# Disassembly for shutil._make_zipfile
# From module file: shutil

## co_consts:
('Create a zip file from all the files under \'base_dir\'.\n\n    The output zip file will be named \'base_name\' + ".zip".  Returns the\n    name of the output zip file.\n    ', 0, None, '.zip', 'creating %s', "creating '%s' and adding '%s' to it", 'w', ('compression',), "adding '%s'")

## co_names:
('zipfile', 'os', 'path', 'dirname', 'exists', 'info', 'makedirs', 'ZipFile', 'ZIP_DEFLATED', 'normpath', 'join', 'curdir', 'write', 'walk', 'relpath', 'sorted', 'isfile', 'abspath')

## bytecode:

   0: RESUME               
   2: LOAD_CONST           0
   4: LOAD_CONST           None
   6: IMPORT_NAME          zipfile
   8: STORE_FAST           zipfile
  10: LOAD_FAST            base_name
  12: LOAD_CONST           '.zip'
  14: BINARY_OP            +
  18: STORE_FAST           zip_filename
  20: LOAD_GLOBAL          os
  32: LOAD_ATTR            path
  42: LOAD_METHOD          dirname
  64: LOAD_FAST            base_name
  66: PRECALL              
  70: CALL                 
  80: STORE_FAST           archive_dir
  82: LOAD_FAST            archive_dir
  84: POP_JUMP_FORWARD_IF_FALSE to 240
  86: LOAD_GLOBAL          os
  98: LOAD_ATTR            path
 108: LOAD_METHOD          exists
 130: LOAD_FAST            archive_dir
 132: PRECALL              
 136: CALL                 
 146: POP_JUMP_FORWARD_IF_TRUE to 240
 148: LOAD_FAST            logger
 150: POP_JUMP_FORWARD_IF_NONE to 196
 152: LOAD_FAST            logger
 154: LOAD_METHOD          info
 176: LOAD_CONST           'creating %s'
 178: LOAD_FAST            archive_dir
 180: PRECALL              
 184: CALL                 
 194: POP_TOP              
 196: LOAD_FAST            dry_run
 198: POP_JUMP_FORWARD_IF_TRUE to 240
 200: LOAD_GLOBAL          NULL + os
 212: LOAD_ATTR            makedirs
 222: LOAD_FAST            archive_dir
 224: PRECALL              
 228: CALL                 
 238: POP_TOP              
 240: LOAD_FAST            logger
 242: POP_JUMP_FORWARD_IF_NONE to 290
 244: LOAD_FAST            logger
 246: LOAD_METHOD          info
 268: LOAD_CONST           "creating '%s' and adding '%s' to it"
 270: LOAD_FAST            zip_filename
 272: LOAD_FAST            base_dir
 274: PRECALL              
 278: CALL                 
 288: POP_TOP              
 290: LOAD_FAST            dry_run
 292: EXTENDED_ARG         
 294: POP_JUMP_FORWARD_IF_TRUE to 1522
 296: LOAD_FAST            zipfile
 298: LOAD_METHOD          ZipFile
 320: LOAD_FAST            zip_filename
 322: LOAD_CONST           'w'
 324: LOAD_FAST            zipfile
 326: LOAD_ATTR            ZIP_DEFLATED
 336: KW_NAMES             
 338: PRECALL              
 342: CALL                 
 352: BEFORE_WITH          
 354: STORE_FAST           zf
 356: LOAD_GLOBAL          os
 368: LOAD_ATTR            path
 378: LOAD_METHOD          normpath
 400: LOAD_FAST            base_dir
 402: PRECALL              
 406: CALL                 
 416: STORE_FAST           arcname
 418: LOAD_FAST            root_dir
 420: POP_JUMP_FORWARD_IF_NONE to 486
 422: LOAD_GLOBAL          os
 434: LOAD_ATTR            path
 444: LOAD_METHOD          join
 466: LOAD_FAST            root_dir
 468: LOAD_FAST            base_dir
 470: PRECALL              
 474: CALL                 
 484: STORE_FAST           base_dir
 486: LOAD_GLOBAL          os
 498: LOAD_ATTR            path
 508: LOAD_METHOD          normpath
 530: LOAD_FAST            base_dir
 532: PRECALL              
 536: CALL                 
 546: STORE_FAST           base_dir
 548: LOAD_FAST            arcname
 550: LOAD_GLOBAL          os
 562: LOAD_ATTR            curdir
 572: COMPARE_OP           !=
 578: POP_JUMP_FORWARD_IF_FALSE to 672
 580: LOAD_FAST            zf
 582: LOAD_METHOD          write
 604: LOAD_FAST            base_dir
 606: LOAD_FAST            arcname
 608: PRECALL              
 612: CALL                 
 622: POP_TOP              
 624: LOAD_FAST            logger
 626: POP_JUMP_FORWARD_IF_NONE to 672
 628: LOAD_FAST            logger
 630: LOAD_METHOD          info
 652: LOAD_CONST           "adding '%s'"
 654: LOAD_FAST            base_dir
 656: PRECALL              
 660: CALL                 
 670: POP_TOP              
 672: LOAD_GLOBAL          NULL + os
 684: LOAD_ATTR            walk
 694: LOAD_FAST            base_dir
 696: PRECALL              
 700: CALL                 
 710: GET_ITER             
 712: EXTENDED_ARG         
 714: FOR_ITER             to 1474
 716: UNPACK_SEQUENCE      
 720: STORE_FAST           dirpath
 722: STORE_FAST           dirnames
 724: STORE_FAST           filenames
 726: LOAD_FAST            dirpath
 728: STORE_FAST           arcdirpath
 730: LOAD_FAST            root_dir
 732: POP_JUMP_FORWARD_IF_NONE to 798
 734: LOAD_GLOBAL          os
 746: LOAD_ATTR            path
 756: LOAD_METHOD          relpath
 778: LOAD_FAST            arcdirpath
 780: LOAD_FAST            root_dir
 782: PRECALL              
 786: CALL                 
 796: STORE_FAST           arcdirpath
 798: LOAD_GLOBAL          os
 810: LOAD_ATTR            path
 820: LOAD_METHOD          normpath
 842: LOAD_FAST            arcdirpath
 844: PRECALL              
 848: CALL                 
 858: STORE_FAST           arcdirpath
 860: LOAD_GLOBAL          NULL + sorted
 872: LOAD_FAST            dirnames
 874: PRECALL              
 878: CALL                 
 888: GET_ITER             
 890: FOR_ITER             to 1116
 892: STORE_FAST           name
 894: LOAD_GLOBAL          os
 906: LOAD_ATTR            path
 916: LOAD_METHOD          join
 938: LOAD_FAST            dirpath
 940: LOAD_FAST            name
 942: PRECALL              
 946: CALL                 
 956: STORE_FAST           path
 958: LOAD_GLOBAL          os
 970: LOAD_ATTR            path
 980: LOAD_METHOD          join
1002: LOAD_FAST            arcdirpath
1004: LOAD_FAST            name
1006: PRECALL              
1010: CALL                 
1020: STORE_FAST           arcname
1022: LOAD_FAST            zf
1024: LOAD_METHOD          write
1046: LOAD_FAST            path
1048: LOAD_FAST            arcname
1050: PRECALL              
1054: CALL                 
1064: POP_TOP              
1066: LOAD_FAST            logger
1068: POP_JUMP_FORWARD_IF_NONE to 1114
1070: LOAD_FAST            logger
1072: LOAD_METHOD          info
1094: LOAD_CONST           "adding '%s'"
1096: LOAD_FAST            path
1098: PRECALL              
1102: CALL                 
1112: POP_TOP              
1114: JUMP_BACKWARD        to 890
1116: LOAD_FAST            filenames
1118: GET_ITER             
1120: FOR_ITER             to 1470
1122: STORE_FAST           name
1124: LOAD_GLOBAL          os
1136: LOAD_ATTR            path
1146: LOAD_METHOD          join
1168: LOAD_FAST            dirpath
1170: LOAD_FAST            name
1172: PRECALL              
1176: CALL                 
1186: STORE_FAST           path
1188: LOAD_GLOBAL          os
1200: LOAD_ATTR            path
1210: LOAD_METHOD          normpath
1232: LOAD_FAST            path
1234: PRECALL              
1238: CALL                 
1248: STORE_FAST           path
1250: LOAD_GLOBAL          os
1262: LOAD_ATTR            path
1272: LOAD_METHOD          isfile
1294: LOAD_FAST            path
1296: PRECALL              
1300: CALL                 
1310: POP_JUMP_FORWARD_IF_FALSE to 1468
1312: LOAD_GLOBAL          os
1324: LOAD_ATTR            path
1334: LOAD_METHOD          join
1356: LOAD_FAST            arcdirpath
1358: LOAD_FAST            name
1360: PRECALL              
1364: CALL                 
1374: STORE_FAST           arcname
1376: LOAD_FAST            zf
1378: LOAD_METHOD          write
1400: LOAD_FAST            path
1402: LOAD_FAST            arcname
1404: PRECALL              
1408: CALL                 
1418: POP_TOP              
1420: LOAD_FAST            logger
1422: POP_JUMP_FORWARD_IF_NONE to 1468
1424: LOAD_FAST            logger
1426: LOAD_METHOD          info
1448: LOAD_CONST           "adding '%s'"
1450: LOAD_FAST            path
1452: PRECALL              
1456: CALL                 
1466: POP_TOP              
1468: JUMP_BACKWARD        to 1120
1470: EXTENDED_ARG         
1472: JUMP_BACKWARD        to 712
1474: NOP                  
1476: LOAD_CONST           None
1478: LOAD_CONST           None
1480: LOAD_CONST           None
1482: PRECALL              
1486: CALL                 
1496: POP_TOP              
1498: JUMP_FORWARD         to 1522
1500: PUSH_EXC_INFO        
1502: WITH_EXCEPT_START    
1504: POP_JUMP_FORWARD_IF_TRUE to 1514
1506: RERAISE              
1508: COPY                 
1510: POP_EXCEPT           
1512: RERAISE              
1514: POP_TOP              
1516: POP_EXCEPT           
1518: POP_TOP              
1520: POP_TOP              
1522: LOAD_FAST            root_dir
1524: POP_JUMP_FORWARD_IF_NONE to 1588
1526: LOAD_GLOBAL          os
1538: LOAD_ATTR            path
1548: LOAD_METHOD          abspath
1570: LOAD_FAST            zip_filename
1572: PRECALL              
1576: CALL                 
1586: STORE_FAST           zip_filename
1588: LOAD_FAST            zip_filename
1590: RETURN_VALUE         
