# Disassembly for shutil.register_archive_format
# From module file: shutil

## co_consts:
('Registers an archive format.\n\n    name is the name of the format. function is the callable that will be\n    used to create archives. If provided, extra_args is a sequence of\n    (name, value) tuples that will be passed as arguments to the callable.\n    description can be provided to describe the format, and will be returned\n    by the get_archive_formats() function.\n    ', None, 'The %s object is not callable', 'extra_args needs to be a sequence', 2, 'extra_args elements are : (arg_name, value)', False)

## co_names:
('callable', 'TypeError', 'isinstance', 'tuple', 'list', 'len', '_ARCHIVE_FORMATS')

## bytecode:

   0: RESUME               
   2: LOAD_FAST            extra_args
   4: POP_JUMP_FORWARD_IF_NOT_NONE to 10
   6: BUILD_LIST           
   8: STORE_FAST           extra_args
  10: LOAD_GLOBAL          NULL + callable
  22: LOAD_FAST            function
  24: PRECALL              
  28: CALL                 
  38: POP_JUMP_FORWARD_IF_TRUE to 76
  40: LOAD_GLOBAL          NULL + TypeError
  52: LOAD_CONST           'The %s object is not callable'
  54: LOAD_FAST            function
  56: BINARY_OP            %
  60: PRECALL              
  64: CALL                 
  74: RAISE_VARARGS        
  76: LOAD_GLOBAL          NULL + isinstance
  88: LOAD_FAST            extra_args
  90: LOAD_GLOBAL          tuple
 102: LOAD_GLOBAL          list
 114: BUILD_TUPLE          
 116: PRECALL              
 120: CALL                 
 130: POP_JUMP_FORWARD_IF_TRUE to 162
 132: LOAD_GLOBAL          NULL + TypeError
 144: LOAD_CONST           'extra_args needs to be a sequence'
 146: PRECALL              
 150: CALL                 
 160: RAISE_VARARGS        
 162: LOAD_FAST            extra_args
 164: GET_ITER             
 166: FOR_ITER             to 296
 168: STORE_FAST           element
 170: LOAD_GLOBAL          NULL + isinstance
 182: LOAD_FAST            element
 184: LOAD_GLOBAL          tuple
 196: LOAD_GLOBAL          list
 208: BUILD_TUPLE          
 210: PRECALL              
 214: CALL                 
 224: POP_JUMP_FORWARD_IF_FALSE to 264
 226: LOAD_GLOBAL          NULL + len
 238: LOAD_FAST            element
 240: PRECALL              
 244: CALL                 
 254: LOAD_CONST           2
 256: COMPARE_OP           !=
 262: POP_JUMP_FORWARD_IF_FALSE to 294
 264: LOAD_GLOBAL          NULL + TypeError
 276: LOAD_CONST           'extra_args elements are : (arg_name, value)'
 278: PRECALL              
 282: CALL                 
 292: RAISE_VARARGS        
 294: JUMP_BACKWARD        to 166
 296: LOAD_FAST            function
 298: LOAD_FAST            extra_args
 300: LOAD_FAST            description
 302: LOAD_CONST           False
 304: BUILD_TUPLE          
 306: LOAD_GLOBAL          _ARCHIVE_FORMATS
 318: LOAD_FAST            name
 320: STORE_SUBSCR         
 324: LOAD_CONST           None
 326: RETURN_VALUE         
