# Disassembly for shutil._ensure_directory
# From module file: shutil

## co_consts:
('Ensure that the parent directory of `path` exists', None)

## co_names:
('os', 'path', 'dirname', 'isdir', 'makedirs')

## bytecode:

   0: RESUME               
   2: LOAD_GLOBAL          os
  14: LOAD_ATTR            path
  24: LOAD_METHOD          dirname
  46: LOAD_FAST            path
  48: PRECALL              
  52: CALL                 
  62: STORE_FAST           dirname
  64: LOAD_GLOBAL          os
  76: LOAD_ATTR            path
  86: LOAD_METHOD          isdir
 108: LOAD_FAST            dirname
 110: PRECALL              
 114: CALL                 
 124: POP_JUMP_FORWARD_IF_TRUE to 170
 126: LOAD_GLOBAL          NULL + os
 138: LOAD_ATTR            makedirs
 148: LOAD_FAST            dirname
 150: PRECALL              
 154: CALL                 
 164: POP_TOP              
 166: LOAD_CONST           None
 168: RETURN_VALUE         
 170: LOAD_CONST           None
 172: RETURN_VALUE         
