# Disassembly for shutil._GiveupOnFastCopy
# From module file: shutil

## co_consts:
('_GiveupOnFastCopy', 'Raised as a signal to fallback on using raw read()/write()\n    file copy when fast-copy functions fail to do so.\n    ', None)

## co_names:
('__name__', '__module__', '__qualname__', '__doc__')

## bytecode:

   0: RESUME               
   2: LOAD_NAME            __name__
   4: STORE_NAME           __module__
   6: LOAD_CONST           '_GiveupOnFastCopy'
   8: STORE_NAME           __qualname__
  10: LOAD_CONST           'Raised as a signal to fallback on using raw read()/write()\n    file copy when fast-copy functions fail to do so.\n    '
  12: STORE_NAME           __doc__
  14: LOAD_CONST           None
  16: RETURN_VALUE         
