# Disassembly for shutil.get_unpack_formats.<listcomp>
# From module file: shutil

## co_consts:
(0, 3)

## co_names:
()

## bytecode:

   0: RESUME               
   2: BUILD_LIST           
   4: LOAD_FAST            .0
   6: FOR_ITER             to 52
   8: UNPACK_SEQUENCE      
  12: STORE_FAST           name
  14: STORE_FAST           info
  16: LOAD_FAST            name
  18: LOAD_FAST            info
  20: LOAD_CONST           0
  22: BINARY_SUBSCR        
  32: LOAD_FAST            info
  34: LOAD_CONST           3
  36: BINARY_SUBSCR        
  46: BUILD_TUPLE          
  48: LIST_APPEND          
  50: JUMP_BACKWARD        to 6
  52: RETURN_VALUE         
