# Disassembly for shutil._check_unpack_options
# From module file: shutil

## co_consts:
('Checks what gets registered as an unpacker.', 0, '%s is already registered for "%s"', 'The registered function must be a callable', None)

## co_names:
('_UNPACK_FORMATS', 'items', 'RegistryError', 'callable', 'TypeError')

## bytecode:

   0: RESUME               
   2: BUILD_MAP            
   4: STORE_FAST           existing_extensions
   6: LOAD_GLOBAL          _UNPACK_FORMATS
  18: LOAD_METHOD          items
  40: PRECALL              
  44: CALL                 
  54: GET_ITER             
  56: FOR_ITER             to 100
  58: UNPACK_SEQUENCE      
  62: STORE_FAST           name
  64: STORE_FAST           info
  66: LOAD_FAST            info
  68: LOAD_CONST           0
  70: BINARY_SUBSCR        
  80: GET_ITER             
  82: FOR_ITER             to 98
  84: STORE_FAST           ext
  86: LOAD_FAST            name
  88: LOAD_FAST            existing_extensions
  90: LOAD_FAST            ext
  92: STORE_SUBSCR         
  96: JUMP_BACKWARD        to 82
  98: JUMP_BACKWARD        to 56
 100: LOAD_FAST            extensions
 102: GET_ITER             
 104: FOR_ITER             to 174
 106: STORE_FAST           extension
 108: LOAD_FAST            extension
 110: LOAD_FAST            existing_extensions
 112: CONTAINS_OP          
 114: POP_JUMP_FORWARD_IF_FALSE to 172
 116: LOAD_CONST           '%s is already registered for "%s"'
 118: STORE_FAST           msg
 120: LOAD_GLOBAL          NULL + RegistryError
 132: LOAD_FAST            msg
 134: LOAD_FAST            extension
 136: LOAD_FAST            existing_extensions
 138: LOAD_FAST            extension
 140: BINARY_SUBSCR        
 150: BUILD_TUPLE          
 152: BINARY_OP            %
 156: PRECALL              
 160: CALL                 
 170: RAISE_VARARGS        
 172: JUMP_BACKWARD        to 104
 174: LOAD_GLOBAL          NULL + callable
 186: LOAD_FAST            function
 188: PRECALL              
 192: CALL                 
 202: POP_JUMP_FORWARD_IF_TRUE to 234
 204: LOAD_GLOBAL          NULL + TypeError
 216: LOAD_CONST           'The registered function must be a callable'
 218: PRECALL              
 222: CALL                 
 232: RAISE_VARARGS        
 234: LOAD_CONST           None
 236: RETURN_VALUE         
