# Disassembly for shutil.copyfile
# From module file: shutil

## co_consts:
('Copy data from src to dst in the most efficient way possible.\n\n    If follow_symlinks is not set and src is a symbolic link, a new\n    symlink will be created instead of copying the file it points to.\n\n    ', 'shutil.copyfile', '{!r} and {!r} are the same file', 0, '`%s` is a named pipe', 'rb', 'wb', None, 'Directory does not exist: ')

## co_names:
('sys', 'audit', '_samefile', 'SameFileError', 'format', 'enumerate', '_stat', 'stat', 'S_ISFIFO', 'st_mode', 'isinstance', 'os', 'DirEntry', 'path', 'SpecialFileError', '_WINDOWS', 'st_size', 'OSError', '_islink', 'symlink', 'readlink', 'open', '_HAS_FCOPYFILE', '_fastcopy_fcopyfile', 'posix', '_COPYFILE_DATA', '_GiveupOnFastCopy', '_USE_CP_SENDFILE', '_fastcopy_sendfile', '_copyfileobj_readinto', 'min', 'COPY_BUFSIZE', 'copyfileobj', 'IsADirectoryError', 'exists', 'FileNotFoundError')

## bytecode:

   0: RESUME               
   2: LOAD_GLOBAL          NULL + sys
  14: LOAD_ATTR            audit
  24: LOAD_CONST           'shutil.copyfile'
  26: LOAD_FAST            src
  28: LOAD_FAST            dst
  30: PRECALL              
  34: CALL                 
  44: POP_TOP              
  46: LOAD_GLOBAL          NULL + _samefile
  58: LOAD_FAST            src
  60: LOAD_FAST            dst
  62: PRECALL              
  66: CALL                 
  76: POP_JUMP_FORWARD_IF_FALSE to 148
  78: LOAD_GLOBAL          NULL + SameFileError
  90: LOAD_CONST           '{!r} and {!r} are the same file'
  92: LOAD_METHOD          format
 114: LOAD_FAST            src
 116: LOAD_FAST            dst
 118: PRECALL              
 122: CALL                 
 132: PRECALL              
 136: CALL                 
 146: RAISE_VARARGS        
 148: LOAD_CONST           0
 150: STORE_FAST           file_size
 152: LOAD_GLOBAL          NULL + enumerate
 164: LOAD_FAST            src
 166: LOAD_FAST            dst
 168: BUILD_LIST           
 170: PRECALL              
 174: CALL                 
 184: GET_ITER             
 186: FOR_ITER             to 458
 188: UNPACK_SEQUENCE      
 192: STORE_FAST           i
 194: STORE_FAST           fn
 196: NOP                  
 198: LOAD_GLOBAL          NULL + _stat
 210: LOAD_FAST            fn
 212: PRECALL              
 216: CALL                 
 226: STORE_FAST           st
 228: LOAD_GLOBAL          NULL + stat
 240: LOAD_ATTR            S_ISFIFO
 250: LOAD_FAST            st
 252: LOAD_ATTR            st_mode
 262: PRECALL              
 266: CALL                 
 276: POP_JUMP_FORWARD_IF_FALSE to 384
 278: LOAD_GLOBAL          NULL + isinstance
 290: LOAD_FAST            fn
 292: LOAD_GLOBAL          os
 304: LOAD_ATTR            DirEntry
 314: PRECALL              
 318: CALL                 
 328: POP_JUMP_FORWARD_IF_FALSE to 344
 330: LOAD_FAST            fn
 332: LOAD_ATTR            path
 342: JUMP_FORWARD         to 346
 344: LOAD_FAST            fn
 346: STORE_FAST           fn
 348: LOAD_GLOBAL          NULL + SpecialFileError
 360: LOAD_CONST           '`%s` is a named pipe'
 362: LOAD_FAST            fn
 364: BINARY_OP            %
 368: PRECALL              
 372: CALL                 
 382: RAISE_VARARGS        
 384: LOAD_GLOBAL          _WINDOWS
 396: POP_JUMP_FORWARD_IF_FALSE to 424
 398: LOAD_FAST            i
 400: LOAD_CONST           0
 402: COMPARE_OP           ==
 408: POP_JUMP_FORWARD_IF_FALSE to 424
 410: LOAD_FAST            st
 412: LOAD_ATTR            st_size
 422: STORE_FAST           file_size
 424: JUMP_BACKWARD        to 186
 426: PUSH_EXC_INFO        
 428: LOAD_GLOBAL          OSError
 440: CHECK_EXC_MATCH      
 442: POP_JUMP_FORWARD_IF_FALSE to 450
 444: POP_TOP              
 446: POP_EXCEPT           
 448: JUMP_BACKWARD        to 186
 450: RERAISE              
 452: COPY                 
 454: POP_EXCEPT           
 456: RERAISE              
 458: LOAD_FAST            follow_symlinks
 460: POP_JUMP_FORWARD_IF_TRUE to 574
 462: LOAD_GLOBAL          NULL + _islink
 474: LOAD_FAST            src
 476: PRECALL              
 480: CALL                 
 490: POP_JUMP_FORWARD_IF_FALSE to 574
 492: LOAD_GLOBAL          NULL + os
 504: LOAD_ATTR            symlink
 514: LOAD_GLOBAL          NULL + os
 526: LOAD_ATTR            readlink
 536: LOAD_FAST            src
 538: PRECALL              
 542: CALL                 
 552: LOAD_FAST            dst
 554: PRECALL              
 558: CALL                 
 568: POP_TOP              
 570: EXTENDED_ARG         
 572: JUMP_FORWARD         to 1344
 574: LOAD_GLOBAL          NULL + open
 586: LOAD_FAST            src
 588: LOAD_CONST           'rb'
 590: PRECALL              
 594: CALL                 
 604: BEFORE_WITH          
 606: STORE_FAST           fsrc
 608: NOP                  
 610: LOAD_GLOBAL          NULL + open
 622: LOAD_FAST            dst
 624: LOAD_CONST           'wb'
 626: PRECALL              
 630: CALL                 
 640: BEFORE_WITH          
 642: STORE_FAST           fdst
 644: LOAD_GLOBAL          _HAS_FCOPYFILE
 656: POP_JUMP_FORWARD_IF_FALSE to 798
 658: NOP                  
 660: LOAD_GLOBAL          NULL + _fastcopy_fcopyfile
 672: LOAD_FAST            fsrc
 674: LOAD_FAST            fdst
 676: LOAD_GLOBAL          posix
 688: LOAD_ATTR            _COPYFILE_DATA
 698: PRECALL              
 702: CALL                 
 712: POP_TOP              
 714: LOAD_FAST            dst
 716: SWAP                 
 718: LOAD_CONST           None
 720: LOAD_CONST           None
 722: LOAD_CONST           None
 724: PRECALL              
 728: CALL                 
 738: POP_TOP              
 740: SWAP                 
 742: LOAD_CONST           None
 744: LOAD_CONST           None
 746: LOAD_CONST           None
 748: PRECALL              
 752: CALL                 
 762: POP_TOP              
 764: RETURN_VALUE         
 766: PUSH_EXC_INFO        
 768: LOAD_GLOBAL          _GiveupOnFastCopy
 780: CHECK_EXC_MATCH      
 782: POP_JUMP_FORWARD_IF_FALSE to 790
 784: POP_TOP              
 786: POP_EXCEPT           
 788: JUMP_FORWARD         to 1080
 790: RERAISE              
 792: COPY                 
 794: POP_EXCEPT           
 796: RERAISE              
 798: LOAD_GLOBAL          _USE_CP_SENDFILE
 810: POP_JUMP_FORWARD_IF_FALSE to 930
 812: NOP                  
 814: LOAD_GLOBAL          NULL + _fastcopy_sendfile
 826: LOAD_FAST            fsrc
 828: LOAD_FAST            fdst
 830: PRECALL              
 834: CALL                 
 844: POP_TOP              
 846: LOAD_FAST            dst
 848: SWAP                 
 850: LOAD_CONST           None
 852: LOAD_CONST           None
 854: LOAD_CONST           None
 856: PRECALL              
 860: CALL                 
 870: POP_TOP              
 872: SWAP                 
 874: LOAD_CONST           None
 876: LOAD_CONST           None
 878: LOAD_CONST           None
 880: PRECALL              
 884: CALL                 
 894: POP_TOP              
 896: RETURN_VALUE         
 898: PUSH_EXC_INFO        
 900: LOAD_GLOBAL          _GiveupOnFastCopy
 912: CHECK_EXC_MATCH      
 914: POP_JUMP_FORWARD_IF_FALSE to 922
 916: POP_TOP              
 918: POP_EXCEPT           
 920: JUMP_FORWARD         to 1080
 922: RERAISE              
 924: COPY                 
 926: POP_EXCEPT           
 928: RERAISE              
 930: LOAD_GLOBAL          _WINDOWS
 942: POP_JUMP_FORWARD_IF_FALSE to 1080
 944: LOAD_FAST            file_size
 946: LOAD_CONST           0
 948: COMPARE_OP           >
 954: POP_JUMP_FORWARD_IF_FALSE to 1080
 956: LOAD_GLOBAL          NULL + _copyfileobj_readinto
 968: LOAD_FAST            fsrc
 970: LOAD_FAST            fdst
 972: LOAD_GLOBAL          NULL + min
 984: LOAD_FAST            file_size
 986: LOAD_GLOBAL          COPY_BUFSIZE
 998: PRECALL              
1002: CALL                 
1012: PRECALL              
1016: CALL                 
1026: POP_TOP              
1028: LOAD_FAST            dst
1030: SWAP                 
1032: LOAD_CONST           None
1034: LOAD_CONST           None
1036: LOAD_CONST           None
1038: PRECALL              
1042: CALL                 
1052: POP_TOP              
1054: SWAP                 
1056: LOAD_CONST           None
1058: LOAD_CONST           None
1060: LOAD_CONST           None
1062: PRECALL              
1066: CALL                 
1076: POP_TOP              
1078: RETURN_VALUE         
1080: LOAD_GLOBAL          NULL + copyfileobj
1092: LOAD_FAST            fsrc
1094: LOAD_FAST            fdst
1096: PRECALL              
1100: CALL                 
1110: POP_TOP              
1112: LOAD_CONST           None
1114: LOAD_CONST           None
1116: LOAD_CONST           None
1118: PRECALL              
1122: CALL                 
1132: POP_TOP              
1134: JUMP_FORWARD         to 1158
1136: PUSH_EXC_INFO        
1138: WITH_EXCEPT_START    
1140: POP_JUMP_FORWARD_IF_TRUE to 1150
1142: RERAISE              
1144: COPY                 
1146: POP_EXCEPT           
1148: RERAISE              
1150: POP_TOP              
1152: POP_EXCEPT           
1154: POP_TOP              
1156: POP_TOP              
1158: JUMP_FORWARD         to 1298
1160: PUSH_EXC_INFO        
1162: LOAD_GLOBAL          IsADirectoryError
1174: CHECK_EXC_MATCH      
1176: POP_JUMP_FORWARD_IF_FALSE to 1290
1178: STORE_FAST           e
1180: LOAD_GLOBAL          os
1192: LOAD_ATTR            path
1202: LOAD_METHOD          exists
1224: LOAD_FAST            dst
1226: PRECALL              
1230: CALL                 
1240: POP_JUMP_FORWARD_IF_TRUE to 1280
1242: LOAD_GLOBAL          NULL + FileNotFoundError
1254: LOAD_CONST           'Directory does not exist: '
1256: LOAD_FAST            dst
1258: FORMAT_VALUE         
1260: BUILD_STRING         
1262: PRECALL              
1266: CALL                 
1276: LOAD_FAST            e
1278: RAISE_VARARGS        
1280: RAISE_VARARGS        
1282: LOAD_CONST           None
1284: STORE_FAST           e
1286: DELETE_FAST          e
1288: RERAISE              
1290: RERAISE              
1292: COPY                 
1294: POP_EXCEPT           
1296: RERAISE              
1298: LOAD_CONST           None
1300: LOAD_CONST           None
1302: LOAD_CONST           None
1304: PRECALL              
1308: CALL                 
1318: POP_TOP              
1320: JUMP_FORWARD         to 1344
1322: PUSH_EXC_INFO        
1324: WITH_EXCEPT_START    
1326: POP_JUMP_FORWARD_IF_TRUE to 1336
1328: RERAISE              
1330: COPY                 
1332: POP_EXCEPT           
1334: RERAISE              
1336: POP_TOP              
1338: POP_EXCEPT           
1340: POP_TOP              
1342: POP_TOP              
1344: LOAD_FAST            dst
1346: RETURN_VALUE         
