# Disassembly for shutil._fastcopy_fcopyfile
# From module file: shutil

## co_consts:
('Copy a regular file content or metadata by using high-performance\n    fcopyfile(3) syscall (macOS).\n    ', None)

## co_names:
('fileno', 'Exception', '_GiveupOnFastCopy', 'posix', '_fcopyfile', 'OSError', 'name', 'filename', 'filename2', 'errno', 'EINVAL', 'ENOTSUP')

## bytecode:

   0: RESUME               
   2: NOP                  
   4: LOAD_FAST            fsrc
   6: LOAD_METHOD          fileno
  28: PRECALL              
  32: CALL                 
  42: STORE_FAST           infd
  44: LOAD_FAST            fdst
  46: LOAD_METHOD          fileno
  68: PRECALL              
  72: CALL                 
  82: STORE_FAST           outfd
  84: JUMP_FORWARD         to 152
  86: PUSH_EXC_INFO        
  88: LOAD_GLOBAL          Exception
 100: CHECK_EXC_MATCH      
 102: POP_JUMP_FORWARD_IF_FALSE to 144
 104: STORE_FAST           err
 106: LOAD_GLOBAL          NULL + _GiveupOnFastCopy
 118: LOAD_FAST            err
 120: PRECALL              
 124: CALL                 
 134: RAISE_VARARGS        
 136: LOAD_CONST           None
 138: STORE_FAST           err
 140: DELETE_FAST          err
 142: RERAISE              
 144: RERAISE              
 146: COPY                 
 148: POP_EXCEPT           
 150: RERAISE              
 152: NOP                  
 154: LOAD_GLOBAL          NULL + posix
 166: LOAD_ATTR            _fcopyfile
 176: LOAD_FAST            infd
 178: LOAD_FAST            outfd
 180: LOAD_FAST            flags
 182: PRECALL              
 186: CALL                 
 196: POP_TOP              
 198: LOAD_CONST           None
 200: RETURN_VALUE         
 202: PUSH_EXC_INFO        
 204: LOAD_GLOBAL          OSError
 216: CHECK_EXC_MATCH      
 218: POP_JUMP_FORWARD_IF_FALSE to 376
 220: STORE_FAST           err
 222: LOAD_FAST            fsrc
 224: LOAD_ATTR            name
 234: LOAD_FAST            err
 236: STORE_ATTR           filename
 246: LOAD_FAST            fdst
 248: LOAD_ATTR            name
 258: LOAD_FAST            err
 260: STORE_ATTR           filename2
 270: LOAD_FAST            err
 272: LOAD_ATTR            errno
 282: LOAD_GLOBAL          errno
 294: LOAD_ATTR            EINVAL
 304: LOAD_GLOBAL          errno
 316: LOAD_ATTR            ENOTSUP
 326: BUILD_SET            
 328: CONTAINS_OP          
 330: POP_JUMP_FORWARD_IF_FALSE to 362
 332: LOAD_GLOBAL          NULL + _GiveupOnFastCopy
 344: LOAD_FAST            err
 346: PRECALL              
 350: CALL                 
 360: RAISE_VARARGS        
 362: LOAD_FAST            err
 364: LOAD_CONST           None
 366: RAISE_VARARGS        
 368: LOAD_CONST           None
 370: STORE_FAST           err
 372: DELETE_FAST          err
 374: RERAISE              
 376: RERAISE              
 378: COPY                 
 380: POP_EXCEPT           
 382: RERAISE              
