# Disassembly for shutil._rmtree_safe_fd
# From module file: shutil

## co_consts:
(None, False, ('follow_symlinks',), ('dir_fd',), True, 'Cannot call rmtree on a symbolic link')

## co_names:
('os', 'scandir', 'list', 'OSError', 'filename', 'sys', 'exc_info', 'path', 'join', 'name', 'is_dir', 'stat', 'S_ISDIR', 'st_mode', 'lstat', 'open', 'O_RDONLY', 'samestat', 'fstat', '_rmtree_safe_fd', 'close', 'rmdir', 'islink', 'unlink')

## bytecode:

   0: RESUME               
   2: NOP                  
   4: LOAD_GLOBAL          NULL + os
  16: LOAD_ATTR            scandir
  26: LOAD_FAST            topfd
  28: PRECALL              
  32: CALL                 
  42: BEFORE_WITH          
  44: STORE_FAST           scandir_it
  46: LOAD_GLOBAL          NULL + list
  58: LOAD_FAST            scandir_it
  60: PRECALL              
  64: CALL                 
  74: STORE_FAST           entries
  76: LOAD_CONST           None
  78: LOAD_CONST           None
  80: LOAD_CONST           None
  82: PRECALL              
  86: CALL                 
  96: POP_TOP              
  98: JUMP_FORWARD         to 122
 100: PUSH_EXC_INFO        
 102: WITH_EXCEPT_START    
 104: POP_JUMP_FORWARD_IF_TRUE to 114
 106: RERAISE              
 108: COPY                 
 110: POP_EXCEPT           
 112: RERAISE              
 114: POP_TOP              
 116: POP_EXCEPT           
 118: POP_TOP              
 120: POP_TOP              
 122: JUMP_FORWARD         to 266
 124: PUSH_EXC_INFO        
 126: LOAD_GLOBAL          OSError
 138: CHECK_EXC_MATCH      
 140: POP_JUMP_FORWARD_IF_FALSE to 258
 142: STORE_FAST           err
 144: LOAD_FAST            path
 146: LOAD_FAST            err
 148: STORE_ATTR           filename
 158: PUSH_NULL            
 160: LOAD_FAST            onerror
 162: LOAD_GLOBAL          os
 174: LOAD_ATTR            scandir
 184: LOAD_FAST            path
 186: LOAD_GLOBAL          NULL + sys
 198: LOAD_ATTR            exc_info
 208: PRECALL              
 212: CALL                 
 222: PRECALL              
 226: CALL                 
 236: POP_TOP              
 238: POP_EXCEPT           
 240: LOAD_CONST           None
 242: STORE_FAST           err
 244: DELETE_FAST          err
 246: LOAD_CONST           None
 248: RETURN_VALUE         
 250: LOAD_CONST           None
 252: STORE_FAST           err
 254: DELETE_FAST          err
 256: RERAISE              
 258: RERAISE              
 260: COPY                 
 262: POP_EXCEPT           
 264: RERAISE              
 266: LOAD_FAST            entries
 268: GET_ITER             
 270: EXTENDED_ARG         
 272: FOR_ITER             to 1632
 274: STORE_FAST           entry
 276: LOAD_GLOBAL          os
 288: LOAD_ATTR            path
 298: LOAD_METHOD          join
 320: LOAD_FAST            path
 322: LOAD_FAST            entry
 324: LOAD_ATTR            name
 334: PRECALL              
 338: CALL                 
 348: STORE_FAST           fullname
 350: NOP                  
 352: LOAD_FAST            entry
 354: LOAD_METHOD          is_dir
 376: LOAD_CONST           False
 378: KW_NAMES             
 380: PRECALL              
 384: CALL                 
 394: STORE_FAST           is_dir
 396: LOAD_FAST            is_dir
 398: POP_JUMP_FORWARD_IF_FALSE to 610
 400: NOP                  
 402: LOAD_FAST            entry
 404: LOAD_METHOD          stat
 426: LOAD_CONST           False
 428: KW_NAMES             
 430: PRECALL              
 434: CALL                 
 444: STORE_FAST           orig_st
 446: LOAD_GLOBAL          NULL + stat
 458: LOAD_ATTR            S_ISDIR
 468: LOAD_FAST            orig_st
 470: LOAD_ATTR            st_mode
 480: PRECALL              
 484: CALL                 
 494: STORE_FAST           is_dir
 496: JUMP_FORWARD         to 648
 498: PUSH_EXC_INFO        
 500: LOAD_GLOBAL          OSError
 512: CHECK_EXC_MATCH      
 514: POP_JUMP_FORWARD_IF_FALSE to 602
 516: POP_TOP              
 518: PUSH_NULL            
 520: LOAD_FAST            onerror
 522: LOAD_GLOBAL          os
 534: LOAD_ATTR            lstat
 544: LOAD_FAST            fullname
 546: LOAD_GLOBAL          NULL + sys
 558: LOAD_ATTR            exc_info
 568: PRECALL              
 572: CALL                 
 582: PRECALL              
 586: CALL                 
 596: POP_TOP              
 598: POP_EXCEPT           
 600: JUMP_BACKWARD        to 270
 602: RERAISE              
 604: COPY                 
 606: POP_EXCEPT           
 608: RERAISE              
 610: JUMP_FORWARD         to 648
 612: PUSH_EXC_INFO        
 614: LOAD_GLOBAL          OSError
 626: CHECK_EXC_MATCH      
 628: POP_JUMP_FORWARD_IF_FALSE to 640
 630: POP_TOP              
 632: LOAD_CONST           False
 634: STORE_FAST           is_dir
 636: POP_EXCEPT           
 638: JUMP_FORWARD         to 648
 640: RERAISE              
 642: COPY                 
 644: POP_EXCEPT           
 646: RERAISE              
 648: LOAD_FAST            is_dir
 650: EXTENDED_ARG         
 652: POP_JUMP_FORWARD_IF_FALSE to 1458
 654: NOP                  
 656: LOAD_GLOBAL          NULL + os
 668: LOAD_ATTR            open
 678: LOAD_FAST            entry
 680: LOAD_ATTR            name
 690: LOAD_GLOBAL          os
 702: LOAD_ATTR            O_RDONLY
 712: LOAD_FAST            topfd
 714: KW_NAMES             
 716: PRECALL              
 720: CALL                 
 730: STORE_FAST           dirfd
 732: LOAD_CONST           False
 734: STORE_FAST           dirfd_closed
 736: NOP                  
 738: LOAD_GLOBAL          os
 750: LOAD_ATTR            path
 760: LOAD_METHOD          samestat
 782: LOAD_FAST            orig_st
 784: LOAD_GLOBAL          NULL + os
 796: LOAD_ATTR            fstat
 806: LOAD_FAST            dirfd
 808: PRECALL              
 812: CALL                 
 822: PRECALL              
 826: CALL                 
 836: POP_JUMP_FORWARD_IF_FALSE to 1086
 838: LOAD_GLOBAL          NULL + _rmtree_safe_fd
 850: LOAD_FAST            dirfd
 852: LOAD_FAST            fullname
 854: LOAD_FAST            onerror
 856: PRECALL              
 860: CALL                 
 870: POP_TOP              
 872: NOP                  
 874: LOAD_GLOBAL          NULL + os
 886: LOAD_ATTR            close
 896: LOAD_FAST            dirfd
 898: PRECALL              
 902: CALL                 
 912: POP_TOP              
 914: LOAD_CONST           True
 916: STORE_FAST           dirfd_closed
 918: LOAD_GLOBAL          NULL + os
 930: LOAD_ATTR            rmdir
 940: LOAD_FAST            entry
 942: LOAD_ATTR            name
 952: LOAD_FAST            topfd
 954: KW_NAMES             
 956: PRECALL              
 960: CALL                 
 970: POP_TOP              
 972: JUMP_FORWARD         to 1240
 974: PUSH_EXC_INFO        
 976: LOAD_GLOBAL          OSError
 988: CHECK_EXC_MATCH      
 990: POP_JUMP_FORWARD_IF_FALSE to 1078
 992: POP_TOP              
 994: PUSH_NULL            
 996: LOAD_FAST            onerror
 998: LOAD_GLOBAL          os
1010: LOAD_ATTR            rmdir
1020: LOAD_FAST            fullname
1022: LOAD_GLOBAL          NULL + sys
1034: LOAD_ATTR            exc_info
1044: PRECALL              
1048: CALL                 
1058: PRECALL              
1062: CALL                 
1072: POP_TOP              
1074: POP_EXCEPT           
1076: JUMP_FORWARD         to 1240
1078: RERAISE              
1080: COPY                 
1082: POP_EXCEPT           
1084: RERAISE              
1086: NOP                  
1088: LOAD_GLOBAL          NULL + OSError
1100: LOAD_CONST           'Cannot call rmtree on a symbolic link'
1102: PRECALL              
1106: CALL                 
1116: RAISE_VARARGS        
1118: PUSH_EXC_INFO        
1120: LOAD_GLOBAL          OSError
1132: CHECK_EXC_MATCH      
1134: POP_JUMP_FORWARD_IF_FALSE to 1232
1136: POP_TOP              
1138: PUSH_NULL            
1140: LOAD_FAST            onerror
1142: LOAD_GLOBAL          os
1154: LOAD_ATTR            path
1164: LOAD_ATTR            islink
1174: LOAD_FAST            fullname
1176: LOAD_GLOBAL          NULL + sys
1188: LOAD_ATTR            exc_info
1198: PRECALL              
1202: CALL                 
1212: PRECALL              
1216: CALL                 
1226: POP_TOP              
1228: POP_EXCEPT           
1230: JUMP_FORWARD         to 1240
1232: RERAISE              
1234: COPY                 
1236: POP_EXCEPT           
1238: RERAISE              
1240: LOAD_FAST            dirfd_closed
1242: POP_JUMP_FORWARD_IF_TRUE to 1284
1244: LOAD_GLOBAL          NULL + os
1256: LOAD_ATTR            close
1266: LOAD_FAST            dirfd
1268: PRECALL              
1272: CALL                 
1282: POP_TOP              
1284: EXTENDED_ARG         
1286: JUMP_BACKWARD        to 270
1288: PUSH_EXC_INFO        
1290: LOAD_FAST            dirfd_closed
1292: POP_JUMP_FORWARD_IF_TRUE to 1336
1294: LOAD_GLOBAL          NULL + os
1306: LOAD_ATTR            close
1316: LOAD_FAST            dirfd
1318: PRECALL              
1322: CALL                 
1332: POP_TOP              
1334: RERAISE              
1336: RERAISE              
1338: COPY                 
1340: POP_EXCEPT           
1342: RERAISE              
1344: PUSH_EXC_INFO        
1346: LOAD_GLOBAL          OSError
1358: CHECK_EXC_MATCH      
1360: POP_JUMP_FORWARD_IF_FALSE to 1450
1362: POP_TOP              
1364: PUSH_NULL            
1366: LOAD_FAST            onerror
1368: LOAD_GLOBAL          os
1380: LOAD_ATTR            open
1390: LOAD_FAST            fullname
1392: LOAD_GLOBAL          NULL + sys
1404: LOAD_ATTR            exc_info
1414: PRECALL              
1418: CALL                 
1428: PRECALL              
1432: CALL                 
1442: POP_TOP              
1444: POP_EXCEPT           
1446: EXTENDED_ARG         
1448: JUMP_BACKWARD        to 270
1450: RERAISE              
1452: COPY                 
1454: POP_EXCEPT           
1456: RERAISE              
1458: NOP                  
1460: LOAD_GLOBAL          NULL + os
1472: LOAD_ATTR            unlink
1482: LOAD_FAST            entry
1484: LOAD_ATTR            name
1494: LOAD_FAST            topfd
1496: KW_NAMES             
1498: PRECALL              
1502: CALL                 
1512: POP_TOP              
1514: EXTENDED_ARG         
1516: JUMP_BACKWARD        to 270
1518: PUSH_EXC_INFO        
1520: LOAD_GLOBAL          OSError
1532: CHECK_EXC_MATCH      
1534: POP_JUMP_FORWARD_IF_FALSE to 1624
1536: POP_TOP              
1538: PUSH_NULL            
1540: LOAD_FAST            onerror
1542: LOAD_GLOBAL          os
1554: LOAD_ATTR            unlink
1564: LOAD_FAST            fullname
1566: LOAD_GLOBAL          NULL + sys
1578: LOAD_ATTR            exc_info
1588: PRECALL              
1592: CALL                 
1602: PRECALL              
1606: CALL                 
1616: POP_TOP              
1618: POP_EXCEPT           
1620: EXTENDED_ARG         
1622: JUMP_BACKWARD        to 270
1624: RERAISE              
1626: COPY                 
1628: POP_EXCEPT           
1630: RERAISE              
1632: LOAD_CONST           None
1634: RETURN_VALUE         
