# Disassembly for shutil.chown
# From module file: shutil

## co_consts:
('Change owner user and group of the given path.\n\n    user and group can be the uid/gid or the user/group names, and in that case,\n    they are converted to their respective uid/gid.\n    ', 'shutil.chown', None, 'user and/or group must be set', -1, 'no such user: {!r}', 'no such group: {!r}')

## co_names:
('sys', 'audit', 'ValueError', 'isinstance', 'str', '_get_uid', 'LookupError', 'format', 'int', '_get_gid', 'os', 'chown')

## bytecode:

   0: RESUME               
   2: LOAD_GLOBAL          NULL + sys
  14: LOAD_ATTR            audit
  24: LOAD_CONST           'shutil.chown'
  26: LOAD_FAST            path
  28: LOAD_FAST            user
  30: LOAD_FAST            group
  32: PRECALL              
  36: CALL                 
  46: POP_TOP              
  48: LOAD_FAST            user
  50: POP_JUMP_FORWARD_IF_NOT_NONE to 86
  52: LOAD_FAST            group
  54: POP_JUMP_FORWARD_IF_NOT_NONE to 86
  56: LOAD_GLOBAL          NULL + ValueError
  68: LOAD_CONST           'user and/or group must be set'
  70: PRECALL              
  74: CALL                 
  84: RAISE_VARARGS        
  86: LOAD_FAST            user
  88: STORE_FAST           _user
  90: LOAD_FAST            group
  92: STORE_FAST           _group
  94: LOAD_FAST            user
  96: POP_JUMP_FORWARD_IF_NOT_NONE to 104
  98: LOAD_CONST           -1
 100: STORE_FAST           _user
 102: JUMP_FORWARD         to 248
 104: LOAD_GLOBAL          NULL + isinstance
 116: LOAD_FAST            user
 118: LOAD_GLOBAL          str
 130: PRECALL              
 134: CALL                 
 144: POP_JUMP_FORWARD_IF_FALSE to 248
 146: LOAD_GLOBAL          NULL + _get_uid
 158: LOAD_FAST            user
 160: PRECALL              
 164: CALL                 
 174: STORE_FAST           _user
 176: LOAD_FAST            _user
 178: POP_JUMP_FORWARD_IF_NOT_NONE to 248
 180: LOAD_GLOBAL          NULL + LookupError
 192: LOAD_CONST           'no such user: {!r}'
 194: LOAD_METHOD          format
 216: LOAD_FAST            user
 218: PRECALL              
 222: CALL                 
 232: PRECALL              
 236: CALL                 
 246: RAISE_VARARGS        
 248: LOAD_FAST            group
 250: POP_JUMP_FORWARD_IF_NOT_NONE to 258
 252: LOAD_CONST           -1
 254: STORE_FAST           _group
 256: JUMP_FORWARD         to 402
 258: LOAD_GLOBAL          NULL + isinstance
 270: LOAD_FAST            group
 272: LOAD_GLOBAL          int
 284: PRECALL              
 288: CALL                 
 298: POP_JUMP_FORWARD_IF_TRUE to 402
 300: LOAD_GLOBAL          NULL + _get_gid
 312: LOAD_FAST            group
 314: PRECALL              
 318: CALL                 
 328: STORE_FAST           _group
 330: LOAD_FAST            _group
 332: POP_JUMP_FORWARD_IF_NOT_NONE to 402
 334: LOAD_GLOBAL          NULL + LookupError
 346: LOAD_CONST           'no such group: {!r}'
 348: LOAD_METHOD          format
 370: LOAD_FAST            group
 372: PRECALL              
 376: CALL                 
 386: PRECALL              
 390: CALL                 
 400: RAISE_VARARGS        
 402: LOAD_GLOBAL          NULL + os
 414: LOAD_ATTR            chown
 424: LOAD_FAST            path
 426: LOAD_FAST            _user
 428: LOAD_FAST            _group
 430: PRECALL              
 434: CALL                 
 444: POP_TOP              
 446: LOAD_CONST           None
 448: RETURN_VALUE         
