# Disassembly for shutil.register_unpack_format
# From module file: shutil

## co_consts:
("Registers an unpack format.\n\n    `name` is the name of the format. `extensions` is a list of extensions\n    corresponding to the format.\n\n    `function` is the callable that will be\n    used to unpack archives. The callable will receive archives to unpack.\n    If it's unable to handle an archive, it needs to raise a ReadError\n    exception.\n\n    If provided, `extra_args` is a sequence of\n    (name, value) tuples that will be passed as arguments to the callable.\n    description can be provided to describe the format, and will be returned\n    by the get_unpack_formats() function.\n    ", None)

## co_names:
('_check_unpack_options', '_UNPACK_FORMATS')

## bytecode:

   0: RESUME               
   2: LOAD_FAST            extra_args
   4: POP_JUMP_FORWARD_IF_NOT_NONE to 10
   6: BUILD_LIST           
   8: STORE_FAST           extra_args
  10: LOAD_GLOBAL          NULL + _check_unpack_options
  22: LOAD_FAST            extensions
  24: LOAD_FAST            function
  26: LOAD_FAST            extra_args
  28: PRECALL              
  32: CALL                 
  42: POP_TOP              
  44: LOAD_FAST            extensions
  46: LOAD_FAST            function
  48: LOAD_FAST            extra_args
  50: LOAD_FAST            description
  52: BUILD_TUPLE          
  54: LOAD_GLOBAL          _UNPACK_FORMATS
  66: LOAD_FAST            name
  68: STORE_SUBSCR         
  72: LOAD_CONST           None
  74: RETURN_VALUE         
