# Disassembly for shutil._make_tarball._set_uid_gid
# From module file: shutil

## co_consts:
(None,)

## co_names:
('gid', 'gname', 'uid', 'uname')

## bytecode:

   0: COPY_FREE_VARS       
   2: RESUME               
   4: LOAD_DEREF           gid
   6: POP_JUMP_FORWARD_IF_NONE to 36
   8: LOAD_DEREF           gid
  10: LOAD_FAST            tarinfo
  12: STORE_ATTR           gid
  22: LOAD_DEREF           group
  24: LOAD_FAST            tarinfo
  26: STORE_ATTR           gname
  36: LOAD_DEREF           uid
  38: POP_JUMP_FORWARD_IF_NONE to 68
  40: LOAD_DEREF           uid
  42: LOAD_FAST            tarinfo
  44: STORE_ATTR           uid
  54: LOAD_DEREF           owner
  56: LOAD_FAST            tarinfo
  58: STORE_ATTR           uname
  68: LOAD_FAST            tarinfo
  70: RETURN_VALUE         
