# Disassembly for shutil._find_unpack_format
# From module file: shutil

## co_consts:
(None, 0)

## co_names:
('_UNPACK_FORMATS', 'items', 'endswith')

## bytecode:

   0: RESUME               
   2: LOAD_GLOBAL          _UNPACK_FORMATS
  14: LOAD_METHOD          items
  36: PRECALL              
  40: CALL                 
  50: GET_ITER             
  52: FOR_ITER             to 140
  54: UNPACK_SEQUENCE      
  58: STORE_FAST           name
  60: STORE_FAST           info
  62: LOAD_FAST            info
  64: LOAD_CONST           0
  66: BINARY_SUBSCR        
  76: GET_ITER             
  78: FOR_ITER             to 138
  80: STORE_FAST           extension
  82: LOAD_FAST            filename
  84: LOAD_METHOD          endswith
 106: LOAD_FAST            extension
 108: PRECALL              
 112: CALL                 
 122: POP_JUMP_FORWARD_IF_FALSE to 136
 124: LOAD_FAST            name
 126: SWAP                 
 128: POP_TOP              
 130: SWAP                 
 132: POP_TOP              
 134: RETURN_VALUE         
 136: JUMP_BACKWARD        to 78
 138: JUMP_BACKWARD        to 52
 140: LOAD_CONST           None
 142: RETURN_VALUE         
