# Disassembly for shutil.copyfileobj
# From module file: shutil

## co_consts:
('copy data from file-like object fsrc to file-like object fdst', True, None)

## co_names:
('COPY_BUFSIZE', 'read', 'write')

## bytecode:

   0: RESUME               
   2: LOAD_FAST            length
   4: POP_JUMP_FORWARD_IF_TRUE to 20
   6: LOAD_GLOBAL          COPY_BUFSIZE
  18: STORE_FAST           length
  20: LOAD_FAST            fsrc
  22: LOAD_ATTR            read
  32: STORE_FAST           fsrc_read
  34: LOAD_FAST            fdst
  36: LOAD_ATTR            write
  46: STORE_FAST           fdst_write
  48: NOP                  
  50: PUSH_NULL            
  52: LOAD_FAST            fsrc_read
  54: LOAD_FAST            length
  56: PRECALL              
  60: CALL                 
  70: STORE_FAST           buf
  72: LOAD_FAST            buf
  74: POP_JUMP_FORWARD_IF_TRUE to 80
  76: LOAD_CONST           None
  78: RETURN_VALUE         
  80: PUSH_NULL            
  82: LOAD_FAST            fdst_write
  84: LOAD_FAST            buf
  86: PRECALL              
  90: CALL                 
 100: POP_TOP              
 102: JUMP_BACKWARD        to 50
