# Disassembly for left.Computer.__init__
# From module file: left

## co_consts:
(None, False, 'logical', '')

## co_names:
('super', '__init__', 'checked', 'password', 'note', 'cypher', 'upper')

## bytecode:

   0: COPY_FREE_VARS       
   2: RESUME               
   4: LOAD_GLOBAL          NULL + super
  16: PRECALL              
  20: CALL                 
  30: LOAD_METHOD          __init__
  52: LOAD_FAST            name
  54: PRECALL              
  58: CALL                 
  68: POP_TOP              
  70: LOAD_CONST           False
  72: LOAD_FAST            self
  74: STORE_ATTR           checked
  84: LOAD_CONST           'logical'
  86: LOAD_FAST            self
  88: STORE_ATTR           password
  98: LOAD_CONST           ''
 100: LOAD_FAST            self
 102: STORE_ATTR           note
 112: LOAD_FAST            self
 114: LOAD_ATTR            password
 124: GET_ITER             
 126: FOR_ITER             to 222
 128: STORE_FAST           ch
 130: LOAD_FAST            self
 132: COPY                 
 134: LOAD_ATTR            note
 144: LOAD_GLOBAL          cypher
 156: LOAD_FAST            ch
 158: LOAD_METHOD          upper
 180: PRECALL              
 184: CALL                 
 194: BINARY_SUBSCR        
 204: BINARY_OP            +=
 208: SWAP                 
 210: STORE_ATTR           note
 220: JUMP_BACKWARD        to 126
 222: LOAD_CONST           None
 224: RETURN_VALUE         
