# Disassembly for left.Computer.enter_password
# From module file: left

## co_consts:
(None, 'Please enter password', True, 'Breakroom', 'Password Accepted!  Brilliant work!\n\n<A LOUD CHIME COMES FROM THE BREAKROOM>', 'Incorrect password!  Try again.')

## co_names:
('ask', 'lower', 'password', 'world', 'rooms', 'central_left_unlocked', 'send_message')

## bytecode:

   0: RESUME               
   2: LOAD_FAST            self
   4: LOAD_METHOD          ask
  26: LOAD_CONST           'Please enter password'
  28: PRECALL              
  32: CALL                 
  42: LOAD_METHOD          lower
  64: PRECALL              
  68: CALL                 
  78: LOAD_FAST            self
  80: LOAD_ATTR            password
  90: COMPARE_OP           ==
  96: POP_JUMP_FORWARD_IF_FALSE to 190
  98: LOAD_CONST           True
 100: LOAD_FAST            self
 102: LOAD_ATTR            world
 112: LOAD_ATTR            rooms
 122: LOAD_CONST           'Breakroom'
 124: BINARY_SUBSCR        
 134: STORE_ATTR           central_left_unlocked
 144: LOAD_FAST            self
 146: LOAD_METHOD          send_message
 168: LOAD_CONST           'Password Accepted!  Brilliant work!\n\n<A LOUD CHIME COMES FROM THE BREAKROOM>'
 170: PRECALL              
 174: CALL                 
 184: POP_TOP              
 186: LOAD_CONST           None
 188: RETURN_VALUE         
 190: LOAD_FAST            self
 192: LOAD_METHOD          send_message
 214: LOAD_CONST           'Incorrect password!  Try again.'
 216: PRECALL              
 220: CALL                 
 230: POP_TOP              
 232: LOAD_CONST           None
 234: RETURN_VALUE         
