# Disassembly for left.Computer.check
# From module file: left

## co_consts:
(None, True, "The computer looks like it's asking for a password.\nThere is a cryptic note taped to the corner of the monitor that says:\n --- That is so ")

## co_names:
('checked', 'send_message', 'note')

## bytecode:

   0: RESUME               
   2: LOAD_CONST           True
   4: LOAD_FAST            self
   6: STORE_ATTR           checked
  16: LOAD_FAST            self
  18: LOAD_METHOD          send_message
  40: LOAD_CONST           "The computer looks like it's asking for a password.\nThere is a cryptic note taped to the corner of the monitor that says:\n --- That is so "
  42: LOAD_FAST            self
  44: LOAD_ATTR            note
  54: BINARY_OP            +
  58: PRECALL              
  62: CALL                 
  72: POP_TOP              
  74: LOAD_CONST           None
  76: RETURN_VALUE         
