# Disassembly for fractions.Fraction._floordiv
# From module file: fractions

## co_consts:
('a // b',)

## co_names:
('numerator', 'denominator')

## bytecode:

   0: RESUME               
   2: LOAD_FAST            a
   4: LOAD_ATTR            numerator
  14: LOAD_FAST            b
  16: LOAD_ATTR            denominator
  26: BINARY_OP            *
  30: LOAD_FAST            a
  32: LOAD_ATTR            denominator
  42: LOAD_FAST            b
  44: LOAD_ATTR            numerator
  54: BINARY_OP            *
  58: BINARY_OP            //
  62: RETURN_VALUE         
