# Disassembly for fractions.Fraction.__pow__
# From module file: fractions

## co_consts:
('a ** b\n\n        If b is not an integer, the result will be a float or complex\n        since roots are generally irrational. If b is an integer, the\n        result will be rational.\n\n        ', 1, 0, False, ('_normalize',))

## co_names:
('isinstance', 'numbers', 'Rational', 'denominator', 'numerator', 'Fraction', '_numerator', '_denominator', 'float')

## bytecode:

   0: RESUME               
   2: LOAD_GLOBAL          NULL + isinstance
  14: LOAD_FAST            b
  16: LOAD_GLOBAL          numbers
  28: LOAD_ATTR            Rational
  38: PRECALL              
  42: CALL                 
  52: POP_JUMP_FORWARD_IF_FALSE to 402
  54: LOAD_FAST            b
  56: LOAD_ATTR            denominator
  66: LOAD_CONST           1
  68: COMPARE_OP           ==
  74: POP_JUMP_FORWARD_IF_FALSE to 340
  76: LOAD_FAST            b
  78: LOAD_ATTR            numerator
  88: STORE_FAST           power
  90: LOAD_FAST            power
  92: LOAD_CONST           0
  94: COMPARE_OP           >=
 100: POP_JUMP_FORWARD_IF_FALSE to 170
 102: LOAD_GLOBAL          NULL + Fraction
 114: LOAD_FAST            a
 116: LOAD_ATTR            _numerator
 126: LOAD_FAST            power
 128: BINARY_OP            **
 132: LOAD_FAST            a
 134: LOAD_ATTR            _denominator
 144: LOAD_FAST            power
 146: BINARY_OP            **
 150: LOAD_CONST           False
 152: KW_NAMES             
 154: PRECALL              
 158: CALL                 
 168: RETURN_VALUE         
 170: LOAD_FAST            a
 172: LOAD_ATTR            _numerator
 182: LOAD_CONST           0
 184: COMPARE_OP           >=
 190: POP_JUMP_FORWARD_IF_FALSE to 264
 192: LOAD_GLOBAL          NULL + Fraction
 204: LOAD_FAST            a
 206: LOAD_ATTR            _denominator
 216: LOAD_FAST            power
 218: UNARY_NEGATIVE       
 220: BINARY_OP            **
 224: LOAD_FAST            a
 226: LOAD_ATTR            _numerator
 236: LOAD_FAST            power
 238: UNARY_NEGATIVE       
 240: BINARY_OP            **
 244: LOAD_CONST           False
 246: KW_NAMES             
 248: PRECALL              
 252: CALL                 
 262: RETURN_VALUE         
 264: LOAD_GLOBAL          NULL + Fraction
 276: LOAD_FAST            a
 278: LOAD_ATTR            _denominator
 288: UNARY_NEGATIVE       
 290: LOAD_FAST            power
 292: UNARY_NEGATIVE       
 294: BINARY_OP            **
 298: LOAD_FAST            a
 300: LOAD_ATTR            _numerator
 310: UNARY_NEGATIVE       
 312: LOAD_FAST            power
 314: UNARY_NEGATIVE       
 316: BINARY_OP            **
 320: LOAD_CONST           False
 322: KW_NAMES             
 324: PRECALL              
 328: CALL                 
 338: RETURN_VALUE         
 340: LOAD_GLOBAL          NULL + float
 352: LOAD_FAST            a
 354: PRECALL              
 358: CALL                 
 368: LOAD_GLOBAL          NULL + float
 380: LOAD_FAST            b
 382: PRECALL              
 386: CALL                 
 396: BINARY_OP            **
 400: RETURN_VALUE         
 402: LOAD_GLOBAL          NULL + float
 414: LOAD_FAST            a
 416: PRECALL              
 420: CALL                 
 430: LOAD_FAST            b
 432: BINARY_OP            **
 436: RETURN_VALUE         
