# Disassembly for fractions.Fraction.__rpow__
# From module file: fractions

## co_consts:
('a ** b', 1, 0)

## co_names:
('_denominator', '_numerator', 'isinstance', 'numbers', 'Rational', 'Fraction', 'numerator', 'denominator', 'float')

## bytecode:

   0: RESUME               
   2: LOAD_FAST            b
   4: LOAD_ATTR            _denominator
  14: LOAD_CONST           1
  16: COMPARE_OP           ==
  22: POP_JUMP_FORWARD_IF_FALSE to 66
  24: LOAD_FAST            b
  26: LOAD_ATTR            _numerator
  36: LOAD_CONST           0
  38: COMPARE_OP           >=
  44: POP_JUMP_FORWARD_IF_FALSE to 66
  46: LOAD_FAST            a
  48: LOAD_FAST            b
  50: LOAD_ATTR            _numerator
  60: BINARY_OP            **
  64: RETURN_VALUE         
  66: LOAD_GLOBAL          NULL + isinstance
  78: LOAD_FAST            a
  80: LOAD_GLOBAL          numbers
  92: LOAD_ATTR            Rational
 102: PRECALL              
 106: CALL                 
 116: POP_JUMP_FORWARD_IF_FALSE to 176
 118: LOAD_GLOBAL          NULL + Fraction
 130: LOAD_FAST            a
 132: LOAD_ATTR            numerator
 142: LOAD_FAST            a
 144: LOAD_ATTR            denominator
 154: PRECALL              
 158: CALL                 
 168: LOAD_FAST            b
 170: BINARY_OP            **
 174: RETURN_VALUE         
 176: LOAD_FAST            b
 178: LOAD_ATTR            _denominator
 188: LOAD_CONST           1
 190: COMPARE_OP           ==
 196: POP_JUMP_FORWARD_IF_FALSE to 218
 198: LOAD_FAST            a
 200: LOAD_FAST            b
 202: LOAD_ATTR            _numerator
 212: BINARY_OP            **
 216: RETURN_VALUE         
 218: LOAD_FAST            a
 220: LOAD_GLOBAL          NULL + float
 232: LOAD_FAST            b
 234: PRECALL              
 238: CALL                 
 248: BINARY_OP            **
 252: RETURN_VALUE         
