# Disassembly for fractions.Fraction._add
# From module file: fractions

## co_consts:
('a + b', 1, False, ('_normalize',))

## co_names:
('numerator', 'denominator', 'math', 'gcd', 'Fraction')

## bytecode:

   0: RESUME               
   2: LOAD_FAST            a
   4: LOAD_ATTR            numerator
  14: LOAD_FAST            a
  16: LOAD_ATTR            denominator
  26: STORE_FAST           da
  28: STORE_FAST           na
  30: LOAD_FAST            b
  32: LOAD_ATTR            numerator
  42: LOAD_FAST            b
  44: LOAD_ATTR            denominator
  54: STORE_FAST           db
  56: STORE_FAST           nb
  58: LOAD_GLOBAL          NULL + math
  70: LOAD_ATTR            gcd
  80: LOAD_FAST            da
  82: LOAD_FAST            db
  84: PRECALL              
  88: CALL                 
  98: STORE_FAST           g
 100: LOAD_FAST            g
 102: LOAD_CONST           1
 104: COMPARE_OP           ==
 110: POP_JUMP_FORWARD_IF_FALSE to 172
 112: LOAD_GLOBAL          NULL + Fraction
 124: LOAD_FAST            na
 126: LOAD_FAST            db
 128: BINARY_OP            *
 132: LOAD_FAST            da
 134: LOAD_FAST            nb
 136: BINARY_OP            *
 140: BINARY_OP            +
 144: LOAD_FAST            da
 146: LOAD_FAST            db
 148: BINARY_OP            *
 152: LOAD_CONST           False
 154: KW_NAMES             
 156: PRECALL              
 160: CALL                 
 170: RETURN_VALUE         
 172: LOAD_FAST            da
 174: LOAD_FAST            g
 176: BINARY_OP            //
 180: STORE_FAST           s
 182: LOAD_FAST            na
 184: LOAD_FAST            db
 186: LOAD_FAST            g
 188: BINARY_OP            //
 192: BINARY_OP            *
 196: LOAD_FAST            nb
 198: LOAD_FAST            s
 200: BINARY_OP            *
 204: BINARY_OP            +
 208: STORE_FAST           t
 210: LOAD_GLOBAL          NULL + math
 222: LOAD_ATTR            gcd
 232: LOAD_FAST            t
 234: LOAD_FAST            g
 236: PRECALL              
 240: CALL                 
 250: STORE_FAST           g2
 252: LOAD_FAST            g2
 254: LOAD_CONST           1
 256: COMPARE_OP           ==
 262: POP_JUMP_FORWARD_IF_FALSE to 306
 264: LOAD_GLOBAL          NULL + Fraction
 276: LOAD_FAST            t
 278: LOAD_FAST            s
 280: LOAD_FAST            db
 282: BINARY_OP            *
 286: LOAD_CONST           False
 288: KW_NAMES             
 290: PRECALL              
 294: CALL                 
 304: RETURN_VALUE         
 306: LOAD_GLOBAL          NULL + Fraction
 318: LOAD_FAST            t
 320: LOAD_FAST            g2
 322: BINARY_OP            //
 326: LOAD_FAST            s
 328: LOAD_FAST            db
 330: LOAD_FAST            g2
 332: BINARY_OP            //
 336: BINARY_OP            *
 340: LOAD_CONST           False
 342: KW_NAMES             
 344: PRECALL              
 348: CALL                 
 358: RETURN_VALUE         
