# Disassembly for fractions
# From module file: fractions

## co_consts:
('Fraction, infinite-precision, rational numbers.', 0, ('Decimal',), None, 'Fraction', '\n    \\A\\s*                                 # optional whitespace at the start,\n    (?P<sign>[-+]?)                       # an optional sign, then\n    (?=\\d|\\.\\d)                           # lookahead for digit or .digit\n    (?P<num>\\d*|\\d+(_\\d+)*)               # numerator (possibly empty)\n    (?:                                   # followed by\n       (?:/(?P<denom>\\d+(_\\d+)*))?        # an optional denominator\n    |                                     # or\n       (?:\\.(?P<decimal>d*|\\d+(_\\d+)*))?  # an optional fractional part\n       (?:E(?P<exp>[-+]?\\d+(_\\d+)*))?     # and optional exponent\n    )\n    \\s*\\Z                                 # and optional whitespace to finish\n', <code object Fraction at 0x0000024068B79230, file "fractions.py", line 38>)

## co_names:
('__doc__', 'decimal', 'Decimal', 'math', 'numbers', 'operator', 're', 'sys', '__all__', 'hash_info', 'modulus', '_PyHASH_MODULUS', 'inf', '_PyHASH_INF', 'compile', 'VERBOSE', 'IGNORECASE', '_RATIONAL_FORMAT', 'Rational', 'Fraction')

## bytecode:

   0: RESUME               
   2: LOAD_CONST           'Fraction, infinite-precision, rational numbers.'
   4: STORE_NAME           __doc__
   6: LOAD_CONST           0
   8: LOAD_CONST           ('Decimal',)
  10: IMPORT_NAME          decimal
  12: IMPORT_FROM          Decimal
  14: STORE_NAME           Decimal
  16: POP_TOP              
  18: LOAD_CONST           0
  20: LOAD_CONST           None
  22: IMPORT_NAME          math
  24: STORE_NAME           math
  26: LOAD_CONST           0
  28: LOAD_CONST           None
  30: IMPORT_NAME          numbers
  32: STORE_NAME           numbers
  34: LOAD_CONST           0
  36: LOAD_CONST           None
  38: IMPORT_NAME          operator
  40: STORE_NAME           operator
  42: LOAD_CONST           0
  44: LOAD_CONST           None
  46: IMPORT_NAME          re
  48: STORE_NAME           re
  50: LOAD_CONST           0
  52: LOAD_CONST           None
  54: IMPORT_NAME          sys
  56: STORE_NAME           sys
  58: LOAD_CONST           'Fraction'
  60: BUILD_LIST           
  62: STORE_NAME           __all__
  64: LOAD_NAME            sys
  66: LOAD_ATTR            hash_info
  76: LOAD_ATTR            modulus
  86: STORE_NAME           _PyHASH_MODULUS
  88: LOAD_NAME            sys
  90: LOAD_ATTR            hash_info
 100: LOAD_ATTR            inf
 110: STORE_NAME           _PyHASH_INF
 112: PUSH_NULL            
 114: LOAD_NAME            re
 116: LOAD_ATTR            compile
 126: LOAD_CONST           '\n    \\A\\s*                                 # optional whitespace at the start,\n    (?P<sign>[-+]?)                       # an optional sign, then\n    (?=\\d|\\.\\d)                           # lookahead for digit or .digit\n    (?P<num>\\d*|\\d+(_\\d+)*)               # numerator (possibly empty)\n    (?:                                   # followed by\n       (?:/(?P<denom>\\d+(_\\d+)*))?        # an optional denominator\n    |                                     # or\n       (?:\\.(?P<decimal>d*|\\d+(_\\d+)*))?  # an optional fractional part\n       (?:E(?P<exp>[-+]?\\d+(_\\d+)*))?     # and optional exponent\n    )\n    \\s*\\Z                                 # and optional whitespace to finish\n'
 128: LOAD_NAME            re
 130: LOAD_ATTR            VERBOSE
 140: LOAD_NAME            re
 142: LOAD_ATTR            IGNORECASE
 152: BINARY_OP            |
 156: PRECALL              
 160: CALL                 
 170: STORE_NAME           _RATIONAL_FORMAT
 172: PUSH_NULL            
 174: LOAD_BUILD_CLASS     
 176: LOAD_CONST           <code object Fraction at 0x0000024068B79230, file "fractions.py", line 38>
 178: MAKE_FUNCTION        
 180: LOAD_CONST           'Fraction'
 182: LOAD_NAME            numbers
 184: LOAD_ATTR            Rational
 194: PRECALL              
 198: CALL                 
 208: STORE_NAME           Fraction
 210: LOAD_CONST           None
 212: RETURN_VALUE         
