# Disassembly for fractions.Fraction.from_float
# From module file: fractions

## co_consts:
('Converts a finite float to a rational number, exactly.\n\n        Beware that Fraction.from_float(0.3) != Fraction(3, 10).\n\n        ', '.from_float() only takes floats, not ', ' (', ')')

## co_names:
('isinstance', 'numbers', 'Integral', 'float', 'TypeError', '__name__', 'type', 'as_integer_ratio')

## bytecode:

   0: RESUME               
   2: LOAD_GLOBAL          NULL + isinstance
  14: LOAD_FAST            f
  16: LOAD_GLOBAL          numbers
  28: LOAD_ATTR            Integral
  38: PRECALL              
  42: CALL                 
  52: POP_JUMP_FORWARD_IF_FALSE to 76
  54: PUSH_NULL            
  56: LOAD_FAST            cls
  58: LOAD_FAST            f
  60: PRECALL              
  64: CALL                 
  74: RETURN_VALUE         
  76: LOAD_GLOBAL          NULL + isinstance
  88: LOAD_FAST            f
  90: LOAD_GLOBAL          float
 102: PRECALL              
 106: CALL                 
 116: POP_JUMP_FORWARD_IF_TRUE to 212
 118: LOAD_GLOBAL          NULL + TypeError
 130: LOAD_FAST            cls
 132: LOAD_ATTR            __name__
 142: FORMAT_VALUE         str
 144: LOAD_CONST           '.from_float() only takes floats, not '
 146: LOAD_FAST            f
 148: FORMAT_VALUE         repr
 150: LOAD_CONST           ' ('
 152: LOAD_GLOBAL          NULL + type
 164: LOAD_FAST            f
 166: PRECALL              
 170: CALL                 
 180: LOAD_ATTR            __name__
 190: FORMAT_VALUE         str
 192: LOAD_CONST           ')'
 194: BUILD_STRING         
 196: PRECALL              
 200: CALL                 
 210: RAISE_VARARGS        
 212: PUSH_NULL            
 214: LOAD_FAST            cls
 216: LOAD_FAST            f
 218: LOAD_METHOD          as_integer_ratio
 240: PRECALL              
 244: CALL                 
 254: CALL_FUNCTION_EX     
 256: RETURN_VALUE         
