# Disassembly for fractions.Fraction.__round__
# From module file: fractions

## co_consts:
('round(self, ndigits)\n\n        Rounds half toward even.\n        ', None, 2, 1, 0, 10)

## co_names:
('divmod', 'numerator', 'denominator', 'abs', 'Fraction', 'round')

## bytecode:

   0: RESUME               
   2: LOAD_FAST            ndigits
   4: POP_JUMP_FORWARD_IF_NOT_NONE to 166
   6: LOAD_GLOBAL          NULL + divmod
  18: LOAD_FAST            self
  20: LOAD_ATTR            numerator
  30: LOAD_FAST            self
  32: LOAD_ATTR            denominator
  42: PRECALL              
  46: CALL                 
  56: UNPACK_SEQUENCE      
  60: STORE_FAST           floor
  62: STORE_FAST           remainder
  64: LOAD_FAST            remainder
  66: LOAD_CONST           2
  68: BINARY_OP            *
  72: LOAD_FAST            self
  74: LOAD_ATTR            denominator
  84: COMPARE_OP           <
  90: POP_JUMP_FORWARD_IF_FALSE to 96
  92: LOAD_FAST            floor
  94: RETURN_VALUE         
  96: LOAD_FAST            remainder
  98: LOAD_CONST           2
 100: BINARY_OP            *
 104: LOAD_FAST            self
 106: LOAD_ATTR            denominator
 116: COMPARE_OP           >
 122: POP_JUMP_FORWARD_IF_FALSE to 134
 124: LOAD_FAST            floor
 126: LOAD_CONST           1
 128: BINARY_OP            +
 132: RETURN_VALUE         
 134: LOAD_FAST            floor
 136: LOAD_CONST           2
 138: BINARY_OP            %
 142: LOAD_CONST           0
 144: COMPARE_OP           ==
 150: POP_JUMP_FORWARD_IF_FALSE to 156
 152: LOAD_FAST            floor
 154: RETURN_VALUE         
 156: LOAD_FAST            floor
 158: LOAD_CONST           1
 160: BINARY_OP            +
 164: RETURN_VALUE         
 166: LOAD_CONST           10
 168: LOAD_GLOBAL          NULL + abs
 180: LOAD_FAST            ndigits
 182: PRECALL              
 186: CALL                 
 196: BINARY_OP            **
 200: STORE_FAST           shift
 202: LOAD_FAST            ndigits
 204: LOAD_CONST           0
 206: COMPARE_OP           >
 212: POP_JUMP_FORWARD_IF_FALSE to 278
 214: LOAD_GLOBAL          NULL + Fraction
 226: LOAD_GLOBAL          NULL + round
 238: LOAD_FAST            self
 240: LOAD_FAST            shift
 242: BINARY_OP            *
 246: PRECALL              
 250: CALL                 
 260: LOAD_FAST            shift
 262: PRECALL              
 266: CALL                 
 276: RETURN_VALUE         
 278: LOAD_GLOBAL          NULL + Fraction
 290: LOAD_GLOBAL          NULL + round
 302: LOAD_FAST            self
 304: LOAD_FAST            shift
 306: BINARY_OP            /
 310: PRECALL              
 314: CALL                 
 324: LOAD_FAST            shift
 326: BINARY_OP            *
 330: PRECALL              
 334: CALL                 
 344: RETURN_VALUE         
