# Disassembly for ftplib.FTP.__init__
# From module file: ftplib

## co_consts:
('Initialization method (called by class instantiation).\n        Initialize host to localhost, port to standard ftp port.\n        Optional arguments are host (for connect()),\n        and user, passwd, acct (for login()).\n        ', None)

## co_names:
('encoding', 'source_address', 'timeout', 'connect', 'login')

## bytecode:

   0: RESUME               
   2: LOAD_FAST            encoding
   4: LOAD_FAST            self
   6: STORE_ATTR           encoding
  16: LOAD_FAST            source_address
  18: LOAD_FAST            self
  20: STORE_ATTR           source_address
  30: LOAD_FAST            timeout
  32: LOAD_FAST            self
  34: STORE_ATTR           timeout
  44: LOAD_FAST            host
  46: POP_JUMP_FORWARD_IF_FALSE to 144
  48: LOAD_FAST            self
  50: LOAD_METHOD          connect
  72: LOAD_FAST            host
  74: PRECALL              
  78: CALL                 
  88: POP_TOP              
  90: LOAD_FAST            user
  92: POP_JUMP_FORWARD_IF_FALSE to 148
  94: LOAD_FAST            self
  96: LOAD_METHOD          login
 118: LOAD_FAST            user
 120: LOAD_FAST            passwd
 122: LOAD_FAST            acct
 124: PRECALL              
 128: CALL                 
 138: POP_TOP              
 140: LOAD_CONST           None
 142: RETURN_VALUE         
 144: LOAD_CONST           None
 146: RETURN_VALUE         
 148: LOAD_CONST           None
 150: RETURN_VALUE         
