# Disassembly for ftplib.test
# From module file: ftplib

## co_consts:
('Test program.\n    Usage: ftp [-d] [-r[file]] host [-l[dir]] [-d[dir]] [-p] [file] ...\n\n    -d dir\n    -l list\n    -p password\n    ', 2, 0, None, 1, '-d', '-r', '', 'No account -- using anonymous login.', 'Could not open account file -- using anonymous login.', '-l', 'CWD', ' ', '-p', 'RETR ', 1024)

## co_names:
('len', 'sys', 'argv', 'print', 'test', '__doc__', 'exit', 'netrc', 'FTP', 'set_debuglevel', 'authenticators', 'KeyError', 'stderr', 'write', 'OSError', 'login', 'dir', 'sendcmd', 'set_pasv', 'passiveserver', 'retrbinary', 'stdout', 'quit')

## bytecode:

   0: RESUME               
   2: LOAD_GLOBAL          NULL + len
  14: LOAD_GLOBAL          sys
  26: LOAD_ATTR            argv
  36: PRECALL              
  40: CALL                 
  50: LOAD_CONST           2
  52: COMPARE_OP           <
  58: POP_JUMP_FORWARD_IF_FALSE to 150
  60: LOAD_GLOBAL          NULL + print
  72: LOAD_GLOBAL          test
  84: LOAD_ATTR            __doc__
  94: PRECALL              
  98: CALL                 
 108: POP_TOP              
 110: LOAD_GLOBAL          NULL + sys
 122: LOAD_ATTR            exit
 132: LOAD_CONST           0
 134: PRECALL              
 138: CALL                 
 148: POP_TOP              
 150: LOAD_CONST           0
 152: LOAD_CONST           None
 154: IMPORT_NAME          netrc
 156: STORE_FAST           netrc
 158: LOAD_CONST           0
 160: STORE_FAST           debugging
 162: LOAD_CONST           None
 164: STORE_FAST           rcfile
 166: LOAD_GLOBAL          sys
 178: LOAD_ATTR            argv
 188: LOAD_CONST           1
 190: BINARY_SUBSCR        
 200: LOAD_CONST           '-d'
 202: COMPARE_OP           ==
 208: POP_JUMP_FORWARD_IF_FALSE to 290
 210: LOAD_FAST            debugging
 212: LOAD_CONST           1
 214: BINARY_OP            +
 218: STORE_FAST           debugging
 220: LOAD_GLOBAL          sys
 232: LOAD_ATTR            argv
 242: LOAD_CONST           1
 244: DELETE_SUBSCR        
 246: LOAD_GLOBAL          sys
 258: LOAD_ATTR            argv
 268: LOAD_CONST           1
 270: BINARY_SUBSCR        
 280: LOAD_CONST           '-d'
 282: COMPARE_OP           ==
 288: POP_JUMP_BACKWARD_IF_TRUE to 210
 290: LOAD_GLOBAL          sys
 302: LOAD_ATTR            argv
 312: LOAD_CONST           1
 314: BINARY_SUBSCR        
 324: LOAD_CONST           None
 326: LOAD_CONST           2
 328: BUILD_SLICE          
 330: BINARY_SUBSCR        
 340: LOAD_CONST           '-r'
 342: COMPARE_OP           ==
 348: POP_JUMP_FORWARD_IF_FALSE to 428
 350: LOAD_GLOBAL          sys
 362: LOAD_ATTR            argv
 372: LOAD_CONST           1
 374: BINARY_SUBSCR        
 384: LOAD_CONST           2
 386: LOAD_CONST           None
 388: BUILD_SLICE          
 390: BINARY_SUBSCR        
 400: STORE_FAST           rcfile
 402: LOAD_GLOBAL          sys
 414: LOAD_ATTR            argv
 424: LOAD_CONST           1
 426: DELETE_SUBSCR        
 428: LOAD_GLOBAL          sys
 440: LOAD_ATTR            argv
 450: LOAD_CONST           1
 452: BINARY_SUBSCR        
 462: STORE_FAST           host
 464: LOAD_GLOBAL          NULL + FTP
 476: LOAD_FAST            host
 478: PRECALL              
 482: CALL                 
 492: STORE_FAST           ftp
 494: LOAD_FAST            ftp
 496: LOAD_METHOD          set_debuglevel
 518: LOAD_FAST            debugging
 520: PRECALL              
 524: CALL                 
 534: POP_TOP              
 536: LOAD_CONST           ''
 538: COPY                 
 540: STORE_FAST           userid
 542: COPY                 
 544: STORE_FAST           passwd
 546: STORE_FAST           acct
 548: NOP                  
 550: LOAD_FAST            netrc
 552: LOAD_METHOD          netrc
 574: LOAD_FAST            rcfile
 576: PRECALL              
 580: CALL                 
 590: STORE_FAST           netrcobj
 592: NOP                  
 594: LOAD_FAST            netrcobj
 596: LOAD_METHOD          authenticators
 618: LOAD_FAST            host
 620: PRECALL              
 624: CALL                 
 634: UNPACK_SEQUENCE      
 638: STORE_FAST           userid
 640: STORE_FAST           acct
 642: STORE_FAST           passwd
 644: JUMP_FORWARD         to 838
 646: PUSH_EXC_INFO        
 648: LOAD_GLOBAL          KeyError
 660: CHECK_EXC_MATCH      
 662: POP_JUMP_FORWARD_IF_FALSE to 732
 664: POP_TOP              
 666: LOAD_GLOBAL          sys
 678: LOAD_ATTR            stderr
 688: LOAD_METHOD          write
 710: LOAD_CONST           'No account -- using anonymous login.'
 712: PRECALL              
 716: CALL                 
 726: POP_TOP              
 728: POP_EXCEPT           
 730: JUMP_FORWARD         to 838
 732: RERAISE              
 734: COPY                 
 736: POP_EXCEPT           
 738: RERAISE              
 740: PUSH_EXC_INFO        
 742: LOAD_GLOBAL          OSError
 754: CHECK_EXC_MATCH      
 756: POP_JUMP_FORWARD_IF_FALSE to 830
 758: POP_TOP              
 760: LOAD_FAST            rcfile
 762: POP_JUMP_FORWARD_IF_NONE to 826
 764: LOAD_GLOBAL          sys
 776: LOAD_ATTR            stderr
 786: LOAD_METHOD          write
 808: LOAD_CONST           'Could not open account file -- using anonymous login.'
 810: PRECALL              
 814: CALL                 
 824: POP_TOP              
 826: POP_EXCEPT           
 828: JUMP_FORWARD         to 838
 830: RERAISE              
 832: COPY                 
 834: POP_EXCEPT           
 836: RERAISE              
 838: LOAD_FAST            ftp
 840: LOAD_METHOD          login
 862: LOAD_FAST            userid
 864: LOAD_FAST            passwd
 866: LOAD_FAST            acct
 868: PRECALL              
 872: CALL                 
 882: POP_TOP              
 884: LOAD_GLOBAL          sys
 896: LOAD_ATTR            argv
 906: LOAD_CONST           2
 908: LOAD_CONST           None
 910: BUILD_SLICE          
 912: BINARY_SUBSCR        
 922: GET_ITER             
 924: FOR_ITER             to 1296
 926: STORE_FAST           file
 928: LOAD_FAST            file
 930: LOAD_CONST           None
 932: LOAD_CONST           2
 934: BUILD_SLICE          
 936: BINARY_SUBSCR        
 946: LOAD_CONST           '-l'
 948: COMPARE_OP           ==
 954: POP_JUMP_FORWARD_IF_FALSE to 1016
 956: LOAD_FAST            ftp
 958: LOAD_METHOD          dir
 980: LOAD_FAST            file
 982: LOAD_CONST           2
 984: LOAD_CONST           None
 986: BUILD_SLICE          
 988: BINARY_SUBSCR        
 998: PRECALL              
1002: CALL                 
1012: POP_TOP              
1014: JUMP_BACKWARD        to 924
1016: LOAD_FAST            file
1018: LOAD_CONST           None
1020: LOAD_CONST           2
1022: BUILD_SLICE          
1024: BINARY_SUBSCR        
1034: LOAD_CONST           '-d'
1036: COMPARE_OP           ==
1042: POP_JUMP_FORWARD_IF_FALSE to 1144
1044: LOAD_CONST           'CWD'
1046: STORE_FAST           cmd
1048: LOAD_FAST            file
1050: LOAD_CONST           2
1052: LOAD_CONST           None
1054: BUILD_SLICE          
1056: BINARY_SUBSCR        
1066: POP_JUMP_FORWARD_IF_FALSE to 1100
1068: LOAD_FAST            cmd
1070: LOAD_CONST           ' '
1072: BINARY_OP            +
1076: LOAD_FAST            file
1078: LOAD_CONST           2
1080: LOAD_CONST           None
1082: BUILD_SLICE          
1084: BINARY_SUBSCR        
1094: BINARY_OP            +
1098: STORE_FAST           cmd
1100: LOAD_FAST            ftp
1102: LOAD_METHOD          sendcmd
1124: LOAD_FAST            cmd
1126: PRECALL              
1130: CALL                 
1140: STORE_FAST           resp
1142: JUMP_BACKWARD        to 924
1144: LOAD_FAST            file
1146: LOAD_CONST           '-p'
1148: COMPARE_OP           ==
1154: POP_JUMP_FORWARD_IF_FALSE to 1212
1156: LOAD_FAST            ftp
1158: LOAD_METHOD          set_pasv
1180: LOAD_FAST            ftp
1182: LOAD_ATTR            passiveserver
1192: UNARY_NOT            
1194: PRECALL              
1198: CALL                 
1208: POP_TOP              
1210: JUMP_BACKWARD        to 924
1212: LOAD_FAST            ftp
1214: LOAD_METHOD          retrbinary
1236: LOAD_CONST           'RETR '
1238: LOAD_FAST            file
1240: BINARY_OP            +
1244: LOAD_GLOBAL          sys
1256: LOAD_ATTR            stdout
1266: LOAD_ATTR            write
1276: LOAD_CONST           1024
1278: PRECALL              
1282: CALL                 
1292: POP_TOP              
1294: JUMP_BACKWARD        to 924
1296: LOAD_FAST            ftp
1298: LOAD_METHOD          quit
1320: PRECALL              
1324: CALL                 
1334: POP_TOP              
1336: LOAD_CONST           None
1338: RETURN_VALUE         
