# Disassembly for ftplib.parse150
# From module file: ftplib

## co_consts:
("Parse the '150' response for a RETR request.\n    Returns the expected transfer size or None; size is not guaranteed to\n    be present in the 150 message.\n    ", None, 3, '150', 0, '150 .* \\((\\d+) bytes\\)', 1)

## co_names:
('error_reply', '_150_re', 're', 'compile', 'IGNORECASE', 'ASCII', 'match', 'int', 'group')

## bytecode:

   0: RESUME               
   2: LOAD_FAST            resp
   4: LOAD_CONST           None
   6: LOAD_CONST           3
   8: BUILD_SLICE          
  10: BINARY_SUBSCR        
  20: LOAD_CONST           '150'
  22: COMPARE_OP           !=
  28: POP_JUMP_FORWARD_IF_FALSE to 60
  30: LOAD_GLOBAL          NULL + error_reply
  42: LOAD_FAST            resp
  44: PRECALL              
  48: CALL                 
  58: RAISE_VARARGS        
  60: LOAD_GLOBAL          _150_re
  72: POP_JUMP_FORWARD_IF_NOT_NONE to 152
  74: LOAD_CONST           0
  76: LOAD_CONST           None
  78: IMPORT_NAME          re
  80: STORE_FAST           re
  82: LOAD_FAST            re
  84: LOAD_METHOD          compile
 106: LOAD_CONST           '150 .* \\((\\d+) bytes\\)'
 108: LOAD_FAST            re
 110: LOAD_ATTR            IGNORECASE
 120: LOAD_FAST            re
 122: LOAD_ATTR            ASCII
 132: BINARY_OP            |
 136: PRECALL              
 140: CALL                 
 150: STORE_GLOBAL         _150_re
 152: LOAD_GLOBAL          _150_re
 164: LOAD_METHOD          match
 186: LOAD_FAST            resp
 188: PRECALL              
 192: CALL                 
 202: STORE_FAST           m
 204: LOAD_FAST            m
 206: POP_JUMP_FORWARD_IF_TRUE to 212
 208: LOAD_CONST           None
 210: RETURN_VALUE         
 212: LOAD_GLOBAL          NULL + int
 224: LOAD_FAST            m
 226: LOAD_METHOD          group
 248: LOAD_CONST           1
 250: PRECALL              
 254: CALL                 
 264: PRECALL              
 268: CALL                 
 278: RETURN_VALUE         
