# Disassembly for ftplib.FTP.__exit__
# From module file: ftplib

## co_consts:
(None,)

## co_names:
('sock', 'quit', 'OSError', 'EOFError', 'close')

## bytecode:

   0: RESUME               
   2: LOAD_FAST            self
   4: LOAD_ATTR            sock
  14: POP_JUMP_FORWARD_IF_NONE to 234
  16: NOP                  
  18: LOAD_FAST            self
  20: LOAD_METHOD          quit
  42: PRECALL              
  46: CALL                 
  56: POP_TOP              
  58: JUMP_FORWARD         to 106
  60: PUSH_EXC_INFO        
  62: LOAD_GLOBAL          OSError
  74: LOAD_GLOBAL          EOFError
  86: BUILD_TUPLE          
  88: CHECK_EXC_MATCH      
  90: POP_JUMP_FORWARD_IF_FALSE to 98
  92: POP_TOP              
  94: POP_EXCEPT           
  96: JUMP_FORWARD         to 106
  98: RERAISE              
 100: COPY                 
 102: POP_EXCEPT           
 104: RERAISE              
 106: LOAD_FAST            self
 108: LOAD_ATTR            sock
 118: POP_JUMP_FORWARD_IF_NONE to 164
 120: LOAD_FAST            self
 122: LOAD_METHOD          close
 144: PRECALL              
 148: CALL                 
 158: POP_TOP              
 160: LOAD_CONST           None
 162: RETURN_VALUE         
 164: LOAD_CONST           None
 166: RETURN_VALUE         
 168: PUSH_EXC_INFO        
 170: LOAD_FAST            self
 172: LOAD_ATTR            sock
 182: POP_JUMP_FORWARD_IF_NONE to 226
 184: LOAD_FAST            self
 186: LOAD_METHOD          close
 208: PRECALL              
 212: CALL                 
 222: POP_TOP              
 224: RERAISE              
 226: RERAISE              
 228: COPY                 
 230: POP_EXCEPT           
 232: RERAISE              
 234: LOAD_CONST           None
 236: RETURN_VALUE         
