# Disassembly for ftplib.FTP.voidcmd
# From module file: ftplib

## co_consts:
("Send a command and expect a response beginning with '2'.",)

## co_names:
('putcmd', 'voidresp')

## bytecode:

   0: RESUME               
   2: LOAD_FAST            self
   4: LOAD_METHOD          putcmd
  26: LOAD_FAST            cmd
  28: PRECALL              
  32: CALL                 
  42: POP_TOP              
  44: LOAD_FAST            self
  46: LOAD_METHOD          voidresp
  68: PRECALL              
  72: CALL                 
  82: RETURN_VALUE         
