# Disassembly for ftplib.FTP_TLS.__init__
# From module file: ftplib

## co_consts:
(None, 'context and keyfile arguments are mutually exclusive', 'context and certfile arguments are mutually exclusive', 0, 'keyfile and certfile are deprecated, use a custom context instead', 2, ('certfile', 'keyfile'), False, ('encoding',))

## co_names:
('ValueError', 'warnings', 'warn', 'DeprecationWarning', 'keyfile', 'certfile', 'ssl', '_create_stdlib_context', 'ssl_version', 'context', '_prot_p', 'super', '__init__')

## bytecode:

   0: COPY_FREE_VARS       
   2: RESUME               
   4: LOAD_FAST            context
   6: POP_JUMP_FORWARD_IF_NONE to 42
   8: LOAD_FAST            keyfile
  10: POP_JUMP_FORWARD_IF_NONE to 42
  12: LOAD_GLOBAL          NULL + ValueError
  24: LOAD_CONST           'context and keyfile arguments are mutually exclusive'
  26: PRECALL              
  30: CALL                 
  40: RAISE_VARARGS        
  42: LOAD_FAST            context
  44: POP_JUMP_FORWARD_IF_NONE to 80
  46: LOAD_FAST            certfile
  48: POP_JUMP_FORWARD_IF_NONE to 80
  50: LOAD_GLOBAL          NULL + ValueError
  62: LOAD_CONST           'context and certfile arguments are mutually exclusive'
  64: PRECALL              
  68: CALL                 
  78: RAISE_VARARGS        
  80: LOAD_FAST            keyfile
  82: POP_JUMP_FORWARD_IF_NOT_NONE to 88
  84: LOAD_FAST            certfile
  86: POP_JUMP_FORWARD_IF_NONE to 152
  88: LOAD_CONST           0
  90: LOAD_CONST           None
  92: IMPORT_NAME          warnings
  94: STORE_FAST           warnings
  96: LOAD_FAST            warnings
  98: LOAD_METHOD          warn
 120: LOAD_CONST           'keyfile and certfile are deprecated, use a custom context instead'
 122: LOAD_GLOBAL          DeprecationWarning
 134: LOAD_CONST           2
 136: PRECALL              
 140: CALL                 
 150: POP_TOP              
 152: LOAD_FAST            keyfile
 154: LOAD_FAST            self
 156: STORE_ATTR           keyfile
 166: LOAD_FAST            certfile
 168: LOAD_FAST            self
 170: STORE_ATTR           certfile
 180: LOAD_FAST            context
 182: POP_JUMP_FORWARD_IF_NOT_NONE to 240
 184: LOAD_GLOBAL          NULL + ssl
 196: LOAD_ATTR            _create_stdlib_context
 206: LOAD_FAST            self
 208: LOAD_ATTR            ssl_version
 218: LOAD_FAST            certfile
 220: LOAD_FAST            keyfile
 222: KW_NAMES             
 224: PRECALL              
 228: CALL                 
 238: STORE_FAST           context
 240: LOAD_FAST            context
 242: LOAD_FAST            self
 244: STORE_ATTR           context
 254: LOAD_CONST           False
 256: LOAD_FAST            self
 258: STORE_ATTR           _prot_p
 268: LOAD_GLOBAL          NULL + super
 280: PRECALL              
 284: CALL                 
 294: LOAD_METHOD          __init__
 316: LOAD_FAST            host
 318: LOAD_FAST            user
 320: LOAD_FAST            passwd
 322: LOAD_FAST            acct
 324: LOAD_FAST            timeout
 326: LOAD_FAST            source_address
 328: LOAD_FAST            encoding
 330: KW_NAMES             
 332: PRECALL              
 336: CALL                 
 346: POP_TOP              
 348: LOAD_CONST           None
 350: RETURN_VALUE         
