# Disassembly for ftplib.FTP.mlsd
# From module file: ftplib

## co_consts:
('List a directory in a standardized format by using MLSD\n        command (RFC-3659). If path is omitted the current directory\n        is assumed. "facts" is a list of strings representing the type\n        of information desired (e.g. ["type", "size", "perm"]).\n\n        Return a generator object yielding a tuple of two elements\n        for every file found in path.\n        First element is the file name, the second one is a dictionary\n        including a variable number of "facts" depending on the server\n        and whether "facts" argument has been provided.\n        ', 'OPTS MLST ', ';', 'MLSD %s', 'MLSD', ' ', None, -1, '=')

## co_names:
('sendcmd', 'join', 'retrlines', 'append', 'rstrip', 'CRLF', 'partition', 'split', 'lower')

## bytecode:

   0: RETURN_GENERATOR     
   2: POP_TOP              
   4: RESUME               
   6: LOAD_FAST            facts
   8: POP_JUMP_FORWARD_IF_FALSE to 102
  10: LOAD_FAST            self
  12: LOAD_METHOD          sendcmd
  34: LOAD_CONST           'OPTS MLST '
  36: LOAD_CONST           ';'
  38: LOAD_METHOD          join
  60: LOAD_FAST            facts
  62: PRECALL              
  66: CALL                 
  76: BINARY_OP            +
  80: LOAD_CONST           ';'
  82: BINARY_OP            +
  86: PRECALL              
  90: CALL                 
 100: POP_TOP              
 102: LOAD_FAST            path
 104: POP_JUMP_FORWARD_IF_FALSE to 118
 106: LOAD_CONST           'MLSD %s'
 108: LOAD_FAST            path
 110: BINARY_OP            %
 114: STORE_FAST           cmd
 116: JUMP_FORWARD         to 122
 118: LOAD_CONST           'MLSD'
 120: STORE_FAST           cmd
 122: BUILD_LIST           
 124: STORE_FAST           lines
 126: LOAD_FAST            self
 128: LOAD_METHOD          retrlines
 150: LOAD_FAST            cmd
 152: LOAD_FAST            lines
 154: LOAD_ATTR            append
 164: PRECALL              
 168: CALL                 
 178: POP_TOP              
 180: LOAD_FAST            lines
 182: GET_ITER             
 184: FOR_ITER             to 464
 186: STORE_FAST           line
 188: LOAD_FAST            line
 190: LOAD_METHOD          rstrip
 212: LOAD_GLOBAL          CRLF
 224: PRECALL              
 228: CALL                 
 238: LOAD_METHOD          partition
 260: LOAD_CONST           ' '
 262: PRECALL              
 266: CALL                 
 276: UNPACK_SEQUENCE      
 280: STORE_FAST           facts_found
 282: STORE_FAST           _
 284: STORE_FAST           name
 286: BUILD_MAP            
 288: STORE_FAST           entry
 290: LOAD_FAST            facts_found
 292: LOAD_CONST           None
 294: LOAD_CONST           -1
 296: BUILD_SLICE          
 298: BINARY_SUBSCR        
 308: LOAD_METHOD          split
 330: LOAD_CONST           ';'
 332: PRECALL              
 336: CALL                 
 346: GET_ITER             
 348: FOR_ITER             to 450
 350: STORE_FAST           fact
 352: LOAD_FAST            fact
 354: LOAD_METHOD          partition
 376: LOAD_CONST           '='
 378: PRECALL              
 382: CALL                 
 392: UNPACK_SEQUENCE      
 396: STORE_FAST           key
 398: STORE_FAST           _
 400: STORE_FAST           value
 402: LOAD_FAST            value
 404: LOAD_FAST            entry
 406: LOAD_FAST            key
 408: LOAD_METHOD          lower
 430: PRECALL              
 434: CALL                 
 444: STORE_SUBSCR         
 448: JUMP_BACKWARD        to 348
 450: LOAD_FAST            name
 452: LOAD_FAST            entry
 454: BUILD_TUPLE          
 456: YIELD_VALUE          
 458: RESUME               
 460: POP_TOP              
 462: JUMP_BACKWARD        to 184
 464: LOAD_CONST           None
 466: RETURN_VALUE         
