# Disassembly for ftplib.FTP.sendcmd
# From module file: ftplib

## co_consts:
('Send a command and return the response.',)

## co_names:
('putcmd', 'getresp')

## bytecode:

   0: RESUME               
   2: LOAD_FAST            self
   4: LOAD_METHOD          putcmd
  26: LOAD_FAST            cmd
  28: PRECALL              
  32: CALL                 
  42: POP_TOP              
  44: LOAD_FAST            self
  46: LOAD_METHOD          getresp
  68: PRECALL              
  72: CALL                 
  82: RETURN_VALUE         
