# Disassembly for ftplib
# From module file: ftplib

## co_consts:
("An FTP client class and some helper functions.\n\nBased on RFC 959: File Transfer Protocol (FTP), by J. Postel and J. Reynolds\n\nExample:\n\n>>> from ftplib import FTP\n>>> ftp = FTP('ftp.python.org') # connect to host, default port\n>>> ftp.login() # default, i.e.: user anonymous, passwd anonymous@\n'230 Guest login ok, access restrictions apply.'\n>>> ftp.retrlines('LIST') # list directory contents\ntotal 9\ndrwxr-xr-x   8 root     wheel        1024 Jan  3  1994 .\ndrwxr-xr-x   8 root     wheel        1024 Jan  3  1994 ..\ndrwxr-xr-x   2 root     wheel        1024 Jan  3  1994 bin\ndrwxr-xr-x   2 root     wheel        1024 Jan  3  1994 etc\nd-wxrwxr-x   2 ftp      wheel        1024 Sep  5 13:43 incoming\ndrwxr-xr-x   2 root     wheel        1024 Nov 17  1993 lib\ndrwxr-xr-x   6 1094     wheel        1024 Sep 13 19:07 pub\ndrwxr-xr-x   3 root     wheel        1024 Jan  3  1994 usr\n-rw-r--r--   1 root     root          312 Aug  1  1994 welcome.msg\n'226 Transfer complete.'\n>>> ftp.quit()\n'221 Goodbye.'\n>>>\n\nA nice test that reveals some of the network dialogue would be:\npython ftplib.py -d localhost -l -p -l\n", 0, None, ('_GLOBAL_DEFAULT_TIMEOUT',), ('FTP', 'error_reply', 'error_temp', 'error_perm', 'error_proto', 'all_errors'), 1, 21, 8192, <code object Error at 0x0000024069427770, file "ftplib.py", line 57>, 'Error', <code object error_reply at 0x00000240694946B0, file "ftplib.py", line 58>, 'error_reply', <code object error_temp at 0x0000024069495890, file "ftplib.py", line 59>, 'error_temp', <code object error_perm at 0x0000024069495A30, file "ftplib.py", line 60>, 'error_perm', <code object error_proto at 0x0000024069495D70, file "ftplib.py", line 61>, 'error_proto', '\r\n', b'\r\n', <code object FTP at 0x0000024068E22820, file "ftplib.py", line 74>, 'FTP', <code object FTP_TLS at 0x00000240693ABC30, file "ftplib.py", line 683>, 'FTP_TLS', <code object parse150 at 0x00000240691DAF50, file "ftplib.py", line 814>, <code object parse227 at 0x0000024068E1C840, file "ftplib.py", line 834>, <code object parse229 at 0x0000024068C0B240, file "ftplib.py", line 853>, <code object parse257 at 0x0000024069498030, file "ftplib.py", line 874>, <code object print_line at 0x0000024069465FB0, file "ftplib.py", line 896>, '', 'I', <code object ftpcp at 0x0000024068D328A0, file "ftplib.py", line 901>, <code object test at 0x0000024068CF54C0, file "ftplib.py", line 923>, '__main__', ('', 'I'))

## co_names:
('__doc__', 'sys', 'socket', '_GLOBAL_DEFAULT_TIMEOUT', '__all__', 'MSG_OOB', 'FTP_PORT', 'MAXLINE', 'Exception', 'Error', 'error_reply', 'error_temp', 'error_perm', 'error_proto', 'OSError', 'EOFError', 'all_errors', 'CRLF', 'B_CRLF', 'FTP', 'ssl', 'SSLSocket', '_SSLSocket', 'FTP_TLS', 'append', 'SSLError', 'ImportError', '_150_re', 'parse150', '_227_re', 'parse227', 'parse229', 'parse257', 'print_line', 'ftpcp', 'test', '__name__')

## bytecode:

   0: RESUME               
   2: LOAD_CONST           "An FTP client class and some helper functions.\n\nBased on RFC 959: File Transfer Protocol (FTP), by J. Postel and J. Reynolds\n\nExample:\n\n>>> from ftplib import FTP\n>>> ftp = FTP('ftp.python.org') # connect to host, default port\n>>> ftp.login() # default, i.e.: user anonymous, passwd anonymous@\n'230 Guest login ok, access restrictions apply.'\n>>> ftp.retrlines('LIST') # list directory contents\ntotal 9\ndrwxr-xr-x   8 root     wheel        1024 Jan  3  1994 .\ndrwxr-xr-x   8 root     wheel        1024 Jan  3  1994 ..\ndrwxr-xr-x   2 root     wheel        1024 Jan  3  1994 bin\ndrwxr-xr-x   2 root     wheel        1024 Jan  3  1994 etc\nd-wxrwxr-x   2 ftp      wheel        1024 Sep  5 13:43 incoming\ndrwxr-xr-x   2 root     wheel        1024 Nov 17  1993 lib\ndrwxr-xr-x   6 1094     wheel        1024 Sep 13 19:07 pub\ndrwxr-xr-x   3 root     wheel        1024 Jan  3  1994 usr\n-rw-r--r--   1 root     root          312 Aug  1  1994 welcome.msg\n'226 Transfer complete.'\n>>> ftp.quit()\n'221 Goodbye.'\n>>>\n\nA nice test that reveals some of the network dialogue would be:\npython ftplib.py -d localhost -l -p -l\n"
   4: STORE_NAME           __doc__
   6: LOAD_CONST           0
   8: LOAD_CONST           None
  10: IMPORT_NAME          sys
  12: STORE_NAME           sys
  14: LOAD_CONST           0
  16: LOAD_CONST           None
  18: IMPORT_NAME          socket
  20: STORE_NAME           socket
  22: LOAD_CONST           0
  24: LOAD_CONST           ('_GLOBAL_DEFAULT_TIMEOUT',)
  26: IMPORT_NAME          socket
  28: IMPORT_FROM          _GLOBAL_DEFAULT_TIMEOUT
  30: STORE_NAME           _GLOBAL_DEFAULT_TIMEOUT
  32: POP_TOP              
  34: BUILD_LIST           
  36: LOAD_CONST           ('FTP', 'error_reply', 'error_temp', 'error_perm', 'error_proto', 'all_errors')
  38: LIST_EXTEND          
  40: STORE_NAME           __all__
  42: LOAD_CONST           1
  44: STORE_NAME           MSG_OOB
  46: LOAD_CONST           21
  48: STORE_NAME           FTP_PORT
  50: LOAD_CONST           8192
  52: STORE_NAME           MAXLINE
  54: PUSH_NULL            
  56: LOAD_BUILD_CLASS     
  58: LOAD_CONST           <code object Error at 0x0000024069427770, file "ftplib.py", line 57>
  60: MAKE_FUNCTION        
  62: LOAD_CONST           'Error'
  64: LOAD_NAME            Exception
  66: PRECALL              
  70: CALL                 
  80: STORE_NAME           Error
  82: PUSH_NULL            
  84: LOAD_BUILD_CLASS     
  86: LOAD_CONST           <code object error_reply at 0x00000240694946B0, file "ftplib.py", line 58>
  88: MAKE_FUNCTION        
  90: LOAD_CONST           'error_reply'
  92: LOAD_NAME            Error
  94: PRECALL              
  98: CALL                 
 108: STORE_NAME           error_reply
 110: PUSH_NULL            
 112: LOAD_BUILD_CLASS     
 114: LOAD_CONST           <code object error_temp at 0x0000024069495890, file "ftplib.py", line 59>
 116: MAKE_FUNCTION        
 118: LOAD_CONST           'error_temp'
 120: LOAD_NAME            Error
 122: PRECALL              
 126: CALL                 
 136: STORE_NAME           error_temp
 138: PUSH_NULL            
 140: LOAD_BUILD_CLASS     
 142: LOAD_CONST           <code object error_perm at 0x0000024069495A30, file "ftplib.py", line 60>
 144: MAKE_FUNCTION        
 146: LOAD_CONST           'error_perm'
 148: LOAD_NAME            Error
 150: PRECALL              
 154: CALL                 
 164: STORE_NAME           error_perm
 166: PUSH_NULL            
 168: LOAD_BUILD_CLASS     
 170: LOAD_CONST           <code object error_proto at 0x0000024069495D70, file "ftplib.py", line 61>
 172: MAKE_FUNCTION        
 174: LOAD_CONST           'error_proto'
 176: LOAD_NAME            Error
 178: PRECALL              
 182: CALL                 
 192: STORE_NAME           error_proto
 194: LOAD_NAME            Error
 196: LOAD_NAME            OSError
 198: LOAD_NAME            EOFError
 200: BUILD_TUPLE          
 202: STORE_NAME           all_errors
 204: LOAD_CONST           '\r\n'
 206: STORE_NAME           CRLF
 208: LOAD_CONST           b'\r\n'
 210: STORE_NAME           B_CRLF
 212: PUSH_NULL            
 214: LOAD_BUILD_CLASS     
 216: LOAD_CONST           <code object FTP at 0x0000024068E22820, file "ftplib.py", line 74>
 218: MAKE_FUNCTION        
 220: LOAD_CONST           'FTP'
 222: PRECALL              
 226: CALL                 
 236: STORE_NAME           FTP
 238: NOP                  
 240: LOAD_CONST           0
 242: LOAD_CONST           None
 244: IMPORT_NAME          ssl
 246: STORE_NAME           ssl
 248: LOAD_NAME            ssl
 250: LOAD_ATTR            SSLSocket
 260: STORE_NAME           _SSLSocket
 262: PUSH_NULL            
 264: LOAD_BUILD_CLASS     
 266: LOAD_CONST           <code object FTP_TLS at 0x00000240693ABC30, file "ftplib.py", line 683>
 268: MAKE_FUNCTION        
 270: LOAD_CONST           'FTP_TLS'
 272: LOAD_NAME            FTP
 274: PRECALL              
 278: CALL                 
 288: STORE_NAME           FTP_TLS
 290: LOAD_NAME            __all__
 292: LOAD_METHOD          append
 314: LOAD_CONST           'FTP_TLS'
 316: PRECALL              
 320: CALL                 
 330: POP_TOP              
 332: LOAD_NAME            Error
 334: LOAD_NAME            OSError
 336: LOAD_NAME            EOFError
 338: LOAD_NAME            ssl
 340: LOAD_ATTR            SSLError
 350: BUILD_TUPLE          
 352: STORE_NAME           all_errors
 354: JUMP_FORWARD         to 382
 356: PUSH_EXC_INFO        
 358: LOAD_NAME            ImportError
 360: CHECK_EXC_MATCH      
 362: POP_JUMP_FORWARD_IF_FALSE to 374
 364: POP_TOP              
 366: LOAD_CONST           None
 368: STORE_NAME           _SSLSocket
 370: POP_EXCEPT           
 372: JUMP_FORWARD         to 382
 374: RERAISE              
 376: COPY                 
 378: POP_EXCEPT           
 380: RERAISE              
 382: LOAD_CONST           None
 384: STORE_GLOBAL         _150_re
 386: LOAD_CONST           <code object parse150 at 0x00000240691DAF50, file "ftplib.py", line 814>
 388: MAKE_FUNCTION        
 390: STORE_NAME           parse150
 392: LOAD_CONST           None
 394: STORE_GLOBAL         _227_re
 396: LOAD_CONST           <code object parse227 at 0x0000024068E1C840, file "ftplib.py", line 834>
 398: MAKE_FUNCTION        
 400: STORE_NAME           parse227
 402: LOAD_CONST           <code object parse229 at 0x0000024068C0B240, file "ftplib.py", line 853>
 404: MAKE_FUNCTION        
 406: STORE_NAME           parse229
 408: LOAD_CONST           <code object parse257 at 0x0000024069498030, file "ftplib.py", line 874>
 410: MAKE_FUNCTION        
 412: STORE_NAME           parse257
 414: LOAD_CONST           <code object print_line at 0x0000024069465FB0, file "ftplib.py", line 896>
 416: MAKE_FUNCTION        
 418: STORE_NAME           print_line
 420: LOAD_CONST           ('', 'I')
 422: LOAD_CONST           <code object ftpcp at 0x0000024068D328A0, file "ftplib.py", line 901>
 424: MAKE_FUNCTION        defaults
 426: STORE_NAME           ftpcp
 428: LOAD_CONST           <code object test at 0x0000024068CF54C0, file "ftplib.py", line 923>
 430: MAKE_FUNCTION        
 432: STORE_NAME           test
 434: LOAD_NAME            __name__
 436: LOAD_CONST           '__main__'
 438: COMPARE_OP           ==
 444: POP_JUMP_FORWARD_IF_FALSE to 470
 446: PUSH_NULL            
 448: LOAD_NAME            test
 450: PRECALL              
 454: CALL                 
 464: POP_TOP              
 466: LOAD_CONST           None
 468: RETURN_VALUE         
 470: LOAD_CONST           None
 472: RETURN_VALUE         
