# Disassembly for ftplib.FTP.quit
# From module file: ftplib

## co_consts:
('Quit, and close the connection.', 'QUIT')

## co_names:
('voidcmd', 'close')

## bytecode:

   0: RESUME               
   2: LOAD_FAST            self
   4: LOAD_METHOD          voidcmd
  26: LOAD_CONST           'QUIT'
  28: PRECALL              
  32: CALL                 
  42: STORE_FAST           resp
  44: LOAD_FAST            self
  46: LOAD_METHOD          close
  68: PRECALL              
  72: CALL                 
  82: POP_TOP              
  84: LOAD_FAST            resp
  86: RETURN_VALUE         
