# Disassembly for ftplib.FTP.makeport
# From module file: ftplib

## co_consts:
('Create a new socket and send a PORT command for it.', ('', 0), 1, ('family', 'backlog'), 0)

## co_names:
('socket', 'create_server', 'af', 'getsockname', 'sock', 'AF_INET', 'sendport', 'sendeprt', 'timeout', '_GLOBAL_DEFAULT_TIMEOUT', 'settimeout')

## bytecode:

   0: RESUME               
   2: LOAD_GLOBAL          NULL + socket
  14: LOAD_ATTR            create_server
  24: LOAD_CONST           ('', 0)
  26: LOAD_FAST            self
  28: LOAD_ATTR            af
  38: LOAD_CONST           1
  40: KW_NAMES             
  42: PRECALL              
  46: CALL                 
  56: STORE_FAST           sock
  58: LOAD_FAST            sock
  60: LOAD_METHOD          getsockname
  82: PRECALL              
  86: CALL                 
  96: LOAD_CONST           1
  98: BINARY_SUBSCR        
 108: STORE_FAST           port
 110: LOAD_FAST            self
 112: LOAD_ATTR            sock
 122: LOAD_METHOD          getsockname
 144: PRECALL              
 148: CALL                 
 158: LOAD_CONST           0
 160: BINARY_SUBSCR        
 170: STORE_FAST           host
 172: LOAD_FAST            self
 174: LOAD_ATTR            af
 184: LOAD_GLOBAL          socket
 196: LOAD_ATTR            AF_INET
 206: COMPARE_OP           ==
 212: POP_JUMP_FORWARD_IF_FALSE to 260
 214: LOAD_FAST            self
 216: LOAD_METHOD          sendport
 238: LOAD_FAST            host
 240: LOAD_FAST            port
 242: PRECALL              
 246: CALL                 
 256: STORE_FAST           resp
 258: JUMP_FORWARD         to 304
 260: LOAD_FAST            self
 262: LOAD_METHOD          sendeprt
 284: LOAD_FAST            host
 286: LOAD_FAST            port
 288: PRECALL              
 292: CALL                 
 302: STORE_FAST           resp
 304: LOAD_FAST            self
 306: LOAD_ATTR            timeout
 316: LOAD_GLOBAL          _GLOBAL_DEFAULT_TIMEOUT
 328: IS_OP                
 330: POP_JUMP_FORWARD_IF_FALSE to 384
 332: LOAD_FAST            sock
 334: LOAD_METHOD          settimeout
 356: LOAD_FAST            self
 358: LOAD_ATTR            timeout
 368: PRECALL              
 372: CALL                 
 382: POP_TOP              
 384: LOAD_FAST            sock
 386: RETURN_VALUE         
