# Disassembly for copy._deepcopy_dict
# From module file: copy

## co_consts:
(None,)

## co_names:
('id', 'items')

## bytecode:

   0: RESUME               
   2: BUILD_MAP            
   4: STORE_FAST           y
   6: LOAD_FAST            y
   8: LOAD_FAST            memo
  10: LOAD_GLOBAL          NULL + id
  22: LOAD_FAST            x
  24: PRECALL              
  28: CALL                 
  38: STORE_SUBSCR         
  42: LOAD_FAST            x
  44: LOAD_METHOD          items
  66: PRECALL              
  70: CALL                 
  80: GET_ITER             
  82: FOR_ITER             to 144
  84: UNPACK_SEQUENCE      
  88: STORE_FAST           key
  90: STORE_FAST           value
  92: PUSH_NULL            
  94: LOAD_FAST            deepcopy
  96: LOAD_FAST            value
  98: LOAD_FAST            memo
 100: PRECALL              
 104: CALL                 
 114: LOAD_FAST            y
 116: PUSH_NULL            
 118: LOAD_FAST            deepcopy
 120: LOAD_FAST            key
 122: LOAD_FAST            memo
 124: PRECALL              
 128: CALL                 
 138: STORE_SUBSCR         
 142: JUMP_BACKWARD        to 82
 144: LOAD_FAST            y
 146: RETURN_VALUE         
