# Disassembly for copy
# From module file: copy

## co_consts:
('Generic (shallow and deep) copying operations.\n\nInterface summary:\n\n        import copy\n\n        x = copy.copy(y)        # make a shallow copy of y\n        x = copy.deepcopy(y)    # make a deep copy of y\n\nFor module specific errors, copy.Error is raised.\n\nThe difference between shallow and deep copying is only relevant for\ncompound objects (objects that contain other objects, like lists or\nclass instances).\n\n- A shallow copy constructs a new compound object and then (to the\n  extent possible) inserts *the same objects* into it that the\n  original contains.\n\n- A deep copy constructs a new compound object and then, recursively,\n  inserts *copies* into it of the objects found in the original.\n\nTwo problems often exist with deep copy operations that don\'t exist\nwith shallow copy operations:\n\n a) recursive objects (compound objects that, directly or indirectly,\n    contain a reference to themselves) may cause a recursive loop\n\n b) because deep copy copies *everything* it may copy too much, e.g.\n    administrative data structures that should be shared even between\n    copies\n\nPython\'s deep copy operation avoids these problems by:\n\n a) keeping a table of objects already copied during the current\n    copying pass\n\n b) letting user-defined classes override the copying operation or the\n    set of components copied\n\nThis version does not copy types like module, class, function, method,\nnor stack trace, stack frame, nor file, socket, window, nor any\nsimilar types.\n\nClasses can use the same interfaces to control copying that they use\nto control pickling: they can define methods called __getinitargs__(),\n__getstate__() and __setstate__().  See the documentation for module\n"pickle" for information on these methods.\n', 0, None, ('dispatch_table',), <code object Error at 0x00000240694279E0, file "copy.py", line 55>, 'Error', ('PyStringMap',), ('Error', 'copy', 'deepcopy'), <code object copy at 0x0000024068C08720, file "copy.py", line 66>, <code object _copy_immutable at 0x000002406943BB70, file "copy.py", line 107>, 'CodeType', <code object deepcopy at 0x0000024068C35D30, file "copy.py", line 128>, <code object _deepcopy_atomic at 0x000002406943B930, file "copy.py", line 182>, <code object _deepcopy_list at 0x00000240693D3930, file "copy.py", line 201>, <code object _deepcopy_tuple at 0x000002406942DAC0, file "copy.py", line 210>, <code object _deepcopy_dict at 0x00000240691F3B40, file "copy.py", line 227>, <code object _deepcopy_method at 0x000002406941AC10, file "copy.py", line 237>, <code object _keep_alive at 0x00000240691C02F0, file "copy.py", line 243>, ('deepcopy',), <code object _reconstruct at 0x0000024068C360B0, file "copy.py", line 259>, (None, None, None))

## co_names:
('__doc__', 'types', 'weakref', 'copyreg', 'dispatch_table', 'Exception', 'Error', 'error', 'org.python.core', 'PyStringMap', 'ImportError', '__all__', 'copy', '_copy_dispatch', 'd', '_copy_immutable', 'type', 'int', 'float', 'bool', 'complex', 'str', 'tuple', 'bytes', 'frozenset', 'range', 'slice', 'property', 'BuiltinFunctionType', 'Ellipsis', 'NotImplemented', 'FunctionType', 'ref', 't', 'getattr', 'list', 'dict', 'set', 'bytearray', 'deepcopy', '_deepcopy_dispatch', '_deepcopy_atomic', 'CodeType', '_deepcopy_list', '_deepcopy_tuple', '_deepcopy_dict', '_deepcopy_method', 'MethodType', '_keep_alive', '_reconstruct')

## bytecode:

   0: RESUME               
   2: LOAD_CONST           'Generic (shallow and deep) copying operations.\n\nInterface summary:\n\n        import copy\n\n        x = copy.copy(y)        # make a shallow copy of y\n        x = copy.deepcopy(y)    # make a deep copy of y\n\nFor module specific errors, copy.Error is raised.\n\nThe difference between shallow and deep copying is only relevant for\ncompound objects (objects that contain other objects, like lists or\nclass instances).\n\n- A shallow copy constructs a new compound object and then (to the\n  extent possible) inserts *the same objects* into it that the\n  original contains.\n\n- A deep copy constructs a new compound object and then, recursively,\n  inserts *copies* into it of the objects found in the original.\n\nTwo problems often exist with deep copy operations that don\'t exist\nwith shallow copy operations:\n\n a) recursive objects (compound objects that, directly or indirectly,\n    contain a reference to themselves) may cause a recursive loop\n\n b) because deep copy copies *everything* it may copy too much, e.g.\n    administrative data structures that should be shared even between\n    copies\n\nPython\'s deep copy operation avoids these problems by:\n\n a) keeping a table of objects already copied during the current\n    copying pass\n\n b) letting user-defined classes override the copying operation or the\n    set of components copied\n\nThis version does not copy types like module, class, function, method,\nnor stack trace, stack frame, nor file, socket, window, nor any\nsimilar types.\n\nClasses can use the same interfaces to control copying that they use\nto control pickling: they can define methods called __getinitargs__(),\n__getstate__() and __setstate__().  See the documentation for module\n"pickle" for information on these methods.\n'
   4: STORE_NAME           __doc__
   6: LOAD_CONST           0
   8: LOAD_CONST           None
  10: IMPORT_NAME          types
  12: STORE_NAME           types
  14: LOAD_CONST           0
  16: LOAD_CONST           None
  18: IMPORT_NAME          weakref
  20: STORE_NAME           weakref
  22: LOAD_CONST           0
  24: LOAD_CONST           ('dispatch_table',)
  26: IMPORT_NAME          copyreg
  28: IMPORT_FROM          dispatch_table
  30: STORE_NAME           dispatch_table
  32: POP_TOP              
  34: PUSH_NULL            
  36: LOAD_BUILD_CLASS     
  38: LOAD_CONST           <code object Error at 0x00000240694279E0, file "copy.py", line 55>
  40: MAKE_FUNCTION        
  42: LOAD_CONST           'Error'
  44: LOAD_NAME            Exception
  46: PRECALL              
  50: CALL                 
  60: STORE_NAME           Error
  62: LOAD_NAME            Error
  64: STORE_NAME           error
  66: NOP                  
  68: LOAD_CONST           0
  70: LOAD_CONST           ('PyStringMap',)
  72: IMPORT_NAME          org.python.core
  74: IMPORT_FROM          PyStringMap
  76: STORE_NAME           PyStringMap
  78: POP_TOP              
  80: JUMP_FORWARD         to 108
  82: PUSH_EXC_INFO        
  84: LOAD_NAME            ImportError
  86: CHECK_EXC_MATCH      
  88: POP_JUMP_FORWARD_IF_FALSE to 100
  90: POP_TOP              
  92: LOAD_CONST           None
  94: STORE_NAME           PyStringMap
  96: POP_EXCEPT           
  98: JUMP_FORWARD         to 108
 100: RERAISE              
 102: COPY                 
 104: POP_EXCEPT           
 106: RERAISE              
 108: BUILD_LIST           
 110: LOAD_CONST           ('Error', 'copy', 'deepcopy')
 112: LIST_EXTEND          
 114: STORE_NAME           __all__
 116: LOAD_CONST           <code object copy at 0x0000024068C08720, file "copy.py", line 66>
 118: MAKE_FUNCTION        
 120: STORE_NAME           copy
 122: BUILD_MAP            
 124: COPY                 
 126: STORE_NAME           _copy_dispatch
 128: STORE_NAME           d
 130: LOAD_CONST           <code object _copy_immutable at 0x000002406943BB70, file "copy.py", line 107>
 132: MAKE_FUNCTION        
 134: STORE_NAME           _copy_immutable
 136: PUSH_NULL            
 138: LOAD_NAME            type
 140: LOAD_CONST           None
 142: PRECALL              
 146: CALL                 
 156: LOAD_NAME            int
 158: LOAD_NAME            float
 160: LOAD_NAME            bool
 162: LOAD_NAME            complex
 164: LOAD_NAME            str
 166: LOAD_NAME            tuple
 168: LOAD_NAME            bytes
 170: LOAD_NAME            frozenset
 172: LOAD_NAME            type
 174: LOAD_NAME            range
 176: LOAD_NAME            slice
 178: LOAD_NAME            property
 180: LOAD_NAME            types
 182: LOAD_ATTR            BuiltinFunctionType
 192: PUSH_NULL            
 194: LOAD_NAME            type
 196: LOAD_NAME            Ellipsis
 198: PRECALL              
 202: CALL                 
 212: PUSH_NULL            
 214: LOAD_NAME            type
 216: LOAD_NAME            NotImplemented
 218: PRECALL              
 222: CALL                 
 232: LOAD_NAME            types
 234: LOAD_ATTR            FunctionType
 244: LOAD_NAME            weakref
 246: LOAD_ATTR            ref
 256: BUILD_TUPLE          
 258: GET_ITER             
 260: FOR_ITER             to 276
 262: STORE_NAME           t
 264: LOAD_NAME            _copy_immutable
 266: LOAD_NAME            d
 268: LOAD_NAME            t
 270: STORE_SUBSCR         
 274: JUMP_BACKWARD        to 260
 276: PUSH_NULL            
 278: LOAD_NAME            getattr
 280: LOAD_NAME            types
 282: LOAD_CONST           'CodeType'
 284: LOAD_CONST           None
 286: PRECALL              
 290: CALL                 
 300: STORE_NAME           t
 302: LOAD_NAME            t
 304: POP_JUMP_FORWARD_IF_NONE to 316
 306: LOAD_NAME            _copy_immutable
 308: LOAD_NAME            d
 310: LOAD_NAME            t
 312: STORE_SUBSCR         
 316: LOAD_NAME            list
 318: LOAD_ATTR            copy
 328: LOAD_NAME            d
 330: LOAD_NAME            list
 332: STORE_SUBSCR         
 336: LOAD_NAME            dict
 338: LOAD_ATTR            copy
 348: LOAD_NAME            d
 350: LOAD_NAME            dict
 352: STORE_SUBSCR         
 356: LOAD_NAME            set
 358: LOAD_ATTR            copy
 368: LOAD_NAME            d
 370: LOAD_NAME            set
 372: STORE_SUBSCR         
 376: LOAD_NAME            bytearray
 378: LOAD_ATTR            copy
 388: LOAD_NAME            d
 390: LOAD_NAME            bytearray
 392: STORE_SUBSCR         
 396: LOAD_NAME            PyStringMap
 398: POP_JUMP_FORWARD_IF_NONE to 420
 400: LOAD_NAME            PyStringMap
 402: LOAD_ATTR            copy
 412: LOAD_NAME            d
 414: LOAD_NAME            PyStringMap
 416: STORE_SUBSCR         
 420: DELETE_NAME          d
 422: DELETE_NAME          t
 424: LOAD_CONST           None
 426: BUILD_LIST           
 428: BUILD_TUPLE          
 430: LOAD_CONST           <code object deepcopy at 0x0000024068C35D30, file "copy.py", line 128>
 432: MAKE_FUNCTION        defaults
 434: STORE_NAME           deepcopy
 436: BUILD_MAP            
 438: COPY                 
 440: STORE_NAME           _deepcopy_dispatch
 442: STORE_NAME           d
 444: LOAD_CONST           <code object _deepcopy_atomic at 0x000002406943B930, file "copy.py", line 182>
 446: MAKE_FUNCTION        
 448: STORE_NAME           _deepcopy_atomic
 450: LOAD_NAME            _deepcopy_atomic
 452: LOAD_NAME            d
 454: PUSH_NULL            
 456: LOAD_NAME            type
 458: LOAD_CONST           None
 460: PRECALL              
 464: CALL                 
 474: STORE_SUBSCR         
 478: LOAD_NAME            _deepcopy_atomic
 480: LOAD_NAME            d
 482: PUSH_NULL            
 484: LOAD_NAME            type
 486: LOAD_NAME            Ellipsis
 488: PRECALL              
 492: CALL                 
 502: STORE_SUBSCR         
 506: LOAD_NAME            _deepcopy_atomic
 508: LOAD_NAME            d
 510: PUSH_NULL            
 512: LOAD_NAME            type
 514: LOAD_NAME            NotImplemented
 516: PRECALL              
 520: CALL                 
 530: STORE_SUBSCR         
 534: LOAD_NAME            _deepcopy_atomic
 536: LOAD_NAME            d
 538: LOAD_NAME            int
 540: STORE_SUBSCR         
 544: LOAD_NAME            _deepcopy_atomic
 546: LOAD_NAME            d
 548: LOAD_NAME            float
 550: STORE_SUBSCR         
 554: LOAD_NAME            _deepcopy_atomic
 556: LOAD_NAME            d
 558: LOAD_NAME            bool
 560: STORE_SUBSCR         
 564: LOAD_NAME            _deepcopy_atomic
 566: LOAD_NAME            d
 568: LOAD_NAME            complex
 570: STORE_SUBSCR         
 574: LOAD_NAME            _deepcopy_atomic
 576: LOAD_NAME            d
 578: LOAD_NAME            bytes
 580: STORE_SUBSCR         
 584: LOAD_NAME            _deepcopy_atomic
 586: LOAD_NAME            d
 588: LOAD_NAME            str
 590: STORE_SUBSCR         
 594: LOAD_NAME            _deepcopy_atomic
 596: LOAD_NAME            d
 598: LOAD_NAME            types
 600: LOAD_ATTR            CodeType
 610: STORE_SUBSCR         
 614: LOAD_NAME            _deepcopy_atomic
 616: LOAD_NAME            d
 618: LOAD_NAME            type
 620: STORE_SUBSCR         
 624: LOAD_NAME            _deepcopy_atomic
 626: LOAD_NAME            d
 628: LOAD_NAME            range
 630: STORE_SUBSCR         
 634: LOAD_NAME            _deepcopy_atomic
 636: LOAD_NAME            d
 638: LOAD_NAME            types
 640: LOAD_ATTR            BuiltinFunctionType
 650: STORE_SUBSCR         
 654: LOAD_NAME            _deepcopy_atomic
 656: LOAD_NAME            d
 658: LOAD_NAME            types
 660: LOAD_ATTR            FunctionType
 670: STORE_SUBSCR         
 674: LOAD_NAME            _deepcopy_atomic
 676: LOAD_NAME            d
 678: LOAD_NAME            weakref
 680: LOAD_ATTR            ref
 690: STORE_SUBSCR         
 694: LOAD_NAME            _deepcopy_atomic
 696: LOAD_NAME            d
 698: LOAD_NAME            property
 700: STORE_SUBSCR         
 704: LOAD_NAME            deepcopy
 706: BUILD_TUPLE          
 708: LOAD_CONST           <code object _deepcopy_list at 0x00000240693D3930, file "copy.py", line 201>
 710: MAKE_FUNCTION        defaults
 712: STORE_NAME           _deepcopy_list
 714: LOAD_NAME            _deepcopy_list
 716: LOAD_NAME            d
 718: LOAD_NAME            list
 720: STORE_SUBSCR         
 724: LOAD_NAME            deepcopy
 726: BUILD_TUPLE          
 728: LOAD_CONST           <code object _deepcopy_tuple at 0x000002406942DAC0, file "copy.py", line 210>
 730: MAKE_FUNCTION        defaults
 732: STORE_NAME           _deepcopy_tuple
 734: LOAD_NAME            _deepcopy_tuple
 736: LOAD_NAME            d
 738: LOAD_NAME            tuple
 740: STORE_SUBSCR         
 744: LOAD_NAME            deepcopy
 746: BUILD_TUPLE          
 748: LOAD_CONST           <code object _deepcopy_dict at 0x00000240691F3B40, file "copy.py", line 227>
 750: MAKE_FUNCTION        defaults
 752: STORE_NAME           _deepcopy_dict
 754: LOAD_NAME            _deepcopy_dict
 756: LOAD_NAME            d
 758: LOAD_NAME            dict
 760: STORE_SUBSCR         
 764: LOAD_NAME            PyStringMap
 766: POP_JUMP_FORWARD_IF_NONE to 778
 768: LOAD_NAME            _deepcopy_dict
 770: LOAD_NAME            d
 772: LOAD_NAME            PyStringMap
 774: STORE_SUBSCR         
 778: LOAD_CONST           <code object _deepcopy_method at 0x000002406941AC10, file "copy.py", line 237>
 780: MAKE_FUNCTION        
 782: STORE_NAME           _deepcopy_method
 784: LOAD_NAME            _deepcopy_method
 786: LOAD_NAME            d
 788: LOAD_NAME            types
 790: LOAD_ATTR            MethodType
 800: STORE_SUBSCR         
 804: DELETE_NAME          d
 806: LOAD_CONST           <code object _keep_alive at 0x00000240691C02F0, file "copy.py", line 243>
 808: MAKE_FUNCTION        
 810: STORE_NAME           _keep_alive
 812: NOP                  
 814: LOAD_CONST           (None, None, None)
 816: LOAD_NAME            deepcopy
 818: LOAD_CONST           ('deepcopy',)
 820: BUILD_CONST_KEY_MAP  
 822: LOAD_CONST           <code object _reconstruct at 0x0000024068C360B0, file "copy.py", line 259>
 824: MAKE_FUNCTION        defaults, kwdefaults
 826: STORE_NAME           _reconstruct
 828: DELETE_NAME          types
 830: DELETE_NAME          weakref
 832: DELETE_NAME          PyStringMap
 834: LOAD_CONST           None
 836: RETURN_VALUE         
