# Disassembly for copy.deepcopy
# From module file: copy

## co_consts:
("Deep copy operation on arbitrary Python objects.\n\n    See the module's __doc__ string for more info.\n    ", None, '__deepcopy__', '__reduce_ex__', 4, '__reduce__', 'un(deep)copyable object of type %s')

## co_names:
('id', 'get', 'type', '_deepcopy_dispatch', 'issubclass', '_deepcopy_atomic', 'getattr', 'dispatch_table', 'Error', 'isinstance', 'str', '_reconstruct', '_keep_alive')

## bytecode:

   0: RESUME               
   2: LOAD_FAST            memo
   4: POP_JUMP_FORWARD_IF_NOT_NONE to 10
   6: BUILD_MAP            
   8: STORE_FAST           memo
  10: LOAD_GLOBAL          NULL + id
  22: LOAD_FAST            x
  24: PRECALL              
  28: CALL                 
  38: STORE_FAST           d
  40: LOAD_FAST            memo
  42: LOAD_METHOD          get
  64: LOAD_FAST            d
  66: LOAD_FAST            _nil
  68: PRECALL              
  72: CALL                 
  82: STORE_FAST           y
  84: LOAD_FAST            y
  86: LOAD_FAST            _nil
  88: IS_OP                
  90: POP_JUMP_FORWARD_IF_FALSE to 96
  92: LOAD_FAST            y
  94: RETURN_VALUE         
  96: LOAD_GLOBAL          NULL + type
 108: LOAD_FAST            x
 110: PRECALL              
 114: CALL                 
 124: STORE_FAST           cls
 126: LOAD_GLOBAL          _deepcopy_dispatch
 138: LOAD_METHOD          get
 160: LOAD_FAST            cls
 162: PRECALL              
 166: CALL                 
 176: STORE_FAST           copier
 178: LOAD_FAST            copier
 180: POP_JUMP_FORWARD_IF_NONE to 208
 182: PUSH_NULL            
 184: LOAD_FAST            copier
 186: LOAD_FAST            x
 188: LOAD_FAST            memo
 190: PRECALL              
 194: CALL                 
 204: STORE_FAST           y
 206: JUMP_FORWARD         to 648
 208: LOAD_GLOBAL          NULL + issubclass
 220: LOAD_FAST            cls
 222: LOAD_GLOBAL          type
 234: PRECALL              
 238: CALL                 
 248: POP_JUMP_FORWARD_IF_FALSE to 284
 250: LOAD_GLOBAL          NULL + _deepcopy_atomic
 262: LOAD_FAST            x
 264: LOAD_FAST            memo
 266: PRECALL              
 270: CALL                 
 280: STORE_FAST           y
 282: JUMP_FORWARD         to 648
 284: LOAD_GLOBAL          NULL + getattr
 296: LOAD_FAST            x
 298: LOAD_CONST           '__deepcopy__'
 300: LOAD_CONST           None
 302: PRECALL              
 306: CALL                 
 316: STORE_FAST           copier
 318: LOAD_FAST            copier
 320: POP_JUMP_FORWARD_IF_NONE to 346
 322: PUSH_NULL            
 324: LOAD_FAST            copier
 326: LOAD_FAST            memo
 328: PRECALL              
 332: CALL                 
 342: STORE_FAST           y
 344: JUMP_FORWARD         to 648
 346: LOAD_GLOBAL          NULL + dispatch_table
 358: LOAD_ATTR            get
 368: LOAD_FAST            cls
 370: PRECALL              
 374: CALL                 
 384: STORE_FAST           reductor
 386: LOAD_FAST            reductor
 388: POP_JUMP_FORWARD_IF_FALSE to 414
 390: PUSH_NULL            
 392: LOAD_FAST            reductor
 394: LOAD_FAST            x
 396: PRECALL              
 400: CALL                 
 410: STORE_FAST           rv
 412: JUMP_FORWARD         to 572
 414: LOAD_GLOBAL          NULL + getattr
 426: LOAD_FAST            x
 428: LOAD_CONST           '__reduce_ex__'
 430: LOAD_CONST           None
 432: PRECALL              
 436: CALL                 
 446: STORE_FAST           reductor
 448: LOAD_FAST            reductor
 450: POP_JUMP_FORWARD_IF_NONE to 476
 452: PUSH_NULL            
 454: LOAD_FAST            reductor
 456: LOAD_CONST           4
 458: PRECALL              
 462: CALL                 
 472: STORE_FAST           rv
 474: JUMP_FORWARD         to 572
 476: LOAD_GLOBAL          NULL + getattr
 488: LOAD_FAST            x
 490: LOAD_CONST           '__reduce__'
 492: LOAD_CONST           None
 494: PRECALL              
 498: CALL                 
 508: STORE_FAST           reductor
 510: LOAD_FAST            reductor
 512: POP_JUMP_FORWARD_IF_FALSE to 536
 514: PUSH_NULL            
 516: LOAD_FAST            reductor
 518: PRECALL              
 522: CALL                 
 532: STORE_FAST           rv
 534: JUMP_FORWARD         to 572
 536: LOAD_GLOBAL          NULL + Error
 548: LOAD_CONST           'un(deep)copyable object of type %s'
 550: LOAD_FAST            cls
 552: BINARY_OP            %
 556: PRECALL              
 560: CALL                 
 570: RAISE_VARARGS        
 572: LOAD_GLOBAL          NULL + isinstance
 584: LOAD_FAST            rv
 586: LOAD_GLOBAL          str
 598: PRECALL              
 602: CALL                 
 612: POP_JUMP_FORWARD_IF_FALSE to 620
 614: LOAD_FAST            x
 616: STORE_FAST           y
 618: JUMP_FORWARD         to 648
 620: LOAD_GLOBAL          NULL + _reconstruct
 632: LOAD_FAST            x
 634: LOAD_FAST            memo
 636: BUILD_LIST           
 638: LOAD_FAST            rv
 640: LIST_EXTEND          
 642: LIST_TO_TUPLE        
 644: CALL_FUNCTION_EX     
 646: STORE_FAST           y
 648: LOAD_FAST            y
 650: LOAD_FAST            x
 652: IS_OP                
 654: POP_JUMP_FORWARD_IF_FALSE to 698
 656: LOAD_FAST            y
 658: LOAD_FAST            memo
 660: LOAD_FAST            d
 662: STORE_SUBSCR         
 666: LOAD_GLOBAL          NULL + _keep_alive
 678: LOAD_FAST            x
 680: LOAD_FAST            memo
 682: PRECALL              
 686: CALL                 
 696: POP_TOP              
 698: LOAD_FAST            y
 700: RETURN_VALUE         
