# Disassembly for dis._get_const_info
# From module file: dis

## co_consts:
('Helper to get optional details about const references\n\n       Returns the dereferenced constant and its repr if the value\n       can be calculated.\n       Otherwise returns the sentinel value dis.UNKNOWN for the value\n       and an empty string for its repr.\n    ', '')

## co_names:
('_get_const_value', 'UNKNOWN', 'repr')

## bytecode:

   0: RESUME               
   2: LOAD_GLOBAL          NULL + _get_const_value
  14: LOAD_FAST            op
  16: LOAD_FAST            arg
  18: LOAD_FAST            co_consts
  20: PRECALL              
  24: CALL                 
  34: STORE_FAST           argval
  36: LOAD_FAST            argval
  38: LOAD_GLOBAL          UNKNOWN
  50: IS_OP                
  52: POP_JUMP_FORWARD_IF_FALSE to 84
  54: LOAD_GLOBAL          NULL + repr
  66: LOAD_FAST            argval
  68: PRECALL              
  72: CALL                 
  82: JUMP_FORWARD         to 86
  84: LOAD_CONST           ''
  86: STORE_FAST           argrepr
  88: LOAD_FAST            argval
  90: LOAD_FAST            argrepr
  92: BUILD_TUPLE          
  94: RETURN_VALUE         
