# Disassembly for dis.show_code
# From module file: dis

## co_consts:
('Print details of methods, functions, or code to *file*.\n\n    If *file* is not provided, the output is printed on stdout.\n    ', ('file',), None)

## co_names:
('print', 'code_info')

## bytecode:

   0: RESUME               
   2: LOAD_GLOBAL          NULL + print
  14: LOAD_GLOBAL          NULL + code_info
  26: LOAD_FAST            co
  28: PRECALL              
  32: CALL                 
  42: LOAD_FAST            file
  44: KW_NAMES             
  46: PRECALL              
  50: CALL                 
  60: POP_TOP              
  62: LOAD_CONST           None
  64: RETURN_VALUE         
