# Disassembly for dis.<listcomp>
# From module file: dis

## co_consts:
('<',)

## co_names:
('startswith',)

## bytecode:

   0: RESUME               
   2: BUILD_LIST           
   4: LOAD_FAST            .0
   6: FOR_ITER             to 64
   8: UNPACK_SEQUENCE      
  12: STORE_FAST           slot
  14: STORE_FAST           name
  16: LOAD_FAST            name
  18: LOAD_METHOD          startswith
  40: LOAD_CONST           '<'
  42: PRECALL              
  46: CALL                 
  56: POP_JUMP_BACKWARD_IF_FALSE to 6
  58: LOAD_FAST            slot
  60: LIST_APPEND          
  62: JUMP_BACKWARD        to 6
  64: RETURN_VALUE         
