# Disassembly for dis._disassemble_str
# From module file: dis

## co_consts:
('Compile the source string, then disassemble the code object.', '<dis>', None)

## co_names:
('_disassemble_recursive', '_try_compile')

## bytecode:

   0: RESUME               
   2: LOAD_GLOBAL          NULL + _disassemble_recursive
  14: LOAD_GLOBAL          NULL + _try_compile
  26: LOAD_FAST            source
  28: LOAD_CONST           '<dis>'
  30: PRECALL              
  34: CALL                 
  44: BUILD_TUPLE          
  46: BUILD_MAP            
  48: LOAD_FAST            kwargs
  50: DICT_MERGE           
  52: CALL_FUNCTION_EX     
  54: POP_TOP              
  56: LOAD_CONST           None
  58: RETURN_VALUE         
