# Disassembly for dis._get_instructions_bytes.<genexpr>
# From module file: dis

## co_consts:
(1, None)

## co_names:
()

## bytecode:

   0: COPY_FREE_VARS       
   2: RETURN_GENERATOR     
   4: POP_TOP              
   6: RESUME               
   8: LOAD_FAST            .0
  10: FOR_ITER             to 46
  12: UNPACK_SEQUENCE      
  16: STORE_FAST           i
  18: STORE_FAST           s
  20: LOAD_DEREF           arg
  22: LOAD_CONST           1
  24: LOAD_FAST            i
  26: BINARY_OP            <<
  30: BINARY_OP            &
  34: POP_JUMP_BACKWARD_IF_FALSE to 10
  36: LOAD_FAST            s
  38: YIELD_VALUE          
  40: RESUME               
  42: POP_TOP              
  44: JUMP_BACKWARD        to 10
  46: LOAD_CONST           None
  48: RETURN_VALUE         
