# Disassembly for dis.get_instructions
# From module file: dis

## co_consts:
('Iterator for the opcodes in methods, functions or code\n\n    Generates a series of Instruction named tuples giving the details of\n    each operations in the supplied code.\n\n    If *first_line* is not None, it indicates the line number that should\n    be reported for the first source line in the disassembled code.\n    Otherwise, the source line information (if any) is taken directly from\n    the disassembled code object.\n    ', None, 0, ('co_positions', 'show_caches'))

## co_names:
('_get_code_object', 'dict', 'findlinestarts', 'co_firstlineno', '_get_instructions_bytes', '_get_code_array', '_varname_from_oparg', 'co_names', 'co_consts', 'co_positions')

## bytecode:

   0: RESUME               
   2: LOAD_GLOBAL          NULL + _get_code_object
  14: LOAD_FAST            x
  16: PRECALL              
  20: CALL                 
  30: STORE_FAST           co
  32: LOAD_GLOBAL          NULL + dict
  44: LOAD_GLOBAL          NULL + findlinestarts
  56: LOAD_FAST            co
  58: PRECALL              
  62: CALL                 
  72: PRECALL              
  76: CALL                 
  86: STORE_FAST           linestarts
  88: LOAD_FAST            first_line
  90: POP_JUMP_FORWARD_IF_NONE to 114
  92: LOAD_FAST            first_line
  94: LOAD_FAST            co
  96: LOAD_ATTR            co_firstlineno
 106: BINARY_OP            -
 110: STORE_FAST           line_offset
 112: JUMP_FORWARD         to 118
 114: LOAD_CONST           0
 116: STORE_FAST           line_offset
 118: LOAD_GLOBAL          NULL + _get_instructions_bytes
 130: LOAD_GLOBAL          NULL + _get_code_array
 142: LOAD_FAST            co
 144: LOAD_FAST            adaptive
 146: PRECALL              
 150: CALL                 
 160: LOAD_FAST            co
 162: LOAD_ATTR            _varname_from_oparg
 172: LOAD_FAST            co
 174: LOAD_ATTR            co_names
 184: LOAD_FAST            co
 186: LOAD_ATTR            co_consts
 196: LOAD_FAST            linestarts
 198: LOAD_FAST            line_offset
 200: LOAD_FAST            co
 202: LOAD_METHOD          co_positions
 224: PRECALL              
 228: CALL                 
 238: LOAD_FAST            show_caches
 240: KW_NAMES             
 242: PRECALL              
 246: CALL                 
 256: RETURN_VALUE         
