# Disassembly for dis.<dictcomp>
# From module file: dis

## co_consts:
()

## co_names:
()

## bytecode:

   0: RESUME               
   2: BUILD_MAP            
   4: LOAD_FAST            .0
   6: FOR_ITER             to 34
   8: UNPACK_SEQUENCE      
  12: STORE_FAST           base
  14: STORE_FAST           family
  16: LOAD_FAST            family
  18: GET_ITER             
  20: FOR_ITER             to 32
  22: STORE_FAST           specialized
  24: LOAD_FAST            specialized
  26: LOAD_FAST            base
  28: MAP_ADD              
  30: JUMP_BACKWARD        to 20
  32: JUMP_BACKWARD        to 6
  34: RETURN_VALUE         
