# Disassembly for dis.Bytecode
# From module file: dis

## co_consts:
('Bytecode', 'The bytecode operations of a piece of code\n\n    Instantiate this with a function, method, other compiled object, string of\n    code, or a code object (as returned by compile()).\n\n    Iterating over this yields the bytecode operations as Instruction instances.\n    ', None, False, ('first_line', 'current_offset', 'show_caches', 'adaptive'), <code object __init__ at 0x0000024069365D40, file "dis.py", line 698>, <code object __iter__ at 0x000002406942DAC0, file "dis.py", line 713>, <code object __repr__ at 0x000002406944A230, file "dis.py", line 724>, ('show_caches', 'adaptive'), <code object from_traceback at 0x0000024069419C50, file "dis.py", line 728>, <code object info at 0x000002406945D2F0, file "dis.py", line 737>, <code object dis at 0x0000024068DB5390, file "dis.py", line 741>)

## co_names:
('__name__', '__module__', '__qualname__', '__doc__', '__init__', '__iter__', '__repr__', 'classmethod', 'from_traceback', 'info', 'dis')

## bytecode:

   0: RESUME               
   2: LOAD_NAME            __name__
   4: STORE_NAME           __module__
   6: LOAD_CONST           'Bytecode'
   8: STORE_NAME           __qualname__
  10: LOAD_CONST           'The bytecode operations of a piece of code\n\n    Instantiate this with a function, method, other compiled object, string of\n    code, or a code object (as returned by compile()).\n\n    Iterating over this yields the bytecode operations as Instruction instances.\n    '
  12: STORE_NAME           __doc__
  14: LOAD_CONST           None
  16: LOAD_CONST           None
  18: LOAD_CONST           False
  20: LOAD_CONST           False
  22: LOAD_CONST           ('first_line', 'current_offset', 'show_caches', 'adaptive')
  24: BUILD_CONST_KEY_MAP  
  26: LOAD_CONST           <code object __init__ at 0x0000024069365D40, file "dis.py", line 698>
  28: MAKE_FUNCTION        kwdefaults
  30: STORE_NAME           __init__
  32: LOAD_CONST           <code object __iter__ at 0x000002406942DAC0, file "dis.py", line 713>
  34: MAKE_FUNCTION        
  36: STORE_NAME           __iter__
  38: LOAD_CONST           <code object __repr__ at 0x000002406944A230, file "dis.py", line 724>
  40: MAKE_FUNCTION        
  42: STORE_NAME           __repr__
  44: LOAD_NAME            classmethod
  46: LOAD_CONST           False
  48: LOAD_CONST           False
  50: LOAD_CONST           ('show_caches', 'adaptive')
  52: BUILD_CONST_KEY_MAP  
  54: LOAD_CONST           <code object from_traceback at 0x0000024069419C50, file "dis.py", line 728>
  56: MAKE_FUNCTION        kwdefaults
  58: PRECALL              
  62: CALL                 
  72: STORE_NAME           from_traceback
  74: LOAD_CONST           <code object info at 0x000002406945D2F0, file "dis.py", line 737>
  76: MAKE_FUNCTION        
  78: STORE_NAME           info
  80: LOAD_CONST           <code object dis at 0x0000024068DB5390, file "dis.py", line 741>
  82: MAKE_FUNCTION        
  84: STORE_NAME           dis
  86: LOAD_CONST           None
  88: RETURN_VALUE         
