# Disassembly for dis._deoptop
# From module file: dis

## co_consts:
(None,)

## co_names:
('_all_opname', 'deoptmap', '_all_opmap')

## bytecode:

   0: RESUME               
   2: LOAD_GLOBAL          _all_opname
  14: LOAD_FAST            op
  16: BINARY_SUBSCR        
  26: STORE_FAST           name
  28: LOAD_FAST            name
  30: LOAD_GLOBAL          deoptmap
  42: CONTAINS_OP          
  44: POP_JUMP_FORWARD_IF_FALSE to 94
  46: LOAD_GLOBAL          _all_opmap
  58: LOAD_GLOBAL          deoptmap
  70: LOAD_FAST            name
  72: BINARY_SUBSCR        
  82: BINARY_SUBSCR        
  92: JUMP_FORWARD         to 96
  94: LOAD_FAST            op
  96: RETURN_VALUE         
