# Disassembly for dis._unpack_opargs
# From module file: dis

## co_consts:
(None, 0, 2, 1, 8)

## co_names:
('range', 'len', '_deoptop', '_inline_cache_entries', 'HAVE_ARGUMENT', 'EXTENDED_ARG', '_INT_OVERFLOW')

## bytecode:

   0: RETURN_GENERATOR     
   2: POP_TOP              
   4: RESUME               
   6: LOAD_CONST           0
   8: STORE_FAST           extended_arg
  10: LOAD_CONST           0
  12: STORE_FAST           caches
  14: LOAD_GLOBAL          NULL + range
  26: LOAD_CONST           0
  28: LOAD_GLOBAL          NULL + len
  40: LOAD_FAST            code
  42: PRECALL              
  46: CALL                 
  56: LOAD_CONST           2
  58: PRECALL              
  62: CALL                 
  72: GET_ITER             
  74: FOR_ITER             to 326
  76: STORE_FAST           i
  78: LOAD_FAST            caches
  80: POP_JUMP_FORWARD_IF_FALSE to 94
  82: LOAD_FAST            caches
  84: LOAD_CONST           1
  86: BINARY_OP            -=
  90: STORE_FAST           caches
  92: JUMP_BACKWARD        to 74
  94: LOAD_FAST            code
  96: LOAD_FAST            i
  98: BINARY_SUBSCR        
 108: STORE_FAST           op
 110: LOAD_GLOBAL          NULL + _deoptop
 122: LOAD_FAST            op
 124: PRECALL              
 128: CALL                 
 138: STORE_FAST           deop
 140: LOAD_GLOBAL          _inline_cache_entries
 152: LOAD_FAST            deop
 154: BINARY_SUBSCR        
 164: STORE_FAST           caches
 166: LOAD_FAST            deop
 168: LOAD_GLOBAL          HAVE_ARGUMENT
 180: COMPARE_OP           >=
 186: POP_JUMP_FORWARD_IF_FALSE to 302
 188: LOAD_FAST            code
 190: LOAD_FAST            i
 192: LOAD_CONST           1
 194: BINARY_OP            +
 198: BINARY_SUBSCR        
 208: LOAD_FAST            extended_arg
 210: BINARY_OP            |
 214: STORE_FAST           arg
 216: LOAD_FAST            deop
 218: LOAD_GLOBAL          EXTENDED_ARG
 230: COMPARE_OP           ==
 236: POP_JUMP_FORWARD_IF_FALSE to 248
 238: LOAD_FAST            arg
 240: LOAD_CONST           8
 242: BINARY_OP            <<
 246: JUMP_FORWARD         to 250
 248: LOAD_CONST           0
 250: STORE_FAST           extended_arg
 252: LOAD_FAST            extended_arg
 254: LOAD_GLOBAL          _INT_OVERFLOW
 266: COMPARE_OP           >=
 272: POP_JUMP_FORWARD_IF_FALSE to 300
 274: LOAD_FAST            extended_arg
 276: LOAD_CONST           2
 278: LOAD_GLOBAL          _INT_OVERFLOW
 290: BINARY_OP            *
 294: BINARY_OP            -=
 298: STORE_FAST           extended_arg
 300: JUMP_FORWARD         to 310
 302: LOAD_CONST           None
 304: STORE_FAST           arg
 306: LOAD_CONST           0
 308: STORE_FAST           extended_arg
 310: LOAD_FAST            i
 312: LOAD_FAST            op
 314: LOAD_FAST            arg
 316: BUILD_TUPLE          
 318: YIELD_VALUE          
 320: RESUME               
 322: POP_TOP              
 324: JUMP_BACKWARD        to 74
 326: LOAD_CONST           None
 328: RETURN_VALUE         
