# Disassembly for dis._get_name_info
# From module file: dis

## co_consts:
('Helper to get optional details about named references\n\n       Returns the dereferenced name as both value and repr if the name\n       list is defined.\n       Otherwise returns the sentinel value dis.UNKNOWN for the value\n       and an empty string for its repr.\n    ', None, '')

## co_names:
('UNKNOWN',)

## bytecode:

   0: RESUME               
   2: LOAD_FAST            get_name
   4: POP_JUMP_FORWARD_IF_NONE to 32
   6: PUSH_NULL            
   8: LOAD_FAST            get_name
  10: LOAD_FAST            name_index
  12: BUILD_TUPLE          
  14: BUILD_MAP            
  16: LOAD_FAST            extrainfo
  18: DICT_MERGE           
  20: CALL_FUNCTION_EX     
  22: STORE_FAST           argval
  24: LOAD_FAST            argval
  26: LOAD_FAST            argval
  28: BUILD_TUPLE          
  30: RETURN_VALUE         
  32: LOAD_GLOBAL          UNKNOWN
  44: LOAD_CONST           ''
  46: BUILD_TUPLE          
  48: RETURN_VALUE         
