# Disassembly for dis._find_imports.<listcomp>
# From module file: dis

## co_consts:
()

## co_names:
('EXTENDED_ARG',)

## bytecode:

   0: RESUME               
   2: BUILD_LIST           
   4: LOAD_FAST            .0
   6: FOR_ITER             to 50
   8: UNPACK_SEQUENCE      
  12: STORE_FAST           _
  14: STORE_FAST           op
  16: STORE_FAST           arg
  18: LOAD_FAST            op
  20: LOAD_GLOBAL          EXTENDED_ARG
  32: COMPARE_OP           !=
  38: POP_JUMP_BACKWARD_IF_FALSE to 6
  40: LOAD_FAST            op
  42: LOAD_FAST            arg
  44: BUILD_TUPLE          
  46: LIST_APPEND          
  48: JUMP_BACKWARD        to 6
  50: RETURN_VALUE         
