# Disassembly for dis._find_store_names
# From module file: dis

## co_consts:
('Find names of variables which are written in the code\n\n    Generate sequence of strings\n    ', 'STORE_NAME', 'STORE_GLOBAL', None)

## co_names:
('opmap', 'co_names', '_unpack_opargs', 'co_code')

## bytecode:

   0: RETURN_GENERATOR     
   2: POP_TOP              
   4: RESUME               
   6: LOAD_GLOBAL          opmap
  18: LOAD_CONST           'STORE_NAME'
  20: BINARY_SUBSCR        
  30: LOAD_GLOBAL          opmap
  42: LOAD_CONST           'STORE_GLOBAL'
  44: BINARY_SUBSCR        
  54: BUILD_SET            
  56: STORE_FAST           STORE_OPS
  58: LOAD_FAST            co
  60: LOAD_ATTR            co_names
  70: STORE_FAST           names
  72: LOAD_GLOBAL          NULL + _unpack_opargs
  84: LOAD_FAST            co
  86: LOAD_ATTR            co_code
  96: PRECALL              
 100: CALL                 
 110: GET_ITER             
 112: FOR_ITER             to 154
 114: UNPACK_SEQUENCE      
 118: STORE_FAST           _
 120: STORE_FAST           op
 122: STORE_FAST           arg
 124: LOAD_FAST            op
 126: LOAD_FAST            STORE_OPS
 128: CONTAINS_OP          
 130: POP_JUMP_FORWARD_IF_FALSE to 152
 132: LOAD_FAST            names
 134: LOAD_FAST            arg
 136: BINARY_SUBSCR        
 146: YIELD_VALUE          
 148: RESUME               
 150: POP_TOP              
 152: JUMP_BACKWARD        to 112
 154: LOAD_CONST           None
 156: RETURN_VALUE         
