# Disassembly for dis.distb
# From module file: dis

## co_consts:
('Disassemble a traceback (default: last traceback).', None, 'no last traceback to disassemble', ('file', 'show_caches', 'adaptive'))

## co_names:
('sys', 'last_traceback', 'AttributeError', 'RuntimeError', 'tb_next', 'disassemble', 'tb_frame', 'f_code', 'tb_lasti')

## bytecode:

   0: RESUME               
   2: LOAD_FAST            tb
   4: POP_JUMP_FORWARD_IF_NOT_NONE to 136
   6: NOP                  
   8: LOAD_GLOBAL          sys
  20: LOAD_ATTR            last_traceback
  30: STORE_FAST           tb
  32: JUMP_FORWARD         to 94
  34: PUSH_EXC_INFO        
  36: LOAD_GLOBAL          AttributeError
  48: CHECK_EXC_MATCH      
  50: POP_JUMP_FORWARD_IF_FALSE to 86
  52: POP_TOP              
  54: LOAD_GLOBAL          NULL + RuntimeError
  66: LOAD_CONST           'no last traceback to disassemble'
  68: PRECALL              
  72: CALL                 
  82: LOAD_CONST           None
  84: RAISE_VARARGS        
  86: RERAISE              
  88: COPY                 
  90: POP_EXCEPT           
  92: RERAISE              
  94: LOAD_FAST            tb
  96: LOAD_ATTR            tb_next
 106: POP_JUMP_FORWARD_IF_FALSE to 136
 108: LOAD_FAST            tb
 110: LOAD_ATTR            tb_next
 120: STORE_FAST           tb
 122: LOAD_FAST            tb
 124: LOAD_ATTR            tb_next
 134: POP_JUMP_BACKWARD_IF_TRUE to 108
 136: LOAD_GLOBAL          NULL + disassemble
 148: LOAD_FAST            tb
 150: LOAD_ATTR            tb_frame
 160: LOAD_ATTR            f_code
 170: LOAD_FAST            tb
 172: LOAD_ATTR            tb_lasti
 182: LOAD_FAST            file
 184: LOAD_FAST            show_caches
 186: LOAD_FAST            adaptive
 188: KW_NAMES             
 190: PRECALL              
 194: CALL                 
 204: POP_TOP              
 206: LOAD_CONST           None
 208: RETURN_VALUE         
