# Disassembly for stringprep.in_table_c4
# From module file: stringprep

## co_consts:
(None, 64976, False, 65008, True, 65535, (65534, 65535))

## co_names:
('ord',)

## bytecode:

   0: RESUME               
   2: LOAD_GLOBAL          NULL + ord
  14: LOAD_FAST            code
  16: PRECALL              
  20: CALL                 
  30: STORE_FAST           c
  32: LOAD_FAST            c
  34: LOAD_CONST           64976
  36: COMPARE_OP           <
  42: POP_JUMP_FORWARD_IF_FALSE to 48
  44: LOAD_CONST           False
  46: RETURN_VALUE         
  48: LOAD_FAST            c
  50: LOAD_CONST           65008
  52: COMPARE_OP           <
  58: POP_JUMP_FORWARD_IF_FALSE to 64
  60: LOAD_CONST           True
  62: RETURN_VALUE         
  64: LOAD_GLOBAL          NULL + ord
  76: LOAD_FAST            code
  78: PRECALL              
  82: CALL                 
  92: LOAD_CONST           65535
  94: BINARY_OP            &
  98: LOAD_CONST           (65534, 65535)
 100: CONTAINS_OP          
 102: RETURN_VALUE         
