# Disassembly for stringprep.map_table_b3
# From module file: stringprep

## co_consts:
(None,)

## co_names:
('b3_exceptions', 'get', 'ord', 'lower')

## bytecode:

   0: RESUME               
   2: LOAD_GLOBAL          b3_exceptions
  14: LOAD_METHOD          get
  36: LOAD_GLOBAL          NULL + ord
  48: LOAD_FAST            code
  50: PRECALL              
  54: CALL                 
  64: PRECALL              
  68: CALL                 
  78: STORE_FAST           r
  80: LOAD_FAST            r
  82: POP_JUMP_FORWARD_IF_NONE to 88
  84: LOAD_FAST            r
  86: RETURN_VALUE         
  88: LOAD_FAST            code
  90: LOAD_METHOD          lower
 112: PRECALL              
 116: CALL                 
 126: RETURN_VALUE         
