# Disassembly for stringprep
# From module file: stringprep

## co_consts:
('Library that exposes various tables found in the StringPrep RFC 3454.\n\nThere are two kinds of tables: sets, for which a member test is provided,\nand mappings, for which a mapping function is provided.\n', 0, ('ucd_3_2_0',), '3.2.0', <code object in_table_a1 at 0x00000240693AB730, file "stringprep.py", line 12>, (173, 847, 6150, 6155, 6156, 6157, 8203, 8204, 8205, 8288, 65279), 65024, 65040, <code object in_table_b1 at 0x000002406945E3D0, file "stringprep.py", line 20>, 181, 'μ', 223, 'ss', 304, 'i̇', 329, 'ʼn', 383, 's', 496, 'ǰ', 837, 'ι', 890, ' ι', 912, 'ΐ', 944, 'ΰ', 962, 'σ', 976, 'β', 977, 'θ', 978, 'υ', 979, 'ύ', 980, 'ϋ', 981, 'φ', 982, 'π', 1008, 'κ', 1009, 'ρ', 1010, 1013, 'ε', 1415, 'եւ', 7830, 'ẖ', 7831, 'ẗ', 7832, 'ẘ', 7833, 'ẙ', 7834, 'aʾ', 7835, 'ṡ', 8016, 'ὐ', 8018, 'ὒ', 8020, 'ὔ', 8022, 'ὖ', 8064, 'ἀι', 8065, 'ἁι', 8066, 'ἂι', 8067, 'ἃι', 8068, 'ἄι', 8069, 'ἅι', 8070, 'ἆι', 8071, 'ἇι', 8072, 8073, 8074, 8075, 8076, 8077, 8078, 8079, 8080, 'ἠι', 8081, 'ἡι', 8082, 'ἢι', 8083, 'ἣι', 8084, 'ἤι', 8085, 'ἥι', 8086, 'ἦι', 8087, 'ἧι', 8088, 8089, 8090, 8091, 8092, 8093, 8094, 8095, 8096, 'ὠι', 8097, 'ὡι', 8098, 'ὢι', 8099, 'ὣι', 8100, 'ὤι', 8101, 'ὥι', 8102, 'ὦι', 8103, 'ὧι', 8104, 8105, 8106, 8107, 8108, 8109, 8110, 8111, 8114, 'ὰι', 8115, 'αι', 8116, 'άι', 8118, 'ᾶ', 8119, 'ᾶι', 8124, 8126, 8130, 'ὴι', 8131, 'ηι', 8132, 'ήι', 8134, 'ῆ', 8135, 'ῆι', 8140, 8146, 'ῒ', 8147, 8150, 'ῖ', 8151, 'ῗ', 8162, 'ῢ', 8163, 8164, 'ῤ', 8166, 'ῦ', 8167, 'ῧ', 8178, 'ὼι', 8179, 'ωι', 8180, 'ώι', 8182, 'ῶ', 8183, 'ῶι', 8188, 8360, 'rs', 8450, 'c', 8451, '°c', 8455, 'ɛ', 8457, '°f', 8459, 'h', 8460, 8461, 8464, 'i', 8465, 8466, 'l', 8469, 'n', 8470, 'no', 8473, 'p', 8474, 'q', 8475, 'r', 8476, 8477, 8480, 'sm', 8481, 'tel', 8482, 'tm', 8484, 'z', 8488, 8492, 'b', 8493, 8496, 'e', 8497, 'f', 8499, 'm', 8510, 'γ', 8511, 8517, 'd', 13169, 'hpa', 13171, 'au', 13173, 'ov', 13184, 'pa', 13185, 'na', 13186, 'μa', 13187, 'ma', 13188, 'ka', 13189, 'kb', 13190, 'mb', 13191, 'gb', 13194, 'pf', 13195, 'nf', 13196, 'μf', 13200, 'hz', 13201, 'khz', 13202, 'mhz', 13203, 'ghz', 13204, 'thz', 13225, 13226, 'kpa', 13227, 'mpa', 13228, 'gpa', 13236, 'pv', 13237, 'nv', 13238, 'μv', 13239, 'mv', 13240, 'kv', 13241, 13242, 'pw', 13243, 'nw', 13244, 'μw', 13245, 'mw', 13246, 'kw', 13247, 13248, 'kω', 13249, 'mω', 13251, 'bq', 13254, 'c∕kg', 13255, 'co.', 13256, 'db', 13257, 'gy', 13259, 'hp', 13261, 'kk', 13262, 'km', 13271, 'ph', 13273, 'ppm', 13274, 'pr', 13276, 'sv', 13277, 'wb', 64256, 'ff', 64257, 'fi', 64258, 'fl', 64259, 'ffi', 64260, 'ffl', 64261, 'st', 64262, 64275, 'մն', 64276, 'մե', 64277, 'մի', 64278, 'վն', 64279, 'մխ', 119808, 'a', 119809, 119810, 119811, 119812, 119813, 119814, 'g', 119815, 119816, 119817, 'j', 119818, 'k', 119819, 119820, 119821, 119822, 'o', 119823, 119824, 119825, 119826, 119827, 't', 119828, 'u', 119829, 'v', 119830, 'w', 119831, 'x', 119832, 'y', 119833, 119860, 119861, 119862, 119863, 119864, 119865, 119866, 119867, 119868, 119869, 119870, 119871, 119872, 119873, 119874, 119875, 119876, 119877, 119878, 119879, 119880, 119881, 119882, 119883, 119884, 119885, 119912, 119913, 119914, 119915, 119916, 119917, 119918, 119919, 119920, 119921, 119922, 119923, 119924, 119925, 119926, 119927, 119928, 119929, 119930, 119931, 119932, 119933, 119934, 119935, 119936, 119937, 119964, 119966, 119967, 119970, 119973, 119974, 119977, 119978, 119979, 119980, 119982, 119983, 119984, 119985, 119986, 119987, 119988, 119989, 120016, 120017, 120018, 120019, 120020, 120021, 120022, 120023, 120024, 120025, 120026, 120027, 120028, 120029, 120030, 120031, 120032, 120033, 120034, 120035, 120036, 120037, 120038, 120039, 120040, 120041, 120068, 120069, 120071, 120072, 120073, 120074, 120077, 120078, 120079, 120080, 120081, 120082, 120083, 120084, 120086, 120087, 120088, 120089, 120090, 120091, 120092, 120120, 120121, 120123, 120124, 120125, 120126, 120128, 120129, 120130, 120131, 120132, 120134, 120138, 120139, 120140, 120141, 120142, 120143, 120144, 120172, 120173, 120174, 120175, 120176, 120177, 120178, 120179, 120180, 120181, 120182, 120183, 120184, 120185, 120186, 120187, 120188, 120189, 120190, 120191, 120192, 120193, 120194, 120195, 120196, 120197, 120224, 120225, 120226, 120227, 120228, 120229, 120230, 120231, 120232, 120233, 120234, 120235, 120236, 120237, 120238, 120239, 120240, 120241, 120242, 120243, 120244, 120245, 120246, 120247, 120248, 120249, 120276, 120277, 120278, 120279, 120280, 120281, 120282, 120283, 120284, 120285, 120286, 120287, 120288, 120289, 120290, 120291, 120292, 120293, 120294, 120295, 120296, 120297, 120298, 120299, 120300, 120301, 120328, 120329, 120330, 120331, 120332, 120333, 120334, 120335, 120336, 120337, 120338, 120339, 120340, 120341, 120342, 120343, 120344, 120345, 120346, 120347, 120348, 120349, 120350, 120351, 120352, 120353, 120380, 120381, 120382, 120383, 120384, 120385, 120386, 120387, 120388, 120389, 120390, 120391, 120392, 120393, 120394, 120395, 120396, 120397, 120398, 120399, 120400, 120401, 120402, 120403, 120404, 120405, 120432, 120433, 120434, 120435, 120436, 120437, 120438, 120439, 120440, 120441, 120442, 120443, 120444, 120445, 120446, 120447, 120448, 120449, 120450, 120451, 120452, 120453, 120454, 120455, 120456, 120457, 120488, 'α', 120489, 120490, 120491, 'δ', 120492, 120493, 'ζ', 120494, 'η', 120495, 120496, 120497, 120498, 'λ', 120499, 120500, 'ν', 120501, 'ξ', 120502, 'ο', 120503, 120504, 120505, 120506, 120507, 'τ', 120508, 120509, 120510, 'χ', 120511, 'ψ', 120512, 'ω', 120531, 120546, 120547, 120548, 120549, 120550, 120551, 120552, 120553, 120554, 120555, 120556, 120557, 120558, 120559, 120560, 120561, 120562, 120563, 120564, 120565, 120566, 120567, 120568, 120569, 120570, 120589, 120604, 120605, 120606, 120607, 120608, 120609, 120610, 120611, 120612, 120613, 120614, 120615, 120616, 120617, 120618, 120619, 120620, 120621, 120622, 120623, 120624, 120625, 120626, 120627, 120628, 120647, 120662, 120663, 120664, 120665, 120666, 120667, 120668, 120669, 120670, 120671, 120672, 120673, 120674, 120675, 120676, 120677, 120678, 120679, 120680, 120681, 120682, 120683, 120684, 120685, 120686, 120705, 120720, 120721, 120722, 120723, 120724, 120725, 120726, 120727, 120728, 120729, 120730, 120731, 120732, 120733, 120734, 120735, 120736, 120737, 120738, 120739, 120740, 120741, (120742, 120743, 120744, 120763), <code object map_table_b3 at 0x00000240693AB230, file "stringprep.py", line 189>, <code object map_table_b2 at 0x00000240691E9830, file "stringprep.py", line 195>, <code object in_table_c11 at 0x0000024069496180, file "stringprep.py", line 206>, <code object in_table_c12 at 0x00000240693EB730, file "stringprep.py", line 210>, <code object in_table_c11_c12 at 0x000002406945EA60, file "stringprep.py", line 213>, <code object in_table_c21 at 0x000002406944AAB0, file "stringprep.py", line 217>, (1757, 1807, 6158, 8204, 8205, 8232, 8233, 65279), 8288, 8292, 8298, 8304, 65529, 65533, 119155, 119163, <code object in_table_c22 at 0x00000240693D23D0, file "stringprep.py", line 221>, <code object in_table_c21_c22 at 0x000002406941B2D0, file "stringprep.py", line 227>, <code object in_table_c3 at 0x000002406945F2D0, file "stringprep.py", line 232>, <code object in_table_c4 at 0x000002406941A310, file "stringprep.py", line 236>, <code object in_table_c5 at 0x000002406945FD20, file "stringprep.py", line 243>, 65534, <code object in_table_c6 at 0x000002406945DC50, file "stringprep.py", line 248>, 12272, 12284, <code object in_table_c7 at 0x000002406945F000, file "stringprep.py", line 253>, (832, 833, 8206, 8207), 8234, 8239, <code object in_table_c8 at 0x000002406945FC30, file "stringprep.py", line 258>, 917505, 917536, 917632, <code object in_table_c9 at 0x000002406945DF20, file "stringprep.py", line 263>, <code object in_table_d1 at 0x000002406945DE30, file "stringprep.py", line 267>, <code object in_table_d2 at 0x000002406945E880, file "stringprep.py", line 271>, None)

## co_names:
('__doc__', 'unicodedata', 'ucd_3_2_0', 'unidata_version', 'in_table_a1', 'set', 'list', 'range', 'b1_set', 'in_table_b1', 'b3_exceptions', 'map_table_b3', 'map_table_b2', 'in_table_c11', 'in_table_c12', 'in_table_c11_c12', 'in_table_c21', 'c22_specials', 'in_table_c22', 'in_table_c21_c22', 'in_table_c3', 'in_table_c4', 'in_table_c5', 'c6_set', 'in_table_c6', 'c7_set', 'in_table_c7', 'c8_set', 'in_table_c8', 'c9_set', 'in_table_c9', 'in_table_d1', 'in_table_d2')

## bytecode:

   0: RESUME               
   2: LOAD_CONST           'Library that exposes various tables found in the StringPrep RFC 3454.\n\nThere are two kinds of tables: sets, for which a member test is provided,\nand mappings, for which a mapping function is provided.\n'
   4: STORE_NAME           __doc__
   6: LOAD_CONST           0
   8: LOAD_CONST           ('ucd_3_2_0',)
  10: IMPORT_NAME          unicodedata
  12: IMPORT_FROM          ucd_3_2_0
  14: STORE_NAME           unicodedata
  16: POP_TOP              
  18: LOAD_NAME            unicodedata
  20: LOAD_ATTR            unidata_version
  30: LOAD_CONST           '3.2.0'
  32: COMPARE_OP           ==
  38: POP_JUMP_FORWARD_IF_TRUE to 44
  40: LOAD_ASSERTION_ERROR 
  42: RAISE_VARARGS        
  44: LOAD_CONST           <code object in_table_a1 at 0x00000240693AB730, file "stringprep.py", line 12>
  46: MAKE_FUNCTION        
  48: STORE_NAME           in_table_a1
  50: PUSH_NULL            
  52: LOAD_NAME            set
  54: BUILD_LIST           
  56: LOAD_CONST           (173, 847, 6150, 6155, 6156, 6157, 8203, 8204, 8205, 8288, 65279)
  58: LIST_EXTEND          
  60: PUSH_NULL            
  62: LOAD_NAME            list
  64: PUSH_NULL            
  66: LOAD_NAME            range
  68: LOAD_CONST           65024
  70: LOAD_CONST           65040
  72: PRECALL              
  76: CALL                 
  86: PRECALL              
  90: CALL                 
 100: BINARY_OP            +
 104: PRECALL              
 108: CALL                 
 118: STORE_NAME           b1_set
 120: LOAD_CONST           <code object in_table_b1 at 0x000002406945E3D0, file "stringprep.py", line 20>
 122: MAKE_FUNCTION        
 124: STORE_NAME           in_table_b1
 126: BUILD_MAP            
 128: LOAD_CONST           181
 130: LOAD_CONST           'μ'
 132: MAP_ADD              
 134: LOAD_CONST           223
 136: LOAD_CONST           'ss'
 138: MAP_ADD              
 140: LOAD_CONST           304
 142: LOAD_CONST           'i̇'
 144: MAP_ADD              
 146: LOAD_CONST           329
 148: LOAD_CONST           'ʼn'
 150: MAP_ADD              
 152: LOAD_CONST           383
 154: LOAD_CONST           's'
 156: MAP_ADD              
 158: LOAD_CONST           496
 160: LOAD_CONST           'ǰ'
 162: MAP_ADD              
 164: LOAD_CONST           837
 166: LOAD_CONST           'ι'
 168: MAP_ADD              
 170: LOAD_CONST           890
 172: LOAD_CONST           ' ι'
 174: MAP_ADD              
 176: LOAD_CONST           912
 178: LOAD_CONST           'ΐ'
 180: MAP_ADD              
 182: LOAD_CONST           944
 184: LOAD_CONST           'ΰ'
 186: MAP_ADD              
 188: LOAD_CONST           962
 190: LOAD_CONST           'σ'
 192: MAP_ADD              
 194: LOAD_CONST           976
 196: LOAD_CONST           'β'
 198: MAP_ADD              
 200: LOAD_CONST           977
 202: LOAD_CONST           'θ'
 204: MAP_ADD              
 206: LOAD_CONST           978
 208: LOAD_CONST           'υ'
 210: MAP_ADD              
 212: LOAD_CONST           979
 214: LOAD_CONST           'ύ'
 216: MAP_ADD              
 218: LOAD_CONST           980
 220: LOAD_CONST           'ϋ'
 222: MAP_ADD              
 224: LOAD_CONST           981
 226: LOAD_CONST           'φ'
 228: MAP_ADD              
 230: BUILD_MAP            
 232: LOAD_CONST           982
 234: LOAD_CONST           'π'
 236: MAP_ADD              
 238: LOAD_CONST           1008
 240: LOAD_CONST           'κ'
 242: MAP_ADD              
 244: LOAD_CONST           1009
 246: LOAD_CONST           'ρ'
 248: MAP_ADD              
 250: LOAD_CONST           1010
 252: LOAD_CONST           'σ'
 254: MAP_ADD              
 256: LOAD_CONST           1013
 258: LOAD_CONST           'ε'
 260: MAP_ADD              
 262: LOAD_CONST           1415
 264: LOAD_CONST           'եւ'
 266: MAP_ADD              
 268: LOAD_CONST           7830
 270: LOAD_CONST           'ẖ'
 272: MAP_ADD              
 274: LOAD_CONST           7831
 276: LOAD_CONST           'ẗ'
 278: MAP_ADD              
 280: LOAD_CONST           7832
 282: LOAD_CONST           'ẘ'
 284: MAP_ADD              
 286: LOAD_CONST           7833
 288: LOAD_CONST           'ẙ'
 290: MAP_ADD              
 292: LOAD_CONST           7834
 294: LOAD_CONST           'aʾ'
 296: MAP_ADD              
 298: LOAD_CONST           7835
 300: LOAD_CONST           'ṡ'
 302: MAP_ADD              
 304: LOAD_CONST           8016
 306: LOAD_CONST           'ὐ'
 308: MAP_ADD              
 310: LOAD_CONST           8018
 312: LOAD_CONST           'ὒ'
 314: MAP_ADD              
 316: LOAD_CONST           8020
 318: LOAD_CONST           'ὔ'
 320: MAP_ADD              
 322: LOAD_CONST           8022
 324: LOAD_CONST           'ὖ'
 326: MAP_ADD              
 328: LOAD_CONST           8064
 330: LOAD_CONST           'ἀι'
 332: MAP_ADD              
 334: DICT_UPDATE          
 336: BUILD_MAP            
 338: LOAD_CONST           8065
 340: LOAD_CONST           'ἁι'
 342: MAP_ADD              
 344: LOAD_CONST           8066
 346: LOAD_CONST           'ἂι'
 348: MAP_ADD              
 350: LOAD_CONST           8067
 352: LOAD_CONST           'ἃι'
 354: MAP_ADD              
 356: LOAD_CONST           8068
 358: LOAD_CONST           'ἄι'
 360: MAP_ADD              
 362: LOAD_CONST           8069
 364: LOAD_CONST           'ἅι'
 366: MAP_ADD              
 368: LOAD_CONST           8070
 370: LOAD_CONST           'ἆι'
 372: MAP_ADD              
 374: LOAD_CONST           8071
 376: LOAD_CONST           'ἇι'
 378: MAP_ADD              
 380: LOAD_CONST           8072
 382: LOAD_CONST           'ἀι'
 384: MAP_ADD              
 386: LOAD_CONST           8073
 388: LOAD_CONST           'ἁι'
 390: MAP_ADD              
 392: LOAD_CONST           8074
 394: LOAD_CONST           'ἂι'
 396: MAP_ADD              
 398: LOAD_CONST           8075
 400: LOAD_CONST           'ἃι'
 402: MAP_ADD              
 404: LOAD_CONST           8076
 406: LOAD_CONST           'ἄι'
 408: MAP_ADD              
 410: LOAD_CONST           8077
 412: LOAD_CONST           'ἅι'
 414: MAP_ADD              
 416: LOAD_CONST           8078
 418: LOAD_CONST           'ἆι'
 420: MAP_ADD              
 422: LOAD_CONST           8079
 424: LOAD_CONST           'ἇι'
 426: MAP_ADD              
 428: LOAD_CONST           8080
 430: LOAD_CONST           'ἠι'
 432: MAP_ADD              
 434: LOAD_CONST           8081
 436: LOAD_CONST           'ἡι'
 438: MAP_ADD              
 440: DICT_UPDATE          
 442: BUILD_MAP            
 444: LOAD_CONST           8082
 446: LOAD_CONST           'ἢι'
 448: MAP_ADD              
 450: LOAD_CONST           8083
 452: LOAD_CONST           'ἣι'
 454: MAP_ADD              
 456: LOAD_CONST           8084
 458: LOAD_CONST           'ἤι'
 460: MAP_ADD              
 462: LOAD_CONST           8085
 464: LOAD_CONST           'ἥι'
 466: MAP_ADD              
 468: LOAD_CONST           8086
 470: LOAD_CONST           'ἦι'
 472: MAP_ADD              
 474: LOAD_CONST           8087
 476: LOAD_CONST           'ἧι'
 478: MAP_ADD              
 480: LOAD_CONST           8088
 482: LOAD_CONST           'ἠι'
 484: MAP_ADD              
 486: LOAD_CONST           8089
 488: LOAD_CONST           'ἡι'
 490: MAP_ADD              
 492: LOAD_CONST           8090
 494: LOAD_CONST           'ἢι'
 496: MAP_ADD              
 498: LOAD_CONST           8091
 500: LOAD_CONST           'ἣι'
 502: MAP_ADD              
 504: LOAD_CONST           8092
 506: LOAD_CONST           'ἤι'
 508: MAP_ADD              
 510: LOAD_CONST           8093
 512: LOAD_CONST           'ἥι'
 514: MAP_ADD              
 516: LOAD_CONST           8094
 518: LOAD_CONST           'ἦι'
 520: MAP_ADD              
 522: LOAD_CONST           8095
 524: LOAD_CONST           'ἧι'
 526: MAP_ADD              
 528: LOAD_CONST           8096
 530: LOAD_CONST           'ὠι'
 532: MAP_ADD              
 534: LOAD_CONST           8097
 536: LOAD_CONST           'ὡι'
 538: MAP_ADD              
 540: LOAD_CONST           8098
 542: LOAD_CONST           'ὢι'
 544: MAP_ADD              
 546: DICT_UPDATE          
 548: BUILD_MAP            
 550: LOAD_CONST           8099
 552: LOAD_CONST           'ὣι'
 554: MAP_ADD              
 556: LOAD_CONST           8100
 558: LOAD_CONST           'ὤι'
 560: MAP_ADD              
 562: LOAD_CONST           8101
 564: LOAD_CONST           'ὥι'
 566: MAP_ADD              
 568: LOAD_CONST           8102
 570: LOAD_CONST           'ὦι'
 572: MAP_ADD              
 574: LOAD_CONST           8103
 576: LOAD_CONST           'ὧι'
 578: MAP_ADD              
 580: LOAD_CONST           8104
 582: LOAD_CONST           'ὠι'
 584: MAP_ADD              
 586: LOAD_CONST           8105
 588: LOAD_CONST           'ὡι'
 590: MAP_ADD              
 592: LOAD_CONST           8106
 594: LOAD_CONST           'ὢι'
 596: MAP_ADD              
 598: LOAD_CONST           8107
 600: LOAD_CONST           'ὣι'
 602: MAP_ADD              
 604: LOAD_CONST           8108
 606: LOAD_CONST           'ὤι'
 608: MAP_ADD              
 610: LOAD_CONST           8109
 612: LOAD_CONST           'ὥι'
 614: MAP_ADD              
 616: LOAD_CONST           8110
 618: LOAD_CONST           'ὦι'
 620: MAP_ADD              
 622: LOAD_CONST           8111
 624: LOAD_CONST           'ὧι'
 626: MAP_ADD              
 628: LOAD_CONST           8114
 630: LOAD_CONST           'ὰι'
 632: MAP_ADD              
 634: LOAD_CONST           8115
 636: LOAD_CONST           'αι'
 638: MAP_ADD              
 640: LOAD_CONST           8116
 642: LOAD_CONST           'άι'
 644: MAP_ADD              
 646: LOAD_CONST           8118
 648: LOAD_CONST           'ᾶ'
 650: MAP_ADD              
 652: DICT_UPDATE          
 654: BUILD_MAP            
 656: LOAD_CONST           8119
 658: LOAD_CONST           'ᾶι'
 660: MAP_ADD              
 662: LOAD_CONST           8124
 664: LOAD_CONST           'αι'
 666: MAP_ADD              
 668: LOAD_CONST           8126
 670: LOAD_CONST           'ι'
 672: MAP_ADD              
 674: LOAD_CONST           8130
 676: LOAD_CONST           'ὴι'
 678: MAP_ADD              
 680: LOAD_CONST           8131
 682: LOAD_CONST           'ηι'
 684: MAP_ADD              
 686: LOAD_CONST           8132
 688: LOAD_CONST           'ήι'
 690: MAP_ADD              
 692: LOAD_CONST           8134
 694: LOAD_CONST           'ῆ'
 696: MAP_ADD              
 698: LOAD_CONST           8135
 700: LOAD_CONST           'ῆι'
 702: MAP_ADD              
 704: LOAD_CONST           8140
 706: LOAD_CONST           'ηι'
 708: MAP_ADD              
 710: LOAD_CONST           8146
 712: LOAD_CONST           'ῒ'
 714: MAP_ADD              
 716: LOAD_CONST           8147
 718: LOAD_CONST           'ΐ'
 720: MAP_ADD              
 722: LOAD_CONST           8150
 724: LOAD_CONST           'ῖ'
 726: MAP_ADD              
 728: LOAD_CONST           8151
 730: LOAD_CONST           'ῗ'
 732: MAP_ADD              
 734: LOAD_CONST           8162
 736: LOAD_CONST           'ῢ'
 738: MAP_ADD              
 740: LOAD_CONST           8163
 742: LOAD_CONST           'ΰ'
 744: MAP_ADD              
 746: LOAD_CONST           8164
 748: LOAD_CONST           'ῤ'
 750: MAP_ADD              
 752: LOAD_CONST           8166
 754: LOAD_CONST           'ῦ'
 756: MAP_ADD              
 758: DICT_UPDATE          
 760: BUILD_MAP            
 762: LOAD_CONST           8167
 764: LOAD_CONST           'ῧ'
 766: MAP_ADD              
 768: LOAD_CONST           8178
 770: LOAD_CONST           'ὼι'
 772: MAP_ADD              
 774: LOAD_CONST           8179
 776: LOAD_CONST           'ωι'
 778: MAP_ADD              
 780: LOAD_CONST           8180
 782: LOAD_CONST           'ώι'
 784: MAP_ADD              
 786: LOAD_CONST           8182
 788: LOAD_CONST           'ῶ'
 790: MAP_ADD              
 792: LOAD_CONST           8183
 794: LOAD_CONST           'ῶι'
 796: MAP_ADD              
 798: LOAD_CONST           8188
 800: LOAD_CONST           'ωι'
 802: MAP_ADD              
 804: LOAD_CONST           8360
 806: LOAD_CONST           'rs'
 808: MAP_ADD              
 810: LOAD_CONST           8450
 812: LOAD_CONST           'c'
 814: MAP_ADD              
 816: LOAD_CONST           8451
 818: LOAD_CONST           '°c'
 820: MAP_ADD              
 822: LOAD_CONST           8455
 824: LOAD_CONST           'ɛ'
 826: MAP_ADD              
 828: LOAD_CONST           8457
 830: LOAD_CONST           '°f'
 832: MAP_ADD              
 834: LOAD_CONST           8459
 836: LOAD_CONST           'h'
 838: MAP_ADD              
 840: LOAD_CONST           8460
 842: LOAD_CONST           'h'
 844: MAP_ADD              
 846: LOAD_CONST           8461
 848: LOAD_CONST           'h'
 850: MAP_ADD              
 852: LOAD_CONST           8464
 854: LOAD_CONST           'i'
 856: MAP_ADD              
 858: LOAD_CONST           8465
 860: LOAD_CONST           'i'
 862: MAP_ADD              
 864: DICT_UPDATE          
 866: BUILD_MAP            
 868: LOAD_CONST           8466
 870: LOAD_CONST           'l'
 872: MAP_ADD              
 874: LOAD_CONST           8469
 876: LOAD_CONST           'n'
 878: MAP_ADD              
 880: LOAD_CONST           8470
 882: LOAD_CONST           'no'
 884: MAP_ADD              
 886: LOAD_CONST           8473
 888: LOAD_CONST           'p'
 890: MAP_ADD              
 892: LOAD_CONST           8474
 894: LOAD_CONST           'q'
 896: MAP_ADD              
 898: LOAD_CONST           8475
 900: LOAD_CONST           'r'
 902: MAP_ADD              
 904: LOAD_CONST           8476
 906: LOAD_CONST           'r'
 908: MAP_ADD              
 910: LOAD_CONST           8477
 912: LOAD_CONST           'r'
 914: MAP_ADD              
 916: LOAD_CONST           8480
 918: LOAD_CONST           'sm'
 920: MAP_ADD              
 922: LOAD_CONST           8481
 924: LOAD_CONST           'tel'
 926: MAP_ADD              
 928: LOAD_CONST           8482
 930: LOAD_CONST           'tm'
 932: MAP_ADD              
 934: LOAD_CONST           8484
 936: LOAD_CONST           'z'
 938: MAP_ADD              
 940: LOAD_CONST           8488
 942: LOAD_CONST           'z'
 944: MAP_ADD              
 946: LOAD_CONST           8492
 948: LOAD_CONST           'b'
 950: MAP_ADD              
 952: LOAD_CONST           8493
 954: LOAD_CONST           'c'
 956: MAP_ADD              
 958: LOAD_CONST           8496
 960: LOAD_CONST           'e'
 962: MAP_ADD              
 964: LOAD_CONST           8497
 966: LOAD_CONST           'f'
 968: MAP_ADD              
 970: DICT_UPDATE          
 972: BUILD_MAP            
 974: LOAD_CONST           8499
 976: LOAD_CONST           'm'
 978: MAP_ADD              
 980: LOAD_CONST           8510
 982: LOAD_CONST           'γ'
 984: MAP_ADD              
 986: LOAD_CONST           8511
 988: LOAD_CONST           'π'
 990: MAP_ADD              
 992: LOAD_CONST           8517
 994: LOAD_CONST           'd'
 996: MAP_ADD              
 998: LOAD_CONST           13169
1000: LOAD_CONST           'hpa'
1002: MAP_ADD              
1004: LOAD_CONST           13171
1006: LOAD_CONST           'au'
1008: MAP_ADD              
1010: LOAD_CONST           13173
1012: LOAD_CONST           'ov'
1014: MAP_ADD              
1016: EXTENDED_ARG         
1018: LOAD_CONST           13184
1020: EXTENDED_ARG         
1022: LOAD_CONST           'pa'
1024: MAP_ADD              
1026: EXTENDED_ARG         
1028: LOAD_CONST           13185
1030: EXTENDED_ARG         
1032: LOAD_CONST           'na'
1034: MAP_ADD              
1036: EXTENDED_ARG         
1038: LOAD_CONST           13186
1040: EXTENDED_ARG         
1042: LOAD_CONST           'μa'
1044: MAP_ADD              
1046: EXTENDED_ARG         
1048: LOAD_CONST           13187
1050: EXTENDED_ARG         
1052: LOAD_CONST           'ma'
1054: MAP_ADD              
1056: EXTENDED_ARG         
1058: LOAD_CONST           13188
1060: EXTENDED_ARG         
1062: LOAD_CONST           'ka'
1064: MAP_ADD              
1066: EXTENDED_ARG         
1068: LOAD_CONST           13189
1070: EXTENDED_ARG         
1072: LOAD_CONST           'kb'
1074: MAP_ADD              
1076: EXTENDED_ARG         
1078: LOAD_CONST           13190
1080: EXTENDED_ARG         
1082: LOAD_CONST           'mb'
1084: MAP_ADD              
1086: EXTENDED_ARG         
1088: LOAD_CONST           13191
1090: EXTENDED_ARG         
1092: LOAD_CONST           'gb'
1094: MAP_ADD              
1096: EXTENDED_ARG         
1098: LOAD_CONST           13194
1100: EXTENDED_ARG         
1102: LOAD_CONST           'pf'
1104: MAP_ADD              
1106: EXTENDED_ARG         
1108: LOAD_CONST           13195
1110: EXTENDED_ARG         
1112: LOAD_CONST           'nf'
1114: MAP_ADD              
1116: DICT_UPDATE          
1118: BUILD_MAP            
1120: EXTENDED_ARG         
1122: LOAD_CONST           13196
1124: EXTENDED_ARG         
1126: LOAD_CONST           'μf'
1128: MAP_ADD              
1130: EXTENDED_ARG         
1132: LOAD_CONST           13200
1134: EXTENDED_ARG         
1136: LOAD_CONST           'hz'
1138: MAP_ADD              
1140: EXTENDED_ARG         
1142: LOAD_CONST           13201
1144: EXTENDED_ARG         
1146: LOAD_CONST           'khz'
1148: MAP_ADD              
1150: EXTENDED_ARG         
1152: LOAD_CONST           13202
1154: EXTENDED_ARG         
1156: LOAD_CONST           'mhz'
1158: MAP_ADD              
1160: EXTENDED_ARG         
1162: LOAD_CONST           13203
1164: EXTENDED_ARG         
1166: LOAD_CONST           'ghz'
1168: MAP_ADD              
1170: EXTENDED_ARG         
1172: LOAD_CONST           13204
1174: EXTENDED_ARG         
1176: LOAD_CONST           'thz'
1178: MAP_ADD              
1180: EXTENDED_ARG         
1182: LOAD_CONST           13225
1184: EXTENDED_ARG         
1186: LOAD_CONST           'pa'
1188: MAP_ADD              
1190: EXTENDED_ARG         
1192: LOAD_CONST           13226
1194: EXTENDED_ARG         
1196: LOAD_CONST           'kpa'
1198: MAP_ADD              
1200: EXTENDED_ARG         
1202: LOAD_CONST           13227
1204: EXTENDED_ARG         
1206: LOAD_CONST           'mpa'
1208: MAP_ADD              
1210: EXTENDED_ARG         
1212: LOAD_CONST           13228
1214: EXTENDED_ARG         
1216: LOAD_CONST           'gpa'
1218: MAP_ADD              
1220: EXTENDED_ARG         
1222: LOAD_CONST           13236
1224: EXTENDED_ARG         
1226: LOAD_CONST           'pv'
1228: MAP_ADD              
1230: EXTENDED_ARG         
1232: LOAD_CONST           13237
1234: EXTENDED_ARG         
1236: LOAD_CONST           'nv'
1238: MAP_ADD              
1240: EXTENDED_ARG         
1242: LOAD_CONST           13238
1244: EXTENDED_ARG         
1246: LOAD_CONST           'μv'
1248: MAP_ADD              
1250: EXTENDED_ARG         
1252: LOAD_CONST           13239
1254: EXTENDED_ARG         
1256: LOAD_CONST           'mv'
1258: MAP_ADD              
1260: EXTENDED_ARG         
1262: LOAD_CONST           13240
1264: EXTENDED_ARG         
1266: LOAD_CONST           'kv'
1268: MAP_ADD              
1270: EXTENDED_ARG         
1272: LOAD_CONST           13241
1274: EXTENDED_ARG         
1276: LOAD_CONST           'mv'
1278: MAP_ADD              
1280: EXTENDED_ARG         
1282: LOAD_CONST           13242
1284: EXTENDED_ARG         
1286: LOAD_CONST           'pw'
1288: MAP_ADD              
1290: DICT_UPDATE          
1292: BUILD_MAP            
1294: EXTENDED_ARG         
1296: LOAD_CONST           13243
1298: EXTENDED_ARG         
1300: LOAD_CONST           'nw'
1302: MAP_ADD              
1304: EXTENDED_ARG         
1306: LOAD_CONST           13244
1308: EXTENDED_ARG         
1310: LOAD_CONST           'μw'
1312: MAP_ADD              
1314: EXTENDED_ARG         
1316: LOAD_CONST           13245
1318: EXTENDED_ARG         
1320: LOAD_CONST           'mw'
1322: MAP_ADD              
1324: EXTENDED_ARG         
1326: LOAD_CONST           13246
1328: EXTENDED_ARG         
1330: LOAD_CONST           'kw'
1332: MAP_ADD              
1334: EXTENDED_ARG         
1336: LOAD_CONST           13247
1338: EXTENDED_ARG         
1340: LOAD_CONST           'mw'
1342: MAP_ADD              
1344: EXTENDED_ARG         
1346: LOAD_CONST           13248
1348: EXTENDED_ARG         
1350: LOAD_CONST           'kω'
1352: MAP_ADD              
1354: EXTENDED_ARG         
1356: LOAD_CONST           13249
1358: EXTENDED_ARG         
1360: LOAD_CONST           'mω'
1362: MAP_ADD              
1364: EXTENDED_ARG         
1366: LOAD_CONST           13251
1368: EXTENDED_ARG         
1370: LOAD_CONST           'bq'
1372: MAP_ADD              
1374: EXTENDED_ARG         
1376: LOAD_CONST           13254
1378: EXTENDED_ARG         
1380: LOAD_CONST           'c∕kg'
1382: MAP_ADD              
1384: EXTENDED_ARG         
1386: LOAD_CONST           13255
1388: EXTENDED_ARG         
1390: LOAD_CONST           'co.'
1392: MAP_ADD              
1394: EXTENDED_ARG         
1396: LOAD_CONST           13256
1398: EXTENDED_ARG         
1400: LOAD_CONST           'db'
1402: MAP_ADD              
1404: EXTENDED_ARG         
1406: LOAD_CONST           13257
1408: EXTENDED_ARG         
1410: LOAD_CONST           'gy'
1412: MAP_ADD              
1414: EXTENDED_ARG         
1416: LOAD_CONST           13259
1418: EXTENDED_ARG         
1420: LOAD_CONST           'hp'
1422: MAP_ADD              
1424: EXTENDED_ARG         
1426: LOAD_CONST           13261
1428: EXTENDED_ARG         
1430: LOAD_CONST           'kk'
1432: MAP_ADD              
1434: EXTENDED_ARG         
1436: LOAD_CONST           13262
1438: EXTENDED_ARG         
1440: LOAD_CONST           'km'
1442: MAP_ADD              
1444: EXTENDED_ARG         
1446: LOAD_CONST           13271
1448: EXTENDED_ARG         
1450: LOAD_CONST           'ph'
1452: MAP_ADD              
1454: EXTENDED_ARG         
1456: LOAD_CONST           13273
1458: EXTENDED_ARG         
1460: LOAD_CONST           'ppm'
1462: MAP_ADD              
1464: DICT_UPDATE          
1466: BUILD_MAP            
1468: EXTENDED_ARG         
1470: LOAD_CONST           13274
1472: EXTENDED_ARG         
1474: LOAD_CONST           'pr'
1476: MAP_ADD              
1478: EXTENDED_ARG         
1480: LOAD_CONST           13276
1482: EXTENDED_ARG         
1484: LOAD_CONST           'sv'
1486: MAP_ADD              
1488: EXTENDED_ARG         
1490: LOAD_CONST           13277
1492: EXTENDED_ARG         
1494: LOAD_CONST           'wb'
1496: MAP_ADD              
1498: EXTENDED_ARG         
1500: LOAD_CONST           64256
1502: EXTENDED_ARG         
1504: LOAD_CONST           'ff'
1506: MAP_ADD              
1508: EXTENDED_ARG         
1510: LOAD_CONST           64257
1512: EXTENDED_ARG         
1514: LOAD_CONST           'fi'
1516: MAP_ADD              
1518: EXTENDED_ARG         
1520: LOAD_CONST           64258
1522: EXTENDED_ARG         
1524: LOAD_CONST           'fl'
1526: MAP_ADD              
1528: EXTENDED_ARG         
1530: LOAD_CONST           64259
1532: EXTENDED_ARG         
1534: LOAD_CONST           'ffi'
1536: MAP_ADD              
1538: EXTENDED_ARG         
1540: LOAD_CONST           64260
1542: EXTENDED_ARG         
1544: LOAD_CONST           'ffl'
1546: MAP_ADD              
1548: EXTENDED_ARG         
1550: LOAD_CONST           64261
1552: EXTENDED_ARG         
1554: LOAD_CONST           'st'
1556: MAP_ADD              
1558: EXTENDED_ARG         
1560: LOAD_CONST           64262
1562: EXTENDED_ARG         
1564: LOAD_CONST           'st'
1566: MAP_ADD              
1568: EXTENDED_ARG         
1570: LOAD_CONST           64275
1572: EXTENDED_ARG         
1574: LOAD_CONST           'մն'
1576: MAP_ADD              
1578: EXTENDED_ARG         
1580: LOAD_CONST           64276
1582: EXTENDED_ARG         
1584: LOAD_CONST           'մե'
1586: MAP_ADD              
1588: EXTENDED_ARG         
1590: LOAD_CONST           64277
1592: EXTENDED_ARG         
1594: LOAD_CONST           'մի'
1596: MAP_ADD              
1598: EXTENDED_ARG         
1600: LOAD_CONST           64278
1602: EXTENDED_ARG         
1604: LOAD_CONST           'վն'
1606: MAP_ADD              
1608: EXTENDED_ARG         
1610: LOAD_CONST           64279
1612: EXTENDED_ARG         
1614: LOAD_CONST           'մխ'
1616: MAP_ADD              
1618: EXTENDED_ARG         
1620: LOAD_CONST           119808
1622: EXTENDED_ARG         
1624: LOAD_CONST           'a'
1626: MAP_ADD              
1628: EXTENDED_ARG         
1630: LOAD_CONST           119809
1632: LOAD_CONST           'b'
1634: MAP_ADD              
1636: DICT_UPDATE          
1638: BUILD_MAP            
1640: EXTENDED_ARG         
1642: LOAD_CONST           119810
1644: LOAD_CONST           'c'
1646: MAP_ADD              
1648: EXTENDED_ARG         
1650: LOAD_CONST           119811
1652: LOAD_CONST           'd'
1654: MAP_ADD              
1656: EXTENDED_ARG         
1658: LOAD_CONST           119812
1660: LOAD_CONST           'e'
1662: MAP_ADD              
1664: EXTENDED_ARG         
1666: LOAD_CONST           119813
1668: LOAD_CONST           'f'
1670: MAP_ADD              
1672: EXTENDED_ARG         
1674: LOAD_CONST           119814
1676: EXTENDED_ARG         
1678: LOAD_CONST           'g'
1680: MAP_ADD              
1682: EXTENDED_ARG         
1684: LOAD_CONST           119815
1686: LOAD_CONST           'h'
1688: MAP_ADD              
1690: EXTENDED_ARG         
1692: LOAD_CONST           119816
1694: LOAD_CONST           'i'
1696: MAP_ADD              
1698: EXTENDED_ARG         
1700: LOAD_CONST           119817
1702: EXTENDED_ARG         
1704: LOAD_CONST           'j'
1706: MAP_ADD              
1708: EXTENDED_ARG         
1710: LOAD_CONST           119818
1712: EXTENDED_ARG         
1714: LOAD_CONST           'k'
1716: MAP_ADD              
1718: EXTENDED_ARG         
1720: LOAD_CONST           119819
1722: LOAD_CONST           'l'
1724: MAP_ADD              
1726: EXTENDED_ARG         
1728: LOAD_CONST           119820
1730: LOAD_CONST           'm'
1732: MAP_ADD              
1734: EXTENDED_ARG         
1736: LOAD_CONST           119821
1738: LOAD_CONST           'n'
1740: MAP_ADD              
1742: EXTENDED_ARG         
1744: LOAD_CONST           119822
1746: EXTENDED_ARG         
1748: LOAD_CONST           'o'
1750: MAP_ADD              
1752: EXTENDED_ARG         
1754: LOAD_CONST           119823
1756: LOAD_CONST           'p'
1758: MAP_ADD              
1760: EXTENDED_ARG         
1762: LOAD_CONST           119824
1764: LOAD_CONST           'q'
1766: MAP_ADD              
1768: EXTENDED_ARG         
1770: LOAD_CONST           119825
1772: LOAD_CONST           'r'
1774: MAP_ADD              
1776: EXTENDED_ARG         
1778: LOAD_CONST           119826
1780: LOAD_CONST           's'
1782: MAP_ADD              
1784: DICT_UPDATE          
1786: BUILD_MAP            
1788: EXTENDED_ARG         
1790: LOAD_CONST           119827
1792: EXTENDED_ARG         
1794: LOAD_CONST           't'
1796: MAP_ADD              
1798: EXTENDED_ARG         
1800: LOAD_CONST           119828
1802: EXTENDED_ARG         
1804: LOAD_CONST           'u'
1806: MAP_ADD              
1808: EXTENDED_ARG         
1810: LOAD_CONST           119829
1812: EXTENDED_ARG         
1814: LOAD_CONST           'v'
1816: MAP_ADD              
1818: EXTENDED_ARG         
1820: LOAD_CONST           119830
1822: EXTENDED_ARG         
1824: LOAD_CONST           'w'
1826: MAP_ADD              
1828: EXTENDED_ARG         
1830: LOAD_CONST           119831
1832: EXTENDED_ARG         
1834: LOAD_CONST           'x'
1836: MAP_ADD              
1838: EXTENDED_ARG         
1840: LOAD_CONST           119832
1842: EXTENDED_ARG         
1844: LOAD_CONST           'y'
1846: MAP_ADD              
1848: EXTENDED_ARG         
1850: LOAD_CONST           119833
1852: LOAD_CONST           'z'
1854: MAP_ADD              
1856: EXTENDED_ARG         
1858: LOAD_CONST           119860
1860: EXTENDED_ARG         
1862: LOAD_CONST           'a'
1864: MAP_ADD              
1866: EXTENDED_ARG         
1868: LOAD_CONST           119861
1870: LOAD_CONST           'b'
1872: MAP_ADD              
1874: EXTENDED_ARG         
1876: LOAD_CONST           119862
1878: LOAD_CONST           'c'
1880: MAP_ADD              
1882: EXTENDED_ARG         
1884: LOAD_CONST           119863
1886: LOAD_CONST           'd'
1888: MAP_ADD              
1890: EXTENDED_ARG         
1892: LOAD_CONST           119864
1894: LOAD_CONST           'e'
1896: MAP_ADD              
1898: EXTENDED_ARG         
1900: LOAD_CONST           119865
1902: LOAD_CONST           'f'
1904: MAP_ADD              
1906: EXTENDED_ARG         
1908: LOAD_CONST           119866
1910: EXTENDED_ARG         
1912: LOAD_CONST           'g'
1914: MAP_ADD              
1916: EXTENDED_ARG         
1918: LOAD_CONST           119867
1920: LOAD_CONST           'h'
1922: MAP_ADD              
1924: EXTENDED_ARG         
1926: LOAD_CONST           119868
1928: LOAD_CONST           'i'
1930: MAP_ADD              
1932: EXTENDED_ARG         
1934: LOAD_CONST           119869
1936: EXTENDED_ARG         
1938: LOAD_CONST           'j'
1940: MAP_ADD              
1942: DICT_UPDATE          
1944: BUILD_MAP            
1946: EXTENDED_ARG         
1948: LOAD_CONST           119870
1950: EXTENDED_ARG         
1952: LOAD_CONST           'k'
1954: MAP_ADD              
1956: EXTENDED_ARG         
1958: LOAD_CONST           119871
1960: LOAD_CONST           'l'
1962: MAP_ADD              
1964: EXTENDED_ARG         
1966: LOAD_CONST           119872
1968: LOAD_CONST           'm'
1970: MAP_ADD              
1972: EXTENDED_ARG         
1974: LOAD_CONST           119873
1976: LOAD_CONST           'n'
1978: MAP_ADD              
1980: EXTENDED_ARG         
1982: LOAD_CONST           119874
1984: EXTENDED_ARG         
1986: LOAD_CONST           'o'
1988: MAP_ADD              
1990: EXTENDED_ARG         
1992: LOAD_CONST           119875
1994: LOAD_CONST           'p'
1996: MAP_ADD              
1998: EXTENDED_ARG         
2000: LOAD_CONST           119876
2002: LOAD_CONST           'q'
2004: MAP_ADD              
2006: EXTENDED_ARG         
2008: LOAD_CONST           119877
2010: LOAD_CONST           'r'
2012: MAP_ADD              
2014: EXTENDED_ARG         
2016: LOAD_CONST           119878
2018: LOAD_CONST           's'
2020: MAP_ADD              
2022: EXTENDED_ARG         
2024: LOAD_CONST           119879
2026: EXTENDED_ARG         
2028: LOAD_CONST           't'
2030: MAP_ADD              
2032: EXTENDED_ARG         
2034: LOAD_CONST           119880
2036: EXTENDED_ARG         
2038: LOAD_CONST           'u'
2040: MAP_ADD              
2042: EXTENDED_ARG         
2044: LOAD_CONST           119881
2046: EXTENDED_ARG         
2048: LOAD_CONST           'v'
2050: MAP_ADD              
2052: EXTENDED_ARG         
2054: LOAD_CONST           119882
2056: EXTENDED_ARG         
2058: LOAD_CONST           'w'
2060: MAP_ADD              
2062: EXTENDED_ARG         
2064: LOAD_CONST           119883
2066: EXTENDED_ARG         
2068: LOAD_CONST           'x'
2070: MAP_ADD              
2072: EXTENDED_ARG         
2074: LOAD_CONST           119884
2076: EXTENDED_ARG         
2078: LOAD_CONST           'y'
2080: MAP_ADD              
2082: EXTENDED_ARG         
2084: LOAD_CONST           119885
2086: LOAD_CONST           'z'
2088: MAP_ADD              
2090: EXTENDED_ARG         
2092: LOAD_CONST           119912
2094: EXTENDED_ARG         
2096: LOAD_CONST           'a'
2098: MAP_ADD              
2100: DICT_UPDATE          
2102: BUILD_MAP            
2104: EXTENDED_ARG         
2106: LOAD_CONST           119913
2108: LOAD_CONST           'b'
2110: MAP_ADD              
2112: EXTENDED_ARG         
2114: LOAD_CONST           119914
2116: LOAD_CONST           'c'
2118: MAP_ADD              
2120: EXTENDED_ARG         
2122: LOAD_CONST           119915
2124: LOAD_CONST           'd'
2126: MAP_ADD              
2128: EXTENDED_ARG         
2130: LOAD_CONST           119916
2132: LOAD_CONST           'e'
2134: MAP_ADD              
2136: EXTENDED_ARG         
2138: LOAD_CONST           119917
2140: LOAD_CONST           'f'
2142: MAP_ADD              
2144: EXTENDED_ARG         
2146: LOAD_CONST           119918
2148: EXTENDED_ARG         
2150: LOAD_CONST           'g'
2152: MAP_ADD              
2154: EXTENDED_ARG         
2156: LOAD_CONST           119919
2158: LOAD_CONST           'h'
2160: MAP_ADD              
2162: EXTENDED_ARG         
2164: LOAD_CONST           119920
2166: LOAD_CONST           'i'
2168: MAP_ADD              
2170: EXTENDED_ARG         
2172: LOAD_CONST           119921
2174: EXTENDED_ARG         
2176: LOAD_CONST           'j'
2178: MAP_ADD              
2180: EXTENDED_ARG         
2182: LOAD_CONST           119922
2184: EXTENDED_ARG         
2186: LOAD_CONST           'k'
2188: MAP_ADD              
2190: EXTENDED_ARG         
2192: LOAD_CONST           119923
2194: LOAD_CONST           'l'
2196: MAP_ADD              
2198: EXTENDED_ARG         
2200: LOAD_CONST           119924
2202: LOAD_CONST           'm'
2204: MAP_ADD              
2206: EXTENDED_ARG         
2208: LOAD_CONST           119925
2210: LOAD_CONST           'n'
2212: MAP_ADD              
2214: EXTENDED_ARG         
2216: LOAD_CONST           119926
2218: EXTENDED_ARG         
2220: LOAD_CONST           'o'
2222: MAP_ADD              
2224: EXTENDED_ARG         
2226: LOAD_CONST           119927
2228: LOAD_CONST           'p'
2230: MAP_ADD              
2232: EXTENDED_ARG         
2234: LOAD_CONST           119928
2236: LOAD_CONST           'q'
2238: MAP_ADD              
2240: EXTENDED_ARG         
2242: LOAD_CONST           119929
2244: LOAD_CONST           'r'
2246: MAP_ADD              
2248: DICT_UPDATE          
2250: BUILD_MAP            
2252: EXTENDED_ARG         
2254: LOAD_CONST           119930
2256: LOAD_CONST           's'
2258: MAP_ADD              
2260: EXTENDED_ARG         
2262: LOAD_CONST           119931
2264: EXTENDED_ARG         
2266: LOAD_CONST           't'
2268: MAP_ADD              
2270: EXTENDED_ARG         
2272: LOAD_CONST           119932
2274: EXTENDED_ARG         
2276: LOAD_CONST           'u'
2278: MAP_ADD              
2280: EXTENDED_ARG         
2282: LOAD_CONST           119933
2284: EXTENDED_ARG         
2286: LOAD_CONST           'v'
2288: MAP_ADD              
2290: EXTENDED_ARG         
2292: LOAD_CONST           119934
2294: EXTENDED_ARG         
2296: LOAD_CONST           'w'
2298: MAP_ADD              
2300: EXTENDED_ARG         
2302: LOAD_CONST           119935
2304: EXTENDED_ARG         
2306: LOAD_CONST           'x'
2308: MAP_ADD              
2310: EXTENDED_ARG         
2312: LOAD_CONST           119936
2314: EXTENDED_ARG         
2316: LOAD_CONST           'y'
2318: MAP_ADD              
2320: EXTENDED_ARG         
2322: LOAD_CONST           119937
2324: LOAD_CONST           'z'
2326: MAP_ADD              
2328: EXTENDED_ARG         
2330: LOAD_CONST           119964
2332: EXTENDED_ARG         
2334: LOAD_CONST           'a'
2336: MAP_ADD              
2338: EXTENDED_ARG         
2340: LOAD_CONST           119966
2342: LOAD_CONST           'c'
2344: MAP_ADD              
2346: EXTENDED_ARG         
2348: LOAD_CONST           119967
2350: LOAD_CONST           'd'
2352: MAP_ADD              
2354: EXTENDED_ARG         
2356: LOAD_CONST           119970
2358: EXTENDED_ARG         
2360: LOAD_CONST           'g'
2362: MAP_ADD              
2364: EXTENDED_ARG         
2366: LOAD_CONST           119973
2368: EXTENDED_ARG         
2370: LOAD_CONST           'j'
2372: MAP_ADD              
2374: EXTENDED_ARG         
2376: LOAD_CONST           119974
2378: EXTENDED_ARG         
2380: LOAD_CONST           'k'
2382: MAP_ADD              
2384: EXTENDED_ARG         
2386: LOAD_CONST           119977
2388: LOAD_CONST           'n'
2390: MAP_ADD              
2392: EXTENDED_ARG         
2394: LOAD_CONST           119978
2396: EXTENDED_ARG         
2398: LOAD_CONST           'o'
2400: MAP_ADD              
2402: EXTENDED_ARG         
2404: LOAD_CONST           119979
2406: LOAD_CONST           'p'
2408: MAP_ADD              
2410: DICT_UPDATE          
2412: BUILD_MAP            
2414: EXTENDED_ARG         
2416: LOAD_CONST           119980
2418: LOAD_CONST           'q'
2420: MAP_ADD              
2422: EXTENDED_ARG         
2424: LOAD_CONST           119982
2426: LOAD_CONST           's'
2428: MAP_ADD              
2430: EXTENDED_ARG         
2432: LOAD_CONST           119983
2434: EXTENDED_ARG         
2436: LOAD_CONST           't'
2438: MAP_ADD              
2440: EXTENDED_ARG         
2442: LOAD_CONST           119984
2444: EXTENDED_ARG         
2446: LOAD_CONST           'u'
2448: MAP_ADD              
2450: EXTENDED_ARG         
2452: LOAD_CONST           119985
2454: EXTENDED_ARG         
2456: LOAD_CONST           'v'
2458: MAP_ADD              
2460: EXTENDED_ARG         
2462: LOAD_CONST           119986
2464: EXTENDED_ARG         
2466: LOAD_CONST           'w'
2468: MAP_ADD              
2470: EXTENDED_ARG         
2472: LOAD_CONST           119987
2474: EXTENDED_ARG         
2476: LOAD_CONST           'x'
2478: MAP_ADD              
2480: EXTENDED_ARG         
2482: LOAD_CONST           119988
2484: EXTENDED_ARG         
2486: LOAD_CONST           'y'
2488: MAP_ADD              
2490: EXTENDED_ARG         
2492: LOAD_CONST           119989
2494: LOAD_CONST           'z'
2496: MAP_ADD              
2498: EXTENDED_ARG         
2500: LOAD_CONST           120016
2502: EXTENDED_ARG         
2504: LOAD_CONST           'a'
2506: MAP_ADD              
2508: EXTENDED_ARG         
2510: LOAD_CONST           120017
2512: LOAD_CONST           'b'
2514: MAP_ADD              
2516: EXTENDED_ARG         
2518: LOAD_CONST           120018
2520: LOAD_CONST           'c'
2522: MAP_ADD              
2524: EXTENDED_ARG         
2526: LOAD_CONST           120019
2528: LOAD_CONST           'd'
2530: MAP_ADD              
2532: EXTENDED_ARG         
2534: LOAD_CONST           120020
2536: LOAD_CONST           'e'
2538: MAP_ADD              
2540: EXTENDED_ARG         
2542: LOAD_CONST           120021
2544: LOAD_CONST           'f'
2546: MAP_ADD              
2548: EXTENDED_ARG         
2550: LOAD_CONST           120022
2552: EXTENDED_ARG         
2554: LOAD_CONST           'g'
2556: MAP_ADD              
2558: EXTENDED_ARG         
2560: LOAD_CONST           120023
2562: LOAD_CONST           'h'
2564: MAP_ADD              
2566: DICT_UPDATE          
2568: BUILD_MAP            
2570: EXTENDED_ARG         
2572: LOAD_CONST           120024
2574: LOAD_CONST           'i'
2576: MAP_ADD              
2578: EXTENDED_ARG         
2580: LOAD_CONST           120025
2582: EXTENDED_ARG         
2584: LOAD_CONST           'j'
2586: MAP_ADD              
2588: EXTENDED_ARG         
2590: LOAD_CONST           120026
2592: EXTENDED_ARG         
2594: LOAD_CONST           'k'
2596: MAP_ADD              
2598: EXTENDED_ARG         
2600: LOAD_CONST           120027
2602: LOAD_CONST           'l'
2604: MAP_ADD              
2606: EXTENDED_ARG         
2608: LOAD_CONST           120028
2610: LOAD_CONST           'm'
2612: MAP_ADD              
2614: EXTENDED_ARG         
2616: LOAD_CONST           120029
2618: LOAD_CONST           'n'
2620: MAP_ADD              
2622: EXTENDED_ARG         
2624: LOAD_CONST           120030
2626: EXTENDED_ARG         
2628: LOAD_CONST           'o'
2630: MAP_ADD              
2632: EXTENDED_ARG         
2634: LOAD_CONST           120031
2636: LOAD_CONST           'p'
2638: MAP_ADD              
2640: EXTENDED_ARG         
2642: LOAD_CONST           120032
2644: LOAD_CONST           'q'
2646: MAP_ADD              
2648: EXTENDED_ARG         
2650: LOAD_CONST           120033
2652: LOAD_CONST           'r'
2654: MAP_ADD              
2656: EXTENDED_ARG         
2658: LOAD_CONST           120034
2660: LOAD_CONST           's'
2662: MAP_ADD              
2664: EXTENDED_ARG         
2666: LOAD_CONST           120035
2668: EXTENDED_ARG         
2670: LOAD_CONST           't'
2672: MAP_ADD              
2674: EXTENDED_ARG         
2676: LOAD_CONST           120036
2678: EXTENDED_ARG         
2680: LOAD_CONST           'u'
2682: MAP_ADD              
2684: EXTENDED_ARG         
2686: LOAD_CONST           120037
2688: EXTENDED_ARG         
2690: LOAD_CONST           'v'
2692: MAP_ADD              
2694: EXTENDED_ARG         
2696: LOAD_CONST           120038
2698: EXTENDED_ARG         
2700: LOAD_CONST           'w'
2702: MAP_ADD              
2704: EXTENDED_ARG         
2706: LOAD_CONST           120039
2708: EXTENDED_ARG         
2710: LOAD_CONST           'x'
2712: MAP_ADD              
2714: EXTENDED_ARG         
2716: LOAD_CONST           120040
2718: EXTENDED_ARG         
2720: LOAD_CONST           'y'
2722: MAP_ADD              
2724: DICT_UPDATE          
2726: BUILD_MAP            
2728: EXTENDED_ARG         
2730: LOAD_CONST           120041
2732: LOAD_CONST           'z'
2734: MAP_ADD              
2736: EXTENDED_ARG         
2738: LOAD_CONST           120068
2740: EXTENDED_ARG         
2742: LOAD_CONST           'a'
2744: MAP_ADD              
2746: EXTENDED_ARG         
2748: LOAD_CONST           120069
2750: LOAD_CONST           'b'
2752: MAP_ADD              
2754: EXTENDED_ARG         
2756: LOAD_CONST           120071
2758: LOAD_CONST           'd'
2760: MAP_ADD              
2762: EXTENDED_ARG         
2764: LOAD_CONST           120072
2766: LOAD_CONST           'e'
2768: MAP_ADD              
2770: EXTENDED_ARG         
2772: LOAD_CONST           120073
2774: LOAD_CONST           'f'
2776: MAP_ADD              
2778: EXTENDED_ARG         
2780: LOAD_CONST           120074
2782: EXTENDED_ARG         
2784: LOAD_CONST           'g'
2786: MAP_ADD              
2788: EXTENDED_ARG         
2790: LOAD_CONST           120077
2792: EXTENDED_ARG         
2794: LOAD_CONST           'j'
2796: MAP_ADD              
2798: EXTENDED_ARG         
2800: LOAD_CONST           120078
2802: EXTENDED_ARG         
2804: LOAD_CONST           'k'
2806: MAP_ADD              
2808: EXTENDED_ARG         
2810: LOAD_CONST           120079
2812: LOAD_CONST           'l'
2814: MAP_ADD              
2816: EXTENDED_ARG         
2818: LOAD_CONST           120080
2820: LOAD_CONST           'm'
2822: MAP_ADD              
2824: EXTENDED_ARG         
2826: LOAD_CONST           120081
2828: LOAD_CONST           'n'
2830: MAP_ADD              
2832: EXTENDED_ARG         
2834: LOAD_CONST           120082
2836: EXTENDED_ARG         
2838: LOAD_CONST           'o'
2840: MAP_ADD              
2842: EXTENDED_ARG         
2844: LOAD_CONST           120083
2846: LOAD_CONST           'p'
2848: MAP_ADD              
2850: EXTENDED_ARG         
2852: LOAD_CONST           120084
2854: LOAD_CONST           'q'
2856: MAP_ADD              
2858: EXTENDED_ARG         
2860: LOAD_CONST           120086
2862: LOAD_CONST           's'
2864: MAP_ADD              
2866: EXTENDED_ARG         
2868: LOAD_CONST           120087
2870: EXTENDED_ARG         
2872: LOAD_CONST           't'
2874: MAP_ADD              
2876: DICT_UPDATE          
2878: BUILD_MAP            
2880: EXTENDED_ARG         
2882: LOAD_CONST           120088
2884: EXTENDED_ARG         
2886: LOAD_CONST           'u'
2888: MAP_ADD              
2890: EXTENDED_ARG         
2892: LOAD_CONST           120089
2894: EXTENDED_ARG         
2896: LOAD_CONST           'v'
2898: MAP_ADD              
2900: EXTENDED_ARG         
2902: LOAD_CONST           120090
2904: EXTENDED_ARG         
2906: LOAD_CONST           'w'
2908: MAP_ADD              
2910: EXTENDED_ARG         
2912: LOAD_CONST           120091
2914: EXTENDED_ARG         
2916: LOAD_CONST           'x'
2918: MAP_ADD              
2920: EXTENDED_ARG         
2922: LOAD_CONST           120092
2924: EXTENDED_ARG         
2926: LOAD_CONST           'y'
2928: MAP_ADD              
2930: EXTENDED_ARG         
2932: LOAD_CONST           120120
2934: EXTENDED_ARG         
2936: LOAD_CONST           'a'
2938: MAP_ADD              
2940: EXTENDED_ARG         
2942: LOAD_CONST           120121
2944: LOAD_CONST           'b'
2946: MAP_ADD              
2948: EXTENDED_ARG         
2950: LOAD_CONST           120123
2952: LOAD_CONST           'd'
2954: MAP_ADD              
2956: EXTENDED_ARG         
2958: LOAD_CONST           120124
2960: LOAD_CONST           'e'
2962: MAP_ADD              
2964: EXTENDED_ARG         
2966: LOAD_CONST           120125
2968: LOAD_CONST           'f'
2970: MAP_ADD              
2972: EXTENDED_ARG         
2974: LOAD_CONST           120126
2976: EXTENDED_ARG         
2978: LOAD_CONST           'g'
2980: MAP_ADD              
2982: EXTENDED_ARG         
2984: LOAD_CONST           120128
2986: LOAD_CONST           'i'
2988: MAP_ADD              
2990: EXTENDED_ARG         
2992: LOAD_CONST           120129
2994: EXTENDED_ARG         
2996: LOAD_CONST           'j'
2998: MAP_ADD              
3000: EXTENDED_ARG         
3002: LOAD_CONST           120130
3004: EXTENDED_ARG         
3006: LOAD_CONST           'k'
3008: MAP_ADD              
3010: EXTENDED_ARG         
3012: LOAD_CONST           120131
3014: LOAD_CONST           'l'
3016: MAP_ADD              
3018: EXTENDED_ARG         
3020: LOAD_CONST           120132
3022: LOAD_CONST           'm'
3024: MAP_ADD              
3026: EXTENDED_ARG         
3028: LOAD_CONST           120134
3030: EXTENDED_ARG         
3032: LOAD_CONST           'o'
3034: MAP_ADD              
3036: DICT_UPDATE          
3038: BUILD_MAP            
3040: EXTENDED_ARG         
3042: LOAD_CONST           120138
3044: LOAD_CONST           's'
3046: MAP_ADD              
3048: EXTENDED_ARG         
3050: LOAD_CONST           120139
3052: EXTENDED_ARG         
3054: LOAD_CONST           't'
3056: MAP_ADD              
3058: EXTENDED_ARG         
3060: LOAD_CONST           120140
3062: EXTENDED_ARG         
3064: LOAD_CONST           'u'
3066: MAP_ADD              
3068: EXTENDED_ARG         
3070: LOAD_CONST           120141
3072: EXTENDED_ARG         
3074: LOAD_CONST           'v'
3076: MAP_ADD              
3078: EXTENDED_ARG         
3080: LOAD_CONST           120142
3082: EXTENDED_ARG         
3084: LOAD_CONST           'w'
3086: MAP_ADD              
3088: EXTENDED_ARG         
3090: LOAD_CONST           120143
3092: EXTENDED_ARG         
3094: LOAD_CONST           'x'
3096: MAP_ADD              
3098: EXTENDED_ARG         
3100: LOAD_CONST           120144
3102: EXTENDED_ARG         
3104: LOAD_CONST           'y'
3106: MAP_ADD              
3108: EXTENDED_ARG         
3110: LOAD_CONST           120172
3112: EXTENDED_ARG         
3114: LOAD_CONST           'a'
3116: MAP_ADD              
3118: EXTENDED_ARG         
3120: LOAD_CONST           120173
3122: LOAD_CONST           'b'
3124: MAP_ADD              
3126: EXTENDED_ARG         
3128: LOAD_CONST           120174
3130: LOAD_CONST           'c'
3132: MAP_ADD              
3134: EXTENDED_ARG         
3136: LOAD_CONST           120175
3138: LOAD_CONST           'd'
3140: MAP_ADD              
3142: EXTENDED_ARG         
3144: LOAD_CONST           120176
3146: LOAD_CONST           'e'
3148: MAP_ADD              
3150: EXTENDED_ARG         
3152: LOAD_CONST           120177
3154: LOAD_CONST           'f'
3156: MAP_ADD              
3158: EXTENDED_ARG         
3160: LOAD_CONST           120178
3162: EXTENDED_ARG         
3164: LOAD_CONST           'g'
3166: MAP_ADD              
3168: EXTENDED_ARG         
3170: LOAD_CONST           120179
3172: LOAD_CONST           'h'
3174: MAP_ADD              
3176: EXTENDED_ARG         
3178: LOAD_CONST           120180
3180: LOAD_CONST           'i'
3182: MAP_ADD              
3184: EXTENDED_ARG         
3186: LOAD_CONST           120181
3188: EXTENDED_ARG         
3190: LOAD_CONST           'j'
3192: MAP_ADD              
3194: DICT_UPDATE          
3196: BUILD_MAP            
3198: EXTENDED_ARG         
3200: LOAD_CONST           120182
3202: EXTENDED_ARG         
3204: LOAD_CONST           'k'
3206: MAP_ADD              
3208: EXTENDED_ARG         
3210: LOAD_CONST           120183
3212: LOAD_CONST           'l'
3214: MAP_ADD              
3216: EXTENDED_ARG         
3218: LOAD_CONST           120184
3220: LOAD_CONST           'm'
3222: MAP_ADD              
3224: EXTENDED_ARG         
3226: LOAD_CONST           120185
3228: LOAD_CONST           'n'
3230: MAP_ADD              
3232: EXTENDED_ARG         
3234: LOAD_CONST           120186
3236: EXTENDED_ARG         
3238: LOAD_CONST           'o'
3240: MAP_ADD              
3242: EXTENDED_ARG         
3244: LOAD_CONST           120187
3246: LOAD_CONST           'p'
3248: MAP_ADD              
3250: EXTENDED_ARG         
3252: LOAD_CONST           120188
3254: LOAD_CONST           'q'
3256: MAP_ADD              
3258: EXTENDED_ARG         
3260: LOAD_CONST           120189
3262: LOAD_CONST           'r'
3264: MAP_ADD              
3266: EXTENDED_ARG         
3268: LOAD_CONST           120190
3270: LOAD_CONST           's'
3272: MAP_ADD              
3274: EXTENDED_ARG         
3276: LOAD_CONST           120191
3278: EXTENDED_ARG         
3280: LOAD_CONST           't'
3282: MAP_ADD              
3284: EXTENDED_ARG         
3286: LOAD_CONST           120192
3288: EXTENDED_ARG         
3290: LOAD_CONST           'u'
3292: MAP_ADD              
3294: EXTENDED_ARG         
3296: LOAD_CONST           120193
3298: EXTENDED_ARG         
3300: LOAD_CONST           'v'
3302: MAP_ADD              
3304: EXTENDED_ARG         
3306: LOAD_CONST           120194
3308: EXTENDED_ARG         
3310: LOAD_CONST           'w'
3312: MAP_ADD              
3314: EXTENDED_ARG         
3316: LOAD_CONST           120195
3318: EXTENDED_ARG         
3320: LOAD_CONST           'x'
3322: MAP_ADD              
3324: EXTENDED_ARG         
3326: LOAD_CONST           120196
3328: EXTENDED_ARG         
3330: LOAD_CONST           'y'
3332: MAP_ADD              
3334: EXTENDED_ARG         
3336: LOAD_CONST           120197
3338: LOAD_CONST           'z'
3340: MAP_ADD              
3342: EXTENDED_ARG         
3344: LOAD_CONST           120224
3346: EXTENDED_ARG         
3348: LOAD_CONST           'a'
3350: MAP_ADD              
3352: DICT_UPDATE          
3354: BUILD_MAP            
3356: EXTENDED_ARG         
3358: LOAD_CONST           120225
3360: LOAD_CONST           'b'
3362: MAP_ADD              
3364: EXTENDED_ARG         
3366: LOAD_CONST           120226
3368: LOAD_CONST           'c'
3370: MAP_ADD              
3372: EXTENDED_ARG         
3374: LOAD_CONST           120227
3376: LOAD_CONST           'd'
3378: MAP_ADD              
3380: EXTENDED_ARG         
3382: LOAD_CONST           120228
3384: LOAD_CONST           'e'
3386: MAP_ADD              
3388: EXTENDED_ARG         
3390: LOAD_CONST           120229
3392: LOAD_CONST           'f'
3394: MAP_ADD              
3396: EXTENDED_ARG         
3398: LOAD_CONST           120230
3400: EXTENDED_ARG         
3402: LOAD_CONST           'g'
3404: MAP_ADD              
3406: EXTENDED_ARG         
3408: LOAD_CONST           120231
3410: LOAD_CONST           'h'
3412: MAP_ADD              
3414: EXTENDED_ARG         
3416: LOAD_CONST           120232
3418: LOAD_CONST           'i'
3420: MAP_ADD              
3422: EXTENDED_ARG         
3424: LOAD_CONST           120233
3426: EXTENDED_ARG         
3428: LOAD_CONST           'j'
3430: MAP_ADD              
3432: EXTENDED_ARG         
3434: LOAD_CONST           120234
3436: EXTENDED_ARG         
3438: LOAD_CONST           'k'
3440: MAP_ADD              
3442: EXTENDED_ARG         
3444: LOAD_CONST           120235
3446: LOAD_CONST           'l'
3448: MAP_ADD              
3450: EXTENDED_ARG         
3452: LOAD_CONST           120236
3454: LOAD_CONST           'm'
3456: MAP_ADD              
3458: EXTENDED_ARG         
3460: LOAD_CONST           120237
3462: LOAD_CONST           'n'
3464: MAP_ADD              
3466: EXTENDED_ARG         
3468: LOAD_CONST           120238
3470: EXTENDED_ARG         
3472: LOAD_CONST           'o'
3474: MAP_ADD              
3476: EXTENDED_ARG         
3478: LOAD_CONST           120239
3480: LOAD_CONST           'p'
3482: MAP_ADD              
3484: EXTENDED_ARG         
3486: LOAD_CONST           120240
3488: LOAD_CONST           'q'
3490: MAP_ADD              
3492: EXTENDED_ARG         
3494: LOAD_CONST           120241
3496: LOAD_CONST           'r'
3498: MAP_ADD              
3500: DICT_UPDATE          
3502: BUILD_MAP            
3504: EXTENDED_ARG         
3506: LOAD_CONST           120242
3508: LOAD_CONST           's'
3510: MAP_ADD              
3512: EXTENDED_ARG         
3514: LOAD_CONST           120243
3516: EXTENDED_ARG         
3518: LOAD_CONST           't'
3520: MAP_ADD              
3522: EXTENDED_ARG         
3524: LOAD_CONST           120244
3526: EXTENDED_ARG         
3528: LOAD_CONST           'u'
3530: MAP_ADD              
3532: EXTENDED_ARG         
3534: LOAD_CONST           120245
3536: EXTENDED_ARG         
3538: LOAD_CONST           'v'
3540: MAP_ADD              
3542: EXTENDED_ARG         
3544: LOAD_CONST           120246
3546: EXTENDED_ARG         
3548: LOAD_CONST           'w'
3550: MAP_ADD              
3552: EXTENDED_ARG         
3554: LOAD_CONST           120247
3556: EXTENDED_ARG         
3558: LOAD_CONST           'x'
3560: MAP_ADD              
3562: EXTENDED_ARG         
3564: LOAD_CONST           120248
3566: EXTENDED_ARG         
3568: LOAD_CONST           'y'
3570: MAP_ADD              
3572: EXTENDED_ARG         
3574: LOAD_CONST           120249
3576: LOAD_CONST           'z'
3578: MAP_ADD              
3580: EXTENDED_ARG         
3582: LOAD_CONST           120276
3584: EXTENDED_ARG         
3586: LOAD_CONST           'a'
3588: MAP_ADD              
3590: EXTENDED_ARG         
3592: LOAD_CONST           120277
3594: LOAD_CONST           'b'
3596: MAP_ADD              
3598: EXTENDED_ARG         
3600: LOAD_CONST           120278
3602: LOAD_CONST           'c'
3604: MAP_ADD              
3606: EXTENDED_ARG         
3608: LOAD_CONST           120279
3610: LOAD_CONST           'd'
3612: MAP_ADD              
3614: EXTENDED_ARG         
3616: LOAD_CONST           120280
3618: LOAD_CONST           'e'
3620: MAP_ADD              
3622: EXTENDED_ARG         
3624: LOAD_CONST           120281
3626: LOAD_CONST           'f'
3628: MAP_ADD              
3630: EXTENDED_ARG         
3632: LOAD_CONST           120282
3634: EXTENDED_ARG         
3636: LOAD_CONST           'g'
3638: MAP_ADD              
3640: EXTENDED_ARG         
3642: LOAD_CONST           120283
3644: LOAD_CONST           'h'
3646: MAP_ADD              
3648: EXTENDED_ARG         
3650: LOAD_CONST           120284
3652: LOAD_CONST           'i'
3654: MAP_ADD              
3656: DICT_UPDATE          
3658: BUILD_MAP            
3660: EXTENDED_ARG         
3662: LOAD_CONST           120285
3664: EXTENDED_ARG         
3666: LOAD_CONST           'j'
3668: MAP_ADD              
3670: EXTENDED_ARG         
3672: LOAD_CONST           120286
3674: EXTENDED_ARG         
3676: LOAD_CONST           'k'
3678: MAP_ADD              
3680: EXTENDED_ARG         
3682: LOAD_CONST           120287
3684: LOAD_CONST           'l'
3686: MAP_ADD              
3688: EXTENDED_ARG         
3690: LOAD_CONST           120288
3692: LOAD_CONST           'm'
3694: MAP_ADD              
3696: EXTENDED_ARG         
3698: LOAD_CONST           120289
3700: LOAD_CONST           'n'
3702: MAP_ADD              
3704: EXTENDED_ARG         
3706: LOAD_CONST           120290
3708: EXTENDED_ARG         
3710: LOAD_CONST           'o'
3712: MAP_ADD              
3714: EXTENDED_ARG         
3716: LOAD_CONST           120291
3718: LOAD_CONST           'p'
3720: MAP_ADD              
3722: EXTENDED_ARG         
3724: LOAD_CONST           120292
3726: LOAD_CONST           'q'
3728: MAP_ADD              
3730: EXTENDED_ARG         
3732: LOAD_CONST           120293
3734: LOAD_CONST           'r'
3736: MAP_ADD              
3738: EXTENDED_ARG         
3740: LOAD_CONST           120294
3742: LOAD_CONST           's'
3744: MAP_ADD              
3746: EXTENDED_ARG         
3748: LOAD_CONST           120295
3750: EXTENDED_ARG         
3752: LOAD_CONST           't'
3754: MAP_ADD              
3756: EXTENDED_ARG         
3758: LOAD_CONST           120296
3760: EXTENDED_ARG         
3762: LOAD_CONST           'u'
3764: MAP_ADD              
3766: EXTENDED_ARG         
3768: LOAD_CONST           120297
3770: EXTENDED_ARG         
3772: LOAD_CONST           'v'
3774: MAP_ADD              
3776: EXTENDED_ARG         
3778: LOAD_CONST           120298
3780: EXTENDED_ARG         
3782: LOAD_CONST           'w'
3784: MAP_ADD              
3786: EXTENDED_ARG         
3788: LOAD_CONST           120299
3790: EXTENDED_ARG         
3792: LOAD_CONST           'x'
3794: MAP_ADD              
3796: EXTENDED_ARG         
3798: LOAD_CONST           120300
3800: EXTENDED_ARG         
3802: LOAD_CONST           'y'
3804: MAP_ADD              
3806: EXTENDED_ARG         
3808: LOAD_CONST           120301
3810: LOAD_CONST           'z'
3812: MAP_ADD              
3814: DICT_UPDATE          
3816: BUILD_MAP            
3818: EXTENDED_ARG         
3820: LOAD_CONST           120328
3822: EXTENDED_ARG         
3824: LOAD_CONST           'a'
3826: MAP_ADD              
3828: EXTENDED_ARG         
3830: LOAD_CONST           120329
3832: LOAD_CONST           'b'
3834: MAP_ADD              
3836: EXTENDED_ARG         
3838: LOAD_CONST           120330
3840: LOAD_CONST           'c'
3842: MAP_ADD              
3844: EXTENDED_ARG         
3846: LOAD_CONST           120331
3848: LOAD_CONST           'd'
3850: MAP_ADD              
3852: EXTENDED_ARG         
3854: LOAD_CONST           120332
3856: LOAD_CONST           'e'
3858: MAP_ADD              
3860: EXTENDED_ARG         
3862: LOAD_CONST           120333
3864: LOAD_CONST           'f'
3866: MAP_ADD              
3868: EXTENDED_ARG         
3870: LOAD_CONST           120334
3872: EXTENDED_ARG         
3874: LOAD_CONST           'g'
3876: MAP_ADD              
3878: EXTENDED_ARG         
3880: LOAD_CONST           120335
3882: LOAD_CONST           'h'
3884: MAP_ADD              
3886: EXTENDED_ARG         
3888: LOAD_CONST           120336
3890: LOAD_CONST           'i'
3892: MAP_ADD              
3894: EXTENDED_ARG         
3896: LOAD_CONST           120337
3898: EXTENDED_ARG         
3900: LOAD_CONST           'j'
3902: MAP_ADD              
3904: EXTENDED_ARG         
3906: LOAD_CONST           120338
3908: EXTENDED_ARG         
3910: LOAD_CONST           'k'
3912: MAP_ADD              
3914: EXTENDED_ARG         
3916: LOAD_CONST           120339
3918: LOAD_CONST           'l'
3920: MAP_ADD              
3922: EXTENDED_ARG         
3924: LOAD_CONST           120340
3926: LOAD_CONST           'm'
3928: MAP_ADD              
3930: EXTENDED_ARG         
3932: LOAD_CONST           120341
3934: LOAD_CONST           'n'
3936: MAP_ADD              
3938: EXTENDED_ARG         
3940: LOAD_CONST           120342
3942: EXTENDED_ARG         
3944: LOAD_CONST           'o'
3946: MAP_ADD              
3948: EXTENDED_ARG         
3950: LOAD_CONST           120343
3952: LOAD_CONST           'p'
3954: MAP_ADD              
3956: EXTENDED_ARG         
3958: LOAD_CONST           120344
3960: LOAD_CONST           'q'
3962: MAP_ADD              
3964: DICT_UPDATE          
3966: BUILD_MAP            
3968: EXTENDED_ARG         
3970: LOAD_CONST           120345
3972: LOAD_CONST           'r'
3974: MAP_ADD              
3976: EXTENDED_ARG         
3978: LOAD_CONST           120346
3980: LOAD_CONST           's'
3982: MAP_ADD              
3984: EXTENDED_ARG         
3986: LOAD_CONST           120347
3988: EXTENDED_ARG         
3990: LOAD_CONST           't'
3992: MAP_ADD              
3994: EXTENDED_ARG         
3996: LOAD_CONST           120348
3998: EXTENDED_ARG         
4000: LOAD_CONST           'u'
4002: MAP_ADD              
4004: EXTENDED_ARG         
4006: LOAD_CONST           120349
4008: EXTENDED_ARG         
4010: LOAD_CONST           'v'
4012: MAP_ADD              
4014: EXTENDED_ARG         
4016: LOAD_CONST           120350
4018: EXTENDED_ARG         
4020: LOAD_CONST           'w'
4022: MAP_ADD              
4024: EXTENDED_ARG         
4026: LOAD_CONST           120351
4028: EXTENDED_ARG         
4030: LOAD_CONST           'x'
4032: MAP_ADD              
4034: EXTENDED_ARG         
4036: LOAD_CONST           120352
4038: EXTENDED_ARG         
4040: LOAD_CONST           'y'
4042: MAP_ADD              
4044: EXTENDED_ARG         
4046: LOAD_CONST           120353
4048: LOAD_CONST           'z'
4050: MAP_ADD              
4052: EXTENDED_ARG         
4054: LOAD_CONST           120380
4056: EXTENDED_ARG         
4058: LOAD_CONST           'a'
4060: MAP_ADD              
4062: EXTENDED_ARG         
4064: LOAD_CONST           120381
4066: LOAD_CONST           'b'
4068: MAP_ADD              
4070: EXTENDED_ARG         
4072: LOAD_CONST           120382
4074: LOAD_CONST           'c'
4076: MAP_ADD              
4078: EXTENDED_ARG         
4080: LOAD_CONST           120383
4082: LOAD_CONST           'd'
4084: MAP_ADD              
4086: EXTENDED_ARG         
4088: LOAD_CONST           120384
4090: LOAD_CONST           'e'
4092: MAP_ADD              
4094: EXTENDED_ARG         
4096: LOAD_CONST           120385
4098: LOAD_CONST           'f'
4100: MAP_ADD              
4102: EXTENDED_ARG         
4104: LOAD_CONST           120386
4106: EXTENDED_ARG         
4108: LOAD_CONST           'g'
4110: MAP_ADD              
4112: EXTENDED_ARG         
4114: LOAD_CONST           120387
4116: LOAD_CONST           'h'
4118: MAP_ADD              
4120: DICT_UPDATE          
4122: BUILD_MAP            
4124: EXTENDED_ARG         
4126: LOAD_CONST           120388
4128: LOAD_CONST           'i'
4130: MAP_ADD              
4132: EXTENDED_ARG         
4134: LOAD_CONST           120389
4136: EXTENDED_ARG         
4138: LOAD_CONST           'j'
4140: MAP_ADD              
4142: EXTENDED_ARG         
4144: LOAD_CONST           120390
4146: EXTENDED_ARG         
4148: LOAD_CONST           'k'
4150: MAP_ADD              
4152: EXTENDED_ARG         
4154: LOAD_CONST           120391
4156: LOAD_CONST           'l'
4158: MAP_ADD              
4160: EXTENDED_ARG         
4162: LOAD_CONST           120392
4164: LOAD_CONST           'm'
4166: MAP_ADD              
4168: EXTENDED_ARG         
4170: LOAD_CONST           120393
4172: LOAD_CONST           'n'
4174: MAP_ADD              
4176: EXTENDED_ARG         
4178: LOAD_CONST           120394
4180: EXTENDED_ARG         
4182: LOAD_CONST           'o'
4184: MAP_ADD              
4186: EXTENDED_ARG         
4188: LOAD_CONST           120395
4190: LOAD_CONST           'p'
4192: MAP_ADD              
4194: EXTENDED_ARG         
4196: LOAD_CONST           120396
4198: LOAD_CONST           'q'
4200: MAP_ADD              
4202: EXTENDED_ARG         
4204: LOAD_CONST           120397
4206: LOAD_CONST           'r'
4208: MAP_ADD              
4210: EXTENDED_ARG         
4212: LOAD_CONST           120398
4214: LOAD_CONST           's'
4216: MAP_ADD              
4218: EXTENDED_ARG         
4220: LOAD_CONST           120399
4222: EXTENDED_ARG         
4224: LOAD_CONST           't'
4226: MAP_ADD              
4228: EXTENDED_ARG         
4230: LOAD_CONST           120400
4232: EXTENDED_ARG         
4234: LOAD_CONST           'u'
4236: MAP_ADD              
4238: EXTENDED_ARG         
4240: LOAD_CONST           120401
4242: EXTENDED_ARG         
4244: LOAD_CONST           'v'
4246: MAP_ADD              
4248: EXTENDED_ARG         
4250: LOAD_CONST           120402
4252: EXTENDED_ARG         
4254: LOAD_CONST           'w'
4256: MAP_ADD              
4258: EXTENDED_ARG         
4260: LOAD_CONST           120403
4262: EXTENDED_ARG         
4264: LOAD_CONST           'x'
4266: MAP_ADD              
4268: EXTENDED_ARG         
4270: LOAD_CONST           120404
4272: EXTENDED_ARG         
4274: LOAD_CONST           'y'
4276: MAP_ADD              
4278: DICT_UPDATE          
4280: BUILD_MAP            
4282: EXTENDED_ARG         
4284: LOAD_CONST           120405
4286: LOAD_CONST           'z'
4288: MAP_ADD              
4290: EXTENDED_ARG         
4292: LOAD_CONST           120432
4294: EXTENDED_ARG         
4296: LOAD_CONST           'a'
4298: MAP_ADD              
4300: EXTENDED_ARG         
4302: LOAD_CONST           120433
4304: LOAD_CONST           'b'
4306: MAP_ADD              
4308: EXTENDED_ARG         
4310: LOAD_CONST           120434
4312: LOAD_CONST           'c'
4314: MAP_ADD              
4316: EXTENDED_ARG         
4318: LOAD_CONST           120435
4320: LOAD_CONST           'd'
4322: MAP_ADD              
4324: EXTENDED_ARG         
4326: LOAD_CONST           120436
4328: LOAD_CONST           'e'
4330: MAP_ADD              
4332: EXTENDED_ARG         
4334: LOAD_CONST           120437
4336: LOAD_CONST           'f'
4338: MAP_ADD              
4340: EXTENDED_ARG         
4342: LOAD_CONST           120438
4344: EXTENDED_ARG         
4346: LOAD_CONST           'g'
4348: MAP_ADD              
4350: EXTENDED_ARG         
4352: LOAD_CONST           120439
4354: LOAD_CONST           'h'
4356: MAP_ADD              
4358: EXTENDED_ARG         
4360: LOAD_CONST           120440
4362: LOAD_CONST           'i'
4364: MAP_ADD              
4366: EXTENDED_ARG         
4368: LOAD_CONST           120441
4370: EXTENDED_ARG         
4372: LOAD_CONST           'j'
4374: MAP_ADD              
4376: EXTENDED_ARG         
4378: LOAD_CONST           120442
4380: EXTENDED_ARG         
4382: LOAD_CONST           'k'
4384: MAP_ADD              
4386: EXTENDED_ARG         
4388: LOAD_CONST           120443
4390: LOAD_CONST           'l'
4392: MAP_ADD              
4394: EXTENDED_ARG         
4396: LOAD_CONST           120444
4398: LOAD_CONST           'm'
4400: MAP_ADD              
4402: EXTENDED_ARG         
4404: LOAD_CONST           120445
4406: LOAD_CONST           'n'
4408: MAP_ADD              
4410: EXTENDED_ARG         
4412: LOAD_CONST           120446
4414: EXTENDED_ARG         
4416: LOAD_CONST           'o'
4418: MAP_ADD              
4420: EXTENDED_ARG         
4422: LOAD_CONST           120447
4424: LOAD_CONST           'p'
4426: MAP_ADD              
4428: DICT_UPDATE          
4430: BUILD_MAP            
4432: EXTENDED_ARG         
4434: LOAD_CONST           120448
4436: LOAD_CONST           'q'
4438: MAP_ADD              
4440: EXTENDED_ARG         
4442: LOAD_CONST           120449
4444: LOAD_CONST           'r'
4446: MAP_ADD              
4448: EXTENDED_ARG         
4450: LOAD_CONST           120450
4452: LOAD_CONST           's'
4454: MAP_ADD              
4456: EXTENDED_ARG         
4458: LOAD_CONST           120451
4460: EXTENDED_ARG         
4462: LOAD_CONST           't'
4464: MAP_ADD              
4466: EXTENDED_ARG         
4468: LOAD_CONST           120452
4470: EXTENDED_ARG         
4472: LOAD_CONST           'u'
4474: MAP_ADD              
4476: EXTENDED_ARG         
4478: LOAD_CONST           120453
4480: EXTENDED_ARG         
4482: LOAD_CONST           'v'
4484: MAP_ADD              
4486: EXTENDED_ARG         
4488: LOAD_CONST           120454
4490: EXTENDED_ARG         
4492: LOAD_CONST           'w'
4494: MAP_ADD              
4496: EXTENDED_ARG         
4498: LOAD_CONST           120455
4500: EXTENDED_ARG         
4502: LOAD_CONST           'x'
4504: MAP_ADD              
4506: EXTENDED_ARG         
4508: LOAD_CONST           120456
4510: EXTENDED_ARG         
4512: LOAD_CONST           'y'
4514: MAP_ADD              
4516: EXTENDED_ARG         
4518: LOAD_CONST           120457
4520: LOAD_CONST           'z'
4522: MAP_ADD              
4524: EXTENDED_ARG         
4526: LOAD_CONST           120488
4528: EXTENDED_ARG         
4530: LOAD_CONST           'α'
4532: MAP_ADD              
4534: EXTENDED_ARG         
4536: LOAD_CONST           120489
4538: LOAD_CONST           'β'
4540: MAP_ADD              
4542: EXTENDED_ARG         
4544: LOAD_CONST           120490
4546: LOAD_CONST           'γ'
4548: MAP_ADD              
4550: EXTENDED_ARG         
4552: LOAD_CONST           120491
4554: EXTENDED_ARG         
4556: LOAD_CONST           'δ'
4558: MAP_ADD              
4560: EXTENDED_ARG         
4562: LOAD_CONST           120492
4564: LOAD_CONST           'ε'
4566: MAP_ADD              
4568: EXTENDED_ARG         
4570: LOAD_CONST           120493
4572: EXTENDED_ARG         
4574: LOAD_CONST           'ζ'
4576: MAP_ADD              
4578: EXTENDED_ARG         
4580: LOAD_CONST           120494
4582: EXTENDED_ARG         
4584: LOAD_CONST           'η'
4586: MAP_ADD              
4588: DICT_UPDATE          
4590: BUILD_MAP            
4592: EXTENDED_ARG         
4594: LOAD_CONST           120495
4596: LOAD_CONST           'θ'
4598: MAP_ADD              
4600: EXTENDED_ARG         
4602: LOAD_CONST           120496
4604: LOAD_CONST           'ι'
4606: MAP_ADD              
4608: EXTENDED_ARG         
4610: LOAD_CONST           120497
4612: LOAD_CONST           'κ'
4614: MAP_ADD              
4616: EXTENDED_ARG         
4618: LOAD_CONST           120498
4620: EXTENDED_ARG         
4622: LOAD_CONST           'λ'
4624: MAP_ADD              
4626: EXTENDED_ARG         
4628: LOAD_CONST           120499
4630: LOAD_CONST           'μ'
4632: MAP_ADD              
4634: EXTENDED_ARG         
4636: LOAD_CONST           120500
4638: EXTENDED_ARG         
4640: LOAD_CONST           'ν'
4642: MAP_ADD              
4644: EXTENDED_ARG         
4646: LOAD_CONST           120501
4648: EXTENDED_ARG         
4650: LOAD_CONST           'ξ'
4652: MAP_ADD              
4654: EXTENDED_ARG         
4656: LOAD_CONST           120502
4658: EXTENDED_ARG         
4660: LOAD_CONST           'ο'
4662: MAP_ADD              
4664: EXTENDED_ARG         
4666: LOAD_CONST           120503
4668: LOAD_CONST           'π'
4670: MAP_ADD              
4672: EXTENDED_ARG         
4674: LOAD_CONST           120504
4676: LOAD_CONST           'ρ'
4678: MAP_ADD              
4680: EXTENDED_ARG         
4682: LOAD_CONST           120505
4684: LOAD_CONST           'θ'
4686: MAP_ADD              
4688: EXTENDED_ARG         
4690: LOAD_CONST           120506
4692: LOAD_CONST           'σ'
4694: MAP_ADD              
4696: EXTENDED_ARG         
4698: LOAD_CONST           120507
4700: EXTENDED_ARG         
4702: LOAD_CONST           'τ'
4704: MAP_ADD              
4706: EXTENDED_ARG         
4708: LOAD_CONST           120508
4710: LOAD_CONST           'υ'
4712: MAP_ADD              
4714: EXTENDED_ARG         
4716: LOAD_CONST           120509
4718: LOAD_CONST           'φ'
4720: MAP_ADD              
4722: EXTENDED_ARG         
4724: LOAD_CONST           120510
4726: EXTENDED_ARG         
4728: LOAD_CONST           'χ'
4730: MAP_ADD              
4732: EXTENDED_ARG         
4734: LOAD_CONST           120511
4736: EXTENDED_ARG         
4738: LOAD_CONST           'ψ'
4740: MAP_ADD              
4742: DICT_UPDATE          
4744: BUILD_MAP            
4746: EXTENDED_ARG         
4748: LOAD_CONST           120512
4750: EXTENDED_ARG         
4752: LOAD_CONST           'ω'
4754: MAP_ADD              
4756: EXTENDED_ARG         
4758: LOAD_CONST           120531
4760: LOAD_CONST           'σ'
4762: MAP_ADD              
4764: EXTENDED_ARG         
4766: LOAD_CONST           120546
4768: EXTENDED_ARG         
4770: LOAD_CONST           'α'
4772: MAP_ADD              
4774: EXTENDED_ARG         
4776: LOAD_CONST           120547
4778: LOAD_CONST           'β'
4780: MAP_ADD              
4782: EXTENDED_ARG         
4784: LOAD_CONST           120548
4786: LOAD_CONST           'γ'
4788: MAP_ADD              
4790: EXTENDED_ARG         
4792: LOAD_CONST           120549
4794: EXTENDED_ARG         
4796: LOAD_CONST           'δ'
4798: MAP_ADD              
4800: EXTENDED_ARG         
4802: LOAD_CONST           120550
4804: LOAD_CONST           'ε'
4806: MAP_ADD              
4808: EXTENDED_ARG         
4810: LOAD_CONST           120551
4812: EXTENDED_ARG         
4814: LOAD_CONST           'ζ'
4816: MAP_ADD              
4818: EXTENDED_ARG         
4820: LOAD_CONST           120552
4822: EXTENDED_ARG         
4824: LOAD_CONST           'η'
4826: MAP_ADD              
4828: EXTENDED_ARG         
4830: LOAD_CONST           120553
4832: LOAD_CONST           'θ'
4834: MAP_ADD              
4836: EXTENDED_ARG         
4838: LOAD_CONST           120554
4840: LOAD_CONST           'ι'
4842: MAP_ADD              
4844: EXTENDED_ARG         
4846: LOAD_CONST           120555
4848: LOAD_CONST           'κ'
4850: MAP_ADD              
4852: EXTENDED_ARG         
4854: LOAD_CONST           120556
4856: EXTENDED_ARG         
4858: LOAD_CONST           'λ'
4860: MAP_ADD              
4862: EXTENDED_ARG         
4864: LOAD_CONST           120557
4866: LOAD_CONST           'μ'
4868: MAP_ADD              
4870: EXTENDED_ARG         
4872: LOAD_CONST           120558
4874: EXTENDED_ARG         
4876: LOAD_CONST           'ν'
4878: MAP_ADD              
4880: EXTENDED_ARG         
4882: LOAD_CONST           120559
4884: EXTENDED_ARG         
4886: LOAD_CONST           'ξ'
4888: MAP_ADD              
4890: EXTENDED_ARG         
4892: LOAD_CONST           120560
4894: EXTENDED_ARG         
4896: LOAD_CONST           'ο'
4898: MAP_ADD              
4900: DICT_UPDATE          
4902: BUILD_MAP            
4904: EXTENDED_ARG         
4906: LOAD_CONST           120561
4908: LOAD_CONST           'π'
4910: MAP_ADD              
4912: EXTENDED_ARG         
4914: LOAD_CONST           120562
4916: LOAD_CONST           'ρ'
4918: MAP_ADD              
4920: EXTENDED_ARG         
4922: LOAD_CONST           120563
4924: LOAD_CONST           'θ'
4926: MAP_ADD              
4928: EXTENDED_ARG         
4930: LOAD_CONST           120564
4932: LOAD_CONST           'σ'
4934: MAP_ADD              
4936: EXTENDED_ARG         
4938: LOAD_CONST           120565
4940: EXTENDED_ARG         
4942: LOAD_CONST           'τ'
4944: MAP_ADD              
4946: EXTENDED_ARG         
4948: LOAD_CONST           120566
4950: LOAD_CONST           'υ'
4952: MAP_ADD              
4954: EXTENDED_ARG         
4956: LOAD_CONST           120567
4958: LOAD_CONST           'φ'
4960: MAP_ADD              
4962: EXTENDED_ARG         
4964: LOAD_CONST           120568
4966: EXTENDED_ARG         
4968: LOAD_CONST           'χ'
4970: MAP_ADD              
4972: EXTENDED_ARG         
4974: LOAD_CONST           120569
4976: EXTENDED_ARG         
4978: LOAD_CONST           'ψ'
4980: MAP_ADD              
4982: EXTENDED_ARG         
4984: LOAD_CONST           120570
4986: EXTENDED_ARG         
4988: LOAD_CONST           'ω'
4990: MAP_ADD              
4992: EXTENDED_ARG         
4994: LOAD_CONST           120589
4996: LOAD_CONST           'σ'
4998: MAP_ADD              
5000: EXTENDED_ARG         
5002: LOAD_CONST           120604
5004: EXTENDED_ARG         
5006: LOAD_CONST           'α'
5008: MAP_ADD              
5010: EXTENDED_ARG         
5012: LOAD_CONST           120605
5014: LOAD_CONST           'β'
5016: MAP_ADD              
5018: EXTENDED_ARG         
5020: LOAD_CONST           120606
5022: LOAD_CONST           'γ'
5024: MAP_ADD              
5026: EXTENDED_ARG         
5028: LOAD_CONST           120607
5030: EXTENDED_ARG         
5032: LOAD_CONST           'δ'
5034: MAP_ADD              
5036: EXTENDED_ARG         
5038: LOAD_CONST           120608
5040: LOAD_CONST           'ε'
5042: MAP_ADD              
5044: EXTENDED_ARG         
5046: LOAD_CONST           120609
5048: EXTENDED_ARG         
5050: LOAD_CONST           'ζ'
5052: MAP_ADD              
5054: DICT_UPDATE          
5056: BUILD_MAP            
5058: EXTENDED_ARG         
5060: LOAD_CONST           120610
5062: EXTENDED_ARG         
5064: LOAD_CONST           'η'
5066: MAP_ADD              
5068: EXTENDED_ARG         
5070: LOAD_CONST           120611
5072: LOAD_CONST           'θ'
5074: MAP_ADD              
5076: EXTENDED_ARG         
5078: LOAD_CONST           120612
5080: LOAD_CONST           'ι'
5082: MAP_ADD              
5084: EXTENDED_ARG         
5086: LOAD_CONST           120613
5088: LOAD_CONST           'κ'
5090: MAP_ADD              
5092: EXTENDED_ARG         
5094: LOAD_CONST           120614
5096: EXTENDED_ARG         
5098: LOAD_CONST           'λ'
5100: MAP_ADD              
5102: EXTENDED_ARG         
5104: LOAD_CONST           120615
5106: LOAD_CONST           'μ'
5108: MAP_ADD              
5110: EXTENDED_ARG         
5112: LOAD_CONST           120616
5114: EXTENDED_ARG         
5116: LOAD_CONST           'ν'
5118: MAP_ADD              
5120: EXTENDED_ARG         
5122: LOAD_CONST           120617
5124: EXTENDED_ARG         
5126: LOAD_CONST           'ξ'
5128: MAP_ADD              
5130: EXTENDED_ARG         
5132: LOAD_CONST           120618
5134: EXTENDED_ARG         
5136: LOAD_CONST           'ο'
5138: MAP_ADD              
5140: EXTENDED_ARG         
5142: LOAD_CONST           120619
5144: LOAD_CONST           'π'
5146: MAP_ADD              
5148: EXTENDED_ARG         
5150: LOAD_CONST           120620
5152: LOAD_CONST           'ρ'
5154: MAP_ADD              
5156: EXTENDED_ARG         
5158: LOAD_CONST           120621
5160: LOAD_CONST           'θ'
5162: MAP_ADD              
5164: EXTENDED_ARG         
5166: LOAD_CONST           120622
5168: LOAD_CONST           'σ'
5170: MAP_ADD              
5172: EXTENDED_ARG         
5174: LOAD_CONST           120623
5176: EXTENDED_ARG         
5178: LOAD_CONST           'τ'
5180: MAP_ADD              
5182: EXTENDED_ARG         
5184: LOAD_CONST           120624
5186: LOAD_CONST           'υ'
5188: MAP_ADD              
5190: EXTENDED_ARG         
5192: LOAD_CONST           120625
5194: LOAD_CONST           'φ'
5196: MAP_ADD              
5198: EXTENDED_ARG         
5200: LOAD_CONST           120626
5202: EXTENDED_ARG         
5204: LOAD_CONST           'χ'
5206: MAP_ADD              
5208: DICT_UPDATE          
5210: BUILD_MAP            
5212: EXTENDED_ARG         
5214: LOAD_CONST           120627
5216: EXTENDED_ARG         
5218: LOAD_CONST           'ψ'
5220: MAP_ADD              
5222: EXTENDED_ARG         
5224: LOAD_CONST           120628
5226: EXTENDED_ARG         
5228: LOAD_CONST           'ω'
5230: MAP_ADD              
5232: EXTENDED_ARG         
5234: LOAD_CONST           120647
5236: LOAD_CONST           'σ'
5238: MAP_ADD              
5240: EXTENDED_ARG         
5242: LOAD_CONST           120662
5244: EXTENDED_ARG         
5246: LOAD_CONST           'α'
5248: MAP_ADD              
5250: EXTENDED_ARG         
5252: LOAD_CONST           120663
5254: LOAD_CONST           'β'
5256: MAP_ADD              
5258: EXTENDED_ARG         
5260: LOAD_CONST           120664
5262: LOAD_CONST           'γ'
5264: MAP_ADD              
5266: EXTENDED_ARG         
5268: LOAD_CONST           120665
5270: EXTENDED_ARG         
5272: LOAD_CONST           'δ'
5274: MAP_ADD              
5276: EXTENDED_ARG         
5278: LOAD_CONST           120666
5280: LOAD_CONST           'ε'
5282: MAP_ADD              
5284: EXTENDED_ARG         
5286: LOAD_CONST           120667
5288: EXTENDED_ARG         
5290: LOAD_CONST           'ζ'
5292: MAP_ADD              
5294: EXTENDED_ARG         
5296: LOAD_CONST           120668
5298: EXTENDED_ARG         
5300: LOAD_CONST           'η'
5302: MAP_ADD              
5304: EXTENDED_ARG         
5306: LOAD_CONST           120669
5308: LOAD_CONST           'θ'
5310: MAP_ADD              
5312: EXTENDED_ARG         
5314: LOAD_CONST           120670
5316: LOAD_CONST           'ι'
5318: MAP_ADD              
5320: EXTENDED_ARG         
5322: LOAD_CONST           120671
5324: LOAD_CONST           'κ'
5326: MAP_ADD              
5328: EXTENDED_ARG         
5330: LOAD_CONST           120672
5332: EXTENDED_ARG         
5334: LOAD_CONST           'λ'
5336: MAP_ADD              
5338: EXTENDED_ARG         
5340: LOAD_CONST           120673
5342: LOAD_CONST           'μ'
5344: MAP_ADD              
5346: EXTENDED_ARG         
5348: LOAD_CONST           120674
5350: EXTENDED_ARG         
5352: LOAD_CONST           'ν'
5354: MAP_ADD              
5356: EXTENDED_ARG         
5358: LOAD_CONST           120675
5360: EXTENDED_ARG         
5362: LOAD_CONST           'ξ'
5364: MAP_ADD              
5366: DICT_UPDATE          
5368: BUILD_MAP            
5370: EXTENDED_ARG         
5372: LOAD_CONST           120676
5374: EXTENDED_ARG         
5376: LOAD_CONST           'ο'
5378: MAP_ADD              
5380: EXTENDED_ARG         
5382: LOAD_CONST           120677
5384: LOAD_CONST           'π'
5386: MAP_ADD              
5388: EXTENDED_ARG         
5390: LOAD_CONST           120678
5392: LOAD_CONST           'ρ'
5394: MAP_ADD              
5396: EXTENDED_ARG         
5398: LOAD_CONST           120679
5400: LOAD_CONST           'θ'
5402: MAP_ADD              
5404: EXTENDED_ARG         
5406: LOAD_CONST           120680
5408: LOAD_CONST           'σ'
5410: MAP_ADD              
5412: EXTENDED_ARG         
5414: LOAD_CONST           120681
5416: EXTENDED_ARG         
5418: LOAD_CONST           'τ'
5420: MAP_ADD              
5422: EXTENDED_ARG         
5424: LOAD_CONST           120682
5426: LOAD_CONST           'υ'
5428: MAP_ADD              
5430: EXTENDED_ARG         
5432: LOAD_CONST           120683
5434: LOAD_CONST           'φ'
5436: MAP_ADD              
5438: EXTENDED_ARG         
5440: LOAD_CONST           120684
5442: EXTENDED_ARG         
5444: LOAD_CONST           'χ'
5446: MAP_ADD              
5448: EXTENDED_ARG         
5450: LOAD_CONST           120685
5452: EXTENDED_ARG         
5454: LOAD_CONST           'ψ'
5456: MAP_ADD              
5458: EXTENDED_ARG         
5460: LOAD_CONST           120686
5462: EXTENDED_ARG         
5464: LOAD_CONST           'ω'
5466: MAP_ADD              
5468: EXTENDED_ARG         
5470: LOAD_CONST           120705
5472: LOAD_CONST           'σ'
5474: MAP_ADD              
5476: EXTENDED_ARG         
5478: LOAD_CONST           120720
5480: EXTENDED_ARG         
5482: LOAD_CONST           'α'
5484: MAP_ADD              
5486: EXTENDED_ARG         
5488: LOAD_CONST           120721
5490: LOAD_CONST           'β'
5492: MAP_ADD              
5494: EXTENDED_ARG         
5496: LOAD_CONST           120722
5498: LOAD_CONST           'γ'
5500: MAP_ADD              
5502: EXTENDED_ARG         
5504: LOAD_CONST           120723
5506: EXTENDED_ARG         
5508: LOAD_CONST           'δ'
5510: MAP_ADD              
5512: EXTENDED_ARG         
5514: LOAD_CONST           120724
5516: LOAD_CONST           'ε'
5518: MAP_ADD              
5520: DICT_UPDATE          
5522: BUILD_MAP            
5524: EXTENDED_ARG         
5526: LOAD_CONST           120725
5528: EXTENDED_ARG         
5530: LOAD_CONST           'ζ'
5532: MAP_ADD              
5534: EXTENDED_ARG         
5536: LOAD_CONST           120726
5538: EXTENDED_ARG         
5540: LOAD_CONST           'η'
5542: MAP_ADD              
5544: EXTENDED_ARG         
5546: LOAD_CONST           120727
5548: LOAD_CONST           'θ'
5550: MAP_ADD              
5552: EXTENDED_ARG         
5554: LOAD_CONST           120728
5556: LOAD_CONST           'ι'
5558: MAP_ADD              
5560: EXTENDED_ARG         
5562: LOAD_CONST           120729
5564: LOAD_CONST           'κ'
5566: MAP_ADD              
5568: EXTENDED_ARG         
5570: LOAD_CONST           120730
5572: EXTENDED_ARG         
5574: LOAD_CONST           'λ'
5576: MAP_ADD              
5578: EXTENDED_ARG         
5580: LOAD_CONST           120731
5582: LOAD_CONST           'μ'
5584: MAP_ADD              
5586: EXTENDED_ARG         
5588: LOAD_CONST           120732
5590: EXTENDED_ARG         
5592: LOAD_CONST           'ν'
5594: MAP_ADD              
5596: EXTENDED_ARG         
5598: LOAD_CONST           120733
5600: EXTENDED_ARG         
5602: LOAD_CONST           'ξ'
5604: MAP_ADD              
5606: EXTENDED_ARG         
5608: LOAD_CONST           120734
5610: EXTENDED_ARG         
5612: LOAD_CONST           'ο'
5614: MAP_ADD              
5616: EXTENDED_ARG         
5618: LOAD_CONST           120735
5620: LOAD_CONST           'π'
5622: MAP_ADD              
5624: EXTENDED_ARG         
5626: LOAD_CONST           120736
5628: LOAD_CONST           'ρ'
5630: MAP_ADD              
5632: EXTENDED_ARG         
5634: LOAD_CONST           120737
5636: LOAD_CONST           'θ'
5638: MAP_ADD              
5640: EXTENDED_ARG         
5642: LOAD_CONST           120738
5644: LOAD_CONST           'σ'
5646: MAP_ADD              
5648: EXTENDED_ARG         
5650: LOAD_CONST           120739
5652: EXTENDED_ARG         
5654: LOAD_CONST           'τ'
5656: MAP_ADD              
5658: EXTENDED_ARG         
5660: LOAD_CONST           120740
5662: LOAD_CONST           'υ'
5664: MAP_ADD              
5666: EXTENDED_ARG         
5668: LOAD_CONST           120741
5670: LOAD_CONST           'φ'
5672: MAP_ADD              
5674: DICT_UPDATE          
5676: EXTENDED_ARG         
5678: LOAD_CONST           'χ'
5680: EXTENDED_ARG         
5682: LOAD_CONST           'ψ'
5684: EXTENDED_ARG         
5686: LOAD_CONST           'ω'
5688: LOAD_CONST           'σ'
5690: EXTENDED_ARG         
5692: LOAD_CONST           (120742, 120743, 120744, 120763)
5694: BUILD_CONST_KEY_MAP  
5696: DICT_UPDATE          
5698: STORE_NAME           b3_exceptions
5700: EXTENDED_ARG         
5702: LOAD_CONST           <code object map_table_b3 at 0x00000240693AB230, file "stringprep.py", line 189>
5704: MAKE_FUNCTION        
5706: STORE_NAME           map_table_b3
5708: EXTENDED_ARG         
5710: LOAD_CONST           <code object map_table_b2 at 0x00000240691E9830, file "stringprep.py", line 195>
5712: MAKE_FUNCTION        
5714: STORE_NAME           map_table_b2
5716: EXTENDED_ARG         
5718: LOAD_CONST           <code object in_table_c11 at 0x0000024069496180, file "stringprep.py", line 206>
5720: MAKE_FUNCTION        
5722: STORE_NAME           in_table_c11
5724: EXTENDED_ARG         
5726: LOAD_CONST           <code object in_table_c12 at 0x00000240693EB730, file "stringprep.py", line 210>
5728: MAKE_FUNCTION        
5730: STORE_NAME           in_table_c12
5732: EXTENDED_ARG         
5734: LOAD_CONST           <code object in_table_c11_c12 at 0x000002406945EA60, file "stringprep.py", line 213>
5736: MAKE_FUNCTION        
5738: STORE_NAME           in_table_c11_c12
5740: EXTENDED_ARG         
5742: LOAD_CONST           <code object in_table_c21 at 0x000002406944AAB0, file "stringprep.py", line 217>
5744: MAKE_FUNCTION        
5746: STORE_NAME           in_table_c21
5748: PUSH_NULL            
5750: LOAD_NAME            set
5752: BUILD_LIST           
5754: EXTENDED_ARG         
5756: LOAD_CONST           (1757, 1807, 6158, 8204, 8205, 8232, 8233, 65279)
5758: LIST_EXTEND          
5760: PUSH_NULL            
5762: LOAD_NAME            list
5764: PUSH_NULL            
5766: LOAD_NAME            range
5768: EXTENDED_ARG         
5770: LOAD_CONST           8288
5772: EXTENDED_ARG         
5774: LOAD_CONST           8292
5776: PRECALL              
5780: CALL                 
5790: PRECALL              
5794: CALL                 
5804: BINARY_OP            +
5808: PUSH_NULL            
5810: LOAD_NAME            list
5812: PUSH_NULL            
5814: LOAD_NAME            range
5816: EXTENDED_ARG         
5818: LOAD_CONST           8298
5820: EXTENDED_ARG         
5822: LOAD_CONST           8304
5824: PRECALL              
5828: CALL                 
5838: PRECALL              
5842: CALL                 
5852: BINARY_OP            +
5856: PUSH_NULL            
5858: LOAD_NAME            list
5860: PUSH_NULL            
5862: LOAD_NAME            range
5864: EXTENDED_ARG         
5866: LOAD_CONST           65529
5868: EXTENDED_ARG         
5870: LOAD_CONST           65533
5872: PRECALL              
5876: CALL                 
5886: PRECALL              
5890: CALL                 
5900: BINARY_OP            +
5904: PUSH_NULL            
5906: LOAD_NAME            list
5908: PUSH_NULL            
5910: LOAD_NAME            range
5912: EXTENDED_ARG         
5914: LOAD_CONST           119155
5916: EXTENDED_ARG         
5918: LOAD_CONST           119163
5920: PRECALL              
5924: CALL                 
5934: PRECALL              
5938: CALL                 
5948: BINARY_OP            +
5952: PRECALL              
5956: CALL                 
5966: STORE_NAME           c22_specials
5968: EXTENDED_ARG         
5970: LOAD_CONST           <code object in_table_c22 at 0x00000240693D23D0, file "stringprep.py", line 221>
5972: MAKE_FUNCTION        
5974: STORE_NAME           in_table_c22
5976: EXTENDED_ARG         
5978: LOAD_CONST           <code object in_table_c21_c22 at 0x000002406941B2D0, file "stringprep.py", line 227>
5980: MAKE_FUNCTION        
5982: STORE_NAME           in_table_c21_c22
5984: EXTENDED_ARG         
5986: LOAD_CONST           <code object in_table_c3 at 0x000002406945F2D0, file "stringprep.py", line 232>
5988: MAKE_FUNCTION        
5990: STORE_NAME           in_table_c3
5992: EXTENDED_ARG         
5994: LOAD_CONST           <code object in_table_c4 at 0x000002406941A310, file "stringprep.py", line 236>
5996: MAKE_FUNCTION        
5998: STORE_NAME           in_table_c4
6000: EXTENDED_ARG         
6002: LOAD_CONST           <code object in_table_c5 at 0x000002406945FD20, file "stringprep.py", line 243>
6004: MAKE_FUNCTION        
6006: STORE_NAME           in_table_c5
6008: PUSH_NULL            
6010: LOAD_NAME            set
6012: PUSH_NULL            
6014: LOAD_NAME            range
6016: EXTENDED_ARG         
6018: LOAD_CONST           65529
6020: EXTENDED_ARG         
6022: LOAD_CONST           65534
6024: PRECALL              
6028: CALL                 
6038: PRECALL              
6042: CALL                 
6052: STORE_NAME           c6_set
6054: EXTENDED_ARG         
6056: LOAD_CONST           <code object in_table_c6 at 0x000002406945DC50, file "stringprep.py", line 248>
6058: MAKE_FUNCTION        
6060: STORE_NAME           in_table_c6
6062: PUSH_NULL            
6064: LOAD_NAME            set
6066: PUSH_NULL            
6068: LOAD_NAME            range
6070: EXTENDED_ARG         
6072: LOAD_CONST           12272
6074: EXTENDED_ARG         
6076: LOAD_CONST           12284
6078: PRECALL              
6082: CALL                 
6092: PRECALL              
6096: CALL                 
6106: STORE_NAME           c7_set
6108: EXTENDED_ARG         
6110: LOAD_CONST           <code object in_table_c7 at 0x000002406945F000, file "stringprep.py", line 253>
6112: MAKE_FUNCTION        
6114: STORE_NAME           in_table_c7
6116: PUSH_NULL            
6118: LOAD_NAME            set
6120: BUILD_LIST           
6122: EXTENDED_ARG         
6124: LOAD_CONST           (832, 833, 8206, 8207)
6126: LIST_EXTEND          
6128: PUSH_NULL            
6130: LOAD_NAME            list
6132: PUSH_NULL            
6134: LOAD_NAME            range
6136: EXTENDED_ARG         
6138: LOAD_CONST           8234
6140: EXTENDED_ARG         
6142: LOAD_CONST           8239
6144: PRECALL              
6148: CALL                 
6158: PRECALL              
6162: CALL                 
6172: BINARY_OP            +
6176: PUSH_NULL            
6178: LOAD_NAME            list
6180: PUSH_NULL            
6182: LOAD_NAME            range
6184: EXTENDED_ARG         
6186: LOAD_CONST           8298
6188: EXTENDED_ARG         
6190: LOAD_CONST           8304
6192: PRECALL              
6196: CALL                 
6206: PRECALL              
6210: CALL                 
6220: BINARY_OP            +
6224: PRECALL              
6228: CALL                 
6238: STORE_NAME           c8_set
6240: EXTENDED_ARG         
6242: LOAD_CONST           <code object in_table_c8 at 0x000002406945FC30, file "stringprep.py", line 258>
6244: MAKE_FUNCTION        
6246: STORE_NAME           in_table_c8
6248: PUSH_NULL            
6250: LOAD_NAME            set
6252: EXTENDED_ARG         
6254: LOAD_CONST           917505
6256: BUILD_LIST           
6258: PUSH_NULL            
6260: LOAD_NAME            list
6262: PUSH_NULL            
6264: LOAD_NAME            range
6266: EXTENDED_ARG         
6268: LOAD_CONST           917536
6270: EXTENDED_ARG         
6272: LOAD_CONST           917632
6274: PRECALL              
6278: CALL                 
6288: PRECALL              
6292: CALL                 
6302: BINARY_OP            +
6306: PRECALL              
6310: CALL                 
6320: STORE_NAME           c9_set
6322: EXTENDED_ARG         
6324: LOAD_CONST           <code object in_table_c9 at 0x000002406945DF20, file "stringprep.py", line 263>
6326: MAKE_FUNCTION        
6328: STORE_NAME           in_table_c9
6330: EXTENDED_ARG         
6332: LOAD_CONST           <code object in_table_d1 at 0x000002406945DE30, file "stringprep.py", line 267>
6334: MAKE_FUNCTION        
6336: STORE_NAME           in_table_d1
6338: EXTENDED_ARG         
6340: LOAD_CONST           <code object in_table_d2 at 0x000002406945E880, file "stringprep.py", line 271>
6342: MAKE_FUNCTION        
6344: STORE_NAME           in_table_d2
6346: EXTENDED_ARG         
6348: LOAD_CONST           None
6350: RETURN_VALUE         
