# Disassembly for tarfile.TarInfo._create_header
# From module file: tarfile

## co_consts:
('Return a header block. info is a dictionary with file\n           information, format must be one of the *_FORMAT constants.\n        ', 'type', 'devmajor', 0, 8, 'devminor', '', None, 'TarInfo.type must not be None', 'name', 100, 'mode', 4095, 'uid', 'gid', 'size', 12, 'mtime', b'        ', 'linkname', 'magic', 'uname', 32, 'gname', 'prefix', 155, '%ds', b'', -364, '%06o\x00', 'ascii', -357)

## co_names:
('get', 'CHRTYPE', 'BLKTYPE', 'itn', 'stn', 'REGTYPE', 'ValueError', 'POSIX_MAGIC', 'struct', 'pack', 'BLOCKSIZE', 'join', 'calc_chksums', 'bytes')

## bytecode:

   0: RESUME               
   2: LOAD_FAST            info
   4: LOAD_METHOD          get
  26: LOAD_CONST           'type'
  28: PRECALL              
  32: CALL                 
  42: LOAD_GLOBAL          CHRTYPE
  54: LOAD_GLOBAL          BLKTYPE
  66: BUILD_TUPLE          
  68: CONTAINS_OP          
  70: STORE_FAST           has_device_fields
  72: LOAD_FAST            has_device_fields
  74: POP_JUMP_FORWARD_IF_FALSE to 226
  76: LOAD_GLOBAL          NULL + itn
  88: LOAD_FAST            info
  90: LOAD_METHOD          get
 112: LOAD_CONST           'devmajor'
 114: LOAD_CONST           0
 116: PRECALL              
 120: CALL                 
 130: LOAD_CONST           8
 132: LOAD_FAST            format
 134: PRECALL              
 138: CALL                 
 148: STORE_FAST           devmajor
 150: LOAD_GLOBAL          NULL + itn
 162: LOAD_FAST            info
 164: LOAD_METHOD          get
 186: LOAD_CONST           'devminor'
 188: LOAD_CONST           0
 190: PRECALL              
 194: CALL                 
 204: LOAD_CONST           8
 206: LOAD_FAST            format
 208: PRECALL              
 212: CALL                 
 222: STORE_FAST           devminor
 224: JUMP_FORWARD         to 298
 226: LOAD_GLOBAL          NULL + stn
 238: LOAD_CONST           ''
 240: LOAD_CONST           8
 242: LOAD_FAST            encoding
 244: LOAD_FAST            errors
 246: PRECALL              
 250: CALL                 
 260: STORE_FAST           devmajor
 262: LOAD_GLOBAL          NULL + stn
 274: LOAD_CONST           ''
 276: LOAD_CONST           8
 278: LOAD_FAST            encoding
 280: LOAD_FAST            errors
 282: PRECALL              
 286: CALL                 
 296: STORE_FAST           devminor
 298: LOAD_FAST            info
 300: LOAD_METHOD          get
 322: LOAD_CONST           'type'
 324: LOAD_GLOBAL          REGTYPE
 336: PRECALL              
 340: CALL                 
 350: STORE_FAST           filetype
 352: LOAD_FAST            filetype
 354: POP_JUMP_FORWARD_IF_NOT_NONE to 386
 356: LOAD_GLOBAL          NULL + ValueError
 368: LOAD_CONST           'TarInfo.type must not be None'
 370: PRECALL              
 374: CALL                 
 384: RAISE_VARARGS        
 386: LOAD_GLOBAL          NULL + stn
 398: LOAD_FAST            info
 400: LOAD_METHOD          get
 422: LOAD_CONST           'name'
 424: LOAD_CONST           ''
 426: PRECALL              
 430: CALL                 
 440: LOAD_CONST           100
 442: LOAD_FAST            encoding
 444: LOAD_FAST            errors
 446: PRECALL              
 450: CALL                 
 460: LOAD_GLOBAL          NULL + itn
 472: LOAD_FAST            info
 474: LOAD_METHOD          get
 496: LOAD_CONST           'mode'
 498: LOAD_CONST           0
 500: PRECALL              
 504: CALL                 
 514: LOAD_CONST           4095
 516: BINARY_OP            &
 520: LOAD_CONST           8
 522: LOAD_FAST            format
 524: PRECALL              
 528: CALL                 
 538: LOAD_GLOBAL          NULL + itn
 550: LOAD_FAST            info
 552: LOAD_METHOD          get
 574: LOAD_CONST           'uid'
 576: LOAD_CONST           0
 578: PRECALL              
 582: CALL                 
 592: LOAD_CONST           8
 594: LOAD_FAST            format
 596: PRECALL              
 600: CALL                 
 610: LOAD_GLOBAL          NULL + itn
 622: LOAD_FAST            info
 624: LOAD_METHOD          get
 646: LOAD_CONST           'gid'
 648: LOAD_CONST           0
 650: PRECALL              
 654: CALL                 
 664: LOAD_CONST           8
 666: LOAD_FAST            format
 668: PRECALL              
 672: CALL                 
 682: LOAD_GLOBAL          NULL + itn
 694: LOAD_FAST            info
 696: LOAD_METHOD          get
 718: LOAD_CONST           'size'
 720: LOAD_CONST           0
 722: PRECALL              
 726: CALL                 
 736: LOAD_CONST           12
 738: LOAD_FAST            format
 740: PRECALL              
 744: CALL                 
 754: LOAD_GLOBAL          NULL + itn
 766: LOAD_FAST            info
 768: LOAD_METHOD          get
 790: LOAD_CONST           'mtime'
 792: LOAD_CONST           0
 794: PRECALL              
 798: CALL                 
 808: LOAD_CONST           12
 810: LOAD_FAST            format
 812: PRECALL              
 816: CALL                 
 826: LOAD_CONST           b'        '
 828: LOAD_FAST            filetype
 830: LOAD_GLOBAL          NULL + stn
 842: LOAD_FAST            info
 844: LOAD_METHOD          get
 866: LOAD_CONST           'linkname'
 868: LOAD_CONST           ''
 870: PRECALL              
 874: CALL                 
 884: LOAD_CONST           100
 886: LOAD_FAST            encoding
 888: LOAD_FAST            errors
 890: PRECALL              
 894: CALL                 
 904: LOAD_FAST            info
 906: LOAD_METHOD          get
 928: LOAD_CONST           'magic'
 930: LOAD_GLOBAL          POSIX_MAGIC
 942: PRECALL              
 946: CALL                 
 956: LOAD_GLOBAL          NULL + stn
 968: LOAD_FAST            info
 970: LOAD_METHOD          get
 992: LOAD_CONST           'uname'
 994: LOAD_CONST           ''
 996: PRECALL              
1000: CALL                 
1010: LOAD_CONST           32
1012: LOAD_FAST            encoding
1014: LOAD_FAST            errors
1016: PRECALL              
1020: CALL                 
1030: LOAD_GLOBAL          NULL + stn
1042: LOAD_FAST            info
1044: LOAD_METHOD          get
1066: LOAD_CONST           'gname'
1068: LOAD_CONST           ''
1070: PRECALL              
1074: CALL                 
1084: LOAD_CONST           32
1086: LOAD_FAST            encoding
1088: LOAD_FAST            errors
1090: PRECALL              
1094: CALL                 
1104: LOAD_FAST            devmajor
1106: LOAD_FAST            devminor
1108: LOAD_GLOBAL          NULL + stn
1120: LOAD_FAST            info
1122: LOAD_METHOD          get
1144: LOAD_CONST           'prefix'
1146: LOAD_CONST           ''
1148: PRECALL              
1152: CALL                 
1162: LOAD_CONST           155
1164: LOAD_FAST            encoding
1166: LOAD_FAST            errors
1168: PRECALL              
1172: CALL                 
1182: BUILD_LIST           
1184: STORE_FAST           parts
1186: LOAD_GLOBAL          NULL + struct
1198: LOAD_ATTR            pack
1208: LOAD_CONST           '%ds'
1210: LOAD_GLOBAL          BLOCKSIZE
1222: BINARY_OP            %
1226: LOAD_CONST           b''
1228: LOAD_METHOD          join
1250: LOAD_FAST            parts
1252: PRECALL              
1256: CALL                 
1266: PRECALL              
1270: CALL                 
1280: STORE_FAST           buf
1282: LOAD_GLOBAL          NULL + calc_chksums
1294: LOAD_FAST            buf
1296: LOAD_GLOBAL          BLOCKSIZE
1308: UNARY_NEGATIVE       
1310: LOAD_CONST           None
1312: BUILD_SLICE          
1314: BINARY_SUBSCR        
1324: PRECALL              
1328: CALL                 
1338: LOAD_CONST           0
1340: BINARY_SUBSCR        
1350: STORE_FAST           chksum
1352: LOAD_FAST            buf
1354: LOAD_CONST           None
1356: LOAD_CONST           -364
1358: BUILD_SLICE          
1360: BINARY_SUBSCR        
1370: LOAD_GLOBAL          NULL + bytes
1382: LOAD_CONST           '%06o\x00'
1384: LOAD_FAST            chksum
1386: BINARY_OP            %
1390: LOAD_CONST           'ascii'
1392: PRECALL              
1396: CALL                 
1406: BINARY_OP            +
1410: LOAD_FAST            buf
1412: LOAD_CONST           -357
1414: LOAD_CONST           None
1416: BUILD_SLICE          
1418: BINARY_SUBSCR        
1428: BINARY_OP            +
1432: STORE_FAST           buf
1434: LOAD_FAST            buf
1436: RETURN_VALUE         
