# Disassembly for tarfile.SubsequentHeaderError
# From module file: tarfile

## co_consts:
('SubsequentHeaderError', 'Exception for missing and invalid extended headers.', None)

## co_names:
('__name__', '__module__', '__qualname__', '__doc__')

## bytecode:

   0: RESUME               
   2: LOAD_NAME            __name__
   4: STORE_NAME           __module__
   6: LOAD_CONST           'SubsequentHeaderError'
   8: STORE_NAME           __qualname__
  10: LOAD_CONST           'Exception for missing and invalid extended headers.'
  12: STORE_NAME           __doc__
  14: LOAD_CONST           None
  16: RETURN_VALUE         
