# Disassembly for tarfile._get_filtered_attrs
# From module file: tarfile

## co_consts:
(None, '/', 'name', 493, 64, -74, 384, 'mode', 'uid', 'gid', 'uname', 'gname')

## co_names:
('name', 'os', 'path', 'realpath', 'startswith', 'sep', 'lstrip', 'isabs', 'AbsolutePathError', 'join', 'commonpath', 'OutsideDestinationError', 'mode', 'isreg', 'islnk', 'isdir', 'issym', 'SpecialFileError', 'uid', 'gid', 'uname', 'gname', 'linkname', 'AbsoluteLinkError', 'dirname', 'LinkOutsideDestinationError')

## bytecode:

   0: RESUME               
   2: BUILD_MAP            
   4: STORE_FAST           new_attrs
   6: LOAD_FAST            member
   8: LOAD_ATTR            name
  18: STORE_FAST           name
  20: LOAD_GLOBAL          os
  32: LOAD_ATTR            path
  42: LOAD_METHOD          realpath
  64: LOAD_FAST            dest_path
  66: PRECALL              
  70: CALL                 
  80: STORE_FAST           dest_path
  82: LOAD_FAST            name
  84: LOAD_METHOD          startswith
 106: LOAD_CONST           '/'
 108: LOAD_GLOBAL          os
 120: LOAD_ATTR            sep
 130: BUILD_TUPLE          
 132: PRECALL              
 136: CALL                 
 146: POP_JUMP_FORWARD_IF_FALSE to 236
 148: LOAD_FAST            member
 150: LOAD_ATTR            path
 160: LOAD_METHOD          lstrip
 182: LOAD_CONST           '/'
 184: LOAD_GLOBAL          os
 196: LOAD_ATTR            sep
 206: BINARY_OP            +
 210: PRECALL              
 214: CALL                 
 224: COPY                 
 226: STORE_FAST           name
 228: LOAD_FAST            new_attrs
 230: LOAD_CONST           'name'
 232: STORE_SUBSCR         
 236: LOAD_GLOBAL          os
 248: LOAD_ATTR            path
 258: LOAD_METHOD          isabs
 280: LOAD_FAST            name
 282: PRECALL              
 286: CALL                 
 296: POP_JUMP_FORWARD_IF_FALSE to 328
 298: LOAD_GLOBAL          NULL + AbsolutePathError
 310: LOAD_FAST            member
 312: PRECALL              
 316: CALL                 
 326: RAISE_VARARGS        
 328: LOAD_GLOBAL          os
 340: LOAD_ATTR            path
 350: LOAD_METHOD          realpath
 372: LOAD_GLOBAL          os
 384: LOAD_ATTR            path
 394: LOAD_METHOD          join
 416: LOAD_FAST            dest_path
 418: LOAD_FAST            name
 420: PRECALL              
 424: CALL                 
 434: PRECALL              
 438: CALL                 
 448: STORE_FAST           target_path
 450: LOAD_GLOBAL          os
 462: LOAD_ATTR            path
 472: LOAD_METHOD          commonpath
 494: LOAD_FAST            target_path
 496: LOAD_FAST            dest_path
 498: BUILD_LIST           
 500: PRECALL              
 504: CALL                 
 514: LOAD_FAST            dest_path
 516: COMPARE_OP           !=
 522: POP_JUMP_FORWARD_IF_FALSE to 556
 524: LOAD_GLOBAL          NULL + OutsideDestinationError
 536: LOAD_FAST            member
 538: LOAD_FAST            target_path
 540: PRECALL              
 544: CALL                 
 554: RAISE_VARARGS        
 556: LOAD_FAST            member
 558: LOAD_ATTR            mode
 568: STORE_FAST           mode
 570: LOAD_FAST            mode
 572: POP_JUMP_FORWARD_IF_NONE to 848
 574: LOAD_FAST            mode
 576: LOAD_CONST           493
 578: BINARY_OP            &
 582: STORE_FAST           mode
 584: LOAD_FAST            for_data
 586: POP_JUMP_FORWARD_IF_FALSE to 816
 588: LOAD_FAST            member
 590: LOAD_METHOD          isreg
 612: PRECALL              
 616: CALL                 
 626: POP_JUMP_FORWARD_IF_TRUE to 668
 628: LOAD_FAST            member
 630: LOAD_METHOD          islnk
 652: PRECALL              
 656: CALL                 
 666: POP_JUMP_FORWARD_IF_FALSE to 700
 668: LOAD_FAST            mode
 670: LOAD_CONST           64
 672: BINARY_OP            &
 676: POP_JUMP_FORWARD_IF_TRUE to 688
 678: LOAD_FAST            mode
 680: LOAD_CONST           -74
 682: BINARY_OP            &=
 686: STORE_FAST           mode
 688: LOAD_FAST            mode
 690: LOAD_CONST           384
 692: BINARY_OP            |=
 696: STORE_FAST           mode
 698: JUMP_FORWARD         to 816
 700: LOAD_FAST            member
 702: LOAD_METHOD          isdir
 724: PRECALL              
 728: CALL                 
 738: POP_JUMP_FORWARD_IF_TRUE to 780
 740: LOAD_FAST            member
 742: LOAD_METHOD          issym
 764: PRECALL              
 768: CALL                 
 778: POP_JUMP_FORWARD_IF_FALSE to 786
 780: LOAD_CONST           None
 782: STORE_FAST           mode
 784: JUMP_FORWARD         to 816
 786: LOAD_GLOBAL          NULL + SpecialFileError
 798: LOAD_FAST            member
 800: PRECALL              
 804: CALL                 
 814: RAISE_VARARGS        
 816: LOAD_FAST            mode
 818: LOAD_FAST            member
 820: LOAD_ATTR            mode
 830: COMPARE_OP           !=
 836: POP_JUMP_FORWARD_IF_FALSE to 848
 838: LOAD_FAST            mode
 840: LOAD_FAST            new_attrs
 842: LOAD_CONST           'mode'
 844: STORE_SUBSCR         
 848: LOAD_FAST            for_data
 850: EXTENDED_ARG         
 852: POP_JUMP_FORWARD_IF_FALSE to 1552
 854: LOAD_FAST            member
 856: LOAD_ATTR            uid
 866: POP_JUMP_FORWARD_IF_NONE to 878
 868: LOAD_CONST           None
 870: LOAD_FAST            new_attrs
 872: LOAD_CONST           'uid'
 874: STORE_SUBSCR         
 878: LOAD_FAST            member
 880: LOAD_ATTR            gid
 890: POP_JUMP_FORWARD_IF_NONE to 902
 892: LOAD_CONST           None
 894: LOAD_FAST            new_attrs
 896: LOAD_CONST           'gid'
 898: STORE_SUBSCR         
 902: LOAD_FAST            member
 904: LOAD_ATTR            uname
 914: POP_JUMP_FORWARD_IF_NONE to 926
 916: LOAD_CONST           None
 918: LOAD_FAST            new_attrs
 920: LOAD_CONST           'uname'
 922: STORE_SUBSCR         
 926: LOAD_FAST            member
 928: LOAD_ATTR            gname
 938: POP_JUMP_FORWARD_IF_NONE to 950
 940: LOAD_CONST           None
 942: LOAD_FAST            new_attrs
 944: LOAD_CONST           'gname'
 946: STORE_SUBSCR         
 950: LOAD_FAST            member
 952: LOAD_METHOD          islnk
 974: PRECALL              
 978: CALL                 
 988: POP_JUMP_FORWARD_IF_TRUE to 1032
 990: LOAD_FAST            member
 992: LOAD_METHOD          issym
1014: PRECALL              
1018: CALL                 
1028: EXTENDED_ARG         
1030: POP_JUMP_FORWARD_IF_FALSE to 1552
1032: LOAD_GLOBAL          os
1044: LOAD_ATTR            path
1054: LOAD_METHOD          isabs
1076: LOAD_FAST            member
1078: LOAD_ATTR            linkname
1088: PRECALL              
1092: CALL                 
1102: POP_JUMP_FORWARD_IF_FALSE to 1134
1104: LOAD_GLOBAL          NULL + AbsoluteLinkError
1116: LOAD_FAST            member
1118: PRECALL              
1122: CALL                 
1132: RAISE_VARARGS        
1134: LOAD_FAST            member
1136: LOAD_METHOD          issym
1158: PRECALL              
1162: CALL                 
1172: POP_JUMP_FORWARD_IF_FALSE to 1310
1174: LOAD_GLOBAL          os
1186: LOAD_ATTR            path
1196: LOAD_METHOD          join
1218: LOAD_FAST            dest_path
1220: LOAD_GLOBAL          os
1232: LOAD_ATTR            path
1242: LOAD_METHOD          dirname
1264: LOAD_FAST            name
1266: PRECALL              
1270: CALL                 
1280: LOAD_FAST            member
1282: LOAD_ATTR            linkname
1292: PRECALL              
1296: CALL                 
1306: STORE_FAST           target_path
1308: JUMP_FORWARD         to 1384
1310: LOAD_GLOBAL          os
1322: LOAD_ATTR            path
1332: LOAD_METHOD          join
1354: LOAD_FAST            dest_path
1356: LOAD_FAST            member
1358: LOAD_ATTR            linkname
1368: PRECALL              
1372: CALL                 
1382: STORE_FAST           target_path
1384: LOAD_GLOBAL          os
1396: LOAD_ATTR            path
1406: LOAD_METHOD          realpath
1428: LOAD_FAST            target_path
1430: PRECALL              
1434: CALL                 
1444: STORE_FAST           target_path
1446: LOAD_GLOBAL          os
1458: LOAD_ATTR            path
1468: LOAD_METHOD          commonpath
1490: LOAD_FAST            target_path
1492: LOAD_FAST            dest_path
1494: BUILD_LIST           
1496: PRECALL              
1500: CALL                 
1510: LOAD_FAST            dest_path
1512: COMPARE_OP           !=
1518: POP_JUMP_FORWARD_IF_FALSE to 1552
1520: LOAD_GLOBAL          NULL + LinkOutsideDestinationError
1532: LOAD_FAST            member
1534: LOAD_FAST            target_path
1536: PRECALL              
1540: CALL                 
1550: RAISE_VARARGS        
1552: LOAD_FAST            new_attrs
1554: RETURN_VALUE         
