# Disassembly for tarfile.TarFile.makefifo
# From module file: tarfile

## co_consts:
('Make a fifo called targetpath.\n        ', 'mkfifo', 'fifo not supported by system', None)

## co_names:
('hasattr', 'os', 'mkfifo', 'ExtractError')

## bytecode:

   0: RESUME               
   2: LOAD_GLOBAL          NULL + hasattr
  14: LOAD_GLOBAL          os
  26: LOAD_CONST           'mkfifo'
  28: PRECALL              
  32: CALL                 
  42: POP_JUMP_FORWARD_IF_FALSE to 88
  44: LOAD_GLOBAL          NULL + os
  56: LOAD_ATTR            mkfifo
  66: LOAD_FAST            targetpath
  68: PRECALL              
  72: CALL                 
  82: POP_TOP              
  84: LOAD_CONST           None
  86: RETURN_VALUE         
  88: LOAD_GLOBAL          NULL + ExtractError
 100: LOAD_CONST           'fifo not supported by system'
 102: PRECALL              
 106: CALL                 
 116: RAISE_VARARGS        
