# Disassembly for tarfile._Stream.__read
# From module file: tarfile

## co_consts:
('Return size bytes from stream. If internal buffer is empty,\n           read another block from the stream.\n        ', b'', None)

## co_names:
('len', 'buf', 'fileobj', 'read', 'bufsize', 'append', 'join')

## bytecode:

   0: RESUME               
   2: LOAD_GLOBAL          NULL + len
  14: LOAD_FAST            self
  16: LOAD_ATTR            buf
  26: PRECALL              
  30: CALL                 
  40: STORE_FAST           c
  42: LOAD_FAST            self
  44: LOAD_ATTR            buf
  54: BUILD_LIST           
  56: STORE_FAST           t
  58: LOAD_FAST            c
  60: LOAD_FAST            size
  62: COMPARE_OP           <
  68: POP_JUMP_FORWARD_IF_FALSE to 228
  70: LOAD_FAST            self
  72: LOAD_ATTR            fileobj
  82: LOAD_METHOD          read
 104: LOAD_FAST            self
 106: LOAD_ATTR            bufsize
 116: PRECALL              
 120: CALL                 
 130: STORE_FAST           buf
 132: LOAD_FAST            buf
 134: POP_JUMP_FORWARD_IF_TRUE to 138
 136: JUMP_FORWARD         to 228
 138: LOAD_FAST            t
 140: LOAD_METHOD          append
 162: LOAD_FAST            buf
 164: PRECALL              
 168: CALL                 
 178: POP_TOP              
 180: LOAD_FAST            c
 182: LOAD_GLOBAL          NULL + len
 194: LOAD_FAST            buf
 196: PRECALL              
 200: CALL                 
 210: BINARY_OP            +=
 214: STORE_FAST           c
 216: LOAD_FAST            c
 218: LOAD_FAST            size
 220: COMPARE_OP           <
 226: POP_JUMP_BACKWARD_IF_TRUE to 70
 228: LOAD_CONST           b''
 230: LOAD_METHOD          join
 252: LOAD_FAST            t
 254: PRECALL              
 258: CALL                 
 268: STORE_FAST           t
 270: LOAD_FAST            t
 272: LOAD_FAST            size
 274: LOAD_CONST           None
 276: BUILD_SLICE          
 278: BINARY_SUBSCR        
 288: LOAD_FAST            self
 290: STORE_ATTR           buf
 300: LOAD_FAST            t
 302: LOAD_CONST           None
 304: LOAD_FAST            size
 306: BUILD_SLICE          
 308: BINARY_SUBSCR        
 318: RETURN_VALUE         
