# Disassembly for tarfile.TarFile._load
# From module file: tarfile

## co_consts:
('Read through the entire archive file and look for readable\n           members.\n        ', True, None)

## co_names:
('next', '_loaded')

## bytecode:

   0: RESUME               
   2: NOP                  
   4: LOAD_FAST            self
   6: LOAD_METHOD          next
  28: PRECALL              
  32: CALL                 
  42: STORE_FAST           tarinfo
  44: LOAD_FAST            tarinfo
  46: POP_JUMP_FORWARD_IF_NOT_NONE to 50
  48: JUMP_FORWARD         to 52
  50: JUMP_BACKWARD        to 4
  52: LOAD_CONST           True
  54: LOAD_FAST            self
  56: STORE_ATTR           _loaded
  66: LOAD_CONST           None
  68: RETURN_VALUE         
