# Disassembly for tarfile.stn
# From module file: tarfile

## co_consts:
('Convert a string to a null-terminated bytes object.\n    ', None, 'metadata cannot contain None')

## co_names:
('ValueError', 'encode', 'len', 'NUL')

## bytecode:

   0: RESUME               
   2: LOAD_FAST            s
   4: POP_JUMP_FORWARD_IF_NOT_NONE to 36
   6: LOAD_GLOBAL          NULL + ValueError
  18: LOAD_CONST           'metadata cannot contain None'
  20: PRECALL              
  24: CALL                 
  34: RAISE_VARARGS        
  36: LOAD_FAST            s
  38: LOAD_METHOD          encode
  60: LOAD_FAST            encoding
  62: LOAD_FAST            errors
  64: PRECALL              
  68: CALL                 
  78: STORE_FAST           s
  80: LOAD_FAST            s
  82: LOAD_CONST           None
  84: LOAD_FAST            length
  86: BUILD_SLICE          
  88: BINARY_SUBSCR        
  98: LOAD_FAST            length
 100: LOAD_GLOBAL          NULL + len
 112: LOAD_FAST            s
 114: PRECALL              
 118: CALL                 
 128: BINARY_OP            -
 132: LOAD_GLOBAL          NUL
 144: BINARY_OP            *
 148: BINARY_OP            +
 152: RETURN_VALUE         
