# Disassembly for tarfile.TarFile._dbg
# From module file: tarfile

## co_consts:
('Write debugging output to sys.stderr.\n        ', ('file',), None)

## co_names:
('debug', 'print', 'sys', 'stderr')

## bytecode:

   0: RESUME               
   2: LOAD_FAST            level
   4: LOAD_FAST            self
   6: LOAD_ATTR            debug
  16: COMPARE_OP           <=
  22: POP_JUMP_FORWARD_IF_FALSE to 82
  24: LOAD_GLOBAL          NULL + print
  36: LOAD_FAST            msg
  38: LOAD_GLOBAL          sys
  50: LOAD_ATTR            stderr
  60: KW_NAMES             
  62: PRECALL              
  66: CALL                 
  76: POP_TOP              
  78: LOAD_CONST           None
  80: RETURN_VALUE         
  82: LOAD_CONST           None
  84: RETURN_VALUE         
