# Disassembly for tarfile.TarFile.gettarinfo
# From module file: tarfile

## co_consts:
("Create a TarInfo object from the result of os.stat or equivalent\n           on an existing file. The file is either named by `name', or\n           specified as a file object `fileobj' with a file descriptor. If\n           given, `arcname' specifies an alternative name for the file in the\n           archive, otherwise, the name is taken from the 'name' attribute of\n           'fileobj', or the 'name' argument. The name should be a text\n           string.\n        ", 'awx', None, '/', '', 1, 0, 'major', 'minor')

## co_names:
('_check', 'name', 'os', 'path', 'splitdrive', 'replace', 'sep', 'lstrip', 'tarinfo', 'tarfile', 'dereference', 'lstat', 'stat', 'fstat', 'fileno', 'st_mode', 'S_ISREG', 'st_ino', 'st_dev', 'st_nlink', 'inodes', 'LNKTYPE', 'REGTYPE', 'S_ISDIR', 'DIRTYPE', 'S_ISFIFO', 'FIFOTYPE', 'S_ISLNK', 'SYMTYPE', 'readlink', 'S_ISCHR', 'CHRTYPE', 'S_ISBLK', 'BLKTYPE', 'mode', 'st_uid', 'uid', 'st_gid', 'gid', 'st_size', 'size', 'st_mtime', 'mtime', 'type', 'linkname', 'pwd', 'getpwuid', 'uname', 'KeyError', 'grp', 'getgrgid', 'gname', 'hasattr', 'major', 'st_rdev', 'devmajor', 'minor', 'devminor')

## bytecode:

   0: RESUME               
   2: LOAD_FAST            self
   4: LOAD_METHOD          _check
  26: LOAD_CONST           'awx'
  28: PRECALL              
  32: CALL                 
  42: POP_TOP              
  44: LOAD_FAST            fileobj
  46: POP_JUMP_FORWARD_IF_NONE to 62
  48: LOAD_FAST            fileobj
  50: LOAD_ATTR            name
  60: STORE_FAST           name
  62: LOAD_FAST            arcname
  64: POP_JUMP_FORWARD_IF_NOT_NONE to 70
  66: LOAD_FAST            name
  68: STORE_FAST           arcname
  70: LOAD_GLOBAL          os
  82: LOAD_ATTR            path
  92: LOAD_METHOD          splitdrive
 114: LOAD_FAST            arcname
 116: PRECALL              
 120: CALL                 
 130: UNPACK_SEQUENCE      
 134: STORE_FAST           drv
 136: STORE_FAST           arcname
 138: LOAD_FAST            arcname
 140: LOAD_METHOD          replace
 162: LOAD_GLOBAL          os
 174: LOAD_ATTR            sep
 184: LOAD_CONST           '/'
 186: PRECALL              
 190: CALL                 
 200: STORE_FAST           arcname
 202: LOAD_FAST            arcname
 204: LOAD_METHOD          lstrip
 226: LOAD_CONST           '/'
 228: PRECALL              
 232: CALL                 
 242: STORE_FAST           arcname
 244: LOAD_FAST            self
 246: LOAD_METHOD          tarinfo
 268: PRECALL              
 272: CALL                 
 282: STORE_FAST           tarinfo
 284: LOAD_FAST            self
 286: LOAD_FAST            tarinfo
 288: STORE_ATTR           tarfile
 298: LOAD_FAST            fileobj
 300: POP_JUMP_FORWARD_IF_NOT_NONE to 400
 302: LOAD_FAST            self
 304: LOAD_ATTR            dereference
 314: POP_JUMP_FORWARD_IF_TRUE to 358
 316: LOAD_GLOBAL          NULL + os
 328: LOAD_ATTR            lstat
 338: LOAD_FAST            name
 340: PRECALL              
 344: CALL                 
 354: STORE_FAST           statres
 356: JUMP_FORWARD         to 476
 358: LOAD_GLOBAL          NULL + os
 370: LOAD_ATTR            stat
 380: LOAD_FAST            name
 382: PRECALL              
 386: CALL                 
 396: STORE_FAST           statres
 398: JUMP_FORWARD         to 476
 400: LOAD_GLOBAL          NULL + os
 412: LOAD_ATTR            fstat
 422: LOAD_FAST            fileobj
 424: LOAD_METHOD          fileno
 446: PRECALL              
 450: CALL                 
 460: PRECALL              
 464: CALL                 
 474: STORE_FAST           statres
 476: LOAD_CONST           ''
 478: STORE_FAST           linkname
 480: LOAD_FAST            statres
 482: LOAD_ATTR            st_mode
 492: STORE_FAST           stmd
 494: LOAD_GLOBAL          NULL + stat
 506: LOAD_ATTR            S_ISREG
 516: LOAD_FAST            stmd
 518: PRECALL              
 522: CALL                 
 532: POP_JUMP_FORWARD_IF_FALSE to 744
 534: LOAD_FAST            statres
 536: LOAD_ATTR            st_ino
 546: LOAD_FAST            statres
 548: LOAD_ATTR            st_dev
 558: BUILD_TUPLE          
 560: STORE_FAST           inode
 562: LOAD_FAST            self
 564: LOAD_ATTR            dereference
 574: POP_JUMP_FORWARD_IF_TRUE to 692
 576: LOAD_FAST            statres
 578: LOAD_ATTR            st_nlink
 588: LOAD_CONST           1
 590: COMPARE_OP           >
 596: POP_JUMP_FORWARD_IF_FALSE to 692
 598: LOAD_FAST            inode
 600: LOAD_FAST            self
 602: LOAD_ATTR            inodes
 612: CONTAINS_OP          
 614: POP_JUMP_FORWARD_IF_FALSE to 692
 616: LOAD_FAST            arcname
 618: LOAD_FAST            self
 620: LOAD_ATTR            inodes
 630: LOAD_FAST            inode
 632: BINARY_SUBSCR        
 642: COMPARE_OP           !=
 648: POP_JUMP_FORWARD_IF_FALSE to 692
 650: LOAD_GLOBAL          LNKTYPE
 662: STORE_FAST           type
 664: LOAD_FAST            self
 666: LOAD_ATTR            inodes
 676: LOAD_FAST            inode
 678: BINARY_SUBSCR        
 688: STORE_FAST           linkname
 690: JUMP_FORWARD         to 1068
 692: LOAD_GLOBAL          REGTYPE
 704: STORE_FAST           type
 706: LOAD_FAST            inode
 708: LOAD_CONST           0
 710: BINARY_SUBSCR        
 720: POP_JUMP_FORWARD_IF_FALSE to 742
 722: LOAD_FAST            arcname
 724: LOAD_FAST            self
 726: LOAD_ATTR            inodes
 736: LOAD_FAST            inode
 738: STORE_SUBSCR         
 742: JUMP_FORWARD         to 1068
 744: LOAD_GLOBAL          NULL + stat
 756: LOAD_ATTR            S_ISDIR
 766: LOAD_FAST            stmd
 768: PRECALL              
 772: CALL                 
 782: POP_JUMP_FORWARD_IF_FALSE to 800
 784: LOAD_GLOBAL          DIRTYPE
 796: STORE_FAST           type
 798: JUMP_FORWARD         to 1068
 800: LOAD_GLOBAL          NULL + stat
 812: LOAD_ATTR            S_ISFIFO
 822: LOAD_FAST            stmd
 824: PRECALL              
 828: CALL                 
 838: POP_JUMP_FORWARD_IF_FALSE to 856
 840: LOAD_GLOBAL          FIFOTYPE
 852: STORE_FAST           type
 854: JUMP_FORWARD         to 1068
 856: LOAD_GLOBAL          NULL + stat
 868: LOAD_ATTR            S_ISLNK
 878: LOAD_FAST            stmd
 880: PRECALL              
 884: CALL                 
 894: POP_JUMP_FORWARD_IF_FALSE to 952
 896: LOAD_GLOBAL          SYMTYPE
 908: STORE_FAST           type
 910: LOAD_GLOBAL          NULL + os
 922: LOAD_ATTR            readlink
 932: LOAD_FAST            name
 934: PRECALL              
 938: CALL                 
 948: STORE_FAST           linkname
 950: JUMP_FORWARD         to 1068
 952: LOAD_GLOBAL          NULL + stat
 964: LOAD_ATTR            S_ISCHR
 974: LOAD_FAST            stmd
 976: PRECALL              
 980: CALL                 
 990: POP_JUMP_FORWARD_IF_FALSE to 1008
 992: LOAD_GLOBAL          CHRTYPE
1004: STORE_FAST           type
1006: JUMP_FORWARD         to 1068
1008: LOAD_GLOBAL          NULL + stat
1020: LOAD_ATTR            S_ISBLK
1030: LOAD_FAST            stmd
1032: PRECALL              
1036: CALL                 
1046: POP_JUMP_FORWARD_IF_FALSE to 1064
1048: LOAD_GLOBAL          BLKTYPE
1060: STORE_FAST           type
1062: JUMP_FORWARD         to 1068
1064: LOAD_CONST           None
1066: RETURN_VALUE         
1068: LOAD_FAST            arcname
1070: LOAD_FAST            tarinfo
1072: STORE_ATTR           name
1082: LOAD_FAST            stmd
1084: LOAD_FAST            tarinfo
1086: STORE_ATTR           mode
1096: LOAD_FAST            statres
1098: LOAD_ATTR            st_uid
1108: LOAD_FAST            tarinfo
1110: STORE_ATTR           uid
1120: LOAD_FAST            statres
1122: LOAD_ATTR            st_gid
1132: LOAD_FAST            tarinfo
1134: STORE_ATTR           gid
1144: LOAD_FAST            type
1146: LOAD_GLOBAL          REGTYPE
1158: COMPARE_OP           ==
1164: POP_JUMP_FORWARD_IF_FALSE to 1192
1166: LOAD_FAST            statres
1168: LOAD_ATTR            st_size
1178: LOAD_FAST            tarinfo
1180: STORE_ATTR           size
1190: JUMP_FORWARD         to 1206
1192: LOAD_CONST           0
1194: LOAD_FAST            tarinfo
1196: STORE_ATTR           size
1206: LOAD_FAST            statres
1208: LOAD_ATTR            st_mtime
1218: LOAD_FAST            tarinfo
1220: STORE_ATTR           mtime
1230: LOAD_FAST            type
1232: LOAD_FAST            tarinfo
1234: STORE_ATTR           type
1244: LOAD_FAST            linkname
1246: LOAD_FAST            tarinfo
1248: STORE_ATTR           linkname
1258: LOAD_GLOBAL          pwd
1270: POP_JUMP_FORWARD_IF_FALSE to 1380
1272: NOP                  
1274: LOAD_GLOBAL          NULL + pwd
1286: LOAD_ATTR            getpwuid
1296: LOAD_FAST            tarinfo
1298: LOAD_ATTR            uid
1308: PRECALL              
1312: CALL                 
1322: LOAD_CONST           0
1324: BINARY_SUBSCR        
1334: LOAD_FAST            tarinfo
1336: STORE_ATTR           uname
1346: JUMP_FORWARD         to 1380
1348: PUSH_EXC_INFO        
1350: LOAD_GLOBAL          KeyError
1362: CHECK_EXC_MATCH      
1364: POP_JUMP_FORWARD_IF_FALSE to 1372
1366: POP_TOP              
1368: POP_EXCEPT           
1370: JUMP_FORWARD         to 1380
1372: RERAISE              
1374: COPY                 
1376: POP_EXCEPT           
1378: RERAISE              
1380: LOAD_GLOBAL          grp
1392: POP_JUMP_FORWARD_IF_FALSE to 1502
1394: NOP                  
1396: LOAD_GLOBAL          NULL + grp
1408: LOAD_ATTR            getgrgid
1418: LOAD_FAST            tarinfo
1420: LOAD_ATTR            gid
1430: PRECALL              
1434: CALL                 
1444: LOAD_CONST           0
1446: BINARY_SUBSCR        
1456: LOAD_FAST            tarinfo
1458: STORE_ATTR           gname
1468: JUMP_FORWARD         to 1502
1470: PUSH_EXC_INFO        
1472: LOAD_GLOBAL          KeyError
1484: CHECK_EXC_MATCH      
1486: POP_JUMP_FORWARD_IF_FALSE to 1494
1488: POP_TOP              
1490: POP_EXCEPT           
1492: JUMP_FORWARD         to 1502
1494: RERAISE              
1496: COPY                 
1498: POP_EXCEPT           
1500: RERAISE              
1502: LOAD_FAST            type
1504: LOAD_GLOBAL          CHRTYPE
1516: LOAD_GLOBAL          BLKTYPE
1528: BUILD_TUPLE          
1530: CONTAINS_OP          
1532: POP_JUMP_FORWARD_IF_FALSE to 1738
1534: LOAD_GLOBAL          NULL + hasattr
1546: LOAD_GLOBAL          os
1558: LOAD_CONST           'major'
1560: PRECALL              
1564: CALL                 
1574: POP_JUMP_FORWARD_IF_FALSE to 1738
1576: LOAD_GLOBAL          NULL + hasattr
1588: LOAD_GLOBAL          os
1600: LOAD_CONST           'minor'
1602: PRECALL              
1606: CALL                 
1616: POP_JUMP_FORWARD_IF_FALSE to 1738
1618: LOAD_GLOBAL          NULL + os
1630: LOAD_ATTR            major
1640: LOAD_FAST            statres
1642: LOAD_ATTR            st_rdev
1652: PRECALL              
1656: CALL                 
1666: LOAD_FAST            tarinfo
1668: STORE_ATTR           devmajor
1678: LOAD_GLOBAL          NULL + os
1690: LOAD_ATTR            minor
1700: LOAD_FAST            statres
1702: LOAD_ATTR            st_rdev
1712: PRECALL              
1716: CALL                 
1726: LOAD_FAST            tarinfo
1728: STORE_ATTR           devminor
1738: LOAD_FAST            tarinfo
1740: RETURN_VALUE         
