# Disassembly for tarfile.TarInfo._decode_pax_field
# From module file: tarfile

## co_consts:
('Decode a single field from a pax record.\n        ', 'strict')

## co_names:
('decode', 'UnicodeDecodeError')

## bytecode:

   0: RESUME               
   2: NOP                  
   4: LOAD_FAST            value
   6: LOAD_METHOD          decode
  28: LOAD_FAST            encoding
  30: LOAD_CONST           'strict'
  32: PRECALL              
  36: CALL                 
  46: RETURN_VALUE         
  48: PUSH_EXC_INFO        
  50: LOAD_GLOBAL          UnicodeDecodeError
  62: CHECK_EXC_MATCH      
  64: POP_JUMP_FORWARD_IF_FALSE to 116
  66: POP_TOP              
  68: LOAD_FAST            value
  70: LOAD_METHOD          decode
  92: LOAD_FAST            fallback_encoding
  94: LOAD_FAST            fallback_errors
  96: PRECALL              
 100: CALL                 
 110: SWAP                 
 112: POP_EXCEPT           
 114: RETURN_VALUE         
 116: RERAISE              
 118: COPY                 
 120: POP_EXCEPT           
 122: RERAISE              
