# Disassembly for tarfile._Stream._init_write_gz
# From module file: tarfile

## co_consts:
('Initialize for writing with gzip compression.\n        ', 9, 0, '<L', b'\x1f\x8b\x08\x08', b'\x02\xff', '.gz', None, -3, 'iso-8859-1', 'replace')

## co_names:
('zlib', 'compressobj', 'DEFLATED', 'MAX_WBITS', 'DEF_MEM_LEVEL', 'cmp', 'struct', 'pack', 'int', 'time', '_Stream__write', 'name', 'endswith', 'os', 'path', 'basename', 'encode', 'NUL')

## bytecode:

   0: RESUME               
   2: LOAD_FAST            self
   4: LOAD_ATTR            zlib
  14: LOAD_METHOD          compressobj
  36: LOAD_CONST           9
  38: LOAD_FAST            self
  40: LOAD_ATTR            zlib
  50: LOAD_ATTR            DEFLATED
  60: LOAD_FAST            self
  62: LOAD_ATTR            zlib
  72: LOAD_ATTR            MAX_WBITS
  82: UNARY_NEGATIVE       
  84: LOAD_FAST            self
  86: LOAD_ATTR            zlib
  96: LOAD_ATTR            DEF_MEM_LEVEL
 106: LOAD_CONST           0
 108: PRECALL              
 112: CALL                 
 122: LOAD_FAST            self
 124: STORE_ATTR           cmp
 134: LOAD_GLOBAL          NULL + struct
 146: LOAD_ATTR            pack
 156: LOAD_CONST           '<L'
 158: LOAD_GLOBAL          NULL + int
 170: LOAD_GLOBAL          NULL + time
 182: LOAD_ATTR            time
 192: PRECALL              
 196: CALL                 
 206: PRECALL              
 210: CALL                 
 220: PRECALL              
 224: CALL                 
 234: STORE_FAST           timestamp
 236: LOAD_FAST            self
 238: LOAD_METHOD          _Stream__write
 260: LOAD_CONST           b'\x1f\x8b\x08\x08'
 262: LOAD_FAST            timestamp
 264: BINARY_OP            +
 268: LOAD_CONST           b'\x02\xff'
 270: BINARY_OP            +
 274: PRECALL              
 278: CALL                 
 288: POP_TOP              
 290: LOAD_FAST            self
 292: LOAD_ATTR            name
 302: LOAD_METHOD          endswith
 324: LOAD_CONST           '.gz'
 326: PRECALL              
 330: CALL                 
 340: POP_JUMP_FORWARD_IF_FALSE to 382
 342: LOAD_FAST            self
 344: LOAD_ATTR            name
 354: LOAD_CONST           None
 356: LOAD_CONST           -3
 358: BUILD_SLICE          
 360: BINARY_SUBSCR        
 370: LOAD_FAST            self
 372: STORE_ATTR           name
 382: LOAD_GLOBAL          os
 394: LOAD_ATTR            path
 404: LOAD_METHOD          basename
 426: LOAD_FAST            self
 428: LOAD_ATTR            name
 438: PRECALL              
 442: CALL                 
 452: LOAD_FAST            self
 454: STORE_ATTR           name
 464: LOAD_FAST            self
 466: LOAD_METHOD          _Stream__write
 488: LOAD_FAST            self
 490: LOAD_ATTR            name
 500: LOAD_METHOD          encode
 522: LOAD_CONST           'iso-8859-1'
 524: LOAD_CONST           'replace'
 526: PRECALL              
 530: CALL                 
 540: LOAD_GLOBAL          NUL
 552: BINARY_OP            +
 556: PRECALL              
 560: CALL                 
 570: POP_TOP              
 572: LOAD_CONST           None
 574: RETURN_VALUE         
