# Disassembly for tarfile._LowLevelFile
# From module file: tarfile

## co_consts:
('_LowLevelFile', 'Low-level file object. Supports reading and writing.\n       It is used instead of a regular file object for streaming\n       access.\n    ', <code object __init__ at 0x000002406934F120, file "tarfile.py", line 314>, <code object close at 0x000002406945FD20, file "tarfile.py", line 323>, <code object read at 0x000002406945DC50, file "tarfile.py", line 326>, <code object write at 0x00000240693EBA30, file "tarfile.py", line 329>, None)

## co_names:
('__name__', '__module__', '__qualname__', '__doc__', '__init__', 'close', 'read', 'write')

## bytecode:

   0: RESUME               
   2: LOAD_NAME            __name__
   4: STORE_NAME           __module__
   6: LOAD_CONST           '_LowLevelFile'
   8: STORE_NAME           __qualname__
  10: LOAD_CONST           'Low-level file object. Supports reading and writing.\n       It is used instead of a regular file object for streaming\n       access.\n    '
  12: STORE_NAME           __doc__
  14: LOAD_CONST           <code object __init__ at 0x000002406934F120, file "tarfile.py", line 314>
  16: MAKE_FUNCTION        
  18: STORE_NAME           __init__
  20: LOAD_CONST           <code object close at 0x000002406945FD20, file "tarfile.py", line 323>
  22: MAKE_FUNCTION        
  24: STORE_NAME           close
  26: LOAD_CONST           <code object read at 0x000002406945DC50, file "tarfile.py", line 326>
  28: MAKE_FUNCTION        
  30: STORE_NAME           read
  32: LOAD_CONST           <code object write at 0x00000240693EBA30, file "tarfile.py", line 329>
  34: MAKE_FUNCTION        
  36: STORE_NAME           write
  38: LOAD_CONST           None
  40: RETURN_VALUE         
