# Disassembly for tarfile._Stream._init_read_gz
# From module file: tarfile

## co_consts:
('Initialize for reading a gzip compressed fileobj.\n        ', b'', 2, b'\x1f\x8b', 'not a gzip file', 1, b'\x08', 'unsupported compression method', 6, 4, 256, 8, True, 16, None)

## co_names:
('zlib', 'decompressobj', 'MAX_WBITS', 'cmp', 'dbuf', '_Stream__read', 'ReadError', 'CompressionError', 'ord', 'read', 'NUL')

## bytecode:

   0: RESUME               
   2: LOAD_FAST            self
   4: LOAD_ATTR            zlib
  14: LOAD_METHOD          decompressobj
  36: LOAD_FAST            self
  38: LOAD_ATTR            zlib
  48: LOAD_ATTR            MAX_WBITS
  58: UNARY_NEGATIVE       
  60: PRECALL              
  64: CALL                 
  74: LOAD_FAST            self
  76: STORE_ATTR           cmp
  86: LOAD_CONST           b''
  88: LOAD_FAST            self
  90: STORE_ATTR           dbuf
 100: LOAD_FAST            self
 102: LOAD_METHOD          _Stream__read
 124: LOAD_CONST           2
 126: PRECALL              
 130: CALL                 
 140: LOAD_CONST           b'\x1f\x8b'
 142: COMPARE_OP           !=
 148: POP_JUMP_FORWARD_IF_FALSE to 180
 150: LOAD_GLOBAL          NULL + ReadError
 162: LOAD_CONST           'not a gzip file'
 164: PRECALL              
 168: CALL                 
 178: RAISE_VARARGS        
 180: LOAD_FAST            self
 182: LOAD_METHOD          _Stream__read
 204: LOAD_CONST           1
 206: PRECALL              
 210: CALL                 
 220: LOAD_CONST           b'\x08'
 222: COMPARE_OP           !=
 228: POP_JUMP_FORWARD_IF_FALSE to 260
 230: LOAD_GLOBAL          NULL + CompressionError
 242: LOAD_CONST           'unsupported compression method'
 244: PRECALL              
 248: CALL                 
 258: RAISE_VARARGS        
 260: LOAD_GLOBAL          NULL + ord
 272: LOAD_FAST            self
 274: LOAD_METHOD          _Stream__read
 296: LOAD_CONST           1
 298: PRECALL              
 302: CALL                 
 312: PRECALL              
 316: CALL                 
 326: STORE_FAST           flag
 328: LOAD_FAST            self
 330: LOAD_METHOD          _Stream__read
 352: LOAD_CONST           6
 354: PRECALL              
 358: CALL                 
 368: POP_TOP              
 370: LOAD_FAST            flag
 372: LOAD_CONST           4
 374: BINARY_OP            &
 378: POP_JUMP_FORWARD_IF_FALSE to 566
 380: LOAD_GLOBAL          NULL + ord
 392: LOAD_FAST            self
 394: LOAD_METHOD          _Stream__read
 416: LOAD_CONST           1
 418: PRECALL              
 422: CALL                 
 432: PRECALL              
 436: CALL                 
 446: LOAD_CONST           256
 448: LOAD_GLOBAL          NULL + ord
 460: LOAD_FAST            self
 462: LOAD_METHOD          _Stream__read
 484: LOAD_CONST           1
 486: PRECALL              
 490: CALL                 
 500: PRECALL              
 504: CALL                 
 514: BINARY_OP            *
 518: BINARY_OP            +
 522: STORE_FAST           xlen
 524: LOAD_FAST            self
 526: LOAD_METHOD          read
 548: LOAD_FAST            xlen
 550: PRECALL              
 554: CALL                 
 564: POP_TOP              
 566: LOAD_FAST            flag
 568: LOAD_CONST           8
 570: BINARY_OP            &
 574: POP_JUMP_FORWARD_IF_FALSE to 650
 576: NOP                  
 578: LOAD_FAST            self
 580: LOAD_METHOD          _Stream__read
 602: LOAD_CONST           1
 604: PRECALL              
 608: CALL                 
 618: STORE_FAST           s
 620: LOAD_FAST            s
 622: POP_JUMP_FORWARD_IF_FALSE to 646
 624: LOAD_FAST            s
 626: LOAD_GLOBAL          NUL
 638: COMPARE_OP           ==
 644: POP_JUMP_FORWARD_IF_FALSE to 648
 646: JUMP_FORWARD         to 650
 648: JUMP_BACKWARD        to 578
 650: LOAD_FAST            flag
 652: LOAD_CONST           16
 654: BINARY_OP            &
 658: POP_JUMP_FORWARD_IF_FALSE to 734
 660: NOP                  
 662: LOAD_FAST            self
 664: LOAD_METHOD          _Stream__read
 686: LOAD_CONST           1
 688: PRECALL              
 692: CALL                 
 702: STORE_FAST           s
 704: LOAD_FAST            s
 706: POP_JUMP_FORWARD_IF_FALSE to 730
 708: LOAD_FAST            s
 710: LOAD_GLOBAL          NUL
 722: COMPARE_OP           ==
 728: POP_JUMP_FORWARD_IF_FALSE to 732
 730: JUMP_FORWARD         to 734
 732: JUMP_BACKWARD        to 662
 734: LOAD_FAST            flag
 736: LOAD_CONST           2
 738: BINARY_OP            &
 742: POP_JUMP_FORWARD_IF_FALSE to 790
 744: LOAD_FAST            self
 746: LOAD_METHOD          _Stream__read
 768: LOAD_CONST           2
 770: PRECALL              
 774: CALL                 
 784: POP_TOP              
 786: LOAD_CONST           None
 788: RETURN_VALUE         
 790: LOAD_CONST           None
 792: RETURN_VALUE         
