# Disassembly for tarfile.TarFile.open
# From module file: tarfile

## co_consts:
("Open a tar archive for reading, writing or appending. Return\n           an appropriate TarFile class.\n\n           mode:\n           'r' or 'r:*' open for reading with transparent compression\n           'r:'         open for reading exclusively uncompressed\n           'r:gz'       open for reading with gzip compression\n           'r:bz2'      open for reading with bzip2 compression\n           'r:xz'       open for reading with lzma compression\n           'a' or 'a:'  open for appending, creating the file if necessary\n           'w' or 'w:'  open for writing without compression\n           'w:gz'       open for writing with gzip compression\n           'w:bz2'      open for writing with bzip2 compression\n           'w:xz'       open for writing with lzma compression\n\n           'x' or 'x:'  create a tarfile exclusively without compression, raise\n                        an exception if the file is already created\n           'x:gz'       create a gzip compressed tarfile, raise an exception\n                        if the file is already created\n           'x:bz2'      create a bzip2 compressed tarfile, raise an exception\n                        if the file is already created\n           'x:xz'       create an lzma compressed tarfile, raise an exception\n                        if the file is already created\n\n           'r|*'        open a stream of tar blocks with transparent compression\n           'r|'         open an uncompressed stream of tar blocks for reading\n           'r|gz'       open a gzip compressed stream of tar blocks\n           'r|bz2'      open a bzip2 compressed stream of tar blocks\n           'r|xz'       open an lzma compressed stream of tar blocks\n           'w|'         open an uncompressed stream for writing\n           'w|gz'       open a gzip compressed stream for writing\n           'w|bz2'      open a bzip2 compressed stream for writing\n           'w|xz'       open an lzma compressed stream for writing\n        ", 'nothing to open', ('r', 'r:*'), <code object not_compressed at 0x00000240694666B0, file "tarfile.py", line 1796>, ('key',), None, 'r', '- method ', ': ', '\n', 'file could not be opened successfully:\n', ':', 1, 'tar', 'unknown compression type %r', '|', ('r', 'w'), "mode must be 'r' or 'w'", False, ('a', 'w', 'x'), 'undiscernible mode')

## co_names:
('ValueError', 'sorted', 'OPEN_METH', 'getattr', 'tell', 'ReadError', 'CompressionError', 'append', 'seek', 'join', 'split', '_Stream', 'close', '_extfileobj', 'taropen')

## bytecode:

   0: MAKE_CELL            cls
   2: RESUME               
   4: LOAD_FAST            name
   6: POP_JUMP_FORWARD_IF_TRUE to 42
   8: LOAD_FAST            fileobj
  10: POP_JUMP_FORWARD_IF_TRUE to 42
  12: LOAD_GLOBAL          NULL + ValueError
  24: LOAD_CONST           'nothing to open'
  26: PRECALL              
  30: CALL                 
  40: RAISE_VARARGS        
  42: LOAD_FAST            mode
  44: LOAD_CONST           ('r', 'r:*')
  46: CONTAINS_OP          
  48: POP_JUMP_FORWARD_IF_FALSE to 476
  50: LOAD_CLOSURE         cls
  52: BUILD_TUPLE          
  54: LOAD_CONST           <code object not_compressed at 0x00000240694666B0, file "tarfile.py", line 1796>
  56: MAKE_FUNCTION        closure
  58: STORE_FAST           not_compressed
  60: BUILD_LIST           
  62: STORE_FAST           error_msgs
  64: LOAD_GLOBAL          NULL + sorted
  76: LOAD_DEREF           cls
  78: LOAD_ATTR            OPEN_METH
  88: LOAD_FAST            not_compressed
  90: KW_NAMES             
  92: PRECALL              
  96: CALL                 
 106: GET_ITER             
 108: FOR_ITER             to 398
 110: STORE_FAST           comptype
 112: LOAD_GLOBAL          NULL + getattr
 124: LOAD_DEREF           cls
 126: LOAD_DEREF           cls
 128: LOAD_ATTR            OPEN_METH
 138: LOAD_FAST            comptype
 140: BINARY_SUBSCR        
 150: PRECALL              
 154: CALL                 
 164: STORE_FAST           func
 166: LOAD_FAST            fileobj
 168: POP_JUMP_FORWARD_IF_NONE to 210
 170: LOAD_FAST            fileobj
 172: LOAD_METHOD          tell
 194: PRECALL              
 198: CALL                 
 208: STORE_FAST           saved_pos
 210: NOP                  
 212: PUSH_NULL            
 214: LOAD_FAST            func
 216: LOAD_FAST            name
 218: LOAD_CONST           'r'
 220: LOAD_FAST            fileobj
 222: BUILD_TUPLE          
 224: BUILD_MAP            
 226: LOAD_FAST            kwargs
 228: DICT_MERGE           
 230: CALL_FUNCTION_EX     
 232: SWAP                 
 234: POP_TOP              
 236: RETURN_VALUE         
 238: PUSH_EXC_INFO        
 240: LOAD_GLOBAL          ReadError
 252: LOAD_GLOBAL          CompressionError
 264: BUILD_TUPLE          
 266: CHECK_EXC_MATCH      
 268: POP_JUMP_FORWARD_IF_FALSE to 390
 270: STORE_FAST           e
 272: LOAD_FAST            error_msgs
 274: LOAD_METHOD          append
 296: LOAD_CONST           '- method '
 298: LOAD_FAST            comptype
 300: FORMAT_VALUE         
 302: LOAD_CONST           ': '
 304: LOAD_FAST            e
 306: FORMAT_VALUE         repr
 308: BUILD_STRING         
 310: PRECALL              
 314: CALL                 
 324: POP_TOP              
 326: LOAD_FAST            fileobj
 328: POP_JUMP_FORWARD_IF_NONE to 372
 330: LOAD_FAST            fileobj
 332: LOAD_METHOD          seek
 354: LOAD_FAST            saved_pos
 356: PRECALL              
 360: CALL                 
 370: POP_TOP              
 372: POP_EXCEPT           
 374: LOAD_CONST           None
 376: STORE_FAST           e
 378: DELETE_FAST          e
 380: JUMP_BACKWARD        to 108
 382: LOAD_CONST           None
 384: STORE_FAST           e
 386: DELETE_FAST          e
 388: RERAISE              
 390: RERAISE              
 392: COPY                 
 394: POP_EXCEPT           
 396: RERAISE              
 398: LOAD_CONST           '\n'
 400: LOAD_METHOD          join
 422: LOAD_FAST            error_msgs
 424: PRECALL              
 428: CALL                 
 438: STORE_FAST           error_msgs_summary
 440: LOAD_GLOBAL          NULL + ReadError
 452: LOAD_CONST           'file could not be opened successfully:\n'
 454: LOAD_FAST            error_msgs_summary
 456: FORMAT_VALUE         
 458: BUILD_STRING         
 460: PRECALL              
 464: CALL                 
 474: RAISE_VARARGS        
 476: LOAD_CONST           ':'
 478: LOAD_FAST            mode
 480: CONTAINS_OP          
 482: POP_JUMP_FORWARD_IF_FALSE to 682
 484: LOAD_FAST            mode
 486: LOAD_METHOD          split
 508: LOAD_CONST           ':'
 510: LOAD_CONST           1
 512: PRECALL              
 516: CALL                 
 526: UNPACK_SEQUENCE      
 530: STORE_FAST           filemode
 532: STORE_FAST           comptype
 534: LOAD_FAST            filemode
 536: JUMP_IF_TRUE_OR_POP  to 540
 538: LOAD_CONST           'r'
 540: STORE_FAST           filemode
 542: LOAD_FAST            comptype
 544: JUMP_IF_TRUE_OR_POP  to 548
 546: LOAD_CONST           'tar'
 548: STORE_FAST           comptype
 550: LOAD_FAST            comptype
 552: LOAD_DEREF           cls
 554: LOAD_ATTR            OPEN_METH
 564: CONTAINS_OP          
 566: POP_JUMP_FORWARD_IF_FALSE to 624
 568: LOAD_GLOBAL          NULL + getattr
 580: LOAD_DEREF           cls
 582: LOAD_DEREF           cls
 584: LOAD_ATTR            OPEN_METH
 594: LOAD_FAST            comptype
 596: BINARY_SUBSCR        
 606: PRECALL              
 610: CALL                 
 620: STORE_FAST           func
 622: JUMP_FORWARD         to 660
 624: LOAD_GLOBAL          NULL + CompressionError
 636: LOAD_CONST           'unknown compression type %r'
 638: LOAD_FAST            comptype
 640: BINARY_OP            %
 644: PRECALL              
 648: CALL                 
 658: RAISE_VARARGS        
 660: PUSH_NULL            
 662: LOAD_FAST            func
 664: LOAD_FAST            name
 666: LOAD_FAST            filemode
 668: LOAD_FAST            fileobj
 670: BUILD_TUPLE          
 672: BUILD_MAP            
 674: LOAD_FAST            kwargs
 676: DICT_MERGE           
 678: CALL_FUNCTION_EX     
 680: RETURN_VALUE         
 682: LOAD_CONST           '|'
 684: LOAD_FAST            mode
 686: CONTAINS_OP          
 688: POP_JUMP_FORWARD_IF_FALSE to 928
 690: LOAD_FAST            mode
 692: LOAD_METHOD          split
 714: LOAD_CONST           '|'
 716: LOAD_CONST           1
 718: PRECALL              
 722: CALL                 
 732: UNPACK_SEQUENCE      
 736: STORE_FAST           filemode
 738: STORE_FAST           comptype
 740: LOAD_FAST            filemode
 742: JUMP_IF_TRUE_OR_POP  to 746
 744: LOAD_CONST           'r'
 746: STORE_FAST           filemode
 748: LOAD_FAST            comptype
 750: JUMP_IF_TRUE_OR_POP  to 754
 752: LOAD_CONST           'tar'
 754: STORE_FAST           comptype
 756: LOAD_FAST            filemode
 758: LOAD_CONST           ('r', 'w')
 760: CONTAINS_OP          
 762: POP_JUMP_FORWARD_IF_FALSE to 794
 764: LOAD_GLOBAL          NULL + ValueError
 776: LOAD_CONST           "mode must be 'r' or 'w'"
 778: PRECALL              
 782: CALL                 
 792: RAISE_VARARGS        
 794: LOAD_GLOBAL          NULL + _Stream
 806: LOAD_FAST            name
 808: LOAD_FAST            filemode
 810: LOAD_FAST            comptype
 812: LOAD_FAST            fileobj
 814: LOAD_FAST            bufsize
 816: PRECALL              
 820: CALL                 
 830: STORE_FAST           stream
 832: NOP                  
 834: PUSH_NULL            
 836: LOAD_DEREF           cls
 838: LOAD_FAST            name
 840: LOAD_FAST            filemode
 842: LOAD_FAST            stream
 844: BUILD_TUPLE          
 846: BUILD_MAP            
 848: LOAD_FAST            kwargs
 850: DICT_MERGE           
 852: CALL_FUNCTION_EX     
 854: STORE_FAST           t
 856: JUMP_FORWARD         to 910
 858: PUSH_EXC_INFO        
 860: POP_TOP              
 862: LOAD_FAST            stream
 864: LOAD_METHOD          close
 886: PRECALL              
 890: CALL                 
 900: POP_TOP              
 902: RAISE_VARARGS        
 904: COPY                 
 906: POP_EXCEPT           
 908: RERAISE              
 910: LOAD_CONST           False
 912: LOAD_FAST            t
 914: STORE_ATTR           _extfileobj
 924: LOAD_FAST            t
 926: RETURN_VALUE         
 928: LOAD_FAST            mode
 930: LOAD_CONST           ('a', 'w', 'x')
 932: CONTAINS_OP          
 934: POP_JUMP_FORWARD_IF_FALSE to 968
 936: PUSH_NULL            
 938: LOAD_DEREF           cls
 940: LOAD_ATTR            taropen
 950: LOAD_FAST            name
 952: LOAD_FAST            mode
 954: LOAD_FAST            fileobj
 956: BUILD_TUPLE          
 958: BUILD_MAP            
 960: LOAD_FAST            kwargs
 962: DICT_MERGE           
 964: CALL_FUNCTION_EX     
 966: RETURN_VALUE         
 968: LOAD_GLOBAL          NULL + ValueError
 980: LOAD_CONST           'undiscernible mode'
 982: PRECALL              
 986: CALL                 
 996: RAISE_VARARGS        
