# Disassembly for tarfile.TarFile.getmember
# From module file: tarfile

## co_consts:
("Return a TarInfo object for member `name'. If `name' can not be\n           found in the archive, KeyError is raised. If a member occurs more\n           than once in the archive, its last occurrence is assumed to be the\n           most up-to-date version.\n        ", '/', None, 'filename %r not found')

## co_names:
('_getmember', 'rstrip', 'KeyError')

## bytecode:

   0: RESUME               
   2: LOAD_FAST            self
   4: LOAD_METHOD          _getmember
  26: LOAD_FAST            name
  28: LOAD_METHOD          rstrip
  50: LOAD_CONST           '/'
  52: PRECALL              
  56: CALL                 
  66: PRECALL              
  70: CALL                 
  80: STORE_FAST           tarinfo
  82: LOAD_FAST            tarinfo
  84: POP_JUMP_FORWARD_IF_NOT_NONE to 122
  86: LOAD_GLOBAL          NULL + KeyError
  98: LOAD_CONST           'filename %r not found'
 100: LOAD_FAST            name
 102: BINARY_OP            %
 106: PRECALL              
 110: CALL                 
 120: RAISE_VARARGS        
 122: LOAD_FAST            tarinfo
 124: RETURN_VALUE         
