# Disassembly for tarfile.TarInfo._proc_gnusparse_01
# From module file: tarfile

## co_consts:
('Process a GNU tar extended sparse header, version 0.1.\n        ', <code object <listcomp> at 0x000002406945DB60, file "tarfile.py", line 1516>, 'GNU.sparse.map', ',', None, 2, 1)

## co_names:
('split', 'list', 'zip', 'sparse')

## bytecode:

   0: RESUME               
   2: LOAD_CONST           <code object <listcomp> at 0x000002406945DB60, file "tarfile.py", line 1516>
   4: MAKE_FUNCTION        
   6: LOAD_FAST            pax_headers
   8: LOAD_CONST           'GNU.sparse.map'
  10: BINARY_SUBSCR        
  20: LOAD_METHOD          split
  42: LOAD_CONST           ','
  44: PRECALL              
  48: CALL                 
  58: GET_ITER             
  60: PRECALL              
  64: CALL                 
  74: STORE_FAST           sparse
  76: LOAD_GLOBAL          NULL + list
  88: LOAD_GLOBAL          NULL + zip
 100: LOAD_FAST            sparse
 102: LOAD_CONST           None
 104: LOAD_CONST           None
 106: LOAD_CONST           2
 108: BUILD_SLICE          
 110: BINARY_SUBSCR        
 120: LOAD_FAST            sparse
 122: LOAD_CONST           1
 124: LOAD_CONST           None
 126: LOAD_CONST           2
 128: BUILD_SLICE          
 130: BINARY_SUBSCR        
 140: PRECALL              
 144: CALL                 
 154: PRECALL              
 158: CALL                 
 168: LOAD_FAST            next
 170: STORE_ATTR           sparse
 180: LOAD_CONST           None
 182: RETURN_VALUE         
