# Disassembly for tarfile._Stream.__init__
# From module file: tarfile

## co_consts:
('Construct a _Stream object.\n        ', True, None, False, '*', '', b'', 0, 'gz', 'zlib module is not available', 'r', 'bz2', 'bz2 module is not available', 'xz', 'lzma module is not available', 'tar', 'unknown compression type %r')

## co_names:
('_extfileobj', '_LowLevelFile', '_StreamProxy', 'getcomptype', 'name', 'mode', 'comptype', 'fileobj', 'bufsize', 'buf', 'pos', 'closed', 'zlib', 'ImportError', 'CompressionError', 'crc32', 'crc', 'error', 'exception', '_init_read_gz', '_init_write_gz', 'bz2', 'dbuf', 'BZ2Decompressor', 'cmp', 'OSError', 'BZ2Compressor', 'lzma', 'LZMADecompressor', 'LZMAError', 'LZMACompressor', 'close')

## bytecode:

   0: RESUME               
   2: LOAD_CONST           True
   4: LOAD_FAST            self
   6: STORE_ATTR           _extfileobj
  16: LOAD_FAST            fileobj
  18: POP_JUMP_FORWARD_IF_NOT_NONE to 66
  20: LOAD_GLOBAL          NULL + _LowLevelFile
  32: LOAD_FAST            name
  34: LOAD_FAST            mode
  36: PRECALL              
  40: CALL                 
  50: STORE_FAST           fileobj
  52: LOAD_CONST           False
  54: LOAD_FAST            self
  56: STORE_ATTR           _extfileobj
  66: LOAD_FAST            comptype
  68: LOAD_CONST           '*'
  70: COMPARE_OP           ==
  76: POP_JUMP_FORWARD_IF_FALSE to 148
  78: LOAD_GLOBAL          NULL + _StreamProxy
  90: LOAD_FAST            fileobj
  92: PRECALL              
  96: CALL                 
 106: STORE_FAST           fileobj
 108: LOAD_FAST            fileobj
 110: LOAD_METHOD          getcomptype
 132: PRECALL              
 136: CALL                 
 146: STORE_FAST           comptype
 148: LOAD_FAST            name
 150: JUMP_IF_TRUE_OR_POP  to 154
 152: LOAD_CONST           ''
 154: LOAD_FAST            self
 156: STORE_ATTR           name
 166: LOAD_FAST            mode
 168: LOAD_FAST            self
 170: STORE_ATTR           mode
 180: LOAD_FAST            comptype
 182: LOAD_FAST            self
 184: STORE_ATTR           comptype
 194: LOAD_FAST            fileobj
 196: LOAD_FAST            self
 198: STORE_ATTR           fileobj
 208: LOAD_FAST            bufsize
 210: LOAD_FAST            self
 212: STORE_ATTR           bufsize
 222: LOAD_CONST           b''
 224: LOAD_FAST            self
 226: STORE_ATTR           buf
 236: LOAD_CONST           0
 238: LOAD_FAST            self
 240: STORE_ATTR           pos
 250: LOAD_CONST           False
 252: LOAD_FAST            self
 254: STORE_ATTR           closed
 264: NOP                  
 266: LOAD_FAST            comptype
 268: LOAD_CONST           'gz'
 270: COMPARE_OP           ==
 276: POP_JUMP_FORWARD_IF_FALSE to 540
 278: NOP                  
 280: LOAD_CONST           0
 282: LOAD_CONST           None
 284: IMPORT_NAME          zlib
 286: STORE_FAST           zlib
 288: JUMP_FORWARD         to 350
 290: PUSH_EXC_INFO        
 292: LOAD_GLOBAL          ImportError
 304: CHECK_EXC_MATCH      
 306: POP_JUMP_FORWARD_IF_FALSE to 342
 308: POP_TOP              
 310: LOAD_GLOBAL          NULL + CompressionError
 322: LOAD_CONST           'zlib module is not available'
 324: PRECALL              
 328: CALL                 
 338: LOAD_CONST           None
 340: RAISE_VARARGS        
 342: RERAISE              
 344: COPY                 
 346: POP_EXCEPT           
 348: RERAISE              
 350: LOAD_FAST            zlib
 352: LOAD_FAST            self
 354: STORE_ATTR           zlib
 364: LOAD_FAST            zlib
 366: LOAD_METHOD          crc32
 388: LOAD_CONST           b''
 390: PRECALL              
 394: CALL                 
 404: LOAD_FAST            self
 406: STORE_ATTR           crc
 416: LOAD_FAST            mode
 418: LOAD_CONST           'r'
 420: COMPARE_OP           ==
 426: POP_JUMP_FORWARD_IF_FALSE to 496
 428: LOAD_FAST            zlib
 430: LOAD_ATTR            error
 440: LOAD_FAST            self
 442: STORE_ATTR           exception
 452: LOAD_FAST            self
 454: LOAD_METHOD          _init_read_gz
 476: PRECALL              
 480: CALL                 
 490: POP_TOP              
 492: LOAD_CONST           None
 494: RETURN_VALUE         
 496: LOAD_FAST            self
 498: LOAD_METHOD          _init_write_gz
 520: PRECALL              
 524: CALL                 
 534: POP_TOP              
 536: LOAD_CONST           None
 538: RETURN_VALUE         
 540: LOAD_FAST            comptype
 542: LOAD_CONST           'bz2'
 544: COMPARE_OP           ==
 550: POP_JUMP_FORWARD_IF_FALSE to 782
 552: NOP                  
 554: LOAD_CONST           0
 556: LOAD_CONST           None
 558: IMPORT_NAME          bz2
 560: STORE_FAST           bz2
 562: JUMP_FORWARD         to 624
 564: PUSH_EXC_INFO        
 566: LOAD_GLOBAL          ImportError
 578: CHECK_EXC_MATCH      
 580: POP_JUMP_FORWARD_IF_FALSE to 616
 582: POP_TOP              
 584: LOAD_GLOBAL          NULL + CompressionError
 596: LOAD_CONST           'bz2 module is not available'
 598: PRECALL              
 602: CALL                 
 612: LOAD_CONST           None
 614: RAISE_VARARGS        
 616: RERAISE              
 618: COPY                 
 620: POP_EXCEPT           
 622: RERAISE              
 624: LOAD_FAST            mode
 626: LOAD_CONST           'r'
 628: COMPARE_OP           ==
 634: POP_JUMP_FORWARD_IF_FALSE to 728
 636: LOAD_CONST           b''
 638: LOAD_FAST            self
 640: STORE_ATTR           dbuf
 650: LOAD_FAST            bz2
 652: LOAD_METHOD          BZ2Decompressor
 674: PRECALL              
 678: CALL                 
 688: LOAD_FAST            self
 690: STORE_ATTR           cmp
 700: LOAD_GLOBAL          OSError
 712: LOAD_FAST            self
 714: STORE_ATTR           exception
 724: LOAD_CONST           None
 726: RETURN_VALUE         
 728: LOAD_FAST            bz2
 730: LOAD_METHOD          BZ2Compressor
 752: PRECALL              
 756: CALL                 
 766: LOAD_FAST            self
 768: STORE_ATTR           cmp
 778: LOAD_CONST           None
 780: RETURN_VALUE         
 782: LOAD_FAST            comptype
 784: LOAD_CONST           'xz'
 786: COMPARE_OP           ==
 792: POP_JUMP_FORWARD_IF_FALSE to 1024
 794: NOP                  
 796: LOAD_CONST           0
 798: LOAD_CONST           None
 800: IMPORT_NAME          lzma
 802: STORE_FAST           lzma
 804: JUMP_FORWARD         to 866
 806: PUSH_EXC_INFO        
 808: LOAD_GLOBAL          ImportError
 820: CHECK_EXC_MATCH      
 822: POP_JUMP_FORWARD_IF_FALSE to 858
 824: POP_TOP              
 826: LOAD_GLOBAL          NULL + CompressionError
 838: LOAD_CONST           'lzma module is not available'
 840: PRECALL              
 844: CALL                 
 854: LOAD_CONST           None
 856: RAISE_VARARGS        
 858: RERAISE              
 860: COPY                 
 862: POP_EXCEPT           
 864: RERAISE              
 866: LOAD_FAST            mode
 868: LOAD_CONST           'r'
 870: COMPARE_OP           ==
 876: POP_JUMP_FORWARD_IF_FALSE to 970
 878: LOAD_CONST           b''
 880: LOAD_FAST            self
 882: STORE_ATTR           dbuf
 892: LOAD_FAST            lzma
 894: LOAD_METHOD          LZMADecompressor
 916: PRECALL              
 920: CALL                 
 930: LOAD_FAST            self
 932: STORE_ATTR           cmp
 942: LOAD_FAST            lzma
 944: LOAD_ATTR            LZMAError
 954: LOAD_FAST            self
 956: STORE_ATTR           exception
 966: LOAD_CONST           None
 968: RETURN_VALUE         
 970: LOAD_FAST            lzma
 972: LOAD_METHOD          LZMACompressor
 994: PRECALL              
 998: CALL                 
1008: LOAD_FAST            self
1010: STORE_ATTR           cmp
1020: LOAD_CONST           None
1022: RETURN_VALUE         
1024: LOAD_FAST            comptype
1026: LOAD_CONST           'tar'
1028: COMPARE_OP           !=
1034: POP_JUMP_FORWARD_IF_FALSE to 1072
1036: LOAD_GLOBAL          NULL + CompressionError
1048: LOAD_CONST           'unknown compression type %r'
1050: LOAD_FAST            comptype
1052: BINARY_OP            %
1056: PRECALL              
1060: CALL                 
1070: RAISE_VARARGS        
1072: LOAD_CONST           None
1074: RETURN_VALUE         
1076: PUSH_EXC_INFO        
1078: POP_TOP              
1080: LOAD_FAST            self
1082: LOAD_ATTR            _extfileobj
1092: POP_JUMP_FORWARD_IF_TRUE to 1144
1094: LOAD_FAST            self
1096: LOAD_ATTR            fileobj
1106: LOAD_METHOD          close
1128: PRECALL              
1132: CALL                 
1142: POP_TOP              
1144: LOAD_CONST           True
1146: LOAD_FAST            self
1148: STORE_ATTR           closed
1158: RAISE_VARARGS        
1160: COPY                 
1162: POP_EXCEPT           
1164: RERAISE              
