# Disassembly for tarfile.TarFile.makedir
# From module file: tarfile

## co_consts:
('Make a directory called targetpath.\n        ', None, 448)

## co_names:
('mode', 'os', 'mkdir', 'FileExistsError')

## bytecode:

   0: RESUME               
   2: NOP                  
   4: LOAD_FAST            tarinfo
   6: LOAD_ATTR            mode
  16: POP_JUMP_FORWARD_IF_NOT_NONE to 62
  18: LOAD_GLOBAL          NULL + os
  30: LOAD_ATTR            mkdir
  40: LOAD_FAST            targetpath
  42: PRECALL              
  46: CALL                 
  56: POP_TOP              
  58: LOAD_CONST           None
  60: RETURN_VALUE         
  62: LOAD_GLOBAL          NULL + os
  74: LOAD_ATTR            mkdir
  84: LOAD_FAST            targetpath
  86: LOAD_CONST           448
  88: PRECALL              
  92: CALL                 
 102: POP_TOP              
 104: LOAD_CONST           None
 106: RETURN_VALUE         
 108: PUSH_EXC_INFO        
 110: LOAD_GLOBAL          FileExistsError
 122: CHECK_EXC_MATCH      
 124: POP_JUMP_FORWARD_IF_FALSE to 134
 126: POP_TOP              
 128: POP_EXCEPT           
 130: LOAD_CONST           None
 132: RETURN_VALUE         
 134: RERAISE              
 136: COPY                 
 138: POP_EXCEPT           
 140: RERAISE              
