# Disassembly for tarfile._Stream
# From module file: tarfile

## co_consts:
('_Stream', 'Class that serves as an adapter between TarFile and\n       a stream-like object.  The stream-like object only\n       needs to have a read() or write() method and is accessed\n       blockwise.  Use of gzip or bzip2 compression is possible.\n       A stream-like object could be for example: sys.stdin,\n       sys.stdout, a socket, a tape device etc.\n\n       _Stream is intended to be used only internally.\n    ', <code object __init__ at 0x0000024068E11050, file "tarfile.py", line 343>, <code object __del__ at 0x000002406941B510, file "tarfile.py", line 413>, <code object _init_write_gz at 0x0000024068B3F550, file "tarfile.py", line 417>, <code object write at 0x00000240691DBC00, file "tarfile.py", line 433>, <code object __write at 0x000002406947CB70, file "tarfile.py", line 443>, <code object close at 0x0000024068B39060, file "tarfile.py", line 452>, <code object _init_read_gz at 0x00000240695941C0, file "tarfile.py", line 474>, <code object tell at 0x00000240694968D0, file "tarfile.py", line 505>, 0, <code object seek at 0x00000240691DBA30, file "tarfile.py", line 510>, <code object read at 0x00000240693D2D50, file "tarfile.py", line 523>, <code object _read at 0x0000024068DBE910, file "tarfile.py", line 530>, <code object __read at 0x000002406931F630, file "tarfile.py", line 557>, None, (0,))

## co_names:
('__name__', '__module__', '__qualname__', '__doc__', '__init__', '__del__', '_init_write_gz', 'write', '_Stream__write', 'close', '_init_read_gz', 'tell', 'seek', 'read', '_read', '_Stream__read')

## bytecode:

   0: RESUME               
   2: LOAD_NAME            __name__
   4: STORE_NAME           __module__
   6: LOAD_CONST           '_Stream'
   8: STORE_NAME           __qualname__
  10: LOAD_CONST           'Class that serves as an adapter between TarFile and\n       a stream-like object.  The stream-like object only\n       needs to have a read() or write() method and is accessed\n       blockwise.  Use of gzip or bzip2 compression is possible.\n       A stream-like object could be for example: sys.stdin,\n       sys.stdout, a socket, a tape device etc.\n\n       _Stream is intended to be used only internally.\n    '
  12: STORE_NAME           __doc__
  14: LOAD_CONST           <code object __init__ at 0x0000024068E11050, file "tarfile.py", line 343>
  16: MAKE_FUNCTION        
  18: STORE_NAME           __init__
  20: LOAD_CONST           <code object __del__ at 0x000002406941B510, file "tarfile.py", line 413>
  22: MAKE_FUNCTION        
  24: STORE_NAME           __del__
  26: LOAD_CONST           <code object _init_write_gz at 0x0000024068B3F550, file "tarfile.py", line 417>
  28: MAKE_FUNCTION        
  30: STORE_NAME           _init_write_gz
  32: LOAD_CONST           <code object write at 0x00000240691DBC00, file "tarfile.py", line 433>
  34: MAKE_FUNCTION        
  36: STORE_NAME           write
  38: LOAD_CONST           <code object __write at 0x000002406947CB70, file "tarfile.py", line 443>
  40: MAKE_FUNCTION        
  42: STORE_NAME           _Stream__write
  44: LOAD_CONST           <code object close at 0x0000024068B39060, file "tarfile.py", line 452>
  46: MAKE_FUNCTION        
  48: STORE_NAME           close
  50: LOAD_CONST           <code object _init_read_gz at 0x00000240695941C0, file "tarfile.py", line 474>
  52: MAKE_FUNCTION        
  54: STORE_NAME           _init_read_gz
  56: LOAD_CONST           <code object tell at 0x00000240694968D0, file "tarfile.py", line 505>
  58: MAKE_FUNCTION        
  60: STORE_NAME           tell
  62: LOAD_CONST           (0,)
  64: LOAD_CONST           <code object seek at 0x00000240691DBA30, file "tarfile.py", line 510>
  66: MAKE_FUNCTION        defaults
  68: STORE_NAME           seek
  70: LOAD_CONST           <code object read at 0x00000240693D2D50, file "tarfile.py", line 523>
  72: MAKE_FUNCTION        
  74: STORE_NAME           read
  76: LOAD_CONST           <code object _read at 0x0000024068DBE910, file "tarfile.py", line 530>
  78: MAKE_FUNCTION        
  80: STORE_NAME           _read
  82: LOAD_CONST           <code object __read at 0x000002406931F630, file "tarfile.py", line 557>
  84: MAKE_FUNCTION        
  86: STORE_NAME           _Stream__read
  88: LOAD_CONST           None
  90: RETURN_VALUE         
