# Disassembly for tarfile.TarInfo._proc_sparse
# From module file: tarfile

## co_consts:
('Process a GNU sparse header plus extra headers.\n        ', 0, 21, 12, 24, 504)

## co_names:
('_sparse_structs', 'fileobj', 'read', 'BLOCKSIZE', 'range', 'nti', 'ValueError', 'append', 'bool', 'sparse', 'tell', 'offset_data', '_block', 'size', 'offset')

## bytecode:

   0: RESUME               
   2: LOAD_FAST            self
   4: LOAD_ATTR            _sparse_structs
  14: UNPACK_SEQUENCE      
  18: STORE_FAST           structs
  20: STORE_FAST           isextended
  22: STORE_FAST           origsize
  24: LOAD_FAST            self
  26: DELETE_ATTR          _sparse_structs
  28: LOAD_FAST            isextended
  30: POP_JUMP_FORWARD_IF_FALSE to 392
  32: LOAD_FAST            tarfile
  34: LOAD_ATTR            fileobj
  44: LOAD_METHOD          read
  66: LOAD_GLOBAL          BLOCKSIZE
  78: PRECALL              
  82: CALL                 
  92: STORE_FAST           buf
  94: LOAD_CONST           0
  96: STORE_FAST           pos
  98: LOAD_GLOBAL          NULL + range
 110: LOAD_CONST           21
 112: PRECALL              
 116: CALL                 
 126: GET_ITER             
 128: FOR_ITER             to 346
 130: STORE_FAST           i
 132: NOP                  
 134: LOAD_GLOBAL          NULL + nti
 146: LOAD_FAST            buf
 148: LOAD_FAST            pos
 150: LOAD_FAST            pos
 152: LOAD_CONST           12
 154: BINARY_OP            +
 158: BUILD_SLICE          
 160: BINARY_SUBSCR        
 170: PRECALL              
 174: CALL                 
 184: STORE_FAST           offset
 186: LOAD_GLOBAL          NULL + nti
 198: LOAD_FAST            buf
 200: LOAD_FAST            pos
 202: LOAD_CONST           12
 204: BINARY_OP            +
 208: LOAD_FAST            pos
 210: LOAD_CONST           24
 212: BINARY_OP            +
 216: BUILD_SLICE          
 218: BINARY_SUBSCR        
 228: PRECALL              
 232: CALL                 
 242: STORE_FAST           numbytes
 244: JUMP_FORWARD         to 280
 246: PUSH_EXC_INFO        
 248: LOAD_GLOBAL          ValueError
 260: CHECK_EXC_MATCH      
 262: POP_JUMP_FORWARD_IF_FALSE to 272
 264: POP_TOP              
 266: POP_EXCEPT           
 268: POP_TOP              
 270: JUMP_FORWARD         to 346
 272: RERAISE              
 274: COPY                 
 276: POP_EXCEPT           
 278: RERAISE              
 280: LOAD_FAST            offset
 282: POP_JUMP_FORWARD_IF_FALSE to 334
 284: LOAD_FAST            numbytes
 286: POP_JUMP_FORWARD_IF_FALSE to 334
 288: LOAD_FAST            structs
 290: LOAD_METHOD          append
 312: LOAD_FAST            offset
 314: LOAD_FAST            numbytes
 316: BUILD_TUPLE          
 318: PRECALL              
 322: CALL                 
 332: POP_TOP              
 334: LOAD_FAST            pos
 336: LOAD_CONST           24
 338: BINARY_OP            +=
 342: STORE_FAST           pos
 344: JUMP_BACKWARD        to 128
 346: LOAD_GLOBAL          NULL + bool
 358: LOAD_FAST            buf
 360: LOAD_CONST           504
 362: BINARY_SUBSCR        
 372: PRECALL              
 376: CALL                 
 386: STORE_FAST           isextended
 388: LOAD_FAST            isextended
 390: POP_JUMP_BACKWARD_IF_TRUE to 32
 392: LOAD_FAST            structs
 394: LOAD_FAST            self
 396: STORE_ATTR           sparse
 406: LOAD_FAST            tarfile
 408: LOAD_ATTR            fileobj
 418: LOAD_METHOD          tell
 440: PRECALL              
 444: CALL                 
 454: LOAD_FAST            self
 456: STORE_ATTR           offset_data
 466: LOAD_FAST            self
 468: LOAD_ATTR            offset_data
 478: LOAD_FAST            self
 480: LOAD_METHOD          _block
 502: LOAD_FAST            self
 504: LOAD_ATTR            size
 514: PRECALL              
 518: CALL                 
 528: BINARY_OP            +
 532: LOAD_FAST            tarfile
 534: STORE_ATTR           offset
 544: LOAD_FAST            origsize
 546: LOAD_FAST            self
 548: STORE_ATTR           size
 558: LOAD_FAST            self
 560: RETURN_VALUE         
