# Disassembly for tarfile._Stream.write
# From module file: tarfile

## co_consts:
('Write string s to the stream.\n        ', 'gz', 'tar', None)

## co_names:
('comptype', 'zlib', 'crc32', 'crc', 'pos', 'len', 'cmp', 'compress', '_Stream__write')

## bytecode:

   0: RESUME               
   2: LOAD_FAST            self
   4: LOAD_ATTR            comptype
  14: LOAD_CONST           'gz'
  16: COMPARE_OP           ==
  22: POP_JUMP_FORWARD_IF_FALSE to 98
  24: LOAD_FAST            self
  26: LOAD_ATTR            zlib
  36: LOAD_METHOD          crc32
  58: LOAD_FAST            s
  60: LOAD_FAST            self
  62: LOAD_ATTR            crc
  72: PRECALL              
  76: CALL                 
  86: LOAD_FAST            self
  88: STORE_ATTR           crc
  98: LOAD_FAST            self
 100: COPY                 
 102: LOAD_ATTR            pos
 112: LOAD_GLOBAL          NULL + len
 124: LOAD_FAST            s
 126: PRECALL              
 130: CALL                 
 140: BINARY_OP            +=
 144: SWAP                 
 146: STORE_ATTR           pos
 156: LOAD_FAST            self
 158: LOAD_ATTR            comptype
 168: LOAD_CONST           'tar'
 170: COMPARE_OP           !=
 176: POP_JUMP_FORWARD_IF_FALSE to 230
 178: LOAD_FAST            self
 180: LOAD_ATTR            cmp
 190: LOAD_METHOD          compress
 212: LOAD_FAST            s
 214: PRECALL              
 218: CALL                 
 228: STORE_FAST           s
 230: LOAD_FAST            self
 232: LOAD_METHOD          _Stream__write
 254: LOAD_FAST            s
 256: PRECALL              
 260: CALL                 
 270: POP_TOP              
 272: LOAD_CONST           None
 274: RETURN_VALUE         
