# Disassembly for tarfile.TarInfo._proc_builtin
# From module file: tarfile

## co_consts:
('Process a builtin type or an unknown type which\n           will be treated as a regular file.\n        ', '/')

## co_names:
('fileobj', 'tell', 'offset_data', 'isreg', 'type', 'SUPPORTED_TYPES', '_block', 'size', 'offset', '_apply_pax_info', 'pax_headers', 'encoding', 'errors', 'isdir', 'name', 'rstrip')

## bytecode:

   0: RESUME               
   2: LOAD_FAST            tarfile
   4: LOAD_ATTR            fileobj
  14: LOAD_METHOD          tell
  36: PRECALL              
  40: CALL                 
  50: LOAD_FAST            self
  52: STORE_ATTR           offset_data
  62: LOAD_FAST            self
  64: LOAD_ATTR            offset_data
  74: STORE_FAST           offset
  76: LOAD_FAST            self
  78: LOAD_METHOD          isreg
 100: PRECALL              
 104: CALL                 
 114: POP_JUMP_FORWARD_IF_TRUE to 144
 116: LOAD_FAST            self
 118: LOAD_ATTR            type
 128: LOAD_GLOBAL          SUPPORTED_TYPES
 140: CONTAINS_OP          
 142: POP_JUMP_FORWARD_IF_FALSE to 202
 144: LOAD_FAST            offset
 146: LOAD_FAST            self
 148: LOAD_METHOD          _block
 170: LOAD_FAST            self
 172: LOAD_ATTR            size
 182: PRECALL              
 186: CALL                 
 196: BINARY_OP            +=
 200: STORE_FAST           offset
 202: LOAD_FAST            offset
 204: LOAD_FAST            tarfile
 206: STORE_ATTR           offset
 216: LOAD_FAST            self
 218: LOAD_METHOD          _apply_pax_info
 240: LOAD_FAST            tarfile
 242: LOAD_ATTR            pax_headers
 252: LOAD_FAST            tarfile
 254: LOAD_ATTR            encoding
 264: LOAD_FAST            tarfile
 266: LOAD_ATTR            errors
 276: PRECALL              
 280: CALL                 
 290: POP_TOP              
 292: LOAD_FAST            self
 294: LOAD_METHOD          isdir
 316: PRECALL              
 320: CALL                 
 330: POP_JUMP_FORWARD_IF_FALSE to 394
 332: LOAD_FAST            self
 334: LOAD_ATTR            name
 344: LOAD_METHOD          rstrip
 366: LOAD_CONST           '/'
 368: PRECALL              
 372: CALL                 
 382: LOAD_FAST            self
 384: STORE_ATTR           name
 394: LOAD_FAST            self
 396: RETURN_VALUE         
