# Disassembly for tarfile.TarFile._handle_nonfatal_error
# From module file: tarfile

## co_consts:
('Handle non-fatal error (ExtractError) according to errorlevel', 1, 'tarfile: %s', None)

## co_names:
('errorlevel', '_dbg')

## bytecode:

   0: RESUME               
   2: LOAD_FAST            self
   4: LOAD_ATTR            errorlevel
  14: LOAD_CONST           1
  16: COMPARE_OP           >
  22: POP_JUMP_FORWARD_IF_FALSE to 26
  24: RAISE_VARARGS        
  26: LOAD_FAST            self
  28: LOAD_METHOD          _dbg
  50: LOAD_CONST           1
  52: LOAD_CONST           'tarfile: %s'
  54: LOAD_FAST            e
  56: BINARY_OP            %
  60: PRECALL              
  64: CALL                 
  74: POP_TOP              
  76: LOAD_CONST           None
  78: RETURN_VALUE         
