# Disassembly for tarfile.TarFile._extract_one
# From module file: tarfile

## co_consts:
('Extract from filtered tarinfo to disk', 'r', ('set_attrs', 'numeric_owner'), None)

## co_names:
('_check', '_extract_member', 'os', 'path', 'join', 'name', 'OSError', '_handle_fatal_error', 'ExtractError', '_handle_nonfatal_error')

## bytecode:

   0: RESUME               
   2: LOAD_FAST            self
   4: LOAD_METHOD          _check
  26: LOAD_CONST           'r'
  28: PRECALL              
  32: CALL                 
  42: POP_TOP              
  44: NOP                  
  46: LOAD_FAST            self
  48: LOAD_METHOD          _extract_member
  70: LOAD_FAST            tarinfo
  72: LOAD_GLOBAL          os
  84: LOAD_ATTR            path
  94: LOAD_METHOD          join
 116: LOAD_FAST            path
 118: LOAD_FAST            tarinfo
 120: LOAD_ATTR            name
 130: PRECALL              
 134: CALL                 
 144: LOAD_FAST            set_attrs
 146: LOAD_FAST            numeric_owner
 148: KW_NAMES             
 150: PRECALL              
 154: CALL                 
 164: POP_TOP              
 166: LOAD_CONST           None
 168: RETURN_VALUE         
 170: PUSH_EXC_INFO        
 172: LOAD_GLOBAL          OSError
 184: CHECK_EXC_MATCH      
 186: POP_JUMP_FORWARD_IF_FALSE to 252
 188: STORE_FAST           e
 190: LOAD_FAST            self
 192: LOAD_METHOD          _handle_fatal_error
 214: LOAD_FAST            e
 216: PRECALL              
 220: CALL                 
 230: POP_TOP              
 232: POP_EXCEPT           
 234: LOAD_CONST           None
 236: STORE_FAST           e
 238: DELETE_FAST          e
 240: LOAD_CONST           None
 242: RETURN_VALUE         
 244: LOAD_CONST           None
 246: STORE_FAST           e
 248: DELETE_FAST          e
 250: RERAISE              
 252: LOAD_GLOBAL          ExtractError
 264: CHECK_EXC_MATCH      
 266: POP_JUMP_FORWARD_IF_FALSE to 332
 268: STORE_FAST           e
 270: LOAD_FAST            self
 272: LOAD_METHOD          _handle_nonfatal_error
 294: LOAD_FAST            e
 296: PRECALL              
 300: CALL                 
 310: POP_TOP              
 312: POP_EXCEPT           
 314: LOAD_CONST           None
 316: STORE_FAST           e
 318: DELETE_FAST          e
 320: LOAD_CONST           None
 322: RETURN_VALUE         
 324: LOAD_CONST           None
 326: STORE_FAST           e
 328: DELETE_FAST          e
 330: RERAISE              
 332: RERAISE              
 334: COPY                 
 336: POP_EXCEPT           
 338: RERAISE              
