# Disassembly for tarfile.TarFile.extractall
# From module file: tarfile

## co_consts:
("Extract all members from the archive to the current working\n           directory and set owner, modification time and permissions on\n           directories afterwards. `path' specifies a different directory\n           to extract to. `members' is optional and must be a subset of the\n           list returned by getmembers(). If `numeric_owner` is True, only\n           the numbers for user/group names are used and not the names.\n\n           The `filter` function will be called on each member just\n           before extraction.\n           It can return a changed TarInfo or None to skip the member.\n           String names of common filters are accepted.\n        ", None, ('set_attrs', 'numeric_owner'), <code object <lambda> at 0x0000024069496E80, file "tarfile.py", line 2268>, True, ('key', 'reverse'), ('numeric_owner',))

## co_names:
('_get_filter_function', '_get_extract_tarinfo', 'isdir', 'append', '_extract_one', 'sort', 'os', 'path', 'join', 'name', 'chown', 'utime', 'chmod', 'ExtractError', '_handle_nonfatal_error')

## bytecode:

   0: RESUME               
   2: BUILD_LIST           
   4: STORE_FAST           directories
   6: LOAD_FAST            self
   8: LOAD_METHOD          _get_filter_function
  30: LOAD_FAST            filter
  32: PRECALL              
  36: CALL                 
  46: STORE_FAST           filter_function
  48: LOAD_FAST            members
  50: POP_JUMP_FORWARD_IF_NOT_NONE to 56
  52: LOAD_FAST            self
  54: STORE_FAST           members
  56: LOAD_FAST            members
  58: GET_ITER             
  60: FOR_ITER             to 288
  62: STORE_FAST           member
  64: LOAD_FAST            self
  66: LOAD_METHOD          _get_extract_tarinfo
  88: LOAD_FAST            member
  90: LOAD_FAST            filter_function
  92: LOAD_FAST            path
  94: PRECALL              
  98: CALL                 
 108: STORE_FAST           tarinfo
 110: LOAD_FAST            tarinfo
 112: POP_JUMP_FORWARD_IF_NOT_NONE to 116
 114: JUMP_BACKWARD        to 60
 116: LOAD_FAST            tarinfo
 118: LOAD_METHOD          isdir
 140: PRECALL              
 144: CALL                 
 154: POP_JUMP_FORWARD_IF_FALSE to 198
 156: LOAD_FAST            directories
 158: LOAD_METHOD          append
 180: LOAD_FAST            tarinfo
 182: PRECALL              
 186: CALL                 
 196: POP_TOP              
 198: LOAD_FAST            self
 200: LOAD_METHOD          _extract_one
 222: LOAD_FAST            tarinfo
 224: LOAD_FAST            path
 226: LOAD_FAST            tarinfo
 228: LOAD_METHOD          isdir
 250: PRECALL              
 254: CALL                 
 264: UNARY_NOT            
 266: LOAD_FAST            numeric_owner
 268: KW_NAMES             
 270: PRECALL              
 274: CALL                 
 284: POP_TOP              
 286: JUMP_BACKWARD        to 60
 288: LOAD_FAST            directories
 290: LOAD_METHOD          sort
 312: LOAD_CONST           <code object <lambda> at 0x0000024069496E80, file "tarfile.py", line 2268>
 314: MAKE_FUNCTION        
 316: LOAD_CONST           True
 318: KW_NAMES             
 320: PRECALL              
 324: CALL                 
 334: POP_TOP              
 336: LOAD_FAST            directories
 338: GET_ITER             
 340: FOR_ITER             to 646
 342: STORE_FAST           tarinfo
 344: LOAD_GLOBAL          os
 356: LOAD_ATTR            path
 366: LOAD_METHOD          join
 388: LOAD_FAST            path
 390: LOAD_FAST            tarinfo
 392: LOAD_ATTR            name
 402: PRECALL              
 406: CALL                 
 416: STORE_FAST           dirpath
 418: NOP                  
 420: LOAD_FAST            self
 422: LOAD_METHOD          chown
 444: LOAD_FAST            tarinfo
 446: LOAD_FAST            dirpath
 448: LOAD_FAST            numeric_owner
 450: KW_NAMES             
 452: PRECALL              
 456: CALL                 
 466: POP_TOP              
 468: LOAD_FAST            self
 470: LOAD_METHOD          utime
 492: LOAD_FAST            tarinfo
 494: LOAD_FAST            dirpath
 496: PRECALL              
 500: CALL                 
 510: POP_TOP              
 512: LOAD_FAST            self
 514: LOAD_METHOD          chmod
 536: LOAD_FAST            tarinfo
 538: LOAD_FAST            dirpath
 540: PRECALL              
 544: CALL                 
 554: POP_TOP              
 556: JUMP_BACKWARD        to 340
 558: PUSH_EXC_INFO        
 560: LOAD_GLOBAL          ExtractError
 572: CHECK_EXC_MATCH      
 574: POP_JUMP_FORWARD_IF_FALSE to 638
 576: STORE_FAST           e
 578: LOAD_FAST            self
 580: LOAD_METHOD          _handle_nonfatal_error
 602: LOAD_FAST            e
 604: PRECALL              
 608: CALL                 
 618: POP_TOP              
 620: POP_EXCEPT           
 622: LOAD_CONST           None
 624: STORE_FAST           e
 626: DELETE_FAST          e
 628: JUMP_BACKWARD        to 340
 630: LOAD_CONST           None
 632: STORE_FAST           e
 634: DELETE_FAST          e
 636: RERAISE              
 638: RERAISE              
 640: COPY                 
 642: POP_EXCEPT           
 644: RERAISE              
 646: LOAD_CONST           None
 648: RETURN_VALUE         
