# Disassembly for tarfile.TarInfo.create_pax_global_header
# From module file: tarfile

## co_consts:
('Return the object as a pax global header block sequence.\n        ', 'utf-8')

## co_names:
('_create_pax_generic_header', 'XGLTYPE')

## bytecode:

   0: RESUME               
   2: LOAD_FAST            cls
   4: LOAD_METHOD          _create_pax_generic_header
  26: LOAD_FAST            pax_headers
  28: LOAD_GLOBAL          XGLTYPE
  40: LOAD_CONST           'utf-8'
  42: PRECALL              
  46: CALL                 
  56: RETURN_VALUE         
