# Disassembly for tarfile.TarFile._check
# From module file: tarfile

## co_consts:
("Check if TarFile is still open, and if the operation's mode\n           corresponds to TarFile's mode.\n        ", '%s is closed', None, 'bad operation for mode %r')

## co_names:
('closed', 'OSError', '__class__', '__name__', 'mode')

## bytecode:

   0: RESUME               
   2: LOAD_FAST            self
   4: LOAD_ATTR            closed
  14: POP_JUMP_FORWARD_IF_FALSE to 72
  16: LOAD_GLOBAL          NULL + OSError
  28: LOAD_CONST           '%s is closed'
  30: LOAD_FAST            self
  32: LOAD_ATTR            __class__
  42: LOAD_ATTR            __name__
  52: BINARY_OP            %
  56: PRECALL              
  60: CALL                 
  70: RAISE_VARARGS        
  72: LOAD_FAST            mode
  74: POP_JUMP_FORWARD_IF_NONE to 140
  76: LOAD_FAST            self
  78: LOAD_ATTR            mode
  88: LOAD_FAST            mode
  90: CONTAINS_OP          
  92: POP_JUMP_FORWARD_IF_FALSE to 144
  94: LOAD_GLOBAL          NULL + OSError
 106: LOAD_CONST           'bad operation for mode %r'
 108: LOAD_FAST            self
 110: LOAD_ATTR            mode
 120: BINARY_OP            %
 124: PRECALL              
 128: CALL                 
 138: RAISE_VARARGS        
 140: LOAD_CONST           None
 142: RETURN_VALUE         
 144: LOAD_CONST           None
 146: RETURN_VALUE         
