# Disassembly for tarfile.TarFile.makeunknown
# From module file: tarfile

## co_consts:
('Make a file from a TarInfo object with an unknown type\n           at targetpath.\n        ', 1, 'tarfile: Unknown file type %r, extracted as regular file.', None)

## co_names:
('makefile', '_dbg', 'type')

## bytecode:

   0: RESUME               
   2: LOAD_FAST            self
   4: LOAD_METHOD          makefile
  26: LOAD_FAST            tarinfo
  28: LOAD_FAST            targetpath
  30: PRECALL              
  34: CALL                 
  44: POP_TOP              
  46: LOAD_FAST            self
  48: LOAD_METHOD          _dbg
  70: LOAD_CONST           1
  72: LOAD_CONST           'tarfile: Unknown file type %r, extracted as regular file.'
  74: LOAD_FAST            tarinfo
  76: LOAD_ATTR            type
  86: BINARY_OP            %
  90: PRECALL              
  94: CALL                 
 104: POP_TOP              
 106: LOAD_CONST           None
 108: RETURN_VALUE         
