# Disassembly for subprocess.CalledProcessError.__init__
# From module file: subprocess

## co_consts:
(None,)

## co_names:
('returncode', 'cmd', 'output', 'stderr')

## bytecode:

   0: RESUME               
   2: LOAD_FAST            returncode
   4: LOAD_FAST            self
   6: STORE_ATTR           returncode
  16: LOAD_FAST            cmd
  18: LOAD_FAST            self
  20: STORE_ATTR           cmd
  30: LOAD_FAST            output
  32: LOAD_FAST            self
  34: STORE_ATTR           output
  44: LOAD_FAST            stderr
  46: LOAD_FAST            self
  48: STORE_ATTR           stderr
  58: LOAD_CONST           None
  60: RETURN_VALUE         
