# Disassembly for subprocess.Popen.wait
# From module file: subprocess

## co_consts:
('Wait for child process to terminate; returns self.returncode.', None, ('timeout',), 0)

## co_names:
('_time', '_wait', 'KeyboardInterrupt', 'min', '_sigint_wait_secs', '_remaining_time', 'TimeoutExpired')

## bytecode:

   0: RESUME               
   2: LOAD_FAST            timeout
   4: POP_JUMP_FORWARD_IF_NONE to 40
   6: LOAD_GLOBAL          NULL + _time
  18: PRECALL              
  22: CALL                 
  32: LOAD_FAST            timeout
  34: BINARY_OP            +
  38: STORE_FAST           endtime
  40: NOP                  
  42: LOAD_FAST            self
  44: LOAD_METHOD          _wait
  66: LOAD_FAST            timeout
  68: KW_NAMES             
  70: PRECALL              
  74: CALL                 
  84: RETURN_VALUE         
  86: PUSH_EXC_INFO        
  88: LOAD_GLOBAL          KeyboardInterrupt
 100: CHECK_EXC_MATCH      
 102: POP_JUMP_FORWARD_IF_FALSE to 302
 104: POP_TOP              
 106: LOAD_FAST            timeout
 108: POP_JUMP_FORWARD_IF_NONE to 192
 110: LOAD_GLOBAL          NULL + min
 122: LOAD_FAST            self
 124: LOAD_ATTR            _sigint_wait_secs
 134: LOAD_FAST            self
 136: LOAD_METHOD          _remaining_time
 158: LOAD_FAST            endtime
 160: PRECALL              
 164: CALL                 
 174: PRECALL              
 178: CALL                 
 188: STORE_FAST           sigint_timeout
 190: JUMP_FORWARD         to 206
 192: LOAD_FAST            self
 194: LOAD_ATTR            _sigint_wait_secs
 204: STORE_FAST           sigint_timeout
 206: LOAD_CONST           0
 208: LOAD_FAST            self
 210: STORE_ATTR           _sigint_wait_secs
 220: NOP                  
 222: LOAD_FAST            self
 224: LOAD_METHOD          _wait
 246: LOAD_FAST            sigint_timeout
 248: KW_NAMES             
 250: PRECALL              
 254: CALL                 
 264: POP_TOP              
 266: JUMP_FORWARD         to 300
 268: PUSH_EXC_INFO        
 270: LOAD_GLOBAL          TimeoutExpired
 282: CHECK_EXC_MATCH      
 284: POP_JUMP_FORWARD_IF_FALSE to 292
 286: POP_TOP              
 288: POP_EXCEPT           
 290: JUMP_FORWARD         to 300
 292: RERAISE              
 294: COPY                 
 296: POP_EXCEPT           
 298: RERAISE              
 300: RAISE_VARARGS        
 302: RERAISE              
 304: COPY                 
 306: POP_EXCEPT           
 308: RERAISE              
