# Disassembly for subprocess.TimeoutExpired
# From module file: subprocess

## co_consts:
('TimeoutExpired', 'This exception is raised when the timeout expires while waiting for a\n    child process.\n\n    Attributes:\n        cmd, output, stdout, stderr, timeout\n    ', None, <code object __init__ at 0x00000240693EB030, file "subprocess.py", line 170>, <code object __str__ at 0x0000024069465530, file "subprocess.py", line 176>, <code object stdout at 0x0000024069495550, file "subprocess.py", line 180>, <code object stdout at 0x00000240694952E0, file "subprocess.py", line 184>, (None, None))

## co_names:
('__name__', '__module__', '__qualname__', '__doc__', '__init__', '__str__', 'property', 'stdout', 'setter')

## bytecode:

   0: RESUME               
   2: LOAD_NAME            __name__
   4: STORE_NAME           __module__
   6: LOAD_CONST           'TimeoutExpired'
   8: STORE_NAME           __qualname__
  10: LOAD_CONST           'This exception is raised when the timeout expires while waiting for a\n    child process.\n\n    Attributes:\n        cmd, output, stdout, stderr, timeout\n    '
  12: STORE_NAME           __doc__
  14: LOAD_CONST           (None, None)
  16: LOAD_CONST           <code object __init__ at 0x00000240693EB030, file "subprocess.py", line 170>
  18: MAKE_FUNCTION        defaults
  20: STORE_NAME           __init__
  22: LOAD_CONST           <code object __str__ at 0x0000024069465530, file "subprocess.py", line 176>
  24: MAKE_FUNCTION        
  26: STORE_NAME           __str__
  28: LOAD_NAME            property
  30: LOAD_CONST           <code object stdout at 0x0000024069495550, file "subprocess.py", line 180>
  32: MAKE_FUNCTION        
  34: PRECALL              
  38: CALL                 
  48: STORE_NAME           stdout
  50: LOAD_NAME            stdout
  52: LOAD_ATTR            setter
  62: LOAD_CONST           <code object stdout at 0x00000240694952E0, file "subprocess.py", line 184>
  64: MAKE_FUNCTION        
  66: PRECALL              
  70: CALL                 
  80: STORE_NAME           stdout
  82: LOAD_CONST           None
  84: RETURN_VALUE         
