# Disassembly for subprocess.Popen.__exit__
# From module file: subprocess

## co_consts:
(None, 0, ('timeout',))

## co_names:
('stdout', 'close', 'stderr', 'stdin', 'KeyboardInterrupt', '_sigint_wait_secs', '_wait', 'TimeoutExpired', 'wait')

## bytecode:

   0: RESUME               
   2: LOAD_FAST            self
   4: LOAD_ATTR            stdout
  14: POP_JUMP_FORWARD_IF_FALSE to 66
  16: LOAD_FAST            self
  18: LOAD_ATTR            stdout
  28: LOAD_METHOD          close
  50: PRECALL              
  54: CALL                 
  64: POP_TOP              
  66: LOAD_FAST            self
  68: LOAD_ATTR            stderr
  78: POP_JUMP_FORWARD_IF_FALSE to 130
  80: LOAD_FAST            self
  82: LOAD_ATTR            stderr
  92: LOAD_METHOD          close
 114: PRECALL              
 118: CALL                 
 128: POP_TOP              
 130: NOP                  
 132: LOAD_FAST            self
 134: LOAD_ATTR            stdin
 144: POP_JUMP_FORWARD_IF_FALSE to 196
 146: LOAD_FAST            self
 148: LOAD_ATTR            stdin
 158: LOAD_METHOD          close
 180: PRECALL              
 184: CALL                 
 194: POP_TOP              
 196: LOAD_FAST            exc_type
 198: LOAD_GLOBAL          KeyboardInterrupt
 210: COMPARE_OP           ==
 216: POP_JUMP_FORWARD_IF_FALSE to 348
 218: LOAD_FAST            self
 220: LOAD_ATTR            _sigint_wait_secs
 230: LOAD_CONST           0
 232: COMPARE_OP           >
 238: POP_JUMP_FORWARD_IF_FALSE to 330
 240: NOP                  
 242: LOAD_FAST            self
 244: LOAD_METHOD          _wait
 266: LOAD_FAST            self
 268: LOAD_ATTR            _sigint_wait_secs
 278: KW_NAMES             
 280: PRECALL              
 284: CALL                 
 294: POP_TOP              
 296: JUMP_FORWARD         to 330
 298: PUSH_EXC_INFO        
 300: LOAD_GLOBAL          TimeoutExpired
 312: CHECK_EXC_MATCH      
 314: POP_JUMP_FORWARD_IF_FALSE to 322
 316: POP_TOP              
 318: POP_EXCEPT           
 320: JUMP_FORWARD         to 330
 322: RERAISE              
 324: COPY                 
 326: POP_EXCEPT           
 328: RERAISE              
 330: LOAD_CONST           0
 332: LOAD_FAST            self
 334: STORE_ATTR           _sigint_wait_secs
 344: LOAD_CONST           None
 346: RETURN_VALUE         
 348: LOAD_FAST            self
 350: LOAD_METHOD          wait
 372: PRECALL              
 376: CALL                 
 386: POP_TOP              
 388: LOAD_CONST           None
 390: RETURN_VALUE         
 392: PUSH_EXC_INFO        
 394: LOAD_FAST            exc_type
 396: LOAD_GLOBAL          KeyboardInterrupt
 408: COMPARE_OP           ==
 414: POP_JUMP_FORWARD_IF_FALSE to 550
 416: LOAD_FAST            self
 418: LOAD_ATTR            _sigint_wait_secs
 428: LOAD_CONST           0
 430: COMPARE_OP           >
 436: POP_JUMP_FORWARD_IF_FALSE to 528
 438: NOP                  
 440: LOAD_FAST            self
 442: LOAD_METHOD          _wait
 464: LOAD_FAST            self
 466: LOAD_ATTR            _sigint_wait_secs
 476: KW_NAMES             
 478: PRECALL              
 482: CALL                 
 492: POP_TOP              
 494: JUMP_FORWARD         to 528
 496: PUSH_EXC_INFO        
 498: LOAD_GLOBAL          TimeoutExpired
 510: CHECK_EXC_MATCH      
 512: POP_JUMP_FORWARD_IF_FALSE to 520
 514: POP_TOP              
 516: POP_EXCEPT           
 518: JUMP_FORWARD         to 528
 520: RERAISE              
 522: COPY                 
 524: POP_EXCEPT           
 526: RERAISE              
 528: LOAD_CONST           0
 530: LOAD_FAST            self
 532: STORE_ATTR           _sigint_wait_secs
 542: POP_TOP              
 544: POP_EXCEPT           
 546: LOAD_CONST           None
 548: RETURN_VALUE         
 550: LOAD_FAST            self
 552: LOAD_METHOD          wait
 574: PRECALL              
 578: CALL                 
 588: POP_TOP              
 590: RERAISE              
 592: COPY                 
 594: POP_EXCEPT           
 596: RERAISE              
