# Disassembly for subprocess.run
# From module file: subprocess

## co_consts:
('Run command with arguments and return a CompletedProcess instance.\n\n    The returned instance will have attributes args, returncode, stdout and\n    stderr. By default, stdout and stderr are not captured, and those attributes\n    will be None. Pass stdout=PIPE and/or stderr=PIPE in order to capture them,\n    or pass capture_output=True to capture both.\n\n    If check is True and the exit code was non-zero, it raises a\n    CalledProcessError. The CalledProcessError object will have the return code\n    in the returncode attribute, and output & stderr attributes if those streams\n    were captured.\n\n    If timeout is given, and the process takes too long, a TimeoutExpired\n    exception will be raised.\n\n    There is an optional argument "input", allowing you to\n    pass bytes or a string to the subprocess\'s stdin.  If you use this argument\n    you may not also use the Popen constructor\'s "stdin" argument, as\n    it will be used internally.\n\n    By default, all communication is in bytes, and therefore any "input" should\n    be bytes, and the stdout and stderr will be bytes. If in text mode, any\n    "input" should be a string, and stdout and stderr will be strings decoded\n    according to locale encoding, or by "encoding" if set. Text mode is\n    triggered by setting any of text, encoding, errors or universal_newlines.\n\n    The other arguments are the same as for the Popen constructor.\n    ', None, 'stdin', 'stdin and input arguments may not both be used.', 'stdout', 'stderr', 'stdout and stderr arguments may not be used with capture_output.', ('timeout',), ('output', 'stderr'))

## co_names:
('get', 'ValueError', 'PIPE', 'Popen', 'communicate', 'TimeoutExpired', 'kill', '_mswindows', 'stdout', 'stderr', 'wait', 'poll', 'CalledProcessError', 'args', 'CompletedProcess')

## bytecode:

   0: RESUME               
   2: LOAD_FAST            input
   4: POP_JUMP_FORWARD_IF_NONE to 98
   6: LOAD_FAST            kwargs
   8: LOAD_METHOD          get
  30: LOAD_CONST           'stdin'
  32: PRECALL              
  36: CALL                 
  46: POP_JUMP_FORWARD_IF_NONE to 78
  48: LOAD_GLOBAL          NULL + ValueError
  60: LOAD_CONST           'stdin and input arguments may not both be used.'
  62: PRECALL              
  66: CALL                 
  76: RAISE_VARARGS        
  78: LOAD_GLOBAL          PIPE
  90: LOAD_FAST            kwargs
  92: LOAD_CONST           'stdin'
  94: STORE_SUBSCR         
  98: LOAD_FAST            capture_output
 100: POP_JUMP_FORWARD_IF_FALSE to 256
 102: LOAD_FAST            kwargs
 104: LOAD_METHOD          get
 126: LOAD_CONST           'stdout'
 128: PRECALL              
 132: CALL                 
 142: POP_JUMP_FORWARD_IF_NOT_NONE to 186
 144: LOAD_FAST            kwargs
 146: LOAD_METHOD          get
 168: LOAD_CONST           'stderr'
 170: PRECALL              
 174: CALL                 
 184: POP_JUMP_FORWARD_IF_NONE to 216
 186: LOAD_GLOBAL          NULL + ValueError
 198: LOAD_CONST           'stdout and stderr arguments may not be used with capture_output.'
 200: PRECALL              
 204: CALL                 
 214: RAISE_VARARGS        
 216: LOAD_GLOBAL          PIPE
 228: LOAD_FAST            kwargs
 230: LOAD_CONST           'stdout'
 232: STORE_SUBSCR         
 236: LOAD_GLOBAL          PIPE
 248: LOAD_FAST            kwargs
 250: LOAD_CONST           'stderr'
 252: STORE_SUBSCR         
 256: LOAD_GLOBAL          NULL + Popen
 268: LOAD_FAST            popenargs
 270: BUILD_MAP            
 272: LOAD_FAST            kwargs
 274: DICT_MERGE           
 276: CALL_FUNCTION_EX     
 278: BEFORE_WITH          
 280: STORE_FAST           process
 282: NOP                  
 284: LOAD_FAST            process
 286: LOAD_METHOD          communicate
 308: LOAD_FAST            input
 310: LOAD_FAST            timeout
 312: KW_NAMES             
 314: PRECALL              
 318: CALL                 
 328: UNPACK_SEQUENCE      
 332: STORE_FAST           stdout
 334: STORE_FAST           stderr
 336: JUMP_FORWARD         to 580
 338: PUSH_EXC_INFO        
 340: LOAD_GLOBAL          TimeoutExpired
 352: CHECK_EXC_MATCH      
 354: POP_JUMP_FORWARD_IF_FALSE to 530
 356: STORE_FAST           exc
 358: LOAD_FAST            process
 360: LOAD_METHOD          kill
 382: PRECALL              
 386: CALL                 
 396: POP_TOP              
 398: LOAD_GLOBAL          _mswindows
 410: POP_JUMP_FORWARD_IF_FALSE to 480
 412: LOAD_FAST            process
 414: LOAD_METHOD          communicate
 436: PRECALL              
 440: CALL                 
 450: UNPACK_SEQUENCE      
 454: LOAD_FAST            exc
 456: STORE_ATTR           stdout
 466: LOAD_FAST            exc
 468: STORE_ATTR           stderr
 478: JUMP_FORWARD         to 520
 480: LOAD_FAST            process
 482: LOAD_METHOD          wait
 504: PRECALL              
 508: CALL                 
 518: POP_TOP              
 520: RAISE_VARARGS        
 522: LOAD_CONST           None
 524: STORE_FAST           exc
 526: DELETE_FAST          exc
 528: RERAISE              
 530: POP_TOP              
 532: LOAD_FAST            process
 534: LOAD_METHOD          kill
 556: PRECALL              
 560: CALL                 
 570: POP_TOP              
 572: RAISE_VARARGS        
 574: COPY                 
 576: POP_EXCEPT           
 578: RERAISE              
 580: LOAD_FAST            process
 582: LOAD_METHOD          poll
 604: PRECALL              
 608: CALL                 
 618: STORE_FAST           retcode
 620: LOAD_FAST            check
 622: POP_JUMP_FORWARD_IF_FALSE to 676
 624: LOAD_FAST            retcode
 626: POP_JUMP_FORWARD_IF_FALSE to 676
 628: LOAD_GLOBAL          NULL + CalledProcessError
 640: LOAD_FAST            retcode
 642: LOAD_FAST            process
 644: LOAD_ATTR            args
 654: LOAD_FAST            stdout
 656: LOAD_FAST            stderr
 658: KW_NAMES             
 660: PRECALL              
 664: CALL                 
 674: RAISE_VARARGS        
 676: LOAD_CONST           None
 678: LOAD_CONST           None
 680: LOAD_CONST           None
 682: PRECALL              
 686: CALL                 
 696: POP_TOP              
 698: JUMP_FORWARD         to 722
 700: PUSH_EXC_INFO        
 702: WITH_EXCEPT_START    
 704: POP_JUMP_FORWARD_IF_TRUE to 714
 706: RERAISE              
 708: COPY                 
 710: POP_EXCEPT           
 712: RERAISE              
 714: POP_TOP              
 716: POP_EXCEPT           
 718: POP_TOP              
 720: POP_TOP              
 722: LOAD_GLOBAL          NULL + CompletedProcess
 734: LOAD_FAST            process
 736: LOAD_ATTR            args
 746: LOAD_FAST            retcode
 748: LOAD_FAST            stdout
 750: LOAD_FAST            stderr
 752: PRECALL              
 756: CALL                 
 766: RETURN_VALUE         
