# Disassembly for subprocess.Popen.terminate
# From module file: subprocess

## co_consts:
('Terminate the process with SIGTERM\n            ', None)

## co_names:
('send_signal', 'signal', 'SIGTERM')

## bytecode:

   0: RESUME               
   2: LOAD_FAST            self
   4: LOAD_METHOD          send_signal
  26: LOAD_GLOBAL          signal
  38: LOAD_ATTR            SIGTERM
  48: PRECALL              
  52: CALL                 
  62: POP_TOP              
  64: LOAD_CONST           None
  66: RETURN_VALUE         
