# Disassembly for subprocess.CalledProcessError.__str__
# From module file: subprocess

## co_consts:
(None, 0, "Command '", "' died with ", '.', "Command '%s' died with unknown signal %d.", "Command '%s' returned non-zero exit status %d.")

## co_names:
('returncode', 'cmd', 'signal', 'Signals', 'ValueError')

## bytecode:

   0: RESUME               
   2: LOAD_FAST            self
   4: LOAD_ATTR            returncode
  14: POP_JUMP_FORWARD_IF_FALSE to 182
  16: LOAD_FAST            self
  18: LOAD_ATTR            returncode
  28: LOAD_CONST           0
  30: COMPARE_OP           <
  36: POP_JUMP_FORWARD_IF_FALSE to 182
  38: LOAD_CONST           "Command '"
  40: LOAD_FAST            self
  42: LOAD_ATTR            cmd
  52: FORMAT_VALUE         str
  54: LOAD_CONST           "' died with "
  56: LOAD_GLOBAL          NULL + signal
  68: LOAD_ATTR            Signals
  78: LOAD_FAST            self
  80: LOAD_ATTR            returncode
  90: UNARY_NEGATIVE       
  92: PRECALL              
  96: CALL                 
 106: FORMAT_VALUE         repr
 108: LOAD_CONST           '.'
 110: BUILD_STRING         
 112: RETURN_VALUE         
 114: PUSH_EXC_INFO        
 116: LOAD_GLOBAL          ValueError
 128: CHECK_EXC_MATCH      
 130: POP_JUMP_FORWARD_IF_FALSE to 174
 132: POP_TOP              
 134: LOAD_CONST           "Command '%s' died with unknown signal %d."
 136: LOAD_FAST            self
 138: LOAD_ATTR            cmd
 148: LOAD_FAST            self
 150: LOAD_ATTR            returncode
 160: UNARY_NEGATIVE       
 162: BUILD_TUPLE          
 164: BINARY_OP            %
 168: SWAP                 
 170: POP_EXCEPT           
 172: RETURN_VALUE         
 174: RERAISE              
 176: COPY                 
 178: POP_EXCEPT           
 180: RERAISE              
 182: LOAD_CONST           "Command '%s' returned non-zero exit status %d."
 184: LOAD_FAST            self
 186: LOAD_ATTR            cmd
 196: LOAD_FAST            self
 198: LOAD_ATTR            returncode
 208: BUILD_TUPLE          
 210: BINARY_OP            %
 214: RETURN_VALUE         
