# Disassembly for subprocess.Popen._on_error_fd_closer
# From module file: subprocess

## co_consts:
('Helper to ensure file descriptors opened in _get_handles are closed', '_devnull', None)

## co_names:
('hasattr', 'append', '_devnull', '_mswindows', 'isinstance', 'Handle', 'Close', 'os', 'close', 'OSError')

## bytecode:

   0: RETURN_GENERATOR     
   2: POP_TOP              
   4: RESUME               
   6: BUILD_LIST           
   8: STORE_FAST           to_close
  10: NOP                  
  12: LOAD_FAST            to_close
  14: YIELD_VALUE          
  16: RESUME               
  18: POP_TOP              
  20: LOAD_CONST           None
  22: RETURN_VALUE         
  24: PUSH_EXC_INFO        
  26: POP_TOP              
  28: LOAD_GLOBAL          NULL + hasattr
  40: LOAD_FAST            self
  42: LOAD_CONST           '_devnull'
  44: PRECALL              
  48: CALL                 
  58: POP_JUMP_FORWARD_IF_FALSE to 116
  60: LOAD_FAST            to_close
  62: LOAD_METHOD          append
  84: LOAD_FAST            self
  86: LOAD_ATTR            _devnull
  96: PRECALL              
 100: CALL                 
 110: POP_TOP              
 112: LOAD_FAST            self
 114: DELETE_ATTR          _devnull
 116: LOAD_FAST            to_close
 118: GET_ITER             
 120: FOR_ITER             to 298
 122: STORE_FAST           fd
 124: NOP                  
 126: LOAD_GLOBAL          _mswindows
 138: POP_JUMP_FORWARD_IF_FALSE to 224
 140: LOAD_GLOBAL          NULL + isinstance
 152: LOAD_FAST            fd
 154: LOAD_GLOBAL          Handle
 166: PRECALL              
 170: CALL                 
 180: POP_JUMP_FORWARD_IF_FALSE to 224
 182: LOAD_FAST            fd
 184: LOAD_METHOD          Close
 206: PRECALL              
 210: CALL                 
 220: POP_TOP              
 222: JUMP_FORWARD         to 264
 224: LOAD_GLOBAL          NULL + os
 236: LOAD_ATTR            close
 246: LOAD_FAST            fd
 248: PRECALL              
 252: CALL                 
 262: POP_TOP              
 264: JUMP_BACKWARD        to 120
 266: PUSH_EXC_INFO        
 268: LOAD_GLOBAL          OSError
 280: CHECK_EXC_MATCH      
 282: POP_JUMP_FORWARD_IF_FALSE to 290
 284: POP_TOP              
 286: POP_EXCEPT           
 288: JUMP_BACKWARD        to 120
 290: RERAISE              
 292: COPY                 
 294: POP_EXCEPT           
 296: RERAISE              
 298: RAISE_VARARGS        
 300: COPY                 
 302: POP_EXCEPT           
 304: RERAISE              
