# Disassembly for subprocess.Popen.send_signal
# From module file: subprocess

## co_consts:
('Send a signal to the process.', None)

## co_names:
('poll', 'returncode', 'os', 'kill', 'pid', 'ProcessLookupError')

## bytecode:

   0: RESUME               
   2: LOAD_FAST            self
   4: LOAD_METHOD          poll
  26: PRECALL              
  30: CALL                 
  40: POP_TOP              
  42: LOAD_FAST            self
  44: LOAD_ATTR            returncode
  54: POP_JUMP_FORWARD_IF_NONE to 60
  56: LOAD_CONST           None
  58: RETURN_VALUE         
  60: NOP                  
  62: LOAD_GLOBAL          NULL + os
  74: LOAD_ATTR            kill
  84: LOAD_FAST            self
  86: LOAD_ATTR            pid
  96: LOAD_FAST            sig
  98: PRECALL              
 102: CALL                 
 112: POP_TOP              
 114: LOAD_CONST           None
 116: RETURN_VALUE         
 118: PUSH_EXC_INFO        
 120: LOAD_GLOBAL          ProcessLookupError
 132: CHECK_EXC_MATCH      
 134: POP_JUMP_FORWARD_IF_FALSE to 144
 136: POP_TOP              
 138: POP_EXCEPT           
 140: LOAD_CONST           None
 142: RETURN_VALUE         
 144: RERAISE              
 146: COPY                 
 148: POP_EXCEPT           
 150: RERAISE              
