# Disassembly for subprocess.Popen.__repr__
# From module file: subprocess

## co_consts:
(None, '<', ': returncode: ', ' args: ', '>', 80, 76, '...>')

## co_names:
('__class__', '__name__', 'returncode', 'args', 'len')

## bytecode:

   0: RESUME               
   2: LOAD_CONST           '<'
   4: LOAD_FAST            self
   6: LOAD_ATTR            __class__
  16: LOAD_ATTR            __name__
  26: FORMAT_VALUE         
  28: LOAD_CONST           ': returncode: '
  30: LOAD_FAST            self
  32: LOAD_ATTR            returncode
  42: FORMAT_VALUE         
  44: LOAD_CONST           ' args: '
  46: LOAD_FAST            self
  48: LOAD_ATTR            args
  58: FORMAT_VALUE         repr
  60: LOAD_CONST           '>'
  62: BUILD_STRING         
  64: STORE_FAST           obj_repr
  66: LOAD_GLOBAL          NULL + len
  78: LOAD_FAST            obj_repr
  80: PRECALL              
  84: CALL                 
  94: LOAD_CONST           80
  96: COMPARE_OP           >
 102: POP_JUMP_FORWARD_IF_FALSE to 130
 104: LOAD_FAST            obj_repr
 106: LOAD_CONST           None
 108: LOAD_CONST           76
 110: BUILD_SLICE          
 112: BINARY_SUBSCR        
 122: LOAD_CONST           '...>'
 124: BINARY_OP            +
 128: STORE_FAST           obj_repr
 130: LOAD_FAST            obj_repr
 132: RETURN_VALUE         
