# Disassembly for subprocess.check_call
# From module file: subprocess

## co_consts:
('Run command with arguments.  Wait for command to complete.  If\n    the exit code was zero then return, otherwise raise\n    CalledProcessError.  The CalledProcessError object will have the\n    return code in the returncode attribute.\n\n    The arguments are the same as for the call function.  Example:\n\n    check_call(["ls", "-l"])\n    ', 'args', None, 0)

## co_names:
('call', 'get', 'CalledProcessError')

## bytecode:

   0: RESUME               
   2: LOAD_GLOBAL          NULL + call
  14: LOAD_FAST            popenargs
  16: BUILD_MAP            
  18: LOAD_FAST            kwargs
  20: DICT_MERGE           
  22: CALL_FUNCTION_EX     
  24: STORE_FAST           retcode
  26: LOAD_FAST            retcode
  28: POP_JUMP_FORWARD_IF_FALSE to 124
  30: LOAD_FAST            kwargs
  32: LOAD_METHOD          get
  54: LOAD_CONST           'args'
  56: PRECALL              
  60: CALL                 
  70: STORE_FAST           cmd
  72: LOAD_FAST            cmd
  74: POP_JUMP_FORWARD_IF_NOT_NONE to 92
  76: LOAD_FAST            popenargs
  78: LOAD_CONST           0
  80: BINARY_SUBSCR        
  90: STORE_FAST           cmd
  92: LOAD_GLOBAL          NULL + CalledProcessError
 104: LOAD_FAST            retcode
 106: LOAD_FAST            cmd
 108: PRECALL              
 112: CALL                 
 122: RAISE_VARARGS        
 124: LOAD_CONST           0
 126: RETURN_VALUE         
