# Disassembly for subprocess.Popen.__del__
# From module file: subprocess

## co_consts:
(None, 'subprocess %s is still running', ('source',), ('_deadstate',))

## co_names:
('_child_created', 'returncode', 'pid', 'ResourceWarning', '_internal_poll', '_active', 'append')

## bytecode:

   0: RESUME               
   2: LOAD_FAST            self
   4: LOAD_ATTR            _child_created
  14: POP_JUMP_FORWARD_IF_TRUE to 20
  16: LOAD_CONST           None
  18: RETURN_VALUE         
  20: LOAD_FAST            self
  22: LOAD_ATTR            returncode
  32: POP_JUMP_FORWARD_IF_NOT_NONE to 88
  34: PUSH_NULL            
  36: LOAD_FAST            _warn
  38: LOAD_CONST           'subprocess %s is still running'
  40: LOAD_FAST            self
  42: LOAD_ATTR            pid
  52: BINARY_OP            %
  56: LOAD_GLOBAL          ResourceWarning
  68: LOAD_FAST            self
  70: KW_NAMES             
  72: PRECALL              
  76: CALL                 
  86: POP_TOP              
  88: LOAD_FAST            self
  90: LOAD_METHOD          _internal_poll
 112: LOAD_FAST            _maxsize
 114: KW_NAMES             
 116: PRECALL              
 120: CALL                 
 130: POP_TOP              
 132: LOAD_FAST            self
 134: LOAD_ATTR            returncode
 144: POP_JUMP_FORWARD_IF_NOT_NONE to 216
 146: LOAD_GLOBAL          _active
 158: POP_JUMP_FORWARD_IF_NONE to 220
 160: LOAD_GLOBAL          _active
 172: LOAD_METHOD          append
 194: LOAD_FAST            self
 196: PRECALL              
 200: CALL                 
 210: POP_TOP              
 212: LOAD_CONST           None
 214: RETURN_VALUE         
 216: LOAD_CONST           None
 218: RETURN_VALUE         
 220: LOAD_CONST           None
 222: RETURN_VALUE         
