# Disassembly for subprocess.Popen._make_inheritable
# From module file: subprocess

## co_consts:
('Return a duplicate of handle, which is inheritable', 0, 1)

## co_names:
('_winapi', 'DuplicateHandle', 'GetCurrentProcess', 'DUPLICATE_SAME_ACCESS', 'Handle')

## bytecode:

   0: RESUME               
   2: LOAD_GLOBAL          NULL + _winapi
  14: LOAD_ATTR            DuplicateHandle
  24: LOAD_GLOBAL          NULL + _winapi
  36: LOAD_ATTR            GetCurrentProcess
  46: PRECALL              
  50: CALL                 
  60: LOAD_FAST            handle
  62: LOAD_GLOBAL          NULL + _winapi
  74: LOAD_ATTR            GetCurrentProcess
  84: PRECALL              
  88: CALL                 
  98: LOAD_CONST           0
 100: LOAD_CONST           1
 102: LOAD_GLOBAL          _winapi
 114: LOAD_ATTR            DUPLICATE_SAME_ACCESS
 124: PRECALL              
 128: CALL                 
 138: STORE_FAST           h
 140: LOAD_GLOBAL          NULL + Handle
 152: LOAD_FAST            h
 154: PRECALL              
 158: CALL                 
 168: RETURN_VALUE         
