# Disassembly for subprocess.Popen._stdin_write
# From module file: subprocess

## co_consts:
(None,)

## co_names:
('stdin', 'write', 'BrokenPipeError', 'OSError', 'errno', 'EINVAL', 'close')

## bytecode:

   0: RESUME               
   2: LOAD_FAST            input
   4: POP_JUMP_FORWARD_IF_FALSE to 176
   6: NOP                  
   8: LOAD_FAST            self
  10: LOAD_ATTR            stdin
  20: LOAD_METHOD          write
  42: LOAD_FAST            input
  44: PRECALL              
  48: CALL                 
  58: POP_TOP              
  60: JUMP_FORWARD         to 176
  62: PUSH_EXC_INFO        
  64: LOAD_GLOBAL          BrokenPipeError
  76: CHECK_EXC_MATCH      
  78: POP_JUMP_FORWARD_IF_FALSE to 86
  80: POP_TOP              
  82: POP_EXCEPT           
  84: JUMP_FORWARD         to 176
  86: LOAD_GLOBAL          OSError
  98: CHECK_EXC_MATCH      
 100: POP_JUMP_FORWARD_IF_FALSE to 168
 102: STORE_FAST           exc
 104: LOAD_FAST            exc
 106: LOAD_ATTR            errno
 116: LOAD_GLOBAL          errno
 128: LOAD_ATTR            EINVAL
 138: COMPARE_OP           ==
 144: POP_JUMP_FORWARD_IF_FALSE to 148
 146: JUMP_FORWARD         to 150
 148: RAISE_VARARGS        
 150: POP_EXCEPT           
 152: LOAD_CONST           None
 154: STORE_FAST           exc
 156: DELETE_FAST          exc
 158: JUMP_FORWARD         to 176
 160: LOAD_CONST           None
 162: STORE_FAST           exc
 164: DELETE_FAST          exc
 166: RERAISE              
 168: RERAISE              
 170: COPY                 
 172: POP_EXCEPT           
 174: RERAISE              
 176: NOP                  
 178: LOAD_FAST            self
 180: LOAD_ATTR            stdin
 190: LOAD_METHOD          close
 212: PRECALL              
 216: CALL                 
 226: POP_TOP              
 228: LOAD_CONST           None
 230: RETURN_VALUE         
 232: PUSH_EXC_INFO        
 234: LOAD_GLOBAL          BrokenPipeError
 246: CHECK_EXC_MATCH      
 248: POP_JUMP_FORWARD_IF_FALSE to 258
 250: POP_TOP              
 252: POP_EXCEPT           
 254: LOAD_CONST           None
 256: RETURN_VALUE         
 258: LOAD_GLOBAL          OSError
 270: CHECK_EXC_MATCH      
 272: POP_JUMP_FORWARD_IF_FALSE to 342
 274: STORE_FAST           exc
 276: LOAD_FAST            exc
 278: LOAD_ATTR            errno
 288: LOAD_GLOBAL          errno
 300: LOAD_ATTR            EINVAL
 310: COMPARE_OP           ==
 316: POP_JUMP_FORWARD_IF_FALSE to 320
 318: JUMP_FORWARD         to 322
 320: RAISE_VARARGS        
 322: POP_EXCEPT           
 324: LOAD_CONST           None
 326: STORE_FAST           exc
 328: DELETE_FAST          exc
 330: LOAD_CONST           None
 332: RETURN_VALUE         
 334: LOAD_CONST           None
 336: STORE_FAST           exc
 338: DELETE_FAST          exc
 340: RERAISE              
 342: RERAISE              
 344: COPY                 
 346: POP_EXCEPT           
 348: RERAISE              
