# Disassembly for subprocess.Popen._handle_exitstatus
# From module file: subprocess

## co_consts:
('All callers to this function MUST hold self._waitpid_lock.', None)

## co_names:
('returncode',)

## bytecode:

   0: RESUME               
   2: PUSH_NULL            
   4: LOAD_FAST            _WIFSTOPPED
   6: LOAD_FAST            sts
   8: PRECALL              
  12: CALL                 
  22: POP_JUMP_FORWARD_IF_FALSE to 62
  24: PUSH_NULL            
  26: LOAD_FAST            _WSTOPSIG
  28: LOAD_FAST            sts
  30: PRECALL              
  34: CALL                 
  44: UNARY_NEGATIVE       
  46: LOAD_FAST            self
  48: STORE_ATTR           returncode
  58: LOAD_CONST           None
  60: RETURN_VALUE         
  62: PUSH_NULL            
  64: LOAD_FAST            _waitstatus_to_exitcode
  66: LOAD_FAST            sts
  68: PRECALL              
  72: CALL                 
  82: LOAD_FAST            self
  84: STORE_ATTR           returncode
  94: LOAD_CONST           None
  96: RETURN_VALUE         
