# Disassembly for subprocess.Popen.kill
# From module file: subprocess

## co_consts:
('Kill the process with SIGKILL\n            ', None)

## co_names:
('send_signal', 'signal', 'SIGKILL')

## bytecode:

   0: RESUME               
   2: LOAD_FAST            self
   4: LOAD_METHOD          send_signal
  26: LOAD_GLOBAL          signal
  38: LOAD_ATTR            SIGKILL
  48: PRECALL              
  52: CALL                 
  62: POP_TOP              
  64: LOAD_CONST           None
  66: RETURN_VALUE         
