# Disassembly for subprocess.Handle.__repr__
# From module file: subprocess

## co_consts:
(None, '%s(%d)')

## co_names:
('__class__', '__name__', 'int')

## bytecode:

   0: RESUME               
   2: LOAD_CONST           '%s(%d)'
   4: LOAD_FAST            self
   6: LOAD_ATTR            __class__
  16: LOAD_ATTR            __name__
  26: LOAD_GLOBAL          NULL + int
  38: LOAD_FAST            self
  40: PRECALL              
  44: CALL                 
  54: BUILD_TUPLE          
  56: BINARY_OP            %
  60: RETURN_VALUE         
