# Disassembly for string.capwords
# From module file: string

## co_consts:
('capwords(s [,sep]) -> string\n\n    Split the argument into words using split, capitalize each\n    word using capitalize, and join the capitalized words using\n    join.  If the optional second argument sep is absent or None,\n    runs of whitespace characters are replaced by a single space\n    and leading and trailing whitespace are removed, otherwise\n    sep is used to split and join the words.\n\n    ', ' ')

## co_names:
('join', 'map', 'str', 'capitalize', 'split')

## bytecode:

   0: RESUME               
   2: LOAD_FAST            sep
   4: JUMP_IF_TRUE_OR_POP  to 8
   6: LOAD_CONST           ' '
   8: LOAD_METHOD          join
  30: LOAD_GLOBAL          NULL + map
  42: LOAD_GLOBAL          str
  54: LOAD_ATTR            capitalize
  64: LOAD_FAST            s
  66: LOAD_METHOD          split
  88: LOAD_FAST            sep
  90: PRECALL              
  94: CALL                 
 104: PRECALL              
 108: CALL                 
 118: PRECALL              
 122: CALL                 
 132: RETURN_VALUE         
