# Disassembly for string.Formatter._vformat
# From module file: string

## co_consts:
(None, 0, 'Max string recursion exceeded', '', False, 'cannot switch from manual field specification to automatic field numbering', 1, ('auto_arg_index',))

## co_names:
('ValueError', 'parse', 'append', 'str', 'isdigit', 'get_field', 'add', 'convert_field', '_vformat', 'format_field', 'join')

## bytecode:

   0: RESUME               
   2: LOAD_FAST            recursion_depth
   4: LOAD_CONST           0
   6: COMPARE_OP           <
  12: POP_JUMP_FORWARD_IF_FALSE to 44
  14: LOAD_GLOBAL          NULL + ValueError
  26: LOAD_CONST           'Max string recursion exceeded'
  28: PRECALL              
  32: CALL                 
  42: RAISE_VARARGS        
  44: BUILD_LIST           
  46: STORE_FAST           result
  48: LOAD_FAST            self
  50: LOAD_METHOD          parse
  72: LOAD_FAST            format_string
  74: PRECALL              
  78: CALL                 
  88: GET_ITER             
  90: EXTENDED_ARG         
  92: FOR_ITER             to 616
  94: UNPACK_SEQUENCE      
  98: STORE_FAST           literal_text
 100: STORE_FAST           field_name
 102: STORE_FAST           format_spec
 104: STORE_FAST           conversion
 106: LOAD_FAST            literal_text
 108: POP_JUMP_FORWARD_IF_FALSE to 152
 110: LOAD_FAST            result
 112: LOAD_METHOD          append
 134: LOAD_FAST            literal_text
 136: PRECALL              
 140: CALL                 
 150: POP_TOP              
 152: LOAD_FAST            field_name
 154: POP_JUMP_FORWARD_IF_NONE to 612
 156: LOAD_FAST            field_name
 158: LOAD_CONST           ''
 160: COMPARE_OP           ==
 166: POP_JUMP_FORWARD_IF_FALSE to 248
 168: LOAD_FAST            auto_arg_index
 170: LOAD_CONST           False
 172: IS_OP                
 174: POP_JUMP_FORWARD_IF_FALSE to 206
 176: LOAD_GLOBAL          NULL + ValueError
 188: LOAD_CONST           'cannot switch from manual field specification to automatic field numbering'
 190: PRECALL              
 194: CALL                 
 204: RAISE_VARARGS        
 206: LOAD_GLOBAL          NULL + str
 218: LOAD_FAST            auto_arg_index
 220: PRECALL              
 224: CALL                 
 234: STORE_FAST           field_name
 236: LOAD_FAST            auto_arg_index
 238: LOAD_CONST           1
 240: BINARY_OP            +=
 244: STORE_FAST           auto_arg_index
 246: JUMP_FORWARD         to 326
 248: LOAD_FAST            field_name
 250: LOAD_METHOD          isdigit
 272: PRECALL              
 276: CALL                 
 286: POP_JUMP_FORWARD_IF_FALSE to 326
 288: LOAD_FAST            auto_arg_index
 290: POP_JUMP_FORWARD_IF_FALSE to 322
 292: LOAD_GLOBAL          NULL + ValueError
 304: LOAD_CONST           'cannot switch from manual field specification to automatic field numbering'
 306: PRECALL              
 310: CALL                 
 320: RAISE_VARARGS        
 322: LOAD_CONST           False
 324: STORE_FAST           auto_arg_index
 326: LOAD_FAST            self
 328: LOAD_METHOD          get_field
 350: LOAD_FAST            field_name
 352: LOAD_FAST            args
 354: LOAD_FAST            kwargs
 356: PRECALL              
 360: CALL                 
 370: UNPACK_SEQUENCE      
 374: STORE_FAST           obj
 376: STORE_FAST           arg_used
 378: LOAD_FAST            used_args
 380: LOAD_METHOD          add
 402: LOAD_FAST            arg_used
 404: PRECALL              
 408: CALL                 
 418: POP_TOP              
 420: LOAD_FAST            self
 422: LOAD_METHOD          convert_field
 444: LOAD_FAST            obj
 446: LOAD_FAST            conversion
 448: PRECALL              
 452: CALL                 
 462: STORE_FAST           obj
 464: LOAD_FAST            self
 466: LOAD_METHOD          _vformat
 488: LOAD_FAST            format_spec
 490: LOAD_FAST            args
 492: LOAD_FAST            kwargs
 494: LOAD_FAST            used_args
 496: LOAD_FAST            recursion_depth
 498: LOAD_CONST           1
 500: BINARY_OP            -
 504: LOAD_FAST            auto_arg_index
 506: KW_NAMES             
 508: PRECALL              
 512: CALL                 
 522: UNPACK_SEQUENCE      
 526: STORE_FAST           format_spec
 528: STORE_FAST           auto_arg_index
 530: LOAD_FAST            result
 532: LOAD_METHOD          append
 554: LOAD_FAST            self
 556: LOAD_METHOD          format_field
 578: LOAD_FAST            obj
 580: LOAD_FAST            format_spec
 582: PRECALL              
 586: CALL                 
 596: PRECALL              
 600: CALL                 
 610: POP_TOP              
 612: EXTENDED_ARG         
 614: JUMP_BACKWARD        to 90
 616: LOAD_CONST           ''
 618: LOAD_METHOD          join
 640: LOAD_FAST            result
 642: PRECALL              
 646: CALL                 
 656: LOAD_FAST            auto_arg_index
 658: BUILD_TUPLE          
 660: RETURN_VALUE         
