# Disassembly for string.Template
# From module file: string

## co_consts:
('Template', 'A string class for supporting $-substitutions.', '$', '(?a:[_a-z][_a-z0-9]*)', None, <code object __init_subclass__ at 0x000002406931FA30, file "string.py", line 69>, <code object __init__ at 0x00000240694941D0, file "string.py", line 87>, <code object _invalid at 0x000002406947C5D0, file "string.py", line 92>, <code object substitute at 0x000002406922D680, file "string.py", line 104>, <code object safe_substitute at 0x000002406922D920, file "string.py", line 123>, <code object is_valid at 0x000002406947CD50, file "string.py", line 144>, <code object get_identifiers at 0x0000024068E232C0, file "string.py", line 157>)

## co_names:
('__name__', '__module__', '__qualname__', '__doc__', 'delimiter', 'idpattern', 'braceidpattern', '_re', 'IGNORECASE', 'flags', '__init_subclass__', '__init__', '_invalid', '_sentinel_dict', 'substitute', 'safe_substitute', 'is_valid', 'get_identifiers', '__classcell__')

## bytecode:

   0: MAKE_CELL            __class__
   2: RESUME               
   4: LOAD_NAME            __name__
   6: STORE_NAME           __module__
   8: LOAD_CONST           'Template'
  10: STORE_NAME           __qualname__
  12: LOAD_CONST           'A string class for supporting $-substitutions.'
  14: STORE_NAME           __doc__
  16: LOAD_CONST           '$'
  18: STORE_NAME           delimiter
  20: LOAD_CONST           '(?a:[_a-z][_a-z0-9]*)'
  22: STORE_NAME           idpattern
  24: LOAD_CONST           None
  26: STORE_NAME           braceidpattern
  28: LOAD_NAME            _re
  30: LOAD_ATTR            IGNORECASE
  40: STORE_NAME           flags
  42: LOAD_CLOSURE         __class__
  44: BUILD_TUPLE          
  46: LOAD_CONST           <code object __init_subclass__ at 0x000002406931FA30, file "string.py", line 69>
  48: MAKE_FUNCTION        closure
  50: STORE_NAME           __init_subclass__
  52: LOAD_CONST           <code object __init__ at 0x00000240694941D0, file "string.py", line 87>
  54: MAKE_FUNCTION        
  56: STORE_NAME           __init__
  58: LOAD_CONST           <code object _invalid at 0x000002406947C5D0, file "string.py", line 92>
  60: MAKE_FUNCTION        
  62: STORE_NAME           _invalid
  64: LOAD_NAME            _sentinel_dict
  66: BUILD_TUPLE          
  68: LOAD_CONST           <code object substitute at 0x000002406922D680, file "string.py", line 104>
  70: MAKE_FUNCTION        defaults
  72: STORE_NAME           substitute
  74: LOAD_NAME            _sentinel_dict
  76: BUILD_TUPLE          
  78: LOAD_CONST           <code object safe_substitute at 0x000002406922D920, file "string.py", line 123>
  80: MAKE_FUNCTION        defaults
  82: STORE_NAME           safe_substitute
  84: LOAD_CONST           <code object is_valid at 0x000002406947CD50, file "string.py", line 144>
  86: MAKE_FUNCTION        
  88: STORE_NAME           is_valid
  90: LOAD_CONST           <code object get_identifiers at 0x0000024068E232C0, file "string.py", line 157>
  92: MAKE_FUNCTION        
  94: STORE_NAME           get_identifiers
  96: LOAD_CLOSURE         __class__
  98: COPY                 
 100: STORE_NAME           __classcell__
 102: RETURN_VALUE         
