# Disassembly for string.Template.safe_substitute.convert
# From module file: string

## co_consts:
(None, 'named', 'braced', 'escaped', 'invalid', 'Unrecognized named group in pattern')

## co_names:
('group', 'str', 'KeyError', 'delimiter', 'ValueError', 'pattern')

## bytecode:

   0: COPY_FREE_VARS       
   2: RESUME               
   4: LOAD_FAST            mo
   6: LOAD_METHOD          group
  28: LOAD_CONST           'named'
  30: PRECALL              
  34: CALL                 
  44: JUMP_IF_TRUE_OR_POP  to 86
  46: LOAD_FAST            mo
  48: LOAD_METHOD          group
  70: LOAD_CONST           'braced'
  72: PRECALL              
  76: CALL                 
  86: STORE_FAST           named
  88: LOAD_FAST            named
  90: POP_JUMP_FORWARD_IF_NONE to 208
  92: NOP                  
  94: LOAD_GLOBAL          NULL + str
 106: LOAD_DEREF           mapping
 108: LOAD_FAST            named
 110: BINARY_SUBSCR        
 120: PRECALL              
 124: CALL                 
 134: RETURN_VALUE         
 136: PUSH_EXC_INFO        
 138: LOAD_GLOBAL          KeyError
 150: CHECK_EXC_MATCH      
 152: POP_JUMP_FORWARD_IF_FALSE to 200
 154: POP_TOP              
 156: LOAD_FAST            mo
 158: LOAD_METHOD          group
 180: PRECALL              
 184: CALL                 
 194: SWAP                 
 196: POP_EXCEPT           
 198: RETURN_VALUE         
 200: RERAISE              
 202: COPY                 
 204: POP_EXCEPT           
 206: RERAISE              
 208: LOAD_FAST            mo
 210: LOAD_METHOD          group
 232: LOAD_CONST           'escaped'
 234: PRECALL              
 238: CALL                 
 248: POP_JUMP_FORWARD_IF_NONE to 264
 250: LOAD_DEREF           self
 252: LOAD_ATTR            delimiter
 262: RETURN_VALUE         
 264: LOAD_FAST            mo
 266: LOAD_METHOD          group
 288: LOAD_CONST           'invalid'
 290: PRECALL              
 294: CALL                 
 304: POP_JUMP_FORWARD_IF_NONE to 346
 306: LOAD_FAST            mo
 308: LOAD_METHOD          group
 330: PRECALL              
 334: CALL                 
 344: RETURN_VALUE         
 346: LOAD_GLOBAL          NULL + ValueError
 358: LOAD_CONST           'Unrecognized named group in pattern'
 360: LOAD_DEREF           self
 362: LOAD_ATTR            pattern
 372: PRECALL              
 376: CALL                 
 386: RAISE_VARARGS        
