# Disassembly for string.Formatter.get_field
# From module file: string

## co_consts:
(None,)

## co_names:
('_string', 'formatter_field_name_split', 'get_value', 'getattr')

## bytecode:

   0: RESUME               
   2: LOAD_GLOBAL          NULL + _string
  14: LOAD_ATTR            formatter_field_name_split
  24: LOAD_FAST            field_name
  26: PRECALL              
  30: CALL                 
  40: UNPACK_SEQUENCE      
  44: STORE_FAST           first
  46: STORE_FAST           rest
  48: LOAD_FAST            self
  50: LOAD_METHOD          get_value
  72: LOAD_FAST            first
  74: LOAD_FAST            args
  76: LOAD_FAST            kwargs
  78: PRECALL              
  82: CALL                 
  92: STORE_FAST           obj
  94: LOAD_FAST            rest
  96: GET_ITER             
  98: FOR_ITER             to 164
 100: UNPACK_SEQUENCE      
 104: STORE_FAST           is_attr
 106: STORE_FAST           i
 108: LOAD_FAST            is_attr
 110: POP_JUMP_FORWARD_IF_FALSE to 146
 112: LOAD_GLOBAL          NULL + getattr
 124: LOAD_FAST            obj
 126: LOAD_FAST            i
 128: PRECALL              
 132: CALL                 
 142: STORE_FAST           obj
 144: JUMP_BACKWARD        to 98
 146: LOAD_FAST            obj
 148: LOAD_FAST            i
 150: BINARY_SUBSCR        
 160: STORE_FAST           obj
 162: JUMP_BACKWARD        to 98
 164: LOAD_FAST            obj
 166: LOAD_FAST            first
 168: BUILD_TUPLE          
 170: RETURN_VALUE         
