# Disassembly for string.Template.substitute
# From module file: string

## co_consts:
(None, <code object convert at 0x0000024069498030, file "string.py", line 110>)

## co_names:
('_sentinel_dict', '_ChainMap', 'pattern', 'sub', 'template')

## bytecode:

   0: MAKE_CELL            self
   2: MAKE_CELL            mapping
   4: RESUME               
   6: LOAD_DEREF           mapping
   8: LOAD_GLOBAL          _sentinel_dict
  20: IS_OP                
  22: POP_JUMP_FORWARD_IF_FALSE to 30
  24: LOAD_FAST            kws
  26: STORE_DEREF          mapping
  28: JUMP_FORWARD         to 66
  30: LOAD_FAST            kws
  32: POP_JUMP_FORWARD_IF_FALSE to 66
  34: LOAD_GLOBAL          NULL + _ChainMap
  46: LOAD_FAST            kws
  48: LOAD_DEREF           mapping
  50: PRECALL              
  54: CALL                 
  64: STORE_DEREF          mapping
  66: LOAD_CLOSURE         mapping
  68: LOAD_CLOSURE         self
  70: BUILD_TUPLE          
  72: LOAD_CONST           <code object convert at 0x0000024069498030, file "string.py", line 110>
  74: MAKE_FUNCTION        closure
  76: STORE_FAST           convert
  78: LOAD_DEREF           self
  80: LOAD_ATTR            pattern
  90: LOAD_METHOD          sub
 112: LOAD_FAST            convert
 114: LOAD_DEREF           self
 116: LOAD_ATTR            template
 126: PRECALL              
 130: CALL                 
 140: RETURN_VALUE         
