# Disassembly for string.Template.is_valid
# From module file: string

## co_consts:
(None, 'invalid', False, 'named', 'braced', 'escaped', 'Unrecognized named group in pattern', True)

## co_names:
('pattern', 'finditer', 'template', 'group', 'ValueError')

## bytecode:

   0: RESUME               
   2: LOAD_FAST            self
   4: LOAD_ATTR            pattern
  14: LOAD_METHOD          finditer
  36: LOAD_FAST            self
  38: LOAD_ATTR            template
  48: PRECALL              
  52: CALL                 
  62: GET_ITER             
  64: FOR_ITER             to 286
  66: STORE_FAST           mo
  68: LOAD_FAST            mo
  70: LOAD_METHOD          group
  92: LOAD_CONST           'invalid'
  94: PRECALL              
  98: CALL                 
 108: POP_JUMP_FORWARD_IF_NONE to 116
 110: POP_TOP              
 112: LOAD_CONST           False
 114: RETURN_VALUE         
 116: LOAD_FAST            mo
 118: LOAD_METHOD          group
 140: LOAD_CONST           'named'
 142: PRECALL              
 146: CALL                 
 156: POP_JUMP_FORWARD_IF_NOT_NONE to 284
 158: LOAD_FAST            mo
 160: LOAD_METHOD          group
 182: LOAD_CONST           'braced'
 184: PRECALL              
 188: CALL                 
 198: POP_JUMP_FORWARD_IF_NOT_NONE to 284
 200: LOAD_FAST            mo
 202: LOAD_METHOD          group
 224: LOAD_CONST           'escaped'
 226: PRECALL              
 230: CALL                 
 240: POP_JUMP_FORWARD_IF_NOT_NONE to 284
 242: LOAD_GLOBAL          NULL + ValueError
 254: LOAD_CONST           'Unrecognized named group in pattern'
 256: LOAD_FAST            self
 258: LOAD_ATTR            pattern
 268: PRECALL              
 272: CALL                 
 282: RAISE_VARARGS        
 284: JUMP_BACKWARD        to 64
 286: LOAD_CONST           True
 288: RETURN_VALUE         
