# Disassembly for getpass.getuser
# From module file: getpass

## co_consts:
('Get the username from the environment or password database.\n\n    First try various environment variables, then the password\n    database.  This works on Windows as long as USERNAME is set.\n\n    ', ('LOGNAME', 'USER', 'LNAME', 'USERNAME'), 0, None)

## co_names:
('os', 'environ', 'get', 'pwd', 'getpwuid', 'getuid')

## bytecode:

   0: RESUME               
   2: LOAD_CONST           ('LOGNAME', 'USER', 'LNAME', 'USERNAME')
   4: GET_ITER             
   6: FOR_ITER             to 86
   8: STORE_FAST           name
  10: LOAD_GLOBAL          os
  22: LOAD_ATTR            environ
  32: LOAD_METHOD          get
  54: LOAD_FAST            name
  56: PRECALL              
  60: CALL                 
  70: STORE_FAST           user
  72: LOAD_FAST            user
  74: POP_JUMP_FORWARD_IF_FALSE to 84
  76: LOAD_FAST            user
  78: SWAP                 
  80: POP_TOP              
  82: RETURN_VALUE         
  84: JUMP_BACKWARD        to 6
  86: LOAD_CONST           0
  88: LOAD_CONST           None
  90: IMPORT_NAME          pwd
  92: STORE_FAST           pwd
  94: LOAD_FAST            pwd
  96: LOAD_METHOD          getpwuid
 118: LOAD_GLOBAL          NULL + os
 130: LOAD_ATTR            getuid
 140: PRECALL              
 144: CALL                 
 154: PRECALL              
 158: CALL                 
 168: LOAD_CONST           0
 170: BINARY_SUBSCR        
 180: RETURN_VALUE         
