# Disassembly for getpass.unix_getpass
# From module file: getpass

## co_consts:
("Prompt for a password, with echo turned off.\n\n    Args:\n      prompt: Written on stream to ask for the input.  Default: 'Password: '\n      stream: A writable file object to display the prompt.  Defaults to\n              the tty.  If no tty is available defaults to sys.stderr.\n    Returns:\n      The seKr3t input.\n    Raises:\n      EOFError: If our input tty or stdin was closed.\n      GetPassWarning: When we were unable to turn echo off on the input.\n\n    Always restores terminal settings before returning.\n    ", None, '/dev/tty', 'w+', 3, 'TCSASOFT', ('input',), '\n')

## co_names:
('contextlib', 'ExitStack', 'os', 'open', 'O_RDWR', 'O_NOCTTY', 'io', 'FileIO', 'enter_context', 'TextIOWrapper', 'OSError', 'close', 'sys', 'stdin', 'fileno', 'AttributeError', 'ValueError', 'fallback_getpass', 'stderr', 'termios', 'tcgetattr', 'ECHO', 'TCSAFLUSH', 'hasattr', 'TCSASOFT', 'tcsetattr', '_raw_input', 'flush', 'error', 'write')

## bytecode:

   0: RESUME               
   2: LOAD_CONST           None
   4: STORE_FAST           passwd
   6: LOAD_GLOBAL          NULL + contextlib
  18: LOAD_ATTR            ExitStack
  28: PRECALL              
  32: CALL                 
  42: BEFORE_WITH          
  44: STORE_FAST           stack
  46: NOP                  
  48: LOAD_GLOBAL          NULL + os
  60: LOAD_ATTR            open
  70: LOAD_CONST           '/dev/tty'
  72: LOAD_GLOBAL          os
  84: LOAD_ATTR            O_RDWR
  94: LOAD_GLOBAL          os
 106: LOAD_ATTR            O_NOCTTY
 116: BINARY_OP            |
 120: PRECALL              
 124: CALL                 
 134: STORE_FAST           fd
 136: LOAD_GLOBAL          NULL + io
 148: LOAD_ATTR            FileIO
 158: LOAD_FAST            fd
 160: LOAD_CONST           'w+'
 162: PRECALL              
 166: CALL                 
 176: STORE_FAST           tty
 178: LOAD_FAST            stack
 180: LOAD_METHOD          enter_context
 202: LOAD_FAST            tty
 204: PRECALL              
 208: CALL                 
 218: POP_TOP              
 220: LOAD_GLOBAL          NULL + io
 232: LOAD_ATTR            TextIOWrapper
 242: LOAD_FAST            tty
 244: PRECALL              
 248: CALL                 
 258: STORE_FAST           input
 260: LOAD_FAST            stack
 262: LOAD_METHOD          enter_context
 284: LOAD_FAST            input
 286: PRECALL              
 290: CALL                 
 300: POP_TOP              
 302: LOAD_FAST            stream
 304: POP_JUMP_FORWARD_IF_TRUE to 310
 306: LOAD_FAST            input
 308: STORE_FAST           stream
 310: JUMP_FORWARD         to 582
 312: PUSH_EXC_INFO        
 314: LOAD_GLOBAL          OSError
 326: CHECK_EXC_MATCH      
 328: POP_JUMP_FORWARD_IF_FALSE to 574
 330: POP_TOP              
 332: LOAD_FAST            stack
 334: LOAD_METHOD          close
 356: PRECALL              
 360: CALL                 
 370: POP_TOP              
 372: NOP                  
 374: LOAD_GLOBAL          sys
 386: LOAD_ATTR            stdin
 396: LOAD_METHOD          fileno
 418: PRECALL              
 422: CALL                 
 432: STORE_FAST           fd
 434: JUMP_FORWARD         to 518
 436: PUSH_EXC_INFO        
 438: LOAD_GLOBAL          AttributeError
 450: LOAD_GLOBAL          ValueError
 462: BUILD_TUPLE          
 464: CHECK_EXC_MATCH      
 466: POP_JUMP_FORWARD_IF_FALSE to 510
 468: POP_TOP              
 470: LOAD_CONST           None
 472: STORE_FAST           fd
 474: LOAD_GLOBAL          NULL + fallback_getpass
 486: LOAD_FAST            prompt
 488: LOAD_FAST            stream
 490: PRECALL              
 494: CALL                 
 504: STORE_FAST           passwd
 506: POP_EXCEPT           
 508: JUMP_FORWARD         to 518
 510: RERAISE              
 512: COPY                 
 514: POP_EXCEPT           
 516: RERAISE              
 518: LOAD_GLOBAL          sys
 530: LOAD_ATTR            stdin
 540: STORE_FAST           input
 542: LOAD_FAST            stream
 544: POP_JUMP_FORWARD_IF_TRUE to 570
 546: LOAD_GLOBAL          sys
 558: LOAD_ATTR            stderr
 568: STORE_FAST           stream
 570: POP_EXCEPT           
 572: JUMP_FORWARD         to 582
 574: RERAISE              
 576: COPY                 
 578: POP_EXCEPT           
 580: RERAISE              
 582: LOAD_FAST            fd
 584: EXTENDED_ARG         
 586: POP_JUMP_FORWARD_IF_NONE to 1192
 588: NOP                  
 590: LOAD_GLOBAL          NULL + termios
 602: LOAD_ATTR            tcgetattr
 612: LOAD_FAST            fd
 614: PRECALL              
 618: CALL                 
 628: STORE_FAST           old
 630: LOAD_FAST            old
 632: LOAD_CONST           None
 634: LOAD_CONST           None
 636: BUILD_SLICE          
 638: BINARY_SUBSCR        
 648: STORE_FAST           new
 650: LOAD_FAST            new
 652: LOAD_CONST           3
 654: COPY                 
 656: COPY                 
 658: BINARY_SUBSCR        
 668: LOAD_GLOBAL          termios
 680: LOAD_ATTR            ECHO
 690: UNARY_INVERT         
 692: BINARY_OP            &=
 696: SWAP                 
 698: SWAP                 
 700: STORE_SUBSCR         
 704: LOAD_GLOBAL          termios
 716: LOAD_ATTR            TCSAFLUSH
 726: STORE_FAST           tcsetattr_flags
 728: LOAD_GLOBAL          NULL + hasattr
 740: LOAD_GLOBAL          termios
 752: LOAD_CONST           'TCSASOFT'
 754: PRECALL              
 758: CALL                 
 768: POP_JUMP_FORWARD_IF_FALSE to 800
 770: LOAD_FAST            tcsetattr_flags
 772: LOAD_GLOBAL          termios
 784: LOAD_ATTR            TCSASOFT
 794: BINARY_OP            |=
 798: STORE_FAST           tcsetattr_flags
 800: NOP                  
 802: LOAD_GLOBAL          NULL + termios
 814: LOAD_ATTR            tcsetattr
 824: LOAD_FAST            fd
 826: LOAD_FAST            tcsetattr_flags
 828: LOAD_FAST            new
 830: PRECALL              
 834: CALL                 
 844: POP_TOP              
 846: LOAD_GLOBAL          NULL + _raw_input
 858: LOAD_FAST            prompt
 860: LOAD_FAST            stream
 862: LOAD_FAST            input
 864: KW_NAMES             
 866: PRECALL              
 870: CALL                 
 880: STORE_FAST           passwd
 882: LOAD_GLOBAL          NULL + termios
 894: LOAD_ATTR            tcsetattr
 904: LOAD_FAST            fd
 906: LOAD_FAST            tcsetattr_flags
 908: LOAD_FAST            old
 910: PRECALL              
 914: CALL                 
 924: POP_TOP              
 926: LOAD_FAST            stream
 928: LOAD_METHOD          flush
 950: PRECALL              
 954: CALL                 
 964: POP_TOP              
 966: JUMP_FORWARD         to 1062
 968: PUSH_EXC_INFO        
 970: LOAD_GLOBAL          NULL + termios
 982: LOAD_ATTR            tcsetattr
 992: LOAD_FAST            fd
 994: LOAD_FAST            tcsetattr_flags
 996: LOAD_FAST            old
 998: PRECALL              
1002: CALL                 
1012: POP_TOP              
1014: LOAD_FAST            stream
1016: LOAD_METHOD          flush
1038: PRECALL              
1042: CALL                 
1052: POP_TOP              
1054: RERAISE              
1056: COPY                 
1058: POP_EXCEPT           
1060: RERAISE              
1062: JUMP_FORWARD         to 1192
1064: PUSH_EXC_INFO        
1066: LOAD_GLOBAL          termios
1078: LOAD_ATTR            error
1088: CHECK_EXC_MATCH      
1090: POP_JUMP_FORWARD_IF_FALSE to 1184
1092: POP_TOP              
1094: LOAD_FAST            passwd
1096: POP_JUMP_FORWARD_IF_NONE to 1100
1098: RAISE_VARARGS        
1100: LOAD_FAST            stream
1102: LOAD_FAST            input
1104: IS_OP                
1106: POP_JUMP_FORWARD_IF_FALSE to 1148
1108: LOAD_FAST            stack
1110: LOAD_METHOD          close
1132: PRECALL              
1136: CALL                 
1146: POP_TOP              
1148: LOAD_GLOBAL          NULL + fallback_getpass
1160: LOAD_FAST            prompt
1162: LOAD_FAST            stream
1164: PRECALL              
1168: CALL                 
1178: STORE_FAST           passwd
1180: POP_EXCEPT           
1182: JUMP_FORWARD         to 1192
1184: RERAISE              
1186: COPY                 
1188: POP_EXCEPT           
1190: RERAISE              
1192: LOAD_FAST            stream
1194: LOAD_METHOD          write
1216: LOAD_CONST           '\n'
1218: PRECALL              
1222: CALL                 
1232: POP_TOP              
1234: LOAD_FAST            passwd
1236: SWAP                 
1238: LOAD_CONST           None
1240: LOAD_CONST           None
1242: LOAD_CONST           None
1244: PRECALL              
1248: CALL                 
1258: POP_TOP              
1260: RETURN_VALUE         
1262: PUSH_EXC_INFO        
1264: WITH_EXCEPT_START    
1266: POP_JUMP_FORWARD_IF_TRUE to 1276
1268: RERAISE              
1270: COPY                 
1272: POP_EXCEPT           
1274: RERAISE              
1276: POP_TOP              
1278: POP_EXCEPT           
1280: POP_TOP              
1282: POP_TOP              
1284: LOAD_CONST           None
1286: RETURN_VALUE         
