# Disassembly for hashlib.file_digest
# From module file: hashlib

## co_consts:
("Hash the contents of a file-like object. Returns a digest object.\n\n    *fileobj* must be a file-like object opened for reading in binary mode.\n    It accepts file objects from open(), io.BytesIO(), and SocketIO objects.\n    The function may bypass Python's I/O and use the file descriptor *fileno*\n    directly.\n\n    *digest* must either be a hash algorithm name as a *str*, a hash\n    constructor, or a callable that returns a hash object.\n    ", 'getbuffer', 'readinto', 'readable', "'", "' is not a file-like object in binary reading mode.", True, 0, None)

## co_names:
('isinstance', 'str', 'new', 'hasattr', 'update', 'getbuffer', 'readable', 'ValueError', 'bytearray', 'memoryview', 'readinto')

## bytecode:

   0: RESUME               
   2: LOAD_GLOBAL          NULL + isinstance
  14: LOAD_FAST            digest
  16: LOAD_GLOBAL          str
  28: PRECALL              
  32: CALL                 
  42: POP_JUMP_FORWARD_IF_FALSE to 76
  44: LOAD_GLOBAL          NULL + new
  56: LOAD_FAST            digest
  58: PRECALL              
  62: CALL                 
  72: STORE_FAST           digestobj
  74: JUMP_FORWARD         to 96
  76: PUSH_NULL            
  78: LOAD_FAST            digest
  80: PRECALL              
  84: CALL                 
  94: STORE_FAST           digestobj
  96: LOAD_GLOBAL          NULL + hasattr
 108: LOAD_FAST            fileobj
 110: LOAD_CONST           'getbuffer'
 112: PRECALL              
 116: CALL                 
 126: POP_JUMP_FORWARD_IF_FALSE to 210
 128: LOAD_FAST            digestobj
 130: LOAD_METHOD          update
 152: LOAD_FAST            fileobj
 154: LOAD_METHOD          getbuffer
 176: PRECALL              
 180: CALL                 
 190: PRECALL              
 194: CALL                 
 204: POP_TOP              
 206: LOAD_FAST            digestobj
 208: RETURN_VALUE         
 210: LOAD_GLOBAL          NULL + hasattr
 222: LOAD_FAST            fileobj
 224: LOAD_CONST           'readinto'
 226: PRECALL              
 230: CALL                 
 240: POP_JUMP_FORWARD_IF_FALSE to 314
 242: LOAD_GLOBAL          NULL + hasattr
 254: LOAD_FAST            fileobj
 256: LOAD_CONST           'readable'
 258: PRECALL              
 262: CALL                 
 272: POP_JUMP_FORWARD_IF_FALSE to 314
 274: LOAD_FAST            fileobj
 276: LOAD_METHOD          readable
 298: PRECALL              
 302: CALL                 
 312: POP_JUMP_FORWARD_IF_TRUE to 352
 314: LOAD_GLOBAL          NULL + ValueError
 326: LOAD_CONST           "'"
 328: LOAD_FAST            fileobj
 330: FORMAT_VALUE         repr
 332: LOAD_CONST           "' is not a file-like object in binary reading mode."
 334: BUILD_STRING         
 336: PRECALL              
 340: CALL                 
 350: RAISE_VARARGS        
 352: LOAD_GLOBAL          NULL + bytearray
 364: LOAD_FAST            _bufsize
 366: PRECALL              
 370: CALL                 
 380: STORE_FAST           buf
 382: LOAD_GLOBAL          NULL + memoryview
 394: LOAD_FAST            buf
 396: PRECALL              
 400: CALL                 
 410: STORE_FAST           view
 412: NOP                  
 414: LOAD_FAST            fileobj
 416: LOAD_METHOD          readinto
 438: LOAD_FAST            buf
 440: PRECALL              
 444: CALL                 
 454: STORE_FAST           size
 456: LOAD_FAST            size
 458: LOAD_CONST           0
 460: COMPARE_OP           ==
 466: POP_JUMP_FORWARD_IF_FALSE to 470
 468: JUMP_FORWARD         to 530
 470: LOAD_FAST            digestobj
 472: LOAD_METHOD          update
 494: LOAD_FAST            view
 496: LOAD_CONST           None
 498: LOAD_FAST            size
 500: BUILD_SLICE          
 502: BINARY_SUBSCR        
 512: PRECALL              
 516: CALL                 
 526: POP_TOP              
 528: JUMP_BACKWARD        to 414
 530: LOAD_FAST            digestobj
 532: RETURN_VALUE         
