# Disassembly for hashlib.__py_new
# From module file: hashlib

## co_consts:
("new(name, data=b'', **kwargs) - Return a new hashing object using the\n    named algorithm; optionally initialized with data (which must be\n    a bytes-like object).\n    ",)

## co_names:
('__get_builtin_constructor',)

## bytecode:

   0: RESUME               
   2: PUSH_NULL            
   4: LOAD_GLOBAL          NULL + __get_builtin_constructor
  16: LOAD_FAST            name
  18: PRECALL              
  22: CALL                 
  32: LOAD_FAST            data
  34: BUILD_TUPLE          
  36: BUILD_MAP            
  38: LOAD_FAST            kwargs
  40: DICT_MERGE           
  42: CALL_FUNCTION_EX     
  44: RETURN_VALUE         
