# Disassembly for hashlib.pbkdf2_hmac
# From module file: hashlib

## co_consts:
("Password based key derivation function 2 (PKCS #5 v2.0)\n\n        This Python implementations based on the hmac module about as fast\n        as OpenSSL's PKCS5_PBKDF2_HMAC for short passwords and much faster\n        for long passwords.\n        ", 'Python implementation of pbkdf2_hmac() is deprecated.', 2, ('category', 'stacklevel'), 'block_size', 64, b'\x00', <code object prf at 0x000002406934FCF0, file "hashlib.py", line 218>, 1, None, b'', 4)

## co_names:
('_warn', 'DeprecationWarning', 'isinstance', 'str', 'TypeError', 'bytes', 'bytearray', 'memoryview', 'new', 'getattr', 'len', 'digest', 'update', 'translate', '_trans_36', '_trans_5C', 'ValueError', 'digest_size', 'int', 'from_bytes', 'to_bytes', 'range')

## bytecode:

   0: RESUME               
   2: LOAD_GLOBAL          NULL + _warn
  14: LOAD_CONST           'Python implementation of pbkdf2_hmac() is deprecated.'
  16: LOAD_GLOBAL          DeprecationWarning
  28: LOAD_CONST           2
  30: KW_NAMES             
  32: PRECALL              
  36: CALL                 
  46: POP_TOP              
  48: LOAD_GLOBAL          NULL + isinstance
  60: LOAD_FAST            hash_name
  62: LOAD_GLOBAL          str
  74: PRECALL              
  78: CALL                 
  88: POP_JUMP_FORWARD_IF_TRUE to 120
  90: LOAD_GLOBAL          NULL + TypeError
 102: LOAD_FAST            hash_name
 104: PRECALL              
 108: CALL                 
 118: RAISE_VARARGS        
 120: LOAD_GLOBAL          NULL + isinstance
 132: LOAD_FAST            password
 134: LOAD_GLOBAL          bytes
 146: LOAD_GLOBAL          bytearray
 158: BUILD_TUPLE          
 160: PRECALL              
 164: CALL                 
 174: POP_JUMP_FORWARD_IF_TRUE to 232
 176: LOAD_GLOBAL          NULL + bytes
 188: LOAD_GLOBAL          NULL + memoryview
 200: LOAD_FAST            password
 202: PRECALL              
 206: CALL                 
 216: PRECALL              
 220: CALL                 
 230: STORE_FAST           password
 232: LOAD_GLOBAL          NULL + isinstance
 244: LOAD_FAST            salt
 246: LOAD_GLOBAL          bytes
 258: LOAD_GLOBAL          bytearray
 270: BUILD_TUPLE          
 272: PRECALL              
 276: CALL                 
 286: POP_JUMP_FORWARD_IF_TRUE to 344
 288: LOAD_GLOBAL          NULL + bytes
 300: LOAD_GLOBAL          NULL + memoryview
 312: LOAD_FAST            salt
 314: PRECALL              
 318: CALL                 
 328: PRECALL              
 332: CALL                 
 342: STORE_FAST           salt
 344: LOAD_GLOBAL          NULL + new
 356: LOAD_FAST            hash_name
 358: PRECALL              
 362: CALL                 
 372: STORE_FAST           inner
 374: LOAD_GLOBAL          NULL + new
 386: LOAD_FAST            hash_name
 388: PRECALL              
 392: CALL                 
 402: STORE_FAST           outer
 404: LOAD_GLOBAL          NULL + getattr
 416: LOAD_FAST            inner
 418: LOAD_CONST           'block_size'
 420: LOAD_CONST           64
 422: PRECALL              
 426: CALL                 
 436: STORE_FAST           blocksize
 438: LOAD_GLOBAL          NULL + len
 450: LOAD_FAST            password
 452: PRECALL              
 456: CALL                 
 466: LOAD_FAST            blocksize
 468: COMPARE_OP           >
 474: POP_JUMP_FORWARD_IF_FALSE to 544
 476: LOAD_GLOBAL          NULL + new
 488: LOAD_FAST            hash_name
 490: LOAD_FAST            password
 492: PRECALL              
 496: CALL                 
 506: LOAD_METHOD          digest
 528: PRECALL              
 532: CALL                 
 542: STORE_FAST           password
 544: LOAD_FAST            password
 546: LOAD_CONST           b'\x00'
 548: LOAD_FAST            blocksize
 550: LOAD_GLOBAL          NULL + len
 562: LOAD_FAST            password
 564: PRECALL              
 568: CALL                 
 578: BINARY_OP            -
 582: BINARY_OP            *
 586: BINARY_OP            +
 590: STORE_FAST           password
 592: LOAD_FAST            inner
 594: LOAD_METHOD          update
 616: LOAD_FAST            password
 618: LOAD_METHOD          translate
 640: LOAD_GLOBAL          _trans_36
 652: PRECALL              
 656: CALL                 
 666: PRECALL              
 670: CALL                 
 680: POP_TOP              
 682: LOAD_FAST            outer
 684: LOAD_METHOD          update
 706: LOAD_FAST            password
 708: LOAD_METHOD          translate
 730: LOAD_GLOBAL          _trans_5C
 742: PRECALL              
 746: CALL                 
 756: PRECALL              
 760: CALL                 
 770: POP_TOP              
 772: LOAD_FAST            inner
 774: LOAD_FAST            outer
 776: BUILD_TUPLE          
 778: LOAD_CONST           <code object prf at 0x000002406934FCF0, file "hashlib.py", line 218>
 780: MAKE_FUNCTION        defaults
 782: STORE_FAST           prf
 784: LOAD_FAST            iterations
 786: LOAD_CONST           1
 788: COMPARE_OP           <
 794: POP_JUMP_FORWARD_IF_FALSE to 826
 796: LOAD_GLOBAL          NULL + ValueError
 808: LOAD_FAST            iterations
 810: PRECALL              
 814: CALL                 
 824: RAISE_VARARGS        
 826: LOAD_FAST            dklen
 828: POP_JUMP_FORWARD_IF_NOT_NONE to 844
 830: LOAD_FAST            outer
 832: LOAD_ATTR            digest_size
 842: STORE_FAST           dklen
 844: LOAD_FAST            dklen
 846: LOAD_CONST           1
 848: COMPARE_OP           <
 854: POP_JUMP_FORWARD_IF_FALSE to 886
 856: LOAD_GLOBAL          NULL + ValueError
 868: LOAD_FAST            dklen
 870: PRECALL              
 874: CALL                 
 884: RAISE_VARARGS        
 886: LOAD_CONST           b''
 888: STORE_FAST           dkey
 890: LOAD_CONST           1
 892: STORE_FAST           loop
 894: LOAD_GLOBAL          int
 906: LOAD_ATTR            from_bytes
 916: STORE_FAST           from_bytes
 918: LOAD_GLOBAL          NULL + len
 930: LOAD_FAST            dkey
 932: PRECALL              
 936: CALL                 
 946: LOAD_FAST            dklen
 948: COMPARE_OP           <
 954: POP_JUMP_FORWARD_IF_FALSE to 1242
 956: PUSH_NULL            
 958: LOAD_FAST            prf
 960: LOAD_FAST            salt
 962: LOAD_FAST            loop
 964: LOAD_METHOD          to_bytes
 986: LOAD_CONST           4
 988: PRECALL              
 992: CALL                 
1002: BINARY_OP            +
1006: PRECALL              
1010: CALL                 
1020: STORE_FAST           prev
1022: PUSH_NULL            
1024: LOAD_FAST            from_bytes
1026: LOAD_FAST            prev
1028: PRECALL              
1032: CALL                 
1042: STORE_FAST           rkey
1044: LOAD_GLOBAL          NULL + range
1056: LOAD_FAST            iterations
1058: LOAD_CONST           1
1060: BINARY_OP            -
1064: PRECALL              
1068: CALL                 
1078: GET_ITER             
1080: FOR_ITER             to 1136
1082: STORE_FAST           i
1084: PUSH_NULL            
1086: LOAD_FAST            prf
1088: LOAD_FAST            prev
1090: PRECALL              
1094: CALL                 
1104: STORE_FAST           prev
1106: LOAD_FAST            rkey
1108: PUSH_NULL            
1110: LOAD_FAST            from_bytes
1112: LOAD_FAST            prev
1114: PRECALL              
1118: CALL                 
1128: BINARY_OP            ^=
1132: STORE_FAST           rkey
1134: JUMP_BACKWARD        to 1080
1136: LOAD_FAST            loop
1138: LOAD_CONST           1
1140: BINARY_OP            +=
1144: STORE_FAST           loop
1146: LOAD_FAST            dkey
1148: LOAD_FAST            rkey
1150: LOAD_METHOD          to_bytes
1172: LOAD_FAST            inner
1174: LOAD_ATTR            digest_size
1184: PRECALL              
1188: CALL                 
1198: BINARY_OP            +=
1202: STORE_FAST           dkey
1204: LOAD_GLOBAL          NULL + len
1216: LOAD_FAST            dkey
1218: PRECALL              
1222: CALL                 
1232: LOAD_FAST            dklen
1234: COMPARE_OP           <
1240: POP_JUMP_BACKWARD_IF_TRUE to 956
1242: LOAD_FAST            dkey
1244: LOAD_CONST           None
1246: LOAD_FAST            dklen
1248: BUILD_SLICE          
1250: BINARY_SUBSCR        
1260: RETURN_VALUE         
