# Disassembly for playroom
# From module file: playroom

## co_consts:
(0, ('*',), <code object Drawings at 0x00000240693AA6F0, file "playroom.py", line 4>, 'Drawings', <code object FactoryModel at 0x00000240693AB9B0, file "playroom.py", line 39>, 'FactoryModel', <code object Playroom at 0x00000240691F39F0, file "playroom.py", line 72>, 'Playroom', None)

## co_names:
('entities', 'Item', 'Drawings', 'FactoryModel', 'Room', 'Playroom')

## bytecode:

   0: RESUME               
   2: LOAD_CONST           0
   4: LOAD_CONST           ('*',)
   6: IMPORT_NAME          entities
   8: IMPORT_STAR          
  10: PUSH_NULL            
  12: LOAD_BUILD_CLASS     
  14: LOAD_CONST           <code object Drawings at 0x00000240693AA6F0, file "playroom.py", line 4>
  16: MAKE_FUNCTION        
  18: LOAD_CONST           'Drawings'
  20: LOAD_NAME            Item
  22: PRECALL              
  26: CALL                 
  36: STORE_NAME           Drawings
  38: PUSH_NULL            
  40: LOAD_BUILD_CLASS     
  42: LOAD_CONST           <code object FactoryModel at 0x00000240693AB9B0, file "playroom.py", line 39>
  44: MAKE_FUNCTION        
  46: LOAD_CONST           'FactoryModel'
  48: LOAD_NAME            Item
  50: PRECALL              
  54: CALL                 
  64: STORE_NAME           FactoryModel
  66: PUSH_NULL            
  68: LOAD_BUILD_CLASS     
  70: LOAD_CONST           <code object Playroom at 0x00000240691F39F0, file "playroom.py", line 72>
  72: MAKE_FUNCTION        
  74: LOAD_CONST           'Playroom'
  76: LOAD_NAME            Room
  78: PRECALL              
  82: CALL                 
  92: STORE_NAME           Playroom
  94: LOAD_CONST           None
  96: RETURN_VALUE         
