# Disassembly for playroom.Drawings.get_options
# From module file: playroom

## co_consts:
(None, <code object <lambda> at 0x000002406945FF00, file "playroom.py", line 14>, 'Check out the crayon drawings on the walls.')

## co_names:
('append',)

## bytecode:

   0: MAKE_CELL            self
   2: RESUME               
   4: BUILD_LIST           
   6: STORE_FAST           options
   8: LOAD_FAST            options
  10: LOAD_METHOD          append
  32: LOAD_CLOSURE         self
  34: BUILD_TUPLE          
  36: LOAD_CONST           <code object <lambda> at 0x000002406945FF00, file "playroom.py", line 14>
  38: MAKE_FUNCTION        closure
  40: LOAD_CONST           'Check out the crayon drawings on the walls.'
  42: BUILD_TUPLE          
  44: PRECALL              
  48: CALL                 
  58: POP_TOP              
  60: LOAD_FAST            options
  62: RETURN_VALUE         
