# Disassembly for dataclasses._hash_add
# From module file: dataclasses

## co_consts:
(None, <code object <listcomp> at 0x00000240693EAC30, file "dataclasses.py", line 846>)

## co_names:
('_set_qualname', '_hash_fn')

## bytecode:

   0: RESUME               
   2: LOAD_CONST           <code object <listcomp> at 0x00000240693EAC30, file "dataclasses.py", line 846>
   4: MAKE_FUNCTION        
   6: LOAD_FAST            fields
   8: GET_ITER             
  10: PRECALL              
  14: CALL                 
  24: STORE_FAST           flds
  26: LOAD_GLOBAL          NULL + _set_qualname
  38: LOAD_FAST            cls
  40: LOAD_GLOBAL          NULL + _hash_fn
  52: LOAD_FAST            flds
  54: LOAD_FAST            globals
  56: PRECALL              
  60: CALL                 
  70: PRECALL              
  74: CALL                 
  84: RETURN_VALUE         
