# Disassembly for dataclasses._DataclassParams
# From module file: dataclasses

## co_consts:
('_DataclassParams', ('init', 'repr', 'eq', 'order', 'unsafe_hash', 'frozen'), <code object __init__ at 0x000002406941AAF0, file "dataclasses.py", line 346>, <code object __repr__ at 0x000002406941B090, file "dataclasses.py", line 354>, None)

## co_names:
('__name__', '__module__', '__qualname__', '__slots__', '__init__', '__repr__')

## bytecode:

   0: RESUME               
   2: LOAD_NAME            __name__
   4: STORE_NAME           __module__
   6: LOAD_CONST           '_DataclassParams'
   8: STORE_NAME           __qualname__
  10: LOAD_CONST           ('init', 'repr', 'eq', 'order', 'unsafe_hash', 'frozen')
  12: STORE_NAME           __slots__
  14: LOAD_CONST           <code object __init__ at 0x000002406941AAF0, file "dataclasses.py", line 346>
  16: MAKE_FUNCTION        
  18: STORE_NAME           __init__
  20: LOAD_CONST           <code object __repr__ at 0x000002406941B090, file "dataclasses.py", line 354>
  22: MAKE_FUNCTION        
  24: STORE_NAME           __repr__
  26: LOAD_CONST           None
  28: RETURN_VALUE         
