# Disassembly for dataclasses.replace
# From module file: dataclasses

## co_consts:
('Return a new object replacing specified fields with new values.\n\n    This is especially useful for frozen classes.  Example usage::\n\n      @dataclass(frozen=True)\n      class C:\n          x: int\n          y: int\n\n      c = C(1, 2)\n      c1 = replace(c, x=3)\n      assert c1.x == 3 and c1.y == 2\n    ', 'replace() should be called on dataclass instances', 'field ', ' is declared with init=False, it cannot be specified with replace()', 'InitVar ', ' must be specified with replace()', ())

## co_names:
('_is_dataclass_instance', 'TypeError', 'getattr', '_FIELDS', 'values', '_field_type', '_FIELD_CLASSVAR', 'init', 'name', 'ValueError', '_FIELD_INITVAR', 'default', 'MISSING', '__class__')

## bytecode:

   0: RESUME               
   2: LOAD_GLOBAL          NULL + _is_dataclass_instance
  14: LOAD_FAST            obj
  16: PRECALL              
  20: CALL                 
  30: POP_JUMP_FORWARD_IF_TRUE to 62
  32: LOAD_GLOBAL          NULL + TypeError
  44: LOAD_CONST           'replace() should be called on dataclass instances'
  46: PRECALL              
  50: CALL                 
  60: RAISE_VARARGS        
  62: LOAD_GLOBAL          NULL + getattr
  74: LOAD_FAST            obj
  76: LOAD_GLOBAL          _FIELDS
  88: PRECALL              
  92: CALL                 
 102: LOAD_METHOD          values
 124: PRECALL              
 128: CALL                 
 138: GET_ITER             
 140: FOR_ITER             to 438
 142: STORE_FAST           f
 144: LOAD_FAST            f
 146: LOAD_ATTR            _field_type
 156: LOAD_GLOBAL          _FIELD_CLASSVAR
 168: IS_OP                
 170: POP_JUMP_FORWARD_IF_FALSE to 174
 172: JUMP_BACKWARD        to 140
 174: LOAD_FAST            f
 176: LOAD_ATTR            init
 186: POP_JUMP_FORWARD_IF_TRUE to 256
 188: LOAD_FAST            f
 190: LOAD_ATTR            name
 200: LOAD_FAST            changes
 202: CONTAINS_OP          
 204: POP_JUMP_FORWARD_IF_FALSE to 254
 206: LOAD_GLOBAL          NULL + ValueError
 218: LOAD_CONST           'field '
 220: LOAD_FAST            f
 222: LOAD_ATTR            name
 232: FORMAT_VALUE         
 234: LOAD_CONST           ' is declared with init=False, it cannot be specified with replace()'
 236: BUILD_STRING         
 238: PRECALL              
 242: CALL                 
 252: RAISE_VARARGS        
 254: JUMP_BACKWARD        to 140
 256: LOAD_FAST            f
 258: LOAD_ATTR            name
 268: LOAD_FAST            changes
 270: CONTAINS_OP          
 272: POP_JUMP_FORWARD_IF_FALSE to 436
 274: LOAD_FAST            f
 276: LOAD_ATTR            _field_type
 286: LOAD_GLOBAL          _FIELD_INITVAR
 298: IS_OP                
 300: POP_JUMP_FORWARD_IF_FALSE to 378
 302: LOAD_FAST            f
 304: LOAD_ATTR            default
 314: LOAD_GLOBAL          MISSING
 326: IS_OP                
 328: POP_JUMP_FORWARD_IF_FALSE to 378
 330: LOAD_GLOBAL          NULL + ValueError
 342: LOAD_CONST           'InitVar '
 344: LOAD_FAST            f
 346: LOAD_ATTR            name
 356: FORMAT_VALUE         repr
 358: LOAD_CONST           ' must be specified with replace()'
 360: BUILD_STRING         
 362: PRECALL              
 366: CALL                 
 376: RAISE_VARARGS        
 378: LOAD_GLOBAL          NULL + getattr
 390: LOAD_FAST            obj
 392: LOAD_FAST            f
 394: LOAD_ATTR            name
 404: PRECALL              
 408: CALL                 
 418: LOAD_FAST            changes
 420: LOAD_FAST            f
 422: LOAD_ATTR            name
 432: STORE_SUBSCR         
 436: JUMP_BACKWARD        to 140
 438: PUSH_NULL            
 440: LOAD_FAST            obj
 442: LOAD_ATTR            __class__
 452: LOAD_CONST           ()
 454: BUILD_MAP            
 456: LOAD_FAST            changes
 458: DICT_MERGE           
 460: CALL_FUNCTION_EX     
 462: RETURN_VALUE         
