# Disassembly for dataclasses._tuple_str.<listcomp>
# From module file: dataclasses

## co_consts:
('.',)

## co_names:
('name',)

## bytecode:

   0: COPY_FREE_VARS       
   2: RESUME               
   4: BUILD_LIST           
   6: LOAD_FAST            .0
   8: FOR_ITER             to 38
  10: STORE_FAST           f
  12: LOAD_DEREF           obj_name
  14: FORMAT_VALUE         
  16: LOAD_CONST           '.'
  18: LOAD_FAST            f
  20: LOAD_ATTR            name
  30: FORMAT_VALUE         
  32: BUILD_STRING         
  34: LIST_APPEND          
  36: JUMP_BACKWARD        to 8
  38: RETURN_VALUE         
