# Disassembly for dataclasses._astuple_inner.<listcomp>
# From module file: dataclasses

## co_consts:
()

## co_names:
('_astuple_inner',)

## bytecode:

   0: COPY_FREE_VARS       
   2: RESUME               
   4: BUILD_LIST           
   6: LOAD_FAST            .0
   8: FOR_ITER             to 46
  10: STORE_FAST           v
  12: LOAD_GLOBAL          NULL + _astuple_inner
  24: LOAD_FAST            v
  26: LOAD_DEREF           tuple_factory
  28: PRECALL              
  32: CALL                 
  42: LIST_APPEND          
  44: JUMP_BACKWARD        to 8
  46: RETURN_VALUE         
