# Disassembly for dataclasses._cmp_fn
# From module file: dataclasses

## co_consts:
(None, ('self', 'other'), 'if other.__class__ is self.__class__:', ' return ', 'return NotImplemented', ('globals',))

## co_names:
('_create_fn',)

## bytecode:

   0: RESUME               
   2: LOAD_GLOBAL          NULL + _create_fn
  14: LOAD_FAST            name
  16: LOAD_CONST           ('self', 'other')
  18: LOAD_CONST           'if other.__class__ is self.__class__:'
  20: LOAD_CONST           ' return '
  22: LOAD_FAST            self_tuple
  24: FORMAT_VALUE         
  26: LOAD_FAST            op
  28: FORMAT_VALUE         
  30: LOAD_FAST            other_tuple
  32: FORMAT_VALUE         
  34: BUILD_STRING         
  36: LOAD_CONST           'return NotImplemented'
  38: BUILD_LIST           
  40: LOAD_FAST            globals
  42: KW_NAMES             
  44: PRECALL              
  48: CALL                 
  58: RETURN_VALUE         
