# Disassembly for dataclasses._recursive_repr
# From module file: dataclasses

## co_consts:
(None, <code object wrapper at 0x00000240691A7D70, file "dataclasses.py", line 233>)

## co_names:
('set', 'functools', 'wraps')

## bytecode:

   0: MAKE_CELL            user_function
   2: MAKE_CELL            repr_running
   4: RESUME               
   6: LOAD_GLOBAL          NULL + set
  18: PRECALL              
  22: CALL                 
  32: STORE_DEREF          repr_running
  34: LOAD_GLOBAL          NULL + functools
  46: LOAD_ATTR            wraps
  56: LOAD_DEREF           user_function
  58: PRECALL              
  62: CALL                 
  72: LOAD_CLOSURE         repr_running
  74: LOAD_CLOSURE         user_function
  76: BUILD_TUPLE          
  78: LOAD_CONST           <code object wrapper at 0x00000240691A7D70, file "dataclasses.py", line 233>
  80: MAKE_FUNCTION        closure
  82: PRECALL              
  86: CALL                 
  96: STORE_FAST           wrapper
  98: LOAD_FAST            wrapper
 100: RETURN_VALUE         
