# Disassembly for dataclasses._process_class
# From module file: dataclasses

## co_consts:
(None, False, -1, 0, True, '__annotations__', ' is KW_ONLY, but KW_ONLY has already been specified', ' is a field but has no type annotation', 'cannot inherit non-frozen dataclass from a frozen one', 'cannot inherit frozen dataclass from a non-frozen one', '__hash__', '__eq__', 'eq must be true if order is true', <code object <listcomp> at 0x00000240693EAA30, file "dataclasses.py", line 1017>, '__init__', 'self', '__dataclass_self__', <code object <listcomp> at 0x000002406945F4B0, file "dataclasses.py", line 1043>, <code object <listcomp> at 0x0000024069466330, file "dataclasses.py", line 1046>, '__repr__', <code object <listcomp> at 0x0000024069467E50, file "dataclasses.py", line 1052>, 'other', '==', ('globals',), <code object <listcomp> at 0x0000024069465610, file "dataclasses.py", line 1062>, (('__lt__', '<'), ('__le__', '<='), ('__gt__', '>'), ('__ge__', '>=')), 'Cannot overwrite attribute ', ' in class ', '. Consider using functools.total_ordering', '__doc__', ' -> None', '', '__match_args__', <code object <genexpr> at 0x0000024069467BB0, file "dataclasses.py", line 1106>, 'weakref_slot is True but slots is False')

## co_names:
('__module__', 'sys', 'modules', '__dict__', 'setattr', '_PARAMS', '_DataclassParams', '__mro__', 'getattr', '_FIELDS', 'values', 'name', 'frozen', 'get', '__name__', 'items', '_is_kw_only', 'isinstance', 'str', '_is_type', 'KW_ONLY', 'TypeError', 'append', '_get_field', 'Field', 'default', 'MISSING', 'delattr', 'ValueError', '_fields_in_init_order', 'hasattr', '_POST_INIT_NAME', '_set_new_attribute', '_init_fn', '_repr_fn', '_tuple_str', '_cmp_fn', '_frozen_get_del_attr', '_hash_action', 'bool', '__hash__', 'inspect', 'signature', 'replace', '__doc__', 'tuple', '_add_slots', 'abc', 'update_abstractmethods')

## bytecode:

   0: RESUME               
   2: BUILD_MAP            
   4: STORE_FAST           fields
   6: LOAD_FAST            cls
   8: LOAD_ATTR            __module__
  18: LOAD_GLOBAL          sys
  30: LOAD_ATTR            modules
  40: CONTAINS_OP          
  42: POP_JUMP_FORWARD_IF_FALSE to 102
  44: LOAD_GLOBAL          sys
  56: LOAD_ATTR            modules
  66: LOAD_FAST            cls
  68: LOAD_ATTR            __module__
  78: BINARY_SUBSCR        
  88: LOAD_ATTR            __dict__
  98: STORE_FAST           globals
 100: JUMP_FORWARD         to 106
 102: BUILD_MAP            
 104: STORE_FAST           globals
 106: LOAD_GLOBAL          NULL + setattr
 118: LOAD_FAST            cls
 120: LOAD_GLOBAL          _PARAMS
 132: LOAD_GLOBAL          NULL + _DataclassParams
 144: LOAD_FAST            init
 146: LOAD_FAST            repr
 148: LOAD_FAST            eq
 150: LOAD_FAST            order
 152: LOAD_FAST            unsafe_hash
 154: LOAD_FAST            frozen
 156: PRECALL              
 160: CALL                 
 170: PRECALL              
 174: CALL                 
 184: POP_TOP              
 186: LOAD_CONST           False
 188: STORE_FAST           any_frozen_base
 190: LOAD_CONST           False
 192: STORE_FAST           has_dataclass_bases
 194: LOAD_FAST            cls
 196: LOAD_ATTR            __mro__
 206: LOAD_CONST           -1
 208: LOAD_CONST           0
 210: LOAD_CONST           -1
 212: BUILD_SLICE          
 214: BINARY_SUBSCR        
 224: GET_ITER             
 226: FOR_ITER             to 406
 228: STORE_FAST           b
 230: LOAD_GLOBAL          NULL + getattr
 242: LOAD_FAST            b
 244: LOAD_GLOBAL          _FIELDS
 256: LOAD_CONST           None
 258: PRECALL              
 262: CALL                 
 272: STORE_FAST           base_fields
 274: LOAD_FAST            base_fields
 276: POP_JUMP_FORWARD_IF_NONE to 404
 278: LOAD_CONST           True
 280: STORE_FAST           has_dataclass_bases
 282: LOAD_FAST            base_fields
 284: LOAD_METHOD          values
 306: PRECALL              
 310: CALL                 
 320: GET_ITER             
 322: FOR_ITER             to 348
 324: STORE_FAST           f
 326: LOAD_FAST            f
 328: LOAD_FAST            fields
 330: LOAD_FAST            f
 332: LOAD_ATTR            name
 342: STORE_SUBSCR         
 346: JUMP_BACKWARD        to 322
 348: LOAD_GLOBAL          NULL + getattr
 360: LOAD_FAST            b
 362: LOAD_GLOBAL          _PARAMS
 374: PRECALL              
 378: CALL                 
 388: LOAD_ATTR            frozen
 398: POP_JUMP_FORWARD_IF_FALSE to 404
 400: LOAD_CONST           True
 402: STORE_FAST           any_frozen_base
 404: JUMP_BACKWARD        to 226
 406: LOAD_FAST            cls
 408: LOAD_ATTR            __dict__
 418: LOAD_METHOD          get
 440: LOAD_CONST           '__annotations__'
 442: BUILD_MAP            
 444: PRECALL              
 448: CALL                 
 458: STORE_FAST           cls_annotations
 460: BUILD_LIST           
 462: STORE_FAST           cls_fields
 464: LOAD_CONST           False
 466: STORE_FAST           KW_ONLY_seen
 468: LOAD_GLOBAL          sys
 480: LOAD_ATTR            modules
 490: LOAD_GLOBAL          __name__
 502: BINARY_SUBSCR        
 512: STORE_FAST           dataclasses
 514: LOAD_FAST            cls_annotations
 516: LOAD_METHOD          items
 538: PRECALL              
 542: CALL                 
 552: GET_ITER             
 554: FOR_ITER             to 822
 556: UNPACK_SEQUENCE      
 560: STORE_FAST           name
 562: STORE_FAST           type
 564: LOAD_GLOBAL          NULL + _is_kw_only
 576: LOAD_FAST            type
 578: LOAD_FAST            dataclasses
 580: PRECALL              
 584: CALL                 
 594: POP_JUMP_FORWARD_IF_TRUE to 696
 596: LOAD_GLOBAL          NULL + isinstance
 608: LOAD_FAST            type
 610: LOAD_GLOBAL          str
 622: PRECALL              
 626: CALL                 
 636: POP_JUMP_FORWARD_IF_FALSE to 746
 638: LOAD_GLOBAL          NULL + _is_type
 650: LOAD_FAST            type
 652: LOAD_FAST            cls
 654: LOAD_FAST            dataclasses
 656: LOAD_FAST            dataclasses
 658: LOAD_ATTR            KW_ONLY
 668: LOAD_GLOBAL          _is_kw_only
 680: PRECALL              
 684: CALL                 
 694: POP_JUMP_FORWARD_IF_FALSE to 746
 696: LOAD_FAST            KW_ONLY_seen
 698: POP_JUMP_FORWARD_IF_FALSE to 736
 700: LOAD_GLOBAL          NULL + TypeError
 712: LOAD_FAST            name
 714: FORMAT_VALUE         repr
 716: LOAD_CONST           ' is KW_ONLY, but KW_ONLY has already been specified'
 718: BUILD_STRING         
 720: PRECALL              
 724: CALL                 
 734: RAISE_VARARGS        
 736: LOAD_CONST           True
 738: STORE_FAST           KW_ONLY_seen
 740: LOAD_CONST           True
 742: STORE_FAST           kw_only
 744: JUMP_BACKWARD        to 554
 746: LOAD_FAST            cls_fields
 748: LOAD_METHOD          append
 770: LOAD_GLOBAL          NULL + _get_field
 782: LOAD_FAST            cls
 784: LOAD_FAST            name
 786: LOAD_FAST            type
 788: LOAD_FAST            kw_only
 790: PRECALL              
 794: CALL                 
 804: PRECALL              
 808: CALL                 
 818: POP_TOP              
 820: JUMP_BACKWARD        to 554
 822: LOAD_FAST            cls_fields
 824: GET_ITER             
 826: FOR_ITER             to 1060
 828: STORE_FAST           f
 830: LOAD_FAST            f
 832: LOAD_FAST            fields
 834: LOAD_FAST            f
 836: LOAD_ATTR            name
 846: STORE_SUBSCR         
 850: LOAD_GLOBAL          NULL + isinstance
 862: LOAD_GLOBAL          NULL + getattr
 874: LOAD_FAST            cls
 876: LOAD_FAST            f
 878: LOAD_ATTR            name
 888: LOAD_CONST           None
 890: PRECALL              
 894: CALL                 
 904: LOAD_GLOBAL          Field
 916: PRECALL              
 920: CALL                 
 930: POP_JUMP_FORWARD_IF_FALSE to 1058
 932: LOAD_FAST            f
 934: LOAD_ATTR            default
 944: LOAD_GLOBAL          MISSING
 956: IS_OP                
 958: POP_JUMP_FORWARD_IF_FALSE to 1004
 960: LOAD_GLOBAL          NULL + delattr
 972: LOAD_FAST            cls
 974: LOAD_FAST            f
 976: LOAD_ATTR            name
 986: PRECALL              
 990: CALL                 
1000: POP_TOP              
1002: JUMP_BACKWARD        to 826
1004: LOAD_GLOBAL          NULL + setattr
1016: LOAD_FAST            cls
1018: LOAD_FAST            f
1020: LOAD_ATTR            name
1030: LOAD_FAST            f
1032: LOAD_ATTR            default
1042: PRECALL              
1046: CALL                 
1056: POP_TOP              
1058: JUMP_BACKWARD        to 826
1060: LOAD_FAST            cls
1062: LOAD_ATTR            __dict__
1072: LOAD_METHOD          items
1094: PRECALL              
1098: CALL                 
1108: GET_ITER             
1110: FOR_ITER             to 1208
1112: UNPACK_SEQUENCE      
1116: STORE_FAST           name
1118: STORE_FAST           value
1120: LOAD_GLOBAL          NULL + isinstance
1132: LOAD_FAST            value
1134: LOAD_GLOBAL          Field
1146: PRECALL              
1150: CALL                 
1160: POP_JUMP_FORWARD_IF_FALSE to 1206
1162: LOAD_FAST            name
1164: LOAD_FAST            cls_annotations
1166: CONTAINS_OP          
1168: POP_JUMP_FORWARD_IF_FALSE to 1206
1170: LOAD_GLOBAL          NULL + TypeError
1182: LOAD_FAST            name
1184: FORMAT_VALUE         repr
1186: LOAD_CONST           ' is a field but has no type annotation'
1188: BUILD_STRING         
1190: PRECALL              
1194: CALL                 
1204: RAISE_VARARGS        
1206: JUMP_BACKWARD        to 1110
1208: LOAD_FAST            has_dataclass_bases
1210: POP_JUMP_FORWARD_IF_FALSE to 1288
1212: LOAD_FAST            any_frozen_base
1214: POP_JUMP_FORWARD_IF_FALSE to 1250
1216: LOAD_FAST            frozen
1218: POP_JUMP_FORWARD_IF_TRUE to 1250
1220: LOAD_GLOBAL          NULL + TypeError
1232: LOAD_CONST           'cannot inherit non-frozen dataclass from a frozen one'
1234: PRECALL              
1238: CALL                 
1248: RAISE_VARARGS        
1250: LOAD_FAST            any_frozen_base
1252: POP_JUMP_FORWARD_IF_TRUE to 1288
1254: LOAD_FAST            frozen
1256: POP_JUMP_FORWARD_IF_FALSE to 1288
1258: LOAD_GLOBAL          NULL + TypeError
1270: LOAD_CONST           'cannot inherit frozen dataclass from a non-frozen one'
1272: PRECALL              
1276: CALL                 
1286: RAISE_VARARGS        
1288: LOAD_GLOBAL          NULL + setattr
1300: LOAD_FAST            cls
1302: LOAD_GLOBAL          _FIELDS
1314: LOAD_FAST            fields
1316: PRECALL              
1320: CALL                 
1330: POP_TOP              
1332: LOAD_FAST            cls
1334: LOAD_ATTR            __dict__
1344: LOAD_METHOD          get
1366: LOAD_CONST           '__hash__'
1368: LOAD_GLOBAL          MISSING
1380: PRECALL              
1384: CALL                 
1394: STORE_FAST           class_hash
1396: LOAD_FAST            class_hash
1398: LOAD_GLOBAL          MISSING
1410: IS_OP                
1412: JUMP_IF_TRUE_OR_POP  to 1438
1414: LOAD_FAST            class_hash
1416: LOAD_CONST           None
1418: IS_OP                
1420: JUMP_IF_FALSE_OR_POP to 1438
1422: LOAD_CONST           '__eq__'
1424: LOAD_FAST            cls
1426: LOAD_ATTR            __dict__
1436: CONTAINS_OP          
1438: UNARY_NOT            
1440: STORE_FAST           has_explicit_hash
1442: LOAD_FAST            order
1444: POP_JUMP_FORWARD_IF_FALSE to 1480
1446: LOAD_FAST            eq
1448: POP_JUMP_FORWARD_IF_TRUE to 1480
1450: LOAD_GLOBAL          NULL + ValueError
1462: LOAD_CONST           'eq must be true if order is true'
1464: PRECALL              
1468: CALL                 
1478: RAISE_VARARGS        
1480: LOAD_CONST           <code object <listcomp> at 0x00000240693EAA30, file "dataclasses.py", line 1017>
1482: MAKE_FUNCTION        
1484: LOAD_FAST            fields
1486: LOAD_METHOD          values
1508: PRECALL              
1512: CALL                 
1522: GET_ITER             
1524: PRECALL              
1528: CALL                 
1538: STORE_FAST           all_init_fields
1540: LOAD_GLOBAL          NULL + _fields_in_init_order
1552: LOAD_FAST            all_init_fields
1554: PRECALL              
1558: CALL                 
1568: UNPACK_SEQUENCE      
1572: STORE_FAST           std_init_fields
1574: STORE_FAST           kw_only_init_fields
1576: LOAD_FAST            init
1578: POP_JUMP_FORWARD_IF_FALSE to 1708
1580: LOAD_GLOBAL          NULL + hasattr
1592: LOAD_FAST            cls
1594: LOAD_GLOBAL          _POST_INIT_NAME
1606: PRECALL              
1610: CALL                 
1620: STORE_FAST           has_post_init
1622: LOAD_GLOBAL          NULL + _set_new_attribute
1634: LOAD_FAST            cls
1636: LOAD_CONST           '__init__'
1638: LOAD_GLOBAL          NULL + _init_fn
1650: LOAD_FAST            all_init_fields
1652: LOAD_FAST            std_init_fields
1654: LOAD_FAST            kw_only_init_fields
1656: LOAD_FAST            frozen
1658: LOAD_FAST            has_post_init
1660: LOAD_CONST           'self'
1662: LOAD_FAST            fields
1664: CONTAINS_OP          
1666: POP_JUMP_FORWARD_IF_FALSE to 1672
1668: LOAD_CONST           '__dataclass_self__'
1670: JUMP_FORWARD         to 1674
1672: LOAD_CONST           'self'
1674: LOAD_FAST            globals
1676: LOAD_FAST            slots
1678: PRECALL              
1682: CALL                 
1692: PRECALL              
1696: CALL                 
1706: POP_TOP              
1708: LOAD_CONST           <code object <listcomp> at 0x000002406945F4B0, file "dataclasses.py", line 1043>
1710: MAKE_FUNCTION        
1712: LOAD_FAST            fields
1714: LOAD_METHOD          values
1736: PRECALL              
1740: CALL                 
1750: GET_ITER             
1752: PRECALL              
1756: CALL                 
1766: STORE_FAST           field_list
1768: LOAD_FAST            repr
1770: POP_JUMP_FORWARD_IF_FALSE to 1858
1772: LOAD_CONST           <code object <listcomp> at 0x0000024069466330, file "dataclasses.py", line 1046>
1774: MAKE_FUNCTION        
1776: LOAD_FAST            field_list
1778: GET_ITER             
1780: PRECALL              
1784: CALL                 
1794: STORE_FAST           flds
1796: LOAD_GLOBAL          NULL + _set_new_attribute
1808: LOAD_FAST            cls
1810: LOAD_CONST           '__repr__'
1812: LOAD_GLOBAL          NULL + _repr_fn
1824: LOAD_FAST            flds
1826: LOAD_FAST            globals
1828: PRECALL              
1832: CALL                 
1842: PRECALL              
1846: CALL                 
1856: POP_TOP              
1858: LOAD_FAST            eq
1860: POP_JUMP_FORWARD_IF_FALSE to 2020
1862: LOAD_CONST           <code object <listcomp> at 0x0000024069467E50, file "dataclasses.py", line 1052>
1864: MAKE_FUNCTION        
1866: LOAD_FAST            field_list
1868: GET_ITER             
1870: PRECALL              
1874: CALL                 
1884: STORE_FAST           flds
1886: LOAD_GLOBAL          NULL + _tuple_str
1898: LOAD_CONST           'self'
1900: LOAD_FAST            flds
1902: PRECALL              
1906: CALL                 
1916: STORE_FAST           self_tuple
1918: LOAD_GLOBAL          NULL + _tuple_str
1930: LOAD_CONST           'other'
1932: LOAD_FAST            flds
1934: PRECALL              
1938: CALL                 
1948: STORE_FAST           other_tuple
1950: LOAD_GLOBAL          NULL + _set_new_attribute
1962: LOAD_FAST            cls
1964: LOAD_CONST           '__eq__'
1966: LOAD_GLOBAL          NULL + _cmp_fn
1978: LOAD_CONST           '__eq__'
1980: LOAD_CONST           '=='
1982: LOAD_FAST            self_tuple
1984: LOAD_FAST            other_tuple
1986: LOAD_FAST            globals
1988: KW_NAMES             
1990: PRECALL              
1994: CALL                 
2004: PRECALL              
2008: CALL                 
2018: POP_TOP              
2020: LOAD_FAST            order
2022: POP_JUMP_FORWARD_IF_FALSE to 2252
2024: LOAD_CONST           <code object <listcomp> at 0x0000024069465610, file "dataclasses.py", line 1062>
2026: MAKE_FUNCTION        
2028: LOAD_FAST            field_list
2030: GET_ITER             
2032: PRECALL              
2036: CALL                 
2046: STORE_FAST           flds
2048: LOAD_GLOBAL          NULL + _tuple_str
2060: LOAD_CONST           'self'
2062: LOAD_FAST            flds
2064: PRECALL              
2068: CALL                 
2078: STORE_FAST           self_tuple
2080: LOAD_GLOBAL          NULL + _tuple_str
2092: LOAD_CONST           'other'
2094: LOAD_FAST            flds
2096: PRECALL              
2100: CALL                 
2110: STORE_FAST           other_tuple
2112: LOAD_CONST           (('__lt__', '<'), ('__le__', '<='), ('__gt__', '>'), ('__ge__', '>='))
2114: GET_ITER             
2116: FOR_ITER             to 2252
2118: UNPACK_SEQUENCE      
2122: STORE_FAST           name
2124: STORE_FAST           op
2126: LOAD_GLOBAL          NULL + _set_new_attribute
2138: LOAD_FAST            cls
2140: LOAD_FAST            name
2142: LOAD_GLOBAL          NULL + _cmp_fn
2154: LOAD_FAST            name
2156: LOAD_FAST            op
2158: LOAD_FAST            self_tuple
2160: LOAD_FAST            other_tuple
2162: LOAD_FAST            globals
2164: KW_NAMES             
2166: PRECALL              
2170: CALL                 
2180: PRECALL              
2184: CALL                 
2194: POP_JUMP_FORWARD_IF_FALSE to 2250
2196: LOAD_GLOBAL          NULL + TypeError
2208: LOAD_CONST           'Cannot overwrite attribute '
2210: LOAD_FAST            name
2212: FORMAT_VALUE         
2214: LOAD_CONST           ' in class '
2216: LOAD_FAST            cls
2218: LOAD_ATTR            __name__
2228: FORMAT_VALUE         
2230: LOAD_CONST           '. Consider using functools.total_ordering'
2232: BUILD_STRING         
2234: PRECALL              
2238: CALL                 
2248: RAISE_VARARGS        
2250: JUMP_BACKWARD        to 2116
2252: LOAD_FAST            frozen
2254: POP_JUMP_FORWARD_IF_FALSE to 2402
2256: LOAD_GLOBAL          NULL + _frozen_get_del_attr
2268: LOAD_FAST            cls
2270: LOAD_FAST            field_list
2272: LOAD_FAST            globals
2274: PRECALL              
2278: CALL                 
2288: GET_ITER             
2290: FOR_ITER             to 2402
2292: STORE_FAST           fn
2294: LOAD_GLOBAL          NULL + _set_new_attribute
2306: LOAD_FAST            cls
2308: LOAD_FAST            fn
2310: LOAD_ATTR            __name__
2320: LOAD_FAST            fn
2322: PRECALL              
2326: CALL                 
2336: POP_JUMP_FORWARD_IF_FALSE to 2400
2338: LOAD_GLOBAL          NULL + TypeError
2350: LOAD_CONST           'Cannot overwrite attribute '
2352: LOAD_FAST            fn
2354: LOAD_ATTR            __name__
2364: FORMAT_VALUE         
2366: LOAD_CONST           ' in class '
2368: LOAD_FAST            cls
2370: LOAD_ATTR            __name__
2380: FORMAT_VALUE         
2382: BUILD_STRING         
2384: PRECALL              
2388: CALL                 
2398: RAISE_VARARGS        
2400: JUMP_BACKWARD        to 2290
2402: LOAD_GLOBAL          _hash_action
2414: LOAD_GLOBAL          NULL + bool
2426: LOAD_FAST            unsafe_hash
2428: PRECALL              
2432: CALL                 
2442: LOAD_GLOBAL          NULL + bool
2454: LOAD_FAST            eq
2456: PRECALL              
2460: CALL                 
2470: LOAD_GLOBAL          NULL + bool
2482: LOAD_FAST            frozen
2484: PRECALL              
2488: CALL                 
2498: LOAD_FAST            has_explicit_hash
2500: BUILD_TUPLE          
2502: BINARY_SUBSCR        
2512: STORE_FAST           hash_action
2514: LOAD_FAST            hash_action
2516: POP_JUMP_FORWARD_IF_FALSE to 2554
2518: PUSH_NULL            
2520: LOAD_FAST            hash_action
2522: LOAD_FAST            cls
2524: LOAD_FAST            field_list
2526: LOAD_FAST            globals
2528: PRECALL              
2532: CALL                 
2542: LOAD_FAST            cls
2544: STORE_ATTR           __hash__
2554: LOAD_GLOBAL          NULL + getattr
2566: LOAD_FAST            cls
2568: LOAD_CONST           '__doc__'
2570: PRECALL              
2574: CALL                 
2584: POP_JUMP_FORWARD_IF_TRUE to 2776
2586: NOP                  
2588: LOAD_GLOBAL          NULL + str
2600: LOAD_GLOBAL          NULL + inspect
2612: LOAD_ATTR            signature
2622: LOAD_FAST            cls
2624: PRECALL              
2628: CALL                 
2638: PRECALL              
2642: CALL                 
2652: LOAD_METHOD          replace
2674: LOAD_CONST           ' -> None'
2676: LOAD_CONST           ''
2678: PRECALL              
2682: CALL                 
2692: STORE_FAST           text_sig
2694: JUMP_FORWARD         to 2746
2696: PUSH_EXC_INFO        
2698: LOAD_GLOBAL          TypeError
2710: LOAD_GLOBAL          ValueError
2722: BUILD_TUPLE          
2724: CHECK_EXC_MATCH      
2726: POP_JUMP_FORWARD_IF_FALSE to 2738
2728: POP_TOP              
2730: LOAD_CONST           ''
2732: STORE_FAST           text_sig
2734: POP_EXCEPT           
2736: JUMP_FORWARD         to 2746
2738: RERAISE              
2740: COPY                 
2742: POP_EXCEPT           
2744: RERAISE              
2746: LOAD_FAST            cls
2748: LOAD_ATTR            __name__
2758: LOAD_FAST            text_sig
2760: BINARY_OP            +
2764: LOAD_FAST            cls
2766: STORE_ATTR           __doc__
2776: LOAD_FAST            match_args
2778: POP_JUMP_FORWARD_IF_FALSE to 2860
2780: LOAD_GLOBAL          NULL + _set_new_attribute
2792: LOAD_FAST            cls
2794: LOAD_CONST           '__match_args__'
2796: LOAD_GLOBAL          NULL + tuple
2808: LOAD_CONST           <code object <genexpr> at 0x0000024069467BB0, file "dataclasses.py", line 1106>
2810: MAKE_FUNCTION        
2812: LOAD_FAST            std_init_fields
2814: GET_ITER             
2816: PRECALL              
2820: CALL                 
2830: PRECALL              
2834: CALL                 
2844: PRECALL              
2848: CALL                 
2858: POP_TOP              
2860: LOAD_FAST            weakref_slot
2862: POP_JUMP_FORWARD_IF_FALSE to 2898
2864: LOAD_FAST            slots
2866: POP_JUMP_FORWARD_IF_TRUE to 2898
2868: LOAD_GLOBAL          NULL + TypeError
2880: LOAD_CONST           'weakref_slot is True but slots is False'
2882: PRECALL              
2886: CALL                 
2896: RAISE_VARARGS        
2898: LOAD_FAST            slots
2900: POP_JUMP_FORWARD_IF_FALSE to 2936
2902: LOAD_GLOBAL          NULL + _add_slots
2914: LOAD_FAST            cls
2916: LOAD_FAST            frozen
2918: LOAD_FAST            weakref_slot
2920: PRECALL              
2924: CALL                 
2934: STORE_FAST           cls
2936: LOAD_GLOBAL          NULL + abc
2948: LOAD_ATTR            update_abstractmethods
2958: LOAD_FAST            cls
2960: PRECALL              
2964: CALL                 
2974: POP_TOP              
2976: LOAD_FAST            cls
2978: RETURN_VALUE         
