# Disassembly for dataclasses._is_dataclass_instance
# From module file: dataclasses

## co_consts:
('Returns True if obj is an instance of a dataclass.',)

## co_names:
('hasattr', 'type', '_FIELDS')

## bytecode:

   0: RESUME               
   2: LOAD_GLOBAL          NULL + hasattr
  14: LOAD_GLOBAL          NULL + type
  26: LOAD_FAST            obj
  28: PRECALL              
  32: CALL                 
  42: LOAD_GLOBAL          _FIELDS
  54: PRECALL              
  58: CALL                 
  68: RETURN_VALUE         
