# Disassembly for dataclasses._add_slots
# From module file: dataclasses

## co_consts:
(None, '__slots__', ' already specifies __slots__', <code object <genexpr> at 0x0000024069466870, file "dataclasses.py", line 1157>, 1, -1, ('__weakref__',), (), '__dict__', '__weakref__', '__qualname__', '__getstate__', '__setstate__')

## co_names:
('__dict__', 'TypeError', '__name__', 'dict', 'tuple', 'fields', 'set', 'itertools', 'chain', 'from_iterable', 'map', '_get_slots', '__mro__', 'filterfalse', '__contains__', 'pop', 'getattr', 'type', '__bases__', '__qualname__', '_dataclass_getstate', '__getstate__', '_dataclass_setstate', '__setstate__')

## bytecode:

   0: RESUME               
   2: LOAD_CONST           '__slots__'
   4: LOAD_FAST            cls
   6: LOAD_ATTR            __dict__
  16: CONTAINS_OP          
  18: POP_JUMP_FORWARD_IF_FALSE to 66
  20: LOAD_GLOBAL          NULL + TypeError
  32: LOAD_FAST            cls
  34: LOAD_ATTR            __name__
  44: FORMAT_VALUE         
  46: LOAD_CONST           ' already specifies __slots__'
  48: BUILD_STRING         
  50: PRECALL              
  54: CALL                 
  64: RAISE_VARARGS        
  66: LOAD_GLOBAL          NULL + dict
  78: LOAD_FAST            cls
  80: LOAD_ATTR            __dict__
  90: PRECALL              
  94: CALL                 
 104: STORE_FAST           cls_dict
 106: LOAD_GLOBAL          NULL + tuple
 118: LOAD_CONST           <code object <genexpr> at 0x0000024069466870, file "dataclasses.py", line 1157>
 120: MAKE_FUNCTION        
 122: LOAD_GLOBAL          NULL + fields
 134: LOAD_FAST            cls
 136: PRECALL              
 140: CALL                 
 150: GET_ITER             
 152: PRECALL              
 156: CALL                 
 166: PRECALL              
 170: CALL                 
 180: STORE_FAST           field_names
 182: LOAD_GLOBAL          NULL + set
 194: LOAD_GLOBAL          itertools
 206: LOAD_ATTR            chain
 216: LOAD_METHOD          from_iterable
 238: LOAD_GLOBAL          NULL + map
 250: LOAD_GLOBAL          _get_slots
 262: LOAD_FAST            cls
 264: LOAD_ATTR            __mro__
 274: LOAD_CONST           1
 276: LOAD_CONST           -1
 278: BUILD_SLICE          
 280: BINARY_SUBSCR        
 290: PRECALL              
 294: CALL                 
 304: PRECALL              
 308: CALL                 
 318: PRECALL              
 322: CALL                 
 332: STORE_FAST           inherited_slots
 334: LOAD_GLOBAL          NULL + tuple
 346: LOAD_GLOBAL          NULL + itertools
 358: LOAD_ATTR            filterfalse
 368: LOAD_FAST            inherited_slots
 370: LOAD_ATTR            __contains__
 380: LOAD_GLOBAL          NULL + itertools
 392: LOAD_ATTR            chain
 402: LOAD_FAST            field_names
 404: LOAD_FAST            weakref_slot
 406: POP_JUMP_FORWARD_IF_FALSE to 412
 408: LOAD_CONST           ('__weakref__',)
 410: JUMP_FORWARD         to 414
 412: LOAD_CONST           ()
 414: PRECALL              
 418: CALL                 
 428: PRECALL              
 432: CALL                 
 442: PRECALL              
 446: CALL                 
 456: LOAD_FAST            cls_dict
 458: LOAD_CONST           '__slots__'
 460: STORE_SUBSCR         
 464: LOAD_FAST            field_names
 466: GET_ITER             
 468: FOR_ITER             to 518
 470: STORE_FAST           field_name
 472: LOAD_FAST            cls_dict
 474: LOAD_METHOD          pop
 496: LOAD_FAST            field_name
 498: LOAD_CONST           None
 500: PRECALL              
 504: CALL                 
 514: POP_TOP              
 516: JUMP_BACKWARD        to 468
 518: LOAD_FAST            cls_dict
 520: LOAD_METHOD          pop
 542: LOAD_CONST           '__dict__'
 544: LOAD_CONST           None
 546: PRECALL              
 550: CALL                 
 560: POP_TOP              
 562: LOAD_FAST            cls_dict
 564: LOAD_METHOD          pop
 586: LOAD_CONST           '__weakref__'
 588: LOAD_CONST           None
 590: PRECALL              
 594: CALL                 
 604: POP_TOP              
 606: LOAD_GLOBAL          NULL + getattr
 618: LOAD_FAST            cls
 620: LOAD_CONST           '__qualname__'
 622: LOAD_CONST           None
 624: PRECALL              
 628: CALL                 
 638: STORE_FAST           qualname
 640: PUSH_NULL            
 642: LOAD_GLOBAL          NULL + type
 654: LOAD_FAST            cls
 656: PRECALL              
 660: CALL                 
 670: LOAD_FAST            cls
 672: LOAD_ATTR            __name__
 682: LOAD_FAST            cls
 684: LOAD_ATTR            __bases__
 694: LOAD_FAST            cls_dict
 696: PRECALL              
 700: CALL                 
 710: STORE_FAST           cls
 712: LOAD_FAST            qualname
 714: POP_JUMP_FORWARD_IF_NONE to 730
 716: LOAD_FAST            qualname
 718: LOAD_FAST            cls
 720: STORE_ATTR           __qualname__
 730: LOAD_FAST            is_frozen
 732: POP_JUMP_FORWARD_IF_FALSE to 798
 734: LOAD_CONST           '__getstate__'
 736: LOAD_FAST            cls_dict
 738: CONTAINS_OP          
 740: POP_JUMP_FORWARD_IF_FALSE to 766
 742: LOAD_GLOBAL          _dataclass_getstate
 754: LOAD_FAST            cls
 756: STORE_ATTR           __getstate__
 766: LOAD_CONST           '__setstate__'
 768: LOAD_FAST            cls_dict
 770: CONTAINS_OP          
 772: POP_JUMP_FORWARD_IF_FALSE to 798
 774: LOAD_GLOBAL          _dataclass_setstate
 786: LOAD_FAST            cls
 788: STORE_ATTR           __setstate__
 798: LOAD_FAST            cls
 800: RETURN_VALUE         
