# Disassembly for dataclasses._set_qualname
# From module file: dataclasses

## co_consts:
(None, '.')

## co_names:
('isinstance', 'FunctionType', '__qualname__', '__name__')

## bytecode:

   0: RESUME               
   2: LOAD_GLOBAL          NULL + isinstance
  14: LOAD_FAST            value
  16: LOAD_GLOBAL          FunctionType
  28: PRECALL              
  32: CALL                 
  42: POP_JUMP_FORWARD_IF_FALSE to 88
  44: LOAD_FAST            cls
  46: LOAD_ATTR            __qualname__
  56: FORMAT_VALUE         
  58: LOAD_CONST           '.'
  60: LOAD_FAST            value
  62: LOAD_ATTR            __name__
  72: FORMAT_VALUE         
  74: BUILD_STRING         
  76: LOAD_FAST            value
  78: STORE_ATTR           __qualname__
  88: LOAD_FAST            value
  90: RETURN_VALUE         
