# Disassembly for dataclasses.asdict
# From module file: dataclasses

## co_consts:
("Return the fields of a dataclass instance as a new dictionary mapping\n    field names to field values.\n\n    Example usage::\n\n      @dataclass\n      class C:\n          x: int\n          y: int\n\n      c = C(1, 2)\n      assert asdict(c) == {'x': 1, 'y': 2}\n\n    If given, 'dict_factory' will be used instead of built-in dict.\n    The function applies recursively to field values that are\n    dataclass instances. This will also look into built-in containers:\n    tuples, lists, and dicts.\n    ", 'asdict() should be called on dataclass instances')

## co_names:
('_is_dataclass_instance', 'TypeError', '_asdict_inner')

## bytecode:

   0: RESUME               
   2: LOAD_GLOBAL          NULL + _is_dataclass_instance
  14: LOAD_FAST            obj
  16: PRECALL              
  20: CALL                 
  30: POP_JUMP_FORWARD_IF_TRUE to 62
  32: LOAD_GLOBAL          NULL + TypeError
  44: LOAD_CONST           'asdict() should be called on dataclass instances'
  46: PRECALL              
  50: CALL                 
  60: RAISE_VARARGS        
  62: LOAD_GLOBAL          NULL + _asdict_inner
  74: LOAD_FAST            obj
  76: LOAD_FAST            dict_factory
  78: PRECALL              
  82: CALL                 
  92: RETURN_VALUE         
