# Disassembly for dataclasses._frozen_get_del_attr
# From module file: dataclasses

## co_consts:
(None, ('cls', 'FrozenInstanceError'), '(', ',', <code object <genexpr> at 0x00000240693EA830, file "dataclasses.py", line 603>, ',)', '()', '__setattr__', ('self', 'name', 'value'), 'if type(self) is cls or name in ', ':', ' raise FrozenInstanceError(f"cannot assign to field {name!r}")', 'super(cls, self).__setattr__(name, value)', ('locals', 'globals'), '__delattr__', ('self', 'name'), ' raise FrozenInstanceError(f"cannot delete field {name!r}")', 'super(cls, self).__delattr__(name)')

## co_names:
('FrozenInstanceError', 'join', '_create_fn')

## bytecode:

   0: RESUME               
   2: LOAD_FAST            cls
   4: LOAD_GLOBAL          FrozenInstanceError
  16: LOAD_CONST           ('cls', 'FrozenInstanceError')
  18: BUILD_CONST_KEY_MAP  
  20: STORE_FAST           locals
  22: LOAD_FAST            fields
  24: POP_JUMP_FORWARD_IF_FALSE to 102
  26: LOAD_CONST           '('
  28: LOAD_CONST           ','
  30: LOAD_METHOD          join
  52: LOAD_CONST           <code object <genexpr> at 0x00000240693EA830, file "dataclasses.py", line 603>
  54: MAKE_FUNCTION        
  56: LOAD_FAST            fields
  58: GET_ITER             
  60: PRECALL              
  64: CALL                 
  74: PRECALL              
  78: CALL                 
  88: BINARY_OP            +
  92: LOAD_CONST           ',)'
  94: BINARY_OP            +
  98: STORE_FAST           fields_str
 100: JUMP_FORWARD         to 106
 102: LOAD_CONST           '()'
 104: STORE_FAST           fields_str
 106: LOAD_GLOBAL          NULL + _create_fn
 118: LOAD_CONST           '__setattr__'
 120: LOAD_CONST           ('self', 'name', 'value')
 122: LOAD_CONST           'if type(self) is cls or name in '
 124: LOAD_FAST            fields_str
 126: FORMAT_VALUE         
 128: LOAD_CONST           ':'
 130: BUILD_STRING         
 132: LOAD_CONST           ' raise FrozenInstanceError(f"cannot assign to field {name!r}")'
 134: LOAD_CONST           'super(cls, self).__setattr__(name, value)'
 136: BUILD_TUPLE          
 138: LOAD_FAST            locals
 140: LOAD_FAST            globals
 142: KW_NAMES             
 144: PRECALL              
 148: CALL                 
 158: LOAD_GLOBAL          NULL + _create_fn
 170: LOAD_CONST           '__delattr__'
 172: LOAD_CONST           ('self', 'name')
 174: LOAD_CONST           'if type(self) is cls or name in '
 176: LOAD_FAST            fields_str
 178: FORMAT_VALUE         
 180: LOAD_CONST           ':'
 182: BUILD_STRING         
 184: LOAD_CONST           ' raise FrozenInstanceError(f"cannot delete field {name!r}")'
 186: LOAD_CONST           'super(cls, self).__delattr__(name)'
 188: BUILD_TUPLE          
 190: LOAD_FAST            locals
 192: LOAD_FAST            globals
 194: KW_NAMES             
 196: PRECALL              
 200: CALL                 
 210: BUILD_TUPLE          
 212: RETURN_VALUE         
