# Disassembly for dataclasses._get_field
# From module file: dataclasses

## co_consts:
(None, ('default',), 'typing', 'field ', ' cannot have a default factory', ' is a ClassVar but specifies kw_only', 'mutable default ', ' for field ', ' is not allowed: use default_factory')

## co_names:
('getattr', 'MISSING', 'isinstance', 'Field', 'types', 'MemberDescriptorType', 'field', 'name', 'type', '_FIELD', '_field_type', 'sys', 'modules', 'get', '_is_classvar', 'str', '_is_type', 'ClassVar', '_FIELD_CLASSVAR', '__name__', '_is_initvar', 'InitVar', '_FIELD_INITVAR', 'default_factory', 'TypeError', 'kw_only', 'default', '__class__', '__hash__', 'ValueError')

## bytecode:

   0: RESUME               
   2: LOAD_GLOBAL          NULL + getattr
  14: LOAD_FAST            cls
  16: LOAD_FAST            a_name
  18: LOAD_GLOBAL          MISSING
  30: PRECALL              
  34: CALL                 
  44: STORE_FAST           default
  46: LOAD_GLOBAL          NULL + isinstance
  58: LOAD_FAST            default
  60: LOAD_GLOBAL          Field
  72: PRECALL              
  76: CALL                 
  86: POP_JUMP_FORWARD_IF_FALSE to 94
  88: LOAD_FAST            default
  90: STORE_FAST           f
  92: JUMP_FORWARD         to 192
  94: LOAD_GLOBAL          NULL + isinstance
 106: LOAD_FAST            default
 108: LOAD_GLOBAL          types
 120: LOAD_ATTR            MemberDescriptorType
 130: PRECALL              
 134: CALL                 
 144: POP_JUMP_FORWARD_IF_FALSE to 160
 146: LOAD_GLOBAL          MISSING
 158: STORE_FAST           default
 160: LOAD_GLOBAL          NULL + field
 172: LOAD_FAST            default
 174: KW_NAMES             
 176: PRECALL              
 180: CALL                 
 190: STORE_FAST           f
 192: LOAD_FAST            a_name
 194: LOAD_FAST            f
 196: STORE_ATTR           name
 206: LOAD_FAST            a_type
 208: LOAD_FAST            f
 210: STORE_ATTR           type
 220: LOAD_GLOBAL          _FIELD
 232: LOAD_FAST            f
 234: STORE_ATTR           _field_type
 244: LOAD_GLOBAL          sys
 256: LOAD_ATTR            modules
 266: LOAD_METHOD          get
 288: LOAD_CONST           'typing'
 290: PRECALL              
 294: CALL                 
 304: STORE_FAST           typing
 306: LOAD_FAST            typing
 308: POP_JUMP_FORWARD_IF_FALSE to 486
 310: LOAD_GLOBAL          NULL + _is_classvar
 322: LOAD_FAST            a_type
 324: LOAD_FAST            typing
 326: PRECALL              
 330: CALL                 
 340: POP_JUMP_FORWARD_IF_TRUE to 462
 342: LOAD_GLOBAL          NULL + isinstance
 354: LOAD_FAST            f
 356: LOAD_ATTR            type
 366: LOAD_GLOBAL          str
 378: PRECALL              
 382: CALL                 
 392: POP_JUMP_FORWARD_IF_FALSE to 486
 394: LOAD_GLOBAL          NULL + _is_type
 406: LOAD_FAST            f
 408: LOAD_ATTR            type
 418: LOAD_FAST            cls
 420: LOAD_FAST            typing
 422: LOAD_FAST            typing
 424: LOAD_ATTR            ClassVar
 434: LOAD_GLOBAL          _is_classvar
 446: PRECALL              
 450: CALL                 
 460: POP_JUMP_FORWARD_IF_FALSE to 486
 462: LOAD_GLOBAL          _FIELD_CLASSVAR
 474: LOAD_FAST            f
 476: STORE_ATTR           _field_type
 486: LOAD_FAST            f
 488: LOAD_ATTR            _field_type
 498: LOAD_GLOBAL          _FIELD
 510: IS_OP                
 512: POP_JUMP_FORWARD_IF_FALSE to 736
 514: LOAD_GLOBAL          sys
 526: LOAD_ATTR            modules
 536: LOAD_GLOBAL          __name__
 548: BINARY_SUBSCR        
 558: STORE_FAST           dataclasses
 560: LOAD_GLOBAL          NULL + _is_initvar
 572: LOAD_FAST            a_type
 574: LOAD_FAST            dataclasses
 576: PRECALL              
 580: CALL                 
 590: POP_JUMP_FORWARD_IF_TRUE to 712
 592: LOAD_GLOBAL          NULL + isinstance
 604: LOAD_FAST            f
 606: LOAD_ATTR            type
 616: LOAD_GLOBAL          str
 628: PRECALL              
 632: CALL                 
 642: POP_JUMP_FORWARD_IF_FALSE to 736
 644: LOAD_GLOBAL          NULL + _is_type
 656: LOAD_FAST            f
 658: LOAD_ATTR            type
 668: LOAD_FAST            cls
 670: LOAD_FAST            dataclasses
 672: LOAD_FAST            dataclasses
 674: LOAD_ATTR            InitVar
 684: LOAD_GLOBAL          _is_initvar
 696: PRECALL              
 700: CALL                 
 710: POP_JUMP_FORWARD_IF_FALSE to 736
 712: LOAD_GLOBAL          _FIELD_INITVAR
 724: LOAD_FAST            f
 726: STORE_ATTR           _field_type
 736: LOAD_FAST            f
 738: LOAD_ATTR            _field_type
 748: LOAD_GLOBAL          _FIELD_CLASSVAR
 760: LOAD_GLOBAL          _FIELD_INITVAR
 772: BUILD_TUPLE          
 774: CONTAINS_OP          
 776: POP_JUMP_FORWARD_IF_FALSE to 854
 778: LOAD_FAST            f
 780: LOAD_ATTR            default_factory
 790: LOAD_GLOBAL          MISSING
 802: IS_OP                
 804: POP_JUMP_FORWARD_IF_FALSE to 854
 806: LOAD_GLOBAL          NULL + TypeError
 818: LOAD_CONST           'field '
 820: LOAD_FAST            f
 822: LOAD_ATTR            name
 832: FORMAT_VALUE         
 834: LOAD_CONST           ' cannot have a default factory'
 836: BUILD_STRING         
 838: PRECALL              
 842: CALL                 
 852: RAISE_VARARGS        
 854: LOAD_FAST            f
 856: LOAD_ATTR            _field_type
 866: LOAD_GLOBAL          _FIELD
 878: LOAD_GLOBAL          _FIELD_INITVAR
 890: BUILD_TUPLE          
 892: CONTAINS_OP          
 894: POP_JUMP_FORWARD_IF_FALSE to 940
 896: LOAD_FAST            f
 898: LOAD_ATTR            kw_only
 908: LOAD_GLOBAL          MISSING
 920: IS_OP                
 922: POP_JUMP_FORWARD_IF_FALSE to 938
 924: LOAD_FAST            default_kw_only
 926: LOAD_FAST            f
 928: STORE_ATTR           kw_only
 938: JUMP_FORWARD         to 1048
 940: LOAD_FAST            f
 942: LOAD_ATTR            _field_type
 952: LOAD_GLOBAL          _FIELD_CLASSVAR
 964: IS_OP                
 966: POP_JUMP_FORWARD_IF_TRUE to 972
 968: LOAD_ASSERTION_ERROR 
 970: RAISE_VARARGS        
 972: LOAD_FAST            f
 974: LOAD_ATTR            kw_only
 984: LOAD_GLOBAL          MISSING
 996: IS_OP                
 998: POP_JUMP_FORWARD_IF_FALSE to 1048
1000: LOAD_GLOBAL          NULL + TypeError
1012: LOAD_CONST           'field '
1014: LOAD_FAST            f
1016: LOAD_ATTR            name
1026: FORMAT_VALUE         
1028: LOAD_CONST           ' is a ClassVar but specifies kw_only'
1030: BUILD_STRING         
1032: PRECALL              
1036: CALL                 
1046: RAISE_VARARGS        
1048: LOAD_FAST            f
1050: LOAD_ATTR            _field_type
1060: LOAD_GLOBAL          _FIELD
1072: IS_OP                
1074: POP_JUMP_FORWARD_IF_FALSE to 1200
1076: LOAD_FAST            f
1078: LOAD_ATTR            default
1088: LOAD_ATTR            __class__
1098: LOAD_ATTR            __hash__
1108: POP_JUMP_FORWARD_IF_NOT_NONE to 1200
1110: LOAD_GLOBAL          NULL + ValueError
1122: LOAD_CONST           'mutable default '
1124: LOAD_GLOBAL          NULL + type
1136: LOAD_FAST            f
1138: LOAD_ATTR            default
1148: PRECALL              
1152: CALL                 
1162: FORMAT_VALUE         
1164: LOAD_CONST           ' for field '
1166: LOAD_FAST            f
1168: LOAD_ATTR            name
1178: FORMAT_VALUE         
1180: LOAD_CONST           ' is not allowed: use default_factory'
1182: BUILD_STRING         
1184: PRECALL              
1188: CALL                 
1198: RAISE_VARARGS        
1200: LOAD_FAST            f
1202: RETURN_VALUE         
