# Disassembly for dataclasses._DataclassParams.__init__
# From module file: dataclasses

## co_consts:
(None,)

## co_names:
('init', 'repr', 'eq', 'order', 'unsafe_hash', 'frozen')

## bytecode:

   0: RESUME               
   2: LOAD_FAST            init
   4: LOAD_FAST            self
   6: STORE_ATTR           init
  16: LOAD_FAST            repr
  18: LOAD_FAST            self
  20: STORE_ATTR           repr
  30: LOAD_FAST            eq
  32: LOAD_FAST            self
  34: STORE_ATTR           eq
  44: LOAD_FAST            order
  46: LOAD_FAST            self
  48: STORE_ATTR           order
  58: LOAD_FAST            unsafe_hash
  60: LOAD_FAST            self
  62: STORE_ATTR           unsafe_hash
  72: LOAD_FAST            frozen
  74: LOAD_FAST            self
  76: STORE_ATTR           frozen
  86: LOAD_CONST           None
  88: RETURN_VALUE         
