# Disassembly for dataclasses._get_slots
# From module file: dataclasses

## co_consts:
(None, '__slots__', (), '__next__', "Slots of '", "' cannot be determined")

## co_names:
('__dict__', 'get', 'str', 'hasattr', 'TypeError', '__name__')

## bytecode:

   0: RETURN_GENERATOR     
   2: POP_TOP              
   4: RESUME               
   6: LOAD_FAST            cls
   8: LOAD_ATTR            __dict__
  18: LOAD_METHOD          get
  40: LOAD_CONST           '__slots__'
  42: PRECALL              
  46: CALL                 
  56: COPY                 
  58: POP_JUMP_FORWARD_IF_NOT_NONE to 66
  60: POP_TOP              
  62: LOAD_CONST           None
  64: RETURN_VALUE         
  66: COPY                 
  68: LOAD_GLOBAL          str
  80: LOAD_CONST           ()
  82: MATCH_CLASS          
  84: COPY                 
  86: POP_JUMP_FORWARD_IF_NONE to 108
  88: UNPACK_SEQUENCE      
  92: STORE_FAST           slot
  94: POP_TOP              
  96: LOAD_FAST            slot
  98: YIELD_VALUE          
 100: RESUME               
 102: POP_TOP              
 104: LOAD_CONST           None
 106: RETURN_VALUE         
 108: POP_TOP              
 110: STORE_FAST           iterable
 112: LOAD_GLOBAL          NULL + hasattr
 124: LOAD_FAST            iterable
 126: LOAD_CONST           '__next__'
 128: PRECALL              
 132: CALL                 
 142: POP_JUMP_FORWARD_IF_TRUE to 164
 144: LOAD_FAST            iterable
 146: GET_YIELD_FROM_ITER  
 148: LOAD_CONST           None
 150: SEND                 to 158
 152: YIELD_VALUE          
 154: RESUME               
 156: JUMP_BACKWARD_NO_INTERRUPT to 150
 158: POP_TOP              
 160: LOAD_CONST           None
 162: RETURN_VALUE         
 164: NOP                  
 166: LOAD_GLOBAL          NULL + TypeError
 178: LOAD_CONST           "Slots of '"
 180: LOAD_FAST            cls
 182: LOAD_ATTR            __name__
 192: FORMAT_VALUE         
 194: LOAD_CONST           "' cannot be determined"
 196: BUILD_STRING         
 198: PRECALL              
 202: CALL                 
 212: RAISE_VARARGS        
