# Disassembly for dataclasses._set_new_attribute
# From module file: dataclasses

## co_consts:
(None, True, False)

## co_names:
('__dict__', '_set_qualname', 'setattr')

## bytecode:

   0: RESUME               
   2: LOAD_FAST            name
   4: LOAD_FAST            cls
   6: LOAD_ATTR            __dict__
  16: CONTAINS_OP          
  18: POP_JUMP_FORWARD_IF_FALSE to 24
  20: LOAD_CONST           True
  22: RETURN_VALUE         
  24: LOAD_GLOBAL          NULL + _set_qualname
  36: LOAD_FAST            cls
  38: LOAD_FAST            value
  40: PRECALL              
  44: CALL                 
  54: POP_TOP              
  56: LOAD_GLOBAL          NULL + setattr
  68: LOAD_FAST            cls
  70: LOAD_FAST            name
  72: LOAD_FAST            value
  74: PRECALL              
  78: CALL                 
  88: POP_TOP              
  90: LOAD_CONST           False
  92: RETURN_VALUE         
