# Disassembly for dataclasses._frozen_get_del_attr.<genexpr>
# From module file: dataclasses

## co_consts:
(None,)

## co_names:
('repr', 'name')

## bytecode:

   0: RETURN_GENERATOR     
   2: POP_TOP              
   4: RESUME               
   6: LOAD_FAST            .0
   8: FOR_ITER             to 58
  10: STORE_FAST           f
  12: LOAD_GLOBAL          NULL + repr
  24: LOAD_FAST            f
  26: LOAD_ATTR            name
  36: PRECALL              
  40: CALL                 
  50: YIELD_VALUE          
  52: RESUME               
  54: POP_TOP              
  56: JUMP_BACKWARD        to 8
  58: LOAD_CONST           None
  60: RETURN_VALUE         
