# Disassembly for dataclasses._dataclass_getstate.<listcomp>
# From module file: dataclasses

## co_consts:
()

## co_names:
('getattr', 'name')

## bytecode:

   0: COPY_FREE_VARS       
   2: RESUME               
   4: BUILD_LIST           
   6: LOAD_FAST            .0
   8: FOR_ITER             to 56
  10: STORE_FAST           f
  12: LOAD_GLOBAL          NULL + getattr
  24: LOAD_DEREF           self
  26: LOAD_FAST            f
  28: LOAD_ATTR            name
  38: PRECALL              
  42: CALL                 
  52: LIST_APPEND          
  54: JUMP_BACKWARD        to 8
  56: RETURN_VALUE         
