# Disassembly for dataclasses._tuple_str
# From module file: dataclasses

## co_consts:
(None, '()', '(', ',', <code object <listcomp> at 0x0000024069467910, file "dataclasses.py", line 410>, ',)')

## co_names:
('join',)

## bytecode:

   0: MAKE_CELL            obj_name
   2: RESUME               
   4: LOAD_FAST            fields
   6: POP_JUMP_FORWARD_IF_TRUE to 12
   8: LOAD_CONST           '()'
  10: RETURN_VALUE         
  12: LOAD_CONST           '('
  14: LOAD_CONST           ','
  16: LOAD_METHOD          join
  38: LOAD_CLOSURE         obj_name
  40: BUILD_TUPLE          
  42: LOAD_CONST           <code object <listcomp> at 0x0000024069467910, file "dataclasses.py", line 410>
  44: MAKE_FUNCTION        closure
  46: LOAD_FAST            fields
  48: GET_ITER             
  50: PRECALL              
  54: CALL                 
  64: PRECALL              
  68: CALL                 
  78: FORMAT_VALUE         
  80: LOAD_CONST           ',)'
  82: BUILD_STRING         
  84: RETURN_VALUE         
