# Disassembly for dataclasses.make_dataclass.exec_body_callback
# From module file: dataclasses

## co_consts:
(None, '__annotations__')

## co_names:
('update',)

## bytecode:

   0: COPY_FREE_VARS       
   2: RESUME               
   4: LOAD_FAST            ns
   6: LOAD_METHOD          update
  28: LOAD_DEREF           namespace
  30: PRECALL              
  34: CALL                 
  44: POP_TOP              
  46: LOAD_FAST            ns
  48: LOAD_METHOD          update
  70: LOAD_DEREF           defaults
  72: PRECALL              
  76: CALL                 
  86: POP_TOP              
  88: LOAD_DEREF           annotations
  90: LOAD_FAST            ns
  92: LOAD_CONST           '__annotations__'
  94: STORE_SUBSCR         
  98: LOAD_CONST           None
 100: RETURN_VALUE         
