# Disassembly for numbers.Rational.__float__
# From module file: numbers

## co_consts:
('float(self) = self.numerator / self.denominator\n\n        It\'s important that this conversion use the integer\'s "true"\n        division rather than casting one side to float before dividing\n        so that ratios of huge integers convert without overflowing.\n\n        ',)

## co_names:
('int', 'numerator', 'denominator')

## bytecode:

   0: RESUME               
   2: LOAD_GLOBAL          NULL + int
  14: LOAD_FAST            self
  16: LOAD_ATTR            numerator
  26: PRECALL              
  30: CALL                 
  40: LOAD_GLOBAL          NULL + int
  52: LOAD_FAST            self
  54: LOAD_ATTR            denominator
  64: PRECALL              
  68: CALL                 
  78: BINARY_OP            /
  82: RETURN_VALUE         
