# Disassembly for numbers.Number
# From module file: numbers

## co_consts:
('Number', 'All numbers inherit from this class.\n\n    If you just want to check if an argument x is a number, without\n    caring what kind, use isinstance(x, Number).\n    ', (), None)

## co_names:
('__name__', '__module__', '__qualname__', '__doc__', '__slots__', '__hash__')

## bytecode:

   0: RESUME               
   2: LOAD_NAME            __name__
   4: STORE_NAME           __module__
   6: LOAD_CONST           'Number'
   8: STORE_NAME           __qualname__
  10: LOAD_CONST           'All numbers inherit from this class.\n\n    If you just want to check if an argument x is a number, without\n    caring what kind, use isinstance(x, Number).\n    '
  12: STORE_NAME           __doc__
  14: LOAD_CONST           ()
  16: STORE_NAME           __slots__
  18: LOAD_CONST           None
  20: STORE_NAME           __hash__
  22: LOAD_CONST           None
  24: RETURN_VALUE         
