# Disassembly for numbers.Real.__rdivmod__
# From module file: numbers

## co_consts:
('divmod(other, self): The pair (self // other, self % other).\n\n        Sometimes this can be computed faster than the pair of\n        operations.\n        ',)

## co_names:
()

## bytecode:

   0: RESUME               
   2: LOAD_FAST            other
   4: LOAD_FAST            self
   6: BINARY_OP            //
  10: LOAD_FAST            other
  12: LOAD_FAST            self
  14: BINARY_OP            %
  18: BUILD_TUPLE          
  20: RETURN_VALUE         
