# Disassembly for getopt.do_shorts
# From module file: getopt

## co_consts:
(None, '', 0, 1, 'option -%s requires argument', '-')

## co_names:
('short_has_arg', 'GetoptError', '_', 'append')

## bytecode:

   0: RESUME               
   2: LOAD_FAST            optstring
   4: LOAD_CONST           ''
   6: COMPARE_OP           !=
  12: POP_JUMP_FORWARD_IF_FALSE to 276
  14: LOAD_FAST            optstring
  16: LOAD_CONST           0
  18: BINARY_SUBSCR        
  28: LOAD_FAST            optstring
  30: LOAD_CONST           1
  32: LOAD_CONST           None
  34: BUILD_SLICE          
  36: BINARY_SUBSCR        
  46: STORE_FAST           optstring
  48: STORE_FAST           opt
  50: LOAD_GLOBAL          NULL + short_has_arg
  62: LOAD_FAST            opt
  64: LOAD_FAST            shortopts
  66: PRECALL              
  70: CALL                 
  80: POP_JUMP_FORWARD_IF_FALSE to 208
  82: LOAD_FAST            optstring
  84: LOAD_CONST           ''
  86: COMPARE_OP           ==
  92: POP_JUMP_FORWARD_IF_FALSE to 198
  94: LOAD_FAST            args
  96: POP_JUMP_FORWARD_IF_TRUE to 162
  98: LOAD_GLOBAL          NULL + GetoptError
 110: LOAD_GLOBAL          NULL + _
 122: LOAD_CONST           'option -%s requires argument'
 124: PRECALL              
 128: CALL                 
 138: LOAD_FAST            opt
 140: BINARY_OP            %
 144: LOAD_FAST            opt
 146: PRECALL              
 150: CALL                 
 160: RAISE_VARARGS        
 162: LOAD_FAST            args
 164: LOAD_CONST           0
 166: BINARY_SUBSCR        
 176: LOAD_FAST            args
 178: LOAD_CONST           1
 180: LOAD_CONST           None
 182: BUILD_SLICE          
 184: BINARY_SUBSCR        
 194: STORE_FAST           args
 196: STORE_FAST           optstring
 198: LOAD_FAST            optstring
 200: LOAD_CONST           ''
 202: STORE_FAST           optstring
 204: STORE_FAST           optarg
 206: JUMP_FORWARD         to 212
 208: LOAD_CONST           ''
 210: STORE_FAST           optarg
 212: LOAD_FAST            opts
 214: LOAD_METHOD          append
 236: LOAD_CONST           '-'
 238: LOAD_FAST            opt
 240: BINARY_OP            +
 244: LOAD_FAST            optarg
 246: BUILD_TUPLE          
 248: PRECALL              
 252: CALL                 
 262: POP_TOP              
 264: LOAD_FAST            optstring
 266: LOAD_CONST           ''
 268: COMPARE_OP           !=
 274: POP_JUMP_BACKWARD_IF_TRUE to 14
 276: LOAD_FAST            opts
 278: LOAD_FAST            args
 280: BUILD_TUPLE          
 282: RETURN_VALUE         
