# Disassembly for getopt.long_has_args.<listcomp>
# From module file: getopt

## co_consts:
()

## co_names:
('startswith',)

## bytecode:

   0: COPY_FREE_VARS       
   2: RESUME               
   4: BUILD_LIST           
   6: LOAD_FAST            .0
   8: FOR_ITER             to 60
  10: STORE_FAST           o
  12: LOAD_FAST            o
  14: LOAD_METHOD          startswith
  36: LOAD_DEREF           opt
  38: PRECALL              
  42: CALL                 
  52: POP_JUMP_BACKWARD_IF_FALSE to 8
  54: LOAD_FAST            o
  56: LIST_APPEND          
  58: JUMP_BACKWARD        to 8
  60: RETURN_VALUE         
