# Disassembly for getopt.short_has_arg
# From module file: getopt

## co_consts:
(None, ':', 1, 'option -%s not recognized')

## co_names:
('range', 'len', 'startswith', 'GetoptError', '_')

## bytecode:

   0: RESUME               
   2: LOAD_GLOBAL          NULL + range
  14: LOAD_GLOBAL          NULL + len
  26: LOAD_FAST            shortopts
  28: PRECALL              
  32: CALL                 
  42: PRECALL              
  46: CALL                 
  56: GET_ITER             
  58: FOR_ITER             to 162
  60: STORE_FAST           i
  62: LOAD_FAST            opt
  64: LOAD_FAST            shortopts
  66: LOAD_FAST            i
  68: BINARY_SUBSCR        
  78: SWAP                 
  80: COPY                 
  82: COMPARE_OP           ==
  88: POP_JUMP_FORWARD_IF_FALSE to 102
  90: LOAD_CONST           ':'
  92: COMPARE_OP           !=
  98: POP_JUMP_FORWARD_IF_FALSE to 160
 100: JUMP_FORWARD         to 106
 102: POP_TOP              
 104: JUMP_BACKWARD        to 58
 106: LOAD_FAST            shortopts
 108: LOAD_METHOD          startswith
 130: LOAD_CONST           ':'
 132: LOAD_FAST            i
 134: LOAD_CONST           1
 136: BINARY_OP            +
 140: PRECALL              
 144: CALL                 
 154: SWAP                 
 156: POP_TOP              
 158: RETURN_VALUE         
 160: JUMP_BACKWARD        to 58
 162: LOAD_GLOBAL          NULL + GetoptError
 174: LOAD_GLOBAL          NULL + _
 186: LOAD_CONST           'option -%s not recognized'
 188: PRECALL              
 192: CALL                 
 202: LOAD_FAST            opt
 204: BINARY_OP            %
 208: LOAD_FAST            opt
 210: PRECALL              
 214: CALL                 
 224: RAISE_VARARGS        
