# Disassembly for getopt.getopt
# From module file: getopt

## co_consts:
('getopt(args, options[, long_options]) -> opts, args\n\n    Parses command line options and parameter list.  args is the\n    argument list to be parsed, without the leading reference to the\n    running program.  Typically, this means "sys.argv[1:]".  shortopts\n    is the string of option letters that the script wants to\n    recognize, with options that require an argument followed by a\n    colon (i.e., the same format that Unix getopt() uses).  If\n    specified, longopts is a list of strings with the names of the\n    long options which should be supported.  The leading \'--\'\n    characters should not be included in the option name.  Options\n    which require an argument should be followed by an equal sign\n    (\'=\').\n\n    The return value consists of two elements: the first is a list of\n    (option, value) pairs; the second is the list of program arguments\n    left after the option list was stripped (this is a trailing slice\n    of the first argument).  Each option-and-value pair returned has\n    the option as its first element, prefixed with a hyphen (e.g.,\n    \'-x\'), and the option argument as its second element, or an empty\n    string if the option has no argument.  The options occur in the\n    list in the same order in which they were found, thus allowing\n    multiple occurrences.  Long and short options may be mixed.\n\n    ', '', 0, '-', '--', 1, None, 2)

## co_names:
('type', 'list', 'startswith', 'do_longs', 'do_shorts')

## bytecode:

   0: RESUME               
   2: BUILD_LIST           
   4: STORE_FAST           opts
   6: LOAD_GLOBAL          NULL + type
  18: LOAD_FAST            longopts
  20: PRECALL              
  24: CALL                 
  34: LOAD_GLOBAL          NULL + type
  46: LOAD_CONST           ''
  48: PRECALL              
  52: CALL                 
  62: COMPARE_OP           ==
  68: POP_JUMP_FORWARD_IF_FALSE to 78
  70: LOAD_FAST            longopts
  72: BUILD_LIST           
  74: STORE_FAST           longopts
  76: JUMP_FORWARD         to 108
  78: LOAD_GLOBAL          NULL + list
  90: LOAD_FAST            longopts
  92: PRECALL              
  96: CALL                 
 106: STORE_FAST           longopts
 108: LOAD_FAST            args
 110: POP_JUMP_FORWARD_IF_FALSE to 546
 112: LOAD_FAST            args
 114: LOAD_CONST           0
 116: BINARY_SUBSCR        
 126: LOAD_METHOD          startswith
 148: LOAD_CONST           '-'
 150: PRECALL              
 154: CALL                 
 164: POP_JUMP_FORWARD_IF_FALSE to 546
 166: LOAD_FAST            args
 168: LOAD_CONST           0
 170: BINARY_SUBSCR        
 180: LOAD_CONST           '-'
 182: COMPARE_OP           !=
 188: POP_JUMP_FORWARD_IF_FALSE to 546
 190: LOAD_FAST            args
 192: LOAD_CONST           0
 194: BINARY_SUBSCR        
 204: LOAD_CONST           '--'
 206: COMPARE_OP           ==
 212: POP_JUMP_FORWARD_IF_FALSE to 236
 214: LOAD_FAST            args
 216: LOAD_CONST           1
 218: LOAD_CONST           None
 220: BUILD_SLICE          
 222: BINARY_SUBSCR        
 232: STORE_FAST           args
 234: JUMP_FORWARD         to 546
 236: LOAD_FAST            args
 238: LOAD_CONST           0
 240: BINARY_SUBSCR        
 250: LOAD_METHOD          startswith
 272: LOAD_CONST           '--'
 274: PRECALL              
 278: CALL                 
 288: POP_JUMP_FORWARD_IF_FALSE to 378
 290: LOAD_GLOBAL          NULL + do_longs
 302: LOAD_FAST            opts
 304: LOAD_FAST            args
 306: LOAD_CONST           0
 308: BINARY_SUBSCR        
 318: LOAD_CONST           2
 320: LOAD_CONST           None
 322: BUILD_SLICE          
 324: BINARY_SUBSCR        
 334: LOAD_FAST            longopts
 336: LOAD_FAST            args
 338: LOAD_CONST           1
 340: LOAD_CONST           None
 342: BUILD_SLICE          
 344: BINARY_SUBSCR        
 354: PRECALL              
 358: CALL                 
 368: UNPACK_SEQUENCE      
 372: STORE_FAST           opts
 374: STORE_FAST           args
 376: JUMP_FORWARD         to 464
 378: LOAD_GLOBAL          NULL + do_shorts
 390: LOAD_FAST            opts
 392: LOAD_FAST            args
 394: LOAD_CONST           0
 396: BINARY_SUBSCR        
 406: LOAD_CONST           1
 408: LOAD_CONST           None
 410: BUILD_SLICE          
 412: BINARY_SUBSCR        
 422: LOAD_FAST            shortopts
 424: LOAD_FAST            args
 426: LOAD_CONST           1
 428: LOAD_CONST           None
 430: BUILD_SLICE          
 432: BINARY_SUBSCR        
 442: PRECALL              
 446: CALL                 
 456: UNPACK_SEQUENCE      
 460: STORE_FAST           opts
 462: STORE_FAST           args
 464: LOAD_FAST            args
 466: POP_JUMP_FORWARD_IF_FALSE to 546
 468: LOAD_FAST            args
 470: LOAD_CONST           0
 472: BINARY_SUBSCR        
 482: LOAD_METHOD          startswith
 504: LOAD_CONST           '-'
 506: PRECALL              
 510: CALL                 
 520: POP_JUMP_FORWARD_IF_FALSE to 546
 522: LOAD_FAST            args
 524: LOAD_CONST           0
 526: BINARY_SUBSCR        
 536: LOAD_CONST           '-'
 538: COMPARE_OP           !=
 544: POP_JUMP_BACKWARD_IF_TRUE to 190
 546: LOAD_FAST            opts
 548: LOAD_FAST            args
 550: BUILD_TUPLE          
 552: RETURN_VALUE         
