# Disassembly for getopt.do_longs
# From module file: getopt

## co_consts:
(None, '=', 1, 'option --%s requires argument', 0, 'option --%s must not have an argument', '--', '')

## co_names:
('index', 'ValueError', 'long_has_args', 'GetoptError', '_', 'append')

## bytecode:

   0: RESUME               
   2: NOP                  
   4: LOAD_FAST            opt
   6: LOAD_METHOD          index
  28: LOAD_CONST           '='
  30: PRECALL              
  34: CALL                 
  44: STORE_FAST           i
  46: LOAD_FAST            opt
  48: LOAD_CONST           None
  50: LOAD_FAST            i
  52: BUILD_SLICE          
  54: BINARY_SUBSCR        
  64: LOAD_FAST            opt
  66: LOAD_FAST            i
  68: LOAD_CONST           1
  70: BINARY_OP            +
  74: LOAD_CONST           None
  76: BUILD_SLICE          
  78: BINARY_SUBSCR        
  88: STORE_FAST           optarg
  90: STORE_FAST           opt
  92: JUMP_FORWARD         to 130
  94: PUSH_EXC_INFO        
  96: LOAD_GLOBAL          ValueError
 108: CHECK_EXC_MATCH      
 110: POP_JUMP_FORWARD_IF_FALSE to 122
 112: POP_TOP              
 114: LOAD_CONST           None
 116: STORE_FAST           optarg
 118: POP_EXCEPT           
 120: JUMP_FORWARD         to 130
 122: RERAISE              
 124: COPY                 
 126: POP_EXCEPT           
 128: RERAISE              
 130: LOAD_GLOBAL          NULL + long_has_args
 142: LOAD_FAST            opt
 144: LOAD_FAST            longopts
 146: PRECALL              
 150: CALL                 
 160: UNPACK_SEQUENCE      
 164: STORE_FAST           has_arg
 166: STORE_FAST           opt
 168: LOAD_FAST            has_arg
 170: POP_JUMP_FORWARD_IF_FALSE to 282
 172: LOAD_FAST            optarg
 174: POP_JUMP_FORWARD_IF_NOT_NONE to 280
 176: LOAD_FAST            args
 178: POP_JUMP_FORWARD_IF_TRUE to 244
 180: LOAD_GLOBAL          NULL + GetoptError
 192: LOAD_GLOBAL          NULL + _
 204: LOAD_CONST           'option --%s requires argument'
 206: PRECALL              
 210: CALL                 
 220: LOAD_FAST            opt
 222: BINARY_OP            %
 226: LOAD_FAST            opt
 228: PRECALL              
 232: CALL                 
 242: RAISE_VARARGS        
 244: LOAD_FAST            args
 246: LOAD_CONST           0
 248: BINARY_SUBSCR        
 258: LOAD_FAST            args
 260: LOAD_CONST           1
 262: LOAD_CONST           None
 264: BUILD_SLICE          
 266: BINARY_SUBSCR        
 276: STORE_FAST           args
 278: STORE_FAST           optarg
 280: JUMP_FORWARD         to 350
 282: LOAD_FAST            optarg
 284: POP_JUMP_FORWARD_IF_NONE to 350
 286: LOAD_GLOBAL          NULL + GetoptError
 298: LOAD_GLOBAL          NULL + _
 310: LOAD_CONST           'option --%s must not have an argument'
 312: PRECALL              
 316: CALL                 
 326: LOAD_FAST            opt
 328: BINARY_OP            %
 332: LOAD_FAST            opt
 334: PRECALL              
 338: CALL                 
 348: RAISE_VARARGS        
 350: LOAD_FAST            opts
 352: LOAD_METHOD          append
 374: LOAD_CONST           '--'
 376: LOAD_FAST            opt
 378: BINARY_OP            +
 382: LOAD_FAST            optarg
 384: JUMP_IF_TRUE_OR_POP  to 388
 386: LOAD_CONST           ''
 388: BUILD_TUPLE          
 390: PRECALL              
 394: CALL                 
 404: POP_TOP              
 406: LOAD_FAST            opts
 408: LOAD_FAST            args
 410: BUILD_TUPLE          
 412: RETURN_VALUE         
