# Disassembly for entities.Entity.send_message
# From module file: entities

## co_consts:
(None,)

## co_names:
('world', 'player', 'send_message')

## bytecode:

   0: RESUME               
   2: LOAD_FAST            self
   4: LOAD_ATTR            world
  14: POP_JUMP_FORWARD_IF_NONE to 106
  16: LOAD_FAST            self
  18: LOAD_ATTR            world
  28: LOAD_ATTR            player
  38: POP_JUMP_FORWARD_IF_NONE to 110
  40: LOAD_FAST            self
  42: LOAD_ATTR            world
  52: LOAD_ATTR            player
  62: LOAD_METHOD          send_message
  84: LOAD_FAST            message
  86: PRECALL              
  90: CALL                 
 100: POP_TOP              
 102: LOAD_CONST           None
 104: RETURN_VALUE         
 106: LOAD_CONST           None
 108: RETURN_VALUE         
 110: LOAD_CONST           None
 112: RETURN_VALUE         
