# Disassembly for entities.Entity.set_world
# From module file: entities

## co_consts:
(None,)

## co_names:
('world', 'children', 'set_world')

## bytecode:

   0: RESUME               
   2: LOAD_FAST            world
   4: LOAD_FAST            self
   6: STORE_ATTR           world
  16: LOAD_FAST            self
  18: LOAD_ATTR            children
  28: GET_ITER             
  30: FOR_ITER             to 88
  32: STORE_FAST           child
  34: LOAD_FAST            child
  36: LOAD_METHOD          set_world
  58: LOAD_FAST            self
  60: LOAD_ATTR            world
  70: PRECALL              
  74: CALL                 
  84: POP_TOP              
  86: JUMP_BACKWARD        to 30
  88: LOAD_FAST            self
  90: RETURN_VALUE         
