# Disassembly for entities.Entity.look
# From module file: entities

## co_consts:
(None, False)

## co_names:
('world', 'player', 'send_message', 'get_description', 'first_look')

## bytecode:

   0: RESUME               
   2: LOAD_FAST            self
   4: LOAD_ATTR            world
  14: POP_JUMP_FORWARD_IF_NONE to 156
  16: LOAD_FAST            self
  18: LOAD_ATTR            world
  28: LOAD_ATTR            player
  38: POP_JUMP_FORWARD_IF_NONE to 160
  40: LOAD_FAST            self
  42: LOAD_ATTR            world
  52: LOAD_ATTR            player
  62: LOAD_METHOD          send_message
  84: LOAD_FAST            self
  86: LOAD_METHOD          get_description
 108: PRECALL              
 112: CALL                 
 122: PRECALL              
 126: CALL                 
 136: POP_TOP              
 138: LOAD_CONST           False
 140: LOAD_FAST            self
 142: STORE_ATTR           first_look
 152: LOAD_CONST           None
 154: RETURN_VALUE         
 156: LOAD_CONST           None
 158: RETURN_VALUE         
 160: LOAD_CONST           None
 162: RETURN_VALUE         
