# Disassembly for entities.World.add_child
# From module file: entities

## co_consts:
(None,)

## co_names:
('super', 'add_child', 'is_a', 'Room', 'rooms', 'name')

## bytecode:

   0: COPY_FREE_VARS       
   2: RESUME               
   4: LOAD_GLOBAL          NULL + super
  16: PRECALL              
  20: CALL                 
  30: LOAD_METHOD          add_child
  52: LOAD_FAST            child
  54: PRECALL              
  58: CALL                 
  68: POP_TOP              
  70: LOAD_FAST            child
  72: LOAD_METHOD          is_a
  94: LOAD_GLOBAL          Room
 106: PRECALL              
 110: CALL                 
 120: POP_JUMP_FORWARD_IF_FALSE to 156
 122: LOAD_FAST            child
 124: LOAD_FAST            self
 126: LOAD_ATTR            rooms
 136: LOAD_FAST            child
 138: LOAD_ATTR            name
 148: STORE_SUBSCR         
 152: LOAD_CONST           None
 154: RETURN_VALUE         
 156: LOAD_CONST           None
 158: RETURN_VALUE         
