# Disassembly for entities.Entity.set_parent
# From module file: entities

## co_consts:
(None, 'World')

## co_names:
('parent', 'remove_child', 'add_child', 'world', 'set_world', 'is_a')

## bytecode:

   0: RESUME               
   2: LOAD_FAST            self
   4: LOAD_ATTR            parent
  14: POP_JUMP_FORWARD_IF_NONE to 68
  16: LOAD_FAST            self
  18: LOAD_ATTR            parent
  28: LOAD_METHOD          remove_child
  50: LOAD_FAST            self
  52: PRECALL              
  56: CALL                 
  66: POP_TOP              
  68: LOAD_FAST            parent
  70: POP_JUMP_FORWARD_IF_NONE to 128
  72: LOAD_FAST            parent
  74: LOAD_METHOD          add_child
  96: LOAD_FAST            self
  98: PRECALL              
 102: CALL                 
 112: POP_TOP              
 114: LOAD_FAST            parent
 116: LOAD_FAST            self
 118: STORE_ATTR           parent
 128: LOAD_FAST            self
 130: LOAD_ATTR            world
 140: POP_JUMP_FORWARD_IF_NOT_NONE to 330
 142: LOAD_FAST            parent
 144: POP_JUMP_FORWARD_IF_NONE to 330
 146: LOAD_FAST            parent
 148: LOAD_ATTR            world
 158: POP_JUMP_FORWARD_IF_NONE to 214
 160: LOAD_FAST            self
 162: LOAD_METHOD          set_world
 184: LOAD_FAST            parent
 186: LOAD_ATTR            world
 196: PRECALL              
 200: CALL                 
 210: POP_TOP              
 212: JUMP_FORWARD         to 298
 214: LOAD_FAST            parent
 216: LOAD_METHOD          is_a
 238: LOAD_CONST           'World'
 240: PRECALL              
 244: CALL                 
 254: POP_JUMP_FORWARD_IF_FALSE to 298
 256: LOAD_FAST            self
 258: LOAD_METHOD          set_world
 280: LOAD_FAST            parent
 282: PRECALL              
 286: CALL                 
 296: POP_TOP              
 298: LOAD_FAST            parent
 300: LOAD_ATTR            parent
 310: STORE_FAST           parent
 312: LOAD_FAST            self
 314: LOAD_ATTR            world
 324: POP_JUMP_FORWARD_IF_NOT_NONE to 330
 326: LOAD_FAST            parent
 328: POP_JUMP_BACKWARD_IF_NOT_NONE to 146
 330: LOAD_FAST            self
 332: RETURN_VALUE         
