# Disassembly for entities.Entity.add_child
# From module file: entities

## co_consts:
(None,)

## co_names:
('children', 'append', 'set_world', 'world')

## bytecode:

   0: RESUME               
   2: LOAD_FAST            self
   4: LOAD_ATTR            children
  14: LOAD_METHOD          append
  36: LOAD_FAST            child
  38: PRECALL              
  42: CALL                 
  52: POP_TOP              
  54: LOAD_FAST            child
  56: LOAD_METHOD          set_world
  78: LOAD_FAST            self
  80: LOAD_ATTR            world
  90: PRECALL              
  94: CALL                 
 104: POP_TOP              
 106: LOAD_FAST            self
 108: RETURN_VALUE         
