# Disassembly for entities.Room
# From module file: entities

## co_consts:
('Room', 'name', <code object __init__ at 0x000002406944A890, file "entities.py", line 109>, <code object get_options_prompt at 0x000002406943BB70, file "entities.py", line 112>, 'value', <code object handle_option_answer at 0x000002406943AEB0, file "entities.py", line 115>, <code object look at 0x000002406947C990, file "entities.py", line 118>)

## co_names:
('__name__', '__module__', '__qualname__', 'str', '__init__', 'get_options_prompt', 'handle_option_answer', 'look', '__classcell__')

## bytecode:

   0: MAKE_CELL            __class__
   2: RESUME               
   4: LOAD_NAME            __name__
   6: STORE_NAME           __module__
   8: LOAD_CONST           'Room'
  10: STORE_NAME           __qualname__
  12: LOAD_CONST           'name'
  14: LOAD_NAME            str
  16: BUILD_TUPLE          
  18: LOAD_CLOSURE         __class__
  20: BUILD_TUPLE          
  22: LOAD_CONST           <code object __init__ at 0x000002406944A890, file "entities.py", line 109>
  24: MAKE_FUNCTION        annotations, closure
  26: STORE_NAME           __init__
  28: LOAD_CONST           <code object get_options_prompt at 0x000002406943BB70, file "entities.py", line 112>
  30: MAKE_FUNCTION        
  32: STORE_NAME           get_options_prompt
  34: LOAD_CONST           'value'
  36: LOAD_NAME            str
  38: BUILD_TUPLE          
  40: LOAD_CONST           <code object handle_option_answer at 0x000002406943AEB0, file "entities.py", line 115>
  42: MAKE_FUNCTION        annotations
  44: STORE_NAME           handle_option_answer
  46: LOAD_CLOSURE         __class__
  48: BUILD_TUPLE          
  50: LOAD_CONST           <code object look at 0x000002406947C990, file "entities.py", line 118>
  52: MAKE_FUNCTION        closure
  54: STORE_NAME           look
  56: LOAD_CLOSURE         __class__
  58: COPY                 
  60: STORE_NAME           __classcell__
  62: RETURN_VALUE         
