# Disassembly for entities.Entity.ask_option
# From module file: entities

## co_consts:
(None, '')

## co_names:
('world', 'player', 'ask_option')

## bytecode:

   0: RESUME               
   2: LOAD_FAST            self
   4: LOAD_ATTR            world
  14: POP_JUMP_FORWARD_IF_NONE to 106
  16: LOAD_FAST            self
  18: LOAD_ATTR            world
  28: LOAD_ATTR            player
  38: POP_JUMP_FORWARD_IF_NONE to 106
  40: LOAD_FAST            self
  42: LOAD_ATTR            world
  52: LOAD_ATTR            player
  62: LOAD_METHOD          ask_option
  84: LOAD_FAST            prompt
  86: LOAD_FAST            options
  88: LOAD_FAST            include_defaults
  90: PRECALL              
  94: CALL                 
 104: RETURN_VALUE         
 106: LOAD_CONST           ''
 108: RETURN_VALUE         
