# Disassembly for entities.Room.look
# From module file: entities

## co_consts:
(None,)

## co_names:
('super', 'look', 'world', 'player', 'handle_option_answer', 'ask_option', 'get_options_prompt', 'get_options')

## bytecode:

   0: COPY_FREE_VARS       
   2: RESUME               
   4: LOAD_GLOBAL          NULL + super
  16: PRECALL              
  20: CALL                 
  30: LOAD_METHOD          look
  52: PRECALL              
  56: CALL                 
  66: POP_TOP              
  68: LOAD_FAST            self
  70: LOAD_ATTR            world
  80: POP_JUMP_FORWARD_IF_NONE to 284
  82: LOAD_FAST            self
  84: LOAD_ATTR            world
  94: LOAD_ATTR            player
 104: POP_JUMP_FORWARD_IF_NONE to 288
 106: LOAD_FAST            self
 108: LOAD_METHOD          handle_option_answer
 130: LOAD_FAST            self
 132: LOAD_ATTR            world
 142: LOAD_ATTR            player
 152: LOAD_METHOD          ask_option
 174: LOAD_FAST            self
 176: LOAD_METHOD          get_options_prompt
 198: PRECALL              
 202: CALL                 
 212: LOAD_FAST            self
 214: LOAD_METHOD          get_options
 236: PRECALL              
 240: CALL                 
 250: PRECALL              
 254: CALL                 
 264: PRECALL              
 268: CALL                 
 278: POP_TOP              
 280: LOAD_CONST           None
 282: RETURN_VALUE         
 284: LOAD_CONST           None
 286: RETURN_VALUE         
 288: LOAD_CONST           None
 290: RETURN_VALUE         
