# Disassembly for socket.fromfd
# From module file: socket

## co_consts:
(' fromfd(fd, family, type[, proto]) -> socket object\n\n    Create a socket object from a duplicate of the given file\n    descriptor.  The remaining arguments are the same as for socket().\n    ',)

## co_names:
('dup', 'socket')

## bytecode:

   0: RESUME               
   2: LOAD_GLOBAL          NULL + dup
  14: LOAD_FAST            fd
  16: PRECALL              
  20: CALL                 
  30: STORE_FAST           nfd
  32: LOAD_GLOBAL          NULL + socket
  44: LOAD_FAST            family
  46: LOAD_FAST            type
  48: LOAD_FAST            proto
  50: LOAD_FAST            nfd
  52: PRECALL              
  56: CALL                 
  66: RETURN_VALUE         
