# Disassembly for socket.socket.detach
# From module file: socket

## co_consts:
('detach() -> file descriptor\n\n        Close the socket object without closing the underlying file descriptor.\n        The object cannot be used after this call, but the file descriptor\n        can be reused for other purposes.  The file descriptor is returned.\n        ', True)

## co_names:
('_closed', 'super', 'detach')

## bytecode:

   0: COPY_FREE_VARS       
   2: RESUME               
   4: LOAD_CONST           True
   6: LOAD_FAST            self
   8: STORE_ATTR           _closed
  18: LOAD_GLOBAL          NULL + super
  30: PRECALL              
  34: CALL                 
  44: LOAD_METHOD          detach
  66: PRECALL              
  70: CALL                 
  80: RETURN_VALUE         
