# Disassembly for socket.socket.set_inheritable
# From module file: socket

## co_consts:
(None,)

## co_names:
('os', 'set_inheritable', 'fileno')

## bytecode:

   0: RESUME               
   2: LOAD_GLOBAL          NULL + os
  14: LOAD_ATTR            set_inheritable
  24: LOAD_FAST            self
  26: LOAD_METHOD          fileno
  48: PRECALL              
  52: CALL                 
  62: LOAD_FAST            inheritable
  64: PRECALL              
  68: CALL                 
  78: POP_TOP              
  80: LOAD_CONST           None
  82: RETURN_VALUE         
