# Disassembly for socket.SocketIO.fileno
# From module file: socket

## co_consts:
('Return the file descriptor of the underlying socket.\n        ',)

## co_names:
('_checkClosed', '_sock', 'fileno')

## bytecode:

   0: RESUME               
   2: LOAD_FAST            self
   4: LOAD_METHOD          _checkClosed
  26: PRECALL              
  30: CALL                 
  40: POP_TOP              
  42: LOAD_FAST            self
  44: LOAD_ATTR            _sock
  54: LOAD_METHOD          fileno
  76: PRECALL              
  80: CALL                 
  90: RETURN_VALUE         
