# Disassembly for socket
# From module file: socket

## co_consts:
("This module provides socket operations and some related functions.\nOn Unix, it supports IP (Internet Protocol) and Unix domain sockets.\nOn other systems, it only supports IP. Functions specific for a\nsocket are available as methods of the socket object.\n\nFunctions:\n\nsocket() -- create a new socket object\nsocketpair() -- create a pair of new socket objects [*]\nfromfd() -- create a socket object from an open file descriptor [*]\nsend_fds() -- Send file descriptor to the socket.\nrecv_fds() -- Receive file descriptors from the socket.\nfromshare() -- create a socket object from data received from socket.share() [*]\ngethostname() -- return the current hostname\ngethostbyname() -- map a hostname to its IP number\ngethostbyaddr() -- map an IP number or hostname to DNS info\ngetservbyname() -- map a service name and a protocol name to a port number\ngetprotobyname() -- map a protocol name (e.g. 'tcp') to a number\nntohs(), ntohl() -- convert 16, 32 bit int from network to host byte order\nhtons(), htonl() -- convert 16, 32 bit int from host to network byte order\ninet_aton() -- convert IP addr string (123.45.67.89) to 32-bit packed format\ninet_ntoa() -- convert 32-bit packed format IP to string (123.45.67.89)\nsocket.getdefaulttimeout() -- get the default timeout value\nsocket.setdefaulttimeout() -- set the default timeout value\ncreate_connection() -- connects to an address, with an optional timeout and\n                       optional source address.\n\n [*] not available on all platforms!\n\nSpecial objects:\n\nSocketType -- type object for socket objects\nerror -- exception raised for I/O errors\nhas_ipv6 -- boolean value indicating if IPv6 is supported\n\nIntEnum constants:\n\nAF_INET, AF_UNIX -- socket domains (first argument to socket() call)\nSOCK_STREAM, SOCK_DGRAM, SOCK_RAW -- socket types (second argument)\n\nInteger constants:\n\nMany other constants may be defined; these may be used in calls to\nthe setsockopt() and getsockopt() methods.\n", 0, None, ('*',), ('IntEnum', 'IntFlag'), 'EBADF', 9, 'EAGAIN', 11, 'EWOULDBLOCK', ('fromfd', 'getfqdn', 'create_connection', 'create_server', 'has_dualstack_ipv6', 'AddressFamily', 'SocketKind'), 'AddressFamily', <code object <lambda> at 0x000002406944BEE0, file "socket.py", line 78>, 'SocketKind', <code object <lambda> at 0x000002406944AAB0, file "socket.py", line 83>, 'MsgFlag', <code object <lambda> at 0x000002406944B220, file "socket.py", line 88>, 'AddressInfo', <code object <lambda> at 0x000002406944A010, file "socket.py", line 93>, '127.0.0.1', '::1', <code object _intenum_converter at 0x00000240693EB530, file "socket.py", line 99>, 'win', 'Specified event object handle is invalid.', 6, 'Insufficient memory available.', 8, 'One or more parameters are invalid.', 87, 'Overlapped operation aborted.', 995, 'Overlapped I/O event object not in signaled state.', 996, 'Overlapped operation will complete later.', 997, 'The operation was interrupted.', 10004, 'A bad file handle was passed.', 10009, 'Permission denied.', 10013, 'A fault occurred on the network??', 10014, 'An invalid operation was attempted.', 10022, 'Too many open files.', 10024, 'The socket operation would block.', 10035, 'A blocking operation is already in progress.', 10036, 'Operation already in progress.', 10037, 'Socket operation on nonsocket.', 10038, 'Destination address required.', 10039, 'Message too long.', 10040, 'Protocol wrong type for socket.', 10041, 'Bad protocol option.', 10042, 'Protocol not supported.', 10043, 'Socket type not supported.', 10044, 'Operation not supported.', 10045, 'Protocol family not supported.', 10046, 'Address family not supported by protocol family.', 10047, 'The network address is in use.', 10048, 'Cannot assign requested address.', 10049, 'Network is down.', 10050, 'Network is unreachable.', 10051, 'Network dropped connection on reset.', 10052, 'Software caused connection abort.', 10053, 'The connection has been reset.', 10054, 'No buffer space available.', 10055, 'Socket is already connected.', 10056, 'Socket is not connected.', 10057, 'The network has been shut down.', 10058, 'Too many references.', 10059, 'The operation timed out.', 10060, 'Connection refused.', 10061, 'Cannot translate name.', 10062, 'The name is too long.', 10063, 'The host is down.', 10064, 'The host is unreachable.', 10065, 'Directory not empty.', 10066, 'Too many processes.', 10067, 'User quota exceeded.', 10068, 'Disk quota exceeded.', 10069, 'Stale file handle reference.', 10070, 'Item is remote.', 10071, 'Network subsystem is unavailable.', 10091, 'Winsock.dll version out of range.', 10092, 'Successful WSAStartup not yet performed.', 10093, 'Graceful shutdown in progress.', 10101, 'No more results from WSALookupServiceNext.', 10102, 'Call has been canceled.', 10103, 'Procedure call table is invalid.', 10104, 'Service provider is invalid.', 10105, 'Service provider failed to initialize.', 10106, 'System call failure.', 10107, 'Service not found.', 10108, 'Class type not found.', 10109, 10110, 'Call was canceled.', 10111, 'Database query was refused.', 10112, 'Host not found.', 11001, 'Nonauthoritative host not found.', 11002, 'This is a nonrecoverable error.', 11003, 'Valid name, no data record requested type.', 11004, 'QoS receivers.', 11005, 'QoS senders.', 11006, 'No QoS senders.', 11007, 'QoS no receivers.', 11008, 'QoS request confirmed.', 11009, 'QoS admission error.', 11010, 'QoS policy failure.', 11011, 'QoS bad style.', 11012, 'QoS bad object.', 11013, 'QoS traffic control error.', 11014, 'QoS generic error.', 11015, 'QoS service type error.', 11016, 'QoS flowspec error.', 11017, 'Invalid QoS provider buffer.', 11018, 'Invalid QoS filter style.', 11019, 11020, 'Incorrect QoS filter count.', 11021, 'Invalid QoS object length.', 11022, 'Incorrect QoS flow count.', 11023, 'Unrecognized QoS object.', 11024, 'Invalid QoS policy object.', 11025, 'Invalid QoS flow descriptor.', 11026, 'Invalid QoS provider-specific flowspec.', 11027, 'Invalid QoS provider-specific filterspec.', 11028, 'Invalid QoS shape discard mode object.', 11029, 'Invalid QoS shaping rate object.', 11030, 'Reserved policy QoS element type.', 11031, 'errorTab', <code object _GiveupOnSendfile at 0x0000024069427C50, file "socket.py", line 211>, '_GiveupOnSendfile', <code object socket at 0x000002406931FA30, file "socket.py", line 214>, 'socket', <code object fromfd at 0x00000240693EB030, file "socket.py", line 540>, 'sendmsg', <code object send_fds at 0x00000240693AA6F0, file "socket.py", line 552>, 'send_fds', 'recvmsg', <code object recv_fds at 0x0000024068D6CC00, file "socket.py", line 564>, 'recv_fds', 'share', <code object fromshare at 0x0000024069466DB0, file "socket.py", line 584>, 'fromshare', 'socketpair', <code object socketpair at 0x00000240691DBC00, file "socket.py", line 595>, <code object socketpair at 0x0000024068D071A0, file "socket.py", line 616>, 'socketpair([family[, type[, proto]]]) -> (socket object, socket object)\nCreate a pair of socket objects from the sockets returned by the platform\nsocketpair() function.\nThe arguments are the same as for socket() except the default family is AF_UNIX\nif defined on the platform; otherwise, the default is AF_INET.\n', <code object SocketIO at 0x00000240693D2890, file "socket.py", line 663>, 'SocketIO', '', <code object getfqdn at 0x00000240691F5890, file "socket.py", line 780>, False, ('all_errors',), <code object create_connection at 0x0000024066347D50, file "socket.py", line 809>, <code object has_dualstack_ipv6 at 0x000002406931FC30, file "socket.py", line 860>, ('family', 'backlog', 'reuse_port', 'dualstack_ipv6'), <code object create_server at 0x0000024068D020D0, file "socket.py", line 876>, <code object getaddrinfo at 0x000002406942E740, file "socket.py", line 945>, (0,), (0, None), ('',), (0, 0, 0, 0))

## co_names:
('__doc__', '_socket', 'os', 'sys', 'io', 'selectors', 'enum', 'IntEnum', 'IntFlag', 'errno', 'ImportError', 'getattr', 'EBADF', 'EAGAIN', 'EWOULDBLOCK', '__all__', 'extend', '_get_exports_list', '_convert_', '__name__', '_LOCALHOST', '_LOCALHOST_V6', '_intenum_converter', 'platform', 'lower', 'startswith', 'errorTab', 'append', 'Exception', '_GiveupOnSendfile', 'socket', 'fromfd', 'hasattr', 'array', 'send_fds', 'recv_fds', 'fromshare', 'SOCK_STREAM', 'socketpair', 'AF_INET', '_blocking_errnos', 'RawIOBase', 'SocketIO', 'getfqdn', 'object', '_GLOBAL_DEFAULT_TIMEOUT', 'create_connection', 'has_dualstack_ipv6', 'create_server', 'getaddrinfo')

## bytecode:

   0: RESUME               
   2: LOAD_CONST           "This module provides socket operations and some related functions.\nOn Unix, it supports IP (Internet Protocol) and Unix domain sockets.\nOn other systems, it only supports IP. Functions specific for a\nsocket are available as methods of the socket object.\n\nFunctions:\n\nsocket() -- create a new socket object\nsocketpair() -- create a pair of new socket objects [*]\nfromfd() -- create a socket object from an open file descriptor [*]\nsend_fds() -- Send file descriptor to the socket.\nrecv_fds() -- Receive file descriptors from the socket.\nfromshare() -- create a socket object from data received from socket.share() [*]\ngethostname() -- return the current hostname\ngethostbyname() -- map a hostname to its IP number\ngethostbyaddr() -- map an IP number or hostname to DNS info\ngetservbyname() -- map a service name and a protocol name to a port number\ngetprotobyname() -- map a protocol name (e.g. 'tcp') to a number\nntohs(), ntohl() -- convert 16, 32 bit int from network to host byte order\nhtons(), htonl() -- convert 16, 32 bit int from host to network byte order\ninet_aton() -- convert IP addr string (123.45.67.89) to 32-bit packed format\ninet_ntoa() -- convert 32-bit packed format IP to string (123.45.67.89)\nsocket.getdefaulttimeout() -- get the default timeout value\nsocket.setdefaulttimeout() -- set the default timeout value\ncreate_connection() -- connects to an address, with an optional timeout and\n                       optional source address.\n\n [*] not available on all platforms!\n\nSpecial objects:\n\nSocketType -- type object for socket objects\nerror -- exception raised for I/O errors\nhas_ipv6 -- boolean value indicating if IPv6 is supported\n\nIntEnum constants:\n\nAF_INET, AF_UNIX -- socket domains (first argument to socket() call)\nSOCK_STREAM, SOCK_DGRAM, SOCK_RAW -- socket types (second argument)\n\nInteger constants:\n\nMany other constants may be defined; these may be used in calls to\nthe setsockopt() and getsockopt() methods.\n"
   4: STORE_NAME           __doc__
   6: LOAD_CONST           0
   8: LOAD_CONST           None
  10: IMPORT_NAME          _socket
  12: STORE_NAME           _socket
  14: LOAD_CONST           0
  16: LOAD_CONST           ('*',)
  18: IMPORT_NAME          _socket
  20: IMPORT_STAR          
  22: LOAD_CONST           0
  24: LOAD_CONST           None
  26: IMPORT_NAME          os
  28: STORE_NAME           os
  30: LOAD_CONST           0
  32: LOAD_CONST           None
  34: IMPORT_NAME          sys
  36: STORE_NAME           sys
  38: LOAD_CONST           0
  40: LOAD_CONST           None
  42: IMPORT_NAME          io
  44: STORE_NAME           io
  46: LOAD_CONST           0
  48: LOAD_CONST           None
  50: IMPORT_NAME          selectors
  52: STORE_NAME           selectors
  54: LOAD_CONST           0
  56: LOAD_CONST           ('IntEnum', 'IntFlag')
  58: IMPORT_NAME          enum
  60: IMPORT_FROM          IntEnum
  62: STORE_NAME           IntEnum
  64: IMPORT_FROM          IntFlag
  66: STORE_NAME           IntFlag
  68: POP_TOP              
  70: NOP                  
  72: LOAD_CONST           0
  74: LOAD_CONST           None
  76: IMPORT_NAME          errno
  78: STORE_NAME           errno
  80: JUMP_FORWARD         to 108
  82: PUSH_EXC_INFO        
  84: LOAD_NAME            ImportError
  86: CHECK_EXC_MATCH      
  88: POP_JUMP_FORWARD_IF_FALSE to 100
  90: POP_TOP              
  92: LOAD_CONST           None
  94: STORE_NAME           errno
  96: POP_EXCEPT           
  98: JUMP_FORWARD         to 108
 100: RERAISE              
 102: COPY                 
 104: POP_EXCEPT           
 106: RERAISE              
 108: PUSH_NULL            
 110: LOAD_NAME            getattr
 112: LOAD_NAME            errno
 114: LOAD_CONST           'EBADF'
 116: LOAD_CONST           9
 118: PRECALL              
 122: CALL                 
 132: STORE_NAME           EBADF
 134: PUSH_NULL            
 136: LOAD_NAME            getattr
 138: LOAD_NAME            errno
 140: LOAD_CONST           'EAGAIN'
 142: LOAD_CONST           11
 144: PRECALL              
 148: CALL                 
 158: STORE_NAME           EAGAIN
 160: PUSH_NULL            
 162: LOAD_NAME            getattr
 164: LOAD_NAME            errno
 166: LOAD_CONST           'EWOULDBLOCK'
 168: LOAD_CONST           11
 170: PRECALL              
 174: CALL                 
 184: STORE_NAME           EWOULDBLOCK
 186: BUILD_LIST           
 188: LOAD_CONST           ('fromfd', 'getfqdn', 'create_connection', 'create_server', 'has_dualstack_ipv6', 'AddressFamily', 'SocketKind')
 190: LIST_EXTEND          
 192: STORE_NAME           __all__
 194: LOAD_NAME            __all__
 196: LOAD_METHOD          extend
 218: PUSH_NULL            
 220: LOAD_NAME            os
 222: LOAD_ATTR            _get_exports_list
 232: LOAD_NAME            _socket
 234: PRECALL              
 238: CALL                 
 248: PRECALL              
 252: CALL                 
 262: POP_TOP              
 264: PUSH_NULL            
 266: LOAD_NAME            IntEnum
 268: LOAD_ATTR            _convert_
 278: LOAD_CONST           'AddressFamily'
 280: LOAD_NAME            __name__
 282: LOAD_CONST           <code object <lambda> at 0x000002406944BEE0, file "socket.py", line 78>
 284: MAKE_FUNCTION        
 286: PRECALL              
 290: CALL                 
 300: POP_TOP              
 302: PUSH_NULL            
 304: LOAD_NAME            IntEnum
 306: LOAD_ATTR            _convert_
 316: LOAD_CONST           'SocketKind'
 318: LOAD_NAME            __name__
 320: LOAD_CONST           <code object <lambda> at 0x000002406944AAB0, file "socket.py", line 83>
 322: MAKE_FUNCTION        
 324: PRECALL              
 328: CALL                 
 338: POP_TOP              
 340: PUSH_NULL            
 342: LOAD_NAME            IntFlag
 344: LOAD_ATTR            _convert_
 354: LOAD_CONST           'MsgFlag'
 356: LOAD_NAME            __name__
 358: LOAD_CONST           <code object <lambda> at 0x000002406944B220, file "socket.py", line 88>
 360: MAKE_FUNCTION        
 362: PRECALL              
 366: CALL                 
 376: POP_TOP              
 378: PUSH_NULL            
 380: LOAD_NAME            IntFlag
 382: LOAD_ATTR            _convert_
 392: LOAD_CONST           'AddressInfo'
 394: LOAD_NAME            __name__
 396: LOAD_CONST           <code object <lambda> at 0x000002406944A010, file "socket.py", line 93>
 398: MAKE_FUNCTION        
 400: PRECALL              
 404: CALL                 
 414: POP_TOP              
 416: LOAD_CONST           '127.0.0.1'
 418: STORE_NAME           _LOCALHOST
 420: LOAD_CONST           '::1'
 422: STORE_NAME           _LOCALHOST_V6
 424: LOAD_CONST           <code object _intenum_converter at 0x00000240693EB530, file "socket.py", line 99>
 426: MAKE_FUNCTION        
 428: STORE_NAME           _intenum_converter
 430: LOAD_NAME            sys
 432: LOAD_ATTR            platform
 442: LOAD_METHOD          lower
 464: PRECALL              
 468: CALL                 
 478: LOAD_METHOD          startswith
 500: LOAD_CONST           'win'
 502: PRECALL              
 506: CALL                 
 516: EXTENDED_ARG         
 518: POP_JUMP_FORWARD_IF_FALSE to 1516
 520: BUILD_MAP            
 522: STORE_NAME           errorTab
 524: LOAD_CONST           'Specified event object handle is invalid.'
 526: LOAD_NAME            errorTab
 528: LOAD_CONST           6
 530: STORE_SUBSCR         
 534: LOAD_CONST           'Insufficient memory available.'
 536: LOAD_NAME            errorTab
 538: LOAD_CONST           8
 540: STORE_SUBSCR         
 544: LOAD_CONST           'One or more parameters are invalid.'
 546: LOAD_NAME            errorTab
 548: LOAD_CONST           87
 550: STORE_SUBSCR         
 554: LOAD_CONST           'Overlapped operation aborted.'
 556: LOAD_NAME            errorTab
 558: LOAD_CONST           995
 560: STORE_SUBSCR         
 564: LOAD_CONST           'Overlapped I/O event object not in signaled state.'
 566: LOAD_NAME            errorTab
 568: LOAD_CONST           996
 570: STORE_SUBSCR         
 574: LOAD_CONST           'Overlapped operation will complete later.'
 576: LOAD_NAME            errorTab
 578: LOAD_CONST           997
 580: STORE_SUBSCR         
 584: LOAD_CONST           'The operation was interrupted.'
 586: LOAD_NAME            errorTab
 588: LOAD_CONST           10004
 590: STORE_SUBSCR         
 594: LOAD_CONST           'A bad file handle was passed.'
 596: LOAD_NAME            errorTab
 598: LOAD_CONST           10009
 600: STORE_SUBSCR         
 604: LOAD_CONST           'Permission denied.'
 606: LOAD_NAME            errorTab
 608: LOAD_CONST           10013
 610: STORE_SUBSCR         
 614: LOAD_CONST           'A fault occurred on the network??'
 616: LOAD_NAME            errorTab
 618: LOAD_CONST           10014
 620: STORE_SUBSCR         
 624: LOAD_CONST           'An invalid operation was attempted.'
 626: LOAD_NAME            errorTab
 628: LOAD_CONST           10022
 630: STORE_SUBSCR         
 634: LOAD_CONST           'Too many open files.'
 636: LOAD_NAME            errorTab
 638: LOAD_CONST           10024
 640: STORE_SUBSCR         
 644: LOAD_CONST           'The socket operation would block.'
 646: LOAD_NAME            errorTab
 648: LOAD_CONST           10035
 650: STORE_SUBSCR         
 654: LOAD_CONST           'A blocking operation is already in progress.'
 656: LOAD_NAME            errorTab
 658: LOAD_CONST           10036
 660: STORE_SUBSCR         
 664: LOAD_CONST           'Operation already in progress.'
 666: LOAD_NAME            errorTab
 668: LOAD_CONST           10037
 670: STORE_SUBSCR         
 674: LOAD_CONST           'Socket operation on nonsocket.'
 676: LOAD_NAME            errorTab
 678: LOAD_CONST           10038
 680: STORE_SUBSCR         
 684: LOAD_CONST           'Destination address required.'
 686: LOAD_NAME            errorTab
 688: LOAD_CONST           10039
 690: STORE_SUBSCR         
 694: LOAD_CONST           'Message too long.'
 696: LOAD_NAME            errorTab
 698: LOAD_CONST           10040
 700: STORE_SUBSCR         
 704: LOAD_CONST           'Protocol wrong type for socket.'
 706: LOAD_NAME            errorTab
 708: LOAD_CONST           10041
 710: STORE_SUBSCR         
 714: LOAD_CONST           'Bad protocol option.'
 716: LOAD_NAME            errorTab
 718: LOAD_CONST           10042
 720: STORE_SUBSCR         
 724: LOAD_CONST           'Protocol not supported.'
 726: LOAD_NAME            errorTab
 728: LOAD_CONST           10043
 730: STORE_SUBSCR         
 734: LOAD_CONST           'Socket type not supported.'
 736: LOAD_NAME            errorTab
 738: LOAD_CONST           10044
 740: STORE_SUBSCR         
 744: LOAD_CONST           'Operation not supported.'
 746: LOAD_NAME            errorTab
 748: LOAD_CONST           10045
 750: STORE_SUBSCR         
 754: LOAD_CONST           'Protocol family not supported.'
 756: LOAD_NAME            errorTab
 758: LOAD_CONST           10046
 760: STORE_SUBSCR         
 764: LOAD_CONST           'Address family not supported by protocol family.'
 766: LOAD_NAME            errorTab
 768: LOAD_CONST           10047
 770: STORE_SUBSCR         
 774: LOAD_CONST           'The network address is in use.'
 776: LOAD_NAME            errorTab
 778: LOAD_CONST           10048
 780: STORE_SUBSCR         
 784: LOAD_CONST           'Cannot assign requested address.'
 786: LOAD_NAME            errorTab
 788: LOAD_CONST           10049
 790: STORE_SUBSCR         
 794: LOAD_CONST           'Network is down.'
 796: LOAD_NAME            errorTab
 798: LOAD_CONST           10050
 800: STORE_SUBSCR         
 804: LOAD_CONST           'Network is unreachable.'
 806: LOAD_NAME            errorTab
 808: LOAD_CONST           10051
 810: STORE_SUBSCR         
 814: LOAD_CONST           'Network dropped connection on reset.'
 816: LOAD_NAME            errorTab
 818: LOAD_CONST           10052
 820: STORE_SUBSCR         
 824: LOAD_CONST           'Software caused connection abort.'
 826: LOAD_NAME            errorTab
 828: LOAD_CONST           10053
 830: STORE_SUBSCR         
 834: LOAD_CONST           'The connection has been reset.'
 836: LOAD_NAME            errorTab
 838: LOAD_CONST           10054
 840: STORE_SUBSCR         
 844: LOAD_CONST           'No buffer space available.'
 846: LOAD_NAME            errorTab
 848: LOAD_CONST           10055
 850: STORE_SUBSCR         
 854: LOAD_CONST           'Socket is already connected.'
 856: LOAD_NAME            errorTab
 858: LOAD_CONST           10056
 860: STORE_SUBSCR         
 864: LOAD_CONST           'Socket is not connected.'
 866: LOAD_NAME            errorTab
 868: LOAD_CONST           10057
 870: STORE_SUBSCR         
 874: LOAD_CONST           'The network has been shut down.'
 876: LOAD_NAME            errorTab
 878: LOAD_CONST           10058
 880: STORE_SUBSCR         
 884: LOAD_CONST           'Too many references.'
 886: LOAD_NAME            errorTab
 888: LOAD_CONST           10059
 890: STORE_SUBSCR         
 894: LOAD_CONST           'The operation timed out.'
 896: LOAD_NAME            errorTab
 898: LOAD_CONST           10060
 900: STORE_SUBSCR         
 904: LOAD_CONST           'Connection refused.'
 906: LOAD_NAME            errorTab
 908: LOAD_CONST           10061
 910: STORE_SUBSCR         
 914: LOAD_CONST           'Cannot translate name.'
 916: LOAD_NAME            errorTab
 918: LOAD_CONST           10062
 920: STORE_SUBSCR         
 924: LOAD_CONST           'The name is too long.'
 926: LOAD_NAME            errorTab
 928: LOAD_CONST           10063
 930: STORE_SUBSCR         
 934: LOAD_CONST           'The host is down.'
 936: LOAD_NAME            errorTab
 938: LOAD_CONST           10064
 940: STORE_SUBSCR         
 944: LOAD_CONST           'The host is unreachable.'
 946: LOAD_NAME            errorTab
 948: LOAD_CONST           10065
 950: STORE_SUBSCR         
 954: LOAD_CONST           'Directory not empty.'
 956: LOAD_NAME            errorTab
 958: LOAD_CONST           10066
 960: STORE_SUBSCR         
 964: LOAD_CONST           'Too many processes.'
 966: LOAD_NAME            errorTab
 968: LOAD_CONST           10067
 970: STORE_SUBSCR         
 974: LOAD_CONST           'User quota exceeded.'
 976: LOAD_NAME            errorTab
 978: LOAD_CONST           10068
 980: STORE_SUBSCR         
 984: LOAD_CONST           'Disk quota exceeded.'
 986: LOAD_NAME            errorTab
 988: LOAD_CONST           10069
 990: STORE_SUBSCR         
 994: LOAD_CONST           'Stale file handle reference.'
 996: LOAD_NAME            errorTab
 998: LOAD_CONST           10070
1000: STORE_SUBSCR         
1004: LOAD_CONST           'Item is remote.'
1006: LOAD_NAME            errorTab
1008: LOAD_CONST           10071
1010: STORE_SUBSCR         
1014: LOAD_CONST           'Network subsystem is unavailable.'
1016: LOAD_NAME            errorTab
1018: LOAD_CONST           10091
1020: STORE_SUBSCR         
1024: LOAD_CONST           'Winsock.dll version out of range.'
1026: LOAD_NAME            errorTab
1028: LOAD_CONST           10092
1030: STORE_SUBSCR         
1034: LOAD_CONST           'Successful WSAStartup not yet performed.'
1036: LOAD_NAME            errorTab
1038: LOAD_CONST           10093
1040: STORE_SUBSCR         
1044: LOAD_CONST           'Graceful shutdown in progress.'
1046: LOAD_NAME            errorTab
1048: LOAD_CONST           10101
1050: STORE_SUBSCR         
1054: LOAD_CONST           'No more results from WSALookupServiceNext.'
1056: LOAD_NAME            errorTab
1058: LOAD_CONST           10102
1060: STORE_SUBSCR         
1064: LOAD_CONST           'Call has been canceled.'
1066: LOAD_NAME            errorTab
1068: LOAD_CONST           10103
1070: STORE_SUBSCR         
1074: LOAD_CONST           'Procedure call table is invalid.'
1076: LOAD_NAME            errorTab
1078: LOAD_CONST           10104
1080: STORE_SUBSCR         
1084: LOAD_CONST           'Service provider is invalid.'
1086: LOAD_NAME            errorTab
1088: LOAD_CONST           10105
1090: STORE_SUBSCR         
1094: LOAD_CONST           'Service provider failed to initialize.'
1096: LOAD_NAME            errorTab
1098: LOAD_CONST           10106
1100: STORE_SUBSCR         
1104: LOAD_CONST           'System call failure.'
1106: LOAD_NAME            errorTab
1108: LOAD_CONST           10107
1110: STORE_SUBSCR         
1114: LOAD_CONST           'Service not found.'
1116: LOAD_NAME            errorTab
1118: LOAD_CONST           10108
1120: STORE_SUBSCR         
1124: LOAD_CONST           'Class type not found.'
1126: LOAD_NAME            errorTab
1128: LOAD_CONST           10109
1130: STORE_SUBSCR         
1134: LOAD_CONST           'No more results from WSALookupServiceNext.'
1136: LOAD_NAME            errorTab
1138: LOAD_CONST           10110
1140: STORE_SUBSCR         
1144: LOAD_CONST           'Call was canceled.'
1146: LOAD_NAME            errorTab
1148: LOAD_CONST           10111
1150: STORE_SUBSCR         
1154: LOAD_CONST           'Database query was refused.'
1156: LOAD_NAME            errorTab
1158: LOAD_CONST           10112
1160: STORE_SUBSCR         
1164: LOAD_CONST           'Host not found.'
1166: LOAD_NAME            errorTab
1168: LOAD_CONST           11001
1170: STORE_SUBSCR         
1174: LOAD_CONST           'Nonauthoritative host not found.'
1176: LOAD_NAME            errorTab
1178: LOAD_CONST           11002
1180: STORE_SUBSCR         
1184: LOAD_CONST           'This is a nonrecoverable error.'
1186: LOAD_NAME            errorTab
1188: LOAD_CONST           11003
1190: STORE_SUBSCR         
1194: LOAD_CONST           'Valid name, no data record requested type.'
1196: LOAD_NAME            errorTab
1198: LOAD_CONST           11004
1200: STORE_SUBSCR         
1204: LOAD_CONST           'QoS receivers.'
1206: LOAD_NAME            errorTab
1208: LOAD_CONST           11005
1210: STORE_SUBSCR         
1214: LOAD_CONST           'QoS senders.'
1216: LOAD_NAME            errorTab
1218: LOAD_CONST           11006
1220: STORE_SUBSCR         
1224: LOAD_CONST           'No QoS senders.'
1226: LOAD_NAME            errorTab
1228: LOAD_CONST           11007
1230: STORE_SUBSCR         
1234: LOAD_CONST           'QoS no receivers.'
1236: LOAD_NAME            errorTab
1238: LOAD_CONST           11008
1240: STORE_SUBSCR         
1244: LOAD_CONST           'QoS request confirmed.'
1246: LOAD_NAME            errorTab
1248: LOAD_CONST           11009
1250: STORE_SUBSCR         
1254: LOAD_CONST           'QoS admission error.'
1256: LOAD_NAME            errorTab
1258: LOAD_CONST           11010
1260: STORE_SUBSCR         
1264: LOAD_CONST           'QoS policy failure.'
1266: LOAD_NAME            errorTab
1268: LOAD_CONST           11011
1270: STORE_SUBSCR         
1274: LOAD_CONST           'QoS bad style.'
1276: LOAD_NAME            errorTab
1278: LOAD_CONST           11012
1280: STORE_SUBSCR         
1284: LOAD_CONST           'QoS bad object.'
1286: LOAD_NAME            errorTab
1288: LOAD_CONST           11013
1290: STORE_SUBSCR         
1294: LOAD_CONST           'QoS traffic control error.'
1296: LOAD_NAME            errorTab
1298: LOAD_CONST           11014
1300: STORE_SUBSCR         
1304: LOAD_CONST           'QoS generic error.'
1306: LOAD_NAME            errorTab
1308: LOAD_CONST           11015
1310: STORE_SUBSCR         
1314: LOAD_CONST           'QoS service type error.'
1316: LOAD_NAME            errorTab
1318: LOAD_CONST           11016
1320: STORE_SUBSCR         
1324: LOAD_CONST           'QoS flowspec error.'
1326: LOAD_NAME            errorTab
1328: LOAD_CONST           11017
1330: STORE_SUBSCR         
1334: LOAD_CONST           'Invalid QoS provider buffer.'
1336: LOAD_NAME            errorTab
1338: LOAD_CONST           11018
1340: STORE_SUBSCR         
1344: LOAD_CONST           'Invalid QoS filter style.'
1346: LOAD_NAME            errorTab
1348: LOAD_CONST           11019
1350: STORE_SUBSCR         
1354: LOAD_CONST           'Invalid QoS filter style.'
1356: LOAD_NAME            errorTab
1358: LOAD_CONST           11020
1360: STORE_SUBSCR         
1364: LOAD_CONST           'Incorrect QoS filter count.'
1366: LOAD_NAME            errorTab
1368: LOAD_CONST           11021
1370: STORE_SUBSCR         
1374: LOAD_CONST           'Invalid QoS object length.'
1376: LOAD_NAME            errorTab
1378: LOAD_CONST           11022
1380: STORE_SUBSCR         
1384: LOAD_CONST           'Incorrect QoS flow count.'
1386: LOAD_NAME            errorTab
1388: LOAD_CONST           11023
1390: STORE_SUBSCR         
1394: LOAD_CONST           'Unrecognized QoS object.'
1396: LOAD_NAME            errorTab
1398: LOAD_CONST           11024
1400: STORE_SUBSCR         
1404: LOAD_CONST           'Invalid QoS policy object.'
1406: LOAD_NAME            errorTab
1408: LOAD_CONST           11025
1410: STORE_SUBSCR         
1414: LOAD_CONST           'Invalid QoS flow descriptor.'
1416: LOAD_NAME            errorTab
1418: LOAD_CONST           11026
1420: STORE_SUBSCR         
1424: LOAD_CONST           'Invalid QoS provider-specific flowspec.'
1426: LOAD_NAME            errorTab
1428: LOAD_CONST           11027
1430: STORE_SUBSCR         
1434: LOAD_CONST           'Invalid QoS provider-specific filterspec.'
1436: LOAD_NAME            errorTab
1438: LOAD_CONST           11028
1440: STORE_SUBSCR         
1444: LOAD_CONST           'Invalid QoS shape discard mode object.'
1446: LOAD_NAME            errorTab
1448: LOAD_CONST           11029
1450: STORE_SUBSCR         
1454: LOAD_CONST           'Invalid QoS shaping rate object.'
1456: LOAD_NAME            errorTab
1458: LOAD_CONST           11030
1460: STORE_SUBSCR         
1464: LOAD_CONST           'Reserved policy QoS element type.'
1466: LOAD_NAME            errorTab
1468: LOAD_CONST           11031
1470: STORE_SUBSCR         
1474: LOAD_NAME            __all__
1476: LOAD_METHOD          append
1498: LOAD_CONST           'errorTab'
1500: PRECALL              
1504: CALL                 
1514: POP_TOP              
1516: PUSH_NULL            
1518: LOAD_BUILD_CLASS     
1520: LOAD_CONST           <code object _GiveupOnSendfile at 0x0000024069427C50, file "socket.py", line 211>
1522: MAKE_FUNCTION        
1524: LOAD_CONST           '_GiveupOnSendfile'
1526: LOAD_NAME            Exception
1528: PRECALL              
1532: CALL                 
1542: STORE_NAME           _GiveupOnSendfile
1544: PUSH_NULL            
1546: LOAD_BUILD_CLASS     
1548: LOAD_CONST           <code object socket at 0x000002406931FA30, file "socket.py", line 214>
1550: MAKE_FUNCTION        
1552: LOAD_CONST           'socket'
1554: LOAD_NAME            _socket
1556: LOAD_ATTR            socket
1566: PRECALL              
1570: CALL                 
1580: STORE_NAME           socket
1582: LOAD_CONST           (0,)
1584: LOAD_CONST           <code object fromfd at 0x00000240693EB030, file "socket.py", line 540>
1586: MAKE_FUNCTION        defaults
1588: STORE_NAME           fromfd
1590: PUSH_NULL            
1592: LOAD_NAME            hasattr
1594: LOAD_NAME            _socket
1596: LOAD_ATTR            socket
1606: LOAD_CONST           'sendmsg'
1608: PRECALL              
1612: CALL                 
1622: POP_JUMP_FORWARD_IF_FALSE to 1682
1624: LOAD_CONST           0
1626: LOAD_CONST           None
1628: IMPORT_NAME          array
1630: STORE_NAME           array
1632: LOAD_CONST           (0, None)
1634: LOAD_CONST           <code object send_fds at 0x00000240693AA6F0, file "socket.py", line 552>
1636: MAKE_FUNCTION        defaults
1638: STORE_NAME           send_fds
1640: LOAD_NAME            __all__
1642: LOAD_METHOD          append
1664: LOAD_CONST           'send_fds'
1666: PRECALL              
1670: CALL                 
1680: POP_TOP              
1682: PUSH_NULL            
1684: LOAD_NAME            hasattr
1686: LOAD_NAME            _socket
1688: LOAD_ATTR            socket
1698: LOAD_CONST           'recvmsg'
1700: PRECALL              
1704: CALL                 
1714: POP_JUMP_FORWARD_IF_FALSE to 1774
1716: LOAD_CONST           0
1718: LOAD_CONST           None
1720: IMPORT_NAME          array
1722: STORE_NAME           array
1724: LOAD_CONST           (0,)
1726: LOAD_CONST           <code object recv_fds at 0x0000024068D6CC00, file "socket.py", line 564>
1728: MAKE_FUNCTION        defaults
1730: STORE_NAME           recv_fds
1732: LOAD_NAME            __all__
1734: LOAD_METHOD          append
1756: LOAD_CONST           'recv_fds'
1758: PRECALL              
1762: CALL                 
1772: POP_TOP              
1774: PUSH_NULL            
1776: LOAD_NAME            hasattr
1778: LOAD_NAME            _socket
1780: LOAD_ATTR            socket
1790: LOAD_CONST           'share'
1792: PRECALL              
1796: CALL                 
1806: POP_JUMP_FORWARD_IF_FALSE to 1856
1808: LOAD_CONST           <code object fromshare at 0x0000024069466DB0, file "socket.py", line 584>
1810: MAKE_FUNCTION        
1812: STORE_NAME           fromshare
1814: LOAD_NAME            __all__
1816: LOAD_METHOD          append
1838: LOAD_CONST           'fromshare'
1840: PRECALL              
1844: CALL                 
1854: POP_TOP              
1856: PUSH_NULL            
1858: LOAD_NAME            hasattr
1860: LOAD_NAME            _socket
1862: LOAD_CONST           'socketpair'
1864: PRECALL              
1868: CALL                 
1878: POP_JUMP_FORWARD_IF_FALSE to 1896
1880: LOAD_CONST           None
1882: LOAD_NAME            SOCK_STREAM
1884: LOAD_CONST           0
1886: BUILD_TUPLE          
1888: LOAD_CONST           <code object socketpair at 0x00000240691DBC00, file "socket.py", line 595>
1890: MAKE_FUNCTION        defaults
1892: STORE_NAME           socketpair
1894: JUMP_FORWARD         to 1952
1896: LOAD_NAME            AF_INET
1898: LOAD_NAME            SOCK_STREAM
1900: LOAD_CONST           0
1902: BUILD_TUPLE          
1904: LOAD_CONST           <code object socketpair at 0x0000024068D071A0, file "socket.py", line 616>
1906: MAKE_FUNCTION        defaults
1908: STORE_NAME           socketpair
1910: LOAD_NAME            __all__
1912: LOAD_METHOD          append
1934: LOAD_CONST           'socketpair'
1936: PRECALL              
1940: CALL                 
1950: POP_TOP              
1952: LOAD_CONST           'socketpair([family[, type[, proto]]]) -> (socket object, socket object)\nCreate a pair of socket objects from the sockets returned by the platform\nsocketpair() function.\nThe arguments are the same as for socket() except the default family is AF_UNIX\nif defined on the platform; otherwise, the default is AF_INET.\n'
1954: LOAD_NAME            socketpair
1956: STORE_ATTR           __doc__
1966: LOAD_NAME            EAGAIN
1968: LOAD_NAME            EWOULDBLOCK
1970: BUILD_SET            
1972: STORE_NAME           _blocking_errnos
1974: PUSH_NULL            
1976: LOAD_BUILD_CLASS     
1978: LOAD_CONST           <code object SocketIO at 0x00000240693D2890, file "socket.py", line 663>
1980: MAKE_FUNCTION        
1982: LOAD_CONST           'SocketIO'
1984: LOAD_NAME            io
1986: LOAD_ATTR            RawIOBase
1996: PRECALL              
2000: CALL                 
2010: STORE_NAME           SocketIO
2012: LOAD_CONST           ('',)
2014: LOAD_CONST           <code object getfqdn at 0x00000240691F5890, file "socket.py", line 780>
2016: MAKE_FUNCTION        defaults
2018: STORE_NAME           getfqdn
2020: PUSH_NULL            
2022: LOAD_NAME            object
2024: PRECALL              
2028: CALL                 
2038: STORE_NAME           _GLOBAL_DEFAULT_TIMEOUT
2040: LOAD_NAME            _GLOBAL_DEFAULT_TIMEOUT
2042: LOAD_CONST           None
2044: BUILD_TUPLE          
2046: LOAD_CONST           False
2048: LOAD_CONST           ('all_errors',)
2050: BUILD_CONST_KEY_MAP  
2052: LOAD_CONST           <code object create_connection at 0x0000024066347D50, file "socket.py", line 809>
2054: MAKE_FUNCTION        defaults, kwdefaults
2056: STORE_NAME           create_connection
2058: LOAD_CONST           <code object has_dualstack_ipv6 at 0x000002406931FC30, file "socket.py", line 860>
2060: MAKE_FUNCTION        
2062: STORE_NAME           has_dualstack_ipv6
2064: LOAD_NAME            AF_INET
2066: LOAD_CONST           None
2068: LOAD_CONST           False
2070: LOAD_CONST           False
2072: LOAD_CONST           ('family', 'backlog', 'reuse_port', 'dualstack_ipv6')
2074: BUILD_CONST_KEY_MAP  
2076: LOAD_CONST           <code object create_server at 0x0000024068D020D0, file "socket.py", line 876>
2078: MAKE_FUNCTION        kwdefaults
2080: STORE_NAME           create_server
2082: LOAD_CONST           (0, 0, 0, 0)
2084: LOAD_CONST           <code object getaddrinfo at 0x000002406942E740, file "socket.py", line 945>
2086: MAKE_FUNCTION        defaults
2088: STORE_NAME           getaddrinfo
2090: LOAD_CONST           None
2092: RETURN_VALUE         
