# Disassembly for socket.SocketIO.seekable
# From module file: socket

## co_consts:
('True if the SocketIO is open for seeking.\n        ', 'I/O operation on closed socket.')

## co_names:
('closed', 'ValueError', 'super', 'seekable')

## bytecode:

   0: COPY_FREE_VARS       
   2: RESUME               
   4: LOAD_FAST            self
   6: LOAD_ATTR            closed
  16: POP_JUMP_FORWARD_IF_FALSE to 48
  18: LOAD_GLOBAL          NULL + ValueError
  30: LOAD_CONST           'I/O operation on closed socket.'
  32: PRECALL              
  36: CALL                 
  46: RAISE_VARARGS        
  48: LOAD_GLOBAL          NULL + super
  60: PRECALL              
  64: CALL                 
  74: LOAD_METHOD          seekable
  96: PRECALL              
 100: CALL                 
 110: RETURN_VALUE         
