# Disassembly for socket.socket._decref_socketios
# From module file: socket

## co_consts:
(None, 0, 1)

## co_names:
('_io_refs', '_closed', 'close')

## bytecode:

   0: RESUME               
   2: LOAD_FAST            self
   4: LOAD_ATTR            _io_refs
  14: LOAD_CONST           0
  16: COMPARE_OP           >
  22: POP_JUMP_FORWARD_IF_FALSE to 56
  24: LOAD_FAST            self
  26: COPY                 
  28: LOAD_ATTR            _io_refs
  38: LOAD_CONST           1
  40: BINARY_OP            -=
  44: SWAP                 
  46: STORE_ATTR           _io_refs
  56: LOAD_FAST            self
  58: LOAD_ATTR            _closed
  68: POP_JUMP_FORWARD_IF_FALSE to 114
  70: LOAD_FAST            self
  72: LOAD_METHOD          close
  94: PRECALL              
  98: CALL                 
 108: POP_TOP              
 110: LOAD_CONST           None
 112: RETURN_VALUE         
 114: LOAD_CONST           None
 116: RETURN_VALUE         
