# Disassembly for socket.socket.dup
# From module file: socket

## co_consts:
('dup() -> socket object\n\n        Duplicate the socket. Return a new socket object connected to the same\n        system resource. The new socket is non-inheritable.\n        ', ('fileno',))

## co_names:
('dup', 'fileno', '__class__', 'family', 'type', 'proto', 'settimeout', 'gettimeout')

## bytecode:

   0: RESUME               
   2: LOAD_GLOBAL          NULL + dup
  14: LOAD_FAST            self
  16: LOAD_METHOD          fileno
  38: PRECALL              
  42: CALL                 
  52: PRECALL              
  56: CALL                 
  66: STORE_FAST           fd
  68: LOAD_FAST            self
  70: LOAD_METHOD          __class__
  92: LOAD_FAST            self
  94: LOAD_ATTR            family
 104: LOAD_FAST            self
 106: LOAD_ATTR            type
 116: LOAD_FAST            self
 118: LOAD_ATTR            proto
 128: LOAD_FAST            fd
 130: KW_NAMES             
 132: PRECALL              
 136: CALL                 
 146: STORE_FAST           sock
 148: LOAD_FAST            sock
 150: LOAD_METHOD          settimeout
 172: LOAD_FAST            self
 174: LOAD_METHOD          gettimeout
 196: PRECALL              
 200: CALL                 
 210: PRECALL              
 214: CALL                 
 224: POP_TOP              
 226: LOAD_FAST            sock
 228: RETURN_VALUE         
