# Disassembly for socket.fromshare
# From module file: socket

## co_consts:
(' fromshare(info) -> socket object\n\n        Create a socket object from the bytes object returned by\n        socket.share(pid).\n        ', 0)

## co_names:
('socket',)

## bytecode:

   0: RESUME               
   2: LOAD_GLOBAL          NULL + socket
  14: LOAD_CONST           0
  16: LOAD_CONST           0
  18: LOAD_CONST           0
  20: LOAD_FAST            info
  22: PRECALL              
  26: CALL                 
  36: RETURN_VALUE         
