# Disassembly for http.LWPCookieJar.save
# From module file: http.cookiejar

## co_consts:
(None, 384, 'w', '#LWP-Cookies-2.0\n')

## co_names:
('filename', 'ValueError', 'MISSING_FILENAME_TEXT', 'os', 'fdopen', 'open', 'O_CREAT', 'O_WRONLY', 'O_TRUNC', 'write', 'as_lwp_str')

## bytecode:

   0: RESUME               
   2: LOAD_FAST            filename
   4: POP_JUMP_FORWARD_IF_NOT_NONE to 76
   6: LOAD_FAST            self
   8: LOAD_ATTR            filename
  18: POP_JUMP_FORWARD_IF_NONE to 36
  20: LOAD_FAST            self
  22: LOAD_ATTR            filename
  32: STORE_FAST           filename
  34: JUMP_FORWARD         to 76
  36: LOAD_GLOBAL          NULL + ValueError
  48: LOAD_GLOBAL          MISSING_FILENAME_TEXT
  60: PRECALL              
  64: CALL                 
  74: RAISE_VARARGS        
  76: LOAD_GLOBAL          NULL + os
  88: LOAD_ATTR            fdopen
  98: LOAD_GLOBAL          NULL + os
 110: LOAD_ATTR            open
 120: LOAD_FAST            filename
 122: LOAD_GLOBAL          os
 134: LOAD_ATTR            O_CREAT
 144: LOAD_GLOBAL          os
 156: LOAD_ATTR            O_WRONLY
 166: BINARY_OP            |
 170: LOAD_GLOBAL          os
 182: LOAD_ATTR            O_TRUNC
 192: BINARY_OP            |
 196: LOAD_CONST           384
 198: PRECALL              
 202: CALL                 
 212: LOAD_CONST           'w'
 214: PRECALL              
 218: CALL                 
 228: BEFORE_WITH          
 230: STORE_FAST           f
 232: LOAD_FAST            f
 234: LOAD_METHOD          write
 256: LOAD_CONST           '#LWP-Cookies-2.0\n'
 258: PRECALL              
 262: CALL                 
 272: POP_TOP              
 274: LOAD_FAST            f
 276: LOAD_METHOD          write
 298: LOAD_FAST            self
 300: LOAD_METHOD          as_lwp_str
 322: LOAD_FAST            ignore_discard
 324: LOAD_FAST            ignore_expires
 326: PRECALL              
 330: CALL                 
 340: PRECALL              
 344: CALL                 
 354: POP_TOP              
 356: LOAD_CONST           None
 358: LOAD_CONST           None
 360: LOAD_CONST           None
 362: PRECALL              
 366: CALL                 
 376: POP_TOP              
 378: LOAD_CONST           None
 380: RETURN_VALUE         
 382: PUSH_EXC_INFO        
 384: WITH_EXCEPT_START    
 386: POP_JUMP_FORWARD_IF_TRUE to 396
 388: RERAISE              
 390: COPY                 
 392: POP_EXCEPT           
 394: RERAISE              
 396: POP_TOP              
 398: POP_EXCEPT           
 400: POP_TOP              
 402: POP_TOP              
 404: LOAD_CONST           None
 406: RETURN_VALUE         
