# Disassembly for http.lwp_cookie_str
# From module file: http.cookiejar

## co_consts:
('Return string representation of Cookie in the LWP cookie file format.\n\n    Actually, the format is extended a bit -- see module docstring.\n\n    ', 'path', 'domain', None, 'port', ('path_spec', None), ('port_spec', None), ('domain_dot', None), ('secure', None), 'expires', ('discard', None), 'comment', 'commenturl', 'version')

## co_names:
('name', 'value', 'path', 'domain', 'port', 'append', 'path_specified', 'port_specified', 'domain_initial_dot', 'secure', 'expires', 'time2isoz', 'float', 'discard', 'comment', 'comment_url', 'sorted', '_rest', 'keys', 'str', 'version', 'join_header_words')

## bytecode:

   0: RESUME               
   2: LOAD_FAST            cookie
   4: LOAD_ATTR            name
  14: LOAD_FAST            cookie
  16: LOAD_ATTR            value
  26: BUILD_TUPLE          
  28: LOAD_CONST           'path'
  30: LOAD_FAST            cookie
  32: LOAD_ATTR            path
  42: BUILD_TUPLE          
  44: LOAD_CONST           'domain'
  46: LOAD_FAST            cookie
  48: LOAD_ATTR            domain
  58: BUILD_TUPLE          
  60: BUILD_LIST           
  62: STORE_FAST           h
  64: LOAD_FAST            cookie
  66: LOAD_ATTR            port
  76: POP_JUMP_FORWARD_IF_NONE to 134
  78: LOAD_FAST            h
  80: LOAD_METHOD          append
 102: LOAD_CONST           'port'
 104: LOAD_FAST            cookie
 106: LOAD_ATTR            port
 116: BUILD_TUPLE          
 118: PRECALL              
 122: CALL                 
 132: POP_TOP              
 134: LOAD_FAST            cookie
 136: LOAD_ATTR            path_specified
 146: POP_JUMP_FORWARD_IF_FALSE to 190
 148: LOAD_FAST            h
 150: LOAD_METHOD          append
 172: LOAD_CONST           ('path_spec', None)
 174: PRECALL              
 178: CALL                 
 188: POP_TOP              
 190: LOAD_FAST            cookie
 192: LOAD_ATTR            port_specified
 202: POP_JUMP_FORWARD_IF_FALSE to 246
 204: LOAD_FAST            h
 206: LOAD_METHOD          append
 228: LOAD_CONST           ('port_spec', None)
 230: PRECALL              
 234: CALL                 
 244: POP_TOP              
 246: LOAD_FAST            cookie
 248: LOAD_ATTR            domain_initial_dot
 258: POP_JUMP_FORWARD_IF_FALSE to 302
 260: LOAD_FAST            h
 262: LOAD_METHOD          append
 284: LOAD_CONST           ('domain_dot', None)
 286: PRECALL              
 290: CALL                 
 300: POP_TOP              
 302: LOAD_FAST            cookie
 304: LOAD_ATTR            secure
 314: POP_JUMP_FORWARD_IF_FALSE to 358
 316: LOAD_FAST            h
 318: LOAD_METHOD          append
 340: LOAD_CONST           ('secure', None)
 342: PRECALL              
 346: CALL                 
 356: POP_TOP              
 358: LOAD_FAST            cookie
 360: LOAD_ATTR            expires
 370: POP_JUMP_FORWARD_IF_FALSE to 480
 372: LOAD_FAST            h
 374: LOAD_METHOD          append
 396: LOAD_CONST           'expires'
 398: LOAD_GLOBAL          NULL + time2isoz
 410: LOAD_GLOBAL          NULL + float
 422: LOAD_FAST            cookie
 424: LOAD_ATTR            expires
 434: PRECALL              
 438: CALL                 
 448: PRECALL              
 452: CALL                 
 462: BUILD_TUPLE          
 464: PRECALL              
 468: CALL                 
 478: POP_TOP              
 480: LOAD_FAST            cookie
 482: LOAD_ATTR            discard
 492: POP_JUMP_FORWARD_IF_FALSE to 536
 494: LOAD_FAST            h
 496: LOAD_METHOD          append
 518: LOAD_CONST           ('discard', None)
 520: PRECALL              
 524: CALL                 
 534: POP_TOP              
 536: LOAD_FAST            cookie
 538: LOAD_ATTR            comment
 548: POP_JUMP_FORWARD_IF_FALSE to 606
 550: LOAD_FAST            h
 552: LOAD_METHOD          append
 574: LOAD_CONST           'comment'
 576: LOAD_FAST            cookie
 578: LOAD_ATTR            comment
 588: BUILD_TUPLE          
 590: PRECALL              
 594: CALL                 
 604: POP_TOP              
 606: LOAD_FAST            cookie
 608: LOAD_ATTR            comment_url
 618: POP_JUMP_FORWARD_IF_FALSE to 676
 620: LOAD_FAST            h
 622: LOAD_METHOD          append
 644: LOAD_CONST           'commenturl'
 646: LOAD_FAST            cookie
 648: LOAD_ATTR            comment_url
 658: BUILD_TUPLE          
 660: PRECALL              
 664: CALL                 
 674: POP_TOP              
 676: LOAD_GLOBAL          NULL + sorted
 688: LOAD_FAST            cookie
 690: LOAD_ATTR            _rest
 700: LOAD_METHOD          keys
 722: PRECALL              
 726: CALL                 
 736: PRECALL              
 740: CALL                 
 750: STORE_FAST           keys
 752: LOAD_FAST            keys
 754: GET_ITER             
 756: FOR_ITER             to 856
 758: STORE_FAST           k
 760: LOAD_FAST            h
 762: LOAD_METHOD          append
 784: LOAD_FAST            k
 786: LOAD_GLOBAL          NULL + str
 798: LOAD_FAST            cookie
 800: LOAD_ATTR            _rest
 810: LOAD_FAST            k
 812: BINARY_SUBSCR        
 822: PRECALL              
 826: CALL                 
 836: BUILD_TUPLE          
 838: PRECALL              
 842: CALL                 
 852: POP_TOP              
 854: JUMP_BACKWARD        to 756
 856: LOAD_FAST            h
 858: LOAD_METHOD          append
 880: LOAD_CONST           'version'
 882: LOAD_GLOBAL          NULL + str
 894: LOAD_FAST            cookie
 896: LOAD_ATTR            version
 906: PRECALL              
 910: CALL                 
 920: BUILD_TUPLE          
 922: PRECALL              
 926: CALL                 
 936: POP_TOP              
 938: LOAD_GLOBAL          NULL + join_header_words
 950: LOAD_FAST            h
 952: BUILD_LIST           
 954: PRECALL              
 958: CALL                 
 968: RETURN_VALUE         
