# Disassembly for http.CookieJar.__len__
# From module file: http.cookiejar

## co_consts:
('Return number of contained cookies.', 0, 1)

## co_names:
()

## bytecode:

   0: RESUME               
   2: LOAD_CONST           0
   4: STORE_FAST           i
   6: LOAD_FAST            self
   8: GET_ITER             
  10: FOR_ITER             to 26
  12: STORE_FAST           cookie
  14: LOAD_FAST            i
  16: LOAD_CONST           1
  18: BINARY_OP            +
  22: STORE_FAST           i
  24: JUMP_BACKWARD        to 10
  26: LOAD_FAST            i
  28: RETURN_VALUE         
