# Disassembly for http.is_HDN
# From module file: http.cookiejar

## co_consts:
('Return True if text is a host domain name.', False, '', 0, '.', -1, True)

## co_names:
('IPV4_RE', 'search')

## bytecode:

   0: RESUME               
   2: LOAD_GLOBAL          IPV4_RE
  14: LOAD_METHOD          search
  36: LOAD_FAST            text
  38: PRECALL              
  42: CALL                 
  52: POP_JUMP_FORWARD_IF_FALSE to 58
  54: LOAD_CONST           False
  56: RETURN_VALUE         
  58: LOAD_FAST            text
  60: LOAD_CONST           ''
  62: COMPARE_OP           ==
  68: POP_JUMP_FORWARD_IF_FALSE to 74
  70: LOAD_CONST           False
  72: RETURN_VALUE         
  74: LOAD_FAST            text
  76: LOAD_CONST           0
  78: BINARY_SUBSCR        
  88: LOAD_CONST           '.'
  90: COMPARE_OP           ==
  96: POP_JUMP_FORWARD_IF_TRUE to 122
  98: LOAD_FAST            text
 100: LOAD_CONST           -1
 102: BINARY_SUBSCR        
 112: LOAD_CONST           '.'
 114: COMPARE_OP           ==
 120: POP_JUMP_FORWARD_IF_FALSE to 126
 122: LOAD_CONST           False
 124: RETURN_VALUE         
 126: LOAD_CONST           True
 128: RETURN_VALUE         
