# Disassembly for http.iso2time
# From module file: http.cookiejar

## co_consts:
('\n    As for http2time, but parses the ISO 8601 formats:\n\n    1994-02-03 14:15:29 -0100    -- ISO 8601 format\n    1994-02-03 14:15:29          -- zone is optional\n    1994-02-03                   -- only date\n    1994-02-03T14:15:29          -- Use T as separator\n    19940203T141529Z             -- ISO 8601 compact format\n    19940203                     -- only date\n\n    ', None, 7)

## co_names:
('lstrip', 'ISO_DATE_RE', 'search', 'groups', '_str2time')

## bytecode:

   0: RESUME               
   2: LOAD_FAST            text
   4: LOAD_METHOD          lstrip
  26: PRECALL              
  30: CALL                 
  40: STORE_FAST           text
  42: LOAD_CONST           None
  44: BUILD_LIST           
  46: LOAD_CONST           7
  48: BINARY_OP            *
  52: UNPACK_SEQUENCE      
  56: STORE_FAST           day
  58: STORE_FAST           mon
  60: STORE_FAST           yr
  62: STORE_FAST           hr
  64: STORE_FAST           min
  66: STORE_FAST           sec
  68: STORE_FAST           tz
  70: LOAD_GLOBAL          ISO_DATE_RE
  82: LOAD_METHOD          search
 104: LOAD_FAST            text
 106: PRECALL              
 110: CALL                 
 120: STORE_FAST           m
 122: LOAD_FAST            m
 124: POP_JUMP_FORWARD_IF_NONE to 186
 126: LOAD_FAST            m
 128: LOAD_METHOD          groups
 150: PRECALL              
 154: CALL                 
 164: UNPACK_SEQUENCE      
 168: STORE_FAST           yr
 170: STORE_FAST           mon
 172: STORE_FAST           day
 174: STORE_FAST           hr
 176: STORE_FAST           min
 178: STORE_FAST           sec
 180: STORE_FAST           tz
 182: STORE_FAST           _
 184: JUMP_FORWARD         to 190
 186: LOAD_CONST           None
 188: RETURN_VALUE         
 190: LOAD_GLOBAL          NULL + _str2time
 202: LOAD_FAST            day
 204: LOAD_FAST            mon
 206: LOAD_FAST            yr
 208: LOAD_FAST            hr
 210: LOAD_FAST            min
 212: LOAD_FAST            sec
 214: LOAD_FAST            tz
 216: PRECALL              
 220: CALL                 
 230: RETURN_VALUE         
