# Disassembly for http.Cookie.__str__
# From module file: http.cookiejar

## co_consts:
(None, '', ':', '=', '<Cookie ', ' for ', '>')

## co_names:
('port', 'domain', 'path', 'value', 'name')

## bytecode:

   0: RESUME               
   2: LOAD_FAST            self
   4: LOAD_ATTR            port
  14: POP_JUMP_FORWARD_IF_NOT_NONE to 22
  16: LOAD_CONST           ''
  18: STORE_FAST           p
  20: JUMP_FORWARD         to 42
  22: LOAD_CONST           ':'
  24: LOAD_FAST            self
  26: LOAD_ATTR            port
  36: BINARY_OP            +
  40: STORE_FAST           p
  42: LOAD_FAST            self
  44: LOAD_ATTR            domain
  54: LOAD_FAST            p
  56: BINARY_OP            +
  60: LOAD_FAST            self
  62: LOAD_ATTR            path
  72: BINARY_OP            +
  76: STORE_FAST           limit
  78: LOAD_FAST            self
  80: LOAD_ATTR            value
  90: POP_JUMP_FORWARD_IF_NONE to 128
  92: LOAD_FAST            self
  94: LOAD_ATTR            name
 104: FORMAT_VALUE         str
 106: LOAD_CONST           '='
 108: LOAD_FAST            self
 110: LOAD_ATTR            value
 120: FORMAT_VALUE         str
 122: BUILD_STRING         
 124: STORE_FAST           namevalue
 126: JUMP_FORWARD         to 142
 128: LOAD_FAST            self
 130: LOAD_ATTR            name
 140: STORE_FAST           namevalue
 142: LOAD_CONST           '<Cookie '
 144: LOAD_FAST            namevalue
 146: FORMAT_VALUE         str
 148: LOAD_CONST           ' for '
 150: LOAD_FAST            limit
 152: FORMAT_VALUE         str
 154: LOAD_CONST           '>'
 156: BUILD_STRING         
 158: RETURN_VALUE         
