# Disassembly for http.CookieJar._cookie_from_cookie_tuple
# From module file: http.cookiejar

## co_consts:
(None, 'domain', 'path', 'port', 'expires', 'version', 'secure', False, 'discard', 'comment', 'commenturl', '', True, '/', -1, 0, 1, '.', '\\s+', "Expiring cookie, domain='%s', path='%s', name='%s'")

## co_names:
('get', 'Absent', 'int', 'ValueError', 'escape_path', 'request_path', 'rfind', 'len', 'bool', 'startswith', 'eff_request_host', 'request_port', 're', 'sub', '_now', 'clear', 'KeyError', '_debug', 'Cookie')

## bytecode:

   0: RESUME               
   2: LOAD_FAST            tup
   4: UNPACK_SEQUENCE      
   8: STORE_FAST           name
  10: STORE_FAST           value
  12: STORE_FAST           standard
  14: STORE_FAST           rest
  16: LOAD_FAST            standard
  18: LOAD_METHOD          get
  40: LOAD_CONST           'domain'
  42: LOAD_GLOBAL          Absent
  54: PRECALL              
  58: CALL                 
  68: STORE_FAST           domain
  70: LOAD_FAST            standard
  72: LOAD_METHOD          get
  94: LOAD_CONST           'path'
  96: LOAD_GLOBAL          Absent
 108: PRECALL              
 112: CALL                 
 122: STORE_FAST           path
 124: LOAD_FAST            standard
 126: LOAD_METHOD          get
 148: LOAD_CONST           'port'
 150: LOAD_GLOBAL          Absent
 162: PRECALL              
 166: CALL                 
 176: STORE_FAST           port
 178: LOAD_FAST            standard
 180: LOAD_METHOD          get
 202: LOAD_CONST           'expires'
 204: LOAD_GLOBAL          Absent
 216: PRECALL              
 220: CALL                 
 230: STORE_FAST           expires
 232: LOAD_FAST            standard
 234: LOAD_METHOD          get
 256: LOAD_CONST           'version'
 258: LOAD_CONST           None
 260: PRECALL              
 264: CALL                 
 274: STORE_FAST           version
 276: LOAD_FAST            version
 278: POP_JUMP_FORWARD_IF_NONE to 348
 280: NOP                  
 282: LOAD_GLOBAL          NULL + int
 294: LOAD_FAST            version
 296: PRECALL              
 300: CALL                 
 310: STORE_FAST           version
 312: JUMP_FORWARD         to 348
 314: PUSH_EXC_INFO        
 316: LOAD_GLOBAL          ValueError
 328: CHECK_EXC_MATCH      
 330: POP_JUMP_FORWARD_IF_FALSE to 340
 332: POP_TOP              
 334: POP_EXCEPT           
 336: LOAD_CONST           None
 338: RETURN_VALUE         
 340: RERAISE              
 342: COPY                 
 344: POP_EXCEPT           
 346: RERAISE              
 348: LOAD_FAST            standard
 350: LOAD_METHOD          get
 372: LOAD_CONST           'secure'
 374: LOAD_CONST           False
 376: PRECALL              
 380: CALL                 
 390: STORE_FAST           secure
 392: LOAD_FAST            standard
 394: LOAD_METHOD          get
 416: LOAD_CONST           'discard'
 418: LOAD_CONST           False
 420: PRECALL              
 424: CALL                 
 434: STORE_FAST           discard
 436: LOAD_FAST            standard
 438: LOAD_METHOD          get
 460: LOAD_CONST           'comment'
 462: LOAD_CONST           None
 464: PRECALL              
 468: CALL                 
 478: STORE_FAST           comment
 480: LOAD_FAST            standard
 482: LOAD_METHOD          get
 504: LOAD_CONST           'commenturl'
 506: LOAD_CONST           None
 508: PRECALL              
 512: CALL                 
 522: STORE_FAST           comment_url
 524: LOAD_FAST            path
 526: LOAD_GLOBAL          Absent
 538: IS_OP                
 540: POP_JUMP_FORWARD_IF_FALSE to 590
 542: LOAD_FAST            path
 544: LOAD_CONST           ''
 546: COMPARE_OP           !=
 552: POP_JUMP_FORWARD_IF_FALSE to 590
 554: LOAD_CONST           True
 556: STORE_FAST           path_specified
 558: LOAD_GLOBAL          NULL + escape_path
 570: LOAD_FAST            path
 572: PRECALL              
 576: CALL                 
 586: STORE_FAST           path
 588: JUMP_FORWARD         to 780
 590: LOAD_CONST           False
 592: STORE_FAST           path_specified
 594: LOAD_GLOBAL          NULL + request_path
 606: LOAD_FAST            request
 608: PRECALL              
 612: CALL                 
 622: STORE_FAST           path
 624: LOAD_FAST            path
 626: LOAD_METHOD          rfind
 648: LOAD_CONST           '/'
 650: PRECALL              
 654: CALL                 
 664: STORE_FAST           i
 666: LOAD_FAST            i
 668: LOAD_CONST           -1
 670: COMPARE_OP           !=
 676: POP_JUMP_FORWARD_IF_FALSE to 738
 678: LOAD_FAST            version
 680: LOAD_CONST           0
 682: COMPARE_OP           ==
 688: POP_JUMP_FORWARD_IF_FALSE to 712
 690: LOAD_FAST            path
 692: LOAD_CONST           None
 694: LOAD_FAST            i
 696: BUILD_SLICE          
 698: BINARY_SUBSCR        
 708: STORE_FAST           path
 710: JUMP_FORWARD         to 738
 712: LOAD_FAST            path
 714: LOAD_CONST           None
 716: LOAD_FAST            i
 718: LOAD_CONST           1
 720: BINARY_OP            +
 724: BUILD_SLICE          
 726: BINARY_SUBSCR        
 736: STORE_FAST           path
 738: LOAD_GLOBAL          NULL + len
 750: LOAD_FAST            path
 752: PRECALL              
 756: CALL                 
 766: LOAD_CONST           0
 768: COMPARE_OP           ==
 774: POP_JUMP_FORWARD_IF_FALSE to 780
 776: LOAD_CONST           '/'
 778: STORE_FAST           path
 780: LOAD_FAST            domain
 782: LOAD_GLOBAL          Absent
 794: IS_OP                
 796: STORE_FAST           domain_specified
 798: LOAD_CONST           False
 800: STORE_FAST           domain_initial_dot
 802: LOAD_FAST            domain_specified
 804: POP_JUMP_FORWARD_IF_FALSE to 874
 806: LOAD_GLOBAL          NULL + bool
 818: LOAD_FAST            domain
 820: LOAD_METHOD          startswith
 842: LOAD_CONST           '.'
 844: PRECALL              
 848: CALL                 
 858: PRECALL              
 862: CALL                 
 872: STORE_FAST           domain_initial_dot
 874: LOAD_FAST            domain
 876: LOAD_GLOBAL          Absent
 888: IS_OP                
 890: POP_JUMP_FORWARD_IF_FALSE to 934
 892: LOAD_GLOBAL          NULL + eff_request_host
 904: LOAD_FAST            request
 906: PRECALL              
 910: CALL                 
 920: UNPACK_SEQUENCE      
 924: STORE_FAST           req_host
 926: STORE_FAST           erhn
 928: LOAD_FAST            erhn
 930: STORE_FAST           domain
 932: JUMP_FORWARD         to 986
 934: LOAD_FAST            domain
 936: LOAD_METHOD          startswith
 958: LOAD_CONST           '.'
 960: PRECALL              
 964: CALL                 
 974: POP_JUMP_FORWARD_IF_TRUE to 986
 976: LOAD_CONST           '.'
 978: LOAD_FAST            domain
 980: BINARY_OP            +
 984: STORE_FAST           domain
 986: LOAD_CONST           False
 988: STORE_FAST           port_specified
 990: LOAD_FAST            port
 992: LOAD_GLOBAL          Absent
1004: IS_OP                
1006: POP_JUMP_FORWARD_IF_FALSE to 1094
1008: LOAD_FAST            port
1010: POP_JUMP_FORWARD_IF_NOT_NONE to 1044
1012: LOAD_GLOBAL          NULL + request_port
1024: LOAD_FAST            request
1026: PRECALL              
1030: CALL                 
1040: STORE_FAST           port
1042: JUMP_FORWARD         to 1098
1044: LOAD_CONST           True
1046: STORE_FAST           port_specified
1048: LOAD_GLOBAL          NULL + re
1060: LOAD_ATTR            sub
1070: LOAD_CONST           '\\s+'
1072: LOAD_CONST           ''
1074: LOAD_FAST            port
1076: PRECALL              
1080: CALL                 
1090: STORE_FAST           port
1092: JUMP_FORWARD         to 1098
1094: LOAD_CONST           None
1096: STORE_FAST           port
1098: LOAD_FAST            expires
1100: LOAD_GLOBAL          Absent
1112: IS_OP                
1114: POP_JUMP_FORWARD_IF_FALSE to 1126
1116: LOAD_CONST           None
1118: STORE_FAST           expires
1120: LOAD_CONST           True
1122: STORE_FAST           discard
1124: JUMP_FORWARD         to 1270
1126: LOAD_FAST            expires
1128: LOAD_FAST            self
1130: LOAD_ATTR            _now
1140: COMPARE_OP           <=
1146: POP_JUMP_FORWARD_IF_FALSE to 1270
1148: NOP                  
1150: LOAD_FAST            self
1152: LOAD_METHOD          clear
1174: LOAD_FAST            domain
1176: LOAD_FAST            path
1178: LOAD_FAST            name
1180: PRECALL              
1184: CALL                 
1194: POP_TOP              
1196: JUMP_FORWARD         to 1230
1198: PUSH_EXC_INFO        
1200: LOAD_GLOBAL          KeyError
1212: CHECK_EXC_MATCH      
1214: POP_JUMP_FORWARD_IF_FALSE to 1222
1216: POP_TOP              
1218: POP_EXCEPT           
1220: JUMP_FORWARD         to 1230
1222: RERAISE              
1224: COPY                 
1226: POP_EXCEPT           
1228: RERAISE              
1230: LOAD_GLOBAL          NULL + _debug
1242: LOAD_CONST           "Expiring cookie, domain='%s', path='%s', name='%s'"
1244: LOAD_FAST            domain
1246: LOAD_FAST            path
1248: LOAD_FAST            name
1250: PRECALL              
1254: CALL                 
1264: POP_TOP              
1266: LOAD_CONST           None
1268: RETURN_VALUE         
1270: LOAD_GLOBAL          NULL + Cookie
1282: LOAD_FAST            version
1284: LOAD_FAST            name
1286: LOAD_FAST            value
1288: LOAD_FAST            port
1290: LOAD_FAST            port_specified
1292: LOAD_FAST            domain
1294: LOAD_FAST            domain_specified
1296: LOAD_FAST            domain_initial_dot
1298: LOAD_FAST            path
1300: LOAD_FAST            path_specified
1302: LOAD_FAST            secure
1304: LOAD_FAST            expires
1306: LOAD_FAST            discard
1308: LOAD_FAST            comment
1310: LOAD_FAST            comment_url
1312: LOAD_FAST            rest
1314: PRECALL              
1318: CALL                 
1328: RETURN_VALUE         
