# Disassembly for http.HTTPResponse._peek_chunked
# From module file: http.client

## co_consts:
(None, b'')

## co_names:
('_get_chunk_left', 'IncompleteRead', 'fp', 'peek')

## bytecode:

   0: RESUME               
   2: NOP                  
   4: LOAD_FAST            self
   6: LOAD_METHOD          _get_chunk_left
  28: PRECALL              
  32: CALL                 
  42: STORE_FAST           chunk_left
  44: JUMP_FORWARD         to 80
  46: PUSH_EXC_INFO        
  48: LOAD_GLOBAL          IncompleteRead
  60: CHECK_EXC_MATCH      
  62: POP_JUMP_FORWARD_IF_FALSE to 72
  64: POP_TOP              
  66: POP_EXCEPT           
  68: LOAD_CONST           b''
  70: RETURN_VALUE         
  72: RERAISE              
  74: COPY                 
  76: POP_EXCEPT           
  78: RERAISE              
  80: LOAD_FAST            chunk_left
  82: POP_JUMP_FORWARD_IF_NOT_NONE to 88
  84: LOAD_CONST           b''
  86: RETURN_VALUE         
  88: LOAD_FAST            self
  90: LOAD_ATTR            fp
 100: LOAD_METHOD          peek
 122: LOAD_FAST            chunk_left
 124: PRECALL              
 128: CALL                 
 138: LOAD_CONST           None
 140: LOAD_FAST            chunk_left
 142: BUILD_SLICE          
 144: BINARY_SUBSCR        
 154: RETURN_VALUE         
