# Disassembly for http.HTTPConnection._output
# From module file: http.client

## co_consts:
('Add a line of output to the current request buffer.\n\n        Assumes that the line does *not* end with \\r\\n.\n        ', None)

## co_names:
('_buffer', 'append')

## bytecode:

   0: RESUME               
   2: LOAD_FAST            self
   4: LOAD_ATTR            _buffer
  14: LOAD_METHOD          append
  36: LOAD_FAST            s
  38: PRECALL              
  42: CALL                 
  52: POP_TOP              
  54: LOAD_CONST           None
  56: RETURN_VALUE         
