# Disassembly for http.DefaultCookiePolicy.return_ok_secure
# From module file: http.cookiejar

## co_consts:
(None, '   secure cookie with non-secure request', False, True)

## co_names:
('secure', 'type', 'secure_protocols', '_debug')

## bytecode:

   0: RESUME               
   2: LOAD_FAST            cookie
   4: LOAD_ATTR            secure
  14: POP_JUMP_FORWARD_IF_FALSE to 78
  16: LOAD_FAST            request
  18: LOAD_ATTR            type
  28: LOAD_FAST            self
  30: LOAD_ATTR            secure_protocols
  40: CONTAINS_OP          
  42: POP_JUMP_FORWARD_IF_FALSE to 78
  44: LOAD_GLOBAL          NULL + _debug
  56: LOAD_CONST           '   secure cookie with non-secure request'
  58: PRECALL              
  62: CALL                 
  72: POP_TOP              
  74: LOAD_CONST           False
  76: RETURN_VALUE         
  78: LOAD_CONST           True
  80: RETURN_VALUE         
