# Disassembly for http.DefaultCookiePolicy.set_ok_path
# From module file: http.cookiejar

## co_consts:
(None, 0, '   path attribute %s is not a prefix of request path %s', False, True)

## co_names:
('path_specified', 'request_path', 'version', 'strict_ns_set_path', 'path_return_ok', 'path', '_debug')

## bytecode:

   0: RESUME               
   2: LOAD_FAST            cookie
   4: LOAD_ATTR            path_specified
  14: POP_JUMP_FORWARD_IF_FALSE to 206
  16: LOAD_GLOBAL          NULL + request_path
  28: LOAD_FAST            request
  30: PRECALL              
  34: CALL                 
  44: STORE_FAST           req_path
  46: LOAD_FAST            cookie
  48: LOAD_ATTR            version
  58: LOAD_CONST           0
  60: COMPARE_OP           >
  66: POP_JUMP_FORWARD_IF_TRUE to 104
  68: LOAD_FAST            cookie
  70: LOAD_ATTR            version
  80: LOAD_CONST           0
  82: COMPARE_OP           ==
  88: POP_JUMP_FORWARD_IF_FALSE to 206
  90: LOAD_FAST            self
  92: LOAD_ATTR            strict_ns_set_path
 102: POP_JUMP_FORWARD_IF_FALSE to 206
 104: LOAD_FAST            self
 106: LOAD_METHOD          path_return_ok
 128: LOAD_FAST            cookie
 130: LOAD_ATTR            path
 140: LOAD_FAST            request
 142: PRECALL              
 146: CALL                 
 156: POP_JUMP_FORWARD_IF_TRUE to 206
 158: LOAD_GLOBAL          NULL + _debug
 170: LOAD_CONST           '   path attribute %s is not a prefix of request path %s'
 172: LOAD_FAST            cookie
 174: LOAD_ATTR            path
 184: LOAD_FAST            req_path
 186: PRECALL              
 190: CALL                 
 200: POP_TOP              
 202: LOAD_CONST           False
 204: RETURN_VALUE         
 206: LOAD_CONST           True
 208: RETURN_VALUE         
