# Disassembly for http.DefaultCookiePolicy.is_not_allowed
# From module file: http.cookiejar

## co_consts:
(None, False, True)

## co_names:
('_allowed_domains', 'user_domain_match')

## bytecode:

   0: RESUME               
   2: LOAD_FAST            self
   4: LOAD_ATTR            _allowed_domains
  14: POP_JUMP_FORWARD_IF_NOT_NONE to 20
  16: LOAD_CONST           False
  18: RETURN_VALUE         
  20: LOAD_FAST            self
  22: LOAD_ATTR            _allowed_domains
  32: GET_ITER             
  34: FOR_ITER             to 78
  36: STORE_FAST           allowed_domain
  38: LOAD_GLOBAL          NULL + user_domain_match
  50: LOAD_FAST            domain
  52: LOAD_FAST            allowed_domain
  54: PRECALL              
  58: CALL                 
  68: POP_JUMP_FORWARD_IF_FALSE to 76
  70: POP_TOP              
  72: LOAD_CONST           False
  74: RETURN_VALUE         
  76: JUMP_BACKWARD        to 34
  78: LOAD_CONST           True
  80: RETURN_VALUE         
