# Disassembly for http.HTTPResponse._safe_read
# From module file: http.client

## co_consts:
('Read the number of bytes requested.\n\n        This function should be used when <amt> bytes "should" be present for\n        reading. If the bytes are truly not available (due to EOF), then the\n        IncompleteRead exception can be used to detect the problem.\n        ',)

## co_names:
('fp', 'read', 'len', 'IncompleteRead')

## bytecode:

   0: RESUME               
   2: LOAD_FAST            self
   4: LOAD_ATTR            fp
  14: LOAD_METHOD          read
  36: LOAD_FAST            amt
  38: PRECALL              
  42: CALL                 
  52: STORE_FAST           data
  54: LOAD_GLOBAL          NULL + len
  66: LOAD_FAST            data
  68: PRECALL              
  72: CALL                 
  82: LOAD_FAST            amt
  84: COMPARE_OP           <
  90: POP_JUMP_FORWARD_IF_FALSE to 156
  92: LOAD_GLOBAL          NULL + IncompleteRead
 104: LOAD_FAST            data
 106: LOAD_FAST            amt
 108: LOAD_GLOBAL          NULL + len
 120: LOAD_FAST            data
 122: PRECALL              
 126: CALL                 
 136: BINARY_OP            -
 140: PRECALL              
 144: CALL                 
 154: RAISE_VARARGS        
 156: LOAD_FAST            data
 158: RETURN_VALUE         
