# Disassembly for http.IncompleteRead.__repr__
# From module file: http.client

## co_consts:
(None, ', %i more expected', '', '%s(%i bytes read%s)')

## co_names:
('expected', '__class__', '__name__', 'len', 'partial')

## bytecode:

   0: RESUME               
   2: LOAD_FAST            self
   4: LOAD_ATTR            expected
  14: POP_JUMP_FORWARD_IF_NONE to 38
  16: LOAD_CONST           ', %i more expected'
  18: LOAD_FAST            self
  20: LOAD_ATTR            expected
  30: BINARY_OP            %
  34: STORE_FAST           e
  36: JUMP_FORWARD         to 42
  38: LOAD_CONST           ''
  40: STORE_FAST           e
  42: LOAD_CONST           '%s(%i bytes read%s)'
  44: LOAD_FAST            self
  46: LOAD_ATTR            __class__
  56: LOAD_ATTR            __name__
  66: LOAD_GLOBAL          NULL + len
  78: LOAD_FAST            self
  80: LOAD_ATTR            partial
  90: PRECALL              
  94: CALL                 
 104: LOAD_FAST            e
 106: BUILD_TUPLE          
 108: BINARY_OP            %
 112: RETURN_VALUE         
