# Disassembly for http.DefaultCookiePolicy.set_ok_version
# From module file: http.cookiejar

## co_consts:
(None, '   Set-Cookie2 without version attribute (%s=%s)', False, 0, '   RFC 2965 cookies are switched off', '   Netscape cookies are switched off', True)

## co_names:
('version', '_debug', 'name', 'value', 'rfc2965', 'netscape')

## bytecode:

   0: RESUME               
   2: LOAD_FAST            cookie
   4: LOAD_ATTR            version
  14: POP_JUMP_FORWARD_IF_NOT_NONE to 74
  16: LOAD_GLOBAL          NULL + _debug
  28: LOAD_CONST           '   Set-Cookie2 without version attribute (%s=%s)'
  30: LOAD_FAST            cookie
  32: LOAD_ATTR            name
  42: LOAD_FAST            cookie
  44: LOAD_ATTR            value
  54: PRECALL              
  58: CALL                 
  68: POP_TOP              
  70: LOAD_CONST           False
  72: RETURN_VALUE         
  74: LOAD_FAST            cookie
  76: LOAD_ATTR            version
  86: LOAD_CONST           0
  88: COMPARE_OP           >
  94: POP_JUMP_FORWARD_IF_FALSE to 144
  96: LOAD_FAST            self
  98: LOAD_ATTR            rfc2965
 108: POP_JUMP_FORWARD_IF_TRUE to 144
 110: LOAD_GLOBAL          NULL + _debug
 122: LOAD_CONST           '   RFC 2965 cookies are switched off'
 124: PRECALL              
 128: CALL                 
 138: POP_TOP              
 140: LOAD_CONST           False
 142: RETURN_VALUE         
 144: LOAD_FAST            cookie
 146: LOAD_ATTR            version
 156: LOAD_CONST           0
 158: COMPARE_OP           ==
 164: POP_JUMP_FORWARD_IF_FALSE to 214
 166: LOAD_FAST            self
 168: LOAD_ATTR            netscape
 178: POP_JUMP_FORWARD_IF_TRUE to 214
 180: LOAD_GLOBAL          NULL + _debug
 192: LOAD_CONST           '   Netscape cookies are switched off'
 194: PRECALL              
 198: CALL                 
 208: POP_TOP              
 210: LOAD_CONST           False
 212: RETURN_VALUE         
 214: LOAD_CONST           True
 216: RETURN_VALUE         
