# Disassembly for http.DefaultCookiePolicy.return_ok_verifiability
# From module file: http.cookiejar

## co_consts:
(None, 0, '   third-party RFC 2965 cookie during unverifiable transaction', False, '   third-party Netscape cookie during unverifiable transaction', True)

## co_names:
('unverifiable', 'is_third_party', 'version', 'strict_rfc2965_unverifiable', '_debug', 'strict_ns_unverifiable')

## bytecode:

   0: RESUME               
   2: LOAD_FAST            request
   4: LOAD_ATTR            unverifiable
  14: POP_JUMP_FORWARD_IF_FALSE to 186
  16: LOAD_GLOBAL          NULL + is_third_party
  28: LOAD_FAST            request
  30: PRECALL              
  34: CALL                 
  44: POP_JUMP_FORWARD_IF_FALSE to 186
  46: LOAD_FAST            cookie
  48: LOAD_ATTR            version
  58: LOAD_CONST           0
  60: COMPARE_OP           >
  66: POP_JUMP_FORWARD_IF_FALSE to 116
  68: LOAD_FAST            self
  70: LOAD_ATTR            strict_rfc2965_unverifiable
  80: POP_JUMP_FORWARD_IF_FALSE to 116
  82: LOAD_GLOBAL          NULL + _debug
  94: LOAD_CONST           '   third-party RFC 2965 cookie during unverifiable transaction'
  96: PRECALL              
 100: CALL                 
 110: POP_TOP              
 112: LOAD_CONST           False
 114: RETURN_VALUE         
 116: LOAD_FAST            cookie
 118: LOAD_ATTR            version
 128: LOAD_CONST           0
 130: COMPARE_OP           ==
 136: POP_JUMP_FORWARD_IF_FALSE to 186
 138: LOAD_FAST            self
 140: LOAD_ATTR            strict_ns_unverifiable
 150: POP_JUMP_FORWARD_IF_FALSE to 186
 152: LOAD_GLOBAL          NULL + _debug
 164: LOAD_CONST           '   third-party Netscape cookie during unverifiable transaction'
 166: PRECALL              
 170: CALL                 
 180: POP_TOP              
 182: LOAD_CONST           False
 184: RETURN_VALUE         
 186: LOAD_CONST           True
 188: RETURN_VALUE         
