# Disassembly for http.HTTPConnection._tunnel
# From module file: http.client

## co_consts:
(None, b'CONNECT %s:%d HTTP/1.0\r\n', 'ascii', ': ', '\r\n', 'latin-1', b'\r\n', b'', ('method',), 'Tunnel connection failed: ', ' ', True, 1, 'header line', (b'\r\n', b'\n', b''), 0, 'header:')

## co_names:
('_tunnel_host', 'encode', '_tunnel_port', '_tunnel_headers', 'items', 'append', 'send', 'join', 'response_class', 'sock', '_method', '_read_status', 'http', 'HTTPStatus', 'OK', 'close', 'OSError', 'strip', 'fp', 'readline', '_MAXLINE', 'len', 'LineTooLong', 'debuglevel', 'print', 'decode')

## bytecode:

   0: RESUME               
   2: LOAD_CONST           b'CONNECT %s:%d HTTP/1.0\r\n'
   4: LOAD_FAST            self
   6: LOAD_ATTR            _tunnel_host
  16: LOAD_METHOD          encode
  38: LOAD_CONST           'ascii'
  40: PRECALL              
  44: CALL                 
  54: LOAD_FAST            self
  56: LOAD_ATTR            _tunnel_port
  66: BUILD_TUPLE          
  68: BINARY_OP            %
  72: STORE_FAST           connect
  74: LOAD_FAST            connect
  76: BUILD_LIST           
  78: STORE_FAST           headers
  80: LOAD_FAST            self
  82: LOAD_ATTR            _tunnel_headers
  92: LOAD_METHOD          items
 114: PRECALL              
 118: CALL                 
 128: GET_ITER             
 130: FOR_ITER             to 234
 132: UNPACK_SEQUENCE      
 136: STORE_FAST           header
 138: STORE_FAST           value
 140: LOAD_FAST            headers
 142: LOAD_METHOD          append
 164: LOAD_FAST            header
 166: FORMAT_VALUE         
 168: LOAD_CONST           ': '
 170: LOAD_FAST            value
 172: FORMAT_VALUE         
 174: LOAD_CONST           '\r\n'
 176: BUILD_STRING         
 178: LOAD_METHOD          encode
 200: LOAD_CONST           'latin-1'
 202: PRECALL              
 206: CALL                 
 216: PRECALL              
 220: CALL                 
 230: POP_TOP              
 232: JUMP_BACKWARD        to 130
 234: LOAD_FAST            headers
 236: LOAD_METHOD          append
 258: LOAD_CONST           b'\r\n'
 260: PRECALL              
 264: CALL                 
 274: POP_TOP              
 276: LOAD_FAST            self
 278: LOAD_METHOD          send
 300: LOAD_CONST           b''
 302: LOAD_METHOD          join
 324: LOAD_FAST            headers
 326: PRECALL              
 330: CALL                 
 340: PRECALL              
 344: CALL                 
 354: POP_TOP              
 356: DELETE_FAST          headers
 358: LOAD_FAST            self
 360: LOAD_METHOD          response_class
 382: LOAD_FAST            self
 384: LOAD_ATTR            sock
 394: LOAD_FAST            self
 396: LOAD_ATTR            _method
 406: KW_NAMES             
 408: PRECALL              
 412: CALL                 
 422: STORE_FAST           response
 424: NOP                  
 426: LOAD_FAST            response
 428: LOAD_METHOD          _read_status
 450: PRECALL              
 454: CALL                 
 464: UNPACK_SEQUENCE      
 468: STORE_FAST           version
 470: STORE_FAST           code
 472: STORE_FAST           message
 474: LOAD_FAST            code
 476: LOAD_GLOBAL          http
 488: LOAD_ATTR            HTTPStatus
 498: LOAD_ATTR            OK
 508: COMPARE_OP           !=
 514: POP_JUMP_FORWARD_IF_FALSE to 634
 516: LOAD_FAST            self
 518: LOAD_METHOD          close
 540: PRECALL              
 544: CALL                 
 554: POP_TOP              
 556: LOAD_GLOBAL          NULL + OSError
 568: LOAD_CONST           'Tunnel connection failed: '
 570: LOAD_FAST            code
 572: FORMAT_VALUE         
 574: LOAD_CONST           ' '
 576: LOAD_FAST            message
 578: LOAD_METHOD          strip
 600: PRECALL              
 604: CALL                 
 614: FORMAT_VALUE         
 616: BUILD_STRING         
 618: PRECALL              
 622: CALL                 
 632: RAISE_VARARGS        
 634: NOP                  
 636: LOAD_FAST            response
 638: LOAD_ATTR            fp
 648: LOAD_METHOD          readline
 670: LOAD_GLOBAL          _MAXLINE
 682: LOAD_CONST           1
 684: BINARY_OP            +
 688: PRECALL              
 692: CALL                 
 702: STORE_FAST           line
 704: LOAD_GLOBAL          NULL + len
 716: LOAD_FAST            line
 718: PRECALL              
 722: CALL                 
 732: LOAD_GLOBAL          _MAXLINE
 744: COMPARE_OP           >
 750: POP_JUMP_FORWARD_IF_FALSE to 782
 752: LOAD_GLOBAL          NULL + LineTooLong
 764: LOAD_CONST           'header line'
 766: PRECALL              
 770: CALL                 
 780: RAISE_VARARGS        
 782: LOAD_FAST            line
 784: POP_JUMP_FORWARD_IF_TRUE to 788
 786: JUMP_FORWARD         to 890
 788: LOAD_FAST            line
 790: LOAD_CONST           (b'\r\n', b'\n', b'')
 792: CONTAINS_OP          
 794: POP_JUMP_FORWARD_IF_FALSE to 798
 796: JUMP_FORWARD         to 890
 798: LOAD_FAST            self
 800: LOAD_ATTR            debuglevel
 810: LOAD_CONST           0
 812: COMPARE_OP           >
 818: POP_JUMP_FORWARD_IF_FALSE to 888
 820: LOAD_GLOBAL          NULL + print
 832: LOAD_CONST           'header:'
 834: LOAD_FAST            line
 836: LOAD_METHOD          decode
 858: PRECALL              
 862: CALL                 
 872: PRECALL              
 876: CALL                 
 886: POP_TOP              
 888: JUMP_BACKWARD        to 636
 890: LOAD_FAST            response
 892: LOAD_METHOD          close
 914: PRECALL              
 918: CALL                 
 928: POP_TOP              
 930: LOAD_CONST           None
 932: RETURN_VALUE         
 934: PUSH_EXC_INFO        
 936: LOAD_FAST            response
 938: LOAD_METHOD          close
 960: PRECALL              
 964: CALL                 
 974: POP_TOP              
 976: RERAISE              
 978: COPY                 
 980: POP_EXCEPT           
 982: RERAISE              
