# Disassembly for http.HTTPResponse._close_conn
# From module file: http.client

## co_consts:
(None,)

## co_names:
('fp', 'close')

## bytecode:

   0: RESUME               
   2: LOAD_FAST            self
   4: LOAD_ATTR            fp
  14: STORE_FAST           fp
  16: LOAD_CONST           None
  18: LOAD_FAST            self
  20: STORE_ATTR           fp
  30: LOAD_FAST            fp
  32: LOAD_METHOD          close
  54: PRECALL              
  58: CALL                 
  68: POP_TOP              
  70: LOAD_CONST           None
  72: RETURN_VALUE         
