# Disassembly for http.HTTPConnection.request
# From module file: http.client

## co_consts:
('Send a complete request to the server.', None)

## co_names:
('_send_request',)

## bytecode:

   0: RESUME               
   2: LOAD_FAST            self
   4: LOAD_METHOD          _send_request
  26: LOAD_FAST            method
  28: LOAD_FAST            url
  30: LOAD_FAST            body
  32: LOAD_FAST            headers
  34: LOAD_FAST            encode_chunked
  36: PRECALL              
  40: CALL                 
  50: POP_TOP              
  52: LOAD_CONST           None
  54: RETURN_VALUE         
