# Disassembly for http.HTTPSConnection.connect
# From module file: http.client

## co_consts:
('Connect to a host on a given (SSL) port.', ('server_hostname',), None)

## co_names:
('super', 'connect', '_tunnel_host', 'host', '_context', 'wrap_socket', 'sock')

## bytecode:

   0: COPY_FREE_VARS       
   2: RESUME               
   4: LOAD_GLOBAL          NULL + super
  16: PRECALL              
  20: CALL                 
  30: LOAD_METHOD          connect
  52: PRECALL              
  56: CALL                 
  66: POP_TOP              
  68: LOAD_FAST            self
  70: LOAD_ATTR            _tunnel_host
  80: POP_JUMP_FORWARD_IF_FALSE to 98
  82: LOAD_FAST            self
  84: LOAD_ATTR            _tunnel_host
  94: STORE_FAST           server_hostname
  96: JUMP_FORWARD         to 112
  98: LOAD_FAST            self
 100: LOAD_ATTR            host
 110: STORE_FAST           server_hostname
 112: LOAD_FAST            self
 114: LOAD_ATTR            _context
 124: LOAD_METHOD          wrap_socket
 146: LOAD_FAST            self
 148: LOAD_ATTR            sock
 158: LOAD_FAST            server_hostname
 160: KW_NAMES             
 162: PRECALL              
 166: CALL                 
 176: LOAD_FAST            self
 178: STORE_ATTR           sock
 188: LOAD_CONST           None
 190: RETURN_VALUE         
