# Disassembly for http.parse_ns_headers
# From module file: http.cookiejar

## co_consts:
('Ad-hoc parser for Netscape protocol cookie-attributes.\n\n    The old Netscape cookie format for Set-Cookie can for instance contain\n    an unquoted "," in the expires field, so we have to use this ad-hoc\n    parser instead of split_header_words.\n\n    XXX This may not make the best possible effort to parse all the crap\n    that Netscape Cookie headers contain.  Ronald Tschalar\'s HTTPClient\n    parser is probably better, so could do worse than following that if\n    this ever gives any trouble.\n\n    Currently, this is also used for parsing RFC 2109 cookies.\n\n    ', ('expires', 'domain', 'path', 'secure', 'version', 'port', 'max-age'), False, ';', '=', 0, None, 'version', True, 'expires', ('version', '0'))

## co_names:
('enumerate', 'split', 'strip', 'partition', 'lower', 'strip_quotes', 'http2time', 'append')

## bytecode:

   0: RESUME               
   2: LOAD_CONST           ('expires', 'domain', 'path', 'secure', 'version', 'port', 'max-age')
   4: STORE_FAST           known_attrs
   6: BUILD_LIST           
   8: STORE_FAST           result
  10: LOAD_FAST            ns_headers
  12: GET_ITER             
  14: EXTENDED_ARG         
  16: FOR_ITER             to 638
  18: STORE_FAST           ns_header
  20: BUILD_LIST           
  22: STORE_FAST           pairs
  24: LOAD_CONST           False
  26: STORE_FAST           version_set
  28: LOAD_GLOBAL          NULL + enumerate
  40: LOAD_FAST            ns_header
  42: LOAD_METHOD          split
  64: LOAD_CONST           ';'
  66: PRECALL              
  70: CALL                 
  80: PRECALL              
  84: CALL                 
  94: GET_ITER             
  96: FOR_ITER             to 542
  98: UNPACK_SEQUENCE      
 102: STORE_FAST           ii
 104: STORE_FAST           param
 106: LOAD_FAST            param
 108: LOAD_METHOD          strip
 130: PRECALL              
 134: CALL                 
 144: STORE_FAST           param
 146: LOAD_FAST            param
 148: LOAD_METHOD          partition
 170: LOAD_CONST           '='
 172: PRECALL              
 176: CALL                 
 186: UNPACK_SEQUENCE      
 190: STORE_FAST           key
 192: STORE_FAST           sep
 194: STORE_FAST           val
 196: LOAD_FAST            key
 198: LOAD_METHOD          strip
 220: PRECALL              
 224: CALL                 
 234: STORE_FAST           key
 236: LOAD_FAST            key
 238: POP_JUMP_FORWARD_IF_TRUE to 258
 240: LOAD_FAST            ii
 242: LOAD_CONST           0
 244: COMPARE_OP           ==
 250: POP_JUMP_FORWARD_IF_FALSE to 256
 252: POP_TOP              
 254: JUMP_FORWARD         to 542
 256: JUMP_BACKWARD        to 96
 258: LOAD_FAST            sep
 260: POP_JUMP_FORWARD_IF_FALSE to 302
 262: LOAD_FAST            val
 264: LOAD_METHOD          strip
 286: PRECALL              
 290: CALL                 
 300: JUMP_FORWARD         to 304
 302: LOAD_CONST           None
 304: STORE_FAST           val
 306: LOAD_FAST            ii
 308: LOAD_CONST           0
 310: COMPARE_OP           !=
 316: POP_JUMP_FORWARD_IF_FALSE to 494
 318: LOAD_FAST            key
 320: LOAD_METHOD          lower
 342: PRECALL              
 346: CALL                 
 356: STORE_FAST           lc
 358: LOAD_FAST            lc
 360: LOAD_FAST            known_attrs
 362: CONTAINS_OP          
 364: POP_JUMP_FORWARD_IF_FALSE to 370
 366: LOAD_FAST            lc
 368: STORE_FAST           key
 370: LOAD_FAST            key
 372: LOAD_CONST           'version'
 374: COMPARE_OP           ==
 380: POP_JUMP_FORWARD_IF_FALSE to 422
 382: LOAD_FAST            val
 384: POP_JUMP_FORWARD_IF_NONE to 416
 386: LOAD_GLOBAL          NULL + strip_quotes
 398: LOAD_FAST            val
 400: PRECALL              
 404: CALL                 
 414: STORE_FAST           val
 416: LOAD_CONST           True
 418: STORE_FAST           version_set
 420: JUMP_FORWARD         to 494
 422: LOAD_FAST            key
 424: LOAD_CONST           'expires'
 426: COMPARE_OP           ==
 432: POP_JUMP_FORWARD_IF_FALSE to 494
 434: LOAD_FAST            val
 436: POP_JUMP_FORWARD_IF_NONE to 494
 438: LOAD_GLOBAL          NULL + http2time
 450: LOAD_GLOBAL          NULL + strip_quotes
 462: LOAD_FAST            val
 464: PRECALL              
 468: CALL                 
 478: PRECALL              
 482: CALL                 
 492: STORE_FAST           val
 494: LOAD_FAST            pairs
 496: LOAD_METHOD          append
 518: LOAD_FAST            key
 520: LOAD_FAST            val
 522: BUILD_TUPLE          
 524: PRECALL              
 528: CALL                 
 538: POP_TOP              
 540: JUMP_BACKWARD        to 96
 542: LOAD_FAST            pairs
 544: POP_JUMP_FORWARD_IF_FALSE to 634
 546: LOAD_FAST            version_set
 548: POP_JUMP_FORWARD_IF_TRUE to 592
 550: LOAD_FAST            pairs
 552: LOAD_METHOD          append
 574: LOAD_CONST           ('version', '0')
 576: PRECALL              
 580: CALL                 
 590: POP_TOP              
 592: LOAD_FAST            result
 594: LOAD_METHOD          append
 616: LOAD_FAST            pairs
 618: PRECALL              
 622: CALL                 
 632: POP_TOP              
 634: EXTENDED_ARG         
 636: JUMP_BACKWARD        to 14
 638: LOAD_FAST            result
 640: RETURN_VALUE         
