# Disassembly for http.liberal_is_HDN
# From module file: http.cookiejar

## co_consts:
('Return True if text is a sort-of-like a host domain name.\n\n    For accepting/blocking domains.\n\n    ', False, True)

## co_names:
('IPV4_RE', 'search')

## bytecode:

   0: RESUME               
   2: LOAD_GLOBAL          IPV4_RE
  14: LOAD_METHOD          search
  36: LOAD_FAST            text
  38: PRECALL              
  42: CALL                 
  52: POP_JUMP_FORWARD_IF_FALSE to 58
  54: LOAD_CONST           False
  56: RETURN_VALUE         
  58: LOAD_CONST           True
  60: RETURN_VALUE         
