# Disassembly for http.LineTooLong.__init__
# From module file: http.client

## co_consts:
(None, 'got more than %d bytes when reading %s')

## co_names:
('HTTPException', '__init__', '_MAXLINE')

## bytecode:

   0: RESUME               
   2: LOAD_GLOBAL          HTTPException
  14: LOAD_METHOD          __init__
  36: LOAD_FAST            self
  38: LOAD_CONST           'got more than %d bytes when reading %s'
  40: LOAD_GLOBAL          _MAXLINE
  52: LOAD_FAST            line_type
  54: BUILD_TUPLE          
  56: BINARY_OP            %
  60: PRECALL              
  64: CALL                 
  74: POP_TOP              
  76: LOAD_CONST           None
  78: RETURN_VALUE         
