# Disassembly for http.HTTPConnection
# From module file: http.client

## co_consts:
('HTTPConnection', 11, 'HTTP/1.1', 1, 0, <code object _is_textIO at 0x000002406945FD20, file "http\client.py", line 800>, <code object _get_content_length at 0x00000240691A7BB0, file "http\client.py", line 806>, None, 8192, <code object __init__ at 0x0000024069498230, file "http\client.py", line 838>, <code object set_tunnel at 0x00000240691E84B0, file "http\client.py", line 860>, <code object _get_hostport at 0x0000024068CA0B00, file "http\client.py", line 884>, <code object set_debuglevel at 0x00000240694960B0, file "http\client.py", line 904>, <code object _tunnel at 0x0000024068D5FCF0, file "http\client.py", line 907>, <code object connect at 0x0000024068E1B4C0, file "http\client.py", line 942>, <code object close at 0x0000024069CD81F0, file "http\client.py", line 957>, <code object send at 0x0000024068D3EB50, file "http\client.py", line 971>, <code object _output at 0x00000240693EB830, file "http\client.py", line 1011>, <code object _read_readable at 0x00000240691DAD80, file "http\client.py", line 1018>, False, <code object _send_output at 0x0000024068C242C0, file "http\client.py", line 1032>, <code object putrequest at 0x0000024068BBEAF0, file "http\client.py", line 1086>, <code object _encode_request at 0x000002406945D4D0, file "http\client.py", line 1213>, <code object _validate_method at 0x000002406922CEA0, file "http\client.py", line 1217>, <code object _validate_path at 0x000002406922C6C0, file "http\client.py", line 1226>, <code object _validate_host at 0x000002406922C420, file "http\client.py", line 1234>, <code object putheader at 0x0000024066349190, file "http\client.py", line 1242>, ('encode_chunked',), <code object endheaders at 0x000002406922C2D0, file "http\client.py", line 1270>, <code object request at 0x000002406945FC30, file "http\client.py", line 1283>, <code object _send_request at 0x0000024068C54980, file "http\client.py", line 1288>, <code object getresponse at 0x0000024068BFE6F0, file "http\client.py", line 1334>, (None, None), (None, False), (False, False), (None,))

## co_names:
('__name__', '__module__', '__qualname__', '_http_vsn', '_http_vsn_str', 'HTTPResponse', 'response_class', 'HTTP_PORT', 'default_port', 'auto_open', 'debuglevel', 'staticmethod', '_is_textIO', '_get_content_length', 'socket', '_GLOBAL_DEFAULT_TIMEOUT', '__init__', 'set_tunnel', '_get_hostport', 'set_debuglevel', '_tunnel', 'connect', 'close', 'send', '_output', '_read_readable', '_send_output', 'putrequest', '_encode_request', '_validate_method', '_validate_path', '_validate_host', 'putheader', 'endheaders', 'request', '_send_request', 'getresponse')

## bytecode:

   0: RESUME               
   2: LOAD_NAME            __name__
   4: STORE_NAME           __module__
   6: LOAD_CONST           'HTTPConnection'
   8: STORE_NAME           __qualname__
  10: LOAD_CONST           11
  12: STORE_NAME           _http_vsn
  14: LOAD_CONST           'HTTP/1.1'
  16: STORE_NAME           _http_vsn_str
  18: LOAD_NAME            HTTPResponse
  20: STORE_NAME           response_class
  22: LOAD_NAME            HTTP_PORT
  24: STORE_NAME           default_port
  26: LOAD_CONST           1
  28: STORE_NAME           auto_open
  30: LOAD_CONST           0
  32: STORE_NAME           debuglevel
  34: LOAD_NAME            staticmethod
  36: LOAD_CONST           <code object _is_textIO at 0x000002406945FD20, file "http\client.py", line 800>
  38: MAKE_FUNCTION        
  40: PRECALL              
  44: CALL                 
  54: STORE_NAME           _is_textIO
  56: LOAD_NAME            staticmethod
  58: LOAD_CONST           <code object _get_content_length at 0x00000240691A7BB0, file "http\client.py", line 806>
  60: MAKE_FUNCTION        
  62: PRECALL              
  66: CALL                 
  76: STORE_NAME           _get_content_length
  78: LOAD_CONST           None
  80: LOAD_NAME            socket
  82: LOAD_ATTR            _GLOBAL_DEFAULT_TIMEOUT
  92: LOAD_CONST           None
  94: LOAD_CONST           8192
  96: BUILD_TUPLE          
  98: LOAD_CONST           <code object __init__ at 0x0000024069498230, file "http\client.py", line 838>
 100: MAKE_FUNCTION        defaults
 102: STORE_NAME           __init__
 104: LOAD_CONST           (None, None)
 106: LOAD_CONST           <code object set_tunnel at 0x00000240691E84B0, file "http\client.py", line 860>
 108: MAKE_FUNCTION        defaults
 110: STORE_NAME           set_tunnel
 112: LOAD_CONST           <code object _get_hostport at 0x0000024068CA0B00, file "http\client.py", line 884>
 114: MAKE_FUNCTION        
 116: STORE_NAME           _get_hostport
 118: LOAD_CONST           <code object set_debuglevel at 0x00000240694960B0, file "http\client.py", line 904>
 120: MAKE_FUNCTION        
 122: STORE_NAME           set_debuglevel
 124: LOAD_CONST           <code object _tunnel at 0x0000024068D5FCF0, file "http\client.py", line 907>
 126: MAKE_FUNCTION        
 128: STORE_NAME           _tunnel
 130: LOAD_CONST           <code object connect at 0x0000024068E1B4C0, file "http\client.py", line 942>
 132: MAKE_FUNCTION        
 134: STORE_NAME           connect
 136: LOAD_CONST           <code object close at 0x0000024069CD81F0, file "http\client.py", line 957>
 138: MAKE_FUNCTION        
 140: STORE_NAME           close
 142: LOAD_CONST           <code object send at 0x0000024068D3EB50, file "http\client.py", line 971>
 144: MAKE_FUNCTION        
 146: STORE_NAME           send
 148: LOAD_CONST           <code object _output at 0x00000240693EB830, file "http\client.py", line 1011>
 150: MAKE_FUNCTION        
 152: STORE_NAME           _output
 154: LOAD_CONST           <code object _read_readable at 0x00000240691DAD80, file "http\client.py", line 1018>
 156: MAKE_FUNCTION        
 158: STORE_NAME           _read_readable
 160: LOAD_CONST           (None, False)
 162: LOAD_CONST           <code object _send_output at 0x0000024068C242C0, file "http\client.py", line 1032>
 164: MAKE_FUNCTION        defaults
 166: STORE_NAME           _send_output
 168: NOP                  
 170: NOP                  
 172: LOAD_CONST           (False, False)
 174: LOAD_CONST           <code object putrequest at 0x0000024068BBEAF0, file "http\client.py", line 1086>
 176: MAKE_FUNCTION        defaults
 178: STORE_NAME           putrequest
 180: LOAD_CONST           <code object _encode_request at 0x000002406945D4D0, file "http\client.py", line 1213>
 182: MAKE_FUNCTION        
 184: STORE_NAME           _encode_request
 186: LOAD_CONST           <code object _validate_method at 0x000002406922CEA0, file "http\client.py", line 1217>
 188: MAKE_FUNCTION        
 190: STORE_NAME           _validate_method
 192: LOAD_CONST           <code object _validate_path at 0x000002406922C6C0, file "http\client.py", line 1226>
 194: MAKE_FUNCTION        
 196: STORE_NAME           _validate_path
 198: LOAD_CONST           <code object _validate_host at 0x000002406922C420, file "http\client.py", line 1234>
 200: MAKE_FUNCTION        
 202: STORE_NAME           _validate_host
 204: LOAD_CONST           <code object putheader at 0x0000024066349190, file "http\client.py", line 1242>
 206: MAKE_FUNCTION        
 208: STORE_NAME           putheader
 210: LOAD_CONST           (None,)
 212: LOAD_CONST           False
 214: LOAD_CONST           ('encode_chunked',)
 216: BUILD_CONST_KEY_MAP  
 218: LOAD_CONST           <code object endheaders at 0x000002406922C2D0, file "http\client.py", line 1270>
 220: MAKE_FUNCTION        defaults, kwdefaults
 222: STORE_NAME           endheaders
 224: LOAD_CONST           None
 226: BUILD_MAP            
 228: BUILD_TUPLE          
 230: LOAD_CONST           False
 232: LOAD_CONST           ('encode_chunked',)
 234: BUILD_CONST_KEY_MAP  
 236: LOAD_CONST           <code object request at 0x000002406945FC30, file "http\client.py", line 1283>
 238: MAKE_FUNCTION        defaults, kwdefaults
 240: STORE_NAME           request
 242: LOAD_CONST           <code object _send_request at 0x0000024068C54980, file "http\client.py", line 1288>
 244: MAKE_FUNCTION        
 246: STORE_NAME           _send_request
 248: LOAD_CONST           <code object getresponse at 0x0000024068BFE6F0, file "http\client.py", line 1334>
 250: MAKE_FUNCTION        
 252: STORE_NAME           getresponse
 254: LOAD_CONST           None
 256: RETURN_VALUE         
