# Disassembly for http.CookiePolicy
# From module file: http.cookiejar

## co_consts:
('CookiePolicy', 'Defines which cookies get accepted from and returned to server.\n\n    May also modify cookies, though this is probably a bad idea.\n\n    The subclass DefaultCookiePolicy defines the standard rules for Netscape\n    and RFC 2965 cookies -- override that if you want a customized policy.\n\n    ', <code object set_ok at 0x0000024069465450, file "http\cookiejar.py", line 850>, <code object return_ok at 0x0000024069466870, file "http\cookiejar.py", line 859>, <code object domain_return_ok at 0x000002406943B330, file "http\cookiejar.py", line 863>, <code object path_return_ok at 0x000002406943B270, file "http\cookiejar.py", line 868>, None)

## co_names:
('__name__', '__module__', '__qualname__', '__doc__', 'set_ok', 'return_ok', 'domain_return_ok', 'path_return_ok')

## bytecode:

   0: RESUME               
   2: LOAD_NAME            __name__
   4: STORE_NAME           __module__
   6: LOAD_CONST           'CookiePolicy'
   8: STORE_NAME           __qualname__
  10: LOAD_CONST           'Defines which cookies get accepted from and returned to server.\n\n    May also modify cookies, though this is probably a bad idea.\n\n    The subclass DefaultCookiePolicy defines the standard rules for Netscape\n    and RFC 2965 cookies -- override that if you want a customized policy.\n\n    '
  12: STORE_NAME           __doc__
  14: LOAD_CONST           <code object set_ok at 0x0000024069465450, file "http\cookiejar.py", line 850>
  16: MAKE_FUNCTION        
  18: STORE_NAME           set_ok
  20: LOAD_CONST           <code object return_ok at 0x0000024069466870, file "http\cookiejar.py", line 859>
  22: MAKE_FUNCTION        
  24: STORE_NAME           return_ok
  26: LOAD_CONST           <code object domain_return_ok at 0x000002406943B330, file "http\cookiejar.py", line 863>
  28: MAKE_FUNCTION        
  30: STORE_NAME           domain_return_ok
  32: LOAD_CONST           <code object path_return_ok at 0x000002406943B270, file "http\cookiejar.py", line 868>
  34: MAKE_FUNCTION        
  36: STORE_NAME           path_return_ok
  38: LOAD_CONST           None
  40: RETURN_VALUE         
