# Disassembly for http.HTTPMethod
# From module file: http

## co_consts:
('HTTPMethod', 'HTTP methods and descriptions\n\n    Methods from the following RFCs are all observed:\n\n        * RFC 7231: Hypertext Transfer Protocol (HTTP/1.1), obsoletes 2616\n        * RFC 5789: PATCH Method for HTTP\n    ', <code object __new__ at 0x000002406944A780, file "http\__init__.py", line 163>, <code object __repr__ at 0x000002406945F870, file "http\__init__.py", line 169>, ('CONNECT', 'Establish a connection to the server.'), ('DELETE', 'Remove the target.'), ('GET', 'Retrieve the target.'), ('HEAD', 'Same as GET, but only retrieve the status line and header section.'), ('OPTIONS', 'Describe the communication options for the target.'), ('PATCH', 'Apply partial modifications to a target.'), ('POST', 'Perform target-specific processing with the request payload.'), ('PUT', 'Replace the target with the request payload.'), ('TRACE', 'Perform a message loop-back test along the path to the target.'), None)

## co_names:
('__name__', '__module__', '__qualname__', '__doc__', '__new__', '__repr__', 'CONNECT', 'DELETE', 'GET', 'HEAD', 'OPTIONS', 'PATCH', 'POST', 'PUT', 'TRACE')

## bytecode:

   0: RESUME               
   2: LOAD_NAME            __name__
   4: STORE_NAME           __module__
   6: LOAD_CONST           'HTTPMethod'
   8: STORE_NAME           __qualname__
  10: LOAD_CONST           'HTTP methods and descriptions\n\n    Methods from the following RFCs are all observed:\n\n        * RFC 7231: Hypertext Transfer Protocol (HTTP/1.1), obsoletes 2616\n        * RFC 5789: PATCH Method for HTTP\n    '
  12: STORE_NAME           __doc__
  14: LOAD_CONST           <code object __new__ at 0x000002406944A780, file "http\__init__.py", line 163>
  16: MAKE_FUNCTION        
  18: STORE_NAME           __new__
  20: LOAD_CONST           <code object __repr__ at 0x000002406945F870, file "http\__init__.py", line 169>
  22: MAKE_FUNCTION        
  24: STORE_NAME           __repr__
  26: LOAD_CONST           ('CONNECT', 'Establish a connection to the server.')
  28: STORE_NAME           CONNECT
  30: LOAD_CONST           ('DELETE', 'Remove the target.')
  32: STORE_NAME           DELETE
  34: LOAD_CONST           ('GET', 'Retrieve the target.')
  36: STORE_NAME           GET
  38: LOAD_CONST           ('HEAD', 'Same as GET, but only retrieve the status line and header section.')
  40: STORE_NAME           HEAD
  42: LOAD_CONST           ('OPTIONS', 'Describe the communication options for the target.')
  44: STORE_NAME           OPTIONS
  46: LOAD_CONST           ('PATCH', 'Apply partial modifications to a target.')
  48: STORE_NAME           PATCH
  50: LOAD_CONST           ('POST', 'Perform target-specific processing with the request payload.')
  52: STORE_NAME           POST
  54: LOAD_CONST           ('PUT', 'Replace the target with the request payload.')
  56: STORE_NAME           PUT
  58: LOAD_CONST           ('TRACE', 'Perform a message loop-back test along the path to the target.')
  60: STORE_NAME           TRACE
  62: LOAD_CONST           None
  64: RETURN_VALUE         
