# Disassembly for http.DefaultCookiePolicy.set_ok
# From module file: http.cookiejar

## co_consts:
('\n        If you override .set_ok(), be sure to call this method.  If it returns\n        false, so should your subclass (assuming your subclass wants to be more\n        strict about which cookies to accept).\n\n        ', ' - checking cookie %s=%s', None, ('version', 'verifiability', 'name', 'path', 'domain', 'port'), 'set_ok_', False, True)

## co_names:
('_debug', 'name', 'value', 'getattr')

## bytecode:

   0: RESUME               
   2: LOAD_GLOBAL          NULL + _debug
  14: LOAD_CONST           ' - checking cookie %s=%s'
  16: LOAD_FAST            cookie
  18: LOAD_ATTR            name
  28: LOAD_FAST            cookie
  30: LOAD_ATTR            value
  40: PRECALL              
  44: CALL                 
  54: POP_TOP              
  56: LOAD_FAST            cookie
  58: LOAD_ATTR            name
  68: POP_JUMP_FORWARD_IF_NOT_NONE to 74
  70: LOAD_ASSERTION_ERROR 
  72: RAISE_VARARGS        
  74: LOAD_CONST           ('version', 'verifiability', 'name', 'path', 'domain', 'port')
  76: GET_ITER             
  78: FOR_ITER             to 156
  80: STORE_FAST           n
  82: LOAD_CONST           'set_ok_'
  84: LOAD_FAST            n
  86: BINARY_OP            +
  90: STORE_FAST           fn_name
  92: LOAD_GLOBAL          NULL + getattr
 104: LOAD_FAST            self
 106: LOAD_FAST            fn_name
 108: PRECALL              
 112: CALL                 
 122: STORE_FAST           fn
 124: PUSH_NULL            
 126: LOAD_FAST            fn
 128: LOAD_FAST            cookie
 130: LOAD_FAST            request
 132: PRECALL              
 136: CALL                 
 146: POP_JUMP_FORWARD_IF_TRUE to 154
 148: POP_TOP              
 150: LOAD_CONST           False
 152: RETURN_VALUE         
 154: JUMP_BACKWARD        to 78
 156: LOAD_CONST           True
 158: RETURN_VALUE         
