# Disassembly for http.Cookie
# From module file: http.cookiejar

## co_consts:
('Cookie', 'HTTP Cookie.\n\n    This class represents both Netscape and RFC 2965 cookies.\n\n    This is deliberately a very simple class.  It just holds attributes.  It\'s\n    possible to construct Cookie instances that don\'t comply with the cookie\n    standards.  CookieJar.make_cookies is the factory function for Cookie\n    objects -- it deals with cookie parsing, supplying defaults, and\n    normalising to the representation used in this class.  CookiePolicy is\n    responsible for checking them to see whether they should be accepted from\n    and returned to the server.\n\n    Note that the port may be present in the headers, but unspecified ("Port"\n    rather than"Port=80", for example); if this is the case, port is None.\n\n    ', False, <code object __init__ at 0x0000024066C26B10, file "http\cookiejar.py", line 761>, <code object has_nonstandard_attr at 0x00000240694946B0, file "http\cookiejar.py", line 803>, None, <code object get_nonstandard_attr at 0x000002406945E4C0, file "http\cookiejar.py", line 805>, <code object set_nonstandard_attr at 0x0000024069465610, file "http\cookiejar.py", line 807>, <code object is_expired at 0x000002406944AEF0, file "http\cookiejar.py", line 810>, <code object __str__ at 0x00000240691C0F50, file "http\cookiejar.py", line 816>, <code object __repr__ at 0x0000024068C8E3E0, file "http\cookiejar.py", line 826>, (False,), (None,))

## co_names:
('__name__', '__module__', '__qualname__', '__doc__', '__init__', 'has_nonstandard_attr', 'get_nonstandard_attr', 'set_nonstandard_attr', 'is_expired', '__str__', '__repr__')

## bytecode:

   0: RESUME               
   2: LOAD_NAME            __name__
   4: STORE_NAME           __module__
   6: LOAD_CONST           'Cookie'
   8: STORE_NAME           __qualname__
  10: LOAD_CONST           'HTTP Cookie.\n\n    This class represents both Netscape and RFC 2965 cookies.\n\n    This is deliberately a very simple class.  It just holds attributes.  It\'s\n    possible to construct Cookie instances that don\'t comply with the cookie\n    standards.  CookieJar.make_cookies is the factory function for Cookie\n    objects -- it deals with cookie parsing, supplying defaults, and\n    normalising to the representation used in this class.  CookiePolicy is\n    responsible for checking them to see whether they should be accepted from\n    and returned to the server.\n\n    Note that the port may be present in the headers, but unspecified ("Port"\n    rather than"Port=80", for example); if this is the case, port is None.\n\n    '
  12: STORE_NAME           __doc__
  14: NOP                  
  16: LOAD_CONST           (False,)
  18: LOAD_CONST           <code object __init__ at 0x0000024066C26B10, file "http\cookiejar.py", line 761>
  20: MAKE_FUNCTION        defaults
  22: STORE_NAME           __init__
  24: LOAD_CONST           <code object has_nonstandard_attr at 0x00000240694946B0, file "http\cookiejar.py", line 803>
  26: MAKE_FUNCTION        
  28: STORE_NAME           has_nonstandard_attr
  30: LOAD_CONST           (None,)
  32: LOAD_CONST           <code object get_nonstandard_attr at 0x000002406945E4C0, file "http\cookiejar.py", line 805>
  34: MAKE_FUNCTION        defaults
  36: STORE_NAME           get_nonstandard_attr
  38: LOAD_CONST           <code object set_nonstandard_attr at 0x0000024069465610, file "http\cookiejar.py", line 807>
  40: MAKE_FUNCTION        
  42: STORE_NAME           set_nonstandard_attr
  44: LOAD_CONST           (None,)
  46: LOAD_CONST           <code object is_expired at 0x000002406944AEF0, file "http\cookiejar.py", line 810>
  48: MAKE_FUNCTION        defaults
  50: STORE_NAME           is_expired
  52: LOAD_CONST           <code object __str__ at 0x00000240691C0F50, file "http\cookiejar.py", line 816>
  54: MAKE_FUNCTION        
  56: STORE_NAME           __str__
  58: LOAD_CONST           <code object __repr__ at 0x0000024068C8E3E0, file "http\cookiejar.py", line 826>
  60: MAKE_FUNCTION        
  62: STORE_NAME           __repr__
  64: LOAD_CONST           None
  66: RETURN_VALUE         
