# Disassembly for http.HTTPMethod.__new__
# From module file: http

## co_consts:
(None,)

## co_names:
('str', '__new__', '_value_', 'description')

## bytecode:

   0: RESUME               
   2: LOAD_GLOBAL          str
  14: LOAD_METHOD          __new__
  36: LOAD_FAST            cls
  38: LOAD_FAST            value
  40: PRECALL              
  44: CALL                 
  54: STORE_FAST           obj
  56: LOAD_FAST            value
  58: LOAD_FAST            obj
  60: STORE_ATTR           _value_
  70: LOAD_FAST            description
  72: LOAD_FAST            obj
  74: STORE_ATTR           description
  84: LOAD_FAST            obj
  86: RETURN_VALUE         
