# Disassembly for http.CookieJar.__repr__
# From module file: http.cookiejar

## co_consts:
(None, '<', '[', ', ', ']>')

## co_names:
('append', 'repr', '__class__', '__name__', 'join')

## bytecode:

   0: RESUME               
   2: BUILD_LIST           
   4: STORE_FAST           r
   6: LOAD_FAST            self
   8: GET_ITER             
  10: FOR_ITER             to 84
  12: STORE_FAST           cookie
  14: LOAD_FAST            r
  16: LOAD_METHOD          append
  38: LOAD_GLOBAL          NULL + repr
  50: LOAD_FAST            cookie
  52: PRECALL              
  56: CALL                 
  66: PRECALL              
  70: CALL                 
  80: POP_TOP              
  82: JUMP_BACKWARD        to 10
  84: LOAD_CONST           '<'
  86: LOAD_FAST            self
  88: LOAD_ATTR            __class__
  98: LOAD_ATTR            __name__
 108: FORMAT_VALUE         str
 110: LOAD_CONST           '['
 112: LOAD_CONST           ', '
 114: LOAD_METHOD          join
 136: LOAD_FAST            r
 138: PRECALL              
 142: CALL                 
 152: FORMAT_VALUE         str
 154: LOAD_CONST           ']>'
 156: BUILD_STRING         
 158: RETURN_VALUE         
