# Disassembly for http.CookieJar.clear_expired_cookies
# From module file: http.cookiejar

## co_consts:
("Discard all expired cookies.\n\n        You probably don't need to call this method: expired cookies are never\n        sent back to the server (provided you're using DefaultCookiePolicy),\n        this method is called by CookieJar itself every so often, and the\n        .save() method won't save expired cookies anyway (unless you ask\n        otherwise by passing a true ignore_expires argument).\n\n        ", None)

## co_names:
('_cookies_lock', 'acquire', 'time', 'is_expired', 'clear', 'domain', 'path', 'name', 'release')

## bytecode:

   0: RESUME               
   2: LOAD_FAST            self
   4: LOAD_ATTR            _cookies_lock
  14: LOAD_METHOD          acquire
  36: PRECALL              
  40: CALL                 
  50: POP_TOP              
  52: NOP                  
  54: LOAD_GLOBAL          NULL + time
  66: LOAD_ATTR            time
  76: PRECALL              
  80: CALL                 
  90: STORE_FAST           now
  92: LOAD_FAST            self
  94: GET_ITER             
  96: FOR_ITER             to 220
  98: STORE_FAST           cookie
 100: LOAD_FAST            cookie
 102: LOAD_METHOD          is_expired
 124: LOAD_FAST            now
 126: PRECALL              
 130: CALL                 
 140: POP_JUMP_FORWARD_IF_FALSE to 218
 142: LOAD_FAST            self
 144: LOAD_METHOD          clear
 166: LOAD_FAST            cookie
 168: LOAD_ATTR            domain
 178: LOAD_FAST            cookie
 180: LOAD_ATTR            path
 190: LOAD_FAST            cookie
 192: LOAD_ATTR            name
 202: PRECALL              
 206: CALL                 
 216: POP_TOP              
 218: JUMP_BACKWARD        to 96
 220: NOP                  
 222: LOAD_FAST            self
 224: LOAD_ATTR            _cookies_lock
 234: LOAD_METHOD          release
 256: PRECALL              
 260: CALL                 
 270: POP_TOP              
 272: LOAD_CONST           None
 274: RETURN_VALUE         
 276: PUSH_EXC_INFO        
 278: LOAD_FAST            self
 280: LOAD_ATTR            _cookies_lock
 290: LOAD_METHOD          release
 312: PRECALL              
 316: CALL                 
 326: POP_TOP              
 328: RERAISE              
 330: COPY                 
 332: POP_EXCEPT           
 334: RERAISE              
