# Disassembly for http.escape_path
# From module file: http.cookiejar

## co_consts:
('Escape any invalid characters in HTTP URL, and uppercase all escapes.',)

## co_names:
('urllib', 'parse', 'quote', 'HTTP_PATH_SAFE', 'ESCAPED_CHAR_RE', 'sub', 'uppercase_escaped_char')

## bytecode:

   0: RESUME               
   2: LOAD_GLOBAL          urllib
  14: LOAD_ATTR            parse
  24: LOAD_METHOD          quote
  46: LOAD_FAST            path
  48: LOAD_GLOBAL          HTTP_PATH_SAFE
  60: PRECALL              
  64: CALL                 
  74: STORE_FAST           path
  76: LOAD_GLOBAL          ESCAPED_CHAR_RE
  88: LOAD_METHOD          sub
 110: LOAD_GLOBAL          uppercase_escaped_char
 122: LOAD_FAST            path
 124: PRECALL              
 128: CALL                 
 138: STORE_FAST           path
 140: LOAD_FAST            path
 142: RETURN_VALUE         
