# Disassembly for http.HTTPConnection._get_content_length
# From module file: http.client

## co_consts:
('Get the content-length based on the body.\n\n        If the body is None, we set Content-Length: 0 for methods that expect\n        a body (RFC 7230, Section 3.3.2). We also set the Content-Length for\n        any method if the body is a str or bytes-like object and not a file.\n        ', None, 0, 'read')

## co_names:
('upper', '_METHODS_EXPECTING_BODY', 'hasattr', 'memoryview', 'nbytes', 'TypeError', 'isinstance', 'str', 'len')

## bytecode:

   0: RESUME               
   2: LOAD_FAST            body
   4: POP_JUMP_FORWARD_IF_NOT_NONE to 68
   6: LOAD_FAST            method
   8: LOAD_METHOD          upper
  30: PRECALL              
  34: CALL                 
  44: LOAD_GLOBAL          _METHODS_EXPECTING_BODY
  56: CONTAINS_OP          
  58: POP_JUMP_FORWARD_IF_FALSE to 64
  60: LOAD_CONST           0
  62: RETURN_VALUE         
  64: LOAD_CONST           None
  66: RETURN_VALUE         
  68: LOAD_GLOBAL          NULL + hasattr
  80: LOAD_FAST            body
  82: LOAD_CONST           'read'
  84: PRECALL              
  88: CALL                 
  98: POP_JUMP_FORWARD_IF_FALSE to 104
 100: LOAD_CONST           None
 102: RETURN_VALUE         
 104: NOP                  
 106: LOAD_GLOBAL          NULL + memoryview
 118: LOAD_FAST            body
 120: PRECALL              
 124: CALL                 
 134: STORE_FAST           mv
 136: LOAD_FAST            mv
 138: LOAD_ATTR            nbytes
 148: RETURN_VALUE         
 150: PUSH_EXC_INFO        
 152: LOAD_GLOBAL          TypeError
 164: CHECK_EXC_MATCH      
 166: POP_JUMP_FORWARD_IF_FALSE to 174
 168: POP_TOP              
 170: POP_EXCEPT           
 172: JUMP_FORWARD         to 182
 174: RERAISE              
 176: COPY                 
 178: POP_EXCEPT           
 180: RERAISE              
 182: LOAD_GLOBAL          NULL + isinstance
 194: LOAD_FAST            body
 196: LOAD_GLOBAL          str
 208: PRECALL              
 212: CALL                 
 222: POP_JUMP_FORWARD_IF_FALSE to 254
 224: LOAD_GLOBAL          NULL + len
 236: LOAD_FAST            body
 238: PRECALL              
 242: CALL                 
 252: RETURN_VALUE         
 254: LOAD_CONST           None
 256: RETURN_VALUE         
