# Disassembly for http.DefaultCookiePolicy.set_blocked_domains
# From module file: http.cookiejar

## co_consts:
('Set the sequence of blocked domains.', None)

## co_names:
('tuple', '_blocked_domains')

## bytecode:

   0: RESUME               
   2: LOAD_GLOBAL          NULL + tuple
  14: LOAD_FAST            blocked_domains
  16: PRECALL              
  20: CALL                 
  30: LOAD_FAST            self
  32: STORE_ATTR           _blocked_domains
  42: LOAD_CONST           None
  44: RETURN_VALUE         
