# Disassembly for http._debug
# From module file: http.cookiejar

## co_consts:
(None, 0, 'http.cookiejar')

## co_names:
('debug', 'logger', 'logging', 'getLogger')

## bytecode:

   0: RESUME               
   2: LOAD_GLOBAL          debug
  14: POP_JUMP_FORWARD_IF_TRUE to 20
  16: LOAD_CONST           None
  18: RETURN_VALUE         
  20: LOAD_GLOBAL          logger
  32: POP_JUMP_FORWARD_IF_TRUE to 84
  34: LOAD_CONST           0
  36: LOAD_CONST           None
  38: IMPORT_NAME          logging
  40: STORE_FAST           logging
  42: LOAD_FAST            logging
  44: LOAD_METHOD          getLogger
  66: LOAD_CONST           'http.cookiejar'
  68: PRECALL              
  72: CALL                 
  82: STORE_GLOBAL         logger
  84: LOAD_GLOBAL          NULL + logger
  96: LOAD_ATTR            debug
 106: LOAD_FAST            args
 108: CALL_FUNCTION_EX     
 110: RETURN_VALUE         
