# Disassembly for http.Cookie.is_expired
# From module file: http.cookiejar

## co_consts:
(None, True, False)

## co_names:
('time', 'expires')

## bytecode:

   0: RESUME               
   2: LOAD_FAST            now
   4: POP_JUMP_FORWARD_IF_NOT_NONE to 44
   6: LOAD_GLOBAL          NULL + time
  18: LOAD_ATTR            time
  28: PRECALL              
  32: CALL                 
  42: STORE_FAST           now
  44: LOAD_FAST            self
  46: LOAD_ATTR            expires
  56: POP_JUMP_FORWARD_IF_NONE to 84
  58: LOAD_FAST            self
  60: LOAD_ATTR            expires
  70: LOAD_FAST            now
  72: COMPARE_OP           <=
  78: POP_JUMP_FORWARD_IF_FALSE to 84
  80: LOAD_CONST           True
  82: RETURN_VALUE         
  84: LOAD_CONST           False
  86: RETURN_VALUE         
