# Disassembly for ssl.SSLSocket.sendall
# From module file: ssl

## co_consts:
(None, 0, 'non-zero flags not allowed in calls to sendall() on %s', 'B')

## co_names:
('_checkClosed', '_sslobj', 'ValueError', '__class__', 'memoryview', 'cast', 'len', 'send', 'super', 'sendall')

## bytecode:

   0: COPY_FREE_VARS       
   2: RESUME               
   4: LOAD_FAST            self
   6: LOAD_METHOD          _checkClosed
  28: PRECALL              
  32: CALL                 
  42: POP_TOP              
  44: LOAD_FAST            self
  46: LOAD_ATTR            _sslobj
  56: POP_JUMP_FORWARD_IF_NONE to 416
  58: LOAD_FAST            flags
  60: LOAD_CONST           0
  62: COMPARE_OP           !=
  68: POP_JUMP_FORWARD_IF_FALSE to 116
  70: LOAD_GLOBAL          NULL + ValueError
  82: LOAD_CONST           'non-zero flags not allowed in calls to sendall() on %s'
  84: LOAD_FAST            self
  86: LOAD_ATTR            __class__
  96: BINARY_OP            %
 100: PRECALL              
 104: CALL                 
 114: RAISE_VARARGS        
 116: LOAD_CONST           0
 118: STORE_FAST           count
 120: LOAD_GLOBAL          NULL + memoryview
 132: LOAD_FAST            data
 134: PRECALL              
 138: CALL                 
 148: BEFORE_WITH          
 150: STORE_FAST           view
 152: LOAD_FAST            view
 154: LOAD_METHOD          cast
 176: LOAD_CONST           'B'
 178: PRECALL              
 182: CALL                 
 192: BEFORE_WITH          
 194: STORE_FAST           byte_view
 196: LOAD_GLOBAL          NULL + len
 208: LOAD_FAST            byte_view
 210: PRECALL              
 214: CALL                 
 224: STORE_FAST           amount
 226: LOAD_FAST            count
 228: LOAD_FAST            amount
 230: COMPARE_OP           <
 236: POP_JUMP_FORWARD_IF_FALSE to 318
 238: LOAD_FAST            self
 240: LOAD_METHOD          send
 262: LOAD_FAST            byte_view
 264: LOAD_FAST            count
 266: LOAD_CONST           None
 268: BUILD_SLICE          
 270: BINARY_SUBSCR        
 280: PRECALL              
 284: CALL                 
 294: STORE_FAST           v
 296: LOAD_FAST            count
 298: LOAD_FAST            v
 300: BINARY_OP            +=
 304: STORE_FAST           count
 306: LOAD_FAST            count
 308: LOAD_FAST            amount
 310: COMPARE_OP           <
 316: POP_JUMP_BACKWARD_IF_TRUE to 238
 318: LOAD_CONST           None
 320: LOAD_CONST           None
 322: LOAD_CONST           None
 324: PRECALL              
 328: CALL                 
 338: POP_TOP              
 340: JUMP_FORWARD         to 364
 342: PUSH_EXC_INFO        
 344: WITH_EXCEPT_START    
 346: POP_JUMP_FORWARD_IF_TRUE to 356
 348: RERAISE              
 350: COPY                 
 352: POP_EXCEPT           
 354: RERAISE              
 356: POP_TOP              
 358: POP_EXCEPT           
 360: POP_TOP              
 362: POP_TOP              
 364: LOAD_CONST           None
 366: LOAD_CONST           None
 368: LOAD_CONST           None
 370: PRECALL              
 374: CALL                 
 384: POP_TOP              
 386: LOAD_CONST           None
 388: RETURN_VALUE         
 390: PUSH_EXC_INFO        
 392: WITH_EXCEPT_START    
 394: POP_JUMP_FORWARD_IF_TRUE to 404
 396: RERAISE              
 398: COPY                 
 400: POP_EXCEPT           
 402: RERAISE              
 404: POP_TOP              
 406: POP_EXCEPT           
 408: POP_TOP              
 410: POP_TOP              
 412: LOAD_CONST           None
 414: RETURN_VALUE         
 416: LOAD_GLOBAL          NULL + super
 428: PRECALL              
 432: CALL                 
 442: LOAD_METHOD          sendall
 464: LOAD_FAST            data
 466: LOAD_FAST            flags
 468: PRECALL              
 472: CALL                 
 482: RETURN_VALUE         
