# Disassembly for ssl.SSLSocket.getpeercert
# From module file: ssl

## co_consts:
(None,)

## co_names:
('_checkClosed', '_check_connected', '_sslobj', 'getpeercert')

## bytecode:

   0: RESUME               
   2: LOAD_FAST            self
   4: LOAD_METHOD          _checkClosed
  26: PRECALL              
  30: CALL                 
  40: POP_TOP              
  42: LOAD_FAST            self
  44: LOAD_METHOD          _check_connected
  66: PRECALL              
  70: CALL                 
  80: POP_TOP              
  82: LOAD_FAST            self
  84: LOAD_ATTR            _sslobj
  94: LOAD_METHOD          getpeercert
 116: LOAD_FAST            binary_form
 118: PRECALL              
 122: CALL                 
 132: RETURN_VALUE         
