# Disassembly for ssl.Purpose
# From module file: ssl

## co_consts:
('Purpose', 'SSLContext purpose flags with X509v3 Extended Key Usage objects\n    ', '1.3.6.1.5.5.7.3.1', '1.3.6.1.5.5.7.3.2', None)

## co_names:
('__name__', '__module__', '__qualname__', '__doc__', 'SERVER_AUTH', 'CLIENT_AUTH')

## bytecode:

   0: RESUME               
   2: LOAD_NAME            __name__
   4: STORE_NAME           __module__
   6: LOAD_CONST           'Purpose'
   8: STORE_NAME           __qualname__
  10: LOAD_CONST           'SSLContext purpose flags with X509v3 Extended Key Usage objects\n    '
  12: STORE_NAME           __doc__
  14: LOAD_CONST           '1.3.6.1.5.5.7.3.1'
  16: STORE_NAME           SERVER_AUTH
  18: LOAD_CONST           '1.3.6.1.5.5.7.3.2'
  20: STORE_NAME           CLIENT_AUTH
  22: LOAD_CONST           None
  24: RETURN_VALUE         
