# Disassembly for ssl._ASN1Object.__new__
# From module file: ssl

## co_consts:
(None, False, ('name',))

## co_names:
('super', '__new__', '_txt2obj')

## bytecode:

   0: COPY_FREE_VARS       
   2: RESUME               
   4: PUSH_NULL            
   6: LOAD_GLOBAL          NULL + super
  18: PRECALL              
  22: CALL                 
  32: LOAD_ATTR            __new__
  42: LOAD_FAST            cls
  44: BUILD_LIST           
  46: LOAD_GLOBAL          NULL + _txt2obj
  58: LOAD_FAST            oid
  60: LOAD_CONST           False
  62: KW_NAMES             
  64: PRECALL              
  68: CALL                 
  78: LIST_EXTEND          
  80: LIST_TO_TUPLE        
  82: CALL_FUNCTION_EX     
  84: RETURN_VALUE         
