# Disassembly for ssl.PEM_cert_to_DER_cert
# From module file: ssl

## co_consts:
('Takes a certificate in ASCII PEM format and returns the\n    DER-encoded version of it as a byte sequence', 'Invalid PEM encoding; must start with %s', 'Invalid PEM encoding; must end with %s', 'ASCII', 'strict')

## co_names:
('startswith', 'PEM_HEADER', 'ValueError', 'strip', 'endswith', 'PEM_FOOTER', 'len', 'base64', 'decodebytes', 'encode')

## bytecode:

   0: RESUME               
   2: LOAD_FAST            pem_cert_string
   4: LOAD_METHOD          startswith
  26: LOAD_GLOBAL          PEM_HEADER
  38: PRECALL              
  42: CALL                 
  52: POP_JUMP_FORWARD_IF_TRUE to 100
  54: LOAD_GLOBAL          NULL + ValueError
  66: LOAD_CONST           'Invalid PEM encoding; must start with %s'
  68: LOAD_GLOBAL          PEM_HEADER
  80: BINARY_OP            %
  84: PRECALL              
  88: CALL                 
  98: RAISE_VARARGS        
 100: LOAD_FAST            pem_cert_string
 102: LOAD_METHOD          strip
 124: PRECALL              
 128: CALL                 
 138: LOAD_METHOD          endswith
 160: LOAD_GLOBAL          PEM_FOOTER
 172: PRECALL              
 176: CALL                 
 186: POP_JUMP_FORWARD_IF_TRUE to 234
 188: LOAD_GLOBAL          NULL + ValueError
 200: LOAD_CONST           'Invalid PEM encoding; must end with %s'
 202: LOAD_GLOBAL          PEM_FOOTER
 214: BINARY_OP            %
 218: PRECALL              
 222: CALL                 
 232: RAISE_VARARGS        
 234: LOAD_FAST            pem_cert_string
 236: LOAD_METHOD          strip
 258: PRECALL              
 262: CALL                 
 272: LOAD_GLOBAL          NULL + len
 284: LOAD_GLOBAL          PEM_HEADER
 296: PRECALL              
 300: CALL                 
 310: LOAD_GLOBAL          NULL + len
 322: LOAD_GLOBAL          PEM_FOOTER
 334: PRECALL              
 338: CALL                 
 348: UNARY_NEGATIVE       
 350: BUILD_SLICE          
 352: BINARY_SUBSCR        
 362: STORE_FAST           d
 364: LOAD_GLOBAL          NULL + base64
 376: LOAD_ATTR            decodebytes
 386: LOAD_FAST            d
 388: LOAD_METHOD          encode
 410: LOAD_CONST           'ASCII'
 412: LOAD_CONST           'strict'
 414: PRECALL              
 418: CALL                 
 428: PRECALL              
 432: CALL                 
 442: RETURN_VALUE         
