# Disassembly for ssl.SSLObject.read
# From module file: ssl

## co_consts:
("Read up to 'len' bytes from the SSL object and return them.\n\n        If 'buffer' is provided, read into this buffer and return the number of\n        bytes read.\n        ",)

## co_names:
('_sslobj', 'read')

## bytecode:

   0: RESUME               
   2: LOAD_FAST            buffer
   4: POP_JUMP_FORWARD_IF_NONE to 62
   6: LOAD_FAST            self
   8: LOAD_ATTR            _sslobj
  18: LOAD_METHOD          read
  40: LOAD_FAST            len
  42: LOAD_FAST            buffer
  44: PRECALL              
  48: CALL                 
  58: STORE_FAST           v
  60: JUMP_FORWARD         to 114
  62: LOAD_FAST            self
  64: LOAD_ATTR            _sslobj
  74: LOAD_METHOD          read
  96: LOAD_FAST            len
  98: PRECALL              
 102: CALL                 
 112: STORE_FAST           v
 114: LOAD_FAST            v
 116: RETURN_VALUE         
