# Disassembly for ssl.SSLObject._create
# From module file: ssl

## co_consts:
(None, ('server_side', 'server_hostname', 'owner', 'session'))

## co_names:
('__new__', '_wrap_bio', '_sslobj')

## bytecode:

   0: RESUME               
   2: LOAD_FAST            cls
   4: LOAD_METHOD          __new__
  26: LOAD_FAST            cls
  28: PRECALL              
  32: CALL                 
  42: STORE_FAST           self
  44: LOAD_FAST            context
  46: LOAD_METHOD          _wrap_bio
  68: LOAD_FAST            incoming
  70: LOAD_FAST            outgoing
  72: LOAD_FAST            server_side
  74: LOAD_FAST            server_hostname
  76: LOAD_FAST            self
  78: LOAD_FAST            session
  80: KW_NAMES             
  82: PRECALL              
  86: CALL                 
  96: STORE_FAST           sslobj
  98: LOAD_FAST            sslobj
 100: LOAD_FAST            self
 102: STORE_ATTR           _sslobj
 112: LOAD_FAST            self
 114: RETURN_VALUE         
