# Disassembly for ssl.SSLSocket.get_channel_binding
# From module file: ssl

## co_consts:
(None, '{0} channel binding type not implemented')

## co_names:
('_sslobj', 'get_channel_binding', 'CHANNEL_BINDING_TYPES', 'ValueError', 'format')

## bytecode:

   0: RESUME               
   2: LOAD_FAST            self
   4: LOAD_ATTR            _sslobj
  14: POP_JUMP_FORWARD_IF_NONE to 68
  16: LOAD_FAST            self
  18: LOAD_ATTR            _sslobj
  28: LOAD_METHOD          get_channel_binding
  50: LOAD_FAST            cb_type
  52: PRECALL              
  56: CALL                 
  66: RETURN_VALUE         
  68: LOAD_FAST            cb_type
  70: LOAD_GLOBAL          CHANNEL_BINDING_TYPES
  82: CONTAINS_OP          
  84: POP_JUMP_FORWARD_IF_FALSE to 154
  86: LOAD_GLOBAL          NULL + ValueError
  98: LOAD_CONST           '{0} channel binding type not implemented'
 100: LOAD_METHOD          format
 122: LOAD_FAST            cb_type
 124: PRECALL              
 128: CALL                 
 138: PRECALL              
 142: CALL                 
 152: RAISE_VARARGS        
 154: LOAD_CONST           None
 156: RETURN_VALUE         
