# Disassembly for ssl.SSLContext.__new__
# From module file: ssl

## co_consts:
(None, 'ssl.SSLContext() without protocol argument is deprecated.', 2, ('category', 'stacklevel'))

## co_names:
('warnings', 'warn', 'DeprecationWarning', 'PROTOCOL_TLS', '_SSLContext', '__new__')

## bytecode:

   0: RESUME               
   2: LOAD_FAST            protocol
   4: POP_JUMP_FORWARD_IF_NOT_NONE to 76
   6: LOAD_GLOBAL          NULL + warnings
  18: LOAD_ATTR            warn
  28: LOAD_CONST           'ssl.SSLContext() without protocol argument is deprecated.'
  30: LOAD_GLOBAL          DeprecationWarning
  42: LOAD_CONST           2
  44: KW_NAMES             
  46: PRECALL              
  50: CALL                 
  60: POP_TOP              
  62: LOAD_GLOBAL          PROTOCOL_TLS
  74: STORE_FAST           protocol
  76: LOAD_GLOBAL          NULL + _SSLContext
  88: LOAD_ATTR            __new__
  98: LOAD_FAST            cls
 100: LOAD_FAST            protocol
 102: PRECALL              
 106: CALL                 
 116: STORE_FAST           self
 118: LOAD_FAST            self
 120: RETURN_VALUE         
