# Disassembly for ssl.SSLSocket.version
# From module file: ssl

## co_consts:
(None,)

## co_names:
('_sslobj', 'version')

## bytecode:

   0: RESUME               
   2: LOAD_FAST            self
   4: LOAD_ATTR            _sslobj
  14: POP_JUMP_FORWARD_IF_NONE to 66
  16: LOAD_FAST            self
  18: LOAD_ATTR            _sslobj
  28: LOAD_METHOD          version
  50: PRECALL              
  54: CALL                 
  64: RETURN_VALUE         
  66: LOAD_CONST           None
  68: RETURN_VALUE         
