# Disassembly for ssl._ASN1Object.fromname
# From module file: ssl

## co_consts:
('Create _ASN1Object from short name, long name or OID\n        ', True, ('name',))

## co_names:
('super', '__new__', '_txt2obj')

## bytecode:

   0: COPY_FREE_VARS       
   2: RESUME               
   4: PUSH_NULL            
   6: LOAD_GLOBAL          NULL + super
  18: PRECALL              
  22: CALL                 
  32: LOAD_ATTR            __new__
  42: LOAD_FAST            cls
  44: BUILD_LIST           
  46: LOAD_GLOBAL          NULL + _txt2obj
  58: LOAD_FAST            name
  60: LOAD_CONST           True
  62: KW_NAMES             
  64: PRECALL              
  68: CALL                 
  78: LIST_EXTEND          
  80: LIST_TO_TUPLE        
  82: CALL_FUNCTION_EX     
  84: RETURN_VALUE         
