# Disassembly for ssl.SSLContext.wrap_socket
# From module file: ssl

## co_consts:
(None, ('sock', 'server_side', 'do_handshake_on_connect', 'suppress_ragged_eofs', 'server_hostname', 'context', 'session'))

## co_names:
('sslsocket_class', '_create')

## bytecode:

   0: RESUME               
   2: LOAD_FAST            self
   4: LOAD_ATTR            sslsocket_class
  14: LOAD_METHOD          _create
  36: LOAD_FAST            sock
  38: LOAD_FAST            server_side
  40: LOAD_FAST            do_handshake_on_connect
  42: LOAD_FAST            suppress_ragged_eofs
  44: LOAD_FAST            server_hostname
  46: LOAD_FAST            self
  48: LOAD_FAST            session
  50: KW_NAMES             
  52: PRECALL              
  56: CALL                 
  66: RETURN_VALUE         
