# Disassembly for ssl.SSLObject.get_channel_binding
# From module file: ssl

## co_consts:
('Get channel binding data for current connection.  Raise ValueError\n        if the requested `cb_type` is not supported.  Return bytes of the data\n        or None if the data is not available (e.g. before the handshake).',)

## co_names:
('_sslobj', 'get_channel_binding')

## bytecode:

   0: RESUME               
   2: LOAD_FAST            self
   4: LOAD_ATTR            _sslobj
  14: LOAD_METHOD          get_channel_binding
  36: LOAD_FAST            cb_type
  38: PRECALL              
  42: CALL                 
  52: RETURN_VALUE         
