# Disassembly for ssl.SSLContext._msg_callback.inner
# From module file: ssl

## co_consts:
(None,)

## co_names:
('TLSVersion', 'ValueError', '_TLSContentType', 'HEADER', 'ALERT', '_TLSAlertType', '_TLSMessageType')

## bytecode:

   0: COPY_FREE_VARS       
   2: RESUME               
   4: NOP                  
   6: LOAD_GLOBAL          NULL + TLSVersion
  18: LOAD_FAST            version
  20: PRECALL              
  24: CALL                 
  34: STORE_FAST           version
  36: JUMP_FORWARD         to 70
  38: PUSH_EXC_INFO        
  40: LOAD_GLOBAL          ValueError
  52: CHECK_EXC_MATCH      
  54: POP_JUMP_FORWARD_IF_FALSE to 62
  56: POP_TOP              
  58: POP_EXCEPT           
  60: JUMP_FORWARD         to 70
  62: RERAISE              
  64: COPY                 
  66: POP_EXCEPT           
  68: RERAISE              
  70: NOP                  
  72: LOAD_GLOBAL          NULL + _TLSContentType
  84: LOAD_FAST            content_type
  86: PRECALL              
  90: CALL                 
 100: STORE_FAST           content_type
 102: JUMP_FORWARD         to 136
 104: PUSH_EXC_INFO        
 106: LOAD_GLOBAL          ValueError
 118: CHECK_EXC_MATCH      
 120: POP_JUMP_FORWARD_IF_FALSE to 128
 122: POP_TOP              
 124: POP_EXCEPT           
 126: JUMP_FORWARD         to 136
 128: RERAISE              
 130: COPY                 
 132: POP_EXCEPT           
 134: RERAISE              
 136: LOAD_FAST            content_type
 138: LOAD_GLOBAL          _TLSContentType
 150: LOAD_ATTR            HEADER
 160: COMPARE_OP           ==
 166: POP_JUMP_FORWARD_IF_FALSE to 184
 168: LOAD_GLOBAL          _TLSContentType
 180: STORE_FAST           msg_enum
 182: JUMP_FORWARD         to 246
 184: LOAD_FAST            content_type
 186: LOAD_GLOBAL          _TLSContentType
 198: LOAD_ATTR            ALERT
 208: COMPARE_OP           ==
 214: POP_JUMP_FORWARD_IF_FALSE to 232
 216: LOAD_GLOBAL          _TLSAlertType
 228: STORE_FAST           msg_enum
 230: JUMP_FORWARD         to 246
 232: LOAD_GLOBAL          _TLSMessageType
 244: STORE_FAST           msg_enum
 246: NOP                  
 248: PUSH_NULL            
 250: LOAD_FAST            msg_enum
 252: LOAD_FAST            msg_type
 254: PRECALL              
 258: CALL                 
 268: STORE_FAST           msg_type
 270: JUMP_FORWARD         to 304
 272: PUSH_EXC_INFO        
 274: LOAD_GLOBAL          ValueError
 286: CHECK_EXC_MATCH      
 288: POP_JUMP_FORWARD_IF_FALSE to 296
 290: POP_TOP              
 292: POP_EXCEPT           
 294: JUMP_FORWARD         to 304
 296: RERAISE              
 298: COPY                 
 300: POP_EXCEPT           
 302: RERAISE              
 304: PUSH_NULL            
 306: LOAD_DEREF           callback
 308: LOAD_FAST            conn
 310: LOAD_FAST            direction
 312: LOAD_FAST            version
 314: LOAD_FAST            content_type
 316: LOAD_FAST            msg_type
 318: LOAD_FAST            data
 320: PRECALL              
 324: CALL                 
 334: RETURN_VALUE         
