# Disassembly for ssl.SSLSocket.sendto
# From module file: ssl

## co_consts:
(None, 'sendto not allowed on instances of %s')

## co_names:
('_checkClosed', '_sslobj', 'ValueError', '__class__', 'super', 'sendto')

## bytecode:

   0: COPY_FREE_VARS       
   2: RESUME               
   4: LOAD_FAST            self
   6: LOAD_METHOD          _checkClosed
  28: PRECALL              
  32: CALL                 
  42: POP_TOP              
  44: LOAD_FAST            self
  46: LOAD_ATTR            _sslobj
  56: POP_JUMP_FORWARD_IF_NONE to 104
  58: LOAD_GLOBAL          NULL + ValueError
  70: LOAD_CONST           'sendto not allowed on instances of %s'
  72: LOAD_FAST            self
  74: LOAD_ATTR            __class__
  84: BINARY_OP            %
  88: PRECALL              
  92: CALL                 
 102: RAISE_VARARGS        
 104: LOAD_FAST            addr
 106: POP_JUMP_FORWARD_IF_NOT_NONE to 176
 108: LOAD_GLOBAL          NULL + super
 120: PRECALL              
 124: CALL                 
 134: LOAD_METHOD          sendto
 156: LOAD_FAST            data
 158: LOAD_FAST            flags_or_addr
 160: PRECALL              
 164: CALL                 
 174: RETURN_VALUE         
 176: LOAD_GLOBAL          NULL + super
 188: PRECALL              
 192: CALL                 
 202: LOAD_METHOD          sendto
 224: LOAD_FAST            data
 226: LOAD_FAST            flags_or_addr
 228: LOAD_FAST            addr
 230: PRECALL              
 234: CALL                 
 244: RETURN_VALUE         
