# Disassembly for ssl.SSLSocket.do_handshake
# From module file: ssl

## co_consts:
(None, 0.0)

## co_names:
('_check_connected', 'gettimeout', 'settimeout', '_sslobj', 'do_handshake')

## bytecode:

   0: RESUME               
   2: LOAD_FAST            self
   4: LOAD_METHOD          _check_connected
  26: PRECALL              
  30: CALL                 
  40: POP_TOP              
  42: LOAD_FAST            self
  44: LOAD_METHOD          gettimeout
  66: PRECALL              
  70: CALL                 
  80: STORE_FAST           timeout
  82: NOP                  
  84: LOAD_FAST            timeout
  86: LOAD_CONST           0.0
  88: COMPARE_OP           ==
  94: POP_JUMP_FORWARD_IF_FALSE to 142
  96: LOAD_FAST            block
  98: POP_JUMP_FORWARD_IF_FALSE to 142
 100: LOAD_FAST            self
 102: LOAD_METHOD          settimeout
 124: LOAD_CONST           None
 126: PRECALL              
 130: CALL                 
 140: POP_TOP              
 142: LOAD_FAST            self
 144: LOAD_ATTR            _sslobj
 154: LOAD_METHOD          do_handshake
 176: PRECALL              
 180: CALL                 
 190: POP_TOP              
 192: LOAD_FAST            self
 194: LOAD_METHOD          settimeout
 216: LOAD_FAST            timeout
 218: PRECALL              
 222: CALL                 
 232: POP_TOP              
 234: LOAD_CONST           None
 236: RETURN_VALUE         
 238: PUSH_EXC_INFO        
 240: LOAD_FAST            self
 242: LOAD_METHOD          settimeout
 264: LOAD_FAST            timeout
 266: PRECALL              
 270: CALL                 
 280: POP_TOP              
 282: RERAISE              
 284: COPY                 
 286: POP_EXCEPT           
 288: RERAISE              
