# Disassembly for ssl.SSLSocket.accept
# From module file: ssl

## co_consts:
('Accepts a new connection from a remote client, and returns\n        a tuple containing that new connection wrapped with a server-side\n        SSL channel, and the address of the remote client.', True, ('do_handshake_on_connect', 'suppress_ragged_eofs', 'server_side'))

## co_names:
('super', 'accept', 'context', 'wrap_socket', 'do_handshake_on_connect', 'suppress_ragged_eofs')

## bytecode:

   0: COPY_FREE_VARS       
   2: RESUME               
   4: LOAD_GLOBAL          NULL + super
  16: PRECALL              
  20: CALL                 
  30: LOAD_METHOD          accept
  52: PRECALL              
  56: CALL                 
  66: UNPACK_SEQUENCE      
  70: STORE_FAST           newsock
  72: STORE_FAST           addr
  74: LOAD_FAST            self
  76: LOAD_ATTR            context
  86: LOAD_METHOD          wrap_socket
 108: LOAD_FAST            newsock
 110: LOAD_FAST            self
 112: LOAD_ATTR            do_handshake_on_connect
 122: LOAD_FAST            self
 124: LOAD_ATTR            suppress_ragged_eofs
 134: LOAD_CONST           True
 136: KW_NAMES             
 138: PRECALL              
 142: CALL                 
 152: STORE_FAST           newsock
 154: LOAD_FAST            newsock
 156: LOAD_FAST            addr
 158: BUILD_TUPLE          
 160: RETURN_VALUE         
