# Disassembly for ssl.SSLSocket.recv_into
# From module file: ssl

## co_consts:
(None, 1024, 0, 'non-zero flags not allowed in calls to recv_into() on %s')

## co_names:
('_checkClosed', 'len', '_sslobj', 'ValueError', '__class__', 'read', 'super', 'recv_into')

## bytecode:

   0: COPY_FREE_VARS       
   2: RESUME               
   4: LOAD_FAST            self
   6: LOAD_METHOD          _checkClosed
  28: PRECALL              
  32: CALL                 
  42: POP_TOP              
  44: LOAD_FAST            buffer
  46: POP_JUMP_FORWARD_IF_FALSE to 84
  48: LOAD_FAST            nbytes
  50: POP_JUMP_FORWARD_IF_NOT_NONE to 84
  52: LOAD_GLOBAL          NULL + len
  64: LOAD_FAST            buffer
  66: PRECALL              
  70: CALL                 
  80: STORE_FAST           nbytes
  82: JUMP_FORWARD         to 92
  84: LOAD_FAST            nbytes
  86: POP_JUMP_FORWARD_IF_NOT_NONE to 92
  88: LOAD_CONST           1024
  90: STORE_FAST           nbytes
  92: LOAD_FAST            self
  94: LOAD_ATTR            _sslobj
 104: POP_JUMP_FORWARD_IF_NONE to 208
 106: LOAD_FAST            flags
 108: LOAD_CONST           0
 110: COMPARE_OP           !=
 116: POP_JUMP_FORWARD_IF_FALSE to 164
 118: LOAD_GLOBAL          NULL + ValueError
 130: LOAD_CONST           'non-zero flags not allowed in calls to recv_into() on %s'
 132: LOAD_FAST            self
 134: LOAD_ATTR            __class__
 144: BINARY_OP            %
 148: PRECALL              
 152: CALL                 
 162: RAISE_VARARGS        
 164: LOAD_FAST            self
 166: LOAD_METHOD          read
 188: LOAD_FAST            nbytes
 190: LOAD_FAST            buffer
 192: PRECALL              
 196: CALL                 
 206: RETURN_VALUE         
 208: LOAD_GLOBAL          NULL + super
 220: PRECALL              
 224: CALL                 
 234: LOAD_METHOD          recv_into
 256: LOAD_FAST            buffer
 258: LOAD_FAST            nbytes
 260: LOAD_FAST            flags
 262: PRECALL              
 266: CALL                 
 276: RETURN_VALUE         
