# Disassembly for ssl.SSLContext.maximum_version
# From module file: ssl

## co_consts:
(None,)

## co_names:
('super', 'SSLContext', 'maximum_version', '__set__')

## bytecode:

   0: COPY_FREE_VARS       
   2: RESUME               
   4: LOAD_GLOBAL          NULL + super
  16: LOAD_GLOBAL          SSLContext
  28: LOAD_GLOBAL          SSLContext
  40: PRECALL              
  44: CALL                 
  54: LOAD_ATTR            maximum_version
  64: LOAD_METHOD          __set__
  86: LOAD_FAST            self
  88: LOAD_FAST            value
  90: PRECALL              
  94: CALL                 
 104: POP_TOP              
 106: LOAD_CONST           None
 108: RETURN_VALUE         
