# Disassembly for lobby.Lobby.get_options
# From module file: lobby

## co_consts:
(None, ('X', 'Try to leave.'), ('F', 'Go through Employees Only door.'), ('L', 'Go through left door.'))

## co_names:
('super', 'get_options', 'append')

## bytecode:

   0: COPY_FREE_VARS       
   2: RESUME               
   4: LOAD_GLOBAL          NULL + super
  16: PRECALL              
  20: CALL                 
  30: LOAD_METHOD          get_options
  52: PRECALL              
  56: CALL                 
  66: STORE_FAST           options
  68: LOAD_FAST            options
  70: LOAD_METHOD          append
  92: LOAD_CONST           ('X', 'Try to leave.')
  94: PRECALL              
  98: CALL                 
 108: POP_TOP              
 110: LOAD_FAST            options
 112: LOAD_METHOD          append
 134: LOAD_CONST           ('F', 'Go through Employees Only door.')
 136: PRECALL              
 140: CALL                 
 150: POP_TOP              
 152: LOAD_FAST            options
 154: LOAD_METHOD          append
 176: LOAD_CONST           ('L', 'Go through left door.')
 178: PRECALL              
 182: CALL                 
 192: POP_TOP              
 194: LOAD_FAST            options
 196: RETURN_VALUE         
