# Disassembly for lobby.Notepad.take
# From module file: lobby

## co_consts:
(None, 'You grab the notepad and pen.')

## co_names:
('set_parent', 'world', 'player', 'send_message')

## bytecode:

   0: RESUME               
   2: LOAD_FAST            self
   4: LOAD_METHOD          set_parent
  26: LOAD_FAST            self
  28: LOAD_ATTR            world
  38: LOAD_ATTR            player
  48: PRECALL              
  52: CALL                 
  62: POP_TOP              
  64: LOAD_FAST            self
  66: LOAD_METHOD          send_message
  88: LOAD_CONST           'You grab the notepad and pen.'
  90: PRECALL              
  94: CALL                 
 104: POP_TOP              
 106: LOAD_CONST           None
 108: RETURN_VALUE         
