# Disassembly for lobby.TicketMachine.get_description
# From module file: lobby

## co_consts:
(None, 'The ticket machine parts lay broken on the floor.', "There is a dusty, classic ticket machine on a post next to the counter.  Maybe take a ticket so you know when it's your turn?")

## co_names:
('broken',)

## bytecode:

   0: RESUME               
   2: LOAD_FAST            self
   4: LOAD_ATTR            broken
  14: POP_JUMP_FORWARD_IF_FALSE to 20
  16: LOAD_CONST           'The ticket machine parts lay broken on the floor.'
  18: RETURN_VALUE         
  20: NOP                  
  22: LOAD_CONST           "There is a dusty, classic ticket machine on a post next to the counter.  Maybe take a ticket so you know when it's your turn?"
  24: RETURN_VALUE         
