# Disassembly for lobby.TicketMachine.use
# From module file: lobby

## co_consts:
(None, True, 'You take the next ticket from the machine.  Looks like you are E5.\nThe machine falls apart on the counter and kicks up a cloud of dust.\nAt least you have a ticket now.  Anyone else that shows up is out of luck.')

## co_names:
('broken', 'send_message', 'Ticket', 'set_parent', 'world', 'player')

## bytecode:

   0: RESUME               
   2: LOAD_CONST           True
   4: LOAD_FAST            self
   6: STORE_ATTR           broken
  16: LOAD_FAST            self
  18: LOAD_METHOD          send_message
  40: LOAD_CONST           'You take the next ticket from the machine.  Looks like you are E5.\nThe machine falls apart on the counter and kicks up a cloud of dust.\nAt least you have a ticket now.  Anyone else that shows up is out of luck.'
  42: PRECALL              
  46: CALL                 
  56: POP_TOP              
  58: LOAD_GLOBAL          NULL + Ticket
  70: PRECALL              
  74: CALL                 
  84: LOAD_METHOD          set_parent
 106: LOAD_FAST            self
 108: LOAD_ATTR            world
 118: LOAD_ATTR            player
 128: PRECALL              
 132: CALL                 
 142: POP_TOP              
 144: LOAD_CONST           None
 146: RETURN_VALUE         
