# Disassembly for lobby.Telephone.__init__
# From module file: lobby

## co_consts:
(None, False)

## co_names:
('super', '__init__', 'plugged_in', 'tried_phone', 'ready_for_number')

## bytecode:

   0: COPY_FREE_VARS       
   2: RESUME               
   4: LOAD_GLOBAL          NULL + super
  16: PRECALL              
  20: CALL                 
  30: LOAD_METHOD          __init__
  52: LOAD_FAST            name
  54: PRECALL              
  58: CALL                 
  68: POP_TOP              
  70: LOAD_CONST           False
  72: LOAD_FAST            self
  74: STORE_ATTR           plugged_in
  84: LOAD_CONST           False
  86: LOAD_FAST            self
  88: STORE_ATTR           tried_phone
  98: LOAD_CONST           False
 100: LOAD_FAST            self
 102: STORE_ATTR           ready_for_number
 112: LOAD_CONST           None
 114: RETURN_VALUE         
