# Disassembly for lobby.SignInSheet.read
# From module file: lobby

## co_consts:
(None, True, 'Looks like a sing in sheet for interviews.\nThese must be the previous people who tried to get a job here.\nThe list has:\n --- Hank Little\n --- Barbara James\n --- Chuck Huitt\n --- Emily Johnson', '\n --- %s')

## co_names:
('sheet_read', 'signed', 'world', 'player', 'name', 'send_message')

## bytecode:

   0: RESUME               
   2: LOAD_CONST           True
   4: LOAD_FAST            self
   6: STORE_ATTR           sheet_read
  16: LOAD_CONST           'Looks like a sing in sheet for interviews.\nThese must be the previous people who tried to get a job here.\nThe list has:\n --- Hank Little\n --- Barbara James\n --- Chuck Huitt\n --- Emily Johnson'
  18: STORE_FAST           message
  20: LOAD_FAST            self
  22: LOAD_ATTR            signed
  32: POP_JUMP_FORWARD_IF_FALSE to 80
  34: LOAD_FAST            message
  36: LOAD_CONST           '\n --- %s'
  38: LOAD_FAST            self
  40: LOAD_ATTR            world
  50: LOAD_ATTR            player
  60: LOAD_ATTR            name
  70: BINARY_OP            %
  74: BINARY_OP            +=
  78: STORE_FAST           message
  80: LOAD_FAST            self
  82: LOAD_METHOD          send_message
 104: LOAD_FAST            message
 106: PRECALL              
 110: CALL                 
 120: POP_TOP              
 122: LOAD_CONST           None
 124: RETURN_VALUE         
