# Disassembly for lobby.Telephone.dial_extension
# From module file: lobby

## co_consts:
(None, 'Enter 2 digit extension', 2, "The pops and crackles stop.  It's quiet for few seconds.\nThen a woman's voice says:\n --- Cat...Dog...Mouse", 'You hear more pops and crackles...then a faint song in the background.\nIs that Happy Birthday?')

## co_names:
('ask_number', 'world', 'player', 'age', 'send_message')

## bytecode:

   0: RESUME               
   2: LOAD_FAST            self
   4: LOAD_METHOD          ask_number
  26: LOAD_CONST           'Enter 2 digit extension'
  28: LOAD_CONST           2
  30: PRECALL              
  34: CALL                 
  44: STORE_FAST           extension
  46: LOAD_FAST            extension
  48: LOAD_FAST            self
  50: LOAD_ATTR            world
  60: LOAD_ATTR            player
  70: LOAD_ATTR            age
  80: COMPARE_OP           ==
  86: POP_JUMP_FORWARD_IF_FALSE to 134
  88: LOAD_FAST            self
  90: LOAD_METHOD          send_message
 112: LOAD_CONST           "The pops and crackles stop.  It's quiet for few seconds.\nThen a woman's voice says:\n --- Cat...Dog...Mouse"
 114: PRECALL              
 118: CALL                 
 128: POP_TOP              
 130: LOAD_CONST           None
 132: RETURN_VALUE         
 134: LOAD_FAST            self
 136: LOAD_METHOD          send_message
 158: LOAD_CONST           'You hear more pops and crackles...then a faint song in the background.\nIs that Happy Birthday?'
 160: PRECALL              
 164: CALL                 
 174: POP_TOP              
 176: LOAD_CONST           None
 178: RETURN_VALUE         
