# Disassembly for zipfile._get_decompressor
# From module file: zipfile

## co_consts:
(None, -15, 'compression type %d (%s)', 'compression type %d')

## co_names:
('_check_compression', 'ZIP_STORED', 'ZIP_DEFLATED', 'zlib', 'decompressobj', 'ZIP_BZIP2', 'bz2', 'BZ2Decompressor', 'ZIP_LZMA', 'LZMADecompressor', 'compressor_names', 'get', 'NotImplementedError')

## bytecode:

   0: RESUME               
   2: LOAD_GLOBAL          NULL + _check_compression
  14: LOAD_FAST            compress_type
  16: PRECALL              
  20: CALL                 
  30: POP_TOP              
  32: LOAD_FAST            compress_type
  34: LOAD_GLOBAL          ZIP_STORED
  46: COMPARE_OP           ==
  52: POP_JUMP_FORWARD_IF_FALSE to 58
  54: LOAD_CONST           None
  56: RETURN_VALUE         
  58: LOAD_FAST            compress_type
  60: LOAD_GLOBAL          ZIP_DEFLATED
  72: COMPARE_OP           ==
  78: POP_JUMP_FORWARD_IF_FALSE to 120
  80: LOAD_GLOBAL          NULL + zlib
  92: LOAD_ATTR            decompressobj
 102: LOAD_CONST           -15
 104: PRECALL              
 108: CALL                 
 118: RETURN_VALUE         
 120: LOAD_FAST            compress_type
 122: LOAD_GLOBAL          ZIP_BZIP2
 134: COMPARE_OP           ==
 140: POP_JUMP_FORWARD_IF_FALSE to 180
 142: LOAD_GLOBAL          NULL + bz2
 154: LOAD_ATTR            BZ2Decompressor
 164: PRECALL              
 168: CALL                 
 178: RETURN_VALUE         
 180: LOAD_FAST            compress_type
 182: LOAD_GLOBAL          ZIP_LZMA
 194: COMPARE_OP           ==
 200: POP_JUMP_FORWARD_IF_FALSE to 230
 202: LOAD_GLOBAL          NULL + LZMADecompressor
 214: PRECALL              
 218: CALL                 
 228: RETURN_VALUE         
 230: LOAD_GLOBAL          compressor_names
 242: LOAD_METHOD          get
 264: LOAD_FAST            compress_type
 266: PRECALL              
 270: CALL                 
 280: STORE_FAST           descr
 282: LOAD_FAST            descr
 284: POP_JUMP_FORWARD_IF_FALSE to 326
 286: LOAD_GLOBAL          NULL + NotImplementedError
 298: LOAD_CONST           'compression type %d (%s)'
 300: LOAD_FAST            compress_type
 302: LOAD_FAST            descr
 304: BUILD_TUPLE          
 306: BINARY_OP            %
 310: PRECALL              
 314: CALL                 
 324: RAISE_VARARGS        
 326: LOAD_GLOBAL          NULL + NotImplementedError
 338: LOAD_CONST           'compression type %d'
 340: LOAD_FAST            compress_type
 342: BUILD_TUPLE          
 344: BINARY_OP            %
 348: PRECALL              
 352: CALL                 
 362: RAISE_VARARGS        
