# Disassembly for zipfile.ZipExtFile.seekable
# From module file: zipfile

## co_consts:
(None, 'I/O operation on closed file.')

## co_names:
('closed', 'ValueError', '_seekable')

## bytecode:

   0: RESUME               
   2: LOAD_FAST            self
   4: LOAD_ATTR            closed
  14: POP_JUMP_FORWARD_IF_FALSE to 46
  16: LOAD_GLOBAL          NULL + ValueError
  28: LOAD_CONST           'I/O operation on closed file.'
  30: PRECALL              
  34: CALL                 
  44: RAISE_VARARGS        
  46: LOAD_FAST            self
  48: LOAD_ATTR            _seekable
  58: RETURN_VALUE         
