# Disassembly for zipfile.LargeZipFile
# From module file: zipfile

## co_consts:
('LargeZipFile', '\n    Raised when writing a zipfile, the zipfile requires ZIP64 extensions\n    and those extensions are disabled.\n    ', None)

## co_names:
('__name__', '__module__', '__qualname__', '__doc__')

## bytecode:

   0: RESUME               
   2: LOAD_NAME            __name__
   4: STORE_NAME           __module__
   6: LOAD_CONST           'LargeZipFile'
   8: STORE_NAME           __qualname__
  10: LOAD_CONST           '\n    Raised when writing a zipfile, the zipfile requires ZIP64 extensions\n    and those extensions are disabled.\n    '
  12: STORE_NAME           __doc__
  14: LOAD_CONST           None
  16: RETURN_VALUE         
