# Disassembly for zipfile.PyZipFile._get_codename._compile
# From module file: zipfile

## co_consts:
(None, 0, 'Compiling', True, ('doraise', 'optimize'), False)

## co_names:
('py_compile', 'debug', 'print', 'compile', 'PyCompileError', 'msg')

## bytecode:

   0: COPY_FREE_VARS       
   2: RESUME               
   4: LOAD_CONST           0
   6: LOAD_CONST           None
   8: IMPORT_NAME          py_compile
  10: STORE_FAST           py_compile
  12: LOAD_DEREF           self
  14: LOAD_ATTR            debug
  24: POP_JUMP_FORWARD_IF_FALSE to 58
  26: LOAD_GLOBAL          NULL + print
  38: LOAD_CONST           'Compiling'
  40: LOAD_FAST            file
  42: PRECALL              
  46: CALL                 
  56: POP_TOP              
  58: NOP                  
  60: LOAD_FAST            py_compile
  62: LOAD_METHOD          compile
  84: LOAD_FAST            file
  86: LOAD_CONST           True
  88: LOAD_FAST            optimize
  90: KW_NAMES             
  92: PRECALL              
  96: CALL                 
 106: POP_TOP              
 108: JUMP_FORWARD         to 198
 110: PUSH_EXC_INFO        
 112: LOAD_FAST            py_compile
 114: LOAD_ATTR            PyCompileError
 124: CHECK_EXC_MATCH      
 126: POP_JUMP_FORWARD_IF_FALSE to 190
 128: STORE_FAST           err
 130: LOAD_GLOBAL          NULL + print
 142: LOAD_FAST            err
 144: LOAD_ATTR            msg
 154: PRECALL              
 158: CALL                 
 168: POP_TOP              
 170: POP_EXCEPT           
 172: LOAD_CONST           None
 174: STORE_FAST           err
 176: DELETE_FAST          err
 178: LOAD_CONST           False
 180: RETURN_VALUE         
 182: LOAD_CONST           None
 184: STORE_FAST           err
 186: DELETE_FAST          err
 188: RERAISE              
 190: RERAISE              
 192: COPY                 
 194: POP_EXCEPT           
 196: RERAISE              
 198: LOAD_CONST           True
 200: RETURN_VALUE         
