# Disassembly for zipfile.ZipFile._extract_member.<genexpr>
# From module file: zipfile

## co_consts:
(None,)

## co_names:
()

## bytecode:

   0: COPY_FREE_VARS       
   2: RETURN_GENERATOR     
   4: POP_TOP              
   6: RESUME               
   8: LOAD_FAST            .0
  10: FOR_ITER             to 32
  12: STORE_FAST           x
  14: LOAD_FAST            x
  16: LOAD_DEREF           invalid_path_parts
  18: CONTAINS_OP          
  20: POP_JUMP_BACKWARD_IF_FALSE to 10
  22: LOAD_FAST            x
  24: YIELD_VALUE          
  26: RESUME               
  28: POP_TOP              
  30: JUMP_BACKWARD        to 10
  32: LOAD_CONST           None
  34: RETURN_VALUE         
