# Disassembly for zipfile._difference
# From module file: zipfile

## co_consts:
('\n    Return items in minuend not in subtrahend, retaining order\n    with O(1) lookup.\n    ',)

## co_names:
('itertools', 'filterfalse', 'set', '__contains__')

## bytecode:

   0: RESUME               
   2: LOAD_GLOBAL          NULL + itertools
  14: LOAD_ATTR            filterfalse
  24: LOAD_GLOBAL          NULL + set
  36: LOAD_FAST            subtrahend
  38: PRECALL              
  42: CALL                 
  52: LOAD_ATTR            __contains__
  62: LOAD_FAST            minuend
  64: PRECALL              
  68: CALL                 
  78: RETURN_VALUE         
