# Disassembly for zipfile.Path._base
# From module file: zipfile

## co_consts:
(None,)

## co_names:
('pathlib', 'PurePosixPath', 'at', 'root', 'filename')

## bytecode:

   0: RESUME               
   2: LOAD_GLOBAL          NULL + pathlib
  14: LOAD_ATTR            PurePosixPath
  24: LOAD_FAST            self
  26: LOAD_ATTR            at
  36: JUMP_IF_TRUE_OR_POP  to 60
  38: LOAD_FAST            self
  40: LOAD_ATTR            root
  50: LOAD_ATTR            filename
  60: PRECALL              
  64: CALL                 
  74: RETURN_VALUE         
