# Disassembly for zipfile.Path.open
# From module file: zipfile

## co_consts:
('\n        Open this entry as text or binary following the semantics\n        of ``pathlib.Path.open()`` by passing arguments through\n        to io.TextIOWrapper().\n        ', 0, 'r', ('pwd',), 'b', 'encoding args invalid for binary operation')

## co_names:
('is_dir', 'IsADirectoryError', 'exists', 'FileNotFoundError', 'root', 'open', 'at', 'ValueError', '_extract_text_encoding', 'io', 'TextIOWrapper')

## bytecode:

   0: RESUME               
   2: LOAD_FAST            self
   4: LOAD_METHOD          is_dir
  26: PRECALL              
  30: CALL                 
  40: POP_JUMP_FORWARD_IF_FALSE to 72
  42: LOAD_GLOBAL          NULL + IsADirectoryError
  54: LOAD_FAST            self
  56: PRECALL              
  60: CALL                 
  70: RAISE_VARARGS        
  72: LOAD_FAST            mode
  74: LOAD_CONST           0
  76: BINARY_SUBSCR        
  86: STORE_FAST           zip_mode
  88: LOAD_FAST            self
  90: LOAD_METHOD          exists
 112: PRECALL              
 116: CALL                 
 126: POP_JUMP_FORWARD_IF_TRUE to 170
 128: LOAD_FAST            zip_mode
 130: LOAD_CONST           'r'
 132: COMPARE_OP           ==
 138: POP_JUMP_FORWARD_IF_FALSE to 170
 140: LOAD_GLOBAL          NULL + FileNotFoundError
 152: LOAD_FAST            self
 154: PRECALL              
 158: CALL                 
 168: RAISE_VARARGS        
 170: LOAD_FAST            self
 172: LOAD_ATTR            root
 182: LOAD_METHOD          open
 204: LOAD_FAST            self
 206: LOAD_ATTR            at
 216: LOAD_FAST            zip_mode
 218: LOAD_FAST            pwd
 220: KW_NAMES             
 222: PRECALL              
 226: CALL                 
 236: STORE_FAST           stream
 238: LOAD_CONST           'b'
 240: LOAD_FAST            mode
 242: CONTAINS_OP          
 244: POP_JUMP_FORWARD_IF_FALSE to 288
 246: LOAD_FAST            args
 248: POP_JUMP_FORWARD_IF_TRUE to 254
 250: LOAD_FAST            kwargs
 252: POP_JUMP_FORWARD_IF_FALSE to 284
 254: LOAD_GLOBAL          NULL + ValueError
 266: LOAD_CONST           'encoding args invalid for binary operation'
 268: PRECALL              
 272: CALL                 
 282: RAISE_VARARGS        
 284: LOAD_FAST            stream
 286: RETURN_VALUE         
 288: LOAD_GLOBAL          NULL + _extract_text_encoding
 300: LOAD_FAST            args
 302: BUILD_MAP            
 304: LOAD_FAST            kwargs
 306: DICT_MERGE           
 308: CALL_FUNCTION_EX     
 310: UNPACK_SEQUENCE      
 314: STORE_FAST           encoding
 316: STORE_FAST           args
 318: STORE_FAST           kwargs
 320: LOAD_GLOBAL          NULL + io
 332: LOAD_ATTR            TextIOWrapper
 342: LOAD_FAST            stream
 344: LOAD_FAST            encoding
 346: BUILD_LIST           
 348: LOAD_FAST            args
 350: LIST_EXTEND          
 352: LIST_TO_TUPLE        
 354: BUILD_MAP            
 356: LOAD_FAST            kwargs
 358: DICT_MERGE           
 360: CALL_FUNCTION_EX     
 362: RETURN_VALUE         
