# Disassembly for zipfile.ZipFile.__repr__
# From module file: zipfile

## co_consts:
(None, '<', '.', ' file=%r', ' filename=%r', ' mode=%r', ' [closed]', '>', '')

## co_names:
('__class__', '__module__', '__qualname__', 'fp', '_filePassed', 'append', 'filename', 'mode', 'join')

## bytecode:

   0: RESUME               
   2: LOAD_CONST           '<'
   4: LOAD_FAST            self
   6: LOAD_ATTR            __class__
  16: LOAD_ATTR            __module__
  26: FORMAT_VALUE         str
  28: LOAD_CONST           '.'
  30: LOAD_FAST            self
  32: LOAD_ATTR            __class__
  42: LOAD_ATTR            __qualname__
  52: FORMAT_VALUE         str
  54: BUILD_STRING         
  56: BUILD_LIST           
  58: STORE_FAST           result
  60: LOAD_FAST            self
  62: LOAD_ATTR            fp
  72: POP_JUMP_FORWARD_IF_NONE to 280
  74: LOAD_FAST            self
  76: LOAD_ATTR            _filePassed
  86: POP_JUMP_FORWARD_IF_FALSE to 148
  88: LOAD_FAST            result
  90: LOAD_METHOD          append
 112: LOAD_CONST           ' file=%r'
 114: LOAD_FAST            self
 116: LOAD_ATTR            fp
 126: BINARY_OP            %
 130: PRECALL              
 134: CALL                 
 144: POP_TOP              
 146: JUMP_FORWARD         to 220
 148: LOAD_FAST            self
 150: LOAD_ATTR            filename
 160: POP_JUMP_FORWARD_IF_NONE to 220
 162: LOAD_FAST            result
 164: LOAD_METHOD          append
 186: LOAD_CONST           ' filename=%r'
 188: LOAD_FAST            self
 190: LOAD_ATTR            filename
 200: BINARY_OP            %
 204: PRECALL              
 208: CALL                 
 218: POP_TOP              
 220: LOAD_FAST            result
 222: LOAD_METHOD          append
 244: LOAD_CONST           ' mode=%r'
 246: LOAD_FAST            self
 248: LOAD_ATTR            mode
 258: BINARY_OP            %
 262: PRECALL              
 266: CALL                 
 276: POP_TOP              
 278: JUMP_FORWARD         to 322
 280: LOAD_FAST            result
 282: LOAD_METHOD          append
 304: LOAD_CONST           ' [closed]'
 306: PRECALL              
 310: CALL                 
 320: POP_TOP              
 322: LOAD_FAST            result
 324: LOAD_METHOD          append
 346: LOAD_CONST           '>'
 348: PRECALL              
 352: CALL                 
 362: POP_TOP              
 364: LOAD_CONST           ''
 366: LOAD_METHOD          join
 388: LOAD_FAST            result
 390: PRECALL              
 394: CALL                 
 404: RETURN_VALUE         
