# Disassembly for zipfile.ZipFile.getinfo
# From module file: zipfile

## co_consts:
("Return the instance of ZipInfo given 'name'.", None, 'There is no item named %r in the archive')

## co_names:
('NameToInfo', 'get', 'KeyError')

## bytecode:

   0: RESUME               
   2: LOAD_FAST            self
   4: LOAD_ATTR            NameToInfo
  14: LOAD_METHOD          get
  36: LOAD_FAST            name
  38: PRECALL              
  42: CALL                 
  52: STORE_FAST           info
  54: LOAD_FAST            info
  56: POP_JUMP_FORWARD_IF_NOT_NONE to 94
  58: LOAD_GLOBAL          NULL + KeyError
  70: LOAD_CONST           'There is no item named %r in the archive'
  72: LOAD_FAST            name
  74: BINARY_OP            %
  78: PRECALL              
  82: CALL                 
  92: RAISE_VARARGS        
  94: LOAD_FAST            info
  96: RETURN_VALUE         
