# Disassembly for zipfile.CompleteDirs.getinfo
# From module file: zipfile

## co_consts:
('\n        Supplement getinfo for implied dirs.\n        ', '/', ('filename',))

## co_names:
('super', 'getinfo', 'KeyError', 'endswith', '_name_set', 'ZipInfo')

## bytecode:

   0: COPY_FREE_VARS       
   2: RESUME               
   4: NOP                  
   6: LOAD_GLOBAL          NULL + super
  18: PRECALL              
  22: CALL                 
  32: LOAD_METHOD          getinfo
  54: LOAD_FAST            name
  56: PRECALL              
  60: CALL                 
  70: RETURN_VALUE         
  72: PUSH_EXC_INFO        
  74: LOAD_GLOBAL          KeyError
  86: CHECK_EXC_MATCH      
  88: POP_JUMP_FORWARD_IF_FALSE to 216
  90: POP_TOP              
  92: LOAD_FAST            name
  94: LOAD_METHOD          endswith
 116: LOAD_CONST           '/'
 118: PRECALL              
 122: CALL                 
 132: POP_JUMP_FORWARD_IF_FALSE to 178
 134: LOAD_FAST            name
 136: LOAD_FAST            self
 138: LOAD_METHOD          _name_set
 160: PRECALL              
 164: CALL                 
 174: CONTAINS_OP          
 176: POP_JUMP_FORWARD_IF_FALSE to 180
 178: RAISE_VARARGS        
 180: LOAD_GLOBAL          NULL + ZipInfo
 192: LOAD_FAST            name
 194: KW_NAMES             
 196: PRECALL              
 200: CALL                 
 210: SWAP                 
 212: POP_EXCEPT           
 214: RETURN_VALUE         
 216: RERAISE              
 218: COPY                 
 220: POP_EXCEPT           
 222: RERAISE              
