# Disassembly for zipfile._ZipWriteFile.__init__
# From module file: zipfile

## co_consts:
(None, 0)

## co_names:
('_zinfo', '_zip64', '_zipfile', '_get_compressor', 'compress_type', '_compresslevel', '_compressor', '_file_size', '_compress_size', '_crc')

## bytecode:

   0: RESUME               
   2: LOAD_FAST            zinfo
   4: LOAD_FAST            self
   6: STORE_ATTR           _zinfo
  16: LOAD_FAST            zip64
  18: LOAD_FAST            self
  20: STORE_ATTR           _zip64
  30: LOAD_FAST            zf
  32: LOAD_FAST            self
  34: STORE_ATTR           _zipfile
  44: LOAD_GLOBAL          NULL + _get_compressor
  56: LOAD_FAST            zinfo
  58: LOAD_ATTR            compress_type
  68: LOAD_FAST            zinfo
  70: LOAD_ATTR            _compresslevel
  80: PRECALL              
  84: CALL                 
  94: LOAD_FAST            self
  96: STORE_ATTR           _compressor
 106: LOAD_CONST           0
 108: LOAD_FAST            self
 110: STORE_ATTR           _file_size
 120: LOAD_CONST           0
 122: LOAD_FAST            self
 124: STORE_ATTR           _compress_size
 134: LOAD_CONST           0
 136: LOAD_FAST            self
 138: STORE_ATTR           _crc
 148: LOAD_CONST           None
 150: RETURN_VALUE         
