# Disassembly for zipfile.ZipFile
# From module file: zipfile

## co_consts:
('ZipFile', ' Class with methods to open, read, write, close, list zip files.\n\n    z = ZipFile(file, mode="r", compression=ZIP_STORED, allowZip64=True,\n                compresslevel=None)\n\n    file: Either the path to the file, or a file-like object.\n          If it is a path, the file will be opened and closed by ZipFile.\n    mode: The mode can be either read \'r\', write \'w\', exclusive create \'x\',\n          or append \'a\'.\n    compression: ZIP_STORED (no compression), ZIP_DEFLATED (requires zlib),\n                 ZIP_BZIP2 (requires bz2) or ZIP_LZMA (requires lzma).\n    allowZip64: if True ZipFile will create files with ZIP64 extensions when\n                needed, otherwise it will raise an exception when this would\n                be necessary.\n    compresslevel: None (default for the given compression type) or an integer\n                   specifying the level to pass to the compressor.\n                   When using ZIP_STORED or ZIP_LZMA this keyword has no effect.\n                   When using ZIP_DEFLATED integers 0 through 9 are accepted.\n                   When using ZIP_BZIP2 integers 1 through 9 are accepted.\n\n    ', None, 'r', True, ('strict_timestamps', 'metadata_encoding'), <code object __init__ at 0x0000024068CA2EC0, file "zipfile.py", line 1245>, <code object __enter__ at 0x0000024069CCA670, file "zipfile.py", line 1341>, <code object __exit__ at 0x000002406945FC30, file "zipfile.py", line 1344>, <code object __repr__ at 0x0000024068E900B0, file "zipfile.py", line 1347>, <code object _RealGetContents at 0x0000024068CA3E20, file "zipfile.py", line 1361>, <code object namelist at 0x0000024069CF0570, file "zipfile.py", line 1441>, <code object infolist at 0x0000024069497020, file "zipfile.py", line 1445>, <code object printdir at 0x00000240691C1BB0, file "zipfile.py", line 1450>, <code object testzip at 0x00000240691DB690, file "zipfile.py", line 1459>, <code object getinfo at 0x0000024069419A10, file "zipfile.py", line 1472>, <code object setpassword at 0x00000240691C3890, file "zipfile.py", line 1481>, <code object comment at 0x0000024069497360, file "zipfile.py", line 1490>, <code object comment at 0x000002406947D110, file "zipfile.py", line 1495>, <code object read at 0x000002406922CD50, file "zipfile.py", line 1508>, False, ('force_zip64',), <code object open at 0x0000024068CA4DA0, file "zipfile.py", line 1513>, <code object _open_to_write at 0x0000024068C27030, file "zipfile.py", line 1611>, <code object extract at 0x00000240693AA6F0, file "zipfile.py", line 1653>, <code object extractall at 0x00000240691E87B0, file "zipfile.py", line 1666>, <code object _sanitize_windows_name at 0x000002406947C3F0, file "zipfile.py", line 1683>, <code object _extract_member at 0x0000024068C85430, file "zipfile.py", line 1698>, <code object _writecheck at 0x0000024068DA73D0, file "zipfile.py", line 1740>, <code object write at 0x0000024068DE2440, file "zipfile.py", line 1763>, <code object writestr at 0x0000024068C242C0, file "zipfile.py", line 1796>, 511, <code object mkdir at 0x0000024068E17000, file "zipfile.py", line 1837>, <code object __del__ at 0x0000024069CF6100, file "zipfile.py", line 1872>, <code object close at 0x0000024068E1DBC0, file "zipfile.py", line 1876>, <code object _write_end_record at 0x0000024068C85F10, file "zipfile.py", line 1898>, <code object _fpclose at 0x000002406922C2D0, file "zipfile.py", line 1992>, (None,), ('r', None), (False,), (None, None), (None, None, None), (511,))

## co_names:
('__name__', '__module__', '__qualname__', '__doc__', 'fp', '_windows_illegal_name_trans_table', 'ZIP_STORED', '__init__', '__enter__', '__exit__', '__repr__', '_RealGetContents', 'namelist', 'infolist', 'printdir', 'testzip', 'getinfo', 'setpassword', 'property', 'comment', 'setter', 'read', 'open', '_open_to_write', 'extract', 'extractall', 'classmethod', '_sanitize_windows_name', '_extract_member', '_writecheck', 'write', 'writestr', 'mkdir', '__del__', 'close', '_write_end_record', '_fpclose')

## bytecode:

   0: RESUME               
   2: LOAD_NAME            __name__
   4: STORE_NAME           __module__
   6: LOAD_CONST           'ZipFile'
   8: STORE_NAME           __qualname__
  10: LOAD_CONST           ' Class with methods to open, read, write, close, list zip files.\n\n    z = ZipFile(file, mode="r", compression=ZIP_STORED, allowZip64=True,\n                compresslevel=None)\n\n    file: Either the path to the file, or a file-like object.\n          If it is a path, the file will be opened and closed by ZipFile.\n    mode: The mode can be either read \'r\', write \'w\', exclusive create \'x\',\n          or append \'a\'.\n    compression: ZIP_STORED (no compression), ZIP_DEFLATED (requires zlib),\n                 ZIP_BZIP2 (requires bz2) or ZIP_LZMA (requires lzma).\n    allowZip64: if True ZipFile will create files with ZIP64 extensions when\n                needed, otherwise it will raise an exception when this would\n                be necessary.\n    compresslevel: None (default for the given compression type) or an integer\n                   specifying the level to pass to the compressor.\n                   When using ZIP_STORED or ZIP_LZMA this keyword has no effect.\n                   When using ZIP_DEFLATED integers 0 through 9 are accepted.\n                   When using ZIP_BZIP2 integers 1 through 9 are accepted.\n\n    '
  12: STORE_NAME           __doc__
  14: LOAD_CONST           None
  16: STORE_NAME           fp
  18: LOAD_CONST           None
  20: STORE_NAME           _windows_illegal_name_trans_table
  22: LOAD_CONST           'r'
  24: LOAD_NAME            ZIP_STORED
  26: LOAD_CONST           True
  28: LOAD_CONST           None
  30: BUILD_TUPLE          
  32: LOAD_CONST           True
  34: LOAD_CONST           None
  36: LOAD_CONST           ('strict_timestamps', 'metadata_encoding')
  38: BUILD_CONST_KEY_MAP  
  40: LOAD_CONST           <code object __init__ at 0x0000024068CA2EC0, file "zipfile.py", line 1245>
  42: MAKE_FUNCTION        defaults, kwdefaults
  44: STORE_NAME           __init__
  46: LOAD_CONST           <code object __enter__ at 0x0000024069CCA670, file "zipfile.py", line 1341>
  48: MAKE_FUNCTION        
  50: STORE_NAME           __enter__
  52: LOAD_CONST           <code object __exit__ at 0x000002406945FC30, file "zipfile.py", line 1344>
  54: MAKE_FUNCTION        
  56: STORE_NAME           __exit__
  58: LOAD_CONST           <code object __repr__ at 0x0000024068E900B0, file "zipfile.py", line 1347>
  60: MAKE_FUNCTION        
  62: STORE_NAME           __repr__
  64: LOAD_CONST           <code object _RealGetContents at 0x0000024068CA3E20, file "zipfile.py", line 1361>
  66: MAKE_FUNCTION        
  68: STORE_NAME           _RealGetContents
  70: LOAD_CONST           <code object namelist at 0x0000024069CF0570, file "zipfile.py", line 1441>
  72: MAKE_FUNCTION        
  74: STORE_NAME           namelist
  76: LOAD_CONST           <code object infolist at 0x0000024069497020, file "zipfile.py", line 1445>
  78: MAKE_FUNCTION        
  80: STORE_NAME           infolist
  82: LOAD_CONST           (None,)
  84: LOAD_CONST           <code object printdir at 0x00000240691C1BB0, file "zipfile.py", line 1450>
  86: MAKE_FUNCTION        defaults
  88: STORE_NAME           printdir
  90: LOAD_CONST           <code object testzip at 0x00000240691DB690, file "zipfile.py", line 1459>
  92: MAKE_FUNCTION        
  94: STORE_NAME           testzip
  96: LOAD_CONST           <code object getinfo at 0x0000024069419A10, file "zipfile.py", line 1472>
  98: MAKE_FUNCTION        
 100: STORE_NAME           getinfo
 102: LOAD_CONST           <code object setpassword at 0x00000240691C3890, file "zipfile.py", line 1481>
 104: MAKE_FUNCTION        
 106: STORE_NAME           setpassword
 108: LOAD_NAME            property
 110: LOAD_CONST           <code object comment at 0x0000024069497360, file "zipfile.py", line 1490>
 112: MAKE_FUNCTION        
 114: PRECALL              
 118: CALL                 
 128: STORE_NAME           comment
 130: LOAD_NAME            comment
 132: LOAD_ATTR            setter
 142: LOAD_CONST           <code object comment at 0x000002406947D110, file "zipfile.py", line 1495>
 144: MAKE_FUNCTION        
 146: PRECALL              
 150: CALL                 
 160: STORE_NAME           comment
 162: LOAD_CONST           (None,)
 164: LOAD_CONST           <code object read at 0x000002406922CD50, file "zipfile.py", line 1508>
 166: MAKE_FUNCTION        defaults
 168: STORE_NAME           read
 170: LOAD_CONST           ('r', None)
 172: LOAD_CONST           False
 174: LOAD_CONST           ('force_zip64',)
 176: BUILD_CONST_KEY_MAP  
 178: LOAD_CONST           <code object open at 0x0000024068CA4DA0, file "zipfile.py", line 1513>
 180: MAKE_FUNCTION        defaults, kwdefaults
 182: STORE_NAME           open
 184: LOAD_CONST           (False,)
 186: LOAD_CONST           <code object _open_to_write at 0x0000024068C27030, file "zipfile.py", line 1611>
 188: MAKE_FUNCTION        defaults
 190: STORE_NAME           _open_to_write
 192: LOAD_CONST           (None, None)
 194: LOAD_CONST           <code object extract at 0x00000240693AA6F0, file "zipfile.py", line 1653>
 196: MAKE_FUNCTION        defaults
 198: STORE_NAME           extract
 200: LOAD_CONST           (None, None, None)
 202: LOAD_CONST           <code object extractall at 0x00000240691E87B0, file "zipfile.py", line 1666>
 204: MAKE_FUNCTION        defaults
 206: STORE_NAME           extractall
 208: LOAD_NAME            classmethod
 210: LOAD_CONST           <code object _sanitize_windows_name at 0x000002406947C3F0, file "zipfile.py", line 1683>
 212: MAKE_FUNCTION        
 214: PRECALL              
 218: CALL                 
 228: STORE_NAME           _sanitize_windows_name
 230: LOAD_CONST           <code object _extract_member at 0x0000024068C85430, file "zipfile.py", line 1698>
 232: MAKE_FUNCTION        
 234: STORE_NAME           _extract_member
 236: LOAD_CONST           <code object _writecheck at 0x0000024068DA73D0, file "zipfile.py", line 1740>
 238: MAKE_FUNCTION        
 240: STORE_NAME           _writecheck
 242: NOP                  
 244: NOP                  
 246: LOAD_CONST           (None, None, None)
 248: LOAD_CONST           <code object write at 0x0000024068DE2440, file "zipfile.py", line 1763>
 250: MAKE_FUNCTION        defaults
 252: STORE_NAME           write
 254: NOP                  
 256: LOAD_CONST           (None, None)
 258: LOAD_CONST           <code object writestr at 0x0000024068C242C0, file "zipfile.py", line 1796>
 260: MAKE_FUNCTION        defaults
 262: STORE_NAME           writestr
 264: LOAD_CONST           (511,)
 266: LOAD_CONST           <code object mkdir at 0x0000024068E17000, file "zipfile.py", line 1837>
 268: MAKE_FUNCTION        defaults
 270: STORE_NAME           mkdir
 272: LOAD_CONST           <code object __del__ at 0x0000024069CF6100, file "zipfile.py", line 1872>
 274: MAKE_FUNCTION        
 276: STORE_NAME           __del__
 278: LOAD_CONST           <code object close at 0x0000024068E1DBC0, file "zipfile.py", line 1876>
 280: MAKE_FUNCTION        
 282: STORE_NAME           close
 284: LOAD_CONST           <code object _write_end_record at 0x0000024068C85F10, file "zipfile.py", line 1898>
 286: MAKE_FUNCTION        
 288: STORE_NAME           _write_end_record
 290: LOAD_CONST           <code object _fpclose at 0x000002406922C2D0, file "zipfile.py", line 1992>
 292: MAKE_FUNCTION        
 294: STORE_NAME           _fpclose
 296: LOAD_CONST           None
 298: RETURN_VALUE         
