# Disassembly for zipfile.ZipExtFile.close
# From module file: zipfile

## co_consts:
(None,)

## co_names:
('_close_fileobj', '_fileobj', 'close', 'super')

## bytecode:

   0: COPY_FREE_VARS       
   2: RESUME               
   4: NOP                  
   6: LOAD_FAST            self
   8: LOAD_ATTR            _close_fileobj
  18: POP_JUMP_FORWARD_IF_FALSE to 70
  20: LOAD_FAST            self
  22: LOAD_ATTR            _fileobj
  32: LOAD_METHOD          close
  54: PRECALL              
  58: CALL                 
  68: POP_TOP              
  70: LOAD_GLOBAL          NULL + super
  82: PRECALL              
  86: CALL                 
  96: LOAD_METHOD          close
 118: PRECALL              
 122: CALL                 
 132: POP_TOP              
 134: LOAD_CONST           None
 136: RETURN_VALUE         
 138: PUSH_EXC_INFO        
 140: LOAD_GLOBAL          NULL + super
 152: PRECALL              
 156: CALL                 
 166: LOAD_METHOD          close
 188: PRECALL              
 192: CALL                 
 202: POP_TOP              
 204: RERAISE              
 206: COPY                 
 208: POP_EXCEPT           
 210: RERAISE              
