# Disassembly for zipfile._parents
# From module file: zipfile

## co_consts:
("\n    Given a path with elements separated by\n    posixpath.sep, generate all parents of that path.\n\n    >>> list(_parents('b/d'))\n    ['b']\n    >>> list(_parents('/b/d/'))\n    ['/b']\n    >>> list(_parents('b/d/f/'))\n    ['b/d', 'b']\n    >>> list(_parents('b'))\n    []\n    >>> list(_parents(''))\n    []\n    ", 1, None)

## co_names:
('itertools', 'islice', '_ancestry')

## bytecode:

   0: RESUME               
   2: LOAD_GLOBAL          NULL + itertools
  14: LOAD_ATTR            islice
  24: LOAD_GLOBAL          NULL + _ancestry
  36: LOAD_FAST            path
  38: PRECALL              
  42: CALL                 
  52: LOAD_CONST           1
  54: LOAD_CONST           None
  56: PRECALL              
  60: CALL                 
  70: RETURN_VALUE         
