# Disassembly for zipfile.ZipFile.extract
# From module file: zipfile

## co_consts:
("Extract a member from the archive to the current working directory,\n           using its full name. Its file information is extracted as accurately\n           as possible. `member' may be a filename or a ZipInfo object. You can\n           specify a different directory using `path'.\n        ",)

## co_names:
('os', 'getcwd', 'fspath', '_extract_member')

## bytecode:

   0: RESUME               
   2: LOAD_FAST            path
   4: POP_JUMP_FORWARD_IF_NOT_NONE to 46
   6: LOAD_GLOBAL          NULL + os
  18: LOAD_ATTR            getcwd
  28: PRECALL              
  32: CALL                 
  42: STORE_FAST           path
  44: JUMP_FORWARD         to 86
  46: LOAD_GLOBAL          NULL + os
  58: LOAD_ATTR            fspath
  68: LOAD_FAST            path
  70: PRECALL              
  74: CALL                 
  84: STORE_FAST           path
  86: LOAD_FAST            self
  88: LOAD_METHOD          _extract_member
 110: LOAD_FAST            member
 112: LOAD_FAST            path
 114: LOAD_FAST            pwd
 116: PRECALL              
 120: CALL                 
 130: RETURN_VALUE         
