# Disassembly for zipfile.ZipExtFile.peek
# From module file: zipfile

## co_consts:
('Returns buffered bytes without advancing the position.', None, 0, 512)

## co_names:
('len', '_readbuffer', '_offset', 'read')

## bytecode:

   0: RESUME               
   2: LOAD_FAST            n
   4: LOAD_GLOBAL          NULL + len
  16: LOAD_FAST            self
  18: LOAD_ATTR            _readbuffer
  28: PRECALL              
  32: CALL                 
  42: LOAD_FAST            self
  44: LOAD_ATTR            _offset
  54: BINARY_OP            -
  58: COMPARE_OP           >
  64: POP_JUMP_FORWARD_IF_FALSE to 286
  66: LOAD_FAST            self
  68: LOAD_METHOD          read
  90: LOAD_FAST            n
  92: PRECALL              
  96: CALL                 
 106: STORE_FAST           chunk
 108: LOAD_GLOBAL          NULL + len
 120: LOAD_FAST            chunk
 122: PRECALL              
 126: CALL                 
 136: LOAD_FAST            self
 138: LOAD_ATTR            _offset
 148: COMPARE_OP           >
 154: POP_JUMP_FORWARD_IF_FALSE to 228
 156: LOAD_FAST            chunk
 158: LOAD_FAST            self
 160: LOAD_ATTR            _readbuffer
 170: LOAD_FAST            self
 172: LOAD_ATTR            _offset
 182: LOAD_CONST           None
 184: BUILD_SLICE          
 186: BINARY_SUBSCR        
 196: BINARY_OP            +
 200: LOAD_FAST            self
 202: STORE_ATTR           _readbuffer
 212: LOAD_CONST           0
 214: LOAD_FAST            self
 216: STORE_ATTR           _offset
 226: JUMP_FORWARD         to 286
 228: LOAD_FAST            self
 230: COPY                 
 232: LOAD_ATTR            _offset
 242: LOAD_GLOBAL          NULL + len
 254: LOAD_FAST            chunk
 256: PRECALL              
 260: CALL                 
 270: BINARY_OP            -=
 274: SWAP                 
 276: STORE_ATTR           _offset
 286: LOAD_FAST            self
 288: LOAD_ATTR            _readbuffer
 298: LOAD_FAST            self
 300: LOAD_ATTR            _offset
 310: LOAD_FAST            self
 312: LOAD_ATTR            _offset
 322: LOAD_CONST           512
 324: BINARY_OP            +
 328: BUILD_SLICE          
 330: BINARY_SUBSCR        
 340: RETURN_VALUE         
