# Disassembly for zipfile.ZipExtFile.readline
# From module file: zipfile

## co_consts:
('Read and return a line from the stream.\n\n        If limit is specified, at most limit bytes will be read.\n        ', 0, b'\n', 1)

## co_names:
('_readbuffer', 'find', '_offset', 'io', 'BufferedIOBase', 'readline')

## bytecode:

   0: RESUME               
   2: LOAD_FAST            limit
   4: LOAD_CONST           0
   6: COMPARE_OP           <
  12: POP_JUMP_FORWARD_IF_FALSE to 154
  14: LOAD_FAST            self
  16: LOAD_ATTR            _readbuffer
  26: LOAD_METHOD          find
  48: LOAD_CONST           b'\n'
  50: LOAD_FAST            self
  52: LOAD_ATTR            _offset
  62: PRECALL              
  66: CALL                 
  76: LOAD_CONST           1
  78: BINARY_OP            +
  82: STORE_FAST           i
  84: LOAD_FAST            i
  86: LOAD_CONST           0
  88: COMPARE_OP           >
  94: POP_JUMP_FORWARD_IF_FALSE to 154
  96: LOAD_FAST            self
  98: LOAD_ATTR            _readbuffer
 108: LOAD_FAST            self
 110: LOAD_ATTR            _offset
 120: LOAD_FAST            i
 122: BUILD_SLICE          
 124: BINARY_SUBSCR        
 134: STORE_FAST           line
 136: LOAD_FAST            i
 138: LOAD_FAST            self
 140: STORE_ATTR           _offset
 150: LOAD_FAST            line
 152: RETURN_VALUE         
 154: LOAD_GLOBAL          io
 166: LOAD_ATTR            BufferedIOBase
 176: LOAD_METHOD          readline
 198: LOAD_FAST            self
 200: LOAD_FAST            limit
 202: PRECALL              
 206: CALL                 
 216: RETURN_VALUE         
