# Disassembly for zipfile.ZipFile.open
# From module file: zipfile

## co_consts:
("Return file-like object for 'name'.\n\n        name is a string for the file name within the ZIP file, or a ZipInfo\n        object.\n\n        mode should be 'r' to read a file already in the ZIP file, or 'w' to\n        write to a file newly added to the archive.\n\n        pwd is the password to decrypt files (only used for reading).\n\n        When writing, if the file size is not known in advance but may exceed\n        2 GiB, pass force_zip64 to use the ZIP64 format, which can handle large\n        files.  If the size is known in advance, it is best to pass a ZipInfo\n        instance for name, with zinfo.file_size set.\n        ", frozenset({'w', 'r'}), 'open() requires mode "r" or "w"', 'w', 'pwd is only supported for reading files', 'Attempt to use ZIP archive that was already closed', ('force_zip64',), "Can't read from the ZIP file while there is an open writing handle on it. Close the writing handle before trying to read.", 1, <code object <lambda> at 0x0000024069497430, file "zipfile.py", line 1560>, 'Truncated file header', 'Bad magic number for file header', 'compressed patched data (flag bit 5)', 'strong encryption (flag bit 6)', 'utf-8', 'cp437', 'File name in directory ', ' and header ', ' differ.', 'pwd: expected bytes, got %s', 'File %r is encrypted, password required for extraction', None, True)

## co_names:
('ValueError', 'fp', 'isinstance', 'ZipInfo', 'compression', 'compress_type', 'compresslevel', '_compresslevel', 'getinfo', '_open_to_write', '_writing', '_fileRefCnt', '_SharedFile', 'header_offset', '_fpclose', '_lock', 'read', 'sizeFileHeader', 'len', 'BadZipFile', 'struct', 'unpack', 'structFileHeader', '_FH_SIGNATURE', 'stringFileHeader', '_FH_FILENAME_LENGTH', '_FH_EXTRA_FIELD_LENGTH', 'flag_bits', '_MASK_COMPRESSED_PATCH', 'NotImplementedError', '_MASK_STRONG_ENCRYPTION', '_FH_GENERAL_PURPOSE_FLAG_BITS', '_MASK_UTF_FILENAME', 'decode', 'metadata_encoding', 'orig_filename', '_MASK_ENCRYPTED', 'pwd', 'bytes', 'TypeError', 'type', '__name__', 'RuntimeError', 'ZipExtFile', 'close')

## bytecode:

   0: MAKE_CELL            self
   2: RESUME               
   4: LOAD_FAST            mode
   6: LOAD_CONST           frozenset({'w', 'r'})
   8: CONTAINS_OP          
  10: POP_JUMP_FORWARD_IF_FALSE to 42
  12: LOAD_GLOBAL          NULL + ValueError
  24: LOAD_CONST           'open() requires mode "r" or "w"'
  26: PRECALL              
  30: CALL                 
  40: RAISE_VARARGS        
  42: LOAD_FAST            pwd
  44: POP_JUMP_FORWARD_IF_FALSE to 88
  46: LOAD_FAST            mode
  48: LOAD_CONST           'w'
  50: COMPARE_OP           ==
  56: POP_JUMP_FORWARD_IF_FALSE to 88
  58: LOAD_GLOBAL          NULL + ValueError
  70: LOAD_CONST           'pwd is only supported for reading files'
  72: PRECALL              
  76: CALL                 
  86: RAISE_VARARGS        
  88: LOAD_DEREF           self
  90: LOAD_ATTR            fp
 100: POP_JUMP_FORWARD_IF_TRUE to 132
 102: LOAD_GLOBAL          NULL + ValueError
 114: LOAD_CONST           'Attempt to use ZIP archive that was already closed'
 116: PRECALL              
 120: CALL                 
 130: RAISE_VARARGS        
 132: LOAD_GLOBAL          NULL + isinstance
 144: LOAD_FAST            name
 146: LOAD_GLOBAL          ZipInfo
 158: PRECALL              
 162: CALL                 
 172: POP_JUMP_FORWARD_IF_FALSE to 180
 174: LOAD_FAST            name
 176: STORE_FAST           zinfo
 178: JUMP_FORWARD         to 314
 180: LOAD_FAST            mode
 182: LOAD_CONST           'w'
 184: COMPARE_OP           ==
 190: POP_JUMP_FORWARD_IF_FALSE to 272
 192: LOAD_GLOBAL          NULL + ZipInfo
 204: LOAD_FAST            name
 206: PRECALL              
 210: CALL                 
 220: STORE_FAST           zinfo
 222: LOAD_DEREF           self
 224: LOAD_ATTR            compression
 234: LOAD_FAST            zinfo
 236: STORE_ATTR           compress_type
 246: LOAD_DEREF           self
 248: LOAD_ATTR            compresslevel
 258: LOAD_FAST            zinfo
 260: STORE_ATTR           _compresslevel
 270: JUMP_FORWARD         to 314
 272: LOAD_DEREF           self
 274: LOAD_METHOD          getinfo
 296: LOAD_FAST            name
 298: PRECALL              
 302: CALL                 
 312: STORE_FAST           zinfo
 314: LOAD_FAST            mode
 316: LOAD_CONST           'w'
 318: COMPARE_OP           ==
 324: POP_JUMP_FORWARD_IF_FALSE to 372
 326: LOAD_DEREF           self
 328: LOAD_METHOD          _open_to_write
 350: LOAD_FAST            zinfo
 352: LOAD_FAST            force_zip64
 354: KW_NAMES             
 356: PRECALL              
 360: CALL                 
 370: RETURN_VALUE         
 372: LOAD_DEREF           self
 374: LOAD_ATTR            _writing
 384: POP_JUMP_FORWARD_IF_FALSE to 416
 386: LOAD_GLOBAL          NULL + ValueError
 398: LOAD_CONST           "Can't read from the ZIP file while there is an open writing handle on it. Close the writing handle before trying to read."
 400: PRECALL              
 404: CALL                 
 414: RAISE_VARARGS        
 416: LOAD_DEREF           self
 418: COPY                 
 420: LOAD_ATTR            _fileRefCnt
 430: LOAD_CONST           1
 432: BINARY_OP            +=
 436: SWAP                 
 438: STORE_ATTR           _fileRefCnt
 448: LOAD_GLOBAL          NULL + _SharedFile
 460: LOAD_DEREF           self
 462: LOAD_ATTR            fp
 472: LOAD_FAST            zinfo
 474: LOAD_ATTR            header_offset
 484: LOAD_DEREF           self
 486: LOAD_ATTR            _fpclose
 496: LOAD_DEREF           self
 498: LOAD_ATTR            _lock
 508: LOAD_CLOSURE         self
 510: BUILD_TUPLE          
 512: LOAD_CONST           <code object <lambda> at 0x0000024069497430, file "zipfile.py", line 1560>
 514: MAKE_FUNCTION        closure
 516: PRECALL              
 520: CALL                 
 530: STORE_FAST           zef_file
 532: NOP                  
 534: LOAD_FAST            zef_file
 536: LOAD_METHOD          read
 558: LOAD_GLOBAL          sizeFileHeader
 570: PRECALL              
 574: CALL                 
 584: STORE_FAST           fheader
 586: LOAD_GLOBAL          NULL + len
 598: LOAD_FAST            fheader
 600: PRECALL              
 604: CALL                 
 614: LOAD_GLOBAL          sizeFileHeader
 626: COMPARE_OP           !=
 632: POP_JUMP_FORWARD_IF_FALSE to 664
 634: LOAD_GLOBAL          NULL + BadZipFile
 646: LOAD_CONST           'Truncated file header'
 648: PRECALL              
 652: CALL                 
 662: RAISE_VARARGS        
 664: LOAD_GLOBAL          NULL + struct
 676: LOAD_ATTR            unpack
 686: LOAD_GLOBAL          structFileHeader
 698: LOAD_FAST            fheader
 700: PRECALL              
 704: CALL                 
 714: STORE_FAST           fheader
 716: LOAD_FAST            fheader
 718: LOAD_GLOBAL          _FH_SIGNATURE
 730: BINARY_SUBSCR        
 740: LOAD_GLOBAL          stringFileHeader
 752: COMPARE_OP           !=
 758: POP_JUMP_FORWARD_IF_FALSE to 790
 760: LOAD_GLOBAL          NULL + BadZipFile
 772: LOAD_CONST           'Bad magic number for file header'
 774: PRECALL              
 778: CALL                 
 788: RAISE_VARARGS        
 790: LOAD_FAST            zef_file
 792: LOAD_METHOD          read
 814: LOAD_FAST            fheader
 816: LOAD_GLOBAL          _FH_FILENAME_LENGTH
 828: BINARY_SUBSCR        
 838: PRECALL              
 842: CALL                 
 852: STORE_FAST           fname
 854: LOAD_FAST            fheader
 856: LOAD_GLOBAL          _FH_EXTRA_FIELD_LENGTH
 868: BINARY_SUBSCR        
 878: POP_JUMP_FORWARD_IF_FALSE to 944
 880: LOAD_FAST            zef_file
 882: LOAD_METHOD          read
 904: LOAD_FAST            fheader
 906: LOAD_GLOBAL          _FH_EXTRA_FIELD_LENGTH
 918: BINARY_SUBSCR        
 928: PRECALL              
 932: CALL                 
 942: POP_TOP              
 944: LOAD_FAST            zinfo
 946: LOAD_ATTR            flag_bits
 956: LOAD_GLOBAL          _MASK_COMPRESSED_PATCH
 968: BINARY_OP            &
 972: POP_JUMP_FORWARD_IF_FALSE to 1004
 974: LOAD_GLOBAL          NULL + NotImplementedError
 986: LOAD_CONST           'compressed patched data (flag bit 5)'
 988: PRECALL              
 992: CALL                 
1002: RAISE_VARARGS        
1004: LOAD_FAST            zinfo
1006: LOAD_ATTR            flag_bits
1016: LOAD_GLOBAL          _MASK_STRONG_ENCRYPTION
1028: BINARY_OP            &
1032: POP_JUMP_FORWARD_IF_FALSE to 1064
1034: LOAD_GLOBAL          NULL + NotImplementedError
1046: LOAD_CONST           'strong encryption (flag bit 6)'
1048: PRECALL              
1052: CALL                 
1062: RAISE_VARARGS        
1064: LOAD_FAST            fheader
1066: LOAD_GLOBAL          _FH_GENERAL_PURPOSE_FLAG_BITS
1078: BINARY_SUBSCR        
1088: LOAD_GLOBAL          _MASK_UTF_FILENAME
1100: BINARY_OP            &
1104: POP_JUMP_FORWARD_IF_FALSE to 1150
1106: LOAD_FAST            fname
1108: LOAD_METHOD          decode
1130: LOAD_CONST           'utf-8'
1132: PRECALL              
1136: CALL                 
1146: STORE_FAST           fname_str
1148: JUMP_FORWARD         to 1206
1150: LOAD_FAST            fname
1152: LOAD_METHOD          decode
1174: LOAD_DEREF           self
1176: LOAD_ATTR            metadata_encoding
1186: JUMP_IF_TRUE_OR_POP  to 1190
1188: LOAD_CONST           'cp437'
1190: PRECALL              
1194: CALL                 
1204: STORE_FAST           fname_str
1206: LOAD_FAST            fname_str
1208: LOAD_FAST            zinfo
1210: LOAD_ATTR            orig_filename
1220: COMPARE_OP           !=
1226: POP_JUMP_FORWARD_IF_FALSE to 1282
1228: LOAD_GLOBAL          NULL + BadZipFile
1240: LOAD_CONST           'File name in directory '
1242: LOAD_FAST            zinfo
1244: LOAD_ATTR            orig_filename
1254: FORMAT_VALUE         repr
1256: LOAD_CONST           ' and header '
1258: LOAD_FAST            fname
1260: FORMAT_VALUE         repr
1262: LOAD_CONST           ' differ.'
1264: BUILD_STRING         
1266: PRECALL              
1270: CALL                 
1280: RAISE_VARARGS        
1282: LOAD_FAST            zinfo
1284: LOAD_ATTR            flag_bits
1294: LOAD_GLOBAL          _MASK_ENCRYPTED
1306: BINARY_OP            &
1310: STORE_FAST           is_encrypted
1312: LOAD_FAST            is_encrypted
1314: POP_JUMP_FORWARD_IF_FALSE to 1494
1316: LOAD_FAST            pwd
1318: POP_JUMP_FORWARD_IF_TRUE to 1334
1320: LOAD_DEREF           self
1322: LOAD_ATTR            pwd
1332: STORE_FAST           pwd
1334: LOAD_FAST            pwd
1336: POP_JUMP_FORWARD_IF_FALSE to 1452
1338: LOAD_GLOBAL          NULL + isinstance
1350: LOAD_FAST            pwd
1352: LOAD_GLOBAL          bytes
1364: PRECALL              
1368: CALL                 
1378: POP_JUMP_FORWARD_IF_TRUE to 1452
1380: LOAD_GLOBAL          NULL + TypeError
1392: LOAD_CONST           'pwd: expected bytes, got %s'
1394: LOAD_GLOBAL          NULL + type
1406: LOAD_FAST            pwd
1408: PRECALL              
1412: CALL                 
1422: LOAD_ATTR            __name__
1432: BINARY_OP            %
1436: PRECALL              
1440: CALL                 
1450: RAISE_VARARGS        
1452: LOAD_FAST            pwd
1454: POP_JUMP_FORWARD_IF_TRUE to 1492
1456: LOAD_GLOBAL          NULL + RuntimeError
1468: LOAD_CONST           'File %r is encrypted, password required for extraction'
1470: LOAD_FAST            name
1472: BINARY_OP            %
1476: PRECALL              
1480: CALL                 
1490: RAISE_VARARGS        
1492: JUMP_FORWARD         to 1498
1494: LOAD_CONST           None
1496: STORE_FAST           pwd
1498: LOAD_GLOBAL          NULL + ZipExtFile
1510: LOAD_FAST            zef_file
1512: LOAD_FAST            mode
1514: LOAD_FAST            zinfo
1516: LOAD_FAST            pwd
1518: LOAD_CONST           True
1520: PRECALL              
1524: CALL                 
1534: RETURN_VALUE         
1536: PUSH_EXC_INFO        
1538: POP_TOP              
1540: LOAD_FAST            zef_file
1542: LOAD_METHOD          close
1564: PRECALL              
1568: CALL                 
1578: POP_TOP              
1580: RAISE_VARARGS        
1582: COPY                 
1584: POP_EXCEPT           
1586: RERAISE              
