# Disassembly for zipfile._ZipDecrypter.crc32
# From module file: zipfile

## co_consts:
('Compute the CRC32 primitive on one byte.', 8, 255)

## co_names:
()

## bytecode:

   0: COPY_FREE_VARS       
   2: RESUME               
   4: LOAD_FAST            crc
   6: LOAD_CONST           8
   8: BINARY_OP            >>
  12: LOAD_DEREF           crctable
  14: LOAD_FAST            crc
  16: LOAD_FAST            ch
  18: BINARY_OP            ^
  22: LOAD_CONST           255
  24: BINARY_OP            &
  28: BINARY_SUBSCR        
  38: BINARY_OP            ^
  42: RETURN_VALUE         
