# Disassembly for zipfile.LZMADecompressor.__init__
# From module file: zipfile

## co_consts:
(None, b'', False)

## co_names:
('_decomp', '_unconsumed', 'eof')

## bytecode:

   0: RESUME               
   2: LOAD_CONST           None
   4: LOAD_FAST            self
   6: STORE_ATTR           _decomp
  16: LOAD_CONST           b''
  18: LOAD_FAST            self
  20: STORE_ATTR           _unconsumed
  30: LOAD_CONST           False
  32: LOAD_FAST            self
  34: STORE_ATTR           eof
  44: LOAD_CONST           None
  46: RETURN_VALUE         
