# Disassembly for zipfile.CompleteDirs._implied_dirs.<genexpr>
# From module file: zipfile

## co_consts:
(None,)

## co_names:
('posixpath', 'sep')

## bytecode:

   0: RETURN_GENERATOR     
   2: POP_TOP              
   4: RESUME               
   6: LOAD_FAST            .0
   8: FOR_ITER             to 48
  10: STORE_FAST           p
  12: LOAD_FAST            p
  14: LOAD_GLOBAL          posixpath
  26: LOAD_ATTR            sep
  36: BINARY_OP            +
  40: YIELD_VALUE          
  42: RESUME               
  44: POP_TOP              
  46: JUMP_BACKWARD        to 8
  48: LOAD_CONST           None
  50: RETURN_VALUE         
