# Disassembly for zipfile.LZMACompressor.compress
# From module file: zipfile

## co_consts:
(None,)

## co_names:
('_comp', '_init', 'compress')

## bytecode:

   0: RESUME               
   2: LOAD_FAST            self
   4: LOAD_ATTR            _comp
  14: POP_JUMP_FORWARD_IF_NOT_NONE to 110
  16: LOAD_FAST            self
  18: LOAD_METHOD          _init
  40: PRECALL              
  44: CALL                 
  54: LOAD_FAST            self
  56: LOAD_ATTR            _comp
  66: LOAD_METHOD          compress
  88: LOAD_FAST            data
  90: PRECALL              
  94: CALL                 
 104: BINARY_OP            +
 108: RETURN_VALUE         
 110: LOAD_FAST            self
 112: LOAD_ATTR            _comp
 122: LOAD_METHOD          compress
 144: LOAD_FAST            data
 146: PRECALL              
 150: CALL                 
 160: RETURN_VALUE         
