# Disassembly for zipfile.CompleteDirs.make
# From module file: zipfile

## co_consts:
('\n        Given a source (filename or zipfile), return an\n        appropriate CompleteDirs subclass.\n        ', 'r')

## co_names:
('isinstance', 'CompleteDirs', 'ZipFile', 'mode', '__class__')

## bytecode:

   0: RESUME               
   2: LOAD_GLOBAL          NULL + isinstance
  14: LOAD_FAST            source
  16: LOAD_GLOBAL          CompleteDirs
  28: PRECALL              
  32: CALL                 
  42: POP_JUMP_FORWARD_IF_FALSE to 48
  44: LOAD_FAST            source
  46: RETURN_VALUE         
  48: LOAD_GLOBAL          NULL + isinstance
  60: LOAD_FAST            source
  62: LOAD_GLOBAL          ZipFile
  74: PRECALL              
  78: CALL                 
  88: POP_JUMP_FORWARD_IF_TRUE to 112
  90: PUSH_NULL            
  92: LOAD_FAST            cls
  94: LOAD_FAST            source
  96: PRECALL              
 100: CALL                 
 110: RETURN_VALUE         
 112: LOAD_CONST           'r'
 114: LOAD_FAST            source
 116: LOAD_ATTR            mode
 126: CONTAINS_OP          
 128: POP_JUMP_FORWARD_IF_FALSE to 144
 130: LOAD_GLOBAL          CompleteDirs
 142: STORE_FAST           cls
 144: LOAD_FAST            cls
 146: LOAD_FAST            source
 148: STORE_ATTR           __class__
 158: LOAD_FAST            source
 160: RETURN_VALUE         
