# Disassembly for zipfile.Path.filename
# From module file: zipfile

## co_consts:
(None,)

## co_names:
('pathlib', 'Path', 'root', 'filename', 'joinpath', 'at')

## bytecode:

   0: RESUME               
   2: LOAD_GLOBAL          NULL + pathlib
  14: LOAD_ATTR            Path
  24: LOAD_FAST            self
  26: LOAD_ATTR            root
  36: LOAD_ATTR            filename
  46: PRECALL              
  50: CALL                 
  60: LOAD_METHOD          joinpath
  82: LOAD_FAST            self
  84: LOAD_ATTR            at
  94: PRECALL              
  98: CALL                 
 108: RETURN_VALUE         
