# Disassembly for zipfile.CompleteDirs.resolve_dir
# From module file: zipfile

## co_consts:
('\n        If the name represents a directory, return that name\n        as a directory (with the trailing slash).\n        ', '/')

## co_names:
('_name_set',)

## bytecode:

   0: RESUME               
   2: LOAD_FAST            self
   4: LOAD_METHOD          _name_set
  26: PRECALL              
  30: CALL                 
  40: STORE_FAST           names
  42: LOAD_FAST            name
  44: LOAD_CONST           '/'
  46: BINARY_OP            +
  50: STORE_FAST           dirname
  52: LOAD_FAST            name
  54: LOAD_FAST            names
  56: CONTAINS_OP          
  58: JUMP_IF_FALSE_OR_POP to 66
  60: LOAD_FAST            dirname
  62: LOAD_FAST            names
  64: CONTAINS_OP          
  66: STORE_FAST           dir_match
  68: LOAD_FAST            dir_match
  70: POP_JUMP_FORWARD_IF_FALSE to 76
  72: LOAD_FAST            dirname
  74: JUMP_FORWARD         to 78
  76: LOAD_FAST            name
  78: RETURN_VALUE         
