# Disassembly for zipfile._get_compressor
# From module file: zipfile

## co_consts:
(None, -15)

## co_names:
('ZIP_DEFLATED', 'zlib', 'compressobj', 'DEFLATED', 'Z_DEFAULT_COMPRESSION', 'ZIP_BZIP2', 'bz2', 'BZ2Compressor', 'ZIP_LZMA', 'LZMACompressor')

## bytecode:

   0: RESUME               
   2: LOAD_FAST            compress_type
   4: LOAD_GLOBAL          ZIP_DEFLATED
  16: COMPARE_OP           ==
  22: POP_JUMP_FORWARD_IF_FALSE to 176
  24: LOAD_FAST            compresslevel
  26: POP_JUMP_FORWARD_IF_NONE to 92
  28: LOAD_GLOBAL          NULL + zlib
  40: LOAD_ATTR            compressobj
  50: LOAD_FAST            compresslevel
  52: LOAD_GLOBAL          zlib
  64: LOAD_ATTR            DEFLATED
  74: LOAD_CONST           -15
  76: PRECALL              
  80: CALL                 
  90: RETURN_VALUE         
  92: LOAD_GLOBAL          NULL + zlib
 104: LOAD_ATTR            compressobj
 114: LOAD_GLOBAL          zlib
 126: LOAD_ATTR            Z_DEFAULT_COMPRESSION
 136: LOAD_GLOBAL          zlib
 148: LOAD_ATTR            DEFLATED
 158: LOAD_CONST           -15
 160: PRECALL              
 164: CALL                 
 174: RETURN_VALUE         
 176: LOAD_FAST            compress_type
 178: LOAD_GLOBAL          ZIP_BZIP2
 190: COMPARE_OP           ==
 196: POP_JUMP_FORWARD_IF_FALSE to 280
 198: LOAD_FAST            compresslevel
 200: POP_JUMP_FORWARD_IF_NONE to 242
 202: LOAD_GLOBAL          NULL + bz2
 214: LOAD_ATTR            BZ2Compressor
 224: LOAD_FAST            compresslevel
 226: PRECALL              
 230: CALL                 
 240: RETURN_VALUE         
 242: LOAD_GLOBAL          NULL + bz2
 254: LOAD_ATTR            BZ2Compressor
 264: PRECALL              
 268: CALL                 
 278: RETURN_VALUE         
 280: LOAD_FAST            compress_type
 282: LOAD_GLOBAL          ZIP_LZMA
 294: COMPARE_OP           ==
 300: POP_JUMP_FORWARD_IF_FALSE to 330
 302: LOAD_GLOBAL          NULL + LZMACompressor
 314: PRECALL              
 318: CALL                 
 328: RETURN_VALUE         
 330: LOAD_CONST           None
 332: RETURN_VALUE         
