# Disassembly for zipfile._ancestry
# From module file: zipfile

## co_consts:
("\n    Given a path with elements separated by\n    posixpath.sep, generate all elements of that path\n\n    >>> list(_ancestry('b/d'))\n    ['b/d', 'b']\n    >>> list(_ancestry('/b/d/'))\n    ['/b/d', '/b']\n    >>> list(_ancestry('b/d/f/'))\n    ['b/d/f', 'b/d', 'b']\n    >>> list(_ancestry('b'))\n    ['b']\n    >>> list(_ancestry(''))\n    []\n    ", None)

## co_names:
('rstrip', 'posixpath', 'sep', 'split')

## bytecode:

   0: RETURN_GENERATOR     
   2: POP_TOP              
   4: RESUME               
   6: LOAD_FAST            path
   8: LOAD_METHOD          rstrip
  30: LOAD_GLOBAL          posixpath
  42: LOAD_ATTR            sep
  52: PRECALL              
  56: CALL                 
  66: STORE_FAST           path
  68: LOAD_FAST            path
  70: POP_JUMP_FORWARD_IF_FALSE to 198
  72: LOAD_FAST            path
  74: LOAD_GLOBAL          posixpath
  86: LOAD_ATTR            sep
  96: COMPARE_OP           !=
 102: POP_JUMP_FORWARD_IF_FALSE to 206
 104: LOAD_FAST            path
 106: YIELD_VALUE          
 108: RESUME               
 110: POP_TOP              
 112: LOAD_GLOBAL          NULL + posixpath
 124: LOAD_ATTR            split
 134: LOAD_FAST            path
 136: PRECALL              
 140: CALL                 
 150: UNPACK_SEQUENCE      
 154: STORE_FAST           path
 156: STORE_FAST           tail
 158: LOAD_FAST            path
 160: POP_JUMP_FORWARD_IF_FALSE to 202
 162: LOAD_FAST            path
 164: LOAD_GLOBAL          posixpath
 176: LOAD_ATTR            sep
 186: COMPARE_OP           !=
 192: POP_JUMP_BACKWARD_IF_TRUE to 104
 194: LOAD_CONST           None
 196: RETURN_VALUE         
 198: LOAD_CONST           None
 200: RETURN_VALUE         
 202: LOAD_CONST           None
 204: RETURN_VALUE         
 206: LOAD_CONST           None
 208: RETURN_VALUE         
