# Disassembly for zipfile.Path.iterdir
# From module file: zipfile

## co_consts:
(None, "Can't listdir a file")

## co_names:
('is_dir', 'ValueError', 'map', '_next', 'root', 'namelist', 'filter', '_is_child')

## bytecode:

   0: RESUME               
   2: LOAD_FAST            self
   4: LOAD_METHOD          is_dir
  26: PRECALL              
  30: CALL                 
  40: POP_JUMP_FORWARD_IF_TRUE to 72
  42: LOAD_GLOBAL          NULL + ValueError
  54: LOAD_CONST           "Can't listdir a file"
  56: PRECALL              
  60: CALL                 
  70: RAISE_VARARGS        
  72: LOAD_GLOBAL          NULL + map
  84: LOAD_FAST            self
  86: LOAD_ATTR            _next
  96: LOAD_FAST            self
  98: LOAD_ATTR            root
 108: LOAD_METHOD          namelist
 130: PRECALL              
 134: CALL                 
 144: PRECALL              
 148: CALL                 
 158: STORE_FAST           subs
 160: LOAD_GLOBAL          NULL + filter
 172: LOAD_FAST            self
 174: LOAD_ATTR            _is_child
 184: LOAD_FAST            subs
 186: PRECALL              
 190: CALL                 
 200: RETURN_VALUE         
