# Disassembly for zipfile._strip_extra
# From module file: zipfile

## co_consts:
(None, False, 0, 4, True, b'')

## co_names:
('_EXTRA_FIELD_STRUCT', 'unpack', 'len', 'append', 'join')

## bytecode:

   0: RESUME               
   2: LOAD_GLOBAL          _EXTRA_FIELD_STRUCT
  14: LOAD_ATTR            unpack
  24: STORE_FAST           unpack
  26: LOAD_CONST           False
  28: STORE_FAST           modified
  30: BUILD_LIST           
  32: STORE_FAST           buffer
  34: LOAD_CONST           0
  36: COPY                 
  38: STORE_FAST           start
  40: STORE_FAST           i
  42: LOAD_FAST            i
  44: LOAD_CONST           4
  46: BINARY_OP            +
  50: LOAD_GLOBAL          NULL + len
  62: LOAD_FAST            extra
  64: PRECALL              
  68: CALL                 
  78: COMPARE_OP           <=
  84: POP_JUMP_FORWARD_IF_FALSE to 286
  86: PUSH_NULL            
  88: LOAD_FAST            unpack
  90: LOAD_FAST            extra
  92: LOAD_FAST            i
  94: LOAD_FAST            i
  96: LOAD_CONST           4
  98: BINARY_OP            +
 102: BUILD_SLICE          
 104: BINARY_SUBSCR        
 114: PRECALL              
 118: CALL                 
 128: UNPACK_SEQUENCE      
 132: STORE_FAST           xid
 134: STORE_FAST           xlen
 136: LOAD_FAST            i
 138: LOAD_CONST           4
 140: BINARY_OP            +
 144: LOAD_FAST            xlen
 146: BINARY_OP            +
 150: STORE_FAST           j
 152: LOAD_FAST            xid
 154: LOAD_FAST            xids
 156: CONTAINS_OP          
 158: POP_JUMP_FORWARD_IF_FALSE to 238
 160: LOAD_FAST            i
 162: LOAD_FAST            start
 164: COMPARE_OP           !=
 170: POP_JUMP_FORWARD_IF_FALSE to 230
 172: LOAD_FAST            buffer
 174: LOAD_METHOD          append
 196: LOAD_FAST            extra
 198: LOAD_FAST            start
 200: LOAD_FAST            i
 202: BUILD_SLICE          
 204: BINARY_SUBSCR        
 214: PRECALL              
 218: CALL                 
 228: POP_TOP              
 230: LOAD_FAST            j
 232: STORE_FAST           start
 234: LOAD_CONST           True
 236: STORE_FAST           modified
 238: LOAD_FAST            j
 240: STORE_FAST           i
 242: LOAD_FAST            i
 244: LOAD_CONST           4
 246: BINARY_OP            +
 250: LOAD_GLOBAL          NULL + len
 262: LOAD_FAST            extra
 264: PRECALL              
 268: CALL                 
 278: COMPARE_OP           <=
 284: POP_JUMP_BACKWARD_IF_TRUE to 86
 286: LOAD_FAST            modified
 288: POP_JUMP_FORWARD_IF_TRUE to 294
 290: LOAD_FAST            extra
 292: RETURN_VALUE         
 294: LOAD_FAST            start
 296: LOAD_GLOBAL          NULL + len
 308: LOAD_FAST            extra
 310: PRECALL              
 314: CALL                 
 324: COMPARE_OP           !=
 330: POP_JUMP_FORWARD_IF_FALSE to 390
 332: LOAD_FAST            buffer
 334: LOAD_METHOD          append
 356: LOAD_FAST            extra
 358: LOAD_FAST            start
 360: LOAD_CONST           None
 362: BUILD_SLICE          
 364: BINARY_SUBSCR        
 374: PRECALL              
 378: CALL                 
 388: POP_TOP              
 390: LOAD_CONST           b''
 392: LOAD_METHOD          join
 414: LOAD_FAST            buffer
 416: PRECALL              
 420: CALL                 
 430: RETURN_VALUE         
