# Disassembly for zipfile.main
# From module file: zipfile

## co_consts:
(None, 0, 'A simple command-line interface for zipfile module.', ('description',), True, ('required',), '-l', '--list', '<zipfile>', 'Show listing of a zipfile', ('metavar', 'help'), '-e', '--extract', 2, ('<zipfile>', '<output_dir>'), 'Extract zipfile into target dir', ('nargs', 'metavar', 'help'), '-c', '--create', '+', ('<name>', '<file>'), 'Create zipfile from sources', '-t', '--test', 'Test if a zipfile is valid', '--metadata-encoding', '<encoding>', 'Specify encoding of member names for -l, -e and -t', 'r', ('metadata_encoding',), 'The following enclosed file is corrupted: {!r}', 'Done testing', 'Non-conforming encodings not supported with -c.', ('file',), 1, <code object addToZip at 0x0000024066C26DA0, file "zipfile.py", line 2547>, 'w', '')

## co_names:
('argparse', 'ArgumentParser', 'add_mutually_exclusive_group', 'add_argument', 'parse_args', 'metadata_encoding', 'test', 'ZipFile', 'testzip', 'print', 'format', 'list', 'printdir', 'extract', 'extractall', 'create', 'sys', 'stderr', 'exit', 'pop', 'os', 'path', 'basename', 'dirname', 'curdir', 'pardir')

## bytecode:

   0: MAKE_CELL            addToZip
   2: RESUME               
   4: LOAD_CONST           0
   6: LOAD_CONST           None
   8: IMPORT_NAME          argparse
  10: STORE_FAST           argparse
  12: LOAD_CONST           'A simple command-line interface for zipfile module.'
  14: STORE_FAST           description
  16: LOAD_FAST            argparse
  18: LOAD_METHOD          ArgumentParser
  40: LOAD_FAST            description
  42: KW_NAMES             
  44: PRECALL              
  48: CALL                 
  58: STORE_FAST           parser
  60: LOAD_FAST            parser
  62: LOAD_METHOD          add_mutually_exclusive_group
  84: LOAD_CONST           True
  86: KW_NAMES             
  88: PRECALL              
  92: CALL                 
 102: STORE_FAST           group
 104: LOAD_FAST            group
 106: LOAD_METHOD          add_argument
 128: LOAD_CONST           '-l'
 130: LOAD_CONST           '--list'
 132: LOAD_CONST           '<zipfile>'
 134: LOAD_CONST           'Show listing of a zipfile'
 136: KW_NAMES             
 138: PRECALL              
 142: CALL                 
 152: POP_TOP              
 154: LOAD_FAST            group
 156: LOAD_METHOD          add_argument
 178: LOAD_CONST           '-e'
 180: LOAD_CONST           '--extract'
 182: LOAD_CONST           2
 184: LOAD_CONST           ('<zipfile>', '<output_dir>')
 186: LOAD_CONST           'Extract zipfile into target dir'
 188: KW_NAMES             
 190: PRECALL              
 194: CALL                 
 204: POP_TOP              
 206: LOAD_FAST            group
 208: LOAD_METHOD          add_argument
 230: LOAD_CONST           '-c'
 232: LOAD_CONST           '--create'
 234: LOAD_CONST           '+'
 236: LOAD_CONST           ('<name>', '<file>')
 238: LOAD_CONST           'Create zipfile from sources'
 240: KW_NAMES             
 242: PRECALL              
 246: CALL                 
 256: POP_TOP              
 258: LOAD_FAST            group
 260: LOAD_METHOD          add_argument
 282: LOAD_CONST           '-t'
 284: LOAD_CONST           '--test'
 286: LOAD_CONST           '<zipfile>'
 288: LOAD_CONST           'Test if a zipfile is valid'
 290: KW_NAMES             
 292: PRECALL              
 296: CALL                 
 306: POP_TOP              
 308: LOAD_FAST            parser
 310: LOAD_METHOD          add_argument
 332: LOAD_CONST           '--metadata-encoding'
 334: LOAD_CONST           '<encoding>'
 336: LOAD_CONST           'Specify encoding of member names for -l, -e and -t'
 338: KW_NAMES             
 340: PRECALL              
 344: CALL                 
 354: POP_TOP              
 356: LOAD_FAST            parser
 358: LOAD_METHOD          parse_args
 380: LOAD_FAST            args
 382: PRECALL              
 386: CALL                 
 396: STORE_FAST           args
 398: LOAD_FAST            args
 400: LOAD_ATTR            metadata_encoding
 410: STORE_FAST           encoding
 412: LOAD_FAST            args
 414: LOAD_ATTR            test
 424: POP_JUMP_FORWARD_IF_NONE to 670
 426: LOAD_FAST            args
 428: LOAD_ATTR            test
 438: STORE_FAST           src
 440: LOAD_GLOBAL          NULL + ZipFile
 452: LOAD_FAST            src
 454: LOAD_CONST           'r'
 456: LOAD_FAST            encoding
 458: KW_NAMES             
 460: PRECALL              
 464: CALL                 
 474: BEFORE_WITH          
 476: STORE_FAST           zf
 478: LOAD_FAST            zf
 480: LOAD_METHOD          testzip
 502: PRECALL              
 506: CALL                 
 516: STORE_FAST           badfile
 518: LOAD_CONST           None
 520: LOAD_CONST           None
 522: LOAD_CONST           None
 524: PRECALL              
 528: CALL                 
 538: POP_TOP              
 540: JUMP_FORWARD         to 564
 542: PUSH_EXC_INFO        
 544: WITH_EXCEPT_START    
 546: POP_JUMP_FORWARD_IF_TRUE to 556
 548: RERAISE              
 550: COPY                 
 552: POP_EXCEPT           
 554: RERAISE              
 556: POP_TOP              
 558: POP_EXCEPT           
 560: POP_TOP              
 562: POP_TOP              
 564: LOAD_FAST            badfile
 566: POP_JUMP_FORWARD_IF_FALSE to 636
 568: LOAD_GLOBAL          NULL + print
 580: LOAD_CONST           'The following enclosed file is corrupted: {!r}'
 582: LOAD_METHOD          format
 604: LOAD_FAST            badfile
 606: PRECALL              
 610: CALL                 
 620: PRECALL              
 624: CALL                 
 634: POP_TOP              
 636: LOAD_GLOBAL          NULL + print
 648: LOAD_CONST           'Done testing'
 650: PRECALL              
 654: CALL                 
 664: POP_TOP              
 666: LOAD_CONST           None
 668: RETURN_VALUE         
 670: LOAD_FAST            args
 672: LOAD_ATTR            list
 682: POP_JUMP_FORWARD_IF_NONE to 828
 684: LOAD_FAST            args
 686: LOAD_ATTR            list
 696: STORE_FAST           src
 698: LOAD_GLOBAL          NULL + ZipFile
 710: LOAD_FAST            src
 712: LOAD_CONST           'r'
 714: LOAD_FAST            encoding
 716: KW_NAMES             
 718: PRECALL              
 722: CALL                 
 732: BEFORE_WITH          
 734: STORE_FAST           zf
 736: LOAD_FAST            zf
 738: LOAD_METHOD          printdir
 760: PRECALL              
 764: CALL                 
 774: POP_TOP              
 776: LOAD_CONST           None
 778: LOAD_CONST           None
 780: LOAD_CONST           None
 782: PRECALL              
 786: CALL                 
 796: POP_TOP              
 798: LOAD_CONST           None
 800: RETURN_VALUE         
 802: PUSH_EXC_INFO        
 804: WITH_EXCEPT_START    
 806: POP_JUMP_FORWARD_IF_TRUE to 816
 808: RERAISE              
 810: COPY                 
 812: POP_EXCEPT           
 814: RERAISE              
 816: POP_TOP              
 818: POP_EXCEPT           
 820: POP_TOP              
 822: POP_TOP              
 824: LOAD_CONST           None
 826: RETURN_VALUE         
 828: LOAD_FAST            args
 830: LOAD_ATTR            extract
 840: POP_JUMP_FORWARD_IF_NONE to 994
 842: LOAD_FAST            args
 844: LOAD_ATTR            extract
 854: UNPACK_SEQUENCE      
 858: STORE_FAST           src
 860: STORE_FAST           curdir
 862: LOAD_GLOBAL          NULL + ZipFile
 874: LOAD_FAST            src
 876: LOAD_CONST           'r'
 878: LOAD_FAST            encoding
 880: KW_NAMES             
 882: PRECALL              
 886: CALL                 
 896: BEFORE_WITH          
 898: STORE_FAST           zf
 900: LOAD_FAST            zf
 902: LOAD_METHOD          extractall
 924: LOAD_FAST            curdir
 926: PRECALL              
 930: CALL                 
 940: POP_TOP              
 942: LOAD_CONST           None
 944: LOAD_CONST           None
 946: LOAD_CONST           None
 948: PRECALL              
 952: CALL                 
 962: POP_TOP              
 964: LOAD_CONST           None
 966: RETURN_VALUE         
 968: PUSH_EXC_INFO        
 970: WITH_EXCEPT_START    
 972: POP_JUMP_FORWARD_IF_TRUE to 982
 974: RERAISE              
 976: COPY                 
 978: POP_EXCEPT           
 980: RERAISE              
 982: POP_TOP              
 984: POP_EXCEPT           
 986: POP_TOP              
 988: POP_TOP              
 990: LOAD_CONST           None
 992: RETURN_VALUE         
 994: LOAD_FAST            args
 996: LOAD_ATTR            create
1006: EXTENDED_ARG         
1008: POP_JUMP_FORWARD_IF_NONE to 1552
1010: LOAD_FAST            encoding
1012: POP_JUMP_FORWARD_IF_FALSE to 1108
1014: LOAD_GLOBAL          NULL + print
1026: LOAD_CONST           'Non-conforming encodings not supported with -c.'
1028: LOAD_GLOBAL          sys
1040: LOAD_ATTR            stderr
1050: KW_NAMES             
1052: PRECALL              
1056: CALL                 
1066: POP_TOP              
1068: LOAD_GLOBAL          NULL + sys
1080: LOAD_ATTR            exit
1090: LOAD_CONST           1
1092: PRECALL              
1096: CALL                 
1106: POP_TOP              
1108: LOAD_FAST            args
1110: LOAD_ATTR            create
1120: LOAD_METHOD          pop
1142: LOAD_CONST           0
1144: PRECALL              
1148: CALL                 
1158: STORE_FAST           zip_name
1160: LOAD_FAST            args
1162: LOAD_ATTR            create
1172: STORE_FAST           files
1174: LOAD_CLOSURE         addToZip
1176: BUILD_TUPLE          
1178: LOAD_CONST           <code object addToZip at 0x0000024066C26DA0, file "zipfile.py", line 2547>
1180: MAKE_FUNCTION        closure
1182: STORE_DEREF          addToZip
1184: LOAD_GLOBAL          NULL + ZipFile
1196: LOAD_FAST            zip_name
1198: LOAD_CONST           'w'
1200: PRECALL              
1204: CALL                 
1214: BEFORE_WITH          
1216: STORE_FAST           zf
1218: LOAD_FAST            files
1220: GET_ITER             
1222: FOR_ITER             to 1498
1224: STORE_FAST           path
1226: LOAD_GLOBAL          os
1238: LOAD_ATTR            path
1248: LOAD_METHOD          basename
1270: LOAD_FAST            path
1272: PRECALL              
1276: CALL                 
1286: STORE_FAST           zippath
1288: LOAD_FAST            zippath
1290: POP_JUMP_FORWARD_IF_TRUE to 1412
1292: LOAD_GLOBAL          os
1304: LOAD_ATTR            path
1314: LOAD_METHOD          basename
1336: LOAD_GLOBAL          os
1348: LOAD_ATTR            path
1358: LOAD_METHOD          dirname
1380: LOAD_FAST            path
1382: PRECALL              
1386: CALL                 
1396: PRECALL              
1400: CALL                 
1410: STORE_FAST           zippath
1412: LOAD_FAST            zippath
1414: LOAD_CONST           ''
1416: LOAD_GLOBAL          os
1428: LOAD_ATTR            curdir
1438: LOAD_GLOBAL          os
1450: LOAD_ATTR            pardir
1460: BUILD_TUPLE          
1462: CONTAINS_OP          
1464: POP_JUMP_FORWARD_IF_FALSE to 1470
1466: LOAD_CONST           ''
1468: STORE_FAST           zippath
1470: PUSH_NULL            
1472: LOAD_DEREF           addToZip
1474: LOAD_FAST            zf
1476: LOAD_FAST            path
1478: LOAD_FAST            zippath
1480: PRECALL              
1484: CALL                 
1494: POP_TOP              
1496: JUMP_BACKWARD        to 1222
1498: NOP                  
1500: LOAD_CONST           None
1502: LOAD_CONST           None
1504: LOAD_CONST           None
1506: PRECALL              
1510: CALL                 
1520: POP_TOP              
1522: LOAD_CONST           None
1524: RETURN_VALUE         
1526: PUSH_EXC_INFO        
1528: WITH_EXCEPT_START    
1530: POP_JUMP_FORWARD_IF_TRUE to 1540
1532: RERAISE              
1534: COPY                 
1536: POP_EXCEPT           
1538: RERAISE              
1540: POP_TOP              
1542: POP_EXCEPT           
1544: POP_TOP              
1546: POP_TOP              
1548: LOAD_CONST           None
1550: RETURN_VALUE         
1552: LOAD_CONST           None
1554: RETURN_VALUE         
