# Disassembly for zipfile.ZipExtFile.__init__
# From module file: zipfile

## co_consts:
(None, False, b'', 0, 'CRC', True, 8, 255, 24, 'Bad password for file %r')

## co_names:
('_fileobj', '_pwd', '_close_fileobj', 'compress_type', '_compress_type', 'compress_size', '_compress_left', 'file_size', '_left', '_get_decompressor', '_decompressor', '_eof', '_readbuffer', '_offset', 'newlines', 'mode', 'filename', 'name', 'hasattr', 'CRC', '_expected_crc', 'crc32', '_running_crc', '_seekable', 'seekable', 'tell', '_orig_compress_start', '_orig_compress_size', '_orig_file_size', '_orig_start_crc', 'AttributeError', '_decrypter', 'flag_bits', '_MASK_USE_DATA_DESCRIPTOR', '_raw_time', '_init_decrypter', 'RuntimeError', 'orig_filename')

## bytecode:

   0: RESUME               
   2: LOAD_FAST            fileobj
   4: LOAD_FAST            self
   6: STORE_ATTR           _fileobj
  16: LOAD_FAST            pwd
  18: LOAD_FAST            self
  20: STORE_ATTR           _pwd
  30: LOAD_FAST            close_fileobj
  32: LOAD_FAST            self
  34: STORE_ATTR           _close_fileobj
  44: LOAD_FAST            zipinfo
  46: LOAD_ATTR            compress_type
  56: LOAD_FAST            self
  58: STORE_ATTR           _compress_type
  68: LOAD_FAST            zipinfo
  70: LOAD_ATTR            compress_size
  80: LOAD_FAST            self
  82: STORE_ATTR           _compress_left
  92: LOAD_FAST            zipinfo
  94: LOAD_ATTR            file_size
 104: LOAD_FAST            self
 106: STORE_ATTR           _left
 116: LOAD_GLOBAL          NULL + _get_decompressor
 128: LOAD_FAST            self
 130: LOAD_ATTR            _compress_type
 140: PRECALL              
 144: CALL                 
 154: LOAD_FAST            self
 156: STORE_ATTR           _decompressor
 166: LOAD_CONST           False
 168: LOAD_FAST            self
 170: STORE_ATTR           _eof
 180: LOAD_CONST           b''
 182: LOAD_FAST            self
 184: STORE_ATTR           _readbuffer
 194: LOAD_CONST           0
 196: LOAD_FAST            self
 198: STORE_ATTR           _offset
 208: LOAD_CONST           None
 210: LOAD_FAST            self
 212: STORE_ATTR           newlines
 222: LOAD_FAST            mode
 224: LOAD_FAST            self
 226: STORE_ATTR           mode
 236: LOAD_FAST            zipinfo
 238: LOAD_ATTR            filename
 248: LOAD_FAST            self
 250: STORE_ATTR           name
 260: LOAD_GLOBAL          NULL + hasattr
 272: LOAD_FAST            zipinfo
 274: LOAD_CONST           'CRC'
 276: PRECALL              
 280: CALL                 
 290: POP_JUMP_FORWARD_IF_FALSE to 358
 292: LOAD_FAST            zipinfo
 294: LOAD_ATTR            CRC
 304: LOAD_FAST            self
 306: STORE_ATTR           _expected_crc
 316: LOAD_GLOBAL          NULL + crc32
 328: LOAD_CONST           b''
 330: PRECALL              
 334: CALL                 
 344: LOAD_FAST            self
 346: STORE_ATTR           _running_crc
 356: JUMP_FORWARD         to 372
 358: LOAD_CONST           None
 360: LOAD_FAST            self
 362: STORE_ATTR           _expected_crc
 372: LOAD_CONST           False
 374: LOAD_FAST            self
 376: STORE_ATTR           _seekable
 386: NOP                  
 388: LOAD_FAST            fileobj
 390: LOAD_METHOD          seekable
 412: PRECALL              
 416: CALL                 
 426: POP_JUMP_FORWARD_IF_FALSE to 564
 428: LOAD_FAST            fileobj
 430: LOAD_METHOD          tell
 452: PRECALL              
 456: CALL                 
 466: LOAD_FAST            self
 468: STORE_ATTR           _orig_compress_start
 478: LOAD_FAST            zipinfo
 480: LOAD_ATTR            compress_size
 490: LOAD_FAST            self
 492: STORE_ATTR           _orig_compress_size
 502: LOAD_FAST            zipinfo
 504: LOAD_ATTR            file_size
 514: LOAD_FAST            self
 516: STORE_ATTR           _orig_file_size
 526: LOAD_FAST            self
 528: LOAD_ATTR            _running_crc
 538: LOAD_FAST            self
 540: STORE_ATTR           _orig_start_crc
 550: LOAD_CONST           True
 552: LOAD_FAST            self
 554: STORE_ATTR           _seekable
 564: JUMP_FORWARD         to 598
 566: PUSH_EXC_INFO        
 568: LOAD_GLOBAL          AttributeError
 580: CHECK_EXC_MATCH      
 582: POP_JUMP_FORWARD_IF_FALSE to 590
 584: POP_TOP              
 586: POP_EXCEPT           
 588: JUMP_FORWARD         to 598
 590: RERAISE              
 592: COPY                 
 594: POP_EXCEPT           
 596: RERAISE              
 598: LOAD_CONST           None
 600: LOAD_FAST            self
 602: STORE_ATTR           _decrypter
 612: LOAD_FAST            pwd
 614: POP_JUMP_FORWARD_IF_FALSE to 798
 616: LOAD_FAST            zipinfo
 618: LOAD_ATTR            flag_bits
 628: LOAD_GLOBAL          _MASK_USE_DATA_DESCRIPTOR
 640: BINARY_OP            &
 644: POP_JUMP_FORWARD_IF_FALSE to 674
 646: LOAD_FAST            zipinfo
 648: LOAD_ATTR            _raw_time
 658: LOAD_CONST           8
 660: BINARY_OP            >>
 664: LOAD_CONST           255
 666: BINARY_OP            &
 670: STORE_FAST           check_byte
 672: JUMP_FORWARD         to 700
 674: LOAD_FAST            zipinfo
 676: LOAD_ATTR            CRC
 686: LOAD_CONST           24
 688: BINARY_OP            >>
 692: LOAD_CONST           255
 694: BINARY_OP            &
 698: STORE_FAST           check_byte
 700: LOAD_FAST            self
 702: LOAD_METHOD          _init_decrypter
 724: PRECALL              
 728: CALL                 
 738: STORE_FAST           h
 740: LOAD_FAST            h
 742: LOAD_FAST            check_byte
 744: COMPARE_OP           !=
 750: POP_JUMP_FORWARD_IF_FALSE to 802
 752: LOAD_GLOBAL          NULL + RuntimeError
 764: LOAD_CONST           'Bad password for file %r'
 766: LOAD_FAST            zipinfo
 768: LOAD_ATTR            orig_filename
 778: BINARY_OP            %
 782: PRECALL              
 786: CALL                 
 796: RAISE_VARARGS        
 798: LOAD_CONST           None
 800: RETURN_VALUE         
 802: LOAD_CONST           None
 804: RETURN_VALUE         
