# Disassembly for tempfile._TemporaryFileWrapper.__init__
# From module file: tempfile

## co_consts:
(None,)

## co_names:
('file', 'name', 'delete', '_TemporaryFileCloser', '_closer')

## bytecode:

   0: RESUME               
   2: LOAD_FAST            file
   4: LOAD_FAST            self
   6: STORE_ATTR           file
  16: LOAD_FAST            name
  18: LOAD_FAST            self
  20: STORE_ATTR           name
  30: LOAD_FAST            delete
  32: LOAD_FAST            self
  34: STORE_ATTR           delete
  44: LOAD_GLOBAL          NULL + _TemporaryFileCloser
  56: LOAD_FAST            file
  58: LOAD_FAST            name
  60: LOAD_FAST            delete
  62: PRECALL              
  66: CALL                 
  76: LOAD_FAST            self
  78: STORE_ATTR           _closer
  88: LOAD_CONST           None
  90: RETURN_VALUE         
