# Disassembly for tempfile._TemporaryFileCloser.close
# From module file: tempfile

## co_consts:
(None, True)

## co_names:
('close_called', 'file', 'close')

## bytecode:

   0: RESUME               
   2: LOAD_FAST            self
   4: LOAD_ATTR            close_called
  14: POP_JUMP_FORWARD_IF_TRUE to 84
  16: LOAD_CONST           True
  18: LOAD_FAST            self
  20: STORE_ATTR           close_called
  30: LOAD_FAST            self
  32: LOAD_ATTR            file
  42: LOAD_METHOD          close
  64: PRECALL              
  68: CALL                 
  78: POP_TOP              
  80: LOAD_CONST           None
  82: RETURN_VALUE         
  84: LOAD_CONST           None
  86: RETURN_VALUE         
