# Disassembly for tempfile.SpooledTemporaryFile.__init__
# From module file: tempfile

## co_consts:
(None, 'b', ('encoding', 'errors', 'newline'), False, ('mode', 'buffering', 'suffix', 'prefix', 'encoding', 'newline', 'dir', 'errors'))

## co_names:
('_io', 'BytesIO', '_file', 'text_encoding', 'TextIOWrapper', '_max_size', '_rolled', '_TemporaryFileArgs')

## bytecode:

   0: RESUME               
   2: LOAD_CONST           'b'
   4: LOAD_FAST            mode
   6: CONTAINS_OP          
   8: POP_JUMP_FORWARD_IF_FALSE to 60
  10: LOAD_GLOBAL          NULL + _io
  22: LOAD_ATTR            BytesIO
  32: PRECALL              
  36: CALL                 
  46: LOAD_FAST            self
  48: STORE_ATTR           _file
  58: JUMP_FORWARD         to 192
  60: LOAD_GLOBAL          NULL + _io
  72: LOAD_ATTR            text_encoding
  82: LOAD_FAST            encoding
  84: PRECALL              
  88: CALL                 
  98: STORE_FAST           encoding
 100: LOAD_GLOBAL          NULL + _io
 112: LOAD_ATTR            TextIOWrapper
 122: LOAD_GLOBAL          NULL + _io
 134: LOAD_ATTR            BytesIO
 144: PRECALL              
 148: CALL                 
 158: LOAD_FAST            encoding
 160: LOAD_FAST            errors
 162: LOAD_FAST            newline
 164: KW_NAMES             
 166: PRECALL              
 170: CALL                 
 180: LOAD_FAST            self
 182: STORE_ATTR           _file
 192: LOAD_FAST            max_size
 194: LOAD_FAST            self
 196: STORE_ATTR           _max_size
 206: LOAD_CONST           False
 208: LOAD_FAST            self
 210: STORE_ATTR           _rolled
 220: LOAD_FAST            mode
 222: LOAD_FAST            buffering
 224: LOAD_FAST            suffix
 226: LOAD_FAST            prefix
 228: LOAD_FAST            encoding
 230: LOAD_FAST            newline
 232: LOAD_FAST            dir
 234: LOAD_FAST            errors
 236: LOAD_CONST           ('mode', 'buffering', 'suffix', 'prefix', 'encoding', 'newline', 'dir', 'errors')
 238: BUILD_CONST_KEY_MAP  
 240: LOAD_FAST            self
 242: STORE_ATTR           _TemporaryFileArgs
 252: LOAD_CONST           None
 254: RETURN_VALUE         
