# Disassembly for tempfile.SpooledTemporaryFile._check
# From module file: tempfile

## co_consts:
(None,)

## co_names:
('_rolled', '_max_size', 'tell', 'rollover')

## bytecode:

   0: RESUME               
   2: LOAD_FAST            self
   4: LOAD_ATTR            _rolled
  14: POP_JUMP_FORWARD_IF_FALSE to 20
  16: LOAD_CONST           None
  18: RETURN_VALUE         
  20: LOAD_FAST            self
  22: LOAD_ATTR            _max_size
  32: STORE_FAST           max_size
  34: LOAD_FAST            max_size
  36: POP_JUMP_FORWARD_IF_FALSE to 130
  38: LOAD_FAST            file
  40: LOAD_METHOD          tell
  62: PRECALL              
  66: CALL                 
  76: LOAD_FAST            max_size
  78: COMPARE_OP           >
  84: POP_JUMP_FORWARD_IF_FALSE to 134
  86: LOAD_FAST            self
  88: LOAD_METHOD          rollover
 110: PRECALL              
 114: CALL                 
 124: POP_TOP              
 126: LOAD_CONST           None
 128: RETURN_VALUE         
 130: LOAD_CONST           None
 132: RETURN_VALUE         
 134: LOAD_CONST           None
 136: RETURN_VALUE         
