# Disassembly for tempfile.TemporaryDirectory._rmtree
# From module file: tempfile

## co_consts:
(None, <code object onerror at 0x0000024068E1CD20, file "tempfile.py", line 863>, ('onerror',))

## co_names:
('_shutil', 'rmtree')

## bytecode:

   0: MAKE_CELL            cls
   2: MAKE_CELL            name
   4: MAKE_CELL            ignore_errors
   6: RESUME               
   8: LOAD_CLOSURE         cls
  10: LOAD_CLOSURE         ignore_errors
  12: LOAD_CLOSURE         name
  14: BUILD_TUPLE          
  16: LOAD_CONST           <code object onerror at 0x0000024068E1CD20, file "tempfile.py", line 863>
  18: MAKE_FUNCTION        closure
  20: STORE_FAST           onerror
  22: LOAD_GLOBAL          NULL + _shutil
  34: LOAD_ATTR            rmtree
  44: LOAD_DEREF           name
  46: LOAD_FAST            onerror
  48: KW_NAMES             
  50: PRECALL              
  54: CALL                 
  64: POP_TOP              
  66: LOAD_CONST           None
  68: RETURN_VALUE         
