# Disassembly for calendar.HTMLCalendar.formatweekheader
# From module file: calendar

## co_consts:
('\n        Return a header for a week as a table row.\n        ', '', <code object <genexpr> at 0x00000240693EAC30, file "calendar.py", line 466>, '<tr>%s</tr>')

## co_names:
('join', 'iterweekdays')

## bytecode:

   0: MAKE_CELL            self
   2: RESUME               
   4: LOAD_CONST           ''
   6: LOAD_METHOD          join
  28: LOAD_CLOSURE         self
  30: BUILD_TUPLE          
  32: LOAD_CONST           <code object <genexpr> at 0x00000240693EAC30, file "calendar.py", line 466>
  34: MAKE_FUNCTION        closure
  36: LOAD_DEREF           self
  38: LOAD_METHOD          iterweekdays
  60: PRECALL              
  64: CALL                 
  74: GET_ITER             
  76: PRECALL              
  80: CALL                 
  90: PRECALL              
  94: CALL                 
 104: STORE_FAST           s
 106: LOAD_CONST           '<tr>%s</tr>'
 108: LOAD_FAST            s
 110: BINARY_OP            %
 114: RETURN_VALUE         
