# Disassembly for calendar.HTMLCalendar.formatweekday
# From module file: calendar

## co_consts:
('\n        Return a weekday name as a table header.\n        ', '<th class="', '">', '</th>')

## co_names:
('cssclasses_weekday_head', 'day_abbr')

## bytecode:

   0: RESUME               
   2: LOAD_CONST           '<th class="'
   4: LOAD_FAST            self
   6: LOAD_ATTR            cssclasses_weekday_head
  16: LOAD_FAST            day
  18: BINARY_SUBSCR        
  28: FORMAT_VALUE         str
  30: LOAD_CONST           '">'
  32: LOAD_GLOBAL          day_abbr
  44: LOAD_FAST            day
  46: BINARY_SUBSCR        
  56: FORMAT_VALUE         str
  58: LOAD_CONST           '</th>'
  60: BUILD_STRING         
  62: RETURN_VALUE         
