# Disassembly for calendar.Calendar.itermonthdays
# From module file: calendar

## co_consts:
('\n        Like itermonthdates(), but will yield day numbers. For days outside\n        the specified month the day number is 0.\n        ', 7, 0, None, 1)

## co_names:
('monthrange', 'firstweekday', 'repeat', 'range')

## bytecode:

   0: RETURN_GENERATOR     
   2: POP_TOP              
   4: RESUME               
   6: LOAD_GLOBAL          NULL + monthrange
  18: LOAD_FAST            year
  20: LOAD_FAST            month
  22: PRECALL              
  26: CALL                 
  36: UNPACK_SEQUENCE      
  40: STORE_FAST           day1
  42: STORE_FAST           ndays
  44: LOAD_FAST            day1
  46: LOAD_FAST            self
  48: LOAD_ATTR            firstweekday
  58: BINARY_OP            -
  62: LOAD_CONST           7
  64: BINARY_OP            %
  68: STORE_FAST           days_before
  70: LOAD_GLOBAL          NULL + repeat
  82: LOAD_CONST           0
  84: LOAD_FAST            days_before
  86: PRECALL              
  90: CALL                 
 100: GET_YIELD_FROM_ITER  
 102: LOAD_CONST           None
 104: SEND                 to 112
 106: YIELD_VALUE          
 108: RESUME               
 110: JUMP_BACKWARD_NO_INTERRUPT to 104
 112: POP_TOP              
 114: LOAD_GLOBAL          NULL + range
 126: LOAD_CONST           1
 128: LOAD_FAST            ndays
 130: LOAD_CONST           1
 132: BINARY_OP            +
 136: PRECALL              
 140: CALL                 
 150: GET_YIELD_FROM_ITER  
 152: LOAD_CONST           None
 154: SEND                 to 162
 156: YIELD_VALUE          
 158: RESUME               
 160: JUMP_BACKWARD_NO_INTERRUPT to 154
 162: POP_TOP              
 164: LOAD_FAST            self
 166: LOAD_ATTR            firstweekday
 176: LOAD_FAST            day1
 178: BINARY_OP            -
 182: LOAD_FAST            ndays
 184: BINARY_OP            -
 188: LOAD_CONST           7
 190: BINARY_OP            %
 194: STORE_FAST           days_after
 196: LOAD_GLOBAL          NULL + repeat
 208: LOAD_CONST           0
 210: LOAD_FAST            days_after
 212: PRECALL              
 216: CALL                 
 226: GET_YIELD_FROM_ITER  
 228: LOAD_CONST           None
 230: SEND                 to 238
 232: YIELD_VALUE          
 234: RESUME               
 236: JUMP_BACKWARD_NO_INTERRUPT to 230
 238: POP_TOP              
 240: LOAD_CONST           None
 242: RETURN_VALUE         
