# Disassembly for calendar.setfirstweekday
# From module file: calendar

## co_consts:
(None,)

## co_names:
('MONDAY', 'SUNDAY', 'IllegalWeekdayError', 'c', 'firstweekday')

## bytecode:

   0: RESUME               
   2: LOAD_GLOBAL          MONDAY
  14: LOAD_FAST            firstweekday
  16: SWAP                 
  18: COPY                 
  20: COMPARE_OP           <=
  26: POP_JUMP_FORWARD_IF_FALSE to 50
  28: LOAD_GLOBAL          SUNDAY
  40: COMPARE_OP           <=
  46: POP_JUMP_FORWARD_IF_TRUE to 82
  48: JUMP_FORWARD         to 52
  50: POP_TOP              
  52: LOAD_GLOBAL          NULL + IllegalWeekdayError
  64: LOAD_FAST            firstweekday
  66: PRECALL              
  70: CALL                 
  80: RAISE_VARARGS        
  82: LOAD_FAST            firstweekday
  84: LOAD_GLOBAL          c
  96: STORE_ATTR           firstweekday
 106: LOAD_CONST           None
 108: RETURN_VALUE         
