# Disassembly for calendar.TextCalendar
# From module file: calendar

## co_consts:
('TextCalendar', '\n    Subclass of Calendar that outputs a calendar as a simple plain text\n    similar to the UNIX program cal.\n    ', <code object prweek at 0x000002406944A340, file "calendar.py", line 301>, <code object formatday at 0x00000240693EA230, file "calendar.py", line 307>, <code object formatweek at 0x000002406944A780, file "calendar.py", line 317>, <code object formatweekday at 0x00000240693D2C20, file "calendar.py", line 323>, <code object formatweekheader at 0x00000240693D2760, file "calendar.py", line 333>, True, <code object formatmonthname at 0x000002406944A890, file "calendar.py", line 339>, 0, <code object prmonth at 0x000002406944A9A0, file "calendar.py", line 348>, <code object formatmonth at 0x0000024068DA7150, file "calendar.py", line 354>, 2, 1, 6, 3, <code object formatyear at 0x0000024068D5FCF0, file "calendar.py", line 370>, <code object pryear at 0x000002406944ABC0, file "calendar.py", line 407>, None, (True,), (0, 0), (2, 1, 6, 3), (0, 0, 6, 3))

## co_names:
('__name__', '__module__', '__qualname__', '__doc__', 'prweek', 'formatday', 'formatweek', 'formatweekday', 'formatweekheader', 'formatmonthname', 'prmonth', 'formatmonth', 'formatyear', 'pryear')

## bytecode:

   0: RESUME               
   2: LOAD_NAME            __name__
   4: STORE_NAME           __module__
   6: LOAD_CONST           'TextCalendar'
   8: STORE_NAME           __qualname__
  10: LOAD_CONST           '\n    Subclass of Calendar that outputs a calendar as a simple plain text\n    similar to the UNIX program cal.\n    '
  12: STORE_NAME           __doc__
  14: LOAD_CONST           <code object prweek at 0x000002406944A340, file "calendar.py", line 301>
  16: MAKE_FUNCTION        
  18: STORE_NAME           prweek
  20: LOAD_CONST           <code object formatday at 0x00000240693EA230, file "calendar.py", line 307>
  22: MAKE_FUNCTION        
  24: STORE_NAME           formatday
  26: LOAD_CONST           <code object formatweek at 0x000002406944A780, file "calendar.py", line 317>
  28: MAKE_FUNCTION        
  30: STORE_NAME           formatweek
  32: LOAD_CONST           <code object formatweekday at 0x00000240693D2C20, file "calendar.py", line 323>
  34: MAKE_FUNCTION        
  36: STORE_NAME           formatweekday
  38: LOAD_CONST           <code object formatweekheader at 0x00000240693D2760, file "calendar.py", line 333>
  40: MAKE_FUNCTION        
  42: STORE_NAME           formatweekheader
  44: LOAD_CONST           (True,)
  46: LOAD_CONST           <code object formatmonthname at 0x000002406944A890, file "calendar.py", line 339>
  48: MAKE_FUNCTION        defaults
  50: STORE_NAME           formatmonthname
  52: LOAD_CONST           (0, 0)
  54: LOAD_CONST           <code object prmonth at 0x000002406944A9A0, file "calendar.py", line 348>
  56: MAKE_FUNCTION        defaults
  58: STORE_NAME           prmonth
  60: LOAD_CONST           (0, 0)
  62: LOAD_CONST           <code object formatmonth at 0x0000024068DA7150, file "calendar.py", line 354>
  64: MAKE_FUNCTION        defaults
  66: STORE_NAME           formatmonth
  68: LOAD_CONST           (2, 1, 6, 3)
  70: LOAD_CONST           <code object formatyear at 0x0000024068D5FCF0, file "calendar.py", line 370>
  72: MAKE_FUNCTION        defaults
  74: STORE_NAME           formatyear
  76: LOAD_CONST           (0, 0, 6, 3)
  78: LOAD_CONST           <code object pryear at 0x000002406944ABC0, file "calendar.py", line 407>
  80: MAKE_FUNCTION        defaults
  82: STORE_NAME           pryear
  84: LOAD_CONST           None
  86: RETURN_VALUE         
