# Disassembly for calendar.format
# From module file: calendar

## co_consts:
('Prints multi-column formatting for year calendars', None)

## co_names:
('print', 'formatstring')

## bytecode:

   0: RESUME               
   2: LOAD_GLOBAL          NULL + print
  14: LOAD_GLOBAL          NULL + formatstring
  26: LOAD_FAST            cols
  28: LOAD_FAST            colwidth
  30: LOAD_FAST            spacing
  32: PRECALL              
  36: CALL                 
  46: PRECALL              
  50: CALL                 
  60: POP_TOP              
  62: LOAD_CONST           None
  64: RETURN_VALUE         
