# Disassembly for calendar
# From module file: calendar

## co_consts:
('Calendar printing functions\n\nNote when comparing these calendars to the ones printed by cal(1): By\ndefault, these calendars have Monday as the first day of the week, and\nSunday as the last (the European convention). Use setfirstweekday() to\nset the first day of the week (0=Monday, 6=Sunday).', 0, None, ('repeat',), ('IllegalMonthError', 'IllegalWeekdayError', 'setfirstweekday', 'firstweekday', 'isleap', 'leapdays', 'weekday', 'monthrange', 'monthcalendar', 'prmonth', 'month', 'prcal', 'calendar', 'timegm', 'month_name', 'month_abbr', 'day_name', 'day_abbr', 'Calendar', 'TextCalendar', 'HTMLCalendar', 'LocaleTextCalendar', 'LocaleHTMLCalendar', 'weekheader', 'MONDAY', 'TUESDAY', 'WEDNESDAY', 'THURSDAY', 'FRIDAY', 'SATURDAY', 'SUNDAY'), <code object IllegalMonthError at 0x00000240694657D0, file "calendar.py", line 26>, 'IllegalMonthError', <code object IllegalWeekdayError at 0x0000024069466090, file "calendar.py", line 33>, 'IllegalWeekdayError', 1, 2, (0, 31, 28, 31, 30, 31, 30, 31, 31, 30, 31, 30, 31), <code object _localized_month at 0x00000240693D3930, file "calendar.py", line 52>, '_localized_month', <code object _localized_day at 0x000002406944B770, file "calendar.py", line 71>, '_localized_day', '%A', '%a', '%B', '%b', 7, <code object isleap at 0x000002406945DD40, file "calendar.py", line 102>, <code object leapdays at 0x000002406941AC10, file "calendar.py", line 107>, <code object weekday at 0x00000240691C02F0, file "calendar.py", line 115>, <code object monthrange at 0x000002406921FB20, file "calendar.py", line 122>, <code object _monthlen at 0x000002406944A230, file "calendar.py", line 132>, <code object _prevmonth at 0x000002406945D2F0, file "calendar.py", line 136>, <code object _nextmonth at 0x000002406945DE30, file "calendar.py", line 143>, <code object Calendar at 0x00000240691F39F0, file "calendar.py", line 150>, 'Calendar', <code object TextCalendar at 0x000002406944AEF0, file "calendar.py", line 295>, 'TextCalendar', <code object HTMLCalendar at 0x00000240693D36D0, file "calendar.py", line 412>, 'HTMLCalendar', <code object different_locale at 0x00000240694679F0, file "calendar.py", line 548>, 'different_locale', <code object _get_default_locale at 0x00000240691F60B0, file "calendar.py", line 563>, <code object LocaleTextCalendar at 0x000002406945F4B0, file "calendar.py", line 573>, 'LocaleTextCalendar', <code object LocaleHTMLCalendar at 0x000002406945F5A0, file "calendar.py", line 594>, 'LocaleHTMLCalendar', <code object setfirstweekday at 0x00000240693D2E80, file "calendar.py", line 618>, 20, 6, <code object format at 0x00000240693EAD30, file "calendar.py", line 638>, <code object formatstring at 0x000002406944B110, file "calendar.py", line 643>, 1970, <code object timegm at 0x00000240691E9E30, file "calendar.py", line 653>, <code object main at 0x0000024068E0ECB0, file "calendar.py", line 663>, '__main__')

## co_names:
('__doc__', 'sys', 'datetime', 'locale', '_locale', 'itertools', 'repeat', '__all__', 'ValueError', 'error', 'IllegalMonthError', 'IllegalWeekdayError', 'January', 'February', 'mdays', '_localized_month', '_localized_day', 'day_name', 'day_abbr', 'month_name', 'month_abbr', 'range', 'MONDAY', 'TUESDAY', 'WEDNESDAY', 'THURSDAY', 'FRIDAY', 'SATURDAY', 'SUNDAY', 'isleap', 'leapdays', 'weekday', 'monthrange', '_monthlen', '_prevmonth', '_nextmonth', 'object', 'Calendar', 'TextCalendar', 'HTMLCalendar', 'different_locale', '_get_default_locale', 'LocaleTextCalendar', 'LocaleHTMLCalendar', 'c', 'getfirstweekday', 'firstweekday', 'setfirstweekday', 'monthdayscalendar', 'monthcalendar', 'prweek', 'formatweek', 'week', 'formatweekheader', 'weekheader', 'prmonth', 'formatmonth', 'month', 'formatyear', 'calendar', 'pryear', 'prcal', '_colwidth', '_spacing', 'format', 'formatstring', 'EPOCH', 'date', 'toordinal', '_EPOCH_ORD', 'timegm', 'main', '__name__', 'argv')

## bytecode:

   0: RESUME               
   2: LOAD_CONST           'Calendar printing functions\n\nNote when comparing these calendars to the ones printed by cal(1): By\ndefault, these calendars have Monday as the first day of the week, and\nSunday as the last (the European convention). Use setfirstweekday() to\nset the first day of the week (0=Monday, 6=Sunday).'
   4: STORE_NAME           __doc__
   6: LOAD_CONST           0
   8: LOAD_CONST           None
  10: IMPORT_NAME          sys
  12: STORE_NAME           sys
  14: LOAD_CONST           0
  16: LOAD_CONST           None
  18: IMPORT_NAME          datetime
  20: STORE_NAME           datetime
  22: LOAD_CONST           0
  24: LOAD_CONST           None
  26: IMPORT_NAME          locale
  28: STORE_NAME           _locale
  30: LOAD_CONST           0
  32: LOAD_CONST           ('repeat',)
  34: IMPORT_NAME          itertools
  36: IMPORT_FROM          repeat
  38: STORE_NAME           repeat
  40: POP_TOP              
  42: BUILD_LIST           
  44: LOAD_CONST           ('IllegalMonthError', 'IllegalWeekdayError', 'setfirstweekday', 'firstweekday', 'isleap', 'leapdays', 'weekday', 'monthrange', 'monthcalendar', 'prmonth', 'month', 'prcal', 'calendar', 'timegm', 'month_name', 'month_abbr', 'day_name', 'day_abbr', 'Calendar', 'TextCalendar', 'HTMLCalendar', 'LocaleTextCalendar', 'LocaleHTMLCalendar', 'weekheader', 'MONDAY', 'TUESDAY', 'WEDNESDAY', 'THURSDAY', 'FRIDAY', 'SATURDAY', 'SUNDAY')
  46: LIST_EXTEND          
  48: STORE_NAME           __all__
  50: LOAD_NAME            ValueError
  52: STORE_NAME           error
  54: PUSH_NULL            
  56: LOAD_BUILD_CLASS     
  58: LOAD_CONST           <code object IllegalMonthError at 0x00000240694657D0, file "calendar.py", line 26>
  60: MAKE_FUNCTION        
  62: LOAD_CONST           'IllegalMonthError'
  64: LOAD_NAME            ValueError
  66: PRECALL              
  70: CALL                 
  80: STORE_NAME           IllegalMonthError
  82: PUSH_NULL            
  84: LOAD_BUILD_CLASS     
  86: LOAD_CONST           <code object IllegalWeekdayError at 0x0000024069466090, file "calendar.py", line 33>
  88: MAKE_FUNCTION        
  90: LOAD_CONST           'IllegalWeekdayError'
  92: LOAD_NAME            ValueError
  94: PRECALL              
  98: CALL                 
 108: STORE_NAME           IllegalWeekdayError
 110: LOAD_CONST           1
 112: STORE_NAME           January
 114: LOAD_CONST           2
 116: STORE_NAME           February
 118: BUILD_LIST           
 120: LOAD_CONST           (0, 31, 28, 31, 30, 31, 30, 31, 31, 30, 31, 30, 31)
 122: LIST_EXTEND          
 124: STORE_NAME           mdays
 126: PUSH_NULL            
 128: LOAD_BUILD_CLASS     
 130: LOAD_CONST           <code object _localized_month at 0x00000240693D3930, file "calendar.py", line 52>
 132: MAKE_FUNCTION        
 134: LOAD_CONST           '_localized_month'
 136: PRECALL              
 140: CALL                 
 150: STORE_NAME           _localized_month
 152: PUSH_NULL            
 154: LOAD_BUILD_CLASS     
 156: LOAD_CONST           <code object _localized_day at 0x000002406944B770, file "calendar.py", line 71>
 158: MAKE_FUNCTION        
 160: LOAD_CONST           '_localized_day'
 162: PRECALL              
 166: CALL                 
 176: STORE_NAME           _localized_day
 178: PUSH_NULL            
 180: LOAD_NAME            _localized_day
 182: LOAD_CONST           '%A'
 184: PRECALL              
 188: CALL                 
 198: STORE_NAME           day_name
 200: PUSH_NULL            
 202: LOAD_NAME            _localized_day
 204: LOAD_CONST           '%a'
 206: PRECALL              
 210: CALL                 
 220: STORE_NAME           day_abbr
 222: PUSH_NULL            
 224: LOAD_NAME            _localized_month
 226: LOAD_CONST           '%B'
 228: PRECALL              
 232: CALL                 
 242: STORE_NAME           month_name
 244: PUSH_NULL            
 246: LOAD_NAME            _localized_month
 248: LOAD_CONST           '%b'
 250: PRECALL              
 254: CALL                 
 264: STORE_NAME           month_abbr
 266: PUSH_NULL            
 268: LOAD_NAME            range
 270: LOAD_CONST           7
 272: PRECALL              
 276: CALL                 
 286: UNPACK_SEQUENCE      
 290: STORE_NAME           MONDAY
 292: STORE_NAME           TUESDAY
 294: STORE_NAME           WEDNESDAY
 296: STORE_NAME           THURSDAY
 298: STORE_NAME           FRIDAY
 300: STORE_NAME           SATURDAY
 302: STORE_NAME           SUNDAY
 304: LOAD_CONST           <code object isleap at 0x000002406945DD40, file "calendar.py", line 102>
 306: MAKE_FUNCTION        
 308: STORE_NAME           isleap
 310: LOAD_CONST           <code object leapdays at 0x000002406941AC10, file "calendar.py", line 107>
 312: MAKE_FUNCTION        
 314: STORE_NAME           leapdays
 316: LOAD_CONST           <code object weekday at 0x00000240691C02F0, file "calendar.py", line 115>
 318: MAKE_FUNCTION        
 320: STORE_NAME           weekday
 322: LOAD_CONST           <code object monthrange at 0x000002406921FB20, file "calendar.py", line 122>
 324: MAKE_FUNCTION        
 326: STORE_NAME           monthrange
 328: LOAD_CONST           <code object _monthlen at 0x000002406944A230, file "calendar.py", line 132>
 330: MAKE_FUNCTION        
 332: STORE_NAME           _monthlen
 334: LOAD_CONST           <code object _prevmonth at 0x000002406945D2F0, file "calendar.py", line 136>
 336: MAKE_FUNCTION        
 338: STORE_NAME           _prevmonth
 340: LOAD_CONST           <code object _nextmonth at 0x000002406945DE30, file "calendar.py", line 143>
 342: MAKE_FUNCTION        
 344: STORE_NAME           _nextmonth
 346: PUSH_NULL            
 348: LOAD_BUILD_CLASS     
 350: LOAD_CONST           <code object Calendar at 0x00000240691F39F0, file "calendar.py", line 150>
 352: MAKE_FUNCTION        
 354: LOAD_CONST           'Calendar'
 356: LOAD_NAME            object
 358: PRECALL              
 362: CALL                 
 372: STORE_NAME           Calendar
 374: PUSH_NULL            
 376: LOAD_BUILD_CLASS     
 378: LOAD_CONST           <code object TextCalendar at 0x000002406944AEF0, file "calendar.py", line 295>
 380: MAKE_FUNCTION        
 382: LOAD_CONST           'TextCalendar'
 384: LOAD_NAME            Calendar
 386: PRECALL              
 390: CALL                 
 400: STORE_NAME           TextCalendar
 402: PUSH_NULL            
 404: LOAD_BUILD_CLASS     
 406: LOAD_CONST           <code object HTMLCalendar at 0x00000240693D36D0, file "calendar.py", line 412>
 408: MAKE_FUNCTION        
 410: LOAD_CONST           'HTMLCalendar'
 412: LOAD_NAME            Calendar
 414: PRECALL              
 418: CALL                 
 428: STORE_NAME           HTMLCalendar
 430: PUSH_NULL            
 432: LOAD_BUILD_CLASS     
 434: LOAD_CONST           <code object different_locale at 0x00000240694679F0, file "calendar.py", line 548>
 436: MAKE_FUNCTION        
 438: LOAD_CONST           'different_locale'
 440: PRECALL              
 444: CALL                 
 454: STORE_NAME           different_locale
 456: LOAD_CONST           <code object _get_default_locale at 0x00000240691F60B0, file "calendar.py", line 563>
 458: MAKE_FUNCTION        
 460: STORE_NAME           _get_default_locale
 462: PUSH_NULL            
 464: LOAD_BUILD_CLASS     
 466: LOAD_CONST           <code object LocaleTextCalendar at 0x000002406945F4B0, file "calendar.py", line 573>
 468: MAKE_FUNCTION        
 470: LOAD_CONST           'LocaleTextCalendar'
 472: LOAD_NAME            TextCalendar
 474: PRECALL              
 478: CALL                 
 488: STORE_NAME           LocaleTextCalendar
 490: PUSH_NULL            
 492: LOAD_BUILD_CLASS     
 494: LOAD_CONST           <code object LocaleHTMLCalendar at 0x000002406945F5A0, file "calendar.py", line 594>
 496: MAKE_FUNCTION        
 498: LOAD_CONST           'LocaleHTMLCalendar'
 500: LOAD_NAME            HTMLCalendar
 502: PRECALL              
 506: CALL                 
 516: STORE_NAME           LocaleHTMLCalendar
 518: PUSH_NULL            
 520: LOAD_NAME            TextCalendar
 522: PRECALL              
 526: CALL                 
 536: STORE_NAME           c
 538: LOAD_NAME            c
 540: LOAD_ATTR            getfirstweekday
 550: STORE_NAME           firstweekday
 552: LOAD_CONST           <code object setfirstweekday at 0x00000240693D2E80, file "calendar.py", line 618>
 554: MAKE_FUNCTION        
 556: STORE_NAME           setfirstweekday
 558: LOAD_NAME            c
 560: LOAD_ATTR            monthdayscalendar
 570: STORE_NAME           monthcalendar
 572: LOAD_NAME            c
 574: LOAD_ATTR            prweek
 584: STORE_NAME           prweek
 586: LOAD_NAME            c
 588: LOAD_ATTR            formatweek
 598: STORE_NAME           week
 600: LOAD_NAME            c
 602: LOAD_ATTR            formatweekheader
 612: STORE_NAME           weekheader
 614: LOAD_NAME            c
 616: LOAD_ATTR            prmonth
 626: STORE_NAME           prmonth
 628: LOAD_NAME            c
 630: LOAD_ATTR            formatmonth
 640: STORE_NAME           month
 642: LOAD_NAME            c
 644: LOAD_ATTR            formatyear
 654: STORE_NAME           calendar
 656: LOAD_NAME            c
 658: LOAD_ATTR            pryear
 668: STORE_NAME           prcal
 670: LOAD_CONST           20
 672: STORE_NAME           _colwidth
 674: LOAD_CONST           6
 676: STORE_NAME           _spacing
 678: LOAD_NAME            _colwidth
 680: LOAD_NAME            _spacing
 682: BUILD_TUPLE          
 684: LOAD_CONST           <code object format at 0x00000240693EAD30, file "calendar.py", line 638>
 686: MAKE_FUNCTION        defaults
 688: STORE_NAME           format
 690: LOAD_NAME            _colwidth
 692: LOAD_NAME            _spacing
 694: BUILD_TUPLE          
 696: LOAD_CONST           <code object formatstring at 0x000002406944B110, file "calendar.py", line 643>
 698: MAKE_FUNCTION        defaults
 700: STORE_NAME           formatstring
 702: LOAD_CONST           1970
 704: STORE_NAME           EPOCH
 706: PUSH_NULL            
 708: LOAD_NAME            datetime
 710: LOAD_ATTR            date
 720: LOAD_NAME            EPOCH
 722: LOAD_CONST           1
 724: LOAD_CONST           1
 726: PRECALL              
 730: CALL                 
 740: LOAD_METHOD          toordinal
 762: PRECALL              
 766: CALL                 
 776: STORE_NAME           _EPOCH_ORD
 778: LOAD_CONST           <code object timegm at 0x00000240691E9E30, file "calendar.py", line 653>
 780: MAKE_FUNCTION        
 782: STORE_NAME           timegm
 784: LOAD_CONST           <code object main at 0x0000024068E0ECB0, file "calendar.py", line 663>
 786: MAKE_FUNCTION        
 788: STORE_NAME           main
 790: LOAD_NAME            __name__
 792: LOAD_CONST           '__main__'
 794: COMPARE_OP           ==
 800: POP_JUMP_FORWARD_IF_FALSE to 838
 802: PUSH_NULL            
 804: LOAD_NAME            main
 806: LOAD_NAME            sys
 808: LOAD_ATTR            argv
 818: PRECALL              
 822: CALL                 
 832: POP_TOP              
 834: LOAD_CONST           None
 836: RETURN_VALUE         
 838: LOAD_CONST           None
 840: RETURN_VALUE         
