# Disassembly for calendar.monthrange
# From module file: calendar

## co_consts:
('Return weekday (0-6 ~ Mon-Sun) and number of days (28-31) for\n       year, month.', 1, 12)

## co_names:
('IllegalMonthError', 'weekday', 'mdays', 'February', 'isleap')

## bytecode:

   0: RESUME               
   2: LOAD_CONST           1
   4: LOAD_FAST            month
   6: SWAP                 
   8: COPY                 
  10: COMPARE_OP           <=
  16: POP_JUMP_FORWARD_IF_FALSE to 30
  18: LOAD_CONST           12
  20: COMPARE_OP           <=
  26: POP_JUMP_FORWARD_IF_TRUE to 62
  28: JUMP_FORWARD         to 32
  30: POP_TOP              
  32: LOAD_GLOBAL          NULL + IllegalMonthError
  44: LOAD_FAST            month
  46: PRECALL              
  50: CALL                 
  60: RAISE_VARARGS        
  62: LOAD_GLOBAL          NULL + weekday
  74: LOAD_FAST            year
  76: LOAD_FAST            month
  78: LOAD_CONST           1
  80: PRECALL              
  84: CALL                 
  94: STORE_FAST           day1
  96: LOAD_GLOBAL          mdays
 108: LOAD_FAST            month
 110: BINARY_SUBSCR        
 120: LOAD_FAST            month
 122: LOAD_GLOBAL          February
 134: COMPARE_OP           ==
 140: JUMP_IF_FALSE_OR_POP to 170
 142: LOAD_GLOBAL          NULL + isleap
 154: LOAD_FAST            year
 156: PRECALL              
 160: CALL                 
 170: BINARY_OP            +
 174: STORE_FAST           ndays
 176: LOAD_FAST            day1
 178: LOAD_FAST            ndays
 180: BUILD_TUPLE          
 182: RETURN_VALUE         
