# Disassembly for calendar.TextCalendar.formatyear
# From module file: calendar

## co_consts:
("\n        Returns a year's calendar as a multi-line string.\n        ", 2, 1, 7, '\n', 13, <code object <genexpr> at 0x00000240693EA630, file "calendar.py", line 387>, <code object <genexpr> at 0x0000024069467830, file "calendar.py", line 391>, <code object <genexpr> at 0x000002406945F3C0, file "calendar.py", line 395>, '')

## co_names:
('max', 'append', 'repr', 'center', 'rstrip', 'formatweekheader', 'enumerate', 'yeardays2calendar', 'range', 'min', 'formatstring', 'len', 'formatweek', 'join')

## bytecode:

   0: MAKE_CELL            self
   2: MAKE_CELL            theyear
   4: MAKE_CELL            colwidth
   6: MAKE_CELL            header
   8: RESUME               
  10: LOAD_GLOBAL          NULL + max
  22: LOAD_CONST           2
  24: LOAD_FAST            w
  26: PRECALL              
  30: CALL                 
  40: STORE_FAST           w
  42: LOAD_GLOBAL          NULL + max
  54: LOAD_CONST           1
  56: LOAD_FAST            l
  58: PRECALL              
  62: CALL                 
  72: STORE_FAST           l
  74: LOAD_GLOBAL          NULL + max
  86: LOAD_CONST           2
  88: LOAD_FAST            c
  90: PRECALL              
  94: CALL                 
 104: STORE_FAST           c
 106: LOAD_FAST            w
 108: LOAD_CONST           1
 110: BINARY_OP            +
 114: LOAD_CONST           7
 116: BINARY_OP            *
 120: LOAD_CONST           1
 122: BINARY_OP            -
 126: STORE_DEREF          colwidth
 128: BUILD_LIST           
 130: STORE_FAST           v
 132: LOAD_FAST            v
 134: LOAD_ATTR            append
 144: STORE_FAST           a
 146: PUSH_NULL            
 148: LOAD_FAST            a
 150: LOAD_GLOBAL          NULL + repr
 162: LOAD_DEREF           theyear
 164: PRECALL              
 168: CALL                 
 178: LOAD_METHOD          center
 200: LOAD_DEREF           colwidth
 202: LOAD_FAST            m
 204: BINARY_OP            *
 208: LOAD_FAST            c
 210: LOAD_FAST            m
 212: LOAD_CONST           1
 214: BINARY_OP            -
 218: BINARY_OP            *
 222: BINARY_OP            +
 226: PRECALL              
 230: CALL                 
 240: LOAD_METHOD          rstrip
 262: PRECALL              
 266: CALL                 
 276: PRECALL              
 280: CALL                 
 290: POP_TOP              
 292: PUSH_NULL            
 294: LOAD_FAST            a
 296: LOAD_CONST           '\n'
 298: LOAD_FAST            l
 300: BINARY_OP            *
 304: PRECALL              
 308: CALL                 
 318: POP_TOP              
 320: LOAD_DEREF           self
 322: LOAD_METHOD          formatweekheader
 344: LOAD_FAST            w
 346: PRECALL              
 350: CALL                 
 360: STORE_DEREF          header
 362: LOAD_GLOBAL          NULL + enumerate
 374: LOAD_DEREF           self
 376: LOAD_METHOD          yeardays2calendar
 398: LOAD_DEREF           theyear
 400: LOAD_FAST            m
 402: PRECALL              
 406: CALL                 
 416: PRECALL              
 420: CALL                 
 430: GET_ITER             
 432: EXTENDED_ARG         
 434: FOR_ITER             to 1250
 436: UNPACK_SEQUENCE      
 440: STORE_FAST           i
 442: STORE_FAST           row
 444: LOAD_GLOBAL          NULL + range
 456: LOAD_FAST            m
 458: LOAD_FAST            i
 460: BINARY_OP            *
 464: LOAD_CONST           1
 466: BINARY_OP            +
 470: LOAD_GLOBAL          NULL + min
 482: LOAD_FAST            m
 484: LOAD_FAST            i
 486: LOAD_CONST           1
 488: BINARY_OP            +
 492: BINARY_OP            *
 496: LOAD_CONST           1
 498: BINARY_OP            +
 502: LOAD_CONST           13
 504: PRECALL              
 508: CALL                 
 518: PRECALL              
 522: CALL                 
 532: STORE_FAST           months
 534: PUSH_NULL            
 536: LOAD_FAST            a
 538: LOAD_CONST           '\n'
 540: LOAD_FAST            l
 542: BINARY_OP            *
 546: PRECALL              
 550: CALL                 
 560: POP_TOP              
 562: LOAD_CLOSURE         colwidth
 564: LOAD_CLOSURE         self
 566: LOAD_CLOSURE         theyear
 568: BUILD_TUPLE          
 570: LOAD_CONST           <code object <genexpr> at 0x00000240693EA630, file "calendar.py", line 387>
 572: MAKE_FUNCTION        closure
 574: LOAD_FAST            months
 576: GET_ITER             
 578: PRECALL              
 582: CALL                 
 592: STORE_FAST           names
 594: PUSH_NULL            
 596: LOAD_FAST            a
 598: LOAD_GLOBAL          NULL + formatstring
 610: LOAD_FAST            names
 612: LOAD_DEREF           colwidth
 614: LOAD_FAST            c
 616: PRECALL              
 620: CALL                 
 630: LOAD_METHOD          rstrip
 652: PRECALL              
 656: CALL                 
 666: PRECALL              
 670: CALL                 
 680: POP_TOP              
 682: PUSH_NULL            
 684: LOAD_FAST            a
 686: LOAD_CONST           '\n'
 688: LOAD_FAST            l
 690: BINARY_OP            *
 694: PRECALL              
 698: CALL                 
 708: POP_TOP              
 710: LOAD_CLOSURE         header
 712: BUILD_TUPLE          
 714: LOAD_CONST           <code object <genexpr> at 0x0000024069467830, file "calendar.py", line 391>
 716: MAKE_FUNCTION        closure
 718: LOAD_FAST            months
 720: GET_ITER             
 722: PRECALL              
 726: CALL                 
 736: STORE_FAST           headers
 738: PUSH_NULL            
 740: LOAD_FAST            a
 742: LOAD_GLOBAL          NULL + formatstring
 754: LOAD_FAST            headers
 756: LOAD_DEREF           colwidth
 758: LOAD_FAST            c
 760: PRECALL              
 764: CALL                 
 774: LOAD_METHOD          rstrip
 796: PRECALL              
 800: CALL                 
 810: PRECALL              
 814: CALL                 
 824: POP_TOP              
 826: PUSH_NULL            
 828: LOAD_FAST            a
 830: LOAD_CONST           '\n'
 832: LOAD_FAST            l
 834: BINARY_OP            *
 838: PRECALL              
 842: CALL                 
 852: POP_TOP              
 854: LOAD_GLOBAL          NULL + max
 866: LOAD_CONST           <code object <genexpr> at 0x000002406945F3C0, file "calendar.py", line 395>
 868: MAKE_FUNCTION        
 870: LOAD_FAST            row
 872: GET_ITER             
 874: PRECALL              
 878: CALL                 
 888: PRECALL              
 892: CALL                 
 902: STORE_FAST           height
 904: LOAD_GLOBAL          NULL + range
 916: LOAD_FAST            height
 918: PRECALL              
 922: CALL                 
 932: GET_ITER             
 934: FOR_ITER             to 1246
 936: STORE_FAST           j
 938: BUILD_LIST           
 940: STORE_FAST           weeks
 942: LOAD_FAST            row
 944: GET_ITER             
 946: FOR_ITER             to 1128
 948: STORE_FAST           cal
 950: LOAD_FAST            j
 952: LOAD_GLOBAL          NULL + len
 964: LOAD_FAST            cal
 966: PRECALL              
 970: CALL                 
 980: COMPARE_OP           >=
 986: POP_JUMP_FORWARD_IF_FALSE to 1032
 988: LOAD_FAST            weeks
 990: LOAD_METHOD          append
1012: LOAD_CONST           ''
1014: PRECALL              
1018: CALL                 
1028: POP_TOP              
1030: JUMP_BACKWARD        to 946
1032: LOAD_FAST            weeks
1034: LOAD_METHOD          append
1056: LOAD_DEREF           self
1058: LOAD_METHOD          formatweek
1080: LOAD_FAST            cal
1082: LOAD_FAST            j
1084: BINARY_SUBSCR        
1094: LOAD_FAST            w
1096: PRECALL              
1100: CALL                 
1110: PRECALL              
1114: CALL                 
1124: POP_TOP              
1126: JUMP_BACKWARD        to 946
1128: PUSH_NULL            
1130: LOAD_FAST            a
1132: LOAD_GLOBAL          NULL + formatstring
1144: LOAD_FAST            weeks
1146: LOAD_DEREF           colwidth
1148: LOAD_FAST            c
1150: PRECALL              
1154: CALL                 
1164: LOAD_METHOD          rstrip
1186: PRECALL              
1190: CALL                 
1200: PRECALL              
1204: CALL                 
1214: POP_TOP              
1216: PUSH_NULL            
1218: LOAD_FAST            a
1220: LOAD_CONST           '\n'
1222: LOAD_FAST            l
1224: BINARY_OP            *
1228: PRECALL              
1232: CALL                 
1242: POP_TOP              
1244: JUMP_BACKWARD        to 934
1246: EXTENDED_ARG         
1248: JUMP_BACKWARD        to 432
1250: LOAD_CONST           ''
1252: LOAD_METHOD          join
1274: LOAD_FAST            v
1276: PRECALL              
1280: CALL                 
1290: RETURN_VALUE         
