# Disassembly for shlex.shlex.push_source
# From module file: shlex

## co_consts:
("Push an input source onto the lexer's input source stack.", 1, None, 'shlex: pushing to file ', 'shlex: pushing to stream ')

## co_names:
('isinstance', 'str', 'StringIO', 'filestack', 'appendleft', 'infile', 'instream', 'lineno', 'debug', 'print')

## bytecode:

   0: RESUME               
   2: LOAD_GLOBAL          NULL + isinstance
  14: LOAD_FAST            newstream
  16: LOAD_GLOBAL          str
  28: PRECALL              
  32: CALL                 
  42: POP_JUMP_FORWARD_IF_FALSE to 74
  44: LOAD_GLOBAL          NULL + StringIO
  56: LOAD_FAST            newstream
  58: PRECALL              
  62: CALL                 
  72: STORE_FAST           newstream
  74: LOAD_FAST            self
  76: LOAD_ATTR            filestack
  86: LOAD_METHOD          appendleft
 108: LOAD_FAST            self
 110: LOAD_ATTR            infile
 120: LOAD_FAST            self
 122: LOAD_ATTR            instream
 132: LOAD_FAST            self
 134: LOAD_ATTR            lineno
 144: BUILD_TUPLE          
 146: PRECALL              
 150: CALL                 
 160: POP_TOP              
 162: LOAD_FAST            newfile
 164: LOAD_FAST            self
 166: STORE_ATTR           infile
 176: LOAD_FAST            newstream
 178: LOAD_FAST            self
 180: STORE_ATTR           instream
 190: LOAD_CONST           1
 192: LOAD_FAST            self
 194: STORE_ATTR           lineno
 204: LOAD_FAST            self
 206: LOAD_ATTR            debug
 216: POP_JUMP_FORWARD_IF_FALSE to 322
 218: LOAD_FAST            newfile
 220: POP_JUMP_FORWARD_IF_NONE to 272
 222: LOAD_GLOBAL          NULL + print
 234: LOAD_CONST           'shlex: pushing to file '
 236: LOAD_FAST            self
 238: LOAD_ATTR            infile
 248: FORMAT_VALUE         str
 250: BUILD_STRING         
 252: PRECALL              
 256: CALL                 
 266: POP_TOP              
 268: LOAD_CONST           None
 270: RETURN_VALUE         
 272: LOAD_GLOBAL          NULL + print
 284: LOAD_CONST           'shlex: pushing to stream '
 286: LOAD_FAST            self
 288: LOAD_ATTR            instream
 298: FORMAT_VALUE         str
 300: BUILD_STRING         
 302: PRECALL              
 306: CALL                 
 316: POP_TOP              
 318: LOAD_CONST           None
 320: RETURN_VALUE         
 322: LOAD_CONST           None
 324: RETURN_VALUE         
