# Disassembly for importlib.resources.CompatibilityFiles
# From module file: importlib.resources._adapters

## co_consts:
('CompatibilityFiles', '\n    Adapter for an existing or non-existent resource reader\n    to provide a compatibility .files().\n    ', <code object SpecPath at 0x000002406944B110, file "importlib\resources\_adapters.py", line 48>, 'SpecPath', <code object ChildPath at 0x000002406944B550, file "importlib\resources\_adapters.py", line 83>, 'ChildPath', <code object OrphanPath at 0x000002406944A890, file "importlib\resources\_adapters.py", line 114>, 'OrphanPath', <code object __init__ at 0x0000024069495620, file "importlib\resources\_adapters.py", line 143>, <code object _reader at 0x000002406921FB20, file "importlib\resources\_adapters.py", line 146>, <code object _native at 0x000002406945EC40, file "importlib\resources\_adapters.py", line 151>, <code object __getattr__ at 0x000002406945DE30, file "importlib\resources\_adapters.py", line 158>, <code object files at 0x000002406944AAB0, file "importlib\resources\_adapters.py", line 161>, None)

## co_names:
('__name__', '__module__', '__qualname__', '__doc__', 'abc', 'Traversable', 'SpecPath', 'ChildPath', 'OrphanPath', '__init__', 'property', '_reader', '_native', '__getattr__', 'files')

## bytecode:

   0: RESUME               
   2: LOAD_NAME            __name__
   4: STORE_NAME           __module__
   6: LOAD_CONST           'CompatibilityFiles'
   8: STORE_NAME           __qualname__
  10: LOAD_CONST           '\n    Adapter for an existing or non-existent resource reader\n    to provide a compatibility .files().\n    '
  12: STORE_NAME           __doc__
  14: PUSH_NULL            
  16: LOAD_BUILD_CLASS     
  18: LOAD_CONST           <code object SpecPath at 0x000002406944B110, file "importlib\resources\_adapters.py", line 48>
  20: MAKE_FUNCTION        
  22: LOAD_CONST           'SpecPath'
  24: LOAD_NAME            abc
  26: LOAD_ATTR            Traversable
  36: PRECALL              
  40: CALL                 
  50: STORE_NAME           SpecPath
  52: PUSH_NULL            
  54: LOAD_BUILD_CLASS     
  56: LOAD_CONST           <code object ChildPath at 0x000002406944B550, file "importlib\resources\_adapters.py", line 83>
  58: MAKE_FUNCTION        
  60: LOAD_CONST           'ChildPath'
  62: LOAD_NAME            abc
  64: LOAD_ATTR            Traversable
  74: PRECALL              
  78: CALL                 
  88: STORE_NAME           ChildPath
  90: PUSH_NULL            
  92: LOAD_BUILD_CLASS     
  94: LOAD_CONST           <code object OrphanPath at 0x000002406944A890, file "importlib\resources\_adapters.py", line 114>
  96: MAKE_FUNCTION        
  98: LOAD_CONST           'OrphanPath'
 100: LOAD_NAME            abc
 102: LOAD_ATTR            Traversable
 112: PRECALL              
 116: CALL                 
 126: STORE_NAME           OrphanPath
 128: LOAD_CONST           <code object __init__ at 0x0000024069495620, file "importlib\resources\_adapters.py", line 143>
 130: MAKE_FUNCTION        
 132: STORE_NAME           __init__
 134: LOAD_NAME            property
 136: LOAD_CONST           <code object _reader at 0x000002406921FB20, file "importlib\resources\_adapters.py", line 146>
 138: MAKE_FUNCTION        
 140: PRECALL              
 144: CALL                 
 154: STORE_NAME           _reader
 156: LOAD_CONST           <code object _native at 0x000002406945EC40, file "importlib\resources\_adapters.py", line 151>
 158: MAKE_FUNCTION        
 160: STORE_NAME           _native
 162: LOAD_CONST           <code object __getattr__ at 0x000002406945DE30, file "importlib\resources\_adapters.py", line 158>
 164: MAKE_FUNCTION        
 166: STORE_NAME           __getattr__
 168: LOAD_CONST           <code object files at 0x000002406944AAB0, file "importlib\resources\_adapters.py", line 161>
 170: MAKE_FUNCTION        
 172: STORE_NAME           files
 174: LOAD_CONST           None
 176: RETURN_VALUE         
