# Disassembly for importlib.resources.read_text
# From module file: importlib.resources._legacy

## co_consts:
('Return the decoded string of the resource.\n\n    The decoding-related arguments have the same semantics as those of\n    bytes.decode().\n    ', None)

## co_names:
('open_text', 'read')

## bytecode:

   0: RESUME               
   2: LOAD_GLOBAL          NULL + open_text
  14: LOAD_FAST            package
  16: LOAD_FAST            resource
  18: LOAD_FAST            encoding
  20: LOAD_FAST            errors
  22: PRECALL              
  26: CALL                 
  36: BEFORE_WITH          
  38: STORE_FAST           fp
  40: LOAD_FAST            fp
  42: LOAD_METHOD          read
  64: PRECALL              
  68: CALL                 
  78: SWAP                 
  80: LOAD_CONST           None
  82: LOAD_CONST           None
  84: LOAD_CONST           None
  86: PRECALL              
  90: CALL                 
 100: POP_TOP              
 102: RETURN_VALUE         
 104: PUSH_EXC_INFO        
 106: WITH_EXCEPT_START    
 108: POP_JUMP_FORWARD_IF_TRUE to 118
 110: RERAISE              
 112: COPY                 
 114: POP_EXCEPT           
 116: RERAISE              
 118: POP_TOP              
 120: POP_EXCEPT           
 122: POP_TOP              
 124: POP_TOP              
 126: LOAD_CONST           None
 128: RETURN_VALUE         
