# Disassembly for importlib.resources.SpecLoaderAdapter.__init__
# From module file: importlib.resources._adapters

## co_consts:
(None,)

## co_names:
('spec', 'loader')

## bytecode:

   0: RESUME               
   2: LOAD_FAST            spec
   4: LOAD_FAST            self
   6: STORE_ATTR           spec
  16: PUSH_NULL            
  18: LOAD_FAST            adapter
  20: LOAD_FAST            spec
  22: PRECALL              
  26: CALL                 
  36: LOAD_FAST            self
  38: STORE_ATTR           loader
  48: LOAD_CONST           None
  50: RETURN_VALUE         
