# Disassembly for importlib.resources.ZipReader.files
# From module file: importlib.resources.readers

## co_consts:
(None,)

## co_names:
('zipfile', 'Path', 'archive', 'prefix')

## bytecode:

   0: RESUME               
   2: LOAD_GLOBAL          NULL + zipfile
  14: LOAD_ATTR            Path
  24: LOAD_FAST            self
  26: LOAD_ATTR            archive
  36: LOAD_FAST            self
  38: LOAD_ATTR            prefix
  48: PRECALL              
  52: CALL                 
  62: RETURN_VALUE         
