# Disassembly for importlib.resources.remove_duplicates
# From module file: importlib.resources.readers

## co_consts:
(None,)

## co_names:
('iter', 'collections', 'OrderedDict', 'fromkeys')

## bytecode:

   0: RESUME               
   2: LOAD_GLOBAL          NULL + iter
  14: LOAD_GLOBAL          collections
  26: LOAD_ATTR            OrderedDict
  36: LOAD_METHOD          fromkeys
  58: LOAD_FAST            items
  60: PRECALL              
  64: CALL                 
  74: PRECALL              
  78: CALL                 
  88: RETURN_VALUE         
