# Disassembly for importlib.resources.CompatibilityFiles.ChildPath.open
# From module file: importlib.resources._adapters

## co_consts:
(None,)

## co_names:
('_io_wrapper', '_reader', 'open_resource', 'name')

## bytecode:

   0: RESUME               
   2: LOAD_GLOBAL          NULL + _io_wrapper
  14: LOAD_FAST            self
  16: LOAD_ATTR            _reader
  26: LOAD_METHOD          open_resource
  48: LOAD_FAST            self
  50: LOAD_ATTR            name
  60: PRECALL              
  64: CALL                 
  74: LOAD_FAST            mode
  76: BUILD_LIST           
  78: LOAD_FAST            args
  80: LIST_EXTEND          
  82: LIST_TO_TUPLE        
  84: BUILD_MAP            
  86: LOAD_FAST            kwargs
  88: DICT_MERGE           
  90: CALL_FUNCTION_EX     
  92: RETURN_VALUE         
