# Disassembly for importlib.resources.normalize_path
# From module file: importlib.resources._legacy

## co_consts:
('Normalize a path by ensuring it is a string.\n\n    If the resulting string contains path separators, an exception is raised.\n    ', ' must be only a file name')

## co_names:
('str', 'os', 'path', 'split', 'ValueError')

## bytecode:

   0: RESUME               
   2: LOAD_GLOBAL          NULL + str
  14: LOAD_FAST            path
  16: PRECALL              
  20: CALL                 
  30: STORE_FAST           str_path
  32: LOAD_GLOBAL          os
  44: LOAD_ATTR            path
  54: LOAD_METHOD          split
  76: LOAD_FAST            str_path
  78: PRECALL              
  82: CALL                 
  92: UNPACK_SEQUENCE      
  96: STORE_FAST           parent
  98: STORE_FAST           file_name
 100: LOAD_FAST            parent
 102: POP_JUMP_FORWARD_IF_FALSE to 140
 104: LOAD_GLOBAL          NULL + ValueError
 116: LOAD_FAST            path
 118: FORMAT_VALUE         repr
 120: LOAD_CONST           ' must be only a file name'
 122: BUILD_STRING         
 124: PRECALL              
 128: CALL                 
 138: RAISE_VARARGS        
 140: LOAD_FAST            file_name
 142: RETURN_VALUE         
