# Disassembly for importlib.resources.files
# From module file: importlib.resources._common

## co_consts:
('\n    Get a Traversable resource from a package\n    ',)

## co_names:
('from_package', 'get_package')

## bytecode:

   0: RESUME               
   2: LOAD_GLOBAL          NULL + from_package
  14: LOAD_GLOBAL          NULL + get_package
  26: LOAD_FAST            package
  28: PRECALL              
  32: CALL                 
  42: PRECALL              
  46: CALL                 
  56: RETURN_VALUE         
