# Disassembly for importlib.resources.read_binary
# From module file: importlib.resources._legacy

## co_consts:
('Return the binary contents of the resource.',)

## co_names:
('_common', 'files', 'normalize_path', 'read_bytes')

## bytecode:

   0: RESUME               
   2: LOAD_GLOBAL          NULL + _common
  14: LOAD_ATTR            files
  24: LOAD_FAST            package
  26: PRECALL              
  30: CALL                 
  40: LOAD_GLOBAL          NULL + normalize_path
  52: LOAD_FAST            resource
  54: PRECALL              
  58: CALL                 
  68: BINARY_OP            /
  72: LOAD_METHOD          read_bytes
  94: PRECALL              
  98: CALL                 
 108: RETURN_VALUE         
