# Disassembly for importlib.resources.SpecLoaderAdapter
# From module file: importlib.resources._adapters

## co_consts:
('SpecLoaderAdapter', '\n    Adapt a package spec to adapt the underlying loader.\n    ', <code object <lambda> at 0x0000024069427C50, file "importlib\resources\_adapters.py", line 12>, <code object __init__ at 0x000002406945FF00, file "importlib\resources\_adapters.py", line 12>, <code object __getattr__ at 0x000002406945E4C0, file "importlib\resources\_adapters.py", line 16>, None)

## co_names:
('__name__', '__module__', '__qualname__', '__doc__', '__init__', '__getattr__')

## bytecode:

   0: RESUME               
   2: LOAD_NAME            __name__
   4: STORE_NAME           __module__
   6: LOAD_CONST           'SpecLoaderAdapter'
   8: STORE_NAME           __qualname__
  10: LOAD_CONST           '\n    Adapt a package spec to adapt the underlying loader.\n    '
  12: STORE_NAME           __doc__
  14: LOAD_CONST           <code object <lambda> at 0x0000024069427C50, file "importlib\resources\_adapters.py", line 12>
  16: MAKE_FUNCTION        
  18: BUILD_TUPLE          
  20: LOAD_CONST           <code object __init__ at 0x000002406945FF00, file "importlib\resources\_adapters.py", line 12>
  22: MAKE_FUNCTION        defaults
  24: STORE_NAME           __init__
  26: LOAD_CONST           <code object __getattr__ at 0x000002406945E4C0, file "importlib\resources\_adapters.py", line 16>
  28: MAKE_FUNCTION        
  30: STORE_NAME           __getattr__
  32: LOAD_CONST           None
  34: RETURN_VALUE         
