# Disassembly for importlib.resources.TraversableResourcesLoader.get_resource_reader
# From module file: importlib.resources._adapters

## co_consts:
(None,)

## co_names:
('CompatibilityFiles', 'spec', '_native')

## bytecode:

   0: RESUME               
   2: LOAD_GLOBAL          NULL + CompatibilityFiles
  14: LOAD_FAST            self
  16: LOAD_ATTR            spec
  26: PRECALL              
  30: CALL                 
  40: LOAD_METHOD          _native
  62: PRECALL              
  66: CALL                 
  76: RETURN_VALUE         
