# Disassembly for importlib.resources.FileReader.__init__
# From module file: importlib.resources.readers

## co_consts:
(None,)

## co_names:
('pathlib', 'Path', 'path', 'parent')

## bytecode:

   0: RESUME               
   2: LOAD_GLOBAL          NULL + pathlib
  14: LOAD_ATTR            Path
  24: LOAD_FAST            loader
  26: LOAD_ATTR            path
  36: PRECALL              
  40: CALL                 
  50: LOAD_ATTR            parent
  60: LOAD_FAST            self
  62: STORE_ATTR           path
  72: LOAD_CONST           None
  74: RETURN_VALUE         
