# Disassembly for importlib.resources.CompatibilityFiles._reader
# From module file: importlib.resources._adapters

## co_consts:
(None,)

## co_names:
('suppress', 'AttributeError', 'spec', 'loader', 'get_resource_reader', 'name')

## bytecode:

   0: RESUME               
   2: LOAD_GLOBAL          NULL + suppress
  14: LOAD_GLOBAL          AttributeError
  26: PRECALL              
  30: CALL                 
  40: BEFORE_WITH          
  42: POP_TOP              
  44: LOAD_FAST            self
  46: LOAD_ATTR            spec
  56: LOAD_ATTR            loader
  66: LOAD_METHOD          get_resource_reader
  88: LOAD_FAST            self
  90: LOAD_ATTR            spec
 100: LOAD_ATTR            name
 110: PRECALL              
 114: CALL                 
 124: SWAP                 
 126: LOAD_CONST           None
 128: LOAD_CONST           None
 130: LOAD_CONST           None
 132: PRECALL              
 136: CALL                 
 146: POP_TOP              
 148: RETURN_VALUE         
 150: PUSH_EXC_INFO        
 152: WITH_EXCEPT_START    
 154: POP_JUMP_FORWARD_IF_TRUE to 164
 156: RERAISE              
 158: COPY                 
 160: POP_EXCEPT           
 162: RERAISE              
 164: POP_TOP              
 166: POP_EXCEPT           
 168: POP_TOP              
 170: POP_TOP              
 172: LOAD_CONST           None
 174: RETURN_VALUE         
