# Disassembly for importlib.resources.CompatibilityFiles.files
# From module file: importlib.resources._adapters

## co_consts:
(None,)

## co_names:
('CompatibilityFiles', 'SpecPath', 'spec', '_reader')

## bytecode:

   0: RESUME               
   2: LOAD_GLOBAL          CompatibilityFiles
  14: LOAD_METHOD          SpecPath
  36: LOAD_FAST            self
  38: LOAD_ATTR            spec
  48: LOAD_FAST            self
  50: LOAD_ATTR            _reader
  60: PRECALL              
  64: CALL                 
  74: RETURN_VALUE         
