# Disassembly for importlib.resources.get_package
# From module file: importlib.resources._common

## co_consts:
('Take a package name or module object and return the module.\n\n    Raise an exception if the resolved module is not a package.\n    ', None, ' is not a package')

## co_names:
('resolve', 'wrap_spec', 'submodule_search_locations', 'TypeError')

## bytecode:

   0: RESUME               
   2: LOAD_GLOBAL          NULL + resolve
  14: LOAD_FAST            package
  16: PRECALL              
  20: CALL                 
  30: STORE_FAST           resolved
  32: LOAD_GLOBAL          NULL + wrap_spec
  44: LOAD_FAST            resolved
  46: PRECALL              
  50: CALL                 
  60: LOAD_ATTR            submodule_search_locations
  70: POP_JUMP_FORWARD_IF_NOT_NONE to 108
  72: LOAD_GLOBAL          NULL + TypeError
  84: LOAD_FAST            package
  86: FORMAT_VALUE         repr
  88: LOAD_CONST           ' is not a package'
  90: BUILD_STRING         
  92: PRECALL              
  96: CALL                 
 106: RAISE_VARARGS        
 108: LOAD_FAST            resolved
 110: RETURN_VALUE         
