# Disassembly for importlib.resources.deprecated.wrapper
# From module file: importlib.resources._legacy

## co_consts:
(None, ' is deprecated. Use files() instead. Refer to https://importlib-resources.readthedocs.io/en/latest/using.html#migrating-from-legacy for migration advice.', 2, ('stacklevel',))

## co_names:
('warnings', 'warn', '__name__', 'DeprecationWarning')

## bytecode:

   0: COPY_FREE_VARS       
   2: RESUME               
   4: LOAD_GLOBAL          NULL + warnings
  16: LOAD_ATTR            warn
  26: LOAD_DEREF           func
  28: LOAD_ATTR            __name__
  38: FORMAT_VALUE         
  40: LOAD_CONST           ' is deprecated. Use files() instead. Refer to https://importlib-resources.readthedocs.io/en/latest/using.html#migrating-from-legacy for migration advice.'
  42: BUILD_STRING         
  44: LOAD_GLOBAL          DeprecationWarning
  56: LOAD_CONST           2
  58: KW_NAMES             
  60: PRECALL              
  64: CALL                 
  74: POP_TOP              
  76: PUSH_NULL            
  78: LOAD_DEREF           func
  80: LOAD_FAST            args
  82: BUILD_MAP            
  84: LOAD_FAST            kwargs
  86: DICT_MERGE           
  88: CALL_FUNCTION_EX     
  90: RETURN_VALUE         
