# Disassembly for importlib.resources.path
# From module file: importlib.resources._legacy

## co_consts:
('A context manager providing a file path object to the resource.\n\n    If the resource does not already exist on its own on the file system,\n    a temporary file will be created. If the file was created, the file\n    will be deleted upon exiting the context manager (no exception is\n    raised if the file was deleted prior to the context manager\n    exiting).\n    ',)

## co_names:
('_common', 'as_file', 'files', 'normalize_path')

## bytecode:

   0: RESUME               
   2: LOAD_GLOBAL          NULL + _common
  14: LOAD_ATTR            as_file
  24: LOAD_GLOBAL          NULL + _common
  36: LOAD_ATTR            files
  46: LOAD_FAST            package
  48: PRECALL              
  52: CALL                 
  62: LOAD_GLOBAL          NULL + normalize_path
  74: LOAD_FAST            resource
  76: PRECALL              
  80: CALL                 
  90: BINARY_OP            /
  94: PRECALL              
  98: CALL                 
 108: RETURN_VALUE         
