# Disassembly for importlib.resources.CompatibilityFiles.OrphanPath.joinpath
# From module file: importlib.resources._adapters

## co_consts:
(None,)

## co_names:
('CompatibilityFiles', 'OrphanPath', '_path')

## bytecode:

   0: RESUME               
   2: LOAD_GLOBAL          NULL + CompatibilityFiles
  14: LOAD_ATTR            OrphanPath
  24: BUILD_LIST           
  26: LOAD_FAST            self
  28: LOAD_ATTR            _path
  38: LIST_EXTEND          
  40: LOAD_FAST            other
  42: LIST_APPEND          
  44: LIST_TO_TUPLE        
  46: CALL_FUNCTION_EX     
  48: RETURN_VALUE         
