# Disassembly for importlib.resources.CompatibilityFiles.SpecPath.iterdir.<genexpr>
# From module file: importlib.resources._adapters

## co_consts:
(None,)

## co_names:
('CompatibilityFiles', 'ChildPath', '_reader')

## bytecode:

   0: COPY_FREE_VARS       
   2: RETURN_GENERATOR     
   4: POP_TOP              
   6: RESUME               
   8: LOAD_FAST            .0
  10: FOR_ITER             to 84
  12: STORE_FAST           path
  14: LOAD_GLOBAL          CompatibilityFiles
  26: LOAD_METHOD          ChildPath
  48: LOAD_DEREF           self
  50: LOAD_ATTR            _reader
  60: LOAD_FAST            path
  62: PRECALL              
  66: CALL                 
  76: YIELD_VALUE          
  78: RESUME               
  80: POP_TOP              
  82: JUMP_BACKWARD        to 10
  84: LOAD_CONST           None
  86: RETURN_VALUE         
