# Disassembly for importlib.resources.CompatibilityFiles.ChildPath
# From module file: importlib.resources._adapters

## co_consts:
('CompatibilityFiles.ChildPath', "\n        Path tied to a resource reader child.\n        Can be read but doesn't expose any meaningful children.\n        ", <code object __init__ at 0x0000024069465FB0, file "importlib\resources\_adapters.py", line 89>, <code object iterdir at 0x0000024069465D10, file "importlib\resources\_adapters.py", line 93>, <code object is_file at 0x00000240693EB930, file "importlib\resources\_adapters.py", line 96>, <code object is_dir at 0x000002406945F960, file "importlib\resources\_adapters.py", line 99>, <code object joinpath at 0x00000240693EB730, file "importlib\resources\_adapters.py", line 102>, <code object name at 0x0000024069496180, file "importlib\resources\_adapters.py", line 105>, 'r', <code object open at 0x000002406941B2D0, file "importlib\resources\_adapters.py", line 109>, None, ('r',))

## co_names:
('__name__', '__module__', '__qualname__', '__doc__', '__init__', 'iterdir', 'is_file', 'is_dir', 'joinpath', 'property', 'name', 'open')

## bytecode:

   0: RESUME               
   2: LOAD_NAME            __name__
   4: STORE_NAME           __module__
   6: LOAD_CONST           'CompatibilityFiles.ChildPath'
   8: STORE_NAME           __qualname__
  10: LOAD_CONST           "\n        Path tied to a resource reader child.\n        Can be read but doesn't expose any meaningful children.\n        "
  12: STORE_NAME           __doc__
  14: LOAD_CONST           <code object __init__ at 0x0000024069465FB0, file "importlib\resources\_adapters.py", line 89>
  16: MAKE_FUNCTION        
  18: STORE_NAME           __init__
  20: LOAD_CONST           <code object iterdir at 0x0000024069465D10, file "importlib\resources\_adapters.py", line 93>
  22: MAKE_FUNCTION        
  24: STORE_NAME           iterdir
  26: LOAD_CONST           <code object is_file at 0x00000240693EB930, file "importlib\resources\_adapters.py", line 96>
  28: MAKE_FUNCTION        
  30: STORE_NAME           is_file
  32: LOAD_CONST           <code object is_dir at 0x000002406945F960, file "importlib\resources\_adapters.py", line 99>
  34: MAKE_FUNCTION        
  36: STORE_NAME           is_dir
  38: LOAD_CONST           <code object joinpath at 0x00000240693EB730, file "importlib\resources\_adapters.py", line 102>
  40: MAKE_FUNCTION        
  42: STORE_NAME           joinpath
  44: LOAD_NAME            property
  46: LOAD_CONST           <code object name at 0x0000024069496180, file "importlib\resources\_adapters.py", line 105>
  48: MAKE_FUNCTION        
  50: PRECALL              
  54: CALL                 
  64: STORE_NAME           name
  66: LOAD_CONST           ('r',)
  68: LOAD_CONST           <code object open at 0x000002406941B2D0, file "importlib\resources\_adapters.py", line 109>
  70: MAKE_FUNCTION        defaults
  72: STORE_NAME           open
  74: LOAD_CONST           None
  76: RETURN_VALUE         
