# Disassembly for importlib.resources.TraversableResourcesLoader
# From module file: importlib.resources._adapters

## co_consts:
('TraversableResourcesLoader', '\n    Adapt a loader to provide TraversableResources.\n    ', <code object __init__ at 0x0000024069495B00, file "importlib\resources\_adapters.py", line 25>, <code object get_resource_reader at 0x000002406944A230, file "importlib\resources\_adapters.py", line 28>, None)

## co_names:
('__name__', '__module__', '__qualname__', '__doc__', '__init__', 'get_resource_reader')

## bytecode:

   0: RESUME               
   2: LOAD_NAME            __name__
   4: STORE_NAME           __module__
   6: LOAD_CONST           'TraversableResourcesLoader'
   8: STORE_NAME           __qualname__
  10: LOAD_CONST           '\n    Adapt a loader to provide TraversableResources.\n    '
  12: STORE_NAME           __doc__
  14: LOAD_CONST           <code object __init__ at 0x0000024069495B00, file "importlib\resources\_adapters.py", line 25>
  16: MAKE_FUNCTION        
  18: STORE_NAME           __init__
  20: LOAD_CONST           <code object get_resource_reader at 0x000002406944A230, file "importlib\resources\_adapters.py", line 28>
  22: MAKE_FUNCTION        
  24: STORE_NAME           get_resource_reader
  26: LOAD_CONST           None
  28: RETURN_VALUE         
