# Disassembly for importlib.resources.from_package
# From module file: importlib.resources._common

## co_consts:
('\n    Return a Traversable object for the given package.\n\n    ',)

## co_names:
('wrap_spec', 'loader', 'get_resource_reader', 'name', 'files')

## bytecode:

   0: RESUME               
   2: LOAD_GLOBAL          NULL + wrap_spec
  14: LOAD_FAST            package
  16: PRECALL              
  20: CALL                 
  30: STORE_FAST           spec
  32: LOAD_FAST            spec
  34: LOAD_ATTR            loader
  44: LOAD_METHOD          get_resource_reader
  66: LOAD_FAST            spec
  68: LOAD_ATTR            name
  78: PRECALL              
  82: CALL                 
  92: STORE_FAST           reader
  94: LOAD_FAST            reader
  96: LOAD_METHOD          files
 118: PRECALL              
 122: CALL                 
 132: RETURN_VALUE         
