# Disassembly for gzip.GzipFile.__init__
# From module file: gzip

## co_consts:
("Constructor for the GzipFile class.\n\n        At least one of fileobj and filename must be given a\n        non-trivial value.\n\n        The new class instance is based on fileobj, which can be a regular\n        file, an io.BytesIO object, or any other object which simulates a file.\n        It defaults to None, in which case filename is opened to provide\n        a file object.\n\n        When fileobj is not None, the filename argument is only used to be\n        included in the gzip file header, which may include the original\n        filename of the uncompressed file.  It defaults to the filename of\n        fileobj, if discernible; otherwise, it defaults to the empty string,\n        and in this case the original filename is not included in the header.\n\n        The mode argument can be any of 'r', 'rb', 'a', 'ab', 'w', 'wb', 'x', or\n        'xb' depending on whether the file will be read or written.  The default\n        is the mode of fileobj if discernible; otherwise, the default is 'rb'.\n        A mode of 'r' is equivalent to one of 'rb', and similarly for 'w' and\n        'wb', 'a' and 'ab', and 'x' and 'xb'.\n\n        The compresslevel argument is an integer from 0 to 9 controlling the\n        level of compression; 1 is fastest and produces the least compression,\n        and 9 is slowest and produces the most compression. 0 is no compression\n        at all. The default is 9.\n\n        The mtime argument is an optional numeric timestamp to be written\n        to the last modification time field in the stream when compressing.\n        If omitted or None, the current time is used.\n\n        ", 't', 'U', 'Invalid mode: {!r}', 'b', None, 'rb', 'name', '', 'mode', 'r', ('w', 'a', 'x'), 0, 'GzipFile was opened for writing, but this will change in future Python releases.  Specify the mode argument for opening it for writing.', 2)

## co_names:
('ValueError', 'format', 'builtins', 'open', 'myfileobj', 'getattr', 'isinstance', 'str', 'bytes', 'os', 'fspath', 'startswith', 'READ', 'mode', '_GzipReader', 'io', 'BufferedReader', '_buffer', 'name', 'warnings', 'warn', 'FutureWarning', 'WRITE', '_init_write', 'zlib', 'compressobj', 'DEFLATED', 'MAX_WBITS', 'DEF_MEM_LEVEL', 'compress', '_write_mtime', 'fileobj', '_write_gzip_header')

## bytecode:

   0: RESUME               
   2: LOAD_FAST            mode
   4: POP_JUMP_FORWARD_IF_FALSE to 90
   6: LOAD_CONST           't'
   8: LOAD_FAST            mode
  10: CONTAINS_OP          
  12: POP_JUMP_FORWARD_IF_TRUE to 22
  14: LOAD_CONST           'U'
  16: LOAD_FAST            mode
  18: CONTAINS_OP          
  20: POP_JUMP_FORWARD_IF_FALSE to 90
  22: LOAD_GLOBAL          NULL + ValueError
  34: LOAD_CONST           'Invalid mode: {!r}'
  36: LOAD_METHOD          format
  58: LOAD_FAST            mode
  60: PRECALL              
  64: CALL                 
  74: PRECALL              
  78: CALL                 
  88: RAISE_VARARGS        
  90: LOAD_FAST            mode
  92: POP_JUMP_FORWARD_IF_FALSE to 112
  94: LOAD_CONST           'b'
  96: LOAD_FAST            mode
  98: CONTAINS_OP          
 100: POP_JUMP_FORWARD_IF_FALSE to 112
 102: LOAD_FAST            mode
 104: LOAD_CONST           'b'
 106: BINARY_OP            +=
 110: STORE_FAST           mode
 112: LOAD_FAST            fileobj
 114: POP_JUMP_FORWARD_IF_NOT_NONE to 176
 116: LOAD_GLOBAL          NULL + builtins
 128: LOAD_ATTR            open
 138: LOAD_FAST            filename
 140: LOAD_FAST            mode
 142: JUMP_IF_TRUE_OR_POP  to 146
 144: LOAD_CONST           'rb'
 146: PRECALL              
 150: CALL                 
 160: COPY                 
 162: STORE_FAST           fileobj
 164: LOAD_FAST            self
 166: STORE_ATTR           myfileobj
 176: LOAD_FAST            filename
 178: POP_JUMP_FORWARD_IF_NOT_NONE to 276
 180: LOAD_GLOBAL          NULL + getattr
 192: LOAD_FAST            fileobj
 194: LOAD_CONST           'name'
 196: LOAD_CONST           ''
 198: PRECALL              
 202: CALL                 
 212: STORE_FAST           filename
 214: LOAD_GLOBAL          NULL + isinstance
 226: LOAD_FAST            filename
 228: LOAD_GLOBAL          str
 240: LOAD_GLOBAL          bytes
 252: BUILD_TUPLE          
 254: PRECALL              
 258: CALL                 
 268: POP_JUMP_FORWARD_IF_TRUE to 274
 270: LOAD_CONST           ''
 272: STORE_FAST           filename
 274: JUMP_FORWARD         to 316
 276: LOAD_GLOBAL          NULL + os
 288: LOAD_ATTR            fspath
 298: LOAD_FAST            filename
 300: PRECALL              
 304: CALL                 
 314: STORE_FAST           filename
 316: LOAD_FAST            mode
 318: STORE_FAST           origmode
 320: LOAD_FAST            mode
 322: POP_JUMP_FORWARD_IF_NOT_NONE to 358
 324: LOAD_GLOBAL          NULL + getattr
 336: LOAD_FAST            fileobj
 338: LOAD_CONST           'mode'
 340: LOAD_CONST           'rb'
 342: PRECALL              
 346: CALL                 
 356: STORE_FAST           mode
 358: LOAD_FAST            mode
 360: LOAD_METHOD          startswith
 382: LOAD_CONST           'r'
 384: PRECALL              
 388: CALL                 
 398: POP_JUMP_FORWARD_IF_FALSE to 520
 400: LOAD_GLOBAL          READ
 412: LOAD_FAST            self
 414: STORE_ATTR           mode
 424: LOAD_GLOBAL          NULL + _GzipReader
 436: LOAD_FAST            fileobj
 438: PRECALL              
 442: CALL                 
 452: STORE_FAST           raw
 454: LOAD_GLOBAL          NULL + io
 466: LOAD_ATTR            BufferedReader
 476: LOAD_FAST            raw
 478: PRECALL              
 482: CALL                 
 492: LOAD_FAST            self
 494: STORE_ATTR           _buffer
 504: LOAD_FAST            filename
 506: LOAD_FAST            self
 508: STORE_ATTR           name
 518: JUMP_FORWARD         to 900
 520: LOAD_FAST            mode
 522: LOAD_METHOD          startswith
 544: LOAD_CONST           ('w', 'a', 'x')
 546: PRECALL              
 550: CALL                 
 560: POP_JUMP_FORWARD_IF_FALSE to 832
 562: LOAD_FAST            origmode
 564: POP_JUMP_FORWARD_IF_NOT_NONE to 630
 566: LOAD_CONST           0
 568: LOAD_CONST           None
 570: IMPORT_NAME          warnings
 572: STORE_FAST           warnings
 574: LOAD_FAST            warnings
 576: LOAD_METHOD          warn
 598: LOAD_CONST           'GzipFile was opened for writing, but this will change in future Python releases.  Specify the mode argument for opening it for writing.'
 600: LOAD_GLOBAL          FutureWarning
 612: LOAD_CONST           2
 614: PRECALL              
 618: CALL                 
 628: POP_TOP              
 630: LOAD_GLOBAL          WRITE
 642: LOAD_FAST            self
 644: STORE_ATTR           mode
 654: LOAD_FAST            self
 656: LOAD_METHOD          _init_write
 678: LOAD_FAST            filename
 680: PRECALL              
 684: CALL                 
 694: POP_TOP              
 696: LOAD_GLOBAL          NULL + zlib
 708: LOAD_ATTR            compressobj
 718: LOAD_FAST            compresslevel
 720: LOAD_GLOBAL          zlib
 732: LOAD_ATTR            DEFLATED
 742: LOAD_GLOBAL          zlib
 754: LOAD_ATTR            MAX_WBITS
 764: UNARY_NEGATIVE       
 766: LOAD_GLOBAL          zlib
 778: LOAD_ATTR            DEF_MEM_LEVEL
 788: LOAD_CONST           0
 790: PRECALL              
 794: CALL                 
 804: LOAD_FAST            self
 806: STORE_ATTR           compress
 816: LOAD_FAST            mtime
 818: LOAD_FAST            self
 820: STORE_ATTR           _write_mtime
 830: JUMP_FORWARD         to 900
 832: LOAD_GLOBAL          NULL + ValueError
 844: LOAD_CONST           'Invalid mode: {!r}'
 846: LOAD_METHOD          format
 868: LOAD_FAST            mode
 870: PRECALL              
 874: CALL                 
 884: PRECALL              
 888: CALL                 
 898: RAISE_VARARGS        
 900: LOAD_FAST            fileobj
 902: LOAD_FAST            self
 904: STORE_ATTR           fileobj
 914: LOAD_FAST            self
 916: LOAD_ATTR            mode
 926: LOAD_GLOBAL          WRITE
 938: COMPARE_OP           ==
 944: POP_JUMP_FORWARD_IF_FALSE to 992
 946: LOAD_FAST            self
 948: LOAD_METHOD          _write_gzip_header
 970: LOAD_FAST            compresslevel
 972: PRECALL              
 976: CALL                 
 986: POP_TOP              
 988: LOAD_CONST           None
 990: RETURN_VALUE         
 992: LOAD_CONST           None
 994: RETURN_VALUE         
