# Disassembly for gzip.BadGzipFile
# From module file: gzip

## co_consts:
('BadGzipFile', 'Exception raised in some cases for invalid gzip files.', None)

## co_names:
('__name__', '__module__', '__qualname__', '__doc__')

## bytecode:

   0: RESUME               
   2: LOAD_NAME            __name__
   4: STORE_NAME           __module__
   6: LOAD_CONST           'BadGzipFile'
   8: STORE_NAME           __qualname__
  10: LOAD_CONST           'Exception raised in some cases for invalid gzip files.'
  12: STORE_NAME           __doc__
  14: LOAD_CONST           None
  16: RETURN_VALUE         
