# Disassembly for gzip._PaddedFile.prepend
# From module file: gzip

## co_consts:
(None, 0)

## co_names:
('_read', '_buffer', 'len', '_length')

## bytecode:

   0: RESUME               
   2: LOAD_FAST            self
   4: LOAD_ATTR            _read
  14: POP_JUMP_FORWARD_IF_NOT_NONE to 32
  16: LOAD_FAST            prepend
  18: LOAD_FAST            self
  20: STORE_ATTR           _buffer
  30: JUMP_FORWARD         to 94
  32: LOAD_FAST            self
  34: COPY                 
  36: LOAD_ATTR            _read
  46: LOAD_GLOBAL          NULL + len
  58: LOAD_FAST            prepend
  60: PRECALL              
  64: CALL                 
  74: BINARY_OP            -=
  78: SWAP                 
  80: STORE_ATTR           _read
  90: LOAD_CONST           None
  92: RETURN_VALUE         
  94: LOAD_GLOBAL          NULL + len
 106: LOAD_FAST            self
 108: LOAD_ATTR            _buffer
 118: PRECALL              
 122: CALL                 
 132: LOAD_FAST            self
 134: STORE_ATTR           _length
 144: LOAD_CONST           0
 146: LOAD_FAST            self
 148: STORE_ATTR           _read
 158: LOAD_CONST           None
 160: RETURN_VALUE         
