# Disassembly for gzip.write32u
# From module file: gzip

## co_consts:
(None, '<L')

## co_names:
('write', 'struct', 'pack')

## bytecode:

   0: RESUME               
   2: LOAD_FAST            output
   4: LOAD_METHOD          write
  26: LOAD_GLOBAL          NULL + struct
  38: LOAD_ATTR            pack
  48: LOAD_CONST           '<L'
  50: LOAD_FAST            value
  52: PRECALL              
  56: CALL                 
  66: PRECALL              
  70: CALL                 
  80: POP_TOP              
  82: LOAD_CONST           None
  84: RETURN_VALUE         
