# Disassembly for gzip.GzipFile.__repr__
# From module file: gzip

## co_consts:
(None, '<gzip ', 1, -1, ' ', '>')

## co_names:
('repr', 'fileobj', 'hex', 'id')

## bytecode:

   0: RESUME               
   2: LOAD_GLOBAL          NULL + repr
  14: LOAD_FAST            self
  16: LOAD_ATTR            fileobj
  26: PRECALL              
  30: CALL                 
  40: STORE_FAST           s
  42: LOAD_CONST           '<gzip '
  44: LOAD_FAST            s
  46: LOAD_CONST           1
  48: LOAD_CONST           -1
  50: BUILD_SLICE          
  52: BINARY_SUBSCR        
  62: BINARY_OP            +
  66: LOAD_CONST           ' '
  68: BINARY_OP            +
  72: LOAD_GLOBAL          NULL + hex
  84: LOAD_GLOBAL          NULL + id
  96: LOAD_FAST            self
  98: PRECALL              
 102: CALL                 
 112: PRECALL              
 116: CALL                 
 126: BINARY_OP            +
 130: LOAD_CONST           '>'
 132: BINARY_OP            +
 136: RETURN_VALUE         
