# Disassembly for gzip.GzipFile.readline
# From module file: gzip

## co_consts:
(None,)

## co_names:
('_check_not_closed', '_buffer', 'readline')

## bytecode:

   0: RESUME               
   2: LOAD_FAST            self
   4: LOAD_METHOD          _check_not_closed
  26: PRECALL              
  30: CALL                 
  40: POP_TOP              
  42: LOAD_FAST            self
  44: LOAD_ATTR            _buffer
  54: LOAD_METHOD          readline
  76: LOAD_FAST            size
  78: PRECALL              
  82: CALL                 
  92: RETURN_VALUE         
