# Disassembly for gzip.GzipFile.rewind
# From module file: gzip

## co_consts:
('Return the uncompressed stream file position indicator to the\n        beginning of the file', "Can't rewind in write mode", 0, None)

## co_names:
('mode', 'READ', 'OSError', '_buffer', 'seek')

## bytecode:

   0: RESUME               
   2: LOAD_FAST            self
   4: LOAD_ATTR            mode
  14: LOAD_GLOBAL          READ
  26: COMPARE_OP           !=
  32: POP_JUMP_FORWARD_IF_FALSE to 64
  34: LOAD_GLOBAL          NULL + OSError
  46: LOAD_CONST           "Can't rewind in write mode"
  48: PRECALL              
  52: CALL                 
  62: RAISE_VARARGS        
  64: LOAD_FAST            self
  66: LOAD_ATTR            _buffer
  76: LOAD_METHOD          seek
  98: LOAD_CONST           0
 100: PRECALL              
 104: CALL                 
 114: POP_TOP              
 116: LOAD_CONST           None
 118: RETURN_VALUE         
