# Disassembly for gzip.open
# From module file: gzip

## co_consts:
('Open a gzip-compressed file in binary or text mode.\n\n    The filename argument can be an actual filename (a str or bytes object), or\n    an existing file object to read from or write to.\n\n    The mode argument can be "r", "rb", "w", "wb", "x", "xb", "a" or "ab" for\n    binary mode, or "rt", "wt", "xt" or "at" for text mode. The default mode is\n    "rb", and the default compresslevel is 9.\n\n    For binary mode, this function is equivalent to the GzipFile constructor:\n    GzipFile(filename, mode, compresslevel). In this case, the encoding, errors\n    and newline arguments must not be provided.\n\n    For text mode, a GzipFile object is created, and wrapped in an\n    io.TextIOWrapper instance with the specified encoding, error handling\n    behavior, and line ending(s).\n\n    ', 't', 'b', 'Invalid mode: ', None, "Argument 'encoding' not supported in binary mode", "Argument 'errors' not supported in binary mode", "Argument 'newline' not supported in binary mode", '', 'read', 'write', 'filename must be a str or bytes object, or a file')

## co_names:
('ValueError', 'replace', 'isinstance', 'str', 'bytes', 'os', 'PathLike', 'GzipFile', 'hasattr', 'TypeError', 'io', 'text_encoding', 'TextIOWrapper')

## bytecode:

   0: RESUME               
   2: LOAD_CONST           't'
   4: LOAD_FAST            mode
   6: CONTAINS_OP          
   8: POP_JUMP_FORWARD_IF_FALSE to 56
  10: LOAD_CONST           'b'
  12: LOAD_FAST            mode
  14: CONTAINS_OP          
  16: POP_JUMP_FORWARD_IF_FALSE to 54
  18: LOAD_GLOBAL          NULL + ValueError
  30: LOAD_CONST           'Invalid mode: '
  32: LOAD_FAST            mode
  34: FORMAT_VALUE         repr
  36: BUILD_STRING         
  38: PRECALL              
  42: CALL                 
  52: RAISE_VARARGS        
  54: JUMP_FORWARD         to 158
  56: LOAD_FAST            encoding
  58: POP_JUMP_FORWARD_IF_NONE to 90
  60: LOAD_GLOBAL          NULL + ValueError
  72: LOAD_CONST           "Argument 'encoding' not supported in binary mode"
  74: PRECALL              
  78: CALL                 
  88: RAISE_VARARGS        
  90: LOAD_FAST            errors
  92: POP_JUMP_FORWARD_IF_NONE to 124
  94: LOAD_GLOBAL          NULL + ValueError
 106: LOAD_CONST           "Argument 'errors' not supported in binary mode"
 108: PRECALL              
 112: CALL                 
 122: RAISE_VARARGS        
 124: LOAD_FAST            newline
 126: POP_JUMP_FORWARD_IF_NONE to 158
 128: LOAD_GLOBAL          NULL + ValueError
 140: LOAD_CONST           "Argument 'newline' not supported in binary mode"
 142: PRECALL              
 146: CALL                 
 156: RAISE_VARARGS        
 158: LOAD_FAST            mode
 160: LOAD_METHOD          replace
 182: LOAD_CONST           't'
 184: LOAD_CONST           ''
 186: PRECALL              
 190: CALL                 
 200: STORE_FAST           gz_mode
 202: LOAD_GLOBAL          NULL + isinstance
 214: LOAD_FAST            filename
 216: LOAD_GLOBAL          str
 228: LOAD_GLOBAL          bytes
 240: LOAD_GLOBAL          os
 252: LOAD_ATTR            PathLike
 262: BUILD_TUPLE          
 264: PRECALL              
 268: CALL                 
 278: POP_JUMP_FORWARD_IF_FALSE to 316
 280: LOAD_GLOBAL          NULL + GzipFile
 292: LOAD_FAST            filename
 294: LOAD_FAST            gz_mode
 296: LOAD_FAST            compresslevel
 298: PRECALL              
 302: CALL                 
 312: STORE_FAST           binary_file
 314: JUMP_FORWARD         to 448
 316: LOAD_GLOBAL          NULL + hasattr
 328: LOAD_FAST            filename
 330: LOAD_CONST           'read'
 332: PRECALL              
 336: CALL                 
 346: POP_JUMP_FORWARD_IF_TRUE to 380
 348: LOAD_GLOBAL          NULL + hasattr
 360: LOAD_FAST            filename
 362: LOAD_CONST           'write'
 364: PRECALL              
 368: CALL                 
 378: POP_JUMP_FORWARD_IF_FALSE to 418
 380: LOAD_GLOBAL          NULL + GzipFile
 392: LOAD_CONST           None
 394: LOAD_FAST            gz_mode
 396: LOAD_FAST            compresslevel
 398: LOAD_FAST            filename
 400: PRECALL              
 404: CALL                 
 414: STORE_FAST           binary_file
 416: JUMP_FORWARD         to 448
 418: LOAD_GLOBAL          NULL + TypeError
 430: LOAD_CONST           'filename must be a str or bytes object, or a file'
 432: PRECALL              
 436: CALL                 
 446: RAISE_VARARGS        
 448: LOAD_CONST           't'
 450: LOAD_FAST            mode
 452: CONTAINS_OP          
 454: POP_JUMP_FORWARD_IF_FALSE to 542
 456: LOAD_GLOBAL          NULL + io
 468: LOAD_ATTR            text_encoding
 478: LOAD_FAST            encoding
 480: PRECALL              
 484: CALL                 
 494: STORE_FAST           encoding
 496: LOAD_GLOBAL          NULL + io
 508: LOAD_ATTR            TextIOWrapper
 518: LOAD_FAST            binary_file
 520: LOAD_FAST            encoding
 522: LOAD_FAST            errors
 524: LOAD_FAST            newline
 526: PRECALL              
 530: CALL                 
 540: RETURN_VALUE         
 542: LOAD_FAST            binary_file
 544: RETURN_VALUE         
