# Disassembly for gzip.main
# From module file: gzip

## co_consts:
(None, 0, ('ArgumentParser',), 'A simple command line interface for the gzip module: act like gzip, but do not delete the input file.', ('description',), '--fast', 'store_true', 'compress faster', ('action', 'help'), '--best', 'compress better', '-d', '--decompress', 'act like gunzip instead of gzip', 'args', '*', '-', 'file', ('nargs', 'default', 'metavar'), '', 'rb', ('filename', 'mode', 'fileobj'), -3, '.gz', "filename doesn't end in .gz: ", 'wb', ('filename', 'mode', 'fileobj', 'compresslevel'))

## co_names:
('argparse', 'ArgumentParser', 'add_mutually_exclusive_group', 'add_argument', 'parse_args', '_COMPRESS_LEVEL_TRADEOFF', 'fast', '_COMPRESS_LEVEL_FAST', 'best', '_COMPRESS_LEVEL_BEST', 'args', 'decompress', 'GzipFile', 'sys', 'stdin', 'buffer', 'stdout', 'exit', 'open', 'builtins', 'read', 'io', 'DEFAULT_BUFFER_SIZE', 'write', 'close')

## bytecode:

   0: RESUME               
   2: LOAD_CONST           0
   4: LOAD_CONST           ('ArgumentParser',)
   6: IMPORT_NAME          argparse
   8: IMPORT_FROM          ArgumentParser
  10: STORE_FAST           ArgumentParser
  12: POP_TOP              
  14: PUSH_NULL            
  16: LOAD_FAST            ArgumentParser
  18: LOAD_CONST           'A simple command line interface for the gzip module: act like gzip, but do not delete the input file.'
  20: KW_NAMES             
  22: PRECALL              
  26: CALL                 
  36: STORE_FAST           parser
  38: LOAD_FAST            parser
  40: LOAD_METHOD          add_mutually_exclusive_group
  62: PRECALL              
  66: CALL                 
  76: STORE_FAST           group
  78: LOAD_FAST            group
  80: LOAD_METHOD          add_argument
 102: LOAD_CONST           '--fast'
 104: LOAD_CONST           'store_true'
 106: LOAD_CONST           'compress faster'
 108: KW_NAMES             
 110: PRECALL              
 114: CALL                 
 124: POP_TOP              
 126: LOAD_FAST            group
 128: LOAD_METHOD          add_argument
 150: LOAD_CONST           '--best'
 152: LOAD_CONST           'store_true'
 154: LOAD_CONST           'compress better'
 156: KW_NAMES             
 158: PRECALL              
 162: CALL                 
 172: POP_TOP              
 174: LOAD_FAST            group
 176: LOAD_METHOD          add_argument
 198: LOAD_CONST           '-d'
 200: LOAD_CONST           '--decompress'
 202: LOAD_CONST           'store_true'
 204: LOAD_CONST           'act like gunzip instead of gzip'
 206: KW_NAMES             
 208: PRECALL              
 212: CALL                 
 222: POP_TOP              
 224: LOAD_FAST            parser
 226: LOAD_METHOD          add_argument
 248: LOAD_CONST           'args'
 250: LOAD_CONST           '*'
 252: LOAD_CONST           '-'
 254: BUILD_LIST           
 256: LOAD_CONST           'file'
 258: KW_NAMES             
 260: PRECALL              
 264: CALL                 
 274: POP_TOP              
 276: LOAD_FAST            parser
 278: LOAD_METHOD          parse_args
 300: PRECALL              
 304: CALL                 
 314: STORE_FAST           args
 316: LOAD_GLOBAL          _COMPRESS_LEVEL_TRADEOFF
 328: STORE_FAST           compresslevel
 330: LOAD_FAST            args
 332: LOAD_ATTR            fast
 342: POP_JUMP_FORWARD_IF_FALSE to 360
 344: LOAD_GLOBAL          _COMPRESS_LEVEL_FAST
 356: STORE_FAST           compresslevel
 358: JUMP_FORWARD         to 388
 360: LOAD_FAST            args
 362: LOAD_ATTR            best
 372: POP_JUMP_FORWARD_IF_FALSE to 388
 374: LOAD_GLOBAL          _COMPRESS_LEVEL_BEST
 386: STORE_FAST           compresslevel
 388: LOAD_FAST            args
 390: LOAD_ATTR            args
 400: GET_ITER             
 402: EXTENDED_ARG         
 404: FOR_ITER             to 1172
 406: STORE_FAST           arg
 408: LOAD_FAST            args
 410: LOAD_ATTR            decompress
 420: POP_JUMP_FORWARD_IF_FALSE to 702
 422: LOAD_FAST            arg
 424: LOAD_CONST           '-'
 426: COMPARE_OP           ==
 432: POP_JUMP_FORWARD_IF_FALSE to 536
 434: LOAD_GLOBAL          NULL + GzipFile
 446: LOAD_CONST           ''
 448: LOAD_CONST           'rb'
 450: LOAD_GLOBAL          sys
 462: LOAD_ATTR            stdin
 472: LOAD_ATTR            buffer
 482: KW_NAMES             
 484: PRECALL              
 488: CALL                 
 498: STORE_FAST           f
 500: LOAD_GLOBAL          sys
 512: LOAD_ATTR            stdout
 522: LOAD_ATTR            buffer
 532: STORE_FAST           g
 534: JUMP_FORWARD         to 898
 536: LOAD_FAST            arg
 538: LOAD_CONST           -3
 540: LOAD_CONST           None
 542: BUILD_SLICE          
 544: BINARY_SUBSCR        
 554: LOAD_CONST           '.gz'
 556: COMPARE_OP           !=
 562: POP_JUMP_FORWARD_IF_FALSE to 610
 564: LOAD_GLOBAL          NULL + sys
 576: LOAD_ATTR            exit
 586: LOAD_CONST           "filename doesn't end in .gz: "
 588: LOAD_FAST            arg
 590: FORMAT_VALUE         repr
 592: BUILD_STRING         
 594: PRECALL              
 598: CALL                 
 608: POP_TOP              
 610: LOAD_GLOBAL          NULL + open
 622: LOAD_FAST            arg
 624: LOAD_CONST           'rb'
 626: PRECALL              
 630: CALL                 
 640: STORE_FAST           f
 642: LOAD_GLOBAL          NULL + builtins
 654: LOAD_ATTR            open
 664: LOAD_FAST            arg
 666: LOAD_CONST           None
 668: LOAD_CONST           -3
 670: BUILD_SLICE          
 672: BINARY_SUBSCR        
 682: LOAD_CONST           'wb'
 684: PRECALL              
 688: CALL                 
 698: STORE_FAST           g
 700: JUMP_FORWARD         to 898
 702: LOAD_FAST            arg
 704: LOAD_CONST           '-'
 706: COMPARE_OP           ==
 712: POP_JUMP_FORWARD_IF_FALSE to 818
 714: LOAD_GLOBAL          sys
 726: LOAD_ATTR            stdin
 736: LOAD_ATTR            buffer
 746: STORE_FAST           f
 748: LOAD_GLOBAL          NULL + GzipFile
 760: LOAD_CONST           ''
 762: LOAD_CONST           'wb'
 764: LOAD_GLOBAL          sys
 776: LOAD_ATTR            stdout
 786: LOAD_ATTR            buffer
 796: LOAD_FAST            compresslevel
 798: KW_NAMES             
 800: PRECALL              
 804: CALL                 
 814: STORE_FAST           g
 816: JUMP_FORWARD         to 898
 818: LOAD_GLOBAL          NULL + builtins
 830: LOAD_ATTR            open
 840: LOAD_FAST            arg
 842: LOAD_CONST           'rb'
 844: PRECALL              
 848: CALL                 
 858: STORE_FAST           f
 860: LOAD_GLOBAL          NULL + open
 872: LOAD_FAST            arg
 874: LOAD_CONST           '.gz'
 876: BINARY_OP            +
 880: LOAD_CONST           'wb'
 882: PRECALL              
 886: CALL                 
 896: STORE_FAST           g
 898: NOP                  
 900: LOAD_FAST            f
 902: LOAD_METHOD          read
 924: LOAD_GLOBAL          io
 936: LOAD_ATTR            DEFAULT_BUFFER_SIZE
 946: PRECALL              
 950: CALL                 
 960: STORE_FAST           chunk
 962: LOAD_FAST            chunk
 964: POP_JUMP_FORWARD_IF_TRUE to 968
 966: JUMP_FORWARD         to 1012
 968: LOAD_FAST            g
 970: LOAD_METHOD          write
 992: LOAD_FAST            chunk
 994: PRECALL              
 998: CALL                 
1008: POP_TOP              
1010: JUMP_BACKWARD        to 900
1012: LOAD_FAST            g
1014: LOAD_GLOBAL          sys
1026: LOAD_ATTR            stdout
1036: LOAD_ATTR            buffer
1046: IS_OP                
1048: POP_JUMP_FORWARD_IF_FALSE to 1090
1050: LOAD_FAST            g
1052: LOAD_METHOD          close
1074: PRECALL              
1078: CALL                 
1088: POP_TOP              
1090: LOAD_FAST            f
1092: LOAD_GLOBAL          sys
1104: LOAD_ATTR            stdin
1114: LOAD_ATTR            buffer
1124: IS_OP                
1126: POP_JUMP_FORWARD_IF_FALSE to 1168
1128: LOAD_FAST            f
1130: LOAD_METHOD          close
1152: PRECALL              
1156: CALL                 
1166: POP_TOP              
1168: EXTENDED_ARG         
1170: JUMP_BACKWARD        to 402
1172: LOAD_CONST           None
1174: RETURN_VALUE         
