# Disassembly for giftshop.GiftShop.__init__
# From module file: giftshop

## co_consts:
(None, False)

## co_names:
('super', '__init__', 'book_taken', 'CashRegister', 'set_parent')

## bytecode:

   0: COPY_FREE_VARS       
   2: RESUME               
   4: LOAD_GLOBAL          NULL + super
  16: PRECALL              
  20: CALL                 
  30: LOAD_METHOD          __init__
  52: LOAD_FAST            name
  54: PRECALL              
  58: CALL                 
  68: POP_TOP              
  70: LOAD_CONST           False
  72: LOAD_FAST            self
  74: STORE_ATTR           book_taken
  84: LOAD_GLOBAL          NULL + CashRegister
  96: PRECALL              
 100: CALL                 
 110: LOAD_METHOD          set_parent
 132: LOAD_FAST            self
 134: PRECALL              
 138: CALL                 
 148: POP_TOP              
 150: LOAD_CONST           None
 152: RETURN_VALUE         
