# Disassembly for giftshop.GiftShop.get_description
# From module file: giftshop

## co_consts:
(None, '$div', 'You\'re in a room with a bunch of shelves that are mostly empty.\nThe shelves do have a couple broken bobble-head dolls, some plush\nhammers and wrenches with stuffing coming out, and a stack of books\nlabeled "$world and Interesting History".\nThis must be a $room.', 'You are in the $room.  You see some broken merch and a stack of books labeled "$world and Interesting History".', 'Player', 0, '\n', '\nThere is a door to the right back to the Lobby.')

## co_names:
('first_look', 'children', 'get_visible', 'is_a', 'get_description', 'len')

## bytecode:

   0: RESUME               
   2: LOAD_CONST           '$div'
   4: STORE_FAST           desc
   6: LOAD_FAST            self
   8: LOAD_ATTR            first_look
  18: POP_JUMP_FORWARD_IF_FALSE to 32
  20: LOAD_FAST            desc
  22: LOAD_CONST           'You\'re in a room with a bunch of shelves that are mostly empty.\nThe shelves do have a couple broken bobble-head dolls, some plush\nhammers and wrenches with stuffing coming out, and a stack of books\nlabeled "$world and Interesting History".\nThis must be a $room.'
  24: BINARY_OP            +=
  28: STORE_FAST           desc
  30: JUMP_FORWARD         to 42
  32: LOAD_FAST            desc
  34: LOAD_CONST           'You are in the $room.  You see some broken merch and a stack of books labeled "$world and Interesting History".'
  36: BINARY_OP            +=
  40: STORE_FAST           desc
  42: LOAD_FAST            self
  44: LOAD_ATTR            children
  54: GET_ITER             
  56: FOR_ITER             to 238
  58: STORE_FAST           child
  60: LOAD_FAST            child
  62: LOAD_METHOD          get_visible
  84: PRECALL              
  88: CALL                 
  98: POP_JUMP_FORWARD_IF_FALSE to 236
 100: LOAD_FAST            child
 102: LOAD_METHOD          is_a
 124: LOAD_CONST           'Player'
 126: PRECALL              
 130: CALL                 
 140: POP_JUMP_FORWARD_IF_TRUE to 236
 142: LOAD_FAST            child
 144: LOAD_METHOD          get_description
 166: PRECALL              
 170: CALL                 
 180: STORE_FAST           child_desc
 182: LOAD_GLOBAL          NULL + len
 194: LOAD_FAST            child_desc
 196: PRECALL              
 200: CALL                 
 210: LOAD_CONST           0
 212: COMPARE_OP           >
 218: POP_JUMP_FORWARD_IF_FALSE to 236
 220: LOAD_FAST            desc
 222: LOAD_CONST           '\n'
 224: LOAD_FAST            child_desc
 226: BINARY_OP            +
 230: BINARY_OP            +=
 234: STORE_FAST           desc
 236: JUMP_BACKWARD        to 56
 238: LOAD_FAST            desc
 240: LOAD_CONST           '\nThere is a door to the right back to the Lobby.'
 242: BINARY_OP            +=
 246: STORE_FAST           desc
 248: LOAD_FAST            desc
 250: RETURN_VALUE         
