# Disassembly for giftshop.CashRegister.get_options
# From module file: giftshop

## co_consts:
(None, <code object <lambda> at 0x000002406945D4D0, file "giftshop.py", line 104>, 'Open the cash register.', <code object <lambda> at 0x000002406945FC30, file "giftshop.py", line 106>, 'Take dollar from cash register.')

## co_names:
('is_open', 'append', 'money_taken')

## bytecode:

   0: MAKE_CELL            self
   2: RESUME               
   4: BUILD_LIST           
   6: STORE_FAST           options
   8: LOAD_DEREF           self
  10: LOAD_ATTR            is_open
  20: POP_JUMP_FORWARD_IF_TRUE to 76
  22: LOAD_FAST            options
  24: LOAD_METHOD          append
  46: LOAD_CLOSURE         self
  48: BUILD_TUPLE          
  50: LOAD_CONST           <code object <lambda> at 0x000002406945D4D0, file "giftshop.py", line 104>
  52: MAKE_FUNCTION        closure
  54: LOAD_CONST           'Open the cash register.'
  56: BUILD_TUPLE          
  58: PRECALL              
  62: CALL                 
  72: POP_TOP              
  74: JUMP_FORWARD         to 142
  76: LOAD_DEREF           self
  78: LOAD_ATTR            money_taken
  88: POP_JUMP_FORWARD_IF_TRUE to 142
  90: LOAD_FAST            options
  92: LOAD_METHOD          append
 114: LOAD_CLOSURE         self
 116: BUILD_TUPLE          
 118: LOAD_CONST           <code object <lambda> at 0x000002406945FC30, file "giftshop.py", line 106>
 120: MAKE_FUNCTION        closure
 122: LOAD_CONST           'Take dollar from cash register.'
 124: BUILD_TUPLE          
 126: PRECALL              
 130: CALL                 
 140: POP_TOP              
 142: LOAD_FAST            options
 144: RETURN_VALUE         
