# Disassembly for giftshop.GiftShop.handle_option_answer
# From module file: giftshop

## co_consts:
(None, 'R', 'You head through the right door.', 'Lobby', 'H', True, 'You take one of the history books.')

## co_names:
('send_message', 'world', 'player', 'set_parent', 'rooms', 'book_taken', 'HistoryBook')

## bytecode:

   0: RESUME               
   2: LOAD_FAST            value
   4: COPY                 
   6: LOAD_CONST           'R'
   8: COMPARE_OP           ==
  14: POP_JUMP_FORWARD_IF_FALSE to 158
  16: POP_TOP              
  18: LOAD_FAST            self
  20: LOAD_METHOD          send_message
  42: LOAD_CONST           'You head through the right door.'
  44: PRECALL              
  48: CALL                 
  58: POP_TOP              
  60: LOAD_FAST            self
  62: LOAD_ATTR            world
  72: LOAD_ATTR            player
  82: LOAD_METHOD          set_parent
 104: LOAD_FAST            self
 106: LOAD_ATTR            world
 116: LOAD_ATTR            rooms
 126: LOAD_CONST           'Lobby'
 128: BINARY_SUBSCR        
 138: PRECALL              
 142: CALL                 
 152: POP_TOP              
 154: LOAD_CONST           None
 156: RETURN_VALUE         
 158: LOAD_CONST           'H'
 160: COMPARE_OP           ==
 166: POP_JUMP_FORWARD_IF_FALSE to 314
 168: LOAD_CONST           True
 170: LOAD_FAST            self
 172: STORE_ATTR           book_taken
 182: LOAD_FAST            self
 184: LOAD_METHOD          send_message
 206: LOAD_CONST           'You take one of the history books.'
 208: PRECALL              
 212: CALL                 
 222: POP_TOP              
 224: LOAD_GLOBAL          NULL + HistoryBook
 236: PRECALL              
 240: CALL                 
 250: LOAD_METHOD          set_parent
 272: LOAD_FAST            self
 274: LOAD_ATTR            world
 284: LOAD_ATTR            player
 294: PRECALL              
 298: CALL                 
 308: POP_TOP              
 310: LOAD_CONST           None
 312: RETURN_VALUE         
 314: LOAD_CONST           None
 316: RETURN_VALUE         
