# Disassembly for giftshop.CashRegister.get_description
# From module file: giftshop

## co_consts:
(None, 'There is a cash register in the corner.', 'There is a cash register in the corner with a dollar in it.', 'There is an empty cash register in the corner.')

## co_names:
('is_open', 'money_taken')

## bytecode:

   0: RESUME               
   2: LOAD_FAST            self
   4: LOAD_ATTR            is_open
  14: POP_JUMP_FORWARD_IF_TRUE to 20
  16: LOAD_CONST           'There is a cash register in the corner.'
  18: RETURN_VALUE         
  20: LOAD_FAST            self
  22: LOAD_ATTR            money_taken
  32: POP_JUMP_FORWARD_IF_TRUE to 38
  34: LOAD_CONST           'There is a cash register in the corner with a dollar in it.'
  36: RETURN_VALUE         
  38: LOAD_CONST           'There is an empty cash register in the corner.'
  40: RETURN_VALUE         
