# Disassembly for giftshop.CashRegister.open
# From module file: giftshop

## co_consts:
(None, True, 'You press a button and open the cash register.  There is a dollar in it.')

## co_names:
('is_open', 'world', 'player', 'send_message')

## bytecode:

   0: RESUME               
   2: LOAD_CONST           True
   4: LOAD_FAST            self
   6: STORE_ATTR           is_open
  16: LOAD_FAST            self
  18: LOAD_ATTR            world
  28: LOAD_ATTR            player
  38: LOAD_METHOD          send_message
  60: LOAD_CONST           'You press a button and open the cash register.  There is a dollar in it.'
  62: PRECALL              
  66: CALL                 
  76: POP_TOP              
  78: LOAD_CONST           None
  80: RETURN_VALUE         
