# Disassembly for breakroom.Photo.get_description
# From module file: breakroom

## co_consts:
(None, "It's a photo of a man and woman.  Their faces are blurry and you can't quite\nmake out who they are.", "It's a picture of your parents.  On the back it says:\n --- Remember")

## co_names:
('blurred',)

## bytecode:

   0: RESUME               
   2: LOAD_FAST            self
   4: LOAD_ATTR            blurred
  14: POP_JUMP_FORWARD_IF_FALSE to 22
  16: NOP                  
  18: LOAD_CONST           "It's a photo of a man and woman.  Their faces are blurry and you can't quite\nmake out who they are."
  20: RETURN_VALUE         
  22: NOP                  
  24: LOAD_CONST           "It's a picture of your parents.  On the back it says:\n --- Remember"
  26: RETURN_VALUE         
