# Disassembly for breakroom.Jacket.get_options
# From module file: breakroom

## co_consts:
(None, <code object <lambda> at 0x000002406945DF20, file "breakroom.py", line 154>, 'Take the jacket off.', <code object <lambda> at 0x000002406945E010, file "breakroom.py", line 156>, 'Check the jacket pocket.', <code object <lambda> at 0x000002406945E100, file "breakroom.py", line 158>, 'Put the jacket on.')

## co_names:
('on', 'append', 'world', 'player', 'get_child_by_type', 'Photo')

## bytecode:

   0: MAKE_CELL            self
   2: RESUME               
   4: BUILD_LIST           
   6: STORE_FAST           options
   8: LOAD_DEREF           self
  10: LOAD_ATTR            on
  20: POP_JUMP_FORWARD_IF_FALSE to 200
  22: LOAD_FAST            options
  24: LOAD_METHOD          append
  46: LOAD_CLOSURE         self
  48: BUILD_TUPLE          
  50: LOAD_CONST           <code object <lambda> at 0x000002406945DF20, file "breakroom.py", line 154>
  52: MAKE_FUNCTION        closure
  54: LOAD_CONST           'Take the jacket off.'
  56: BUILD_TUPLE          
  58: PRECALL              
  62: CALL                 
  72: POP_TOP              
  74: LOAD_DEREF           self
  76: LOAD_ATTR            world
  86: LOAD_ATTR            player
  96: LOAD_METHOD          get_child_by_type
 118: LOAD_GLOBAL          Photo
 130: PRECALL              
 134: CALL                 
 144: POP_JUMP_FORWARD_IF_NOT_NONE to 198
 146: LOAD_FAST            options
 148: LOAD_METHOD          append
 170: LOAD_CLOSURE         self
 172: BUILD_TUPLE          
 174: LOAD_CONST           <code object <lambda> at 0x000002406945E010, file "breakroom.py", line 156>
 176: MAKE_FUNCTION        closure
 178: LOAD_CONST           'Check the jacket pocket.'
 180: BUILD_TUPLE          
 182: PRECALL              
 186: CALL                 
 196: POP_TOP              
 198: JUMP_FORWARD         to 252
 200: LOAD_FAST            options
 202: LOAD_METHOD          append
 224: LOAD_CLOSURE         self
 226: BUILD_TUPLE          
 228: LOAD_CONST           <code object <lambda> at 0x000002406945E100, file "breakroom.py", line 158>
 230: MAKE_FUNCTION        closure
 232: LOAD_CONST           'Put the jacket on.'
 234: BUILD_TUPLE          
 236: PRECALL              
 240: CALL                 
 250: POP_TOP              
 252: LOAD_FAST            options
 254: RETURN_VALUE         
