# Disassembly for breakroom.Jacket.put_on
# From module file: breakroom

## co_consts:
(None, "You put the jacket on.  It's nice and warm.", '\nThe jacket has a pocket on the side.', True)

## co_names:
('world', 'player', 'get_child_by_type', 'Photo', 'on', 'send_message')

## bytecode:

   0: RESUME               
   2: LOAD_CONST           "You put the jacket on.  It's nice and warm."
   4: STORE_FAST           message
   6: LOAD_FAST            self
   8: LOAD_ATTR            world
  18: LOAD_ATTR            player
  28: LOAD_METHOD          get_child_by_type
  50: LOAD_GLOBAL          Photo
  62: PRECALL              
  66: CALL                 
  76: POP_JUMP_FORWARD_IF_NOT_NONE to 82
  78: LOAD_CONST           '\nThe jacket has a pocket on the side.'
  80: STORE_FAST           message
  82: LOAD_CONST           True
  84: LOAD_FAST            self
  86: STORE_ATTR           on
  96: LOAD_FAST            self
  98: LOAD_METHOD          send_message
 120: LOAD_FAST            message
 122: PRECALL              
 126: CALL                 
 136: POP_TOP              
 138: LOAD_CONST           None
 140: RETURN_VALUE         
