# Disassembly for breakroom.ClockInOutBoard.__init__
# From module file: breakroom

## co_consts:
(None, False, 0, ('Hank Little', 'Barbara James', 'Chuck Huitt', 'Emily Johnson'), ('Emily Johnson', 'Chuck Huitt', 'Hank Little', 'Barbara James'))

## co_names:
('super', '__init__', 'clocked_in_checked', 'clock_in_num', 'clock_in_order', 'clocked_in')

## bytecode:

   0: COPY_FREE_VARS       
   2: RESUME               
   4: LOAD_GLOBAL          NULL + super
  16: PRECALL              
  20: CALL                 
  30: LOAD_METHOD          __init__
  52: LOAD_FAST            name
  54: PRECALL              
  58: CALL                 
  68: POP_TOP              
  70: LOAD_CONST           False
  72: LOAD_FAST            self
  74: STORE_ATTR           clocked_in_checked
  84: LOAD_CONST           0
  86: LOAD_FAST            self
  88: STORE_ATTR           clock_in_num
  98: BUILD_LIST           
 100: LOAD_CONST           ('Hank Little', 'Barbara James', 'Chuck Huitt', 'Emily Johnson')
 102: LIST_EXTEND          
 104: LOAD_FAST            self
 106: STORE_ATTR           clock_in_order
 116: LOAD_CONST           False
 118: LOAD_CONST           False
 120: LOAD_CONST           False
 122: LOAD_CONST           False
 124: LOAD_CONST           ('Emily Johnson', 'Chuck Huitt', 'Hank Little', 'Barbara James')
 126: BUILD_CONST_KEY_MAP  
 128: LOAD_FAST            self
 130: STORE_ATTR           clocked_in
 140: LOAD_CONST           None
 142: RETURN_VALUE         
