# Disassembly for random.Random.uniform
# From module file: random

## co_consts:
('Get a random number in the range [a, b) or [a, b] depending on rounding.',)

## co_names:
('random',)

## bytecode:

   0: RESUME               
   2: LOAD_FAST            a
   4: LOAD_FAST            b
   6: LOAD_FAST            a
   8: BINARY_OP            -
  12: LOAD_FAST            self
  14: LOAD_METHOD          random
  36: PRECALL              
  40: CALL                 
  50: BINARY_OP            *
  54: BINARY_OP            +
  58: RETURN_VALUE         
