# Disassembly for random.Random._randbelow_with_getrandbits
# From module file: random

## co_consts:
('Return a random int in the range [0,n).  Defined for n > 0.',)

## co_names:
('getrandbits', 'bit_length')

## bytecode:

   0: RESUME               
   2: LOAD_FAST            self
   4: LOAD_ATTR            getrandbits
  14: STORE_FAST           getrandbits
  16: LOAD_FAST            n
  18: LOAD_METHOD          bit_length
  40: PRECALL              
  44: CALL                 
  54: STORE_FAST           k
  56: PUSH_NULL            
  58: LOAD_FAST            getrandbits
  60: LOAD_FAST            k
  62: PRECALL              
  66: CALL                 
  76: STORE_FAST           r
  78: LOAD_FAST            r
  80: LOAD_FAST            n
  82: COMPARE_OP           >=
  88: POP_JUMP_FORWARD_IF_FALSE to 124
  90: PUSH_NULL            
  92: LOAD_FAST            getrandbits
  94: LOAD_FAST            k
  96: PRECALL              
 100: CALL                 
 110: STORE_FAST           r
 112: LOAD_FAST            r
 114: LOAD_FAST            n
 116: COMPARE_OP           >=
 122: POP_JUMP_BACKWARD_IF_TRUE to 90
 124: LOAD_FAST            r
 126: RETURN_VALUE         
