# Disassembly for random.Random.shuffle
# From module file: random

## co_consts:
('Shuffle list x in place, and return None.', 1, None)

## co_names:
('_randbelow', 'reversed', 'range', 'len')

## bytecode:

   0: RESUME               
   2: LOAD_FAST            self
   4: LOAD_ATTR            _randbelow
  14: STORE_FAST           randbelow
  16: LOAD_GLOBAL          NULL + reversed
  28: LOAD_GLOBAL          NULL + range
  40: LOAD_CONST           1
  42: LOAD_GLOBAL          NULL + len
  54: LOAD_FAST            x
  56: PRECALL              
  60: CALL                 
  70: PRECALL              
  74: CALL                 
  84: PRECALL              
  88: CALL                 
  98: GET_ITER             
 100: FOR_ITER             to 180
 102: STORE_FAST           i
 104: PUSH_NULL            
 106: LOAD_FAST            randbelow
 108: LOAD_FAST            i
 110: LOAD_CONST           1
 112: BINARY_OP            +
 116: PRECALL              
 120: CALL                 
 130: STORE_FAST           j
 132: LOAD_FAST            x
 134: LOAD_FAST            j
 136: BINARY_SUBSCR        
 146: LOAD_FAST            x
 148: LOAD_FAST            i
 150: BINARY_SUBSCR        
 160: SWAP                 
 162: LOAD_FAST            x
 164: LOAD_FAST            i
 166: STORE_SUBSCR         
 170: LOAD_FAST            x
 172: LOAD_FAST            j
 174: STORE_SUBSCR         
 178: JUMP_BACKWARD        to 100
 180: LOAD_CONST           None
 182: RETURN_VALUE         
