# Disassembly for random.Random.choices
# From module file: random

## co_consts:
('Return a k sized list of population elements chosen with replacement.\n\n        If the relative weights or cumulative weights are not specified,\n        the selections are made with equal probability.\n\n        ', None, 0.0, <code object <listcomp> at 0x00000240693EB030, file "random.py", line 493>, 'The number of choices must be a keyword argument: k=', 'Cannot specify both weights and cumulative weights', 'The number of weights does not match the population', -1, 'Total of weights must be greater than zero', 'Total of weights must be finite', 1, <code object <listcomp> at 0x000002406944BEE0, file "random.py", line 514>)

## co_names:
('random', 'len', '_floor', '_repeat', 'list', '_accumulate', 'TypeError', 'isinstance', 'int', 'ValueError', '_isfinite', '_bisect')

## bytecode:

   0: MAKE_CELL            population
   2: MAKE_CELL            cum_weights
   4: MAKE_CELL            bisect
   6: MAKE_CELL            floor
   8: MAKE_CELL            hi
  10: MAKE_CELL            n
  12: MAKE_CELL            random
  14: MAKE_CELL            total
  16: RESUME               
  18: LOAD_FAST            self
  20: LOAD_ATTR            random
  30: STORE_DEREF          random
  32: LOAD_GLOBAL          NULL + len
  44: LOAD_DEREF           population
  46: PRECALL              
  50: CALL                 
  60: STORE_DEREF          n
  62: LOAD_DEREF           cum_weights
  64: POP_JUMP_FORWARD_IF_NOT_NONE to 330
  66: LOAD_FAST            weights
  68: POP_JUMP_FORWARD_IF_NOT_NONE to 156
  70: LOAD_GLOBAL          _floor
  82: STORE_DEREF          floor
  84: LOAD_DEREF           n
  86: LOAD_CONST           0.0
  88: BINARY_OP            +=
  92: STORE_DEREF          n
  94: LOAD_CLOSURE         floor
  96: LOAD_CLOSURE         n
  98: LOAD_CLOSURE         population
 100: LOAD_CLOSURE         random
 102: BUILD_TUPLE          
 104: LOAD_CONST           <code object <listcomp> at 0x00000240693EB030, file "random.py", line 493>
 106: MAKE_FUNCTION        closure
 108: LOAD_GLOBAL          NULL + _repeat
 120: LOAD_CONST           None
 122: LOAD_FAST            k
 124: PRECALL              
 128: CALL                 
 138: GET_ITER             
 140: PRECALL              
 144: CALL                 
 154: RETURN_VALUE         
 156: NOP                  
 158: LOAD_GLOBAL          NULL + list
 170: LOAD_GLOBAL          NULL + _accumulate
 182: LOAD_FAST            weights
 184: PRECALL              
 188: CALL                 
 198: PRECALL              
 202: CALL                 
 212: STORE_DEREF          cum_weights
 214: JUMP_FORWARD         to 364
 216: PUSH_EXC_INFO        
 218: LOAD_GLOBAL          TypeError
 230: CHECK_EXC_MATCH      
 232: POP_JUMP_FORWARD_IF_FALSE to 322
 234: POP_TOP              
 236: LOAD_GLOBAL          NULL + isinstance
 248: LOAD_FAST            weights
 250: LOAD_GLOBAL          int
 262: PRECALL              
 266: CALL                 
 276: POP_JUMP_FORWARD_IF_TRUE to 280
 278: RAISE_VARARGS        
 280: LOAD_FAST            weights
 282: STORE_FAST           k
 284: LOAD_GLOBAL          NULL + TypeError
 296: LOAD_CONST           'The number of choices must be a keyword argument: k='
 298: LOAD_FAST            k
 300: FORMAT_VALUE         repr
 302: BUILD_STRING         
 304: PRECALL              
 308: CALL                 
 318: LOAD_CONST           None
 320: RAISE_VARARGS        
 322: RERAISE              
 324: COPY                 
 326: POP_EXCEPT           
 328: RERAISE              
 330: LOAD_FAST            weights
 332: POP_JUMP_FORWARD_IF_NONE to 364
 334: LOAD_GLOBAL          NULL + TypeError
 346: LOAD_CONST           'Cannot specify both weights and cumulative weights'
 348: PRECALL              
 352: CALL                 
 362: RAISE_VARARGS        
 364: LOAD_GLOBAL          NULL + len
 376: LOAD_DEREF           cum_weights
 378: PRECALL              
 382: CALL                 
 392: LOAD_DEREF           n
 394: COMPARE_OP           !=
 400: POP_JUMP_FORWARD_IF_FALSE to 432
 402: LOAD_GLOBAL          NULL + ValueError
 414: LOAD_CONST           'The number of weights does not match the population'
 416: PRECALL              
 420: CALL                 
 430: RAISE_VARARGS        
 432: LOAD_DEREF           cum_weights
 434: LOAD_CONST           -1
 436: BINARY_SUBSCR        
 446: LOAD_CONST           0.0
 448: BINARY_OP            +
 452: STORE_DEREF          total
 454: LOAD_DEREF           total
 456: LOAD_CONST           0.0
 458: COMPARE_OP           <=
 464: POP_JUMP_FORWARD_IF_FALSE to 496
 466: LOAD_GLOBAL          NULL + ValueError
 478: LOAD_CONST           'Total of weights must be greater than zero'
 480: PRECALL              
 484: CALL                 
 494: RAISE_VARARGS        
 496: LOAD_GLOBAL          NULL + _isfinite
 508: LOAD_DEREF           total
 510: PRECALL              
 514: CALL                 
 524: POP_JUMP_FORWARD_IF_TRUE to 556
 526: LOAD_GLOBAL          NULL + ValueError
 538: LOAD_CONST           'Total of weights must be finite'
 540: PRECALL              
 544: CALL                 
 554: RAISE_VARARGS        
 556: LOAD_GLOBAL          _bisect
 568: STORE_DEREF          bisect
 570: LOAD_DEREF           n
 572: LOAD_CONST           1
 574: BINARY_OP            -
 578: STORE_DEREF          hi
 580: LOAD_CLOSURE         bisect
 582: LOAD_CLOSURE         cum_weights
 584: LOAD_CLOSURE         hi
 586: LOAD_CLOSURE         population
 588: LOAD_CLOSURE         random
 590: LOAD_CLOSURE         total
 592: BUILD_TUPLE          
 594: LOAD_CONST           <code object <listcomp> at 0x000002406944BEE0, file "random.py", line 514>
 596: MAKE_FUNCTION        closure
 598: LOAD_GLOBAL          NULL + _repeat
 610: LOAD_CONST           None
 612: LOAD_FAST            k
 614: PRECALL              
 618: CALL                 
 628: GET_ITER             
 630: PRECALL              
 634: CALL                 
 644: RETURN_VALUE         
