# Disassembly for random.Random.randrange
# From module file: random

## co_consts:
('Choose a random item from range(stop) or range(start, stop[, step]).\n\n        Roughly equivalent to ``choice(range(start, stop, step))`` but\n        supports arbitrarily large ranges and is optimized for common cases.\n\n        ', 'randrange() will raise TypeError in the future', 2, 'non-integer arg 1 for randrange()', 'non-integer arguments to randrange() have been deprecated since Python 3.10 and will be removed in a subsequent version', None, 'Missing a non-None stop argument', 0, 'empty range for randrange()', 'non-integer stop for randrange()', 'non-integer step for randrange()', 1, 'empty range for randrange() (%d, %d, %d)', 'zero step for randrange()')

## co_names:
('_index', 'TypeError', 'int', '_warn', 'DeprecationWarning', 'ValueError', '_ONE', '_randbelow')

## bytecode:

   0: RESUME               
   2: NOP                  
   4: LOAD_GLOBAL          NULL + _index
  16: LOAD_FAST            start
  18: PRECALL              
  22: CALL                 
  32: STORE_FAST           istart
  34: JUMP_FORWARD         to 228
  36: PUSH_EXC_INFO        
  38: LOAD_GLOBAL          TypeError
  50: CHECK_EXC_MATCH      
  52: POP_JUMP_FORWARD_IF_FALSE to 220
  54: POP_TOP              
  56: LOAD_GLOBAL          NULL + int
  68: LOAD_FAST            start
  70: PRECALL              
  74: CALL                 
  84: STORE_FAST           istart
  86: LOAD_FAST            istart
  88: LOAD_FAST            start
  90: COMPARE_OP           !=
  96: POP_JUMP_FORWARD_IF_FALSE to 172
  98: LOAD_GLOBAL          NULL + _warn
 110: LOAD_CONST           'randrange() will raise TypeError in the future'
 112: LOAD_GLOBAL          DeprecationWarning
 124: LOAD_CONST           2
 126: PRECALL              
 130: CALL                 
 140: POP_TOP              
 142: LOAD_GLOBAL          NULL + ValueError
 154: LOAD_CONST           'non-integer arg 1 for randrange()'
 156: PRECALL              
 160: CALL                 
 170: RAISE_VARARGS        
 172: LOAD_GLOBAL          NULL + _warn
 184: LOAD_CONST           'non-integer arguments to randrange() have been deprecated since Python 3.10 and will be removed in a subsequent version'
 186: LOAD_GLOBAL          DeprecationWarning
 198: LOAD_CONST           2
 200: PRECALL              
 204: CALL                 
 214: POP_TOP              
 216: POP_EXCEPT           
 218: JUMP_FORWARD         to 228
 220: RERAISE              
 222: COPY                 
 224: POP_EXCEPT           
 226: RERAISE              
 228: LOAD_FAST            stop
 230: POP_JUMP_FORWARD_IF_NOT_NONE to 364
 232: LOAD_FAST            step
 234: LOAD_GLOBAL          _ONE
 246: IS_OP                
 248: POP_JUMP_FORWARD_IF_FALSE to 280
 250: LOAD_GLOBAL          NULL + TypeError
 262: LOAD_CONST           'Missing a non-None stop argument'
 264: PRECALL              
 268: CALL                 
 278: RAISE_VARARGS        
 280: LOAD_FAST            istart
 282: LOAD_CONST           0
 284: COMPARE_OP           >
 290: POP_JUMP_FORWARD_IF_FALSE to 334
 292: LOAD_FAST            self
 294: LOAD_METHOD          _randbelow
 316: LOAD_FAST            istart
 318: PRECALL              
 322: CALL                 
 332: RETURN_VALUE         
 334: LOAD_GLOBAL          NULL + ValueError
 346: LOAD_CONST           'empty range for randrange()'
 348: PRECALL              
 352: CALL                 
 362: RAISE_VARARGS        
 364: NOP                  
 366: LOAD_GLOBAL          NULL + _index
 378: LOAD_FAST            stop
 380: PRECALL              
 384: CALL                 
 394: STORE_FAST           istop
 396: JUMP_FORWARD         to 590
 398: PUSH_EXC_INFO        
 400: LOAD_GLOBAL          TypeError
 412: CHECK_EXC_MATCH      
 414: POP_JUMP_FORWARD_IF_FALSE to 582
 416: POP_TOP              
 418: LOAD_GLOBAL          NULL + int
 430: LOAD_FAST            stop
 432: PRECALL              
 436: CALL                 
 446: STORE_FAST           istop
 448: LOAD_FAST            istop
 450: LOAD_FAST            stop
 452: COMPARE_OP           !=
 458: POP_JUMP_FORWARD_IF_FALSE to 534
 460: LOAD_GLOBAL          NULL + _warn
 472: LOAD_CONST           'randrange() will raise TypeError in the future'
 474: LOAD_GLOBAL          DeprecationWarning
 486: LOAD_CONST           2
 488: PRECALL              
 492: CALL                 
 502: POP_TOP              
 504: LOAD_GLOBAL          NULL + ValueError
 516: LOAD_CONST           'non-integer stop for randrange()'
 518: PRECALL              
 522: CALL                 
 532: RAISE_VARARGS        
 534: LOAD_GLOBAL          NULL + _warn
 546: LOAD_CONST           'non-integer arguments to randrange() have been deprecated since Python 3.10 and will be removed in a subsequent version'
 548: LOAD_GLOBAL          DeprecationWarning
 560: LOAD_CONST           2
 562: PRECALL              
 566: CALL                 
 576: POP_TOP              
 578: POP_EXCEPT           
 580: JUMP_FORWARD         to 590
 582: RERAISE              
 584: COPY                 
 586: POP_EXCEPT           
 588: RERAISE              
 590: LOAD_FAST            istop
 592: LOAD_FAST            istart
 594: BINARY_OP            -
 598: STORE_FAST           width
 600: NOP                  
 602: LOAD_GLOBAL          NULL + _index
 614: LOAD_FAST            step
 616: PRECALL              
 620: CALL                 
 630: STORE_FAST           istep
 632: JUMP_FORWARD         to 826
 634: PUSH_EXC_INFO        
 636: LOAD_GLOBAL          TypeError
 648: CHECK_EXC_MATCH      
 650: POP_JUMP_FORWARD_IF_FALSE to 818
 652: POP_TOP              
 654: LOAD_GLOBAL          NULL + int
 666: LOAD_FAST            step
 668: PRECALL              
 672: CALL                 
 682: STORE_FAST           istep
 684: LOAD_FAST            istep
 686: LOAD_FAST            step
 688: COMPARE_OP           !=
 694: POP_JUMP_FORWARD_IF_FALSE to 770
 696: LOAD_GLOBAL          NULL + _warn
 708: LOAD_CONST           'randrange() will raise TypeError in the future'
 710: LOAD_GLOBAL          DeprecationWarning
 722: LOAD_CONST           2
 724: PRECALL              
 728: CALL                 
 738: POP_TOP              
 740: LOAD_GLOBAL          NULL + ValueError
 752: LOAD_CONST           'non-integer step for randrange()'
 754: PRECALL              
 758: CALL                 
 768: RAISE_VARARGS        
 770: LOAD_GLOBAL          NULL + _warn
 782: LOAD_CONST           'non-integer arguments to randrange() have been deprecated since Python 3.10 and will be removed in a subsequent version'
 784: LOAD_GLOBAL          DeprecationWarning
 796: LOAD_CONST           2
 798: PRECALL              
 802: CALL                 
 812: POP_TOP              
 814: POP_EXCEPT           
 816: JUMP_FORWARD         to 826
 818: RERAISE              
 820: COPY                 
 822: POP_EXCEPT           
 824: RERAISE              
 826: LOAD_FAST            istep
 828: LOAD_CONST           1
 830: COMPARE_OP           ==
 836: POP_JUMP_FORWARD_IF_FALSE to 940
 838: LOAD_FAST            width
 840: LOAD_CONST           0
 842: COMPARE_OP           >
 848: POP_JUMP_FORWARD_IF_FALSE to 898
 850: LOAD_FAST            istart
 852: LOAD_FAST            self
 854: LOAD_METHOD          _randbelow
 876: LOAD_FAST            width
 878: PRECALL              
 882: CALL                 
 892: BINARY_OP            +
 896: RETURN_VALUE         
 898: LOAD_GLOBAL          NULL + ValueError
 910: LOAD_CONST           'empty range for randrange() (%d, %d, %d)'
 912: LOAD_FAST            istart
 914: LOAD_FAST            istop
 916: LOAD_FAST            width
 918: BUILD_TUPLE          
 920: BINARY_OP            %
 924: PRECALL              
 928: CALL                 
 938: RAISE_VARARGS        
 940: LOAD_FAST            istep
 942: LOAD_CONST           0
 944: COMPARE_OP           >
 950: POP_JUMP_FORWARD_IF_FALSE to 976
 952: LOAD_FAST            width
 954: LOAD_FAST            istep
 956: BINARY_OP            +
 960: LOAD_CONST           1
 962: BINARY_OP            -
 966: LOAD_FAST            istep
 968: BINARY_OP            //
 972: STORE_FAST           n
 974: JUMP_FORWARD         to 1042
 976: LOAD_FAST            istep
 978: LOAD_CONST           0
 980: COMPARE_OP           <
 986: POP_JUMP_FORWARD_IF_FALSE to 1012
 988: LOAD_FAST            width
 990: LOAD_FAST            istep
 992: BINARY_OP            +
 996: LOAD_CONST           1
 998: BINARY_OP            +
1002: LOAD_FAST            istep
1004: BINARY_OP            //
1008: STORE_FAST           n
1010: JUMP_FORWARD         to 1042
1012: LOAD_GLOBAL          NULL + ValueError
1024: LOAD_CONST           'zero step for randrange()'
1026: PRECALL              
1030: CALL                 
1040: RAISE_VARARGS        
1042: LOAD_FAST            n
1044: LOAD_CONST           0
1046: COMPARE_OP           <=
1052: POP_JUMP_FORWARD_IF_FALSE to 1084
1054: LOAD_GLOBAL          NULL + ValueError
1066: LOAD_CONST           'empty range for randrange()'
1068: PRECALL              
1072: CALL                 
1082: RAISE_VARARGS        
1084: LOAD_FAST            istart
1086: LOAD_FAST            istep
1088: LOAD_FAST            self
1090: LOAD_METHOD          _randbelow
1112: LOAD_FAST            n
1114: PRECALL              
1118: CALL                 
1128: BINARY_OP            *
1132: BINARY_OP            +
1136: RETURN_VALUE         
