# Disassembly for random.Random.gammavariate
# From module file: random

## co_consts:
('Gamma distribution.  Not the gamma function!\n\n        Conditions on the parameters are alpha > 0 and beta > 0.\n\n        The probability distribution function is:\n\n                    x ** (alpha - 1) * math.exp(-x / beta)\n          pdf(x) =  --------------------------------------\n                      math.gamma(alpha) * beta ** alpha\n\n        ', 0.0, 'gammavariate: alpha and beta must be > 0.0', 1.0, 2.0, True, 1e-07, 0.9999999, 4.5)

## co_names:
('ValueError', 'random', '_sqrt', 'LOG4', '_log', '_exp', 'SG_MAGICCONST', '_e')

## bytecode:

   0: RESUME               
   2: LOAD_FAST            alpha
   4: LOAD_CONST           0.0
   6: COMPARE_OP           <=
  12: POP_JUMP_FORWARD_IF_TRUE to 26
  14: LOAD_FAST            beta
  16: LOAD_CONST           0.0
  18: COMPARE_OP           <=
  24: POP_JUMP_FORWARD_IF_FALSE to 56
  26: LOAD_GLOBAL          NULL + ValueError
  38: LOAD_CONST           'gammavariate: alpha and beta must be > 0.0'
  40: PRECALL              
  44: CALL                 
  54: RAISE_VARARGS        
  56: LOAD_FAST            self
  58: LOAD_ATTR            random
  68: STORE_FAST           random
  70: LOAD_FAST            alpha
  72: LOAD_CONST           1.0
  74: COMPARE_OP           >
  80: POP_JUMP_FORWARD_IF_FALSE to 446
  82: LOAD_GLOBAL          NULL + _sqrt
  94: LOAD_CONST           2.0
  96: LOAD_FAST            alpha
  98: BINARY_OP            *
 102: LOAD_CONST           1.0
 104: BINARY_OP            -
 108: PRECALL              
 112: CALL                 
 122: STORE_FAST           ainv
 124: LOAD_FAST            alpha
 126: LOAD_GLOBAL          LOG4
 138: BINARY_OP            -
 142: STORE_FAST           bbb
 144: LOAD_FAST            alpha
 146: LOAD_FAST            ainv
 148: BINARY_OP            +
 152: STORE_FAST           ccc
 154: NOP                  
 156: PUSH_NULL            
 158: LOAD_FAST            random
 160: PRECALL              
 164: CALL                 
 174: STORE_FAST           u1
 176: LOAD_CONST           1e-07
 178: LOAD_FAST            u1
 180: SWAP                 
 182: COPY                 
 184: COMPARE_OP           <
 190: POP_JUMP_FORWARD_IF_FALSE to 204
 192: LOAD_CONST           0.9999999
 194: COMPARE_OP           <
 200: POP_JUMP_FORWARD_IF_TRUE to 208
 202: JUMP_FORWARD         to 206
 204: POP_TOP              
 206: JUMP_BACKWARD        to 154
 208: LOAD_CONST           1.0
 210: PUSH_NULL            
 212: LOAD_FAST            random
 214: PRECALL              
 218: CALL                 
 228: BINARY_OP            -
 232: STORE_FAST           u2
 234: LOAD_GLOBAL          NULL + _log
 246: LOAD_FAST            u1
 248: LOAD_CONST           1.0
 250: LOAD_FAST            u1
 252: BINARY_OP            -
 256: BINARY_OP            /
 260: PRECALL              
 264: CALL                 
 274: LOAD_FAST            ainv
 276: BINARY_OP            /
 280: STORE_FAST           v
 282: LOAD_FAST            alpha
 284: LOAD_GLOBAL          NULL + _exp
 296: LOAD_FAST            v
 298: PRECALL              
 302: CALL                 
 312: BINARY_OP            *
 316: STORE_FAST           x
 318: LOAD_FAST            u1
 320: LOAD_FAST            u1
 322: BINARY_OP            *
 326: LOAD_FAST            u2
 328: BINARY_OP            *
 332: STORE_FAST           z
 334: LOAD_FAST            bbb
 336: LOAD_FAST            ccc
 338: LOAD_FAST            v
 340: BINARY_OP            *
 344: BINARY_OP            +
 348: LOAD_FAST            x
 350: BINARY_OP            -
 354: STORE_FAST           r
 356: LOAD_FAST            r
 358: LOAD_GLOBAL          SG_MAGICCONST
 370: BINARY_OP            +
 374: LOAD_CONST           4.5
 376: LOAD_FAST            z
 378: BINARY_OP            *
 382: BINARY_OP            -
 386: LOAD_CONST           0.0
 388: COMPARE_OP           >=
 394: POP_JUMP_FORWARD_IF_TRUE to 434
 396: LOAD_FAST            r
 398: LOAD_GLOBAL          NULL + _log
 410: LOAD_FAST            z
 412: PRECALL              
 416: CALL                 
 426: COMPARE_OP           >=
 432: POP_JUMP_FORWARD_IF_FALSE to 444
 434: LOAD_FAST            x
 436: LOAD_FAST            beta
 438: BINARY_OP            *
 442: RETURN_VALUE         
 444: JUMP_BACKWARD        to 156
 446: LOAD_FAST            alpha
 448: LOAD_CONST           1.0
 450: COMPARE_OP           ==
 456: POP_JUMP_FORWARD_IF_FALSE to 518
 458: LOAD_GLOBAL          NULL + _log
 470: LOAD_CONST           1.0
 472: PUSH_NULL            
 474: LOAD_FAST            random
 476: PRECALL              
 480: CALL                 
 490: BINARY_OP            -
 494: PRECALL              
 498: CALL                 
 508: UNARY_NEGATIVE       
 510: LOAD_FAST            beta
 512: BINARY_OP            *
 516: RETURN_VALUE         
 518: NOP                  
 520: PUSH_NULL            
 522: LOAD_FAST            random
 524: PRECALL              
 528: CALL                 
 538: STORE_FAST           u
 540: LOAD_GLOBAL          _e
 552: LOAD_FAST            alpha
 554: BINARY_OP            +
 558: LOAD_GLOBAL          _e
 570: BINARY_OP            /
 574: STORE_FAST           b
 576: LOAD_FAST            b
 578: LOAD_FAST            u
 580: BINARY_OP            *
 584: STORE_FAST           p
 586: LOAD_FAST            p
 588: LOAD_CONST           1.0
 590: COMPARE_OP           <=
 596: POP_JUMP_FORWARD_IF_FALSE to 616
 598: LOAD_FAST            p
 600: LOAD_CONST           1.0
 602: LOAD_FAST            alpha
 604: BINARY_OP            /
 608: BINARY_OP            **
 612: STORE_FAST           x
 614: JUMP_FORWARD         to 660
 616: LOAD_GLOBAL          NULL + _log
 628: LOAD_FAST            b
 630: LOAD_FAST            p
 632: BINARY_OP            -
 636: LOAD_FAST            alpha
 638: BINARY_OP            /
 642: PRECALL              
 646: CALL                 
 656: UNARY_NEGATIVE       
 658: STORE_FAST           x
 660: PUSH_NULL            
 662: LOAD_FAST            random
 664: PRECALL              
 668: CALL                 
 678: STORE_FAST           u1
 680: LOAD_FAST            p
 682: LOAD_CONST           1.0
 684: COMPARE_OP           >
 690: POP_JUMP_FORWARD_IF_FALSE to 720
 692: LOAD_FAST            u1
 694: LOAD_FAST            x
 696: LOAD_FAST            alpha
 698: LOAD_CONST           1.0
 700: BINARY_OP            -
 704: BINARY_OP            **
 708: COMPARE_OP           <=
 714: POP_JUMP_FORWARD_IF_FALSE to 718
 716: JUMP_FORWARD         to 764
 718: JUMP_FORWARD         to 762
 720: LOAD_FAST            u1
 722: LOAD_GLOBAL          NULL + _exp
 734: LOAD_FAST            x
 736: UNARY_NEGATIVE       
 738: PRECALL              
 742: CALL                 
 752: COMPARE_OP           <=
 758: POP_JUMP_FORWARD_IF_FALSE to 762
 760: JUMP_FORWARD         to 764
 762: JUMP_BACKWARD        to 520
 764: LOAD_FAST            x
 766: LOAD_FAST            beta
 768: BINARY_OP            *
 772: RETURN_VALUE         
