# Disassembly for random._test_generator
# From module file: random

## co_consts:
(None, 0, ('stdev', 'fmean'), ('perf_counter',), <code object <listcomp> at 0x0000024069466DB0, file "random.py", line 865>, '.3f', ' sec, ', ' times ', 'avg %g, stddev %g, min %g, max %g\n')

## co_names:
('statistics', 'stdev', 'fmean', 'time', 'perf_counter', '_repeat', 'min', 'max', 'print', '__name__')

## bytecode:

   0: MAKE_CELL            func
   2: MAKE_CELL            args
   4: RESUME               
   6: LOAD_CONST           0
   8: LOAD_CONST           ('stdev', 'fmean')
  10: IMPORT_NAME          statistics
  12: IMPORT_FROM          stdev
  14: STORE_FAST           stdev
  16: IMPORT_FROM          fmean
  18: STORE_FAST           mean
  20: POP_TOP              
  22: LOAD_CONST           0
  24: LOAD_CONST           ('perf_counter',)
  26: IMPORT_NAME          time
  28: IMPORT_FROM          perf_counter
  30: STORE_FAST           perf_counter
  32: POP_TOP              
  34: PUSH_NULL            
  36: LOAD_FAST            perf_counter
  38: PRECALL              
  42: CALL                 
  52: STORE_FAST           t0
  54: LOAD_CLOSURE         args
  56: LOAD_CLOSURE         func
  58: BUILD_TUPLE          
  60: LOAD_CONST           <code object <listcomp> at 0x0000024069466DB0, file "random.py", line 865>
  62: MAKE_FUNCTION        closure
  64: LOAD_GLOBAL          NULL + _repeat
  76: LOAD_CONST           None
  78: LOAD_FAST            n
  80: PRECALL              
  84: CALL                 
  94: GET_ITER             
  96: PRECALL              
 100: CALL                 
 110: STORE_FAST           data
 112: PUSH_NULL            
 114: LOAD_FAST            perf_counter
 116: PRECALL              
 120: CALL                 
 130: STORE_FAST           t1
 132: PUSH_NULL            
 134: LOAD_FAST            mean
 136: LOAD_FAST            data
 138: PRECALL              
 142: CALL                 
 152: STORE_FAST           xbar
 154: PUSH_NULL            
 156: LOAD_FAST            stdev
 158: LOAD_FAST            data
 160: LOAD_FAST            xbar
 162: PRECALL              
 166: CALL                 
 176: STORE_FAST           sigma
 178: LOAD_GLOBAL          NULL + min
 190: LOAD_FAST            data
 192: PRECALL              
 196: CALL                 
 206: STORE_FAST           low
 208: LOAD_GLOBAL          NULL + max
 220: LOAD_FAST            data
 222: PRECALL              
 226: CALL                 
 236: STORE_FAST           high
 238: LOAD_GLOBAL          NULL + print
 250: LOAD_FAST            t1
 252: LOAD_FAST            t0
 254: BINARY_OP            -
 258: LOAD_CONST           '.3f'
 260: FORMAT_VALUE         with format
 262: LOAD_CONST           ' sec, '
 264: LOAD_FAST            n
 266: FORMAT_VALUE         
 268: LOAD_CONST           ' times '
 270: LOAD_DEREF           func
 272: LOAD_ATTR            __name__
 282: FORMAT_VALUE         
 284: BUILD_STRING         
 286: PRECALL              
 290: CALL                 
 300: POP_TOP              
 302: LOAD_GLOBAL          NULL + print
 314: LOAD_CONST           'avg %g, stddev %g, min %g, max %g\n'
 316: LOAD_FAST            xbar
 318: LOAD_FAST            sigma
 320: LOAD_FAST            low
 322: LOAD_FAST            high
 324: BUILD_TUPLE          
 326: BINARY_OP            %
 330: PRECALL              
 334: CALL                 
 344: POP_TOP              
 346: LOAD_CONST           None
 348: RETURN_VALUE         
