# Disassembly for random.Random.randint
# From module file: random

## co_consts:
('Return random integer in range [a, b], including both end points.\n        ', 1)

## co_names:
('randrange',)

## bytecode:

   0: RESUME               
   2: LOAD_FAST            self
   4: LOAD_METHOD          randrange
  26: LOAD_FAST            a
  28: LOAD_FAST            b
  30: LOAD_CONST           1
  32: BINARY_OP            +
  36: PRECALL              
  40: CALL                 
  50: RETURN_VALUE         
