# Disassembly for random.Random.triangular
# From module file: random

## co_consts:
('Triangular distribution.\n\n        Continuous distribution bounded by given lower and upper limits,\n        and having a given mode value in-between.\n\n        http://en.wikipedia.org/wiki/Triangular_distribution\n\n        ', None, 0.5, 1.0)

## co_names:
('random', 'ZeroDivisionError', '_sqrt')

## bytecode:

   0: RESUME               
   2: LOAD_FAST            self
   4: LOAD_METHOD          random
  26: PRECALL              
  30: CALL                 
  40: STORE_FAST           u
  42: NOP                  
  44: LOAD_FAST            mode
  46: POP_JUMP_FORWARD_IF_NOT_NONE to 52
  48: LOAD_CONST           0.5
  50: JUMP_FORWARD         to 72
  52: LOAD_FAST            mode
  54: LOAD_FAST            low
  56: BINARY_OP            -
  60: LOAD_FAST            high
  62: LOAD_FAST            low
  64: BINARY_OP            -
  68: BINARY_OP            /
  72: STORE_FAST           c
  74: JUMP_FORWARD         to 112
  76: PUSH_EXC_INFO        
  78: LOAD_GLOBAL          ZeroDivisionError
  90: CHECK_EXC_MATCH      
  92: POP_JUMP_FORWARD_IF_FALSE to 104
  94: POP_TOP              
  96: LOAD_FAST            low
  98: SWAP                 
 100: POP_EXCEPT           
 102: RETURN_VALUE         
 104: RERAISE              
 106: COPY                 
 108: POP_EXCEPT           
 110: RERAISE              
 112: LOAD_FAST            u
 114: LOAD_FAST            c
 116: COMPARE_OP           >
 122: POP_JUMP_FORWARD_IF_FALSE to 152
 124: LOAD_CONST           1.0
 126: LOAD_FAST            u
 128: BINARY_OP            -
 132: STORE_FAST           u
 134: LOAD_CONST           1.0
 136: LOAD_FAST            c
 138: BINARY_OP            -
 142: STORE_FAST           c
 144: LOAD_FAST            high
 146: LOAD_FAST            low
 148: STORE_FAST           high
 150: STORE_FAST           low
 152: LOAD_FAST            low
 154: LOAD_FAST            high
 156: LOAD_FAST            low
 158: BINARY_OP            -
 162: LOAD_GLOBAL          NULL + _sqrt
 174: LOAD_FAST            u
 176: LOAD_FAST            c
 178: BINARY_OP            *
 182: PRECALL              
 186: CALL                 
 196: BINARY_OP            *
 200: BINARY_OP            +
 204: RETURN_VALUE         
