# Disassembly for random.Random.getstate
# From module file: random

## co_consts:
('Return internal state; can be passed to setstate() later.',)

## co_names:
('VERSION', 'super', 'getstate', 'gauss_next')

## bytecode:

   0: COPY_FREE_VARS       
   2: RESUME               
   4: LOAD_FAST            self
   6: LOAD_ATTR            VERSION
  16: LOAD_GLOBAL          NULL + super
  28: PRECALL              
  32: CALL                 
  42: LOAD_METHOD          getstate
  64: PRECALL              
  68: CALL                 
  78: LOAD_FAST            self
  80: LOAD_ATTR            gauss_next
  90: BUILD_TUPLE          
  92: RETURN_VALUE         
