# Disassembly for random.Random.paretovariate
# From module file: random

## co_consts:
('Pareto distribution.  alpha is the shape parameter.', 1.0, -1.0)

## co_names:
('random',)

## bytecode:

   0: RESUME               
   2: LOAD_CONST           1.0
   4: LOAD_FAST            self
   6: LOAD_METHOD          random
  28: PRECALL              
  32: CALL                 
  42: BINARY_OP            -
  46: STORE_FAST           u
  48: LOAD_FAST            u
  50: LOAD_CONST           -1.0
  52: LOAD_FAST            alpha
  54: BINARY_OP            /
  58: BINARY_OP            **
  62: RETURN_VALUE         
