# Disassembly for random.Random._randbelow_without_getrandbits
# From module file: random

## co_consts:
('Return a random int in the range [0,n).  Defined for n > 0.\n\n        The implementation does not use getrandbits, but only random.\n        ', 'Underlying random() generator does not supply \nenough bits to choose from a population range this large.\nTo remove the range limitation, add a getrandbits() method.')

## co_names:
('random', '_warn', '_floor')

## bytecode:

   0: RESUME               
   2: LOAD_FAST            self
   4: LOAD_ATTR            random
  14: STORE_FAST           random
  16: LOAD_FAST            n
  18: LOAD_FAST            maxsize
  20: COMPARE_OP           >=
  26: POP_JUMP_FORWARD_IF_FALSE to 110
  28: LOAD_GLOBAL          NULL + _warn
  40: LOAD_CONST           'Underlying random() generator does not supply \nenough bits to choose from a population range this large.\nTo remove the range limitation, add a getrandbits() method.'
  42: PRECALL              
  46: CALL                 
  56: POP_TOP              
  58: LOAD_GLOBAL          NULL + _floor
  70: PUSH_NULL            
  72: LOAD_FAST            random
  74: PRECALL              
  78: CALL                 
  88: LOAD_FAST            n
  90: BINARY_OP            *
  94: PRECALL              
  98: CALL                 
 108: RETURN_VALUE         
 110: LOAD_FAST            maxsize
 112: LOAD_FAST            n
 114: BINARY_OP            %
 118: STORE_FAST           rem
 120: LOAD_FAST            maxsize
 122: LOAD_FAST            rem
 124: BINARY_OP            -
 128: LOAD_FAST            maxsize
 130: BINARY_OP            /
 134: STORE_FAST           limit
 136: PUSH_NULL            
 138: LOAD_FAST            random
 140: PRECALL              
 144: CALL                 
 154: STORE_FAST           r
 156: LOAD_FAST            r
 158: LOAD_FAST            limit
 160: COMPARE_OP           >=
 166: POP_JUMP_FORWARD_IF_FALSE to 200
 168: PUSH_NULL            
 170: LOAD_FAST            random
 172: PRECALL              
 176: CALL                 
 186: STORE_FAST           r
 188: LOAD_FAST            r
 190: LOAD_FAST            limit
 192: COMPARE_OP           >=
 198: POP_JUMP_BACKWARD_IF_TRUE to 168
 200: LOAD_GLOBAL          NULL + _floor
 212: LOAD_FAST            r
 214: LOAD_FAST            maxsize
 216: BINARY_OP            *
 220: PRECALL              
 224: CALL                 
 234: LOAD_FAST            n
 236: BINARY_OP            %
 240: RETURN_VALUE         
