# Disassembly for typing._GenericAlias.__init__
# From module file: typing

## co_consts:
(None, ('inst', 'name'), <code object <genexpr> at 0x000002406945EE20, file "typing.py", line 1358>)

## co_names:
('super', '__init__', 'isinstance', 'tuple', '__args__', '_collect_parameters', '__parameters__', '_paramspec_tvars', '__module__')

## bytecode:

   0: COPY_FREE_VARS       
   2: RESUME               
   4: LOAD_GLOBAL          NULL + super
  16: PRECALL              
  20: CALL                 
  30: LOAD_METHOD          __init__
  52: LOAD_FAST            origin
  54: LOAD_FAST            inst
  56: LOAD_FAST            name
  58: KW_NAMES             
  60: PRECALL              
  64: CALL                 
  74: POP_TOP              
  76: LOAD_GLOBAL          NULL + isinstance
  88: LOAD_FAST            args
  90: LOAD_GLOBAL          tuple
 102: PRECALL              
 106: CALL                 
 116: POP_JUMP_FORWARD_IF_TRUE to 124
 118: LOAD_FAST            args
 120: BUILD_TUPLE          
 122: STORE_FAST           args
 124: LOAD_GLOBAL          NULL + tuple
 136: LOAD_CONST           <code object <genexpr> at 0x000002406945EE20, file "typing.py", line 1358>
 138: MAKE_FUNCTION        
 140: LOAD_FAST            args
 142: GET_ITER             
 144: PRECALL              
 148: CALL                 
 158: PRECALL              
 162: CALL                 
 172: LOAD_FAST            self
 174: STORE_ATTR           __args__
 184: LOAD_GLOBAL          NULL + _collect_parameters
 196: LOAD_FAST            args
 198: PRECALL              
 202: CALL                 
 212: LOAD_FAST            self
 214: STORE_ATTR           __parameters__
 224: LOAD_FAST            _paramspec_tvars
 226: LOAD_FAST            self
 228: STORE_ATTR           _paramspec_tvars
 238: LOAD_FAST            name
 240: POP_JUMP_FORWARD_IF_TRUE to 270
 242: LOAD_FAST            origin
 244: LOAD_ATTR            __module__
 254: LOAD_FAST            self
 256: STORE_ATTR           __module__
 266: LOAD_CONST           None
 268: RETURN_VALUE         
 270: LOAD_CONST           None
 272: RETURN_VALUE         
