# Disassembly for typing._type_repr
# From module file: typing

## co_consts:
('Return the repr() of an object, special-casing types (internal helper).\n\n    If obj is a type, we return a shorter version than the default\n    type.__repr__, based on the module and qualified name, which is\n    typically enough to uniquely identify a type.  For everything\n    else, we fall back on repr(obj).\n    ', 'builtins', '.', Ellipsis, '...')

## co_names:
('isinstance', 'types', 'GenericAlias', 'repr', 'type', '__module__', '__qualname__', 'FunctionType', '__name__')

## bytecode:

   0: RESUME               
   2: LOAD_GLOBAL          NULL + isinstance
  14: LOAD_FAST            obj
  16: LOAD_GLOBAL          types
  28: LOAD_ATTR            GenericAlias
  38: PRECALL              
  42: CALL                 
  52: POP_JUMP_FORWARD_IF_FALSE to 84
  54: LOAD_GLOBAL          NULL + repr
  66: LOAD_FAST            obj
  68: PRECALL              
  72: CALL                 
  82: RETURN_VALUE         
  84: LOAD_GLOBAL          NULL + isinstance
  96: LOAD_FAST            obj
  98: LOAD_GLOBAL          type
 110: PRECALL              
 114: CALL                 
 124: POP_JUMP_FORWARD_IF_FALSE to 196
 126: LOAD_FAST            obj
 128: LOAD_ATTR            __module__
 138: LOAD_CONST           'builtins'
 140: COMPARE_OP           ==
 146: POP_JUMP_FORWARD_IF_FALSE to 162
 148: LOAD_FAST            obj
 150: LOAD_ATTR            __qualname__
 160: RETURN_VALUE         
 162: LOAD_FAST            obj
 164: LOAD_ATTR            __module__
 174: FORMAT_VALUE         
 176: LOAD_CONST           '.'
 178: LOAD_FAST            obj
 180: LOAD_ATTR            __qualname__
 190: FORMAT_VALUE         
 192: BUILD_STRING         
 194: RETURN_VALUE         
 196: LOAD_FAST            obj
 198: LOAD_CONST           Ellipsis
 200: IS_OP                
 202: POP_JUMP_FORWARD_IF_FALSE to 208
 204: LOAD_CONST           '...'
 206: RETURN_VALUE         
 208: LOAD_GLOBAL          NULL + isinstance
 220: LOAD_FAST            obj
 222: LOAD_GLOBAL          types
 234: LOAD_ATTR            FunctionType
 244: PRECALL              
 248: CALL                 
 258: POP_JUMP_FORWARD_IF_FALSE to 274
 260: LOAD_FAST            obj
 262: LOAD_ATTR            __name__
 272: RETURN_VALUE         
 274: LOAD_GLOBAL          NULL + repr
 286: LOAD_FAST            obj
 288: PRECALL              
 292: CALL                 
 302: RETURN_VALUE         
