# Disassembly for typing._AnyMeta
# From module file: typing

## co_consts:
('_AnyMeta', <code object __instancecheck__ at 0x00000240693D3210, file "typing.py", line 492>, <code object __repr__ at 0x000002406941AE50, file "typing.py", line 497>)

## co_names:
('__name__', '__module__', '__qualname__', '__instancecheck__', '__repr__', '__classcell__')

## bytecode:

   0: MAKE_CELL            __class__
   2: RESUME               
   4: LOAD_NAME            __name__
   6: STORE_NAME           __module__
   8: LOAD_CONST           '_AnyMeta'
  10: STORE_NAME           __qualname__
  12: LOAD_CLOSURE         __class__
  14: BUILD_TUPLE          
  16: LOAD_CONST           <code object __instancecheck__ at 0x00000240693D3210, file "typing.py", line 492>
  18: MAKE_FUNCTION        closure
  20: STORE_NAME           __instancecheck__
  22: LOAD_CLOSURE         __class__
  24: BUILD_TUPLE          
  26: LOAD_CONST           <code object __repr__ at 0x000002406941AE50, file "typing.py", line 497>
  28: MAKE_FUNCTION        closure
  30: STORE_NAME           __repr__
  32: LOAD_CLOSURE         __class__
  34: COPY                 
  36: STORE_NAME           __classcell__
  38: RETURN_VALUE         
