# Disassembly for typing._should_unflatten_callable_args
# From module file: typing

## co_consts:
("Internal helper for munging collections.abc.Callable's __args__.\n\n    The canonical representation for a Callable's __args__ flattens the\n    argument types, see https://github.com/python/cpython/issues/86361.\n\n    For example::\n\n        assert collections.abc.Callable[[int, int], str].__args__ == (int, int, str)\n        assert collections.abc.Callable[ParamSpec, str].__args__ == (ParamSpec, str)\n\n    As a result, if we need to reconstruct the Callable from its __args__,\n    we need to unflatten it.\n    ", 2, 0)

## co_names:
('__origin__', 'collections', 'abc', 'Callable', 'len', '_is_param_expr')

## bytecode:

   0: RESUME               
   2: LOAD_FAST            typ
   4: LOAD_ATTR            __origin__
  14: LOAD_GLOBAL          collections
  26: LOAD_ATTR            abc
  36: LOAD_ATTR            Callable
  46: IS_OP                
  48: JUMP_IF_FALSE_OR_POP to 130
  50: LOAD_GLOBAL          NULL + len
  62: LOAD_FAST            args
  64: PRECALL              
  68: CALL                 
  78: LOAD_CONST           2
  80: COMPARE_OP           ==
  86: JUMP_IF_FALSE_OR_POP to 128
  88: LOAD_GLOBAL          NULL + _is_param_expr
 100: LOAD_FAST            args
 102: LOAD_CONST           0
 104: BINARY_SUBSCR        
 114: PRECALL              
 118: CALL                 
 128: UNARY_NOT            
 130: RETURN_VALUE         
