# Disassembly for typing._TupleType.__getitem__
# From module file: typing

## co_consts:
(None, 2, -1, Ellipsis, 'Tuple[t, ...]: t must be a type.', <code object <genexpr> at 0x0000024069CF4030, file "typing.py", line 1653>, 'Tuple[t0, t1, ...]: each t must be a type.', <code object <genexpr> at 0x0000024069CF4120, file "typing.py", line 1656>)

## co_names:
('isinstance', 'tuple', 'len', 'copy_with', '_TypingEllipsis')

## bytecode:

   0: MAKE_CELL            msg
   2: RESUME               
   4: LOAD_GLOBAL          NULL + isinstance
  16: LOAD_FAST            params
  18: LOAD_GLOBAL          tuple
  30: PRECALL              
  34: CALL                 
  44: POP_JUMP_FORWARD_IF_TRUE to 52
  46: LOAD_FAST            params
  48: BUILD_TUPLE          
  50: STORE_FAST           params
  52: LOAD_GLOBAL          NULL + len
  64: LOAD_FAST            params
  66: PRECALL              
  70: CALL                 
  80: LOAD_CONST           2
  82: COMPARE_OP           >=
  88: POP_JUMP_FORWARD_IF_FALSE to 246
  90: LOAD_FAST            params
  92: LOAD_CONST           -1
  94: BINARY_SUBSCR        
 104: LOAD_CONST           Ellipsis
 106: IS_OP                
 108: POP_JUMP_FORWARD_IF_FALSE to 246
 110: LOAD_CONST           'Tuple[t, ...]: t must be a type.'
 112: STORE_DEREF          msg
 114: LOAD_GLOBAL          NULL + tuple
 126: LOAD_CLOSURE         msg
 128: BUILD_TUPLE          
 130: LOAD_CONST           <code object <genexpr> at 0x0000024069CF4030, file "typing.py", line 1653>
 132: MAKE_FUNCTION        closure
 134: LOAD_FAST            params
 136: LOAD_CONST           None
 138: LOAD_CONST           -1
 140: BUILD_SLICE          
 142: BINARY_SUBSCR        
 152: GET_ITER             
 154: PRECALL              
 158: CALL                 
 168: PRECALL              
 172: CALL                 
 182: STORE_FAST           params
 184: LOAD_FAST            self
 186: LOAD_METHOD          copy_with
 208: BUILD_LIST           
 210: LOAD_FAST            params
 212: LIST_EXTEND          
 214: LOAD_GLOBAL          _TypingEllipsis
 226: LIST_APPEND          
 228: LIST_TO_TUPLE        
 230: PRECALL              
 234: CALL                 
 244: RETURN_VALUE         
 246: LOAD_CONST           'Tuple[t0, t1, ...]: each t must be a type.'
 248: STORE_DEREF          msg
 250: LOAD_GLOBAL          NULL + tuple
 262: LOAD_CLOSURE         msg
 264: BUILD_TUPLE          
 266: LOAD_CONST           <code object <genexpr> at 0x0000024069CF4120, file "typing.py", line 1656>
 268: MAKE_FUNCTION        closure
 270: LOAD_FAST            params
 272: GET_ITER             
 274: PRECALL              
 278: CALL                 
 288: PRECALL              
 292: CALL                 
 302: STORE_FAST           params
 304: LOAD_FAST            self
 306: LOAD_METHOD          copy_with
 328: LOAD_FAST            params
 330: PRECALL              
 334: CALL                 
 344: RETURN_VALUE         
