# Disassembly for typing.dataclass_transform.decorator
# From module file: typing

## co_consts:
(None, ('eq_default', 'order_default', 'kw_only_default', 'field_specifiers', 'kwargs'))

## co_names:
('__dataclass_transform__',)

## bytecode:

   0: COPY_FREE_VARS       
   2: RESUME               
   4: LOAD_DEREF           eq_default
   6: LOAD_DEREF           order_default
   8: LOAD_DEREF           kw_only_default
  10: LOAD_DEREF           field_specifiers
  12: LOAD_DEREF           kwargs
  14: LOAD_CONST           ('eq_default', 'order_default', 'kw_only_default', 'field_specifiers', 'kwargs')
  16: BUILD_CONST_KEY_MAP  
  18: LOAD_FAST            cls_or_fn
  20: STORE_ATTR           __dataclass_transform__
  30: LOAD_FAST            cls_or_fn
  32: RETURN_VALUE         
