# Disassembly for typing.overload
# From module file: typing

## co_consts:
('Decorator for overloaded functions/methods.\n\n    In a stub file, place two or more stub definitions for the same\n    function in a row, each decorated with @overload.\n\n    For example::\n\n        @overload\n        def utf8(value: None) -> None: ...\n        @overload\n        def utf8(value: bytes) -> bytes: ...\n        @overload\n        def utf8(value: str) -> bytes: ...\n\n    In a non-stub file (i.e. a regular .py file), do the same but\n    follow it with an implementation.  The implementation should *not*\n    be decorated with @overload::\n\n        @overload\n        def utf8(value: None) -> None: ...\n        @overload\n        def utf8(value: bytes) -> bytes: ...\n        @overload\n        def utf8(value: str) -> bytes: ...\n        def utf8(value):\n            ...  # implementation goes here\n\n    The overloads for a function can be retrieved at runtime using the\n    get_overloads() function.\n    ', '__func__')

## co_names:
('getattr', '_overload_registry', '__module__', '__qualname__', '__code__', 'co_firstlineno', 'AttributeError', '_overload_dummy')

## bytecode:

   0: RESUME               
   2: LOAD_GLOBAL          NULL + getattr
  14: LOAD_FAST            func
  16: LOAD_CONST           '__func__'
  18: LOAD_FAST            func
  20: PRECALL              
  24: CALL                 
  34: STORE_FAST           f
  36: NOP                  
  38: LOAD_FAST            func
  40: LOAD_GLOBAL          _overload_registry
  52: LOAD_FAST            f
  54: LOAD_ATTR            __module__
  64: BINARY_SUBSCR        
  74: LOAD_FAST            f
  76: LOAD_ATTR            __qualname__
  86: BINARY_SUBSCR        
  96: LOAD_FAST            f
  98: LOAD_ATTR            __code__
 108: LOAD_ATTR            co_firstlineno
 118: STORE_SUBSCR         
 122: JUMP_FORWARD         to 156
 124: PUSH_EXC_INFO        
 126: LOAD_GLOBAL          AttributeError
 138: CHECK_EXC_MATCH      
 140: POP_JUMP_FORWARD_IF_FALSE to 148
 142: POP_TOP              
 144: POP_EXCEPT           
 146: JUMP_FORWARD         to 156
 148: RERAISE              
 150: COPY                 
 152: POP_EXCEPT           
 154: RERAISE              
 156: LOAD_GLOBAL          _overload_dummy
 168: RETURN_VALUE         
