# Disassembly for typing.NewType.__mro_entries__
# From module file: typing

## co_consts:
(None, <code object Dummy at 0x0000024069CF1C30, file "typing.py", line 3170>, 'Dummy')

## co_names:
('__name__',)

## bytecode:

   0: MAKE_CELL            superclass_name
   2: RESUME               
   4: LOAD_FAST            self
   6: LOAD_ATTR            __name__
  16: STORE_DEREF          superclass_name
  18: PUSH_NULL            
  20: LOAD_BUILD_CLASS     
  22: LOAD_CLOSURE         superclass_name
  24: BUILD_TUPLE          
  26: LOAD_CONST           <code object Dummy at 0x0000024069CF1C30, file "typing.py", line 3170>
  28: MAKE_FUNCTION        closure
  30: LOAD_CONST           'Dummy'
  32: PRECALL              
  36: CALL                 
  46: STORE_FAST           Dummy
  48: LOAD_FAST            Dummy
  50: BUILD_TUPLE          
  52: RETURN_VALUE         
