# Disassembly for typing._PickleUsingNameMixin
# From module file: typing

## co_consts:
('_PickleUsingNameMixin', 'Mixin enabling pickling based on self.__name__.', <code object __reduce__ at 0x0000024069496CE0, file "typing.py", line 933>, None)

## co_names:
('__name__', '__module__', '__qualname__', '__doc__', '__reduce__')

## bytecode:

   0: RESUME               
   2: LOAD_NAME            __name__
   4: STORE_NAME           __module__
   6: LOAD_CONST           '_PickleUsingNameMixin'
   8: STORE_NAME           __qualname__
  10: LOAD_CONST           'Mixin enabling pickling based on self.__name__.'
  12: STORE_NAME           __doc__
  14: LOAD_CONST           <code object __reduce__ at 0x0000024069496CE0, file "typing.py", line 933>
  16: MAKE_FUNCTION        
  18: STORE_NAME           __reduce__
  20: LOAD_CONST           None
  22: RETURN_VALUE         
