# Disassembly for typing._eval_type.<genexpr>
# From module file: typing

## co_consts:
(None,)

## co_names:
('_eval_type',)

## bytecode:

   0: COPY_FREE_VARS       
   2: RETURN_GENERATOR     
   4: POP_TOP              
   6: RESUME               
   8: LOAD_FAST            .0
  10: FOR_ITER             to 56
  12: STORE_FAST           a
  14: LOAD_GLOBAL          NULL + _eval_type
  26: LOAD_FAST            a
  28: LOAD_DEREF           globalns
  30: LOAD_DEREF           localns
  32: LOAD_DEREF           recursive_guard
  34: PRECALL              
  38: CALL                 
  48: YIELD_VALUE          
  50: RESUME               
  52: POP_TOP              
  54: JUMP_BACKWARD        to 10
  56: LOAD_CONST           None
  58: RETURN_VALUE         
