# Disassembly for typing._ConcatenateGenericAlias.copy_with
# From module file: typing

## co_consts:
(None, -1)

## co_names:
('isinstance', 'list', 'tuple', '_ConcatenateGenericAlias', '__args__', 'super', 'copy_with')

## bytecode:

   0: COPY_FREE_VARS       
   2: RESUME               
   4: LOAD_GLOBAL          NULL + isinstance
  16: LOAD_FAST            params
  18: LOAD_CONST           -1
  20: BINARY_SUBSCR        
  30: LOAD_GLOBAL          list
  42: LOAD_GLOBAL          tuple
  54: BUILD_TUPLE          
  56: PRECALL              
  60: CALL                 
  70: POP_JUMP_FORWARD_IF_FALSE to 114
  72: BUILD_LIST           
  74: LOAD_FAST            params
  76: LOAD_CONST           None
  78: LOAD_CONST           -1
  80: BUILD_SLICE          
  82: BINARY_SUBSCR        
  92: LIST_EXTEND          
  94: LOAD_FAST            params
  96: LOAD_CONST           -1
  98: BINARY_SUBSCR        
 108: LIST_EXTEND          
 110: LIST_TO_TUPLE        
 112: RETURN_VALUE         
 114: LOAD_GLOBAL          NULL + isinstance
 126: LOAD_FAST            params
 128: LOAD_CONST           -1
 130: BINARY_SUBSCR        
 140: LOAD_GLOBAL          _ConcatenateGenericAlias
 152: PRECALL              
 156: CALL                 
 166: POP_JUMP_FORWARD_IF_FALSE to 220
 168: BUILD_LIST           
 170: LOAD_FAST            params
 172: LOAD_CONST           None
 174: LOAD_CONST           -1
 176: BUILD_SLICE          
 178: BINARY_SUBSCR        
 188: LIST_EXTEND          
 190: LOAD_FAST            params
 192: LOAD_CONST           -1
 194: BINARY_SUBSCR        
 204: LOAD_ATTR            __args__
 214: LIST_EXTEND          
 216: LIST_TO_TUPLE        
 218: STORE_FAST           params
 220: LOAD_GLOBAL          NULL + super
 232: PRECALL              
 236: CALL                 
 246: LOAD_METHOD          copy_with
 268: LOAD_FAST            params
 270: PRECALL              
 274: CALL                 
 284: RETURN_VALUE         
