# Disassembly for typing._LiteralGenericAlias
# From module file: typing

## co_consts:
('_LiteralGenericAlias', <code object __eq__ at 0x00000240691EABB0, file "typing.py", line 1699>, <code object __hash__ at 0x00000240694198F0, file "typing.py", line 1705>, None)

## co_names:
('__name__', '__module__', '__qualname__', '__eq__', '__hash__')

## bytecode:

   0: RESUME               
   2: LOAD_NAME            __name__
   4: STORE_NAME           __module__
   6: LOAD_CONST           '_LiteralGenericAlias'
   8: STORE_NAME           __qualname__
  10: LOAD_CONST           <code object __eq__ at 0x00000240691EABB0, file "typing.py", line 1699>
  12: MAKE_FUNCTION        
  14: STORE_NAME           __eq__
  16: LOAD_CONST           <code object __hash__ at 0x00000240694198F0, file "typing.py", line 1705>
  18: MAKE_FUNCTION        
  20: STORE_NAME           __hash__
  22: LOAD_CONST           None
  24: RETURN_VALUE         
