# Disassembly for typing._no_init_or_replace_init
# From module file: typing

## co_consts:
(None, 'Protocols cannot be instantiated', '__init__')

## co_names:
('type', '_is_protocol', 'TypeError', '__init__', '_no_init_or_replace_init', '__mro__', '__dict__', 'get', 'object')

## bytecode:

   0: RESUME               
   2: LOAD_GLOBAL          NULL + type
  14: LOAD_FAST            self
  16: PRECALL              
  20: CALL                 
  30: STORE_FAST           cls
  32: LOAD_FAST            cls
  34: LOAD_ATTR            _is_protocol
  44: POP_JUMP_FORWARD_IF_FALSE to 76
  46: LOAD_GLOBAL          NULL + TypeError
  58: LOAD_CONST           'Protocols cannot be instantiated'
  60: PRECALL              
  64: CALL                 
  74: RAISE_VARARGS        
  76: LOAD_FAST            cls
  78: LOAD_ATTR            __init__
  88: LOAD_GLOBAL          _no_init_or_replace_init
 100: IS_OP                
 102: POP_JUMP_FORWARD_IF_FALSE to 108
 104: LOAD_CONST           None
 106: RETURN_VALUE         
 108: LOAD_FAST            cls
 110: LOAD_ATTR            __mro__
 120: GET_ITER             
 122: FOR_ITER             to 228
 124: STORE_FAST           base
 126: LOAD_FAST            base
 128: LOAD_ATTR            __dict__
 138: LOAD_METHOD          get
 160: LOAD_CONST           '__init__'
 162: LOAD_GLOBAL          _no_init_or_replace_init
 174: PRECALL              
 178: CALL                 
 188: STORE_FAST           init
 190: LOAD_FAST            init
 192: LOAD_GLOBAL          _no_init_or_replace_init
 204: IS_OP                
 206: POP_JUMP_FORWARD_IF_FALSE to 226
 208: LOAD_FAST            init
 210: LOAD_FAST            cls
 212: STORE_ATTR           __init__
 222: POP_TOP              
 224: JUMP_FORWARD         to 262
 226: JUMP_BACKWARD        to 122
 228: LOAD_GLOBAL          object
 240: LOAD_ATTR            __init__
 250: LOAD_FAST            cls
 252: STORE_ATTR           __init__
 262: PUSH_NULL            
 264: LOAD_FAST            cls
 266: LOAD_ATTR            __init__
 276: LOAD_FAST            self
 278: BUILD_LIST           
 280: LOAD_FAST            args
 282: LIST_EXTEND          
 284: LIST_TO_TUPLE        
 286: BUILD_MAP            
 288: LOAD_FAST            kwargs
 290: DICT_MERGE           
 292: CALL_FUNCTION_EX     
 294: POP_TOP              
 296: LOAD_CONST           None
 298: RETURN_VALUE         
