# Disassembly for typing.ForwardRef._evaluate
# From module file: typing

## co_consts:
(None, '__dict__', 'Forward references must evaluate to types.', ('is_argument', 'allow_special_forms'), True)

## co_names:
('__forward_arg__', '__forward_evaluated__', '__forward_module__', 'getattr', 'sys', 'modules', 'get', '_type_check', 'eval', '__forward_code__', '__forward_is_argument__', '__forward_is_class__', '_eval_type', '__forward_value__')

## bytecode:

   0: RESUME               
   2: LOAD_FAST            self
   4: LOAD_ATTR            __forward_arg__
  14: LOAD_FAST            recursive_guard
  16: CONTAINS_OP          
  18: POP_JUMP_FORWARD_IF_FALSE to 24
  20: LOAD_FAST            self
  22: RETURN_VALUE         
  24: LOAD_FAST            self
  26: LOAD_ATTR            __forward_evaluated__
  36: POP_JUMP_FORWARD_IF_FALSE to 46
  38: LOAD_FAST            localns
  40: LOAD_FAST            globalns
  42: IS_OP                
  44: POP_JUMP_FORWARD_IF_FALSE to 376
  46: LOAD_FAST            globalns
  48: POP_JUMP_FORWARD_IF_NOT_NONE to 64
  50: LOAD_FAST            localns
  52: POP_JUMP_FORWARD_IF_NOT_NONE to 64
  54: BUILD_MAP            
  56: COPY                 
  58: STORE_FAST           globalns
  60: STORE_FAST           localns
  62: JUMP_FORWARD         to 82
  64: LOAD_FAST            globalns
  66: POP_JUMP_FORWARD_IF_NOT_NONE to 74
  68: LOAD_FAST            localns
  70: STORE_FAST           globalns
  72: JUMP_FORWARD         to 82
  74: LOAD_FAST            localns
  76: POP_JUMP_FORWARD_IF_NOT_NONE to 82
  78: LOAD_FAST            globalns
  80: STORE_FAST           localns
  82: LOAD_FAST            self
  84: LOAD_ATTR            __forward_module__
  94: POP_JUMP_FORWARD_IF_NONE to 200
  96: LOAD_GLOBAL          NULL + getattr
 108: LOAD_GLOBAL          sys
 120: LOAD_ATTR            modules
 130: LOAD_METHOD          get
 152: LOAD_FAST            self
 154: LOAD_ATTR            __forward_module__
 164: LOAD_CONST           None
 166: PRECALL              
 170: CALL                 
 180: LOAD_CONST           '__dict__'
 182: LOAD_FAST            globalns
 184: PRECALL              
 188: CALL                 
 198: STORE_FAST           globalns
 200: LOAD_GLOBAL          NULL + _type_check
 212: LOAD_GLOBAL          NULL + eval
 224: LOAD_FAST            self
 226: LOAD_ATTR            __forward_code__
 236: LOAD_FAST            globalns
 238: LOAD_FAST            localns
 240: PRECALL              
 244: CALL                 
 254: LOAD_CONST           'Forward references must evaluate to types.'
 256: LOAD_FAST            self
 258: LOAD_ATTR            __forward_is_argument__
 268: LOAD_FAST            self
 270: LOAD_ATTR            __forward_is_class__
 280: KW_NAMES             
 282: PRECALL              
 286: CALL                 
 296: STORE_FAST           type_
 298: LOAD_GLOBAL          NULL + _eval_type
 310: LOAD_FAST            type_
 312: LOAD_FAST            globalns
 314: LOAD_FAST            localns
 316: LOAD_FAST            recursive_guard
 318: LOAD_FAST            self
 320: LOAD_ATTR            __forward_arg__
 330: BUILD_SET            
 332: BINARY_OP            |
 336: PRECALL              
 340: CALL                 
 350: LOAD_FAST            self
 352: STORE_ATTR           __forward_value__
 362: LOAD_CONST           True
 364: LOAD_FAST            self
 366: STORE_ATTR           __forward_evaluated__
 376: LOAD_FAST            self
 378: LOAD_ATTR            __forward_value__
 388: RETURN_VALUE         
