# Disassembly for typing._Final
# From module file: typing

## co_consts:
('_Final', 'Mixin to prohibit subclassing.', ('__weakref__',), <code object __init_subclass__ at 0x000002406945EA60, file "typing.py", line 405>, None)

## co_names:
('__name__', '__module__', '__qualname__', '__doc__', '__slots__', '__init_subclass__')

## bytecode:

   0: RESUME               
   2: LOAD_NAME            __name__
   4: STORE_NAME           __module__
   6: LOAD_CONST           '_Final'
   8: STORE_NAME           __qualname__
  10: LOAD_CONST           'Mixin to prohibit subclassing.'
  12: STORE_NAME           __doc__
  14: LOAD_CONST           ('__weakref__',)
  16: STORE_NAME           __slots__
  18: LOAD_CONST           <code object __init_subclass__ at 0x000002406945EA60, file "typing.py", line 405>
  20: MAKE_FUNCTION        
  22: STORE_NAME           __init_subclass__
  24: LOAD_CONST           None
  26: RETURN_VALUE         
