# Disassembly for typing._ProtocolMeta.__instancecheck__.<genexpr>
# From module file: typing

## co_consts:
(None,)

## co_names:
('hasattr', 'callable', 'getattr')

## bytecode:

   0: COPY_FREE_VARS       
   2: RETURN_GENERATOR     
   4: POP_TOP              
   6: RESUME               
   8: LOAD_FAST            .0
  10: FOR_ITER             to 150
  12: STORE_FAST           attr
  14: LOAD_GLOBAL          NULL + hasattr
  26: LOAD_DEREF           instance
  28: LOAD_FAST            attr
  30: PRECALL              
  34: CALL                 
  44: JUMP_IF_FALSE_OR_POP to 142
  46: LOAD_GLOBAL          NULL + callable
  58: LOAD_GLOBAL          NULL + getattr
  70: LOAD_DEREF           cls
  72: LOAD_FAST            attr
  74: LOAD_CONST           None
  76: PRECALL              
  80: CALL                 
  90: PRECALL              
  94: CALL                 
 104: UNARY_NOT            
 106: JUMP_IF_TRUE_OR_POP  to 142
 108: LOAD_GLOBAL          NULL + getattr
 120: LOAD_DEREF           instance
 122: LOAD_FAST            attr
 124: PRECALL              
 128: CALL                 
 138: LOAD_CONST           None
 140: IS_OP                
 142: YIELD_VALUE          
 144: RESUME               
 146: POP_TOP              
 148: JUMP_BACKWARD        to 10
 150: LOAD_CONST           None
 152: RETURN_VALUE         
