# Disassembly for typing._SpecialGenericAlias.__init__
# From module file: typing

## co_consts:
(None, ('inst', 'name'), 'builtins', 'A generic version of ', '.')

## co_names:
('__name__', 'super', '__init__', '_nparams', '__module__', '__qualname__', '__doc__')

## bytecode:

   0: COPY_FREE_VARS       
   2: RESUME               
   4: LOAD_FAST            name
   6: POP_JUMP_FORWARD_IF_NOT_NONE to 22
   8: LOAD_FAST            origin
  10: LOAD_ATTR            __name__
  20: STORE_FAST           name
  22: LOAD_GLOBAL          NULL + super
  34: PRECALL              
  38: CALL                 
  48: LOAD_METHOD          __init__
  70: LOAD_FAST            origin
  72: LOAD_FAST            inst
  74: LOAD_FAST            name
  76: KW_NAMES             
  78: PRECALL              
  82: CALL                 
  92: POP_TOP              
  94: LOAD_FAST            nparams
  96: LOAD_FAST            self
  98: STORE_ATTR           _nparams
 108: LOAD_FAST            origin
 110: LOAD_ATTR            __module__
 120: LOAD_CONST           'builtins'
 122: COMPARE_OP           ==
 128: POP_JUMP_FORWARD_IF_FALSE to 166
 130: LOAD_CONST           'A generic version of '
 132: LOAD_FAST            origin
 134: LOAD_ATTR            __qualname__
 144: FORMAT_VALUE         
 146: LOAD_CONST           '.'
 148: BUILD_STRING         
 150: LOAD_FAST            self
 152: STORE_ATTR           __doc__
 162: LOAD_CONST           None
 164: RETURN_VALUE         
 166: LOAD_CONST           'A generic version of '
 168: LOAD_FAST            origin
 170: LOAD_ATTR            __module__
 180: FORMAT_VALUE         
 182: LOAD_CONST           '.'
 184: LOAD_FAST            origin
 186: LOAD_ATTR            __qualname__
 196: FORMAT_VALUE         
 198: LOAD_CONST           '.'
 200: BUILD_STRING         
 202: LOAD_FAST            self
 204: STORE_ATTR           __doc__
 214: LOAD_CONST           None
 216: RETURN_VALUE         
