# Disassembly for typing.Any
# From module file: typing

## co_consts:
('Any', 'Special type indicating an unconstrained type.\n\n    - Any is compatible with every type.\n    - Any assumed to have all methods.\n    - All values assumed to be instances of Any.\n\n    Note that all the above statements are true from the point of view of\n    static type checkers. At runtime, Any should not be used with instance\n    checks.\n    ', <code object __new__ at 0x00000240693D23D0, file "typing.py", line 515>)

## co_names:
('__name__', '__module__', '__qualname__', '__doc__', '__new__', '__classcell__')

## bytecode:

   0: MAKE_CELL            __class__
   2: RESUME               
   4: LOAD_NAME            __name__
   6: STORE_NAME           __module__
   8: LOAD_CONST           'Any'
  10: STORE_NAME           __qualname__
  12: LOAD_CONST           'Special type indicating an unconstrained type.\n\n    - Any is compatible with every type.\n    - Any assumed to have all methods.\n    - All values assumed to be instances of Any.\n\n    Note that all the above statements are true from the point of view of\n    static type checkers. At runtime, Any should not be used with instance\n    checks.\n    '
  14: STORE_NAME           __doc__
  16: LOAD_CLOSURE         __class__
  18: BUILD_TUPLE          
  20: LOAD_CONST           <code object __new__ at 0x00000240693D23D0, file "typing.py", line 515>
  22: MAKE_FUNCTION        closure
  24: STORE_NAME           __new__
  26: LOAD_CLOSURE         __class__
  28: COPY                 
  30: STORE_NAME           __classcell__
  32: RETURN_VALUE         
