# Disassembly for typing.ForwardRef.__repr__
# From module file: typing

## co_consts:
(None, '', ', module=', 'ForwardRef(', ')')

## co_names:
('__forward_module__', '__forward_arg__')

## bytecode:

   0: RESUME               
   2: LOAD_FAST            self
   4: LOAD_ATTR            __forward_module__
  14: POP_JUMP_FORWARD_IF_NOT_NONE to 22
  16: LOAD_CONST           ''
  18: STORE_FAST           module_repr
  20: JUMP_FORWARD         to 42
  22: LOAD_CONST           ', module='
  24: LOAD_FAST            self
  26: LOAD_ATTR            __forward_module__
  36: FORMAT_VALUE         repr
  38: BUILD_STRING         
  40: STORE_FAST           module_repr
  42: LOAD_CONST           'ForwardRef('
  44: LOAD_FAST            self
  46: LOAD_ATTR            __forward_arg__
  56: FORMAT_VALUE         repr
  58: LOAD_FAST            module_repr
  60: FORMAT_VALUE         
  62: LOAD_CONST           ')'
  64: BUILD_STRING         
  66: RETURN_VALUE         
