# Disassembly for typing._AnyMeta.__instancecheck__
# From module file: typing

## co_consts:
(None, 'typing.Any cannot be used with isinstance()')

## co_names:
('Any', 'TypeError', 'super', '__instancecheck__')

## bytecode:

   0: COPY_FREE_VARS       
   2: RESUME               
   4: LOAD_FAST            self
   6: LOAD_GLOBAL          Any
  18: IS_OP                
  20: POP_JUMP_FORWARD_IF_FALSE to 52
  22: LOAD_GLOBAL          NULL + TypeError
  34: LOAD_CONST           'typing.Any cannot be used with isinstance()'
  36: PRECALL              
  40: CALL                 
  50: RAISE_VARARGS        
  52: LOAD_GLOBAL          NULL + super
  64: PRECALL              
  68: CALL                 
  78: LOAD_METHOD          __instancecheck__
 100: LOAD_FAST            obj
 102: PRECALL              
 106: CALL                 
 116: RETURN_VALUE         
