# Disassembly for typing.Required
# From module file: typing

## co_consts:
("Special typing construct to mark a TypedDict key as required.\n\n    This is mainly useful for total=False TypedDicts.\n\n    For example::\n\n        class Movie(TypedDict, total=False):\n            title: Required[str]\n            year: int\n\n        m = Movie(\n            title='The Matrix',  # typechecker error if key is omitted\n            year=1999,\n        )\n\n    There is no runtime checking that a required key is actually provided\n    when instantiating a related TypedDict.\n    ", ' accepts only a single type.')

## co_names:
('_type_check', '_name', '_GenericAlias')

## bytecode:

   0: RESUME               
   2: LOAD_GLOBAL          NULL + _type_check
  14: LOAD_FAST            parameters
  16: LOAD_FAST            self
  18: LOAD_ATTR            _name
  28: FORMAT_VALUE         
  30: LOAD_CONST           ' accepts only a single type.'
  32: BUILD_STRING         
  34: PRECALL              
  38: CALL                 
  48: STORE_FAST           item
  50: LOAD_GLOBAL          NULL + _GenericAlias
  62: LOAD_FAST            self
  64: LOAD_FAST            item
  66: BUILD_TUPLE          
  68: PRECALL              
  72: CALL                 
  82: RETURN_VALUE         
