# Disassembly for typing.get_type_hints.<dictcomp>
# From module file: typing

## co_consts:
()

## co_names:
('_strip_annotations',)

## bytecode:

   0: RESUME               
   2: BUILD_MAP            
   4: LOAD_FAST            .0
   6: FOR_ITER             to 50
   8: UNPACK_SEQUENCE      
  12: STORE_FAST           k
  14: STORE_FAST           t
  16: LOAD_FAST            k
  18: LOAD_GLOBAL          NULL + _strip_annotations
  30: LOAD_FAST            t
  32: PRECALL              
  36: CALL                 
  46: MAP_ADD              
  48: JUMP_BACKWARD        to 6
  50: RETURN_VALUE         
