# Disassembly for typing.Literal
# From module file: typing

## co_consts:
("Special typing form to define literal types (a.k.a. value types).\n\n    This form can be used to indicate to type checkers that the corresponding\n    variable or function parameter has a value equivalent to the provided\n    literal (or one of several literals)::\n\n        def validate_simple(data: Any) -> Literal[True]:  # always returns True\n            ...\n\n        MODE = Literal['r', 'rb', 'w', 'wb']\n        def open_helper(file: str, mode: MODE) -> str:\n            ...\n\n        open_helper('/some/path', 'r')  # Passes type check\n        open_helper('/other/path', 'typo')  # Error in type checker\n\n    Literal[...] cannot be subclassed. At runtime, an arbitrary value\n    is allowed as type argument to Literal[...], but type checkers may\n    impose restrictions.\n    ", <code object <genexpr> at 0x0000024069466CD0, file "typing.py", line 736>)

## co_names:
('_flatten_literal_params', 'tuple', '_deduplicate', 'list', '_value_and_type_iter', 'TypeError', '_LiteralGenericAlias')

## bytecode:

   0: RESUME               
   2: LOAD_GLOBAL          NULL + _flatten_literal_params
  14: LOAD_FAST            parameters
  16: PRECALL              
  20: CALL                 
  30: STORE_FAST           parameters
  32: NOP                  
  34: LOAD_GLOBAL          NULL + tuple
  46: LOAD_CONST           <code object <genexpr> at 0x0000024069466CD0, file "typing.py", line 736>
  48: MAKE_FUNCTION        
  50: LOAD_GLOBAL          NULL + _deduplicate
  62: LOAD_GLOBAL          NULL + list
  74: LOAD_GLOBAL          NULL + _value_and_type_iter
  86: LOAD_FAST            parameters
  88: PRECALL              
  92: CALL                 
 102: PRECALL              
 106: CALL                 
 116: PRECALL              
 120: CALL                 
 130: GET_ITER             
 132: PRECALL              
 136: CALL                 
 146: PRECALL              
 150: CALL                 
 160: STORE_FAST           parameters
 162: JUMP_FORWARD         to 196
 164: PUSH_EXC_INFO        
 166: LOAD_GLOBAL          TypeError
 178: CHECK_EXC_MATCH      
 180: POP_JUMP_FORWARD_IF_FALSE to 188
 182: POP_TOP              
 184: POP_EXCEPT           
 186: JUMP_FORWARD         to 196
 188: RERAISE              
 190: COPY                 
 192: POP_EXCEPT           
 194: RERAISE              
 196: LOAD_GLOBAL          NULL + _LiteralGenericAlias
 208: LOAD_FAST            self
 210: LOAD_FAST            parameters
 212: PRECALL              
 216: CALL                 
 226: RETURN_VALUE         
