# Disassembly for typing.NamedTuple
# From module file: typing

## co_consts:
("Typed version of namedtuple.\n\n    Usage::\n\n        class Employee(NamedTuple):\n            name: str\n            id: int\n\n    This is equivalent to::\n\n        Employee = collections.namedtuple('Employee', ['name', 'id'])\n\n    The resulting class has an extra __annotations__ attribute, giving a\n    dict that maps field names to types.  (The field names are also in\n    the _fields attribute, which is part of the namedtuple API.)\n    An alternative equivalent functional syntax is also accepted::\n\n        Employee = NamedTuple('Employee', [('name', str), ('id', int)])\n    ", None, 'Either list of fields or keywords can be provided to NamedTuple, not both', ('module',))

## co_names:
('items', 'TypeError', '_make_nmtuple', '_caller')

## bytecode:

   0: RESUME               
   2: LOAD_FAST            fields
   4: POP_JUMP_FORWARD_IF_NOT_NONE to 48
   6: LOAD_FAST            kwargs
   8: LOAD_METHOD          items
  30: PRECALL              
  34: CALL                 
  44: STORE_FAST           fields
  46: JUMP_FORWARD         to 82
  48: LOAD_FAST            kwargs
  50: POP_JUMP_FORWARD_IF_FALSE to 82
  52: LOAD_GLOBAL          NULL + TypeError
  64: LOAD_CONST           'Either list of fields or keywords can be provided to NamedTuple, not both'
  66: PRECALL              
  70: CALL                 
  80: RAISE_VARARGS        
  82: LOAD_GLOBAL          NULL + _make_nmtuple
  94: LOAD_FAST            typename
  96: LOAD_FAST            fields
  98: LOAD_GLOBAL          NULL + _caller
 110: PRECALL              
 114: CALL                 
 124: KW_NAMES             
 126: PRECALL              
 130: CALL                 
 140: RETURN_VALUE         
