# Disassembly for typing._SpecialGenericAlias
# From module file: typing

## co_consts:
('_SpecialGenericAlias', True, None, ('inst', 'name'), <code object __init__ at 0x00000240691F5550, file "typing.py", line 1553>, <code object __getitem__ at 0x00000240691EA730, file "typing.py", line 1563>, <code object copy_with at 0x00000240693EB030, file "typing.py", line 1572>, <code object __repr__ at 0x0000024069495F10, file "typing.py", line 1576>, <code object __subclasscheck__ at 0x000002406934FB40, file "typing.py", line 1579>, <code object __reduce__ at 0x0000024069495140, file "typing.py", line 1586>, <code object __or__ at 0x0000024069CF0730, file "typing.py", line 1589>, <code object __ror__ at 0x0000024069CF0810, file "typing.py", line 1592>)

## co_names:
('__name__', '__module__', '__qualname__', '__init__', '_tp_cache', '__getitem__', 'copy_with', '__repr__', '__subclasscheck__', '__reduce__', '__or__', '__ror__', '__classcell__')

## bytecode:

   0: MAKE_CELL            __class__
   2: RESUME               
   4: LOAD_NAME            __name__
   6: STORE_NAME           __module__
   8: LOAD_CONST           '_SpecialGenericAlias'
  10: STORE_NAME           __qualname__
  12: LOAD_CONST           True
  14: LOAD_CONST           None
  16: LOAD_CONST           ('inst', 'name')
  18: BUILD_CONST_KEY_MAP  
  20: LOAD_CLOSURE         __class__
  22: BUILD_TUPLE          
  24: LOAD_CONST           <code object __init__ at 0x00000240691F5550, file "typing.py", line 1553>
  26: MAKE_FUNCTION        kwdefaults, closure
  28: STORE_NAME           __init__
  30: LOAD_NAME            _tp_cache
  32: LOAD_CONST           <code object __getitem__ at 0x00000240691EA730, file "typing.py", line 1563>
  34: MAKE_FUNCTION        
  36: PRECALL              
  40: CALL                 
  50: STORE_NAME           __getitem__
  52: LOAD_CONST           <code object copy_with at 0x00000240693EB030, file "typing.py", line 1572>
  54: MAKE_FUNCTION        
  56: STORE_NAME           copy_with
  58: LOAD_CONST           <code object __repr__ at 0x0000024069495F10, file "typing.py", line 1576>
  60: MAKE_FUNCTION        
  62: STORE_NAME           __repr__
  64: LOAD_CLOSURE         __class__
  66: BUILD_TUPLE          
  68: LOAD_CONST           <code object __subclasscheck__ at 0x000002406934FB40, file "typing.py", line 1579>
  70: MAKE_FUNCTION        closure
  72: STORE_NAME           __subclasscheck__
  74: LOAD_CONST           <code object __reduce__ at 0x0000024069495140, file "typing.py", line 1586>
  76: MAKE_FUNCTION        
  78: STORE_NAME           __reduce__
  80: LOAD_CONST           <code object __or__ at 0x0000024069CF0730, file "typing.py", line 1589>
  82: MAKE_FUNCTION        
  84: STORE_NAME           __or__
  86: LOAD_CONST           <code object __ror__ at 0x0000024069CF0810, file "typing.py", line 1592>
  88: MAKE_FUNCTION        
  90: STORE_NAME           __ror__
  92: LOAD_CLOSURE         __class__
  94: COPY                 
  96: STORE_NAME           __classcell__
  98: RETURN_VALUE         
