# Disassembly for typing._UnionGenericAlias.__reduce__
# From module file: typing

## co_consts:
(None,)

## co_names:
('super', '__reduce__', 'Union')

## bytecode:

   0: COPY_FREE_VARS       
   2: RESUME               
   4: LOAD_GLOBAL          NULL + super
  16: PRECALL              
  20: CALL                 
  30: LOAD_METHOD          __reduce__
  52: PRECALL              
  56: CALL                 
  66: UNPACK_SEQUENCE      
  70: STORE_FAST           func
  72: UNPACK_SEQUENCE      
  76: STORE_FAST           origin
  78: STORE_FAST           args
  80: LOAD_FAST            func
  82: LOAD_GLOBAL          Union
  94: LOAD_FAST            args
  96: BUILD_TUPLE          
  98: BUILD_TUPLE          
 100: RETURN_VALUE         
