# Disassembly for typing.no_type_check_decorator
# From module file: typing

## co_consts:
('Decorator to give another decorator the @no_type_check effect.\n\n    This wraps the decorator with something that wraps the decorated\n    function in @no_type_check.\n    ', <code object wrapped_decorator at 0x0000024069CF53E0, file "typing.py", line 2551>)

## co_names:
('functools', 'wraps')

## bytecode:

   0: MAKE_CELL            decorator
   2: RESUME               
   4: LOAD_GLOBAL          NULL + functools
  16: LOAD_ATTR            wraps
  26: LOAD_DEREF           decorator
  28: PRECALL              
  32: CALL                 
  42: LOAD_CLOSURE         decorator
  44: BUILD_TUPLE          
  46: LOAD_CONST           <code object wrapped_decorator at 0x0000024069CF53E0, file "typing.py", line 2551>
  48: MAKE_FUNCTION        closure
  50: PRECALL              
  54: CALL                 
  64: STORE_FAST           wrapped_decorator
  66: LOAD_FAST            wrapped_decorator
  68: RETURN_VALUE         
