# Disassembly for typing.Protocol.__init_subclass__._proto_hook
# From module file: typing

## co_consts:
(None, '_is_protocol', False, '_is_runtime_protocol', 'Instance and class checks can only be used with @runtime_checkable protocols', "Protocols with non-method members don't support issubclass()", 'issubclass() arg 1 must be a class', '__annotations__', True)

## co_names:
('__dict__', 'get', 'NotImplemented', 'getattr', '_allow_reckless_class_checks', 'TypeError', '_is_callable_members_only', 'isinstance', 'type', '_get_protocol_attrs', '__mro__', 'collections', 'abc', 'Mapping', 'issubclass', 'Generic', '_is_protocol')

## bytecode:

   0: COPY_FREE_VARS       
   2: RESUME               
   4: LOAD_DEREF           cls
   6: LOAD_ATTR            __dict__
  16: LOAD_METHOD          get
  38: LOAD_CONST           '_is_protocol'
  40: LOAD_CONST           False
  42: PRECALL              
  46: CALL                 
  56: POP_JUMP_FORWARD_IF_TRUE to 72
  58: LOAD_GLOBAL          NotImplemented
  70: RETURN_VALUE         
  72: LOAD_GLOBAL          NULL + getattr
  84: LOAD_DEREF           cls
  86: LOAD_CONST           '_is_runtime_protocol'
  88: LOAD_CONST           False
  90: PRECALL              
  94: CALL                 
 104: POP_JUMP_FORWARD_IF_TRUE to 178
 106: LOAD_GLOBAL          NULL + _allow_reckless_class_checks
 118: PRECALL              
 122: CALL                 
 132: POP_JUMP_FORWARD_IF_FALSE to 148
 134: LOAD_GLOBAL          NotImplemented
 146: RETURN_VALUE         
 148: LOAD_GLOBAL          NULL + TypeError
 160: LOAD_CONST           'Instance and class checks can only be used with @runtime_checkable protocols'
 162: PRECALL              
 166: CALL                 
 176: RAISE_VARARGS        
 178: LOAD_GLOBAL          NULL + _is_callable_members_only
 190: LOAD_DEREF           cls
 192: PRECALL              
 196: CALL                 
 206: POP_JUMP_FORWARD_IF_TRUE to 280
 208: LOAD_GLOBAL          NULL + _allow_reckless_class_checks
 220: PRECALL              
 224: CALL                 
 234: POP_JUMP_FORWARD_IF_FALSE to 250
 236: LOAD_GLOBAL          NotImplemented
 248: RETURN_VALUE         
 250: LOAD_GLOBAL          NULL + TypeError
 262: LOAD_CONST           "Protocols with non-method members don't support issubclass()"
 264: PRECALL              
 268: CALL                 
 278: RAISE_VARARGS        
 280: LOAD_GLOBAL          NULL + isinstance
 292: LOAD_FAST            other
 294: LOAD_GLOBAL          type
 306: PRECALL              
 310: CALL                 
 320: POP_JUMP_FORWARD_IF_TRUE to 352
 322: LOAD_GLOBAL          NULL + TypeError
 334: LOAD_CONST           'issubclass() arg 1 must be a class'
 336: PRECALL              
 340: CALL                 
 350: RAISE_VARARGS        
 352: LOAD_GLOBAL          NULL + _get_protocol_attrs
 364: LOAD_DEREF           cls
 366: PRECALL              
 370: CALL                 
 380: GET_ITER             
 382: FOR_ITER             to 660
 384: STORE_FAST           attr
 386: LOAD_FAST            other
 388: LOAD_ATTR            __mro__
 398: GET_ITER             
 400: FOR_ITER             to 640
 402: STORE_FAST           base
 404: LOAD_FAST            attr
 406: LOAD_FAST            base
 408: LOAD_ATTR            __dict__
 418: CONTAINS_OP          
 420: POP_JUMP_FORWARD_IF_FALSE to 474
 422: LOAD_FAST            base
 424: LOAD_ATTR            __dict__
 434: LOAD_FAST            attr
 436: BINARY_SUBSCR        
 446: POP_JUMP_FORWARD_IF_NOT_NONE to 470
 448: LOAD_GLOBAL          NotImplemented
 460: SWAP                 
 462: POP_TOP              
 464: SWAP                 
 466: POP_TOP              
 468: RETURN_VALUE         
 470: POP_TOP              
 472: JUMP_FORWARD         to 658
 474: LOAD_GLOBAL          NULL + getattr
 486: LOAD_FAST            base
 488: LOAD_CONST           '__annotations__'
 490: BUILD_MAP            
 492: PRECALL              
 496: CALL                 
 506: STORE_FAST           annotations
 508: LOAD_GLOBAL          NULL + isinstance
 520: LOAD_FAST            annotations
 522: LOAD_GLOBAL          collections
 534: LOAD_ATTR            abc
 544: LOAD_ATTR            Mapping
 554: PRECALL              
 558: CALL                 
 568: POP_JUMP_FORWARD_IF_FALSE to 638
 570: LOAD_FAST            attr
 572: LOAD_FAST            annotations
 574: CONTAINS_OP          
 576: POP_JUMP_FORWARD_IF_FALSE to 638
 578: LOAD_GLOBAL          NULL + issubclass
 590: LOAD_FAST            other
 592: LOAD_GLOBAL          Generic
 604: PRECALL              
 608: CALL                 
 618: POP_JUMP_FORWARD_IF_FALSE to 638
 620: LOAD_FAST            other
 622: LOAD_ATTR            _is_protocol
 632: POP_JUMP_FORWARD_IF_FALSE to 638
 634: POP_TOP              
 636: JUMP_FORWARD         to 658
 638: JUMP_BACKWARD        to 400
 640: LOAD_GLOBAL          NotImplemented
 652: SWAP                 
 654: POP_TOP              
 656: RETURN_VALUE         
 658: JUMP_BACKWARD        to 382
 660: LOAD_CONST           True
 662: RETURN_VALUE         
