# Disassembly for typing._CallableType.__getitem__
# From module file: typing

## co_consts:
(None, 2, 'Callable must be used as Callable[[arg, ...], result].')

## co_names:
('isinstance', 'tuple', 'len', 'TypeError', 'list', '__getitem_inner__')

## bytecode:

   0: RESUME               
   2: LOAD_GLOBAL          NULL + isinstance
  14: LOAD_FAST            params
  16: LOAD_GLOBAL          tuple
  28: PRECALL              
  32: CALL                 
  42: POP_JUMP_FORWARD_IF_FALSE to 82
  44: LOAD_GLOBAL          NULL + len
  56: LOAD_FAST            params
  58: PRECALL              
  62: CALL                 
  72: LOAD_CONST           2
  74: COMPARE_OP           !=
  80: POP_JUMP_FORWARD_IF_FALSE to 112
  82: LOAD_GLOBAL          NULL + TypeError
  94: LOAD_CONST           'Callable must be used as Callable[[arg, ...], result].'
  96: PRECALL              
 100: CALL                 
 110: RAISE_VARARGS        
 112: LOAD_FAST            params
 114: UNPACK_SEQUENCE      
 118: STORE_FAST           args
 120: STORE_FAST           result
 122: LOAD_GLOBAL          NULL + isinstance
 134: LOAD_FAST            args
 136: LOAD_GLOBAL          list
 148: PRECALL              
 152: CALL                 
 162: POP_JUMP_FORWARD_IF_FALSE to 200
 164: LOAD_GLOBAL          NULL + tuple
 176: LOAD_FAST            args
 178: PRECALL              
 182: CALL                 
 192: LOAD_FAST            result
 194: BUILD_TUPLE          
 196: STORE_FAST           params
 198: JUMP_FORWARD         to 208
 200: LOAD_FAST            args
 202: LOAD_FAST            result
 204: BUILD_TUPLE          
 206: STORE_FAST           params
 208: LOAD_FAST            self
 210: LOAD_METHOD          __getitem_inner__
 232: LOAD_FAST            params
 234: PRECALL              
 238: CALL                 
 248: RETURN_VALUE         
