# Disassembly for typing.TypedDict
# From module file: typing

## co_consts:
('A simple typed namespace. At runtime it is equivalent to a plain dict.\n\n    TypedDict creates a dictionary type such that a type checker will expect all\n    instances to have a certain set of keys, where each key is\n    associated with a value of a consistent type. This expectation\n    is not checked at runtime.\n\n    Usage::\n\n        class Point2D(TypedDict):\n            x: int\n            y: int\n            label: str\n\n        a: Point2D = {\'x\': 1, \'y\': 2, \'label\': \'good\'}  # OK\n        b: Point2D = {\'z\': 3, \'label\': \'bad\'}           # Fails type check\n\n        assert Point2D(x=1, y=2, label=\'first\') == dict(x=1, y=2, label=\'first\')\n\n    The type info can be accessed via the Point2D.__annotations__ dict, and\n    the Point2D.__required_keys__ and Point2D.__optional_keys__ frozensets.\n    TypedDict supports an additional equivalent form::\n\n        Point2D = TypedDict(\'Point2D\', {\'x\': int, \'y\': int, \'label\': str})\n\n    By default, all keys must be present in a TypedDict. It is possible\n    to override this by specifying totality::\n\n        class Point2D(TypedDict, total=False):\n            x: int\n            y: int\n\n    This means that a Point2D TypedDict can have any of the keys omitted. A type\n    checker is only expected to support a literal False or True as the value of\n    the total argument. True is the default, and makes all items defined in the\n    class body be required.\n\n    The Required and NotRequired special forms can also be used to mark\n    individual keys as being required or not required::\n\n        class Point2D(TypedDict):\n            x: int               # the "x" key must always be present (Required is the default)\n            y: NotRequired[int]  # the "y" key can be omitted\n\n    See PEP 655 for more details on Required and NotRequired.\n    ', None, 'TypedDict takes either a dict or keyword arguments, but not both', 'The kwargs-based syntax for TypedDict definitions is deprecated in Python 3.11, will be removed in Python 3.13, and may not be understood by third-party type checkers.', 2, ('stacklevel',), '__annotations__', '__module__', (), ('total',))

## co_names:
('TypeError', 'warnings', 'warn', 'DeprecationWarning', 'dict', '_caller', '_TypedDictMeta')

## bytecode:

   0: RESUME               
   2: LOAD_FAST            fields
   4: POP_JUMP_FORWARD_IF_NOT_NONE to 12
   6: LOAD_FAST            kwargs
   8: STORE_FAST           fields
  10: JUMP_FORWARD         to 46
  12: LOAD_FAST            kwargs
  14: POP_JUMP_FORWARD_IF_FALSE to 46
  16: LOAD_GLOBAL          NULL + TypeError
  28: LOAD_CONST           'TypedDict takes either a dict or keyword arguments, but not both'
  30: PRECALL              
  34: CALL                 
  44: RAISE_VARARGS        
  46: LOAD_FAST            kwargs
  48: POP_JUMP_FORWARD_IF_FALSE to 106
  50: LOAD_GLOBAL          NULL + warnings
  62: LOAD_ATTR            warn
  72: LOAD_CONST           'The kwargs-based syntax for TypedDict definitions is deprecated in Python 3.11, will be removed in Python 3.13, and may not be understood by third-party type checkers.'
  74: LOAD_GLOBAL          DeprecationWarning
  86: LOAD_CONST           2
  88: KW_NAMES             
  90: PRECALL              
  94: CALL                 
 104: POP_TOP              
 106: LOAD_CONST           '__annotations__'
 108: LOAD_GLOBAL          NULL + dict
 120: LOAD_FAST            fields
 122: PRECALL              
 126: CALL                 
 136: BUILD_MAP            
 138: STORE_FAST           ns
 140: LOAD_GLOBAL          NULL + _caller
 152: PRECALL              
 156: CALL                 
 166: STORE_FAST           module
 168: LOAD_FAST            module
 170: POP_JUMP_FORWARD_IF_NONE to 182
 172: LOAD_FAST            module
 174: LOAD_FAST            ns
 176: LOAD_CONST           '__module__'
 178: STORE_SUBSCR         
 182: LOAD_GLOBAL          NULL + _TypedDictMeta
 194: LOAD_FAST            typename
 196: LOAD_CONST           ()
 198: LOAD_FAST            ns
 200: LOAD_FAST            total
 202: KW_NAMES             
 204: PRECALL              
 208: CALL                 
 218: RETURN_VALUE         
