# Disassembly for typing.ParamSpecKwargs
# From module file: typing

## co_consts:
('ParamSpecKwargs', 'The kwargs for a ParamSpec object.\n\n    Given a ParamSpec object P, P.kwargs is an instance of ParamSpecKwargs.\n\n    ParamSpecKwargs objects have a reference back to their ParamSpec:\n\n       P.kwargs.__origin__ is P\n\n    This type is meant for runtime introspection and has no special meaning to\n    static type checkers.\n    ', <code object __init__ at 0x0000024069495D70, file "typing.py", line 1157>, <code object __repr__ at 0x0000024069466950, file "typing.py", line 1160>, <code object __eq__ at 0x000002406941B1B0, file "typing.py", line 1163>, None)

## co_names:
('__name__', '__module__', '__qualname__', '__doc__', '__init__', '__repr__', '__eq__')

## bytecode:

   0: RESUME               
   2: LOAD_NAME            __name__
   4: STORE_NAME           __module__
   6: LOAD_CONST           'ParamSpecKwargs'
   8: STORE_NAME           __qualname__
  10: LOAD_CONST           'The kwargs for a ParamSpec object.\n\n    Given a ParamSpec object P, P.kwargs is an instance of ParamSpecKwargs.\n\n    ParamSpecKwargs objects have a reference back to their ParamSpec:\n\n       P.kwargs.__origin__ is P\n\n    This type is meant for runtime introspection and has no special meaning to\n    static type checkers.\n    '
  12: STORE_NAME           __doc__
  14: LOAD_CONST           <code object __init__ at 0x0000024069495D70, file "typing.py", line 1157>
  16: MAKE_FUNCTION        
  18: STORE_NAME           __init__
  20: LOAD_CONST           <code object __repr__ at 0x0000024069466950, file "typing.py", line 1160>
  22: MAKE_FUNCTION        
  24: STORE_NAME           __repr__
  26: LOAD_CONST           <code object __eq__ at 0x000002406941B1B0, file "typing.py", line 1163>
  28: MAKE_FUNCTION        
  30: STORE_NAME           __eq__
  32: LOAD_CONST           None
  34: RETURN_VALUE         
