# Disassembly for typing._UnpackGenericAlias.__getitem__
# From module file: typing

## co_consts:
(None,)

## co_names:
('__typing_is_unpacked_typevartuple__', 'super', '__getitem__')

## bytecode:

   0: COPY_FREE_VARS       
   2: RESUME               
   4: LOAD_FAST            self
   6: LOAD_ATTR            __typing_is_unpacked_typevartuple__
  16: POP_JUMP_FORWARD_IF_FALSE to 22
  18: LOAD_FAST            args
  20: RETURN_VALUE         
  22: LOAD_GLOBAL          NULL + super
  34: PRECALL              
  38: CALL                 
  48: LOAD_METHOD          __getitem__
  70: LOAD_FAST            args
  72: PRECALL              
  76: CALL                 
  86: RETURN_VALUE         
