# Disassembly for typing._SpecialGenericAlias.__getitem__
# From module file: typing

## co_consts:
(None, 'Parameters to generic types must be types.', <code object <genexpr> at 0x000002406945D980, file "typing.py", line 1568>)

## co_names:
('isinstance', 'tuple', '_check_generic', '_nparams', 'copy_with')

## bytecode:

   0: MAKE_CELL            msg
   2: RESUME               
   4: LOAD_GLOBAL          NULL + isinstance
  16: LOAD_FAST            params
  18: LOAD_GLOBAL          tuple
  30: PRECALL              
  34: CALL                 
  44: POP_JUMP_FORWARD_IF_TRUE to 52
  46: LOAD_FAST            params
  48: BUILD_TUPLE          
  50: STORE_FAST           params
  52: LOAD_CONST           'Parameters to generic types must be types.'
  54: STORE_DEREF          msg
  56: LOAD_GLOBAL          NULL + tuple
  68: LOAD_CLOSURE         msg
  70: BUILD_TUPLE          
  72: LOAD_CONST           <code object <genexpr> at 0x000002406945D980, file "typing.py", line 1568>
  74: MAKE_FUNCTION        closure
  76: LOAD_FAST            params
  78: GET_ITER             
  80: PRECALL              
  84: CALL                 
  94: PRECALL              
  98: CALL                 
 108: STORE_FAST           params
 110: LOAD_GLOBAL          NULL + _check_generic
 122: LOAD_FAST            self
 124: LOAD_FAST            params
 126: LOAD_FAST            self
 128: LOAD_ATTR            _nparams
 138: PRECALL              
 142: CALL                 
 152: POP_TOP              
 154: LOAD_FAST            self
 156: LOAD_METHOD          copy_with
 178: LOAD_FAST            params
 180: PRECALL              
 184: CALL                 
 194: RETURN_VALUE         
