# Disassembly for typing.re
# From module file: typing

## co_consts:
('re', 'Wrapper namespace for re type aliases.', 'Pattern', 'Match', None)

## co_names:
('__name__', '__module__', '__qualname__', '__doc__', '__all__', 'Pattern', 'Match')

## bytecode:

   0: RESUME               
   2: LOAD_NAME            __name__
   4: STORE_NAME           __module__
   6: LOAD_CONST           're'
   8: STORE_NAME           __qualname__
  10: LOAD_CONST           'Wrapper namespace for re type aliases.'
  12: STORE_NAME           __doc__
  14: LOAD_CONST           'Pattern'
  16: LOAD_CONST           'Match'
  18: BUILD_LIST           
  20: STORE_NAME           __all__
  22: LOAD_NAME            Pattern
  24: STORE_NAME           Pattern
  26: LOAD_NAME            Match
  28: STORE_NAME           Match
  30: LOAD_CONST           None
  32: RETURN_VALUE         
