# Disassembly for typing._Final.__init_subclass__
# From module file: typing

## co_consts:
(None, '_root', 'Cannot subclass special typing classes')

## co_names:
('TypeError',)

## bytecode:

   0: RESUME               
   2: LOAD_CONST           '_root'
   4: LOAD_FAST            kwds
   6: CONTAINS_OP          
   8: POP_JUMP_FORWARD_IF_FALSE to 40
  10: LOAD_GLOBAL          NULL + TypeError
  22: LOAD_CONST           'Cannot subclass special typing classes'
  24: PRECALL              
  28: CALL                 
  38: RAISE_VARARGS        
  40: LOAD_CONST           None
  42: RETURN_VALUE         
