# Disassembly for typing.Concatenate
# From module file: typing

## co_consts:
('Special form for annotating higher-order functions.\n\n    ``Concatenate`` can be used in conjunction with ``ParamSpec`` and\n    ``Callable`` to represent a higher-order function which adds, removes or\n    transforms the parameters of a callable.\n\n    For example::\n\n        Callable[Concatenate[int, P], int]\n\n    See PEP 612 for detailed information.\n    ', (), 'Cannot take a Concatenate of no types.', -1, Ellipsis, 'The last parameter to Concatenate should be a ParamSpec variable or ellipsis.', 'Concatenate[arg, ...]: each arg must be a type.', <code object <genexpr> at 0x000002406945D5C0, file "typing.py", line 782>, None, True, ('_paramspec_tvars',))

## co_names:
('TypeError', 'isinstance', 'tuple', 'ParamSpec', '_ConcatenateGenericAlias')

## bytecode:

   0: MAKE_CELL            msg
   2: RESUME               
   4: LOAD_FAST            parameters
   6: LOAD_CONST           ()
   8: COMPARE_OP           ==
  14: POP_JUMP_FORWARD_IF_FALSE to 46
  16: LOAD_GLOBAL          NULL + TypeError
  28: LOAD_CONST           'Cannot take a Concatenate of no types.'
  30: PRECALL              
  34: CALL                 
  44: RAISE_VARARGS        
  46: LOAD_GLOBAL          NULL + isinstance
  58: LOAD_FAST            parameters
  60: LOAD_GLOBAL          tuple
  72: PRECALL              
  76: CALL                 
  86: POP_JUMP_FORWARD_IF_TRUE to 94
  88: LOAD_FAST            parameters
  90: BUILD_TUPLE          
  92: STORE_FAST           parameters
  94: LOAD_FAST            parameters
  96: LOAD_CONST           -1
  98: BINARY_SUBSCR        
 108: LOAD_CONST           Ellipsis
 110: IS_OP                
 112: POP_JUMP_FORWARD_IF_TRUE to 198
 114: LOAD_GLOBAL          NULL + isinstance
 126: LOAD_FAST            parameters
 128: LOAD_CONST           -1
 130: BINARY_SUBSCR        
 140: LOAD_GLOBAL          ParamSpec
 152: PRECALL              
 156: CALL                 
 166: POP_JUMP_FORWARD_IF_TRUE to 198
 168: LOAD_GLOBAL          NULL + TypeError
 180: LOAD_CONST           'The last parameter to Concatenate should be a ParamSpec variable or ellipsis.'
 182: PRECALL              
 186: CALL                 
 196: RAISE_VARARGS        
 198: LOAD_CONST           'Concatenate[arg, ...]: each arg must be a type.'
 200: STORE_DEREF          msg
 202: BUILD_LIST           
 204: LOAD_CLOSURE         msg
 206: BUILD_TUPLE          
 208: LOAD_CONST           <code object <genexpr> at 0x000002406945D5C0, file "typing.py", line 782>
 210: MAKE_FUNCTION        closure
 212: LOAD_FAST            parameters
 214: LOAD_CONST           None
 216: LOAD_CONST           -1
 218: BUILD_SLICE          
 220: BINARY_SUBSCR        
 230: GET_ITER             
 232: PRECALL              
 236: CALL                 
 246: LIST_EXTEND          
 248: LOAD_FAST            parameters
 250: LOAD_CONST           -1
 252: BINARY_SUBSCR        
 262: LIST_APPEND          
 264: LIST_TO_TUPLE        
 266: STORE_FAST           parameters
 268: LOAD_GLOBAL          NULL + _ConcatenateGenericAlias
 280: LOAD_FAST            self
 282: LOAD_FAST            parameters
 284: LOAD_CONST           True
 286: KW_NAMES             
 288: PRECALL              
 292: CALL                 
 302: RETURN_VALUE         
