# Disassembly for typing.get_origin
# From module file: typing

## co_consts:
('Get the unsubscripted version of a type.\n\n    This supports generic types, Callable, Tuple, Union, Literal, Final, ClassVar,\n    Annotated, and others. Return None for unsupported types.\n\n    Examples::\n\n        assert get_origin(Literal[42]) is Literal\n        assert get_origin(int) is None\n        assert get_origin(ClassVar[int]) is ClassVar\n        assert get_origin(Generic) is Generic\n        assert get_origin(Generic[T]) is Generic\n        assert get_origin(Union[T, int]) is Union\n        assert get_origin(List[Tuple[T, T]][int]) is list\n        assert get_origin(P.args) is P\n    ', None)

## co_names:
('isinstance', '_AnnotatedAlias', 'Annotated', '_BaseGenericAlias', 'GenericAlias', 'ParamSpecArgs', 'ParamSpecKwargs', '__origin__', 'Generic', 'types', 'UnionType')

## bytecode:

   0: RESUME               
   2: LOAD_GLOBAL          NULL + isinstance
  14: LOAD_FAST            tp
  16: LOAD_GLOBAL          _AnnotatedAlias
  28: PRECALL              
  32: CALL                 
  42: POP_JUMP_FORWARD_IF_FALSE to 58
  44: LOAD_GLOBAL          Annotated
  56: RETURN_VALUE         
  58: LOAD_GLOBAL          NULL + isinstance
  70: LOAD_FAST            tp
  72: LOAD_GLOBAL          _BaseGenericAlias
  84: LOAD_GLOBAL          GenericAlias
  96: LOAD_GLOBAL          ParamSpecArgs
 108: LOAD_GLOBAL          ParamSpecKwargs
 120: BUILD_TUPLE          
 122: PRECALL              
 126: CALL                 
 136: POP_JUMP_FORWARD_IF_FALSE to 152
 138: LOAD_FAST            tp
 140: LOAD_ATTR            __origin__
 150: RETURN_VALUE         
 152: LOAD_FAST            tp
 154: LOAD_GLOBAL          Generic
 166: IS_OP                
 168: POP_JUMP_FORWARD_IF_FALSE to 184
 170: LOAD_GLOBAL          Generic
 182: RETURN_VALUE         
 184: LOAD_GLOBAL          NULL + isinstance
 196: LOAD_FAST            tp
 198: LOAD_GLOBAL          types
 210: LOAD_ATTR            UnionType
 220: PRECALL              
 224: CALL                 
 234: POP_JUMP_FORWARD_IF_FALSE to 260
 236: LOAD_GLOBAL          types
 248: LOAD_ATTR            UnionType
 258: RETURN_VALUE         
 260: LOAD_CONST           None
 262: RETURN_VALUE         
