# Disassembly for typing._GenericAlias.__repr__
# From module file: typing

## co_consts:
(None, 'typing.', ', ', <code object <listcomp> at 0x000002406945DA70, file "typing.py", line 1513>, '()', '[', ']')

## co_names:
('_name', '_type_repr', '__origin__', '__args__', 'join')

## bytecode:

   0: RESUME               
   2: LOAD_FAST            self
   4: LOAD_ATTR            _name
  14: POP_JUMP_FORWARD_IF_FALSE to 38
  16: LOAD_CONST           'typing.'
  18: LOAD_FAST            self
  20: LOAD_ATTR            _name
  30: BINARY_OP            +
  34: STORE_FAST           name
  36: JUMP_FORWARD         to 78
  38: LOAD_GLOBAL          NULL + _type_repr
  50: LOAD_FAST            self
  52: LOAD_ATTR            __origin__
  62: PRECALL              
  66: CALL                 
  76: STORE_FAST           name
  78: LOAD_FAST            self
  80: LOAD_ATTR            __args__
  90: POP_JUMP_FORWARD_IF_FALSE to 166
  92: LOAD_CONST           ', '
  94: LOAD_METHOD          join
 116: LOAD_CONST           <code object <listcomp> at 0x000002406945DA70, file "typing.py", line 1513>
 118: MAKE_FUNCTION        
 120: LOAD_FAST            self
 122: LOAD_ATTR            __args__
 132: GET_ITER             
 134: PRECALL              
 138: CALL                 
 148: PRECALL              
 152: CALL                 
 162: STORE_FAST           args
 164: JUMP_FORWARD         to 170
 166: LOAD_CONST           '()'
 168: STORE_FAST           args
 170: LOAD_FAST            name
 172: FORMAT_VALUE         
 174: LOAD_CONST           '['
 176: LOAD_FAST            args
 178: FORMAT_VALUE         
 180: LOAD_CONST           ']'
 182: BUILD_STRING         
 184: RETURN_VALUE         
