# Disassembly for typing._UnpackGenericAlias.__typing_unpacked_tuple_args__
# From module file: typing

## co_consts:
(None, 1)

## co_names:
('__origin__', 'Unpack', 'len', '__args__', 'isinstance', '_GenericAlias', 'tuple')

## bytecode:

   0: RESUME               
   2: LOAD_FAST            self
   4: LOAD_ATTR            __origin__
  14: LOAD_GLOBAL          Unpack
  26: IS_OP                
  28: POP_JUMP_FORWARD_IF_TRUE to 34
  30: LOAD_ASSERTION_ERROR 
  32: RAISE_VARARGS        
  34: LOAD_GLOBAL          NULL + len
  46: LOAD_FAST            self
  48: LOAD_ATTR            __args__
  58: PRECALL              
  62: CALL                 
  72: LOAD_CONST           1
  74: COMPARE_OP           ==
  80: POP_JUMP_FORWARD_IF_TRUE to 86
  82: LOAD_ASSERTION_ERROR 
  84: RAISE_VARARGS        
  86: LOAD_FAST            self
  88: LOAD_ATTR            __args__
  98: UNPACK_SEQUENCE      
 102: STORE_FAST           arg
 104: LOAD_GLOBAL          NULL + isinstance
 116: LOAD_FAST            arg
 118: LOAD_GLOBAL          _GenericAlias
 130: PRECALL              
 134: CALL                 
 144: POP_JUMP_FORWARD_IF_FALSE to 192
 146: LOAD_FAST            arg
 148: LOAD_ATTR            __origin__
 158: LOAD_GLOBAL          tuple
 170: IS_OP                
 172: POP_JUMP_FORWARD_IF_TRUE to 178
 174: LOAD_ASSERTION_ERROR 
 176: RAISE_VARARGS        
 178: LOAD_FAST            arg
 180: LOAD_ATTR            __args__
 190: RETURN_VALUE         
 192: LOAD_CONST           None
 194: RETURN_VALUE         
