# Disassembly for typing.no_type_check_decorator.wrapped_decorator
# From module file: typing

## co_consts:
(None,)

## co_names:
('no_type_check',)

## bytecode:

   0: COPY_FREE_VARS       
   2: RESUME               
   4: PUSH_NULL            
   6: LOAD_DEREF           decorator
   8: LOAD_FAST            args
  10: BUILD_MAP            
  12: LOAD_FAST            kwds
  14: DICT_MERGE           
  16: CALL_FUNCTION_EX     
  18: STORE_FAST           func
  20: LOAD_GLOBAL          NULL + no_type_check
  32: LOAD_FAST            func
  34: PRECALL              
  38: CALL                 
  48: STORE_FAST           func
  50: LOAD_FAST            func
  52: RETURN_VALUE         
