# Disassembly for typing._GenericAlias.__init__.<genexpr>
# From module file: typing

## co_consts:
(Ellipsis, None)

## co_names:
('_TypingEllipsis',)

## bytecode:

   0: RETURN_GENERATOR     
   2: POP_TOP              
   4: RESUME               
   6: LOAD_FAST            .0
   8: FOR_ITER             to 44
  10: STORE_FAST           a
  12: LOAD_FAST            a
  14: LOAD_GLOBAL          _TypingEllipsis
  26: IS_OP                
  28: POP_JUMP_FORWARD_IF_FALSE to 34
  30: LOAD_CONST           Ellipsis
  32: JUMP_FORWARD         to 36
  34: LOAD_FAST            a
  36: YIELD_VALUE          
  38: RESUME               
  40: POP_TOP              
  42: JUMP_BACKWARD        to 8
  44: LOAD_CONST           None
  46: RETURN_VALUE         
