# Disassembly for typing._SpecialForm.__getattr__
# From module file: typing

## co_consts:
(None, frozenset({'__qualname__', '__name__'}))

## co_names:
('_name', 'AttributeError')

## bytecode:

   0: RESUME               
   2: LOAD_FAST            item
   4: LOAD_CONST           frozenset({'__qualname__', '__name__'})
   6: CONTAINS_OP          
   8: POP_JUMP_FORWARD_IF_FALSE to 24
  10: LOAD_FAST            self
  12: LOAD_ATTR            _name
  22: RETURN_VALUE         
  24: LOAD_GLOBAL          NULL + AttributeError
  36: LOAD_FAST            item
  38: PRECALL              
  42: CALL                 
  52: RAISE_VARARGS        
