# Disassembly for typing.get_args
# From module file: typing

## co_consts:
('Get type arguments with all substitutions performed.\n\n    For unions, basic simplifications used by Union constructor are performed.\n\n    Examples::\n\n        assert get_args(Dict[str, int]) == (str, int)\n        assert get_args(int) == ()\n        assert get_args(Union[int, Union[T, int], str][int]) == (int, str)\n        assert get_args(Union[int, Tuple[T, int]][str]) == (int, Tuple[str, int])\n        assert get_args(Callable[[], T][int]) == ([], int)\n    ', None, -1, ())

## co_names:
('isinstance', '_AnnotatedAlias', '__origin__', '__metadata__', '_GenericAlias', 'GenericAlias', '__args__', '_should_unflatten_callable_args', 'list', 'types', 'UnionType')

## bytecode:

   0: RESUME               
   2: LOAD_GLOBAL          NULL + isinstance
  14: LOAD_FAST            tp
  16: LOAD_GLOBAL          _AnnotatedAlias
  28: PRECALL              
  32: CALL                 
  42: POP_JUMP_FORWARD_IF_FALSE to 76
  44: LOAD_FAST            tp
  46: LOAD_ATTR            __origin__
  56: BUILD_TUPLE          
  58: LOAD_FAST            tp
  60: LOAD_ATTR            __metadata__
  70: BINARY_OP            +
  74: RETURN_VALUE         
  76: LOAD_GLOBAL          NULL + isinstance
  88: LOAD_FAST            tp
  90: LOAD_GLOBAL          _GenericAlias
 102: LOAD_GLOBAL          GenericAlias
 114: BUILD_TUPLE          
 116: PRECALL              
 120: CALL                 
 130: POP_JUMP_FORWARD_IF_FALSE to 244
 132: LOAD_FAST            tp
 134: LOAD_ATTR            __args__
 144: STORE_FAST           res
 146: LOAD_GLOBAL          NULL + _should_unflatten_callable_args
 158: LOAD_FAST            tp
 160: LOAD_FAST            res
 162: PRECALL              
 166: CALL                 
 176: POP_JUMP_FORWARD_IF_FALSE to 240
 178: LOAD_GLOBAL          NULL + list
 190: LOAD_FAST            res
 192: LOAD_CONST           None
 194: LOAD_CONST           -1
 196: BUILD_SLICE          
 198: BINARY_SUBSCR        
 208: PRECALL              
 212: CALL                 
 222: LOAD_FAST            res
 224: LOAD_CONST           -1
 226: BINARY_SUBSCR        
 236: BUILD_TUPLE          
 238: STORE_FAST           res
 240: LOAD_FAST            res
 242: RETURN_VALUE         
 244: LOAD_GLOBAL          NULL + isinstance
 256: LOAD_FAST            tp
 258: LOAD_GLOBAL          types
 270: LOAD_ATTR            UnionType
 280: PRECALL              
 284: CALL                 
 294: POP_JUMP_FORWARD_IF_FALSE to 310
 296: LOAD_FAST            tp
 298: LOAD_ATTR            __args__
 308: RETURN_VALUE         
 310: LOAD_CONST           ()
 312: RETURN_VALUE         
