# Disassembly for typing.ParamSpec.__typing_subst__
# From module file: typing

## co_consts:
(None, <code object <genexpr> at 0x000002406945FA50, file "typing.py", line 1225>, 'Expected a list of types, an ellipsis, ParamSpec, or Concatenate. Got ')

## co_names:
('isinstance', 'list', 'tuple', '_is_param_expr', 'TypeError')

## bytecode:

   0: RESUME               
   2: LOAD_GLOBAL          NULL + isinstance
  14: LOAD_FAST            arg
  16: LOAD_GLOBAL          list
  28: LOAD_GLOBAL          tuple
  40: BUILD_TUPLE          
  42: PRECALL              
  46: CALL                 
  56: POP_JUMP_FORWARD_IF_FALSE to 110
  58: LOAD_GLOBAL          NULL + tuple
  70: LOAD_CONST           <code object <genexpr> at 0x000002406945FA50, file "typing.py", line 1225>
  72: MAKE_FUNCTION        
  74: LOAD_FAST            arg
  76: GET_ITER             
  78: PRECALL              
  82: CALL                 
  92: PRECALL              
  96: CALL                 
 106: STORE_FAST           arg
 108: JUMP_FORWARD         to 176
 110: LOAD_GLOBAL          NULL + _is_param_expr
 122: LOAD_FAST            arg
 124: PRECALL              
 128: CALL                 
 138: POP_JUMP_FORWARD_IF_TRUE to 176
 140: LOAD_GLOBAL          NULL + TypeError
 152: LOAD_CONST           'Expected a list of types, an ellipsis, ParamSpec, or Concatenate. Got '
 154: LOAD_FAST            arg
 156: FORMAT_VALUE         
 158: BUILD_STRING         
 160: PRECALL              
 164: CALL                 
 174: RAISE_VARARGS        
 176: LOAD_FAST            arg
 178: RETURN_VALUE         
