# Disassembly for textwrap.TextWrapper._wrap_chunks
# From module file: textwrap

## co_consts:
('_wrap_chunks(chunks : [string]) -> [string]\n\n        Wrap a sequence of text chunks and return a list of lines of\n        length \'self.width\' or less.  (If \'break_long_words\' is false,\n        some lines may be longer than this.)  Chunks correspond roughly\n        to words and the whitespace between them: each chunk is\n        indivisible (modulo \'break_long_words\'), but a line break can\n        come between any two chunks.  Chunks should not have internal\n        whitespace; ie. a chunk is either all whitespace or a "word".\n        Whitespace chunks will be removed from the beginning and end of\n        lines, but apart from that whitespace is preserved.\n        ', 0, 'invalid width %r (must be > 0)', None, 1, 'placeholder too large for max width', -1, '')

## co_names:
('width', 'ValueError', 'max_lines', 'subsequent_indent', 'initial_indent', 'len', 'placeholder', 'lstrip', 'reverse', 'drop_whitespace', 'strip', 'append', 'pop', '_handle_long_word', 'sum', 'map', 'join', 'rstrip')

## bytecode:

   0: RESUME               
   2: BUILD_LIST           
   4: STORE_FAST           lines
   6: LOAD_FAST            self
   8: LOAD_ATTR            width
  18: LOAD_CONST           0
  20: COMPARE_OP           <=
  26: POP_JUMP_FORWARD_IF_FALSE to 74
  28: LOAD_GLOBAL          NULL + ValueError
  40: LOAD_CONST           'invalid width %r (must be > 0)'
  42: LOAD_FAST            self
  44: LOAD_ATTR            width
  54: BINARY_OP            %
  58: PRECALL              
  62: CALL                 
  72: RAISE_VARARGS        
  74: LOAD_FAST            self
  76: LOAD_ATTR            max_lines
  86: POP_JUMP_FORWARD_IF_NONE to 296
  88: LOAD_FAST            self
  90: LOAD_ATTR            max_lines
 100: LOAD_CONST           1
 102: COMPARE_OP           >
 108: POP_JUMP_FORWARD_IF_FALSE to 126
 110: LOAD_FAST            self
 112: LOAD_ATTR            subsequent_indent
 122: STORE_FAST           indent
 124: JUMP_FORWARD         to 140
 126: LOAD_FAST            self
 128: LOAD_ATTR            initial_indent
 138: STORE_FAST           indent
 140: LOAD_GLOBAL          NULL + len
 152: LOAD_FAST            indent
 154: PRECALL              
 158: CALL                 
 168: LOAD_GLOBAL          NULL + len
 180: LOAD_FAST            self
 182: LOAD_ATTR            placeholder
 192: LOAD_METHOD          lstrip
 214: PRECALL              
 218: CALL                 
 228: PRECALL              
 232: CALL                 
 242: BINARY_OP            +
 246: LOAD_FAST            self
 248: LOAD_ATTR            width
 258: COMPARE_OP           >
 264: POP_JUMP_FORWARD_IF_FALSE to 296
 266: LOAD_GLOBAL          NULL + ValueError
 278: LOAD_CONST           'placeholder too large for max width'
 280: PRECALL              
 284: CALL                 
 294: RAISE_VARARGS        
 296: LOAD_FAST            chunks
 298: LOAD_METHOD          reverse
 320: PRECALL              
 324: CALL                 
 334: POP_TOP              
 336: LOAD_FAST            chunks
 338: EXTENDED_ARG         
 340: POP_JUMP_FORWARD_IF_FALSE to 1844
 342: BUILD_LIST           
 344: STORE_FAST           cur_line
 346: LOAD_CONST           0
 348: STORE_FAST           cur_len
 350: LOAD_FAST            lines
 352: POP_JUMP_FORWARD_IF_FALSE to 370
 354: LOAD_FAST            self
 356: LOAD_ATTR            subsequent_indent
 366: STORE_FAST           indent
 368: JUMP_FORWARD         to 384
 370: LOAD_FAST            self
 372: LOAD_ATTR            initial_indent
 382: STORE_FAST           indent
 384: LOAD_FAST            self
 386: LOAD_ATTR            width
 396: LOAD_GLOBAL          NULL + len
 408: LOAD_FAST            indent
 410: PRECALL              
 414: CALL                 
 424: BINARY_OP            -
 428: STORE_FAST           width
 430: LOAD_FAST            self
 432: LOAD_ATTR            drop_whitespace
 442: POP_JUMP_FORWARD_IF_FALSE to 514
 444: LOAD_FAST            chunks
 446: LOAD_CONST           -1
 448: BINARY_SUBSCR        
 458: LOAD_METHOD          strip
 480: PRECALL              
 484: CALL                 
 494: LOAD_CONST           ''
 496: COMPARE_OP           ==
 502: POP_JUMP_FORWARD_IF_FALSE to 514
 504: LOAD_FAST            lines
 506: POP_JUMP_FORWARD_IF_FALSE to 514
 508: LOAD_FAST            chunks
 510: LOAD_CONST           -1
 512: DELETE_SUBSCR        
 514: LOAD_FAST            chunks
 516: POP_JUMP_FORWARD_IF_FALSE to 674
 518: LOAD_GLOBAL          NULL + len
 530: LOAD_FAST            chunks
 532: LOAD_CONST           -1
 534: BINARY_SUBSCR        
 544: PRECALL              
 548: CALL                 
 558: STORE_FAST           l
 560: LOAD_FAST            cur_len
 562: LOAD_FAST            l
 564: BINARY_OP            +
 568: LOAD_FAST            width
 570: COMPARE_OP           <=
 576: POP_JUMP_FORWARD_IF_FALSE to 668
 578: LOAD_FAST            cur_line
 580: LOAD_METHOD          append
 602: LOAD_FAST            chunks
 604: LOAD_METHOD          pop
 626: PRECALL              
 630: CALL                 
 640: PRECALL              
 644: CALL                 
 654: POP_TOP              
 656: LOAD_FAST            cur_len
 658: LOAD_FAST            l
 660: BINARY_OP            +=
 664: STORE_FAST           cur_len
 666: JUMP_FORWARD         to 670
 668: JUMP_FORWARD         to 674
 670: LOAD_FAST            chunks
 672: POP_JUMP_BACKWARD_IF_TRUE to 518
 674: LOAD_FAST            chunks
 676: POP_JUMP_FORWARD_IF_FALSE to 844
 678: LOAD_GLOBAL          NULL + len
 690: LOAD_FAST            chunks
 692: LOAD_CONST           -1
 694: BINARY_SUBSCR        
 704: PRECALL              
 708: CALL                 
 718: LOAD_FAST            width
 720: COMPARE_OP           >
 726: POP_JUMP_FORWARD_IF_FALSE to 844
 728: LOAD_FAST            self
 730: LOAD_METHOD          _handle_long_word
 752: LOAD_FAST            chunks
 754: LOAD_FAST            cur_line
 756: LOAD_FAST            cur_len
 758: LOAD_FAST            width
 760: PRECALL              
 764: CALL                 
 774: POP_TOP              
 776: LOAD_GLOBAL          NULL + sum
 788: LOAD_GLOBAL          NULL + map
 800: LOAD_GLOBAL          len
 812: LOAD_FAST            cur_line
 814: PRECALL              
 818: CALL                 
 828: PRECALL              
 832: CALL                 
 842: STORE_FAST           cur_len
 844: LOAD_FAST            self
 846: LOAD_ATTR            drop_whitespace
 856: POP_JUMP_FORWARD_IF_FALSE to 976
 858: LOAD_FAST            cur_line
 860: POP_JUMP_FORWARD_IF_FALSE to 976
 862: LOAD_FAST            cur_line
 864: LOAD_CONST           -1
 866: BINARY_SUBSCR        
 876: LOAD_METHOD          strip
 898: PRECALL              
 902: CALL                 
 912: LOAD_CONST           ''
 914: COMPARE_OP           ==
 920: POP_JUMP_FORWARD_IF_FALSE to 976
 922: LOAD_FAST            cur_len
 924: LOAD_GLOBAL          NULL + len
 936: LOAD_FAST            cur_line
 938: LOAD_CONST           -1
 940: BINARY_SUBSCR        
 950: PRECALL              
 954: CALL                 
 964: BINARY_OP            -=
 968: STORE_FAST           cur_len
 970: LOAD_FAST            cur_line
 972: LOAD_CONST           -1
 974: DELETE_SUBSCR        
 976: LOAD_FAST            cur_line
 978: EXTENDED_ARG         
 980: POP_JUMP_FORWARD_IF_FALSE to 1838
 982: LOAD_FAST            self
 984: LOAD_ATTR            max_lines
 994: POP_JUMP_FORWARD_IF_NONE to 1170
 996: LOAD_GLOBAL          NULL + len
1008: LOAD_FAST            lines
1010: PRECALL              
1014: CALL                 
1024: LOAD_CONST           1
1026: BINARY_OP            +
1030: LOAD_FAST            self
1032: LOAD_ATTR            max_lines
1042: COMPARE_OP           <
1048: POP_JUMP_FORWARD_IF_TRUE to 1170
1050: LOAD_FAST            chunks
1052: POP_JUMP_FORWARD_IF_FALSE to 1158
1054: LOAD_FAST            self
1056: LOAD_ATTR            drop_whitespace
1066: POP_JUMP_FORWARD_IF_FALSE to 1260
1068: LOAD_GLOBAL          NULL + len
1080: LOAD_FAST            chunks
1082: PRECALL              
1086: CALL                 
1096: LOAD_CONST           1
1098: COMPARE_OP           ==
1104: POP_JUMP_FORWARD_IF_FALSE to 1260
1106: LOAD_FAST            chunks
1108: LOAD_CONST           0
1110: BINARY_SUBSCR        
1120: LOAD_METHOD          strip
1142: PRECALL              
1146: CALL                 
1156: POP_JUMP_FORWARD_IF_TRUE to 1260
1158: LOAD_FAST            cur_len
1160: LOAD_FAST            width
1162: COMPARE_OP           <=
1168: POP_JUMP_FORWARD_IF_FALSE to 1260
1170: LOAD_FAST            lines
1172: LOAD_METHOD          append
1194: LOAD_FAST            indent
1196: LOAD_CONST           ''
1198: LOAD_METHOD          join
1220: LOAD_FAST            cur_line
1222: PRECALL              
1226: CALL                 
1236: BINARY_OP            +
1240: PRECALL              
1244: CALL                 
1254: POP_TOP              
1256: EXTENDED_ARG         
1258: JUMP_FORWARD         to 1838
1260: LOAD_FAST            cur_line
1262: POP_JUMP_FORWARD_IF_FALSE to 1568
1264: LOAD_FAST            cur_line
1266: LOAD_CONST           -1
1268: BINARY_SUBSCR        
1278: LOAD_METHOD          strip
1300: PRECALL              
1304: CALL                 
1314: POP_JUMP_FORWARD_IF_FALSE to 1510
1316: LOAD_FAST            cur_len
1318: LOAD_GLOBAL          NULL + len
1330: LOAD_FAST            self
1332: LOAD_ATTR            placeholder
1342: PRECALL              
1346: CALL                 
1356: BINARY_OP            +
1360: LOAD_FAST            width
1362: COMPARE_OP           <=
1368: POP_JUMP_FORWARD_IF_FALSE to 1510
1370: LOAD_FAST            cur_line
1372: LOAD_METHOD          append
1394: LOAD_FAST            self
1396: LOAD_ATTR            placeholder
1406: PRECALL              
1410: CALL                 
1420: POP_TOP              
1422: LOAD_FAST            lines
1424: LOAD_METHOD          append
1446: LOAD_FAST            indent
1448: LOAD_CONST           ''
1450: LOAD_METHOD          join
1472: LOAD_FAST            cur_line
1474: PRECALL              
1478: CALL                 
1488: BINARY_OP            +
1492: PRECALL              
1496: CALL                 
1506: POP_TOP              
1508: JUMP_FORWARD         to 1836
1510: LOAD_FAST            cur_len
1512: LOAD_GLOBAL          NULL + len
1524: LOAD_FAST            cur_line
1526: LOAD_CONST           -1
1528: BINARY_SUBSCR        
1538: PRECALL              
1542: CALL                 
1552: BINARY_OP            -=
1556: STORE_FAST           cur_len
1558: LOAD_FAST            cur_line
1560: LOAD_CONST           -1
1562: DELETE_SUBSCR        
1564: LOAD_FAST            cur_line
1566: POP_JUMP_BACKWARD_IF_TRUE to 1264
1568: LOAD_FAST            lines
1570: POP_JUMP_FORWARD_IF_FALSE to 1742
1572: LOAD_FAST            lines
1574: LOAD_CONST           -1
1576: BINARY_SUBSCR        
1586: LOAD_METHOD          rstrip
1608: PRECALL              
1612: CALL                 
1622: STORE_FAST           prev_line
1624: LOAD_GLOBAL          NULL + len
1636: LOAD_FAST            prev_line
1638: PRECALL              
1642: CALL                 
1652: LOAD_GLOBAL          NULL + len
1664: LOAD_FAST            self
1666: LOAD_ATTR            placeholder
1676: PRECALL              
1680: CALL                 
1690: BINARY_OP            +
1694: LOAD_FAST            self
1696: LOAD_ATTR            width
1706: COMPARE_OP           <=
1712: POP_JUMP_FORWARD_IF_FALSE to 1742
1714: LOAD_FAST            prev_line
1716: LOAD_FAST            self
1718: LOAD_ATTR            placeholder
1728: BINARY_OP            +
1732: LOAD_FAST            lines
1734: LOAD_CONST           -1
1736: STORE_SUBSCR         
1740: JUMP_FORWARD         to 1844
1742: LOAD_FAST            lines
1744: LOAD_METHOD          append
1766: LOAD_FAST            indent
1768: LOAD_FAST            self
1770: LOAD_ATTR            placeholder
1780: LOAD_METHOD          lstrip
1802: PRECALL              
1806: CALL                 
1816: BINARY_OP            +
1820: PRECALL              
1824: CALL                 
1834: POP_TOP              
1836: JUMP_FORWARD         to 1844
1838: LOAD_FAST            chunks
1840: EXTENDED_ARG         
1842: POP_JUMP_BACKWARD_IF_TRUE to 342
1844: LOAD_FAST            lines
1846: RETURN_VALUE         
