# Disassembly for textwrap.fill
# From module file: textwrap

## co_consts:
("Fill a single paragraph of text, returning a new string.\n\n    Reformat the single paragraph in 'text' to fit in lines of no more\n    than 'width' columns, and return a new string containing the entire\n    wrapped paragraph.  As with wrap(), tabs are expanded and other\n    whitespace characters converted to space.  See TextWrapper class for\n    available keyword args to customize wrapping behaviour.\n    ", 'width', ())

## co_names:
('TextWrapper', 'fill')

## bytecode:

   0: RESUME               
   2: LOAD_GLOBAL          NULL + TextWrapper
  14: LOAD_CONST           ()
  16: LOAD_CONST           'width'
  18: LOAD_FAST            width
  20: BUILD_MAP            
  22: LOAD_FAST            kwargs
  24: DICT_MERGE           
  26: CALL_FUNCTION_EX     
  28: STORE_FAST           w
  30: LOAD_FAST            w
  32: LOAD_METHOD          fill
  54: LOAD_FAST            text
  56: PRECALL              
  60: CALL                 
  70: RETURN_VALUE         
