# Disassembly for textwrap.indent
# From module file: textwrap

## co_consts:
("Adds 'prefix' to the beginning of selected lines in 'text'.\n\n    If 'predicate' is provided, 'prefix' will only be added to the lines\n    where 'predicate(line)' is True. If 'predicate' is not provided,\n    it will default to adding 'prefix' to all non-empty lines that do not\n    consist solely of whitespace characters.\n    ", None, <code object predicate at 0x000002406945E880, file "textwrap.py", line 479>, <code object prefixed_lines at 0x0000024069419E90, file "textwrap.py", line 482>, '')

## co_names:
('join',)

## bytecode:

   0: MAKE_CELL            text
   2: MAKE_CELL            prefix
   4: MAKE_CELL            predicate
   6: RESUME               
   8: LOAD_DEREF           predicate
  10: POP_JUMP_FORWARD_IF_NOT_NONE to 18
  12: LOAD_CONST           <code object predicate at 0x000002406945E880, file "textwrap.py", line 479>
  14: MAKE_FUNCTION        
  16: STORE_DEREF          predicate
  18: LOAD_CLOSURE         predicate
  20: LOAD_CLOSURE         prefix
  22: LOAD_CLOSURE         text
  24: BUILD_TUPLE          
  26: LOAD_CONST           <code object prefixed_lines at 0x0000024069419E90, file "textwrap.py", line 482>
  28: MAKE_FUNCTION        closure
  30: STORE_FAST           prefixed_lines
  32: LOAD_CONST           ''
  34: LOAD_METHOD          join
  56: PUSH_NULL            
  58: LOAD_FAST            prefixed_lines
  60: PRECALL              
  64: CALL                 
  74: PRECALL              
  78: CALL                 
  88: RETURN_VALUE         
