# Disassembly for textwrap.TextWrapper.__init__
# From module file: textwrap

## co_consts:
(None,)

## co_names:
('width', 'initial_indent', 'subsequent_indent', 'expand_tabs', 'replace_whitespace', 'fix_sentence_endings', 'break_long_words', 'drop_whitespace', 'break_on_hyphens', 'tabsize', 'max_lines', 'placeholder')

## bytecode:

   0: RESUME               
   2: LOAD_FAST            width
   4: LOAD_FAST            self
   6: STORE_ATTR           width
  16: LOAD_FAST            initial_indent
  18: LOAD_FAST            self
  20: STORE_ATTR           initial_indent
  30: LOAD_FAST            subsequent_indent
  32: LOAD_FAST            self
  34: STORE_ATTR           subsequent_indent
  44: LOAD_FAST            expand_tabs
  46: LOAD_FAST            self
  48: STORE_ATTR           expand_tabs
  58: LOAD_FAST            replace_whitespace
  60: LOAD_FAST            self
  62: STORE_ATTR           replace_whitespace
  72: LOAD_FAST            fix_sentence_endings
  74: LOAD_FAST            self
  76: STORE_ATTR           fix_sentence_endings
  86: LOAD_FAST            break_long_words
  88: LOAD_FAST            self
  90: STORE_ATTR           break_long_words
 100: LOAD_FAST            drop_whitespace
 102: LOAD_FAST            self
 104: STORE_ATTR           drop_whitespace
 114: LOAD_FAST            break_on_hyphens
 116: LOAD_FAST            self
 118: STORE_ATTR           break_on_hyphens
 128: LOAD_FAST            tabsize
 130: LOAD_FAST            self
 132: STORE_ATTR           tabsize
 142: LOAD_FAST            max_lines
 144: LOAD_FAST            self
 146: STORE_ATTR           max_lines
 156: LOAD_FAST            placeholder
 158: LOAD_FAST            self
 160: STORE_ATTR           placeholder
 170: LOAD_CONST           None
 172: RETURN_VALUE         
