# Disassembly for textwrap.TextWrapper
# From module file: textwrap

## co_consts:
('TextWrapper', '\n    Object for wrapping/filling text.  The public interface consists of\n    the wrap() and fill() methods; the other methods are just there for\n    subclasses to override in order to tweak the default behaviour.\n    If you want to completely replace the main wrapping algorithm,\n    you\'ll probably have to override _wrap_chunks().\n\n    Several instance attributes control various aspects of wrapping:\n      width (default: 70)\n        the maximum width of wrapped lines (unless break_long_words\n        is false)\n      initial_indent (default: "")\n        string that will be prepended to the first line of wrapped\n        output.  Counts towards the line\'s width.\n      subsequent_indent (default: "")\n        string that will be prepended to all lines save the first\n        of wrapped output; also counts towards each line\'s width.\n      expand_tabs (default: true)\n        Expand tabs in input text to spaces before further processing.\n        Each tab will become 0 .. \'tabsize\' spaces, depending on its position\n        in its line.  If false, each tab is treated as a single character.\n      tabsize (default: 8)\n        Expand tabs in input text to 0 .. \'tabsize\' spaces, unless\n        \'expand_tabs\' is false.\n      replace_whitespace (default: true)\n        Replace all whitespace characters in the input text by spaces\n        after tab expansion.  Note that if expand_tabs is false and\n        replace_whitespace is true, every tab will be converted to a\n        single space!\n      fix_sentence_endings (default: false)\n        Ensure that sentence-ending punctuation is always followed\n        by two spaces.  Off by default because the algorithm is\n        (unavoidably) imperfect.\n      break_long_words (default: true)\n        Break words longer than \'width\'.  If false, those words will not\n        be broken, and some lines might be longer than \'width\'.\n      break_on_hyphens (default: true)\n        Allow breaking hyphenated words. If true, wrapping will occur\n        preferably on whitespaces and right after hyphens part of\n        compound words.\n      drop_whitespace (default: true)\n        Drop leading and trailing whitespace from lines.\n      max_lines (default: None)\n        Truncate wrapped lines.\n      placeholder (default: \' [...]\')\n        Append to the last line of truncated text.\n    ', ' ', '[\\w!"\\\'&.,?]', '[^\\d\\W]', '[%s]', '[^', 1, None, '\n        ( # any whitespace\n          %(ws)s+\n        | # em-dash between words\n          (?<=%(wp)s) -{2,} (?=\\w)\n        | # word, possibly hyphenated\n          %(nws)s+? (?:\n            # hyphenated word\n              -(?: (?<=%(lt)s{2}-) | (?<=%(lt)s-%(lt)s-))\n              (?= %(lt)s -? %(lt)s)\n            | # end of word\n              (?=%(ws)s|\\Z)\n            | # em-dash\n              (?<=%(wp)s) (?=-{2,}\\w)\n            )\n        )', ('wp', 'lt', 'ws', 'nws'), '(%s+)', '[a-z][\\.\\!\\?][\\"\\\']?\\Z', 70, '', True, False, 8, ' [...]', ('max_lines', 'placeholder'), <code object __init__ at 0x000002406921FE00, file "textwrap.py", line 112>, <code object _munge_whitespace at 0x00000240691F23A0, file "textwrap.py", line 143>, <code object _split at 0x00000240691C02F0, file "textwrap.py", line 157>, <code object _fix_sentence_endings at 0x00000240691F5BD0, file "textwrap.py", line 179>, <code object _handle_long_word at 0x0000024068E1B730, file "textwrap.py", line 197>, <code object _wrap_chunks at 0x0000024068E11050, file "textwrap.py", line 238>, <code object _split_chunks at 0x000002406944B660, file "textwrap.py", line 341>, <code object wrap at 0x00000240691F3B40, file "textwrap.py", line 347>, <code object fill at 0x000002406944BEE0, file "textwrap.py", line 361>, (70, '', '', True, True, False, True, True, True, 8))

## co_names:
('__name__', '__module__', '__qualname__', '__doc__', 'dict', 'fromkeys', 'map', 'ord', '_whitespace', 'unicode_whitespace_trans', 'word_punct', 'letter', 're', 'escape', 'whitespace', 'nowhitespace', 'compile', 'VERBOSE', 'wordsep_re', 'wordsep_simple_re', 'sentence_end_re', '__init__', '_munge_whitespace', '_split', '_fix_sentence_endings', '_handle_long_word', '_wrap_chunks', '_split_chunks', 'wrap', 'fill')

## bytecode:

   0: RESUME               
   2: LOAD_NAME            __name__
   4: STORE_NAME           __module__
   6: LOAD_CONST           'TextWrapper'
   8: STORE_NAME           __qualname__
  10: LOAD_CONST           '\n    Object for wrapping/filling text.  The public interface consists of\n    the wrap() and fill() methods; the other methods are just there for\n    subclasses to override in order to tweak the default behaviour.\n    If you want to completely replace the main wrapping algorithm,\n    you\'ll probably have to override _wrap_chunks().\n\n    Several instance attributes control various aspects of wrapping:\n      width (default: 70)\n        the maximum width of wrapped lines (unless break_long_words\n        is false)\n      initial_indent (default: "")\n        string that will be prepended to the first line of wrapped\n        output.  Counts towards the line\'s width.\n      subsequent_indent (default: "")\n        string that will be prepended to all lines save the first\n        of wrapped output; also counts towards each line\'s width.\n      expand_tabs (default: true)\n        Expand tabs in input text to spaces before further processing.\n        Each tab will become 0 .. \'tabsize\' spaces, depending on its position\n        in its line.  If false, each tab is treated as a single character.\n      tabsize (default: 8)\n        Expand tabs in input text to 0 .. \'tabsize\' spaces, unless\n        \'expand_tabs\' is false.\n      replace_whitespace (default: true)\n        Replace all whitespace characters in the input text by spaces\n        after tab expansion.  Note that if expand_tabs is false and\n        replace_whitespace is true, every tab will be converted to a\n        single space!\n      fix_sentence_endings (default: false)\n        Ensure that sentence-ending punctuation is always followed\n        by two spaces.  Off by default because the algorithm is\n        (unavoidably) imperfect.\n      break_long_words (default: true)\n        Break words longer than \'width\'.  If false, those words will not\n        be broken, and some lines might be longer than \'width\'.\n      break_on_hyphens (default: true)\n        Allow breaking hyphenated words. If true, wrapping will occur\n        preferably on whitespaces and right after hyphens part of\n        compound words.\n      drop_whitespace (default: true)\n        Drop leading and trailing whitespace from lines.\n      max_lines (default: None)\n        Truncate wrapped lines.\n      placeholder (default: \' [...]\')\n        Append to the last line of truncated text.\n    '
  12: STORE_NAME           __doc__
  14: LOAD_NAME            dict
  16: LOAD_METHOD          fromkeys
  38: PUSH_NULL            
  40: LOAD_NAME            map
  42: LOAD_NAME            ord
  44: LOAD_NAME            _whitespace
  46: PRECALL              
  50: CALL                 
  60: PUSH_NULL            
  62: LOAD_NAME            ord
  64: LOAD_CONST           ' '
  66: PRECALL              
  70: CALL                 
  80: PRECALL              
  84: CALL                 
  94: STORE_NAME           unicode_whitespace_trans
  96: LOAD_CONST           '[\\w!"\\\'&.,?]'
  98: STORE_NAME           word_punct
 100: LOAD_CONST           '[^\\d\\W]'
 102: STORE_NAME           letter
 104: LOAD_CONST           '[%s]'
 106: PUSH_NULL            
 108: LOAD_NAME            re
 110: LOAD_ATTR            escape
 120: LOAD_NAME            _whitespace
 122: PRECALL              
 126: CALL                 
 136: BINARY_OP            %
 140: STORE_NAME           whitespace
 142: LOAD_CONST           '[^'
 144: LOAD_NAME            whitespace
 146: LOAD_CONST           1
 148: LOAD_CONST           None
 150: BUILD_SLICE          
 152: BINARY_SUBSCR        
 162: BINARY_OP            +
 166: STORE_NAME           nowhitespace
 168: PUSH_NULL            
 170: LOAD_NAME            re
 172: LOAD_ATTR            compile
 182: LOAD_CONST           '\n        ( # any whitespace\n          %(ws)s+\n        | # em-dash between words\n          (?<=%(wp)s) -{2,} (?=\\w)\n        | # word, possibly hyphenated\n          %(nws)s+? (?:\n            # hyphenated word\n              -(?: (?<=%(lt)s{2}-) | (?<=%(lt)s-%(lt)s-))\n              (?= %(lt)s -? %(lt)s)\n            | # end of word\n              (?=%(ws)s|\\Z)\n            | # em-dash\n              (?<=%(wp)s) (?=-{2,}\\w)\n            )\n        )'
 184: LOAD_NAME            word_punct
 186: LOAD_NAME            letter
 188: LOAD_NAME            whitespace
 190: LOAD_NAME            nowhitespace
 192: LOAD_CONST           ('wp', 'lt', 'ws', 'nws')
 194: BUILD_CONST_KEY_MAP  
 196: BINARY_OP            %
 200: LOAD_NAME            re
 202: LOAD_ATTR            VERBOSE
 212: PRECALL              
 216: CALL                 
 226: STORE_NAME           wordsep_re
 228: DELETE_NAME          word_punct
 230: DELETE_NAME          letter
 232: DELETE_NAME          nowhitespace
 234: PUSH_NULL            
 236: LOAD_NAME            re
 238: LOAD_ATTR            compile
 248: LOAD_CONST           '(%s+)'
 250: LOAD_NAME            whitespace
 252: BINARY_OP            %
 256: PRECALL              
 260: CALL                 
 270: STORE_NAME           wordsep_simple_re
 272: DELETE_NAME          whitespace
 274: PUSH_NULL            
 276: LOAD_NAME            re
 278: LOAD_ATTR            compile
 288: LOAD_CONST           '[a-z][\\.\\!\\?][\\"\\\']?\\Z'
 290: PRECALL              
 294: CALL                 
 304: STORE_NAME           sentence_end_re
 306: NOP                  
 308: NOP                  
 310: NOP                  
 312: NOP                  
 314: NOP                  
 316: NOP                  
 318: NOP                  
 320: NOP                  
 322: NOP                  
 324: NOP                  
 326: LOAD_CONST           (70, '', '', True, True, False, True, True, True, 8)
 328: LOAD_CONST           None
 330: LOAD_CONST           ' [...]'
 332: LOAD_CONST           ('max_lines', 'placeholder')
 334: BUILD_CONST_KEY_MAP  
 336: LOAD_CONST           <code object __init__ at 0x000002406921FE00, file "textwrap.py", line 112>
 338: MAKE_FUNCTION        defaults, kwdefaults
 340: STORE_NAME           __init__
 342: LOAD_CONST           <code object _munge_whitespace at 0x00000240691F23A0, file "textwrap.py", line 143>
 344: MAKE_FUNCTION        
 346: STORE_NAME           _munge_whitespace
 348: LOAD_CONST           <code object _split at 0x00000240691C02F0, file "textwrap.py", line 157>
 350: MAKE_FUNCTION        
 352: STORE_NAME           _split
 354: LOAD_CONST           <code object _fix_sentence_endings at 0x00000240691F5BD0, file "textwrap.py", line 179>
 356: MAKE_FUNCTION        
 358: STORE_NAME           _fix_sentence_endings
 360: LOAD_CONST           <code object _handle_long_word at 0x0000024068E1B730, file "textwrap.py", line 197>
 362: MAKE_FUNCTION        
 364: STORE_NAME           _handle_long_word
 366: LOAD_CONST           <code object _wrap_chunks at 0x0000024068E11050, file "textwrap.py", line 238>
 368: MAKE_FUNCTION        
 370: STORE_NAME           _wrap_chunks
 372: LOAD_CONST           <code object _split_chunks at 0x000002406944B660, file "textwrap.py", line 341>
 374: MAKE_FUNCTION        
 376: STORE_NAME           _split_chunks
 378: LOAD_CONST           <code object wrap at 0x00000240691F3B40, file "textwrap.py", line 347>
 380: MAKE_FUNCTION        
 382: STORE_NAME           wrap
 384: LOAD_CONST           <code object fill at 0x000002406944BEE0, file "textwrap.py", line 361>
 386: MAKE_FUNCTION        
 388: STORE_NAME           fill
 390: LOAD_CONST           None
 392: RETURN_VALUE         
