# Disassembly for textwrap.TextWrapper._munge_whitespace
# From module file: textwrap

## co_consts:
('_munge_whitespace(text : string) -> string\n\n        Munge whitespace in text: expand tabs and convert all other\n        whitespace characters to spaces.  Eg. " foo\\tbar\\n\\nbaz"\n        becomes " foo    bar  baz".\n        ',)

## co_names:
('expand_tabs', 'expandtabs', 'tabsize', 'replace_whitespace', 'translate', 'unicode_whitespace_trans')

## bytecode:

   0: RESUME               
   2: LOAD_FAST            self
   4: LOAD_ATTR            expand_tabs
  14: POP_JUMP_FORWARD_IF_FALSE to 68
  16: LOAD_FAST            text
  18: LOAD_METHOD          expandtabs
  40: LOAD_FAST            self
  42: LOAD_ATTR            tabsize
  52: PRECALL              
  56: CALL                 
  66: STORE_FAST           text
  68: LOAD_FAST            self
  70: LOAD_ATTR            replace_whitespace
  80: POP_JUMP_FORWARD_IF_FALSE to 134
  82: LOAD_FAST            text
  84: LOAD_METHOD          translate
 106: LOAD_FAST            self
 108: LOAD_ATTR            unicode_whitespace_trans
 118: PRECALL              
 122: CALL                 
 132: STORE_FAST           text
 134: LOAD_FAST            text
 136: RETURN_VALUE         
