# Disassembly for textwrap.TextWrapper._split_chunks
# From module file: textwrap

## co_consts:
(None,)

## co_names:
('_munge_whitespace', '_split')

## bytecode:

   0: RESUME               
   2: LOAD_FAST            self
   4: LOAD_METHOD          _munge_whitespace
  26: LOAD_FAST            text
  28: PRECALL              
  32: CALL                 
  42: STORE_FAST           text
  44: LOAD_FAST            self
  46: LOAD_METHOD          _split
  68: LOAD_FAST            text
  70: PRECALL              
  74: CALL                 
  84: RETURN_VALUE         
