# Disassembly for base64._b32encode.<listcomp>
# From module file: base64

## co_consts:
()

## co_names:
()

## bytecode:

   0: COPY_FREE_VARS       
   2: RESUME               
   4: BUILD_LIST           
   6: LOAD_FAST            .0
   8: FOR_ITER             to 34
  10: STORE_FAST           a
  12: LOAD_DEREF           b32tab
  14: GET_ITER             
  16: FOR_ITER             to 32
  18: STORE_FAST           b
  20: LOAD_FAST            a
  22: LOAD_FAST            b
  24: BINARY_OP            +
  28: LIST_APPEND          
  30: JUMP_BACKWARD        to 16
  32: JUMP_BACKWARD        to 8
  34: RETURN_VALUE         
