# Disassembly for base64.b85encode
# From module file: base64

## co_consts:
("Encode bytes-like object b in base85 format and return a bytes object.\n\n    If pad is true, the input is padded with b'\\0' so its length is a multiple of\n    4 bytes before encoding.\n    ", None, <code object <listcomp> at 0x000002406945E1F0, file "base64.py", line 457>, <code object <listcomp> at 0x000002406945E2E0, file "base64.py", line 458>)

## co_names:
('_b85chars2', '_b85alphabet', '_b85chars', '_85encode')

## bytecode:

   0: RESUME               
   2: LOAD_GLOBAL          _b85chars2
  14: POP_JUMP_FORWARD_IF_NOT_NONE to 84
  16: LOAD_CONST           <code object <listcomp> at 0x000002406945E1F0, file "base64.py", line 457>
  18: MAKE_FUNCTION        
  20: LOAD_GLOBAL          _b85alphabet
  32: GET_ITER             
  34: PRECALL              
  38: CALL                 
  48: STORE_GLOBAL         _b85chars
  50: LOAD_CONST           <code object <listcomp> at 0x000002406945E2E0, file "base64.py", line 458>
  52: MAKE_FUNCTION        
  54: LOAD_GLOBAL          _b85chars
  66: GET_ITER             
  68: PRECALL              
  72: CALL                 
  82: STORE_GLOBAL         _b85chars2
  84: LOAD_GLOBAL          NULL + _85encode
  96: LOAD_FAST            b
  98: LOAD_GLOBAL          _b85chars
 110: LOAD_GLOBAL          _b85chars2
 122: LOAD_FAST            pad
 124: PRECALL              
 128: CALL                 
 138: RETURN_VALUE         
