# Disassembly for base64.encode
# From module file: base64

## co_consts:
('Encode a file; input and output are binary files.', True, None)

## co_names:
('read', 'MAXBINSIZE', 'len', 'binascii', 'b2a_base64', 'write')

## bytecode:

   0: RESUME               
   2: NOP                  
   4: LOAD_FAST            input
   6: LOAD_METHOD          read
  28: LOAD_GLOBAL          MAXBINSIZE
  40: PRECALL              
  44: CALL                 
  54: STORE_FAST           s
  56: LOAD_FAST            s
  58: POP_JUMP_FORWARD_IF_TRUE to 64
  60: LOAD_CONST           None
  62: RETURN_VALUE         
  64: LOAD_GLOBAL          NULL + len
  76: LOAD_FAST            s
  78: PRECALL              
  82: CALL                 
  92: LOAD_GLOBAL          MAXBINSIZE
 104: COMPARE_OP           <
 110: POP_JUMP_FORWARD_IF_FALSE to 260
 112: LOAD_FAST            input
 114: LOAD_METHOD          read
 136: LOAD_GLOBAL          MAXBINSIZE
 148: LOAD_GLOBAL          NULL + len
 160: LOAD_FAST            s
 162: PRECALL              
 166: CALL                 
 176: BINARY_OP            -
 180: PRECALL              
 184: CALL                 
 194: STORE_FAST           ns
 196: LOAD_FAST            ns
 198: POP_JUMP_FORWARD_IF_TRUE to 202
 200: JUMP_FORWARD         to 260
 202: LOAD_FAST            s
 204: LOAD_FAST            ns
 206: BINARY_OP            +=
 210: STORE_FAST           s
 212: LOAD_GLOBAL          NULL + len
 224: LOAD_FAST            s
 226: PRECALL              
 230: CALL                 
 240: LOAD_GLOBAL          MAXBINSIZE
 252: COMPARE_OP           <
 258: POP_JUMP_BACKWARD_IF_TRUE to 112
 260: LOAD_GLOBAL          NULL + binascii
 272: LOAD_ATTR            b2a_base64
 282: LOAD_FAST            s
 284: PRECALL              
 288: CALL                 
 298: STORE_FAST           line
 300: LOAD_FAST            output
 302: LOAD_METHOD          write
 324: LOAD_FAST            line
 326: PRECALL              
 330: CALL                 
 340: POP_TOP              
 342: JUMP_BACKWARD        to 4
