# Disassembly for base64.decodebytes
# From module file: base64

## co_consts:
('Decode a bytestring of base-64 data into a bytes object.',)

## co_names:
('_input_type_check', 'binascii', 'a2b_base64')

## bytecode:

   0: RESUME               
   2: LOAD_GLOBAL          NULL + _input_type_check
  14: LOAD_FAST            s
  16: PRECALL              
  20: CALL                 
  30: POP_TOP              
  32: LOAD_GLOBAL          NULL + binascii
  44: LOAD_ATTR            a2b_base64
  54: LOAD_FAST            s
  56: PRECALL              
  60: CALL                 
  70: RETURN_VALUE         
