# Disassembly for base64.a85encode
# From module file: base64

## co_consts:
('Encode bytes-like object b using Ascii85 and return a bytes object.\n\n    foldspaces is an optional flag that uses the special short sequence \'y\'\n    instead of 4 consecutive spaces (ASCII 0x20) as supported by \'btoa\'. This\n    feature is not supported by the "standard" Adobe encoding.\n\n    wrapcol controls whether the output should have newline (b\'\\n\') characters\n    added to it. If this is non-zero, each output line will be at most this\n    many characters long.\n\n    pad controls whether the input is padded to a multiple of 4 before\n    encoding. Note that the btoa implementation always pads.\n\n    adobe controls whether the encoded byte sequence is framed with <~ and ~>,\n    which is used by the Adobe implementation.\n    ', None, <code object <listcomp> at 0x000002406945DE30, file "base64.py", line 349>, 33, 118, <code object <listcomp> at 0x000002406945DF20, file "base64.py", line 350>, True, 2, 1, <code object <listcomp> at 0x000002406945E010, file "base64.py", line 358>, 0, -1, b'', b'\n')

## co_names:
('_a85chars2', 'range', '_a85chars', '_85encode', '_A85START', 'max', 'len', 'append', 'join', '_A85END')

## bytecode:

   0: MAKE_CELL            wrapcol
   2: MAKE_CELL            result
   4: RESUME               
   6: LOAD_GLOBAL          _a85chars2
  18: POP_JUMP_FORWARD_IF_NOT_NONE to 106
  20: LOAD_CONST           <code object <listcomp> at 0x000002406945DE30, file "base64.py", line 349>
  22: MAKE_FUNCTION        
  24: LOAD_GLOBAL          NULL + range
  36: LOAD_CONST           33
  38: LOAD_CONST           118
  40: PRECALL              
  44: CALL                 
  54: GET_ITER             
  56: PRECALL              
  60: CALL                 
  70: STORE_GLOBAL         _a85chars
  72: LOAD_CONST           <code object <listcomp> at 0x000002406945DF20, file "base64.py", line 350>
  74: MAKE_FUNCTION        
  76: LOAD_GLOBAL          _a85chars
  88: GET_ITER             
  90: PRECALL              
  94: CALL                 
 104: STORE_GLOBAL         _a85chars2
 106: LOAD_GLOBAL          NULL + _85encode
 118: LOAD_FAST            b
 120: LOAD_GLOBAL          _a85chars
 132: LOAD_GLOBAL          _a85chars2
 144: LOAD_FAST            pad
 146: LOAD_CONST           True
 148: LOAD_FAST            foldspaces
 150: PRECALL              
 154: CALL                 
 164: STORE_DEREF          result
 166: LOAD_FAST            adobe
 168: POP_JUMP_FORWARD_IF_FALSE to 190
 170: LOAD_GLOBAL          _A85START
 182: LOAD_DEREF           result
 184: BINARY_OP            +
 188: STORE_DEREF          result
 190: LOAD_DEREF           wrapcol
 192: POP_JUMP_FORWARD_IF_FALSE to 464
 194: LOAD_GLOBAL          NULL + max
 206: LOAD_FAST            adobe
 208: POP_JUMP_FORWARD_IF_FALSE to 214
 210: LOAD_CONST           2
 212: JUMP_FORWARD         to 216
 214: LOAD_CONST           1
 216: LOAD_DEREF           wrapcol
 218: PRECALL              
 222: CALL                 
 232: STORE_DEREF          wrapcol
 234: LOAD_CLOSURE         result
 236: LOAD_CLOSURE         wrapcol
 238: BUILD_TUPLE          
 240: LOAD_CONST           <code object <listcomp> at 0x000002406945E010, file "base64.py", line 358>
 242: MAKE_FUNCTION        closure
 244: LOAD_GLOBAL          NULL + range
 256: LOAD_CONST           0
 258: LOAD_GLOBAL          NULL + len
 270: LOAD_DEREF           result
 272: PRECALL              
 276: CALL                 
 286: LOAD_DEREF           wrapcol
 288: PRECALL              
 292: CALL                 
 302: GET_ITER             
 304: PRECALL              
 308: CALL                 
 318: STORE_FAST           chunks
 320: LOAD_FAST            adobe
 322: POP_JUMP_FORWARD_IF_FALSE to 422
 324: LOAD_GLOBAL          NULL + len
 336: LOAD_FAST            chunks
 338: LOAD_CONST           -1
 340: BINARY_SUBSCR        
 350: PRECALL              
 354: CALL                 
 364: LOAD_CONST           2
 366: BINARY_OP            +
 370: LOAD_DEREF           wrapcol
 372: COMPARE_OP           >
 378: POP_JUMP_FORWARD_IF_FALSE to 422
 380: LOAD_FAST            chunks
 382: LOAD_METHOD          append
 404: LOAD_CONST           b''
 406: PRECALL              
 410: CALL                 
 420: POP_TOP              
 422: LOAD_CONST           b'\n'
 424: LOAD_METHOD          join
 446: LOAD_FAST            chunks
 448: PRECALL              
 452: CALL                 
 462: STORE_DEREF          result
 464: LOAD_FAST            adobe
 466: POP_JUMP_FORWARD_IF_FALSE to 488
 468: LOAD_DEREF           result
 470: LOAD_GLOBAL          _A85END
 482: BINARY_OP            +=
 486: STORE_DEREF          result
 488: LOAD_DEREF           result
 490: RETURN_VALUE         
