# Disassembly for base64
# From module file: base64

## co_consts:
('Base16, Base32, Base64 (RFC 3548), Base85 and Ascii85 data encodings', 0, None, ('encode', 'decode', 'encodebytes', 'decodebytes', 'b64encode', 'b64decode', 'b32encode', 'b32decode', 'b32hexencode', 'b32hexdecode', 'b16encode', 'b16decode', 'b85encode', 'b85decode', 'a85encode', 'a85decode', 'standard_b64encode', 'standard_b64decode', 'urlsafe_b64encode', 'urlsafe_b64decode'), <code object _bytes_from_decode_data at 0x0000024068E223E0, file "base64.py", line 34>, <code object b64encode at 0x00000240691F56F0, file "base64.py", line 51>, False, <code object b64decode at 0x000002406947C5D0, file "base64.py", line 65>, <code object standard_b64encode at 0x00000240694657D0, file "base64.py", line 91>, <code object standard_b64decode at 0x0000024069465450, file "base64.py", line 98>, b'+/', b'-_', <code object urlsafe_b64encode at 0x000002406944A450, file "base64.py", line 112>, <code object urlsafe_b64decode at 0x00000240693D22A0, file "base64.py", line 121>, '\nEncode the bytes-like objects using {encoding} and return a bytes object.\n', '\nDecode the {encoding} encoded bytes-like object or ASCII string s.\n\nOptional casefold is a flag specifying whether a lowercase alphabet is\nacceptable as input.  For security purposes, the default is False.\n{extra_args}\nThe result is returned as a bytes object.  A binascii.Error is raised if\nthe input is incorrectly padded or if there are non-alphabet\ncharacters present in the input.\n', '\nRFC 3548 allows for optional mapping of the digit 0 (zero) to the\nletter O (oh), and for optional mapping of the digit 1 (one) to\neither the letter I (eye) or letter L (el).  The optional argument\nmap01 when not None, specifies which letter the digit 1 should be\nmapped to (when map01 is not None, the digit 0 is always mapped to\nthe letter O).  For security purposes the default is None, so that\n0 and 1 are not allowed in the input.\n', b'ABCDEFGHIJKLMNOPQRSTUVWXYZ234567', b'0123456789ABCDEFGHIJKLMNOPQRSTUV', <code object _b32encode at 0x0000024068C38030, file "base64.py", line 166>, <code object _b32decode at 0x0000024068E94EF0, file "base64.py", line 202>, <code object b32encode at 0x000002406945D980, file "base64.py", line 249>, 'base32', ('encoding',), <code object b32decode at 0x000002406945DA70, file "base64.py", line 253>, ('encoding', 'extra_args'), <code object b32hexencode at 0x000002406945DB60, file "base64.py", line 258>, 'base32hex', <code object b32hexdecode at 0x000002406945DD40, file "base64.py", line 262>, '', <code object b16encode at 0x000002406944A560, file "base64.py", line 272>, <code object b16decode at 0x00000240691E8F30, file "base64.py", line 278>, b'<~', b'~>', <code object _85encode at 0x0000024068D31100, file "base64.py", line 304>, ('foldspaces', 'wrapcol', 'pad', 'adobe'), <code object a85encode at 0x0000024068E7B900, file "base64.py", line 328>, b' \t\n\r\x0b', ('foldspaces', 'adobe', 'ignorechars'), <code object a85decode at 0x0000024068E17000, file "base64.py", line 369>, b'0123456789ABCDEFGHIJKLMNOPQRSTUVWXYZabcdefghijklmnopqrstuvwxyz!#$%&()*+-;<=>?@^_`{|}~', <code object b85encode at 0x00000240691F3B40, file "base64.py", line 447>, <code object b85decode at 0x0000024068CE2D90, file "base64.py", line 461>, 76, 4, 3, <code object encode at 0x0000024068E22E80, file "base64.py", line 509>, <code object decode at 0x00000240693AAAB0, file "base64.py", line 524>, <code object _input_type_check at 0x0000024069CD8E30, file "base64.py", line 533>, <code object encodebytes at 0x00000240691DAD80, file "base64.py", line 549>, <code object decodebytes at 0x00000240693EAA30, file "base64.py", line 560>, <code object main at 0x0000024068CE1ED0, file "base64.py", line 567>, <code object test at 0x00000240694981F0, file "base64.py", line 596>, '__main__', (None,), (None, False), (False, None), (False,), (False, False, False))

## co_names:
('__doc__', 're', 'struct', 'binascii', '__all__', 'bytes', 'bytearray', 'bytes_types', '_bytes_from_decode_data', 'b64encode', 'b64decode', 'standard_b64encode', 'standard_b64decode', 'maketrans', '_urlsafe_encode_translation', '_urlsafe_decode_translation', 'urlsafe_b64encode', 'urlsafe_b64decode', '_B32_ENCODE_DOCSTRING', '_B32_DECODE_DOCSTRING', '_B32_DECODE_MAP01_DOCSTRING', '_b32alphabet', '_b32hexalphabet', '_b32tab2', '_b32rev', '_b32encode', '_b32decode', 'b32encode', 'format', 'b32decode', 'b32hexencode', 'b32hexdecode', 'b16encode', 'b16decode', '_a85chars', '_a85chars2', '_A85START', '_A85END', '_85encode', 'a85encode', 'a85decode', '_b85alphabet', '_b85chars', '_b85chars2', '_b85dec', 'b85encode', 'b85decode', 'MAXLINESIZE', 'MAXBINSIZE', 'encode', 'decode', '_input_type_check', 'encodebytes', 'decodebytes', 'main', 'test', '__name__')

## bytecode:

   0: RESUME               
   2: LOAD_CONST           'Base16, Base32, Base64 (RFC 3548), Base85 and Ascii85 data encodings'
   4: STORE_NAME           __doc__
   6: LOAD_CONST           0
   8: LOAD_CONST           None
  10: IMPORT_NAME          re
  12: STORE_NAME           re
  14: LOAD_CONST           0
  16: LOAD_CONST           None
  18: IMPORT_NAME          struct
  20: STORE_NAME           struct
  22: LOAD_CONST           0
  24: LOAD_CONST           None
  26: IMPORT_NAME          binascii
  28: STORE_NAME           binascii
  30: BUILD_LIST           
  32: LOAD_CONST           ('encode', 'decode', 'encodebytes', 'decodebytes', 'b64encode', 'b64decode', 'b32encode', 'b32decode', 'b32hexencode', 'b32hexdecode', 'b16encode', 'b16decode', 'b85encode', 'b85decode', 'a85encode', 'a85decode', 'standard_b64encode', 'standard_b64decode', 'urlsafe_b64encode', 'urlsafe_b64decode')
  34: LIST_EXTEND          
  36: STORE_NAME           __all__
  38: LOAD_NAME            bytes
  40: LOAD_NAME            bytearray
  42: BUILD_TUPLE          
  44: STORE_NAME           bytes_types
  46: LOAD_CONST           <code object _bytes_from_decode_data at 0x0000024068E223E0, file "base64.py", line 34>
  48: MAKE_FUNCTION        
  50: STORE_NAME           _bytes_from_decode_data
  52: LOAD_CONST           (None,)
  54: LOAD_CONST           <code object b64encode at 0x00000240691F56F0, file "base64.py", line 51>
  56: MAKE_FUNCTION        defaults
  58: STORE_NAME           b64encode
  60: LOAD_CONST           (None, False)
  62: LOAD_CONST           <code object b64decode at 0x000002406947C5D0, file "base64.py", line 65>
  64: MAKE_FUNCTION        defaults
  66: STORE_NAME           b64decode
  68: LOAD_CONST           <code object standard_b64encode at 0x00000240694657D0, file "base64.py", line 91>
  70: MAKE_FUNCTION        
  72: STORE_NAME           standard_b64encode
  74: LOAD_CONST           <code object standard_b64decode at 0x0000024069465450, file "base64.py", line 98>
  76: MAKE_FUNCTION        
  78: STORE_NAME           standard_b64decode
  80: LOAD_NAME            bytes
  82: LOAD_METHOD          maketrans
 104: LOAD_CONST           b'+/'
 106: LOAD_CONST           b'-_'
 108: PRECALL              
 112: CALL                 
 122: STORE_NAME           _urlsafe_encode_translation
 124: LOAD_NAME            bytes
 126: LOAD_METHOD          maketrans
 148: LOAD_CONST           b'-_'
 150: LOAD_CONST           b'+/'
 152: PRECALL              
 156: CALL                 
 166: STORE_NAME           _urlsafe_decode_translation
 168: LOAD_CONST           <code object urlsafe_b64encode at 0x000002406944A450, file "base64.py", line 112>
 170: MAKE_FUNCTION        
 172: STORE_NAME           urlsafe_b64encode
 174: LOAD_CONST           <code object urlsafe_b64decode at 0x00000240693D22A0, file "base64.py", line 121>
 176: MAKE_FUNCTION        
 178: STORE_NAME           urlsafe_b64decode
 180: LOAD_CONST           '\nEncode the bytes-like objects using {encoding} and return a bytes object.\n'
 182: STORE_NAME           _B32_ENCODE_DOCSTRING
 184: LOAD_CONST           '\nDecode the {encoding} encoded bytes-like object or ASCII string s.\n\nOptional casefold is a flag specifying whether a lowercase alphabet is\nacceptable as input.  For security purposes, the default is False.\n{extra_args}\nThe result is returned as a bytes object.  A binascii.Error is raised if\nthe input is incorrectly padded or if there are non-alphabet\ncharacters present in the input.\n'
 186: STORE_NAME           _B32_DECODE_DOCSTRING
 188: LOAD_CONST           '\nRFC 3548 allows for optional mapping of the digit 0 (zero) to the\nletter O (oh), and for optional mapping of the digit 1 (one) to\neither the letter I (eye) or letter L (el).  The optional argument\nmap01 when not None, specifies which letter the digit 1 should be\nmapped to (when map01 is not None, the digit 0 is always mapped to\nthe letter O).  For security purposes the default is None, so that\n0 and 1 are not allowed in the input.\n'
 190: STORE_NAME           _B32_DECODE_MAP01_DOCSTRING
 192: LOAD_CONST           b'ABCDEFGHIJKLMNOPQRSTUVWXYZ234567'
 194: STORE_NAME           _b32alphabet
 196: LOAD_CONST           b'0123456789ABCDEFGHIJKLMNOPQRSTUV'
 198: STORE_NAME           _b32hexalphabet
 200: BUILD_MAP            
 202: STORE_GLOBAL         _b32tab2
 204: BUILD_MAP            
 206: STORE_GLOBAL         _b32rev
 208: LOAD_CONST           <code object _b32encode at 0x0000024068C38030, file "base64.py", line 166>
 210: MAKE_FUNCTION        
 212: STORE_NAME           _b32encode
 214: LOAD_CONST           (False, None)
 216: LOAD_CONST           <code object _b32decode at 0x0000024068E94EF0, file "base64.py", line 202>
 218: MAKE_FUNCTION        defaults
 220: STORE_NAME           _b32decode
 222: LOAD_CONST           <code object b32encode at 0x000002406945D980, file "base64.py", line 249>
 224: MAKE_FUNCTION        
 226: STORE_NAME           b32encode
 228: LOAD_NAME            _B32_ENCODE_DOCSTRING
 230: LOAD_METHOD          format
 252: LOAD_CONST           'base32'
 254: KW_NAMES             
 256: PRECALL              
 260: CALL                 
 270: LOAD_NAME            b32encode
 272: STORE_ATTR           __doc__
 282: LOAD_CONST           (False, None)
 284: LOAD_CONST           <code object b32decode at 0x000002406945DA70, file "base64.py", line 253>
 286: MAKE_FUNCTION        defaults
 288: STORE_NAME           b32decode
 290: LOAD_NAME            _B32_DECODE_DOCSTRING
 292: LOAD_METHOD          format
 314: LOAD_CONST           'base32'
 316: LOAD_NAME            _B32_DECODE_MAP01_DOCSTRING
 318: KW_NAMES             
 320: PRECALL              
 324: CALL                 
 334: LOAD_NAME            b32decode
 336: STORE_ATTR           __doc__
 346: LOAD_CONST           <code object b32hexencode at 0x000002406945DB60, file "base64.py", line 258>
 348: MAKE_FUNCTION        
 350: STORE_NAME           b32hexencode
 352: LOAD_NAME            _B32_ENCODE_DOCSTRING
 354: LOAD_METHOD          format
 376: LOAD_CONST           'base32hex'
 378: KW_NAMES             
 380: PRECALL              
 384: CALL                 
 394: LOAD_NAME            b32hexencode
 396: STORE_ATTR           __doc__
 406: LOAD_CONST           (False,)
 408: LOAD_CONST           <code object b32hexdecode at 0x000002406945DD40, file "base64.py", line 262>
 410: MAKE_FUNCTION        defaults
 412: STORE_NAME           b32hexdecode
 414: LOAD_NAME            _B32_DECODE_DOCSTRING
 416: LOAD_METHOD          format
 438: LOAD_CONST           'base32hex'
 440: LOAD_CONST           ''
 442: KW_NAMES             
 444: PRECALL              
 448: CALL                 
 458: LOAD_NAME            b32hexdecode
 460: STORE_ATTR           __doc__
 470: LOAD_CONST           <code object b16encode at 0x000002406944A560, file "base64.py", line 272>
 472: MAKE_FUNCTION        
 474: STORE_NAME           b16encode
 476: LOAD_CONST           (False,)
 478: LOAD_CONST           <code object b16decode at 0x00000240691E8F30, file "base64.py", line 278>
 480: MAKE_FUNCTION        defaults
 482: STORE_NAME           b16decode
 484: LOAD_CONST           None
 486: STORE_GLOBAL         _a85chars
 488: LOAD_CONST           None
 490: STORE_GLOBAL         _a85chars2
 492: LOAD_CONST           b'<~'
 494: STORE_NAME           _A85START
 496: LOAD_CONST           b'~>'
 498: STORE_NAME           _A85END
 500: LOAD_CONST           (False, False, False)
 502: LOAD_CONST           <code object _85encode at 0x0000024068D31100, file "base64.py", line 304>
 504: MAKE_FUNCTION        defaults
 506: STORE_NAME           _85encode
 508: LOAD_CONST           False
 510: LOAD_CONST           0
 512: LOAD_CONST           False
 514: LOAD_CONST           False
 516: LOAD_CONST           ('foldspaces', 'wrapcol', 'pad', 'adobe')
 518: BUILD_CONST_KEY_MAP  
 520: LOAD_CONST           <code object a85encode at 0x0000024068E7B900, file "base64.py", line 328>
 522: MAKE_FUNCTION        kwdefaults
 524: STORE_NAME           a85encode
 526: LOAD_CONST           False
 528: LOAD_CONST           False
 530: LOAD_CONST           b' \t\n\r\x0b'
 532: LOAD_CONST           ('foldspaces', 'adobe', 'ignorechars')
 534: BUILD_CONST_KEY_MAP  
 536: LOAD_CONST           <code object a85decode at 0x0000024068E17000, file "base64.py", line 369>
 538: MAKE_FUNCTION        kwdefaults
 540: STORE_NAME           a85decode
 542: LOAD_CONST           b'0123456789ABCDEFGHIJKLMNOPQRSTUVWXYZabcdefghijklmnopqrstuvwxyz!#$%&()*+-;<=>?@^_`{|}~'
 544: STORE_NAME           _b85alphabet
 546: LOAD_CONST           None
 548: STORE_GLOBAL         _b85chars
 550: LOAD_CONST           None
 552: STORE_GLOBAL         _b85chars2
 554: LOAD_CONST           None
 556: STORE_GLOBAL         _b85dec
 558: LOAD_CONST           (False,)
 560: LOAD_CONST           <code object b85encode at 0x00000240691F3B40, file "base64.py", line 447>
 562: MAKE_FUNCTION        defaults
 564: STORE_NAME           b85encode
 566: LOAD_CONST           <code object b85decode at 0x0000024068CE2D90, file "base64.py", line 461>
 568: MAKE_FUNCTION        
 570: STORE_NAME           b85decode
 572: LOAD_CONST           76
 574: STORE_NAME           MAXLINESIZE
 576: LOAD_NAME            MAXLINESIZE
 578: LOAD_CONST           4
 580: BINARY_OP            //
 584: LOAD_CONST           3
 586: BINARY_OP            *
 590: STORE_NAME           MAXBINSIZE
 592: LOAD_CONST           <code object encode at 0x0000024068E22E80, file "base64.py", line 509>
 594: MAKE_FUNCTION        
 596: STORE_NAME           encode
 598: LOAD_CONST           <code object decode at 0x00000240693AAAB0, file "base64.py", line 524>
 600: MAKE_FUNCTION        
 602: STORE_NAME           decode
 604: LOAD_CONST           <code object _input_type_check at 0x0000024069CD8E30, file "base64.py", line 533>
 606: MAKE_FUNCTION        
 608: STORE_NAME           _input_type_check
 610: LOAD_CONST           <code object encodebytes at 0x00000240691DAD80, file "base64.py", line 549>
 612: MAKE_FUNCTION        
 614: STORE_NAME           encodebytes
 616: LOAD_CONST           <code object decodebytes at 0x00000240693EAA30, file "base64.py", line 560>
 618: MAKE_FUNCTION        
 620: STORE_NAME           decodebytes
 622: LOAD_CONST           <code object main at 0x0000024068CE1ED0, file "base64.py", line 567>
 624: MAKE_FUNCTION        
 626: STORE_NAME           main
 628: LOAD_CONST           <code object test at 0x00000240694981F0, file "base64.py", line 596>
 630: MAKE_FUNCTION        
 632: STORE_NAME           test
 634: LOAD_NAME            __name__
 636: LOAD_CONST           '__main__'
 638: COMPARE_OP           ==
 644: POP_JUMP_FORWARD_IF_FALSE to 670
 646: PUSH_NULL            
 648: LOAD_NAME            main
 650: PRECALL              
 654: CALL                 
 664: POP_TOP              
 666: LOAD_CONST           None
 668: RETURN_VALUE         
 670: LOAD_CONST           None
 672: RETURN_VALUE         
