# Disassembly for base64.urlsafe_b64decode
# From module file: base64

## co_consts:
("Decode bytes using the URL- and filesystem-safe Base64 alphabet.\n\n    Argument s is a bytes-like object or ASCII string to decode.  The result\n    is returned as a bytes object.  A binascii.Error is raised if the input\n    is incorrectly padded.  Characters that are not in the URL-safe base-64\n    alphabet, and are not a plus '+' or slash '/', are discarded prior to the\n    padding check.\n\n    The alphabet uses '-' instead of '+' and '_' instead of '/'.\n    ",)

## co_names:
('_bytes_from_decode_data', 'translate', '_urlsafe_decode_translation', 'b64decode')

## bytecode:

   0: RESUME               
   2: LOAD_GLOBAL          NULL + _bytes_from_decode_data
  14: LOAD_FAST            s
  16: PRECALL              
  20: CALL                 
  30: STORE_FAST           s
  32: LOAD_FAST            s
  34: LOAD_METHOD          translate
  56: LOAD_GLOBAL          _urlsafe_decode_translation
  68: PRECALL              
  72: CALL                 
  82: STORE_FAST           s
  84: LOAD_GLOBAL          NULL + b64decode
  96: LOAD_FAST            s
  98: PRECALL              
 102: CALL                 
 112: RETURN_VALUE         
