# Disassembly for base64.encodebytes
# From module file: base64

## co_consts:
('Encode a bytestring into a bytes object containing multiple lines\n    of base-64 data.', 0, b'')

## co_names:
('_input_type_check', 'range', 'len', 'MAXBINSIZE', 'append', 'binascii', 'b2a_base64', 'join')

## bytecode:

   0: RESUME               
   2: LOAD_GLOBAL          NULL + _input_type_check
  14: LOAD_FAST            s
  16: PRECALL              
  20: CALL                 
  30: POP_TOP              
  32: BUILD_LIST           
  34: STORE_FAST           pieces
  36: LOAD_GLOBAL          NULL + range
  48: LOAD_CONST           0
  50: LOAD_GLOBAL          NULL + len
  62: LOAD_FAST            s
  64: PRECALL              
  68: CALL                 
  78: LOAD_GLOBAL          MAXBINSIZE
  90: PRECALL              
  94: CALL                 
 104: GET_ITER             
 106: FOR_ITER             to 226
 108: STORE_FAST           i
 110: LOAD_FAST            s
 112: LOAD_FAST            i
 114: LOAD_FAST            i
 116: LOAD_GLOBAL          MAXBINSIZE
 128: BINARY_OP            +
 132: BUILD_SLICE          
 134: BINARY_SUBSCR        
 144: STORE_FAST           chunk
 146: LOAD_FAST            pieces
 148: LOAD_METHOD          append
 170: LOAD_GLOBAL          NULL + binascii
 182: LOAD_ATTR            b2a_base64
 192: LOAD_FAST            chunk
 194: PRECALL              
 198: CALL                 
 208: PRECALL              
 212: CALL                 
 222: POP_TOP              
 224: JUMP_BACKWARD        to 106
 226: LOAD_CONST           b''
 228: LOAD_METHOD          join
 250: LOAD_FAST            pieces
 252: PRECALL              
 256: CALL                 
 266: RETURN_VALUE         
