# Disassembly for datetime.date
# From module file: datetime

## co_consts:
('date', 'Concrete date type.\n\n    Constructors:\n\n    __new__()\n    fromtimestamp()\n    today()\n    fromordinal()\n\n    Operators:\n\n    __repr__, __str__\n    __eq__, __le__, __lt__, __ge__, __gt__, __hash__\n    __add__, __radd__, __sub__ (add/radd only with timedelta arg)\n\n    Methods:\n\n    timetuple()\n    toordinal()\n    weekday()\n    isoweekday(), isocalendar(), isoformat()\n    ctime()\n    strftime()\n\n    Properties (readonly):\n    year, month, day\n    ', ('_year', '_month', '_day', '_hashcode'), None, <code object __new__ at 0x0000024068DE2D70, file "datetime.py", line 923>, <code object fromtimestamp at 0x000002406944A340, file "datetime.py", line 957>, <code object today at 0x000002406944A780, file "datetime.py", line 963>, <code object fromordinal at 0x00000240693EB730, file "datetime.py", line 969>, <code object fromisoformat at 0x000002406934F120, file "datetime.py", line 979>, <code object fromisocalendar at 0x000002406945CF30, file "datetime.py", line 993>, <code object __repr__ at 0x000002406941AE50, file "datetime.py", line 1002>, <code object ctime at 0x000002406922C6C0, file "datetime.py", line 1024>, <code object strftime at 0x00000240693EB930, file "datetime.py", line 1032>, <code object __format__ at 0x00000240691F56F0, file "datetime.py", line 1040>, <code object isoformat at 0x000002406945FC30, file "datetime.py", line 1047>, <code object year at 0x0000024069495D70, file "datetime.py", line 1061>, <code object month at 0x0000024069495E40, file "datetime.py", line 1066>, <code object day at 0x00000240694960B0, file "datetime.py", line 1071>, <code object timetuple at 0x000002406944A890, file "datetime.py", line 1079>, <code object toordinal at 0x00000240693EBA30, file "datetime.py", line 1084>, <code object replace at 0x00000240693D2630, file "datetime.py", line 1092>, <code object __eq__ at 0x00000240693D22A0, file "datetime.py", line 1104>, <code object __le__ at 0x00000240693D2170, file "datetime.py", line 1109>, <code object __lt__ at 0x00000240693D2FB0, file "datetime.py", line 1114>, <code object __ge__ at 0x00000240693D30E0, file "datetime.py", line 1119>, <code object __gt__ at 0x00000240693D3210, file "datetime.py", line 1124>, <code object _cmp at 0x000002406949CD20, file "datetime.py", line 1129>, <code object __hash__ at 0x00000240693D3340, file "datetime.py", line 1135>, <code object __add__ at 0x00000240694983B0, file "datetime.py", line 1143>, <code object __sub__ at 0x0000024069498570, file "datetime.py", line 1154>, <code object weekday at 0x000002406945FE10, file "datetime.py", line 1164>, <code object isoweekday at 0x000002406945FF00, file "datetime.py", line 1170>, <code object isocalendar at 0x0000024068C8DB20, file "datetime.py", line 1175>, <code object _getstate at 0x00000240693D35A0, file "datetime.py", line 1205>, <code object __setstate at 0x00000240693EBB30, file "datetime.py", line 1209>, <code object __reduce__ at 0x000002406945D7A0, file "datetime.py", line 1213>, (None, None), (None, None, None))

## co_names:
('__name__', '__module__', '__qualname__', '__doc__', '__slots__', '__new__', 'classmethod', 'fromtimestamp', 'today', 'fromordinal', 'fromisoformat', 'fromisocalendar', '__repr__', 'ctime', 'strftime', '__format__', 'isoformat', '__str__', 'property', 'year', 'month', 'day', 'timetuple', 'toordinal', 'replace', '__eq__', '__le__', '__lt__', '__ge__', '__gt__', '_cmp', '__hash__', '__add__', '__radd__', '__sub__', 'weekday', 'isoweekday', 'isocalendar', '_getstate', '_date__setstate', '__reduce__')

## bytecode:

   0: RESUME               
   2: LOAD_NAME            __name__
   4: STORE_NAME           __module__
   6: LOAD_CONST           'date'
   8: STORE_NAME           __qualname__
  10: LOAD_CONST           'Concrete date type.\n\n    Constructors:\n\n    __new__()\n    fromtimestamp()\n    today()\n    fromordinal()\n\n    Operators:\n\n    __repr__, __str__\n    __eq__, __le__, __lt__, __ge__, __gt__, __hash__\n    __add__, __radd__, __sub__ (add/radd only with timedelta arg)\n\n    Methods:\n\n    timetuple()\n    toordinal()\n    weekday()\n    isoweekday(), isocalendar(), isoformat()\n    ctime()\n    strftime()\n\n    Properties (readonly):\n    year, month, day\n    '
  12: STORE_NAME           __doc__
  14: LOAD_CONST           ('_year', '_month', '_day', '_hashcode')
  16: STORE_NAME           __slots__
  18: LOAD_CONST           (None, None)
  20: LOAD_CONST           <code object __new__ at 0x0000024068DE2D70, file "datetime.py", line 923>
  22: MAKE_FUNCTION        defaults
  24: STORE_NAME           __new__
  26: LOAD_NAME            classmethod
  28: LOAD_CONST           <code object fromtimestamp at 0x000002406944A340, file "datetime.py", line 957>
  30: MAKE_FUNCTION        
  32: PRECALL              
  36: CALL                 
  46: STORE_NAME           fromtimestamp
  48: LOAD_NAME            classmethod
  50: LOAD_CONST           <code object today at 0x000002406944A780, file "datetime.py", line 963>
  52: MAKE_FUNCTION        
  54: PRECALL              
  58: CALL                 
  68: STORE_NAME           today
  70: LOAD_NAME            classmethod
  72: LOAD_CONST           <code object fromordinal at 0x00000240693EB730, file "datetime.py", line 969>
  74: MAKE_FUNCTION        
  76: PRECALL              
  80: CALL                 
  90: STORE_NAME           fromordinal
  92: LOAD_NAME            classmethod
  94: LOAD_CONST           <code object fromisoformat at 0x000002406934F120, file "datetime.py", line 979>
  96: MAKE_FUNCTION        
  98: PRECALL              
 102: CALL                 
 112: STORE_NAME           fromisoformat
 114: LOAD_NAME            classmethod
 116: LOAD_CONST           <code object fromisocalendar at 0x000002406945CF30, file "datetime.py", line 993>
 118: MAKE_FUNCTION        
 120: PRECALL              
 124: CALL                 
 134: STORE_NAME           fromisocalendar
 136: LOAD_CONST           <code object __repr__ at 0x000002406941AE50, file "datetime.py", line 1002>
 138: MAKE_FUNCTION        
 140: STORE_NAME           __repr__
 142: LOAD_CONST           <code object ctime at 0x000002406922C6C0, file "datetime.py", line 1024>
 144: MAKE_FUNCTION        
 146: STORE_NAME           ctime
 148: LOAD_CONST           <code object strftime at 0x00000240693EB930, file "datetime.py", line 1032>
 150: MAKE_FUNCTION        
 152: STORE_NAME           strftime
 154: LOAD_CONST           <code object __format__ at 0x00000240691F56F0, file "datetime.py", line 1040>
 156: MAKE_FUNCTION        
 158: STORE_NAME           __format__
 160: LOAD_CONST           <code object isoformat at 0x000002406945FC30, file "datetime.py", line 1047>
 162: MAKE_FUNCTION        
 164: STORE_NAME           isoformat
 166: LOAD_NAME            isoformat
 168: STORE_NAME           __str__
 170: LOAD_NAME            property
 172: LOAD_CONST           <code object year at 0x0000024069495D70, file "datetime.py", line 1061>
 174: MAKE_FUNCTION        
 176: PRECALL              
 180: CALL                 
 190: STORE_NAME           year
 192: LOAD_NAME            property
 194: LOAD_CONST           <code object month at 0x0000024069495E40, file "datetime.py", line 1066>
 196: MAKE_FUNCTION        
 198: PRECALL              
 202: CALL                 
 212: STORE_NAME           month
 214: LOAD_NAME            property
 216: LOAD_CONST           <code object day at 0x00000240694960B0, file "datetime.py", line 1071>
 218: MAKE_FUNCTION        
 220: PRECALL              
 224: CALL                 
 234: STORE_NAME           day
 236: LOAD_CONST           <code object timetuple at 0x000002406944A890, file "datetime.py", line 1079>
 238: MAKE_FUNCTION        
 240: STORE_NAME           timetuple
 242: LOAD_CONST           <code object toordinal at 0x00000240693EBA30, file "datetime.py", line 1084>
 244: MAKE_FUNCTION        
 246: STORE_NAME           toordinal
 248: LOAD_CONST           (None, None, None)
 250: LOAD_CONST           <code object replace at 0x00000240693D2630, file "datetime.py", line 1092>
 252: MAKE_FUNCTION        defaults
 254: STORE_NAME           replace
 256: LOAD_CONST           <code object __eq__ at 0x00000240693D22A0, file "datetime.py", line 1104>
 258: MAKE_FUNCTION        
 260: STORE_NAME           __eq__
 262: LOAD_CONST           <code object __le__ at 0x00000240693D2170, file "datetime.py", line 1109>
 264: MAKE_FUNCTION        
 266: STORE_NAME           __le__
 268: LOAD_CONST           <code object __lt__ at 0x00000240693D2FB0, file "datetime.py", line 1114>
 270: MAKE_FUNCTION        
 272: STORE_NAME           __lt__
 274: LOAD_CONST           <code object __ge__ at 0x00000240693D30E0, file "datetime.py", line 1119>
 276: MAKE_FUNCTION        
 278: STORE_NAME           __ge__
 280: LOAD_CONST           <code object __gt__ at 0x00000240693D3210, file "datetime.py", line 1124>
 282: MAKE_FUNCTION        
 284: STORE_NAME           __gt__
 286: LOAD_CONST           <code object _cmp at 0x000002406949CD20, file "datetime.py", line 1129>
 288: MAKE_FUNCTION        
 290: STORE_NAME           _cmp
 292: LOAD_CONST           <code object __hash__ at 0x00000240693D3340, file "datetime.py", line 1135>
 294: MAKE_FUNCTION        
 296: STORE_NAME           __hash__
 298: LOAD_CONST           <code object __add__ at 0x00000240694983B0, file "datetime.py", line 1143>
 300: MAKE_FUNCTION        
 302: STORE_NAME           __add__
 304: LOAD_NAME            __add__
 306: STORE_NAME           __radd__
 308: LOAD_CONST           <code object __sub__ at 0x0000024069498570, file "datetime.py", line 1154>
 310: MAKE_FUNCTION        
 312: STORE_NAME           __sub__
 314: LOAD_CONST           <code object weekday at 0x000002406945FE10, file "datetime.py", line 1164>
 316: MAKE_FUNCTION        
 318: STORE_NAME           weekday
 320: LOAD_CONST           <code object isoweekday at 0x000002406945FF00, file "datetime.py", line 1170>
 322: MAKE_FUNCTION        
 324: STORE_NAME           isoweekday
 326: LOAD_CONST           <code object isocalendar at 0x0000024068C8DB20, file "datetime.py", line 1175>
 328: MAKE_FUNCTION        
 330: STORE_NAME           isocalendar
 332: LOAD_CONST           <code object _getstate at 0x00000240693D35A0, file "datetime.py", line 1205>
 334: MAKE_FUNCTION        
 336: STORE_NAME           _getstate
 338: LOAD_CONST           <code object __setstate at 0x00000240693EBB30, file "datetime.py", line 1209>
 340: MAKE_FUNCTION        
 342: STORE_NAME           _date__setstate
 344: LOAD_CONST           <code object __reduce__ at 0x000002406945D7A0, file "datetime.py", line 1213>
 346: MAKE_FUNCTION        
 348: STORE_NAME           __reduce__
 350: LOAD_CONST           None
 352: RETURN_VALUE         
