# Disassembly for datetime.datetime.now
# From module file: datetime

## co_consts:
('Construct a datetime from time.time() and optional time zone info.',)

## co_names:
('_time', 'time', 'fromtimestamp')

## bytecode:

   0: RESUME               
   2: LOAD_GLOBAL          NULL + _time
  14: LOAD_ATTR            time
  24: PRECALL              
  28: CALL                 
  38: STORE_FAST           t
  40: LOAD_FAST            cls
  42: LOAD_METHOD          fromtimestamp
  64: LOAD_FAST            t
  66: LOAD_FAST            tz
  68: PRECALL              
  72: CALL                 
  82: RETURN_VALUE         
