# Disassembly for datetime.datetime.utcnow
# From module file: datetime

## co_consts:
('Construct a UTC datetime from time.time().',)

## co_names:
('_time', 'time', 'utcfromtimestamp')

## bytecode:

   0: RESUME               
   2: LOAD_GLOBAL          NULL + _time
  14: LOAD_ATTR            time
  24: PRECALL              
  28: CALL                 
  38: STORE_FAST           t
  40: LOAD_FAST            cls
  42: LOAD_METHOD          utcfromtimestamp
  64: LOAD_FAST            t
  66: PRECALL              
  70: CALL                 
  80: RETURN_VALUE         
