# Disassembly for datetime.datetime.fromisoformat
# From module file: datetime

## co_consts:
('Construct a datetime from a string in one of the ISO 8601 formats.', 'fromisoformat: argument must be str', 7, 'Invalid isoformat string: ', 0, 1, None, (0, 0, 0, 0, None))

## co_names:
('isinstance', 'str', 'TypeError', 'len', 'ValueError', '_find_isoformat_datetime_separator', '_parse_isoformat_date', '_parse_isoformat_time')

## bytecode:

   0: RESUME               
   2: LOAD_GLOBAL          NULL + isinstance
  14: LOAD_FAST            date_string
  16: LOAD_GLOBAL          str
  28: PRECALL              
  32: CALL                 
  42: POP_JUMP_FORWARD_IF_TRUE to 74
  44: LOAD_GLOBAL          NULL + TypeError
  56: LOAD_CONST           'fromisoformat: argument must be str'
  58: PRECALL              
  62: CALL                 
  72: RAISE_VARARGS        
  74: LOAD_GLOBAL          NULL + len
  86: LOAD_FAST            date_string
  88: PRECALL              
  92: CALL                 
 102: LOAD_CONST           7
 104: COMPARE_OP           <
 110: POP_JUMP_FORWARD_IF_FALSE to 148
 112: LOAD_GLOBAL          NULL + ValueError
 124: LOAD_CONST           'Invalid isoformat string: '
 126: LOAD_FAST            date_string
 128: FORMAT_VALUE         repr
 130: BUILD_STRING         
 132: PRECALL              
 136: CALL                 
 146: RAISE_VARARGS        
 148: NOP                  
 150: LOAD_GLOBAL          NULL + _find_isoformat_datetime_separator
 162: LOAD_FAST            date_string
 164: PRECALL              
 168: CALL                 
 178: STORE_FAST           separator_location
 180: LOAD_FAST            date_string
 182: LOAD_CONST           0
 184: LOAD_FAST            separator_location
 186: BUILD_SLICE          
 188: BINARY_SUBSCR        
 198: STORE_FAST           dstr
 200: LOAD_FAST            date_string
 202: LOAD_FAST            separator_location
 204: LOAD_CONST           1
 206: BINARY_OP            +
 210: LOAD_CONST           None
 212: BUILD_SLICE          
 214: BINARY_SUBSCR        
 224: STORE_FAST           tstr
 226: LOAD_GLOBAL          NULL + _parse_isoformat_date
 238: LOAD_FAST            dstr
 240: PRECALL              
 244: CALL                 
 254: STORE_FAST           date_components
 256: JUMP_FORWARD         to 324
 258: PUSH_EXC_INFO        
 260: LOAD_GLOBAL          ValueError
 272: CHECK_EXC_MATCH      
 274: POP_JUMP_FORWARD_IF_FALSE to 316
 276: POP_TOP              
 278: LOAD_GLOBAL          NULL + ValueError
 290: LOAD_CONST           'Invalid isoformat string: '
 292: LOAD_FAST            date_string
 294: FORMAT_VALUE         repr
 296: BUILD_STRING         
 298: PRECALL              
 302: CALL                 
 312: LOAD_CONST           None
 314: RAISE_VARARGS        
 316: RERAISE              
 318: COPY                 
 320: POP_EXCEPT           
 322: RERAISE              
 324: LOAD_FAST            tstr
 326: POP_JUMP_FORWARD_IF_FALSE to 428
 328: NOP                  
 330: LOAD_GLOBAL          NULL + _parse_isoformat_time
 342: LOAD_FAST            tstr
 344: PRECALL              
 348: CALL                 
 358: STORE_FAST           time_components
 360: JUMP_FORWARD         to 436
 362: PUSH_EXC_INFO        
 364: LOAD_GLOBAL          ValueError
 376: CHECK_EXC_MATCH      
 378: POP_JUMP_FORWARD_IF_FALSE to 420
 380: POP_TOP              
 382: LOAD_GLOBAL          NULL + ValueError
 394: LOAD_CONST           'Invalid isoformat string: '
 396: LOAD_FAST            date_string
 398: FORMAT_VALUE         repr
 400: BUILD_STRING         
 402: PRECALL              
 406: CALL                 
 416: LOAD_CONST           None
 418: RAISE_VARARGS        
 420: RERAISE              
 422: COPY                 
 424: POP_EXCEPT           
 426: RERAISE              
 428: BUILD_LIST           
 430: LOAD_CONST           (0, 0, 0, 0, None)
 432: LIST_EXTEND          
 434: STORE_FAST           time_components
 436: PUSH_NULL            
 438: LOAD_FAST            cls
 440: LOAD_FAST            date_components
 442: LOAD_FAST            time_components
 444: BINARY_OP            +
 448: CALL_FUNCTION_EX     
 450: RETURN_VALUE         
