# Disassembly for datetime.timezone.__eq__
# From module file: datetime

## co_consts:
(None,)

## co_names:
('isinstance', 'timezone', '_offset', 'NotImplemented')

## bytecode:

   0: RESUME               
   2: LOAD_GLOBAL          NULL + isinstance
  14: LOAD_FAST            other
  16: LOAD_GLOBAL          timezone
  28: PRECALL              
  32: CALL                 
  42: POP_JUMP_FORWARD_IF_FALSE to 76
  44: LOAD_FAST            self
  46: LOAD_ATTR            _offset
  56: LOAD_FAST            other
  58: LOAD_ATTR            _offset
  68: COMPARE_OP           ==
  74: RETURN_VALUE         
  76: LOAD_GLOBAL          NotImplemented
  88: RETURN_VALUE         
