# Disassembly for datetime.datetime.replace
# From module file: datetime

## co_consts:
('Return a new datetime with new values for the specified fields.', None, True, ('fold',))

## co_names:
('year', 'month', 'day', 'hour', 'minute', 'second', 'microsecond', 'tzinfo', 'fold', 'type')

## bytecode:

   0: RESUME               
   2: LOAD_FAST            year
   4: POP_JUMP_FORWARD_IF_NOT_NONE to 20
   6: LOAD_FAST            self
   8: LOAD_ATTR            year
  18: STORE_FAST           year
  20: LOAD_FAST            month
  22: POP_JUMP_FORWARD_IF_NOT_NONE to 38
  24: LOAD_FAST            self
  26: LOAD_ATTR            month
  36: STORE_FAST           month
  38: LOAD_FAST            day
  40: POP_JUMP_FORWARD_IF_NOT_NONE to 56
  42: LOAD_FAST            self
  44: LOAD_ATTR            day
  54: STORE_FAST           day
  56: LOAD_FAST            hour
  58: POP_JUMP_FORWARD_IF_NOT_NONE to 74
  60: LOAD_FAST            self
  62: LOAD_ATTR            hour
  72: STORE_FAST           hour
  74: LOAD_FAST            minute
  76: POP_JUMP_FORWARD_IF_NOT_NONE to 92
  78: LOAD_FAST            self
  80: LOAD_ATTR            minute
  90: STORE_FAST           minute
  92: LOAD_FAST            second
  94: POP_JUMP_FORWARD_IF_NOT_NONE to 110
  96: LOAD_FAST            self
  98: LOAD_ATTR            second
 108: STORE_FAST           second
 110: LOAD_FAST            microsecond
 112: POP_JUMP_FORWARD_IF_NOT_NONE to 128
 114: LOAD_FAST            self
 116: LOAD_ATTR            microsecond
 126: STORE_FAST           microsecond
 128: LOAD_FAST            tzinfo
 130: LOAD_CONST           True
 132: IS_OP                
 134: POP_JUMP_FORWARD_IF_FALSE to 150
 136: LOAD_FAST            self
 138: LOAD_ATTR            tzinfo
 148: STORE_FAST           tzinfo
 150: LOAD_FAST            fold
 152: POP_JUMP_FORWARD_IF_NOT_NONE to 168
 154: LOAD_FAST            self
 156: LOAD_ATTR            fold
 166: STORE_FAST           fold
 168: PUSH_NULL            
 170: LOAD_GLOBAL          NULL + type
 182: LOAD_FAST            self
 184: PRECALL              
 188: CALL                 
 198: LOAD_FAST            year
 200: LOAD_FAST            month
 202: LOAD_FAST            day
 204: LOAD_FAST            hour
 206: LOAD_FAST            minute
 208: LOAD_FAST            second
 210: LOAD_FAST            microsecond
 212: LOAD_FAST            tzinfo
 214: LOAD_FAST            fold
 216: KW_NAMES             
 218: PRECALL              
 222: CALL                 
 232: RETURN_VALUE         
