# Disassembly for datetime.date.toordinal
# From module file: datetime

## co_consts:
('Return proleptic Gregorian ordinal for the year, month and day.\n\n        January 1 of year 1 is day 1.  Only the year, month and day values\n        contribute to the result.\n        ',)

## co_names:
('_ymd2ord', '_year', '_month', '_day')

## bytecode:

   0: RESUME               
   2: LOAD_GLOBAL          NULL + _ymd2ord
  14: LOAD_FAST            self
  16: LOAD_ATTR            _year
  26: LOAD_FAST            self
  28: LOAD_ATTR            _month
  38: LOAD_FAST            self
  40: LOAD_ATTR            _day
  50: PRECALL              
  54: CALL                 
  64: RETURN_VALUE         
