# Disassembly for datetime.datetime.timetz
# From module file: datetime

## co_consts:
('Return the time part, with same tzinfo.', ('fold',))

## co_names:
('time', 'hour', 'minute', 'second', 'microsecond', '_tzinfo', 'fold')

## bytecode:

   0: RESUME               
   2: LOAD_GLOBAL          NULL + time
  14: LOAD_FAST            self
  16: LOAD_ATTR            hour
  26: LOAD_FAST            self
  28: LOAD_ATTR            minute
  38: LOAD_FAST            self
  40: LOAD_ATTR            second
  50: LOAD_FAST            self
  52: LOAD_ATTR            microsecond
  62: LOAD_FAST            self
  64: LOAD_ATTR            _tzinfo
  74: LOAD_FAST            self
  76: LOAD_ATTR            fold
  86: KW_NAMES             
  88: PRECALL              
  92: CALL                 
 102: RETURN_VALUE         
