# Disassembly for datetime.datetime._mktime.local
# From module file: datetime

## co_consts:
(None, 6, 0, 1)

## co_names:
('_time', 'localtime', 'datetime', 'timedelta')

## bytecode:

   0: COPY_FREE_VARS       
   2: RESUME               
   4: LOAD_GLOBAL          NULL + _time
  16: LOAD_ATTR            localtime
  26: LOAD_FAST            u
  28: PRECALL              
  32: CALL                 
  42: LOAD_CONST           None
  44: LOAD_CONST           6
  46: BUILD_SLICE          
  48: BINARY_SUBSCR        
  58: UNPACK_SEQUENCE      
  62: STORE_FAST           y
  64: STORE_FAST           m
  66: STORE_FAST           d
  68: STORE_FAST           hh
  70: STORE_FAST           mm
  72: STORE_FAST           ss
  74: LOAD_GLOBAL          NULL + datetime
  86: LOAD_FAST            y
  88: LOAD_FAST            m
  90: LOAD_FAST            d
  92: LOAD_FAST            hh
  94: LOAD_FAST            mm
  96: LOAD_FAST            ss
  98: PRECALL              
 102: CALL                 
 112: LOAD_DEREF           epoch
 114: BINARY_OP            -
 118: LOAD_GLOBAL          NULL + timedelta
 130: LOAD_CONST           0
 132: LOAD_CONST           1
 134: PRECALL              
 138: CALL                 
 148: BINARY_OP            //
 152: RETURN_VALUE         
