# Disassembly for datetime.time.__format__
# From module file: datetime

## co_consts:
(None, 'must be str, not %s', 0)

## co_names:
('isinstance', 'str', 'TypeError', 'type', '__name__', 'len', 'strftime')

## bytecode:

   0: RESUME               
   2: LOAD_GLOBAL          NULL + isinstance
  14: LOAD_FAST            fmt
  16: LOAD_GLOBAL          str
  28: PRECALL              
  32: CALL                 
  42: POP_JUMP_FORWARD_IF_TRUE to 116
  44: LOAD_GLOBAL          NULL + TypeError
  56: LOAD_CONST           'must be str, not %s'
  58: LOAD_GLOBAL          NULL + type
  70: LOAD_FAST            fmt
  72: PRECALL              
  76: CALL                 
  86: LOAD_ATTR            __name__
  96: BINARY_OP            %
 100: PRECALL              
 104: CALL                 
 114: RAISE_VARARGS        
 116: LOAD_GLOBAL          NULL + len
 128: LOAD_FAST            fmt
 130: PRECALL              
 134: CALL                 
 144: LOAD_CONST           0
 146: COMPARE_OP           !=
 152: POP_JUMP_FORWARD_IF_FALSE to 196
 154: LOAD_FAST            self
 156: LOAD_METHOD          strftime
 178: LOAD_FAST            fmt
 180: PRECALL              
 184: CALL                 
 194: RETURN_VALUE         
 196: LOAD_GLOBAL          NULL + str
 208: LOAD_FAST            self
 210: PRECALL              
 214: CALL                 
 224: RETURN_VALUE         
