# Disassembly for datetime.timezone
# From module file: datetime

## co_consts:
('timezone', ('_offset', '_name'), <code object __new__ at 0x0000024069366500, file "datetime.py", line 2302>, None, <code object _create at 0x000002406944A450, file "datetime.py", line 2317>, <code object __getinitargs__ at 0x0000024069CDC530, file "datetime.py", line 2324>, <code object __eq__ at 0x0000024069419E90, file "datetime.py", line 2330>, <code object __hash__ at 0x000002406945EC40, file "datetime.py", line 2335>, <code object __repr__ at 0x00000240691EABB0, file "datetime.py", line 2338>, <code object __str__ at 0x000002406945ED30, file "datetime.py", line 2358>, <code object utcoffset at 0x0000024069419FB0, file "datetime.py", line 2361>, <code object tzname at 0x00000240691C1210, file "datetime.py", line 2367>, <code object dst at 0x000002406944B220, file "datetime.py", line 2375>, <code object fromutc at 0x000002406922D530, file "datetime.py", line 2381>, 24, -1, ('hours', 'microseconds'), <code object _name_from_offset at 0x0000024069CD8430, file "datetime.py", line 2393>, (None,))

## co_names:
('__name__', '__module__', '__qualname__', '__slots__', 'object', '_Omitted', '__new__', 'classmethod', '_create', '__getinitargs__', '__eq__', '__hash__', '__repr__', '__str__', 'utcoffset', 'tzname', 'dst', 'fromutc', 'timedelta', '_maxoffset', '_minoffset', 'staticmethod', '_name_from_offset')

## bytecode:

   0: RESUME               
   2: LOAD_NAME            __name__
   4: STORE_NAME           __module__
   6: LOAD_CONST           'timezone'
   8: STORE_NAME           __qualname__
  10: LOAD_CONST           ('_offset', '_name')
  12: STORE_NAME           __slots__
  14: PUSH_NULL            
  16: LOAD_NAME            object
  18: PRECALL              
  22: CALL                 
  32: STORE_NAME           _Omitted
  34: LOAD_NAME            _Omitted
  36: BUILD_TUPLE          
  38: LOAD_CONST           <code object __new__ at 0x0000024069366500, file "datetime.py", line 2302>
  40: MAKE_FUNCTION        defaults
  42: STORE_NAME           __new__
  44: LOAD_NAME            classmethod
  46: LOAD_CONST           (None,)
  48: LOAD_CONST           <code object _create at 0x000002406944A450, file "datetime.py", line 2317>
  50: MAKE_FUNCTION        defaults
  52: PRECALL              
  56: CALL                 
  66: STORE_NAME           _create
  68: LOAD_CONST           <code object __getinitargs__ at 0x0000024069CDC530, file "datetime.py", line 2324>
  70: MAKE_FUNCTION        
  72: STORE_NAME           __getinitargs__
  74: LOAD_CONST           <code object __eq__ at 0x0000024069419E90, file "datetime.py", line 2330>
  76: MAKE_FUNCTION        
  78: STORE_NAME           __eq__
  80: LOAD_CONST           <code object __hash__ at 0x000002406945EC40, file "datetime.py", line 2335>
  82: MAKE_FUNCTION        
  84: STORE_NAME           __hash__
  86: LOAD_CONST           <code object __repr__ at 0x00000240691EABB0, file "datetime.py", line 2338>
  88: MAKE_FUNCTION        
  90: STORE_NAME           __repr__
  92: LOAD_CONST           <code object __str__ at 0x000002406945ED30, file "datetime.py", line 2358>
  94: MAKE_FUNCTION        
  96: STORE_NAME           __str__
  98: LOAD_CONST           <code object utcoffset at 0x0000024069419FB0, file "datetime.py", line 2361>
 100: MAKE_FUNCTION        
 102: STORE_NAME           utcoffset
 104: LOAD_CONST           <code object tzname at 0x00000240691C1210, file "datetime.py", line 2367>
 106: MAKE_FUNCTION        
 108: STORE_NAME           tzname
 110: LOAD_CONST           <code object dst at 0x000002406944B220, file "datetime.py", line 2375>
 112: MAKE_FUNCTION        
 114: STORE_NAME           dst
 116: LOAD_CONST           <code object fromutc at 0x000002406922D530, file "datetime.py", line 2381>
 118: MAKE_FUNCTION        
 120: STORE_NAME           fromutc
 122: PUSH_NULL            
 124: LOAD_NAME            timedelta
 126: LOAD_CONST           24
 128: LOAD_CONST           -1
 130: KW_NAMES             
 132: PRECALL              
 136: CALL                 
 146: STORE_NAME           _maxoffset
 148: LOAD_NAME            _maxoffset
 150: UNARY_NEGATIVE       
 152: STORE_NAME           _minoffset
 154: LOAD_NAME            staticmethod
 156: LOAD_CONST           <code object _name_from_offset at 0x0000024069CD8430, file "datetime.py", line 2393>
 158: MAKE_FUNCTION        
 160: PRECALL              
 164: CALL                 
 174: STORE_NAME           _name_from_offset
 176: LOAD_CONST           None
 178: RETURN_VALUE         
