# Disassembly for datetime.timedelta.__neg__
# From module file: datetime

## co_consts:
(None,)

## co_names:
('timedelta', '_days', '_seconds', '_microseconds')

## bytecode:

   0: RESUME               
   2: LOAD_GLOBAL          NULL + timedelta
  14: LOAD_FAST            self
  16: LOAD_ATTR            _days
  26: UNARY_NEGATIVE       
  28: LOAD_FAST            self
  30: LOAD_ATTR            _seconds
  40: UNARY_NEGATIVE       
  42: LOAD_FAST            self
  44: LOAD_ATTR            _microseconds
  54: UNARY_NEGATIVE       
  56: PRECALL              
  60: CALL                 
  70: RETURN_VALUE         
