# Disassembly for datetime.timedelta._to_microseconds
# From module file: datetime

## co_consts:
(None, 86400, 1000000)

## co_names:
('_days', '_seconds', '_microseconds')

## bytecode:

   0: RESUME               
   2: LOAD_FAST            self
   4: LOAD_ATTR            _days
  14: LOAD_CONST           86400
  16: BINARY_OP            *
  20: LOAD_FAST            self
  22: LOAD_ATTR            _seconds
  32: BINARY_OP            +
  36: LOAD_CONST           1000000
  38: BINARY_OP            *
  42: LOAD_FAST            self
  44: LOAD_ATTR            _microseconds
  54: BINARY_OP            +
  58: RETURN_VALUE         
