# Disassembly for datetime.datetime._fromtimestamp
# From module file: datetime

## co_consts:
('Construct a datetime from a POSIX timestamp (like time.time()).\n\n        A timezone info object may be passed in as well.\n        ', 1000000.0, 1000000, 1, 0, 59, None, 86400, 'win', 6)

## co_names:
('_math', 'modf', 'round', '_time', 'gmtime', 'localtime', 'min', 'sys', 'platform', 'startswith', 'timedelta', 'days', '_fold', 'fromutc')

## bytecode:

   0: RESUME               
   2: LOAD_GLOBAL          NULL + _math
  14: LOAD_ATTR            modf
  24: LOAD_FAST            t
  26: PRECALL              
  30: CALL                 
  40: UNPACK_SEQUENCE      
  44: STORE_FAST           frac
  46: STORE_FAST           t
  48: LOAD_GLOBAL          NULL + round
  60: LOAD_FAST            frac
  62: LOAD_CONST           1000000.0
  64: BINARY_OP            *
  68: PRECALL              
  72: CALL                 
  82: STORE_FAST           us
  84: LOAD_FAST            us
  86: LOAD_CONST           1000000
  88: COMPARE_OP           >=
  94: POP_JUMP_FORWARD_IF_FALSE to 118
  96: LOAD_FAST            t
  98: LOAD_CONST           1
 100: BINARY_OP            +=
 104: STORE_FAST           t
 106: LOAD_FAST            us
 108: LOAD_CONST           1000000
 110: BINARY_OP            -=
 114: STORE_FAST           us
 116: JUMP_FORWARD         to 150
 118: LOAD_FAST            us
 120: LOAD_CONST           0
 122: COMPARE_OP           <
 128: POP_JUMP_FORWARD_IF_FALSE to 150
 130: LOAD_FAST            t
 132: LOAD_CONST           1
 134: BINARY_OP            -=
 138: STORE_FAST           t
 140: LOAD_FAST            us
 142: LOAD_CONST           1000000
 144: BINARY_OP            +=
 148: STORE_FAST           us
 150: LOAD_FAST            utc
 152: POP_JUMP_FORWARD_IF_FALSE to 178
 154: LOAD_GLOBAL          _time
 166: LOAD_ATTR            gmtime
 176: JUMP_FORWARD         to 200
 178: LOAD_GLOBAL          _time
 190: LOAD_ATTR            localtime
 200: STORE_FAST           converter
 202: PUSH_NULL            
 204: LOAD_FAST            converter
 206: LOAD_FAST            t
 208: PRECALL              
 212: CALL                 
 222: UNPACK_SEQUENCE      
 226: STORE_FAST           y
 228: STORE_FAST           m
 230: STORE_FAST           d
 232: STORE_FAST           hh
 234: STORE_FAST           mm
 236: STORE_FAST           ss
 238: STORE_FAST           weekday
 240: STORE_FAST           jday
 242: STORE_FAST           dst
 244: LOAD_GLOBAL          NULL + min
 256: LOAD_FAST            ss
 258: LOAD_CONST           59
 260: PRECALL              
 264: CALL                 
 274: STORE_FAST           ss
 276: PUSH_NULL            
 278: LOAD_FAST            cls
 280: LOAD_FAST            y
 282: LOAD_FAST            m
 284: LOAD_FAST            d
 286: LOAD_FAST            hh
 288: LOAD_FAST            mm
 290: LOAD_FAST            ss
 292: LOAD_FAST            us
 294: LOAD_FAST            tz
 296: PRECALL              
 300: CALL                 
 310: STORE_FAST           result
 312: LOAD_FAST            tz
 314: POP_JUMP_FORWARD_IF_NOT_NONE to 718
 316: LOAD_FAST            utc
 318: POP_JUMP_FORWARD_IF_TRUE to 718
 320: LOAD_CONST           86400
 322: STORE_FAST           max_fold_seconds
 324: LOAD_FAST            t
 326: LOAD_FAST            max_fold_seconds
 328: COMPARE_OP           <
 334: POP_JUMP_FORWARD_IF_FALSE to 402
 336: LOAD_GLOBAL          sys
 348: LOAD_ATTR            platform
 358: LOAD_METHOD          startswith
 380: LOAD_CONST           'win'
 382: PRECALL              
 386: CALL                 
 396: POP_JUMP_FORWARD_IF_FALSE to 402
 398: LOAD_FAST            result
 400: RETURN_VALUE         
 402: PUSH_NULL            
 404: LOAD_FAST            converter
 406: LOAD_FAST            t
 408: LOAD_FAST            max_fold_seconds
 410: BINARY_OP            -
 414: PRECALL              
 418: CALL                 
 428: LOAD_CONST           None
 430: LOAD_CONST           6
 432: BUILD_SLICE          
 434: BINARY_SUBSCR        
 444: UNPACK_SEQUENCE      
 448: STORE_FAST           y
 450: STORE_FAST           m
 452: STORE_FAST           d
 454: STORE_FAST           hh
 456: STORE_FAST           mm
 458: STORE_FAST           ss
 460: PUSH_NULL            
 462: LOAD_FAST            cls
 464: LOAD_FAST            y
 466: LOAD_FAST            m
 468: LOAD_FAST            d
 470: LOAD_FAST            hh
 472: LOAD_FAST            mm
 474: LOAD_FAST            ss
 476: LOAD_FAST            us
 478: LOAD_FAST            tz
 480: PRECALL              
 484: CALL                 
 494: STORE_FAST           probe1
 496: LOAD_FAST            result
 498: LOAD_FAST            probe1
 500: BINARY_OP            -
 504: LOAD_GLOBAL          NULL + timedelta
 516: LOAD_CONST           0
 518: LOAD_FAST            max_fold_seconds
 520: PRECALL              
 524: CALL                 
 534: BINARY_OP            -
 538: STORE_FAST           trans
 540: LOAD_FAST            trans
 542: LOAD_ATTR            days
 552: LOAD_CONST           0
 554: COMPARE_OP           <
 560: POP_JUMP_FORWARD_IF_FALSE to 716
 562: PUSH_NULL            
 564: LOAD_FAST            converter
 566: LOAD_FAST            t
 568: LOAD_FAST            trans
 570: LOAD_GLOBAL          NULL + timedelta
 582: LOAD_CONST           0
 584: LOAD_CONST           1
 586: PRECALL              
 590: CALL                 
 600: BINARY_OP            //
 604: BINARY_OP            +
 608: PRECALL              
 612: CALL                 
 622: LOAD_CONST           None
 624: LOAD_CONST           6
 626: BUILD_SLICE          
 628: BINARY_SUBSCR        
 638: UNPACK_SEQUENCE      
 642: STORE_FAST           y
 644: STORE_FAST           m
 646: STORE_FAST           d
 648: STORE_FAST           hh
 650: STORE_FAST           mm
 652: STORE_FAST           ss
 654: PUSH_NULL            
 656: LOAD_FAST            cls
 658: LOAD_FAST            y
 660: LOAD_FAST            m
 662: LOAD_FAST            d
 664: LOAD_FAST            hh
 666: LOAD_FAST            mm
 668: LOAD_FAST            ss
 670: LOAD_FAST            us
 672: LOAD_FAST            tz
 674: PRECALL              
 678: CALL                 
 688: STORE_FAST           probe2
 690: LOAD_FAST            probe2
 692: LOAD_FAST            result
 694: COMPARE_OP           ==
 700: POP_JUMP_FORWARD_IF_FALSE to 716
 702: LOAD_CONST           1
 704: LOAD_FAST            result
 706: STORE_ATTR           _fold
 716: JUMP_FORWARD         to 764
 718: LOAD_FAST            tz
 720: POP_JUMP_FORWARD_IF_NONE to 764
 722: LOAD_FAST            tz
 724: LOAD_METHOD          fromutc
 746: LOAD_FAST            result
 748: PRECALL              
 752: CALL                 
 762: STORE_FAST           result
 764: LOAD_FAST            result
 766: RETURN_VALUE         
