# Disassembly for datetime._parse_hh_mm_ss_ff
# From module file: datetime

## co_consts:
(None, (0, 0, 0, 0), 0, 3, 2, 'Incomplete time component', 1, ':', 'Invalid time separator: %c', '.,', 'Invalid microsecond component', 6, 'Non-digit values in unparsed fraction')

## co_names:
('len', 'range', 'ValueError', 'int', '_FRACTION_CORRECTION', 'all', 'map', '_is_ascii_digit')

## bytecode:

   0: RESUME               
   2: LOAD_GLOBAL          NULL + len
  14: LOAD_FAST            tstr
  16: PRECALL              
  20: CALL                 
  30: STORE_FAST           len_str
  32: BUILD_LIST           
  34: LOAD_CONST           (0, 0, 0, 0)
  36: LIST_EXTEND          
  38: STORE_FAST           time_comps
  40: LOAD_CONST           0
  42: STORE_FAST           pos
  44: LOAD_GLOBAL          NULL + range
  56: LOAD_CONST           0
  58: LOAD_CONST           3
  60: PRECALL              
  64: CALL                 
  74: GET_ITER             
  76: FOR_ITER             to 330
  78: STORE_FAST           comp
  80: LOAD_FAST            len_str
  82: LOAD_FAST            pos
  84: BINARY_OP            -
  88: LOAD_CONST           2
  90: COMPARE_OP           <
  96: POP_JUMP_FORWARD_IF_FALSE to 128
  98: LOAD_GLOBAL          NULL + ValueError
 110: LOAD_CONST           'Incomplete time component'
 112: PRECALL              
 116: CALL                 
 126: RAISE_VARARGS        
 128: LOAD_GLOBAL          NULL + int
 140: LOAD_FAST            tstr
 142: LOAD_FAST            pos
 144: LOAD_FAST            pos
 146: LOAD_CONST           2
 148: BINARY_OP            +
 152: BUILD_SLICE          
 154: BINARY_SUBSCR        
 164: PRECALL              
 168: CALL                 
 178: LOAD_FAST            time_comps
 180: LOAD_FAST            comp
 182: STORE_SUBSCR         
 186: LOAD_FAST            pos
 188: LOAD_CONST           2
 190: BINARY_OP            +=
 194: STORE_FAST           pos
 196: LOAD_FAST            tstr
 198: LOAD_FAST            pos
 200: LOAD_FAST            pos
 202: LOAD_CONST           1
 204: BINARY_OP            +
 208: BUILD_SLICE          
 210: BINARY_SUBSCR        
 220: STORE_FAST           next_char
 222: LOAD_FAST            comp
 224: LOAD_CONST           0
 226: COMPARE_OP           ==
 232: POP_JUMP_FORWARD_IF_FALSE to 246
 234: LOAD_FAST            next_char
 236: LOAD_CONST           ':'
 238: COMPARE_OP           ==
 244: STORE_FAST           has_sep
 246: LOAD_FAST            next_char
 248: POP_JUMP_FORWARD_IF_FALSE to 262
 250: LOAD_FAST            comp
 252: LOAD_CONST           2
 254: COMPARE_OP           >=
 260: POP_JUMP_FORWARD_IF_FALSE to 266
 262: POP_TOP              
 264: JUMP_FORWARD         to 330
 266: LOAD_FAST            has_sep
 268: POP_JUMP_FORWARD_IF_FALSE to 318
 270: LOAD_FAST            next_char
 272: LOAD_CONST           ':'
 274: COMPARE_OP           !=
 280: POP_JUMP_FORWARD_IF_FALSE to 318
 282: LOAD_GLOBAL          NULL + ValueError
 294: LOAD_CONST           'Invalid time separator: %c'
 296: LOAD_FAST            next_char
 298: BINARY_OP            %
 302: PRECALL              
 306: CALL                 
 316: RAISE_VARARGS        
 318: LOAD_FAST            pos
 320: LOAD_FAST            has_sep
 322: BINARY_OP            +=
 326: STORE_FAST           pos
 328: JUMP_BACKWARD        to 76
 330: LOAD_FAST            pos
 332: LOAD_FAST            len_str
 334: COMPARE_OP           <
 340: POP_JUMP_FORWARD_IF_FALSE to 696
 342: LOAD_FAST            tstr
 344: LOAD_FAST            pos
 346: BINARY_SUBSCR        
 356: LOAD_CONST           '.,'
 358: CONTAINS_OP          
 360: POP_JUMP_FORWARD_IF_FALSE to 392
 362: LOAD_GLOBAL          NULL + ValueError
 374: LOAD_CONST           'Invalid microsecond component'
 376: PRECALL              
 380: CALL                 
 390: RAISE_VARARGS        
 392: LOAD_FAST            pos
 394: LOAD_CONST           1
 396: BINARY_OP            +=
 400: STORE_FAST           pos
 402: LOAD_FAST            len_str
 404: LOAD_FAST            pos
 406: BINARY_OP            -
 410: STORE_FAST           len_remainder
 412: LOAD_FAST            len_remainder
 414: LOAD_CONST           6
 416: COMPARE_OP           >=
 422: POP_JUMP_FORWARD_IF_FALSE to 430
 424: LOAD_CONST           6
 426: STORE_FAST           to_parse
 428: JUMP_FORWARD         to 434
 430: LOAD_FAST            len_remainder
 432: STORE_FAST           to_parse
 434: LOAD_GLOBAL          NULL + int
 446: LOAD_FAST            tstr
 448: LOAD_FAST            pos
 450: LOAD_FAST            pos
 452: LOAD_FAST            to_parse
 454: BINARY_OP            +
 458: BUILD_SLICE          
 460: BINARY_SUBSCR        
 470: PRECALL              
 474: CALL                 
 484: LOAD_FAST            time_comps
 486: LOAD_CONST           3
 488: STORE_SUBSCR         
 492: LOAD_FAST            to_parse
 494: LOAD_CONST           6
 496: COMPARE_OP           <
 502: POP_JUMP_FORWARD_IF_FALSE to 564
 504: LOAD_FAST            time_comps
 506: LOAD_CONST           3
 508: COPY                 
 510: COPY                 
 512: BINARY_SUBSCR        
 522: LOAD_GLOBAL          _FRACTION_CORRECTION
 534: LOAD_FAST            to_parse
 536: LOAD_CONST           1
 538: BINARY_OP            -
 542: BINARY_SUBSCR        
 552: BINARY_OP            *=
 556: SWAP                 
 558: SWAP                 
 560: STORE_SUBSCR         
 564: LOAD_FAST            len_remainder
 566: LOAD_FAST            to_parse
 568: COMPARE_OP           >
 574: POP_JUMP_FORWARD_IF_FALSE to 696
 576: LOAD_GLOBAL          NULL + all
 588: LOAD_GLOBAL          NULL + map
 600: LOAD_GLOBAL          _is_ascii_digit
 612: LOAD_FAST            tstr
 614: LOAD_FAST            pos
 616: LOAD_FAST            to_parse
 618: BINARY_OP            +
 622: LOAD_CONST           None
 624: BUILD_SLICE          
 626: BINARY_SUBSCR        
 636: PRECALL              
 640: CALL                 
 650: PRECALL              
 654: CALL                 
 664: POP_JUMP_FORWARD_IF_TRUE to 696
 666: LOAD_GLOBAL          NULL + ValueError
 678: LOAD_CONST           'Non-digit values in unparsed fraction'
 680: PRECALL              
 684: CALL                 
 694: RAISE_VARARGS        
 696: LOAD_FAST            time_comps
 698: RETURN_VALUE         
