# Disassembly for datetime.date.fromordinal
# From module file: datetime

## co_consts:
('Construct a date from a proleptic Gregorian ordinal.\n\n        January 1 of year 1 is day 1.  Only the year, month and day are\n        non-zero in the result.\n        ',)

## co_names:
('_ord2ymd',)

## bytecode:

   0: RESUME               
   2: LOAD_GLOBAL          NULL + _ord2ymd
  14: LOAD_FAST            n
  16: PRECALL              
  20: CALL                 
  30: UNPACK_SEQUENCE      
  34: STORE_FAST           y
  36: STORE_FAST           m
  38: STORE_FAST           d
  40: PUSH_NULL            
  42: LOAD_FAST            cls
  44: LOAD_FAST            y
  46: LOAD_FAST            m
  48: LOAD_FAST            d
  50: PRECALL              
  54: CALL                 
  64: RETURN_VALUE         
