# Disassembly for datetime.timedelta.__repr__
# From module file: datetime

## co_consts:
(None, 'days=%d', 'seconds=%d', 'microseconds=%d', '0', '.', '(', ', ', ')')

## co_names:
('_days', 'append', '_seconds', '_microseconds', '__class__', '__module__', '__qualname__', 'join')

## bytecode:

   0: RESUME               
   2: BUILD_LIST           
   4: STORE_FAST           args
   6: LOAD_FAST            self
   8: LOAD_ATTR            _days
  18: POP_JUMP_FORWARD_IF_FALSE to 78
  20: LOAD_FAST            args
  22: LOAD_METHOD          append
  44: LOAD_CONST           'days=%d'
  46: LOAD_FAST            self
  48: LOAD_ATTR            _days
  58: BINARY_OP            %
  62: PRECALL              
  66: CALL                 
  76: POP_TOP              
  78: LOAD_FAST            self
  80: LOAD_ATTR            _seconds
  90: POP_JUMP_FORWARD_IF_FALSE to 150
  92: LOAD_FAST            args
  94: LOAD_METHOD          append
 116: LOAD_CONST           'seconds=%d'
 118: LOAD_FAST            self
 120: LOAD_ATTR            _seconds
 130: BINARY_OP            %
 134: PRECALL              
 138: CALL                 
 148: POP_TOP              
 150: LOAD_FAST            self
 152: LOAD_ATTR            _microseconds
 162: POP_JUMP_FORWARD_IF_FALSE to 222
 164: LOAD_FAST            args
 166: LOAD_METHOD          append
 188: LOAD_CONST           'microseconds=%d'
 190: LOAD_FAST            self
 192: LOAD_ATTR            _microseconds
 202: BINARY_OP            %
 206: PRECALL              
 210: CALL                 
 220: POP_TOP              
 222: LOAD_FAST            args
 224: POP_JUMP_FORWARD_IF_TRUE to 268
 226: LOAD_FAST            args
 228: LOAD_METHOD          append
 250: LOAD_CONST           '0'
 252: PRECALL              
 256: CALL                 
 266: POP_TOP              
 268: LOAD_FAST            self
 270: LOAD_ATTR            __class__
 280: LOAD_ATTR            __module__
 290: FORMAT_VALUE         str
 292: LOAD_CONST           '.'
 294: LOAD_FAST            self
 296: LOAD_ATTR            __class__
 306: LOAD_ATTR            __qualname__
 316: FORMAT_VALUE         str
 318: LOAD_CONST           '('
 320: LOAD_CONST           ', '
 322: LOAD_METHOD          join
 344: LOAD_FAST            args
 346: PRECALL              
 350: CALL                 
 360: FORMAT_VALUE         str
 362: LOAD_CONST           ')'
 364: BUILD_STRING         
 366: RETURN_VALUE         
