# Disassembly for datetime.timedelta.__truediv__
# From module file: datetime

## co_consts:
(None, 0)

## co_names:
('isinstance', 'int', 'float', 'timedelta', 'NotImplemented', '_to_microseconds', '_divide_and_round', 'as_integer_ratio')

## bytecode:

   0: RESUME               
   2: LOAD_GLOBAL          NULL + isinstance
  14: LOAD_FAST            other
  16: LOAD_GLOBAL          int
  28: LOAD_GLOBAL          float
  40: LOAD_GLOBAL          timedelta
  52: BUILD_TUPLE          
  54: PRECALL              
  58: CALL                 
  68: POP_JUMP_FORWARD_IF_TRUE to 84
  70: LOAD_GLOBAL          NotImplemented
  82: RETURN_VALUE         
  84: LOAD_FAST            self
  86: LOAD_METHOD          _to_microseconds
 108: PRECALL              
 112: CALL                 
 122: STORE_FAST           usec
 124: LOAD_GLOBAL          NULL + isinstance
 136: LOAD_FAST            other
 138: LOAD_GLOBAL          timedelta
 150: PRECALL              
 154: CALL                 
 164: POP_JUMP_FORWARD_IF_FALSE to 212
 166: LOAD_FAST            usec
 168: LOAD_FAST            other
 170: LOAD_METHOD          _to_microseconds
 192: PRECALL              
 196: CALL                 
 206: BINARY_OP            /
 210: RETURN_VALUE         
 212: LOAD_GLOBAL          NULL + isinstance
 224: LOAD_FAST            other
 226: LOAD_GLOBAL          int
 238: PRECALL              
 242: CALL                 
 252: POP_JUMP_FORWARD_IF_FALSE to 316
 254: LOAD_GLOBAL          NULL + timedelta
 266: LOAD_CONST           0
 268: LOAD_CONST           0
 270: LOAD_GLOBAL          NULL + _divide_and_round
 282: LOAD_FAST            usec
 284: LOAD_FAST            other
 286: PRECALL              
 290: CALL                 
 300: PRECALL              
 304: CALL                 
 314: RETURN_VALUE         
 316: LOAD_GLOBAL          NULL + isinstance
 328: LOAD_FAST            other
 330: LOAD_GLOBAL          float
 342: PRECALL              
 346: CALL                 
 356: POP_JUMP_FORWARD_IF_FALSE to 472
 358: LOAD_FAST            other
 360: LOAD_METHOD          as_integer_ratio
 382: PRECALL              
 386: CALL                 
 396: UNPACK_SEQUENCE      
 400: STORE_FAST           a
 402: STORE_FAST           b
 404: LOAD_GLOBAL          NULL + timedelta
 416: LOAD_CONST           0
 418: LOAD_CONST           0
 420: LOAD_GLOBAL          NULL + _divide_and_round
 432: LOAD_FAST            b
 434: LOAD_FAST            usec
 436: BINARY_OP            *
 440: LOAD_FAST            a
 442: PRECALL              
 446: CALL                 
 456: PRECALL              
 460: CALL                 
 470: RETURN_VALUE         
 472: LOAD_CONST           None
 474: RETURN_VALUE         
