# Disassembly for datetime.timedelta.__hash__
# From module file: datetime

## co_consts:
(None, -1)

## co_names:
('_hashcode', 'hash', '_getstate')

## bytecode:

   0: RESUME               
   2: LOAD_FAST            self
   4: LOAD_ATTR            _hashcode
  14: LOAD_CONST           -1
  16: COMPARE_OP           ==
  22: POP_JUMP_FORWARD_IF_FALSE to 100
  24: LOAD_GLOBAL          NULL + hash
  36: LOAD_FAST            self
  38: LOAD_METHOD          _getstate
  60: PRECALL              
  64: CALL                 
  74: PRECALL              
  78: CALL                 
  88: LOAD_FAST            self
  90: STORE_ATTR           _hashcode
 100: LOAD_FAST            self
 102: LOAD_ATTR            _hashcode
 112: RETURN_VALUE         
