# Disassembly for datetime._build_struct_time
# From module file: datetime

## co_consts:
(None, 6, 7)

## co_names:
('_ymd2ord', '_days_before_month', '_time', 'struct_time')

## bytecode:

   0: RESUME               
   2: LOAD_GLOBAL          NULL + _ymd2ord
  14: LOAD_FAST            y
  16: LOAD_FAST            m
  18: LOAD_FAST            d
  20: PRECALL              
  24: CALL                 
  34: LOAD_CONST           6
  36: BINARY_OP            +
  40: LOAD_CONST           7
  42: BINARY_OP            %
  46: STORE_FAST           wday
  48: LOAD_GLOBAL          NULL + _days_before_month
  60: LOAD_FAST            y
  62: LOAD_FAST            m
  64: PRECALL              
  68: CALL                 
  78: LOAD_FAST            d
  80: BINARY_OP            +
  84: STORE_FAST           dnum
  86: LOAD_GLOBAL          NULL + _time
  98: LOAD_ATTR            struct_time
 108: LOAD_FAST            y
 110: LOAD_FAST            m
 112: LOAD_FAST            d
 114: LOAD_FAST            hh
 116: LOAD_FAST            mm
 118: LOAD_FAST            ss
 120: LOAD_FAST            wday
 122: LOAD_FAST            dnum
 124: LOAD_FAST            dstflag
 126: BUILD_TUPLE          
 128: PRECALL              
 132: CALL                 
 142: RETURN_VALUE         
