# Disassembly for datetime.timezone.tzname
# From module file: datetime

## co_consts:
(None, 'tzname() argument must be a datetime instance or None')

## co_names:
('isinstance', 'datetime', '_name', '_name_from_offset', '_offset', 'TypeError')

## bytecode:

   0: RESUME               
   2: LOAD_GLOBAL          NULL + isinstance
  14: LOAD_FAST            dt
  16: LOAD_GLOBAL          datetime
  28: PRECALL              
  32: CALL                 
  42: POP_JUMP_FORWARD_IF_TRUE to 48
  44: LOAD_FAST            dt
  46: POP_JUMP_FORWARD_IF_NOT_NONE to 128
  48: LOAD_FAST            self
  50: LOAD_ATTR            _name
  60: POP_JUMP_FORWARD_IF_NOT_NONE to 114
  62: LOAD_FAST            self
  64: LOAD_METHOD          _name_from_offset
  86: LOAD_FAST            self
  88: LOAD_ATTR            _offset
  98: PRECALL              
 102: CALL                 
 112: RETURN_VALUE         
 114: LOAD_FAST            self
 116: LOAD_ATTR            _name
 126: RETURN_VALUE         
 128: LOAD_GLOBAL          NULL + TypeError
 140: LOAD_CONST           'tzname() argument must be a datetime instance or None'
 142: PRECALL              
 146: CALL                 
 156: RAISE_VARARGS        
