# Disassembly for datetime.datetime.isoformat
# From module file: datetime

## co_consts:
("Return the time formatted according to ISO.\n\n        The full format looks like 'YYYY-MM-DD HH:MM:SS.mmmmmm'.\n        By default, the fractional part is omitted if self.microsecond == 0.\n\n        If self.tzinfo is not None, the UTC offset is also attached, giving\n        giving a full format of 'YYYY-MM-DD HH:MM:SS.mmmmmm+HH:MM'.\n\n        Optional argument sep specifies the separator between date and\n        time, default 'T'.\n\n        The optional argument timespec specifies the number of additional\n        terms of the time to include. Valid options are 'auto', 'hours',\n        'minutes', 'seconds', 'milliseconds' and 'microseconds'.\n        ", '%04d-%02d-%02d%c')

## co_names:
('_year', '_month', '_day', '_format_time', '_hour', '_minute', '_second', '_microsecond', 'utcoffset', '_format_offset')

## bytecode:

   0: RESUME               
   2: LOAD_CONST           '%04d-%02d-%02d%c'
   4: LOAD_FAST            self
   6: LOAD_ATTR            _year
  16: LOAD_FAST            self
  18: LOAD_ATTR            _month
  28: LOAD_FAST            self
  30: LOAD_ATTR            _day
  40: LOAD_FAST            sep
  42: BUILD_TUPLE          
  44: BINARY_OP            %
  48: LOAD_GLOBAL          NULL + _format_time
  60: LOAD_FAST            self
  62: LOAD_ATTR            _hour
  72: LOAD_FAST            self
  74: LOAD_ATTR            _minute
  84: LOAD_FAST            self
  86: LOAD_ATTR            _second
  96: LOAD_FAST            self
  98: LOAD_ATTR            _microsecond
 108: LOAD_FAST            timespec
 110: PRECALL              
 114: CALL                 
 124: BINARY_OP            +
 128: STORE_FAST           s
 130: LOAD_FAST            self
 132: LOAD_METHOD          utcoffset
 154: PRECALL              
 158: CALL                 
 168: STORE_FAST           off
 170: LOAD_GLOBAL          NULL + _format_offset
 182: LOAD_FAST            off
 184: PRECALL              
 188: CALL                 
 198: STORE_FAST           tz
 200: LOAD_FAST            tz
 202: POP_JUMP_FORWARD_IF_FALSE to 214
 204: LOAD_FAST            s
 206: LOAD_FAST            tz
 208: BINARY_OP            +=
 212: STORE_FAST           s
 214: LOAD_FAST            s
 216: RETURN_VALUE         
