# Disassembly for datetime.timezone.__new__
# From module file: datetime

## co_consts:
(None, 'offset must be a timedelta', 'name must be a string', 'offset must be a timedelta strictly between -timedelta(hours=24) and timedelta(hours=24).')

## co_names:
('isinstance', 'timedelta', 'TypeError', '_Omitted', 'utc', 'str', '_minoffset', '_maxoffset', 'ValueError', '_create')

## bytecode:

   0: RESUME               
   2: LOAD_GLOBAL          NULL + isinstance
  14: LOAD_FAST            offset
  16: LOAD_GLOBAL          timedelta
  28: PRECALL              
  32: CALL                 
  42: POP_JUMP_FORWARD_IF_TRUE to 74
  44: LOAD_GLOBAL          NULL + TypeError
  56: LOAD_CONST           'offset must be a timedelta'
  58: PRECALL              
  62: CALL                 
  72: RAISE_VARARGS        
  74: LOAD_FAST            name
  76: LOAD_FAST            cls
  78: LOAD_ATTR            _Omitted
  88: IS_OP                
  90: POP_JUMP_FORWARD_IF_FALSE to 116
  92: LOAD_FAST            offset
  94: POP_JUMP_FORWARD_IF_TRUE to 110
  96: LOAD_FAST            cls
  98: LOAD_ATTR            utc
 108: RETURN_VALUE         
 110: LOAD_CONST           None
 112: STORE_FAST           name
 114: JUMP_FORWARD         to 188
 116: LOAD_GLOBAL          NULL + isinstance
 128: LOAD_FAST            name
 130: LOAD_GLOBAL          str
 142: PRECALL              
 146: CALL                 
 156: POP_JUMP_FORWARD_IF_TRUE to 188
 158: LOAD_GLOBAL          NULL + TypeError
 170: LOAD_CONST           'name must be a string'
 172: PRECALL              
 176: CALL                 
 186: RAISE_VARARGS        
 188: LOAD_FAST            cls
 190: LOAD_ATTR            _minoffset
 200: LOAD_FAST            offset
 202: SWAP                 
 204: COPY                 
 206: COMPARE_OP           <=
 212: POP_JUMP_FORWARD_IF_FALSE to 236
 214: LOAD_FAST            cls
 216: LOAD_ATTR            _maxoffset
 226: COMPARE_OP           <=
 232: POP_JUMP_FORWARD_IF_TRUE to 268
 234: JUMP_FORWARD         to 238
 236: POP_TOP              
 238: LOAD_GLOBAL          NULL + ValueError
 250: LOAD_CONST           'offset must be a timedelta strictly between -timedelta(hours=24) and timedelta(hours=24).'
 252: PRECALL              
 256: CALL                 
 266: RAISE_VARARGS        
 268: LOAD_FAST            cls
 270: LOAD_METHOD          _create
 292: LOAD_FAST            offset
 294: LOAD_FAST            name
 296: PRECALL              
 300: CALL                 
 310: RETURN_VALUE         
