# Disassembly for datetime.time.isoformat
# From module file: datetime

## co_consts:
("Return the time formatted according to ISO.\n\n        The full format is 'HH:MM:SS.mmmmmm+zz:zz'. By default, the fractional\n        part is omitted if self.microsecond == 0.\n\n        The optional argument timespec specifies the number of additional\n        terms of the time to include. Valid options are 'auto', 'hours',\n        'minutes', 'seconds', 'milliseconds' and 'microseconds'.\n        ",)

## co_names:
('_format_time', '_hour', '_minute', '_second', '_microsecond', '_tzstr')

## bytecode:

   0: RESUME               
   2: LOAD_GLOBAL          NULL + _format_time
  14: LOAD_FAST            self
  16: LOAD_ATTR            _hour
  26: LOAD_FAST            self
  28: LOAD_ATTR            _minute
  38: LOAD_FAST            self
  40: LOAD_ATTR            _second
  50: LOAD_FAST            self
  52: LOAD_ATTR            _microsecond
  62: LOAD_FAST            timespec
  64: PRECALL              
  68: CALL                 
  78: STORE_FAST           s
  80: LOAD_FAST            self
  82: LOAD_METHOD          _tzstr
 104: PRECALL              
 108: CALL                 
 118: STORE_FAST           tz
 120: LOAD_FAST            tz
 122: POP_JUMP_FORWARD_IF_FALSE to 134
 124: LOAD_FAST            s
 126: LOAD_FAST            tz
 128: BINARY_OP            +=
 132: STORE_FAST           s
 134: LOAD_FAST            s
 136: RETURN_VALUE         
