# Disassembly for datetime.date._getstate
# From module file: datetime

## co_consts:
(None, 256)

## co_names:
('divmod', '_year', 'bytes', '_month', '_day')

## bytecode:

   0: RESUME               
   2: LOAD_GLOBAL          NULL + divmod
  14: LOAD_FAST            self
  16: LOAD_ATTR            _year
  26: LOAD_CONST           256
  28: PRECALL              
  32: CALL                 
  42: UNPACK_SEQUENCE      
  46: STORE_FAST           yhi
  48: STORE_FAST           ylo
  50: LOAD_GLOBAL          NULL + bytes
  62: LOAD_FAST            yhi
  64: LOAD_FAST            ylo
  66: LOAD_FAST            self
  68: LOAD_ATTR            _month
  78: LOAD_FAST            self
  80: LOAD_ATTR            _day
  90: BUILD_LIST           
  92: PRECALL              
  96: CALL                 
 106: BUILD_TUPLE          
 108: RETURN_VALUE         
