# Disassembly for datetime.time._cmp
# From module file: datetime

## co_consts:
(None, True, 2, 'cannot compare naive and aware times', 60, 1, ('minutes',))

## co_names:
('isinstance', 'time', '_tzinfo', 'utcoffset', '_cmp', '_hour', '_minute', '_second', '_microsecond', 'TypeError', 'timedelta')

## bytecode:

   0: RESUME               
   2: LOAD_GLOBAL          NULL + isinstance
  14: LOAD_FAST            other
  16: LOAD_GLOBAL          time
  28: PRECALL              
  32: CALL                 
  42: POP_JUMP_FORWARD_IF_TRUE to 48
  44: LOAD_ASSERTION_ERROR 
  46: RAISE_VARARGS        
  48: LOAD_FAST            self
  50: LOAD_ATTR            _tzinfo
  60: STORE_FAST           mytz
  62: LOAD_FAST            other
  64: LOAD_ATTR            _tzinfo
  74: STORE_FAST           ottz
  76: LOAD_CONST           None
  78: COPY                 
  80: STORE_FAST           myoff
  82: STORE_FAST           otoff
  84: LOAD_FAST            mytz
  86: LOAD_FAST            ottz
  88: IS_OP                
  90: POP_JUMP_FORWARD_IF_FALSE to 98
  92: LOAD_CONST           True
  94: STORE_FAST           base_compare
  96: JUMP_FORWARD         to 190
  98: LOAD_FAST            self
 100: LOAD_METHOD          utcoffset
 122: PRECALL              
 126: CALL                 
 136: STORE_FAST           myoff
 138: LOAD_FAST            other
 140: LOAD_METHOD          utcoffset
 162: PRECALL              
 166: CALL                 
 176: STORE_FAST           otoff
 178: LOAD_FAST            myoff
 180: LOAD_FAST            otoff
 182: COMPARE_OP           ==
 188: STORE_FAST           base_compare
 190: LOAD_FAST            base_compare
 192: POP_JUMP_FORWARD_IF_FALSE to 322
 194: LOAD_GLOBAL          NULL + _cmp
 206: LOAD_FAST            self
 208: LOAD_ATTR            _hour
 218: LOAD_FAST            self
 220: LOAD_ATTR            _minute
 230: LOAD_FAST            self
 232: LOAD_ATTR            _second
 242: LOAD_FAST            self
 244: LOAD_ATTR            _microsecond
 254: BUILD_TUPLE          
 256: LOAD_FAST            other
 258: LOAD_ATTR            _hour
 268: LOAD_FAST            other
 270: LOAD_ATTR            _minute
 280: LOAD_FAST            other
 282: LOAD_ATTR            _second
 292: LOAD_FAST            other
 294: LOAD_ATTR            _microsecond
 304: BUILD_TUPLE          
 306: PRECALL              
 310: CALL                 
 320: RETURN_VALUE         
 322: LOAD_FAST            myoff
 324: POP_JUMP_FORWARD_IF_NONE to 330
 326: LOAD_FAST            otoff
 328: POP_JUMP_FORWARD_IF_NOT_NONE to 368
 330: LOAD_FAST            allow_mixed
 332: POP_JUMP_FORWARD_IF_FALSE to 338
 334: LOAD_CONST           2
 336: RETURN_VALUE         
 338: LOAD_GLOBAL          NULL + TypeError
 350: LOAD_CONST           'cannot compare naive and aware times'
 352: PRECALL              
 356: CALL                 
 366: RAISE_VARARGS        
 368: LOAD_FAST            self
 370: LOAD_ATTR            _hour
 380: LOAD_CONST           60
 382: BINARY_OP            *
 386: LOAD_FAST            self
 388: LOAD_ATTR            _minute
 398: BINARY_OP            +
 402: LOAD_FAST            myoff
 404: LOAD_GLOBAL          NULL + timedelta
 416: LOAD_CONST           1
 418: KW_NAMES             
 420: PRECALL              
 424: CALL                 
 434: BINARY_OP            //
 438: BINARY_OP            -
 442: STORE_FAST           myhhmm
 444: LOAD_FAST            other
 446: LOAD_ATTR            _hour
 456: LOAD_CONST           60
 458: BINARY_OP            *
 462: LOAD_FAST            other
 464: LOAD_ATTR            _minute
 474: BINARY_OP            +
 478: LOAD_FAST            otoff
 480: LOAD_GLOBAL          NULL + timedelta
 492: LOAD_CONST           1
 494: KW_NAMES             
 496: PRECALL              
 500: CALL                 
 510: BINARY_OP            //
 514: BINARY_OP            -
 518: STORE_FAST           othhmm
 520: LOAD_GLOBAL          NULL + _cmp
 532: LOAD_FAST            myhhmm
 534: LOAD_FAST            self
 536: LOAD_ATTR            _second
 546: LOAD_FAST            self
 548: LOAD_ATTR            _microsecond
 558: BUILD_TUPLE          
 560: LOAD_FAST            othhmm
 562: LOAD_FAST            other
 564: LOAD_ATTR            _second
 574: LOAD_FAST            other
 576: LOAD_ATTR            _microsecond
 586: BUILD_TUPLE          
 588: PRECALL              
 592: CALL                 
 602: RETURN_VALUE         
