# Disassembly for datetime.datetime
# From module file: datetime

## co_consts:
('datetime', 'datetime(year, month, day[, hour[, minute[, second[, microsecond[,tzinfo]]]]])\n\n    The year, month and day arguments are required. tzinfo may be None, or an\n    instance of a tzinfo subclass. The remaining arguments may be ints.\n    ', None, 0, ('fold',), <code object __new__ at 0x0000024068CE1770, file "datetime.py", line 1677>, <code object hour at 0x00000240694945E0, file "datetime.py", line 1713>, <code object minute at 0x00000240694949F0, file "datetime.py", line 1718>, <code object second at 0x00000240694946B0, file "datetime.py", line 1723>, <code object microsecond at 0x0000024069494780, file "datetime.py", line 1728>, <code object tzinfo at 0x0000024069494850, file "datetime.py", line 1733>, <code object fold at 0x0000024069494ED0, file "datetime.py", line 1738>, <code object _fromtimestamp at 0x0000024068C22C40, file "datetime.py", line 1742>, <code object fromtimestamp at 0x000002406944B110, file "datetime.py", line 1786>, <code object utcfromtimestamp at 0x000002406945E4C0, file "datetime.py", line 1796>, <code object now at 0x000002406944B440, file "datetime.py", line 1801>, <code object utcnow at 0x000002406944B550, file "datetime.py", line 1807>, True, <code object combine at 0x000002406947CD50, file "datetime.py", line 1813>, <code object fromisoformat at 0x0000024066C27A70, file "datetime.py", line 1826>, <code object timetuple at 0x00000240691C1FD0, file "datetime.py", line 1857>, <code object _mktime at 0x0000024068C5ABD0, file "datetime.py", line 1870>, <code object timestamp at 0x000002406922CFF0, file "datetime.py", line 1905>, <code object utctimetuple at 0x000002406949D730, file "datetime.py", line 1913>, <code object date at 0x0000024069CDC230, file "datetime.py", line 1922>, <code object time at 0x000002406941AC10, file "datetime.py", line 1926>, <code object timetz at 0x0000024069419C50, file "datetime.py", line 1930>, <code object replace at 0x000002406934FB40, file "datetime.py", line 1935>, <code object _local_timezone at 0x00000240691DB2F0, file "datetime.py", line 1960>, <code object astimezone at 0x0000024068C46170, file "datetime.py", line 1972>, <code object ctime at 0x000002406949D8A0, file "datetime.py", line 1999>, 'T', 'auto', <code object isoformat at 0x00000240691F5550, file "datetime.py", line 2009>, <code object __repr__ at 0x0000024066C25170, file "datetime.py", line 2036>, <code object __str__ at 0x000002406945E6A0, file "datetime.py", line 2055>, <code object strptime at 0x000002406945E880, file "datetime.py", line 2059>, <code object utcoffset at 0x0000024069CC89B0, file "datetime.py", line 2065>, <code object tzname at 0x0000024069CC8AE0, file "datetime.py", line 2074>, <code object dst at 0x0000024069CC8C10, file "datetime.py", line 2087>, <code object __eq__ at 0x00000240691C09D0, file "datetime.py", line 2104>, <code object __le__ at 0x00000240691EA430, file "datetime.py", line 2112>, <code object __lt__ at 0x00000240691EA730, file "datetime.py", line 2120>, <code object __ge__ at 0x00000240691EA8B0, file "datetime.py", line 2128>, <code object __gt__ at 0x00000240691E8AB0, file "datetime.py", line 2136>, False, <code object _cmp at 0x0000024068C35D30, file "datetime.py", line 2144>, <code object __add__ at 0x0000024068C0A6C0, file "datetime.py", line 2181>, <code object __sub__ at 0x0000024068B3F550, file "datetime.py", line 2202>, <code object __hash__ at 0x0000024068DA78D0, file "datetime.py", line 2226>, 3, <code object _getstate at 0x0000024069CD8230, file "datetime.py", line 2243>, <code object __setstate at 0x0000024069366310, file "datetime.py", line 2258>, <code object __reduce_ex__ at 0x0000024069CDC430, file "datetime.py", line 2273>, <code object __reduce__ at 0x000002406945EA60, file "datetime.py", line 2276>, (None, None, 0, 0, 0, 0, None), (None,), (True,), (None, None, None, None, None, None, None, True), ('T', 'auto'), (False,), (3,))

## co_names:
('__name__', '__module__', '__qualname__', '__doc__', 'date', '__slots__', 'time', '__new__', 'property', 'hour', 'minute', 'second', 'microsecond', 'tzinfo', 'fold', 'classmethod', '_fromtimestamp', 'fromtimestamp', 'utcfromtimestamp', 'now', 'utcnow', 'combine', 'fromisoformat', 'timetuple', '_mktime', 'timestamp', 'utctimetuple', 'timetz', 'replace', '_local_timezone', 'astimezone', 'ctime', 'isoformat', '__repr__', '__str__', 'strptime', 'utcoffset', 'tzname', 'dst', '__eq__', '__le__', '__lt__', '__ge__', '__gt__', '_cmp', '__add__', '__radd__', '__sub__', '__hash__', '_getstate', '_datetime__setstate', '__reduce_ex__', '__reduce__')

## bytecode:

   0: RESUME               
   2: LOAD_NAME            __name__
   4: STORE_NAME           __module__
   6: LOAD_CONST           'datetime'
   8: STORE_NAME           __qualname__
  10: LOAD_CONST           'datetime(year, month, day[, hour[, minute[, second[, microsecond[,tzinfo]]]]])\n\n    The year, month and day arguments are required. tzinfo may be None, or an\n    instance of a tzinfo subclass. The remaining arguments may be ints.\n    '
  12: STORE_NAME           __doc__
  14: LOAD_NAME            date
  16: LOAD_ATTR            __slots__
  26: LOAD_NAME            time
  28: LOAD_ATTR            __slots__
  38: BINARY_OP            +
  42: STORE_NAME           __slots__
  44: NOP                  
  46: NOP                  
  48: LOAD_CONST           (None, None, 0, 0, 0, 0, None)
  50: LOAD_CONST           0
  52: LOAD_CONST           ('fold',)
  54: BUILD_CONST_KEY_MAP  
  56: LOAD_CONST           <code object __new__ at 0x0000024068CE1770, file "datetime.py", line 1677>
  58: MAKE_FUNCTION        defaults, kwdefaults
  60: STORE_NAME           __new__
  62: LOAD_NAME            property
  64: LOAD_CONST           <code object hour at 0x00000240694945E0, file "datetime.py", line 1713>
  66: MAKE_FUNCTION        
  68: PRECALL              
  72: CALL                 
  82: STORE_NAME           hour
  84: LOAD_NAME            property
  86: LOAD_CONST           <code object minute at 0x00000240694949F0, file "datetime.py", line 1718>
  88: MAKE_FUNCTION        
  90: PRECALL              
  94: CALL                 
 104: STORE_NAME           minute
 106: LOAD_NAME            property
 108: LOAD_CONST           <code object second at 0x00000240694946B0, file "datetime.py", line 1723>
 110: MAKE_FUNCTION        
 112: PRECALL              
 116: CALL                 
 126: STORE_NAME           second
 128: LOAD_NAME            property
 130: LOAD_CONST           <code object microsecond at 0x0000024069494780, file "datetime.py", line 1728>
 132: MAKE_FUNCTION        
 134: PRECALL              
 138: CALL                 
 148: STORE_NAME           microsecond
 150: LOAD_NAME            property
 152: LOAD_CONST           <code object tzinfo at 0x0000024069494850, file "datetime.py", line 1733>
 154: MAKE_FUNCTION        
 156: PRECALL              
 160: CALL                 
 170: STORE_NAME           tzinfo
 172: LOAD_NAME            property
 174: LOAD_CONST           <code object fold at 0x0000024069494ED0, file "datetime.py", line 1738>
 176: MAKE_FUNCTION        
 178: PRECALL              
 182: CALL                 
 192: STORE_NAME           fold
 194: LOAD_NAME            classmethod
 196: LOAD_CONST           <code object _fromtimestamp at 0x0000024068C22C40, file "datetime.py", line 1742>
 198: MAKE_FUNCTION        
 200: PRECALL              
 204: CALL                 
 214: STORE_NAME           _fromtimestamp
 216: LOAD_NAME            classmethod
 218: LOAD_CONST           (None,)
 220: LOAD_CONST           <code object fromtimestamp at 0x000002406944B110, file "datetime.py", line 1786>
 222: MAKE_FUNCTION        defaults
 224: PRECALL              
 228: CALL                 
 238: STORE_NAME           fromtimestamp
 240: LOAD_NAME            classmethod
 242: LOAD_CONST           <code object utcfromtimestamp at 0x000002406945E4C0, file "datetime.py", line 1796>
 244: MAKE_FUNCTION        
 246: PRECALL              
 250: CALL                 
 260: STORE_NAME           utcfromtimestamp
 262: LOAD_NAME            classmethod
 264: LOAD_CONST           (None,)
 266: LOAD_CONST           <code object now at 0x000002406944B440, file "datetime.py", line 1801>
 268: MAKE_FUNCTION        defaults
 270: PRECALL              
 274: CALL                 
 284: STORE_NAME           now
 286: LOAD_NAME            classmethod
 288: LOAD_CONST           <code object utcnow at 0x000002406944B550, file "datetime.py", line 1807>
 290: MAKE_FUNCTION        
 292: PRECALL              
 296: CALL                 
 306: STORE_NAME           utcnow
 308: LOAD_NAME            classmethod
 310: LOAD_CONST           (True,)
 312: LOAD_CONST           <code object combine at 0x000002406947CD50, file "datetime.py", line 1813>
 314: MAKE_FUNCTION        defaults
 316: PRECALL              
 320: CALL                 
 330: STORE_NAME           combine
 332: LOAD_NAME            classmethod
 334: LOAD_CONST           <code object fromisoformat at 0x0000024066C27A70, file "datetime.py", line 1826>
 336: MAKE_FUNCTION        
 338: PRECALL              
 342: CALL                 
 352: STORE_NAME           fromisoformat
 354: LOAD_CONST           <code object timetuple at 0x00000240691C1FD0, file "datetime.py", line 1857>
 356: MAKE_FUNCTION        
 358: STORE_NAME           timetuple
 360: LOAD_CONST           <code object _mktime at 0x0000024068C5ABD0, file "datetime.py", line 1870>
 362: MAKE_FUNCTION        
 364: STORE_NAME           _mktime
 366: LOAD_CONST           <code object timestamp at 0x000002406922CFF0, file "datetime.py", line 1905>
 368: MAKE_FUNCTION        
 370: STORE_NAME           timestamp
 372: LOAD_CONST           <code object utctimetuple at 0x000002406949D730, file "datetime.py", line 1913>
 374: MAKE_FUNCTION        
 376: STORE_NAME           utctimetuple
 378: LOAD_CONST           <code object date at 0x0000024069CDC230, file "datetime.py", line 1922>
 380: MAKE_FUNCTION        
 382: STORE_NAME           date
 384: LOAD_CONST           <code object time at 0x000002406941AC10, file "datetime.py", line 1926>
 386: MAKE_FUNCTION        
 388: STORE_NAME           time
 390: LOAD_CONST           <code object timetz at 0x0000024069419C50, file "datetime.py", line 1930>
 392: MAKE_FUNCTION        
 394: STORE_NAME           timetz
 396: NOP                  
 398: NOP                  
 400: LOAD_CONST           (None, None, None, None, None, None, None, True)
 402: LOAD_CONST           None
 404: LOAD_CONST           ('fold',)
 406: BUILD_CONST_KEY_MAP  
 408: LOAD_CONST           <code object replace at 0x000002406934FB40, file "datetime.py", line 1935>
 410: MAKE_FUNCTION        defaults, kwdefaults
 412: STORE_NAME           replace
 414: LOAD_CONST           <code object _local_timezone at 0x00000240691DB2F0, file "datetime.py", line 1960>
 416: MAKE_FUNCTION        
 418: STORE_NAME           _local_timezone
 420: LOAD_CONST           (None,)
 422: LOAD_CONST           <code object astimezone at 0x0000024068C46170, file "datetime.py", line 1972>
 424: MAKE_FUNCTION        defaults
 426: STORE_NAME           astimezone
 428: LOAD_CONST           <code object ctime at 0x000002406949D8A0, file "datetime.py", line 1999>
 430: MAKE_FUNCTION        
 432: STORE_NAME           ctime
 434: LOAD_CONST           ('T', 'auto')
 436: LOAD_CONST           <code object isoformat at 0x00000240691F5550, file "datetime.py", line 2009>
 438: MAKE_FUNCTION        defaults
 440: STORE_NAME           isoformat
 442: LOAD_CONST           <code object __repr__ at 0x0000024066C25170, file "datetime.py", line 2036>
 444: MAKE_FUNCTION        
 446: STORE_NAME           __repr__
 448: LOAD_CONST           <code object __str__ at 0x000002406945E6A0, file "datetime.py", line 2055>
 450: MAKE_FUNCTION        
 452: STORE_NAME           __str__
 454: LOAD_NAME            classmethod
 456: LOAD_CONST           <code object strptime at 0x000002406945E880, file "datetime.py", line 2059>
 458: MAKE_FUNCTION        
 460: PRECALL              
 464: CALL                 
 474: STORE_NAME           strptime
 476: LOAD_CONST           <code object utcoffset at 0x0000024069CC89B0, file "datetime.py", line 2065>
 478: MAKE_FUNCTION        
 480: STORE_NAME           utcoffset
 482: LOAD_CONST           <code object tzname at 0x0000024069CC8AE0, file "datetime.py", line 2074>
 484: MAKE_FUNCTION        
 486: STORE_NAME           tzname
 488: LOAD_CONST           <code object dst at 0x0000024069CC8C10, file "datetime.py", line 2087>
 490: MAKE_FUNCTION        
 492: STORE_NAME           dst
 494: LOAD_CONST           <code object __eq__ at 0x00000240691C09D0, file "datetime.py", line 2104>
 496: MAKE_FUNCTION        
 498: STORE_NAME           __eq__
 500: LOAD_CONST           <code object __le__ at 0x00000240691EA430, file "datetime.py", line 2112>
 502: MAKE_FUNCTION        
 504: STORE_NAME           __le__
 506: LOAD_CONST           <code object __lt__ at 0x00000240691EA730, file "datetime.py", line 2120>
 508: MAKE_FUNCTION        
 510: STORE_NAME           __lt__
 512: LOAD_CONST           <code object __ge__ at 0x00000240691EA8B0, file "datetime.py", line 2128>
 514: MAKE_FUNCTION        
 516: STORE_NAME           __ge__
 518: LOAD_CONST           <code object __gt__ at 0x00000240691E8AB0, file "datetime.py", line 2136>
 520: MAKE_FUNCTION        
 522: STORE_NAME           __gt__
 524: LOAD_CONST           (False,)
 526: LOAD_CONST           <code object _cmp at 0x0000024068C35D30, file "datetime.py", line 2144>
 528: MAKE_FUNCTION        defaults
 530: STORE_NAME           _cmp
 532: LOAD_CONST           <code object __add__ at 0x0000024068C0A6C0, file "datetime.py", line 2181>
 534: MAKE_FUNCTION        
 536: STORE_NAME           __add__
 538: LOAD_NAME            __add__
 540: STORE_NAME           __radd__
 542: LOAD_CONST           <code object __sub__ at 0x0000024068B3F550, file "datetime.py", line 2202>
 544: MAKE_FUNCTION        
 546: STORE_NAME           __sub__
 548: LOAD_CONST           <code object __hash__ at 0x0000024068DA78D0, file "datetime.py", line 2226>
 550: MAKE_FUNCTION        
 552: STORE_NAME           __hash__
 554: LOAD_CONST           (3,)
 556: LOAD_CONST           <code object _getstate at 0x0000024069CD8230, file "datetime.py", line 2243>
 558: MAKE_FUNCTION        defaults
 560: STORE_NAME           _getstate
 562: LOAD_CONST           <code object __setstate at 0x0000024069366310, file "datetime.py", line 2258>
 564: MAKE_FUNCTION        
 566: STORE_NAME           _datetime__setstate
 568: LOAD_CONST           <code object __reduce_ex__ at 0x0000024069CDC430, file "datetime.py", line 2273>
 570: MAKE_FUNCTION        
 572: STORE_NAME           __reduce_ex__
 574: LOAD_CONST           <code object __reduce__ at 0x000002406945EA60, file "datetime.py", line 2276>
 576: MAKE_FUNCTION        
 578: STORE_NAME           __reduce__
 580: LOAD_CONST           None
 582: RETURN_VALUE         
