# Disassembly for datetime.IsoCalendarDate.__new__
# From module file: datetime

## co_consts:
(None,)

## co_names:
('super', '__new__')

## bytecode:

   0: COPY_FREE_VARS       
   2: RESUME               
   4: LOAD_GLOBAL          NULL + super
  16: PRECALL              
  20: CALL                 
  30: LOAD_METHOD          __new__
  52: LOAD_FAST            cls
  54: LOAD_FAST            year
  56: LOAD_FAST            week
  58: LOAD_FAST            weekday
  60: BUILD_TUPLE          
  62: PRECALL              
  66: CALL                 
  76: RETURN_VALUE         
