# Disassembly for datetime.datetime.__new__
# From module file: datetime

## co_consts:
(None, 10, 1, 2, 3, 127, 12, 'latin1', "Failed to encode latin1 string when unpickling a datetime object. pickle.load(data, encoding='latin1') is assumed.", -1)

## co_names:
('isinstance', 'bytes', 'str', 'len', 'ord', 'UnicodeEncodeError', 'ValueError', 'object', '__new__', '_datetime__setstate', '_hashcode', '_check_date_fields', '_check_time_fields', '_check_tzinfo_arg', '_year', '_month', '_day', '_hour', '_minute', '_second', '_microsecond', '_tzinfo', '_fold')

## bytecode:

   0: RESUME               
   2: LOAD_GLOBAL          NULL + isinstance
  14: LOAD_FAST            year
  16: LOAD_GLOBAL          bytes
  28: LOAD_GLOBAL          str
  40: BUILD_TUPLE          
  42: PRECALL              
  46: CALL                 
  56: POP_JUMP_FORWARD_IF_FALSE to 426
  58: LOAD_GLOBAL          NULL + len
  70: LOAD_FAST            year
  72: PRECALL              
  76: CALL                 
  86: LOAD_CONST           10
  88: COMPARE_OP           ==
  94: POP_JUMP_FORWARD_IF_FALSE to 426
  96: LOAD_CONST           1
  98: LOAD_GLOBAL          NULL + ord
 110: LOAD_FAST            year
 112: LOAD_CONST           2
 114: LOAD_CONST           3
 116: BUILD_SLICE          
 118: BINARY_SUBSCR        
 128: PRECALL              
 132: CALL                 
 142: LOAD_CONST           127
 144: BINARY_OP            &
 148: SWAP                 
 150: COPY                 
 152: COMPARE_OP           <=
 158: POP_JUMP_FORWARD_IF_FALSE to 172
 160: LOAD_CONST           12
 162: COMPARE_OP           <=
 168: POP_JUMP_FORWARD_IF_FALSE to 426
 170: JUMP_FORWARD         to 176
 172: POP_TOP              
 174: JUMP_FORWARD         to 426
 176: LOAD_GLOBAL          NULL + isinstance
 188: LOAD_FAST            year
 190: LOAD_GLOBAL          str
 202: PRECALL              
 206: CALL                 
 216: POP_JUMP_FORWARD_IF_FALSE to 312
 218: NOP                  
 220: LOAD_GLOBAL          NULL + bytes
 232: LOAD_FAST            year
 234: LOAD_CONST           'latin1'
 236: PRECALL              
 240: CALL                 
 250: STORE_FAST           year
 252: JUMP_FORWARD         to 312
 254: PUSH_EXC_INFO        
 256: LOAD_GLOBAL          UnicodeEncodeError
 268: CHECK_EXC_MATCH      
 270: POP_JUMP_FORWARD_IF_FALSE to 304
 272: POP_TOP              
 274: LOAD_GLOBAL          NULL + ValueError
 286: LOAD_CONST           "Failed to encode latin1 string when unpickling a datetime object. pickle.load(data, encoding='latin1') is assumed."
 288: PRECALL              
 292: CALL                 
 302: RAISE_VARARGS        
 304: RERAISE              
 306: COPY                 
 308: POP_EXCEPT           
 310: RERAISE              
 312: LOAD_GLOBAL          object
 324: LOAD_METHOD          __new__
 346: LOAD_FAST            cls
 348: PRECALL              
 352: CALL                 
 362: STORE_FAST           self
 364: LOAD_FAST            self
 366: LOAD_METHOD          _datetime__setstate
 388: LOAD_FAST            year
 390: LOAD_FAST            month
 392: PRECALL              
 396: CALL                 
 406: POP_TOP              
 408: LOAD_CONST           -1
 410: LOAD_FAST            self
 412: STORE_ATTR           _hashcode
 422: LOAD_FAST            self
 424: RETURN_VALUE         
 426: LOAD_GLOBAL          NULL + _check_date_fields
 438: LOAD_FAST            year
 440: LOAD_FAST            month
 442: LOAD_FAST            day
 444: PRECALL              
 448: CALL                 
 458: UNPACK_SEQUENCE      
 462: STORE_FAST           year
 464: STORE_FAST           month
 466: STORE_FAST           day
 468: LOAD_GLOBAL          NULL + _check_time_fields
 480: LOAD_FAST            hour
 482: LOAD_FAST            minute
 484: LOAD_FAST            second
 486: LOAD_FAST            microsecond
 488: LOAD_FAST            fold
 490: PRECALL              
 494: CALL                 
 504: UNPACK_SEQUENCE      
 508: STORE_FAST           hour
 510: STORE_FAST           minute
 512: STORE_FAST           second
 514: STORE_FAST           microsecond
 516: STORE_FAST           fold
 518: LOAD_GLOBAL          NULL + _check_tzinfo_arg
 530: LOAD_FAST            tzinfo
 532: PRECALL              
 536: CALL                 
 546: POP_TOP              
 548: LOAD_GLOBAL          object
 560: LOAD_METHOD          __new__
 582: LOAD_FAST            cls
 584: PRECALL              
 588: CALL                 
 598: STORE_FAST           self
 600: LOAD_FAST            year
 602: LOAD_FAST            self
 604: STORE_ATTR           _year
 614: LOAD_FAST            month
 616: LOAD_FAST            self
 618: STORE_ATTR           _month
 628: LOAD_FAST            day
 630: LOAD_FAST            self
 632: STORE_ATTR           _day
 642: LOAD_FAST            hour
 644: LOAD_FAST            self
 646: STORE_ATTR           _hour
 656: LOAD_FAST            minute
 658: LOAD_FAST            self
 660: STORE_ATTR           _minute
 670: LOAD_FAST            second
 672: LOAD_FAST            self
 674: STORE_ATTR           _second
 684: LOAD_FAST            microsecond
 686: LOAD_FAST            self
 688: STORE_ATTR           _microsecond
 698: LOAD_FAST            tzinfo
 700: LOAD_FAST            self
 702: STORE_ATTR           _tzinfo
 712: LOAD_CONST           -1
 714: LOAD_FAST            self
 716: STORE_ATTR           _hashcode
 726: LOAD_FAST            fold
 728: LOAD_FAST            self
 730: STORE_ATTR           _fold
 740: LOAD_FAST            self
 742: RETURN_VALUE         
