# Disassembly for datetime.time.utcoffset
# From module file: datetime

## co_consts:
('Return the timezone offset as timedelta, positive east of UTC\n         (negative west of UTC).', None, 'utcoffset')

## co_names:
('_tzinfo', 'utcoffset', '_check_utc_offset')

## bytecode:

   0: RESUME               
   2: LOAD_FAST            self
   4: LOAD_ATTR            _tzinfo
  14: POP_JUMP_FORWARD_IF_NOT_NONE to 20
  16: LOAD_CONST           None
  18: RETURN_VALUE         
  20: LOAD_FAST            self
  22: LOAD_ATTR            _tzinfo
  32: LOAD_METHOD          utcoffset
  54: LOAD_CONST           None
  56: PRECALL              
  60: CALL                 
  70: STORE_FAST           offset
  72: LOAD_GLOBAL          NULL + _check_utc_offset
  84: LOAD_CONST           'utcoffset'
  86: LOAD_FAST            offset
  88: PRECALL              
  92: CALL                 
 102: POP_TOP              
 104: LOAD_FAST            offset
 106: RETURN_VALUE         
