# Disassembly for datetime.time._tzstr
# From module file: datetime

## co_consts:
('Return formatted timezone offset (+xx:xx) or an empty string.',)

## co_names:
('utcoffset', '_format_offset')

## bytecode:

   0: RESUME               
   2: LOAD_FAST            self
   4: LOAD_METHOD          utcoffset
  26: PRECALL              
  30: CALL                 
  40: STORE_FAST           off
  42: LOAD_GLOBAL          NULL + _format_offset
  54: LOAD_FAST            off
  56: PRECALL              
  60: CALL                 
  70: RETURN_VALUE         
