# Disassembly for datetime._parse_isoformat_time
# From module file: datetime

## co_consts:
(None, 2, 'Isoformat time too short', '-', 1, '+', 'Z', 0, -1, (0, 1, 3), 'Malformed time zone string', <code object <genexpr> at 0x0000024069465450, file "datetime.py", line 444>, 3, ('hours', 'minutes', 'seconds', 'microseconds'))

## co_names:
('len', 'ValueError', 'find', '_parse_hh_mm_ss_ff', 'timezone', 'utc', 'all', 'timedelta', 'append')

## bytecode:

   0: RESUME               
   2: LOAD_GLOBAL          NULL + len
  14: LOAD_FAST            tstr
  16: PRECALL              
  20: CALL                 
  30: STORE_FAST           len_str
  32: LOAD_FAST            len_str
  34: LOAD_CONST           2
  36: COMPARE_OP           <
  42: POP_JUMP_FORWARD_IF_FALSE to 74
  44: LOAD_GLOBAL          NULL + ValueError
  56: LOAD_CONST           'Isoformat time too short'
  58: PRECALL              
  62: CALL                 
  72: RAISE_VARARGS        
  74: LOAD_FAST            tstr
  76: LOAD_METHOD          find
  98: LOAD_CONST           '-'
 100: PRECALL              
 104: CALL                 
 114: LOAD_CONST           1
 116: BINARY_OP            +
 120: JUMP_IF_TRUE_OR_POP  to 216
 122: LOAD_FAST            tstr
 124: LOAD_METHOD          find
 146: LOAD_CONST           '+'
 148: PRECALL              
 152: CALL                 
 162: LOAD_CONST           1
 164: BINARY_OP            +
 168: JUMP_IF_TRUE_OR_POP  to 216
 170: LOAD_FAST            tstr
 172: LOAD_METHOD          find
 194: LOAD_CONST           'Z'
 196: PRECALL              
 200: CALL                 
 210: LOAD_CONST           1
 212: BINARY_OP            +
 216: STORE_FAST           tz_pos
 218: LOAD_FAST            tz_pos
 220: LOAD_CONST           0
 222: COMPARE_OP           >
 228: POP_JUMP_FORWARD_IF_FALSE to 256
 230: LOAD_FAST            tstr
 232: LOAD_CONST           None
 234: LOAD_FAST            tz_pos
 236: LOAD_CONST           1
 238: BINARY_OP            -
 242: BUILD_SLICE          
 244: BINARY_SUBSCR        
 254: JUMP_FORWARD         to 258
 256: LOAD_FAST            tstr
 258: STORE_FAST           timestr
 260: LOAD_GLOBAL          NULL + _parse_hh_mm_ss_ff
 272: LOAD_FAST            timestr
 274: PRECALL              
 278: CALL                 
 288: STORE_FAST           time_comps
 290: LOAD_CONST           None
 292: STORE_FAST           tzi
 294: LOAD_FAST            tz_pos
 296: LOAD_FAST            len_str
 298: COMPARE_OP           ==
 304: POP_JUMP_FORWARD_IF_FALSE to 356
 306: LOAD_FAST            tstr
 308: LOAD_CONST           -1
 310: BINARY_SUBSCR        
 320: LOAD_CONST           'Z'
 322: COMPARE_OP           ==
 328: POP_JUMP_FORWARD_IF_FALSE to 356
 330: LOAD_GLOBAL          timezone
 342: LOAD_ATTR            utc
 352: STORE_FAST           tzi
 354: JUMP_FORWARD         to 718
 356: LOAD_FAST            tz_pos
 358: LOAD_CONST           0
 360: COMPARE_OP           >
 366: POP_JUMP_FORWARD_IF_FALSE to 718
 368: LOAD_FAST            tstr
 370: LOAD_FAST            tz_pos
 372: LOAD_CONST           None
 374: BUILD_SLICE          
 376: BINARY_SUBSCR        
 386: STORE_FAST           tzstr
 388: LOAD_GLOBAL          NULL + len
 400: LOAD_FAST            tzstr
 402: PRECALL              
 406: CALL                 
 416: LOAD_CONST           (0, 1, 3)
 418: CONTAINS_OP          
 420: POP_JUMP_FORWARD_IF_FALSE to 452
 422: LOAD_GLOBAL          NULL + ValueError
 434: LOAD_CONST           'Malformed time zone string'
 436: PRECALL              
 440: CALL                 
 450: RAISE_VARARGS        
 452: LOAD_GLOBAL          NULL + _parse_hh_mm_ss_ff
 464: LOAD_FAST            tzstr
 466: PRECALL              
 470: CALL                 
 480: STORE_FAST           tz_comps
 482: LOAD_GLOBAL          NULL + all
 494: LOAD_CONST           <code object <genexpr> at 0x0000024069465450, file "datetime.py", line 444>
 496: MAKE_FUNCTION        
 498: LOAD_FAST            tz_comps
 500: GET_ITER             
 502: PRECALL              
 506: CALL                 
 516: PRECALL              
 520: CALL                 
 530: POP_JUMP_FORWARD_IF_FALSE to 558
 532: LOAD_GLOBAL          timezone
 544: LOAD_ATTR            utc
 554: STORE_FAST           tzi
 556: JUMP_FORWARD         to 718
 558: LOAD_FAST            tstr
 560: LOAD_FAST            tz_pos
 562: LOAD_CONST           1
 564: BINARY_OP            -
 568: BINARY_SUBSCR        
 578: LOAD_CONST           '-'
 580: COMPARE_OP           ==
 586: POP_JUMP_FORWARD_IF_FALSE to 592
 588: LOAD_CONST           -1
 590: JUMP_FORWARD         to 594
 592: LOAD_CONST           1
 594: STORE_FAST           tzsign
 596: LOAD_GLOBAL          NULL + timedelta
 608: LOAD_FAST            tz_comps
 610: LOAD_CONST           0
 612: BINARY_SUBSCR        
 622: LOAD_FAST            tz_comps
 624: LOAD_CONST           1
 626: BINARY_SUBSCR        
 636: LOAD_FAST            tz_comps
 638: LOAD_CONST           2
 640: BINARY_SUBSCR        
 650: LOAD_FAST            tz_comps
 652: LOAD_CONST           3
 654: BINARY_SUBSCR        
 664: KW_NAMES             
 666: PRECALL              
 670: CALL                 
 680: STORE_FAST           td
 682: LOAD_GLOBAL          NULL + timezone
 694: LOAD_FAST            tzsign
 696: LOAD_FAST            td
 698: BINARY_OP            *
 702: PRECALL              
 706: CALL                 
 716: STORE_FAST           tzi
 718: LOAD_FAST            time_comps
 720: LOAD_METHOD          append
 742: LOAD_FAST            tzi
 744: PRECALL              
 748: CALL                 
 758: POP_TOP              
 760: LOAD_FAST            time_comps
 762: RETURN_VALUE         
