# Disassembly for datetime._is_leap
# From module file: datetime

## co_consts:
('year -> 1 if leap year, else 0.', 4, 0, 100, 400)

## co_names:
()

## bytecode:

   0: RESUME               
   2: LOAD_FAST            year
   4: LOAD_CONST           4
   6: BINARY_OP            %
  10: LOAD_CONST           0
  12: COMPARE_OP           ==
  18: JUMP_IF_FALSE_OR_POP to 54
  20: LOAD_FAST            year
  22: LOAD_CONST           100
  24: BINARY_OP            %
  28: LOAD_CONST           0
  30: COMPARE_OP           !=
  36: JUMP_IF_TRUE_OR_POP  to 54
  38: LOAD_FAST            year
  40: LOAD_CONST           400
  42: BINARY_OP            %
  46: LOAD_CONST           0
  48: COMPARE_OP           ==
  54: RETURN_VALUE         
