# Disassembly for datetime._cmp
# From module file: datetime

## co_consts:
(None, 0, 1, -1)

## co_names:
()

## bytecode:

   0: RESUME               
   2: LOAD_FAST            x
   4: LOAD_FAST            y
   6: COMPARE_OP           ==
  12: POP_JUMP_FORWARD_IF_FALSE to 18
  14: LOAD_CONST           0
  16: JUMP_FORWARD         to 36
  18: LOAD_FAST            x
  20: LOAD_FAST            y
  22: COMPARE_OP           >
  28: POP_JUMP_FORWARD_IF_FALSE to 34
  30: LOAD_CONST           1
  32: JUMP_FORWARD         to 36
  34: LOAD_CONST           -1
  36: RETURN_VALUE         
