# Disassembly for datetime.date.strftime
# From module file: datetime

## co_consts:
('\n        Format using strftime().\n\n        Example: "%d/%m/%Y, %H:%M:%S"\n        ',)

## co_names:
('_wrap_strftime', 'timetuple')

## bytecode:

   0: RESUME               
   2: LOAD_GLOBAL          NULL + _wrap_strftime
  14: LOAD_FAST            self
  16: LOAD_FAST            fmt
  18: LOAD_FAST            self
  20: LOAD_METHOD          timetuple
  42: PRECALL              
  46: CALL                 
  56: PRECALL              
  60: CALL                 
  70: RETURN_VALUE         
