# Disassembly for datetime.date.fromisocalendar
# From module file: datetime

## co_consts:
('Construct a date from the ISO year, week number and weekday.\n\n        This is the inverse of the date.isocalendar() function',)

## co_names:
('_isoweek_to_gregorian',)

## bytecode:

   0: RESUME               
   2: PUSH_NULL            
   4: LOAD_FAST            cls
   6: LOAD_GLOBAL          NULL + _isoweek_to_gregorian
  18: LOAD_FAST            year
  20: LOAD_FAST            week
  22: LOAD_FAST            day
  24: PRECALL              
  28: CALL                 
  38: CALL_FUNCTION_EX     
  40: RETURN_VALUE         
