# Disassembly for csv.DictWriter.writeheader
# From module file: csv

## co_consts:
(None,)

## co_names:
('dict', 'zip', 'fieldnames', 'writerow')

## bytecode:

   0: RESUME               
   2: LOAD_GLOBAL          NULL + dict
  14: LOAD_GLOBAL          NULL + zip
  26: LOAD_FAST            self
  28: LOAD_ATTR            fieldnames
  38: LOAD_FAST            self
  40: LOAD_ATTR            fieldnames
  50: PRECALL              
  54: CALL                 
  64: PRECALL              
  68: CALL                 
  78: STORE_FAST           header
  80: LOAD_FAST            self
  82: LOAD_METHOD          writerow
 104: LOAD_FAST            header
 106: PRECALL              
 110: CALL                 
 120: RETURN_VALUE         
