# Disassembly for csv.DictWriter.writerow
# From module file: csv

## co_consts:
(None,)

## co_names:
('writer', 'writerow', '_dict_to_list')

## bytecode:

   0: RESUME               
   2: LOAD_FAST            self
   4: LOAD_ATTR            writer
  14: LOAD_METHOD          writerow
  36: LOAD_FAST            self
  38: LOAD_METHOD          _dict_to_list
  60: LOAD_FAST            rowdict
  62: PRECALL              
  66: CALL                 
  76: PRECALL              
  80: CALL                 
  90: RETURN_VALUE         
