# Disassembly for csv.Dialect._validate
# From module file: csv

## co_consts:
(None,)

## co_names:
('_Dialect', 'TypeError', 'Error', 'str')

## bytecode:

   0: RESUME               
   2: NOP                  
   4: LOAD_GLOBAL          NULL + _Dialect
  16: LOAD_FAST            self
  18: PRECALL              
  22: CALL                 
  32: POP_TOP              
  34: LOAD_CONST           None
  36: RETURN_VALUE         
  38: PUSH_EXC_INFO        
  40: LOAD_GLOBAL          TypeError
  52: CHECK_EXC_MATCH      
  54: POP_JUMP_FORWARD_IF_FALSE to 122
  56: STORE_FAST           e
  58: LOAD_GLOBAL          NULL + Error
  70: LOAD_GLOBAL          NULL + str
  82: LOAD_FAST            e
  84: PRECALL              
  88: CALL                 
  98: PRECALL              
 102: CALL                 
 112: RAISE_VARARGS        
 114: LOAD_CONST           None
 116: STORE_FAST           e
 118: DELETE_FAST          e
 120: RERAISE              
 122: RERAISE              
 124: COPY                 
 126: POP_EXCEPT           
 128: RERAISE              
