# Disassembly for csv.DictWriter._dict_to_list.<genexpr>
# From module file: csv

## co_consts:
(None,)

## co_names:
('get', 'restval')

## bytecode:

   0: COPY_FREE_VARS       
   2: RETURN_GENERATOR     
   4: POP_TOP              
   6: RESUME               
   8: LOAD_FAST            .0
  10: FOR_ITER             to 74
  12: STORE_FAST           key
  14: LOAD_DEREF           rowdict
  16: LOAD_METHOD          get
  38: LOAD_FAST            key
  40: LOAD_DEREF           self
  42: LOAD_ATTR            restval
  52: PRECALL              
  56: CALL                 
  66: YIELD_VALUE          
  68: RESUME               
  70: POP_TOP              
  72: JUMP_BACKWARD        to 10
  74: LOAD_CONST           None
  76: RETURN_VALUE         
