# Disassembly for csv.DictReader.__init__
# From module file: csv

## co_consts:
(None, 0)

## co_names:
('_fieldnames', 'restkey', 'restval', 'reader', 'dialect', 'line_num')

## bytecode:

   0: RESUME               
   2: LOAD_FAST            fieldnames
   4: LOAD_FAST            self
   6: STORE_ATTR           _fieldnames
  16: LOAD_FAST            restkey
  18: LOAD_FAST            self
  20: STORE_ATTR           restkey
  30: LOAD_FAST            restval
  32: LOAD_FAST            self
  34: STORE_ATTR           restval
  44: LOAD_GLOBAL          NULL + reader
  56: LOAD_FAST            f
  58: LOAD_FAST            dialect
  60: BUILD_LIST           
  62: LOAD_FAST            args
  64: LIST_EXTEND          
  66: LIST_TO_TUPLE        
  68: BUILD_MAP            
  70: LOAD_FAST            kwds
  72: DICT_MERGE           
  74: CALL_FUNCTION_EX     
  76: LOAD_FAST            self
  78: STORE_ATTR           reader
  88: LOAD_FAST            dialect
  90: LOAD_FAST            self
  92: STORE_ATTR           dialect
 102: LOAD_CONST           0
 104: LOAD_FAST            self
 106: STORE_ATTR           line_num
 116: LOAD_CONST           None
 118: RETURN_VALUE         
