# Disassembly for csv.Dialect
# From module file: csv

## co_consts:
('Dialect', 'Describe a CSV dialect.\n\n    This must be subclassed (see csv.excel).  Valid attributes are:\n    delimiter, quotechar, escapechar, doublequote, skipinitialspace,\n    lineterminator, quoting.\n\n    ', '', False, None, <code object __init__ at 0x00000240694196B0, file "csv.py", line 42>, <code object _validate at 0x00000240693AA470, file "csv.py", line 47>)

## co_names:
('__name__', '__module__', '__qualname__', '__doc__', '_name', '_valid', 'delimiter', 'quotechar', 'escapechar', 'doublequote', 'skipinitialspace', 'lineterminator', 'quoting', '__init__', '_validate')

## bytecode:

   0: RESUME               
   2: LOAD_NAME            __name__
   4: STORE_NAME           __module__
   6: LOAD_CONST           'Dialect'
   8: STORE_NAME           __qualname__
  10: LOAD_CONST           'Describe a CSV dialect.\n\n    This must be subclassed (see csv.excel).  Valid attributes are:\n    delimiter, quotechar, escapechar, doublequote, skipinitialspace,\n    lineterminator, quoting.\n\n    '
  12: STORE_NAME           __doc__
  14: LOAD_CONST           ''
  16: STORE_NAME           _name
  18: LOAD_CONST           False
  20: STORE_NAME           _valid
  22: LOAD_CONST           None
  24: STORE_NAME           delimiter
  26: LOAD_CONST           None
  28: STORE_NAME           quotechar
  30: LOAD_CONST           None
  32: STORE_NAME           escapechar
  34: LOAD_CONST           None
  36: STORE_NAME           doublequote
  38: LOAD_CONST           None
  40: STORE_NAME           skipinitialspace
  42: LOAD_CONST           None
  44: STORE_NAME           lineterminator
  46: LOAD_CONST           None
  48: STORE_NAME           quoting
  50: LOAD_CONST           <code object __init__ at 0x00000240694196B0, file "csv.py", line 42>
  52: MAKE_FUNCTION        
  54: STORE_NAME           __init__
  56: LOAD_CONST           <code object _validate at 0x00000240693AA470, file "csv.py", line 47>
  58: MAKE_FUNCTION        
  60: STORE_NAME           _validate
  62: LOAD_CONST           None
  64: RETURN_VALUE         
