# Disassembly for csv.Sniffer._guess_delimiter
# From module file: csv

## co_consts:
("\n        The delimiter /should/ occur the same number of times on\n        each row. However, due to malformed data, it may not. We don't want\n        an all or nothing approach, so we allow for small variations in this\n        number.\n          1) build a table of the frequency of each character on every line.\n          2) build a table of frequencies of this frequency (meta-frequency?),\n             e.g.  'x occurred 5 times in 10 rows, 6 times in 1000 rows,\n             7 times in 2 rows'\n          3) use the mode of the meta-frequency to determine the /expected/\n             frequency for that character\n          4) find out how often the character actually meets that goal\n          5) the character that best meets its goal is the delimiter\n        For performance reasons, the data is evaluated in chunks, so it can\n        try and evaluate the smallest portion of the data possible, evaluating\n        additional chunks as necessary.\n        ", None, '\n', <code object <listcomp> at 0x000002406945D4D0, file "csv.py", line 301>, 127, 10, 0, 1, <code object <lambda> at 0x0000024069495F10, file "csv.py", line 327>, ('key',), <code object <genexpr> at 0x0000024069466250, file "csv.py", line 332>, 1.0, 0.9, 0.01, '%c ', ('', 0), <code object <listcomp> at 0x0000024069465A70, file "csv.py", line 374>, -1)

## co_names:
('list', 'filter', 'split', 'range', 'min', 'len', 'get', 'count', 'keys', 'items', 'max', 'remove', 'sum', 'float', 'preferred', 'sort')

## bytecode:

   0: RESUME               
   2: LOAD_GLOBAL          NULL + list
  14: LOAD_GLOBAL          NULL + filter
  26: LOAD_CONST           None
  28: LOAD_FAST            data
  30: LOAD_METHOD          split
  52: LOAD_CONST           '\n'
  54: PRECALL              
  58: CALL                 
  68: PRECALL              
  72: CALL                 
  82: PRECALL              
  86: CALL                 
  96: STORE_FAST           data
  98: LOAD_CONST           <code object <listcomp> at 0x000002406945D4D0, file "csv.py", line 301>
 100: MAKE_FUNCTION        
 102: LOAD_GLOBAL          NULL + range
 114: LOAD_CONST           127
 116: PRECALL              
 120: CALL                 
 130: GET_ITER             
 132: PRECALL              
 136: CALL                 
 146: STORE_FAST           ascii
 148: LOAD_GLOBAL          NULL + min
 160: LOAD_CONST           10
 162: LOAD_GLOBAL          NULL + len
 174: LOAD_FAST            data
 176: PRECALL              
 180: CALL                 
 190: PRECALL              
 194: CALL                 
 204: STORE_FAST           chunkLength
 206: LOAD_CONST           0
 208: STORE_FAST           iteration
 210: BUILD_MAP            
 212: STORE_FAST           charFrequency
 214: BUILD_MAP            
 216: STORE_FAST           modes
 218: BUILD_MAP            
 220: STORE_FAST           delims
 222: LOAD_CONST           0
 224: LOAD_FAST            chunkLength
 226: STORE_FAST           end
 228: STORE_FAST           start
 230: LOAD_FAST            start
 232: LOAD_GLOBAL          NULL + len
 244: LOAD_FAST            data
 246: PRECALL              
 250: CALL                 
 260: COMPARE_OP           <
 266: EXTENDED_ARG         
 268: POP_JUMP_FORWARD_IF_FALSE to 1600
 270: LOAD_FAST            iteration
 272: LOAD_CONST           1
 274: BINARY_OP            +=
 278: STORE_FAST           iteration
 280: LOAD_FAST            data
 282: LOAD_FAST            start
 284: LOAD_FAST            end
 286: BUILD_SLICE          
 288: BINARY_SUBSCR        
 298: GET_ITER             
 300: FOR_ITER             to 468
 302: STORE_FAST           line
 304: LOAD_FAST            ascii
 306: GET_ITER             
 308: FOR_ITER             to 466
 310: STORE_FAST           char
 312: LOAD_FAST            charFrequency
 314: LOAD_METHOD          get
 336: LOAD_FAST            char
 338: BUILD_MAP            
 340: PRECALL              
 344: CALL                 
 354: STORE_FAST           metaFrequency
 356: LOAD_FAST            line
 358: LOAD_METHOD          count
 380: LOAD_FAST            char
 382: PRECALL              
 386: CALL                 
 396: STORE_FAST           freq
 398: LOAD_FAST            metaFrequency
 400: LOAD_METHOD          get
 422: LOAD_FAST            freq
 424: LOAD_CONST           0
 426: PRECALL              
 430: CALL                 
 440: LOAD_CONST           1
 442: BINARY_OP            +
 446: LOAD_FAST            metaFrequency
 448: LOAD_FAST            freq
 450: STORE_SUBSCR         
 454: LOAD_FAST            metaFrequency
 456: LOAD_FAST            charFrequency
 458: LOAD_FAST            char
 460: STORE_SUBSCR         
 464: JUMP_BACKWARD        to 308
 466: JUMP_BACKWARD        to 300
 468: LOAD_FAST            charFrequency
 470: LOAD_METHOD          keys
 492: PRECALL              
 496: CALL                 
 506: GET_ITER             
 508: FOR_ITER             to 940
 510: STORE_FAST           char
 512: LOAD_GLOBAL          NULL + list
 524: LOAD_FAST            charFrequency
 526: LOAD_FAST            char
 528: BINARY_SUBSCR        
 538: LOAD_METHOD          items
 560: PRECALL              
 564: CALL                 
 574: PRECALL              
 578: CALL                 
 588: STORE_FAST           items
 590: LOAD_GLOBAL          NULL + len
 602: LOAD_FAST            items
 604: PRECALL              
 608: CALL                 
 618: LOAD_CONST           1
 620: COMPARE_OP           ==
 626: POP_JUMP_FORWARD_IF_FALSE to 666
 628: LOAD_FAST            items
 630: LOAD_CONST           0
 632: BINARY_SUBSCR        
 642: LOAD_CONST           0
 644: BINARY_SUBSCR        
 654: LOAD_CONST           0
 656: COMPARE_OP           ==
 662: POP_JUMP_FORWARD_IF_FALSE to 666
 664: JUMP_BACKWARD        to 508
 666: LOAD_GLOBAL          NULL + len
 678: LOAD_FAST            items
 680: PRECALL              
 684: CALL                 
 694: LOAD_CONST           1
 696: COMPARE_OP           >
 702: POP_JUMP_FORWARD_IF_FALSE to 916
 704: LOAD_GLOBAL          NULL + max
 716: LOAD_FAST            items
 718: LOAD_CONST           <code object <lambda> at 0x0000024069495F10, file "csv.py", line 327>
 720: MAKE_FUNCTION        
 722: KW_NAMES             
 724: PRECALL              
 728: CALL                 
 738: LOAD_FAST            modes
 740: LOAD_FAST            char
 742: STORE_SUBSCR         
 746: LOAD_FAST            items
 748: LOAD_METHOD          remove
 770: LOAD_FAST            modes
 772: LOAD_FAST            char
 774: BINARY_SUBSCR        
 784: PRECALL              
 788: CALL                 
 798: POP_TOP              
 800: LOAD_FAST            modes
 802: LOAD_FAST            char
 804: BINARY_SUBSCR        
 814: LOAD_CONST           0
 816: BINARY_SUBSCR        
 826: LOAD_FAST            modes
 828: LOAD_FAST            char
 830: BINARY_SUBSCR        
 840: LOAD_CONST           1
 842: BINARY_SUBSCR        
 852: LOAD_GLOBAL          NULL + sum
 864: LOAD_CONST           <code object <genexpr> at 0x0000024069466250, file "csv.py", line 332>
 866: MAKE_FUNCTION        
 868: LOAD_FAST            items
 870: GET_ITER             
 872: PRECALL              
 876: CALL                 
 886: PRECALL              
 890: CALL                 
 900: BINARY_OP            -
 904: BUILD_TUPLE          
 906: LOAD_FAST            modes
 908: LOAD_FAST            char
 910: STORE_SUBSCR         
 914: JUMP_BACKWARD        to 508
 916: LOAD_FAST            items
 918: LOAD_CONST           0
 920: BINARY_SUBSCR        
 930: LOAD_FAST            modes
 932: LOAD_FAST            char
 934: STORE_SUBSCR         
 938: JUMP_BACKWARD        to 508
 940: LOAD_FAST            modes
 942: LOAD_METHOD          items
 964: PRECALL              
 968: CALL                 
 978: STORE_FAST           modeList
 980: LOAD_GLOBAL          NULL + float
 992: LOAD_GLOBAL          NULL + min
1004: LOAD_FAST            chunkLength
1006: LOAD_FAST            iteration
1008: BINARY_OP            *
1012: LOAD_GLOBAL          NULL + len
1024: LOAD_FAST            data
1026: PRECALL              
1030: CALL                 
1040: PRECALL              
1044: CALL                 
1054: PRECALL              
1058: CALL                 
1068: STORE_FAST           total
1070: LOAD_CONST           1.0
1072: STORE_FAST           consistency
1074: LOAD_CONST           0.9
1076: STORE_FAST           threshold
1078: LOAD_GLOBAL          NULL + len
1090: LOAD_FAST            delims
1092: PRECALL              
1096: CALL                 
1106: LOAD_CONST           0
1108: COMPARE_OP           ==
1114: POP_JUMP_FORWARD_IF_FALSE to 1304
1116: LOAD_FAST            consistency
1118: LOAD_FAST            threshold
1120: COMPARE_OP           >=
1126: POP_JUMP_FORWARD_IF_FALSE to 1304
1128: LOAD_FAST            modeList
1130: GET_ITER             
1132: FOR_ITER             to 1244
1134: UNPACK_SEQUENCE      
1138: STORE_FAST           k
1140: STORE_FAST           v
1142: LOAD_FAST            v
1144: LOAD_CONST           0
1146: BINARY_SUBSCR        
1156: LOAD_CONST           0
1158: COMPARE_OP           >
1164: POP_JUMP_FORWARD_IF_FALSE to 1242
1166: LOAD_FAST            v
1168: LOAD_CONST           1
1170: BINARY_SUBSCR        
1180: LOAD_CONST           0
1182: COMPARE_OP           >
1188: POP_JUMP_FORWARD_IF_FALSE to 1242
1190: LOAD_FAST            v
1192: LOAD_CONST           1
1194: BINARY_SUBSCR        
1204: LOAD_FAST            total
1206: BINARY_OP            /
1210: LOAD_FAST            consistency
1212: COMPARE_OP           >=
1218: POP_JUMP_FORWARD_IF_FALSE to 1242
1220: LOAD_FAST            delimiters
1222: POP_JUMP_FORWARD_IF_NONE to 1232
1224: LOAD_FAST            k
1226: LOAD_FAST            delimiters
1228: CONTAINS_OP          
1230: POP_JUMP_FORWARD_IF_FALSE to 1242
1232: LOAD_FAST            v
1234: LOAD_FAST            delims
1236: LOAD_FAST            k
1238: STORE_SUBSCR         
1242: JUMP_BACKWARD        to 1132
1244: LOAD_FAST            consistency
1246: LOAD_CONST           0.01
1248: BINARY_OP            -=
1252: STORE_FAST           consistency
1254: LOAD_GLOBAL          NULL + len
1266: LOAD_FAST            delims
1268: PRECALL              
1272: CALL                 
1282: LOAD_CONST           0
1284: COMPARE_OP           ==
1290: POP_JUMP_FORWARD_IF_FALSE to 1304
1292: LOAD_FAST            consistency
1294: LOAD_FAST            threshold
1296: COMPARE_OP           >=
1302: POP_JUMP_BACKWARD_IF_TRUE to 1128
1304: LOAD_GLOBAL          NULL + len
1316: LOAD_FAST            delims
1318: PRECALL              
1322: CALL                 
1332: LOAD_CONST           1
1334: COMPARE_OP           ==
1340: POP_JUMP_FORWARD_IF_FALSE to 1546
1342: LOAD_GLOBAL          NULL + list
1354: LOAD_FAST            delims
1356: LOAD_METHOD          keys
1378: PRECALL              
1382: CALL                 
1392: PRECALL              
1396: CALL                 
1406: LOAD_CONST           0
1408: BINARY_SUBSCR        
1418: STORE_FAST           delim
1420: LOAD_FAST            data
1422: LOAD_CONST           0
1424: BINARY_SUBSCR        
1434: LOAD_METHOD          count
1456: LOAD_FAST            delim
1458: PRECALL              
1462: CALL                 
1472: LOAD_FAST            data
1474: LOAD_CONST           0
1476: BINARY_SUBSCR        
1486: LOAD_METHOD          count
1508: LOAD_CONST           '%c '
1510: LOAD_FAST            delim
1512: BINARY_OP            %
1516: PRECALL              
1520: CALL                 
1530: COMPARE_OP           ==
1536: STORE_FAST           skipinitialspace
1538: LOAD_FAST            delim
1540: LOAD_FAST            skipinitialspace
1542: BUILD_TUPLE          
1544: RETURN_VALUE         
1546: LOAD_FAST            end
1548: STORE_FAST           start
1550: LOAD_FAST            end
1552: LOAD_FAST            chunkLength
1554: BINARY_OP            +=
1558: STORE_FAST           end
1560: LOAD_FAST            start
1562: LOAD_GLOBAL          NULL + len
1574: LOAD_FAST            data
1576: PRECALL              
1580: CALL                 
1590: COMPARE_OP           <
1596: EXTENDED_ARG         
1598: POP_JUMP_BACKWARD_IF_TRUE to 270
1600: LOAD_FAST            delims
1602: POP_JUMP_FORWARD_IF_TRUE to 1608
1604: LOAD_CONST           ('', 0)
1606: RETURN_VALUE         
1608: LOAD_GLOBAL          NULL + len
1620: LOAD_FAST            delims
1622: PRECALL              
1626: CALL                 
1636: LOAD_CONST           1
1638: COMPARE_OP           >
1644: POP_JUMP_FORWARD_IF_FALSE to 1840
1646: LOAD_FAST            self
1648: LOAD_ATTR            preferred
1658: GET_ITER             
1660: FOR_ITER             to 1840
1662: STORE_FAST           d
1664: LOAD_FAST            d
1666: LOAD_FAST            delims
1668: LOAD_METHOD          keys
1690: PRECALL              
1694: CALL                 
1704: CONTAINS_OP          
1706: POP_JUMP_FORWARD_IF_FALSE to 1838
1708: LOAD_FAST            data
1710: LOAD_CONST           0
1712: BINARY_SUBSCR        
1722: LOAD_METHOD          count
1744: LOAD_FAST            d
1746: PRECALL              
1750: CALL                 
1760: LOAD_FAST            data
1762: LOAD_CONST           0
1764: BINARY_SUBSCR        
1774: LOAD_METHOD          count
1796: LOAD_CONST           '%c '
1798: LOAD_FAST            d
1800: BINARY_OP            %
1804: PRECALL              
1808: CALL                 
1818: COMPARE_OP           ==
1824: STORE_FAST           skipinitialspace
1826: LOAD_FAST            d
1828: LOAD_FAST            skipinitialspace
1830: BUILD_TUPLE          
1832: SWAP                 
1834: POP_TOP              
1836: RETURN_VALUE         
1838: JUMP_BACKWARD        to 1660
1840: LOAD_CONST           <code object <listcomp> at 0x0000024069465A70, file "csv.py", line 374>
1842: MAKE_FUNCTION        
1844: LOAD_FAST            delims
1846: LOAD_METHOD          items
1868: PRECALL              
1872: CALL                 
1882: GET_ITER             
1884: PRECALL              
1888: CALL                 
1898: STORE_FAST           items
1900: LOAD_FAST            items
1902: LOAD_METHOD          sort
1924: PRECALL              
1928: CALL                 
1938: POP_TOP              
1940: LOAD_FAST            items
1942: LOAD_CONST           -1
1944: BINARY_SUBSCR        
1954: LOAD_CONST           1
1956: BINARY_SUBSCR        
1966: STORE_FAST           delim
1968: LOAD_FAST            data
1970: LOAD_CONST           0
1972: BINARY_SUBSCR        
1982: LOAD_METHOD          count
2004: LOAD_FAST            delim
2006: PRECALL              
2010: CALL                 
2020: LOAD_FAST            data
2022: LOAD_CONST           0
2024: BINARY_SUBSCR        
2034: LOAD_METHOD          count
2056: LOAD_CONST           '%c '
2058: LOAD_FAST            delim
2060: BINARY_OP            %
2064: PRECALL              
2068: CALL                 
2078: COMPARE_OP           ==
2084: STORE_FAST           skipinitialspace
2086: LOAD_FAST            delim
2088: LOAD_FAST            skipinitialspace
2090: BUILD_TUPLE          
2092: RETURN_VALUE         
